{
  "type": "Feature",
  "properties": {
    "gn:admin1_code":"22.0",
    "gn:admin2_code":"9002.0",
    "gn:asciiname":"Esuk John",
    "gn:country_code":"NG",
    "gn:dem":14,
    "gn:feature_class":"P",
    "gn:feature_code":"PPL",
    "gn:name":"Esuk John",
    "gn:population":0,
    "gn:timezone":"Africa/Lagos",
    "iso:country":"NG",
    "wof:name":"Esuk John",
    "wof:placetype":"locality"
},
  "geometry": {"coordinates":[8.4219,5.1142],"type":"Point"}
}