{
  "type": "Feature",
  "properties": {
    "gn:admin1_code":"43.0",
    "gn:admin2_code":"35015",
    "gn:asciiname":"Jauro Garmaho",
    "gn:country_code":"NG",
    "gn:dem":252,
    "gn:feature_class":"P",
    "gn:feature_code":"PPL",
    "gn:name":"Jauro Garmaho",
    "gn:population":0,
    "gn:timezone":"Africa/Lagos",
    "iso:country":"NG",
    "wof:name":"Jauro Garmaho",
    "wof:placetype":"locality"
},
  "geometry": {"coordinates":[11.41243,8.97468],"type":"Point"}
}