{
  "type": "Feature",
  "properties": {
    "gn:admin1_code":"46.0",
    "gn:admin2_code":"5008.0",
    "gn:admin3_code":"BA0811",
    "gn:asciiname":"Dumi",
    "gn:country_code":"NG",
    "gn:dem":600,
    "gn:feature_class":"P",
    "gn:feature_code":"PPL",
    "gn:name":"Dumi",
    "gn:population":0,
    "gn:timezone":"Africa/Lagos",
    "iso:country":"NG",
    "wof:name":"Dumi",
    "wof:placetype":"locality"
},
  "geometry": {"coordinates":[9.90069,10.51019],"type":"Point"}
}