{
  "type": "Feature",
  "properties": {
    "gn:admin1_code":"35.0",
    "gn:admin2_code":"2002.0",
    "gn:asciiname":"Iunguyatu",
    "gn:country_code":"NG",
    "gn:dem":408,
    "gn:feature_class":"P",
    "gn:feature_code":"PPL",
    "gn:name":"Iunguyatu",
    "gn:population":0,
    "gn:timezone":"Africa/Lagos",
    "iso:country":"NG",
    "wof:name":"Iunguyatu",
    "wof:placetype":"locality"
},
  "geometry": {"coordinates":[12.50654,8.82371],"type":"Point"}
}