{
  "type": "Feature",
  "properties": {
    "gn:admin1_code":"44.0",
    "gn:admin2_code":"702.0",
    "gn:admin3_code":"70208",
    "gn:asciiname":"Buruta",
    "gn:country_code":"NG",
    "gn:dem":335,
    "gn:feature_class":"P",
    "gn:feature_code":"PPL",
    "gn:name":"Buruta",
    "gn:population":0,
    "gn:timezone":"Africa/Lagos",
    "iso:country":"NG",
    "wof:name":"Buruta",
    "wof:placetype":"locality"
},
  "geometry": {"coordinates":[11.62148,12.76664],"type":"Point"}
}