{
  "type": "Feature",
  "properties": {
    "gn:admin1_code":"29.0",
    "gn:admin2_code":"20011.0",
    "gn:admin3_code":"KN3604",
    "gn:asciiname":"Karchi",
    "gn:country_code":"NG",
    "gn:dem":529,
    "gn:feature_class":"P",
    "gn:feature_code":"PPL",
    "gn:name":"Karchi",
    "gn:population":0,
    "gn:timezone":"Africa/Lagos",
    "iso:country":"NG",
    "wof:name":"Karchi",
    "wof:placetype":"locality"
},
  "geometry": {"coordinates":[8.93099,11.33664],"type":"Point"}
}