{
  "type": "Feature",
  "properties": {
    "gn:admin1_code":"46.0",
    "gn:admin2_code":"5009.0",
    "gn:admin3_code":"BA0903",
    "gn:asciiname":"Tagwaye",
    "gn:country_code":"NG",
    "gn:dem":470,
    "gn:feature_class":"P",
    "gn:feature_code":"PPL",
    "gn:name":"Tagwaye",
    "gn:population":0,
    "gn:timezone":"Africa/Lagos",
    "iso:country":"NG",
    "wof:name":"Tagwaye",
    "wof:placetype":"locality"
},
  "geometry": {"coordinates":[10.1664,11.3577],"type":"Point"}
}