{
  "type": "Feature",
  "properties": {
    "gn:admin1_code":"37.0",
    "gn:admin2_code":"12015.0",
    "gn:asciiname":"Iguerahon",
    "gn:country_code":"NG",
    "gn:dem":75,
    "gn:feature_class":"P",
    "gn:feature_code":"PPL",
    "gn:name":"Iguerahon",
    "gn:population":0,
    "gn:timezone":"Africa/Lagos",
    "iso:country":"NG",
    "name:und_x_variant":[
        "Iguerhahon",
        "Iguerahon"
    ],
    "wof:name":"Iguerahon",
    "wof:placetype":"locality"
},
  "geometry": {"coordinates":[5.16828,6.44552],"type":"Point"}
}