{
  "type": "Feature",
  "properties": {
    "gn:admin1_code":"42.0",
    "gn:admin2_code":"30013.0",
    "gn:asciiname":"Jatina",
    "gn:country_code":"NG",
    "gn:dem":186,
    "gn:feature_class":"P",
    "gn:feature_code":"PPL",
    "gn:name":"Jatina",
    "gn:population":0,
    "gn:timezone":"Africa/Lagos",
    "iso:country":"NG",
    "wof:name":"Jatina",
    "wof:placetype":"locality"
},
  "geometry": {"coordinates":[4.41667,7.38333],"type":"Point"}
}