{
  "type": "Feature",
  "properties": {
    "gn:admin1_code":"26.0",
    "gn:admin2_code":"7020.0",
    "gn:asciiname":"Nkst",
    "gn:country_code":"NG",
    "gn:dem":176,
    "gn:feature_class":"P",
    "gn:feature_code":"PPL",
    "gn:name":"Nkst",
    "gn:population":0,
    "gn:timezone":"Africa/Lagos",
    "iso:country":"NG",
    "wof:name":"Nkst",
    "wof:placetype":"locality"
},
  "geometry": {"coordinates":[8.86882,7.66084],"type":"Point"}
}