{
  "type": "Feature",
  "properties": {
    "gn:admin1_code":"35.0",
    "gn:admin2_code":"2002.0",
    "gn:asciiname":"Wuro Galdimawo",
    "gn:country_code":"NG",
    "gn:dem":196,
    "gn:feature_class":"P",
    "gn:feature_code":"PPL",
    "gn:name":"Wuro Galdimawo",
    "gn:population":0,
    "gn:timezone":"Africa/Lagos",
    "iso:country":"NG",
    "wof:name":"Wuro Galdimawo",
    "wof:placetype":"locality"
},
  "geometry": {"coordinates":[12.63333,9.15],"type":"Point"}
}