{
  "type": "Feature",
  "properties": {
    "gn:admin1_code":"29.0",
    "gn:admin2_code":"20010.0",
    "gn:admin3_code":"KN1711",
    "gn:asciiname":"Daradou",
    "gn:country_code":"NG",
    "gn:dem":464,
    "gn:feature_class":"P",
    "gn:feature_code":"PPL",
    "gn:name":"Daradou",
    "gn:population":0,
    "gn:timezone":"Africa/Lagos",
    "iso:country":"NG",
    "wof:name":"Daradou",
    "wof:placetype":"locality"
},
  "geometry": {"coordinates":[8.70116,12.05293],"type":"Point"}
}