{
  "type": "Feature",
  "properties": {
    "gn:admin1_code":"56.0",
    "gn:admin2_code":"26012.0",
    "gn:asciiname":"Gwadabo",
    "gn:country_code":"NG",
    "gn:dem":121,
    "gn:feature_class":"P",
    "gn:feature_code":"PPL",
    "gn:name":"Gwadabo",
    "gn:population":0,
    "gn:timezone":"Africa/Lagos",
    "iso:country":"NG",
    "wof:name":"Gwadabo",
    "wof:placetype":"locality"
},
  "geometry": {"coordinates":[7.22417,8.105],"type":"Point"}
}