{
  "type": "Feature",
  "properties": {
    "gn:admin1_code":"37.0",
    "gn:admin2_code":"12018.0",
    "gn:asciiname":"Eilo-Edo",
    "gn:country_code":"NG",
    "gn:dem":82,
    "gn:feature_class":"P",
    "gn:feature_code":"PPL",
    "gn:name":"Eilo-Edo",
    "gn:population":0,
    "gn:timezone":"Africa/Lagos",
    "iso:country":"NG",
    "name:eng_x_preferred":[
        "Eilo-Edo"
    ],
    "wof:name":"Eilo-Edo",
    "wof:placetype":"locality"
},
  "geometry": {"coordinates":[6.12038,6.43638],"type":"Point"}
}