{
  "type": "Feature",
  "properties": {
    "gn:admin1_code":"43.0",
    "gn:admin2_code":"35016.0",
    "gn:asciiname":"Manza",
    "gn:country_code":"NG",
    "gn:dem":481,
    "gn:feature_class":"P",
    "gn:feature_code":"PPL",
    "gn:name":"Manza",
    "gn:population":0,
    "gn:timezone":"Africa/Lagos",
    "iso:country":"NG",
    "name:ceb_x_preferred":[
        "Manza"
    ],
    "name:swe_x_preferred":[
        "Manza"
    ],
    "wof:name":"Manza",
    "wof:placetype":"locality"
},
  "geometry": {"coordinates":[11.6525,8.87829],"type":"Point"}
}