{
  "type": "Feature",
  "properties": {
    "gn:admin1_code":"40.0",
    "gn:admin2_code":"520.0",
    "gn:admin3_code":"52007",
    "gn:asciiname":"Tungan Maikaho",
    "gn:country_code":"NG",
    "gn:dem":176,
    "gn:feature_class":"P",
    "gn:feature_code":"PPL",
    "gn:name":"Tungan Maikaho",
    "gn:population":0,
    "gn:timezone":"Africa/Lagos",
    "iso:country":"NG",
    "name:und_x_variant":[
        "Jinsani",
        "Tungan Maikaho"
    ],
    "wof:name":"Tungan Maikaho",
    "wof:placetype":"locality"
},
  "geometry": {"coordinates":[4.8284,10.8751],"type":"Point"}
}