{
  "type": "Feature",
  "properties": {
    "gn:admin1_code":"35.0",
    "gn:admin2_code":"2011",
    "gn:asciiname":"Bangumo",
    "gn:country_code":"NG",
    "gn:dem":559,
    "gn:feature_class":"P",
    "gn:feature_code":"PPL",
    "gn:name":"Bangumo",
    "gn:population":0,
    "gn:timezone":"Africa/Lagos",
    "iso:country":"NG",
    "wof:name":"Bangumo",
    "wof:placetype":"locality"
},
  "geometry": {"coordinates":[13.19599,9.90654],"type":"Point"}
}