{
  "type": "Feature",
  "properties": {
    "gn:admin1_code":"46.0",
    "gn:admin2_code":"5002.0",
    "gn:admin3_code":"BA0207",
    "gn:asciiname":"Bayara",
    "gn:country_code":"NG",
    "gn:dem":584,
    "gn:feature_class":"P",
    "gn:feature_code":"PPL",
    "gn:name":"Bayara",
    "gn:population":0,
    "gn:timezone":"Africa/Lagos",
    "iso:country":"NG",
    "name:fra_x_preferred":[
        "Bayara"
    ],
    "wof:name":"Bayara",
    "wof:placetype":"locality"
},
  "geometry": {"coordinates":[9.72667,10.2105],"type":"Point"}
}