{
  "type": "Feature",
  "properties": {
    "gn:admin1_code":"23.0",
    "gn:admin2_code":"19021.0",
    "gn:admin3_code":"KD2106",
    "gn:asciiname":"Sabon Birnin",
    "gn:country_code":"NG",
    "gn:dem":636,
    "gn:feature_class":"P",
    "gn:feature_code":"PPL",
    "gn:name":"Sabon Birnin",
    "gn:population":0,
    "gn:timezone":"Africa/Lagos",
    "iso:country":"NG",
    "name:und_x_variant":[
        "Sabon Birni",
        "Sabon Birnin"
    ],
    "wof:name":"Sabon Birnin",
    "wof:placetype":"locality"
},
  "geometry": {"coordinates":[7.89837,11.17734],"type":"Point"}
}