{
  "type": "Feature",
  "properties": {
    "gn:admin1_code":"27.0",
    "gn:admin2_code":"105.0",
    "gn:admin3_code":"10508",
    "gn:asciiname":"Pompomari",
    "gn:country_code":"NG",
    "gn:dem":658,
    "gn:feature_class":"P",
    "gn:feature_code":"PPL",
    "gn:name":"Pompomari",
    "gn:population":0,
    "gn:timezone":"Africa/Lagos",
    "iso:country":"NG",
    "wof:name":"Pompomari",
    "wof:placetype":"locality"
},
  "geometry": {"coordinates":[12.15927,10.72037],"type":"Point"}
}