{
  "type": "Feature",
  "properties": {
    "gn:admin1_code":"36.0",
    "gn:admin2_code":"10018.0",
    "gn:asciiname":"Ugbisi",
    "gn:country_code":"NG",
    "gn:dem":11,
    "gn:feature_class":"P",
    "gn:feature_code":"PPL",
    "gn:name":"Ugbisi",
    "gn:population":0,
    "gn:timezone":"Africa/Lagos",
    "iso:country":"NG",
    "wof:name":"Ugbisi",
    "wof:placetype":"locality"
},
  "geometry": {"coordinates":[5.82343,5.45209],"type":"Point"}
}