{
  "type": "Feature",
  "properties": {
    "gn:admin1_code":"40.0",
    "gn:admin2_code":"507.0",
    "gn:admin3_code":"50701",
    "gn:asciiname":"Tunga Dangaji",
    "gn:country_code":"NG",
    "gn:dem":198,
    "gn:feature_class":"P",
    "gn:feature_code":"PPL",
    "gn:name":"Tunga Dangaji",
    "gn:population":0,
    "gn:timezone":"Africa/Lagos",
    "iso:country":"NG",
    "name:und_x_variant":[
        "Tungan Dangaji",
        "Tunga Dangaji"
    ],
    "wof:name":"Tunga Dangaji",
    "wof:placetype":"locality"
},
  "geometry": {"coordinates":[3.98945,12.10837],"type":"Point"}
}