{
  "type": "Feature",
  "properties": {
    "gn:admin1_code":"56.0",
    "gn:admin2_code":"26009.0",
    "gn:asciiname":"Aburu",
    "gn:country_code":"NG",
    "gn:dem":61,
    "gn:feature_class":"P",
    "gn:feature_code":"PPL",
    "gn:name":"Aburu",
    "gn:population":0,
    "gn:timezone":"Africa/Lagos",
    "iso:country":"NG",
    "wof:name":"Aburu",
    "wof:placetype":"locality"
},
  "geometry": {"coordinates":[7.97683,7.98221],"type":"Point"}
}