{
  "type": "Feature",
  "properties": {
    "gn:admin1_code":"39.0",
    "gn:asciiname":"Gambara",
    "gn:country_code":"NG",
    "gn:dem":387,
    "gn:feature_class":"P",
    "gn:feature_code":"PPL",
    "gn:name":"Gambara",
    "gn:population":0,
    "gn:timezone":"Africa/Lagos",
    "iso:country":"NG",
    "name:azb_x_preferred":[
        "\u0642\u0627\u0645\u0628\u0627\u0631\u0627"
    ],
    "name:bul_x_preferred":[
        "\u0413\u0430\u043c\u0431\u0430\u0440\u0430"
    ],
    "name:ceb_x_preferred":[
        "Gambara"
    ],
    "name:deu_x_preferred":[
        "Gambara"
    ],
    "name:epo_x_preferred":[
        "Gambara"
    ],
    "name:eus_x_preferred":[
        "Gambara"
    ],
    "name:fas_x_preferred":[
        "\u06af\u0627\u0645\u0628\u0627\u0631\u0627"
    ],
    "name:fra_x_preferred":[
        "Gambara"
    ],
    "name:hun_x_preferred":[
        "Gambara"
    ],
    "name:hye_x_preferred":[
        "\u0533\u0561\u0574\u0562\u0561\u0580\u0561"
    ],
    "name:ita_x_preferred":[
        "Gambara"
    ],
    "name:jpn_x_preferred":[
        "\u30ac\u30f3\u30d0\u30e9"
    ],
    "name:kaz_x_preferred":[
        "\u0413\u0430\u043c\u0431\u0430\u0440\u0430"
    ],
    "name:lat_x_preferred":[
        "Gambara"
    ],
    "name:lmo_x_preferred":[
        "G\u00e0mbara"
    ],
    "name:msa_x_preferred":[
        "Gambara"
    ],
    "name:nap_x_preferred":[
        "Gambara"
    ],
    "name:nld_x_preferred":[
        "Gambara"
    ],
    "name:pms_x_preferred":[
        "Gambara"
    ],
    "name:pol_x_preferred":[
        "Gambara"
    ],
    "name:por_x_preferred":[
        "Gambara"
    ],
    "name:ron_x_preferred":[
        "Gambara"
    ],
    "name:rus_x_preferred":[
        "\u0413\u0430\u043c\u0431\u0430\u0440\u0430"
    ],
    "name:scn_x_preferred":[
        "Gambara"
    ],
    "name:spa_x_preferred":[
        "Gambara"
    ],
    "name:srp_x_preferred":[
        "\u0413\u0430\u043c\u0431\u0430\u0440\u0430"
    ],
    "name:tgl_x_preferred":[
        "Gambara"
    ],
    "name:ukr_x_preferred":[
        "\u0413\u0430\u043c\u0431\u0430\u0440\u0430"
    ],
    "name:uzb_x_preferred":[
        "Gambara"
    ],
    "name:vie_x_preferred":[
        "Gambara"
    ],
    "name:vol_x_preferred":[
        "Gambara"
    ],
    "name:war_x_preferred":[
        "Gambara"
    ],
    "name:zho_x_preferred":[
        "\u7518\u5df4\u62c9"
    ],
    "wof:name":"Gambara",
    "wof:placetype":"locality"
},
  "geometry": {"coordinates":[9.69448,11.82814],"type":"Point"}
}