{
  "type": "Feature",
  "properties": {
    "gn:admin1_code":"37.0",
    "gn:admin2_code":"12015.0",
    "gn:asciiname":"Ago-Isobo",
    "gn:country_code":"NG",
    "gn:dem":27,
    "gn:feature_class":"P",
    "gn:feature_code":"PPL",
    "gn:name":"Ago-Isobo",
    "gn:population":0,
    "gn:timezone":"Africa/Lagos",
    "iso:country":"NG",
    "wof:name":"Ago-Isobo",
    "wof:placetype":"locality"
},
  "geometry": {"coordinates":[5.11637,6.41858],"type":"Point"}
}