{
  "type": "Feature",
  "properties": {
    "gn:admin1_code":"50.0",
    "gn:admin2_code":"33008",
    "gn:asciiname":"Ebemaboko",
    "gn:country_code":"NG",
    "gn:dem":10,
    "gn:feature_class":"P",
    "gn:feature_code":"PPL",
    "gn:name":"Ebemaboko",
    "gn:population":0,
    "gn:timezone":"Africa/Lagos",
    "iso:country":"NG",
    "wof:name":"Ebemaboko",
    "wof:placetype":"locality"
},
  "geometry": {"coordinates":[6.81618,4.6433],"type":"Point"}
}