{
  "type": "Feature",
  "properties": {
    "gn:admin1_code":"48.0",
    "gn:asciiname":"Ago-Panu",
    "gn:country_code":"NG",
    "gn:dem":393,
    "gn:feature_class":"P",
    "gn:feature_code":"PPL",
    "gn:name":"Ago-Panu",
    "gn:population":0,
    "gn:timezone":"Africa/Lagos",
    "iso:country":"NG",
    "wof:name":"Ago-Panu",
    "wof:placetype":"locality"
},
  "geometry": {"coordinates":[5.4788,7.341],"type":"Point"}
}