{
  "type": "Feature",
  "properties": {
    "iso:country":"NG",
    "name:ceb_x_preferred":[
        "Eket"
    ],
    "name:eng_x_preferred":[
        "Eket"
    ],
    "name:fra_x_preferred":[
        "Eket"
    ],
    "name:hau_x_preferred":[
        "Eket"
    ],
    "name:ita_x_preferred":[
        "Eket"
    ],
    "name:jpn_x_preferred":[
        "\u30a8\u30b1\u30c8"
    ],
    "name:mrj_x_preferred":[
        "\u042d\u043a\u0435\u0442\u0432\u043b\u04d3"
    ],
    "name:nan_x_preferred":[
        "Eket"
    ],
    "name:nld_x_preferred":[
        "Eket"
    ],
    "name:pol_x_preferred":[
        "Eket"
    ],
    "name:por_x_preferred":[
        "Eket"
    ],
    "name:ron_x_preferred":[
        "Eket"
    ],
    "name:rus_x_preferred":[
        "\u042d\u043a\u0435\u0442"
    ],
    "name:spa_x_preferred":[
        "Eket"
    ],
    "name:ukr_x_preferred":[
        "\u0415\u043a\u0435\u0442"
    ],
    "name:yor_x_preferred":[
        "Eket"
    ],
    "name:zho_min_nan_x_preferred":[
        "Eket"
    ],
    "qs:gn_country":"NG",
    "qs:gn_fcode":"PPL",
    "qs:gn_pop":25569,
    "qs:name":"Eket",
    "qs:name_adm0":"Nigeria",
    "qs:name_adm1":"Akwa Ibom",
    "qs:photos":0,
    "qs:photos_1k":0,
    "qs:photos_9k":1,
    "qs:photos_9r":2,
    "qs:photos_all":61,
    "qs:photos_sr":0,
    "qs:placetype":"Town",
    "qs:pop_sr":"7",
    "qs:woe_adm0":23424908,
    "wd:wordcount":523,
    "wof:name":"Eket",
    "wof:placetype":"locality",
    "wof:population":25569
},
  "geometry": {"coordinates":[7.92092,4.64122],"type":"Point"}
}