{
  "type": "Feature",
  "properties": {
    "gn:admin1_code":"35.0",
    "gn:admin2_code":"2010.0",
    "gn:asciiname":"Jimango",
    "gn:country_code":"NG",
    "gn:dem":556,
    "gn:feature_class":"P",
    "gn:feature_code":"PPL",
    "gn:name":"Jimango",
    "gn:population":0,
    "gn:timezone":"Africa/Lagos",
    "iso:country":"NG",
    "wof:name":"Jimango",
    "wof:placetype":"locality"
},
  "geometry": {"coordinates":[13.6339,10.8162],"type":"Point"}
}