{
  "type": "Feature",
  "properties": {
    "gn:admin1_code":"41.0",
    "gn:admin2_code":"23018.0",
    "gn:asciiname":"Ogbe",
    "gn:country_code":"NG",
    "gn:dem":270,
    "gn:feature_class":"P",
    "gn:feature_code":"PPL",
    "gn:name":"Ogbe",
    "gn:population":0,
    "gn:timezone":"Africa/Lagos",
    "iso:country":"NG",
    "name:und_x_variant":[
        "Ogpe",
        "Okpe",
        "Ogbe"
    ],
    "wof:name":"Ogbe",
    "wof:placetype":"locality"
},
  "geometry": {"coordinates":[7.54358,7.26592],"type":"Point"}
}