{
  "type": "Feature",
  "properties": {
    "gn:admin1_code":"24.0",
    "gn:admin2_code":"420.0",
    "gn:admin3_code":"42005",
    "gn:asciiname":"Sagawa",
    "gn:country_code":"NG",
    "gn:dem":553,
    "gn:feature_class":"P",
    "gn:feature_code":"PPL",
    "gn:name":"Sagawa",
    "gn:population":0,
    "gn:timezone":"Africa/Lagos",
    "iso:country":"NG",
    "wof:name":"Sagawa",
    "wof:placetype":"locality"
},
  "geometry": {"coordinates":[7.74573,12.54403],"type":"Point"}
}