{
  "type": "Feature",
  "properties": {
    "gn:admin1_code":"36.0",
    "gn:admin2_code":"10009.0",
    "gn:asciiname":"Igbide",
    "gn:country_code":"NG",
    "gn:dem":14,
    "gn:feature_class":"P",
    "gn:feature_code":"PPL",
    "gn:name":"Igbide",
    "gn:population":0,
    "gn:timezone":"Africa/Lagos",
    "iso:country":"NG",
    "wof:name":"Igbide",
    "wof:placetype":"locality"
},
  "geometry": {"coordinates":[6.14192,5.48528],"type":"Point"}
}