{
  "type": "Feature",
  "properties": {
    "gn:admin1_code":"32.0",
    "gn:admin2_code":"31005.0",
    "gn:asciiname":"Akinfenwa",
    "gn:country_code":"NG",
    "gn:dem":218,
    "gn:feature_class":"P",
    "gn:feature_code":"PPL",
    "gn:name":"Akinfenwa",
    "gn:population":0,
    "gn:timezone":"Africa/Lagos",
    "iso:country":"NG",
    "wof:name":"Akinfenwa",
    "wof:placetype":"locality"
},
  "geometry": {"coordinates":[3.95667,7.38111],"type":"Point"}
}