{
  "type": "Feature",
  "properties": {
    "gn:admin1_code":"56.0",
    "gn:admin2_code":"26013.0",
    "gn:asciiname":"Ungwan Maiganga",
    "gn:country_code":"NG",
    "gn:dem":427,
    "gn:feature_class":"P",
    "gn:feature_code":"PPL",
    "gn:name":"Ungwan Maiganga",
    "gn:population":0,
    "gn:timezone":"Africa/Lagos",
    "iso:country":"NG",
    "wof:name":"Ungwan Maiganga",
    "wof:placetype":"locality"
},
  "geometry": {"coordinates":[8.5556,9.00222],"type":"Point"}
}