{
  "type": "Feature",
  "properties": {
    "gn:admin1_code":"35.0",
    "gn:asciiname":"Wuro Mayo",
    "gn:country_code":"NG",
    "gn:dem":201,
    "gn:feature_class":"P",
    "gn:feature_code":"PPL",
    "gn:name":"Wuro Mayo",
    "gn:population":0,
    "gn:timezone":"Africa/Lagos",
    "iso:country":"NG",
    "name:eng_x_preferred":[
        "Wuro Mayo"
    ],
    "wof:name":"Wuro Mayo",
    "wof:placetype":"locality"
},
  "geometry": {"coordinates":[12.01974,9.29775],"type":"Point"}
}