{
  "type": "Feature",
  "properties": {
    "gn:admin1_code":"40.0",
    "gn:admin2_code":"515.0",
    "gn:admin3_code":"51506",
    "gn:asciiname":"Tungan Balure",
    "gn:country_code":"NG",
    "gn:dem":205,
    "gn:feature_class":"P",
    "gn:feature_code":"PPL",
    "gn:name":"Tungan Balure",
    "gn:population":0,
    "gn:timezone":"Africa/Lagos",
    "iso:country":"NG",
    "wof:name":"Tungan Balure",
    "wof:placetype":"locality"
},
  "geometry": {"coordinates":[4.94042,10.91133],"type":"Point"}
}