{
  "type": "Feature",
  "properties": {
    "gn:admin1_code":"35.0",
    "gn:admin2_code":"2014",
    "gn:asciiname":"Mbawa",
    "gn:country_code":"NG",
    "gn:dem":563,
    "gn:feature_class":"P",
    "gn:feature_code":"PPL",
    "gn:name":"Mbawa",
    "gn:population":0,
    "gn:timezone":"Africa/Lagos",
    "iso:country":"NG",
    "name:eng_x_preferred":[
        "Mbawa"
    ],
    "wof:name":"Mbawa",
    "wof:placetype":"locality"
},
  "geometry": {"coordinates":[13.1977,10.30075],"type":"Point"}
}