{
  "type": "Feature",
  "properties": {
    "gn:admin1_code":"57.0",
    "gn:admin2_code":"806.0",
    "gn:admin3_code":"80608",
    "gn:asciiname":"Ungwan Noma",
    "gn:country_code":"NG",
    "gn:dem":219,
    "gn:feature_class":"P",
    "gn:feature_code":"PPL",
    "gn:name":"Ungwan Noma",
    "gn:population":0,
    "gn:timezone":"Africa/Lagos",
    "iso:country":"NG",
    "wof:name":"Ungwan Noma",
    "wof:placetype":"locality"
},
  "geometry": {"coordinates":[4.93333,12.16667],"type":"Point"}
}