{
  "type": "Feature",
  "properties": {
    "gn:admin1_code":"52.0",
    "gn:admin2_code":"6006.0",
    "gn:asciiname":"Fati-Camp",
    "gn:country_code":"NG",
    "gn:dem":19,
    "gn:feature_class":"P",
    "gn:feature_code":"PPL",
    "gn:name":"Fati-Camp",
    "gn:population":0,
    "gn:timezone":"Africa/Lagos",
    "iso:country":"NG",
    "wof:name":"Fati-Camp",
    "wof:placetype":"locality"
},
  "geometry": {"coordinates":[6.06567,5.05969],"type":"Point"}
}