{
  "type": "Feature",
  "properties": {
    "gn:admin1_code":"31.0",
    "gn:admin2_code":"27010.0",
    "gn:asciiname":"Etsugale",
    "gn:country_code":"NG",
    "gn:dem":113,
    "gn:feature_class":"P",
    "gn:feature_code":"PPL",
    "gn:name":"Etsugale",
    "gn:population":0,
    "gn:timezone":"Africa/Lagos",
    "iso:country":"NG",
    "name:und_x_variant":[
        "Etsu Gaie",
        "Etsugale"
    ],
    "wof:name":"Etsugale",
    "wof:placetype":"locality"
},
  "geometry": {"coordinates":[6.28763,9.1702],"type":"Point"}
}