{
  "type": "Feature",
  "properties": {
    "gn:admin1_code":"27.0",
    "gn:asciiname":"Kwalam",
    "gn:country_code":"NG",
    "gn:dem":248,
    "gn:feature_class":"P",
    "gn:feature_code":"PPL",
    "gn:name":"Kwalam",
    "gn:population":0,
    "gn:timezone":"Africa/Lagos",
    "iso:country":"NG",
    "wof:name":"Kwalam",
    "wof:placetype":"locality"
},
  "geometry": {"coordinates":[11.57546,10.26381],"type":"Point"}
}