{
  "type": "Feature",
  "properties": {
    "gn:admin1_code":"37.0",
    "gn:admin2_code":"12008.0",
    "gn:asciiname":"Ivianopodi",
    "gn:country_code":"NG",
    "gn:dem":292,
    "gn:feature_class":"P",
    "gn:feature_code":"PPL",
    "gn:name":"Ivianopodi",
    "gn:population":0,
    "gn:timezone":"Africa/Lagos",
    "iso:country":"NG",
    "name:und_x_variant":[
        "Iyanipodi",
        "Ivianopodi"
    ],
    "wof:name":"Ivianopodi",
    "wof:placetype":"locality"
},
  "geometry": {"coordinates":[6.5909,7.137],"type":"Point"}
}