{
  "type": "Feature",
  "properties": {
    "gn:admin1_code":"24.0",
    "gn:admin2_code":"425.0",
    "gn:admin3_code":"42511",
    "gn:asciiname":"Mainashi",
    "gn:country_code":"NG",
    "gn:dem":601,
    "gn:feature_class":"P",
    "gn:feature_code":"PPL",
    "gn:name":"Mainashi",
    "gn:population":0,
    "gn:timezone":"Africa/Lagos",
    "iso:country":"NG",
    "wof:name":"Mainashi",
    "wof:placetype":"locality"
},
  "geometry": {"coordinates":[7.48625,11.79053],"type":"Point"}
}