{
  "type": "Feature",
  "properties": {
    "iso:country":"NG",
    "name:ceb_x_preferred":[
        "Talata Mafara"
    ],
    "name:eng_x_preferred":[
        "Talata Mafara"
    ],
    "name:fra_x_preferred":[
        "Talata Mafara"
    ],
    "name:ful_x_preferred":[
        "Talata Mafara"
    ],
    "name:hau_x_preferred":[
        "Talata-Mafara"
    ],
    "name:ita_x_preferred":[
        "Talata Mafara"
    ],
    "name:nan_x_preferred":[
        "Talata Mafara"
    ],
    "name:spa_x_preferred":[
        "Talata Mafara"
    ],
    "name:yor_x_preferred":[
        "Agb\u00e8gb\u00e8 \u00ccj\u1ecdba \u00ccb\u00edl\u1eb9\u0300 Talata Mafara"
    ],
    "name:zho_min_nan_x_preferred":[
        "Talata Mafara"
    ],
    "name:zho_x_preferred":[
        "\u5854\u62c9\u5854\u9a6c\u6cd5\u62c9"
    ],
    "qs:gn_country":"NG",
    "qs:gn_fcode":"PPL",
    "qs:gn_pop":39045,
    "qs:name":"Talata Mafara",
    "qs:name_adm0":"Nigeria",
    "qs:name_adm1":"Zamfara",
    "qs:photos":0,
    "qs:photos_1k":0,
    "qs:photos_9k":1,
    "qs:photos_9r":1,
    "qs:photos_all":1,
    "qs:photos_sr":0,
    "qs:placetype":"Town",
    "qs:pop_sr":"7",
    "qs:woe_adm0":23424908,
    "wd:wordcount":162,
    "wof:name":"Talata Mafara",
    "wof:placetype":"locality",
    "wof:population":39045
},
  "geometry": {"coordinates":[6.05971,12.57317],"type":"Point"}
}