{
  "type": "Feature",
  "properties": {
    "gn:admin1_code":"43.0",
    "gn:admin2_code":"35002.0",
    "gn:asciiname":"Bunga",
    "gn:country_code":"NG",
    "gn:dem":186,
    "gn:feature_class":"P",
    "gn:feature_code":"PPL",
    "gn:name":"Bunga",
    "gn:population":0,
    "gn:timezone":"Africa/Lagos",
    "iso:country":"NG",
    "name:ceb_x_preferred":[
        "Bunga"
    ],
    "name:ind_x_preferred":[
        "Bunga"
    ],
    "name:swe_x_preferred":[
        "Bunga"
    ],
    "name:tgl_x_preferred":[
        "Bunga"
    ],
    "wof:name":"Bunga",
    "wof:placetype":"locality"
},
  "geometry": {"coordinates":[10.8832,7.85171],"type":"Point"}
}