{
  "type": "Feature",
  "properties": {
    "gn:admin1_code":"46.0",
    "gn:admin2_code":"5020",
    "gn:admin3_code":"BA2003",
    "gn:asciiname":"Alagarno",
    "gn:country_code":"NG",
    "gn:dem":364,
    "gn:feature_class":"P",
    "gn:feature_code":"PPL",
    "gn:name":"Alagarno",
    "gn:population":0,
    "gn:timezone":"Africa/Lagos",
    "iso:country":"NG",
    "wof:name":"Alagarno",
    "wof:placetype":"locality"
},
  "geometry": {"coordinates":[10.27885,12.19931],"type":"Point"}
}