{
  "type": "Feature",
  "properties": {
    "gn:admin1_code":"28.0",
    "gn:admin2_code":"17013.0",
    "gn:asciiname":"Okwudo",
    "gn:country_code":"NG",
    "gn:dem":136,
    "gn:feature_class":"P",
    "gn:feature_code":"PPL",
    "gn:name":"Okwudo",
    "gn:population":0,
    "gn:timezone":"Africa/Lagos",
    "iso:country":"NG",
    "wof:name":"Okwudo",
    "wof:placetype":"locality"
},
  "geometry": {"coordinates":[7.00678,5.71566],"type":"Point"}
}