{
  "type": "Feature",
  "properties": {
    "gn:admin1_code":"55.0",
    "gn:admin2_code":"16001.0",
    "gn:asciiname":"Chabal",
    "gn:country_code":"NG",
    "gn:dem":466,
    "gn:feature_class":"P",
    "gn:feature_code":"PPL",
    "gn:name":"Chabal",
    "gn:population":0,
    "gn:timezone":"Africa/Lagos",
    "iso:country":"NG",
    "name:und_x_variant":[
        "Chabai",
        "Chabal"
    ],
    "wof:name":"Chabal",
    "wof:placetype":"locality"
},
  "geometry": {"coordinates":[11.19357,10.06362],"type":"Point"}
}