{
  "type": "Feature",
  "properties": {
    "gn:admin1_code":"43.0",
    "gn:asciiname":"Kanbu",
    "gn:country_code":"NG",
    "gn:dem":438,
    "gn:feature_class":"P",
    "gn:feature_code":"PPL",
    "gn:name":"Kanbu",
    "gn:population":0,
    "gn:timezone":"Africa/Lagos",
    "iso:country":"NG",
    "name:eng_x_preferred":[
        "Kanbu"
    ],
    "wof:name":"Kanbu",
    "wof:placetype":"locality"
},
  "geometry": {"coordinates":[11.0433,9.46631],"type":"Point"}
}