{
  "type": "Feature",
  "properties": {
    "gn:admin1_code":"25.0",
    "gn:admin2_code":"4020.0",
    "gn:asciiname":"Okpulukpu",
    "gn:country_code":"NG",
    "gn:dem":145,
    "gn:feature_class":"P",
    "gn:feature_code":"PPL",
    "gn:name":"Okpulukpu",
    "gn:population":0,
    "gn:timezone":"Africa/Lagos",
    "iso:country":"NG",
    "wof:name":"Okpulukpu",
    "wof:placetype":"locality"
},
  "geometry": {"coordinates":[7.1591,5.96778],"type":"Point"}
}