{
  "type": "Feature",
  "properties": {
    "gn:admin1_code":"29.0",
    "gn:admin2_code":"20039.0",
    "gn:admin3_code":"KN2905",
    "gn:asciiname":"Sabon Ruwa",
    "gn:country_code":"NG",
    "gn:dem":473,
    "gn:feature_class":"P",
    "gn:feature_code":"PPL",
    "gn:name":"Sabon Ruwa",
    "gn:population":0,
    "gn:timezone":"Africa/Lagos",
    "iso:country":"NG",
    "wof:name":"Sabon Ruwa",
    "wof:placetype":"locality"
},
  "geometry": {"coordinates":[8.43614,12.37129],"type":"Point"}
}