{
  "type": "Feature",
  "properties": {
    "gn:admin1_code":"29.0",
    "gn:admin2_code":"20010.0",
    "gn:admin3_code":"KN1711",
    "gn:asciiname":"Ganmawa",
    "gn:country_code":"NG",
    "gn:dem":449,
    "gn:feature_class":"P",
    "gn:feature_code":"PPL",
    "gn:name":"Ganmawa",
    "gn:population":0,
    "gn:timezone":"Africa/Lagos",
    "iso:country":"NG",
    "wof:name":"Ganmawa",
    "wof:placetype":"locality"
},
  "geometry": {"coordinates":[8.71384,12.0942],"type":"Point"}
}