{
  "type": "Feature",
  "properties": {
    "gn:admin1_code":"37.0",
    "gn:admin2_code":"12010.0",
    "gn:asciiname":"Ewossa",
    "gn:country_code":"NG",
    "gn:dem":278,
    "gn:feature_class":"P",
    "gn:feature_code":"PPL",
    "gn:name":"Ewossa",
    "gn:population":0,
    "gn:timezone":"Africa/Lagos",
    "iso:country":"NG",
    "name:eng_x_preferred":[
        "Ewossa"
    ],
    "wof:name":"Ewossa",
    "wof:placetype":"locality"
},
  "geometry": {"coordinates":[6.27309,6.46124],"type":"Point"}
}