{
  "type": "Feature",
  "properties": {
    "gn:admin1_code":"43.0",
    "gn:asciiname":"Jesal",
    "gn:country_code":"NG",
    "gn:dem":153,
    "gn:feature_class":"P",
    "gn:feature_code":"PPL",
    "gn:name":"Jesal",
    "gn:population":0,
    "gn:timezone":"Africa/Lagos",
    "iso:country":"NG",
    "name:eng_x_preferred":[
        "Jesal"
    ],
    "wof:name":"Jesal",
    "wof:placetype":"locality"
},
  "geometry": {"coordinates":[11.13964,9.31237],"type":"Point"}
}