{
  "type": "Feature",
  "properties": {
    "gn:admin1_code":"26.0",
    "gn:admin2_code":"7001.0",
    "gn:asciiname":"Adidabe",
    "gn:country_code":"NG",
    "gn:dem":88,
    "gn:feature_class":"P",
    "gn:feature_code":"PPL",
    "gn:name":"Adidabe",
    "gn:population":0,
    "gn:timezone":"Africa/Lagos",
    "iso:country":"NG",
    "wof:name":"Adidabe",
    "wof:placetype":"locality"
},
  "geometry": {"coordinates":[8.15331,6.76082],"type":"Point"}
}