{
  "type": "Feature",
  "properties": {
    "gn:admin1_code":"26.0",
    "gn:admin2_code":"7010.0",
    "gn:asciiname":"Ayem",
    "gn:country_code":"NG",
    "gn:dem":107,
    "gn:feature_class":"P",
    "gn:feature_code":"PPL",
    "gn:name":"Ayem",
    "gn:population":0,
    "gn:timezone":"Africa/Lagos",
    "iso:country":"NG",
    "name:ron_x_preferred":[
        "Ayem"
    ],
    "wof:name":"Ayem",
    "wof:placetype":"locality"
},
  "geometry": {"coordinates":[8.5499,7.13973],"type":"Point"}
}