{
  "type": "Feature",
  "properties": {
    "gn:admin1_code":"31.0",
    "gn:admin2_code":"27022",
    "gn:asciiname":"Anguangkola",
    "gn:country_code":"NG",
    "gn:dem":300,
    "gn:feature_class":"P",
    "gn:feature_code":"PPL",
    "gn:name":"Anguangkola",
    "gn:population":0,
    "gn:timezone":"Africa/Lagos",
    "iso:country":"NG",
    "wof:name":"Anguangkola",
    "wof:placetype":"locality"
},
  "geometry": {"coordinates":[6.71461,9.57315],"type":"Point"}
}