{
  "type": "Feature",
  "properties": {
    "gn:admin1_code":"27.0",
    "gn:admin2_code":"117.0",
    "gn:admin3_code":"11709",
    "gn:asciiname":"Tarari",
    "gn:country_code":"NG",
    "gn:dem":291,
    "gn:feature_class":"P",
    "gn:feature_code":"PPL",
    "gn:name":"Tarari",
    "gn:population":0,
    "gn:timezone":"Africa/Lagos",
    "iso:country":"NG",
    "name:und_x_variant":[
        "Bulabulin"
    ],
    "wof:name":"Tarari",
    "wof:placetype":"locality"
},
  "geometry": {"coordinates":[13.61497,12.92955],"type":"Point"}
}