{
  "type": "Feature",
  "properties": {
    "gn:admin1_code":"35.0",
    "gn:admin2_code":"2003.0",
    "gn:asciiname":"Gangjari",
    "gn:country_code":"NG",
    "gn:dem":546,
    "gn:feature_class":"P",
    "gn:feature_code":"PPL",
    "gn:name":"Gangjari",
    "gn:population":0,
    "gn:timezone":"Africa/Lagos",
    "iso:country":"NG",
    "wof:name":"Gangjari",
    "wof:placetype":"locality"
},
  "geometry": {"coordinates":[11.92275,8.54474],"type":"Point"}
}