{
  "type": "Feature",
  "properties": {
    "gn:admin1_code":"36.0",
    "gn:admin2_code":"10017.0",
    "gn:asciiname":"Elume",
    "gn:country_code":"NG",
    "gn:dem":12,
    "gn:feature_class":"P",
    "gn:feature_code":"PPL",
    "gn:name":"Elume",
    "gn:population":0,
    "gn:timezone":"Africa/Lagos",
    "iso:country":"NG",
    "name:eng_x_preferred":[
        "Elume"
    ],
    "wof:name":"Elume",
    "wof:placetype":"locality"
},
  "geometry": {"coordinates":[5.63722,5.73715],"type":"Point"}
}