{
  "type": "Feature",
  "properties": {
    "gn:admin1_code":"31.0",
    "gn:admin2_code":"27008",
    "gn:asciiname":"Emigi",
    "gn:country_code":"NG",
    "gn:dem":103,
    "gn:feature_class":"P",
    "gn:feature_code":"PPL",
    "gn:name":"Emigi",
    "gn:population":0,
    "gn:timezone":"Africa/Lagos",
    "iso:country":"NG",
    "name:ara_x_preferred":[
        "\u0627\u0645\u064a\u063a\u064a"
    ],
    "name:fas_x_preferred":[
        "\u0686\u0648\u062e\u0648\u0646"
    ],
    "name:msa_x_preferred":[
        "Emigi"
    ],
    "wof:name":"Emigi",
    "wof:placetype":"locality"
},
  "geometry": {"coordinates":[5.90693,9.25581],"type":"Point"}
}