{
  "type": "Feature",
  "properties": {
    "gn:admin1_code":"27.0",
    "gn:admin2_code":"102.0",
    "gn:admin3_code":"10203",
    "gn:asciiname":"Bukar Thlawur",
    "gn:country_code":"NG",
    "gn:dem":467,
    "gn:feature_class":"P",
    "gn:feature_code":"PPL",
    "gn:name":"Bukar Thlawur",
    "gn:population":0,
    "gn:timezone":"Africa/Lagos",
    "iso:country":"NG",
    "wof:name":"Bukar Thlawur",
    "wof:placetype":"locality"
},
  "geometry": {"coordinates":[12.88497,10.64523],"type":"Point"}
}