{
  "type": "Feature",
  "properties": {
    "gn:admin1_code":"16.0",
    "gn:admin2_code":"28007.0",
    "gn:asciiname":"Ijoko-Lemode",
    "gn:country_code":"NG",
    "gn:dem":77,
    "gn:feature_class":"P",
    "gn:feature_code":"PPL",
    "gn:name":"Ijoko-Lemode",
    "gn:population":0,
    "gn:timezone":"Africa/Lagos",
    "iso:country":"NG",
    "wof:name":"Ijoko-Lemode",
    "wof:placetype":"neighbourhood"
},
  "geometry": {"coordinates":[3.28745,6.7301],"type":"Point"}
}