{
  "type": "Feature",
  "properties": {
    "gn:admin1_code":"21.0",
    "gn:admin2_code":"3014.0",
    "gn:asciiname":"Ikot Obong Erong",
    "gn:country_code":"NG",
    "gn:dem":86,
    "gn:feature_class":"P",
    "gn:feature_code":"PPL",
    "gn:name":"Ikot Obong Erong",
    "gn:population":0,
    "gn:timezone":"Africa/Lagos",
    "iso:country":"NG",
    "wof:name":"Ikot Obong Erong",
    "wof:placetype":"locality"
},
  "geometry": {"coordinates":[7.69156,5.16583],"type":"Point"}
}