{
  "type": "Feature",
  "properties": {
    "gn:admin1_code":"23.0",
    "gn:admin2_code":"19007.0",
    "gn:admin3_code":"KD0701",
    "gn:asciiname":"Aso",
    "gn:country_code":"NG",
    "gn:dem":527,
    "gn:feature_class":"P",
    "gn:feature_code":"PPL",
    "gn:name":"Aso",
    "gn:population":0,
    "gn:timezone":"Africa/Lagos",
    "iso:country":"NG",
    "name:und_x_variant":[
        "Asau",
        "Aso"
    ],
    "wof:name":"Aso",
    "wof:placetype":"locality"
},
  "geometry": {"coordinates":[8.16565,9.43412],"type":"Point"}
}