{
  "type": "Feature",
  "properties": {
    "gn:admin1_code":"31.0",
    "gn:admin2_code":"27018.0",
    "gn:asciiname":"Bakuchi",
    "gn:country_code":"NG",
    "gn:dem":566,
    "gn:feature_class":"P",
    "gn:feature_code":"PPL",
    "gn:name":"Bakuchi",
    "gn:population":0,
    "gn:timezone":"Africa/Lagos",
    "iso:country":"NG",
    "wof:name":"Bakuchi",
    "wof:placetype":"locality"
},
  "geometry": {"coordinates":[7.23449,9.88712],"type":"Point"}
}