{
  "type": "Feature",
  "properties": {
    "gn:admin1_code":"57.0",
    "gn:admin2_code":"810.0",
    "gn:admin3_code":"81007",
    "gn:asciiname":"Gidan Dago",
    "gn:country_code":"NG",
    "gn:dem":472,
    "gn:feature_class":"P",
    "gn:feature_code":"PPL",
    "gn:name":"Gidan Dago",
    "gn:population":0,
    "gn:timezone":"Africa/Lagos",
    "iso:country":"NG",
    "wof:name":"Gidan Dago",
    "wof:placetype":"locality"
},
  "geometry": {"coordinates":[6.39847,11.24822],"type":"Point"}
}