{
  "type": "Feature",
  "properties": {
    "gn:admin1_code":"40.0",
    "gn:admin2_code":"517.0",
    "gn:admin3_code":"51710",
    "gn:asciiname":"Zugu Teni",
    "gn:country_code":"NG",
    "gn:dem":161,
    "gn:feature_class":"P",
    "gn:feature_code":"PPL",
    "gn:name":"Zugu Teni",
    "gn:population":0,
    "gn:timezone":"Africa/Lagos",
    "iso:country":"NG",
    "wof:name":"Zugu Teni",
    "wof:placetype":"locality"
},
  "geometry": {"coordinates":[4.51746,11.2616],"type":"Point"}
}