{
  "type": "Feature",
  "properties": {
    "gn:admin1_code":"51.0",
    "gn:admin2_code":"606.0",
    "gn:admin3_code":"60608",
    "gn:asciiname":"Dabalmawa",
    "gn:country_code":"NG",
    "gn:dem":224,
    "gn:feature_class":"P",
    "gn:feature_code":"PPL",
    "gn:name":"Dabalmawa",
    "gn:population":0,
    "gn:timezone":"Africa/Lagos",
    "iso:country":"NG",
    "wof:name":"Dabalmawa",
    "wof:placetype":"locality"
},
  "geometry": {"coordinates":[4.35,13.55],"type":"Point"}
}