{
  "type": "Feature",
  "properties": {
    "gn:admin1_code":"54.0",
    "gn:admin2_code":"13008.0",
    "gn:asciiname":"Ido-Ekiti",
    "gn:country_code":"NG",
    "gn:dem":569,
    "gn:feature_class":"P",
    "gn:feature_code":"PPLA2",
    "gn:name":"Ido-Ekiti",
    "gn:population":0,
    "gn:timezone":"Africa/Lagos",
    "iso:country":"NG",
    "name:und_x_variant":[
        "Iddo",
        "Iddo-Ekiti",
        "Ido-Ekiti",
        "Ido"
    ],
    "wof:name":"Ido-Ekiti",
    "wof:placetype":"locality"
},
  "geometry": {"coordinates":[5.18314,7.84598],"type":"Point"}
}