{
  "type": "Feature",
  "properties": {
    "gn:admin1_code":"27.0",
    "gn:admin2_code":"123.0",
    "gn:admin3_code":"12310",
    "gn:asciiname":"Mangal",
    "gn:country_code":"NG",
    "gn:dem":292,
    "gn:feature_class":"P",
    "gn:feature_code":"PPL",
    "gn:name":"Mangal",
    "gn:population":0,
    "gn:timezone":"Africa/Lagos",
    "iso:country":"NG",
    "name:und_x_variant":[
        "Mangol",
        "Mangal"
    ],
    "wof:name":"Mangal",
    "wof:placetype":"locality"
},
  "geometry": {"coordinates":[13.51416,12.50924],"type":"Point"}
}