{
  "type": "Feature",
  "properties": {
    "gn:admin1_code":"27.0",
    "gn:admin2_code":"112.0",
    "gn:admin3_code":"11201",
    "gn:asciiname":"Burugwi",
    "gn:country_code":"NG",
    "gn:dem":790,
    "gn:feature_class":"P",
    "gn:feature_code":"PPL",
    "gn:name":"Burugwi",
    "gn:population":0,
    "gn:timezone":"Africa/Lagos",
    "iso:country":"NG",
    "name:und_x_variant":[
        "Balungwe",
        "Burugwi"
    ],
    "wof:name":"Burugwi",
    "wof:placetype":"locality"
},
  "geometry": {"coordinates":[12.25989,10.49174],"type":"Point"}
}