{
  "type": "Feature",
  "properties": {
    "gn:admin1_code":"11.0",
    "gn:admin2_code":"15004.0",
    "gn:asciiname":"Buzai Tudai",
    "gn:cc2":"NG",
    "gn:country_code":"NG",
    "gn:dem":465,
    "gn:feature_class":"P",
    "gn:feature_code":"PPL",
    "gn:name":"Buzai Tudai",
    "gn:population":0,
    "gn:timezone":"Africa/Lagos",
    "iso:country":"NG",
    "name:und_x_variant":[
        "Tudai",
        "Buzai Tudai"
    ],
    "wof:name":"Buzai Tudai",
    "wof:placetype":"locality"
},
  "geometry": {"coordinates":[7.17667,8.57194],"type":"Point"}
}