{
  "type": "Feature",
  "properties": {
    "gn:admin1_code":"21.0",
    "gn:admin2_code":"3006.0",
    "gn:asciiname":"Nkporikpo",
    "gn:country_code":"NG",
    "gn:dem":43,
    "gn:feature_class":"P",
    "gn:feature_code":"PPL",
    "gn:name":"Nkporikpo",
    "gn:population":0,
    "gn:timezone":"Africa/Lagos",
    "iso:country":"NG",
    "wof:name":"Nkporikpo",
    "wof:placetype":"locality"
},
  "geometry": {"coordinates":[7.4862,4.92598],"type":"Point"}
}