{
  "type": "Feature",
  "properties": {
    "gn:admin1_code":"36.0",
    "gn:admin2_code":"10002.0",
    "gn:asciiname":"Ogbe-Odogwu",
    "gn:country_code":"NG",
    "gn:dem":119,
    "gn:feature_class":"P",
    "gn:feature_code":"PPL",
    "gn:name":"Ogbe-Odogwu",
    "gn:population":0,
    "gn:timezone":"Africa/Lagos",
    "iso:country":"NG",
    "name:eng_x_preferred":[
        "Ogbe-Odogwu"
    ],
    "wof:name":"Ogbe-Odogwu",
    "wof:placetype":"locality"
},
  "geometry": {"coordinates":[6.4942,6.13119],"type":"Point"}
}