{
  "type": "Feature",
  "properties": {
    "gn:admin1_code":"16.0",
    "gn:admin2_code":"28015.0",
    "gn:asciiname":"Oko",
    "gn:country_code":"NG",
    "gn:dem":141,
    "gn:feature_class":"P",
    "gn:feature_code":"PPL",
    "gn:name":"Oko",
    "gn:population":0,
    "gn:timezone":"Africa/Lagos",
    "iso:country":"NG",
    "name:bul_x_preferred":[
        "\u041e\u043a\u043e"
    ],
    "name:deu_x_preferred":[
        "Oko"
    ],
    "name:fin_x_preferred":[
        "Oko"
    ],
    "name:fra_x_preferred":[
        "Oko"
    ],
    "name:pol_x_preferred":[
        "Oko"
    ],
    "name:por_x_preferred":[
        "Oko"
    ],
    "name:rus_x_preferred":[
        "\u041e\u043a\u043e"
    ],
    "wof:name":"Oko",
    "wof:placetype":"locality"
},
  "geometry": {"coordinates":[3.51667,7.13333],"type":"Point"}
}