{
  "type": "Feature",
  "properties": {
    "gn:admin1_code":"27.0",
    "gn:admin2_code":"111.0",
    "gn:admin3_code":"11113",
    "gn:asciiname":"Jokwa",
    "gn:country_code":"NG",
    "gn:dem":346,
    "gn:feature_class":"P",
    "gn:feature_code":"PPL",
    "gn:name":"Jokwa",
    "gn:population":0,
    "gn:timezone":"Africa/Lagos",
    "iso:country":"NG",
    "wof:name":"Jokwa",
    "wof:placetype":"locality"
},
  "geometry": {"coordinates":[13.6559,11.29532],"type":"Point"}
}