{
  "type": "Feature",
  "properties": {
    "gn:admin1_code":"32.0",
    "gn:admin2_code":"31001.0",
    "gn:asciiname":"Baba Sale",
    "gn:country_code":"NG",
    "gn:dem":278,
    "gn:feature_class":"P",
    "gn:feature_code":"PPL",
    "gn:name":"Baba Sale",
    "gn:population":0,
    "gn:timezone":"Africa/Lagos",
    "iso:country":"NG",
    "wof:name":"Baba Sale",
    "wof:placetype":"locality"
},
  "geometry": {"coordinates":[3.86,7.70028],"type":"Point"}
}