{
  "type": "Feature",
  "properties": {
    "gn:admin1_code":"26.0",
    "gn:admin2_code":"7010.0",
    "gn:asciiname":"Ugba-Gbe",
    "gn:country_code":"NG",
    "gn:dem":118,
    "gn:feature_class":"P",
    "gn:feature_code":"PPL",
    "gn:name":"Ugba-Gbe",
    "gn:population":0,
    "gn:timezone":"Africa/Lagos",
    "iso:country":"NG",
    "wof:name":"Ugba-Gbe",
    "wof:placetype":"locality"
},
  "geometry": {"coordinates":[8.55677,7.18967],"type":"Point"}
}