{
  "type": "Feature",
  "properties": {
    "gn:admin1_code":"51.0",
    "gn:admin2_code":"608.0",
    "gn:admin3_code":"60805",
    "gn:asciiname":"Masalawan Duchi",
    "gn:country_code":"NG",
    "gn:dem":320,
    "gn:feature_class":"P",
    "gn:feature_code":"PPL",
    "gn:name":"Masalawan Duchi",
    "gn:population":0,
    "gn:timezone":"Africa/Lagos",
    "iso:country":"NG",
    "wof:name":"Masalawan Duchi",
    "wof:placetype":"locality"
},
  "geometry": {"coordinates":[5.48868,13.63686],"type":"Point"}
}