{
  "type": "Feature",
  "properties": {
    "gn:admin1_code":"43.0",
    "gn:admin2_code":"35001.0",
    "gn:asciiname":"Ungwar Abba",
    "gn:country_code":"NG",
    "gn:dem":238,
    "gn:feature_class":"P",
    "gn:feature_code":"PPL",
    "gn:name":"Ungwar Abba",
    "gn:population":0,
    "gn:timezone":"Africa/Lagos",
    "iso:country":"NG",
    "wof:name":"Ungwar Abba",
    "wof:placetype":"locality"
},
  "geometry": {"coordinates":[11.35996,8.83672],"type":"Point"}
}