{
  "type": "Feature",
  "properties": {
    "gn:admin1_code":"40.0",
    "gn:admin2_code":"515.0",
    "gn:admin3_code":"51507",
    "gn:asciiname":"Guguwa",
    "gn:country_code":"NG",
    "gn:dem":148,
    "gn:feature_class":"P",
    "gn:feature_code":"PPL",
    "gn:name":"Guguwa",
    "gn:population":0,
    "gn:timezone":"Africa/Lagos",
    "iso:country":"NG",
    "wof:name":"Guguwa",
    "wof:placetype":"locality"
},
  "geometry": {"coordinates":[4.69466,10.58181],"type":"Point"}
}