{
  "type": "Feature",
  "properties": {
    "gn:admin1_code":"48.0",
    "gn:admin2_code":"29004.0",
    "gn:asciiname":"Supare",
    "gn:country_code":"NG",
    "gn:dem":335,
    "gn:feature_class":"P",
    "gn:feature_code":"PPL",
    "gn:name":"Supare",
    "gn:population":0,
    "gn:timezone":"Africa/Lagos",
    "iso:country":"NG",
    "name:und_x_variant":[
        "Sopare",
        "Shupare",
        "Supare"
    ],
    "wof:name":"Supare",
    "wof:placetype":"locality"
},
  "geometry": {"coordinates":[5.69357,7.45245],"type":"Point"}
}