{
  "type": "Feature",
  "properties": {
    "gn:admin1_code":"36.0",
    "gn:admin2_code":"10005.0",
    "gn:asciiname":"Oriah",
    "gn:country_code":"NG",
    "gn:dem":24,
    "gn:feature_class":"P",
    "gn:feature_code":"PPL",
    "gn:name":"Oriah",
    "gn:population":0,
    "gn:timezone":"Africa/Lagos",
    "iso:country":"NG",
    "wof:name":"Oriah",
    "wof:placetype":"locality"
},
  "geometry": {"coordinates":[6.05385,5.76009],"type":"Point"}
}