{
  "type": "Feature",
  "properties": {
    "gn:admin1_code":"22.0",
    "gn:admin2_code":"9006.0",
    "gn:asciiname":"Umon Town",
    "gn:country_code":"NG",
    "gn:dem":13,
    "gn:feature_class":"P",
    "gn:feature_code":"PPL",
    "gn:name":"Umon Town",
    "gn:population":0,
    "gn:timezone":"Africa/Lagos",
    "iso:country":"NG",
    "name:und_x_variant":[
        "Umon",
        "Umon Town"
    ],
    "wof:name":"Umon Town",
    "wof:placetype":"locality"
},
  "geometry": {"coordinates":[8.08291,5.31943],"type":"Point"}
}