{
  "type": "Feature",
  "properties": {
    "gn:admin1_code":"49.0",
    "gn:admin2_code":"32003.0",
    "gn:asciiname":"Richa",
    "gn:country_code":"NG",
    "gn:dem":1061,
    "gn:feature_class":"P",
    "gn:feature_code":"PPL",
    "gn:name":"Richa",
    "gn:population":0,
    "gn:timezone":"Africa/Lagos",
    "iso:country":"NG",
    "name:und_x_variant":[
        "Richu",
        "Richa"
    ],
    "wof:name":"Richa",
    "wof:placetype":"locality"
},
  "geometry": {"coordinates":[8.87538,9.12449],"type":"Point"}
}