{
  "type": "Feature",
  "properties": {
    "gn:admin1_code":"26.0",
    "gn:admin2_code":"7012",
    "gn:asciiname":"Gbagur",
    "gn:country_code":"NG",
    "gn:dem":184,
    "gn:feature_class":"P",
    "gn:feature_code":"PPL",
    "gn:name":"Gbagur",
    "gn:population":0,
    "gn:timezone":"Africa/Lagos",
    "iso:country":"NG",
    "wof:name":"Gbagur",
    "wof:placetype":"locality"
},
  "geometry": {"coordinates":[9.3327,7.69192],"type":"Point"}
}