{
  "type": "Feature",
  "properties": {
    "gn:admin1_code":"40.0",
    "gn:admin2_code":"514.0",
    "gn:admin3_code":"51410",
    "gn:asciiname":"Kangiwa",
    "gn:country_code":"NG",
    "gn:dem":236,
    "gn:feature_class":"P",
    "gn:feature_code":"PPL",
    "gn:name":"Kangiwa",
    "gn:population":0,
    "gn:timezone":"Africa/Lagos",
    "iso:country":"NG",
    "wof:name":"Kangiwa",
    "wof:placetype":"locality"
},
  "geometry": {"coordinates":[4.2718,12.29714],"type":"Point"}
}