{
  "type": "Feature",
  "properties": {
    "gn:admin1_code":"42.0",
    "gn:admin2_code":"30026.0",
    "gn:asciiname":"Bode Osi",
    "gn:country_code":"NG",
    "gn:dem":298,
    "gn:feature_class":"P",
    "gn:feature_code":"PPLA2",
    "gn:name":"Bode Osi",
    "gn:population":0,
    "gn:timezone":"Africa/Lagos",
    "iso:country":"NG",
    "name:und_x_variant":[
        "Ibode-Osi",
        "Ibede-Osi",
        "Bode-Olla",
        "Bode Osi",
        "Bode-Olle"
    ],
    "wof:name":"Bode Osi",
    "wof:placetype":"locality"
},
  "geometry": {"coordinates":[4.2298,7.75103],"type":"Point"}
}