{
  "type": "Feature",
  "properties": {
    "gn:admin1_code":"16.0",
    "gn:admin2_code":"28005.0",
    "gn:asciiname":"Idawgo",
    "gn:cc2":"NG",
    "gn:country_code":"NG",
    "gn:dem":14,
    "gn:feature_class":"P",
    "gn:feature_code":"PPL",
    "gn:name":"Idawgo",
    "gn:population":0,
    "gn:timezone":"Africa/Lagos",
    "iso:country":"NG",
    "name:und_x_variant":[
        "Idagaw",
        "Idogo",
        "Idawgaw",
        "Idawgo"
    ],
    "wof:name":"Idawgo",
    "wof:placetype":"locality"
},
  "geometry": {"coordinates":[2.91667,6.83333],"type":"Point"}
}