{
  "type": "Feature",
  "properties": {
    "gn:admin1_code":"51.0",
    "gn:admin2_code":"602.0",
    "gn:admin3_code":"60209",
    "gn:asciiname":"Bute",
    "gn:country_code":"NG",
    "gn:dem":288,
    "gn:feature_class":"P",
    "gn:feature_code":"PPL",
    "gn:name":"Bute",
    "gn:population":0,
    "gn:timezone":"Africa/Lagos",
    "iso:country":"NG",
    "wof:name":"Bute",
    "wof:placetype":"locality"
},
  "geometry": {"coordinates":[5.1876,12.93697],"type":"Point"}
}