{
  "type": "Feature",
  "properties": {
    "gn:admin1_code":"51.0",
    "gn:admin2_code":"602.0",
    "gn:admin3_code":"60209",
    "gn:asciiname":"Bute",
    "gn:country_code":"NG",
    "gn:dem":288,
    "gn:feature_class":"P",
    "gn:feature_code":"PPL",
    "gn:name":"Bute",
    "gn:population":0,
    "gn:timezone":"Africa/Lagos",
    "iso:country":"NG",
    "name:bar_x_preferred":[
        "Bute"
    ],
    "name:bre_x_preferred":[
        "Bute"
    ],
    "name:ceb_x_preferred":[
        "Bute"
    ],
    "name:cym_x_preferred":[
        "Bute"
    ],
    "name:deu_x_preferred":[
        "Bute"
    ],
    "name:fra_x_preferred":[
        "Bute"
    ],
    "name:ita_x_preferred":[
        "Bute"
    ],
    "name:nld_x_preferred":[
        "Bute"
    ],
    "name:nor_x_preferred":[
        "Bute"
    ],
    "name:srp_x_preferred":[
        "Bute"
    ],
    "name:swe_x_preferred":[
        "Bute"
    ],
    "name:ukr_x_preferred":[
        "\u0411'\u044e\u0442"
    ],
    "wof:name":"Bute",
    "wof:placetype":"locality"
},
  "geometry": {"coordinates":[5.1876,12.93697],"type":"Point"}
}