{
  "type": "Feature",
  "properties": {
    "gn:admin1_code":"48.0",
    "gn:admin2_code":"29017.0",
    "gn:asciiname":"Arimogija",
    "gn:country_code":"NG",
    "gn:dem":59,
    "gn:feature_class":"P",
    "gn:feature_code":"PPL",
    "gn:name":"Arimogija",
    "gn:population":0,
    "gn:timezone":"Africa/Lagos",
    "iso:country":"NG",
    "wof:name":"Arimogija",
    "wof:placetype":"locality"
},
  "geometry": {"coordinates":[5.70383,6.82115],"type":"Point"}
}