{
  "type": "Feature",
  "properties": {
    "gn:country":"NG",
    "gn:fcode":"PPL",
    "gn:pop":6801,
    "iso:country":"NG",
    "qs:name":"Abocho",
    "qs:photos_9r":0,
    "qs:photos_sr":0,
    "qs:pop_sr":"5",
    "wof:name":"Abocho",
    "wof:placetype":"locality",
    "wof:population":6801
},
  "geometry": {"coordinates":[6.9863,7.5677],"type":"Point"}
}