{
  "type": "Feature",
  "properties": {
    "gn:admin1_code":"22.0",
    "gn:admin2_code":"9003.0",
    "gn:asciiname":"Idebe Ikot Essien",
    "gn:country_code":"NG",
    "gn:dem":40,
    "gn:feature_class":"P",
    "gn:feature_code":"PPL",
    "gn:name":"Idebe Ikot Essien",
    "gn:population":0,
    "gn:timezone":"Africa/Lagos",
    "iso:country":"NG",
    "wof:name":"Idebe Ikot Essien",
    "wof:placetype":"locality"
},
  "geometry": {"coordinates":[8.4529,4.85877],"type":"Point"}
}