{
  "type": "Feature",
  "properties": {
    "gn:admin1_code":"27.0",
    "gn:admin2_code":"118.0",
    "gn:admin3_code":"11801",
    "gn:asciiname":"Kubo",
    "gn:country_code":"NG",
    "gn:dem":362,
    "gn:feature_class":"P",
    "gn:feature_code":"PPL",
    "gn:name":"Kubo",
    "gn:population":0,
    "gn:timezone":"Africa/Lagos",
    "iso:country":"NG",
    "name:ceb_x_preferred":[
        "Kubo"
    ],
    "name:deu_x_preferred":[
        "Kubo"
    ],
    "name:epo_x_preferred":[
        "Kubo"
    ],
    "name:fra_x_preferred":[
        "Kubo"
    ],
    "name:ita_x_preferred":[
        "Kubo"
    ],
    "name:kor_x_preferred":[
        "\uad6c\ubcf4"
    ],
    "name:rus_x_preferred":[
        "\u041a\u0443\u0431\u043e"
    ],
    "name:slk_x_preferred":[
        "Kubo"
    ],
    "name:tgl_x_preferred":[
        "Kubo"
    ],
    "wof:name":"Kubo",
    "wof:placetype":"locality"
},
  "geometry": {"coordinates":[12.01065,10.37172],"type":"Point"}
}