{
  "type": "Feature",
  "properties": {
    "gn:admin1_code":"46.0",
    "gn:admin2_code":"5005.0",
    "gn:admin3_code":"BA0508",
    "gn:asciiname":"Dallol Aisha",
    "gn:country_code":"NG",
    "gn:dem":384,
    "gn:feature_class":"P",
    "gn:feature_code":"PPL",
    "gn:name":"Dallol Aisha",
    "gn:population":0,
    "gn:timezone":"Africa/Lagos",
    "iso:country":"NG",
    "name:eng_x_preferred":[
        "Dallol Aisha"
    ],
    "wof:name":"Dallol Aisha",
    "wof:placetype":"locality"
},
  "geometry": {"coordinates":[10.53392,10.84006],"type":"Point"}
}