{
  "type": "Feature",
  "properties": {
    "gn:admin1_code":"35.0",
    "gn:admin2_code":"2005.0",
    "gn:asciiname":"Dinga",
    "gn:country_code":"NG",
    "gn:dem":480,
    "gn:feature_class":"P",
    "gn:feature_code":"PPL",
    "gn:name":"Dinga",
    "gn:population":0,
    "gn:timezone":"Africa/Lagos",
    "iso:country":"NG",
    "name:ceb_x_preferred":[
        "Dinga"
    ],
    "name:fas_x_preferred":[
        "\u062f\u06cc\u0646\u06af\u0627"
    ],
    "name:fra_x_preferred":[
        "Dinga"
    ],
    "name:por_x_preferred":[
        "Dinga"
    ],
    "name:spa_x_preferred":[
        "Dinga"
    ],
    "name:urd_x_preferred":[
        "\u0688\u06cc\u0646\u06af\u0627"
    ],
    "wof:name":"Dinga",
    "wof:placetype":"locality"
},
  "geometry": {"coordinates":[12.63705,10.22943],"type":"Point"}
}