{
  "type": "Feature",
  "properties": {
    "gn:admin1_code":"52.0",
    "gn:asciiname":"Ambakagbene",
    "gn:country_code":"NG",
    "gn:dem":4,
    "gn:feature_class":"P",
    "gn:feature_code":"PPL",
    "gn:name":"Ambakagbene",
    "gn:population":0,
    "gn:timezone":"Africa/Lagos",
    "iso:country":"NG",
    "name:eng_x_preferred":[
        "Ambakagbene"
    ],
    "wof:name":"Ambakagbene",
    "wof:placetype":"locality"
},
  "geometry": {"coordinates":[5.82571,4.82916],"type":"Point"}
}