{
  "type": "Feature",
  "properties": {
    "gn:admin1_code":"26.0",
    "gn:admin2_code":"7006",
    "gn:asciiname":"Tseinumbur",
    "gn:country_code":"NG",
    "gn:dem":109,
    "gn:feature_class":"P",
    "gn:feature_code":"PPL",
    "gn:name":"Tseinumbur",
    "gn:population":0,
    "gn:timezone":"Africa/Lagos",
    "iso:country":"NG",
    "wof:name":"Tseinumbur",
    "wof:placetype":"locality"
},
  "geometry": {"coordinates":[9.03894,7.64734],"type":"Point"}
}