{
  "type": "Feature",
  "properties": {
    "gn:admin1_code":"52.0",
    "gn:admin2_code":"6007.0",
    "gn:asciiname":"Kolagbene",
    "gn:country_code":"NG",
    "gn:dem":12,
    "gn:feature_class":"P",
    "gn:feature_code":"PPL",
    "gn:name":"Kolagbene",
    "gn:population":0,
    "gn:timezone":"Africa/Lagos",
    "iso:country":"NG",
    "name:eng_x_preferred":[
        "Kolagbene"
    ],
    "name:eng_x_variant":[
        "Kalagbene"
    ],
    "wof:name":"Kolagbene",
    "wof:placetype":"locality"
},
  "geometry": {"coordinates":[5.78402,4.55948],"type":"Point"}
}