{
  "type": "Feature",
  "properties": {
    "gn:admin1_code":"26.0",
    "gn:admin2_code":"7012",
    "gn:asciiname":"Cheorbiam",
    "gn:country_code":"NG",
    "gn:dem":148,
    "gn:feature_class":"P",
    "gn:feature_code":"PPL",
    "gn:name":"Cheorbiam",
    "gn:population":0,
    "gn:timezone":"Africa/Lagos",
    "iso:country":"NG",
    "wof:name":"Cheorbiam",
    "wof:placetype":"locality"
},
  "geometry": {"coordinates":[9.41799,7.58425],"type":"Point"}
}