{
  "type": "Feature",
  "properties": {
    "gn:admin1_code":"36.0",
    "gn:admin2_code":"10025.0",
    "gn:asciiname":"Ilokiri",
    "gn:country_code":"NG",
    "gn:dem":6,
    "gn:feature_class":"P",
    "gn:feature_code":"PPL",
    "gn:name":"Ilokiri",
    "gn:population":0,
    "gn:timezone":"Africa/Lagos",
    "iso:country":"NG",
    "name:eng_x_preferred":[
        "Ilokiri"
    ],
    "wof:name":"Ilokiri",
    "wof:placetype":"locality"
},
  "geometry": {"coordinates":[5.57524,5.52351],"type":"Point"}
}