{
  "type": "Feature",
  "properties": {
    "gn:admin1_code":"50.0",
    "gn:admin2_code":"33011.0",
    "gn:asciiname":"Rumuebele",
    "gn:country_code":"NG",
    "gn:dem":28,
    "gn:feature_class":"P",
    "gn:feature_code":"PPL",
    "gn:name":"Rumuebele",
    "gn:population":0,
    "gn:timezone":"Africa/Lagos",
    "iso:country":"NG",
    "wof:name":"Rumuebele",
    "wof:placetype":"locality"
},
  "geometry": {"coordinates":[7.13129,4.91287],"type":"Point"}
}