{
  "type": "Feature",
  "properties": {
    "gn:admin1_code":"22.0",
    "gn:admin2_code":"9016.0",
    "gn:asciiname":"Njua-Bano",
    "gn:country_code":"NG",
    "gn:dem":132,
    "gn:feature_class":"P",
    "gn:feature_code":"PPL",
    "gn:name":"Njua-Bano",
    "gn:population":0,
    "gn:timezone":"Africa/Lagos",
    "iso:country":"NG",
    "name:und_x_variant":[
        "Niua-Bano",
        "Njuabano"
    ],
    "wof:name":"Njua-Bano",
    "wof:placetype":"locality"
},
  "geometry": {"coordinates":[8.83244,6.57805],"type":"Point"}
}