{
  "type": "Feature",
  "properties": {
    "gn:admin1_code":"26.0",
    "gn:admin2_code":"7005.0",
    "gn:asciiname":"Tondu",
    "gn:country_code":"NG",
    "gn:dem":222,
    "gn:feature_class":"P",
    "gn:feature_code":"PPL",
    "gn:name":"Tondu",
    "gn:population":0,
    "gn:timezone":"Africa/Lagos",
    "iso:country":"NG",
    "name:bul_x_preferred":[
        "\u0422\u043e\u043d\u0434\u0438"
    ],
    "name:cym_x_preferred":[
        "Tondu"
    ],
    "name:eus_x_preferred":[
        "Tondu"
    ],
    "wof:name":"Tondu",
    "wof:placetype":"locality"
},
  "geometry": {"coordinates":[8.93705,7.36659],"type":"Point"}
}