{
  "type": "Feature",
  "properties": {
    "gn:admin1_code":"41.0",
    "gn:asciiname":"Zagana",
    "gn:country_code":"NG",
    "gn:dem":70,
    "gn:feature_class":"P",
    "gn:feature_code":"PPL",
    "gn:name":"Zagana",
    "gn:population":0,
    "gn:timezone":"Africa/Lagos",
    "iso:country":"NG",
    "wof:name":"Zagana",
    "wof:placetype":"locality"
},
  "geometry": {"coordinates":[6.96318,7.93041],"type":"Point"}
}