{
  "type": "Feature",
  "properties": {
    "gn:admin1_code":"27.0",
    "gn:admin2_code":"112.0",
    "gn:admin3_code":"11203",
    "gn:asciiname":"Tama",
    "gn:country_code":"NG",
    "gn:dem":584,
    "gn:feature_class":"P",
    "gn:feature_code":"PPL",
    "gn:name":"Tama",
    "gn:population":0,
    "gn:timezone":"Africa/Lagos",
    "iso:country":"NG",
    "wof:name":"Tama",
    "wof:placetype":"locality"
},
  "geometry": {"coordinates":[12.06185,10.3141],"type":"Point"}
}