{
  "type": "Feature",
  "properties": {
    "gn:admin1_code":"31.0",
    "gn:admin2_code":"27011.0",
    "gn:asciiname":"Raha Atabo",
    "gn:country_code":"NG",
    "gn:dem":333,
    "gn:feature_class":"P",
    "gn:feature_code":"PPL",
    "gn:name":"Raha Atabo",
    "gn:population":0,
    "gn:timezone":"Africa/Lagos",
    "iso:country":"NG",
    "wof:name":"Raha Atabo",
    "wof:placetype":"locality"
},
  "geometry": {"coordinates":[5.44857,10.63154],"type":"Point"}
}