{
  "type": "Feature",
  "properties": {
    "gn:admin1_code":"31.0",
    "gn:admin2_code":"27022.0",
    "gn:asciiname":"Shiroro",
    "gn:country_code":"NG",
    "gn:dem":279,
    "gn:feature_class":"P",
    "gn:feature_code":"PPL",
    "gn:name":"Shiroro",
    "gn:population":0,
    "gn:timezone":"Africa/Lagos",
    "iso:country":"NG",
    "name:fra_x_preferred":[
        "Shiroro"
    ],
    "name:hau_x_preferred":[
        "Shiroro"
    ],
    "name:ita_x_preferred":[
        "Shiroro"
    ],
    "name:spa_x_preferred":[
        "Shiroro"
    ],
    "wof:name":"Shiroro",
    "wof:placetype":"locality"
},
  "geometry": {"coordinates":[6.81865,9.99258],"type":"Point"}
}