{
  "type": "Feature",
  "properties": {
    "gn:admin1_code":"29.0",
    "gn:admin2_code":"20026.0",
    "gn:admin3_code":"KN2004",
    "gn:asciiname":"Danja",
    "gn:country_code":"NG",
    "gn:dem":531,
    "gn:feature_class":"P",
    "gn:feature_code":"PPL",
    "gn:name":"Danja",
    "gn:population":0,
    "gn:timezone":"Africa/Lagos",
    "iso:country":"NG",
    "name:ceb_x_preferred":[
        "Danja"
    ],
    "name:fra_x_preferred":[
        "Danja"
    ],
    "name:hun_x_preferred":[
        "Danja"
    ],
    "name:ita_x_preferred":[
        "Danja"
    ],
    "wof:name":"Danja",
    "wof:placetype":"locality"
},
  "geometry": {"coordinates":[8.12872,11.99153],"type":"Point"}
}