{
  "type": "Feature",
  "properties": {
    "gn:admin1_code":"26.0",
    "gn:admin2_code":"7005",
    "gn:asciiname":"Bel",
    "gn:country_code":"NG",
    "gn:dem":143,
    "gn:feature_class":"P",
    "gn:feature_code":"PPL",
    "gn:name":"Bel",
    "gn:population":0,
    "gn:timezone":"Africa/Lagos",
    "iso:country":"NG",
    "name:ara_x_preferred":[
        "\u0628\u0644"
    ],
    "name:bul_x_preferred":[
        "\u0411\u0435\u043b"
    ],
    "name:cat_x_preferred":[
        "Bel"
    ],
    "name:ceb_x_preferred":[
        "Bel"
    ],
    "name:dan_x_preferred":[
        "Bel"
    ],
    "name:fin_x_preferred":[
        "Bel"
    ],
    "name:fra_x_preferred":[
        "Bel"
    ],
    "name:hrv_x_preferred":[
        "Bel"
    ],
    "name:hye_x_preferred":[
        "\u0532\u0565\u056c"
    ],
    "name:nld_x_preferred":[
        "Bel"
    ],
    "name:pol_x_preferred":[
        "Bel"
    ],
    "name:por_x_preferred":[
        "Bel"
    ],
    "name:rus_x_preferred":[
        "\u0411\u0435\u043b"
    ],
    "name:slk_x_preferred":[
        "Bel"
    ],
    "name:spa_x_preferred":[
        "Bel"
    ],
    "name:srp_x_preferred":[
        "\u0411\u0435\u043b"
    ],
    "name:swe_x_preferred":[
        "Bel"
    ],
    "name:ukr_x_preferred":[
        "\u0411\u0435\u043b"
    ],
    "name:uzb_x_preferred":[
        "Bel"
    ],
    "wof:name":"Bel",
    "wof:placetype":"locality"
},
  "geometry": {"coordinates":[8.85187,7.36018],"type":"Point"}
}