{
  "type": "Feature",
  "properties": {
    "gn:admin1_code":"57.0",
    "gn:asciiname":"Zugu",
    "gn:country_code":"NG",
    "gn:dem":230,
    "gn:feature_class":"P",
    "gn:feature_code":"PPL",
    "gn:name":"Zugu",
    "gn:population":0,
    "gn:timezone":"Africa/Lagos",
    "iso:country":"NG",
    "wof:name":"Zugu",
    "wof:placetype":"locality"
},
  "geometry": {"coordinates":[4.84923,12.09304],"type":"Point"}
}