{
  "type": "Feature",
  "properties": {
    "gn:admin1_code":"36.0",
    "gn:admin2_code":"10001.0",
    "gn:asciiname":"Anioma",
    "gn:country_code":"NG",
    "gn:dem":77,
    "gn:feature_class":"P",
    "gn:feature_code":"PPL",
    "gn:name":"Anioma",
    "gn:population":0,
    "gn:timezone":"Africa/Lagos",
    "iso:country":"NG",
    "name:eng_x_preferred":[
        "Anioma"
    ],
    "name:eng_x_variant":[
        "Inoma"
    ],
    "name:und_x_variant":[
        "Inoma"
    ],
    "wof:name":"Anioma",
    "wof:placetype":"locality"
},
  "geometry": {"coordinates":[6.53556,6.48215],"type":"Point"}
}