{
  "type": "Feature",
  "properties": {
    "gn:admin1_code":"49.0",
    "gn:admin2_code":"32015.0",
    "gn:asciiname":"Barakin Kwi",
    "gn:country_code":"NG",
    "gn:dem":1283,
    "gn:feature_class":"P",
    "gn:feature_code":"PPL",
    "gn:name":"Barakin Kwi",
    "gn:population":0,
    "gn:timezone":"Africa/Lagos",
    "iso:country":"NG",
    "wof:name":"Barakin Kwi",
    "wof:placetype":"locality"
},
  "geometry": {"coordinates":[8.85403,9.61141],"type":"Point"}
}