{
  "type": "Feature",
  "properties": {
    "gn:admin1_code":"35.0",
    "gn:admin2_code":"2002.0",
    "gn:asciiname":"Wuro Goni",
    "gn:country_code":"NG",
    "gn:dem":232,
    "gn:feature_class":"P",
    "gn:feature_code":"PPL",
    "gn:name":"Wuro Goni",
    "gn:population":0,
    "gn:timezone":"Africa/Lagos",
    "iso:country":"NG",
    "name:eng_x_preferred":[
        "Wuro Goni"
    ],
    "wof:name":"Wuro Goni",
    "wof:placetype":"locality"
},
  "geometry": {"coordinates":[12.20317,9.04249],"type":"Point"}
}