{
  "type": "Feature",
  "properties": {
    "gn:country":"NG",
    "gn:fcode":"PPL",
    "gn:pop":6537,
    "iso:country":"NG",
    "name:unk_x_variant":[
        "Akeze"
    ],
    "qs:name":"Ake-Eze",
    "qs:photos_9r":0,
    "qs:photos_sr":0,
    "qs:pop_sr":"5",
    "wof:name":"Ake-Eze",
    "wof:placetype":"locality",
    "wof:population":6537
},
  "geometry": {"coordinates":[7.67615,5.91677],"type":"Point"}
}