{
  "type": "Feature",
  "properties": {
    "gn:admin1_code":"46.0",
    "gn:admin2_code":"5015.0",
    "gn:admin3_code":"BA1503",
    "gn:asciiname":"Masiya",
    "gn:country_code":"NG",
    "gn:dem":461,
    "gn:feature_class":"P",
    "gn:feature_code":"PPL",
    "gn:name":"Masiya",
    "gn:population":0,
    "gn:timezone":"Africa/Lagos",
    "iso:country":"NG",
    "wof:name":"Masiya",
    "wof:placetype":"locality"
},
  "geometry": {"coordinates":[9.57331,11.23715],"type":"Point"}
}