{
  "type": "Feature",
  "properties": {
    "gn:admin1_code":"31.0",
    "gn:admin2_code":"27011.0",
    "gn:asciiname":"Rafingora",
    "gn:country_code":"NG",
    "gn:dem":306,
    "gn:feature_class":"P",
    "gn:feature_code":"PPL",
    "gn:name":"Rafingora",
    "gn:population":0,
    "gn:timezone":"Africa/Lagos",
    "iso:country":"NG",
    "wof:name":"Rafingora",
    "wof:placetype":"locality"
},
  "geometry": {"coordinates":[5.39738,10.27956],"type":"Point"}
}