{
  "type": "Feature",
  "properties": {
    "gn:admin1_code":"29.0",
    "gn:admin2_code":"20014.0",
    "gn:admin3_code":"KN3205",
    "gn:asciiname":"Rurum",
    "gn:country_code":"NG",
    "gn:dem":546,
    "gn:feature_class":"P",
    "gn:feature_code":"PPL",
    "gn:name":"Rurum",
    "gn:population":0,
    "gn:timezone":"Africa/Lagos",
    "iso:country":"NG",
    "wof:name":"Rurum",
    "wof:placetype":"locality"
},
  "geometry": {"coordinates":[8.48496,11.41375],"type":"Point"}
}