{
  "type": "Feature",
  "properties": {
    "gn:admin1_code":"24.0",
    "gn:admin2_code":"404.0",
    "gn:admin3_code":"40406",
    "gn:asciiname":"Hui",
    "gn:country_code":"NG",
    "gn:dem":399,
    "gn:feature_class":"P",
    "gn:feature_code":"PPL",
    "gn:name":"Hui",
    "gn:population":0,
    "gn:timezone":"Africa/Lagos",
    "iso:country":"NG",
    "name:und_x_variant":[
        "Chinchia",
        "Hui"
    ],
    "wof:name":"Hui",
    "wof:placetype":"locality"
},
  "geometry": {"coordinates":[8.78253,12.6929],"type":"Point"}
}