{
  "type": "Feature",
  "properties": {
    "gn:admin1_code":"25.0",
    "gn:admin2_code":"4003.0",
    "gn:asciiname":"Onono",
    "gn:country_code":"NG",
    "gn:dem":27,
    "gn:feature_class":"P",
    "gn:feature_code":"PPL",
    "gn:name":"Onono",
    "gn:population":0,
    "gn:timezone":"Africa/Lagos",
    "iso:country":"NG",
    "name:eng_x_preferred":[
        "Onono"
    ],
    "wof:name":"Onono",
    "wof:placetype":"locality"
},
  "geometry": {"coordinates":[6.76297,6.20119],"type":"Point"}
}