{
  "type": "Feature",
  "properties": {
    "gn:admin1_code":"43.0",
    "gn:admin2_code":"35016.0",
    "gn:asciiname":"Jasori",
    "gn:country_code":"NG",
    "gn:dem":508,
    "gn:feature_class":"P",
    "gn:feature_code":"PPL",
    "gn:name":"Jasori",
    "gn:population":0,
    "gn:timezone":"Africa/Lagos",
    "iso:country":"NG",
    "wof:name":"Jasori",
    "wof:placetype":"locality"
},
  "geometry": {"coordinates":[11.73136,8.91843],"type":"Point"}
}