{
  "type": "Feature",
  "properties": {
    "gn:admin1_code":"32.0",
    "gn:admin2_code":"31001.0",
    "gn:asciiname":"Lakanle",
    "gn:country_code":"NG",
    "gn:dem":236,
    "gn:feature_class":"P",
    "gn:feature_code":"PPL",
    "gn:name":"Lakanle",
    "gn:population":0,
    "gn:timezone":"Africa/Lagos",
    "iso:country":"NG",
    "wof:name":"Lakanle",
    "wof:placetype":"locality"
},
  "geometry": {"coordinates":[3.80167,7.70778],"type":"Point"}
}