{
  "type": "Feature",
  "properties": {
    "gn:admin1_code":"40.0",
    "gn:admin2_code":"507.0",
    "gn:admin3_code":"50703",
    "gn:asciiname":"Bachaka",
    "gn:country_code":"NG",
    "gn:dem":235,
    "gn:feature_class":"P",
    "gn:feature_code":"PPL",
    "gn:name":"Bachaka",
    "gn:population":0,
    "gn:timezone":"Africa/Lagos",
    "iso:country":"NG",
    "wof:name":"Bachaka",
    "wof:placetype":"locality"
},
  "geometry": {"coordinates":[3.86878,12.12321],"type":"Point"}
}