{
  "type": "Feature",
  "properties": {
    "gn:admin1_code":"23.0",
    "gn:admin2_code":"19003.0",
    "gn:admin3_code":"KD0304",
    "gn:asciiname":"Yakawada",
    "gn:country_code":"NG",
    "gn:dem":663,
    "gn:feature_class":"P",
    "gn:feature_code":"PPL",
    "gn:name":"Yakawada",
    "gn:population":0,
    "gn:timezone":"Africa/Lagos",
    "iso:country":"NG",
    "wof:name":"Yakawada",
    "wof:placetype":"locality"
},
  "geometry": {"coordinates":[7.41776,11.27854],"type":"Point"}
}