{
  "type": "Feature",
  "properties": {
    "gn:admin1_code":"40.0",
    "gn:asciiname":"Milemi",
    "gn:country_code":"NG",
    "gn:dem":199,
    "gn:feature_class":"P",
    "gn:feature_code":"PPL",
    "gn:name":"Milemi",
    "gn:population":0,
    "gn:timezone":"Africa/Lagos",
    "iso:country":"NG",
    "wof:name":"Milemi",
    "wof:placetype":"locality"
},
  "geometry": {"coordinates":[4.59901,10.87024],"type":"Point"}
}