{
  "type": "Feature",
  "properties": {
    "gn:admin1_code":"53.0",
    "gn:admin2_code":"11001.0",
    "gn:asciiname":"Ugbuloke",
    "gn:country_code":"NG",
    "gn:dem":71,
    "gn:feature_class":"P",
    "gn:feature_code":"PPL",
    "gn:name":"Ugbuloke",
    "gn:population":0,
    "gn:timezone":"Africa/Lagos",
    "iso:country":"NG",
    "wof:name":"Ugbuloke",
    "wof:placetype":"locality"
},
  "geometry": {"coordinates":[8.08878,6.27745],"type":"Point"}
}