{
  "type": "Feature",
  "properties": {
    "gn:admin1_code":"23.0",
    "gn:admin2_code":"19002.0",
    "gn:admin3_code":"KD0203",
    "gn:asciiname":"Juji",
    "gn:country_code":"NG",
    "gn:dem":614,
    "gn:feature_class":"P",
    "gn:feature_code":"PPL",
    "gn:name":"Juji",
    "gn:population":0,
    "gn:timezone":"Africa/Lagos",
    "iso:country":"NG",
    "wof:name":"Juji",
    "wof:placetype":"locality"
},
  "geometry": {"coordinates":[7.45886,10.4104],"type":"Point"}
}