{
  "type": "Feature",
  "properties": {
    "gn:admin1_code":"53.0",
    "gn:admin2_code":"11004.0",
    "gn:asciiname":"Ogbaga",
    "gn:country_code":"NG",
    "gn:dem":63,
    "gn:feature_class":"P",
    "gn:feature_code":"PPL",
    "gn:name":"Ogbaga",
    "gn:population":0,
    "gn:timezone":"Africa/Lagos",
    "iso:country":"NG",
    "name:und_x_variant":[
        "Ogbaje",
        "Ogbaga"
    ],
    "wof:name":"Ogbaga",
    "wof:placetype":"locality"
},
  "geometry": {"coordinates":[8.11759,6.37708],"type":"Point"}
}