{
  "type": "Feature",
  "properties": {
    "gn:admin1_code":"56.0",
    "gn:admin2_code":"26002.0",
    "gn:asciiname":"Muntscheri",
    "gn:country_code":"NG",
    "gn:dem":99,
    "gn:feature_class":"P",
    "gn:feature_code":"PPL",
    "gn:name":"Muntscheri",
    "gn:population":0,
    "gn:timezone":"Africa/Lagos",
    "iso:country":"NG",
    "wof:name":"Muntscheri",
    "wof:placetype":"locality"
},
  "geometry": {"coordinates":[9.29039,7.99063],"type":"Point"}
}