{
  "type": "Feature",
  "properties": {
    "gn:admin1_code":"40.0",
    "gn:admin2_code":"512.0",
    "gn:admin3_code":"51209",
    "gn:asciiname":"Wuragauri",
    "gn:country_code":"NG",
    "gn:dem":211,
    "gn:feature_class":"P",
    "gn:feature_code":"PPL",
    "gn:name":"Wuragauri",
    "gn:population":0,
    "gn:timezone":"Africa/Lagos",
    "iso:country":"NG",
    "name:und_x_variant":[
        "Wurogauri",
        "Wuragauri"
    ],
    "wof:name":"Wuragauri",
    "wof:placetype":"locality"
},
  "geometry": {"coordinates":[4.0141,12.33418],"type":"Point"}
}