{
  "type": "Feature",
  "properties": {
    "gn:admin1_code":"23.0",
    "gn:admin2_code":"19004.0",
    "gn:admin3_code":"KD0412",
    "gn:asciiname":"Zangon Aya",
    "gn:country_code":"NG",
    "gn:dem":681,
    "gn:feature_class":"P",
    "gn:feature_code":"PPL",
    "gn:name":"Zangon Aya",
    "gn:population":0,
    "gn:timezone":"Africa/Lagos",
    "iso:country":"NG",
    "name:und_x_variant":[
        "Zangan Aya",
        "Zangwan Aya",
        "Zangon Aya"
    ],
    "wof:name":"Zangon Aya",
    "wof:placetype":"locality"
},
  "geometry": {"coordinates":[7.66376,10.9154],"type":"Point"}
}