{
  "type": "Feature",
  "properties": {
    "gn:admin1_code":"45.0",
    "gn:admin2_code":"1010.0",
    "gn:asciiname":"Ndi-Uduma Ukwu",
    "gn:country_code":"NG",
    "gn:dem":97,
    "gn:feature_class":"P",
    "gn:feature_code":"PPL",
    "gn:name":"Ndi-Uduma Ukwu",
    "gn:population":0,
    "gn:timezone":"Africa/Lagos",
    "iso:country":"NG",
    "wof:name":"Ndi-Uduma Ukwu",
    "wof:placetype":"locality"
},
  "geometry": {"coordinates":[7.79306,5.64397],"type":"Point"}
}