{
  "type": "Feature",
  "properties": {
    "gn:admin1_code":"26.0",
    "gn:admin2_code":"7005",
    "gn:asciiname":"Anahun",
    "gn:country_code":"NG",
    "gn:dem":209,
    "gn:feature_class":"P",
    "gn:feature_code":"PPL",
    "gn:name":"Anahun",
    "gn:population":0,
    "gn:timezone":"Africa/Lagos",
    "iso:country":"NG",
    "wof:name":"Anahun",
    "wof:placetype":"locality"
},
  "geometry": {"coordinates":[9.01627,7.36634],"type":"Point"}
}