{
  "type": "Feature",
  "properties": {
    "gn:admin1_code":"22.0",
    "gn:admin2_code":"9015.0",
    "gn:asciiname":"Idungnyama",
    "gn:country_code":"NG",
    "gn:dem":76,
    "gn:feature_class":"P",
    "gn:feature_code":"PPL",
    "gn:name":"Idungnyama",
    "gn:population":0,
    "gn:timezone":"Africa/Lagos",
    "iso:country":"NG",
    "wof:name":"Idungnyama",
    "wof:placetype":"locality"
},
  "geometry": {"coordinates":[7.97494,5.34682],"type":"Point"}
}