{
  "type": "Feature",
  "properties": {
    "gn:admin1_code":"42.0",
    "gn:admin2_code":"30021.0",
    "gn:asciiname":"Neye",
    "gn:country_code":"NG",
    "gn:dem":209,
    "gn:feature_class":"P",
    "gn:feature_code":"PPL",
    "gn:name":"Neye",
    "gn:population":0,
    "gn:timezone":"Africa/Lagos",
    "iso:country":"NG",
    "name:deu_x_preferred":[
        "Neye"
    ],
    "wof:name":"Neye",
    "wof:placetype":"locality"
},
  "geometry": {"coordinates":[4.21667,7.45],"type":"Point"}
}