{
  "type": "Feature",
  "properties": {
    "iso:country":"NG",
    "name:eng_x_preferred":[
        "Dindima"
    ],
    "name:und_x_variant":[
        "Dindawa"
    ],
    "qs:gn_country":"NG",
    "qs:gn_fcode":"PPL",
    "qs:gn_pop":13356,
    "qs:name":"Dindima",
    "qs:name_adm0":"Nigeria",
    "qs:name_adm1":"Bauchi",
    "qs:photos":0,
    "qs:photos_1k":0,
    "qs:photos_9k":1,
    "qs:photos_9r":1,
    "qs:photos_all":1,
    "qs:photos_sr":0,
    "qs:placetype":"Town",
    "qs:pop_sr":"6",
    "qs:woe_adm0":23424908,
    "wof:name":"Dindima",
    "wof:placetype":"locality",
    "wof:population":13356
},
  "geometry": {"coordinates":[10.15132,10.22629],"type":"Point"}
}