{
  "type": "Feature",
  "properties": {
    "gn:admin1_code":"39.0",
    "gn:admin2_code":"18012.0",
    "gn:admin3_code":"JI0608",
    "gn:asciiname":"Ruru",
    "gn:country_code":"NG",
    "gn:dem":454,
    "gn:feature_class":"P",
    "gn:feature_code":"PPL",
    "gn:name":"Ruru",
    "gn:population":0,
    "gn:timezone":"Africa/Lagos",
    "iso:country":"NG",
    "name:ceb_x_preferred":[
        "Ruru"
    ],
    "name:new_x_preferred":[
        "\u0930\u0941\u0930\u0941"
    ],
    "name:swe_x_preferred":[
        "Ruru"
    ],
    "wof:name":"Ruru",
    "wof:placetype":"locality"
},
  "geometry": {"coordinates":[9.2857,11.62852],"type":"Point"}
}