{
  "type": "Feature",
  "properties": {
    "gn:admin1_code":"43.0",
    "gn:asciiname":"Kulu",
    "gn:country_code":"NG",
    "gn:dem":170,
    "gn:feature_class":"P",
    "gn:feature_code":"PPL",
    "gn:name":"Kulu",
    "gn:population":0,
    "gn:timezone":"Africa/Lagos",
    "iso:country":"NG",
    "name:ceb_x_preferred":[
        "Kulu"
    ],
    "name:deu_x_preferred":[
        "Kulu"
    ],
    "name:eng_x_preferred":[
        "Kulu"
    ],
    "name:fra_x_preferred":[
        "Kulu"
    ],
    "name:ita_x_preferred":[
        "Kulu"
    ],
    "name:min_x_preferred":[
        "Kulu"
    ],
    "name:nld_x_preferred":[
        "Kullu"
    ],
    "name:swe_x_preferred":[
        "Kulu"
    ],
    "wof:name":"Kulu",
    "wof:placetype":"locality"
},
  "geometry": {"coordinates":[11.6166,9.30688],"type":"Point"}
}