{
  "type": "Feature",
  "properties": {
    "gn:admin1_code":"25.0",
    "gn:admin2_code":"4006.0",
    "gn:asciiname":"Umuawulu",
    "gn:country_code":"NG",
    "gn:dem":150,
    "gn:feature_class":"P",
    "gn:feature_code":"PPL",
    "gn:name":"Umuawulu",
    "gn:population":0,
    "gn:timezone":"Africa/Lagos",
    "iso:country":"NG",
    "wof:name":"Umuawulu",
    "wof:placetype":"locality"
},
  "geometry": {"coordinates":[7.1009,6.1481],"type":"Point"}
}