{
  "type": "Feature",
  "properties": {
    "gn:admin1_code":"16.0",
    "gn:admin2_code":"28006.0",
    "gn:asciiname":"Koboro",
    "gn:country_code":"NG",
    "gn:dem":61,
    "gn:feature_class":"P",
    "gn:feature_code":"PPL",
    "gn:name":"Koboro",
    "gn:population":0,
    "gn:timezone":"Africa/Lagos",
    "iso:country":"NG",
    "wof:name":"Koboro",
    "wof:placetype":"locality"
},
  "geometry": {"coordinates":[3.18651,6.9681],"type":"Point"}
}