{
  "type": "Feature",
  "properties": {
    "gn:admin1_code":"53.0",
    "gn:admin2_code":"11006",
    "gn:asciiname":"Alibaluhu",
    "gn:country_code":"NG",
    "gn:dem":37,
    "gn:feature_class":"P",
    "gn:feature_code":"PPL",
    "gn:name":"Alibaluhu",
    "gn:population":0,
    "gn:timezone":"Africa/Lagos",
    "iso:country":"NG",
    "wof:name":"Alibaluhu",
    "wof:placetype":"locality"
},
  "geometry": {"coordinates":[8.14942,6.17818],"type":"Point"}
}