{
  "type": "Feature",
  "properties": {
    "gn:admin1_code":"43.0",
    "gn:asciiname":"Kogi Gwuiwan",
    "gn:country_code":"NG",
    "gn:dem":228,
    "gn:feature_class":"P",
    "gn:feature_code":"PPL",
    "gn:name":"Kogi Gwuiwan",
    "gn:population":0,
    "gn:timezone":"Africa/Lagos",
    "iso:country":"NG",
    "name:eng_x_preferred":[
        "Kogi Gwuiwan"
    ],
    "wof:name":"Kogi Gwuiwan",
    "wof:placetype":"locality"
},
  "geometry": {"coordinates":[10.93578,9.36152],"type":"Point"}
}