{
  "type": "Feature",
  "properties": {
    "gn:admin1_code":"52.0",
    "gn:admin2_code":"6001.0",
    "gn:asciiname":"Awotarighakiri",
    "gn:country_code":"NG",
    "gn:dem":18,
    "gn:feature_class":"P",
    "gn:feature_code":"PPL",
    "gn:name":"Awotarighakiri",
    "gn:population":0,
    "gn:timezone":"Africa/Lagos",
    "iso:country":"NG",
    "wof:name":"Awotarighakiri",
    "wof:placetype":"locality"
},
  "geometry": {"coordinates":[6.54093,4.73891],"type":"Point"}
}