{
  "type": "Feature",
  "properties": {
    "gn:admin1_code":"43.0",
    "gn:admin2_code":"35014.0",
    "gn:asciiname":"Agame",
    "gn:country_code":"NG",
    "gn:dem":129,
    "gn:feature_class":"P",
    "gn:feature_code":"PPL",
    "gn:name":"Agame",
    "gn:population":0,
    "gn:timezone":"Africa/Lagos",
    "iso:country":"NG",
    "name:ara_x_preferred":[
        "\u0639\u0642\u0627\u0645\u0629"
    ],
    "name:fra_x_preferred":[
        "Agam\u00e9"
    ],
    "name:heb_x_preferred":[
        "\u05e2\u05d2\u05de\u05d4"
    ],
    "wof:name":"Agame",
    "wof:placetype":"locality"
},
  "geometry": {"coordinates":[10.01332,7.85764],"type":"Point"}
}