{
  "type": "Feature",
  "properties": {
    "gn:admin1_code":"56.0",
    "gn:admin2_code":"26004",
    "gn:asciiname":"Gidan Mammu",
    "gn:country_code":"NG",
    "gn:dem":432,
    "gn:feature_class":"P",
    "gn:feature_code":"PPL",
    "gn:name":"Gidan Mammu",
    "gn:population":0,
    "gn:timezone":"Africa/Lagos",
    "iso:country":"NG",
    "wof:name":"Gidan Mammu",
    "wof:placetype":"locality"
},
  "geometry": {"coordinates":[7.88027,9.15441],"type":"Point"}
}