{
  "type": "Feature",
  "properties": {
    "gn:admin1_code":"46.0",
    "gn:admin2_code":"5019.0",
    "gn:admin3_code":"BA1906",
    "gn:asciiname":"Warji",
    "gn:country_code":"NG",
    "gn:dem":451,
    "gn:feature_class":"P",
    "gn:feature_code":"PPLA2",
    "gn:name":"Warji",
    "gn:population":0,
    "gn:timezone":"Africa/Lagos",
    "iso:country":"NG",
    "name:ceb_x_preferred":[
        "Warji"
    ],
    "name:fra_x_preferred":[
        "Warji"
    ],
    "name:hau_x_preferred":[
        "Warji"
    ],
    "name:ita_x_preferred":[
        "Warji"
    ],
    "name:spa_x_preferred":[
        "Warji"
    ],
    "name:und_x_variant":[
        "Katangan Warji",
        "Katanga Warji"
    ],
    "wof:name":"Warji",
    "wof:placetype":"locality"
},
  "geometry": {"coordinates":[9.75241,11.17756],"type":"Point"}
}