{
  "type": "Feature",
  "properties": {
    "gn:admin1_code":"44.0",
    "gn:admin2_code":"703.0",
    "gn:admin3_code":"70305",
    "gn:asciiname":"Kalalawa",
    "gn:country_code":"NG",
    "gn:dem":383,
    "gn:feature_class":"P",
    "gn:feature_code":"PPL",
    "gn:name":"Kalalawa",
    "gn:population":0,
    "gn:timezone":"Africa/Lagos",
    "iso:country":"NG",
    "name:und_x_variant":[
        "Kailalawa",
        "Kalalawa"
    ],
    "wof:name":"Kalalawa",
    "wof:placetype":"locality"
},
  "geometry": {"coordinates":[11.85576,11.93883],"type":"Point"}
}