{
  "type": "Feature",
  "properties": {
    "gn:admin1_code":"41.0",
    "gn:admin2_code":"23005.0",
    "gn:asciiname":"Ajiolo",
    "gn:country_code":"NG",
    "gn:dem":304,
    "gn:feature_class":"P",
    "gn:feature_code":"PPL",
    "gn:name":"Ajiolo",
    "gn:population":0,
    "gn:timezone":"Africa/Lagos",
    "iso:country":"NG",
    "name:und_x_variant":[
        "Ajiyolo"
    ],
    "wof:name":"Ajiolo",
    "wof:placetype":"locality"
},
  "geometry": {"coordinates":[7.09671,7.57924],"type":"Point"}
}