{
  "type": "Feature",
  "properties": {
    "gn:admin1_code":"44.0",
    "gn:admin2_code":"706.0",
    "gn:admin3_code":"70608",
    "gn:asciiname":"Dobiri",
    "gn:country_code":"NG",
    "gn:dem":335,
    "gn:feature_class":"P",
    "gn:feature_code":"PPL",
    "gn:name":"Dobiri",
    "gn:population":0,
    "gn:timezone":"Africa/Lagos",
    "iso:country":"NG",
    "wof:name":"Dobiri",
    "wof:placetype":"locality"
},
  "geometry": {"coordinates":[11.8471,12.69508],"type":"Point"}
}