{
  "type": "Feature",
  "properties": {
    "gn:admin1_code":"39.0",
    "gn:admin2_code":"18010.0",
    "gn:admin3_code":"JI1701",
    "gn:asciiname":"Jinowol",
    "gn:country_code":"NG",
    "gn:dem":438,
    "gn:feature_class":"P",
    "gn:feature_code":"PPL",
    "gn:name":"Jinowol",
    "gn:population":0,
    "gn:timezone":"Africa/Lagos",
    "iso:country":"NG",
    "wof:name":"Jinowol",
    "wof:placetype":"locality"
},
  "geometry": {"coordinates":[8.49323,12.72668],"type":"Point"}
}