{
  "type": "Feature",
  "properties": {
    "gn:admin1_code":"27.0",
    "gn:admin2_code":"112.0",
    "gn:admin3_code":"11210",
    "gn:asciiname":"Garin Gwagsa",
    "gn:country_code":"NG",
    "gn:dem":423,
    "gn:feature_class":"P",
    "gn:feature_code":"PPL",
    "gn:name":"Garin Gwagsa",
    "gn:population":0,
    "gn:timezone":"Africa/Lagos",
    "iso:country":"NG",
    "wof:name":"Garin Gwagsa",
    "wof:placetype":"locality"
},
  "geometry": {"coordinates":[12.4009,10.4226],"type":"Point"}
}