{
  "type": "Feature",
  "properties": {
    "gn:admin1_code":"53.0",
    "gn:admin2_code":"11007",
    "gn:asciiname":"Ama-Okpo",
    "gn:country_code":"NG",
    "gn:dem":56,
    "gn:feature_class":"P",
    "gn:feature_code":"PPL",
    "gn:name":"Ama-Okpo",
    "gn:population":0,
    "gn:timezone":"Africa/Lagos",
    "iso:country":"NG",
    "wof:name":"Ama-Okpo",
    "wof:placetype":"locality"
},
  "geometry": {"coordinates":[8.15787,6.0974],"type":"Point"}
}