{
  "type": "Feature",
  "properties": {
    "gn:admin1_code":"43.0",
    "gn:admin2_code":"35004.0",
    "gn:asciiname":"Miji Dadi",
    "gn:country_code":"NG",
    "gn:dem":439,
    "gn:feature_class":"P",
    "gn:feature_code":"PPL",
    "gn:name":"Miji Dadi",
    "gn:population":0,
    "gn:timezone":"Africa/Lagos",
    "iso:country":"NG",
    "wof:name":"Miji Dadi",
    "wof:placetype":"locality"
},
  "geometry": {"coordinates":[11.63333,7.58333],"type":"Point"}
}