{
  "type": "Feature",
  "properties": {
    "gn:admin1_code":"31.0",
    "gn:admin2_code":"27007",
    "gn:asciiname":"Emidzan",
    "gn:country_code":"NG",
    "gn:dem":277,
    "gn:feature_class":"P",
    "gn:feature_code":"PPL",
    "gn:name":"Emidzan",
    "gn:population":0,
    "gn:timezone":"Africa/Lagos",
    "iso:country":"NG",
    "wof:name":"Emidzan",
    "wof:placetype":"locality"
},
  "geometry": {"coordinates":[5.67365,9.10078],"type":"Point"}
}