{
  "type": "Feature",
  "properties": {
    "gn:admin1_code":"41.0",
    "gn:admin2_code":"23014.0",
    "gn:asciiname":"Okokengi",
    "gn:country_code":"NG",
    "gn:dem":43,
    "gn:feature_class":"P",
    "gn:feature_code":"PPL",
    "gn:name":"Okokengi",
    "gn:population":0,
    "gn:timezone":"Africa/Lagos",
    "iso:country":"NG",
    "wof:name":"Okokengi",
    "wof:placetype":"locality"
},
  "geometry": {"coordinates":[6.706,7.3108],"type":"Point"}
}