{
  "type": "Feature",
  "properties": {
    "gn:admin1_code":"37.0",
    "gn:admin2_code":"12004.0",
    "gn:asciiname":"Ughenodua",
    "gn:country_code":"NG",
    "gn:dem":375,
    "gn:feature_class":"P",
    "gn:feature_code":"PPL",
    "gn:name":"Ughenodua",
    "gn:population":0,
    "gn:timezone":"Africa/Lagos",
    "iso:country":"NG",
    "name:eng_x_preferred":[
        "Ugbenolhua"
    ],
    "wof:name":"Ughenodua",
    "wof:placetype":"locality"
},
  "geometry": {"coordinates":[6.23718,6.71169],"type":"Point"}
}