{
  "type": "Feature",
  "properties": {
    "gn:admin1_code":"36.0",
    "gn:admin2_code":"10025.0",
    "gn:asciiname":"Torogbene",
    "gn:country_code":"NG",
    "gn:dem":11,
    "gn:feature_class":"P",
    "gn:feature_code":"PPL",
    "gn:name":"Torogbene",
    "gn:population":0,
    "gn:timezone":"Africa/Lagos",
    "iso:country":"NG",
    "name:eng_x_preferred":[
        "Torogbene"
    ],
    "wof:name":"Torogbene",
    "wof:placetype":"locality"
},
  "geometry": {"coordinates":[5.41586,5.41539],"type":"Point"}
}