{
  "type": "Feature",
  "properties": {
    "gn:admin1_code":"26.0",
    "gn:admin2_code":"7021",
    "gn:asciiname":"Tsegater",
    "gn:country_code":"NG",
    "gn:dem":187,
    "gn:feature_class":"P",
    "gn:feature_code":"PPL",
    "gn:name":"Tsegater",
    "gn:population":0,
    "gn:timezone":"Africa/Lagos",
    "iso:country":"NG",
    "wof:name":"Tsegater",
    "wof:placetype":"locality"
},
  "geometry": {"coordinates":[9.65006,7.64679],"type":"Point"}
}