{
  "type": "Feature",
  "properties": {
    "gn:admin1_code":"27.0",
    "gn:admin2_code":"105.0",
    "gn:admin3_code":"10507",
    "gn:asciiname":"Mandaragirau",
    "gn:country_code":"NG",
    "gn:dem":511,
    "gn:feature_class":"P",
    "gn:feature_code":"PPL",
    "gn:name":"Mandaragirau",
    "gn:population":0,
    "gn:timezone":"Africa/Lagos",
    "iso:country":"NG",
    "name:und_x_variant":[
        "Mandaragarau",
        "Mandaragirau"
    ],
    "wof:name":"Mandaragirau",
    "wof:placetype":"locality"
},
  "geometry": {"coordinates":[12.33134,10.69577],"type":"Point"}
}