{
  "type": "Feature",
  "properties": {
    "gn:admin1_code":"57.0",
    "gn:admin2_code":"812.0",
    "gn:admin3_code":"81204",
    "gn:asciiname":"Dengebe",
    "gn:country_code":"NG",
    "gn:dem":360,
    "gn:feature_class":"P",
    "gn:feature_code":"PPL",
    "gn:name":"Dengebe",
    "gn:population":0,
    "gn:timezone":"Africa/Lagos",
    "iso:country":"NG",
    "wof:name":"Dengebe",
    "wof:placetype":"locality"
},
  "geometry": {"coordinates":[6.06965,12.21943],"type":"Point"}
}