{
  "type": "Feature",
  "properties": {
    "gn:admin1_code":"29.0",
    "gn:admin2_code":"20041.0",
    "gn:admin3_code":"KN2210",
    "gn:asciiname":"Yola",
    "gn:country_code":"NG",
    "gn:dem":539,
    "gn:feature_class":"P",
    "gn:feature_code":"PPL",
    "gn:name":"Yola",
    "gn:population":0,
    "gn:timezone":"Africa/Lagos",
    "iso:country":"NG",
    "name:cat_x_preferred":[
        "Yola"
    ],
    "name:ceb_x_preferred":[
        "Yola"
    ],
    "name:deu_x_preferred":[
        "Yola"
    ],
    "name:fra_x_preferred":[
        "Yola"
    ],
    "name:heb_x_preferred":[
        "\u05d9\u05d5\u05dc\u05d4"
    ],
    "name:por_x_preferred":[
        "Yola"
    ],
    "name:rus_x_preferred":[
        "\u0419\u043e\u043b\u0430"
    ],
    "wof:name":"Yola",
    "wof:placetype":"locality"
},
  "geometry": {"coordinates":[7.96015,11.70375],"type":"Point"}
}