{
  "type": "Feature",
  "properties": {
    "gn:admin1_code":"35.0",
    "gn:asciiname":"Tagombeli",
    "gn:country_code":"NG",
    "gn:dem":256,
    "gn:feature_class":"P",
    "gn:feature_code":"PPL",
    "gn:name":"Tagombeli",
    "gn:population":0,
    "gn:timezone":"Africa/Lagos",
    "iso:country":"NG",
    "name:eng_x_preferred":[
        "Tagombeli"
    ],
    "wof:name":"Tagombeli",
    "wof:placetype":"locality"
},
  "geometry": {"coordinates":[11.82643,9.31169],"type":"Point"}
}