{
  "type": "Feature",
  "properties": {
    "gn:admin1_code":"26.0",
    "gn:admin2_code":"7004",
    "gn:asciiname":"Kwaghcha",
    "gn:country_code":"NG",
    "gn:dem":111,
    "gn:feature_class":"P",
    "gn:feature_code":"PPL",
    "gn:name":"Kwaghcha",
    "gn:population":0,
    "gn:timezone":"Africa/Lagos",
    "iso:country":"NG",
    "wof:name":"Kwaghcha",
    "wof:placetype":"locality"
},
  "geometry": {"coordinates":[9.27647,7.39406],"type":"Point"}
}