{
  "type": "Feature",
  "properties": {
    "gn:admin1_code":"29.0",
    "gn:admin2_code":"20029.0",
    "gn:admin3_code":"KN4111",
    "gn:asciiname":"Sabon Gari",
    "gn:country_code":"NG",
    "gn:dem":556,
    "gn:feature_class":"P",
    "gn:feature_code":"PPL",
    "gn:name":"Sabon Gari",
    "gn:population":0,
    "gn:timezone":"Africa/Lagos",
    "iso:country":"NG",
    "wof:name":"Sabon Gari",
    "wof:placetype":"locality"
},
  "geometry": {"coordinates":[8.31948,11.32367],"type":"Point"}
}