{
  "type": "Feature",
  "properties": {
    "gn:country":"NG",
    "gn:fcode":"PPL",
    "gn:pop":113830,
    "iso:country":"NG",
    "name:ang_x_preferred":[
        "Offa"
    ],
    "name:ara_x_preferred":[
        "\u0625\u064a\u062c\u0627\u063a\u0628\u0648 \u0623\u0648\u0641\u0627"
    ],
    "name:ben_x_preferred":[
        "\u0985\u09ab\u09ab\u09be"
    ],
    "name:cat_x_preferred":[
        "Offa"
    ],
    "name:dan_x_preferred":[
        "Offa"
    ],
    "name:deu_x_preferred":[
        "Offa"
    ],
    "name:ell_x_preferred":[
        "\u038c\u03c6\u03c6\u03b1"
    ],
    "name:eng_x_preferred":[
        "Offa"
    ],
    "name:epo_x_preferred":[
        "Offa"
    ],
    "name:fin_x_preferred":[
        "Offa"
    ],
    "name:fra_x_preferred":[
        "Offa"
    ],
    "name:guj_x_preferred":[
        "\u0a91\u0aab\u0abe"
    ],
    "name:hin_x_preferred":[
        "\u0907\u091c\u093e\u0917\u092c\u094b \u0911\u092b\u093e"
    ],
    "name:ind_x_preferred":[
        "Offa"
    ],
    "name:ita_x_preferred":[
        "Offa"
    ],
    "name:jpn_x_preferred":[
        "\u30aa\u30c3\u30d5\u30a1"
    ],
    "name:kan_x_preferred":[
        "\u0c86\u0cab\u0cbe"
    ],
    "name:kor_x_preferred":[
        "\uc624\ud30c"
    ],
    "name:lav_x_preferred":[
        "Ofa"
    ],
    "name:lit_x_preferred":[
        "Ofa"
    ],
    "name:mar_x_preferred":[
        "\u0911\u092b\u093e"
    ],
    "name:msa_x_preferred":[
        "Offa"
    ],
    "name:nld_x_preferred":[
        "Offa"
    ],
    "name:nob_x_preferred":[
        "Offa"
    ],
    "name:pol_x_preferred":[
        "Offa"
    ],
    "name:por_x_preferred":[
        "Offa"
    ],
    "name:rus_x_preferred":[
        "\u041e\u0444\u0444\u0430"
    ],
    "name:sin_x_preferred":[
        "\u0d94\u0dc6\u0dcf"
    ],
    "name:swe_x_preferred":[
        "Offa"
    ],
    "name:szl_x_preferred":[
        "Offa"
    ],
    "name:tam_x_preferred":[
        "\u0b92\u0baa\u0bcd\u0baa\u0bbe"
    ],
    "name:tel_x_preferred":[
        "\u0c06\u0c2b\u0c40"
    ],
    "name:tha_x_preferred":[
        "\u0e2d\u0e2d\u0e1f\u0e1f\u0e32"
    ],
    "name:tur_x_preferred":[
        "Offa"
    ],
    "name:ukr_x_preferred":[
        "\u041e\u0444\u0444\u0430"
    ],
    "name:urd_x_preferred":[
        "\u0648\u0641\u0627 \u060c \u0646\u0627\u0626\u06cc\u062c\u06cc\u0631\u06cc\u0627"
    ],
    "name:vie_x_preferred":[
        "Offa"
    ],
    "name:yor_x_preferred":[
        "\u1ecc\u0300f\u00e0"
    ],
    "qs:name":"Offa",
    "qs:photos_9r":0,
    "qs:photos_sr":0,
    "qs:pop_sr":"9",
    "wof:name":"Offa",
    "wof:placetype":"locality",
    "wof:population":113830
},
  "geometry": {"coordinates":[4.71667,8.15],"type":"Point"}
}