{
  "type": "Feature",
  "properties": {
    "gn:admin1_code":"31.0",
    "gn:admin2_code":"27004.0",
    "gn:asciiname":"Kabe",
    "gn:country_code":"NG",
    "gn:dem":308,
    "gn:feature_class":"P",
    "gn:feature_code":"PPL",
    "gn:name":"Kabe",
    "gn:population":0,
    "gn:timezone":"Africa/Lagos",
    "iso:country":"NG",
    "name:ceb_x_preferred":[
        "Kabe"
    ],
    "name:deu_x_preferred":[
        "Kabe"
    ],
    "name:est_x_preferred":[
        "Kabe"
    ],
    "name:fra_x_preferred":[
        "Kabe"
    ],
    "name:nor_x_preferred":[
        "Kabe"
    ],
    "name:swe_x_preferred":[
        "Kabe"
    ],
    "wof:name":"Kabe",
    "wof:placetype":"locality"
},
  "geometry": {"coordinates":[4.03239,10.61571],"type":"Point"}
}