{
  "type": "Feature",
  "properties": {
    "gn:admin1_code":"28.0",
    "gn:admin2_code":"17008.0",
    "gn:asciiname":"Ugiri",
    "gn:country_code":"NG",
    "gn:dem":162,
    "gn:feature_class":"P",
    "gn:feature_code":"PPL",
    "gn:name":"Ugiri",
    "gn:population":0,
    "gn:timezone":"Africa/Lagos",
    "iso:country":"NG",
    "wof:name":"Ugiri",
    "wof:placetype":"locality"
},
  "geometry": {"coordinates":[7.21112,5.5701],"type":"Point"}
}