{
  "type": "Feature",
  "properties": {
    "gn:admin1_code":"32.0",
    "gn:admin2_code":"31032.0",
    "gn:asciiname":"Alabafi",
    "gn:country_code":"NG",
    "gn:dem":404,
    "gn:feature_class":"P",
    "gn:feature_code":"PPL",
    "gn:name":"Alabafi",
    "gn:population":0,
    "gn:timezone":"Africa/Lagos",
    "iso:country":"NG",
    "wof:name":"Alabafi",
    "wof:placetype":"locality"
},
  "geometry": {"coordinates":[3.41667,8.85],"type":"Point"}
}