{
  "type": "Feature",
  "properties": {
    "gn:admin1_code":"23.0",
    "gn:admin2_code":"19007.0",
    "gn:admin3_code":"KD0701",
    "gn:asciiname":"Kwagiri",
    "gn:country_code":"NG",
    "gn:dem":495,
    "gn:feature_class":"P",
    "gn:feature_code":"PPL",
    "gn:name":"Kwagiri",
    "gn:population":0,
    "gn:timezone":"Africa/Lagos",
    "iso:country":"NG",
    "wof:name":"Kwagiri",
    "wof:placetype":"locality"
},
  "geometry": {"coordinates":[8.19218,9.38005],"type":"Point"}
}