{
  "type": "Feature",
  "properties": {
    "gn:admin1_code":"45.0",
    "gn:admin2_code":"1005.0",
    "gn:asciiname":"Iyila",
    "gn:country_code":"NG",
    "gn:dem":114,
    "gn:feature_class":"P",
    "gn:feature_code":"PPL",
    "gn:name":"Iyila",
    "gn:population":0,
    "gn:timezone":"Africa/Lagos",
    "iso:country":"NG",
    "wof:name":"Iyila",
    "wof:placetype":"locality"
},
  "geometry": {"coordinates":[7.60646,5.43646],"type":"Point"}
}