{
  "type": "Feature",
  "properties": {
    "gn:admin1_code":"43.0",
    "gn:admin2_code":"35015.0",
    "gn:asciiname":"Pantimazang",
    "gn:country_code":"NG",
    "gn:dem":282,
    "gn:feature_class":"P",
    "gn:feature_code":"PPL",
    "gn:name":"Pantimazang",
    "gn:population":0,
    "gn:timezone":"Africa/Lagos",
    "iso:country":"NG",
    "wof:name":"Pantimazang",
    "wof:placetype":"locality"
},
  "geometry": {"coordinates":[11.48305,8.86392],"type":"Point"}
}