{
  "type": "Feature",
  "properties": {
    "gn:admin1_code":"27.0",
    "gn:asciiname":"Mallam Bindiga",
    "gn:country_code":"NG",
    "gn:dem":312,
    "gn:feature_class":"P",
    "gn:feature_code":"PPL",
    "gn:name":"Mallam Bindiga",
    "gn:population":0,
    "gn:timezone":"Africa/Lagos",
    "iso:country":"NG",
    "wof:name":"Mallam Bindiga",
    "wof:placetype":"locality"
},
  "geometry": {"coordinates":[11.74035,10.78845],"type":"Point"}
}