{
  "type": "Feature",
  "properties": {
    "gn:admin1_code":"43.0",
    "gn:admin2_code":"35001",
    "gn:asciiname":"Pantimanu",
    "gn:country_code":"NG",
    "gn:dem":231,
    "gn:feature_class":"P",
    "gn:feature_code":"PPL",
    "gn:name":"Pantimanu",
    "gn:population":0,
    "gn:timezone":"Africa/Lagos",
    "iso:country":"NG",
    "wof:name":"Pantimanu",
    "wof:placetype":"locality"
},
  "geometry": {"coordinates":[11.31491,8.70991],"type":"Point"}
}