{
  "type": "Feature",
  "properties": {
    "gn:admin1_code":"57.0",
    "gn:admin2_code":"806.0",
    "gn:admin3_code":"80606",
    "gn:asciiname":"Dakawa",
    "gn:country_code":"NG",
    "gn:dem":216,
    "gn:feature_class":"P",
    "gn:feature_code":"PPL",
    "gn:name":"Dakawa",
    "gn:population":0,
    "gn:timezone":"Africa/Lagos",
    "iso:country":"NG",
    "wof:name":"Dakawa",
    "wof:placetype":"locality"
},
  "geometry": {"coordinates":[4.90008,12.15433],"type":"Point"}
}