{
  "type": "Feature",
  "properties": {
    "gn:admin1_code":"44.0",
    "gn:admin2_code":"712.0",
    "gn:admin3_code":"71216",
    "gn:asciiname":"Kayauri",
    "gn:country_code":"NG",
    "gn:dem":390,
    "gn:feature_class":"P",
    "gn:feature_code":"PPL",
    "gn:name":"Kayauri",
    "gn:population":0,
    "gn:timezone":"Africa/Lagos",
    "iso:country":"NG",
    "name:und_x_variant":[
        "Kaiuri",
        "Kayauri"
    ],
    "wof:name":"Kayauri",
    "wof:placetype":"locality"
},
  "geometry": {"coordinates":[11.06588,11.89045],"type":"Point"}
}