{
  "type": "Feature",
  "properties": {
    "gn:admin1_code":"30.0",
    "gn:admin2_code":"24001.0",
    "gn:asciiname":"Sata",
    "gn:cc2":"NG",
    "gn:country_code":"NG",
    "gn:dem":357,
    "gn:feature_class":"P",
    "gn:feature_code":"PPL",
    "gn:name":"Sata",
    "gn:population":0,
    "gn:timezone":"Africa/Lagos",
    "iso:country":"NG",
    "name:und_x_variant":[
        "Essemi",
        "Sata"
    ],
    "wof:name":"Sata",
    "wof:placetype":"locality"
},
  "geometry": {"coordinates":[4.36667,8.36667],"type":"Point"}
}