{
  "type": "Feature",
  "properties": {
    "gn:admin1_code":"23.0",
    "gn:admin2_code":"19002.0",
    "gn:admin3_code":"KD0201",
    "gn:asciiname":"Kafao",
    "gn:country_code":"NG",
    "gn:dem":536,
    "gn:feature_class":"P",
    "gn:feature_code":"PPL",
    "gn:name":"Kafao",
    "gn:population":0,
    "gn:timezone":"Africa/Lagos",
    "iso:country":"NG",
    "wof:name":"Kafao",
    "wof:placetype":"locality"
},
  "geometry": {"coordinates":[7.10363,10.25182],"type":"Point"}
}