{
  "type": "Feature",
  "properties": {
    "iso:country":"NG",
    "name:ara_x_preferred":[
        "\u0645\u0637\u0627\u0631 \u0645\u064a\u062f\u063a\u0631\u064a \u0627\u0644\u062f\u0648\u0644\u064a"
    ],
    "name:ceb_x_preferred":[
        "Maiduguri Airport"
    ],
    "name:cym_x_preferred":[
        "Maes Awyr Rhyngwladol Maiduguri"
    ],
    "name:ell_x_preferred":[
        "\u0394\u03b9\u03b5\u03b8\u03bd\u03ad\u03c2 \u0391\u03b5\u03c1\u03bf\u03b4\u03c1\u03cc\u03bc\u03b9\u03bf \u03c4\u03bf\u03c5 \u039c\u03b1\u03ca\u03bd\u03c4\u03bf\u03cd\u03b3\u03ba\u03bf\u03c5\u03c1\u03b9"
    ],
    "name:eng_x_variant":[
        "MIU",
        "DNMA"
    ],
    "name:fas_x_preferred":[
        "\u0641\u0631\u0648\u062f\u06af\u0627\u0647 \u0628\u06cc\u0646\u200c\u0627\u0644\u0645\u0644\u0644\u06cc \u0645\u0627\u06cc\u062f\u0648\u06af\u0648\u0631\u06cc"
    ],
    "name:hau_x_preferred":[
        "Filin jirgin saman Maiduguri"
    ],
    "name:heb_x_preferred":[
        "\u05e0\u05de\u05dc \u05d4\u05ea\u05e2\u05d5\u05e4\u05d4 \u05d4\u05d1\u05d9\u05e0\u05dc\u05d0\u05d5\u05de\u05d9 \u05de\u05d9\u05d9\u05d3\u05d5\u05d2\u05d5\u05e8\u05d9"
    ],
    "name:ind_x_preferred":[
        "Bandar Udara Internasional Maiduguri"
    ],
    "name:jpn_x_preferred":[
        "\u30de\u30a4\u30c9\u30a5\u30b0\u30ea\u56fd\u969b\u7a7a\u6e2f"
    ],
    "name:pol_x_preferred":[
        "Port lotniczy Maiduguri"
    ],
    "name:ron_x_preferred":[
        "Aeroportul Maiduguri"
    ],
    "oa:elevation_ft":"1099",
    "oa:type":"medium_airport",
    "woe:hierarchy":{
        "country_id":23424908,
        "county_id":56057827,
        "planet_id":1,
        "state_id":2346355
    },
    "wof:name":"Maiduguri Airport",
    "wof:placetype":"campus"
},
  "geometry": {"coordinates":[13.080833,11.855278],"type":"Point"}
}