{
  "type": "Feature",
  "properties": {
    "iso:country":"NG",
    "name:ara_x_preferred":[
        "\u0645\u0637\u0627\u0631 \u0645\u064a\u062f\u063a\u0631\u064a \u0627\u0644\u062f\u0648\u0644\u064a"
    ],
    "name:ceb_x_preferred":[
        "Maiduguri Airport"
    ],
    "name:fas_x_preferred":[
        "\u0641\u0631\u0648\u062f\u06af\u0627\u0647 \u0628\u06cc\u0646\u200c\u0627\u0644\u0645\u0644\u0644\u06cc \u0645\u0627\u06cc\u062f\u0648\u06af\u0648\u0631\u06cc"
    ],
    "name:hau_x_preferred":[
        "Filin jirgin saman Maiduguri"
    ],
    "name:ind_x_preferred":[
        "Bandar Udara Internasional Maiduguri"
    ],
    "name:jpn_x_preferred":[
        "\u30de\u30a4\u30c9\u30a5\u30b0\u30ea\u56fd\u969b\u7a7a\u6e2f"
    ],
    "name:pol_x_preferred":[
        "Port lotniczy Maiduguri"
    ],
    "name:ron_x_preferred":[
        "Aeroportul Maiduguri"
    ],
    "oa:elevation_ft":"1099",
    "oa:type":"medium_airport",
    "woe:hierarchy":{
        "country_id":23424908,
        "county_id":56057827,
        "planet_id":1,
        "state_id":2346355
    },
    "wof:name":"Maiduguri Airport",
    "wof:placetype":"campus"
},
  "geometry": {"coordinates":[13.080833333333,11.855277777778],"type":"Point"}
}