{
  "type": "Feature",
  "properties": {
    "iso:country":"NG",
    "oa:elevation_ft":"1099",
    "oa:type":"medium_airport",
    "woe:hierarchy":{
        "country_id":23424908,
        "county_id":56057827,
        "planet_id":1,
        "state_id":2346355
    },
    "wof:name":"Maiduguri Airport",
    "wof:placetype":"campus"
},
  "geometry": {"coordinates":[13.080833333333,11.855277777778],"type":"Point"}
}