{
  "type": "Feature",
  "properties": {
    "gn:admin1_code":"43.0",
    "gn:admin2_code":"35008.0",
    "gn:asciiname":"Bomanda",
    "gn:country_code":"NG",
    "gn:dem":133,
    "gn:feature_class":"P",
    "gn:feature_code":"PPL",
    "gn:name":"Bomanda",
    "gn:population":0,
    "gn:timezone":"Africa/Lagos",
    "iso:country":"NG",
    "name:eng_x_preferred":[
        "Bomanda"
    ],
    "name:eng_x_variant":[
        "Bumanda"
    ],
    "wof:name":"Bomanda",
    "wof:placetype":"locality"
},
  "geometry": {"coordinates":[10.87637,9.07009],"type":"Point"}
}