{
  "type": "Feature",
  "properties": {
    "gn:admin1_code":"49.0",
    "gn:admin2_code":"32002.0",
    "gn:asciiname":"Gurum",
    "gn:country_code":"NG",
    "gn:dem":1135,
    "gn:feature_class":"P",
    "gn:feature_code":"PPL",
    "gn:name":"Gurum",
    "gn:population":0,
    "gn:timezone":"Africa/Lagos",
    "iso:country":"NG",
    "name:msa_x_preferred":[
        "Gurum"
    ],
    "wof:name":"Gurum",
    "wof:placetype":"locality"
},
  "geometry": {"coordinates":[8.83602,10.02863],"type":"Point"}
}