{
  "type": "Feature",
  "properties": {
    "gn:admin1_code":"51.0",
    "gn:admin2_code":"613.0",
    "gn:admin3_code":"61311",
    "gn:asciiname":"Gidan Leo",
    "gn:country_code":"NG",
    "gn:dem":291,
    "gn:feature_class":"P",
    "gn:feature_code":"PPL",
    "gn:name":"Gidan Leo",
    "gn:population":0,
    "gn:timezone":"Africa/Lagos",
    "iso:country":"NG",
    "wof:name":"Gidan Leo",
    "wof:placetype":"locality"
},
  "geometry": {"coordinates":[5.99599,13.60486],"type":"Point"}
}