{
  "type": "Feature",
  "properties": {
    "gn:admin1_code":"32.0",
    "gn:admin2_code":"31033.0",
    "gn:asciiname":"Gambari",
    "gn:cc2":"NG",
    "gn:country_code":"NG",
    "gn:dem":422,
    "gn:feature_class":"P",
    "gn:feature_code":"PPL",
    "gn:name":"Gambari",
    "gn:population":0,
    "gn:timezone":"Africa/Lagos",
    "iso:country":"NG",
    "name:und_x_variant":[
        "Awbere",
        "Obere",
        "Gambari"
    ],
    "wof:name":"Gambari",
    "wof:placetype":"locality"
},
  "geometry": {"coordinates":[4.33333,8.26667],"type":"Point"}
}