{
  "type": "Feature",
  "properties": {
    "gn:admin1_code":"5.0",
    "gn:admin2_code":"25012.0",
    "gn:asciiname":"Isiwu",
    "gn:country_code":"NG",
    "gn:dem":45,
    "gn:feature_class":"P",
    "gn:feature_code":"PPL",
    "gn:name":"Isiwu",
    "gn:population":0,
    "gn:timezone":"Africa/Lagos",
    "iso:country":"NG",
    "name:und_x_variant":[
        "Isiu",
        "Isiwu"
    ],
    "wof:name":"Isiwu",
    "wof:placetype":"locality"
},
  "geometry": {"coordinates":[3.61872,6.65961],"type":"Point"}
}