{
  "type": "Feature",
  "properties": {
    "gn:admin1_code":"35.0",
    "gn:admin2_code":"2011",
    "gn:asciiname":"Wuro Babboi",
    "gn:country_code":"NG",
    "gn:dem":425,
    "gn:feature_class":"P",
    "gn:feature_code":"PPL",
    "gn:name":"Wuro Babboi",
    "gn:population":0,
    "gn:timezone":"Africa/Lagos",
    "iso:country":"NG",
    "wof:name":"Wuro Babboi",
    "wof:placetype":"locality"
},
  "geometry": {"coordinates":[13.13037,9.76745],"type":"Point"}
}