{
  "type": "Feature",
  "properties": {
    "gn:admin1_code":"5.0",
    "gn:admin2_code":"25007.0",
    "gn:asciiname":"Imope",
    "gn:country_code":"NG",
    "gn:dem":0,
    "gn:feature_class":"P",
    "gn:feature_code":"PPL",
    "gn:name":"Imope",
    "gn:population":0,
    "gn:timezone":"Africa/Lagos",
    "iso:country":"NG",
    "wof:name":"Imope",
    "wof:placetype":"locality"
},
  "geometry": {"coordinates":[3.74623,6.61606],"type":"Point"}
}