{
  "type": "Feature",
  "properties": {
    "gn:admin1_code":"16.0",
    "gn:admin2_code":"28020.0",
    "gn:asciiname":"Eyita",
    "gn:country_code":"NG",
    "gn:dem":51,
    "gn:feature_class":"P",
    "gn:feature_code":"PPL",
    "gn:name":"Eyita",
    "gn:population":0,
    "gn:timezone":"Africa/Lagos",
    "iso:country":"NG",
    "wof:name":"Eyita",
    "wof:placetype":"locality"
},
  "geometry": {"coordinates":[3.5352,6.69025],"type":"Point"}
}