{
  "type": "Feature",
  "properties": {
    "gn:admin1_code":"50.0",
    "gn:admin2_code":"33021.0",
    "gn:asciiname":"Okoloma",
    "gn:country_code":"NG",
    "gn:dem":29,
    "gn:feature_class":"P",
    "gn:feature_code":"PPL",
    "gn:name":"Okoloma",
    "gn:population":0,
    "gn:timezone":"Africa/Lagos",
    "iso:country":"NG",
    "wof:name":"Okoloma",
    "wof:placetype":"locality"
},
  "geometry": {"coordinates":[7.24587,4.84993],"type":"Point"}
}