{
  "type": "Feature",
  "properties": {
    "gn:admin1_code":"26.0",
    "gn:admin2_code":"7013.0",
    "gn:asciiname":"Orchiga",
    "gn:country_code":"NG",
    "gn:dem":92,
    "gn:feature_class":"P",
    "gn:feature_code":"PPL",
    "gn:name":"Orchiga",
    "gn:population":0,
    "gn:timezone":"Africa/Lagos",
    "iso:country":"NG",
    "wof:name":"Orchiga",
    "wof:placetype":"locality"
},
  "geometry": {"coordinates":[8.44655,7.6723],"type":"Point"}
}