{
  "type": "Feature",
  "properties": {
    "gn:admin1_code":"42.0",
    "gn:admin2_code":"30001.0",
    "gn:asciiname":"Alaso Osun",
    "gn:country_code":"NG",
    "gn:dem":188,
    "gn:feature_class":"P",
    "gn:feature_code":"PPL",
    "gn:name":"Alaso Osun",
    "gn:population":0,
    "gn:timezone":"Africa/Lagos",
    "iso:country":"NG",
    "wof:name":"Alaso Osun",
    "wof:placetype":"locality"
},
  "geometry": {"coordinates":[4.16667,7.23333],"type":"Point"}
}