{
  "type": "Feature",
  "properties": {
    "gn:admin1_code":"23.0",
    "gn:admin2_code":"19022",
    "gn:admin3_code":"KD2201",
    "gn:asciiname":"Baffot",
    "gn:country_code":"NG",
    "gn:dem":750,
    "gn:feature_class":"P",
    "gn:feature_code":"PPL",
    "gn:name":"Baffot",
    "gn:population":0,
    "gn:timezone":"Africa/Lagos",
    "iso:country":"NG",
    "wof:name":"Baffot",
    "wof:placetype":"locality"
},
  "geometry": {"coordinates":[8.18621,9.64723],"type":"Point"}
}