{
  "type": "Feature",
  "properties": {
    "gn:admin1_code":"44.0",
    "gn:admin2_code":"708.0",
    "gn:admin3_code":"70806",
    "gn:asciiname":"Mainya",
    "gn:country_code":"NG",
    "gn:dem":329,
    "gn:feature_class":"P",
    "gn:feature_code":"PPL",
    "gn:name":"Mainya",
    "gn:population":0,
    "gn:timezone":"Africa/Lagos",
    "iso:country":"NG",
    "name:und_x_variant":[
        "Mainyada"
    ],
    "wof:name":"Mainya",
    "wof:placetype":"locality"
},
  "geometry": {"coordinates":[11.69478,11.04347],"type":"Point"}
}