{
  "type": "Feature",
  "properties": {
    "gn:admin1_code":"22.0",
    "gn:admin2_code":"9013",
    "gn:asciiname":"Okpangut",
    "gn:country_code":"NG",
    "gn:dem":38,
    "gn:feature_class":"P",
    "gn:feature_code":"PPL",
    "gn:name":"Okpangut",
    "gn:population":0,
    "gn:timezone":"Africa/Lagos",
    "iso:country":"NG",
    "wof:name":"Okpangut",
    "wof:placetype":"locality"
},
  "geometry": {"coordinates":[8.37887,6.05706],"type":"Point"}
}