{
  "type": "Feature",
  "properties": {
    "gn:admin1_code":"44.0",
    "gn:admin2_code":"705.0",
    "gn:admin3_code":"70501",
    "gn:asciiname":"Garin Bauci",
    "gn:country_code":"NG",
    "gn:dem":379,
    "gn:feature_class":"P",
    "gn:feature_code":"PPL",
    "gn:name":"Garin Bauci",
    "gn:population":0,
    "gn:timezone":"Africa/Lagos",
    "iso:country":"NG",
    "wof:name":"Garin Bauci",
    "wof:placetype":"locality"
},
  "geometry": {"coordinates":[11.53825,11.59119],"type":"Point"}
}