{
  "type": "Feature",
  "properties": {
    "gn:admin1_code":"31.0",
    "gn:asciiname":"Gidan Aligeta",
    "gn:country_code":"NG",
    "gn:dem":379,
    "gn:feature_class":"P",
    "gn:feature_code":"PPL",
    "gn:name":"Gidan Aligeta",
    "gn:population":0,
    "gn:timezone":"Africa/Lagos",
    "iso:country":"NG",
    "wof:name":"Gidan Aligeta",
    "wof:placetype":"locality"
},
  "geometry": {"coordinates":[6.40934,10.58275],"type":"Point"}
}