{
  "type": "Feature",
  "properties": {
    "gn:admin1_code":"49.0",
    "gn:asciiname":"Goepil",
    "gn:country_code":"NG",
    "gn:dem":283,
    "gn:feature_class":"P",
    "gn:feature_code":"PPL",
    "gn:name":"Goepil",
    "gn:population":0,
    "gn:timezone":"Africa/Lagos",
    "iso:country":"NG",
    "wof:name":"Goepil",
    "wof:placetype":"locality"
},
  "geometry": {"coordinates":[9.15086,8.92406],"type":"Point"}
}