{
  "type": "Feature",
  "properties": {
    "gn:admin1_code":"27.0",
    "gn:admin2_code":"109.0",
    "gn:admin3_code":"10901",
    "gn:asciiname":"Geltomu",
    "gn:country_code":"NG",
    "gn:dem":306,
    "gn:feature_class":"P",
    "gn:feature_code":"PPL",
    "gn:name":"Geltomu",
    "gn:population":0,
    "gn:timezone":"Africa/Lagos",
    "iso:country":"NG",
    "wof:name":"Geltomu",
    "wof:placetype":"locality"
},
  "geometry": {"coordinates":[12.73855,12.46345],"type":"Point"}
}