{
  "type": "Feature",
  "properties": {
    "gn:admin1_code":"49.0",
    "gn:admin2_code":"32002.0",
    "gn:asciiname":"Barakin Tumbakiri",
    "gn:country_code":"NG",
    "gn:dem":1162,
    "gn:feature_class":"P",
    "gn:feature_code":"PPL",
    "gn:name":"Barakin Tumbakiri",
    "gn:population":0,
    "gn:timezone":"Africa/Lagos",
    "iso:country":"NG",
    "wof:name":"Barakin Tumbakiri",
    "wof:placetype":"locality"
},
  "geometry": {"coordinates":[8.76632,10.04556],"type":"Point"}
}