{
  "type": "Feature",
  "properties": {
    "gn:admin1_code":"23.0",
    "gn:admin2_code":"19003.0",
    "gn:admin3_code":"KD0301",
    "gn:asciiname":"Guga",
    "gn:country_code":"NG",
    "gn:dem":673,
    "gn:feature_class":"P",
    "gn:feature_code":"PPL",
    "gn:name":"Guga",
    "gn:population":0,
    "gn:timezone":"Africa/Lagos",
    "iso:country":"NG",
    "name:ceb_x_preferred":[
        "Guga"
    ],
    "name:deu_x_preferred":[
        "Guga"
    ],
    "name:por_x_preferred":[
        "Guga"
    ],
    "name:swe_x_preferred":[
        "Guga"
    ],
    "wof:name":"Guga",
    "wof:placetype":"locality"
},
  "geometry": {"coordinates":[7.55144,11.25193],"type":"Point"}
}