{
  "type": "Feature",
  "properties": {
    "gn:admin1_code":"21.0",
    "gn:admin2_code":"3005.0",
    "gn:asciiname":"Medim",
    "gn:country_code":"NG",
    "gn:dem":63,
    "gn:feature_class":"P",
    "gn:feature_code":"PPL",
    "gn:name":"Medim",
    "gn:population":0,
    "gn:timezone":"Africa/Lagos",
    "iso:country":"NG",
    "wof:name":"Medim",
    "wof:placetype":"locality"
},
  "geometry": {"coordinates":[7.62798,5.04687],"type":"Point"}
}