{
  "type": "Feature",
  "properties": {
    "gn:admin1_code":"35.0",
    "gn:admin2_code":"2019.0",
    "gn:asciiname":"Wuro Faluku",
    "gn:country_code":"NG",
    "gn:dem":313,
    "gn:feature_class":"P",
    "gn:feature_code":"PPL",
    "gn:name":"Wuro Faluku",
    "gn:population":0,
    "gn:timezone":"Africa/Lagos",
    "iso:country":"NG",
    "wof:name":"Wuro Faluku",
    "wof:placetype":"locality"
},
  "geometry": {"coordinates":[11.48333,7.86667],"type":"Point"}
}