{
  "type": "Feature",
  "properties": {
    "gn:admin1_code":"42.0",
    "gn:admin2_code":"30028.0",
    "gn:asciiname":"Ijeda",
    "gn:cc2":"NG",
    "gn:country_code":"NG",
    "gn:dem":396,
    "gn:feature_class":"P",
    "gn:feature_code":"PPL",
    "gn:name":"Ijeda",
    "gn:population":0,
    "gn:timezone":"Africa/Lagos",
    "iso:country":"NG",
    "name:und_x_variant":[
        "Ijedda",
        "Ijeda"
    ],
    "wof:name":"Ijeda",
    "wof:placetype":"locality"
},
  "geometry": {"coordinates":[4.83333,7.65],"type":"Point"}
}