{
  "type": "Feature",
  "properties": {
    "gn:admin1_code":"30.0",
    "gn:admin2_code":"24001.0",
    "gn:asciiname":"Olugbon",
    "gn:country_code":"NG",
    "gn:dem":381,
    "gn:feature_class":"P",
    "gn:feature_code":"PPL",
    "gn:name":"Olugbon",
    "gn:population":0,
    "gn:timezone":"Africa/Lagos",
    "iso:country":"NG",
    "wof:name":"Olugbon",
    "wof:placetype":"locality"
},
  "geometry": {"coordinates":[4.41667,8.33333],"type":"Point"}
}