{
  "type": "Feature",
  "properties": {
    "gn:admin1_code":"22.0",
    "gn:admin2_code":"9005.0",
    "gn:asciiname":"Akaraba",
    "gn:country_code":"NG",
    "gn:dem":130,
    "gn:feature_class":"P",
    "gn:feature_code":"PPL",
    "gn:name":"Akaraba",
    "gn:population":0,
    "gn:timezone":"Africa/Lagos",
    "iso:country":"NG",
    "wof:name":"Akaraba",
    "wof:placetype":"locality"
},
  "geometry": {"coordinates":[8.94779,6.77967],"type":"Point"}
}