{
  "type": "Feature",
  "properties": {
    "gn:admin1_code":"26.0",
    "gn:admin2_code":"7010.0",
    "gn:asciiname":"Mzungu",
    "gn:country_code":"NG",
    "gn:dem":153,
    "gn:feature_class":"P",
    "gn:feature_code":"PPL",
    "gn:name":"Mzungu",
    "gn:population":0,
    "gn:timezone":"Africa/Lagos",
    "iso:country":"NG",
    "name:deu_x_preferred":[
        "Mzungu"
    ],
    "name:heb_x_preferred":[
        "\u05de\u05d6\u05d5\u05e0\u05d2\u05d5"
    ],
    "name:kat_x_preferred":[
        "\u10db\u10e3\u10d6\u10e3\u10dc\u10d2\u10e3"
    ],
    "name:nor_x_preferred":[
        "Mzungu"
    ],
    "name:swa_x_preferred":[
        "Mzungu"
    ],
    "wof:name":"Mzungu",
    "wof:placetype":"locality"
},
  "geometry": {"coordinates":[8.52204,7.1873],"type":"Point"}
}