{
  "type": "Feature",
  "properties": {
    "gn:admin1_code":"55.0",
    "gn:admin2_code":"16005.0",
    "gn:asciiname":"Gubi",
    "gn:country_code":"NG",
    "gn:dem":267,
    "gn:feature_class":"P",
    "gn:feature_code":"PPL",
    "gn:name":"Gubi",
    "gn:population":0,
    "gn:timezone":"Africa/Lagos",
    "iso:country":"NG",
    "wof:name":"Gubi",
    "wof:placetype":"locality"
},
  "geometry": {"coordinates":[11.39455,11.08618],"type":"Point"}
}