{
  "type": "Feature",
  "properties": {
    "gn:admin1_code":"32.0",
    "gn:admin2_code":"31022.0",
    "gn:asciiname":"Temidire Atoyebi",
    "gn:country_code":"NG",
    "gn:dem":303,
    "gn:feature_class":"P",
    "gn:feature_code":"PPL",
    "gn:name":"Temidire Atoyebi",
    "gn:population":0,
    "gn:timezone":"Africa/Lagos",
    "iso:country":"NG",
    "wof:name":"Temidire Atoyebi",
    "wof:placetype":"neighbourhood"
},
  "geometry": {"coordinates":[4.21667,8.08333],"type":"Point"}
}