{
  "type": "Feature",
  "properties": {
    "gn:admin1_code":"27.0",
    "gn:admin2_code":"115.0",
    "gn:admin3_code":"11506",
    "gn:asciiname":"Misherde",
    "gn:country_code":"NG",
    "gn:dem":294,
    "gn:feature_class":"P",
    "gn:feature_code":"PPL",
    "gn:name":"Misherde",
    "gn:population":0,
    "gn:timezone":"Africa/Lagos",
    "iso:country":"NG",
    "wof:name":"Misherde",
    "wof:placetype":"locality"
},
  "geometry": {"coordinates":[14.45069,11.99351],"type":"Point"}
}