{
  "type": "Feature",
  "properties": {
    "gn:admin1_code":"51.0",
    "gn:admin2_code":"606.0",
    "gn:admin3_code":"60609",
    "gn:asciiname":"Jimojimi Sule",
    "gn:country_code":"NG",
    "gn:dem":297,
    "gn:feature_class":"P",
    "gn:feature_code":"PPL",
    "gn:name":"Jimojimi Sule",
    "gn:population":0,
    "gn:timezone":"Africa/Lagos",
    "iso:country":"NG",
    "wof:name":"Jimojimi Sule",
    "wof:placetype":"locality"
},
  "geometry": {"coordinates":[4.691,13.7201],"type":"Point"}
}