{
  "type": "Feature",
  "properties": {
    "gn:admin1_code":"44.0",
    "gn:admin2_code":"717",
    "gn:admin3_code":"71709",
    "gn:asciiname":"Mubudauri",
    "gn:country_code":"NG",
    "gn:dem":344,
    "gn:feature_class":"P",
    "gn:feature_code":"PPL",
    "gn:name":"Mubudauri",
    "gn:population":0,
    "gn:timezone":"Africa/Lagos",
    "iso:country":"NG",
    "wof:name":"Mubudauri",
    "wof:placetype":"locality"
},
  "geometry": {"coordinates":[11.04766,13.14972],"type":"Point"}
}