{
  "type": "Feature",
  "properties": {
    "gn:admin1_code":"54.0",
    "gn:admin2_code":"13001.0",
    "gn:asciiname":"Erifun",
    "gn:country_code":"NG",
    "gn:dem":380,
    "gn:feature_class":"P",
    "gn:feature_code":"PPL",
    "gn:name":"Erifun",
    "gn:population":0,
    "gn:timezone":"Africa/Lagos",
    "iso:country":"NG",
    "wof:name":"Erifun",
    "wof:placetype":"locality"
},
  "geometry": {"coordinates":[5.28848,7.60649],"type":"Point"}
}