{
  "type": "Feature",
  "properties": {
    "gn:admin1_code":"35.0",
    "gn:admin2_code":"2002.0",
    "gn:asciiname":"Jauro Babale",
    "gn:country_code":"NG",
    "gn:dem":319,
    "gn:feature_class":"P",
    "gn:feature_code":"PPL",
    "gn:name":"Jauro Babale",
    "gn:population":0,
    "gn:timezone":"Africa/Lagos",
    "iso:country":"NG",
    "wof:name":"Jauro Babale",
    "wof:placetype":"locality"
},
  "geometry": {"coordinates":[12.3893,8.83061],"type":"Point"}
}