{
  "type": "Feature",
  "properties": {
    "gn:admin1_code":"56.0",
    "gn:admin2_code":"26009.0",
    "gn:asciiname":"Udegi",
    "gn:country_code":"NG",
    "gn:dem":130,
    "gn:feature_class":"P",
    "gn:feature_code":"PPL",
    "gn:name":"Udegi",
    "gn:population":0,
    "gn:timezone":"Africa/Lagos",
    "iso:country":"NG",
    "wof:name":"Udegi",
    "wof:placetype":"locality"
},
  "geometry": {"coordinates":[7.90222,8.25139],"type":"Point"}
}