{
  "type": "Feature",
  "properties": {
    "gn:admin1_code":"51.0",
    "gn:admin2_code":"606.0",
    "gn:admin3_code":"60610",
    "gn:asciiname":"Danwai",
    "gn:country_code":"NG",
    "gn:dem":262,
    "gn:feature_class":"P",
    "gn:feature_code":"PPL",
    "gn:name":"Danwai",
    "gn:population":0,
    "gn:timezone":"Africa/Lagos",
    "iso:country":"NG",
    "wof:name":"Danwai",
    "wof:placetype":"locality"
},
  "geometry": {"coordinates":[4.27698,13.43444],"type":"Point"}
}