{
  "type": "Feature",
  "properties": {
    "gn:admin1_code":"35.0",
    "gn:admin2_code":"2012",
    "gn:asciiname":"Wuro Sete",
    "gn:country_code":"NG",
    "gn:dem":400,
    "gn:feature_class":"P",
    "gn:feature_code":"PPL",
    "gn:name":"Wuro Sete",
    "gn:population":0,
    "gn:timezone":"Africa/Lagos",
    "iso:country":"NG",
    "wof:name":"Wuro Sete",
    "wof:placetype":"locality"
},
  "geometry": {"coordinates":[12.10287,8.91515],"type":"Point"}
}