{
  "type": "Feature",
  "properties": {
    "gn:admin1_code":"30.0",
    "gn:admin2_code":"24003.0",
    "gn:asciiname":"Bacita",
    "gn:cc2":"NG",
    "gn:country_code":"NG",
    "gn:dem":84,
    "gn:feature_class":"P",
    "gn:feature_code":"PPL",
    "gn:name":"Bacita",
    "gn:population":0,
    "gn:timezone":"Africa/Lagos",
    "iso:country":"NG",
    "name:und_x_variant":[
        "Basita",
        "Bacita"
    ],
    "wof:name":"Bacita",
    "wof:placetype":"locality"
},
  "geometry": {"coordinates":[4.95,9.08333],"type":"Point"}
}