{
  "type": "Feature",
  "properties": {
    "gn:admin1_code":"35.0",
    "gn:admin2_code":"2017.0",
    "gn:asciiname":"Sokra",
    "gn:country_code":"NG",
    "gn:dem":476,
    "gn:feature_class":"P",
    "gn:feature_code":"PPL",
    "gn:name":"Sokra",
    "gn:population":0,
    "gn:timezone":"Africa/Lagos",
    "iso:country":"NG",
    "name:und_x_variant":[
        "Sogra",
        "Sokra"
    ],
    "wof:name":"Sokra",
    "wof:placetype":"locality"
},
  "geometry": {"coordinates":[12.29991,10.26404],"type":"Point"}
}