{
  "type": "Feature",
  "properties": {
    "gn:admin1_code":"51.0",
    "gn:admin2_code":"607.0",
    "gn:admin3_code":"60705",
    "gn:asciiname":"Gigani",
    "gn:country_code":"NG",
    "gn:dem":264,
    "gn:feature_class":"P",
    "gn:feature_code":"PPL",
    "gn:name":"Gigani",
    "gn:population":0,
    "gn:timezone":"Africa/Lagos",
    "iso:country":"NG",
    "name:und_x_variant":[
        "Gigane",
        "Gigani"
    ],
    "wof:name":"Gigani",
    "wof:placetype":"locality"
},
  "geometry": {"coordinates":[5.23347,13.49061],"type":"Point"}
}