{
  "type": "Feature",
  "properties": {
    "gn:admin1_code":"31.0",
    "gn:admin2_code":"27024.0",
    "gn:asciiname":"Babun Tunga",
    "gn:country_code":"NG",
    "gn:dem":485,
    "gn:feature_class":"P",
    "gn:feature_code":"PPL",
    "gn:name":"Babun Tunga",
    "gn:population":0,
    "gn:timezone":"Africa/Lagos",
    "iso:country":"NG",
    "name:und_x_variant":[
        "Babban Tunga",
        "Babun Tunga"
    ],
    "wof:name":"Babun Tunga",
    "wof:placetype":"locality"
},
  "geometry": {"coordinates":[7.21777,9.23552],"type":"Point"}
}