{
  "type": "Feature",
  "properties": {
    "gn:admin1_code":"26.0",
    "gn:admin2_code":"7021",
    "gn:asciiname":"Gberkyon",
    "gn:country_code":"NG",
    "gn:dem":140,
    "gn:feature_class":"P",
    "gn:feature_code":"PPL",
    "gn:name":"Gberkyon",
    "gn:population":0,
    "gn:timezone":"Africa/Lagos",
    "iso:country":"NG",
    "wof:name":"Gberkyon",
    "wof:placetype":"locality"
},
  "geometry": {"coordinates":[9.50961,7.69749],"type":"Point"}
}