{
  "type": "Feature",
  "properties": {
    "gn:admin1_code":"43.0",
    "gn:asciiname":"Gbugbul",
    "gn:country_code":"NG",
    "gn:dem":198,
    "gn:feature_class":"P",
    "gn:feature_code":"PPL",
    "gn:name":"Gbugbul",
    "gn:population":0,
    "gn:timezone":"Africa/Lagos",
    "iso:country":"NG",
    "name:eng_x_preferred":[
        "Gbugbul"
    ],
    "wof:name":"Gbugbul",
    "wof:placetype":"locality"
},
  "geometry": {"coordinates":[11.19611,9.421],"type":"Point"}
}