{
  "type": "Feature",
  "properties": {
    "gn:admin1_code":"46.0",
    "gn:admin2_code":"5005.0",
    "gn:admin3_code":"BA0513",
    "gn:asciiname":"Jimin",
    "gn:country_code":"NG",
    "gn:dem":415,
    "gn:feature_class":"P",
    "gn:feature_code":"PPL",
    "gn:name":"Jimin",
    "gn:population":0,
    "gn:timezone":"Africa/Lagos",
    "iso:country":"NG",
    "wof:name":"Jimin",
    "wof:placetype":"locality"
},
  "geometry": {"coordinates":[10.354,11.1524],"type":"Point"}
}