{
  "type": "Feature",
  "properties": {
    "gn:admin1_code":"26.0",
    "gn:admin2_code":"7004",
    "gn:asciiname":"Gbuusu",
    "gn:country_code":"NG",
    "gn:dem":146,
    "gn:feature_class":"P",
    "gn:feature_code":"PPL",
    "gn:name":"Gbuusu",
    "gn:population":0,
    "gn:timezone":"Africa/Lagos",
    "iso:country":"NG",
    "wof:name":"Gbuusu",
    "wof:placetype":"locality"
},
  "geometry": {"coordinates":[9.28239,7.17438],"type":"Point"}
}