{
  "type": "Feature",
  "properties": {
    "gn:admin1_code":"51.0",
    "gn:admin2_code":"610.0",
    "gn:admin3_code":"61001",
    "gn:asciiname":"Sha Aluashi",
    "gn:country_code":"NG",
    "gn:dem":192,
    "gn:feature_class":"P",
    "gn:feature_code":"PPL",
    "gn:name":"Sha Aluashi",
    "gn:population":0,
    "gn:timezone":"Africa/Lagos",
    "iso:country":"NG",
    "name:und_x_variant":[
        "Garin Magaji",
        "Sha Aluashi"
    ],
    "wof:name":"Sha Aluashi",
    "wof:placetype":"locality"
},
  "geometry": {"coordinates":[4.55911,11.6366],"type":"Point"}
}