{
  "type": "Feature",
  "properties": {
    "gn:admin1_code":"35.0",
    "gn:asciiname":"Ibarre",
    "gn:country_code":"NG",
    "gn:dem":227,
    "gn:feature_class":"P",
    "gn:feature_code":"PPL",
    "gn:name":"Ibarre",
    "gn:population":0,
    "gn:timezone":"Africa/Lagos",
    "iso:country":"NG",
    "name:eng_x_preferred":[
        "Ibarre"
    ],
    "wof:name":"Ibarre",
    "wof:placetype":"locality"
},
  "geometry": {"coordinates":[12.21291,9.05116],"type":"Point"}
}