{
  "type": "Feature",
  "properties": {
    "gn:admin1_code":"53.0",
    "gn:admin2_code":"11004",
    "gn:asciiname":"Ndiogodo",
    "gn:country_code":"NG",
    "gn:dem":100,
    "gn:feature_class":"P",
    "gn:feature_code":"PPL",
    "gn:name":"Ndiogodo",
    "gn:population":0,
    "gn:timezone":"Africa/Lagos",
    "iso:country":"NG",
    "wof:name":"Ndiogodo",
    "wof:placetype":"locality"
},
  "geometry": {"coordinates":[8.13974,6.65198],"type":"Point"}
}