{
  "type": "Feature",
  "properties": {
    "gn:admin1_code":"46.0",
    "gn:admin2_code":"5002.0",
    "gn:admin3_code":"BA0207",
    "gn:asciiname":"Birshi",
    "gn:country_code":"NG",
    "gn:dem":638,
    "gn:feature_class":"P",
    "gn:feature_code":"PPL",
    "gn:name":"Birshi",
    "gn:population":0,
    "gn:timezone":"Africa/Lagos",
    "iso:country":"NG",
    "wof:name":"Birshi",
    "wof:placetype":"locality"
},
  "geometry": {"coordinates":[9.79076,10.2345],"type":"Point"}
}