{
  "type": "Feature",
  "properties": {
    "gn:admin1_code":"50.0",
    "gn:admin2_code":"33013.0",
    "gn:asciiname":"Isioba",
    "gn:country_code":"NG",
    "gn:dem":21,
    "gn:feature_class":"P",
    "gn:feature_code":"PPL",
    "gn:name":"Isioba",
    "gn:population":0,
    "gn:timezone":"Africa/Lagos",
    "iso:country":"NG",
    "name:und_x_variant":[
        "Isoba",
        "Isaba"
    ],
    "wof:name":"Isioba",
    "wof:placetype":"locality"
},
  "geometry": {"coordinates":[6.90754,4.92023],"type":"Point"}
}