{
  "type": "Feature",
  "properties": {
    "gn:admin1_code":"35.0",
    "gn:asciiname":"Nyeberre",
    "gn:country_code":"NG",
    "gn:dem":221,
    "gn:feature_class":"P",
    "gn:feature_code":"PPL",
    "gn:name":"Nyeberre",
    "gn:population":0,
    "gn:timezone":"Africa/Lagos",
    "iso:country":"NG",
    "name:eng_x_preferred":[
        "Nyeberre"
    ],
    "wof:name":"Nyeberre",
    "wof:placetype":"locality"
},
  "geometry": {"coordinates":[12.34317,9.24507],"type":"Point"}
}