{
  "type": "Feature",
  "properties": {
    "gn:admin1_code":"35.0",
    "gn:admin2_code":"2010",
    "gn:asciiname":"Wuro Yolde",
    "gn:country_code":"NG",
    "gn:dem":528,
    "gn:feature_class":"P",
    "gn:feature_code":"PPL",
    "gn:name":"Wuro Yolde",
    "gn:population":0,
    "gn:timezone":"Africa/Lagos",
    "iso:country":"NG",
    "wof:name":"Wuro Yolde",
    "wof:placetype":"locality"
},
  "geometry": {"coordinates":[13.65341,10.86861],"type":"Point"}
}