{
  "type": "Feature",
  "properties": {
    "iso:country":"NG",
    "name:ceb_x_preferred":[
        "Yuli"
    ],
    "name:deu_x_preferred":[
        "Yuli"
    ],
    "name:fra_x_preferred":[
        "Yuli"
    ],
    "name:unk_x_variant":[
        "Anguri"
    ],
    "qs:gn_country":"NG",
    "qs:gn_fcode":"PPL",
    "qs:gn_pop":9549,
    "qs:name":"Yuli",
    "qs:name_adm0":"Nigeria",
    "qs:name_adm1":"Bauchi",
    "qs:photos":0,
    "qs:photos_1k":0,
    "qs:photos_9k":0,
    "qs:photos_9r":0,
    "qs:photos_all":0,
    "qs:photos_sr":0,
    "qs:placetype":"Town",
    "qs:pop_sr":"5",
    "qs:woe_adm0":23424908,
    "wd:wordcount":182,
    "wof:name":"Yuli",
    "wof:placetype":"locality",
    "wof:population":9549
},
  "geometry": {"coordinates":[10.27444,9.69889],"type":"Point"}
}