{
  "type": "Feature",
  "properties": {
    "gn:admin1_code":"43.0",
    "gn:admin2_code":"35003",
    "gn:asciiname":"Kalema",
    "gn:country_code":"NG",
    "gn:dem":210,
    "gn:feature_class":"P",
    "gn:feature_code":"PPL",
    "gn:name":"Kalema",
    "gn:population":0,
    "gn:timezone":"Africa/Lagos",
    "iso:country":"NG",
    "name:azb_x_preferred":[
        "\u06a9\u0627\u0644\u0645\u0627"
    ],
    "name:fas_x_preferred":[
        "\u06a9\u0627\u0644\u0645\u0627"
    ],
    "wof:name":"Kalema",
    "wof:placetype":"locality"
},
  "geometry": {"coordinates":[9.83327,7.60342],"type":"Point"}
}