{
  "type": "Feature",
  "properties": {
    "gn:admin1_code":"40.0",
    "gn:admin2_code":"516.0",
    "gn:admin3_code":"51604",
    "gn:asciiname":"Rambo",
    "gn:country_code":"NG",
    "gn:dem":387,
    "gn:feature_class":"P",
    "gn:feature_code":"PPL",
    "gn:name":"Rambo",
    "gn:population":0,
    "gn:timezone":"Africa/Lagos",
    "iso:country":"NG",
    "wof:name":"Rambo",
    "wof:placetype":"locality"
},
  "geometry": {"coordinates":[5.39884,11.34304],"type":"Point"}
}