{
  "type": "Feature",
  "properties": {
    "gn:admin1_code":"24.0",
    "gn:admin2_code":"417.0",
    "gn:admin3_code":"41701",
    "gn:asciiname":"Magaje",
    "gn:country_code":"NG",
    "gn:dem":576,
    "gn:feature_class":"P",
    "gn:feature_code":"PPL",
    "gn:name":"Magaje",
    "gn:population":0,
    "gn:timezone":"Africa/Lagos",
    "iso:country":"NG",
    "wof:name":"Magaje",
    "wof:placetype":"locality"
},
  "geometry": {"coordinates":[7.81767,11.7584],"type":"Point"}
}