{
  "type": "Feature",
  "properties": {
    "gn:admin1_code":"26.0",
    "gn:admin2_code":"7005",
    "gn:asciiname":"Tse-Tyor",
    "gn:country_code":"NG",
    "gn:dem":222,
    "gn:feature_class":"P",
    "gn:feature_code":"PPL",
    "gn:name":"Tse-Tyor",
    "gn:population":0,
    "gn:timezone":"Africa/Lagos",
    "iso:country":"NG",
    "wof:name":"Tse-Tyor",
    "wof:placetype":"locality"
},
  "geometry": {"coordinates":[8.98981,7.37126],"type":"Point"}
}