{
  "type": "Feature",
  "properties": {
    "gn:admin1_code":"23.0",
    "gn:admin2_code":"19020",
    "gn:admin3_code":"KD2002",
    "gn:asciiname":"Ambe Sarki",
    "gn:country_code":"NG",
    "gn:dem":489,
    "gn:feature_class":"P",
    "gn:feature_code":"PPL",
    "gn:name":"Ambe Sarki",
    "gn:population":0,
    "gn:timezone":"Africa/Lagos",
    "iso:country":"NG",
    "wof:name":"Ambe Sarki",
    "wof:placetype":"locality"
},
  "geometry": {"coordinates":[8.43773,9.29063],"type":"Point"}
}