{
  "type": "Feature",
  "properties": {
    "gn:admin1_code":"26.0",
    "gn:admin2_code":"7013",
    "gn:asciiname":"Penda",
    "gn:country_code":"NG",
    "gn:dem":71,
    "gn:feature_class":"P",
    "gn:feature_code":"PPL",
    "gn:name":"Penda",
    "gn:population":0,
    "gn:timezone":"Africa/Lagos",
    "iso:country":"NG",
    "wof:name":"Penda",
    "wof:placetype":"locality"
},
  "geometry": {"coordinates":[8.47576,7.71161],"type":"Point"}
}