{
  "type": "Feature",
  "properties": {
    "gn:admin1_code":"35.0",
    "gn:asciiname":"Zwangni",
    "gn:country_code":"NG",
    "gn:dem":233,
    "gn:feature_class":"P",
    "gn:feature_code":"PPL",
    "gn:name":"Zwangni",
    "gn:population":0,
    "gn:timezone":"Africa/Lagos",
    "iso:country":"NG",
    "name:eng_x_preferred":[
        "Zwangni"
    ],
    "wof:name":"Zwangni",
    "wof:placetype":"locality"
},
  "geometry": {"coordinates":[11.75292,9.30048],"type":"Point"}
}