{
  "type": "Feature",
  "properties": {
    "gn:admin1_code":"43.0",
    "gn:admin2_code":"35011.0",
    "gn:asciiname":"Dorofi",
    "gn:country_code":"NG",
    "gn:dem":1671,
    "gn:feature_class":"P",
    "gn:feature_code":"PPL",
    "gn:name":"Dorofi",
    "gn:population":0,
    "gn:timezone":"Africa/Lagos",
    "iso:country":"NG",
    "wof:name":"Dorofi",
    "wof:placetype":"locality"
},
  "geometry": {"coordinates":[11.42389,6.57483],"type":"Point"}
}