{
  "type": "Feature",
  "properties": {
    "gn:admin1_code":"35.0",
    "gn:asciiname":"Jalingo",
    "gn:country_code":"NG",
    "gn:dem":178,
    "gn:feature_class":"P",
    "gn:feature_code":"PPL",
    "gn:name":"Jalingo",
    "gn:population":0,
    "gn:timezone":"Africa/Lagos",
    "iso:country":"NG",
    "name:eng_x_preferred":[
        "Jalingo"
    ],
    "wof:name":"Jalingo",
    "wof:placetype":"locality"
},
  "geometry": {"coordinates":[12.23715,9.29508],"type":"Point"}
}