{
  "type": "Feature",
  "properties": {
    "gn:admin1_code":"21.0",
    "gn:admin2_code":"3007.0",
    "gn:asciiname":"Ikot Ibok",
    "gn:country_code":"NG",
    "gn:dem":45,
    "gn:feature_class":"P",
    "gn:feature_code":"PPL",
    "gn:name":"Ikot Ibok",
    "gn:population":0,
    "gn:timezone":"Africa/Lagos",
    "iso:country":"NG",
    "wof:name":"Ikot Ibok",
    "wof:placetype":"locality"
},
  "geometry": {"coordinates":[7.85595,4.76717],"type":"Point"}
}