{
  "type": "Feature",
  "properties": {
    "gn:admin1_code":"35.0",
    "gn:asciiname":"Mbamba",
    "gn:country_code":"NG",
    "gn:dem":199,
    "gn:feature_class":"P",
    "gn:feature_code":"PPL",
    "gn:name":"Mbamba",
    "gn:population":0,
    "gn:timezone":"Africa/Lagos",
    "iso:country":"NG",
    "name:eng_x_preferred":[
        "Mbamba"
    ],
    "wof:name":"Mbamba",
    "wof:placetype":"locality"
},
  "geometry": {"coordinates":[12.36534,9.3155],"type":"Point"}
}