{
  "type": "Feature",
  "properties": {
    "gn:admin1_code":"26.0",
    "gn:admin2_code":"7013.0",
    "gn:asciiname":"Adem",
    "gn:country_code":"NG",
    "gn:dem":88,
    "gn:feature_class":"P",
    "gn:feature_code":"PPL",
    "gn:name":"Adem",
    "gn:population":0,
    "gn:timezone":"Africa/Lagos",
    "iso:country":"NG",
    "name:ara_x_preferred":[
        "\u0622\u062f\u0645"
    ],
    "name:deu_x_preferred":[
        "Adem"
    ],
    "name:hun_x_preferred":[
        "Adem"
    ],
    "name:nor_x_preferred":[
        "Adem"
    ],
    "name:pol_x_preferred":[
        "Adem"
    ],
    "name:slv_x_preferred":[
        "Adem"
    ],
    "name:swe_x_preferred":[
        "Adem"
    ],
    "name:tur_x_preferred":[
        "Adem"
    ],
    "wof:name":"Adem",
    "wof:placetype":"locality"
},
  "geometry": {"coordinates":[8.47566,7.66311],"type":"Point"}
}