{
  "type": "Feature",
  "properties": {
    "gn:admin1_code":"44.0",
    "gn:admin2_code":"704.0",
    "gn:admin3_code":"70407",
    "gn:asciiname":"Dumbulwa",
    "gn:country_code":"NG",
    "gn:dem":297,
    "gn:feature_class":"P",
    "gn:feature_code":"PPL",
    "gn:name":"Dumbulwa",
    "gn:population":0,
    "gn:timezone":"Africa/Lagos",
    "iso:country":"NG",
    "wof:name":"Dumbulwa",
    "wof:placetype":"locality"
},
  "geometry": {"coordinates":[11.47781,11.12458],"type":"Point"}
}