{
  "type": "Feature",
  "properties": {
    "gn:admin1_code":"51.0",
    "gn:admin2_code":"608.0",
    "gn:admin3_code":"60811",
    "gn:asciiname":"Dantule",
    "gn:country_code":"NG",
    "gn:dem":319,
    "gn:feature_class":"P",
    "gn:feature_code":"PPL",
    "gn:name":"Dantule",
    "gn:population":0,
    "gn:timezone":"Africa/Lagos",
    "iso:country":"NG",
    "wof:name":"Dantule",
    "wof:placetype":"locality"
},
  "geometry": {"coordinates":[5.45625,13.51276],"type":"Point"}
}