{
  "type": "Feature",
  "properties": {
    "gn:admin1_code":"21.0",
    "gn:admin2_code":"3003.0",
    "gn:asciiname":"Afaha Atai",
    "gn:country_code":"NG",
    "gn:dem":21,
    "gn:feature_class":"P",
    "gn:feature_code":"PPL",
    "gn:name":"Afaha Atai",
    "gn:population":0,
    "gn:timezone":"Africa/Lagos",
    "iso:country":"NG",
    "wof:name":"Afaha Atai",
    "wof:placetype":"locality"
},
  "geometry": {"coordinates":[7.96889,4.64009],"type":"Point"}
}