{
  "type": "Feature",
  "properties": {
    "gn:admin1_code":"50.0",
    "gn:asciiname":"Ofonibagha",
    "gn:country_code":"NG",
    "gn:dem":26,
    "gn:feature_class":"P",
    "gn:feature_code":"PPL",
    "gn:name":"Ofonibagha",
    "gn:population":0,
    "gn:timezone":"Africa/Lagos",
    "iso:country":"NG",
    "wof:name":"Ofonibagha",
    "wof:placetype":"locality"
},
  "geometry": {"coordinates":[6.48115,5.31146],"type":"Point"}
}