{
  "type": "Feature",
  "properties": {
    "gn:admin1_code":"16.0",
    "gn:admin2_code":"28016.0",
    "gn:asciiname":"Ile Olu",
    "gn:country_code":"NG",
    "gn:dem":166,
    "gn:feature_class":"P",
    "gn:feature_code":"PPL",
    "gn:name":"Ile Olu",
    "gn:population":0,
    "gn:timezone":"Africa/Lagos",
    "iso:country":"NG",
    "wof:name":"Ile Olu",
    "wof:placetype":"locality"
},
  "geometry": {"coordinates":[3.63333,7.25],"type":"Point"}
}