{
  "type": "Feature",
  "properties": {
    "gn:admin1_code":"40.0",
    "gn:admin2_code":"511.0",
    "gn:admin3_code":"51104",
    "gn:asciiname":"Galbi",
    "gn:country_code":"NG",
    "gn:dem":239,
    "gn:feature_class":"P",
    "gn:feature_code":"PPL",
    "gn:name":"Galbi",
    "gn:population":0,
    "gn:timezone":"Africa/Lagos",
    "iso:country":"NG",
    "name:ara_x_preferred":[
        "\u063a\u0627\u0644\u0628\u064a"
    ],
    "name:deu_x_preferred":[
        "Galbi"
    ],
    "name:fra_x_preferred":[
        "Galbi"
    ],
    "name:glg_x_preferred":[
        "Galbi"
    ],
    "name:hun_x_preferred":[
        "Kalbi"
    ],
    "name:hye_x_preferred":[
        "\u053f\u0561\u056c\u0562\u056b"
    ],
    "name:ind_x_preferred":[
        "Galbi"
    ],
    "name:ita_x_preferred":[
        "Galbi"
    ],
    "name:jpn_x_preferred":[
        "\u30ab\u30eb\u30d3"
    ],
    "name:kor_x_preferred":[
        "\uac08\ube44\uad6c\uc774"
    ],
    "name:msa_x_preferred":[
        "Galbi"
    ],
    "name:nld_x_preferred":[
        "Galbi"
    ],
    "name:por_x_preferred":[
        "Galbi"
    ],
    "name:rus_x_preferred":[
        "\u041a\u0430\u043b\u044c\u0431\u0438"
    ],
    "name:spa_x_preferred":[
        "Galbi"
    ],
    "name:swe_x_preferred":[
        "Kalbi"
    ],
    "name:tgl_x_preferred":[
        "Galbi"
    ],
    "name:tha_x_preferred":[
        "\u0e04\u0e31\u0e25\u0e1a\u0e35"
    ],
    "name:tur_x_preferred":[
        "Galbi"
    ],
    "name:ukr_x_preferred":[
        "\u041a\u0430\u043b\u044c\u0431\u0456"
    ],
    "name:vie_x_preferred":[
        "Kalbi"
    ],
    "name:zho_x_preferred":[
        "\u671d\u9bae\u70e4\u725b\u6392"
    ],
    "wof:name":"Galbi",
    "wof:placetype":"locality"
},
  "geometry": {"coordinates":[4.31893,12.23536],"type":"Point"}
}