{
  "type": "Feature",
  "properties": {
    "gn:admin1_code":"21.0",
    "gn:admin2_code":"3026.0",
    "gn:asciiname":"Ibesit",
    "gn:country_code":"NG",
    "gn:dem":54,
    "gn:feature_class":"P",
    "gn:feature_code":"PPL",
    "gn:name":"Ibesit",
    "gn:population":0,
    "gn:timezone":"Africa/Lagos",
    "iso:country":"NG",
    "wof:name":"Ibesit",
    "wof:placetype":"locality"
},
  "geometry": {"coordinates":[7.78454,4.95718],"type":"Point"}
}