{
  "type": "Feature",
  "properties": {
    "gn:admin1_code":"56.0",
    "gn:admin2_code":"26005.0",
    "gn:asciiname":"Keana",
    "gn:country_code":"NG",
    "gn:dem":129,
    "gn:feature_class":"P",
    "gn:feature_code":"PPLA2",
    "gn:name":"Keana",
    "gn:population":0,
    "gn:timezone":"Africa/Lagos",
    "iso:country":"NG",
    "name:fra_x_preferred":[
        "Keana"
    ],
    "name:hau_x_preferred":[
        "Keana"
    ],
    "name:ita_x_preferred":[
        "Keana"
    ],
    "name:por_x_preferred":[
        "Queana"
    ],
    "name:spa_x_preferred":[
        "Keana"
    ],
    "wof:name":"Keana",
    "wof:placetype":"locality"
},
  "geometry": {"coordinates":[8.79601,8.14724],"type":"Point"}
}