{
  "type": "Feature",
  "properties": {
    "gn:admin1_code":"24.0",
    "gn:admin2_code":"430.0",
    "gn:admin3_code":"43002",
    "gn:asciiname":"Gunki",
    "gn:country_code":"NG",
    "gn:dem":496,
    "gn:feature_class":"P",
    "gn:feature_code":"PPL",
    "gn:name":"Gunki",
    "gn:population":0,
    "gn:timezone":"Africa/Lagos",
    "iso:country":"NG",
    "wof:name":"Gunki",
    "wof:placetype":"locality"
},
  "geometry": {"coordinates":[7.72747,12.89188],"type":"Point"}
}