{
  "type": "Feature",
  "properties": {
    "gn:admin1_code":"43.0",
    "gn:admin2_code":"35015",
    "gn:asciiname":"Gonta",
    "gn:country_code":"NG",
    "gn:dem":242,
    "gn:feature_class":"P",
    "gn:feature_code":"PPL",
    "gn:name":"Gonta",
    "gn:population":0,
    "gn:timezone":"Africa/Lagos",
    "iso:country":"NG",
    "wof:name":"Gonta",
    "wof:placetype":"locality"
},
  "geometry": {"coordinates":[11.49402,8.78622],"type":"Point"}
}