{
  "type": "Feature",
  "properties": {
    "gn:admin1_code":"26.0",
    "gn:admin2_code":"7005",
    "gn:asciiname":"Iornongu",
    "gn:country_code":"NG",
    "gn:dem":193,
    "gn:feature_class":"P",
    "gn:feature_code":"PPL",
    "gn:name":"Iornongu",
    "gn:population":0,
    "gn:timezone":"Africa/Lagos",
    "iso:country":"NG",
    "wof:name":"Iornongu",
    "wof:placetype":"locality"
},
  "geometry": {"coordinates":[8.95341,7.38009],"type":"Point"}
}