{
  "type": "Feature",
  "properties": {
    "gn:admin1_code":"57.0",
    "gn:admin2_code":"807.0",
    "gn:admin3_code":"80710",
    "gn:asciiname":"Jira",
    "gn:country_code":"NG",
    "gn:dem":501,
    "gn:feature_class":"P",
    "gn:feature_code":"PPL",
    "gn:name":"Jira",
    "gn:population":0,
    "gn:timezone":"Africa/Lagos",
    "iso:country":"NG",
    "name:ces_x_preferred":[
        "J\u00edra"
    ],
    "name:deu_x_preferred":[
        "Jira"
    ],
    "name:pol_x_preferred":[
        "Jira"
    ],
    "wof:name":"Jira",
    "wof:placetype":"locality"
},
  "geometry": {"coordinates":[6.69372,12.0016],"type":"Point"}
}