{
  "type": "Feature",
  "properties": {
    "gn:admin1_code":"31.0",
    "gn:admin2_code":"27008.0",
    "gn:asciiname":"Jima",
    "gn:country_code":"NG",
    "gn:dem":155,
    "gn:feature_class":"P",
    "gn:feature_code":"PPL",
    "gn:name":"Jima",
    "gn:population":0,
    "gn:timezone":"Africa/Lagos",
    "iso:country":"NG",
    "wof:name":"Jima",
    "wof:placetype":"locality"
},
  "geometry": {"coordinates":[5.86667,9.05],"type":"Point"}
}