{
  "type": "Feature",
  "properties": {
    "gn:admin1_code":"24.0",
    "gn:admin2_code":"427.0",
    "gn:admin3_code":"42701",
    "gn:asciiname":"Kuka",
    "gn:country_code":"NG",
    "gn:dem":445,
    "gn:feature_class":"P",
    "gn:feature_code":"PPL",
    "gn:name":"Kuka",
    "gn:population":0,
    "gn:timezone":"Africa/Lagos",
    "iso:country":"NG",
    "name:bos_x_preferred":[
        "Kuka"
    ],
    "name:bul_x_preferred":[
        "\u041a\u0443\u043a\u0430"
    ],
    "name:ceb_x_preferred":[
        "Kuka"
    ],
    "name:ces_x_preferred":[
        "Kuka"
    ],
    "name:deu_x_preferred":[
        "Kuka"
    ],
    "name:fra_x_preferred":[
        "Kuka"
    ],
    "name:hrv_x_preferred":[
        "Kuka"
    ],
    "name:hun_x_preferred":[
        "Kuka"
    ],
    "name:hye_x_preferred":[
        "\u053f\u0578\u0582\u056f\u0561"
    ],
    "name:rus_x_preferred":[
        "\u041a\u0443\u043a\u0430"
    ],
    "name:srp_x_preferred":[
        "\u041a\u0443\u043a\u0430"
    ],
    "name:swe_x_preferred":[
        "Kuka"
    ],
    "name:ukr_x_preferred":[
        "\u041a\u0443\u043a\u0430"
    ],
    "name:und_x_variant":[
        "Birnin Kuka",
        "Birnikuka",
        "Kuka"
    ],
    "wof:name":"Kuka",
    "wof:placetype":"locality"
},
  "geometry": {"coordinates":[7.98036,13.31785],"type":"Point"}
}