{
  "type": "Feature",
  "properties": {
    "gn:admin1_code":"39.0",
    "gn:admin2_code":"18015.0",
    "gn:admin3_code":"JI2404",
    "gn:asciiname":"Baragumi",
    "gn:country_code":"NG",
    "gn:dem":498,
    "gn:feature_class":"P",
    "gn:feature_code":"PPL",
    "gn:name":"Baragumi",
    "gn:population":0,
    "gn:timezone":"Africa/Lagos",
    "iso:country":"NG",
    "wof:name":"Baragumi",
    "wof:placetype":"locality"
},
  "geometry": {"coordinates":[8.2646,12.61888],"type":"Point"}
}