{
  "type": "Feature",
  "properties": {
    "gn:admin1_code":"26.0",
    "gn:admin2_code":"7005.0",
    "gn:asciiname":"Shaage",
    "gn:country_code":"NG",
    "gn:dem":115,
    "gn:feature_class":"P",
    "gn:feature_code":"PPL",
    "gn:name":"Shaage",
    "gn:population":0,
    "gn:timezone":"Africa/Lagos",
    "iso:country":"NG",
    "wof:name":"Shaage",
    "wof:placetype":"locality"
},
  "geometry": {"coordinates":[8.7463,7.40983],"type":"Point"}
}