{
  "type": "Feature",
  "properties": {
    "gn:admin1_code":"52.0",
    "gn:asciiname":"Akpan Camp",
    "gn:country_code":"NG",
    "gn:dem":11,
    "gn:feature_class":"P",
    "gn:feature_code":"PPL",
    "gn:name":"Akpan Camp",
    "gn:population":0,
    "gn:timezone":"Africa/Lagos",
    "iso:country":"NG",
    "name:eng_x_preferred":[
        "Akpan Camp"
    ],
    "wof:name":"Akpan Camp",
    "wof:placetype":"locality"
},
  "geometry": {"coordinates":[5.64517,4.96522],"type":"Point"}
}