{
  "type": "Feature",
  "properties": {
    "gn:admin1_code":"21.0",
    "gn:admin2_code":"3016.0",
    "gn:asciiname":"Ikot Andem Itam",
    "gn:country_code":"NG",
    "gn:dem":102,
    "gn:feature_class":"P",
    "gn:feature_code":"PPL",
    "gn:name":"Ikot Andem Itam",
    "gn:population":0,
    "gn:timezone":"Africa/Lagos",
    "iso:country":"NG",
    "name:und_x_variant":[
        "Ikot Andem",
        "Ikot Andem Itam"
    ],
    "wof:name":"Ikot Andem Itam",
    "wof:placetype":"locality"
},
  "geometry": {"coordinates":[7.95463,5.14443],"type":"Point"}
}