{
  "type": "Feature",
  "properties": {
    "gn:admin1_code":"23.0",
    "gn:admin2_code":"19014.0",
    "gn:admin3_code":"KD1402",
    "gn:asciiname":"Kinono",
    "gn:country_code":"NG",
    "gn:dem":768,
    "gn:feature_class":"P",
    "gn:feature_code":"PPL",
    "gn:name":"Kinono",
    "gn:population":0,
    "gn:timezone":"Africa/Lagos",
    "iso:country":"NG",
    "name:und_x_variant":[
        "Kinona",
        "Kinono"
    ],
    "wof:name":"Kinono",
    "wof:placetype":"locality"
},
  "geometry": {"coordinates":[8.2653,10.23729],"type":"Point"}
}