{
  "type": "Feature",
  "properties": {
    "gn:admin1_code":"37.0",
    "gn:admin2_code":"12018",
    "gn:asciiname":"Odukhuo",
    "gn:country_code":"NG",
    "gn:dem":280,
    "gn:feature_class":"P",
    "gn:feature_code":"PPL",
    "gn:name":"Odukhuo",
    "gn:population":0,
    "gn:timezone":"Africa/Lagos",
    "iso:country":"NG",
    "wof:name":"Odukhuo",
    "wof:placetype":"locality"
},
  "geometry": {"coordinates":[6.0848,6.65496],"type":"Point"}
}