{
  "type": "Feature",
  "properties": {
    "gn:admin1_code":"43.0",
    "gn:admin2_code":"35007",
    "gn:asciiname":"Hamakado",
    "gn:country_code":"NG",
    "gn:dem":217,
    "gn:feature_class":"P",
    "gn:feature_code":"PPL",
    "gn:name":"Hamakado",
    "gn:population":0,
    "gn:timezone":"Africa/Lagos",
    "iso:country":"NG",
    "wof:name":"Hamakado",
    "wof:placetype":"locality"
},
  "geometry": {"coordinates":[11.40105,8.83886],"type":"Point"}
}