{
  "type": "Feature",
  "properties": {
    "gn:admin1_code":"27.0",
    "gn:admin2_code":"115.0",
    "gn:admin3_code":"11503",
    "gn:asciiname":"Abudeya",
    "gn:country_code":"NG",
    "gn:dem":297,
    "gn:feature_class":"P",
    "gn:feature_code":"PPL",
    "gn:name":"Abudeya",
    "gn:population":0,
    "gn:timezone":"Africa/Lagos",
    "iso:country":"NG",
    "wof:name":"Abudeya",
    "wof:placetype":"locality"
},
  "geometry": {"coordinates":[14.35743,11.85248],"type":"Point"}
}