{
  "type": "Feature",
  "properties": {
    "gn:admin1_code":"27.0",
    "gn:admin2_code":"121.0",
    "gn:admin3_code":"12101",
    "gn:asciiname":"Kaga",
    "gn:country_code":"NG",
    "gn:dem":296,
    "gn:feature_class":"P",
    "gn:feature_code":"PPL",
    "gn:name":"Kaga",
    "gn:population":0,
    "gn:timezone":"Africa/Lagos",
    "iso:country":"NG",
    "wof:name":"Kaga",
    "wof:placetype":"locality"
},
  "geometry": {"coordinates":[13.91072,12.15085],"type":"Point"}
}