{
  "type": "Feature",
  "properties": {
    "gn:admin1_code":"26.0",
    "gn:admin2_code":"7007",
    "gn:asciiname":"Ibi",
    "gn:country_code":"NG",
    "gn:dem":181,
    "gn:feature_class":"P",
    "gn:feature_code":"PPL",
    "gn:name":"Ibi",
    "gn:population":0,
    "gn:timezone":"Africa/Lagos",
    "iso:country":"NG",
    "name:ceb_x_preferred":[
        "Ibi"
    ],
    "name:eus_x_preferred":[
        "Ibi"
    ],
    "name:fra_x_preferred":[
        "Ibi"
    ],
    "name:hun_x_preferred":[
        "Ibi"
    ],
    "name:mlg_x_preferred":[
        "Ibi"
    ],
    "name:por_x_preferred":[
        "Ibi"
    ],
    "name:spa_x_preferred":[
        "Ibi"
    ],
    "name:swe_x_preferred":[
        "Ibi"
    ],
    "wof:name":"Ibi",
    "wof:placetype":"locality"
},
  "geometry": {"coordinates":[8.48708,7.31922],"type":"Point"}
}