{
  "type": "Feature",
  "properties": {
    "gn:admin1_code":"29.0",
    "gn:admin2_code":"20004.0",
    "gn:admin3_code":"KN0103",
    "gn:asciiname":"Yankinta",
    "gn:country_code":"NG",
    "gn:dem":411,
    "gn:feature_class":"P",
    "gn:feature_code":"PPL",
    "gn:name":"Yankinta",
    "gn:population":0,
    "gn:timezone":"Africa/Lagos",
    "iso:country":"NG",
    "wof:name":"Yankinta",
    "wof:placetype":"locality"
},
  "geometry": {"coordinates":[8.97012,12.01789],"type":"Point"}
}