{
  "type": "Feature",
  "properties": {
    "gn:admin1_code":"26.0",
    "gn:admin2_code":"7006.0",
    "gn:asciiname":"Bende",
    "gn:country_code":"NG",
    "gn:dem":125,
    "gn:feature_class":"P",
    "gn:feature_code":"PPL",
    "gn:name":"Bende",
    "gn:population":0,
    "gn:timezone":"Africa/Lagos",
    "iso:country":"NG",
    "name:ceb_x_preferred":[
        "Bende"
    ],
    "name:deu_x_preferred":[
        "Bende"
    ],
    "name:fra_x_preferred":[
        "Bende"
    ],
    "name:ita_x_preferred":[
        "Bende"
    ],
    "name:nld_x_preferred":[
        "Bende"
    ],
    "name:swe_x_preferred":[
        "Bende"
    ],
    "wof:name":"Bende",
    "wof:placetype":"locality"
},
  "geometry": {"coordinates":[8.6319,7.84114],"type":"Point"}
}