{
  "type": "Feature",
  "properties": {
    "gn:admin1_code":"24.0",
    "gn:admin2_code":"417.0",
    "gn:admin3_code":"41702",
    "gn:asciiname":"Bori",
    "gn:country_code":"NG",
    "gn:dem":628,
    "gn:feature_class":"P",
    "gn:feature_code":"PPL",
    "gn:name":"Bori",
    "gn:population":0,
    "gn:timezone":"Africa/Lagos",
    "iso:country":"NG",
    "name:ceb_x_preferred":[
        "Bori"
    ],
    "name:deu_x_preferred":[
        "Bori"
    ],
    "name:fra_x_preferred":[
        "Bori"
    ],
    "name:hun_x_preferred":[
        "Bori"
    ],
    "name:ita_x_preferred":[
        "Bori"
    ],
    "name:kor_x_preferred":[
        "\ubcf4\ub9ac"
    ],
    "name:por_x_preferred":[
        "Bori"
    ],
    "name:swe_x_preferred":[
        "Bori"
    ],
    "name:vie_x_preferred":[
        "Bori"
    ],
    "wof:name":"Bori",
    "wof:placetype":"locality"
},
  "geometry": {"coordinates":[7.58868,11.51584],"type":"Point"}
}