{
  "type": "Feature",
  "properties": {
    "gn:admin1_code":"50.0",
    "gn:admin2_code":"33010.0",
    "gn:asciiname":"Obele Gorri",
    "gn:country_code":"NG",
    "gn:dem":11,
    "gn:feature_class":"P",
    "gn:feature_code":"PPL",
    "gn:name":"Obele Gorri",
    "gn:population":0,
    "gn:timezone":"Africa/Lagos",
    "iso:country":"NG",
    "name:und_x_variant":[
        "Obele Garric"
    ],
    "wof:name":"Obele Gorri",
    "wof:placetype":"locality"
},
  "geometry": {"coordinates":[6.68809,4.95838],"type":"Point"}
}