{
  "type": "Feature",
  "properties": {
    "gn:admin1_code":"30.0",
    "gn:admin2_code":"24011.0",
    "gn:asciiname":"Kimodo",
    "gn:country_code":"NG",
    "gn:dem":349,
    "gn:feature_class":"P",
    "gn:feature_code":"PPL",
    "gn:name":"Kimodo",
    "gn:population":0,
    "gn:timezone":"Africa/Lagos",
    "iso:country":"NG",
    "wof:name":"Kimodo",
    "wof:placetype":"locality"
},
  "geometry": {"coordinates":[3.91667,9.66667],"type":"Point"}
}