{
  "type": "Feature",
  "properties": {
    "gn:admin1_code":"46.0",
    "gn:admin2_code":"5008.0",
    "gn:admin3_code":"BA0807",
    "gn:asciiname":"Laguru",
    "gn:country_code":"NG",
    "gn:dem":514,
    "gn:feature_class":"P",
    "gn:feature_code":"PPL",
    "gn:name":"Laguru",
    "gn:population":0,
    "gn:timezone":"Africa/Lagos",
    "iso:country":"NG",
    "name:eng_x_preferred":[
        "Laguru"
    ],
    "wof:name":"Laguru",
    "wof:placetype":"locality"
},
  "geometry": {"coordinates":[10.03448,10.91244],"type":"Point"}
}