{
  "type": "Feature",
  "properties": {
    "gn:admin1_code":"51.0",
    "gn:admin2_code":"604.0",
    "gn:admin3_code":"60405",
    "gn:asciiname":"Kafa",
    "gn:country_code":"NG",
    "gn:dem":300,
    "gn:feature_class":"P",
    "gn:feature_code":"PPL",
    "gn:name":"Kafa",
    "gn:population":0,
    "gn:timezone":"Africa/Lagos",
    "iso:country":"NG",
    "name:cat_x_preferred":[
        "Kafa"
    ],
    "name:ceb_x_preferred":[
        "Kafa"
    ],
    "name:swe_x_preferred":[
        "Kafa"
    ],
    "name:tur_x_preferred":[
        "Kafa"
    ],
    "name:und_x_variant":[
        "Koffe",
        "Kafe",
        "Kafi",
        "Kafa"
    ],
    "wof:name":"Kafa",
    "wof:placetype":"locality"
},
  "geometry": {"coordinates":[5.72528,13.68644],"type":"Point"}
}