{
  "type": "Feature",
  "properties": {
    "gn:admin1_code":"5.0",
    "gn:admin2_code":"25012.0",
    "gn:asciiname":"Igbore",
    "gn:country_code":"NG",
    "gn:dem":9,
    "gn:feature_class":"P",
    "gn:feature_code":"PPL",
    "gn:name":"Igbore",
    "gn:population":0,
    "gn:timezone":"Africa/Lagos",
    "iso:country":"NG",
    "wof:name":"Igbore",
    "wof:placetype":"locality"
},
  "geometry": {"coordinates":[3.54106,6.55368],"type":"Point"}
}