{
  "type": "Feature",
  "properties": {
    "gn:admin1_code":"21.0",
    "gn:admin2_code":"3022.0",
    "gn:asciiname":"Ikwen",
    "gn:country_code":"NG",
    "gn:dem":117,
    "gn:feature_class":"P",
    "gn:feature_code":"PPL",
    "gn:name":"Ikwen",
    "gn:population":0,
    "gn:timezone":"Africa/Lagos",
    "iso:country":"NG",
    "wof:name":"Ikwen",
    "wof:placetype":"locality"
},
  "geometry": {"coordinates":[7.62879,5.28545],"type":"Point"}
}