{
  "type": "Feature",
  "properties": {
    "gn:admin1_code":"21.0",
    "gn:admin2_code":"3030",
    "gn:asciiname":"Urue Offong",
    "gn:country_code":"NG",
    "gn:dem":39,
    "gn:feature_class":"P",
    "gn:feature_code":"PPLA2",
    "gn:name":"Urue Offong",
    "gn:population":0,
    "gn:timezone":"Africa/Lagos",
    "iso:country":"NG",
    "name:und_x_variant":[
        "Udua Offong"
    ],
    "wof:name":"Urue Offong",
    "wof:placetype":"locality"
},
  "geometry": {"coordinates":[8.1677,4.75275],"type":"Point"}
}