{
  "type": "Feature",
  "properties": {
    "gn:admin1_code":"26.0",
    "gn:admin2_code":"7004",
    "gn:asciiname":"Labe",
    "gn:country_code":"NG",
    "gn:dem":150,
    "gn:feature_class":"P",
    "gn:feature_code":"PPL",
    "gn:name":"Labe",
    "gn:population":0,
    "gn:timezone":"Africa/Lagos",
    "iso:country":"NG",
    "name:ceb_x_preferred":[
        "Labe"
    ],
    "name:lit_x_preferred":[
        "Lab\u0117"
    ],
    "name:nld_x_preferred":[
        "Labe"
    ],
    "name:pol_x_preferred":[
        "Lab"
    ],
    "name:swe_x_preferred":[
        "Labe"
    ],
    "wof:name":"Labe",
    "wof:placetype":"locality"
},
  "geometry": {"coordinates":[9.17271,7.45137],"type":"Point"}
}