{
  "type": "Feature",
  "properties": {
    "gn:admin1_code":"23.0",
    "gn:admin2_code":"19022",
    "gn:admin3_code":"KD2207",
    "gn:asciiname":"Afana Kaje",
    "gn:country_code":"NG",
    "gn:dem":717,
    "gn:feature_class":"P",
    "gn:feature_code":"PPL",
    "gn:name":"Afana Kaje",
    "gn:population":0,
    "gn:timezone":"Africa/Lagos",
    "iso:country":"NG",
    "wof:name":"Afana Kaje",
    "wof:placetype":"locality"
},
  "geometry": {"coordinates":[8.21651,9.54439],"type":"Point"}
}