{
  "type": "Feature",
  "properties": {
    "gn:admin1_code":"25.0",
    "gn:admin2_code":"4002.0",
    "gn:asciiname":"Umuawor-Nando",
    "gn:country_code":"NG",
    "gn:dem":83,
    "gn:feature_class":"P",
    "gn:feature_code":"PPL",
    "gn:name":"Umuawor-Nando",
    "gn:population":0,
    "gn:timezone":"Africa/Lagos",
    "iso:country":"NG",
    "name:eng_x_preferred":[
        "Umuawor-Nando"
    ],
    "wof:name":"Umuawor-Nando",
    "wof:placetype":"locality"
},
  "geometry": {"coordinates":[6.93754,6.30911],"type":"Point"}
}