{
  "type": "Feature",
  "properties": {
    "gn:admin1_code":"53.0",
    "gn:admin2_code":"11010.0",
    "gn:asciiname":"Ijibollor",
    "gn:country_code":"NG",
    "gn:dem":38,
    "gn:feature_class":"P",
    "gn:feature_code":"PPL",
    "gn:name":"Ijibollor",
    "gn:population":0,
    "gn:timezone":"Africa/Lagos",
    "iso:country":"NG",
    "name:und_x_variant":[
        "Ijibollo"
    ],
    "wof:name":"Ijibollor",
    "wof:placetype":"locality"
},
  "geometry": {"coordinates":[8.42652,6.40742],"type":"Point"}
}