{
  "type": "Feature",
  "properties": {
    "gn:admin1_code":"37.0",
    "gn:admin2_code":"12018.0",
    "gn:asciiname":"Egua-Eholor",
    "gn:country_code":"NG",
    "gn:dem":194,
    "gn:feature_class":"P",
    "gn:feature_code":"PPL",
    "gn:name":"Egua-Eholor",
    "gn:population":0,
    "gn:timezone":"Africa/Lagos",
    "iso:country":"NG",
    "name:eng_x_preferred":[
        "Egua-Eholor"
    ],
    "name:eng_x_variant":[
        "Egua Holor"
    ],
    "wof:name":"Egua-Eholor",
    "wof:placetype":"locality"
},
  "geometry": {"coordinates":[6.03044,6.42373],"type":"Point"}
}