{
  "type": "Feature",
  "properties": {
    "gn:admin1_code":"43.0",
    "gn:admin2_code":"35011.0",
    "gn:asciiname":"Inkiri",
    "gn:country_code":"NG",
    "gn:dem":1207,
    "gn:feature_class":"P",
    "gn:feature_code":"PPL",
    "gn:name":"Inkiri",
    "gn:population":0,
    "gn:timezone":"Africa/Lagos",
    "iso:country":"NG",
    "wof:name":"Inkiri",
    "wof:placetype":"locality"
},
  "geometry": {"coordinates":[10.98333,6.78333],"type":"Point"}
}