{
  "type": "Feature",
  "properties": {
    "gn:admin1_code":"47.0",
    "gn:admin2_code":"14013.0",
    "gn:asciiname":"Eha-Alumona",
    "gn:country_code":"NG",
    "gn:dem":518,
    "gn:feature_class":"P",
    "gn:feature_code":"PPL",
    "gn:name":"Eha-Alumona",
    "gn:population":0,
    "gn:timezone":"Africa/Lagos",
    "iso:country":"NG",
    "wof:name":"Eha-Alumona",
    "wof:placetype":"locality"
},
  "geometry": {"coordinates":[7.4531,6.82268],"type":"Point"}
}