{
  "type": "Feature",
  "properties": {
    "gn:admin1_code":"36.0",
    "gn:admin2_code":"10006.0",
    "gn:asciiname":"Akpobome",
    "gn:country_code":"NG",
    "gn:dem":11,
    "gn:feature_class":"P",
    "gn:feature_code":"PPL",
    "gn:name":"Akpobome",
    "gn:population":0,
    "gn:timezone":"Africa/Lagos",
    "iso:country":"NG",
    "name:eng_x_preferred":[
        "Akpobome"
    ],
    "wof:name":"Akpobome",
    "wof:placetype":"locality"
},
  "geometry": {"coordinates":[5.72908,5.87608],"type":"Point"}
}