{
  "type": "Feature",
  "properties": {
    "gn:admin1_code":"56.0",
    "gn:admin2_code":"26003",
    "gn:asciiname":"Ihase",
    "gn:country_code":"NG",
    "gn:dem":86,
    "gn:feature_class":"P",
    "gn:feature_code":"PPL",
    "gn:name":"Ihase",
    "gn:population":0,
    "gn:timezone":"Africa/Lagos",
    "iso:country":"NG",
    "wof:name":"Ihase",
    "wof:placetype":"locality"
},
  "geometry": {"coordinates":[8.29933,7.93469],"type":"Point"}
}