{
  "type": "Feature",
  "properties": {
    "gn:admin1_code":"23.0",
    "gn:admin2_code":"19023.0",
    "gn:admin3_code":"KD2301",
    "gn:asciiname":"Kako",
    "gn:country_code":"NG",
    "gn:dem":627,
    "gn:feature_class":"P",
    "gn:feature_code":"PPL",
    "gn:name":"Kako",
    "gn:population":0,
    "gn:timezone":"Africa/Lagos",
    "iso:country":"NG",
    "name:ceb_x_preferred":[
        "Kako"
    ],
    "name:deu_x_preferred":[
        "Kako"
    ],
    "name:epo_x_preferred":[
        "Kako"
    ],
    "name:est_x_preferred":[
        "Kako"
    ],
    "name:fra_x_preferred":[
        "Kako"
    ],
    "name:ita_x_preferred":[
        "Kako"
    ],
    "name:spa_x_preferred":[
        "Kako"
    ],
    "name:swe_x_preferred":[
        "Kako"
    ],
    "wof:name":"Kako",
    "wof:placetype":"locality"
},
  "geometry": {"coordinates":[7.7406,10.96767],"type":"Point"}
}