{
  "type": "Feature",
  "properties": {
    "gn:admin1_code":"45.0",
    "gn:admin2_code":"1006.0",
    "gn:asciiname":"Umu Akwa",
    "gn:country_code":"NG",
    "gn:dem":107,
    "gn:feature_class":"P",
    "gn:feature_code":"PPL",
    "gn:name":"Umu Akwa",
    "gn:population":0,
    "gn:timezone":"Africa/Lagos",
    "iso:country":"NG",
    "wof:name":"Umu Akwa",
    "wof:placetype":"locality"
},
  "geometry": {"coordinates":[7.39021,5.28828],"type":"Point"}
}