{
  "type": "Feature",
  "properties": {
    "gn:admin1_code":"44.0",
    "gn:admin2_code":"705.0",
    "gn:admin3_code":"70505",
    "gn:asciiname":"Dira",
    "gn:country_code":"NG",
    "gn:dem":431,
    "gn:feature_class":"P",
    "gn:feature_code":"PPL",
    "gn:name":"Dira",
    "gn:population":0,
    "gn:timezone":"Africa/Lagos",
    "iso:country":"NG",
    "name:azb_x_preferred":[
        "\u062f\u06cc\u0631\u0627"
    ],
    "name:ceb_x_preferred":[
        "Dira"
    ],
    "name:fas_x_preferred":[
        "\u062f\u06cc\u0631\u0627"
    ],
    "name:fra_x_preferred":[
        "Dira"
    ],
    "name:lat_x_preferred":[
        "Dira"
    ],
    "name:swe_x_preferred":[
        "Dira"
    ],
    "wof:name":"Dira",
    "wof:placetype":"locality"
},
  "geometry": {"coordinates":[11.32157,11.61389],"type":"Point"}
}