{
  "type": "Feature",
  "properties": {
    "gn:admin1_code":"43.0",
    "gn:admin2_code":"35004.0",
    "gn:asciiname":"Baruwa",
    "gn:country_code":"NG",
    "gn:dem":431,
    "gn:feature_class":"P",
    "gn:feature_code":"PPL",
    "gn:name":"Baruwa",
    "gn:population":0,
    "gn:timezone":"Africa/Lagos",
    "iso:country":"NG",
    "name:ceb_x_preferred":[
        "Baruwa"
    ],
    "name:deu_x_preferred":[
        "Baruwa"
    ],
    "name:fra_x_preferred":[
        "Baruwa"
    ],
    "name:msa_x_preferred":[
        "Baruwa"
    ],
    "name:nep_x_preferred":[
        "\u092c\u0930\u0941\u0935\u093e"
    ],
    "name:pol_x_preferred":[
        "Baruwa"
    ],
    "wof:name":"Baruwa",
    "wof:placetype":"locality"
},
  "geometry": {"coordinates":[11.46667,7.35],"type":"Point"}
}