{
  "type": "Feature",
  "properties": {
    "gn:admin1_code":"21.0",
    "gn:admin2_code":"3019.0",
    "gn:asciiname":"Odot",
    "gn:country_code":"NG",
    "gn:dem":48,
    "gn:feature_class":"P",
    "gn:feature_code":"PPLA2",
    "gn:name":"Odot",
    "gn:population":0,
    "gn:timezone":"Africa/Lagos",
    "iso:country":"NG",
    "wof:name":"Odot",
    "wof:placetype":"locality"
},
  "geometry": {"coordinates":[8.03839,4.83095],"type":"Point"}
}