{
  "type": "Feature",
  "properties": {
    "gn:admin1_code":"27.0",
    "gn:admin2_code":"112.0",
    "gn:admin3_code":"11207",
    "gn:asciiname":"Durkwa",
    "gn:country_code":"NG",
    "gn:dem":702,
    "gn:feature_class":"P",
    "gn:feature_code":"PPL",
    "gn:name":"Durkwa",
    "gn:population":0,
    "gn:timezone":"Africa/Lagos",
    "iso:country":"NG",
    "wof:name":"Durkwa",
    "wof:placetype":"locality"
},
  "geometry": {"coordinates":[12.1166,10.47964],"type":"Point"}
}