{
  "type": "Feature",
  "properties": {
    "gn:admin1_code":"56.0",
    "gn:admin2_code":"26009.0",
    "gn:asciiname":"Kubo",
    "gn:country_code":"NG",
    "gn:dem":101,
    "gn:feature_class":"P",
    "gn:feature_code":"PPL",
    "gn:name":"Kubo",
    "gn:population":0,
    "gn:timezone":"Africa/Lagos",
    "iso:country":"NG",
    "wof:name":"Kubo",
    "wof:placetype":"locality"
},
  "geometry": {"coordinates":[7.88917,8.2675],"type":"Point"}
}