{
  "type": "Feature",
  "properties": {
    "gn:admin1_code":"35.0",
    "gn:admin2_code":"2002",
    "gn:asciiname":"Ugi",
    "gn:country_code":"NG",
    "gn:dem":417,
    "gn:feature_class":"P",
    "gn:feature_code":"PPL",
    "gn:name":"Ugi",
    "gn:population":0,
    "gn:timezone":"Africa/Lagos",
    "iso:country":"NG",
    "name:deu_x_preferred":[
        "Ugi"
    ],
    "wof:name":"Ugi",
    "wof:placetype":"locality"
},
  "geometry": {"coordinates":[12.44302,8.98501],"type":"Point"}
}