{
  "type": "Feature",
  "properties": {
    "gn:admin1_code":"24.0",
    "gn:admin2_code":"401.0",
    "gn:admin3_code":"40104",
    "gn:asciiname":"Tamarke",
    "gn:country_code":"NG",
    "gn:dem":638,
    "gn:feature_class":"P",
    "gn:feature_code":"PPL",
    "gn:name":"Tamarke",
    "gn:population":0,
    "gn:timezone":"Africa/Lagos",
    "iso:country":"NG",
    "wof:name":"Tamarke",
    "wof:placetype":"locality"
},
  "geometry": {"coordinates":[7.56008,11.51839],"type":"Point"}
}