{
  "type": "Feature",
  "properties": {
    "gn:admin1_code":"23.0",
    "gn:admin2_code":"19015.0",
    "gn:admin3_code":"KD1508",
    "gn:asciiname":"Ungwan Mirga",
    "gn:country_code":"NG",
    "gn:dem":666,
    "gn:feature_class":"P",
    "gn:feature_code":"PPL",
    "gn:name":"Ungwan Mirga",
    "gn:population":0,
    "gn:timezone":"Africa/Lagos",
    "iso:country":"NG",
    "name:und_x_variant":[
        "Mirga",
        "Ungwan Mirga"
    ],
    "wof:name":"Ungwan Mirga",
    "wof:placetype":"locality"
},
  "geometry": {"coordinates":[8.24345,11.07597],"type":"Point"}
}