{
  "type": "Feature",
  "properties": {
    "gn:admin1_code":"51.0",
    "gn:admin2_code":"623.0",
    "gn:admin3_code":"62305",
    "gn:asciiname":"Olobawa",
    "gn:country_code":"NG",
    "gn:dem":280,
    "gn:feature_class":"P",
    "gn:feature_code":"PPL",
    "gn:name":"Olobawa",
    "gn:population":0,
    "gn:timezone":"Africa/Lagos",
    "iso:country":"NG",
    "name:und_x_variant":[
        "Qlobawa",
        "Olobawa"
    ],
    "wof:name":"Olobawa",
    "wof:placetype":"locality"
},
  "geometry": {"coordinates":[4.89434,12.63021],"type":"Point"}
}