{
  "type": "Feature",
  "properties": {
    "gn:admin1_code":"37.0",
    "gn:admin2_code":"12014.0",
    "gn:asciiname":"Ago-Iredia",
    "gn:country_code":"NG",
    "gn:dem":52,
    "gn:feature_class":"P",
    "gn:feature_code":"PPL",
    "gn:name":"Ago-Iredia",
    "gn:population":0,
    "gn:timezone":"Africa/Lagos",
    "iso:country":"NG",
    "wof:name":"Ago-Iredia",
    "wof:placetype":"locality"
},
  "geometry": {"coordinates":[5.43656,6.26687],"type":"Point"}
}