{
  "type": "Feature",
  "properties": {
    "gn:admin1_code":"52.0",
    "gn:admin2_code":"6004",
    "gn:asciiname":"Mabokubo",
    "gn:country_code":"NG",
    "gn:dem":27,
    "gn:feature_class":"P",
    "gn:feature_code":"PPL",
    "gn:name":"Mabokubo",
    "gn:population":0,
    "gn:timezone":"Africa/Lagos",
    "iso:country":"NG",
    "wof:name":"Mabokubo",
    "wof:placetype":"locality"
},
  "geometry": {"coordinates":[6.36514,4.44568],"type":"Point"}
}