{
  "type": "Feature",
  "properties": {
    "gn:admin1_code":"21.0",
    "gn:admin2_code":"3026.0",
    "gn:asciiname":"Ikot Obio Nso",
    "gn:country_code":"NG",
    "gn:dem":46,
    "gn:feature_class":"P",
    "gn:feature_code":"PPL",
    "gn:name":"Ikot Obio Nso",
    "gn:population":0,
    "gn:timezone":"Africa/Lagos",
    "iso:country":"NG",
    "wof:name":"Ikot Obio Nso",
    "wof:placetype":"locality"
},
  "geometry": {"coordinates":[7.75093,4.82381],"type":"Point"}
}