{
  "type": "Feature",
  "properties": {
    "gn:admin1_code":"29.0",
    "gn:admin2_code":"20031.0",
    "gn:admin3_code":"KN0502",
    "gn:asciiname":"Karari",
    "gn:country_code":"NG",
    "gn:dem":515,
    "gn:feature_class":"P",
    "gn:feature_code":"PPL",
    "gn:name":"Karari",
    "gn:population":0,
    "gn:timezone":"Africa/Lagos",
    "iso:country":"NG",
    "name:bpy_x_preferred":[
        "\u0995\u09be\u09b0\u09be\u0987"
    ],
    "name:ceb_x_preferred":[
        "Kar\u0101r\u012b"
    ],
    "name:ita_x_preferred":[
        "Karari"
    ],
    "name:mlg_x_preferred":[
        "Karari"
    ],
    "name:msa_x_preferred":[
        "Karari"
    ],
    "name:new_x_preferred":[
        "\u0915\u0930\u093e\u0930\u0940"
    ],
    "name:nld_x_preferred":[
        "Karari"
    ],
    "name:pol_x_preferred":[
        "Karari"
    ],
    "name:por_x_preferred":[
        "Karari"
    ],
    "name:swe_x_preferred":[
        "Kar\u0101r\u012b"
    ],
    "name:urd_x_preferred":[
        "\u06a9\u0631\u0627\u0631\u06cc"
    ],
    "name:vie_x_preferred":[
        "Karari"
    ],
    "name:zho_x_preferred":[
        "\u5361\u62c9\u91cc"
    ],
    "wof:name":"Karari",
    "wof:placetype":"locality"
},
  "geometry": {"coordinates":[8.16917,12.23433],"type":"Point"}
}