{
  "type": "Feature",
  "properties": {
    "gn:admin1_code":"29.0",
    "gn:admin2_code":"20031.0",
    "gn:admin3_code":"KN0502",
    "gn:asciiname":"Karari",
    "gn:country_code":"NG",
    "gn:dem":515,
    "gn:feature_class":"P",
    "gn:feature_code":"PPL",
    "gn:name":"Karari",
    "gn:population":0,
    "gn:timezone":"Africa/Lagos",
    "iso:country":"NG",
    "wof:name":"Karari",
    "wof:placetype":"locality"
},
  "geometry": {"coordinates":[8.16917,12.23433],"type":"Point"}
}