{
  "type": "Feature",
  "properties": {
    "gn:admin1_code":"37.0",
    "gn:admin2_code":"12016.0",
    "gn:asciiname":"Ikhin",
    "gn:country_code":"NG",
    "gn:dem":290,
    "gn:feature_class":"P",
    "gn:feature_code":"PPL",
    "gn:name":"Ikhin",
    "gn:population":0,
    "gn:timezone":"Africa/Lagos",
    "iso:country":"NG",
    "name:und_x_variant":[
        "Iki",
        "Ikhin"
    ],
    "wof:name":"Ikhin",
    "wof:placetype":"locality"
},
  "geometry": {"coordinates":[5.93804,7.14475],"type":"Point"}
}