{
  "type": "Feature",
  "properties": {
    "gn:admin1_code":"31.0",
    "gn:admin2_code":"27020.0",
    "gn:asciiname":"Gidan Jato Simamba",
    "gn:country_code":"NG",
    "gn:dem":301,
    "gn:feature_class":"P",
    "gn:feature_code":"PPL",
    "gn:name":"Gidan Jato Simamba",
    "gn:population":0,
    "gn:timezone":"Africa/Lagos",
    "iso:country":"NG",
    "wof:name":"Gidan Jato Simamba",
    "wof:placetype":"locality"
},
  "geometry": {"coordinates":[6.22027,10.21504],"type":"Point"}
}