{
  "type": "Feature",
  "properties": {
    "gn:admin1_code":"23.0",
    "gn:admin2_code":"19017.0",
    "gn:admin3_code":"KD1709",
    "gn:asciiname":"Jingr",
    "gn:country_code":"NG",
    "gn:dem":812,
    "gn:feature_class":"P",
    "gn:feature_code":"PPL",
    "gn:name":"Jingr",
    "gn:population":0,
    "gn:timezone":"Africa/Lagos",
    "iso:country":"NG",
    "wof:name":"Jingr",
    "wof:placetype":"locality"
},
  "geometry": {"coordinates":[8.47511,10.34864],"type":"Point"}
}