{
  "type": "Feature",
  "properties": {
    "gn:country":"NG",
    "gn:fcode":"PPL",
    "gn:population":84373,
    "iso:country":"NG",
    "name:bul_x_preferred":[
        "\u041e\u0433\u0430\u043c\u0438\u043d\u0430\u043d\u0430"
    ],
    "name:ceb_x_preferred":[
        "Ogaminana"
    ],
    "name:eng_x_preferred":[
        "Ogaminan"
    ],
    "name:nld_x_preferred":[
        "Ogaminan"
    ],
    "qs:name":"Ogaminan",
    "qs:photos_9r":0,
    "qs:photos_sr":0,
    "qs:pop_sr":"8",
    "wd:wordcount":39,
    "wof:name":"Ogaminan",
    "wof:placetype":"neighbourhood",
    "wof:population":84373
},
  "geometry": {"coordinates":[6.22476,7.59464],"type":"Point"}
}