{
  "type": "Feature",
  "properties": {
    "gn:admin1_code":"27.0",
    "gn:admin2_code":"111.0",
    "gn:admin3_code":"11111",
    "gn:asciiname":"Guva",
    "gn:country_code":"NG",
    "gn:dem":472,
    "gn:feature_class":"P",
    "gn:feature_code":"PPL",
    "gn:name":"Guva",
    "gn:population":0,
    "gn:timezone":"Africa/Lagos",
    "iso:country":"NG",
    "name:ceb_x_preferred":[
        "Guva"
    ],
    "name:swe_x_preferred":[
        "Guva"
    ],
    "wof:name":"Guva",
    "wof:placetype":"locality"
},
  "geometry": {"coordinates":[13.79167,11.12675],"type":"Point"}
}