{
  "type": "Feature",
  "properties": {
    "gn:admin1_code":"49.0",
    "gn:admin2_code":"32016.0",
    "gn:asciiname":"Bua",
    "gn:country_code":"NG",
    "gn:dem":116,
    "gn:feature_class":"P",
    "gn:feature_code":"PPL",
    "gn:name":"Bua",
    "gn:population":0,
    "gn:timezone":"Africa/Lagos",
    "iso:country":"NG",
    "name:ceb_x_preferred":[
        "Bua"
    ],
    "name:glg_x_preferred":[
        "Bua"
    ],
    "name:ind_x_preferred":[
        "Bua"
    ],
    "name:nld_x_preferred":[
        "Bua"
    ],
    "name:swe_x_preferred":[
        "Bua"
    ],
    "wof:name":"Bua",
    "wof:placetype":"locality"
},
  "geometry": {"coordinates":[9.7309,8.41905],"type":"Point"}
}