{
  "type": "Feature",
  "properties": {
    "gn:admin1_code":"44.0",
    "gn:admin2_code":"710",
    "gn:admin3_code":"71002",
    "gn:asciiname":"Garin Mallam Bagana",
    "gn:country_code":"NG",
    "gn:dem":341,
    "gn:feature_class":"P",
    "gn:feature_code":"PPL",
    "gn:name":"Garin Mallam Bagana",
    "gn:population":0,
    "gn:timezone":"Africa/Lagos",
    "iso:country":"NG",
    "wof:name":"Garin Mallam Bagana",
    "wof:placetype":"locality"
},
  "geometry": {"coordinates":[10.86952,13.02475],"type":"Point"}
}