{
  "type": "Feature",
  "properties": {
    "gn:admin1_code":"40.0",
    "gn:admin2_code":"511.0",
    "gn:admin3_code":"51104",
    "gn:asciiname":"Danmawa",
    "gn:country_code":"NG",
    "gn:dem":214,
    "gn:feature_class":"P",
    "gn:feature_code":"PPL",
    "gn:name":"Danmawa",
    "gn:population":0,
    "gn:timezone":"Africa/Lagos",
    "iso:country":"NG",
    "wof:name":"Danmawa",
    "wof:placetype":"locality"
},
  "geometry": {"coordinates":[4.35,12.25],"type":"Point"}
}