{
  "type": "Feature",
  "properties": {
    "gn:admin1_code":"21.0",
    "gn:admin2_code":"3005.0",
    "gn:asciiname":"Ikot Offiong",
    "gn:country_code":"NG",
    "gn:dem":75,
    "gn:feature_class":"P",
    "gn:feature_code":"PPL",
    "gn:name":"Ikot Offiong",
    "gn:population":0,
    "gn:timezone":"Africa/Lagos",
    "iso:country":"NG",
    "wof:name":"Ikot Offiong",
    "wof:placetype":"locality"
},
  "geometry": {"coordinates":[7.66589,5.11519],"type":"Point"}
}