{
  "type": "Feature",
  "properties": {
    "gn:admin1_code":"55.0",
    "gn:admin2_code":"16011.0",
    "gn:asciiname":"Ungwa Canteen",
    "gn:country_code":"NG",
    "gn:dem":220,
    "gn:feature_class":"P",
    "gn:feature_code":"PPL",
    "gn:name":"Ungwa Canteen",
    "gn:population":0,
    "gn:timezone":"Africa/Lagos",
    "iso:country":"NG",
    "wof:name":"Ungwa Canteen",
    "wof:placetype":"locality"
},
  "geometry": {"coordinates":[11.51598,10.29813],"type":"Point"}
}