{
  "type": "Feature",
  "properties": {
    "gn:admin1_code":"31.0",
    "gn:admin2_code":"27017.0",
    "gn:asciiname":"Yiko",
    "gn:country_code":"NG",
    "gn:dem":200,
    "gn:feature_class":"P",
    "gn:feature_code":"PPL",
    "gn:name":"Yiko",
    "gn:population":0,
    "gn:timezone":"Africa/Lagos",
    "iso:country":"NG",
    "wof:name":"Yiko",
    "wof:placetype":"locality"
},
  "geometry": {"coordinates":[5.46667,9.23333],"type":"Point"}
}