{
  "type": "Feature",
  "properties": {
    "gn:admin1_code":"23.0",
    "gn:admin2_code":"19001.0",
    "gn:admin3_code":"KD0104",
    "gn:asciiname":"Maidoruwa",
    "gn:country_code":"NG",
    "gn:dem":464,
    "gn:feature_class":"P",
    "gn:feature_code":"PPL",
    "gn:name":"Maidoruwa",
    "gn:population":0,
    "gn:timezone":"Africa/Lagos",
    "iso:country":"NG",
    "wof:name":"Maidoruwa",
    "wof:placetype":"locality"
},
  "geometry": {"coordinates":[6.52546,11.01853],"type":"Point"}
}