{
  "type": "Feature",
  "properties": {
    "gn:admin1_code":"26.0",
    "gn:admin2_code":"7003.0",
    "gn:asciiname":"Alfeti",
    "gn:country_code":"NG",
    "gn:dem":277,
    "gn:feature_class":"P",
    "gn:feature_code":"PPL",
    "gn:name":"Alfeti",
    "gn:population":0,
    "gn:timezone":"Africa/Lagos",
    "iso:country":"NG",
    "wof:name":"Alfeti",
    "wof:placetype":"locality"
},
  "geometry": {"coordinates":[7.8179,7.52861],"type":"Point"}
}