{
  "type": "Feature",
  "properties": {
    "gn:admin1_code":"41.0",
    "gn:admin2_code":"23009.0",
    "gn:asciiname":"Ayere",
    "gn:country_code":"NG",
    "gn:dem":380,
    "gn:feature_class":"P",
    "gn:feature_code":"PPL",
    "gn:name":"Ayere",
    "gn:population":0,
    "gn:timezone":"Africa/Lagos",
    "iso:country":"NG",
    "name:und_x_variant":[
        "Aiere",
        "Ayere"
    ],
    "wof:name":"Ayere",
    "wof:placetype":"locality"
},
  "geometry": {"coordinates":[5.9717,7.70402],"type":"Point"}
}