{
  "type": "Feature",
  "properties": {
    "gn:admin1_code":"37.0",
    "gn:admin2_code":"12015.0",
    "gn:asciiname":"Obozogbe",
    "gn:country_code":"NG",
    "gn:dem":128,
    "gn:feature_class":"P",
    "gn:feature_code":"PPL",
    "gn:name":"Obozogbe",
    "gn:population":0,
    "gn:timezone":"Africa/Lagos",
    "iso:country":"NG",
    "name:und_x_variant":[
        "Obozogbo",
        "Obozogbe"
    ],
    "wof:name":"Obozogbe",
    "wof:placetype":"locality"
},
  "geometry": {"coordinates":[5.38362,6.51368],"type":"Point"}
}