{
  "type": "Feature",
  "properties": {
    "gn:admin1_code":"39.0",
    "gn:admin2_code":"18004.0",
    "gn:admin3_code":"JI0207",
    "gn:asciiname":"Jigawa",
    "gn:country_code":"NG",
    "gn:dem":389,
    "gn:feature_class":"P",
    "gn:feature_code":"PPL",
    "gn:name":"Jigawa",
    "gn:population":0,
    "gn:timezone":"Africa/Lagos",
    "iso:country":"NG",
    "name:hun_x_preferred":[
        "Jigawa"
    ],
    "wof:name":"Jigawa",
    "wof:placetype":"locality"
},
  "geometry": {"coordinates":[8.96687,12.64496],"type":"Point"}
}