{
  "type": "Feature",
  "properties": {
    "gn:admin1_code":"46.0",
    "gn:asciiname":"Gidan Dari",
    "gn:country_code":"NG",
    "gn:dem":311,
    "gn:feature_class":"P",
    "gn:feature_code":"PPL",
    "gn:name":"Gidan Dari",
    "gn:population":0,
    "gn:timezone":"Africa/Lagos",
    "iso:country":"NG",
    "name:eng_x_preferred":[
        "Gidan Dari"
    ],
    "wof:name":"Gidan Dari",
    "wof:placetype":"locality"
},
  "geometry": {"coordinates":[10.95133,9.61503],"type":"Point"}
}