{
  "type": "Feature",
  "properties": {
    "gn:admin1_code":"29.0",
    "gn:admin2_code":"20005.0",
    "gn:admin3_code":"KN3310",
    "gn:asciiname":"Tummawa",
    "gn:country_code":"NG",
    "gn:dem":465,
    "gn:feature_class":"P",
    "gn:feature_code":"PPL",
    "gn:name":"Tummawa",
    "gn:population":0,
    "gn:timezone":"Africa/Lagos",
    "iso:country":"NG",
    "wof:name":"Tummawa",
    "wof:placetype":"locality"
},
  "geometry": {"coordinates":[8.32036,11.88864],"type":"Point"}
}