{
  "type": "Feature",
  "properties": {
    "gn:admin1_code":"39.0",
    "gn:admin2_code":"18019.0",
    "gn:admin3_code":"JI2702",
    "gn:asciiname":"Dankari",
    "gn:country_code":"NG",
    "gn:dem":460,
    "gn:feature_class":"P",
    "gn:feature_code":"PPL",
    "gn:name":"Dankari",
    "gn:population":0,
    "gn:timezone":"Africa/Lagos",
    "iso:country":"NG",
    "wof:name":"Dankari",
    "wof:placetype":"locality"
},
  "geometry": {"coordinates":[8.45105,12.72163],"type":"Point"}
}