{
  "type": "Feature",
  "properties": {
    "gn:admin1_code":"36.0",
    "gn:asciiname":"Ago Atilabo",
    "gn:country_code":"NG",
    "gn:dem":7,
    "gn:feature_class":"P",
    "gn:feature_code":"PPL",
    "gn:name":"Ago Atilabo",
    "gn:population":0,
    "gn:timezone":"Africa/Lagos",
    "iso:country":"NG",
    "name:und_x_variant":[
        "Atilabo",
        "Ago Atilabo"
    ],
    "wof:name":"Ago Atilabo",
    "wof:placetype":"locality"
},
  "geometry": {"coordinates":[5.02991,6.03273],"type":"Point"}
}