{
  "type": "Feature",
  "properties": {
    "gn:admin1_code":"27.0",
    "gn:admin2_code":"112.0",
    "gn:admin3_code":"11210",
    "gn:asciiname":"Gardemna",
    "gn:country_code":"NG",
    "gn:dem":323,
    "gn:feature_class":"P",
    "gn:feature_code":"PPL",
    "gn:name":"Gardemna",
    "gn:population":0,
    "gn:timezone":"Africa/Lagos",
    "iso:country":"NG",
    "wof:name":"Gardemna",
    "wof:placetype":"locality"
},
  "geometry": {"coordinates":[12.41663,10.33018],"type":"Point"}
}