{
  "type": "Feature",
  "properties": {
    "gn:admin1_code":"35.0",
    "gn:admin2_code":"2013",
    "gn:asciiname":"Shike",
    "gn:country_code":"NG",
    "gn:dem":834,
    "gn:feature_class":"P",
    "gn:feature_code":"PPL",
    "gn:name":"Shike",
    "gn:population":0,
    "gn:timezone":"Africa/Lagos",
    "iso:country":"NG",
    "name:eng_x_preferred":[
        "Shike"
    ],
    "wof:name":"Shike",
    "wof:placetype":"locality"
},
  "geometry": {"coordinates":[13.44987,10.54703],"type":"Point"}
}