{
  "type": "Feature",
  "properties": {
    "gn:admin1_code":"45.0",
    "gn:admin2_code":"1014.0",
    "gn:asciiname":"Umuebom",
    "gn:country_code":"NG",
    "gn:dem":31,
    "gn:feature_class":"P",
    "gn:feature_code":"PPL",
    "gn:name":"Umuebom",
    "gn:population":0,
    "gn:timezone":"Africa/Lagos",
    "iso:country":"NG",
    "wof:name":"Umuebom",
    "wof:placetype":"locality"
},
  "geometry": {"coordinates":[7.20886,4.92938],"type":"Point"}
}