{
  "type": "Feature",
  "properties": {
    "gn:admin1_code":"27.0",
    "gn:admin2_code":"118.0",
    "gn:admin3_code":"11801",
    "gn:asciiname":"Huitayankwar",
    "gn:country_code":"NG",
    "gn:dem":440,
    "gn:feature_class":"P",
    "gn:feature_code":"PPL",
    "gn:name":"Huitayankwar",
    "gn:population":0,
    "gn:timezone":"Africa/Lagos",
    "iso:country":"NG",
    "wof:name":"Huitayankwar",
    "wof:placetype":"locality"
},
  "geometry": {"coordinates":[12.03277,10.43696],"type":"Point"}
}