{
  "type": "Feature",
  "properties": {
    "gn:admin1_code":"29.0",
    "gn:admin2_code":"20034.0",
    "gn:admin3_code":"KN2414",
    "gn:asciiname":"Kafin Maiyaki",
    "gn:country_code":"NG",
    "gn:dem":619,
    "gn:feature_class":"P",
    "gn:feature_code":"PPL",
    "gn:name":"Kafin Maiyaki",
    "gn:population":0,
    "gn:timezone":"Africa/Lagos",
    "iso:country":"NG",
    "wof:name":"Kafin Maiyaki",
    "wof:placetype":"locality"
},
  "geometry": {"coordinates":[8.20231,11.4563],"type":"Point"}
}