{
  "type": "Feature",
  "properties": {
    "gn:admin1_code":"57.0",
    "gn:admin2_code":"801.0",
    "gn:admin3_code":"80108",
    "gn:asciiname":"Samli",
    "gn:country_code":"NG",
    "gn:dem":368,
    "gn:feature_class":"P",
    "gn:feature_code":"PPL",
    "gn:name":"Samli",
    "gn:population":0,
    "gn:timezone":"Africa/Lagos",
    "iso:country":"NG",
    "name:und_x_variant":[
        "Sabli",
        "Samli"
    ],
    "wof:name":"Samli",
    "wof:placetype":"locality"
},
  "geometry": {"coordinates":[5.81421,12.22879],"type":"Point"}
}