{
  "type": "Feature",
  "properties": {
    "gn:admin1_code":"39.0",
    "gn:admin2_code":"18005.0",
    "gn:admin3_code":"JI1006",
    "gn:asciiname":"Chachamnau",
    "gn:country_code":"NG",
    "gn:dem":354,
    "gn:feature_class":"P",
    "gn:feature_code":"PPL",
    "gn:name":"Chachamnau",
    "gn:population":0,
    "gn:timezone":"Africa/Lagos",
    "iso:country":"NG",
    "wof:name":"Chachamnau",
    "wof:placetype":"locality"
},
  "geometry": {"coordinates":[10.45005,12.54034],"type":"Point"}
}