{
  "type": "Feature",
  "properties": {
    "gn:admin1_code":"32.0",
    "gn:admin2_code":"31028.0",
    "gn:asciiname":"Somodero",
    "gn:country_code":"NG",
    "gn:dem":378,
    "gn:feature_class":"P",
    "gn:feature_code":"PPL",
    "gn:name":"Somodero",
    "gn:population":0,
    "gn:timezone":"Africa/Lagos",
    "iso:country":"NG",
    "wof:name":"Somodero",
    "wof:placetype":"locality"
},
  "geometry": {"coordinates":[4.25,8.33333],"type":"Point"}
}