{
  "type": "Feature",
  "properties": {
    "gn:admin1_code":"31.0",
    "gn:admin2_code":"27009.0",
    "gn:asciiname":"Dagba",
    "gn:country_code":"NG",
    "gn:dem":278,
    "gn:feature_class":"P",
    "gn:feature_code":"PPL",
    "gn:name":"Dagba",
    "gn:population":0,
    "gn:timezone":"Africa/Lagos",
    "iso:country":"NG",
    "name:und_x_variant":[
        "Daga"
    ],
    "wof:name":"Dagba",
    "wof:placetype":"locality"
},
  "geometry": {"coordinates":[6.98565,9.27422],"type":"Point"}
}