{
  "type": "Feature",
  "properties": {
    "gn:admin1_code":"30.0",
    "gn:admin2_code":"24002.0",
    "gn:asciiname":"Ilesha Ibariba",
    "gn:cc2":"NG",
    "gn:country_code":"NG",
    "gn:dem":390,
    "gn:feature_class":"P",
    "gn:feature_code":"PPL",
    "gn:name":"Ilesha Ibariba",
    "gn:population":0,
    "gn:timezone":"Africa/Lagos",
    "iso:country":"NG",
    "name:und_x_variant":[
        "Ilesha",
        "Ilesha Ibariba"
    ],
    "wof:name":"Ilesha Ibariba",
    "wof:placetype":"locality"
},
  "geometry": {"coordinates":[3.41667,8.91667],"type":"Point"}
}