{
  "type": "Feature",
  "properties": {
    "gn:admin1_code":"31.0",
    "gn:admin2_code":"27009.0",
    "gn:asciiname":"Kadna",
    "gn:country_code":"NG",
    "gn:dem":514,
    "gn:feature_class":"P",
    "gn:feature_code":"PPL",
    "gn:name":"Kadna",
    "gn:population":0,
    "gn:timezone":"Africa/Lagos",
    "iso:country":"NG",
    "wof:name":"Kadna",
    "wof:placetype":"locality"
},
  "geometry": {"coordinates":[7.22767,9.3149],"type":"Point"}
}