{
  "type": "Feature",
  "properties": {
    "gn:admin1_code":"32.0",
    "gn:admin2_code":"31028.0",
    "gn:asciiname":"Alako",
    "gn:country_code":"NG",
    "gn:dem":332,
    "gn:feature_class":"P",
    "gn:feature_code":"PPL",
    "gn:name":"Alako",
    "gn:population":0,
    "gn:timezone":"Africa/Lagos",
    "iso:country":"NG",
    "name:ita_x_preferred":[
        "Alako"
    ],
    "wof:name":"Alako",
    "wof:placetype":"locality"
},
  "geometry": {"coordinates":[4.13333,8.15],"type":"Point"}
}