{
  "type": "Feature",
  "properties": {
    "gn:admin1_code":"24.0",
    "gn:admin2_code":"420.0",
    "gn:admin3_code":"42010",
    "gn:asciiname":"Tsa",
    "gn:country_code":"NG",
    "gn:dem":555,
    "gn:feature_class":"P",
    "gn:feature_code":"PPL",
    "gn:name":"Tsa",
    "gn:population":0,
    "gn:timezone":"Africa/Lagos",
    "iso:country":"NG",
    "wof:name":"Tsa",
    "wof:placetype":"locality"
},
  "geometry": {"coordinates":[7.83202,12.43111],"type":"Point"}
}