{
  "type": "Feature",
  "properties": {
    "gn:admin1_code":"24.0",
    "gn:admin2_code":"404.0",
    "gn:admin3_code":"40406",
    "gn:asciiname":"Dole Masaka",
    "gn:country_code":"NG",
    "gn:dem":403,
    "gn:feature_class":"P",
    "gn:feature_code":"PPL",
    "gn:name":"Dole Masaka",
    "gn:population":0,
    "gn:timezone":"Africa/Lagos",
    "iso:country":"NG",
    "wof:name":"Dole Masaka",
    "wof:placetype":"locality"
},
  "geometry": {"coordinates":[8.70904,12.75957],"type":"Point"}
}