{
  "type": "Feature",
  "properties": {
    "gn:admin1_code":"46.0",
    "gn:admin2_code":"5013.0",
    "gn:admin3_code":"BA1311",
    "gn:asciiname":"Kafin Iyal",
    "gn:country_code":"NG",
    "gn:dem":347,
    "gn:feature_class":"P",
    "gn:feature_code":"PPL",
    "gn:name":"Kafin Iyal",
    "gn:population":0,
    "gn:timezone":"Africa/Lagos",
    "iso:country":"NG",
    "name:eng_x_preferred":[
        "Kafin Iyal"
    ],
    "name:eng_x_variant":[
        "Kafin Lyal"
    ],
    "wof:name":"Kafin Iyal",
    "wof:placetype":"locality"
},
  "geometry": {"coordinates":[10.47026,10.58671],"type":"Point"}
}