{
  "type": "Feature",
  "properties": {
    "gn:admin1_code":"26.0",
    "gn:admin2_code":"7010.0",
    "gn:asciiname":"Naajime-Iorbee",
    "gn:country_code":"NG",
    "gn:dem":133,
    "gn:feature_class":"P",
    "gn:feature_code":"PPL",
    "gn:name":"Naajime-Iorbee",
    "gn:population":0,
    "gn:timezone":"Africa/Lagos",
    "iso:country":"NG",
    "wof:name":"Naajime-Iorbee",
    "wof:placetype":"locality"
},
  "geometry": {"coordinates":[8.50743,7.09155],"type":"Point"}
}