{
  "type": "Feature",
  "properties": {
    "gn:admin1_code":"24.0",
    "gn:admin2_code":"431.0",
    "gn:admin3_code":"43106",
    "gn:asciiname":"Ungwan Usman",
    "gn:country_code":"NG",
    "gn:dem":671,
    "gn:feature_class":"P",
    "gn:feature_code":"PPL",
    "gn:name":"Ungwan Usman",
    "gn:population":0,
    "gn:timezone":"Africa/Lagos",
    "iso:country":"NG",
    "wof:name":"Ungwan Usman",
    "wof:placetype":"locality"
},
  "geometry": {"coordinates":[7.1187,11.21896],"type":"Point"}
}