{
  "type": "Feature",
  "properties": {
    "gn:admin1_code":"27.0",
    "gn:admin2_code":"114.0",
    "gn:admin3_code":"11411",
    "gn:asciiname":"Sugumi",
    "gn:country_code":"NG",
    "gn:dem":391,
    "gn:feature_class":"P",
    "gn:feature_code":"PPL",
    "gn:name":"Sugumi",
    "gn:population":0,
    "gn:timezone":"Africa/Lagos",
    "iso:country":"NG",
    "wof:name":"Sugumi",
    "wof:placetype":"locality"
},
  "geometry": {"coordinates":[12.18333,11.66667],"type":"Point"}
}