{
  "type": "Feature",
  "properties": {
    "gn:admin1_code":"55.0",
    "gn:admin2_code":"16011.0",
    "gn:asciiname":"Palta",
    "gn:country_code":"NG",
    "gn:dem":239,
    "gn:feature_class":"P",
    "gn:feature_code":"PPL",
    "gn:name":"Palta",
    "gn:population":0,
    "gn:timezone":"Africa/Lagos",
    "iso:country":"NG",
    "name:hrv_x_preferred":[
        "Palta"
    ],
    "name:spa_x_preferred":[
        "Paltas"
    ],
    "wof:name":"Palta",
    "wof:placetype":"locality"
},
  "geometry": {"coordinates":[11.59705,10.19587],"type":"Point"}
}