{
  "type": "Feature",
  "properties": {
    "gn:admin1_code":"53.0",
    "gn:admin2_code":"11008.0",
    "gn:asciiname":"Edema",
    "gn:country_code":"NG",
    "gn:dem":88,
    "gn:feature_class":"P",
    "gn:feature_code":"PPL",
    "gn:name":"Edema",
    "gn:population":0,
    "gn:timezone":"Africa/Lagos",
    "iso:country":"NG",
    "wof:name":"Edema",
    "wof:placetype":"locality"
},
  "geometry": {"coordinates":[7.76009,6.4646],"type":"Point"}
}