{
  "type": "Feature",
  "properties": {
    "gn:admin1_code":"27.0",
    "gn:admin2_code":"107.0",
    "gn:admin3_code":"10701",
    "gn:asciiname":"Ajir",
    "gn:country_code":"NG",
    "gn:dem":440,
    "gn:feature_class":"P",
    "gn:feature_code":"PPL",
    "gn:name":"Ajir",
    "gn:population":0,
    "gn:timezone":"Africa/Lagos",
    "iso:country":"NG",
    "wof:name":"Ajir",
    "wof:placetype":"locality"
},
  "geometry": {"coordinates":[12.64791,11.04568],"type":"Point"}
}