{
  "type": "Feature",
  "properties": {
    "gn:admin1_code":"46.0",
    "gn:admin2_code":"5013.0",
    "gn:admin3_code":"BA1312",
    "gn:asciiname":"Kanawa",
    "gn:country_code":"NG",
    "gn:dem":327,
    "gn:feature_class":"P",
    "gn:feature_code":"PPL",
    "gn:name":"Kanawa",
    "gn:population":0,
    "gn:timezone":"Africa/Lagos",
    "iso:country":"NG",
    "name:eng_x_preferred":[
        "Garin Kanawa"
    ],
    "name:eng_x_variant":[
        "Kanawa"
    ],
    "wof:name":"Kanawa",
    "wof:placetype":"locality"
},
  "geometry": {"coordinates":[10.53476,10.25847],"type":"Point"}
}