{
  "type": "Feature",
  "properties": {
    "gn:admin1_code":"40.0",
    "gn:admin2_code":"504.0",
    "gn:admin3_code":"50410",
    "gn:asciiname":"Bagura",
    "gn:country_code":"NG",
    "gn:dem":223,
    "gn:feature_class":"P",
    "gn:feature_code":"PPL",
    "gn:name":"Bagura",
    "gn:population":0,
    "gn:timezone":"Africa/Lagos",
    "iso:country":"NG",
    "wof:name":"Bagura",
    "wof:placetype":"locality"
},
  "geometry": {"coordinates":[4.51667,12.86667],"type":"Point"}
}