{
  "type": "Feature",
  "properties": {
    "gn:admin1_code":"53.0",
    "gn:admin2_code":"11004.0",
    "gn:asciiname":"Mbeke",
    "gn:country_code":"NG",
    "gn:dem":112,
    "gn:feature_class":"P",
    "gn:feature_code":"PPL",
    "gn:name":"Mbeke",
    "gn:population":0,
    "gn:timezone":"Africa/Lagos",
    "iso:country":"NG",
    "wof:name":"Mbeke",
    "wof:placetype":"locality"
},
  "geometry": {"coordinates":[8.11274,6.6734],"type":"Point"}
}