{
  "type": "Feature",
  "properties": {
    "gn:admin1_code":"35.0",
    "gn:admin2_code":"2005.0",
    "gn:asciiname":"Mihawin",
    "gn:country_code":"NG",
    "gn:dem":555,
    "gn:feature_class":"P",
    "gn:feature_code":"PPL",
    "gn:name":"Mihawin",
    "gn:population":0,
    "gn:timezone":"Africa/Lagos",
    "iso:country":"NG",
    "wof:name":"Mihawin",
    "wof:placetype":"locality"
},
  "geometry": {"coordinates":[12.66351,10.08048],"type":"Point"}
}