{
  "type": "Feature",
  "properties": {
    "gn:admin1_code":"26.0",
    "gn:admin2_code":"7004",
    "gn:asciiname":"Orkeghen",
    "gn:country_code":"NG",
    "gn:dem":143,
    "gn:feature_class":"P",
    "gn:feature_code":"PPL",
    "gn:name":"Orkeghen",
    "gn:population":0,
    "gn:timezone":"Africa/Lagos",
    "iso:country":"NG",
    "wof:name":"Orkeghen",
    "wof:placetype":"locality"
},
  "geometry": {"coordinates":[9.15695,7.39948],"type":"Point"}
}