{
  "type": "Feature",
  "properties": {
    "gn:admin1_code":"23.0",
    "gn:admin2_code":"19011",
    "gn:admin3_code":"KD1106",
    "gn:asciiname":"Tsaunin-Barai",
    "gn:country_code":"NG",
    "gn:dem":658,
    "gn:feature_class":"P",
    "gn:feature_code":"PPL",
    "gn:name":"Tsaunin-Barai",
    "gn:population":0,
    "gn:timezone":"Africa/Lagos",
    "iso:country":"NG",
    "wof:name":"Tsaunin-Barai",
    "wof:placetype":"locality"
},
  "geometry": {"coordinates":[7.54002,9.42944],"type":"Point"}
}