{
  "type": "Feature",
  "properties": {
    "gn:admin1_code":"24.0",
    "gn:admin2_code":"415.0",
    "gn:admin3_code":"41507",
    "gn:asciiname":"Kundu Waje",
    "gn:country_code":"NG",
    "gn:dem":514,
    "gn:feature_class":"P",
    "gn:feature_code":"PPL",
    "gn:name":"Kundu Waje",
    "gn:population":0,
    "gn:timezone":"Africa/Lagos",
    "iso:country":"NG",
    "wof:name":"Kundu Waje",
    "wof:placetype":"locality"
},
  "geometry": {"coordinates":[8.00428,12.60978],"type":"Point"}
}