{
  "type": "Feature",
  "properties": {
    "gn:admin1_code":"23.0",
    "gn:admin2_code":"19022",
    "gn:admin3_code":"KD2201",
    "gn:asciiname":"Zuturu Gida",
    "gn:country_code":"NG",
    "gn:dem":911,
    "gn:feature_class":"P",
    "gn:feature_code":"PPL",
    "gn:name":"Zuturu Gida",
    "gn:population":0,
    "gn:timezone":"Africa/Lagos",
    "iso:country":"NG",
    "wof:name":"Zuturu Gida",
    "wof:placetype":"locality"
},
  "geometry": {"coordinates":[8.21462,9.74767],"type":"Point"}
}