{
  "type": "Feature",
  "properties": {
    "gn:admin1_code":"40.0",
    "gn:admin2_code":"519.0",
    "gn:admin3_code":"51904",
    "gn:asciiname":"Donko",
    "gn:country_code":"NG",
    "gn:dem":376,
    "gn:feature_class":"P",
    "gn:feature_code":"PPL",
    "gn:name":"Donko",
    "gn:population":0,
    "gn:timezone":"Africa/Lagos",
    "iso:country":"NG",
    "wof:name":"Donko",
    "wof:placetype":"locality"
},
  "geometry": {"coordinates":[5.29889,11.72944],"type":"Point"}
}