{
  "type": "Feature",
  "properties": {
    "gn:admin1_code":"35.0",
    "gn:admin2_code":"2007.0",
    "gn:asciiname":"Mugzil",
    "gn:country_code":"NG",
    "gn:dem":536,
    "gn:feature_class":"P",
    "gn:feature_code":"PPL",
    "gn:name":"Mugzil",
    "gn:population":0,
    "gn:timezone":"Africa/Lagos",
    "iso:country":"NG",
    "wof:name":"Mugzil",
    "wof:placetype":"locality"
},
  "geometry": {"coordinates":[13.0831,10.33111],"type":"Point"}
}