{
  "type": "Feature",
  "properties": {
    "gn:admin1_code":"46.0",
    "gn:admin2_code":"5001.0",
    "gn:admin3_code":"BA0102",
    "gn:asciiname":"Kwala",
    "gn:country_code":"NG",
    "gn:dem":297,
    "gn:feature_class":"P",
    "gn:feature_code":"PPL",
    "gn:name":"Kwala",
    "gn:population":0,
    "gn:timezone":"Africa/Lagos",
    "iso:country":"NG",
    "name:eng_x_preferred":[
        "Kwala"
    ],
    "wof:name":"Kwala",
    "wof:placetype":"locality"
},
  "geometry": {"coordinates":[10.60729,10.03177],"type":"Point"}
}