{
  "type": "Feature",
  "properties": {
    "gn:admin1_code":"26.0",
    "gn:admin2_code":"7011.0",
    "gn:asciiname":"Alev",
    "gn:country_code":"NG",
    "gn:dem":244,
    "gn:feature_class":"P",
    "gn:feature_code":"PPL",
    "gn:name":"Alev",
    "gn:population":0,
    "gn:timezone":"Africa/Lagos",
    "iso:country":"NG",
    "name:ron_x_preferred":[
        "Alev"
    ],
    "name:srp_x_preferred":[
        "\u0410\u043b\u0435\u0432"
    ],
    "wof:name":"Alev",
    "wof:placetype":"locality"
},
  "geometry": {"coordinates":[9.5627,6.66542],"type":"Point"}
}