{
  "type": "Feature",
  "properties": {
    "gn:admin1_code":"51.0",
    "gn:admin2_code":"619.0",
    "gn:admin3_code":"61910",
    "gn:asciiname":"Hunkui",
    "gn:country_code":"NG",
    "gn:dem":260,
    "gn:feature_class":"P",
    "gn:feature_code":"PPL",
    "gn:name":"Hunkui",
    "gn:population":0,
    "gn:timezone":"Africa/Lagos",
    "iso:country":"NG",
    "wof:name":"Hunkui",
    "wof:placetype":"locality"
},
  "geometry": {"coordinates":[4.92424,13.38116],"type":"Point"}
}