{
  "type": "Feature",
  "properties": {
    "gn:admin1_code":"39.0",
    "gn:admin2_code":"18009.0",
    "gn:admin3_code":"JI1209",
    "gn:asciiname":"Shafe",
    "gn:country_code":"NG",
    "gn:dem":479,
    "gn:feature_class":"P",
    "gn:feature_code":"PPL",
    "gn:name":"Shafe",
    "gn:population":0,
    "gn:timezone":"Africa/Lagos",
    "iso:country":"NG",
    "wof:name":"Shafe",
    "wof:placetype":"locality"
},
  "geometry": {"coordinates":[8.26301,12.8011],"type":"Point"}
}