{
  "type": "Feature",
  "properties": {
    "gn:admin1_code":"35.0",
    "gn:admin2_code":"2005.0",
    "gn:asciiname":"Wuro Ardo Nana",
    "gn:country_code":"NG",
    "gn:dem":547,
    "gn:feature_class":"P",
    "gn:feature_code":"PPL",
    "gn:name":"Wuro Ardo Nana",
    "gn:population":0,
    "gn:timezone":"Africa/Lagos",
    "iso:country":"NG",
    "wof:name":"Wuro Ardo Nana",
    "wof:placetype":"locality"
},
  "geometry": {"coordinates":[12.57431,10.08558],"type":"Point"}
}