{
  "type": "Feature",
  "properties": {
    "gn:admin1_code":"24.0",
    "gn:admin2_code":"401.0",
    "gn:admin3_code":"40103",
    "gn:asciiname":"Dantige",
    "gn:country_code":"NG",
    "gn:dem":593,
    "gn:feature_class":"P",
    "gn:feature_code":"PPL",
    "gn:name":"Dantige",
    "gn:population":0,
    "gn:timezone":"Africa/Lagos",
    "iso:country":"NG",
    "wof:name":"Dantige",
    "wof:placetype":"locality"
},
  "geometry": {"coordinates":[7.61503,11.60872],"type":"Point"}
}