{
  "type": "Feature",
  "properties": {
    "gn:admin1_code":"53.0",
    "gn:admin2_code":"11013.0",
    "gn:asciiname":"Isuachari",
    "gn:country_code":"NG",
    "gn:dem":71,
    "gn:feature_class":"P",
    "gn:feature_code":"PPL",
    "gn:name":"Isuachari",
    "gn:population":0,
    "gn:timezone":"Africa/Lagos",
    "iso:country":"NG",
    "name:und_x_variant":[
        "Isuachara"
    ],
    "wof:name":"Isuachari",
    "wof:placetype":"locality"
},
  "geometry": {"coordinates":[7.76365,6.10777],"type":"Point"}
}