{
  "type": "Feature",
  "properties": {
    "gn:admin1_code":"44.0",
    "gn:admin2_code":"717",
    "gn:admin3_code":"71711",
    "gn:asciiname":"Bulakari",
    "gn:country_code":"NG",
    "gn:dem":338,
    "gn:feature_class":"P",
    "gn:feature_code":"PPL",
    "gn:name":"Bulakari",
    "gn:population":0,
    "gn:timezone":"Africa/Lagos",
    "iso:country":"NG",
    "wof:name":"Bulakari",
    "wof:placetype":"locality"
},
  "geometry": {"coordinates":[11.19819,13.15493],"type":"Point"}
}