{
  "type": "Feature",
  "properties": {
    "gn:admin1_code":"50.0",
    "gn:admin2_code":"33014.0",
    "gn:asciiname":"Ekem",
    "gn:country_code":"NG",
    "gn:dem":20,
    "gn:feature_class":"P",
    "gn:feature_code":"PPL",
    "gn:name":"Ekem",
    "gn:population":0,
    "gn:timezone":"Africa/Lagos",
    "iso:country":"NG",
    "name:und_x_variant":[
        "Eken",
        "Ekem"
    ],
    "wof:name":"Ekem",
    "wof:placetype":"locality"
},
  "geometry": {"coordinates":[7.38757,4.61213],"type":"Point"}
}