{
  "type": "Feature",
  "properties": {
    "gn:admin1_code":"48.0",
    "gn:admin2_code":"29009.0",
    "gn:asciiname":"Igbara-Oke",
    "gn:country_code":"NG",
    "gn:dem":353,
    "gn:feature_class":"P",
    "gn:feature_code":"PPLA2",
    "gn:name":"Igbara-Oke",
    "gn:population":0,
    "gn:timezone":"Africa/Lagos",
    "iso:country":"NG",
    "name:und_x_variant":[
        "Igbaraoke"
    ],
    "wof:name":"Igbara-Oke",
    "wof:placetype":"locality"
},
  "geometry": {"coordinates":[5.05805,7.41172],"type":"Point"}
}