{
  "type": "Feature",
  "properties": {
    "gn:admin1_code":"31.0",
    "gn:admin2_code":"27002.0",
    "gn:asciiname":"Makeri",
    "gn:country_code":"NG",
    "gn:dem":205,
    "gn:feature_class":"P",
    "gn:feature_code":"PPL",
    "gn:name":"Makeri",
    "gn:population":0,
    "gn:timezone":"Africa/Lagos",
    "iso:country":"NG",
    "wof:name":"Makeri",
    "wof:placetype":"locality"
},
  "geometry": {"coordinates":[4.41104,10.8118],"type":"Point"}
}