{
  "type": "Feature",
  "properties": {
    "gn:admin1_code":"39.0",
    "gn:admin2_code":"18010.0",
    "gn:admin3_code":"JI1707",
    "gn:asciiname":"Wawanrafi",
    "gn:country_code":"NG",
    "gn:dem":472,
    "gn:feature_class":"P",
    "gn:feature_code":"PPL",
    "gn:name":"Wawanrafi",
    "gn:population":0,
    "gn:timezone":"Africa/Lagos",
    "iso:country":"NG",
    "wof:name":"Wawanrafi",
    "wof:placetype":"locality"
},
  "geometry": {"coordinates":[8.37248,12.61581],"type":"Point"}
}