{
  "type": "Feature",
  "properties": {
    "iso:country":"NG",
    "name:ceb_x_preferred":[
        "Obudu"
    ],
    "name:eng_x_preferred":[
        "Obudu"
    ],
    "name:fra_x_preferred":[
        "Obudu"
    ],
    "name:ita_x_preferred":[
        "Obudu"
    ],
    "name:nan_x_preferred":[
        "Obudu"
    ],
    "name:spa_x_preferred":[
        "Obudu"
    ],
    "name:yor_x_preferred":[
        "Agb\u00e8gb\u00e8 \u00ccj\u1ecdba \u00ccb\u00edl\u1eb9\u0300 Obudu"
    ],
    "name:zho_min_nan_x_preferred":[
        "Obudu"
    ],
    "qs:gn_country":"NG",
    "qs:gn_fcode":"PPL",
    "qs:gn_pop":19668,
    "qs:name":"Obudu",
    "qs:name_adm0":"Nigeria",
    "qs:name_adm1":"Cross River",
    "qs:photos":3,
    "qs:photos_1k":1,
    "qs:photos_9k":1,
    "qs:photos_9r":1,
    "qs:photos_all":3,
    "qs:photos_sr":1,
    "qs:placetype":"Town",
    "qs:pop_sr":"6",
    "qs:woe_adm0":23424908,
    "wd:wordcount":81,
    "wof:name":"Obudu",
    "wof:placetype":"locality",
    "wof:population":19668
},
  "geometry": {"coordinates":[9.17157,6.66737],"type":"Point"}
}