{
  "type": "Feature",
  "properties": {
    "gn:admin1_code":"25.0",
    "gn:admin2_code":"4016.0",
    "gn:asciiname":"Odugiri Obagwe",
    "gn:country_code":"NG",
    "gn:dem":21,
    "gn:feature_class":"P",
    "gn:feature_code":"PPL",
    "gn:name":"Odugiri Obagwe",
    "gn:population":0,
    "gn:timezone":"Africa/Lagos",
    "iso:country":"NG",
    "name:und_x_variant":[
        "Obagwe",
        "Odugiri Obagwe"
    ],
    "wof:name":"Odugiri Obagwe",
    "wof:placetype":"locality"
},
  "geometry": {"coordinates":[6.66001,5.81627],"type":"Point"}
}