{
  "type": "Feature",
  "properties": {
    "gn:admin1_code":"35.0",
    "gn:admin2_code":"2003",
    "gn:asciiname":"Alhaji Jida",
    "gn:country_code":"NG",
    "gn:dem":512,
    "gn:feature_class":"P",
    "gn:feature_code":"PPL",
    "gn:name":"Alhaji Jida",
    "gn:population":0,
    "gn:timezone":"Africa/Lagos",
    "iso:country":"NG",
    "wof:name":"Alhaji Jida",
    "wof:placetype":"locality"
},
  "geometry": {"coordinates":[11.88908,8.64498],"type":"Point"}
}