{
  "type": "Feature",
  "properties": {
    "gn:admin1_code":"48.0",
    "gn:admin2_code":"29004.0",
    "gn:asciiname":"Oka",
    "gn:country_code":"NG",
    "gn:dem":333,
    "gn:feature_class":"P",
    "gn:feature_code":"PPL",
    "gn:name":"Oka",
    "gn:population":0,
    "gn:timezone":"Africa/Lagos",
    "iso:country":"NG",
    "wof:name":"Oka",
    "wof:placetype":"locality"
},
  "geometry": {"coordinates":[5.6204,7.4477],"type":"Point"}
}