{
  "type": "Feature",
  "properties": {
    "gn:admin1_code":"26.0",
    "gn:admin2_code":"7004",
    "gn:asciiname":"Ede",
    "gn:country_code":"NG",
    "gn:dem":126,
    "gn:feature_class":"P",
    "gn:feature_code":"PPL",
    "gn:name":"Ede",
    "gn:population":0,
    "gn:timezone":"Africa/Lagos",
    "iso:country":"NG",
    "wof:name":"Ede",
    "wof:placetype":"locality"
},
  "geometry": {"coordinates":[9.23494,7.17371],"type":"Point"}
}