{
  "type": "Feature",
  "properties": {
    "gn:admin1_code":"30.0",
    "gn:admin2_code":"24014.0",
    "gn:asciiname":"Odofin Eyinafo",
    "gn:country_code":"NG",
    "gn:dem":456,
    "gn:feature_class":"P",
    "gn:feature_code":"PPL",
    "gn:name":"Odofin Eyinafo",
    "gn:population":0,
    "gn:timezone":"Africa/Lagos",
    "iso:country":"NG",
    "wof:name":"Odofin Eyinafo",
    "wof:placetype":"locality"
},
  "geometry": {"coordinates":[5.28333,8.21667],"type":"Point"}
}