{
  "type": "Feature",
  "properties": {
    "gn:admin1_code":"32.0",
    "gn:admin2_code":"31016.0",
    "gn:asciiname":"Budo Agba",
    "gn:country_code":"NG",
    "gn:dem":212,
    "gn:feature_class":"P",
    "gn:feature_code":"PPL",
    "gn:name":"Budo Agba",
    "gn:population":0,
    "gn:timezone":"Africa/Lagos",
    "iso:country":"NG",
    "wof:name":"Budo Agba",
    "wof:placetype":"locality"
},
  "geometry": {"coordinates":[3.51667,7.75],"type":"Point"}
}