{
  "type": "Feature",
  "properties": {
    "gn:admin1_code":"32.0",
    "gn:admin2_code":"31026.0",
    "gn:asciiname":"Olowe",
    "gn:country_code":"NG",
    "gn:dem":154,
    "gn:feature_class":"P",
    "gn:feature_code":"PPL",
    "gn:name":"Olowe",
    "gn:population":0,
    "gn:timezone":"Africa/Lagos",
    "iso:country":"NG",
    "wof:name":"Olowe",
    "wof:placetype":"locality"
},
  "geometry": {"coordinates":[4.03333,7.21667],"type":"Point"}
}