{
  "type": "Feature",
  "properties": {
    "gn:admin1_code":"53.0",
    "gn:admin2_code":"11007",
    "gn:asciiname":"Okwu-Nyonu",
    "gn:country_code":"NG",
    "gn:dem":39,
    "gn:feature_class":"P",
    "gn:feature_code":"PPL",
    "gn:name":"Okwu-Nyonu",
    "gn:population":0,
    "gn:timezone":"Africa/Lagos",
    "iso:country":"NG",
    "wof:name":"Okwu-Nyonu",
    "wof:placetype":"locality"
},
  "geometry": {"coordinates":[8.31511,6.19411],"type":"Point"}
}