{
  "type": "Feature",
  "properties": {
    "gn:admin1_code":"11.0",
    "gn:admin2_code":"15006.0",
    "gn:asciiname":"Jahi",
    "gn:country_code":"NG",
    "gn:dem":459,
    "gn:feature_class":"P",
    "gn:feature_code":"PPL",
    "gn:name":"Jahi",
    "gn:population":0,
    "gn:timezone":"Africa/Lagos",
    "iso:country":"NG",
    "name:fas_x_preferred":[
        "\u062c\u0647\u06cc"
    ],
    "name:jpn_x_preferred":[
        "\u30b8\u30e3\u30d2\u30fc"
    ],
    "wof:name":"Jahi",
    "wof:placetype":"neighbourhood"
},
  "geometry": {"coordinates":[7.4425,9.10417],"type":"Point"}
}