{
  "type": "Feature",
  "properties": {
    "gn:admin1_code":"52.0",
    "gn:asciiname":"Imbikiri",
    "gn:country_code":"NG",
    "gn:dem":8,
    "gn:feature_class":"P",
    "gn:feature_code":"PPL",
    "gn:name":"Imbikiri",
    "gn:population":0,
    "gn:timezone":"Africa/Lagos",
    "iso:country":"NG",
    "wof:name":"Imbikiri",
    "wof:placetype":"neighbourhood"
},
  "geometry": {"coordinates":[6.24713,4.32107],"type":"Point"}
}