{
  "type": "Feature",
  "properties": {
    "gn:admin1_code":"37.0",
    "gn:admin2_code":"12018.0",
    "gn:asciiname":"Ahor",
    "gn:country_code":"NG",
    "gn:dem":128,
    "gn:feature_class":"P",
    "gn:feature_code":"PPL",
    "gn:name":"Ahor",
    "gn:population":0,
    "gn:timezone":"Africa/Lagos",
    "iso:country":"NG",
    "name:cat_x_preferred":[
        "Ahor"
    ],
    "name:ceb_x_preferred":[
        "Ahor"
    ],
    "name:fas_x_preferred":[
        "\u0627\u0647\u0648\u0631"
    ],
    "name:hin_x_preferred":[
        "\u0906\u0939\u094b\u0930"
    ],
    "name:swe_x_preferred":[
        "Ahor"
    ],
    "name:und_x_variant":[
        "Aho",
        "Ahor"
    ],
    "wof:name":"Ahor",
    "wof:placetype":"locality"
},
  "geometry": {"coordinates":[5.71788,6.41707],"type":"Point"}
}