{
  "type": "Feature",
  "properties": {
    "gn:admin1_code":"54.0",
    "gn:admin2_code":"13001.0",
    "gn:asciiname":"Ago-Ijaiye",
    "gn:country_code":"NG",
    "gn:dem":371,
    "gn:feature_class":"P",
    "gn:feature_code":"PPL",
    "gn:name":"Ago-Ijaiye",
    "gn:population":0,
    "gn:timezone":"Africa/Lagos",
    "iso:country":"NG",
    "wof:name":"Ago-Ijaiye",
    "wof:placetype":"locality"
},
  "geometry": {"coordinates":[5.2873,7.66895],"type":"Point"}
}