{
  "type": "Feature",
  "properties": {
    "gn:admin1_code":"30.0",
    "gn:admin2_code":"24012.0",
    "gn:asciiname":"Pako",
    "gn:country_code":"NG",
    "gn:dem":162,
    "gn:feature_class":"P",
    "gn:feature_code":"PPL",
    "gn:name":"Pako",
    "gn:population":0,
    "gn:timezone":"Africa/Lagos",
    "iso:country":"NG",
    "name:bos_x_preferred":[
        "Pako"
    ],
    "name:ceb_x_preferred":[
        "Pako"
    ],
    "name:epo_x_preferred":[
        "Pako"
    ],
    "name:nld_x_preferred":[
        "Pako"
    ],
    "name:pol_x_preferred":[
        "Pako"
    ],
    "name:ron_x_preferred":[
        "Pako"
    ],
    "name:slv_x_preferred":[
        "Pako"
    ],
    "name:ukr_x_preferred":[
        "\u041f\u0430\u043a\u043e"
    ],
    "wof:name":"Pako",
    "wof:placetype":"locality"
},
  "geometry": {"coordinates":[4.83333,9.08333],"type":"Point"}
}