{
  "type": "Feature",
  "properties": {
    "iso:country":"NG",
    "name:cat_x_preferred":[
        "Gboko"
    ],
    "name:dut_x_preferred":[
        "Gboko"
    ],
    "name:eng_x_preferred":[
        "Gboko"
    ],
    "name:epo_x_preferred":[
        "Gboko"
    ],
    "name:fin_x_preferred":[
        "Gboko"
    ],
    "name:fra_x_preferred":[
        "Gboko"
    ],
    "name:fre_x_preferred":[
        "Gboko"
    ],
    "name:ita_x_preferred":[
        "Gboko"
    ],
    "name:pol_x_preferred":[
        "Gboko"
    ],
    "name:por_x_preferred":[
        "Gboko"
    ],
    "name:ron_x_preferred":[
        "Gboko"
    ],
    "name:rum_x_preferred":[
        "Gboko"
    ],
    "name:rus_x_preferred":[
        "\u0413\u0431\u043e\u043a\u043e"
    ],
    "name:yor_x_preferred":[
        "Gboko"
    ],
    "name:zho_min_nan_x_preferred":[
        "Gboko"
    ],
    "qs:gn_country":"NG",
    "qs:gn_fcode":"PPL",
    "qs:gn_pop":0,
    "qs:name":"Gboko",
    "qs:name_adm0":"Nigeria",
    "qs:name_adm1":"Benue",
    "qs:photos":0,
    "qs:photos_1k":0,
    "qs:photos_9k":1,
    "qs:photos_9r":1,
    "qs:photos_all":2,
    "qs:photos_sr":0,
    "qs:placetype":"Town",
    "qs:pop_sr":"7",
    "qs:woe_adm0":23424908,
    "wd:wordcount":477,
    "wof:name":"Gboko",
    "wof:placetype":"locality"
},
  "geometry": {"coordinates":[8.9951,7.3179],"type":"Point"}
}