{
  "type": "Feature",
  "properties": {
    "gn:admin1_code":"40.0",
    "gn:admin2_code":"502.0",
    "gn:admin3_code":"50208",
    "gn:asciiname":"Tukoy",
    "gn:country_code":"NG",
    "gn:dem":220,
    "gn:feature_class":"P",
    "gn:feature_code":"PPL",
    "gn:name":"Tukoy",
    "gn:population":0,
    "gn:timezone":"Africa/Lagos",
    "iso:country":"NG",
    "wof:name":"Tukoy",
    "wof:placetype":"locality"
},
  "geometry": {"coordinates":[3.66419,12.50546],"type":"Point"}
}