{
  "type": "Feature",
  "properties": {
    "gn:admin1_code":"40.0",
    "gn:admin2_code":"509.0",
    "gn:admin3_code":"50906",
    "gn:asciiname":"Kiri",
    "gn:country_code":"NG",
    "gn:dem":281,
    "gn:feature_class":"P",
    "gn:feature_code":"PPL",
    "gn:name":"Kiri",
    "gn:population":0,
    "gn:timezone":"Africa/Lagos",
    "iso:country":"NG",
    "name:ceb_x_preferred":[
        "Kiri"
    ],
    "name:deu_x_preferred":[
        "Kiri"
    ],
    "name:est_x_preferred":[
        "Kiri"
    ],
    "name:fas_x_preferred":[
        "\u06a9\u06cc\u0631\u06cc"
    ],
    "name:fin_x_preferred":[
        "Kiri"
    ],
    "name:fra_x_preferred":[
        "Kiri"
    ],
    "name:ind_x_preferred":[
        "Kiri"
    ],
    "name:ron_x_preferred":[
        "Kiri"
    ],
    "name:spa_x_preferred":[
        "Kiri"
    ],
    "name:swe_x_preferred":[
        "Kiri"
    ],
    "name:ukr_x_preferred":[
        "\u041a\u0456\u0440\u0456"
    ],
    "wof:name":"Kiri",
    "wof:placetype":"locality"
},
  "geometry": {"coordinates":[4.90262,11.62508],"type":"Point"}
}