{
  "type": "Feature",
  "properties": {
    "gn:admin1_code":"40.0",
    "gn:admin2_code":"509.0",
    "gn:admin3_code":"50906",
    "gn:asciiname":"Kiri",
    "gn:country_code":"NG",
    "gn:dem":281,
    "gn:feature_class":"P",
    "gn:feature_code":"PPL",
    "gn:name":"Kiri",
    "gn:population":0,
    "gn:timezone":"Africa/Lagos",
    "iso:country":"NG",
    "wof:name":"Kiri",
    "wof:placetype":"locality"
},
  "geometry": {"coordinates":[4.90262,11.62508],"type":"Point"}
}