{
  "type": "Feature",
  "properties": {
    "gn:admin1_code":"35.0",
    "gn:admin2_code":"2012.0",
    "gn:asciiname":"Yanshuali",
    "gn:country_code":"NG",
    "gn:dem":436,
    "gn:feature_class":"P",
    "gn:feature_code":"PPL",
    "gn:name":"Yanshuali",
    "gn:population":0,
    "gn:timezone":"Africa/Lagos",
    "iso:country":"NG",
    "wof:name":"Yanshuali",
    "wof:placetype":"locality"
},
  "geometry": {"coordinates":[11.99556,8.80838],"type":"Point"}
}