{
  "type": "Feature",
  "properties": {
    "gn:admin1_code":"56.0",
    "gn:admin2_code":"26007.0",
    "gn:asciiname":"Haderi",
    "gn:country_code":"NG",
    "gn:dem":275,
    "gn:feature_class":"P",
    "gn:feature_code":"PPL",
    "gn:name":"Haderi",
    "gn:population":0,
    "gn:timezone":"Africa/Lagos",
    "iso:country":"NG",
    "wof:name":"Haderi",
    "wof:placetype":"locality"
},
  "geometry": {"coordinates":[7.96556,8.88556],"type":"Point"}
}