{
  "type": "Feature",
  "properties": {
    "gn:admin1_code":"27.0",
    "gn:asciiname":"Wuyaku",
    "gn:country_code":"NG",
    "gn:dem":367,
    "gn:feature_class":"P",
    "gn:feature_code":"PPL",
    "gn:name":"Wuyaku",
    "gn:population":0,
    "gn:timezone":"Africa/Lagos",
    "iso:country":"NG",
    "wof:name":"Wuyaku",
    "wof:placetype":"locality"
},
  "geometry": {"coordinates":[12.56764,10.45153],"type":"Point"}
}