{
  "type": "Feature",
  "properties": {
    "gn:admin1_code":"48.0",
    "gn:admin2_code":"29012.0",
    "gn:asciiname":"Ago Oyinbo",
    "gn:country_code":"NG",
    "gn:dem":23,
    "gn:feature_class":"P",
    "gn:feature_code":"PPL",
    "gn:name":"Ago Oyinbo",
    "gn:population":0,
    "gn:timezone":"Africa/Lagos",
    "iso:country":"NG",
    "wof:name":"Ago Oyinbo",
    "wof:placetype":"locality"
},
  "geometry": {"coordinates":[4.95083,6.46052],"type":"Point"}
}