{
  "type": "Feature",
  "properties": {
    "gn:admin1_code":"31.0",
    "gn:admin2_code":"27008",
    "gn:asciiname":"Ndachebara",
    "gn:country_code":"NG",
    "gn:dem":105,
    "gn:feature_class":"P",
    "gn:feature_code":"PPL",
    "gn:name":"Ndachebara",
    "gn:population":0,
    "gn:timezone":"Africa/Lagos",
    "iso:country":"NG",
    "wof:name":"Ndachebara",
    "wof:placetype":"locality"
},
  "geometry": {"coordinates":[6.09303,9.35977],"type":"Point"}
}