{
  "type": "Feature",
  "properties": {
    "gn:admin1_code":"37.0",
    "gn:admin2_code":"12017.0",
    "gn:asciiname":"Aviosi",
    "gn:country_code":"NG",
    "gn:dem":197,
    "gn:feature_class":"P",
    "gn:feature_code":"PPL",
    "gn:name":"Aviosi",
    "gn:population":0,
    "gn:timezone":"Africa/Lagos",
    "iso:country":"NG",
    "wof:name":"Aviosi",
    "wof:placetype":"locality"
},
  "geometry": {"coordinates":[5.91093,6.9576],"type":"Point"}
}