{
  "type": "Feature",
  "properties": {
    "gn:admin1_code":"49.0",
    "gn:asciiname":"Akku",
    "gn:country_code":"NG",
    "gn:dem":1263,
    "gn:feature_class":"P",
    "gn:feature_code":"PPL",
    "gn:name":"Akku",
    "gn:population":0,
    "gn:timezone":"Africa/Lagos",
    "iso:country":"NG",
    "wof:name":"Akku",
    "wof:placetype":"locality"
},
  "geometry": {"coordinates":[8.7179,9.27531],"type":"Point"}
}