{
  "type": "Feature",
  "properties": {
    "gn:admin1_code":"40.0",
    "gn:admin2_code":"509.0",
    "gn:admin3_code":"50901",
    "gn:asciiname":"Chase",
    "gn:country_code":"NG",
    "gn:dem":243,
    "gn:feature_class":"P",
    "gn:feature_code":"PPL",
    "gn:name":"Chase",
    "gn:population":0,
    "gn:timezone":"Africa/Lagos",
    "iso:country":"NG",
    "name:cat_x_preferred":[
        "Chase"
    ],
    "name:ceb_x_preferred":[
        "Chase"
    ],
    "name:ces_x_preferred":[
        "Chase"
    ],
    "name:deu_x_preferred":[
        "Chase"
    ],
    "name:fin_x_preferred":[
        "Chase"
    ],
    "name:fra_x_preferred":[
        "Chase"
    ],
    "name:heb_x_preferred":[
        "\u05e6'\u05d9\u05d9\u05e1"
    ],
    "name:hun_x_preferred":[
        "Chase"
    ],
    "name:ita_x_preferred":[
        "Chase"
    ],
    "name:jpn_x_preferred":[
        "\u30c1\u30a7\u30a4\u30b9"
    ],
    "name:kor_x_preferred":[
        "\uccb4\uc774\uc2a4"
    ],
    "name:nld_x_preferred":[
        "Chase"
    ],
    "name:pol_x_preferred":[
        "Chase"
    ],
    "name:por_x_preferred":[
        "Chase"
    ],
    "name:rus_x_preferred":[
        "Chase"
    ],
    "name:spa_x_preferred":[
        "Chase"
    ],
    "name:srp_x_preferred":[
        "\u0427\u0435\u0458\u0441"
    ],
    "name:swe_x_preferred":[
        "Chase"
    ],
    "name:tha_x_preferred":[
        "\u0e40\u0e0a\u0e2a"
    ],
    "name:vol_x_preferred":[
        "Chase"
    ],
    "wof:name":"Chase",
    "wof:placetype":"locality"
},
  "geometry": {"coordinates":[4.9395,11.3596],"type":"Point"}
}