{
  "type": "Feature",
  "properties": {
    "gn:admin1_code":"24.0",
    "gn:admin2_code":"417.0",
    "gn:admin3_code":"41703",
    "gn:asciiname":"Tagwayan Marke",
    "gn:country_code":"NG",
    "gn:dem":565,
    "gn:feature_class":"P",
    "gn:feature_code":"PPL",
    "gn:name":"Tagwayan Marke",
    "gn:population":0,
    "gn:timezone":"Africa/Lagos",
    "iso:country":"NG",
    "wof:name":"Tagwayan Marke",
    "wof:placetype":"locality"
},
  "geometry": {"coordinates":[7.84232,11.79255],"type":"Point"}
}