{
  "type": "Feature",
  "properties": {
    "gn:admin1_code":"43.0",
    "gn:admin2_code":"35003",
    "gn:asciiname":"Bosha",
    "gn:country_code":"NG",
    "gn:dem":209,
    "gn:feature_class":"P",
    "gn:feature_code":"PPL",
    "gn:name":"Bosha",
    "gn:population":0,
    "gn:timezone":"Africa/Lagos",
    "iso:country":"NG",
    "name:hye_x_preferred":[
        "\u0532\u0578\u0577\u0561"
    ],
    "wof:name":"Bosha",
    "wof:placetype":"locality"
},
  "geometry": {"coordinates":[9.89454,7.62479],"type":"Point"}
}