{
  "type": "Feature",
  "properties": {
    "gn:admin1_code":"25.0",
    "gn:admin2_code":"4002.0",
    "gn:asciiname":"Ukwu-Abwa",
    "gn:country_code":"NG",
    "gn:dem":84,
    "gn:feature_class":"P",
    "gn:feature_code":"PPL",
    "gn:name":"Ukwu-Abwa",
    "gn:population":0,
    "gn:timezone":"Africa/Lagos",
    "iso:country":"NG",
    "name:eng_x_preferred":[
        "Ukwu-Abwa"
    ],
    "wof:name":"Ukwu-Abwa",
    "wof:placetype":"locality"
},
  "geometry": {"coordinates":[6.80747,6.22986],"type":"Point"}
}