{
  "type": "Feature",
  "properties": {
    "gn:admin1_code":"26.0",
    "gn:asciiname":"Ekwakwa",
    "gn:country_code":"NG",
    "gn:dem":59,
    "gn:feature_class":"P",
    "gn:feature_code":"PPL",
    "gn:name":"Ekwakwa",
    "gn:population":0,
    "gn:timezone":"Africa/Lagos",
    "iso:country":"NG",
    "name:und_x_variant":[
        "Eke",
        "Ekwakwa"
    ],
    "wof:name":"Ekwakwa",
    "wof:placetype":"locality"
},
  "geometry": {"coordinates":[7.98333,7.93333],"type":"Point"}
}