{
  "type": "Feature",
  "properties": {
    "gn:admin1_code":"44.0",
    "gn:admin2_code":"715.0",
    "gn:admin3_code":"71503",
    "gn:asciiname":"Biriri",
    "gn:country_code":"NG",
    "gn:dem":357,
    "gn:feature_class":"P",
    "gn:feature_code":"PPL",
    "gn:name":"Biriri",
    "gn:population":0,
    "gn:timezone":"Africa/Lagos",
    "iso:country":"NG",
    "name:und_x_variant":[
        "Bariri",
        "Biriri"
    ],
    "wof:name":"Biriri",
    "wof:placetype":"locality"
},
  "geometry": {"coordinates":[11.7779,12.056],"type":"Point"}
}