{
  "type": "Feature",
  "properties": {
    "gn:admin1_code":"23.0",
    "gn:admin2_code":"19018.0",
    "gn:admin3_code":"KD1804",
    "gn:asciiname":"Ungwan Mummini",
    "gn:country_code":"NG",
    "gn:dem":664,
    "gn:feature_class":"P",
    "gn:feature_code":"PPL",
    "gn:name":"Ungwan Mummini",
    "gn:population":0,
    "gn:timezone":"Africa/Lagos",
    "iso:country":"NG",
    "wof:name":"Ungwan Mummini",
    "wof:placetype":"locality"
},
  "geometry": {"coordinates":[7.92688,11.30514],"type":"Point"}
}