{
  "type": "Feature",
  "properties": {
    "gn:admin1_code":"43.0",
    "gn:admin2_code":"35005.0",
    "gn:asciiname":"Kwarafa",
    "gn:country_code":"NG",
    "gn:dem":183,
    "gn:feature_class":"P",
    "gn:feature_code":"PPL",
    "gn:name":"Kwarafa",
    "gn:population":0,
    "gn:timezone":"Africa/Lagos",
    "iso:country":"NG",
    "name:und_x_variant":[
        "Kwararfa"
    ],
    "wof:name":"Kwarafa",
    "wof:placetype":"locality"
},
  "geometry": {"coordinates":[10.39236,8.23331],"type":"Point"}
}