{
  "type": "Feature",
  "properties": {
    "gn:admin1_code":"41.0",
    "gn:admin2_code":"23012.0",
    "gn:asciiname":"Numai",
    "gn:country_code":"NG",
    "gn:dem":35,
    "gn:feature_class":"P",
    "gn:feature_code":"PPL",
    "gn:name":"Numai",
    "gn:population":0,
    "gn:timezone":"Africa/Lagos",
    "iso:country":"NG",
    "wof:name":"Numai",
    "wof:placetype":"locality"
},
  "geometry": {"coordinates":[6.76667,7.81667],"type":"Point"}
}