{
  "type": "Feature",
  "properties": {
    "gn:admin1_code":"24.0",
    "gn:asciiname":"Garu",
    "gn:country_code":"NG",
    "gn:dem":637,
    "gn:feature_class":"P",
    "gn:feature_code":"PPL",
    "gn:name":"Garu",
    "gn:population":0,
    "gn:timezone":"Africa/Lagos",
    "iso:country":"NG",
    "wof:name":"Garu",
    "wof:placetype":"locality"
},
  "geometry": {"coordinates":[7.70917,11.25136],"type":"Point"}
}