{
  "type": "Feature",
  "properties": {
    "gn:country":"NG",
    "gn:fcode":"PPL",
    "gn:population":9204,
    "iso:country":"NG",
    "name:und_x_variant":[
        "Ejinrin"
    ],
    "qs:name":"Ejirin",
    "qs:photos_9r":0,
    "qs:photos_sr":0,
    "qs:pop_sr":"5",
    "wof:name":"Ejirin",
    "wof:placetype":"locality",
    "wof:population":9204
},
  "geometry": {"coordinates":[3.90019,6.61423],"type":"Point"}
}