{
  "type": "Feature",
  "properties": {
    "gn:admin1_code":"23.0",
    "gn:admin2_code":"19022.0",
    "gn:admin3_code":"KD2203",
    "gn:asciiname":"Anza",
    "gn:country_code":"NG",
    "gn:dem":780,
    "gn:feature_class":"P",
    "gn:feature_code":"PPL",
    "gn:name":"Anza",
    "gn:population":0,
    "gn:timezone":"Africa/Lagos",
    "iso:country":"NG",
    "name:ara_x_preferred":[
        "\u0639\u0646\u0632\u0629"
    ],
    "name:ceb_x_preferred":[
        "Anza"
    ],
    "name:deu_x_preferred":[
        "Anza"
    ],
    "name:hrv_x_preferred":[
        "Anza"
    ],
    "name:ita_x_preferred":[
        "Anza"
    ],
    "name:nld_x_preferred":[
        "Anza"
    ],
    "name:pol_x_preferred":[
        "Anza"
    ],
    "name:rus_x_preferred":[
        "\u0410\u043d\u0437\u0430"
    ],
    "name:swe_x_preferred":[
        "Anza"
    ],
    "wof:name":"Anza",
    "wof:placetype":"locality"
},
  "geometry": {"coordinates":[8.21118,9.8357],"type":"Point"}
}