{
  "type": "Feature",
  "properties": {
    "gn:admin1_code":"27.0",
    "gn:admin2_code":"107.0",
    "gn:admin3_code":"10701",
    "gn:asciiname":"Mugala",
    "gn:country_code":"NG",
    "gn:dem":452,
    "gn:feature_class":"P",
    "gn:feature_code":"PPL",
    "gn:name":"Mugala",
    "gn:population":0,
    "gn:timezone":"Africa/Lagos",
    "iso:country":"NG",
    "wof:name":"Mugala",
    "wof:placetype":"locality"
},
  "geometry": {"coordinates":[12.44756,10.83777],"type":"Point"}
}