{
  "type": "Feature",
  "properties": {
    "gn:admin1_code":"37.0",
    "gn:admin2_code":"12015.0",
    "gn:asciiname":"Izide",
    "gn:country_code":"NG",
    "gn:dem":18,
    "gn:feature_class":"P",
    "gn:feature_code":"PPL",
    "gn:name":"Izide",
    "gn:population":0,
    "gn:timezone":"Africa/Lagos",
    "iso:country":"NG",
    "name:und_x_variant":[
        "Izide-N-Ame",
        "Izide"
    ],
    "wof:name":"Izide",
    "wof:placetype":"locality"
},
  "geometry": {"coordinates":[5.13687,6.46192],"type":"Point"}
}