{
  "type": "Feature",
  "properties": {
    "gn:admin1_code":"26.0",
    "gn:admin2_code":"7010.0",
    "gn:asciiname":"Uta",
    "gn:country_code":"NG",
    "gn:dem":103,
    "gn:feature_class":"P",
    "gn:feature_code":"PPL",
    "gn:name":"Uta",
    "gn:population":0,
    "gn:timezone":"Africa/Lagos",
    "iso:country":"NG",
    "name:lat_x_preferred":[
        "Uta"
    ],
    "name:nld_x_preferred":[
        "Uta"
    ],
    "name:por_x_preferred":[
        "Uta"
    ],
    "name:swe_x_preferred":[
        "Uta"
    ],
    "wof:name":"Uta",
    "wof:placetype":"locality"
},
  "geometry": {"coordinates":[8.67325,7.09971],"type":"Point"}
}