{
  "type": "Feature",
  "properties": {
    "gn:admin1_code":"56.0",
    "gn:admin2_code":"26007",
    "gn:asciiname":"Gidan Audu",
    "gn:country_code":"NG",
    "gn:dem":351,
    "gn:feature_class":"P",
    "gn:feature_code":"PPL",
    "gn:name":"Gidan Audu",
    "gn:population":0,
    "gn:timezone":"Africa/Lagos",
    "iso:country":"NG",
    "wof:name":"Gidan Audu",
    "wof:placetype":"locality"
},
  "geometry": {"coordinates":[7.96926,9.0338],"type":"Point"}
}