{
  "type": "Feature",
  "properties": {
    "gn:admin1_code":"35.0",
    "gn:admin2_code":"2008.0",
    "gn:asciiname":"Jalingo Fulani",
    "gn:country_code":"NG",
    "gn:dem":376,
    "gn:feature_class":"P",
    "gn:feature_code":"PPL",
    "gn:name":"Jalingo Fulani",
    "gn:population":0,
    "gn:timezone":"Africa/Lagos",
    "iso:country":"NG",
    "wof:name":"Jalingo Fulani",
    "wof:placetype":"locality"
},
  "geometry": {"coordinates":[12.37764,8.71557],"type":"Point"}
}