{
  "type": "Feature",
  "properties": {
    "gn:admin1_code":"35.0",
    "gn:admin2_code":"2020.0",
    "gn:asciiname":"Sangkan",
    "gn:country_code":"NG",
    "gn:dem":174,
    "gn:feature_class":"P",
    "gn:feature_code":"PPL",
    "gn:name":"Sangkan",
    "gn:population":0,
    "gn:timezone":"Africa/Lagos",
    "iso:country":"NG",
    "name:eng_x_preferred":[
        "Sangkan"
    ],
    "name:und_x_variant":[
        "Sangala",
        "Changala"
    ],
    "wof:name":"Sangkan",
    "wof:placetype":"locality"
},
  "geometry": {"coordinates":[12.3374,9.36932],"type":"Point"}
}