{
  "type": "Feature",
  "properties": {
    "gn:admin1_code":"21.0",
    "gn:admin2_code":"3009.0",
    "gn:asciiname":"Ikot Akpan Abia",
    "gn:country_code":"NG",
    "gn:dem":61,
    "gn:feature_class":"P",
    "gn:feature_code":"PPL",
    "gn:name":"Ikot Akpan Abia",
    "gn:population":0,
    "gn:timezone":"Africa/Lagos",
    "iso:country":"NG",
    "wof:name":"Ikot Akpan Abia",
    "wof:placetype":"neighbourhood"
},
  "geometry": {"coordinates":[7.90517,4.98264],"type":"Point"}
}