{
  "type": "Feature",
  "properties": {
    "gn:admin1_code":"30.0",
    "gn:admin2_code":"24009.0",
    "gn:asciiname":"Aran Orin",
    "gn:cc2":"NG",
    "gn:country_code":"NG",
    "gn:dem":564,
    "gn:feature_class":"P",
    "gn:feature_code":"PPL",
    "gn:name":"Aran Orin",
    "gn:population":0,
    "gn:timezone":"Africa/Lagos",
    "iso:country":"NG",
    "name:und_x_variant":[
        "Ara-Orin",
        "Aran Orin"
    ],
    "wof:name":"Aran Orin",
    "wof:placetype":"locality"
},
  "geometry": {"coordinates":[5.06667,8.08333],"type":"Point"}
}