{
  "type": "Feature",
  "properties": {
    "gn:admin1_code":"31.0",
    "gn:admin2_code":"27022.0",
    "gn:asciiname":"Masuku",
    "gn:country_code":"NG",
    "gn:dem":530,
    "gn:feature_class":"P",
    "gn:feature_code":"PPL",
    "gn:name":"Masuku",
    "gn:population":0,
    "gn:timezone":"Africa/Lagos",
    "iso:country":"NG",
    "name:und_x_variant":[
        "Masaka",
        "Masuku"
    ],
    "wof:name":"Masuku",
    "wof:placetype":"locality"
},
  "geometry": {"coordinates":[6.63999,10.48586],"type":"Point"}
}