{
  "type": "Feature",
  "properties": {
    "gn:admin1_code":"53.0",
    "gn:admin2_code":"11012.0",
    "gn:asciiname":"Amokwo Okposieshi",
    "gn:country_code":"NG",
    "gn:dem":126,
    "gn:feature_class":"P",
    "gn:feature_code":"PPL",
    "gn:name":"Amokwo Okposieshi",
    "gn:population":0,
    "gn:timezone":"Africa/Lagos",
    "iso:country":"NG",
    "wof:name":"Amokwo Okposieshi",
    "wof:placetype":"locality"
},
  "geometry": {"coordinates":[7.94466,6.50391],"type":"Point"}
}