{
  "type": "Feature",
  "properties": {
    "gn:admin1_code":"52.0",
    "gn:admin2_code":"6006.0",
    "gn:asciiname":"Urhobo-Camp",
    "gn:country_code":"NG",
    "gn:dem":17,
    "gn:feature_class":"P",
    "gn:feature_code":"PPL",
    "gn:name":"Urhobo-Camp",
    "gn:population":0,
    "gn:timezone":"Africa/Lagos",
    "iso:country":"NG",
    "wof:name":"Urhobo-Camp",
    "wof:placetype":"locality"
},
  "geometry": {"coordinates":[6.2445,5.22791],"type":"Point"}
}