{
  "type": "Feature",
  "properties": {
    "gn:admin1_code":"23.0",
    "gn:admin2_code":"19006.0",
    "gn:admin3_code":"KD0605",
    "gn:asciiname":"Unguwa Sanyi",
    "gn:country_code":"NG",
    "gn:dem":734,
    "gn:feature_class":"P",
    "gn:feature_code":"PPL",
    "gn:name":"Unguwa Sanyi",
    "gn:population":0,
    "gn:timezone":"Africa/Lagos",
    "iso:country":"NG",
    "name:und_x_variant":[
        "Unguwar Sanyi"
    ],
    "wof:name":"Unguwa Sanyi",
    "wof:placetype":"locality"
},
  "geometry": {"coordinates":[7.97746,9.60387],"type":"Point"}
}