{
  "type": "Feature",
  "properties": {
    "gn:admin1_code":"44.0",
    "gn:admin2_code":"702.0",
    "gn:admin3_code":"70206",
    "gn:asciiname":"Garandoili",
    "gn:country_code":"NG",
    "gn:dem":340,
    "gn:feature_class":"P",
    "gn:feature_code":"PPL",
    "gn:name":"Garandoili",
    "gn:population":0,
    "gn:timezone":"Africa/Lagos",
    "iso:country":"NG",
    "wof:name":"Garandoili",
    "wof:placetype":"locality"
},
  "geometry": {"coordinates":[11.22359,12.80248],"type":"Point"}
}