{
  "type": "Feature",
  "properties": {
    "gn:admin1_code":"16.0",
    "gn:admin2_code":"28017.0",
    "gn:asciiname":"Egbe",
    "gn:country_code":"NG",
    "gn:dem":45,
    "gn:feature_class":"P",
    "gn:feature_code":"PPL",
    "gn:name":"Egbe",
    "gn:population":0,
    "gn:timezone":"Africa/Lagos",
    "iso:country":"NG",
    "wof:name":"Egbe",
    "wof:placetype":"locality"
},
  "geometry": {"coordinates":[3.88607,6.79834],"type":"Point"}
}