{
  "type": "Feature",
  "properties": {
    "gn:admin1_code":"49.0",
    "gn:admin2_code":"32001.0",
    "gn:asciiname":"Bar-n-Bako",
    "gn:country_code":"NG",
    "gn:dem":1207,
    "gn:feature_class":"P",
    "gn:feature_code":"PPL",
    "gn:name":"Bar-n-Bako",
    "gn:population":0,
    "gn:timezone":"Africa/Lagos",
    "iso:country":"NG",
    "name:und_x_variant":[
        "Bar-N-Bako",
        "Barikin Bako",
        "Bar-n-Bako"
    ],
    "wof:name":"Bar-n-Bako",
    "wof:placetype":"locality"
},
  "geometry": {"coordinates":[8.94281,9.73738],"type":"Point"}
}