{
  "type": "Feature",
  "properties": {
    "gn:admin1_code":"48.0",
    "gn:admin2_code":"29001.0",
    "gn:asciiname":"Boropa",
    "gn:country_code":"NG",
    "gn:dem":372,
    "gn:feature_class":"P",
    "gn:feature_code":"PPL",
    "gn:name":"Boropa",
    "gn:population":0,
    "gn:timezone":"Africa/Lagos",
    "iso:country":"NG",
    "wof:name":"Boropa",
    "wof:placetype":"locality"
},
  "geometry": {"coordinates":[5.8521,7.53352],"type":"Point"}
}