{
  "type": "Feature",
  "properties": {
    "gn:admin1_code":"50.0",
    "gn:admin2_code":"33001.0",
    "gn:asciiname":"Ighom",
    "gn:country_code":"NG",
    "gn:dem":12,
    "gn:feature_class":"P",
    "gn:feature_code":"PPL",
    "gn:name":"Ighom",
    "gn:population":0,
    "gn:timezone":"Africa/Lagos",
    "iso:country":"NG",
    "wof:name":"Ighom",
    "wof:placetype":"locality"
},
  "geometry": {"coordinates":[6.63505,4.76422],"type":"Point"}
}