{
  "type": "Feature",
  "properties": {
    "gn:admin1_code":"44.0",
    "gn:admin2_code":"713.0",
    "gn:admin3_code":"71301",
    "gn:asciiname":"Merwa Gana",
    "gn:country_code":"NG",
    "gn:dem":350,
    "gn:feature_class":"P",
    "gn:feature_code":"PPL",
    "gn:name":"Merwa Gana",
    "gn:population":0,
    "gn:timezone":"Africa/Lagos",
    "iso:country":"NG",
    "name:und_x_variant":[
        "Murba Gana",
        "Merwa Gana"
    ],
    "wof:name":"Merwa Gana",
    "wof:placetype":"locality"
},
  "geometry": {"coordinates":[10.32741,13.03368],"type":"Point"}
}