{
  "type": "Feature",
  "properties": {
    "gn:admin1_code":"16.0",
    "gn:admin2_code":"28003.0",
    "gn:asciiname":"Igboloye",
    "gn:country_code":"NG",
    "gn:dem":51,
    "gn:feature_class":"P",
    "gn:feature_code":"PPL",
    "gn:name":"Igboloye",
    "gn:population":0,
    "gn:timezone":"Africa/Lagos",
    "iso:country":"NG",
    "wof:name":"Igboloye",
    "wof:placetype":"neighbourhood"
},
  "geometry": {"coordinates":[3.15253,6.68274],"type":"Point"}
}