{
  "type": "Feature",
  "properties": {
    "gn:admin1_code":"39.0",
    "gn:admin2_code":"18025.0",
    "gn:admin3_code":"JI1902",
    "gn:asciiname":"Kadira",
    "gn:country_code":"NG",
    "gn:dem":382,
    "gn:feature_class":"P",
    "gn:feature_code":"PPL",
    "gn:name":"Kadira",
    "gn:population":0,
    "gn:timezone":"Africa/Lagos",
    "iso:country":"NG",
    "wof:name":"Kadira",
    "wof:placetype":"locality"
},
  "geometry": {"coordinates":[9.66667,11.91667],"type":"Point"}
}