{
  "type": "Feature",
  "properties": {
    "gn:admin1_code":"23.0",
    "gn:admin2_code":"19022.0",
    "gn:admin3_code":"KD2203",
    "gn:asciiname":"Dutsin Bako",
    "gn:country_code":"NG",
    "gn:dem":798,
    "gn:feature_class":"P",
    "gn:feature_code":"PPL",
    "gn:name":"Dutsin Bako",
    "gn:population":0,
    "gn:timezone":"Africa/Lagos",
    "iso:country":"NG",
    "name:und_x_variant":[
        "Duchin Bako Station",
        "Dutsin Bako"
    ],
    "wof:name":"Dutsin Bako",
    "wof:placetype":"locality"
},
  "geometry": {"coordinates":[8.1496,9.97485],"type":"Point"}
}