{
  "type": "Feature",
  "properties": {
    "gn:admin1_code":"32.0",
    "gn:admin2_code":"31011.0",
    "gn:asciiname":"Ebo",
    "gn:country_code":"NG",
    "gn:dem":154,
    "gn:feature_class":"P",
    "gn:feature_code":"PPL",
    "gn:name":"Ebo",
    "gn:population":0,
    "gn:timezone":"Africa/Lagos",
    "iso:country":"NG",
    "name:ceb_x_preferred":[
        "Ebo"
    ],
    "name:por_x_preferred":[
        "Ebo"
    ],
    "name:swe_x_preferred":[
        "Ebo"
    ],
    "wof:name":"Ebo",
    "wof:placetype":"locality"
},
  "geometry": {"coordinates":[3.23333,7.43333],"type":"Point"}
}