{
  "type": "Feature",
  "properties": {
    "gn:admin1_code":"55.0",
    "gn:admin2_code":"16002.0",
    "gn:asciiname":"Kwarge",
    "gn:country_code":"NG",
    "gn:dem":313,
    "gn:feature_class":"P",
    "gn:feature_code":"PPL",
    "gn:name":"Kwarge",
    "gn:population":0,
    "gn:timezone":"Africa/Lagos",
    "iso:country":"NG",
    "wof:name":"Kwarge",
    "wof:placetype":"locality"
},
  "geometry": {"coordinates":[11.56667,9.71667],"type":"Point"}
}