{
  "type": "Feature",
  "properties": {
    "gn:admin1_code":"24.0",
    "gn:asciiname":"Gangara",
    "gn:country_code":"NG",
    "gn:dem":398,
    "gn:feature_class":"P",
    "gn:feature_code":"PPL",
    "gn:name":"Gangara",
    "gn:population":0,
    "gn:timezone":"Africa/Lagos",
    "iso:country":"NG",
    "name:ceb_x_preferred":[
        "Gangara"
    ],
    "name:nor_x_preferred":[
        "Gangara"
    ],
    "name:spa_x_preferred":[
        "Gangara"
    ],
    "name:swe_x_preferred":[
        "Gangara"
    ],
    "name:vie_x_preferred":[
        "Gangara"
    ],
    "name:war_x_preferred":[
        "Gangara"
    ],
    "wof:name":"Gangara",
    "wof:placetype":"locality"
},
  "geometry": {"coordinates":[8.80267,12.6649],"type":"Point"}
}