{
  "type": "Feature",
  "properties": {
    "gn:admin1_code":"35.0",
    "gn:admin2_code":"2021.0",
    "gn:asciiname":"Bargare",
    "gn:country_code":"NG",
    "gn:dem":195,
    "gn:feature_class":"P",
    "gn:feature_code":"PPL",
    "gn:name":"Bargare",
    "gn:population":0,
    "gn:timezone":"Africa/Lagos",
    "iso:country":"NG",
    "name:eng_x_preferred":[
        "Bargare"
    ],
    "wof:name":"Bargare",
    "wof:placetype":"locality"
},
  "geometry": {"coordinates":[12.41138,9.22779],"type":"Point"}
}