{
  "type": "Feature",
  "properties": {
    "gn:admin1_code":"26.0",
    "gn:admin2_code":"7010.0",
    "gn:asciiname":"Yeke",
    "gn:country_code":"NG",
    "gn:dem":126,
    "gn:feature_class":"P",
    "gn:feature_code":"PPL",
    "gn:name":"Yeke",
    "gn:population":0,
    "gn:timezone":"Africa/Lagos",
    "iso:country":"NG",
    "name:ceb_x_preferred":[
        "Yeke"
    ],
    "name:fra_x_preferred":[
        "Yeke"
    ],
    "name:swe_x_preferred":[
        "Yeke"
    ],
    "wof:name":"Yeke",
    "wof:placetype":"locality"
},
  "geometry": {"coordinates":[8.55627,7.19501],"type":"Point"}
}