{
  "type": "Feature",
  "properties": {
    "gn:admin1_code":"43.0",
    "gn:asciiname":"Yakoko Lawan",
    "gn:country_code":"NG",
    "gn:dem":339,
    "gn:feature_class":"P",
    "gn:feature_code":"PPL",
    "gn:name":"Yakoko Lawan",
    "gn:population":0,
    "gn:timezone":"Africa/Lagos",
    "iso:country":"NG",
    "name:eng_x_preferred":[
        "Yakoko Lawan"
    ],
    "wof:name":"Yakoko Lawan",
    "wof:placetype":"locality"
},
  "geometry": {"coordinates":[11.59557,9.12331],"type":"Point"}
}