{
  "type": "Feature",
  "properties": {
    "gn:admin1_code":"49.0",
    "gn:admin2_code":"32011.0",
    "gn:asciiname":"Gennaret",
    "gn:country_code":"NG",
    "gn:dem":1123,
    "gn:feature_class":"P",
    "gn:feature_code":"PPL",
    "gn:name":"Gennaret",
    "gn:population":0,
    "gn:timezone":"Africa/Lagos",
    "iso:country":"NG",
    "name:eng_x_preferred":[
        "Gennaret"
    ],
    "wof:name":"Gennaret",
    "wof:placetype":"locality"
},
  "geometry": {"coordinates":[9.27079,9.50233],"type":"Point"}
}