{
  "type": "Feature",
  "properties": {
    "gn:admin1_code":"29.0",
    "gn:admin2_code":"20028.0",
    "gn:admin3_code":"KN0605",
    "gn:asciiname":"Gafan",
    "gn:country_code":"NG",
    "gn:dem":484,
    "gn:feature_class":"P",
    "gn:feature_code":"PPL",
    "gn:name":"Gafan",
    "gn:population":0,
    "gn:timezone":"Africa/Lagos",
    "iso:country":"NG",
    "wof:name":"Gafan",
    "wof:placetype":"locality"
},
  "geometry": {"coordinates":[8.44974,11.67361],"type":"Point"}
}