{
  "type": "Feature",
  "properties": {
    "gn:admin1_code":"35.0",
    "gn:admin2_code":"2010.0",
    "gn:asciiname":"Milding",
    "gn:country_code":"NG",
    "gn:dem":580,
    "gn:feature_class":"P",
    "gn:feature_code":"PPL",
    "gn:name":"Milding",
    "gn:population":0,
    "gn:timezone":"Africa/Lagos",
    "iso:country":"NG",
    "wof:name":"Milding",
    "wof:placetype":"locality"
},
  "geometry": {"coordinates":[13.55861,10.75961],"type":"Point"}
}