{
  "type": "Feature",
  "properties": {
    "gn:admin1_code":"29.0",
    "gn:admin2_code":"20010.0",
    "gn:admin3_code":"KN1702",
    "gn:asciiname":"Malla Mawa",
    "gn:country_code":"NG",
    "gn:dem":446,
    "gn:feature_class":"P",
    "gn:feature_code":"PPL",
    "gn:name":"Malla Mawa",
    "gn:population":0,
    "gn:timezone":"Africa/Lagos",
    "iso:country":"NG",
    "wof:name":"Malla Mawa",
    "wof:placetype":"locality"
},
  "geometry": {"coordinates":[8.74871,12.00069],"type":"Point"}
}