{
  "type": "Feature",
  "properties": {
    "gn:admin1_code":"23.0",
    "gn:admin2_code":"19021.0",
    "gn:admin3_code":"KD2106",
    "gn:asciiname":"Ungwan Turaki",
    "gn:country_code":"NG",
    "gn:dem":663,
    "gn:feature_class":"P",
    "gn:feature_code":"PPL",
    "gn:name":"Ungwan Turaki",
    "gn:population":0,
    "gn:timezone":"Africa/Lagos",
    "iso:country":"NG",
    "wof:name":"Ungwan Turaki",
    "wof:placetype":"locality"
},
  "geometry": {"coordinates":[8.00061,11.15689],"type":"Point"}
}