{
  "type": "Feature",
  "properties": {
    "gn:admin1_code":"46.0",
    "gn:admin2_code":"5014.0",
    "gn:admin3_code":"BA1401",
    "gn:asciiname":"Fagurum",
    "gn:country_code":"NG",
    "gn:dem":442,
    "gn:feature_class":"P",
    "gn:feature_code":"PPL",
    "gn:name":"Fagurum",
    "gn:population":0,
    "gn:timezone":"Africa/Lagos",
    "iso:country":"NG",
    "wof:name":"Fagurum",
    "wof:placetype":"locality"
},
  "geometry": {"coordinates":[10.3826,11.4453],"type":"Point"}
}