{
  "type": "Feature",
  "properties": {
    "gn:admin1_code":"51.0",
    "gn:admin2_code":"610.0",
    "gn:admin3_code":"61009",
    "gn:asciiname":"Maigaraja Lumu",
    "gn:country_code":"NG",
    "gn:dem":198,
    "gn:feature_class":"P",
    "gn:feature_code":"PPL",
    "gn:name":"Maigaraja Lumu",
    "gn:population":0,
    "gn:timezone":"Africa/Lagos",
    "iso:country":"NG",
    "wof:name":"Maigaraja Lumu",
    "wof:placetype":"locality"
},
  "geometry": {"coordinates":[4.6571,11.68495],"type":"Point"}
}