{
  "type": "Feature",
  "properties": {
    "gn:admin1_code":"40.0",
    "gn:admin2_code":"509.0",
    "gn:admin3_code":"50908",
    "gn:asciiname":"Tudun Wada",
    "gn:country_code":"NG",
    "gn:dem":296,
    "gn:feature_class":"P",
    "gn:feature_code":"PPL",
    "gn:name":"Tudun Wada",
    "gn:population":0,
    "gn:timezone":"Africa/Lagos",
    "iso:country":"NG",
    "name:ceb_x_preferred":[
        "Tudun Wada"
    ],
    "name:fra_x_preferred":[
        "Tudun Wada"
    ],
    "name:hau_x_preferred":[
        "Tudun Wada"
    ],
    "name:ita_x_preferred":[
        "Tudun Wada"
    ],
    "name:spa_x_preferred":[
        "Tudun Wada"
    ],
    "wof:name":"Tudun Wada",
    "wof:placetype":"locality"
},
  "geometry": {"coordinates":[5.08671,11.48686],"type":"Point"}
}