{
  "type": "Feature",
  "properties": {
    "gn:admin1_code":"37.0",
    "gn:admin2_code":"12001.0",
    "gn:asciiname":"Ineme-Ekpe",
    "gn:country_code":"NG",
    "gn:dem":338,
    "gn:feature_class":"P",
    "gn:feature_code":"PPL",
    "gn:name":"Ineme-Ekpe",
    "gn:population":0,
    "gn:timezone":"Africa/Lagos",
    "iso:country":"NG",
    "wof:name":"Ineme-Ekpe",
    "wof:placetype":"locality"
},
  "geometry": {"coordinates":[6.1743,7.4177],"type":"Point"}
}