{
  "type": "Feature",
  "properties": {
    "gn:admin1_code":"31.0",
    "gn:admin2_code":"27018.0",
    "gn:asciiname":"Gidan Ganaga",
    "gn:country_code":"NG",
    "gn:dem":383,
    "gn:feature_class":"P",
    "gn:feature_code":"PPL",
    "gn:name":"Gidan Ganaga",
    "gn:population":0,
    "gn:timezone":"Africa/Lagos",
    "iso:country":"NG",
    "name:und_x_variant":[
        "Gidan Ganga"
    ],
    "wof:name":"Gidan Ganaga",
    "wof:placetype":"locality"
},
  "geometry": {"coordinates":[6.87748,9.78771],"type":"Point"}
}