{
  "type": "Feature",
  "properties": {
    "gn:admin1_code":"41.0",
    "gn:admin2_code":"23005.0",
    "gn:asciiname":"Aloko",
    "gn:country_code":"NG",
    "gn:dem":170,
    "gn:feature_class":"P",
    "gn:feature_code":"PPL",
    "gn:name":"Aloko",
    "gn:population":0,
    "gn:timezone":"Africa/Lagos",
    "iso:country":"NG",
    "name:und_x_variant":[
        "Egudi"
    ],
    "wof:name":"Aloko",
    "wof:placetype":"locality"
},
  "geometry": {"coordinates":[7.32051,7.80029],"type":"Point"}
}