{
  "type": "Feature",
  "properties": {
    "gn:admin1_code":"46.0",
    "gn:admin2_code":"5002.0",
    "gn:admin3_code":"BA0207",
    "gn:asciiname":"Yelwa",
    "gn:country_code":"NG",
    "gn:dem":613,
    "gn:feature_class":"P",
    "gn:feature_code":"PPL",
    "gn:name":"Yelwa",
    "gn:population":0,
    "gn:timezone":"Africa/Lagos",
    "iso:country":"NG",
    "name:cat_x_preferred":[
        "Yelwa"
    ],
    "name:pol_x_preferred":[
        "Yelwa"
    ],
    "wof:name":"Yelwa",
    "wof:placetype":"locality"
},
  "geometry": {"coordinates":[9.79245,10.27753],"type":"Point"}
}