{
  "type": "Feature",
  "properties": {
    "gn:admin1_code":"46.0",
    "gn:admin2_code":"5018.0",
    "gn:admin3_code":"BA1809",
    "gn:asciiname":"Kari",
    "gn:country_code":"NG",
    "gn:dem":804,
    "gn:feature_class":"P",
    "gn:feature_code":"PPL",
    "gn:name":"Kari",
    "gn:population":0,
    "gn:timezone":"Africa/Lagos",
    "iso:country":"NG",
    "wof:name":"Kari",
    "wof:placetype":"locality"
},
  "geometry": {"coordinates":[8.96317,10.69355],"type":"Point"}
}