{
  "type": "Feature",
  "properties": {
    "gn:admin1_code":"21.0",
    "gn:asciiname":"Mbiabo Abasi Efiari",
    "gn:country_code":"NG",
    "gn:dem":11,
    "gn:feature_class":"P",
    "gn:feature_code":"PPL",
    "gn:name":"Mbiabo Abasi Efiari",
    "gn:population":0,
    "gn:timezone":"Africa/Lagos",
    "iso:country":"NG",
    "wof:name":"Mbiabo Abasi Efiari",
    "wof:placetype":"locality"
},
  "geometry": {"coordinates":[8.06469,5.21182],"type":"Point"}
}