{
  "type": "Feature",
  "properties": {
    "gn:admin1_code":"29.0",
    "gn:admin2_code":"20002.0",
    "gn:admin3_code":"KN3701",
    "gn:asciiname":"Kayarda",
    "gn:country_code":"NG",
    "gn:dem":455,
    "gn:feature_class":"P",
    "gn:feature_code":"PPL",
    "gn:name":"Kayarda",
    "gn:population":0,
    "gn:timezone":"Africa/Lagos",
    "iso:country":"NG",
    "wof:name":"Kayarda",
    "wof:placetype":"locality"
},
  "geometry": {"coordinates":[9.11667,11.38333],"type":"Point"}
}