{
  "type": "Feature",
  "properties": {
    "gn:admin1_code":"42.0",
    "gn:admin2_code":"30024.0",
    "gn:asciiname":"Esa Odo",
    "gn:cc2":"NG",
    "gn:country_code":"NG",
    "gn:dem":357,
    "gn:feature_class":"P",
    "gn:feature_code":"PPL",
    "gn:name":"Esa Odo",
    "gn:population":0,
    "gn:timezone":"Africa/Lagos",
    "iso:country":"NG",
    "name:und_x_variant":[
        "Imessa Odo",
        "Essa-Odo",
        "Esa Odo"
    ],
    "wof:name":"Esa Odo",
    "wof:placetype":"locality"
},
  "geometry": {"coordinates":[4.81667,7.75],"type":"Point"}
}