{
  "type": "Feature",
  "properties": {
    "gn:admin1_code":"26.0",
    "gn:admin2_code":"7021",
    "gn:asciiname":"Atan",
    "gn:country_code":"NG",
    "gn:dem":203,
    "gn:feature_class":"P",
    "gn:feature_code":"PPL",
    "gn:name":"Atan",
    "gn:population":0,
    "gn:timezone":"Africa/Lagos",
    "iso:country":"NG",
    "name:deu_x_preferred":[
        "Atan"
    ],
    "name:fra_x_preferred":[
        "Atan"
    ],
    "name:ita_x_preferred":[
        "Atan"
    ],
    "name:nld_x_preferred":[
        "Atan"
    ],
    "name:tur_x_preferred":[
        "Atan"
    ],
    "wof:name":"Atan",
    "wof:placetype":"locality"
},
  "geometry": {"coordinates":[9.70527,7.52088],"type":"Point"}
}