{
  "type": "Feature",
  "properties": {
    "gn:admin1_code":"48.0",
    "gn:admin2_code":"29014.0",
    "gn:asciiname":"Ojimu",
    "gn:country_code":"NG",
    "gn:dem":17,
    "gn:feature_class":"P",
    "gn:feature_code":"PPL",
    "gn:name":"Ojimu",
    "gn:population":0,
    "gn:timezone":"Africa/Lagos",
    "iso:country":"NG",
    "wof:name":"Ojimu",
    "wof:placetype":"locality"
},
  "geometry": {"coordinates":[4.70928,6.43785],"type":"Point"}
}