{
  "type": "Feature",
  "properties": {
    "gn:admin1_code":"44.0",
    "gn:admin2_code":"703.0",
    "gn:admin3_code":"70307",
    "gn:asciiname":"Murba",
    "gn:country_code":"NG",
    "gn:dem":392,
    "gn:feature_class":"P",
    "gn:feature_code":"PPL",
    "gn:name":"Murba",
    "gn:population":0,
    "gn:timezone":"Africa/Lagos",
    "iso:country":"NG",
    "name:und_x_variant":[
        "Mirba",
        "Murba"
    ],
    "wof:name":"Murba",
    "wof:placetype":"locality"
},
  "geometry": {"coordinates":[11.83623,11.70567],"type":"Point"}
}