{
  "type": "Feature",
  "properties": {
    "gn:admin1_code":"21.0",
    "gn:admin2_code":"3013.0",
    "gn:asciiname":"Ediduo",
    "gn:country_code":"NG",
    "gn:dem":24,
    "gn:feature_class":"P",
    "gn:feature_code":"PPL",
    "gn:name":"Ediduo",
    "gn:population":0,
    "gn:timezone":"Africa/Lagos",
    "iso:country":"NG",
    "wof:name":"Ediduo",
    "wof:placetype":"locality"
},
  "geometry": {"coordinates":[7.60001,4.61786],"type":"Point"}
}