{
  "type": "Feature",
  "properties": {
    "gn:admin1_code":"24.0",
    "gn:admin2_code":"417.0",
    "gn:admin3_code":"41708",
    "gn:asciiname":"Masari",
    "gn:country_code":"NG",
    "gn:dem":596,
    "gn:feature_class":"P",
    "gn:feature_code":"PPL",
    "gn:name":"Masari",
    "gn:population":0,
    "gn:timezone":"Africa/Lagos",
    "iso:country":"NG",
    "name:ceb_x_preferred":[
        "M\u00e1sari"
    ],
    "name:ell_x_preferred":[
        "\u03a3\u03b1\u03c7\u03af\u03bd\u03bb\u03b5\u03c1"
    ],
    "name:pol_x_preferred":[
        "Masari"
    ],
    "name:swe_x_preferred":[
        "M\u00e1sari"
    ],
    "name:tur_x_preferred":[
        "\u015eahinler"
    ],
    "name:urd_x_preferred":[
        "\u0645\u0627\u0633\u0627\u0631\u06cc"
    ],
    "wof:name":"Masari",
    "wof:placetype":"locality"
},
  "geometry": {"coordinates":[7.68651,11.63978],"type":"Point"}
}