{
  "type": "Feature",
  "properties": {
    "gn:admin1_code":"24.0",
    "gn:admin2_code":"417.0",
    "gn:admin3_code":"41708",
    "gn:asciiname":"Masari",
    "gn:country_code":"NG",
    "gn:dem":596,
    "gn:feature_class":"P",
    "gn:feature_code":"PPL",
    "gn:name":"Masari",
    "gn:population":0,
    "gn:timezone":"Africa/Lagos",
    "iso:country":"NG",
    "wof:name":"Masari",
    "wof:placetype":"locality"
},
  "geometry": {"coordinates":[7.68651,11.63978],"type":"Point"}
}