{
  "type": "Feature",
  "properties": {
    "gn:admin1_code":"42.0",
    "gn:admin2_code":"30004.0",
    "gn:asciiname":"Ayinrin",
    "gn:cc2":"NG",
    "gn:country_code":"NG",
    "gn:dem":253,
    "gn:feature_class":"P",
    "gn:feature_code":"PPL",
    "gn:name":"Ayinrin",
    "gn:population":0,
    "gn:timezone":"Africa/Lagos",
    "iso:country":"NG",
    "name:und_x_variant":[
        "Adedaji",
        "Ayinrin"
    ],
    "wof:name":"Ayinrin",
    "wof:placetype":"locality"
},
  "geometry": {"coordinates":[4.71667,7.36667],"type":"Point"}
}