{
  "type": "Feature",
  "properties": {
    "gn:admin1_code":"46.0",
    "gn:admin2_code":"5012.0",
    "gn:admin3_code":"BA1210",
    "gn:asciiname":"Belako",
    "gn:country_code":"NG",
    "gn:dem":404,
    "gn:feature_class":"P",
    "gn:feature_code":"PPL",
    "gn:name":"Belako",
    "gn:population":0,
    "gn:timezone":"Africa/Lagos",
    "iso:country":"NG",
    "wof:name":"Belako",
    "wof:placetype":"locality"
},
  "geometry": {"coordinates":[10.5825,11.6049],"type":"Point"}
}