{
  "type": "Feature",
  "properties": {
    "gn:admin1_code":"32.0",
    "gn:admin2_code":"31026.0",
    "gn:asciiname":"Apabiekun",
    "gn:country_code":"NG",
    "gn:dem":135,
    "gn:feature_class":"P",
    "gn:feature_code":"PPL",
    "gn:name":"Apabiekun",
    "gn:population":0,
    "gn:timezone":"Africa/Lagos",
    "iso:country":"NG",
    "wof:name":"Apabiekun",
    "wof:placetype":"locality"
},
  "geometry": {"coordinates":[4.01667,7.23333],"type":"Point"}
}