{
  "type": "Feature",
  "properties": {
    "gn:admin1_code":"57.0",
    "gn:admin2_code":"813.0",
    "gn:admin3_code":"81305",
    "gn:asciiname":"Keta",
    "gn:country_code":"NG",
    "gn:dem":578,
    "gn:feature_class":"P",
    "gn:feature_code":"PPL",
    "gn:name":"Keta",
    "gn:population":0,
    "gn:timezone":"Africa/Lagos",
    "iso:country":"NG",
    "name:cat_x_preferred":[
        "Keta"
    ],
    "name:ceb_x_preferred":[
        "Keta"
    ],
    "name:deu_x_preferred":[
        "Keta"
    ],
    "name:ewe_x_preferred":[
        "Keta"
    ],
    "name:fra_x_preferred":[
        "Keta"
    ],
    "name:ind_x_preferred":[
        "Keta"
    ],
    "name:lit_x_preferred":[
        "Keta"
    ],
    "name:pol_x_preferred":[
        "Keta"
    ],
    "name:swe_x_preferred":[
        "Keta"
    ],
    "name:urd_x_preferred":[
        "\u06a9\u06cc\u0679\u0627"
    ],
    "wof:name":"Keta",
    "wof:placetype":"locality"
},
  "geometry": {"coordinates":[6.79641,11.84265],"type":"Point"}
}