{
  "type": "Feature",
  "properties": {
    "gn:admin1_code":"57.0",
    "gn:admin2_code":"813.0",
    "gn:admin3_code":"81305",
    "gn:asciiname":"Keta",
    "gn:country_code":"NG",
    "gn:dem":578,
    "gn:feature_class":"P",
    "gn:feature_code":"PPL",
    "gn:name":"Keta",
    "gn:population":0,
    "gn:timezone":"Africa/Lagos",
    "iso:country":"NG",
    "wof:name":"Keta",
    "wof:placetype":"locality"
},
  "geometry": {"coordinates":[6.79641,11.84265],"type":"Point"}
}