{
  "type": "Feature",
  "properties": {
    "gn:admin1_code":"40.0",
    "gn:admin2_code":"517.0",
    "gn:admin3_code":"51710",
    "gn:asciiname":"Maro",
    "gn:country_code":"NG",
    "gn:dem":158,
    "gn:feature_class":"P",
    "gn:feature_code":"PPL",
    "gn:name":"Maro",
    "gn:population":0,
    "gn:timezone":"Africa/Lagos",
    "iso:country":"NG",
    "name:ceb_x_preferred":[
        "Maro"
    ],
    "name:deu_x_preferred":[
        "Maro"
    ],
    "name:fra_x_preferred":[
        "Maro"
    ],
    "name:ita_x_preferred":[
        "Maro"
    ],
    "name:nld_x_preferred":[
        "Maro"
    ],
    "name:spa_x_preferred":[
        "Maro"
    ],
    "name:swe_x_preferred":[
        "Maro"
    ],
    "name:tgl_x_preferred":[
        "Maro"
    ],
    "wof:name":"Maro",
    "wof:placetype":"locality"
},
  "geometry": {"coordinates":[4.51485,11.22355],"type":"Point"}
}