{
  "type": "Feature",
  "properties": {
    "gn:admin1_code":"31.0",
    "gn:admin2_code":"27008.0",
    "gn:asciiname":"Kalu",
    "gn:country_code":"NG",
    "gn:dem":127,
    "gn:feature_class":"P",
    "gn:feature_code":"PPL",
    "gn:name":"Kalu",
    "gn:population":0,
    "gn:timezone":"Africa/Lagos",
    "iso:country":"NG",
    "name:cat_x_preferred":[
        "Kalu"
    ],
    "name:ceb_x_preferred":[
        "Kalu"
    ],
    "name:deu_x_preferred":[
        "Kalu"
    ],
    "name:fin_x_preferred":[
        "Kalu"
    ],
    "name:fra_x_preferred":[
        "Kalu"
    ],
    "name:rus_x_preferred":[
        "\u041a\u0430\u043b\u0443"
    ],
    "name:srp_x_preferred":[
        "\u041a\u0430\u043b\u0443"
    ],
    "name:swe_x_preferred":[
        "Kalu"
    ],
    "wof:name":"Kalu",
    "wof:placetype":"locality"
},
  "geometry": {"coordinates":[6.0404,9.18887],"type":"Point"}
}