{
  "type": "Feature",
  "properties": {
    "gn:admin1_code":"50.0",
    "gn:admin2_code":"33019.0",
    "gn:asciiname":"Umu Dike I",
    "gn:country_code":"NG",
    "gn:dem":50,
    "gn:feature_class":"P",
    "gn:feature_code":"PPL",
    "gn:name":"Umu Dike I",
    "gn:population":0,
    "gn:timezone":"Africa/Lagos",
    "iso:country":"NG",
    "name:und_x_variant":[
        "Umu Dike",
        "Umu Dike I"
    ],
    "wof:name":"Umu Dike I",
    "wof:placetype":"locality"
},
  "geometry": {"coordinates":[7.22657,5.05505],"type":"Point"}
}