{
  "type": "Feature",
  "properties": {
    "gn:admin1_code":"56.0",
    "gn:admin2_code":"26007.0",
    "gn:asciiname":"Abadu",
    "gn:country_code":"NG",
    "gn:dem":268,
    "gn:feature_class":"P",
    "gn:feature_code":"PPL",
    "gn:name":"Abadu",
    "gn:population":0,
    "gn:timezone":"Africa/Lagos",
    "iso:country":"NG",
    "wof:name":"Abadu",
    "wof:placetype":"locality"
},
  "geometry": {"coordinates":[7.95778,8.75167],"type":"Point"}
}