{
  "type": "Feature",
  "properties": {
    "gn:admin1_code":"46.0",
    "gn:admin2_code":"5002.0",
    "gn:admin3_code":"BA0206",
    "gn:asciiname":"Ju",
    "gn:country_code":"NG",
    "gn:dem":621,
    "gn:feature_class":"P",
    "gn:feature_code":"PPL",
    "gn:name":"Ju",
    "gn:population":0,
    "gn:timezone":"Africa/Lagos",
    "iso:country":"NG",
    "wof:name":"Ju",
    "wof:placetype":"locality"
},
  "geometry": {"coordinates":[9.82725,10.19507],"type":"Point"}
}