{
  "type": "Feature",
  "properties": {
    "gn:admin1_code":"30.0",
    "gn:admin2_code":"24001.0",
    "gn:asciiname":"Ago",
    "gn:country_code":"NG",
    "gn:dem":339,
    "gn:feature_class":"P",
    "gn:feature_code":"PPL",
    "gn:name":"Ago",
    "gn:population":0,
    "gn:timezone":"Africa/Lagos",
    "iso:country":"NG",
    "name:ces_x_preferred":[
        "Ago"
    ],
    "name:hun_x_preferred":[
        "\u00c1g\u00f3"
    ],
    "name:nld_x_preferred":[
        "Ago"
    ],
    "name:pol_x_preferred":[
        "Ago"
    ],
    "wof:name":"Ago",
    "wof:placetype":"locality"
},
  "geometry": {"coordinates":[4.48333,8.46667],"type":"Point"}
}