{
  "type": "Feature",
  "properties": {
    "gn:admin1_code":"35.0",
    "gn:admin2_code":"2020.0",
    "gn:asciiname":"Junde Morkadas",
    "gn:country_code":"NG",
    "gn:dem":204,
    "gn:feature_class":"P",
    "gn:feature_code":"PPL",
    "gn:name":"Junde Morkadas",
    "gn:population":0,
    "gn:timezone":"Africa/Lagos",
    "iso:country":"NG",
    "name:eng_x_preferred":[
        "Junde Morkadas"
    ],
    "wof:name":"Junde Morkadas",
    "wof:placetype":"locality"
},
  "geometry": {"coordinates":[12.16203,9.25728],"type":"Point"}
}