{
  "type": "Feature",
  "properties": {
    "gn:admin1_code":"23.0",
    "gn:admin2_code":"19005.0",
    "gn:admin3_code":"KD0505",
    "gn:asciiname":"Ungwan Gangarda",
    "gn:country_code":"NG",
    "gn:dem":644,
    "gn:feature_class":"P",
    "gn:feature_code":"PPL",
    "gn:name":"Ungwan Gangarda",
    "gn:population":0,
    "gn:timezone":"Africa/Lagos",
    "iso:country":"NG",
    "wof:name":"Ungwan Gangarda",
    "wof:placetype":"locality"
},
  "geometry": {"coordinates":[8.07733,11.38598],"type":"Point"}
}