{
  "type": "Feature",
  "properties": {
    "gn:admin1_code":"22.0",
    "gn:admin2_code":"9002.0",
    "gn:asciiname":"Ekong",
    "gn:country_code":"NG",
    "gn:dem":143,
    "gn:feature_class":"P",
    "gn:feature_code":"PPL",
    "gn:name":"Ekong",
    "gn:population":0,
    "gn:timezone":"Africa/Lagos",
    "iso:country":"NG",
    "wof:name":"Ekong",
    "wof:placetype":"locality"
},
  "geometry": {"coordinates":[8.5562,5.2751],"type":"Point"}
}