{
  "type": "Feature",
  "properties": {
    "gn:admin1_code":"44.0",
    "gn:admin2_code":"717.0",
    "gn:admin3_code":"71706",
    "gn:asciiname":"Musari",
    "gn:country_code":"NG",
    "gn:dem":345,
    "gn:feature_class":"P",
    "gn:feature_code":"PPL",
    "gn:name":"Musari",
    "gn:population":0,
    "gn:timezone":"Africa/Lagos",
    "iso:country":"NG",
    "wof:name":"Musari",
    "wof:placetype":"locality"
},
  "geometry": {"coordinates":[10.47931,13.04572],"type":"Point"}
}