{
  "type": "Feature",
  "properties": {
    "gn:admin1_code":"43.0",
    "gn:admin2_code":"35001",
    "gn:asciiname":"Sunkani",
    "gn:country_code":"NG",
    "gn:dem":231,
    "gn:feature_class":"P",
    "gn:feature_code":"PPLA2",
    "gn:name":"Sunkani",
    "gn:population":0,
    "gn:timezone":"Africa/Lagos",
    "iso:country":"NG",
    "wof:name":"Sunkani",
    "wof:placetype":"locality"
},
  "geometry": {"coordinates":[11.25757,8.70298],"type":"Point"}
}