{
  "type": "Feature",
  "properties": {
    "gn:admin1_code":"46.0",
    "gn:admin2_code":"5005.0",
    "gn:admin3_code":"BA0517",
    "gn:asciiname":"Gamadadi",
    "gn:country_code":"NG",
    "gn:dem":401,
    "gn:feature_class":"P",
    "gn:feature_code":"PPL",
    "gn:name":"Gamadadi",
    "gn:population":0,
    "gn:timezone":"Africa/Lagos",
    "iso:country":"NG",
    "name:eng_x_preferred":[
        "Gamadadi"
    ],
    "wof:name":"Gamadadi",
    "wof:placetype":"locality"
},
  "geometry": {"coordinates":[10.50729,10.77409],"type":"Point"}
}