{
  "type": "Feature",
  "properties": {
    "gn:admin1_code":"44.0",
    "gn:admin2_code":"716.0",
    "gn:admin3_code":"71601",
    "gn:asciiname":"Bagayam",
    "gn:country_code":"NG",
    "gn:dem":335,
    "gn:feature_class":"P",
    "gn:feature_code":"PPL",
    "gn:name":"Bagayam",
    "gn:population":0,
    "gn:timezone":"Africa/Lagos",
    "iso:country":"NG",
    "wof:name":"Bagayam",
    "wof:placetype":"locality"
},
  "geometry": {"coordinates":[12.07858,12.98219],"type":"Point"}
}