{
  "type": "Feature",
  "properties": {
    "gn:admin1_code":"50.0",
    "gn:admin2_code":"33016.0",
    "gn:asciiname":"Mitin Camp",
    "gn:country_code":"NG",
    "gn:dem":34,
    "gn:feature_class":"P",
    "gn:feature_code":"PPL",
    "gn:name":"Mitin Camp",
    "gn:population":0,
    "gn:timezone":"Africa/Lagos",
    "iso:country":"NG",
    "wof:name":"Mitin Camp",
    "wof:placetype":"locality"
},
  "geometry": {"coordinates":[6.62291,5.50744],"type":"Point"}
}