{
  "type": "Feature",
  "properties": {
    "gn:admin1_code":"31.0",
    "gn:admin2_code":"27012.0",
    "gn:asciiname":"Dida",
    "gn:country_code":"NG",
    "gn:dem":184,
    "gn:feature_class":"P",
    "gn:feature_code":"PPL",
    "gn:name":"Dida",
    "gn:population":0,
    "gn:timezone":"Africa/Lagos",
    "iso:country":"NG",
    "name:cat_x_preferred":[
        "Dida"
    ],
    "name:ceb_x_preferred":[
        "Dida"
    ],
    "name:dan_x_preferred":[
        "Dida"
    ],
    "name:deu_x_preferred":[
        "Dida"
    ],
    "name:fin_x_preferred":[
        "Dida"
    ],
    "name:fra_x_preferred":[
        "Dida"
    ],
    "name:hrv_x_preferred":[
        "Dida"
    ],
    "name:jpn_x_preferred":[
        "\u30b8\u30fc\u30c0"
    ],
    "name:nld_x_preferred":[
        "Dida"
    ],
    "name:pol_x_preferred":[
        "Dida"
    ],
    "name:por_x_preferred":[
        "Dida"
    ],
    "name:rus_x_preferred":[
        "\u0414\u0438\u0434\u0430"
    ],
    "name:slk_x_preferred":[
        "Dida"
    ],
    "name:swe_x_preferred":[
        "Dida"
    ],
    "name:tur_x_preferred":[
        "Dida"
    ],
    "wof:name":"Dida",
    "wof:placetype":"locality"
},
  "geometry": {"coordinates":[6.73333,8.43333],"type":"Point"}
}