{
  "type": "Feature",
  "properties": {
    "gn:admin1_code":"45.0",
    "gn:admin2_code":"1007.0",
    "gn:asciiname":"Ubaha-Oloko",
    "gn:country_code":"NG",
    "gn:dem":116,
    "gn:feature_class":"P",
    "gn:feature_code":"PPL",
    "gn:name":"Ubaha-Oloko",
    "gn:population":0,
    "gn:timezone":"Africa/Lagos",
    "iso:country":"NG",
    "name:und_x_variant":[
        "Ubaha",
        "Ubaha-Oloko"
    ],
    "wof:name":"Ubaha-Oloko",
    "wof:placetype":"locality"
},
  "geometry": {"coordinates":[7.48708,5.37262],"type":"Point"}
}