{
  "type": "Feature",
  "properties": {
    "gn:admin1_code":"30.0",
    "gn:admin2_code":"24010.0",
    "gn:asciiname":"Ijomu Oro",
    "gn:cc2":"NG",
    "gn:country_code":"NG",
    "gn:dem":446,
    "gn:feature_class":"P",
    "gn:feature_code":"PPL",
    "gn:name":"Ijomu Oro",
    "gn:population":0,
    "gn:timezone":"Africa/Lagos",
    "iso:country":"NG",
    "name:und_x_variant":[
        "Ijomo",
        "Ijomu Oro"
    ],
    "wof:name":"Ijomu Oro",
    "wof:placetype":"locality"
},
  "geometry": {"coordinates":[4.91667,8.25],"type":"Point"}
}