{
  "type": "Feature",
  "properties": {
    "gn:admin1_code":"45.0",
    "gn:asciiname":"Iyioji",
    "gn:country_code":"NG",
    "gn:dem":38,
    "gn:feature_class":"P",
    "gn:feature_code":"PPL",
    "gn:name":"Iyioji",
    "gn:population":0,
    "gn:timezone":"Africa/Lagos",
    "iso:country":"NG",
    "wof:name":"Iyioji",
    "wof:placetype":"locality"
},
  "geometry": {"coordinates":[7.6707,5.90616],"type":"Point"}
}