{
  "type": "Feature",
  "properties": {
    "gn:admin1_code":"50.0",
    "gn:admin2_code":"33004.0",
    "gn:asciiname":"Elizokiri",
    "gn:country_code":"NG",
    "gn:dem":6,
    "gn:feature_class":"P",
    "gn:feature_code":"PPL",
    "gn:name":"Elizokiri",
    "gn:population":0,
    "gn:timezone":"Africa/Lagos",
    "iso:country":"NG",
    "name:und_x_variant":[
        "Elizakiri"
    ],
    "wof:name":"Elizokiri",
    "wof:placetype":"locality"
},
  "geometry": {"coordinates":[6.63769,4.32647],"type":"Point"}
}