{
  "type": "Feature",
  "properties": {
    "gn:admin1_code":"35.0",
    "gn:admin2_code":"2005.0",
    "gn:asciiname":"Botala",
    "gn:country_code":"NG",
    "gn:dem":565,
    "gn:feature_class":"P",
    "gn:feature_code":"PPL",
    "gn:name":"Botala",
    "gn:population":0,
    "gn:timezone":"Africa/Lagos",
    "iso:country":"NG",
    "name:fas_x_preferred":[
        "\u0628\u0648\u062a\u0627\u0644\u0647"
    ],
    "name:urd_x_preferred":[
        "\u0628\u0648\u062a\u0627\u0644\u06c1"
    ],
    "wof:name":"Botala",
    "wof:placetype":"locality"
},
  "geometry": {"coordinates":[12.55557,10.07563],"type":"Point"}
}