{
  "type": "Feature",
  "properties": {
    "gn:admin1_code":"24.0",
    "gn:admin2_code":"417.0",
    "gn:admin3_code":"41703",
    "gn:asciiname":"Badawa",
    "gn:country_code":"NG",
    "gn:dem":574,
    "gn:feature_class":"P",
    "gn:feature_code":"PPL",
    "gn:name":"Badawa",
    "gn:population":0,
    "gn:timezone":"Africa/Lagos",
    "iso:country":"NG",
    "wof:name":"Badawa",
    "wof:placetype":"locality"
},
  "geometry": {"coordinates":[7.81757,11.78688],"type":"Point"}
}