{
  "type": "Feature",
  "properties": {
    "gn:admin1_code":"29.0",
    "gn:admin2_code":"20003.0",
    "gn:admin3_code":"KN1502",
    "gn:asciiname":"Turedasau Ta Fulani",
    "gn:country_code":"NG",
    "gn:dem":483,
    "gn:feature_class":"P",
    "gn:feature_code":"PPL",
    "gn:name":"Turedasau Ta Fulani",
    "gn:population":0,
    "gn:timezone":"Africa/Lagos",
    "iso:country":"NG",
    "wof:name":"Turedasau Ta Fulani",
    "wof:placetype":"locality"
},
  "geometry": {"coordinates":[8.43614,11.67235],"type":"Point"}
}