{
  "type": "Feature",
  "properties": {
    "gn:admin1_code":"11.0",
    "gn:asciiname":"Gidan-Dutse",
    "gn:country_code":"NG",
    "gn:dem":677,
    "gn:feature_class":"P",
    "gn:feature_code":"PPL",
    "gn:name":"Gidan-Dutse",
    "gn:population":0,
    "gn:timezone":"Africa/Lagos",
    "iso:country":"NG",
    "wof:name":"Gidan-Dutse",
    "wof:placetype":"locality"
},
  "geometry": {"coordinates":[7.67537,9.38926],"type":"Point"}
}