{
  "type": "Feature",
  "properties": {
    "gn:admin1_code":"27.0",
    "gn:admin2_code":"102.0",
    "gn:admin3_code":"10213",
    "gn:asciiname":"Kwabula",
    "gn:country_code":"NG",
    "gn:dem":520,
    "gn:feature_class":"P",
    "gn:feature_code":"PPL",
    "gn:name":"Kwabula",
    "gn:population":0,
    "gn:timezone":"Africa/Lagos",
    "iso:country":"NG",
    "wof:name":"Kwabula",
    "wof:placetype":"locality"
},
  "geometry": {"coordinates":[13.07591,10.5622],"type":"Point"}
}