{
  "type": "Feature",
  "properties": {
    "gn:admin1_code":"39.0",
    "gn:admin2_code":"18009.0",
    "gn:admin3_code":"JI1211",
    "gn:asciiname":"Zaumae Mahauta",
    "gn:country_code":"NG",
    "gn:dem":474,
    "gn:feature_class":"P",
    "gn:feature_code":"PPL",
    "gn:name":"Zaumae Mahauta",
    "gn:population":0,
    "gn:timezone":"Africa/Lagos",
    "iso:country":"NG",
    "wof:name":"Zaumae Mahauta",
    "wof:placetype":"locality"
},
  "geometry": {"coordinates":[8.36603,12.68354],"type":"Point"}
}