{
  "type": "Feature",
  "properties": {
    "gn:admin1_code":"32.0",
    "gn:admin2_code":"31005.0",
    "gn:asciiname":"Asipa",
    "gn:country_code":"NG",
    "gn:dem":224,
    "gn:feature_class":"P",
    "gn:feature_code":"PPL",
    "gn:name":"Asipa",
    "gn:population":0,
    "gn:timezone":"Africa/Lagos",
    "iso:country":"NG",
    "wof:name":"Asipa",
    "wof:placetype":"neighbourhood"
},
  "geometry": {"coordinates":[3.98056,7.39583],"type":"Point"}
}