{
  "type": "Feature",
  "properties": {
    "gn:admin1_code":"32.0",
    "gn:admin2_code":"31030.0",
    "gn:asciiname":"Oyo Ile",
    "gn:country_code":"NG",
    "gn:dem":252,
    "gn:feature_class":"P",
    "gn:feature_code":"PPL",
    "gn:name":"Oyo Ile",
    "gn:population":0,
    "gn:timezone":"Africa/Lagos",
    "iso:country":"NG",
    "wof:name":"Oyo Ile",
    "wof:placetype":"locality"
},
  "geometry": {"coordinates":[3.75,8.03333],"type":"Point"}
}