{
  "type": "Feature",
  "properties": {
    "gn:admin1_code":"28.0",
    "gn:admin2_code":"17002.0",
    "gn:asciiname":"Obwe",
    "gn:country_code":"NG",
    "gn:dem":160,
    "gn:feature_class":"P",
    "gn:feature_code":"PPL",
    "gn:name":"Obwe",
    "gn:population":0,
    "gn:timezone":"Africa/Lagos",
    "iso:country":"NG",
    "wof:name":"Obwe",
    "wof:placetype":"locality"
},
  "geometry": {"coordinates":[7.28204,5.53051],"type":"Point"}
}