{
  "type": "Feature",
  "properties": {
    "gn:admin1_code":"36.0",
    "gn:asciiname":"Olusumere",
    "gn:country_code":"NG",
    "gn:dem":-9999,
    "gn:feature_class":"P",
    "gn:feature_code":"PPL",
    "gn:name":"Olusumere",
    "gn:population":0,
    "gn:timezone":"Africa/Lagos",
    "iso:country":"NG",
    "name:eng_x_preferred":[
        "Olusumere"
    ],
    "wof:name":"Olusumere",
    "wof:placetype":"locality"
},
  "geometry": {"coordinates":[5.23408,5.44709],"type":"Point"}
}