{
  "type": "Feature",
  "properties": {
    "gn:admin1_code":"55.0",
    "gn:admin2_code":"16008.0",
    "gn:asciiname":"Bulturi",
    "gn:country_code":"NG",
    "gn:dem":293,
    "gn:feature_class":"P",
    "gn:feature_code":"PPL",
    "gn:name":"Bulturi",
    "gn:population":0,
    "gn:timezone":"Africa/Lagos",
    "iso:country":"NG",
    "wof:name":"Bulturi",
    "wof:placetype":"locality"
},
  "geometry": {"coordinates":[11.39911,10.58727],"type":"Point"}
}