{
  "type": "Feature",
  "properties": {
    "gn:admin1_code":"21.0",
    "gn:admin2_code":"3012.0",
    "gn:asciiname":"Ndinya-Ikot Imo",
    "gn:country_code":"NG",
    "gn:dem":134,
    "gn:feature_class":"P",
    "gn:feature_code":"PPL",
    "gn:name":"Ndinya-Ikot Imo",
    "gn:population":0,
    "gn:timezone":"Africa/Lagos",
    "iso:country":"NG",
    "wof:name":"Ndinya-Ikot Imo",
    "wof:placetype":"locality"
},
  "geometry": {"coordinates":[7.6974,5.30731],"type":"Point"}
}