{
  "type": "Feature",
  "properties": {
    "gn:admin1_code":"22.0",
    "gn:admin2_code":"9018.0",
    "gn:asciiname":"Elahen Wanakande",
    "gn:country_code":"NG",
    "gn:dem":100,
    "gn:feature_class":"P",
    "gn:feature_code":"PPL",
    "gn:name":"Elahen Wanakande",
    "gn:population":0,
    "gn:timezone":"Africa/Lagos",
    "iso:country":"NG",
    "wof:name":"Elahen Wanakande",
    "wof:placetype":"locality"
},
  "geometry": {"coordinates":[8.47495,6.70962],"type":"Point"}
}