{
  "type": "Feature",
  "properties": {
    "gn:admin1_code":"36.0",
    "gn:admin2_code":"10017.0",
    "gn:asciiname":"Ajakaketie",
    "gn:country_code":"NG",
    "gn:dem":8,
    "gn:feature_class":"P",
    "gn:feature_code":"PPL",
    "gn:name":"Ajakaketie",
    "gn:population":0,
    "gn:timezone":"Africa/Lagos",
    "iso:country":"NG",
    "name:eng_x_preferred":[
        "Ajakaketie"
    ],
    "name:eng_x_variant":[
        "Ajakaketiewe"
    ],
    "wof:name":"Ajakaketie",
    "wof:placetype":"locality"
},
  "geometry": {"coordinates":[5.76989,5.85442],"type":"Point"}
}