{
  "type": "Feature",
  "properties": {
    "gn:country":"NG",
    "gn:fcode":"PPL",
    "gn:pop":11771,
    "iso:country":"NG",
    "name:eng_x_preferred":[
        "Madalla"
    ],
    "name:fra_x_preferred":[
        "Madalla"
    ],
    "name:nld_x_preferred":[
        "Madalla"
    ],
    "name:unk_x_variant":[
        "Madalla"
    ],
    "name:zho_x_preferred":[
        "\u9a6c\u8fbe\u62c9"
    ],
    "qs:name":"Madala",
    "qs:photos_9r":0,
    "qs:photos_sr":0,
    "qs:pop_sr":"6",
    "wd:wordcount":79,
    "wof:name":"Madala",
    "wof:placetype":"locality",
    "wof:population":11771
},
  "geometry": {"coordinates":[7.21333,9.10444],"type":"Point"}
}