{
  "type": "Feature",
  "properties": {
    "gn:country":"NG",
    "gn:fcode":"PPL",
    "gn:population":11771,
    "iso:country":"NG",
    "name:ast_x_preferred":[
        "Madalla"
    ],
    "name:bre_x_preferred":[
        "Madalla"
    ],
    "name:cos_x_preferred":[
        "Madalla"
    ],
    "name:dan_x_preferred":[
        "Madalla"
    ],
    "name:deu_x_preferred":[
        "Madalla"
    ],
    "name:eng_x_preferred":[
        "Madalla"
    ],
    "name:fas_x_preferred":[
        "\u0645\u0627\u062f\u0627\u0644\u0627"
    ],
    "name:fra_x_preferred":[
        "Madalla"
    ],
    "name:ind_x_preferred":[
        "Madalla"
    ],
    "name:ita_x_preferred":[
        "Madalla"
    ],
    "name:nds_x_preferred":[
        "Madalla"
    ],
    "name:nld_x_preferred":[
        "Madalla"
    ],
    "name:por_x_preferred":[
        "Madalla"
    ],
    "name:ron_x_preferred":[
        "Madalla"
    ],
    "name:spa_x_preferred":[
        "Madalla"
    ],
    "name:swe_x_preferred":[
        "Madalla"
    ],
    "name:tah_x_preferred":[
        "Madalla"
    ],
    "name:zho_x_preferred":[
        "\u9a6c\u8fbe\u62c9"
    ],
    "qs:name":"Madala",
    "qs:photos_9r":0,
    "qs:photos_sr":0,
    "qs:pop_sr":"6",
    "wd:wordcount":79,
    "wof:name":"Madala",
    "wof:placetype":"locality",
    "wof:population":11771
},
  "geometry": {"coordinates":[7.21333,9.10444],"type":"Point"}
}