{
  "type": "Feature",
  "properties": {
    "gn:admin1_code":"26.0",
    "gn:admin2_code":"7005",
    "gn:asciiname":"Iorngee",
    "gn:country_code":"NG",
    "gn:dem":138,
    "gn:feature_class":"P",
    "gn:feature_code":"PPL",
    "gn:name":"Iorngee",
    "gn:population":0,
    "gn:timezone":"Africa/Lagos",
    "iso:country":"NG",
    "wof:name":"Iorngee",
    "wof:placetype":"locality"
},
  "geometry": {"coordinates":[8.83141,7.48648],"type":"Point"}
}