{
  "type": "Feature",
  "properties": {
    "gn:admin1_code":"44.0",
    "gn:admin2_code":"717.0",
    "gn:admin3_code":"71708",
    "gn:asciiname":"Fajiganari",
    "gn:country_code":"NG",
    "gn:dem":343,
    "gn:feature_class":"P",
    "gn:feature_code":"PPL",
    "gn:name":"Fajiganari",
    "gn:population":0,
    "gn:timezone":"Africa/Lagos",
    "iso:country":"NG",
    "wof:name":"Fajiganari",
    "wof:placetype":"locality"
},
  "geometry": {"coordinates":[10.69383,13.07599],"type":"Point"}
}