{
  "type": "Feature",
  "properties": {
    "gn:admin1_code":"31.0",
    "gn:admin2_code":"27017",
    "gn:asciiname":"Shegba",
    "gn:country_code":"NG",
    "gn:dem":79,
    "gn:feature_class":"P",
    "gn:feature_code":"PPL",
    "gn:name":"Shegba",
    "gn:population":0,
    "gn:timezone":"Africa/Lagos",
    "iso:country":"NG",
    "wof:name":"Shegba",
    "wof:placetype":"locality"
},
  "geometry": {"coordinates":[5.83026,9.25385],"type":"Point"}
}