{
  "type": "Feature",
  "properties": {
    "gn:admin1_code":"48.0",
    "gn:admin2_code":"29006.0",
    "gn:asciiname":"Adofure",
    "gn:country_code":"NG",
    "gn:dem":338,
    "gn:feature_class":"P",
    "gn:feature_code":"PPL",
    "gn:name":"Adofure",
    "gn:population":0,
    "gn:timezone":"Africa/Lagos",
    "iso:country":"NG",
    "wof:name":"Adofure",
    "wof:placetype":"neighbourhood"
},
  "geometry": {"coordinates":[5.166,7.1975],"type":"Point"}
}