{
  "type": "Feature",
  "properties": {
    "gn:admin1_code":"44.0",
    "gn:admin2_code":"716.0",
    "gn:admin3_code":"71606",
    "gn:asciiname":"Magirari",
    "gn:country_code":"NG",
    "gn:dem":339,
    "gn:feature_class":"P",
    "gn:feature_code":"PPL",
    "gn:name":"Magirari",
    "gn:population":0,
    "gn:timezone":"Africa/Lagos",
    "iso:country":"NG",
    "wof:name":"Magirari",
    "wof:placetype":"locality"
},
  "geometry": {"coordinates":[11.93051,13.01882],"type":"Point"}
}