{
  "type": "Feature",
  "properties": {
    "gn:admin1_code":"42.0",
    "gn:admin2_code":"30026.0",
    "gn:asciiname":"Iwo Oke",
    "gn:country_code":"NG",
    "gn:dem":323,
    "gn:feature_class":"P",
    "gn:feature_code":"PPL",
    "gn:name":"Iwo Oke",
    "gn:population":0,
    "gn:timezone":"Africa/Lagos",
    "iso:country":"NG",
    "wof:name":"Iwo Oke",
    "wof:placetype":"locality"
},
  "geometry": {"coordinates":[4.25,7.81667],"type":"Point"}
}