{
  "type": "Feature",
  "properties": {
    "gn:admin1_code":"43.0",
    "gn:admin2_code":"35011",
    "gn:asciiname":"Nagusu",
    "gn:country_code":"NG",
    "gn:dem":1395,
    "gn:feature_class":"P",
    "gn:feature_code":"PPL",
    "gn:name":"Nagusu",
    "gn:population":0,
    "gn:timezone":"Africa/Lagos",
    "iso:country":"NG",
    "wof:name":"Nagusu",
    "wof:placetype":"locality"
},
  "geometry": {"coordinates":[10.99775,7.25655],"type":"Point"}
}