{
  "type": "Feature",
  "properties": {
    "gn:admin1_code":"57.0",
    "gn:admin2_code":"805.0",
    "gn:admin3_code":"80507",
    "gn:asciiname":"Guidan Ada",
    "gn:country_code":"NG",
    "gn:dem":490,
    "gn:feature_class":"P",
    "gn:feature_code":"PPL",
    "gn:name":"Guidan Ada",
    "gn:population":0,
    "gn:timezone":"Africa/Lagos",
    "iso:country":"NG",
    "name:und_x_variant":[
        "Gidan Ada",
        "Guidan Ada"
    ],
    "wof:name":"Guidan Ada",
    "wof:placetype":"locality"
},
  "geometry": {"coordinates":[6.80645,12.11933],"type":"Point"}
}