{
  "type": "Feature",
  "properties": {
    "gn:admin1_code":"16.0",
    "gn:admin2_code":"28009.0",
    "gn:asciiname":"Kajola",
    "gn:cc2":"NG",
    "gn:country_code":"NG",
    "gn:dem":82,
    "gn:feature_class":"P",
    "gn:feature_code":"PPL",
    "gn:name":"Kajola",
    "gn:population":0,
    "gn:timezone":"Africa/Lagos",
    "iso:country":"NG",
    "name:und_x_variant":[
        "Kajawla",
        "Kajola"
    ],
    "wof:name":"Kajola",
    "wof:placetype":"locality"
},
  "geometry": {"coordinates":[3.91667,7.03333],"type":"Point"}
}