{
  "type": "Feature",
  "properties": {
    "gn:admin1_code":"37.0",
    "gn:admin2_code":"12014.0",
    "gn:asciiname":"Igbekue",
    "gn:country_code":"NG",
    "gn:dem":196,
    "gn:feature_class":"P",
    "gn:feature_code":"PPL",
    "gn:name":"Igbekue",
    "gn:population":0,
    "gn:timezone":"Africa/Lagos",
    "iso:country":"NG",
    "name:und_x_variant":[
        "Ibekwe",
        "Igbekue"
    ],
    "wof:name":"Igbekue",
    "wof:placetype":"locality"
},
  "geometry": {"coordinates":[5.75272,6.58766],"type":"Point"}
}