{
  "type": "Feature",
  "properties": {
    "gn:admin1_code":"32.0",
    "gn:admin2_code":"31024.0",
    "gn:asciiname":"Olopa",
    "gn:country_code":"NG",
    "gn:dem":415,
    "gn:feature_class":"P",
    "gn:feature_code":"PPL",
    "gn:name":"Olopa",
    "gn:population":0,
    "gn:timezone":"Africa/Lagos",
    "iso:country":"NG",
    "name:ceb_x_preferred":[
        "Olopa"
    ],
    "name:fra_x_preferred":[
        "Olopa"
    ],
    "name:ita_x_preferred":[
        "Olopa"
    ],
    "name:pol_x_preferred":[
        "Olopa"
    ],
    "name:por_x_preferred":[
        "Olopa"
    ],
    "name:spa_x_preferred":[
        "Olopa"
    ],
    "name:swe_x_preferred":[
        "Olopa"
    ],
    "name:zho_x_preferred":[
        "\u5967\u6d1b\u5e15"
    ],
    "wof:name":"Olopa",
    "wof:placetype":"locality"
},
  "geometry": {"coordinates":[4.23333,8.91667],"type":"Point"}
}