{
  "type": "Feature",
  "properties": {
    "gn:admin1_code":"51.0",
    "gn:admin2_code":"619.0",
    "gn:admin3_code":"61907",
    "gn:asciiname":"Tagimba",
    "gn:country_code":"NG",
    "gn:dem":273,
    "gn:feature_class":"P",
    "gn:feature_code":"PPL",
    "gn:name":"Tagimba",
    "gn:population":0,
    "gn:timezone":"Africa/Lagos",
    "iso:country":"NG",
    "name:und_x_variant":[
        "Tajimba",
        "Tagimba"
    ],
    "wof:name":"Tagimba",
    "wof:placetype":"locality"
},
  "geometry": {"coordinates":[4.77955,13.59047],"type":"Point"}
}