{
  "type": "Feature",
  "properties": {
    "gn:admin1_code":"29.0",
    "gn:admin2_code":"20036.0",
    "gn:admin3_code":"KN2809",
    "gn:asciiname":"Daburau",
    "gn:country_code":"NG",
    "gn:dem":473,
    "gn:feature_class":"P",
    "gn:feature_code":"PPL",
    "gn:name":"Daburau",
    "gn:population":0,
    "gn:timezone":"Africa/Lagos",
    "iso:country":"NG",
    "wof:name":"Daburau",
    "wof:placetype":"locality"
},
  "geometry": {"coordinates":[8.37111,11.8256],"type":"Point"}
}