{
  "type": "Feature",
  "properties": {
    "gn:admin1_code":"27.0",
    "gn:admin2_code":"114.0",
    "gn:admin3_code":"11410",
    "gn:asciiname":"Lamboa",
    "gn:country_code":"NG",
    "gn:dem":350,
    "gn:feature_class":"P",
    "gn:feature_code":"PPL",
    "gn:name":"Lamboa",
    "gn:population":0,
    "gn:timezone":"Africa/Lagos",
    "iso:country":"NG",
    "wof:name":"Lamboa",
    "wof:placetype":"locality"
},
  "geometry": {"coordinates":[12.63353,11.86447],"type":"Point"}
}