{
  "type": "Feature",
  "properties": {
    "gn:admin1_code":"43.0",
    "gn:admin2_code":"35001",
    "gn:asciiname":"Jauro Manu",
    "gn:country_code":"NG",
    "gn:dem":255,
    "gn:feature_class":"P",
    "gn:feature_code":"PPL",
    "gn:name":"Jauro Manu",
    "gn:population":0,
    "gn:timezone":"Africa/Lagos",
    "iso:country":"NG",
    "wof:name":"Jauro Manu",
    "wof:placetype":"locality"
},
  "geometry": {"coordinates":[11.37386,8.81158],"type":"Point"}
}