{
  "type": "Feature",
  "properties": {
    "gn:admin1_code":"57.0",
    "gn:admin2_code":"805.0",
    "gn:admin3_code":"80508",
    "gn:asciiname":"Guidan Jibo",
    "gn:country_code":"NG",
    "gn:dem":422,
    "gn:feature_class":"P",
    "gn:feature_code":"PPL",
    "gn:name":"Guidan Jibo",
    "gn:population":0,
    "gn:timezone":"Africa/Lagos",
    "iso:country":"NG",
    "name:und_x_variant":[
        "Gidan Jibo",
        "Guidan Jibo"
    ],
    "wof:name":"Guidan Jibo",
    "wof:placetype":"locality"
},
  "geometry": {"coordinates":[6.51709,12.35096],"type":"Point"}
}