{
  "type": "Feature",
  "properties": {
    "gn:admin1_code":"23.0",
    "gn:asciiname":"Zenabi",
    "gn:country_code":"NG",
    "gn:dem":652,
    "gn:feature_class":"P",
    "gn:feature_code":"PPL",
    "gn:name":"Zenabi",
    "gn:population":0,
    "gn:timezone":"Africa/Lagos",
    "iso:country":"NG",
    "wof:name":"Zenabi",
    "wof:placetype":"locality"
},
  "geometry": {"coordinates":[8.77075,10.78951],"type":"Point"}
}