{
  "type": "Feature",
  "properties": {
    "gn:admin1_code":"44.0",
    "gn:admin2_code":"704.0",
    "gn:admin3_code":"70405",
    "gn:asciiname":"Allabuzum",
    "gn:country_code":"NG",
    "gn:dem":452,
    "gn:feature_class":"P",
    "gn:feature_code":"PPL",
    "gn:name":"Allabuzum",
    "gn:population":0,
    "gn:timezone":"Africa/Lagos",
    "iso:country":"NG",
    "wof:name":"Allabuzum",
    "wof:placetype":"locality"
},
  "geometry": {"coordinates":[11.24843,11.6451],"type":"Point"}
}