{
  "type": "Feature",
  "properties": {
    "gn:admin1_code":"41.0",
    "gn:admin2_code":"23014.0",
    "gn:asciiname":"Egbala",
    "gn:country_code":"NG",
    "gn:dem":102,
    "gn:feature_class":"P",
    "gn:feature_code":"PPL",
    "gn:name":"Egbala",
    "gn:population":0,
    "gn:timezone":"Africa/Lagos",
    "iso:country":"NG",
    "name:und_x_variant":[
        "Egbola",
        "Egbala"
    ],
    "wof:name":"Egbala",
    "wof:placetype":"locality"
},
  "geometry": {"coordinates":[6.7813,7.3096],"type":"Point"}
}