{
  "type": "Feature",
  "properties": {
    "gn:admin1_code":"26.0",
    "gn:admin2_code":"7013.0",
    "gn:asciiname":"Chia",
    "gn:country_code":"NG",
    "gn:dem":93,
    "gn:feature_class":"P",
    "gn:feature_code":"PPL",
    "gn:name":"Chia",
    "gn:population":0,
    "gn:timezone":"Africa/Lagos",
    "iso:country":"NG",
    "name:ceb_x_preferred":[
        "Chia"
    ],
    "name:ces_x_preferred":[
        "Chia"
    ],
    "name:dan_x_preferred":[
        "Chia"
    ],
    "name:deu_x_preferred":[
        "Chia"
    ],
    "name:epo_x_preferred":[
        "Chia"
    ],
    "name:eus_x_preferred":[
        "Chia"
    ],
    "name:fin_x_preferred":[
        "Chia"
    ],
    "name:fra_x_preferred":[
        "Chia"
    ],
    "name:ita_x_preferred":[
        "Chia"
    ],
    "name:nld_x_preferred":[
        "Chia"
    ],
    "name:srp_x_preferred":[
        "Chia"
    ],
    "name:swe_x_preferred":[
        "Chia"
    ],
    "name:war_x_preferred":[
        "Chia"
    ],
    "wof:name":"Chia",
    "wof:placetype":"locality"
},
  "geometry": {"coordinates":[8.48422,7.61479],"type":"Point"}
}