{
  "type": "Feature",
  "properties": {
    "gn:admin1_code":"35.0",
    "gn:admin2_code":"2008.0",
    "gn:asciiname":"Wuro Umaru",
    "gn:country_code":"NG",
    "gn:dem":422,
    "gn:feature_class":"P",
    "gn:feature_code":"PPL",
    "gn:name":"Wuro Umaru",
    "gn:population":0,
    "gn:timezone":"Africa/Lagos",
    "iso:country":"NG",
    "wof:name":"Wuro Umaru",
    "wof:placetype":"locality"
},
  "geometry": {"coordinates":[12.09023,8.60355],"type":"Point"}
}