{
  "type": "Feature",
  "properties": {
    "gn:admin1_code":"29.0",
    "gn:admin2_code":"20034.0",
    "gn:admin3_code":"KN2411",
    "gn:asciiname":"Ungwan Dawaki",
    "gn:country_code":"NG",
    "gn:dem":525,
    "gn:feature_class":"P",
    "gn:feature_code":"PPL",
    "gn:name":"Ungwan Dawaki",
    "gn:population":0,
    "gn:timezone":"Africa/Lagos",
    "iso:country":"NG",
    "wof:name":"Ungwan Dawaki",
    "wof:placetype":"locality"
},
  "geometry": {"coordinates":[8.10288,11.71515],"type":"Point"}
}