{
  "type": "Feature",
  "properties": {
    "gn:admin1_code":"24.0",
    "gn:admin2_code":"431.0",
    "gn:admin3_code":"43107",
    "gn:asciiname":"Sarkin Noma",
    "gn:country_code":"NG",
    "gn:dem":680,
    "gn:feature_class":"P",
    "gn:feature_code":"PPL",
    "gn:name":"Sarkin Noma",
    "gn:population":0,
    "gn:timezone":"Africa/Lagos",
    "iso:country":"NG",
    "wof:name":"Sarkin Noma",
    "wof:placetype":"locality"
},
  "geometry": {"coordinates":[7.0257,11.24546],"type":"Point"}
}