{
  "type": "Feature",
  "properties": {
    "gn:admin1_code":"21.0",
    "gn:admin2_code":"3031.0",
    "gn:asciiname":"Atan",
    "gn:country_code":"NG",
    "gn:dem":63,
    "gn:feature_class":"P",
    "gn:feature_code":"PPL",
    "gn:name":"Atan",
    "gn:population":0,
    "gn:timezone":"Africa/Lagos",
    "iso:country":"NG",
    "name:deu_x_preferred":[
        "Atan"
    ],
    "name:fra_x_preferred":[
        "Atan"
    ],
    "name:ita_x_preferred":[
        "Atan"
    ],
    "name:nld_x_preferred":[
        "Atan"
    ],
    "name:tur_x_preferred":[
        "Atan"
    ],
    "wof:name":"Atan",
    "wof:placetype":"neighbourhood"
},
  "geometry": {"coordinates":[7.91131,5.01725],"type":"Point"}
}