{
  "type": "Feature",
  "properties": {
    "gn:admin1_code":"29.0",
    "gn:admin2_code":"20023.0",
    "gn:admin3_code":"KN0808",
    "gn:asciiname":"Bala Kuita",
    "gn:country_code":"NG",
    "gn:dem":407,
    "gn:feature_class":"P",
    "gn:feature_code":"PPL",
    "gn:name":"Bala Kuita",
    "gn:population":0,
    "gn:timezone":"Africa/Lagos",
    "iso:country":"NG",
    "wof:name":"Bala Kuita",
    "wof:placetype":"locality"
},
  "geometry": {"coordinates":[8.75938,12.41665],"type":"Point"}
}