{
  "type": "Feature",
  "properties": {
    "gn:admin1_code":"51.0",
    "gn:admin2_code":"618.0",
    "gn:admin3_code":"61804",
    "gn:asciiname":"Ungwan Alu",
    "gn:country_code":"NG",
    "gn:dem":251,
    "gn:feature_class":"P",
    "gn:feature_code":"PPL",
    "gn:name":"Ungwan Alu",
    "gn:population":0,
    "gn:timezone":"Africa/Lagos",
    "iso:country":"NG",
    "wof:name":"Ungwan Alu",
    "wof:placetype":"locality"
},
  "geometry": {"coordinates":[4.82467,12.45302],"type":"Point"}
}