{
  "type": "Feature",
  "properties": {
    "gn:admin1_code":"37.0",
    "gn:admin2_code":"12011.0",
    "gn:asciiname":"Obenevbueribo",
    "gn:cc2":"NG",
    "gn:country_code":"NG",
    "gn:dem":53,
    "gn:feature_class":"P",
    "gn:feature_code":"PPL",
    "gn:name":"Obenevbueribo",
    "gn:population":0,
    "gn:timezone":"Africa/Lagos",
    "iso:country":"NG",
    "name:und_x_variant":[
        "Obeneubueribo",
        "Obenevbueribo"
    ],
    "wof:name":"Obenevbueribo",
    "wof:placetype":"locality"
},
  "geometry": {"coordinates":[5.66667,6.25],"type":"Point"}
}