{
  "type": "Feature",
  "properties": {
    "gn:admin1_code":"47.0",
    "gn:admin2_code":"14002.0",
    "gn:asciiname":"Ihe",
    "gn:country_code":"NG",
    "gn:dem":197,
    "gn:feature_class":"P",
    "gn:feature_code":"PPL",
    "gn:name":"Ihe",
    "gn:population":0,
    "gn:timezone":"Africa/Lagos",
    "iso:country":"NG",
    "wof:name":"Ihe",
    "wof:placetype":"locality"
},
  "geometry": {"coordinates":[7.46085,6.23438],"type":"Point"}
}