{
  "type": "Feature",
  "properties": {
    "gn:admin1_code":"35.0",
    "gn:admin2_code":"2003.0",
    "gn:asciiname":"Wasi",
    "gn:country_code":"NG",
    "gn:dem":428,
    "gn:feature_class":"P",
    "gn:feature_code":"PPL",
    "gn:name":"Wasi",
    "gn:population":0,
    "gn:timezone":"Africa/Lagos",
    "iso:country":"NG",
    "name:ceb_x_preferred":[
        "Wasi"
    ],
    "name:swe_x_preferred":[
        "Wasi"
    ],
    "wof:name":"Wasi",
    "wof:placetype":"locality"
},
  "geometry": {"coordinates":[11.66667,8.43333],"type":"Point"}
}