{
  "type": "Feature",
  "properties": {
    "gn:admin1_code":"27.0",
    "gn:admin2_code":"104.0",
    "gn:admin3_code":"10409",
    "gn:asciiname":"Kasheri",
    "gn:country_code":"NG",
    "gn:dem":261,
    "gn:feature_class":"P",
    "gn:feature_code":"PPL",
    "gn:name":"Kasheri",
    "gn:population":0,
    "gn:timezone":"Africa/Lagos",
    "iso:country":"NG",
    "wof:name":"Kasheri",
    "wof:placetype":"locality"
},
  "geometry": {"coordinates":[11.80761,10.34616],"type":"Point"}
}