{
  "type": "Feature",
  "properties": {
    "gn:admin1_code":"27.0",
    "gn:admin2_code":"112.0",
    "gn:admin3_code":"11209",
    "gn:asciiname":"Hutenbaya",
    "gn:country_code":"NG",
    "gn:dem":253,
    "gn:feature_class":"P",
    "gn:feature_code":"PPL",
    "gn:name":"Hutenbaya",
    "gn:population":0,
    "gn:timezone":"Africa/Lagos",
    "iso:country":"NG",
    "wof:name":"Hutenbaya",
    "wof:placetype":"locality"
},
  "geometry": {"coordinates":[12.2544,10.39176],"type":"Point"}
}