{
  "type": "Feature",
  "properties": {
    "gn:admin1_code":"31.0",
    "gn:admin2_code":"27007",
    "gn:asciiname":"Emiladan",
    "gn:country_code":"NG",
    "gn:dem":183,
    "gn:feature_class":"P",
    "gn:feature_code":"PPL",
    "gn:name":"Emiladan",
    "gn:population":0,
    "gn:timezone":"Africa/Lagos",
    "iso:country":"NG",
    "wof:name":"Emiladan",
    "wof:placetype":"neighbourhood"
},
  "geometry": {"coordinates":[5.99489,9.04268],"type":"Point"}
}