{
  "type": "Feature",
  "properties": {
    "gn:admin1_code":"48.0",
    "gn:admin2_code":"29006.0",
    "gn:asciiname":"Ipinsa",
    "gn:country_code":"NG",
    "gn:dem":402,
    "gn:feature_class":"P",
    "gn:feature_code":"PPL",
    "gn:name":"Ipinsa",
    "gn:population":0,
    "gn:timezone":"Africa/Lagos",
    "iso:country":"NG",
    "name:und_x_variant":[
        "Ipensa",
        "Ipinsa"
    ],
    "wof:name":"Ipinsa",
    "wof:placetype":"locality"
},
  "geometry": {"coordinates":[5.14677,7.3214],"type":"Point"}
}