{
  "type": "Feature",
  "properties": {
    "gn:admin1_code":"53.0",
    "gn:admin2_code":"11003.0",
    "gn:asciiname":"Ndi-Owere Amangwu",
    "gn:country_code":"NG",
    "gn:dem":68,
    "gn:feature_class":"P",
    "gn:feature_code":"PPL",
    "gn:name":"Ndi-Owere Amangwu",
    "gn:population":0,
    "gn:timezone":"Africa/Lagos",
    "iso:country":"NG",
    "wof:name":"Ndi-Owere Amangwu",
    "wof:placetype":"locality"
},
  "geometry": {"coordinates":[7.84717,5.87738],"type":"Point"}
}