{
  "type": "Feature",
  "properties": {
    "gn:admin1_code":"16.0",
    "gn:admin2_code":"28016.0",
    "gn:asciiname":"Ida",
    "gn:cc2":"NG",
    "gn:country_code":"NG",
    "gn:dem":160,
    "gn:feature_class":"P",
    "gn:feature_code":"PPL",
    "gn:name":"Ida",
    "gn:population":0,
    "gn:timezone":"Africa/Lagos",
    "iso:country":"NG",
    "name:bre_x_preferred":[
        "Ida"
    ],
    "name:bul_x_preferred":[
        "\u0418\u0434\u0430"
    ],
    "name:cat_x_preferred":[
        "Ida"
    ],
    "name:ceb_x_preferred":[
        "Ida"
    ],
    "name:ces_x_preferred":[
        "Ida"
    ],
    "name:deu_x_preferred":[
        "Ida"
    ],
    "name:eus_x_preferred":[
        "Ida"
    ],
    "name:fas_x_preferred":[
        "\u0627\u06cc\u062f\u0627"
    ],
    "name:fin_x_preferred":[
        "Ida"
    ],
    "name:fra_x_preferred":[
        "Ida"
    ],
    "name:heb_x_preferred":[
        "\u05d0\u05d9\u05d3\u05d4"
    ],
    "name:hrv_x_preferred":[
        "Ida"
    ],
    "name:hye_x_preferred":[
        "\u053b\u0564\u0561"
    ],
    "name:isl_x_preferred":[
        "Ida"
    ],
    "name:lat_x_preferred":[
        "Ida"
    ],
    "name:lav_x_preferred":[
        "Ida"
    ],
    "name:lmo_x_preferred":[
        "Ida"
    ],
    "name:mal_x_preferred":[
        "\u0d07\u0d21"
    ],
    "name:nld_x_preferred":[
        "Ida"
    ],
    "name:pol_x_preferred":[
        "Ida"
    ],
    "name:por_x_preferred":[
        "Ida"
    ],
    "name:rus_x_preferred":[
        "\u0418\u0434\u0430"
    ],
    "name:slk_x_preferred":[
        "Ida"
    ],
    "name:spa_x_preferred":[
        "Ida"
    ],
    "name:srp_x_preferred":[
        "\u0418\u0434\u0430"
    ],
    "name:swe_x_preferred":[
        "Ida"
    ],
    "name:tur_x_preferred":[
        "Ida"
    ],
    "name:ukr_x_preferred":[
        "\u0406\u0434\u0430"
    ],
    "name:und_x_variant":[
        "Idiya",
        "Ida"
    ],
    "wof:name":"Ida",
    "wof:placetype":"locality"
},
  "geometry": {"coordinates":[3.65,7.35],"type":"Point"}
}