{
  "type": "Feature",
  "properties": {
    "gn:admin1_code":"16.0",
    "gn:admin2_code":"28016.0",
    "gn:asciiname":"Ida",
    "gn:cc2":"NG",
    "gn:country_code":"NG",
    "gn:dem":160,
    "gn:feature_class":"P",
    "gn:feature_code":"PPL",
    "gn:name":"Ida",
    "gn:population":0,
    "gn:timezone":"Africa/Lagos",
    "iso:country":"NG",
    "name:und_x_variant":[
        "Idiya",
        "Ida"
    ],
    "wof:name":"Ida",
    "wof:placetype":"locality"
},
  "geometry": {"coordinates":[3.65,7.35],"type":"Point"}
}