{
  "type": "Feature",
  "properties": {
    "gn:admin1_code":"31.0",
    "gn:admin2_code":"27021.0",
    "gn:asciiname":"Argida",
    "gn:country_code":"NG",
    "gn:dem":273,
    "gn:feature_class":"P",
    "gn:feature_code":"PPL",
    "gn:name":"Argida",
    "gn:population":0,
    "gn:timezone":"Africa/Lagos",
    "iso:country":"NG",
    "wof:name":"Argida",
    "wof:placetype":"locality"
},
  "geometry": {"coordinates":[5.18333,10.86667],"type":"Point"}
}