{
  "type": "Feature",
  "properties": {
    "gn:admin1_code":"55.0",
    "gn:admin2_code":"16005.0",
    "gn:asciiname":"Gassol",
    "gn:country_code":"NG",
    "gn:dem":284,
    "gn:feature_class":"P",
    "gn:feature_code":"PPL",
    "gn:name":"Gassol",
    "gn:population":0,
    "gn:timezone":"Africa/Lagos",
    "iso:country":"NG",
    "name:cat_x_preferred":[
        "Gassol"
    ],
    "name:fra_x_preferred":[
        "Gassol"
    ],
    "name:hau_x_preferred":[
        "Gassol"
    ],
    "name:ita_x_preferred":[
        "Gassol"
    ],
    "name:spa_x_preferred":[
        "Gassol"
    ],
    "wof:name":"Gassol",
    "wof:placetype":"locality"
},
  "geometry": {"coordinates":[11.4497,10.69222],"type":"Point"}
}