{
  "type": "Feature",
  "properties": {
    "gn:admin1_code":"27.0",
    "gn:admin2_code":"111.0",
    "gn:admin3_code":"11102",
    "gn:asciiname":"Malakwaya Two",
    "gn:country_code":"NG",
    "gn:dem":412,
    "gn:feature_class":"P",
    "gn:feature_code":"PPL",
    "gn:name":"Malakwaya Two",
    "gn:population":0,
    "gn:timezone":"Africa/Lagos",
    "iso:country":"NG",
    "name:und_x_variant":[
        "Malakwaya II"
    ],
    "wof:name":"Malakwaya Two",
    "wof:placetype":"locality"
},
  "geometry": {"coordinates":[13.39514,10.95183],"type":"Point"}
}