{
  "type": "Feature",
  "properties": {
    "gn:admin1_code":"51.0",
    "gn:admin2_code":"605.0",
    "gn:admin3_code":"60502",
    "gn:asciiname":"Gidan-Marafa",
    "gn:country_code":"NG",
    "gn:dem":333,
    "gn:feature_class":"P",
    "gn:feature_code":"PPL",
    "gn:name":"Gidan-Marafa",
    "gn:population":0,
    "gn:timezone":"Africa/Lagos",
    "iso:country":"NG",
    "wof:name":"Gidan-Marafa",
    "wof:placetype":"locality"
},
  "geometry": {"coordinates":[5.55407,13.45543],"type":"Point"}
}