{
  "type": "Feature",
  "properties": {
    "gn:admin1_code":"16.0",
    "gn:admin2_code":"28015.0",
    "gn:asciiname":"Oloko",
    "gn:country_code":"NG",
    "gn:dem":85,
    "gn:feature_class":"P",
    "gn:feature_code":"PPL",
    "gn:name":"Oloko",
    "gn:population":0,
    "gn:timezone":"Africa/Lagos",
    "iso:country":"NG",
    "wof:name":"Oloko",
    "wof:placetype":"locality"
},
  "geometry": {"coordinates":[3.59972,6.97488],"type":"Point"}
}