{
  "type": "Feature",
  "properties": {
    "gn:admin1_code":"43.0",
    "gn:asciiname":"Kurwa",
    "gn:country_code":"NG",
    "gn:dem":152,
    "gn:feature_class":"P",
    "gn:feature_code":"PPL",
    "gn:name":"Kurwa",
    "gn:population":0,
    "gn:timezone":"Africa/Lagos",
    "iso:country":"NG",
    "name:eng_x_preferred":[
        "Kurwa"
    ],
    "wof:name":"Kurwa",
    "wof:placetype":"locality"
},
  "geometry": {"coordinates":[11.57419,9.32245],"type":"Point"}
}