{
  "type": "Feature",
  "properties": {
    "gn:admin1_code":"21.0",
    "gn:admin2_code":"3025.0",
    "gn:asciiname":"Iquita",
    "gn:country_code":"NG",
    "gn:dem":42,
    "gn:feature_class":"P",
    "gn:feature_code":"PPL",
    "gn:name":"Iquita",
    "gn:population":0,
    "gn:timezone":"Africa/Lagos",
    "iso:country":"NG",
    "wof:name":"Iquita",
    "wof:placetype":"locality"
},
  "geometry": {"coordinates":[8.2243,4.80432],"type":"Point"}
}