{
  "type": "Feature",
  "properties": {
    "gn:admin1_code":"40.0",
    "gn:admin2_code":"519.0",
    "gn:admin3_code":"51908",
    "gn:asciiname":"Kuba",
    "gn:country_code":"NG",
    "gn:dem":392,
    "gn:feature_class":"P",
    "gn:feature_code":"PPL",
    "gn:name":"Kuba",
    "gn:population":0,
    "gn:timezone":"Africa/Lagos",
    "iso:country":"NG",
    "wof:name":"Kuba",
    "wof:placetype":"locality"
},
  "geometry": {"coordinates":[5.58377,11.46466],"type":"Point"}
}