{
  "type": "Feature",
  "properties": {
    "gn:admin1_code":"24.0",
    "gn:admin2_code":"425.0",
    "gn:admin3_code":"42505",
    "gn:asciiname":"Layin Minista",
    "gn:country_code":"NG",
    "gn:dem":653,
    "gn:feature_class":"P",
    "gn:feature_code":"PPL",
    "gn:name":"Layin Minista",
    "gn:population":0,
    "gn:timezone":"Africa/Lagos",
    "iso:country":"NG",
    "wof:name":"Layin Minista",
    "wof:placetype":"locality"
},
  "geometry": {"coordinates":[7.51667,11.68333],"type":"Point"}
}