{
  "type": "Feature",
  "properties": {
    "gn:admin1_code":"42.0",
    "gn:admin2_code":"30014.0",
    "gn:asciiname":"Oru Alade",
    "gn:country_code":"NG",
    "gn:dem":198,
    "gn:feature_class":"P",
    "gn:feature_code":"PPL",
    "gn:name":"Oru Alade",
    "gn:population":0,
    "gn:timezone":"Africa/Lagos",
    "iso:country":"NG",
    "wof:name":"Oru Alade",
    "wof:placetype":"locality"
},
  "geometry": {"coordinates":[4.48333,7.21667],"type":"Point"}
}