{
  "type": "Feature",
  "properties": {
    "gn:admin1_code":"27.0",
    "gn:admin2_code":"114.0",
    "gn:admin3_code":"11404",
    "gn:asciiname":"Dongo",
    "gn:country_code":"NG",
    "gn:dem":381,
    "gn:feature_class":"P",
    "gn:feature_code":"PPL",
    "gn:name":"Dongo",
    "gn:population":0,
    "gn:timezone":"Africa/Lagos",
    "iso:country":"NG",
    "name:ceb_x_preferred":[
        "Dongo"
    ],
    "name:deu_x_preferred":[
        "Dongo"
    ],
    "name:epo_x_preferred":[
        "Dongo"
    ],
    "name:fra_x_preferred":[
        "Dongo"
    ],
    "name:ita_x_preferred":[
        "Dongo"
    ],
    "name:nld_x_preferred":[
        "Dongo"
    ],
    "name:rus_x_preferred":[
        "\u0414\u043e\u043d\u0433\u043e"
    ],
    "name:swe_x_preferred":[
        "Dongo"
    ],
    "wof:name":"Dongo",
    "wof:placetype":"locality"
},
  "geometry": {"coordinates":[12.4421,11.56778],"type":"Point"}
}