{
  "type": "Feature",
  "properties": {
    "gn:admin1_code":"46.0",
    "gn:admin2_code":"5020",
    "gn:admin3_code":"BA2006",
    "gn:asciiname":"Langawa",
    "gn:country_code":"NG",
    "gn:dem":367,
    "gn:feature_class":"P",
    "gn:feature_code":"PPL",
    "gn:name":"Langawa",
    "gn:population":0,
    "gn:timezone":"Africa/Lagos",
    "iso:country":"NG",
    "wof:name":"Langawa",
    "wof:placetype":"locality"
},
  "geometry": {"coordinates":[10.3132,12.0376],"type":"Point"}
}