{
  "type": "Feature",
  "properties": {
    "gn:admin1_code":"46.0",
    "gn:admin2_code":"5005.0",
    "gn:admin3_code":"BA0508",
    "gn:asciiname":"Shuwari",
    "gn:country_code":"NG",
    "gn:dem":337,
    "gn:feature_class":"P",
    "gn:feature_code":"PPL",
    "gn:name":"Shuwari",
    "gn:population":0,
    "gn:timezone":"Africa/Lagos",
    "iso:country":"NG",
    "name:eng_x_preferred":[
        "Shuwari"
    ],
    "wof:name":"Shuwari",
    "wof:placetype":"locality"
},
  "geometry": {"coordinates":[10.60723,10.86529],"type":"Point"}
}