{
  "type": "Feature",
  "properties": {
    "gn:admin1_code":"22.0",
    "gn:admin2_code":"9017.0",
    "gn:asciiname":"Epenti",
    "gn:country_code":"NG",
    "gn:dem":34,
    "gn:feature_class":"P",
    "gn:feature_code":"PPL",
    "gn:name":"Epenti",
    "gn:population":0,
    "gn:timezone":"Africa/Lagos",
    "iso:country":"NG",
    "wof:name":"Epenti",
    "wof:placetype":"locality"
},
  "geometry": {"coordinates":[8.10476,5.92737],"type":"Point"}
}