{
  "type": "Feature",
  "properties": {
    "gn:admin1_code":"46.0",
    "gn:admin2_code":"5020.0",
    "gn:admin3_code":"BA2004",
    "gn:asciiname":"Makawa",
    "gn:country_code":"NG",
    "gn:dem":363,
    "gn:feature_class":"P",
    "gn:feature_code":"PPL",
    "gn:name":"Makawa",
    "gn:population":0,
    "gn:timezone":"Africa/Lagos",
    "iso:country":"NG",
    "wof:name":"Makawa",
    "wof:placetype":"locality"
},
  "geometry": {"coordinates":[10.19842,12.20638],"type":"Point"}
}