{
  "type": "Feature",
  "properties": {
    "gn:admin1_code":"26.0",
    "gn:admin2_code":"7019.0",
    "gn:asciiname":"Ijegu",
    "gn:country_code":"NG",
    "gn:dem":109,
    "gn:feature_class":"P",
    "gn:feature_code":"PPL",
    "gn:name":"Ijegu",
    "gn:population":0,
    "gn:timezone":"Africa/Lagos",
    "iso:country":"NG",
    "wof:name":"Ijegu",
    "wof:placetype":"locality"
},
  "geometry": {"coordinates":[8.20189,7.10539],"type":"Point"}
}