{
  "type": "Feature",
  "properties": {
    "gn:admin1_code":"16.0",
    "gn:admin2_code":"28008.0",
    "gn:asciiname":"Iro",
    "gn:country_code":"NG",
    "gn:dem":14,
    "gn:feature_class":"P",
    "gn:feature_code":"PPL",
    "gn:name":"Iro",
    "gn:population":0,
    "gn:timezone":"Africa/Lagos",
    "iso:country":"NG",
    "wof:name":"Iro",
    "wof:placetype":"locality"
},
  "geometry": {"coordinates":[4.11937,6.66378],"type":"Point"}
}