{
  "type": "Feature",
  "properties": {
    "gn:admin1_code":"57.0",
    "gn:admin2_code":"813.0",
    "gn:admin3_code":"81308",
    "gn:asciiname":"Marke",
    "gn:country_code":"NG",
    "gn:dem":519,
    "gn:feature_class":"P",
    "gn:feature_code":"PPL",
    "gn:name":"Marke",
    "gn:population":0,
    "gn:timezone":"Africa/Lagos",
    "iso:country":"NG",
    "name:als_x_preferred":[
        "Marke"
    ],
    "name:ceb_x_preferred":[
        "Marke"
    ],
    "name:deu_x_preferred":[
        "Marke"
    ],
    "name:fry_x_preferred":[
        "Marke"
    ],
    "name:lit_x_preferred":[
        "Mark\u0117"
    ],
    "name:nld_x_preferred":[
        "Marke"
    ],
    "name:pol_x_preferred":[
        "Marke"
    ],
    "name:rus_x_preferred":[
        "\u041c\u0430\u0440\u043a\u0435"
    ],
    "name:swe_x_preferred":[
        "Marke"
    ],
    "wof:name":"Marke",
    "wof:placetype":"locality"
},
  "geometry": {"coordinates":[6.89473,12.0894],"type":"Point"}
}