{
  "type": "Feature",
  "properties": {
    "gn:admin1_code":"57.0",
    "gn:admin2_code":"813.0",
    "gn:admin3_code":"81308",
    "gn:asciiname":"Marke",
    "gn:country_code":"NG",
    "gn:dem":519,
    "gn:feature_class":"P",
    "gn:feature_code":"PPL",
    "gn:name":"Marke",
    "gn:population":0,
    "gn:timezone":"Africa/Lagos",
    "iso:country":"NG",
    "wof:name":"Marke",
    "wof:placetype":"locality"
},
  "geometry": {"coordinates":[6.89473,12.0894],"type":"Point"}
}