{
  "type": "Feature",
  "properties": {
    "gn:admin1_code":"56.0",
    "gn:admin2_code":"26013.0",
    "gn:asciiname":"Arum Ada",
    "gn:country_code":"NG",
    "gn:dem":470,
    "gn:feature_class":"P",
    "gn:feature_code":"PPL",
    "gn:name":"Arum Ada",
    "gn:population":0,
    "gn:timezone":"Africa/Lagos",
    "iso:country":"NG",
    "wof:name":"Arum Ada",
    "wof:placetype":"locality"
},
  "geometry": {"coordinates":[8.64928,9.07804],"type":"Point"}
}