{
  "type": "Feature",
  "properties": {
    "gn:admin1_code":"16.0",
    "gn:admin2_code":"28001.0",
    "gn:asciiname":"Onigbado Market",
    "gn:cc2":"NG",
    "gn:country_code":"NG",
    "gn:dem":191,
    "gn:feature_class":"P",
    "gn:feature_code":"PPL",
    "gn:name":"Onigbado Market",
    "gn:population":0,
    "gn:timezone":"Africa/Lagos",
    "iso:country":"NG",
    "name:und_x_variant":[
        "Onigbado",
        "Onigbagbo-Market",
        "Onigbado Market"
    ],
    "wof:name":"Onigbado Market",
    "wof:placetype":"locality"
},
  "geometry": {"coordinates":[3.06667,7.33333],"type":"Point"}
}