{
  "type": "Feature",
  "properties": {
    "gn:admin1_code":"31.0",
    "gn:admin2_code":"27013.0",
    "gn:asciiname":"Egbati Yelwa",
    "gn:country_code":"NG",
    "gn:dem":190,
    "gn:feature_class":"P",
    "gn:feature_code":"PPL",
    "gn:name":"Egbati Yelwa",
    "gn:population":0,
    "gn:timezone":"Africa/Lagos",
    "iso:country":"NG",
    "name:und_x_variant":[
        "Tungan Salahu",
        "Tungar Salahu",
        "Egbati Yelwa",
        "Egbanti Yelwa"
    ],
    "wof:name":"Egbati Yelwa",
    "wof:placetype":"locality"
},
  "geometry": {"coordinates":[5.63321,9.25226],"type":"Point"}
}