{
  "type": "Feature",
  "properties": {
    "gn:admin1_code":"27.0",
    "gn:admin2_code":"106.0",
    "gn:admin3_code":"10602",
    "gn:asciiname":"Tabang Bula Buba",
    "gn:country_code":"NG",
    "gn:dem":487,
    "gn:feature_class":"P",
    "gn:feature_code":"PPL",
    "gn:name":"Tabang Bula Buba",
    "gn:population":0,
    "gn:timezone":"Africa/Lagos",
    "iso:country":"NG",
    "wof:name":"Tabang Bula Buba",
    "wof:placetype":"locality"
},
  "geometry": {"coordinates":[12.9625,10.68285],"type":"Point"}
}