{
  "type": "Feature",
  "properties": {
    "gn:admin1_code":"27.0",
    "gn:admin2_code":"118.0",
    "gn:admin3_code":"11804",
    "gn:asciiname":"Kubuku Kaduga",
    "gn:country_code":"NG",
    "gn:dem":344,
    "gn:feature_class":"P",
    "gn:feature_code":"PPL",
    "gn:name":"Kubuku Kaduga",
    "gn:population":0,
    "gn:timezone":"Africa/Lagos",
    "iso:country":"NG",
    "wof:name":"Kubuku Kaduga",
    "wof:placetype":"locality"
},
  "geometry": {"coordinates":[11.92671,10.42615],"type":"Point"}
}