{
  "type": "Feature",
  "properties": {
    "gn:admin1_code":"46.0",
    "gn:admin2_code":"5015.0",
    "gn:admin3_code":"BA1514",
    "gn:asciiname":"Buruku",
    "gn:country_code":"NG",
    "gn:dem":701,
    "gn:feature_class":"P",
    "gn:feature_code":"PPL",
    "gn:name":"Buruku",
    "gn:population":0,
    "gn:timezone":"Africa/Lagos",
    "iso:country":"NG",
    "name:fra_x_preferred":[
        "Buruku"
    ],
    "name:hau_x_preferred":[
        "Buruku"
    ],
    "name:ita_x_preferred":[
        "Buruku"
    ],
    "name:por_x_preferred":[
        "Buruku"
    ],
    "name:spa_x_preferred":[
        "Buruku"
    ],
    "wof:name":"Buruku",
    "wof:placetype":"locality"
},
  "geometry": {"coordinates":[8.94773,10.81276],"type":"Point"}
}