{
  "type": "Feature",
  "properties": {
    "gn:admin1_code":"37.0",
    "gn:admin2_code":"12013.0",
    "gn:asciiname":"Ogbahu",
    "gn:country_code":"NG",
    "gn:dem":76,
    "gn:feature_class":"P",
    "gn:feature_code":"PPL",
    "gn:name":"Ogbahu",
    "gn:population":0,
    "gn:timezone":"Africa/Lagos",
    "iso:country":"NG",
    "name:eng_x_preferred":[
        "Ogbahu"
    ],
    "wof:name":"Ogbahu",
    "wof:placetype":"locality"
},
  "geometry": {"coordinates":[6.13909,6.37786],"type":"Point"}
}