{
  "type": "Feature",
  "properties": {
    "gn:admin1_code":"57.0",
    "gn:admin2_code":"809.0",
    "gn:admin3_code":"80903",
    "gn:asciiname":"Ruduno",
    "gn:country_code":"NG",
    "gn:dem":328,
    "gn:feature_class":"P",
    "gn:feature_code":"PPL",
    "gn:name":"Ruduno",
    "gn:population":0,
    "gn:timezone":"Africa/Lagos",
    "iso:country":"NG",
    "wof:name":"Ruduno",
    "wof:placetype":"locality"
},
  "geometry": {"coordinates":[6.2106,12.96826],"type":"Point"}
}