{
  "type": "Feature",
  "properties": {
    "gn:admin1_code":"40.0",
    "gn:admin2_code":"509.0",
    "gn:admin3_code":"50906",
    "gn:asciiname":"Garin Gaou",
    "gn:country_code":"NG",
    "gn:dem":258,
    "gn:feature_class":"P",
    "gn:feature_code":"PPL",
    "gn:name":"Garin Gaou",
    "gn:population":0,
    "gn:timezone":"Africa/Lagos",
    "iso:country":"NG",
    "wof:name":"Garin Gaou",
    "wof:placetype":"locality"
},
  "geometry": {"coordinates":[4.78695,11.65196],"type":"Point"}
}