{
  "type": "Feature",
  "properties": {
    "gn:admin1_code":"53.0",
    "gn:admin2_code":"11003.0",
    "gn:asciiname":"Oso",
    "gn:country_code":"NG",
    "gn:dem":43,
    "gn:feature_class":"P",
    "gn:feature_code":"PPL",
    "gn:name":"Oso",
    "gn:population":0,
    "gn:timezone":"Africa/Lagos",
    "iso:country":"NG",
    "name:ceb_x_preferred":[
        "Oso"
    ],
    "name:fra_x_preferred":[
        "Oso"
    ],
    "name:nld_x_preferred":[
        "Oso"
    ],
    "name:por_x_preferred":[
        "Oso"
    ],
    "name:sco_x_preferred":[
        "Oso"
    ],
    "name:spa_x_preferred":[
        "Oso"
    ],
    "name:swe_x_preferred":[
        "Oso"
    ],
    "wof:name":"Oso",
    "wof:placetype":"locality"
},
  "geometry": {"coordinates":[7.81615,5.8702],"type":"Point"}
}