{
  "type": "Feature",
  "properties": {
    "gn:admin1_code":"23.0",
    "gn:admin2_code":"19020.0",
    "gn:admin3_code":"KD2010",
    "gn:asciiname":"Randa Kamara",
    "gn:country_code":"NG",
    "gn:dem":407,
    "gn:feature_class":"P",
    "gn:feature_code":"PPL",
    "gn:name":"Randa Kamara",
    "gn:population":0,
    "gn:timezone":"Africa/Lagos",
    "iso:country":"NG",
    "name:und_x_variant":[
        "Ungwan Bahago"
    ],
    "wof:name":"Randa Kamara",
    "wof:placetype":"locality"
},
  "geometry": {"coordinates":[8.49295,9.06586],"type":"Point"}
}