{
  "type": "Feature",
  "properties": {
    "gn:admin1_code":"44.0",
    "gn:admin2_code":"709.0",
    "gn:admin3_code":"70909",
    "gn:asciiname":"Dachia",
    "gn:country_code":"NG",
    "gn:dem":348,
    "gn:feature_class":"P",
    "gn:feature_code":"PPL",
    "gn:name":"Dachia",
    "gn:population":0,
    "gn:timezone":"Africa/Lagos",
    "iso:country":"NG",
    "wof:name":"Dachia",
    "wof:placetype":"locality"
},
  "geometry": {"coordinates":[10.78082,12.74786],"type":"Point"}
}