{
  "type": "Feature",
  "properties": {
    "gn:admin1_code":"40.0",
    "gn:asciiname":"Jentulu Hill",
    "gn:country_code":"NG",
    "gn:dem":305,
    "gn:feature_class":"P",
    "gn:feature_code":"PPL",
    "gn:name":"Jentulu Hill",
    "gn:population":0,
    "gn:timezone":"Africa/Lagos",
    "iso:country":"NG",
    "wof:name":"Jentulu Hill",
    "wof:placetype":"locality"
},
  "geometry": {"coordinates":[4.29334,13.21924],"type":"Point"}
}