{
  "type": "Feature",
  "properties": {
    "gn:admin1_code":"35.0",
    "gn:admin2_code":"2007.0",
    "gn:asciiname":"Mabeleri",
    "gn:country_code":"NG",
    "gn:dem":523,
    "gn:feature_class":"P",
    "gn:feature_code":"PPL",
    "gn:name":"Mabeleri",
    "gn:population":0,
    "gn:timezone":"Africa/Lagos",
    "iso:country":"NG",
    "name:und_x_variant":[
        "Mabelen"
    ],
    "wof:name":"Mabeleri",
    "wof:placetype":"locality"
},
  "geometry": {"coordinates":[13.04637,10.09551],"type":"Point"}
}