{
  "type": "Feature",
  "properties": {
    "gn:admin1_code":"37.0",
    "gn:admin2_code":"12001.0",
    "gn:asciiname":"Aiyetoro",
    "gn:country_code":"NG",
    "gn:dem":319,
    "gn:feature_class":"P",
    "gn:feature_code":"PPL",
    "gn:name":"Aiyetoro",
    "gn:population":0,
    "gn:timezone":"Africa/Lagos",
    "iso:country":"NG",
    "wof:name":"Aiyetoro",
    "wof:placetype":"locality"
},
  "geometry": {"coordinates":[6.0942,7.3215],"type":"Point"}
}