{
  "type": "Feature",
  "properties": {
    "gn:admin1_code":"30.0",
    "gn:admin2_code":"24012.0",
    "gn:asciiname":"Alafara",
    "gn:country_code":"NG",
    "gn:dem":291,
    "gn:feature_class":"P",
    "gn:feature_code":"PPL",
    "gn:name":"Alafara",
    "gn:population":0,
    "gn:timezone":"Africa/Lagos",
    "iso:country":"NG",
    "wof:name":"Alafara",
    "wof:placetype":"locality"
},
  "geometry": {"coordinates":[4.36667,8.76667],"type":"Point"}
}