{
  "type": "Feature",
  "properties": {
    "gn:admin1_code":"35.0",
    "gn:asciiname":"Wokare",
    "gn:country_code":"NG",
    "gn:dem":595,
    "gn:feature_class":"P",
    "gn:feature_code":"PPL",
    "gn:name":"Wokare",
    "gn:population":0,
    "gn:timezone":"Africa/Lagos",
    "iso:country":"NG",
    "name:eng_x_preferred":[
        "Wokare"
    ],
    "wof:name":"Wokare",
    "wof:placetype":"locality"
},
  "geometry": {"coordinates":[11.8253,9.09755],"type":"Point"}
}