{
  "type": "Feature",
  "properties": {
    "gn:admin1_code":"49.0",
    "gn:admin2_code":"32008.0",
    "gn:asciiname":"Kabwir",
    "gn:country_code":"NG",
    "gn:dem":765,
    "gn:feature_class":"P",
    "gn:feature_code":"PPL",
    "gn:name":"Kabwir",
    "gn:population":0,
    "gn:timezone":"Africa/Lagos",
    "iso:country":"NG",
    "name:eng_x_preferred":[
        "Kabwir"
    ],
    "wof:name":"Kabwir",
    "wof:placetype":"locality"
},
  "geometry": {"coordinates":[9.57546,9.39663],"type":"Point"}
}