{
  "type": "Feature",
  "properties": {
    "gn:admin1_code":"24.0",
    "gn:admin2_code":"408.0",
    "gn:admin3_code":"40804",
    "gn:asciiname":"Ungwan Rogo",
    "gn:country_code":"NG",
    "gn:dem":684,
    "gn:feature_class":"P",
    "gn:feature_code":"PPL",
    "gn:name":"Ungwan Rogo",
    "gn:population":0,
    "gn:timezone":"Africa/Lagos",
    "iso:country":"NG",
    "wof:name":"Ungwan Rogo",
    "wof:placetype":"locality"
},
  "geometry": {"coordinates":[7.44446,11.46362],"type":"Point"}
}