{
  "type": "Feature",
  "properties": {
    "gn:admin1_code":"52.0",
    "gn:admin2_code":"6002.0",
    "gn:asciiname":"Ogbodugbene",
    "gn:country_code":"NG",
    "gn:dem":13,
    "gn:feature_class":"P",
    "gn:feature_code":"PPL",
    "gn:name":"Ogbodugbene",
    "gn:population":0,
    "gn:timezone":"Africa/Lagos",
    "iso:country":"NG",
    "name:eng_x_preferred":[
        "Ogbodugbene"
    ],
    "wof:name":"Ogbodugbene",
    "wof:placetype":"locality"
},
  "geometry": {"coordinates":[5.67553,4.99564],"type":"Point"}
}