{
  "type": "Feature",
  "properties": {
    "gn:admin1_code":"43.0",
    "gn:admin2_code":"35002.0",
    "gn:asciiname":"Gankoi Ase",
    "gn:country_code":"NG",
    "gn:dem":231,
    "gn:feature_class":"P",
    "gn:feature_code":"PPL",
    "gn:name":"Gankoi Ase",
    "gn:population":0,
    "gn:timezone":"Africa/Lagos",
    "iso:country":"NG",
    "wof:name":"Gankoi Ase",
    "wof:placetype":"locality"
},
  "geometry": {"coordinates":[10.36108,7.57566],"type":"Point"}
}