{
  "type": "Feature",
  "properties": {
    "gn:admin1_code":"16.0",
    "gn:admin2_code":"28014.0",
    "gn:asciiname":"Ijomi",
    "gn:cc2":"NG",
    "gn:country_code":"NG",
    "gn:dem":9,
    "gn:feature_class":"P",
    "gn:feature_code":"PPL",
    "gn:name":"Ijomi",
    "gn:population":0,
    "gn:timezone":"Africa/Lagos",
    "iso:country":"NG",
    "name:und_x_variant":[
        "Ijawmi",
        "Ijomi"
    ],
    "wof:name":"Ijomi",
    "wof:placetype":"locality"
},
  "geometry": {"coordinates":[2.75,6.48333],"type":"Point"}
}