{
  "type": "Feature",
  "properties": {
    "gn:admin1_code":"21.0",
    "gn:admin2_code":"3013.0",
    "gn:asciiname":"Ikot Obioko",
    "gn:country_code":"NG",
    "gn:dem":26,
    "gn:feature_class":"P",
    "gn:feature_code":"PPL",
    "gn:name":"Ikot Obioko",
    "gn:population":0,
    "gn:timezone":"Africa/Lagos",
    "iso:country":"NG",
    "wof:name":"Ikot Obioko",
    "wof:placetype":"locality"
},
  "geometry": {"coordinates":[7.69387,4.68755],"type":"Point"}
}