{
  "type": "Feature",
  "properties": {
    "gn:admin1_code":"48.0",
    "gn:admin2_code":"29007.0",
    "gn:asciiname":"Gbadamosi",
    "gn:country_code":"NG",
    "gn:dem":12,
    "gn:feature_class":"P",
    "gn:feature_code":"PPL",
    "gn:name":"Gbadamosi",
    "gn:population":0,
    "gn:timezone":"Africa/Lagos",
    "iso:country":"NG",
    "wof:name":"Gbadamosi",
    "wof:placetype":"locality"
},
  "geometry": {"coordinates":[4.93967,6.36852],"type":"Point"}
}