{
  "type": "Feature",
  "properties": {
    "gn:admin1_code":"24.0",
    "gn:admin2_code":"404.0",
    "gn:admin3_code":"40406",
    "gn:asciiname":"Kakare",
    "gn:country_code":"NG",
    "gn:dem":397,
    "gn:feature_class":"P",
    "gn:feature_code":"PPL",
    "gn:name":"Kakare",
    "gn:population":0,
    "gn:timezone":"Africa/Lagos",
    "iso:country":"NG",
    "wof:name":"Kakare",
    "wof:placetype":"locality"
},
  "geometry": {"coordinates":[8.76617,12.68451],"type":"Point"}
}