{
  "type": "Feature",
  "properties": {
    "gn:admin1_code":"27.0",
    "gn:admin2_code":"111.0",
    "gn:admin3_code":"11102",
    "gn:asciiname":"Beta",
    "gn:country_code":"NG",
    "gn:dem":373,
    "gn:feature_class":"P",
    "gn:feature_code":"PPL",
    "gn:name":"Beta",
    "gn:population":0,
    "gn:timezone":"Africa/Lagos",
    "iso:country":"NG",
    "name:und_x_variant":[
        "Bitta"
    ],
    "wof:name":"Beta",
    "wof:placetype":"locality"
},
  "geometry": {"coordinates":[13.4162,11.15871],"type":"Point"}
}