{
  "type": "Feature",
  "properties": {
    "gn:admin1_code":"27.0",
    "gn:admin2_code":"101.0",
    "gn:admin3_code":"10111",
    "gn:asciiname":"Mamuri Gana",
    "gn:country_code":"NG",
    "gn:dem":289,
    "gn:feature_class":"P",
    "gn:feature_code":"PPL",
    "gn:name":"Mamuri Gana",
    "gn:population":0,
    "gn:timezone":"Africa/Lagos",
    "iso:country":"NG",
    "wof:name":"Mamuri Gana",
    "wof:placetype":"locality"
},
  "geometry": {"coordinates":[13.3385,13.69031],"type":"Point"}
}