{
  "type": "Feature",
  "properties": {
    "gn:admin1_code":"48.0",
    "gn:admin2_code":"29018.0",
    "gn:asciiname":"Baga",
    "gn:country_code":"NG",
    "gn:dem":322,
    "gn:feature_class":"P",
    "gn:feature_code":"PPL",
    "gn:name":"Baga",
    "gn:population":0,
    "gn:timezone":"Africa/Lagos",
    "iso:country":"NG",
    "wof:name":"Baga",
    "wof:placetype":"locality"
},
  "geometry": {"coordinates":[5.524,7.3015],"type":"Point"}
}