{
  "type": "Feature",
  "properties": {
    "gn:admin1_code":"51.0",
    "gn:admin2_code":"607.0",
    "gn:admin3_code":"60705",
    "gn:asciiname":"Koren Gesu Gesu",
    "gn:country_code":"NG",
    "gn:dem":263,
    "gn:feature_class":"P",
    "gn:feature_code":"PPL",
    "gn:name":"Koren Gesu Gesu",
    "gn:population":0,
    "gn:timezone":"Africa/Lagos",
    "iso:country":"NG",
    "wof:name":"Koren Gesu Gesu",
    "wof:placetype":"locality"
},
  "geometry": {"coordinates":[5.2319,13.4389],"type":"Point"}
}