{
  "type": "Feature",
  "properties": {
    "gn:admin1_code":"11.0",
    "gn:admin2_code":"15006.0",
    "gn:asciiname":"Karshi",
    "gn:cc2":"NG",
    "gn:country_code":"NG",
    "gn:dem":492,
    "gn:feature_class":"P",
    "gn:feature_code":"PPL",
    "gn:name":"Karshi",
    "gn:population":0,
    "gn:timezone":"Africa/Lagos",
    "iso:country":"NG",
    "name:und_x_variant":[
        "Karshe",
        "Karshi"
    ],
    "wof:name":"Karshi",
    "wof:placetype":"locality"
},
  "geometry": {"coordinates":[7.49499,9.07466],"type":"Point"}
}