{
  "type": "Feature",
  "properties": {
    "gn:admin1_code":"35.0",
    "gn:admin2_code":"2018.0",
    "gn:asciiname":"Dumne",
    "gn:cc2":"NG",
    "gn:country_code":"NG",
    "gn:dem":322,
    "gn:feature_class":"P",
    "gn:feature_code":"PPL",
    "gn:name":"Dumne",
    "gn:population":0,
    "gn:timezone":"Africa/Lagos",
    "iso:country":"NG",
    "name:und_x_variant":[
        "Dungma",
        "Dumne"
    ],
    "wof:name":"Dumne",
    "wof:placetype":"locality"
},
  "geometry": {"coordinates":[12.42167,9.77972],"type":"Point"}
}