{
  "type": "Feature",
  "properties": {
    "gn:admin1_code":"16.0",
    "gn:admin2_code":"28011.0",
    "gn:asciiname":"Irawo",
    "gn:country_code":"NG",
    "gn:dem":34,
    "gn:feature_class":"P",
    "gn:feature_code":"PPL",
    "gn:name":"Irawo",
    "gn:population":0,
    "gn:timezone":"Africa/Lagos",
    "iso:country":"NG",
    "name:und_x_variant":[
        "Iraw",
        "Irawo"
    ],
    "wof:name":"Irawo",
    "wof:placetype":"locality"
},
  "geometry": {"coordinates":[4.03566,6.72326],"type":"Point"}
}