{
  "type": "Feature",
  "properties": {
    "gn:admin1_code":"52.0",
    "gn:admin2_code":"6007.0",
    "gn:asciiname":"Eturegbene",
    "gn:country_code":"NG",
    "gn:dem":6,
    "gn:feature_class":"P",
    "gn:feature_code":"PPL",
    "gn:name":"Eturegbene",
    "gn:population":0,
    "gn:timezone":"Africa/Lagos",
    "iso:country":"NG",
    "name:eng_x_preferred":[
        "Eturegbene"
    ],
    "name:eng_x_variant":[
        "Etukegbene"
    ],
    "wof:name":"Eturegbene",
    "wof:placetype":"locality"
},
  "geometry": {"coordinates":[5.95833,4.50259],"type":"Point"}
}