{
  "type": "Feature",
  "properties": {
    "gn:admin1_code":"57.0",
    "gn:admin2_code":"805.0",
    "gn:admin3_code":"80511",
    "gn:asciiname":"Guidan Arna",
    "gn:country_code":"NG",
    "gn:dem":472,
    "gn:feature_class":"P",
    "gn:feature_code":"PPL",
    "gn:name":"Guidan Arna",
    "gn:population":0,
    "gn:timezone":"Africa/Lagos",
    "iso:country":"NG",
    "name:und_x_variant":[
        "Gidan Arna",
        "Guidan Arna"
    ],
    "wof:name":"Guidan Arna",
    "wof:placetype":"locality"
},
  "geometry": {"coordinates":[6.79415,12.21443],"type":"Point"}
}