{
  "type": "Feature",
  "properties": {
    "gn:admin1_code":"32.0",
    "gn:admin2_code":"31014.0",
    "gn:asciiname":"Akunlepon",
    "gn:country_code":"NG",
    "gn:dem":180,
    "gn:feature_class":"P",
    "gn:feature_code":"PPL",
    "gn:name":"Akunlepon",
    "gn:population":0,
    "gn:timezone":"Africa/Lagos",
    "iso:country":"NG",
    "wof:name":"Akunlepon",
    "wof:placetype":"neighbourhood"
},
  "geometry": {"coordinates":[3.835,7.33861],"type":"Point"}
}