{
  "type": "Feature",
  "properties": {
    "gn:admin1_code":"44.0",
    "gn:admin2_code":"701.0",
    "gn:admin3_code":"70109",
    "gn:asciiname":"Jawa",
    "gn:country_code":"NG",
    "gn:dem":339,
    "gn:feature_class":"P",
    "gn:feature_code":"PPL",
    "gn:name":"Jawa",
    "gn:population":0,
    "gn:timezone":"Africa/Lagos",
    "iso:country":"NG",
    "wof:name":"Jawa",
    "wof:placetype":"locality"
},
  "geometry": {"coordinates":[11.03994,12.81399],"type":"Point"}
}