{
  "type": "Feature",
  "properties": {
    "gn:admin1_code":"31.0",
    "gn:admin2_code":"27019.0",
    "gn:asciiname":"Abolo",
    "gn:country_code":"NG",
    "gn:dem":526,
    "gn:feature_class":"P",
    "gn:feature_code":"PPL",
    "gn:name":"Abolo",
    "gn:population":0,
    "gn:timezone":"Africa/Lagos",
    "iso:country":"NG",
    "name:und_x_variant":[
        "Abulo",
        "Abolo"
    ],
    "wof:name":"Abolo",
    "wof:placetype":"locality"
},
  "geometry": {"coordinates":[7.13391,9.60979],"type":"Point"}
}