{
  "type": "Feature",
  "properties": {
    "gn:admin1_code":"43.0",
    "gn:admin2_code":"35005",
    "gn:asciiname":"Kawangilo",
    "gn:country_code":"NG",
    "gn:dem":201,
    "gn:feature_class":"P",
    "gn:feature_code":"PPL",
    "gn:name":"Kawangilo",
    "gn:population":0,
    "gn:timezone":"Africa/Lagos",
    "iso:country":"NG",
    "wof:name":"Kawangilo",
    "wof:placetype":"locality"
},
  "geometry": {"coordinates":[10.82632,8.49465],"type":"Point"}
}