{
  "type": "Feature",
  "properties": {
    "gn:admin1_code":"31.0",
    "gn:admin2_code":"27023",
    "gn:asciiname":"Gwari",
    "gn:country_code":"NG",
    "gn:dem":498,
    "gn:feature_class":"P",
    "gn:feature_code":"PPL",
    "gn:name":"Gwari",
    "gn:population":0,
    "gn:timezone":"Africa/Lagos",
    "iso:country":"NG",
    "wof:name":"Gwari",
    "wof:placetype":"locality"
},
  "geometry": {"coordinates":[7.18137,9.28807],"type":"Point"}
}