{
  "type": "Feature",
  "properties": {
    "gn:admin1_code":"26.0",
    "gn:admin2_code":"7012",
    "gn:asciiname":"Dondo",
    "gn:country_code":"NG",
    "gn:dem":155,
    "gn:feature_class":"P",
    "gn:feature_code":"PPL",
    "gn:name":"Dondo",
    "gn:population":0,
    "gn:timezone":"Africa/Lagos",
    "iso:country":"NG",
    "name:ceb_x_preferred":[
        "Dondo"
    ],
    "name:deu_x_preferred":[
        "Dondo"
    ],
    "name:fra_x_preferred":[
        "Dondo"
    ],
    "name:ita_x_preferred":[
        "Dondo"
    ],
    "name:jpn_x_preferred":[
        "\u30c9\u30f3\u30c9"
    ],
    "name:pol_x_preferred":[
        "Dondo"
    ],
    "name:por_x_preferred":[
        "Dondo"
    ],
    "name:swe_x_preferred":[
        "Dondo"
    ],
    "wof:name":"Dondo",
    "wof:placetype":"locality"
},
  "geometry": {"coordinates":[9.27,7.55973],"type":"Point"}
}