{
  "type": "Feature",
  "properties": {
    "gn:admin1_code":"27.0",
    "gn:admin2_code":"112.0",
    "gn:admin3_code":"11202",
    "gn:asciiname":"Mainta",
    "gn:country_code":"NG",
    "gn:dem":616,
    "gn:feature_class":"P",
    "gn:feature_code":"PPL",
    "gn:name":"Mainta",
    "gn:population":0,
    "gn:timezone":"Africa/Lagos",
    "iso:country":"NG",
    "wof:name":"Mainta",
    "wof:placetype":"locality"
},
  "geometry": {"coordinates":[12.07698,10.53015],"type":"Point"}
}