{
  "type": "Feature",
  "properties": {
    "gn:admin1_code":"44.0",
    "gn:admin2_code":"717",
    "gn:admin3_code":"71707",
    "gn:asciiname":"Bibio",
    "gn:country_code":"NG",
    "gn:dem":344,
    "gn:feature_class":"P",
    "gn:feature_code":"PPL",
    "gn:name":"Bibio",
    "gn:population":0,
    "gn:timezone":"Africa/Lagos",
    "iso:country":"NG",
    "name:fra_x_preferred":[
        "Bibio"
    ],
    "name:ita_x_preferred":[
        "Bibio"
    ],
    "name:pol_x_preferred":[
        "Stephen Wilkinson"
    ],
    "name:spa_x_preferred":[
        "Bibio"
    ],
    "wof:name":"Bibio",
    "wof:placetype":"locality"
},
  "geometry": {"coordinates":[10.80065,13.17095],"type":"Point"}
}