{
  "type": "Feature",
  "properties": {
    "gn:admin1_code":"35.0",
    "gn:admin2_code":"2005.0",
    "gn:asciiname":"Chawa",
    "gn:country_code":"NG",
    "gn:dem":639,
    "gn:feature_class":"P",
    "gn:feature_code":"PPL",
    "gn:name":"Chawa",
    "gn:population":0,
    "gn:timezone":"Africa/Lagos",
    "iso:country":"NG",
    "name:fas_x_preferred":[
        "\u0686\u0627\u0648\u0627"
    ],
    "name:urd_x_preferred":[
        "\u0686\u0627\u0648\u0627"
    ],
    "wof:name":"Chawa",
    "wof:placetype":"locality"
},
  "geometry": {"coordinates":[12.46451,10.05528],"type":"Point"}
}