{
  "type": "Feature",
  "properties": {
    "gn:admin1_code":"16.0",
    "gn:admin2_code":"28014.0",
    "gn:asciiname":"Fatedo",
    "gn:country_code":"NG",
    "gn:dem":45,
    "gn:feature_class":"P",
    "gn:feature_code":"PPL",
    "gn:name":"Fatedo",
    "gn:population":0,
    "gn:timezone":"Africa/Lagos",
    "iso:country":"NG",
    "wof:name":"Fatedo",
    "wof:placetype":"locality"
},
  "geometry": {"coordinates":[2.85,6.63333],"type":"Point"}
}