{
  "type": "Feature",
  "properties": {
    "gn:admin1_code":"45.0",
    "gn:admin2_code":"1006.0",
    "gn:asciiname":"Mvosi",
    "gn:country_code":"NG",
    "gn:dem":107,
    "gn:feature_class":"P",
    "gn:feature_code":"PPL",
    "gn:name":"Mvosi",
    "gn:population":0,
    "gn:timezone":"Africa/Lagos",
    "iso:country":"NG",
    "wof:name":"Mvosi",
    "wof:placetype":"locality"
},
  "geometry": {"coordinates":[7.44667,5.31495],"type":"Point"}
}