{
  "type": "Feature",
  "properties": {
    "gn:admin1_code":"26.0",
    "gn:admin2_code":"7021",
    "gn:asciiname":"Aka",
    "gn:country_code":"NG",
    "gn:dem":128,
    "gn:feature_class":"P",
    "gn:feature_code":"PPL",
    "gn:name":"Aka",
    "gn:population":0,
    "gn:timezone":"Africa/Lagos",
    "iso:country":"NG",
    "name:ceb_x_preferred":[
        "Aka"
    ],
    "name:ces_x_preferred":[
        "Aka"
    ],
    "name:deu_x_preferred":[
        "Aka"
    ],
    "name:fra_x_preferred":[
        "Aka"
    ],
    "name:lav_x_preferred":[
        "AKA"
    ],
    "name:nld_x_preferred":[
        "Aka"
    ],
    "name:pol_x_preferred":[
        "Aka"
    ],
    "name:rus_x_preferred":[
        "\u0410\u043a\u0430"
    ],
    "name:spa_x_preferred":[
        "Aka"
    ],
    "name:swe_x_preferred":[
        "Aka"
    ],
    "name:ukr_x_preferred":[
        "Aka"
    ],
    "wof:name":"Aka",
    "wof:placetype":"locality"
},
  "geometry": {"coordinates":[9.42809,7.79837],"type":"Point"}
}