{
  "type": "Feature",
  "properties": {
    "gn:admin1_code":"36.0",
    "gn:admin2_code":"10023.0",
    "gn:asciiname":"Okitimekpo",
    "gn:country_code":"NG",
    "gn:dem":11,
    "gn:feature_class":"P",
    "gn:feature_code":"PPL",
    "gn:name":"Okitimekpo",
    "gn:population":0,
    "gn:timezone":"Africa/Lagos",
    "iso:country":"NG",
    "name:eng_x_preferred":[
        "Okitimekpo"
    ],
    "name:eng_x_variant":[
        "Okiomekpo"
    ],
    "wof:name":"Okitimekpo",
    "wof:placetype":"locality"
},
  "geometry": {"coordinates":[5.15654,5.61133],"type":"Point"}
}