{
  "type": "Feature",
  "properties": {
    "gn:admin1_code":"27.0",
    "gn:admin2_code":"127.0",
    "gn:admin3_code":"12706",
    "gn:asciiname":"Hamma Lamu",
    "gn:country_code":"NG",
    "gn:dem":227,
    "gn:feature_class":"P",
    "gn:feature_code":"PPL",
    "gn:name":"Hamma Lamu",
    "gn:population":0,
    "gn:timezone":"Africa/Lagos",
    "iso:country":"NG",
    "wof:name":"Hamma Lamu",
    "wof:placetype":"locality"
},
  "geometry": {"coordinates":[12.04872,10.06539],"type":"Point"}
}