{
  "type": "Feature",
  "properties": {
    "gn:admin1_code":"57.0",
    "gn:asciiname":"Zugu",
    "gn:country_code":"NG",
    "gn:dem":223,
    "gn:feature_class":"P",
    "gn:feature_code":"PPL",
    "gn:name":"Zugu",
    "gn:population":0,
    "gn:timezone":"Africa/Lagos",
    "iso:country":"NG",
    "wof:name":"Zugu",
    "wof:placetype":"locality"
},
  "geometry": {"coordinates":[4.55702,11.79739],"type":"Point"}
}