{
  "type": "Feature",
  "properties": {
    "gn:admin1_code":"29.0",
    "gn:admin2_code":"20041.0",
    "gn:admin3_code":"KN2209",
    "gn:asciiname":"Kogin Dabga",
    "gn:country_code":"NG",
    "gn:dem":514,
    "gn:feature_class":"P",
    "gn:feature_code":"PPL",
    "gn:name":"Kogin Dabga",
    "gn:population":0,
    "gn:timezone":"Africa/Lagos",
    "iso:country":"NG",
    "name:und_x_variant":[
        "Dabga",
        "Kogin Dabga"
    ],
    "wof:name":"Kogin Dabga",
    "wof:placetype":"locality"
},
  "geometry": {"coordinates":[8.09931,11.79674],"type":"Point"}
}