{
  "type": "Feature",
  "properties": {
    "gn:admin1_code":"31.0",
    "gn:admin2_code":"27013.0",
    "gn:asciiname":"Wonigi",
    "gn:country_code":"NG",
    "gn:dem":193,
    "gn:feature_class":"P",
    "gn:feature_code":"PPL",
    "gn:name":"Wonigi",
    "gn:population":0,
    "gn:timezone":"Africa/Lagos",
    "iso:country":"NG",
    "name:und_x_variant":[
        "Wantigi"
    ],
    "wof:name":"Wonigi",
    "wof:placetype":"locality"
},
  "geometry": {"coordinates":[5.56275,9.30687],"type":"Point"}
}