{
  "type": "Feature",
  "properties": {
    "gn:admin1_code":"28.0",
    "gn:admin2_code":"17013.0",
    "gn:asciiname":"Amucha",
    "gn:country_code":"NG",
    "gn:dem":153,
    "gn:feature_class":"P",
    "gn:feature_code":"PPL",
    "gn:name":"Amucha",
    "gn:population":0,
    "gn:timezone":"Africa/Lagos",
    "iso:country":"NG",
    "wof:name":"Amucha",
    "wof:placetype":"locality"
},
  "geometry": {"coordinates":[7.04262,5.73878],"type":"Point"}
}