{
  "type": "Feature",
  "properties": {
    "gn:admin1_code":"27.0",
    "gn:admin2_code":"118.0",
    "gn:admin3_code":"11803",
    "gn:asciiname":"Guwal",
    "gn:country_code":"NG",
    "gn:dem":438,
    "gn:feature_class":"P",
    "gn:feature_code":"PPL",
    "gn:name":"Guwal",
    "gn:population":0,
    "gn:timezone":"Africa/Lagos",
    "iso:country":"NG",
    "name:und_x_variant":[
        "Gwol",
        "Guwal"
    ],
    "wof:name":"Guwal",
    "wof:placetype":"locality"
},
  "geometry": {"coordinates":[11.92543,10.51903],"type":"Point"}
}