{
  "type": "Feature",
  "properties": {
    "gn:admin1_code":"27.0",
    "gn:admin2_code":"108.0",
    "gn:admin3_code":"10806",
    "gn:asciiname":"Tambashe",
    "gn:country_code":"NG",
    "gn:dem":296,
    "gn:feature_class":"P",
    "gn:feature_code":"PPL",
    "gn:name":"Tambashe",
    "gn:population":0,
    "gn:timezone":"Africa/Lagos",
    "iso:country":"NG",
    "wof:name":"Tambashe",
    "wof:placetype":"locality"
},
  "geometry": {"coordinates":[14.09748,11.92856],"type":"Point"}
}