{
  "type": "Feature",
  "properties": {
    "gn:admin1_code":"47.0",
    "gn:asciiname":"Ake-Eze Ukwu",
    "gn:country_code":"NG",
    "gn:dem":47,
    "gn:feature_class":"P",
    "gn:feature_code":"PPL",
    "gn:name":"Ake-Eze Ukwu",
    "gn:population":0,
    "gn:timezone":"Africa/Lagos",
    "iso:country":"NG",
    "wof:name":"Ake-Eze Ukwu",
    "wof:placetype":"locality"
},
  "geometry": {"coordinates":[7.70428,5.91678],"type":"Point"}
}