{
  "type": "Feature",
  "properties": {
    "gn:admin1_code":"57.0",
    "gn:admin2_code":"809.0",
    "gn:admin3_code":"80902",
    "gn:asciiname":"Dosara",
    "gn:country_code":"NG",
    "gn:dem":325,
    "gn:feature_class":"P",
    "gn:feature_code":"PPL",
    "gn:name":"Dosara",
    "gn:population":0,
    "gn:timezone":"Africa/Lagos",
    "iso:country":"NG",
    "wof:name":"Dosara",
    "wof:placetype":"locality"
},
  "geometry": {"coordinates":[6.15859,12.52975],"type":"Point"}
}