{
  "type": "Feature",
  "properties": {
    "gn:admin1_code":"49.0",
    "gn:asciiname":"Kopmuyum",
    "gn:country_code":"NG",
    "gn:dem":200,
    "gn:feature_class":"P",
    "gn:feature_code":"PPL",
    "gn:name":"Kopmuyum",
    "gn:population":0,
    "gn:timezone":"Africa/Lagos",
    "iso:country":"NG",
    "wof:name":"Kopmuyum",
    "wof:placetype":"locality"
},
  "geometry": {"coordinates":[9.30177,8.67235],"type":"Point"}
}