{
  "type": "Feature",
  "properties": {
    "gn:admin1_code":"21.0",
    "gn:admin2_code":"3011.0",
    "gn:asciiname":"Nto Ntia",
    "gn:country_code":"NG",
    "gn:dem":76,
    "gn:feature_class":"P",
    "gn:feature_code":"PPL",
    "gn:name":"Nto Ntia",
    "gn:population":0,
    "gn:timezone":"Africa/Lagos",
    "iso:country":"NG",
    "wof:name":"Nto Ntia",
    "wof:placetype":"locality"
},
  "geometry": {"coordinates":[7.57021,5.03858],"type":"Point"}
}