{
  "type": "Feature",
  "properties": {
    "gn:admin1_code":"41.0",
    "gn:admin2_code":"23009.0",
    "gn:asciiname":"Eluhafon",
    "gn:country_code":"NG",
    "gn:dem":451,
    "gn:feature_class":"P",
    "gn:feature_code":"PPL",
    "gn:name":"Eluhafon",
    "gn:population":0,
    "gn:timezone":"Africa/Lagos",
    "iso:country":"NG",
    "wof:name":"Eluhafon",
    "wof:placetype":"locality"
},
  "geometry": {"coordinates":[6.01667,8.11667],"type":"Point"}
}