{
  "type": "Feature",
  "properties": {
    "gn:admin1_code":"26.0",
    "gn:admin2_code":"7021",
    "gn:asciiname":"Abali",
    "gn:country_code":"NG",
    "gn:dem":164,
    "gn:feature_class":"P",
    "gn:feature_code":"PPL",
    "gn:name":"Abali",
    "gn:population":0,
    "gn:timezone":"Africa/Lagos",
    "iso:country":"NG",
    "name:ara_x_preferred":[
        "\u0622\u0628\u0639\u0644\u064a"
    ],
    "name:azb_x_preferred":[
        "\u0622\u0628\u0639\u0644\u06cc"
    ],
    "name:bul_x_preferred":[
        "\u0410\u0431\u0430\u043b\u0438"
    ],
    "name:fas_x_preferred":[
        "\u0622\u0628\u0639\u0644\u06cc"
    ],
    "name:mlg_x_preferred":[
        "Abali"
    ],
    "name:tur_x_preferred":[
        "Abali"
    ],
    "name:und_x_variant":[
        "Kave"
    ],
    "wof:name":"Abali",
    "wof:placetype":"locality"
},
  "geometry": {"coordinates":[9.49108,7.52528],"type":"Point"}
}