{
  "type": "Feature",
  "properties": {
    "gn:admin1_code":"29.0",
    "gn:asciiname":"Kududufawa",
    "gn:country_code":"NG",
    "gn:dem":406,
    "gn:feature_class":"P",
    "gn:feature_code":"PPL",
    "gn:name":"Kududufawa",
    "gn:population":0,
    "gn:timezone":"Africa/Lagos",
    "iso:country":"NG",
    "wof:name":"Kududufawa",
    "wof:placetype":"locality"
},
  "geometry": {"coordinates":[8.79401,12.35201],"type":"Point"}
}