{
  "type": "Feature",
  "properties": {
    "gn:admin1_code":"24.0",
    "gn:admin2_code":"401.0",
    "gn:admin3_code":"40109",
    "gn:asciiname":"Dan Bauchi",
    "gn:country_code":"NG",
    "gn:dem":625,
    "gn:feature_class":"P",
    "gn:feature_code":"PPL",
    "gn:name":"Dan Bauchi",
    "gn:population":0,
    "gn:timezone":"Africa/Lagos",
    "iso:country":"NG",
    "wof:name":"Dan Bauchi",
    "wof:placetype":"locality"
},
  "geometry": {"coordinates":[7.3834,11.73035],"type":"Point"}
}