{
  "type": "Feature",
  "properties": {
    "gn:admin1_code":"55.0",
    "gn:admin2_code":"16005.0",
    "gn:asciiname":"Unguwar Yaiyaro",
    "gn:country_code":"NG",
    "gn:dem":326,
    "gn:feature_class":"P",
    "gn:feature_code":"PPL",
    "gn:name":"Unguwar Yaiyaro",
    "gn:population":0,
    "gn:timezone":"Africa/Lagos",
    "iso:country":"NG",
    "wof:name":"Unguwar Yaiyaro",
    "wof:placetype":"locality"
},
  "geometry": {"coordinates":[11.36053,10.93192],"type":"Point"}
}