{
  "type": "Feature",
  "properties": {
    "gn:admin1_code":"44.0",
    "gn:admin2_code":"715.0",
    "gn:admin3_code":"71505",
    "gn:asciiname":"Malewa",
    "gn:country_code":"NG",
    "gn:dem":366,
    "gn:feature_class":"P",
    "gn:feature_code":"PPL",
    "gn:name":"Malewa",
    "gn:population":0,
    "gn:timezone":"Africa/Lagos",
    "iso:country":"NG",
    "wof:name":"Malewa",
    "wof:placetype":"locality"
},
  "geometry": {"coordinates":[12.06445,12.01844],"type":"Point"}
}