{
  "type": "Feature",
  "properties": {
    "gn:admin1_code":"53.0",
    "gn:admin2_code":"11006.0",
    "gn:asciiname":"Eke-Moha",
    "gn:country_code":"NG",
    "gn:dem":84,
    "gn:feature_class":"P",
    "gn:feature_code":"PPL",
    "gn:name":"Eke-Moha",
    "gn:population":0,
    "gn:timezone":"Africa/Lagos",
    "iso:country":"NG",
    "wof:name":"Eke-Moha",
    "wof:placetype":"locality"
},
  "geometry": {"coordinates":[8.03446,6.16122],"type":"Point"}
}