{
  "type": "Feature",
  "properties": {
    "gn:admin1_code":"56.0",
    "gn:admin2_code":"26008.0",
    "gn:asciiname":"Akumza Janme",
    "gn:cc2":"NG",
    "gn:country_code":"NG",
    "gn:dem":212,
    "gn:feature_class":"P",
    "gn:feature_code":"PPL",
    "gn:name":"Akumza Janme",
    "gn:population":0,
    "gn:timezone":"Africa/Lagos",
    "iso:country":"NG",
    "name:und_x_variant":[
        "Akunzan",
        "Akumza Janme"
    ],
    "wof:name":"Akumza Janme",
    "wof:placetype":"locality"
},
  "geometry": {"coordinates":[8.58333,8.46667],"type":"Point"}
}