{
  "type": "Feature",
  "properties": {
    "gn:admin1_code":"43.0",
    "gn:asciiname":"Mingel",
    "gn:country_code":"NG",
    "gn:dem":151,
    "gn:feature_class":"P",
    "gn:feature_code":"PPL",
    "gn:name":"Mingel",
    "gn:population":0,
    "gn:timezone":"Africa/Lagos",
    "iso:country":"NG",
    "name:eng_x_preferred":[
        "Mingel"
    ],
    "wof:name":"Mingel",
    "wof:placetype":"locality"
},
  "geometry": {"coordinates":[11.14576,9.30841],"type":"Point"}
}