{
  "type": "Feature",
  "properties": {
    "gn:gn_country":"NG",
    "gn:gn_fcode":"PPL",
    "gn:gn_pop":178677,
    "gn:population":178677,
    "iso:country":"NG",
    "name:eng_x_preferred":[
        "Shaki"
    ],
    "name:epo_x_preferred":[
        "Shaki"
    ],
    "name:ita_x_preferred":[
        "Shaki"
    ],
    "name:nld_x_preferred":[
        "Shaki"
    ],
    "name:pol_x_preferred":[
        "Shaki"
    ],
    "name:ron_x_preferred":[
        "Shaki"
    ],
    "name:rus_x_preferred":[
        "\u0421\u0430\u043a\u0438"
    ],
    "name:unk_x_variant":[
        "Shaki"
    ],
    "name:yor_x_preferred":[
        "\u1e62ak\u00ed"
    ],
    "qs_pg:aaroncc":"NG",
    "qs_pg:gn_country":"NG",
    "qs_pg:gn_fcode":"PPL",
    "qs_pg:gn_pop":178677,
    "qs_pg:name":"Saki",
    "qs_pg:photos_9r":0,
    "qs_pg:photos_sr":0,
    "qs_pg:pop_sr":9,
    "qs_pg:qs_pg_placetype":"locality",
    "wof:name":"Saki",
    "wof:placetype":"locality",
    "wof:population":178677
},
  "geometry": {"coordinates":[3.38333,8.66667],"type":"Point"}
}