{
  "type": "Feature",
  "properties": {
    "gn:admin1_code":"44.0",
    "gn:admin2_code":"702.0",
    "gn:admin3_code":"70206",
    "gn:asciiname":"Gilbosu",
    "gn:country_code":"NG",
    "gn:dem":339,
    "gn:feature_class":"P",
    "gn:feature_code":"PPL",
    "gn:name":"Gilbosu",
    "gn:population":0,
    "gn:timezone":"Africa/Lagos",
    "iso:country":"NG",
    "wof:name":"Gilbosu",
    "wof:placetype":"locality"
},
  "geometry": {"coordinates":[11.31531,12.81564],"type":"Point"}
}