{
  "type": "Feature",
  "properties": {
    "gn:admin1_code":"27.0",
    "gn:admin2_code":"119.0",
    "gn:admin3_code":"11909",
    "gn:asciiname":"Doili",
    "gn:country_code":"NG",
    "gn:dem":304,
    "gn:feature_class":"P",
    "gn:feature_code":"PPL",
    "gn:name":"Doili",
    "gn:population":0,
    "gn:timezone":"Africa/Lagos",
    "iso:country":"NG",
    "name:und_x_variant":[
        "Mbuta",
        "Doili"
    ],
    "wof:name":"Doili",
    "wof:placetype":"locality"
},
  "geometry": {"coordinates":[13.25022,12.04028],"type":"Point"}
}