{
  "type": "Feature",
  "properties": {
    "gn:admin1_code":"31.0",
    "gn:admin2_code":"27006",
    "gn:asciiname":"Biako",
    "gn:country_code":"NG",
    "gn:dem":277,
    "gn:feature_class":"P",
    "gn:feature_code":"PPL",
    "gn:name":"Biako",
    "gn:population":0,
    "gn:timezone":"Africa/Lagos",
    "iso:country":"NG",
    "wof:name":"Biako",
    "wof:placetype":"locality"
},
  "geometry": {"coordinates":[6.5153,9.65174],"type":"Point"}
}