{
  "type": "Feature",
  "properties": {
    "gn:admin1_code":"48.0",
    "gn:admin2_code":"29010.0",
    "gn:asciiname":"Itebukunmi",
    "gn:country_code":"NG",
    "gn:dem":5,
    "gn:feature_class":"P",
    "gn:feature_code":"PPL",
    "gn:name":"Itebukunmi",
    "gn:population":0,
    "gn:timezone":"Africa/Lagos",
    "iso:country":"NG",
    "name:und_x_variant":[
        "Itebukumi",
        "Itebukunmi"
    ],
    "wof:name":"Itebukunmi",
    "wof:placetype":"locality"
},
  "geometry": {"coordinates":[4.59604,6.44463],"type":"Point"}
}