{
  "type": "Feature",
  "properties": {
    "gn:admin1_code":"49.0",
    "gn:admin2_code":"32002.0",
    "gn:asciiname":"Dogon Dinia",
    "gn:country_code":"NG",
    "gn:dem":1203,
    "gn:feature_class":"P",
    "gn:feature_code":"PPL",
    "gn:name":"Dogon Dinia",
    "gn:population":0,
    "gn:timezone":"Africa/Lagos",
    "iso:country":"NG",
    "wof:name":"Dogon Dinia",
    "wof:placetype":"locality"
},
  "geometry": {"coordinates":[8.72805,9.76379],"type":"Point"}
}