{
  "type": "Feature",
  "properties": {
    "gn:admin1_code":"43.0",
    "gn:admin2_code":"35015.0",
    "gn:asciiname":"Ungwar Tipi",
    "gn:country_code":"NG",
    "gn:dem":230,
    "gn:feature_class":"P",
    "gn:feature_code":"PPL",
    "gn:name":"Ungwar Tipi",
    "gn:population":0,
    "gn:timezone":"Africa/Lagos",
    "iso:country":"NG",
    "wof:name":"Ungwar Tipi",
    "wof:placetype":"locality"
},
  "geometry": {"coordinates":[11.43948,8.88648],"type":"Point"}
}