{
  "type": "Feature",
  "properties": {
    "gn:admin1_code":"56.0",
    "gn:admin2_code":"26008.0",
    "gn:asciiname":"Monkwar",
    "gn:cc2":"NG",
    "gn:country_code":"NG",
    "gn:dem":203,
    "gn:feature_class":"P",
    "gn:feature_code":"PPL",
    "gn:name":"Monkwar",
    "gn:population":0,
    "gn:timezone":"Africa/Lagos",
    "iso:country":"NG",
    "name:und_x_variant":[
        "Monkwor",
        "Monkwar"
    ],
    "wof:name":"Monkwar",
    "wof:placetype":"locality"
},
  "geometry": {"coordinates":[8.93333,8.88333],"type":"Point"}
}