{
  "type": "Feature",
  "properties": {
    "gn:admin1_code":"26.0",
    "gn:admin2_code":"7009",
    "gn:asciiname":"Benga",
    "gn:country_code":"NG",
    "gn:dem":130,
    "gn:feature_class":"P",
    "gn:feature_code":"PPL",
    "gn:name":"Benga",
    "gn:population":0,
    "gn:timezone":"Africa/Lagos",
    "iso:country":"NG",
    "name:ceb_x_preferred":[
        "Benga"
    ],
    "name:deu_x_preferred":[
        "Benga"
    ],
    "name:fin_x_preferred":[
        "Benga"
    ],
    "name:fra_x_preferred":[
        "Benga"
    ],
    "name:por_x_preferred":[
        "Benga"
    ],
    "name:ron_x_preferred":[
        "Benga"
    ],
    "name:swe_x_preferred":[
        "Benga"
    ],
    "wof:name":"Benga",
    "wof:placetype":"locality"
},
  "geometry": {"coordinates":[9.37373,7.2514],"type":"Point"}
}