{
  "type": "Feature",
  "properties": {
    "gn:admin1_code":"31.0",
    "gn:admin2_code":"27002.0",
    "gn:asciiname":"Tungan Rigia",
    "gn:country_code":"NG",
    "gn:dem":172,
    "gn:feature_class":"P",
    "gn:feature_code":"PPL",
    "gn:name":"Tungan Rigia",
    "gn:population":0,
    "gn:timezone":"Africa/Lagos",
    "iso:country":"NG",
    "wof:name":"Tungan Rigia",
    "wof:placetype":"locality"
},
  "geometry": {"coordinates":[4.46495,10.57145],"type":"Point"}
}