{
  "type": "Feature",
  "properties": {
    "gn:admin1_code":"28.0",
    "gn:admin2_code":"17020.0",
    "gn:asciiname":"Umuowa",
    "gn:country_code":"NG",
    "gn:dem":174,
    "gn:feature_class":"P",
    "gn:feature_code":"PPL",
    "gn:name":"Umuowa",
    "gn:population":0,
    "gn:timezone":"Africa/Lagos",
    "iso:country":"NG",
    "wof:name":"Umuowa",
    "wof:placetype":"locality"
},
  "geometry": {"coordinates":[7.02847,5.75442],"type":"Point"}
}