{
  "type": "Feature",
  "properties": {
    "gn:admin1_code":"26.0",
    "gn:admin2_code":"7009",
    "gn:asciiname":"Angbeda",
    "gn:country_code":"NG",
    "gn:dem":177,
    "gn:feature_class":"P",
    "gn:feature_code":"PPL",
    "gn:name":"Angbeda",
    "gn:population":0,
    "gn:timezone":"Africa/Lagos",
    "iso:country":"NG",
    "wof:name":"Angbeda",
    "wof:placetype":"locality"
},
  "geometry": {"coordinates":[9.42683,7.42194],"type":"Point"}
}