{
  "type": "Feature",
  "properties": {
    "gn:admin1_code":"36.0",
    "gn:admin2_code":"10004.0",
    "gn:asciiname":"Ison",
    "gn:country_code":"NG",
    "gn:dem":6,
    "gn:feature_class":"P",
    "gn:feature_code":"PPL",
    "gn:name":"Ison",
    "gn:population":0,
    "gn:timezone":"Africa/Lagos",
    "iso:country":"NG",
    "wof:name":"Ison",
    "wof:placetype":"locality"
},
  "geometry": {"coordinates":[5.65888,5.33803],"type":"Point"}
}