{
  "type": "Feature",
  "properties": {
    "gn:admin1_code":"42.0",
    "gn:admin2_code":"30001.0",
    "gn:asciiname":"Atore",
    "gn:cc2":"NG",
    "gn:country_code":"NG",
    "gn:dem":265,
    "gn:feature_class":"P",
    "gn:feature_code":"PPL",
    "gn:name":"Atore",
    "gn:population":0,
    "gn:timezone":"Africa/Lagos",
    "iso:country":"NG",
    "name:und_x_variant":[
        "Atawre",
        "Atore"
    ],
    "wof:name":"Atore",
    "wof:placetype":"locality"
},
  "geometry": {"coordinates":[4.33333,7.53333],"type":"Point"}
}