{
  "type": "Feature",
  "properties": {
    "gn:admin1_code":"49.0",
    "gn:asciiname":"Jawando",
    "gn:country_code":"NG",
    "gn:dem":221,
    "gn:feature_class":"P",
    "gn:feature_code":"PPL",
    "gn:name":"Jawando",
    "gn:population":0,
    "gn:timezone":"Africa/Lagos",
    "iso:country":"NG",
    "wof:name":"Jawando",
    "wof:placetype":"locality"
},
  "geometry": {"coordinates":[10.11168,9.03446],"type":"Point"}
}