{
  "type": "Feature",
  "properties": {
    "gn:admin1_code":"35.0",
    "gn:admin2_code":"2001.0",
    "gn:asciiname":"Bolon",
    "gn:country_code":"NG",
    "gn:dem":202,
    "gn:feature_class":"P",
    "gn:feature_code":"PPL",
    "gn:name":"Bolon",
    "gn:population":0,
    "gn:timezone":"Africa/Lagos",
    "iso:country":"NG",
    "name:ceb_x_preferred":[
        "Bolon"
    ],
    "name:eng_x_preferred":[
        "Bolon"
    ],
    "name:eng_x_variant":[
        "Ngbolung"
    ],
    "wof:name":"Bolon",
    "wof:placetype":"locality"
},
  "geometry": {"coordinates":[11.99502,9.40957],"type":"Point"}
}