{
  "type": "Feature",
  "properties": {
    "gn:admin1_code":"21.0",
    "gn:admin2_code":"3029.0",
    "gn:asciiname":"Ikpa",
    "gn:country_code":"NG",
    "gn:dem":8,
    "gn:feature_class":"P",
    "gn:feature_code":"PPL",
    "gn:name":"Ikpa",
    "gn:population":0,
    "gn:timezone":"Africa/Lagos",
    "iso:country":"NG",
    "wof:name":"Ikpa",
    "wof:placetype":"locality"
},
  "geometry": {"coordinates":[8.03012,5.08368],"type":"Point"}
}