{
  "type": "Feature",
  "properties": {
    "gn:admin1_code":"49.0",
    "gn:admin2_code":"32004.0",
    "gn:asciiname":"Maijuju",
    "gn:country_code":"NG",
    "gn:dem":955,
    "gn:feature_class":"P",
    "gn:feature_code":"PPL",
    "gn:name":"Maijuju",
    "gn:population":0,
    "gn:timezone":"Africa/Lagos",
    "iso:country":"NG",
    "name:und_x_variant":[
        "Maijuja",
        "Maidudu",
        "Maijuju"
    ],
    "wof:name":"Maijuju",
    "wof:placetype":"locality"
},
  "geometry": {"coordinates":[9.1461,9.7542],"type":"Point"}
}