{
  "type": "Feature",
  "properties": {
    "gn:admin1_code":"26.0",
    "gn:admin2_code":"7008",
    "gn:asciiname":"Nyon",
    "gn:country_code":"NG",
    "gn:dem":97,
    "gn:feature_class":"P",
    "gn:feature_code":"PPL",
    "gn:name":"Nyon",
    "gn:population":0,
    "gn:timezone":"Africa/Lagos",
    "iso:country":"NG",
    "name:als_x_preferred":[
        "Nyon"
    ],
    "name:ara_x_preferred":[
        "\u0646\u064a\u0648\u0646"
    ],
    "name:azb_x_preferred":[
        "\u0646\u06cc\u0648\u0646"
    ],
    "name:aze_x_preferred":[
        "Nyon"
    ],
    "name:bel_x_preferred":[
        "\u041d\u044c\u0451\u043d"
    ],
    "name:bre_x_preferred":[
        "Nyon"
    ],
    "name:bul_x_preferred":[
        "\u041d\u0438\u043e\u043d"
    ],
    "name:cat_x_preferred":[
        "Nyon"
    ],
    "name:ceb_x_preferred":[
        "Nyon"
    ],
    "name:ces_x_preferred":[
        "Nyon"
    ],
    "name:dan_x_preferred":[
        "Nyon"
    ],
    "name:deu_x_preferred":[
        "Nyon"
    ],
    "name:ell_x_preferred":[
        "\u039d\u03b9\u03cc\u03bd"
    ],
    "name:epo_x_preferred":[
        "Nyon"
    ],
    "name:eus_x_preferred":[
        "Nyon"
    ],
    "name:fas_x_preferred":[
        "\u0646\u06cc\u0648\u0646"
    ],
    "name:fin_x_preferred":[
        "Nyon"
    ],
    "name:fra_x_preferred":[
        "Nyon"
    ],
    "name:frp_x_preferred":[
        "Nion"
    ],
    "name:gle_x_preferred":[
        "Nyon"
    ],
    "name:glg_x_preferred":[
        "Nyon"
    ],
    "name:heb_x_preferred":[
        "\u05e0\u05d9\u05d5\u05df"
    ],
    "name:hrv_x_preferred":[
        "Nyon"
    ],
    "name:hun_x_preferred":[
        "Nyon"
    ],
    "name:ind_x_preferred":[
        "Nyon"
    ],
    "name:ita_x_preferred":[
        "Nyon"
    ],
    "name:jpn_x_preferred":[
        "\u30cb\u30e8\u30f3"
    ],
    "name:kat_x_preferred":[
        "\u10dc\u10d8\u10dd\u10dc\u10d8"
    ],
    "name:kor_x_preferred":[
        "\ub2c8\uc639"
    ],
    "name:lat_x_preferred":[
        "Noviodunum"
    ],
    "name:lav_x_preferred":[
        "Niona"
    ],
    "name:lit_x_preferred":[
        "Nionas"
    ],
    "name:lmo_x_preferred":[
        "Nyon"
    ],
    "name:ltz_x_preferred":[
        "Nyon"
    ],
    "name:msa_x_preferred":[
        "Nyon"
    ],
    "name:nld_x_preferred":[
        "Nyon"
    ],
    "name:nno_x_preferred":[
        "Nyon"
    ],
    "name:nor_x_preferred":[
        "Nyon"
    ],
    "name:pol_x_preferred":[
        "Nyon"
    ],
    "name:por_x_preferred":[
        "Nyon"
    ],
    "name:roh_x_preferred":[
        "Nyon"
    ],
    "name:ron_x_preferred":[
        "Nyon"
    ],
    "name:rus_x_preferred":[
        "\u041d\u044c\u043e\u043d"
    ],
    "name:scn_x_preferred":[
        "Nyon"
    ],
    "name:sco_x_preferred":[
        "Nyon"
    ],
    "name:spa_x_preferred":[
        "Nyon"
    ],
    "name:sqi_x_preferred":[
        "Nyon"
    ],
    "name:srp_x_preferred":[
        "\u041d\u0438\u043e\u043d"
    ],
    "name:swe_x_preferred":[
        "Nyon"
    ],
    "name:tat_x_preferred":[
        "\u041d\u044c\u043e\u04a3"
    ],
    "name:tha_x_preferred":[
        "\u0e19\u0e35\u0e22\u0e07"
    ],
    "name:tur_x_preferred":[
        "Nyon"
    ],
    "name:ukr_x_preferred":[
        "\u041d\u044c\u0439\u043e\u043d"
    ],
    "name:vie_x_preferred":[
        "Nyon"
    ],
    "name:vol_x_preferred":[
        "Nyon"
    ],
    "name:war_x_preferred":[
        "Nyon"
    ],
    "wof:name":"Nyon",
    "wof:placetype":"locality"
},
  "geometry": {"coordinates":[8.196,7.67519],"type":"Point"}
}