{
  "type": "Feature",
  "properties": {
    "gn:admin1_code":"26.0",
    "gn:admin2_code":"7008",
    "gn:asciiname":"Nyon",
    "gn:country_code":"NG",
    "gn:dem":97,
    "gn:feature_class":"P",
    "gn:feature_code":"PPL",
    "gn:name":"Nyon",
    "gn:population":0,
    "gn:timezone":"Africa/Lagos",
    "iso:country":"NG",
    "wof:name":"Nyon",
    "wof:placetype":"locality"
},
  "geometry": {"coordinates":[8.196,7.67519],"type":"Point"}
}