{
  "type": "Feature",
  "properties": {
    "gn:admin1_code":"51.0",
    "gn:admin2_code":"621.0",
    "gn:admin3_code":"62102",
    "gn:asciiname":"Aoarawa",
    "gn:country_code":"NG",
    "gn:dem":285,
    "gn:feature_class":"P",
    "gn:feature_code":"PPL",
    "gn:name":"Aoarawa",
    "gn:population":0,
    "gn:timezone":"Africa/Lagos",
    "iso:country":"NG",
    "name:und_x_variant":[
        "Adarawa",
        "Aoarawa"
    ],
    "wof:name":"Aoarawa",
    "wof:placetype":"locality"
},
  "geometry": {"coordinates":[5.19069,12.96994],"type":"Point"}
}