{
  "type": "Feature",
  "properties": {
    "gn:admin1_code":"40.0",
    "gn:admin2_code":"505.0",
    "gn:admin3_code":"50502",
    "gn:asciiname":"Tunga Bakki Doma",
    "gn:country_code":"NG",
    "gn:dem":159,
    "gn:feature_class":"P",
    "gn:feature_code":"PPL",
    "gn:name":"Tunga Bakki Doma",
    "gn:population":0,
    "gn:timezone":"Africa/Lagos",
    "iso:country":"NG",
    "wof:name":"Tunga Bakki Doma",
    "wof:placetype":"locality"
},
  "geometry": {"coordinates":[4.14186,11.46465],"type":"Point"}
}