{
  "type": "Feature",
  "properties": {
    "gn:admin1_code":"29.0",
    "gn:admin2_code":"20025.0",
    "gn:admin3_code":"KN0413",
    "gn:asciiname":"Yandatsa",
    "gn:country_code":"NG",
    "gn:dem":487,
    "gn:feature_class":"P",
    "gn:feature_code":"PPL",
    "gn:name":"Yandatsa",
    "gn:population":0,
    "gn:timezone":"Africa/Lagos",
    "iso:country":"NG",
    "wof:name":"Yandatsa",
    "wof:placetype":"locality"
},
  "geometry": {"coordinates":[8.33943,11.62796],"type":"Point"}
}