{
  "type": "Feature",
  "properties": {
    "gn:admin1_code":"27.0",
    "gn:admin2_code":"120.0",
    "gn:admin3_code":"12009",
    "gn:asciiname":"Gaske",
    "gn:country_code":"NG",
    "gn:dem":320,
    "gn:feature_class":"P",
    "gn:feature_code":"PPL",
    "gn:name":"Gaske",
    "gn:population":0,
    "gn:timezone":"Africa/Lagos",
    "iso:country":"NG",
    "wof:name":"Gaske",
    "wof:placetype":"locality"
},
  "geometry": {"coordinates":[12.5679,12.40992],"type":"Point"}
}