{
  "type": "Feature",
  "properties": {
    "gn:admin1_code":"32.0",
    "gn:admin2_code":"31003.0",
    "gn:asciiname":"Orokoroko",
    "gn:country_code":"NG",
    "gn:dem":308,
    "gn:feature_class":"P",
    "gn:feature_code":"PPL",
    "gn:name":"Orokoroko",
    "gn:population":0,
    "gn:timezone":"Africa/Lagos",
    "iso:country":"NG",
    "wof:name":"Orokoroko",
    "wof:placetype":"locality"
},
  "geometry": {"coordinates":[3.91667,8.01667],"type":"Point"}
}