{
  "type": "Feature",
  "properties": {
    "gn:admin1_code":"26.0",
    "gn:admin2_code":"7019.0",
    "gn:asciiname":"Ankpechi",
    "gn:country_code":"NG",
    "gn:dem":184,
    "gn:feature_class":"P",
    "gn:feature_code":"PPL",
    "gn:name":"Ankpechi",
    "gn:population":0,
    "gn:timezone":"Africa/Lagos",
    "iso:country":"NG",
    "wof:name":"Ankpechi",
    "wof:placetype":"locality"
},
  "geometry": {"coordinates":[8.05659,7.28916],"type":"Point"}
}