{
  "type": "Feature",
  "properties": {
    "gn:admin1_code":"53.0",
    "gn:admin2_code":"11002.0",
    "gn:asciiname":"Okpo-Ezi",
    "gn:country_code":"NG",
    "gn:dem":51,
    "gn:feature_class":"P",
    "gn:feature_code":"PPL",
    "gn:name":"Okpo-Ezi",
    "gn:population":0,
    "gn:timezone":"Africa/Lagos",
    "iso:country":"NG",
    "wof:name":"Okpo-Ezi",
    "wof:placetype":"locality"
},
  "geometry": {"coordinates":[7.94183,5.95343],"type":"Point"}
}