{
  "type": "Feature",
  "properties": {
    "gn:admin1_code":"24.0",
    "gn:admin2_code":"430.0",
    "gn:admin3_code":"43004",
    "gn:asciiname":"Kadandani",
    "gn:country_code":"NG",
    "gn:dem":540,
    "gn:feature_class":"P",
    "gn:feature_code":"PPL",
    "gn:name":"Kadandani",
    "gn:population":0,
    "gn:timezone":"Africa/Lagos",
    "iso:country":"NG",
    "wof:name":"Kadandani",
    "wof:placetype":"locality"
},
  "geometry": {"coordinates":[7.67849,12.74526],"type":"Point"}
}