{
  "type": "Feature",
  "properties": {
    "gn:admin1_code":"31.0",
    "gn:admin2_code":"27019",
    "gn:asciiname":"Chimbi",
    "gn:country_code":"NG",
    "gn:dem":487,
    "gn:feature_class":"P",
    "gn:feature_code":"PPL",
    "gn:name":"Chimbi",
    "gn:population":0,
    "gn:timezone":"Africa/Lagos",
    "iso:country":"NG",
    "wof:name":"Chimbi",
    "wof:placetype":"locality"
},
  "geometry": {"coordinates":[6.98361,9.53738],"type":"Point"}
}