{
  "type": "Feature",
  "properties": {
    "gn:admin1_code":"31.0",
    "gn:admin2_code":"27018.0",
    "gn:asciiname":"Gidan-Barde",
    "gn:country_code":"NG",
    "gn:dem":433,
    "gn:feature_class":"P",
    "gn:feature_code":"PPL",
    "gn:name":"Gidan-Barde",
    "gn:population":0,
    "gn:timezone":"Africa/Lagos",
    "iso:country":"NG",
    "name:und_x_variant":[
        "Gidan Barde Chibiani",
        "Gidan-Barde"
    ],
    "wof:name":"Gidan-Barde",
    "wof:placetype":"locality"
},
  "geometry": {"coordinates":[7.02095,9.86847],"type":"Point"}
}