{
  "type": "Feature",
  "properties": {
    "gn:admin1_code":"28.0",
    "gn:admin2_code":"17016.0",
    "gn:asciiname":"Ehume",
    "gn:country_code":"NG",
    "gn:dem":81,
    "gn:feature_class":"P",
    "gn:feature_code":"PPL",
    "gn:name":"Ehume",
    "gn:population":0,
    "gn:timezone":"Africa/Lagos",
    "iso:country":"NG",
    "wof:name":"Ehume",
    "wof:placetype":"locality"
},
  "geometry": {"coordinates":[7.37504,5.54556],"type":"Point"}
}