{
  "type": "Feature",
  "properties": {
    "gn:admin1_code":"43.0",
    "gn:admin2_code":"35008.0",
    "gn:asciiname":"Keffi",
    "gn:country_code":"NG",
    "gn:dem":242,
    "gn:feature_class":"P",
    "gn:feature_code":"PPL",
    "gn:name":"Keffi",
    "gn:population":0,
    "gn:timezone":"Africa/Lagos",
    "iso:country":"NG",
    "name:ara_x_preferred":[
        "\u0643\u064a\u0641\u064a"
    ],
    "name:cat_x_preferred":[
        "Keffi"
    ],
    "name:eng_x_preferred":[
        "Keffi"
    ],
    "name:eng_x_variant":[
        "Yelwa"
    ],
    "name:fra_x_preferred":[
        "Keffi"
    ],
    "name:hau_x_preferred":[
        "Keffi"
    ],
    "name:ita_x_preferred":[
        "Keffi"
    ],
    "name:por_x_preferred":[
        "Quefi"
    ],
    "name:ron_x_preferred":[
        "Keffi"
    ],
    "name:spa_x_preferred":[
        "Keffi"
    ],
    "name:yor_x_preferred":[
        "Keffi"
    ],
    "wof:name":"Keffi",
    "wof:placetype":"locality"
},
  "geometry": {"coordinates":[10.84497,9.20069],"type":"Point"}
}