{
  "type": "Feature",
  "properties": {
    "gn:admin1_code":"43.0",
    "gn:admin2_code":"35008.0",
    "gn:asciiname":"Keffi",
    "gn:country_code":"NG",
    "gn:dem":242,
    "gn:feature_class":"P",
    "gn:feature_code":"PPL",
    "gn:name":"Keffi",
    "gn:population":0,
    "gn:timezone":"Africa/Lagos",
    "iso:country":"NG",
    "name:ara_x_preferred":[
        "\u0643\u064a\u0641\u064a"
    ],
    "name:ben_x_preferred":[
        "\u0995\u09c7\u09ab\u09ab\u09bf"
    ],
    "name:cat_x_preferred":[
        "Keffi"
    ],
    "name:deu_x_preferred":[
        "Keffi"
    ],
    "name:ell_x_preferred":[
        "\u039a\u03ad\u03c6\u03b9"
    ],
    "name:eng_x_preferred":[
        "Keffi"
    ],
    "name:eng_x_variant":[
        "Yelwa"
    ],
    "name:fas_x_preferred":[
        "\u06a9\u0641\u06cc"
    ],
    "name:fra_x_preferred":[
        "Keffi"
    ],
    "name:hau_x_preferred":[
        "Keffi"
    ],
    "name:heb_x_preferred":[
        "\u05e7\u05e4\u05d9"
    ],
    "name:hin_x_preferred":[
        "\u0915\u0947\u092b\u093c\u0940"
    ],
    "name:hun_x_preferred":[
        "Keffi"
    ],
    "name:ind_x_preferred":[
        "Keffi"
    ],
    "name:ita_x_preferred":[
        "Keffi"
    ],
    "name:jpn_x_preferred":[
        "\u30b1\u30d5\u30a3"
    ],
    "name:kor_x_preferred":[
        "\ucf00\ud53c"
    ],
    "name:nld_x_preferred":[
        "Keffi"
    ],
    "name:por_x_preferred":[
        "Quefi"
    ],
    "name:ron_x_preferred":[
        "Keffi"
    ],
    "name:rus_x_preferred":[
        "\u041a\u0435\u0444\u0444\u0438"
    ],
    "name:spa_x_preferred":[
        "Keffi"
    ],
    "name:swe_x_preferred":[
        "Keffi"
    ],
    "name:tur_x_preferred":[
        "Keffi"
    ],
    "name:ukr_x_preferred":[
        "\u041a\u0435\u0444\u0444\u0456"
    ],
    "name:urd_x_preferred":[
        "\u06a9\u06cc\u0641\u06cc"
    ],
    "name:vie_x_preferred":[
        "Keffi"
    ],
    "name:yor_x_preferred":[
        "Keffi"
    ],
    "wof:name":"Keffi",
    "wof:placetype":"locality"
},
  "geometry": {"coordinates":[10.84497,9.20069],"type":"Point"}
}