{
  "type": "Feature",
  "properties": {
    "gn:admin1_code":"30.0",
    "gn:admin2_code":"24012.0",
    "gn:asciiname":"Elelu",
    "gn:country_code":"NG",
    "gn:dem":164,
    "gn:feature_class":"P",
    "gn:feature_code":"PPL",
    "gn:name":"Elelu",
    "gn:population":0,
    "gn:timezone":"Africa/Lagos",
    "iso:country":"NG",
    "wof:name":"Elelu",
    "wof:placetype":"locality"
},
  "geometry": {"coordinates":[4.66667,9.06667],"type":"Point"}
}