{
  "type": "Feature",
  "properties": {
    "gn:admin1_code":"41.0",
    "gn:admin2_code":"23004.0",
    "gn:asciiname":"Zarkama",
    "gn:country_code":"NG",
    "gn:dem":161,
    "gn:feature_class":"P",
    "gn:feature_code":"PPL",
    "gn:name":"Zarkama",
    "gn:population":0,
    "gn:timezone":"Africa/Lagos",
    "iso:country":"NG",
    "name:und_x_variant":[
        "Jerkama",
        "Zarkama"
    ],
    "wof:name":"Zarkama",
    "wof:placetype":"locality"
},
  "geometry": {"coordinates":[7.23333,7.91667],"type":"Point"}
}