{
  "type": "Feature",
  "properties": {
    "gn:admin1_code":"35.0",
    "gn:asciiname":"Kaurame Jauro Bakari",
    "gn:country_code":"NG",
    "gn:dem":229,
    "gn:feature_class":"P",
    "gn:feature_code":"PPL",
    "gn:name":"Kaurame Jauro Bakari",
    "gn:population":0,
    "gn:timezone":"Africa/Lagos",
    "iso:country":"NG",
    "name:eng_x_preferred":[
        "Kaurame Jauro Bakari"
    ],
    "wof:name":"Kaurame Jauro Bakari",
    "wof:placetype":"locality"
},
  "geometry": {"coordinates":[12.01413,9.24481],"type":"Point"}
}