{
  "type": "Feature",
  "properties": {
    "gn:admin1_code":"50.0",
    "gn:admin2_code":"33015.0",
    "gn:asciiname":"Rumunduru",
    "gn:country_code":"NG",
    "gn:dem":22,
    "gn:feature_class":"P",
    "gn:feature_code":"PPL",
    "gn:name":"Rumunduru",
    "gn:population":0,
    "gn:timezone":"Africa/Lagos",
    "iso:country":"NG",
    "name:und_x_variant":[
        "Umunduru",
        "Rumunduru"
    ],
    "wof:name":"Rumunduru",
    "wof:placetype":"locality"
},
  "geometry": {"coordinates":[7.03044,4.87048],"type":"Point"}
}