{
  "type": "Feature",
  "properties": {
    "gn:admin1_code":"36.0",
    "gn:admin2_code":"10014.0",
    "gn:asciiname":"Odozienu",
    "gn:country_code":"NG",
    "gn:dem":130,
    "gn:feature_class":"P",
    "gn:feature_code":"PPL",
    "gn:name":"Odozienu",
    "gn:population":0,
    "gn:timezone":"Africa/Lagos",
    "iso:country":"NG",
    "name:eng_x_preferred":[
        "Odozienu"
    ],
    "wof:name":"Odozienu",
    "wof:placetype":"locality"
},
  "geometry": {"coordinates":[6.64167,6.33013],"type":"Point"}
}