{
  "type": "Feature",
  "properties": {
    "gn:admin1_code":"26.0",
    "gn:admin2_code":"7010.0",
    "gn:asciiname":"Angula",
    "gn:country_code":"NG",
    "gn:dem":90,
    "gn:feature_class":"P",
    "gn:feature_code":"PPL",
    "gn:name":"Angula",
    "gn:population":0,
    "gn:timezone":"Africa/Lagos",
    "iso:country":"NG",
    "name:ceb_x_preferred":[
        "Angula"
    ],
    "name:deu_x_preferred":[
        "Angula"
    ],
    "name:swe_x_preferred":[
        "Angula"
    ],
    "wof:name":"Angula",
    "wof:placetype":"locality"
},
  "geometry": {"coordinates":[8.61828,7.12983],"type":"Point"}
}