{
  "type": "Feature",
  "properties": {
    "gn:admin1_code":"49.0",
    "gn:admin2_code":"32006.0",
    "gn:asciiname":"Turu",
    "gn:country_code":"NG",
    "gn:dem":1288,
    "gn:feature_class":"P",
    "gn:feature_code":"PPL",
    "gn:name":"Turu",
    "gn:population":0,
    "gn:timezone":"Africa/Lagos",
    "iso:country":"NG",
    "wof:name":"Turu",
    "wof:placetype":"locality"
},
  "geometry": {"coordinates":[8.76126,9.67913],"type":"Point"}
}