{
  "type": "Feature",
  "properties": {
    "gn:admin1_code":"36.0",
    "gn:admin2_code":"10023.0",
    "gn:asciiname":"Deli",
    "gn:country_code":"NG",
    "gn:dem":7,
    "gn:feature_class":"P",
    "gn:feature_code":"PPL",
    "gn:name":"Deli",
    "gn:population":0,
    "gn:timezone":"Africa/Lagos",
    "iso:country":"NG",
    "name:ceb_x_preferred":[
        "Deli"
    ],
    "name:ces_x_preferred":[
        "Deli"
    ],
    "name:deu_x_preferred":[
        "Deli"
    ],
    "name:fin_x_preferred":[
        "Deli"
    ],
    "name:fra_x_preferred":[
        "Deli"
    ],
    "name:hun_x_preferred":[
        "Deli"
    ],
    "name:kur_x_preferred":[
        "D\u00een"
    ],
    "name:nld_x_preferred":[
        "Deli"
    ],
    "name:swe_x_preferred":[
        "Deli"
    ],
    "name:tur_x_preferred":[
        "Deli"
    ],
    "name:und_x_variant":[
        "Deghele",
        "Deli"
    ],
    "name:zho_x_preferred":[
        "Deli"
    ],
    "wof:name":"Deli",
    "wof:placetype":"locality"
},
  "geometry": {"coordinates":[5.15228,5.74021],"type":"Point"}
}