{
  "type": "Feature",
  "properties": {
    "gn:admin1_code":"29.0",
    "gn:admin2_code":"20041.0",
    "gn:admin3_code":"KN2208",
    "gn:asciiname":"Rimin",
    "gn:country_code":"NG",
    "gn:dem":543,
    "gn:feature_class":"P",
    "gn:feature_code":"PPL",
    "gn:name":"Rimin",
    "gn:population":0,
    "gn:timezone":"Africa/Lagos",
    "iso:country":"NG",
    "wof:name":"Rimin",
    "wof:placetype":"locality"
},
  "geometry": {"coordinates":[7.96218,11.738],"type":"Point"}
}