{
  "type": "Feature",
  "properties": {
    "gn:admin1_code":"28.0",
    "gn:admin2_code":"17004.0",
    "gn:asciiname":"Ezeborgu",
    "gn:country_code":"NG",
    "gn:dem":149,
    "gn:feature_class":"P",
    "gn:feature_code":"PPL",
    "gn:name":"Ezeborgu",
    "gn:population":0,
    "gn:timezone":"Africa/Lagos",
    "iso:country":"NG",
    "wof:name":"Ezeborgu",
    "wof:placetype":"locality"
},
  "geometry": {"coordinates":[7.31061,5.49072],"type":"Point"}
}