{
  "type": "Feature",
  "properties": {
    "gn:admin1_code":"55.0",
    "gn:admin2_code":"16009.0",
    "gn:asciiname":"Sabon Gari",
    "gn:country_code":"NG",
    "gn:dem":280,
    "gn:feature_class":"P",
    "gn:feature_code":"PPL",
    "gn:name":"Sabon Gari",
    "gn:population":0,
    "gn:timezone":"Africa/Lagos",
    "iso:country":"NG",
    "name:pol_x_preferred":[
        "Sabon Gari"
    ],
    "name:und_x_variant":[
        "Burruo Sabon Gari"
    ],
    "wof:name":"Sabon Gari",
    "wof:placetype":"locality"
},
  "geometry": {"coordinates":[11.23629,11.1024],"type":"Point"}
}