{
  "type": "Feature",
  "properties": {
    "gn:admin1_code":"35.0",
    "gn:admin2_code":"2018.0",
    "gn:asciiname":"Bindi",
    "gn:country_code":"NG",
    "gn:dem":714,
    "gn:feature_class":"P",
    "gn:feature_code":"PPL",
    "gn:name":"Bindi",
    "gn:population":0,
    "gn:timezone":"Africa/Lagos",
    "iso:country":"NG",
    "name:ceb_x_preferred":[
        "Bindi"
    ],
    "name:deu_x_preferred":[
        "Bindi"
    ],
    "name:fra_x_preferred":[
        "Bindi"
    ],
    "name:ita_x_preferred":[
        "Bindi"
    ],
    "name:nld_x_preferred":[
        "Bindi"
    ],
    "name:por_x_preferred":[
        "Bindi"
    ],
    "name:slv_x_preferred":[
        "Bindi"
    ],
    "name:swe_x_preferred":[
        "Bindi"
    ],
    "wof:name":"Bindi",
    "wof:placetype":"locality"
},
  "geometry": {"coordinates":[12.33196,10.0353],"type":"Point"}
}