{
  "type": "Feature",
  "properties": {
    "gn:admin1_code":"47.0",
    "gn:admin2_code":"14006.0",
    "gn:asciiname":"Abonuzu",
    "gn:country_code":"NG",
    "gn:dem":264,
    "gn:feature_class":"P",
    "gn:feature_code":"PPL",
    "gn:name":"Abonuzu",
    "gn:population":0,
    "gn:timezone":"Africa/Lagos",
    "iso:country":"NG",
    "wof:name":"Abonuzu",
    "wof:placetype":"locality"
},
  "geometry": {"coordinates":[7.33786,6.38714],"type":"Point"}
}