{
  "type": "Feature",
  "properties": {
    "gn:admin1_code":"39.0",
    "gn:admin2_code":"18025.0",
    "gn:admin3_code":"JI1909",
    "gn:asciiname":"Maje",
    "gn:country_code":"NG",
    "gn:dem":384,
    "gn:feature_class":"P",
    "gn:feature_code":"PPL",
    "gn:name":"Maje",
    "gn:population":0,
    "gn:timezone":"Africa/Lagos",
    "iso:country":"NG",
    "wof:name":"Maje",
    "wof:placetype":"locality"
},
  "geometry": {"coordinates":[9.55,11.95],"type":"Point"}
}