{
  "type": "Feature",
  "properties": {
    "gn:admin1_code":"40.0",
    "gn:admin2_code":"507.0",
    "gn:admin3_code":"50703",
    "gn:asciiname":"Sabon Rijia",
    "gn:country_code":"NG",
    "gn:dem":257,
    "gn:feature_class":"P",
    "gn:feature_code":"PPL",
    "gn:name":"Sabon Rijia",
    "gn:population":0,
    "gn:timezone":"Africa/Lagos",
    "iso:country":"NG",
    "wof:name":"Sabon Rijia",
    "wof:placetype":"locality"
},
  "geometry": {"coordinates":[3.72372,12.1927],"type":"Point"}
}