{
  "type": "Feature",
  "properties": {
    "gn:admin1_code":"50.0",
    "gn:admin2_code":"33005.0",
    "gn:asciiname":"Darile",
    "gn:country_code":"NG",
    "gn:dem":-9999,
    "gn:feature_class":"P",
    "gn:feature_code":"PPL",
    "gn:name":"Darile",
    "gn:population":0,
    "gn:timezone":"Africa/Lagos",
    "iso:country":"NG",
    "wof:name":"Darile",
    "wof:placetype":"locality"
},
  "geometry": {"coordinates":[7.44375,4.43828],"type":"Point"}
}