{
  "type": "Feature",
  "properties": {
    "gn:admin1_code":"35.0",
    "gn:admin2_code":"2002.0",
    "gn:asciiname":"Wuro Sambo",
    "gn:country_code":"NG",
    "gn:dem":257,
    "gn:feature_class":"P",
    "gn:feature_code":"PPL",
    "gn:name":"Wuro Sambo",
    "gn:population":0,
    "gn:timezone":"Africa/Lagos",
    "iso:country":"NG",
    "name:eng_x_preferred":[
        "Wuro Sambo"
    ],
    "wof:name":"Wuro Sambo",
    "wof:placetype":"locality"
},
  "geometry": {"coordinates":[12.35425,9.12382],"type":"Point"}
}