{
  "type": "Feature",
  "properties": {
    "gn:admin1_code":"5.0",
    "gn:admin2_code":"25004.0",
    "gn:asciiname":"Okun-Ibese",
    "gn:country_code":"NG",
    "gn:dem":11,
    "gn:feature_class":"P",
    "gn:feature_code":"PPL",
    "gn:name":"Okun-Ibese",
    "gn:population":0,
    "gn:timezone":"Africa/Lagos",
    "iso:country":"NG",
    "wof:name":"Okun-Ibese",
    "wof:placetype":"locality"
},
  "geometry": {"coordinates":[3.26083,6.40611],"type":"Point"}
}