{
  "type": "Feature",
  "properties": {
    "gn:admin1_code":"50.0",
    "gn:admin2_code":"33010.0",
    "gn:asciiname":"Mgbuhie",
    "gn:country_code":"NG",
    "gn:dem":15,
    "gn:feature_class":"P",
    "gn:feature_code":"PPL",
    "gn:name":"Mgbuhie",
    "gn:population":0,
    "gn:timezone":"Africa/Lagos",
    "iso:country":"NG",
    "name:und_x_variant":[
        "Ngbuhie"
    ],
    "wof:name":"Mgbuhie",
    "wof:placetype":"locality"
},
  "geometry": {"coordinates":[6.68793,4.95152],"type":"Point"}
}