{
  "type": "Feature",
  "properties": {
    "gn:admin1_code":"50.0",
    "gn:admin2_code":"33016.0",
    "gn:asciiname":"Umuajie",
    "gn:country_code":"NG",
    "gn:dem":21,
    "gn:feature_class":"P",
    "gn:feature_code":"PPL",
    "gn:name":"Umuajie",
    "gn:population":0,
    "gn:timezone":"Africa/Lagos",
    "iso:country":"NG",
    "wof:name":"Umuajie",
    "wof:placetype":"locality"
},
  "geometry": {"coordinates":[6.60942,5.53714],"type":"Point"}
}