{
  "type": "Feature",
  "properties": {
    "gn:admin1_code":"24.0",
    "gn:admin2_code":"407.0",
    "gn:admin3_code":"40702",
    "gn:asciiname":"Mai Kandamba",
    "gn:country_code":"NG",
    "gn:dem":668,
    "gn:feature_class":"P",
    "gn:feature_code":"PPL",
    "gn:name":"Mai Kandamba",
    "gn:population":0,
    "gn:timezone":"Africa/Lagos",
    "iso:country":"NG",
    "wof:name":"Mai Kandamba",
    "wof:placetype":"locality"
},
  "geometry": {"coordinates":[7.11534,11.52183],"type":"Point"}
}