{
  "type": "Feature",
  "properties": {
    "gn:admin1_code":"49.0",
    "gn:admin2_code":"32012.0",
    "gn:asciiname":"Gerkawa",
    "gn:country_code":"NG",
    "gn:dem":223,
    "gn:feature_class":"P",
    "gn:feature_code":"PPL",
    "gn:name":"Gerkawa",
    "gn:population":0,
    "gn:timezone":"Africa/Lagos",
    "iso:country":"NG",
    "name:und_x_variant":[
        "Garkawa"
    ],
    "wof:name":"Gerkawa",
    "wof:placetype":"locality"
},
  "geometry": {"coordinates":[9.80361,8.94177],"type":"Point"}
}