{
  "type": "Feature",
  "properties": {
    "gn:admin1_code":"26.0",
    "gn:admin2_code":"7009",
    "gn:asciiname":"Wada",
    "gn:country_code":"NG",
    "gn:dem":120,
    "gn:feature_class":"P",
    "gn:feature_code":"PPL",
    "gn:name":"Wada",
    "gn:population":0,
    "gn:timezone":"Africa/Lagos",
    "iso:country":"NG",
    "name:ceb_x_preferred":[
        "Wada"
    ],
    "name:deu_x_preferred":[
        "Wada"
    ],
    "name:fra_x_preferred":[
        "Wada"
    ],
    "name:mar_x_preferred":[
        "\u0935\u093e\u0921\u093e"
    ],
    "name:pol_x_preferred":[
        "Wada"
    ],
    "name:rus_x_preferred":[
        "\u0412\u0430\u0434\u0430"
    ],
    "name:swe_x_preferred":[
        "Wada"
    ],
    "wof:name":"Wada",
    "wof:placetype":"locality"
},
  "geometry": {"coordinates":[9.34251,7.37291],"type":"Point"}
}