{
  "type": "Feature",
  "properties": {
    "gn:admin1_code":"23.0",
    "gn:admin2_code":"19004.0",
    "gn:admin3_code":"KD0407",
    "gn:asciiname":"Shigagi",
    "gn:country_code":"NG",
    "gn:dem":604,
    "gn:feature_class":"P",
    "gn:feature_code":"PPL",
    "gn:name":"Shigagi",
    "gn:population":0,
    "gn:timezone":"Africa/Lagos",
    "iso:country":"NG",
    "name:und_x_variant":[
        "Shikagi",
        "Shigagi"
    ],
    "wof:name":"Shigagi",
    "wof:placetype":"locality"
},
  "geometry": {"coordinates":[7.54673,10.60418],"type":"Point"}
}