{
  "type": "Feature",
  "properties": {
    "gn:admin1_code":"57.0",
    "gn:admin2_code":"806.0",
    "gn:admin3_code":"80606",
    "gn:asciiname":"Dumka",
    "gn:cc2":"NG",
    "gn:country_code":"NG",
    "gn:dem":238,
    "gn:feature_class":"P",
    "gn:feature_code":"PPL",
    "gn:name":"Dumka",
    "gn:population":0,
    "gn:timezone":"Africa/Lagos",
    "iso:country":"NG",
    "name:und_x_variant":[
        "Dunka",
        "Dumka"
    ],
    "wof:name":"Dumka",
    "wof:placetype":"locality"
},
  "geometry": {"coordinates":[4.86667,12.15],"type":"Point"}
}