{
  "type": "Feature",
  "properties": {
    "gn:admin1_code":"57.0",
    "gn:admin2_code":"806.0",
    "gn:admin3_code":"80606",
    "gn:asciiname":"Dumka",
    "gn:cc2":"NG",
    "gn:country_code":"NG",
    "gn:dem":238,
    "gn:feature_class":"P",
    "gn:feature_code":"PPL",
    "gn:name":"Dumka",
    "gn:population":0,
    "gn:timezone":"Africa/Lagos",
    "iso:country":"NG",
    "name:ara_x_preferred":[
        "\u062f\u0648\u0645\u0643\u0627"
    ],
    "name:bih_x_preferred":[
        "\u0926\u0941\u092e\u0915\u093e"
    ],
    "name:bpy_x_preferred":[
        "\u09a6\u09c1\u09ae\u0995\u09be"
    ],
    "name:ceb_x_preferred":[
        "Dumka"
    ],
    "name:fra_x_preferred":[
        "Dumka"
    ],
    "name:hin_x_preferred":[
        "\u0926\u0941\u092e\u0915\u093e"
    ],
    "name:ita_x_preferred":[
        "Dumka"
    ],
    "name:mai_x_preferred":[
        "\u0926\u0941\u092e\u0915\u093e"
    ],
    "name:mar_x_preferred":[
        "\u0921\u0941\u092e\u0915\u093e"
    ],
    "name:mlg_x_preferred":[
        "Dumka"
    ],
    "name:msa_x_preferred":[
        "Dumka"
    ],
    "name:nep_x_preferred":[
        "\u0926\u0941\u092e\u0915\u093e"
    ],
    "name:new_x_preferred":[
        "\u0926\u0941\u092e\u094d\u0915\u093e"
    ],
    "name:nor_x_preferred":[
        "Dumka"
    ],
    "name:ori_x_preferred":[
        "\u0b21\u0b41\u0b2e\u0b15\u0b3e"
    ],
    "name:pnb_x_preferred":[
        "\u062f\u0645\u06a9\u0627"
    ],
    "name:san_x_preferred":[
        "\u0926\u0941\u092e\u0915\u093e"
    ],
    "name:sat_x_preferred":[
        "\u1c6b\u1c69\u1c62\u1c60\u1c5f"
    ],
    "name:spa_x_preferred":[
        "Dumka"
    ],
    "name:swe_x_preferred":[
        "Dumka"
    ],
    "name:und_x_variant":[
        "Dunka"
    ],
    "name:urd_x_preferred":[
        "\u062f\u0645\u06a9\u0627"
    ],
    "name:vie_x_preferred":[
        "Dumka"
    ],
    "name:zho_x_preferred":[
        "\u675c\u59c6\u5361"
    ],
    "wof:name":"Dumka",
    "wof:placetype":"locality"
},
  "geometry": {"coordinates":[4.86667,12.15],"type":"Point"}
}