{
  "type": "Feature",
  "properties": {
    "gn:admin1_code":"50.0",
    "gn:admin2_code":"33008.0",
    "gn:asciiname":"Old Bakana",
    "gn:country_code":"NG",
    "gn:dem":8,
    "gn:feature_class":"P",
    "gn:feature_code":"PPL",
    "gn:name":"Old Bakana",
    "gn:population":0,
    "gn:timezone":"Africa/Lagos",
    "iso:country":"NG",
    "name:und_x_variant":[
        "Bush Bakana",
        "Old Bakana"
    ],
    "wof:name":"Old Bakana",
    "wof:placetype":"locality"
},
  "geometry": {"coordinates":[6.96373,4.74658],"type":"Point"}
}