{
  "type": "Feature",
  "properties": {
    "gn:admin1_code":"27.0",
    "gn:asciiname":"Maigana",
    "gn:country_code":"NG",
    "gn:dem":422,
    "gn:feature_class":"P",
    "gn:feature_code":"PPL",
    "gn:name":"Maigana",
    "gn:population":0,
    "gn:timezone":"Africa/Lagos",
    "iso:country":"NG",
    "wof:name":"Maigana",
    "wof:placetype":"locality"
},
  "geometry": {"coordinates":[13.3376,10.79586],"type":"Point"}
}