{
  "type": "Feature",
  "properties": {
    "gn:admin1_code":"52.0",
    "gn:admin2_code":"6001.0",
    "gn:asciiname":"Agrisaba",
    "gn:country_code":"NG",
    "gn:dem":8,
    "gn:feature_class":"P",
    "gn:feature_code":"PPL",
    "gn:name":"Agrisaba",
    "gn:population":0,
    "gn:timezone":"Africa/Lagos",
    "iso:country":"NG",
    "wof:name":"Agrisaba",
    "wof:placetype":"locality"
},
  "geometry": {"coordinates":[6.42066,4.59425],"type":"Point"}
}