{
  "type": "Feature",
  "properties": {
    "gn:admin1_code":"24.0",
    "gn:admin2_code":"414.0",
    "gn:admin3_code":"41404",
    "gn:asciiname":"Dukke",
    "gn:country_code":"NG",
    "gn:dem":653,
    "gn:feature_class":"P",
    "gn:feature_code":"PPL",
    "gn:name":"Dukke",
    "gn:population":0,
    "gn:timezone":"Africa/Lagos",
    "iso:country":"NG",
    "wof:name":"Dukke",
    "wof:placetype":"locality"
},
  "geometry": {"coordinates":[7.25066,11.57469],"type":"Point"}
}