{
  "type": "Feature",
  "properties": {
    "gn:admin1_code":"46.0",
    "gn:admin2_code":"5008.0",
    "gn:admin3_code":"BA0801",
    "gn:asciiname":"Kafin Magaji",
    "gn:country_code":"NG",
    "gn:dem":483,
    "gn:feature_class":"P",
    "gn:feature_code":"PPL",
    "gn:name":"Kafin Magaji",
    "gn:population":0,
    "gn:timezone":"Africa/Lagos",
    "iso:country":"NG",
    "name:eng_x_preferred":[
        "Kafin Magaji"
    ],
    "wof:name":"Kafin Magaji",
    "wof:placetype":"locality"
},
  "geometry": {"coordinates":[10.25787,10.83486],"type":"Point"}
}