{
  "type": "Feature",
  "properties": {
    "gn:admin1_code":"43.0",
    "gn:admin2_code":"35016.0",
    "gn:asciiname":"Pwana",
    "gn:country_code":"NG",
    "gn:dem":544,
    "gn:feature_class":"P",
    "gn:feature_code":"PPL",
    "gn:name":"Pwana",
    "gn:population":0,
    "gn:timezone":"Africa/Lagos",
    "iso:country":"NG",
    "name:eng_x_preferred":[
        "Pwana"
    ],
    "wof:name":"Pwana",
    "wof:placetype":"locality"
},
  "geometry": {"coordinates":[11.70627,9.0103],"type":"Point"}
}