{
  "type": "Feature",
  "properties": {
    "gn:admin1_code":"36.0",
    "gn:admin2_code":"10013.0",
    "gn:asciiname":"Egbeleku",
    "gn:country_code":"NG",
    "gn:dem":11,
    "gn:feature_class":"P",
    "gn:feature_code":"PPL",
    "gn:name":"Egbeleku",
    "gn:population":0,
    "gn:timezone":"Africa/Lagos",
    "iso:country":"NG",
    "name:eng_x_preferred":[
        "Egbeleku"
    ],
    "wof:name":"Egbeleku",
    "wof:placetype":"locality"
},
  "geometry": {"coordinates":[5.79163,5.6933],"type":"Point"}
}