{
  "type": "Feature",
  "properties": {
    "gn:admin1_code":"47.0",
    "gn:admin2_code":"14012.0",
    "gn:asciiname":"Umuatugbuoma",
    "gn:country_code":"NG",
    "gn:dem":214,
    "gn:feature_class":"P",
    "gn:feature_code":"PPL",
    "gn:name":"Umuatugbuoma",
    "gn:population":0,
    "gn:timezone":"Africa/Lagos",
    "iso:country":"NG",
    "wof:name":"Umuatugbuoma",
    "wof:placetype":"locality"
},
  "geometry": {"coordinates":[7.47829,6.34618],"type":"Point"}
}