{
  "type": "Feature",
  "properties": {
    "gn:admin1_code":"26.0",
    "gn:admin2_code":"7012",
    "gn:asciiname":"Cheakoso",
    "gn:country_code":"NG",
    "gn:dem":151,
    "gn:feature_class":"P",
    "gn:feature_code":"PPL",
    "gn:name":"Cheakoso",
    "gn:population":0,
    "gn:timezone":"Africa/Lagos",
    "iso:country":"NG",
    "wof:name":"Cheakoso",
    "wof:placetype":"locality"
},
  "geometry": {"coordinates":[9.39699,7.54757],"type":"Point"}
}