{
  "type": "Feature",
  "properties": {
    "gn:admin1_code":"51.0",
    "gn:admin2_code":"611.0",
    "gn:admin3_code":"61109",
    "gn:asciiname":"Tunga-Majakai",
    "gn:country_code":"NG",
    "gn:dem":283,
    "gn:feature_class":"P",
    "gn:feature_code":"PPL",
    "gn:name":"Tunga-Majakai",
    "gn:population":0,
    "gn:timezone":"Africa/Lagos",
    "iso:country":"NG",
    "wof:name":"Tunga-Majakai",
    "wof:placetype":"locality"
},
  "geometry": {"coordinates":[5.25956,13.312],"type":"Point"}
}