{
  "type": "Feature",
  "properties": {
    "gn:admin1_code":"57.0",
    "gn:admin2_code":"813.0",
    "gn:admin3_code":"81311",
    "gn:asciiname":"Tudun Mairaira",
    "gn:country_code":"NG",
    "gn:dem":466,
    "gn:feature_class":"P",
    "gn:feature_code":"PPL",
    "gn:name":"Tudun Mairaira",
    "gn:population":0,
    "gn:timezone":"Africa/Lagos",
    "iso:country":"NG",
    "wof:name":"Tudun Mairaira",
    "wof:placetype":"locality"
},
  "geometry": {"coordinates":[7.09144,12.08506],"type":"Point"}
}