{
  "type": "Feature",
  "properties": {
    "gn:admin1_code":"28.0",
    "gn:admin2_code":"17019.0",
    "gn:asciiname":"Ogeh",
    "gn:country_code":"NG",
    "gn:dem":134,
    "gn:feature_class":"P",
    "gn:feature_code":"PPL",
    "gn:name":"Ogeh",
    "gn:population":0,
    "gn:timezone":"Africa/Lagos",
    "iso:country":"NG",
    "wof:name":"Ogeh",
    "wof:placetype":"locality"
},
  "geometry": {"coordinates":[7.35192,5.79284],"type":"Point"}
}