{
  "type": "Feature",
  "properties": {
    "gn:admin1_code":"24.0",
    "gn:admin2_code":"406.0",
    "gn:admin3_code":"40607",
    "gn:asciiname":"Kukiya",
    "gn:country_code":"NG",
    "gn:dem":539,
    "gn:feature_class":"P",
    "gn:feature_code":"PPL",
    "gn:name":"Kukiya",
    "gn:population":0,
    "gn:timezone":"Africa/Lagos",
    "iso:country":"NG",
    "name:azb_x_preferred":[
        "\u06a9\u0648\u06a9\u06cc\u0627"
    ],
    "name:aze_x_preferred":[
        "Kukiya"
    ],
    "name:ceb_x_preferred":[
        "K\u016bk\u012by\u0101"
    ],
    "name:fas_x_preferred":[
        "\u06a9\u0648\u06a9\u06cc\u0627"
    ],
    "name:msa_x_preferred":[
        "Kukiya"
    ],
    "name:pol_x_preferred":[
        "Kukija"
    ],
    "name:swe_x_preferred":[
        "K\u016bk\u012by\u0101"
    ],
    "name:ukr_x_preferred":[
        "\u041a\u0443\u043a\u0456\u044f"
    ],
    "wof:name":"Kukiya",
    "wof:placetype":"locality"
},
  "geometry": {"coordinates":[7.67521,12.55744],"type":"Point"}
}