{
  "type": "Feature",
  "properties": {
    "gn:admin1_code":"24.0",
    "gn:admin2_code":"406.0",
    "gn:admin3_code":"40607",
    "gn:asciiname":"Kukiya",
    "gn:country_code":"NG",
    "gn:dem":539,
    "gn:feature_class":"P",
    "gn:feature_code":"PPL",
    "gn:name":"Kukiya",
    "gn:population":0,
    "gn:timezone":"Africa/Lagos",
    "iso:country":"NG",
    "wof:name":"Kukiya",
    "wof:placetype":"locality"
},
  "geometry": {"coordinates":[7.67521,12.55744],"type":"Point"}
}