{
  "type": "Feature",
  "properties": {
    "gn:admin1_code":"5.0",
    "gn:admin2_code":"25006.0",
    "gn:asciiname":"Mosafejo",
    "gn:cc2":"NG",
    "gn:country_code":"NG",
    "gn:dem":7,
    "gn:feature_class":"P",
    "gn:feature_code":"PPL",
    "gn:name":"Mosafejo",
    "gn:population":0,
    "gn:timezone":"Africa/Lagos",
    "iso:country":"NG",
    "name:und_x_variant":[
        "Mosafejaw",
        "Mosafejo"
    ],
    "wof:name":"Mosafejo",
    "wof:placetype":"locality"
},
  "geometry": {"coordinates":[2.95,6.43333],"type":"Point"}
}