{
  "type": "Feature",
  "properties": {
    "gn:admin1_code":"36.0",
    "gn:asciiname":"Beniboye",
    "gn:country_code":"NG",
    "gn:dem":7,
    "gn:feature_class":"P",
    "gn:feature_code":"PPL",
    "gn:name":"Beniboye",
    "gn:population":0,
    "gn:timezone":"Africa/Lagos",
    "iso:country":"NG",
    "name:eng_x_preferred":[
        "Beniboye"
    ],
    "wof:name":"Beniboye",
    "wof:placetype":"locality"
},
  "geometry": {"coordinates":[5.34158,5.2757],"type":"Point"}
}