{
  "type": "Feature",
  "properties": {
    "gn:admin1_code":"27.0",
    "gn:admin2_code":"105.0",
    "gn:admin3_code":"10501",
    "gn:asciiname":"Wula Wula",
    "gn:country_code":"NG",
    "gn:dem":509,
    "gn:feature_class":"P",
    "gn:feature_code":"PPL",
    "gn:name":"Wula Wula",
    "gn:population":0,
    "gn:timezone":"Africa/Lagos",
    "iso:country":"NG",
    "wof:name":"Wula Wula",
    "wof:placetype":"locality"
},
  "geometry": {"coordinates":[12.25653,10.95695],"type":"Point"}
}