{
  "type": "Feature",
  "properties": {
    "gn:admin1_code":"50.0",
    "gn:admin2_code":"33014.0",
    "gn:asciiname":"Wiikwe Luebon",
    "gn:country_code":"NG",
    "gn:dem":31,
    "gn:feature_class":"P",
    "gn:feature_code":"PPL",
    "gn:name":"Wiikwe Luebon",
    "gn:population":0,
    "gn:timezone":"Africa/Lagos",
    "iso:country":"NG",
    "name:und_x_variant":[
        "Wiikwe Luekon",
        "Wiikwe Luebon"
    ],
    "wof:name":"Wiikwe Luebon",
    "wof:placetype":"locality"
},
  "geometry": {"coordinates":[7.41356,4.77713],"type":"Point"}
}