{
  "type": "Feature",
  "properties": {
    "gn:admin1_code":"5.0",
    "gn:admin2_code":"25012.0",
    "gn:asciiname":"Ofin",
    "gn:country_code":"NG",
    "gn:dem":3,
    "gn:feature_class":"P",
    "gn:feature_code":"PPL",
    "gn:name":"Ofin",
    "gn:population":0,
    "gn:timezone":"Africa/Lagos",
    "iso:country":"NG",
    "name:und_x_variant":[
        "Awfin",
        "Ofin"
    ],
    "wof:name":"Ofin",
    "wof:placetype":"locality"
},
  "geometry": {"coordinates":[3.49962,6.5398],"type":"Point"}
}