{
  "type": "Feature",
  "properties": {
    "gn:admin1_code":"36.0",
    "gn:admin2_code":"10005.0",
    "gn:asciiname":"Urhodo",
    "gn:country_code":"NG",
    "gn:dem":12,
    "gn:feature_class":"P",
    "gn:feature_code":"PPL",
    "gn:name":"Urhodo",
    "gn:population":0,
    "gn:timezone":"Africa/Lagos",
    "iso:country":"NG",
    "name:eng_x_preferred":[
        "Urhodo"
    ],
    "wof:name":"Urhodo",
    "wof:placetype":"locality"
},
  "geometry": {"coordinates":[5.89709,5.69932],"type":"Point"}
}