{
  "type": "Feature",
  "properties": {
    "gn:admin1_code":"53.0",
    "gn:admin2_code":"11008.0",
    "gn:asciiname":"Obogu",
    "gn:country_code":"NG",
    "gn:dem":105,
    "gn:feature_class":"P",
    "gn:feature_code":"PPL",
    "gn:name":"Obogu",
    "gn:population":0,
    "gn:timezone":"Africa/Lagos",
    "iso:country":"NG",
    "name:aka_x_preferred":[
        "Obogu"
    ],
    "name:twi_x_preferred":[
        "Obogu"
    ],
    "name:und_x_variant":[
        "Obego",
        "Obeagu",
        "Obogu"
    ],
    "wof:name":"Obogu",
    "wof:placetype":"locality"
},
  "geometry": {"coordinates":[7.72532,6.59683],"type":"Point"}
}