{
  "type": "Feature",
  "properties": {
    "gn:admin1_code":"50.0",
    "gn:admin2_code":"33001.0",
    "gn:asciiname":"Egorbiri",
    "gn:country_code":"NG",
    "gn:dem":18,
    "gn:feature_class":"P",
    "gn:feature_code":"PPL",
    "gn:name":"Egorbiri",
    "gn:population":0,
    "gn:timezone":"Africa/Lagos",
    "iso:country":"NG",
    "wof:name":"Egorbiri",
    "wof:placetype":"locality"
},
  "geometry": {"coordinates":[6.59577,4.80952],"type":"Point"}
}