{
  "type": "Feature",
  "properties": {
    "gn:admin1_code":"35.0",
    "gn:admin2_code":"2010",
    "gn:asciiname":"Kurang",
    "gn:country_code":"NG",
    "gn:dem":906,
    "gn:feature_class":"P",
    "gn:feature_code":"PPL",
    "gn:name":"Kurang",
    "gn:population":0,
    "gn:timezone":"Africa/Lagos",
    "iso:country":"NG",
    "wof:name":"Kurang",
    "wof:placetype":"locality"
},
  "geometry": {"coordinates":[13.60288,10.72405],"type":"Point"}
}