{
  "type": "Feature",
  "properties": {
    "gn:admin1_code":"31.0",
    "gn:admin2_code":"27001.0",
    "gn:asciiname":"Usogba",
    "gn:country_code":"NG",
    "gn:dem":62,
    "gn:feature_class":"P",
    "gn:feature_code":"PPL",
    "gn:name":"Usogba",
    "gn:population":0,
    "gn:timezone":"Africa/Lagos",
    "iso:country":"NG",
    "wof:name":"Usogba",
    "wof:placetype":"locality"
},
  "geometry": {"coordinates":[6.36667,8.71667],"type":"Point"}
}