{
  "type": "Feature",
  "properties": {
    "gn:admin1_code":"23.0",
    "gn:admin2_code":"19007.0",
    "gn:admin3_code":"KD0703",
    "gn:asciiname":"Kwarabe",
    "gn:country_code":"NG",
    "gn:dem":547,
    "gn:feature_class":"P",
    "gn:feature_code":"PPL",
    "gn:name":"Kwarabe",
    "gn:population":0,
    "gn:timezone":"Africa/Lagos",
    "iso:country":"NG",
    "name:und_x_variant":[
        "Kano"
    ],
    "wof:name":"Kwarabe",
    "wof:placetype":"locality"
},
  "geometry": {"coordinates":[8.04343,9.34721],"type":"Point"}
}