{
  "type": "Feature",
  "properties": {
    "gn:admin1_code":"51.0",
    "gn:admin2_code":"601.0",
    "gn:admin3_code":"60105",
    "gn:asciiname":"Gidan-Here",
    "gn:country_code":"NG",
    "gn:dem":255,
    "gn:feature_class":"P",
    "gn:feature_code":"PPL",
    "gn:name":"Gidan-Here",
    "gn:population":0,
    "gn:timezone":"Africa/Lagos",
    "iso:country":"NG",
    "wof:name":"Gidan-Here",
    "wof:placetype":"locality"
},
  "geometry": {"coordinates":[4.87783,13.27471],"type":"Point"}
}