{
  "type": "Feature",
  "properties": {
    "gn:admin1_code":"24.0",
    "gn:admin2_code":"402.0",
    "gn:admin3_code":"40204",
    "gn:asciiname":"Busau",
    "gn:country_code":"NG",
    "gn:dem":537,
    "gn:feature_class":"P",
    "gn:feature_code":"PPL",
    "gn:name":"Busau",
    "gn:population":0,
    "gn:timezone":"Africa/Lagos",
    "iso:country":"NG",
    "wof:name":"Busau",
    "wof:placetype":"locality"
},
  "geometry": {"coordinates":[7.61999,12.82969],"type":"Point"}
}