{
  "type": "Feature",
  "properties": {
    "gn:admin1_code":"55.0",
    "gn:asciiname":"Maulamidu",
    "gn:country_code":"NG",
    "gn:dem":325,
    "gn:feature_class":"P",
    "gn:feature_code":"PPL",
    "gn:name":"Maulamidu",
    "gn:population":0,
    "gn:timezone":"Africa/Lagos",
    "iso:country":"NG",
    "name:eng_x_preferred":[
        "Maulamidu"
    ],
    "wof:name":"Maulamidu",
    "wof:placetype":"locality"
},
  "geometry": {"coordinates":[10.71109,10.92914],"type":"Point"}
}