{
  "type": "Feature",
  "properties": {
    "gn:admin1_code":"16.0",
    "gn:admin2_code":"28016.0",
    "gn:asciiname":"Osu",
    "gn:country_code":"NG",
    "gn:dem":161,
    "gn:feature_class":"P",
    "gn:feature_code":"PPL",
    "gn:name":"Osu",
    "gn:population":0,
    "gn:timezone":"Africa/Lagos",
    "iso:country":"NG",
    "name:zho_x_preferred":[
        "Osu"
    ],
    "wof:name":"Osu",
    "wof:placetype":"locality"
},
  "geometry": {"coordinates":[3.73333,7.25],"type":"Point"}
}