{
  "type": "Feature",
  "properties": {
    "gn:admin1_code":"32.0",
    "gn:admin2_code":"31014.0",
    "gn:asciiname":"Ketu",
    "gn:country_code":"NG",
    "gn:dem":236,
    "gn:feature_class":"P",
    "gn:feature_code":"PPL",
    "gn:name":"Ketu",
    "gn:population":0,
    "gn:timezone":"Africa/Lagos",
    "iso:country":"NG",
    "name:ben_x_preferred":[
        "\u0995\u09c7\u09a4\u09c1"
    ],
    "name:cat_x_preferred":[
        "Ketu"
    ],
    "name:ceb_x_preferred":[
        "Ketu"
    ],
    "name:est_x_preferred":[
        "Ketu"
    ],
    "name:fra_x_preferred":[
        "Ketu"
    ],
    "name:por_x_preferred":[
        "Ketu"
    ],
    "name:san_x_preferred":[
        "\u0915\u0947\u0924\u0941\u0903"
    ],
    "name:swe_x_preferred":[
        "Ketu"
    ],
    "wof:name":"Ketu",
    "wof:placetype":"locality"
},
  "geometry": {"coordinates":[3.80639,7.55222],"type":"Point"}
}