{
  "type": "Feature",
  "properties": {
    "gn:admin1_code":"40.0",
    "gn:admin2_code":"517.0",
    "gn:admin3_code":"51703",
    "gn:asciiname":"Kiyafa",
    "gn:country_code":"NG",
    "gn:dem":150,
    "gn:feature_class":"P",
    "gn:feature_code":"PPL",
    "gn:name":"Kiyafa",
    "gn:population":0,
    "gn:timezone":"Africa/Lagos",
    "iso:country":"NG",
    "wof:name":"Kiyafa",
    "wof:placetype":"locality"
},
  "geometry": {"coordinates":[4.62754,11.10089],"type":"Point"}
}