{
  "type": "Feature",
  "properties": {
    "gn:admin1_code":"49.0",
    "gn:asciiname":"Kerifa",
    "gn:country_code":"NG",
    "gn:dem":1270,
    "gn:feature_class":"P",
    "gn:feature_code":"PPL",
    "gn:name":"Kerifa",
    "gn:population":0,
    "gn:timezone":"Africa/Lagos",
    "iso:country":"NG",
    "wof:name":"Kerifa",
    "wof:placetype":"locality"
},
  "geometry": {"coordinates":[8.70618,9.21375],"type":"Point"}
}