{
  "type": "Feature",
  "properties": {
    "gn:admin1_code":"29.0",
    "gn:admin2_code":"20017.0",
    "gn:admin3_code":"KN1902",
    "gn:asciiname":"Kayu",
    "gn:country_code":"NG",
    "gn:dem":576,
    "gn:feature_class":"P",
    "gn:feature_code":"PPL",
    "gn:name":"Kayu",
    "gn:population":0,
    "gn:timezone":"Africa/Lagos",
    "iso:country":"NG",
    "wof:name":"Kayu",
    "wof:placetype":"locality"
},
  "geometry": {"coordinates":[7.95154,11.90173],"type":"Point"}
}