{
  "type": "Feature",
  "properties": {
    "gn:admin1_code":"36.0",
    "gn:admin2_code":"10016.0",
    "gn:asciiname":"Mukoro Camp",
    "gn:country_code":"NG",
    "gn:dem":20,
    "gn:feature_class":"P",
    "gn:feature_code":"PPL",
    "gn:name":"Mukoro Camp",
    "gn:population":0,
    "gn:timezone":"Africa/Lagos",
    "iso:country":"NG",
    "wof:name":"Mukoro Camp",
    "wof:placetype":"locality"
},
  "geometry": {"coordinates":[6.19659,5.1967],"type":"Point"}
}