{
  "type": "Feature",
  "properties": {
    "gn:admin1_code":"40.0",
    "gn:admin2_code":"513.0",
    "gn:admin3_code":"51302",
    "gn:asciiname":"Tunga Dodo",
    "gn:country_code":"NG",
    "gn:dem":224,
    "gn:feature_class":"P",
    "gn:feature_code":"PPL",
    "gn:name":"Tunga Dodo",
    "gn:population":0,
    "gn:timezone":"Africa/Lagos",
    "iso:country":"NG",
    "wof:name":"Tunga Dodo",
    "wof:placetype":"locality"
},
  "geometry": {"coordinates":[4.41685,11.45956],"type":"Point"}
}