{
  "type": "Feature",
  "properties": {
    "gn:admin1_code":"46.0",
    "gn:admin2_code":"5007.0",
    "gn:admin3_code":"BA0710",
    "gn:asciiname":"Bauna",
    "gn:country_code":"NG",
    "gn:dem":375,
    "gn:feature_class":"P",
    "gn:feature_code":"PPL",
    "gn:name":"Bauna",
    "gn:population":0,
    "gn:timezone":"Africa/Lagos",
    "iso:country":"NG",
    "name:chv_x_preferred":[
        "\u0411\u0430\u0443\u043d\u0430"
    ],
    "name:deu_x_preferred":[
        "Bauna"
    ],
    "name:rus_x_preferred":[
        "\u0411\u0430\u0443\u043d\u0430"
    ],
    "wof:name":"Bauna",
    "wof:placetype":"locality"
},
  "geometry": {"coordinates":[10.53036,12.01215],"type":"Point"}
}