{
  "type": "Feature",
  "properties": {
    "gn:admin1_code":"40.0",
    "gn:admin2_code":"508.0",
    "gn:admin3_code":"50807",
    "gn:asciiname":"Tungan Kade",
    "gn:country_code":"NG",
    "gn:dem":237,
    "gn:feature_class":"P",
    "gn:feature_code":"PPL",
    "gn:name":"Tungan Kade",
    "gn:population":0,
    "gn:timezone":"Africa/Lagos",
    "iso:country":"NG",
    "wof:name":"Tungan Kade",
    "wof:placetype":"locality"
},
  "geometry": {"coordinates":[3.89406,12.03701],"type":"Point"}
}