{
  "type": "Feature",
  "properties": {
    "gn:admin1_code":"51.0",
    "gn:admin2_code":"623.0",
    "gn:admin3_code":"62303",
    "gn:asciiname":"Yakanari",
    "gn:country_code":"NG",
    "gn:dem":258,
    "gn:feature_class":"P",
    "gn:feature_code":"PPL",
    "gn:name":"Yakanari",
    "gn:population":0,
    "gn:timezone":"Africa/Lagos",
    "iso:country":"NG",
    "name:und_x_variant":[
        "Yakunari",
        "Yakanari"
    ],
    "wof:name":"Yakanari",
    "wof:placetype":"locality"
},
  "geometry": {"coordinates":[4.82846,12.83372],"type":"Point"}
}