{
  "type": "Feature",
  "properties": {
    "gn:admin1_code":"39.0",
    "gn:admin2_code":"18004.0",
    "gn:admin3_code":"JI0202",
    "gn:asciiname":"Tumushiri",
    "gn:country_code":"NG",
    "gn:dem":398,
    "gn:feature_class":"P",
    "gn:feature_code":"PPL",
    "gn:name":"Tumushiri",
    "gn:population":0,
    "gn:timezone":"Africa/Lagos",
    "iso:country":"NG",
    "wof:name":"Tumushiri",
    "wof:placetype":"locality"
},
  "geometry": {"coordinates":[8.80568,12.64051],"type":"Point"}
}