{
  "type": "Feature",
  "properties": {
    "gn:admin1_code":"44.0",
    "gn:admin2_code":"712.0",
    "gn:admin3_code":"71207",
    "gn:asciiname":"Kuka-Suguriwa",
    "gn:country_code":"NG",
    "gn:dem":373,
    "gn:feature_class":"P",
    "gn:feature_code":"PPL",
    "gn:name":"Kuka-Suguriwa",
    "gn:population":0,
    "gn:timezone":"Africa/Lagos",
    "iso:country":"NG",
    "wof:name":"Kuka-Suguriwa",
    "wof:placetype":"locality"
},
  "geometry": {"coordinates":[10.929,11.9044],"type":"Point"}
}