{
  "type": "Feature",
  "properties": {
    "gn:admin1_code":"57.0",
    "gn:asciiname":"Ungwan-Mama-Meduma",
    "gn:country_code":"NG",
    "gn:dem":466,
    "gn:feature_class":"P",
    "gn:feature_code":"PPL",
    "gn:name":"Ungwan-Mama-Meduma",
    "gn:population":0,
    "gn:timezone":"Africa/Lagos",
    "iso:country":"NG",
    "wof:name":"Ungwan-Mama-Meduma",
    "wof:placetype":"locality"
},
  "geometry": {"coordinates":[6.13866,11.32583],"type":"Point"}
}