{
  "type": "Feature",
  "properties": {
    "gn:admin1_code":"31.0",
    "gn:admin2_code":"27007.0",
    "gn:asciiname":"Gaba",
    "gn:country_code":"NG",
    "gn:dem":105,
    "gn:feature_class":"P",
    "gn:feature_code":"PPL",
    "gn:name":"Gaba",
    "gn:population":0,
    "gn:timezone":"Africa/Lagos",
    "iso:country":"NG",
    "name:ceb_x_preferred":[
        "Gaba"
    ],
    "name:ita_x_preferred":[
        "Gaba"
    ],
    "name:rus_x_preferred":[
        "\u0413\u0430\u0431\u0430"
    ],
    "name:swe_x_preferred":[
        "Gaba"
    ],
    "wof:name":"Gaba",
    "wof:placetype":"locality"
},
  "geometry": {"coordinates":[6.06667,8.91667],"type":"Point"}
}