{
  "type": "Feature",
  "properties": {
    "gn:admin1_code":"49.0",
    "gn:asciiname":"Andel",
    "gn:country_code":"NG",
    "gn:dem":243,
    "gn:feature_class":"P",
    "gn:feature_code":"PPL",
    "gn:name":"Andel",
    "gn:population":0,
    "gn:timezone":"Africa/Lagos",
    "iso:country":"NG",
    "wof:name":"Andel",
    "wof:placetype":"locality"
},
  "geometry": {"coordinates":[9.38018,8.79763],"type":"Point"}
}