{
  "type": "Feature",
  "properties": {
    "gn:admin1_code":"49.0",
    "gn:asciiname":"Andel",
    "gn:country_code":"NG",
    "gn:dem":243,
    "gn:feature_class":"P",
    "gn:feature_code":"PPL",
    "gn:name":"Andel",
    "gn:population":0,
    "gn:timezone":"Africa/Lagos",
    "iso:country":"NG",
    "name:ceb_x_preferred":[
        "Andel"
    ],
    "name:ces_x_preferred":[
        "And\u011bl"
    ],
    "name:deu_x_preferred":[
        "Andel"
    ],
    "name:fra_x_preferred":[
        "Andel"
    ],
    "name:ita_x_preferred":[
        "Andel"
    ],
    "name:nld_x_preferred":[
        "Andel"
    ],
    "name:slk_x_preferred":[
        "And\u011bl"
    ],
    "wof:name":"Andel",
    "wof:placetype":"locality"
},
  "geometry": {"coordinates":[9.38018,8.79763],"type":"Point"}
}