{
  "type": "Feature",
  "properties": {
    "gn:admin1_code":"41.0",
    "gn:admin2_code":"23019.0",
    "gn:asciiname":"Braidu",
    "gn:country_code":"NG",
    "gn:dem":204,
    "gn:feature_class":"P",
    "gn:feature_code":"PPL",
    "gn:name":"Braidu",
    "gn:population":0,
    "gn:timezone":"Africa/Lagos",
    "iso:country":"NG",
    "wof:name":"Braidu",
    "wof:placetype":"locality"
},
  "geometry": {"coordinates":[7.42295,7.9049],"type":"Point"}
}