{
  "type": "Feature",
  "properties": {
    "gn:admin1_code":"46.0",
    "gn:admin2_code":"5013.0",
    "gn:admin3_code":"BA1313",
    "gn:asciiname":"Mantawa",
    "gn:country_code":"NG",
    "gn:dem":332,
    "gn:feature_class":"P",
    "gn:feature_code":"PPL",
    "gn:name":"Mantawa",
    "gn:population":0,
    "gn:timezone":"Africa/Lagos",
    "iso:country":"NG",
    "name:eng_x_preferred":[
        "Mantawa"
    ],
    "wof:name":"Mantawa",
    "wof:placetype":"locality"
},
  "geometry": {"coordinates":[10.75367,10.3086],"type":"Point"}
}