{
  "type": "Feature",
  "properties": {
    "gn:admin1_code":"27.0",
    "gn:admin2_code":"127.0",
    "gn:admin3_code":"12704",
    "gn:asciiname":"Gora",
    "gn:country_code":"NG",
    "gn:dem":187,
    "gn:feature_class":"P",
    "gn:feature_code":"PPL",
    "gn:name":"Gora",
    "gn:population":0,
    "gn:timezone":"Africa/Lagos",
    "iso:country":"NG",
    "name:bos_x_preferred":[
        "Gora"
    ],
    "name:bul_x_preferred":[
        "\u0413\u043e\u0440\u0430"
    ],
    "name:ceb_x_preferred":[
        "Gora"
    ],
    "name:deu_x_preferred":[
        "Gora"
    ],
    "name:fin_x_preferred":[
        "Gora"
    ],
    "name:fra_x_preferred":[
        "Gora"
    ],
    "name:heb_x_preferred":[
        "\u05d2\u05d5\u05e8\u05d4"
    ],
    "name:hrv_x_preferred":[
        "Gora"
    ],
    "name:hun_x_preferred":[
        "Gora"
    ],
    "name:ind_x_preferred":[
        "Gora"
    ],
    "name:ita_x_preferred":[
        "Gora"
    ],
    "name:nld_x_preferred":[
        "Gora"
    ],
    "name:rue_x_preferred":[
        "\u0413\u043e\u0440\u0430"
    ],
    "name:rus_x_preferred":[
        "\u0413\u043e\u0440\u0430"
    ],
    "name:slv_x_preferred":[
        "Gora"
    ],
    "name:sna_x_preferred":[
        "Gora"
    ],
    "name:srp_x_preferred":[
        "\u0413\u043e\u0440\u0430"
    ],
    "name:swe_x_preferred":[
        "Gora"
    ],
    "name:tur_x_preferred":[
        "Gora"
    ],
    "name:ukr_x_preferred":[
        "\u0413\u043e\u0440\u0430"
    ],
    "name:und_x_variant":[
        "Gwara",
        "Gora"
    ],
    "wof:name":"Gora",
    "wof:placetype":"locality"
},
  "geometry": {"coordinates":[11.90525,10.05118],"type":"Point"}
}