{
  "type": "Feature",
  "properties": {
    "gn:admin1_code":"27.0",
    "gn:admin2_code":"127.0",
    "gn:admin3_code":"12704",
    "gn:asciiname":"Gora",
    "gn:country_code":"NG",
    "gn:dem":187,
    "gn:feature_class":"P",
    "gn:feature_code":"PPL",
    "gn:name":"Gora",
    "gn:population":0,
    "gn:timezone":"Africa/Lagos",
    "iso:country":"NG",
    "name:und_x_variant":[
        "Gwara",
        "Gora"
    ],
    "wof:name":"Gora",
    "wof:placetype":"locality"
},
  "geometry": {"coordinates":[11.90525,10.05118],"type":"Point"}
}