{
  "type": "Feature",
  "properties": {
    "gn:admin1_code":"27.0",
    "gn:asciiname":"Tunish",
    "gn:country_code":"NG",
    "gn:dem":292,
    "gn:feature_class":"P",
    "gn:feature_code":"PPL",
    "gn:name":"Tunish",
    "gn:population":0,
    "gn:timezone":"Africa/Lagos",
    "iso:country":"NG",
    "wof:name":"Tunish",
    "wof:placetype":"locality"
},
  "geometry": {"coordinates":[14.41691,12.30301],"type":"Point"}
}