{
  "type": "Feature",
  "properties": {
    "gn:admin1_code":"40.0",
    "gn:admin2_code":"511.0",
    "gn:admin3_code":"51105",
    "gn:asciiname":"Tanza Hill",
    "gn:country_code":"NG",
    "gn:dem":284,
    "gn:feature_class":"P",
    "gn:feature_code":"PPL",
    "gn:name":"Tanza Hill",
    "gn:population":0,
    "gn:timezone":"Africa/Lagos",
    "iso:country":"NG",
    "wof:name":"Tanza Hill",
    "wof:placetype":"locality"
},
  "geometry": {"coordinates":[4.54041,12.06818],"type":"Point"}
}