{
  "type": "Feature",
  "properties": {
    "gn:admin1_code":"27.0",
    "gn:admin2_code":"111.0",
    "gn:admin3_code":"11110",
    "gn:asciiname":"Gesosawa",
    "gn:country_code":"NG",
    "gn:dem":974,
    "gn:feature_class":"P",
    "gn:feature_code":"PPL",
    "gn:name":"Gesosawa",
    "gn:population":0,
    "gn:timezone":"Africa/Lagos",
    "iso:country":"NG",
    "wof:name":"Gesosawa",
    "wof:placetype":"locality"
},
  "geometry": {"coordinates":[13.70735,10.95472],"type":"Point"}
}