{
  "type": "Feature",
  "properties": {
    "gn:admin1_code":"50.0",
    "gn:admin2_code":"33009.0",
    "gn:asciiname":"Ejaka",
    "gn:country_code":"NG",
    "gn:dem":20,
    "gn:feature_class":"P",
    "gn:feature_code":"PPL",
    "gn:name":"Ejaka",
    "gn:population":0,
    "gn:timezone":"Africa/Lagos",
    "iso:country":"NG",
    "wof:name":"Ejaka",
    "wof:placetype":"locality"
},
  "geometry": {"coordinates":[7.15214,4.77581],"type":"Point"}
}