{
  "type": "Feature",
  "properties": {
    "gn:admin1_code":"43.0",
    "gn:admin2_code":"35016",
    "gn:asciiname":"Wasam",
    "gn:country_code":"NG",
    "gn:dem":447,
    "gn:feature_class":"P",
    "gn:feature_code":"PPL",
    "gn:name":"Wasam",
    "gn:population":0,
    "gn:timezone":"Africa/Lagos",
    "iso:country":"NG",
    "wof:name":"Wasam",
    "wof:placetype":"locality"
},
  "geometry": {"coordinates":[11.89197,8.86583],"type":"Point"}
}