{
  "type": "Feature",
  "properties": {
    "gn:admin1_code":"37.0",
    "gn:admin2_code":"12006.0",
    "gn:asciiname":"Ugianmwen",
    "gn:country_code":"NG",
    "gn:dem":287,
    "gn:feature_class":"P",
    "gn:feature_code":"PPL",
    "gn:name":"Ugianmwen",
    "gn:population":0,
    "gn:timezone":"Africa/Lagos",
    "iso:country":"NG",
    "name:eng_x_preferred":[
        "Ugianmuen"
    ],
    "name:eng_x_variant":[
        "Ugiamen",
        "Ugiame"
    ],
    "name:und_x_variant":[
        "Ugiame",
        "Ugiamen",
        "Ugianmwen"
    ],
    "wof:name":"Ugianmwen",
    "wof:placetype":"locality"
},
  "geometry": {"coordinates":[6.08896,6.67859],"type":"Point"}
}