{
  "type": "Feature",
  "properties": {
    "gn:admin1_code":"57.0",
    "gn:admin2_code":"813.0",
    "gn:admin3_code":"81303",
    "gn:asciiname":"Tudun Bakin Gulbi",
    "gn:country_code":"NG",
    "gn:dem":560,
    "gn:feature_class":"P",
    "gn:feature_code":"PPL",
    "gn:name":"Tudun Bakin Gulbi",
    "gn:population":0,
    "gn:timezone":"Africa/Lagos",
    "iso:country":"NG",
    "wof:name":"Tudun Bakin Gulbi",
    "wof:placetype":"locality"
},
  "geometry": {"coordinates":[6.72507,11.67121],"type":"Point"}
}