{
  "type": "Feature",
  "properties": {
    "gn:admin1_code":"51.0",
    "gn:admin2_code":"602.0",
    "gn:admin3_code":"60209",
    "gn:asciiname":"Gobirawa",
    "gn:country_code":"NG",
    "gn:dem":287,
    "gn:feature_class":"P",
    "gn:feature_code":"PPL",
    "gn:name":"Gobirawa",
    "gn:population":0,
    "gn:timezone":"Africa/Lagos",
    "iso:country":"NG",
    "name:und_x_variant":[
        "Gubrawa",
        "Gobirawa"
    ],
    "wof:name":"Gobirawa",
    "wof:placetype":"locality"
},
  "geometry": {"coordinates":[5.17666,12.9441],"type":"Point"}
}