{
  "type": "Feature",
  "properties": {
    "gn:admin1_code":"44.0",
    "gn:admin2_code":"710",
    "gn:admin3_code":"71008",
    "gn:asciiname":"Mamiram",
    "gn:country_code":"NG",
    "gn:dem":343,
    "gn:feature_class":"P",
    "gn:feature_code":"PPL",
    "gn:name":"Mamiram",
    "gn:population":0,
    "gn:timezone":"Africa/Lagos",
    "iso:country":"NG",
    "wof:name":"Mamiram",
    "wof:placetype":"locality"
},
  "geometry": {"coordinates":[10.81624,13.11172],"type":"Point"}
}