{
  "type": "Feature",
  "properties": {
    "gn:admin1_code":"39.0",
    "gn:admin2_code":"18024.0",
    "gn:admin3_code":"JI0809",
    "gn:asciiname":"Nabanawa",
    "gn:country_code":"NG",
    "gn:dem":391,
    "gn:feature_class":"P",
    "gn:feature_code":"PPL",
    "gn:name":"Nabanawa",
    "gn:population":0,
    "gn:timezone":"Africa/Lagos",
    "iso:country":"NG",
    "wof:name":"Nabanawa",
    "wof:placetype":"locality"
},
  "geometry": {"coordinates":[8.96168,12.48092],"type":"Point"}
}