{
  "type": "Feature",
  "properties": {
    "gn:admin1_code":"52.0",
    "gn:admin2_code":"6008.0",
    "gn:asciiname":"Anyama",
    "gn:country_code":"NG",
    "gn:dem":11,
    "gn:feature_class":"P",
    "gn:feature_code":"PPL",
    "gn:name":"Anyama",
    "gn:population":0,
    "gn:timezone":"Africa/Lagos",
    "iso:country":"NG",
    "name:und_x_variant":[
        "Ayama",
        "Anyama"
    ],
    "wof:name":"Anyama",
    "wof:placetype":"locality"
},
  "geometry": {"coordinates":[6.20909,4.86958],"type":"Point"}
}