{
  "type": "Feature",
  "properties": {
    "gn:admin1_code":"52.0",
    "gn:admin2_code":"6008.0",
    "gn:asciiname":"Anyama",
    "gn:country_code":"NG",
    "gn:dem":11,
    "gn:feature_class":"P",
    "gn:feature_code":"PPL",
    "gn:name":"Anyama",
    "gn:population":0,
    "gn:timezone":"Africa/Lagos",
    "iso:country":"NG",
    "name:ceb_x_preferred":[
        "Anyama"
    ],
    "name:deu_x_preferred":[
        "Anyama"
    ],
    "name:epo_x_preferred":[
        "Anyama"
    ],
    "name:fra_x_preferred":[
        "Anyama"
    ],
    "name:ita_x_preferred":[
        "Anyama"
    ],
    "name:kaz_x_preferred":[
        "\u0410\u043d\u044c\u044f\u043c\u0430"
    ],
    "name:lit_x_preferred":[
        "Anjama"
    ],
    "name:msa_x_preferred":[
        "Anyama"
    ],
    "name:nau_x_preferred":[
        "Anyama"
    ],
    "name:nld_x_preferred":[
        "Anyama"
    ],
    "name:pol_x_preferred":[
        "Anyama"
    ],
    "name:ron_x_preferred":[
        "\u00c1nyama"
    ],
    "name:rus_x_preferred":[
        "\u0410\u043d\u044c\u044f\u043c\u0430"
    ],
    "name:spa_x_preferred":[
        "\u00c1nyama"
    ],
    "name:swe_x_preferred":[
        "Anyama"
    ],
    "name:und_x_variant":[
        "Ayama",
        "Anyama"
    ],
    "name:zho_x_preferred":[
        "\u963f\u5c3c\u4e9e\u99ac"
    ],
    "wof:name":"Anyama",
    "wof:placetype":"locality"
},
  "geometry": {"coordinates":[6.20909,4.86958],"type":"Point"}
}