{
  "type": "Feature",
  "properties": {
    "gn:admin1_code":"40.0",
    "gn:admin2_code":"506.0",
    "gn:admin3_code":"50606",
    "gn:asciiname":"Kardi",
    "gn:country_code":"NG",
    "gn:dem":235,
    "gn:feature_class":"P",
    "gn:feature_code":"PPL",
    "gn:name":"Kardi",
    "gn:population":0,
    "gn:timezone":"Africa/Lagos",
    "iso:country":"NG",
    "name:ceb_x_preferred":[
        "Kardi"
    ],
    "name:swe_x_preferred":[
        "Kardi"
    ],
    "wof:name":"Kardi",
    "wof:placetype":"locality"
},
  "geometry": {"coordinates":[4.28552,12.4195],"type":"Point"}
}