{
  "type": "Feature",
  "properties": {
    "gn:admin1_code":"57.0",
    "gn:admin2_code":"813.0",
    "gn:admin3_code":"81301",
    "gn:asciiname":"Mamman",
    "gn:country_code":"NG",
    "gn:dem":593,
    "gn:feature_class":"P",
    "gn:feature_code":"PPL",
    "gn:name":"Mamman",
    "gn:population":0,
    "gn:timezone":"Africa/Lagos",
    "iso:country":"NG",
    "wof:name":"Mamman",
    "wof:placetype":"locality"
},
  "geometry": {"coordinates":[6.94529,11.85906],"type":"Point"}
}