{
  "type": "Feature",
  "properties": {
    "gn:admin1_code":"32.0",
    "gn:admin2_code":"31001.0",
    "gn:asciiname":"Ojele",
    "gn:country_code":"NG",
    "gn:dem":281,
    "gn:feature_class":"P",
    "gn:feature_code":"PPL",
    "gn:name":"Ojele",
    "gn:population":0,
    "gn:timezone":"Africa/Lagos",
    "iso:country":"NG",
    "wof:name":"Ojele",
    "wof:placetype":"locality"
},
  "geometry": {"coordinates":[3.86528,7.73694],"type":"Point"}
}