{
  "type": "Feature",
  "properties": {
    "gn:admin1_code":"35.0",
    "gn:asciiname":"Maningare",
    "gn:country_code":"NG",
    "gn:dem":199,
    "gn:feature_class":"P",
    "gn:feature_code":"PPL",
    "gn:name":"Maningare",
    "gn:population":0,
    "gn:timezone":"Africa/Lagos",
    "iso:country":"NG",
    "name:eng_x_preferred":[
        "Maningare"
    ],
    "wof:name":"Maningare",
    "wof:placetype":"locality"
},
  "geometry": {"coordinates":[12.47417,9.49249],"type":"Point"}
}