{
  "type": "Feature",
  "properties": {
    "gn:admin1_code":"23.0",
    "gn:admin2_code":"19006.0",
    "gn:admin3_code":"KD0605",
    "gn:asciiname":"Pangajere",
    "gn:country_code":"NG",
    "gn:dem":765,
    "gn:feature_class":"P",
    "gn:feature_code":"PPL",
    "gn:name":"Pangajere",
    "gn:population":0,
    "gn:timezone":"Africa/Lagos",
    "iso:country":"NG",
    "name:und_x_variant":[
        "Pan Gajere"
    ],
    "wof:name":"Pangajere",
    "wof:placetype":"locality"
},
  "geometry": {"coordinates":[7.97406,9.5406],"type":"Point"}
}