{
  "type": "Feature",
  "properties": {
    "gn:admin1_code":"26.0",
    "gn:admin2_code":"7010.0",
    "gn:asciiname":"Haruna",
    "gn:country_code":"NG",
    "gn:dem":158,
    "gn:feature_class":"P",
    "gn:feature_code":"PPL",
    "gn:name":"Haruna",
    "gn:population":0,
    "gn:timezone":"Africa/Lagos",
    "iso:country":"NG",
    "name:ces_x_preferred":[
        "Haruna"
    ],
    "name:deu_x_preferred":[
        "Haruna"
    ],
    "name:fin_x_preferred":[
        "Haruna"
    ],
    "name:ita_x_preferred":[
        "Haruna"
    ],
    "name:jpn_x_preferred":[
        "\u306f\u308b\u306a"
    ],
    "name:kor_x_preferred":[
        "\ud558\ub8e8\ub098"
    ],
    "name:nld_x_preferred":[
        "Haruna"
    ],
    "name:pol_x_preferred":[
        "Haruna"
    ],
    "name:rus_x_preferred":[
        "\u0425\u0430\u0440\u0443\u043d\u0430"
    ],
    "name:slk_x_preferred":[
        "Haruna"
    ],
    "name:spa_x_preferred":[
        "Haruna"
    ],
    "name:tha_x_preferred":[
        "\u0e2e\u0e32\u0e23\u0e38\u0e19\u0e30"
    ],
    "wof:name":"Haruna",
    "wof:placetype":"locality"
},
  "geometry": {"coordinates":[8.50925,7.29136],"type":"Point"}
}