{
  "type": "Feature",
  "properties": {
    "gn:admin1_code":"35.0",
    "gn:admin2_code":"2003.0",
    "gn:asciiname":"Wuro Hausa",
    "gn:country_code":"NG",
    "gn:dem":549,
    "gn:feature_class":"P",
    "gn:feature_code":"PPL",
    "gn:name":"Wuro Hausa",
    "gn:population":0,
    "gn:timezone":"Africa/Lagos",
    "iso:country":"NG",
    "wof:name":"Wuro Hausa",
    "wof:placetype":"locality"
},
  "geometry": {"coordinates":[12.06667,8.36667],"type":"Point"}
}