{
  "type": "Feature",
  "properties": {
    "gn:admin1_code":"48.0",
    "gn:admin2_code":"29008.0",
    "gn:asciiname":"Ago-Okeluse",
    "gn:country_code":"NG",
    "gn:dem":315,
    "gn:feature_class":"P",
    "gn:feature_code":"PPL",
    "gn:name":"Ago-Okeluse",
    "gn:population":0,
    "gn:timezone":"Africa/Lagos",
    "iso:country":"NG",
    "wof:name":"Ago-Okeluse",
    "wof:placetype":"locality"
},
  "geometry": {"coordinates":[5.1561,7.1347],"type":"Point"}
}