{
  "type": "Feature",
  "properties": {
    "gn:admin1_code":"31.0",
    "gn:admin2_code":"27013.0",
    "gn:asciiname":"Mamuzhi",
    "gn:country_code":"NG",
    "gn:dem":112,
    "gn:feature_class":"P",
    "gn:feature_code":"PPL",
    "gn:name":"Mamuzhi",
    "gn:population":0,
    "gn:timezone":"Africa/Lagos",
    "iso:country":"NG",
    "name:und_x_variant":[
        "Marmozhi"
    ],
    "wof:name":"Mamuzhi",
    "wof:placetype":"locality"
},
  "geometry": {"coordinates":[5.68105,9.48518],"type":"Point"}
}