{
  "type": "Feature",
  "properties": {
    "gn:admin1_code":"28.0",
    "gn:admin2_code":"17017.0",
    "gn:asciiname":"Okwu-Ogbaku",
    "gn:country_code":"NG",
    "gn:dem":74,
    "gn:feature_class":"P",
    "gn:feature_code":"PPL",
    "gn:name":"Okwu-Ogbaku",
    "gn:population":0,
    "gn:timezone":"Africa/Lagos",
    "iso:country":"NG",
    "wof:name":"Okwu-Ogbaku",
    "wof:placetype":"locality"
},
  "geometry": {"coordinates":[6.94169,5.57234],"type":"Point"}
}