{
  "type": "Feature",
  "properties": {
    "gn:admin1_code":"44.0",
    "gn:admin2_code":"710.0",
    "gn:admin3_code":"71008",
    "gn:asciiname":"Ndijiu",
    "gn:country_code":"NG",
    "gn:dem":345,
    "gn:feature_class":"P",
    "gn:feature_code":"PPL",
    "gn:name":"Ndijiu",
    "gn:population":0,
    "gn:timezone":"Africa/Lagos",
    "iso:country":"NG",
    "name:und_x_variant":[
        "Chinjaidia"
    ],
    "wof:name":"Ndijiu",
    "wof:placetype":"locality"
},
  "geometry": {"coordinates":[10.89633,13.17835],"type":"Point"}
}