{
  "type": "Feature",
  "properties": {
    "gn:admin1_code":"36.0",
    "gn:admin2_code":"10019.0",
    "gn:asciiname":"Okoh Ondhwakpor",
    "gn:country_code":"NG",
    "gn:dem":17,
    "gn:feature_class":"P",
    "gn:feature_code":"PPL",
    "gn:name":"Okoh Ondhwakpor",
    "gn:population":0,
    "gn:timezone":"Africa/Lagos",
    "iso:country":"NG",
    "wof:name":"Okoh Ondhwakpor",
    "wof:placetype":"locality"
},
  "geometry": {"coordinates":[6.02337,5.71764],"type":"Point"}
}