{
  "type": "Feature",
  "properties": {
    "gn:admin1_code":"51.0",
    "gn:admin2_code":"613.0",
    "gn:admin3_code":"61310",
    "gn:asciiname":"Gidan Gago",
    "gn:country_code":"NG",
    "gn:dem":288,
    "gn:feature_class":"P",
    "gn:feature_code":"PPL",
    "gn:name":"Gidan Gago",
    "gn:population":0,
    "gn:timezone":"Africa/Lagos",
    "iso:country":"NG",
    "wof:name":"Gidan Gago",
    "wof:placetype":"locality"
},
  "geometry": {"coordinates":[5.98158,13.66399],"type":"Point"}
}