{
  "type": "Feature",
  "properties": {
    "gn:admin1_code":"53.0",
    "gn:admin2_code":"11010",
    "gn:asciiname":"Akalaku",
    "gn:country_code":"NG",
    "gn:dem":55,
    "gn:feature_class":"P",
    "gn:feature_code":"PPL",
    "gn:name":"Akalaku",
    "gn:population":0,
    "gn:timezone":"Africa/Lagos",
    "iso:country":"NG",
    "wof:name":"Akalaku",
    "wof:placetype":"locality"
},
  "geometry": {"coordinates":[8.23462,6.74351],"type":"Point"}
}