{
  "type": "Feature",
  "properties": {
    "gn:admin1_code":"52.0",
    "gn:admin2_code":"6002.0",
    "gn:asciiname":"Womoposigbene",
    "gn:country_code":"NG",
    "gn:dem":5,
    "gn:feature_class":"P",
    "gn:feature_code":"PPL",
    "gn:name":"Womoposigbene",
    "gn:population":0,
    "gn:timezone":"Africa/Lagos",
    "iso:country":"NG",
    "name:eng_x_preferred":[
        "Womoposigbene"
    ],
    "wof:name":"Womoposigbene",
    "wof:placetype":"locality"
},
  "geometry": {"coordinates":[5.57773,4.80586],"type":"Point"}
}