{
  "type": "Feature",
  "properties": {
    "gn:admin1_code":"37.0",
    "gn:admin2_code":"12014.0",
    "gn:asciiname":"Ugbokun Junction",
    "gn:country_code":"NG",
    "gn:dem":160,
    "gn:feature_class":"P",
    "gn:feature_code":"PPL",
    "gn:name":"Ugbokun Junction",
    "gn:population":0,
    "gn:timezone":"Africa/Lagos",
    "iso:country":"NG",
    "wof:name":"Ugbokun Junction",
    "wof:placetype":"locality"
},
  "geometry": {"coordinates":[5.43708,6.5955],"type":"Point"}
}