{
  "type": "Feature",
  "properties": {
    "gn:admin1_code":"35.0",
    "gn:asciiname":"Ndiyam Kojoli",
    "gn:country_code":"NG",
    "gn:dem":221,
    "gn:feature_class":"P",
    "gn:feature_code":"PPL",
    "gn:name":"Ndiyam Kojoli",
    "gn:population":0,
    "gn:timezone":"Africa/Lagos",
    "iso:country":"NG",
    "name:eng_x_preferred":[
        "Ndiyam Kojoli"
    ],
    "wof:name":"Ndiyam Kojoli",
    "wof:placetype":"locality"
},
  "geometry": {"coordinates":[12.15725,9.12999],"type":"Point"}
}