{
  "type": "Feature",
  "properties": {
    "gn:admin1_code":"24.0",
    "gn:admin2_code":"407.0",
    "gn:admin3_code":"40711",
    "gn:asciiname":"Ungwan Ruan Ango",
    "gn:country_code":"NG",
    "gn:dem":673,
    "gn:feature_class":"P",
    "gn:feature_code":"PPL",
    "gn:name":"Ungwan Ruan Ango",
    "gn:population":0,
    "gn:timezone":"Africa/Lagos",
    "iso:country":"NG",
    "wof:name":"Ungwan Ruan Ango",
    "wof:placetype":"locality"
},
  "geometry": {"coordinates":[7.27236,11.39851],"type":"Point"}
}