{
  "type": "Feature",
  "properties": {
    "gn:admin1_code":"43.0",
    "gn:admin2_code":"35001",
    "gn:asciiname":"Zongon Konbi Jauro Habu",
    "gn:country_code":"NG",
    "gn:dem":170,
    "gn:feature_class":"P",
    "gn:feature_code":"PPL",
    "gn:name":"Zongon Konbi Jauro Habu",
    "gn:population":0,
    "gn:timezone":"Africa/Lagos",
    "iso:country":"NG",
    "wof:name":"Zongon Konbi Jauro Habu",
    "wof:placetype":"locality"
},
  "geometry": {"coordinates":[11.03687,8.7953],"type":"Point"}
}