{
  "type": "Feature",
  "properties": {
    "gn:admin1_code":"23.0",
    "gn:admin2_code":"19020",
    "gn:admin3_code":"KD2006",
    "gn:asciiname":"Fadan Karshe",
    "gn:country_code":"NG",
    "gn:dem":521,
    "gn:feature_class":"P",
    "gn:feature_code":"PPL",
    "gn:name":"Fadan Karshe",
    "gn:population":0,
    "gn:timezone":"Africa/Lagos",
    "iso:country":"NG",
    "wof:name":"Fadan Karshe",
    "wof:placetype":"locality"
},
  "geometry": {"coordinates":[8.57775,9.38876],"type":"Point"}
}