{
  "type": "Feature",
  "properties": {
    "gn:admin1_code":"35.0",
    "gn:admin2_code":"2008.0",
    "gn:asciiname":"Lugere Ibi",
    "gn:country_code":"NG",
    "gn:dem":388,
    "gn:feature_class":"P",
    "gn:feature_code":"PPL",
    "gn:name":"Lugere Ibi",
    "gn:population":0,
    "gn:timezone":"Africa/Lagos",
    "iso:country":"NG",
    "wof:name":"Lugere Ibi",
    "wof:placetype":"locality"
},
  "geometry": {"coordinates":[12.15796,8.86994],"type":"Point"}
}