{
  "type": "Feature",
  "properties": {
    "gn:admin1_code":"32.0",
    "gn:admin2_code":"31018.0",
    "gn:asciiname":"Aiyetoro",
    "gn:country_code":"NG",
    "gn:dem":274,
    "gn:feature_class":"P",
    "gn:feature_code":"PPL",
    "gn:name":"Aiyetoro",
    "gn:population":0,
    "gn:timezone":"Africa/Lagos",
    "iso:country":"NG",
    "wof:name":"Aiyetoro",
    "wof:placetype":"locality"
},
  "geometry": {"coordinates":[3.08333,7.98333],"type":"Point"}
}