{
  "type": "Feature",
  "properties": {
    "gn:admin1_code":"36.0",
    "gn:admin2_code":"10017.0",
    "gn:asciiname":"Obotie",
    "gn:country_code":"NG",
    "gn:dem":9,
    "gn:feature_class":"P",
    "gn:feature_code":"PPL",
    "gn:name":"Obotie",
    "gn:population":0,
    "gn:timezone":"Africa/Lagos",
    "iso:country":"NG",
    "name:eng_x_preferred":[
        "Obotie"
    ],
    "wof:name":"Obotie",
    "wof:placetype":"locality"
},
  "geometry": {"coordinates":[5.5704,5.84131],"type":"Point"}
}