{
  "type": "Feature",
  "properties": {
    "gn:admin1_code":"27.0",
    "gn:admin2_code":"127.0",
    "gn:admin3_code":"12705",
    "gn:asciiname":"Bedenu",
    "gn:country_code":"NG",
    "gn:dem":240,
    "gn:feature_class":"P",
    "gn:feature_code":"PPL",
    "gn:name":"Bedenu",
    "gn:population":0,
    "gn:timezone":"Africa/Lagos",
    "iso:country":"NG",
    "wof:name":"Bedenu",
    "wof:placetype":"locality"
},
  "geometry": {"coordinates":[12.12503,10.23406],"type":"Point"}
}