{
  "type": "Feature",
  "properties": {
    "gn:admin1_code":"23.0",
    "gn:admin2_code":"19003.0",
    "gn:admin3_code":"KD0301",
    "gn:asciiname":"Madobi",
    "gn:country_code":"NG",
    "gn:dem":659,
    "gn:feature_class":"P",
    "gn:feature_code":"PPL",
    "gn:name":"Madobi",
    "gn:population":0,
    "gn:timezone":"Africa/Lagos",
    "iso:country":"NG",
    "name:ceb_x_preferred":[
        "Madobi"
    ],
    "name:fra_x_preferred":[
        "Madobi"
    ],
    "name:hau_x_preferred":[
        "Madobi"
    ],
    "name:ita_x_preferred":[
        "Madobi"
    ],
    "name:por_x_preferred":[
        "Madobi"
    ],
    "name:spa_x_preferred":[
        "Madobi"
    ],
    "name:urd_x_preferred":[
        "\u0645\u06cc\u0688\u0648\u0628\u06cc"
    ],
    "wof:name":"Madobi",
    "wof:placetype":"locality"
},
  "geometry": {"coordinates":[7.59546,11.25826],"type":"Point"}
}