{
  "type": "Feature",
  "properties": {
    "gn:admin1_code":"46.0",
    "gn:admin2_code":"5009.0",
    "gn:admin3_code":"BA0913",
    "gn:asciiname":"Mainari",
    "gn:country_code":"NG",
    "gn:dem":433,
    "gn:feature_class":"P",
    "gn:feature_code":"PPL",
    "gn:name":"Mainari",
    "gn:population":0,
    "gn:timezone":"Africa/Lagos",
    "iso:country":"NG",
    "wof:name":"Mainari",
    "wof:placetype":"locality"
},
  "geometry": {"coordinates":[10.2752,11.4658],"type":"Point"}
}