{
  "type": "Feature",
  "properties": {
    "gn:admin1_code":"31.0",
    "gn:admin2_code":"27009.0",
    "gn:asciiname":"Baji",
    "gn:country_code":"NG",
    "gn:dem":295,
    "gn:feature_class":"P",
    "gn:feature_code":"PPL",
    "gn:name":"Baji",
    "gn:population":0,
    "gn:timezone":"Africa/Lagos",
    "iso:country":"NG",
    "name:ceb_x_preferred":[
        "Baji"
    ],
    "name:swe_x_preferred":[
        "Baji"
    ],
    "wof:name":"Baji",
    "wof:placetype":"locality"
},
  "geometry": {"coordinates":[6.93726,9.31164],"type":"Point"}
}