{
  "type": "Feature",
  "properties": {
    "gn:admin1_code":"31.0",
    "gn:admin2_code":"27004.0",
    "gn:asciiname":"Kwaroin",
    "gn:country_code":"NG",
    "gn:dem":158,
    "gn:feature_class":"P",
    "gn:feature_code":"PPL",
    "gn:name":"Kwaroin",
    "gn:population":0,
    "gn:timezone":"Africa/Lagos",
    "iso:country":"NG",
    "wof:name":"Kwaroin",
    "wof:placetype":"locality"
},
  "geometry": {"coordinates":[4.53333,9.81667],"type":"Point"}
}