{
  "type": "Feature",
  "properties": {
    "gn:admin1_code":"49.0",
    "gn:asciiname":"Sha",
    "gn:country_code":"NG",
    "gn:dem":1288,
    "gn:feature_class":"P",
    "gn:feature_code":"PPL",
    "gn:name":"Sha",
    "gn:population":0,
    "gn:timezone":"Africa/Lagos",
    "iso:country":"NG",
    "wof:name":"Sha",
    "wof:placetype":"locality"
},
  "geometry": {"coordinates":[8.7677,9.19313],"type":"Point"}
}