{
  "type": "Feature",
  "properties": {
    "gn:admin1_code":"35.0",
    "gn:admin2_code":"2008",
    "gn:asciiname":"Wuro Adamu",
    "gn:country_code":"NG",
    "gn:dem":385,
    "gn:feature_class":"P",
    "gn:feature_code":"PPL",
    "gn:name":"Wuro Adamu",
    "gn:population":0,
    "gn:timezone":"Africa/Lagos",
    "iso:country":"NG",
    "wof:name":"Wuro Adamu",
    "wof:placetype":"locality"
},
  "geometry": {"coordinates":[12.28059,8.75214],"type":"Point"}
}