{
  "type": "Feature",
  "properties": {
    "gn:admin1_code":"46.0",
    "gn:admin2_code":"5005.0",
    "gn:admin3_code":"BA0512",
    "gn:asciiname":"Lugge",
    "gn:country_code":"NG",
    "gn:dem":466,
    "gn:feature_class":"P",
    "gn:feature_code":"PPL",
    "gn:name":"Lugge",
    "gn:population":0,
    "gn:timezone":"Africa/Lagos",
    "iso:country":"NG",
    "name:eng_x_preferred":[
        "Lugge"
    ],
    "wof:name":"Lugge",
    "wof:placetype":"locality"
},
  "geometry": {"coordinates":[10.35096,10.95403],"type":"Point"}
}