{
  "type": "Feature",
  "properties": {
    "gn:admin1_code":"27.0",
    "gn:admin2_code":"105.0",
    "gn:admin3_code":"10501",
    "gn:asciiname":"Klare Kuda",
    "gn:country_code":"NG",
    "gn:dem":574,
    "gn:feature_class":"P",
    "gn:feature_code":"PPL",
    "gn:name":"Klare Kuda",
    "gn:population":0,
    "gn:timezone":"Africa/Lagos",
    "iso:country":"NG",
    "wof:name":"Klare Kuda",
    "wof:placetype":"locality"
},
  "geometry": {"coordinates":[11.97713,10.85394],"type":"Point"}
}