{
  "type": "Feature",
  "properties": {
    "gn:admin1_code":"40.0",
    "gn:admin2_code":"506.0",
    "gn:admin3_code":"50606",
    "gn:asciiname":"Gazo Hausawa",
    "gn:country_code":"NG",
    "gn:dem":232,
    "gn:feature_class":"P",
    "gn:feature_code":"PPL",
    "gn:name":"Gazo Hausawa",
    "gn:population":0,
    "gn:timezone":"Africa/Lagos",
    "iso:country":"NG",
    "wof:name":"Gazo Hausawa",
    "wof:placetype":"locality"
},
  "geometry": {"coordinates":[4.27841,12.44408],"type":"Point"}
}