{
  "type": "Feature",
  "properties": {
    "gn:admin1_code":"35.0",
    "gn:admin2_code":"2005.0",
    "gn:asciiname":"Peratemsa",
    "gn:country_code":"NG",
    "gn:dem":687,
    "gn:feature_class":"P",
    "gn:feature_code":"PPL",
    "gn:name":"Peratemsa",
    "gn:population":0,
    "gn:timezone":"Africa/Lagos",
    "iso:country":"NG",
    "wof:name":"Peratemsa",
    "wof:placetype":"locality"
},
  "geometry": {"coordinates":[12.3364,10.07296],"type":"Point"}
}