{
  "type": "Feature",
  "properties": {
    "gn:admin1_code":"11.0",
    "gn:admin2_code":"15006.0",
    "gn:asciiname":"Kukwaba",
    "gn:country_code":"NG",
    "gn:dem":482,
    "gn:feature_class":"P",
    "gn:feature_code":"PPL",
    "gn:name":"Kukwaba",
    "gn:population":0,
    "gn:timezone":"Africa/Lagos",
    "iso:country":"NG",
    "name:und_x_variant":[
        "Kunkwaba",
        "Kukwaba"
    ],
    "wof:name":"Kukwaba",
    "wof:placetype":"locality"
},
  "geometry": {"coordinates":[7.45768,9.03741],"type":"Point"}
}