{
  "type": "Feature",
  "properties": {
    "gn:admin1_code":"16.0",
    "gn:admin2_code":"28013.0",
    "gn:asciiname":"Alagogo",
    "gn:country_code":"NG",
    "gn:dem":115,
    "gn:feature_class":"P",
    "gn:feature_code":"PPL",
    "gn:name":"Alagogo",
    "gn:population":0,
    "gn:timezone":"Africa/Lagos",
    "iso:country":"NG",
    "wof:name":"Alagogo",
    "wof:placetype":"locality"
},
  "geometry": {"coordinates":[3.06667,7.46667],"type":"Point"}
}