{
  "type": "Feature",
  "properties": {
    "gn:admin1_code":"55.0",
    "gn:admin2_code":"16004",
    "gn:asciiname":"Bolari",
    "gn:country_code":"NG",
    "gn:dem":341,
    "gn:feature_class":"P",
    "gn:feature_code":"PPL",
    "gn:name":"Bolari",
    "gn:population":0,
    "gn:timezone":"Africa/Lagos",
    "iso:country":"NG",
    "wof:name":"Bolari",
    "wof:placetype":"locality"
},
  "geometry": {"coordinates":[11.11622,11.0139],"type":"Point"}
}