{
  "type": "Feature",
  "properties": {
    "gn:admin1_code":"28.0",
    "gn:admin2_code":"17009.0",
    "gn:asciiname":"Umu-Neke",
    "gn:country_code":"NG",
    "gn:dem":214,
    "gn:feature_class":"P",
    "gn:feature_code":"PPL",
    "gn:name":"Umu-Neke",
    "gn:population":0,
    "gn:timezone":"Africa/Lagos",
    "iso:country":"NG",
    "wof:name":"Umu-Neke",
    "wof:placetype":"locality"
},
  "geometry": {"coordinates":[7.18431,5.66126],"type":"Point"}
}