{
  "type": "Feature",
  "properties": {
    "gn:admin1_code":"26.0",
    "gn:admin2_code":"7008.0",
    "gn:asciiname":"Zeku",
    "gn:country_code":"NG",
    "gn:dem":92,
    "gn:feature_class":"P",
    "gn:feature_code":"PPL",
    "gn:name":"Zeku",
    "gn:population":0,
    "gn:timezone":"Africa/Lagos",
    "iso:country":"NG",
    "wof:name":"Zeku",
    "wof:placetype":"locality"
},
  "geometry": {"coordinates":[8.13616,7.73398],"type":"Point"}
}