{
  "type": "Feature",
  "properties": {
    "gn:admin1_code":"51.0",
    "gn:admin2_code":"614.0",
    "gn:admin3_code":"61404",
    "gn:asciiname":"Gidan Sarkin Dutse",
    "gn:country_code":"NG",
    "gn:dem":305,
    "gn:feature_class":"P",
    "gn:feature_code":"PPL",
    "gn:name":"Gidan Sarkin Dutse",
    "gn:population":0,
    "gn:timezone":"Africa/Lagos",
    "iso:country":"NG",
    "wof:name":"Gidan Sarkin Dutse",
    "wof:placetype":"locality"
},
  "geometry": {"coordinates":[5.18333,12.71667],"type":"Point"}
}