{
  "type": "Feature",
  "properties": {
    "gn:admin1_code":"16.0",
    "gn:admin2_code":"28001.0",
    "gn:asciiname":"Akala",
    "gn:country_code":"NG",
    "gn:dem":71,
    "gn:feature_class":"P",
    "gn:feature_code":"PPL",
    "gn:name":"Akala",
    "gn:population":0,
    "gn:timezone":"Africa/Lagos",
    "iso:country":"NG",
    "name:srp_x_preferred":[
        "\u0410\u043a\u0430\u043b\u0430"
    ],
    "wof:name":"Akala",
    "wof:placetype":"locality"
},
  "geometry": {"coordinates":[3.13333,7.35],"type":"Point"}
}