{
  "type": "Feature",
  "properties": {
    "gn:admin1_code":"31.0",
    "gn:admin2_code":"27007",
    "gn:asciiname":"Emindatsu",
    "gn:country_code":"NG",
    "gn:dem":273,
    "gn:feature_class":"P",
    "gn:feature_code":"PPL",
    "gn:name":"Emindatsu",
    "gn:population":0,
    "gn:timezone":"Africa/Lagos",
    "iso:country":"NG",
    "wof:name":"Emindatsu",
    "wof:placetype":"locality"
},
  "geometry": {"coordinates":[5.69392,9.11142],"type":"Point"}
}