{
  "type": "Feature",
  "properties": {
    "gn:admin1_code":"23.0",
    "gn:admin2_code":"19002.0",
    "gn:admin3_code":"KD0201",
    "gn:asciiname":"Galibi",
    "gn:country_code":"NG",
    "gn:dem":549,
    "gn:feature_class":"P",
    "gn:feature_code":"PPL",
    "gn:name":"Galibi",
    "gn:population":0,
    "gn:timezone":"Africa/Lagos",
    "iso:country":"NG",
    "wof:name":"Galibi",
    "wof:placetype":"locality"
},
  "geometry": {"coordinates":[7.15,10.33333],"type":"Point"}
}