{
  "type": "Feature",
  "properties": {
    "gn:admin1_code":"43.0",
    "gn:admin2_code":"35004.0",
    "gn:asciiname":"Garbabi",
    "gn:country_code":"NG",
    "gn:dem":200,
    "gn:feature_class":"P",
    "gn:feature_code":"PPL",
    "gn:name":"Garbabi",
    "gn:population":0,
    "gn:timezone":"Africa/Lagos",
    "iso:country":"NG",
    "wof:name":"Garbabi",
    "wof:placetype":"locality"
},
  "geometry": {"coordinates":[11.03333,7.83333],"type":"Point"}
}