{
  "type": "Feature",
  "properties": {
    "gn:admin1_code":"16.0",
    "gn:admin2_code":"28006.0",
    "gn:asciiname":"Isola",
    "gn:country_code":"NG",
    "gn:dem":26,
    "gn:feature_class":"P",
    "gn:feature_code":"PPL",
    "gn:name":"Isola",
    "gn:population":0,
    "gn:timezone":"Africa/Lagos",
    "iso:country":"NG",
    "name:ceb_x_preferred":[
        "Isola"
    ],
    "name:deu_x_preferred":[
        "Isola"
    ],
    "name:fin_x_preferred":[
        "Isola"
    ],
    "name:fra_x_preferred":[
        "Isola"
    ],
    "name:ita_x_preferred":[
        "Isola"
    ],
    "name:jpn_x_preferred":[
        "\u30a4\u30bd\u30e9"
    ],
    "name:nld_x_preferred":[
        "Isola"
    ],
    "name:nor_x_preferred":[
        "Isola"
    ],
    "name:por_x_preferred":[
        "Isola"
    ],
    "name:scn_x_preferred":[
        "\u00ccsula"
    ],
    "name:srp_x_preferred":[
        "\u0418\u0437\u043e\u043b\u0430"
    ],
    "name:swe_x_preferred":[
        "Isola"
    ],
    "name:und_x_variant":[
        "Ishola"
    ],
    "name:vol_x_preferred":[
        "Isola"
    ],
    "wof:name":"Isola",
    "wof:placetype":"locality"
},
  "geometry": {"coordinates":[3.32347,6.8355],"type":"Point"}
}