{
  "type": "Feature",
  "properties": {
    "gn:admin1_code":"27.0",
    "gn:admin2_code":"102.0",
    "gn:admin3_code":"10203",
    "gn:asciiname":"Chanchan Bulguman Gabas",
    "gn:country_code":"NG",
    "gn:dem":469,
    "gn:feature_class":"P",
    "gn:feature_code":"PPL",
    "gn:name":"Chanchan Bulguman Gabas",
    "gn:population":0,
    "gn:timezone":"Africa/Lagos",
    "iso:country":"NG",
    "wof:name":"Chanchan Bulguman Gabas",
    "wof:placetype":"locality"
},
  "geometry": {"coordinates":[12.9059,10.67117],"type":"Point"}
}