{
  "type": "Feature",
  "properties": {
    "gn:admin1_code":"35.0",
    "gn:admin2_code":"2011.0",
    "gn:asciiname":"Guzum Maha",
    "gn:country_code":"NG",
    "gn:dem":619,
    "gn:feature_class":"P",
    "gn:feature_code":"PPL",
    "gn:name":"Guzum Maha",
    "gn:population":0,
    "gn:timezone":"Africa/Lagos",
    "iso:country":"NG",
    "wof:name":"Guzum Maha",
    "wof:placetype":"locality"
},
  "geometry": {"coordinates":[13.19658,10.07849],"type":"Point"}
}