{
  "type": "Feature",
  "properties": {
    "gn:admin1_code":"43.0",
    "gn:admin2_code":"35014",
    "gn:asciiname":"Alam",
    "gn:country_code":"NG",
    "gn:dem":178,
    "gn:feature_class":"P",
    "gn:feature_code":"PPL",
    "gn:name":"Alam",
    "gn:population":0,
    "gn:timezone":"Africa/Lagos",
    "iso:country":"NG",
    "wof:name":"Alam",
    "wof:placetype":"locality"
},
  "geometry": {"coordinates":[9.76272,7.72933],"type":"Point"}
}