{
  "type": "Feature",
  "properties": {
    "gn:admin1_code":"44.0",
    "gn:admin2_code":"716.0",
    "gn:admin3_code":"71609",
    "gn:asciiname":"Murimari",
    "gn:country_code":"NG",
    "gn:dem":330,
    "gn:feature_class":"P",
    "gn:feature_code":"PPL",
    "gn:name":"Murimari",
    "gn:population":0,
    "gn:timezone":"Africa/Lagos",
    "iso:country":"NG",
    "wof:name":"Murimari",
    "wof:placetype":"locality"
},
  "geometry": {"coordinates":[11.75374,13.09858],"type":"Point"}
}