{
  "type": "Feature",
  "properties": {
    "gn:admin1_code":"43.0",
    "gn:admin2_code":"35011.0",
    "gn:asciiname":"Usuman",
    "gn:country_code":"NG",
    "gn:dem":1530,
    "gn:feature_class":"P",
    "gn:feature_code":"PPL",
    "gn:name":"Usuman",
    "gn:population":0,
    "gn:timezone":"Africa/Lagos",
    "iso:country":"NG",
    "wof:name":"Usuman",
    "wof:placetype":"locality"
},
  "geometry": {"coordinates":[11.03333,7.23333],"type":"Point"}
}