{
  "type": "Feature",
  "properties": {
    "gn:admin1_code":"37.0",
    "gn:admin2_code":"12006.0",
    "gn:asciiname":"Urohi",
    "gn:country_code":"NG",
    "gn:dem":237,
    "gn:feature_class":"P",
    "gn:feature_code":"PPL",
    "gn:name":"Urohi",
    "gn:population":0,
    "gn:timezone":"Africa/Lagos",
    "iso:country":"NG",
    "name:eng_x_preferred":[
        "Urohi"
    ],
    "name:und_x_variant":[
        "Eguare-Urohi"
    ],
    "wof:name":"Urohi",
    "wof:placetype":"locality"
},
  "geometry": {"coordinates":[6.09156,6.59304],"type":"Point"}
}