{
  "type": "Feature",
  "properties": {
    "gn:admin1_code":"31.0",
    "gn:admin2_code":"27009.0",
    "gn:asciiname":"Shegi",
    "gn:country_code":"NG",
    "gn:dem":501,
    "gn:feature_class":"P",
    "gn:feature_code":"PPL",
    "gn:name":"Shegi",
    "gn:population":0,
    "gn:timezone":"Africa/Lagos",
    "iso:country":"NG",
    "wof:name":"Shegi",
    "wof:placetype":"locality"
},
  "geometry": {"coordinates":[7.11533,9.46132],"type":"Point"}
}