{
  "type": "Feature",
  "properties": {
    "gn:admin1_code":"26.0",
    "gn:admin2_code":"7021",
    "gn:asciiname":"Agogo",
    "gn:country_code":"NG",
    "gn:dem":201,
    "gn:feature_class":"P",
    "gn:feature_code":"PPL",
    "gn:name":"Agogo",
    "gn:population":0,
    "gn:timezone":"Africa/Lagos",
    "iso:country":"NG",
    "name:ceb_x_preferred":[
        "Agogo"
    ],
    "name:deu_x_preferred":[
        "Agogo"
    ],
    "name:ita_x_preferred":[
        "Agogo"
    ],
    "name:nld_x_preferred":[
        "Agogo"
    ],
    "name:por_x_preferred":[
        "Agogo"
    ],
    "name:swe_x_preferred":[
        "Agogo"
    ],
    "wof:name":"Agogo",
    "wof:placetype":"locality"
},
  "geometry": {"coordinates":[9.59576,7.70753],"type":"Point"}
}