{
  "type": "Feature",
  "properties": {
    "gn:admin1_code":"23.0",
    "gn:admin2_code":"19005.0",
    "gn:admin3_code":"KD0503",
    "gn:asciiname":"Malikanchi",
    "gn:country_code":"NG",
    "gn:dem":611,
    "gn:feature_class":"P",
    "gn:feature_code":"PPL",
    "gn:name":"Malikanchi",
    "gn:population":0,
    "gn:timezone":"Africa/Lagos",
    "iso:country":"NG",
    "wof:name":"Malikanchi",
    "wof:placetype":"locality"
},
  "geometry": {"coordinates":[8.29278,11.16062],"type":"Point"}
}