{
  "type": "Feature",
  "properties": {
    "gn:admin1_code":"49.0",
    "gn:admin2_code":"32016",
    "gn:asciiname":"Boret",
    "gn:country_code":"NG",
    "gn:dem":228,
    "gn:feature_class":"P",
    "gn:feature_code":"PPL",
    "gn:name":"Boret",
    "gn:population":0,
    "gn:timezone":"Africa/Lagos",
    "iso:country":"NG",
    "wof:name":"Boret",
    "wof:placetype":"locality"
},
  "geometry": {"coordinates":[9.56766,8.92439],"type":"Point"}
}