{
  "type": "Feature",
  "properties": {
    "gn:admin1_code":"48.0",
    "gn:admin2_code":"29006.0",
    "gn:asciiname":"Ilesha",
    "gn:country_code":"NG",
    "gn:dem":292,
    "gn:feature_class":"P",
    "gn:feature_code":"PPL",
    "gn:name":"Ilesha",
    "gn:population":0,
    "gn:timezone":"Africa/Lagos",
    "iso:country":"NG",
    "wof:name":"Ilesha",
    "wof:placetype":"locality"
},
  "geometry": {"coordinates":[5.2583,7.1371],"type":"Point"}
}