{
  "type": "Feature",
  "properties": {
    "gn:admin1_code":"24.0",
    "gn:admin2_code":"416.0",
    "gn:admin3_code":"41602",
    "gn:asciiname":"Zandam",
    "gn:country_code":"NG",
    "gn:dem":413,
    "gn:feature_class":"P",
    "gn:feature_code":"PPL",
    "gn:name":"Zandam",
    "gn:population":0,
    "gn:timezone":"Africa/Lagos",
    "iso:country":"NG",
    "wof:name":"Zandam",
    "wof:placetype":"locality"
},
  "geometry": {"coordinates":[7.25,13.03333],"type":"Point"}
}