{
  "type": "Feature",
  "properties": {
    "gn:admin1_code":"30.0",
    "gn:admin2_code":"24005.0",
    "gn:asciiname":"Kunmi",
    "gn:country_code":"NG",
    "gn:dem":347,
    "gn:feature_class":"P",
    "gn:feature_code":"PPL",
    "gn:name":"Kunmi",
    "gn:population":0,
    "gn:timezone":"Africa/Lagos",
    "iso:country":"NG",
    "wof:name":"Kunmi",
    "wof:placetype":"locality"
},
  "geometry": {"coordinates":[4.88333,8.46667],"type":"Point"}
}