{
  "type": "Feature",
  "properties": {
    "gn:admin1_code":"23.0",
    "gn:admin2_code":"19022.0",
    "gn:admin3_code":"KD2203",
    "gn:asciiname":"Adage",
    "gn:country_code":"NG",
    "gn:dem":734,
    "gn:feature_class":"P",
    "gn:feature_code":"PPL",
    "gn:name":"Adage",
    "gn:population":0,
    "gn:timezone":"Africa/Lagos",
    "iso:country":"NG",
    "wof:name":"Adage",
    "wof:placetype":"locality"
},
  "geometry": {"coordinates":[8.07127,9.91926],"type":"Point"}
}