{
  "type": "Feature",
  "properties": {
    "gn:admin1_code":"23.0",
    "gn:admin2_code":"19022.0",
    "gn:admin3_code":"KD2203",
    "gn:asciiname":"Adage",
    "gn:country_code":"NG",
    "gn:dem":734,
    "gn:feature_class":"P",
    "gn:feature_code":"PPL",
    "gn:name":"Adage",
    "gn:population":0,
    "gn:timezone":"Africa/Lagos",
    "iso:country":"NG",
    "name:ara_x_preferred":[
        "\u0642\u0648\u0644 \u0645\u0623\u062b\u0648\u0631"
    ],
    "name:ast_x_preferred":[
        "Adaxu"
    ],
    "name:bel_x_preferred":[
        "\u041f\u0440\u044b\u043c\u0430\u045e\u043a\u0430"
    ],
    "name:bul_x_preferred":[
        "\u041f\u043e\u0433\u043e\u0432\u043e\u0440\u043a\u0430"
    ],
    "name:cat_x_preferred":[
        "Adagi"
    ],
    "name:ces_x_preferred":[
        "R\u010den\u00ed"
    ],
    "name:deu_x_preferred":[
        "Sinnspruch"
    ],
    "name:eus_x_preferred":[
        "Zuhur-hitz"
    ],
    "name:fra_x_preferred":[
        "Adage"
    ],
    "name:ina_x_preferred":[
        "Adagio"
    ],
    "name:ita_x_preferred":[
        "Adagio"
    ],
    "name:kan_x_preferred":[
        "\u0c85\u0c82\u0ca4\u0cc6-\u0c95\u0c82\u0ca4\u0cc6"
    ],
    "name:lim_x_preferred":[
        "Gez\u00e8kde"
    ],
    "name:mar_x_preferred":[
        "\u092e\u094d\u0939\u0923\u0940"
    ],
    "name:nld_x_preferred":[
        "Adagium"
    ],
    "name:pol_x_preferred":[
        "Porzekad\u0142o"
    ],
    "name:rus_x_preferred":[
        "\u041f\u043e\u0433\u043e\u0432\u043e\u0440\u043a\u0430"
    ],
    "name:sah_x_preferred":[
        "\u04e8\u0441 \u043d\u043e\u043c\u043e\u0495\u043e"
    ],
    "name:slk_x_preferred":[
        "Porekadlo"
    ],
    "name:spa_x_preferred":[
        "Adagio"
    ],
    "name:ukr_x_preferred":[
        "\u041f\u0440\u0438\u043a\u0430\u0437\u043a\u0430"
    ],
    "wof:name":"Adage",
    "wof:placetype":"locality"
},
  "geometry": {"coordinates":[8.07127,9.91926],"type":"Point"}
}