{
  "type": "Feature",
  "properties": {
    "gn:admin1_code":"11.0",
    "gn:admin2_code":"15005.0",
    "gn:asciiname":"Tungan Galadima",
    "gn:country_code":"NG",
    "gn:dem":180,
    "gn:feature_class":"P",
    "gn:feature_code":"PPL",
    "gn:name":"Tungan Galadima",
    "gn:population":0,
    "gn:timezone":"Africa/Lagos",
    "iso:country":"NG",
    "wof:name":"Tungan Galadima",
    "wof:placetype":"locality"
},
  "geometry": {"coordinates":[6.93333,8.83333],"type":"Point"}
}