{
  "type": "Feature",
  "properties": {
    "gn:admin1_code":"24.0",
    "gn:admin2_code":"431.0",
    "gn:admin3_code":"43106",
    "gn:asciiname":"Ungwan Musa",
    "gn:country_code":"NG",
    "gn:dem":691,
    "gn:feature_class":"P",
    "gn:feature_code":"PPL",
    "gn:name":"Ungwan Musa",
    "gn:population":0,
    "gn:timezone":"Africa/Lagos",
    "iso:country":"NG",
    "wof:name":"Ungwan Musa",
    "wof:placetype":"locality"
},
  "geometry": {"coordinates":[7.15112,11.22977],"type":"Point"}
}