{
  "type": "Feature",
  "properties": {
    "gn:admin1_code":"5.0",
    "gn:admin2_code":"25008.0",
    "gn:asciiname":"Iru",
    "gn:country_code":"NG",
    "gn:dem":9,
    "gn:feature_class":"P",
    "gn:feature_code":"PPL",
    "gn:name":"Iru",
    "gn:population":0,
    "gn:timezone":"Africa/Lagos",
    "iso:country":"NG",
    "name:ceb_x_preferred":[
        "Iru"
    ],
    "name:ces_x_preferred":[
        "Iru"
    ],
    "name:hye_x_preferred":[
        "\u053b\u057c\u0578\u0582"
    ],
    "name:nld_x_preferred":[
        "Iru"
    ],
    "name:spa_x_preferred":[
        "Iru"
    ],
    "name:swe_x_preferred":[
        "Iru"
    ],
    "wof:name":"Iru",
    "wof:placetype":"neighbourhood"
},
  "geometry": {"coordinates":[3.41667,6.43333],"type":"Point"}
}