{
  "type": "Feature",
  "properties": {
    "gn:admin1_code":"43.0",
    "gn:admin2_code":"35006.0",
    "gn:asciiname":"Adi",
    "gn:country_code":"NG",
    "gn:dem":95,
    "gn:feature_class":"P",
    "gn:feature_code":"PPL",
    "gn:name":"Adi",
    "gn:population":0,
    "gn:timezone":"Africa/Lagos",
    "iso:country":"NG",
    "name:ceb_x_preferred":[
        "Adi"
    ],
    "name:ces_x_preferred":[
        "Adi"
    ],
    "name:dan_x_preferred":[
        "ADI"
    ],
    "name:deu_x_preferred":[
        "Adi"
    ],
    "name:fas_x_preferred":[
        "\u0627\u062f\u06cc"
    ],
    "name:fra_x_preferred":[
        "Adi"
    ],
    "name:nld_x_preferred":[
        "Adi"
    ],
    "name:pol_x_preferred":[
        "Adi"
    ],
    "name:ron_x_preferred":[
        "Adi"
    ],
    "name:rus_x_preferred":[
        "\u0410\u0434\u0438"
    ],
    "name:ukr_x_preferred":[
        "\u0410\u0434\u0456"
    ],
    "wof:name":"Adi",
    "wof:placetype":"locality"
},
  "geometry": {"coordinates":[9.43333,8.08333],"type":"Point"}
}