{
  "type": "Feature",
  "properties": {
    "gn:admin1_code":"35.0",
    "gn:admin2_code":"2008",
    "gn:asciiname":"Bapa Iya",
    "gn:country_code":"NG",
    "gn:dem":302,
    "gn:feature_class":"P",
    "gn:feature_code":"PPL",
    "gn:name":"Bapa Iya",
    "gn:population":0,
    "gn:timezone":"Africa/Lagos",
    "iso:country":"NG",
    "wof:name":"Bapa Iya",
    "wof:placetype":"locality"
},
  "geometry": {"coordinates":[12.2137,8.86132],"type":"Point"}
}