{
  "type": "Feature",
  "properties": {
    "gn:admin1_code":"35.0",
    "gn:admin2_code":"2015.0",
    "gn:asciiname":"Burka",
    "gn:country_code":"NG",
    "gn:dem":901,
    "gn:feature_class":"P",
    "gn:feature_code":"PPL",
    "gn:name":"Burka",
    "gn:population":0,
    "gn:timezone":"Africa/Lagos",
    "iso:country":"NG",
    "name:deu_x_preferred":[
        "Burka"
    ],
    "name:fra_x_preferred":[
        "Burka"
    ],
    "name:jpn_x_preferred":[
        "\u30d6\u30eb\u30ab"
    ],
    "name:nld_x_preferred":[
        "Boerka"
    ],
    "name:rus_x_preferred":[
        "\u0411\u0443\u0440\u043a\u0430"
    ],
    "name:ukr_x_preferred":[
        "\u0411\u0443\u0440\u043a\u0430"
    ],
    "wof:name":"Burka",
    "wof:placetype":"locality"
},
  "geometry": {"coordinates":[13.38779,10.19886],"type":"Point"}
}