{
  "type": "Feature",
  "properties": {
    "gn:admin1_code":"36.0",
    "gn:admin2_code":"10007.0",
    "gn:asciiname":"Uteh-Alohen",
    "gn:country_code":"NG",
    "gn:dem":162,
    "gn:feature_class":"P",
    "gn:feature_code":"PPL",
    "gn:name":"Uteh-Alohen",
    "gn:population":0,
    "gn:timezone":"Africa/Lagos",
    "iso:country":"NG",
    "name:eng_x_preferred":[
        "Uteh-Alohen"
    ],
    "wof:name":"Uteh-Alohen",
    "wof:placetype":"locality"
},
  "geometry": {"coordinates":[6.25458,6.19252],"type":"Point"}
}