{
  "type": "Feature",
  "properties": {
    "gn:admin1_code":"26.0",
    "gn:admin2_code":"7007",
    "gn:asciiname":"Atsembe",
    "gn:country_code":"NG",
    "gn:dem":178,
    "gn:feature_class":"P",
    "gn:feature_code":"PPL",
    "gn:name":"Atsembe",
    "gn:population":0,
    "gn:timezone":"Africa/Lagos",
    "iso:country":"NG",
    "wof:name":"Atsembe",
    "wof:placetype":"locality"
},
  "geometry": {"coordinates":[8.44864,7.28381],"type":"Point"}
}