{
  "type": "Feature",
  "properties": {
    "gn:admin1_code":"50.0",
    "gn:admin2_code":"33016.0",
    "gn:asciiname":"Ogbuku",
    "gn:country_code":"NG",
    "gn:dem":18,
    "gn:feature_class":"P",
    "gn:feature_code":"PPL",
    "gn:name":"Ogbuku",
    "gn:population":0,
    "gn:timezone":"Africa/Lagos",
    "iso:country":"NG",
    "wof:name":"Ogbuku",
    "wof:placetype":"locality"
},
  "geometry": {"coordinates":[6.58896,5.54962],"type":"Point"}
}