{
  "type": "Feature",
  "properties": {
    "gn:admin1_code":"16.0",
    "gn:admin2_code":"28016.0",
    "gn:asciiname":"Balogun",
    "gn:country_code":"NG",
    "gn:dem":85,
    "gn:feature_class":"P",
    "gn:feature_code":"PPL",
    "gn:name":"Balogun",
    "gn:population":0,
    "gn:timezone":"Africa/Lagos",
    "iso:country":"NG",
    "name:deu_x_preferred":[
        "Balogun"
    ],
    "wof:name":"Balogun",
    "wof:placetype":"locality"
},
  "geometry": {"coordinates":[3.35,7.26667],"type":"Point"}
}