{
  "type": "Feature",
  "properties": {
    "gn:admin1_code":"21.0",
    "gn:admin2_code":"3024.0",
    "gn:asciiname":"Awa Ndon",
    "gn:country_code":"NG",
    "gn:dem":34,
    "gn:feature_class":"P",
    "gn:feature_code":"PPL",
    "gn:name":"Awa Ndon",
    "gn:population":0,
    "gn:timezone":"Africa/Lagos",
    "iso:country":"NG",
    "wof:name":"Awa Ndon",
    "wof:placetype":"locality"
},
  "geometry": {"coordinates":[7.82525,4.67307],"type":"Point"}
}