{
  "type": "Feature",
  "properties": {
    "gn:admin1_code":"36.0",
    "gn:admin2_code":"10018.0",
    "gn:asciiname":"Okolo",
    "gn:country_code":"NG",
    "gn:dem":10,
    "gn:feature_class":"P",
    "gn:feature_code":"PPL",
    "gn:name":"Okolo",
    "gn:population":0,
    "gn:timezone":"Africa/Lagos",
    "iso:country":"NG",
    "wof:name":"Okolo",
    "wof:placetype":"locality"
},
  "geometry": {"coordinates":[5.83524,5.42229],"type":"Point"}
}