{
  "type": "Feature",
  "properties": {
    "gn:admin1_code":"35.0",
    "gn:admin2_code":"2012.0",
    "gn:asciiname":"Lumde Jamtari",
    "gn:country_code":"NG",
    "gn:dem":342,
    "gn:feature_class":"P",
    "gn:feature_code":"PPL",
    "gn:name":"Lumde Jamtari",
    "gn:population":0,
    "gn:timezone":"Africa/Lagos",
    "iso:country":"NG",
    "wof:name":"Lumde Jamtari",
    "wof:placetype":"locality"
},
  "geometry": {"coordinates":[11.91966,8.97929],"type":"Point"}
}