{
  "type": "Feature",
  "properties": {
    "gn:admin1_code":"40.0",
    "gn:admin2_code":"507.0",
    "gn:admin3_code":"50706",
    "gn:asciiname":"Kulba",
    "gn:country_code":"NG",
    "gn:dem":231,
    "gn:feature_class":"P",
    "gn:feature_code":"PPL",
    "gn:name":"Kulba",
    "gn:population":0,
    "gn:timezone":"Africa/Lagos",
    "iso:country":"NG",
    "wof:name":"Kulba",
    "wof:placetype":"locality"
},
  "geometry": {"coordinates":[4.1687,12.2639],"type":"Point"}
}