{
  "type": "Feature",
  "properties": {
    "gn:admin1_code":"31.0",
    "gn:admin2_code":"27007.0",
    "gn:asciiname":"Emagiti",
    "gn:country_code":"NG",
    "gn:dem":161,
    "gn:feature_class":"P",
    "gn:feature_code":"PPL",
    "gn:name":"Emagiti",
    "gn:population":0,
    "gn:timezone":"Africa/Lagos",
    "iso:country":"NG",
    "wof:name":"Emagiti",
    "wof:placetype":"neighbourhood"
},
  "geometry": {"coordinates":[6.0228,9.06231],"type":"Point"}
}