{
  "type": "Feature",
  "properties": {
    "gn:admin1_code":"41.0",
    "gn:admin2_code":"23009.0",
    "gn:asciiname":"Ekinrin",
    "gn:country_code":"NG",
    "gn:dem":509,
    "gn:feature_class":"P",
    "gn:feature_code":"PPL",
    "gn:name":"Ekinrin",
    "gn:population":0,
    "gn:timezone":"Africa/Lagos",
    "iso:country":"NG",
    "name:und_x_variant":[
        "Ikinri",
        "Ekinrin"
    ],
    "wof:name":"Ekinrin",
    "wof:placetype":"locality"
},
  "geometry": {"coordinates":[5.86635,7.83191],"type":"Point"}
}