{
  "type": "Feature",
  "properties": {
    "gn:admin1_code":"46.0",
    "gn:admin2_code":"5018.0",
    "gn:admin3_code":"BA1806",
    "gn:asciiname":"Feidi",
    "gn:country_code":"NG",
    "gn:dem":685,
    "gn:feature_class":"P",
    "gn:feature_code":"PPL",
    "gn:name":"Feidi",
    "gn:population":0,
    "gn:timezone":"Africa/Lagos",
    "iso:country":"NG",
    "name:und_x_variant":[
        "Feldi",
        "Feidi"
    ],
    "wof:name":"Feidi",
    "wof:placetype":"locality"
},
  "geometry": {"coordinates":[9.60265,10.22702],"type":"Point"}
}