{
  "type": "Feature",
  "properties": {
    "gn:admin1_code":"24.0",
    "gn:admin2_code":"418.0",
    "gn:admin3_code":"41804",
    "gn:asciiname":"Lalarni",
    "gn:country_code":"NG",
    "gn:dem":421,
    "gn:feature_class":"P",
    "gn:feature_code":"PPL",
    "gn:name":"Lalarni",
    "gn:population":0,
    "gn:timezone":"Africa/Lagos",
    "iso:country":"NG",
    "name:und_x_variant":[
        "Lalaini",
        "Lalarni"
    ],
    "wof:name":"Lalarni",
    "wof:placetype":"locality"
},
  "geometry": {"coordinates":[7.80783,13.28871],"type":"Point"}
}