{
  "type": "Feature",
  "properties": {
    "gn:admin1_code":"27.0",
    "gn:admin2_code":"112.0",
    "gn:admin3_code":"11206",
    "gn:asciiname":"Haran-Ali",
    "gn:country_code":"NG",
    "gn:dem":462,
    "gn:feature_class":"P",
    "gn:feature_code":"PPL",
    "gn:name":"Haran-Ali",
    "gn:population":0,
    "gn:timezone":"Africa/Lagos",
    "iso:country":"NG",
    "name:und_x_variant":[
        "Haran",
        "Haran-Ali"
    ],
    "wof:name":"Haran-Ali",
    "wof:placetype":"locality"
},
  "geometry": {"coordinates":[12.46695,10.56577],"type":"Point"}
}