{
  "type": "Feature",
  "properties": {
    "gn:admin1_code":"57.0",
    "gn:admin2_code":"808.0",
    "gn:admin3_code":"80802",
    "gn:asciiname":"Madawa",
    "gn:country_code":"NG",
    "gn:dem":413,
    "gn:feature_class":"P",
    "gn:feature_code":"PPL",
    "gn:name":"Madawa",
    "gn:population":0,
    "gn:timezone":"Africa/Lagos",
    "iso:country":"NG",
    "wof:name":"Madawa",
    "wof:placetype":"locality"
},
  "geometry": {"coordinates":[6.72429,12.37326],"type":"Point"}
}