{
  "type": "Feature",
  "properties": {
    "gn:admin1_code":"26.0",
    "gn:admin2_code":"7003.0",
    "gn:asciiname":"Odugbo",
    "gn:country_code":"NG",
    "gn:dem":119,
    "gn:feature_class":"P",
    "gn:feature_code":"PPL",
    "gn:name":"Odugbo",
    "gn:population":0,
    "gn:timezone":"Africa/Lagos",
    "iso:country":"NG",
    "wof:name":"Odugbo",
    "wof:placetype":"locality"
},
  "geometry": {"coordinates":[8.01165,7.64508],"type":"Point"}
}