{
  "type": "Feature",
  "properties": {
    "gn:admin1_code":"32.0",
    "gn:admin2_code":"31005.0",
    "gn:asciiname":"Ogundele",
    "gn:country_code":"NG",
    "gn:dem":206,
    "gn:feature_class":"P",
    "gn:feature_code":"PPL",
    "gn:name":"Ogundele",
    "gn:population":0,
    "gn:timezone":"Africa/Lagos",
    "iso:country":"NG",
    "wof:name":"Ogundele",
    "wof:placetype":"locality"
},
  "geometry": {"coordinates":[3.99028,7.37444],"type":"Point"}
}