{
  "type": "Feature",
  "properties": {
    "gn:admin1_code":"46.0",
    "gn:admin2_code":"5018.0",
    "gn:admin3_code":"BA1802",
    "gn:asciiname":"Deriko",
    "gn:country_code":"NG",
    "gn:dem":866,
    "gn:feature_class":"P",
    "gn:feature_code":"PPL",
    "gn:name":"Deriko",
    "gn:population":0,
    "gn:timezone":"Africa/Lagos",
    "iso:country":"NG",
    "wof:name":"Deriko",
    "wof:placetype":"locality"
},
  "geometry": {"coordinates":[8.99572,10.08342],"type":"Point"}
}