{
  "type": "Feature",
  "properties": {
    "gn:admin1_code":"52.0",
    "gn:admin2_code":"6001",
    "gn:asciiname":"Opuaba",
    "gn:country_code":"NG",
    "gn:dem":7,
    "gn:feature_class":"P",
    "gn:feature_code":"PPL",
    "gn:name":"Opuaba",
    "gn:population":0,
    "gn:timezone":"Africa/Lagos",
    "iso:country":"NG",
    "wof:name":"Opuaba",
    "wof:placetype":"locality"
},
  "geometry": {"coordinates":[6.09011,4.34828],"type":"Point"}
}