{
  "type": "Feature",
  "properties": {
    "gn:admin1_code":"29.0",
    "gn:admin2_code":"20040.0",
    "gn:admin3_code":"KN3007",
    "gn:asciiname":"Dingim",
    "gn:country_code":"NG",
    "gn:dem":443,
    "gn:feature_class":"P",
    "gn:feature_code":"PPL",
    "gn:name":"Dingim",
    "gn:population":0,
    "gn:timezone":"Africa/Lagos",
    "iso:country":"NG",
    "wof:name":"Dingim",
    "wof:placetype":"locality"
},
  "geometry": {"coordinates":[8.64823,12.16813],"type":"Point"}
}