{
  "type": "Feature",
  "properties": {
    "gn:admin1_code":"28.0",
    "gn:admin2_code":"17026.0",
    "gn:asciiname":"Emeabiam",
    "gn:country_code":"NG",
    "gn:dem":56,
    "gn:feature_class":"P",
    "gn:feature_code":"PPL",
    "gn:name":"Emeabiam",
    "gn:population":0,
    "gn:timezone":"Africa/Lagos",
    "iso:country":"NG",
    "wof:name":"Emeabiam",
    "wof:placetype":"locality"
},
  "geometry": {"coordinates":[6.9919,5.33406],"type":"Point"}
}