{
  "type": "Feature",
  "properties": {
    "gn:admin1_code":"31.0",
    "gn:admin2_code":"27005.0",
    "gn:asciiname":"Tunda Wada",
    "gn:country_code":"NG",
    "gn:dem":185,
    "gn:feature_class":"P",
    "gn:feature_code":"PPL",
    "gn:name":"Tunda Wada",
    "gn:population":0,
    "gn:timezone":"Africa/Lagos",
    "iso:country":"NG",
    "wof:name":"Tunda Wada",
    "wof:placetype":"locality"
},
  "geometry": {"coordinates":[6.25253,9.65397],"type":"Point"}
}