{
  "type": "Feature",
  "properties": {
    "gn:admin1_code":"46.0",
    "gn:admin2_code":"5010.0",
    "gn:admin3_code":"BA1008",
    "gn:asciiname":"Dingiri",
    "gn:country_code":"NG",
    "gn:dem":391,
    "gn:feature_class":"P",
    "gn:feature_code":"PPL",
    "gn:name":"Dingiri",
    "gn:population":0,
    "gn:timezone":"Africa/Lagos",
    "iso:country":"NG",
    "wof:name":"Dingiri",
    "wof:placetype":"locality"
},
  "geometry": {"coordinates":[9.66132,11.75664],"type":"Point"}
}