{
  "type": "Feature",
  "properties": {
    "gn:admin1_code":"53.0",
    "gn:admin2_code":"11010.0",
    "gn:asciiname":"Oji Egbe",
    "gn:country_code":"NG",
    "gn:dem":54,
    "gn:feature_class":"P",
    "gn:feature_code":"PPL",
    "gn:name":"Oji Egbe",
    "gn:population":0,
    "gn:timezone":"Africa/Lagos",
    "iso:country":"NG",
    "wof:name":"Oji Egbe",
    "wof:placetype":"locality"
},
  "geometry": {"coordinates":[8.30576,6.62412],"type":"Point"}
}