{
  "type": "Feature",
  "properties": {
    "gn:admin1_code":"27.0",
    "gn:admin2_code":"101.0",
    "gn:admin3_code":"10105",
    "gn:asciiname":"Bula Chesabe",
    "gn:country_code":"NG",
    "gn:dem":297,
    "gn:feature_class":"P",
    "gn:feature_code":"PPL",
    "gn:name":"Bula Chesabe",
    "gn:population":0,
    "gn:timezone":"Africa/Lagos",
    "iso:country":"NG",
    "wof:name":"Bula Chesabe",
    "wof:placetype":"locality"
},
  "geometry": {"coordinates":[13.13472,13.53593],"type":"Point"}
}