{
  "type": "Feature",
  "properties": {
    "gn:admin1_code":"50.0",
    "gn:admin2_code":"33011.0",
    "gn:asciiname":"Ibodo",
    "gn:country_code":"NG",
    "gn:dem":59,
    "gn:feature_class":"P",
    "gn:feature_code":"PPL",
    "gn:name":"Ibodo",
    "gn:population":0,
    "gn:timezone":"Africa/Lagos",
    "iso:country":"NG",
    "wof:name":"Ibodo",
    "wof:placetype":"locality"
},
  "geometry": {"coordinates":[7.16475,5.18091],"type":"Point"}
}