{
  "type": "Feature",
  "properties": {
    "gn:admin1_code":"41.0",
    "gn:admin2_code":"23006.0",
    "gn:asciiname":"Ogaine",
    "gn:country_code":"NG",
    "gn:dem":33,
    "gn:feature_class":"P",
    "gn:feature_code":"PPL",
    "gn:name":"Ogaine",
    "gn:population":0,
    "gn:timezone":"Africa/Lagos",
    "iso:country":"NG",
    "name:eng_x_preferred":[
        "Ogaine"
    ],
    "wof:name":"Ogaine",
    "wof:placetype":"locality"
},
  "geometry": {"coordinates":[6.67592,6.89874],"type":"Point"}
}