{
  "type": "Feature",
  "properties": {
    "gn:admin1_code":"23.0",
    "gn:admin2_code":"19014.0",
    "gn:admin3_code":"KD1409",
    "gn:asciiname":"New Kwasam",
    "gn:country_code":"NG",
    "gn:dem":756,
    "gn:feature_class":"P",
    "gn:feature_code":"PPL",
    "gn:name":"New Kwasam",
    "gn:population":0,
    "gn:timezone":"Africa/Lagos",
    "iso:country":"NG",
    "wof:name":"New Kwasam",
    "wof:placetype":"locality"
},
  "geometry": {"coordinates":[8.24114,10.34283],"type":"Point"}
}