{
  "type": "Feature",
  "properties": {
    "gn:admin1_code":"40.0",
    "gn:admin2_code":"501.0",
    "gn:admin3_code":"50109",
    "gn:asciiname":"Marmaro",
    "gn:country_code":"NG",
    "gn:dem":244,
    "gn:feature_class":"P",
    "gn:feature_code":"PPL",
    "gn:name":"Marmaro",
    "gn:population":0,
    "gn:timezone":"Africa/Lagos",
    "iso:country":"NG",
    "name:spa_x_preferred":[
        "M\u00e1rmaro"
    ],
    "wof:name":"Marmaro",
    "wof:placetype":"locality"
},
  "geometry": {"coordinates":[4.44716,12.36486],"type":"Point"}
}