{
  "type": "Feature",
  "properties": {
    "gn:admin1_code":"39.0",
    "gn:admin2_code":"18013.0",
    "gn:admin3_code":"JI0102",
    "gn:asciiname":"Hada",
    "gn:country_code":"NG",
    "gn:dem":364,
    "gn:feature_class":"P",
    "gn:feature_code":"PPL",
    "gn:name":"Hada",
    "gn:population":0,
    "gn:timezone":"Africa/Lagos",
    "iso:country":"NG",
    "wof:name":"Hada",
    "wof:placetype":"locality"
},
  "geometry": {"coordinates":[9.92133,12.36784],"type":"Point"}
}