{
  "type": "Feature",
  "properties": {
    "gn:admin1_code":"23.0",
    "gn:asciiname":"Katirje",
    "gn:country_code":"NG",
    "gn:dem":602,
    "gn:feature_class":"P",
    "gn:feature_code":"PPL",
    "gn:name":"Katirje",
    "gn:population":0,
    "gn:timezone":"Africa/Lagos",
    "iso:country":"NG",
    "wof:name":"Katirje",
    "wof:placetype":"locality"
},
  "geometry": {"coordinates":[8.51477,11.19115],"type":"Point"}
}