{
  "type": "Feature",
  "properties": {
    "gn:admin1_code":"40.0",
    "gn:admin2_code":"503.0",
    "gn:admin3_code":"50309",
    "gn:asciiname":"Bagoni",
    "gn:country_code":"NG",
    "gn:dem":225,
    "gn:feature_class":"P",
    "gn:feature_code":"PPL",
    "gn:name":"Bagoni",
    "gn:population":0,
    "gn:timezone":"Africa/Lagos",
    "iso:country":"NG",
    "wof:name":"Bagoni",
    "wof:placetype":"locality"
},
  "geometry": {"coordinates":[4.47563,12.81636],"type":"Point"}
}