{
  "type": "Feature",
  "properties": {
    "gn:admin1_code":"24.0",
    "gn:admin2_code":"434.0",
    "gn:admin3_code":"43407",
    "gn:asciiname":"Ngorgege",
    "gn:country_code":"NG",
    "gn:dem":461,
    "gn:feature_class":"P",
    "gn:feature_code":"PPL",
    "gn:name":"Ngorgege",
    "gn:population":0,
    "gn:timezone":"Africa/Lagos",
    "iso:country":"NG",
    "wof:name":"Ngorgege",
    "wof:placetype":"locality"
},
  "geometry": {"coordinates":[8.54678,12.90565],"type":"Point"}
}