{
  "type": "Feature",
  "properties": {
    "gn:admin1_code":"16.0",
    "gn:admin2_code":"28005.0",
    "gn:asciiname":"Olorunda",
    "gn:country_code":"NG",
    "gn:dem":88,
    "gn:feature_class":"P",
    "gn:feature_code":"PPL",
    "gn:name":"Olorunda",
    "gn:population":0,
    "gn:timezone":"Africa/Lagos",
    "iso:country":"NG",
    "wof:name":"Olorunda",
    "wof:placetype":"locality"
},
  "geometry": {"coordinates":[2.98333,6.78333],"type":"Point"}
}