{
  "type": "Feature",
  "properties": {
    "gn:admin1_code":"50.0",
    "gn:admin2_code":"33022.0",
    "gn:asciiname":"Oroworokwo",
    "gn:country_code":"NG",
    "gn:dem":16,
    "gn:feature_class":"P",
    "gn:feature_code":"PPL",
    "gn:name":"Oroworokwo",
    "gn:population":0,
    "gn:timezone":"Africa/Lagos",
    "iso:country":"NG",
    "wof:name":"Oroworokwo",
    "wof:placetype":"locality"
},
  "geometry": {"coordinates":[7.02105,4.81046],"type":"Point"}
}