{
  "type": "Feature",
  "properties": {
    "gn:admin1_code":"27.0",
    "gn:admin2_code":"111.0",
    "gn:admin3_code":"11107",
    "gn:asciiname":"Santow",
    "gn:country_code":"NG",
    "gn:dem":419,
    "gn:feature_class":"P",
    "gn:feature_code":"PPL",
    "gn:name":"Santow",
    "gn:population":0,
    "gn:timezone":"Africa/Lagos",
    "iso:country":"NG",
    "name:und_x_variant":[
        "Sandau",
        "Santow"
    ],
    "wof:name":"Santow",
    "wof:placetype":"locality"
},
  "geometry": {"coordinates":[13.44531,11.01676],"type":"Point"}
}