{
  "type": "Feature",
  "properties": {
    "gn:admin1_code":"22.0",
    "gn:admin2_code":"9008.0",
    "gn:asciiname":"Ikot Enebong",
    "gn:country_code":"NG",
    "gn:dem":71,
    "gn:feature_class":"P",
    "gn:feature_code":"PPL",
    "gn:name":"Ikot Enebong",
    "gn:population":0,
    "gn:timezone":"Africa/Lagos",
    "iso:country":"NG",
    "wof:name":"Ikot Enebong",
    "wof:placetype":"locality"
},
  "geometry": {"coordinates":[8.36206,5.05172],"type":"Point"}
}