{
  "type": "Feature",
  "properties": {
    "gn:admin1_code":"23.0",
    "gn:admin2_code":"19001.0",
    "gn:admin3_code":"KD0104",
    "gn:asciiname":"Dagara",
    "gn:country_code":"NG",
    "gn:dem":412,
    "gn:feature_class":"P",
    "gn:feature_code":"PPL",
    "gn:name":"Dagara",
    "gn:population":0,
    "gn:timezone":"Africa/Lagos",
    "iso:country":"NG",
    "name:und_x_variant":[
        "Dogara",
        "Dagara"
    ],
    "wof:name":"Dagara",
    "wof:placetype":"locality"
},
  "geometry": {"coordinates":[6.40101,10.7295],"type":"Point"}
}