{
  "type": "Feature",
  "properties": {
    "gn:admin1_code":"56.0",
    "gn:admin2_code":"26011.0",
    "gn:asciiname":"Huwe",
    "gn:country_code":"NG",
    "gn:dem":218,
    "gn:feature_class":"P",
    "gn:feature_code":"PPL",
    "gn:name":"Huwe",
    "gn:population":0,
    "gn:timezone":"Africa/Lagos",
    "iso:country":"NG",
    "wof:name":"Huwe",
    "wof:placetype":"locality"
},
  "geometry": {"coordinates":[8.98333,8.33333],"type":"Point"}
}