{
  "type": "Feature",
  "properties": {
    "gn:admin1_code":"27.0",
    "gn:admin2_code":"111.0",
    "gn:admin3_code":"11109",
    "gn:asciiname":"Daure",
    "gn:country_code":"NG",
    "gn:dem":375,
    "gn:feature_class":"P",
    "gn:feature_code":"PPL",
    "gn:name":"Daure",
    "gn:population":0,
    "gn:timezone":"Africa/Lagos",
    "iso:country":"NG",
    "wof:name":"Daure",
    "wof:placetype":"locality"
},
  "geometry": {"coordinates":[13.8967,11.21637],"type":"Point"}
}