{
  "type": "Feature",
  "properties": {
    "gn:admin1_code":"51.0",
    "gn:admin2_code":"610.0",
    "gn:admin3_code":"61001",
    "gn:asciiname":"Bindanu",
    "gn:country_code":"NG",
    "gn:dem":193,
    "gn:feature_class":"P",
    "gn:feature_code":"PPL",
    "gn:name":"Bindanu",
    "gn:population":0,
    "gn:timezone":"Africa/Lagos",
    "iso:country":"NG",
    "wof:name":"Bindanu",
    "wof:placetype":"locality"
},
  "geometry": {"coordinates":[4.51044,11.63154],"type":"Point"}
}