{
  "type": "Feature",
  "properties": {
    "gn:admin1_code":"21.0",
    "gn:admin2_code":"3016.0",
    "gn:asciiname":"Nung Ukot",
    "gn:country_code":"NG",
    "gn:dem":72,
    "gn:feature_class":"P",
    "gn:feature_code":"PPL",
    "gn:name":"Nung Ukot",
    "gn:population":0,
    "gn:timezone":"Africa/Lagos",
    "iso:country":"NG",
    "wof:name":"Nung Ukot",
    "wof:placetype":"locality"
},
  "geometry": {"coordinates":[7.90203,5.05002],"type":"Point"}
}