{
  "type": "Feature",
  "properties": {
    "gn:admin1_code":"31.0",
    "gn:admin2_code":"27008",
    "gn:asciiname":"Kochikota Hill",
    "gn:country_code":"NG",
    "gn:dem":220,
    "gn:feature_class":"P",
    "gn:feature_code":"PPL",
    "gn:name":"Kochikota Hill",
    "gn:population":0,
    "gn:timezone":"Africa/Lagos",
    "iso:country":"NG",
    "wof:name":"Kochikota Hill",
    "wof:placetype":"locality"
},
  "geometry": {"coordinates":[6.04786,9.12448],"type":"Point"}
}