{
  "type": "Feature",
  "properties": {
    "gn:admin1_code":"44.0",
    "gn:admin2_code":"710.0",
    "gn:admin3_code":"71005",
    "gn:asciiname":"Gassima",
    "gn:country_code":"NG",
    "gn:dem":338,
    "gn:feature_class":"P",
    "gn:feature_code":"PPL",
    "gn:name":"Gassima",
    "gn:population":0,
    "gn:timezone":"Africa/Lagos",
    "iso:country":"NG",
    "wof:name":"Gassima",
    "wof:placetype":"locality"
},
  "geometry": {"coordinates":[11.00848,12.90503],"type":"Point"}
}