{
  "type": "Feature",
  "properties": {
    "gn:admin1_code":"29.0",
    "gn:admin2_code":"20025.0",
    "gn:admin3_code":"KN0406",
    "gn:asciiname":"Gargai",
    "gn:country_code":"NG",
    "gn:dem":539,
    "gn:feature_class":"P",
    "gn:feature_code":"PPL",
    "gn:name":"Gargai",
    "gn:population":0,
    "gn:timezone":"Africa/Lagos",
    "iso:country":"NG",
    "wof:name":"Gargai",
    "wof:placetype":"locality"
},
  "geometry": {"coordinates":[8.38586,11.54385],"type":"Point"}
}