{
  "type": "Feature",
  "properties": {
    "gn:admin1_code":"36.0",
    "gn:admin2_code":"10004.0",
    "gn:asciiname":"Edegbene",
    "gn:country_code":"NG",
    "gn:dem":16,
    "gn:feature_class":"P",
    "gn:feature_code":"PPL",
    "gn:name":"Edegbene",
    "gn:population":0,
    "gn:timezone":"Africa/Lagos",
    "iso:country":"NG",
    "name:und_x_variant":[
        "Idegbene",
        "Edegbene"
    ],
    "wof:name":"Edegbene",
    "wof:placetype":"locality"
},
  "geometry": {"coordinates":[5.69684,5.14804],"type":"Point"}
}