{
  "type": "Feature",
  "properties": {
    "gn:admin1_code":"23.0",
    "gn:admin2_code":"19003.0",
    "gn:admin3_code":"KD0307",
    "gn:asciiname":"Ungwan Kanawa",
    "gn:country_code":"NG",
    "gn:dem":631,
    "gn:feature_class":"P",
    "gn:feature_code":"PPL",
    "gn:name":"Ungwan Kanawa",
    "gn:population":0,
    "gn:timezone":"Africa/Lagos",
    "iso:country":"NG",
    "wof:name":"Ungwan Kanawa",
    "wof:placetype":"locality"
},
  "geometry": {"coordinates":[7.2196,11.06021],"type":"Point"}
}