{
  "type": "Feature",
  "properties": {
    "gn:admin1_code":"45.0",
    "gn:admin2_code":"1008.0",
    "gn:asciiname":"Isi-Ikwuato",
    "gn:country_code":"NG",
    "gn:dem":178,
    "gn:feature_class":"P",
    "gn:feature_code":"PPL",
    "gn:name":"Isi-Ikwuato",
    "gn:population":0,
    "gn:timezone":"Africa/Lagos",
    "iso:country":"NG",
    "wof:name":"Isi-Ikwuato",
    "wof:placetype":"locality"
},
  "geometry": {"coordinates":[7.50226,5.73985],"type":"Point"}
}