{
  "type": "Feature",
  "properties": {
    "gn:admin1_code":"23.0",
    "gn:admin2_code":"19011",
    "gn:admin3_code":"KD1110",
    "gn:asciiname":"Dogon Kurmi",
    "gn:country_code":"NG",
    "gn:dem":644,
    "gn:feature_class":"P",
    "gn:feature_code":"PPL",
    "gn:name":"Dogon Kurmi",
    "gn:population":0,
    "gn:timezone":"Africa/Lagos",
    "iso:country":"NG",
    "wof:name":"Dogon Kurmi",
    "wof:placetype":"locality"
},
  "geometry": {"coordinates":[7.77378,9.44819],"type":"Point"}
}