{
  "type": "Feature",
  "properties": {
    "gn:admin1_code":"32.0",
    "gn:admin2_code":"31014.0",
    "gn:asciiname":"Eresu",
    "gn:country_code":"NG",
    "gn:dem":183,
    "gn:feature_class":"P",
    "gn:feature_code":"PPL",
    "gn:name":"Eresu",
    "gn:population":0,
    "gn:timezone":"Africa/Lagos",
    "iso:country":"NG",
    "wof:name":"Eresu",
    "wof:placetype":"neighbourhood"
},
  "geometry": {"coordinates":[3.76833,7.36472],"type":"Point"}
}