{
  "type": "Feature",
  "properties": {
    "gn:admin1_code":"40.0",
    "gn:admin2_code":"505.0",
    "gn:admin3_code":"50510",
    "gn:asciiname":"Tungan Yero",
    "gn:country_code":"NG",
    "gn:dem":160,
    "gn:feature_class":"P",
    "gn:feature_code":"PPL",
    "gn:name":"Tungan Yero",
    "gn:population":0,
    "gn:timezone":"Africa/Lagos",
    "iso:country":"NG",
    "wof:name":"Tungan Yero",
    "wof:placetype":"locality"
},
  "geometry": {"coordinates":[4.16204,11.62788],"type":"Point"}
}