{
  "type": "Feature",
  "properties": {
    "gn:admin1_code":"53.0",
    "gn:admin2_code":"11002.0",
    "gn:asciiname":"Amuro",
    "gn:country_code":"NG",
    "gn:dem":67,
    "gn:feature_class":"P",
    "gn:feature_code":"PPL",
    "gn:name":"Amuro",
    "gn:population":0,
    "gn:timezone":"Africa/Lagos",
    "iso:country":"NG",
    "name:deu_x_preferred":[
        "Amuro"
    ],
    "name:kor_x_preferred":[
        "\uc544\ubb34\ub85c"
    ],
    "wof:name":"Amuro",
    "wof:placetype":"neighbourhood"
},
  "geometry": {"coordinates":[7.93464,5.88586],"type":"Point"}
}