{
  "type": "Feature",
  "properties": {
    "gn:admin1_code":"26.0",
    "gn:admin2_code":"7021",
    "gn:asciiname":"Lanshima",
    "gn:country_code":"NG",
    "gn:dem":142,
    "gn:feature_class":"P",
    "gn:feature_code":"PPL",
    "gn:name":"Lanshima",
    "gn:population":0,
    "gn:timezone":"Africa/Lagos",
    "iso:country":"NG",
    "wof:name":"Lanshima",
    "wof:placetype":"locality"
},
  "geometry": {"coordinates":[9.68602,7.72059],"type":"Point"}
}