{
  "type": "Feature",
  "properties": {
    "gn:admin1_code":"24.0",
    "gn:admin2_code":"414.0",
    "gn:admin3_code":"41411",
    "gn:asciiname":"Ungwan Mai Laya",
    "gn:country_code":"NG",
    "gn:dem":655,
    "gn:feature_class":"P",
    "gn:feature_code":"PPL",
    "gn:name":"Ungwan Mai Laya",
    "gn:population":0,
    "gn:timezone":"Africa/Lagos",
    "iso:country":"NG",
    "wof:name":"Ungwan Mai Laya",
    "wof:placetype":"locality"
},
  "geometry": {"coordinates":[7.34002,11.29906],"type":"Point"}
}