{
  "type": "Feature",
  "properties": {
    "gn:admin1_code":"35.0",
    "gn:admin2_code":"2002.0",
    "gn:asciiname":"Mayo Jeyi",
    "gn:country_code":"NG",
    "gn:dem":466,
    "gn:feature_class":"P",
    "gn:feature_code":"PPL",
    "gn:name":"Mayo Jeyi",
    "gn:population":0,
    "gn:timezone":"Africa/Lagos",
    "iso:country":"NG",
    "wof:name":"Mayo Jeyi",
    "wof:placetype":"locality"
},
  "geometry": {"coordinates":[12.46333,8.88424],"type":"Point"}
}