{
  "type": "Feature",
  "properties": {
    "gn:admin1_code":"39.0",
    "gn:admin2_code":"18016.0",
    "gn:admin3_code":"JI0710",
    "gn:asciiname":"Gamji",
    "gn:country_code":"NG",
    "gn:dem":368,
    "gn:feature_class":"P",
    "gn:feature_code":"PPL",
    "gn:name":"Gamji",
    "gn:population":0,
    "gn:timezone":"Africa/Lagos",
    "iso:country":"NG",
    "wof:name":"Gamji",
    "wof:placetype":"locality"
},
  "geometry": {"coordinates":[9.4668,12.58295],"type":"Point"}
}