{
  "type": "Feature",
  "properties": {
    "gn:admin1_code":"53.0",
    "gn:admin2_code":"11004",
    "gn:asciiname":"Okoria-Nkaliki",
    "gn:country_code":"NG",
    "gn:dem":64,
    "gn:feature_class":"P",
    "gn:feature_code":"PPL",
    "gn:name":"Okoria-Nkaliki",
    "gn:population":0,
    "gn:timezone":"Africa/Lagos",
    "iso:country":"NG",
    "wof:name":"Okoria-Nkaliki",
    "wof:placetype":"locality"
},
  "geometry": {"coordinates":[8.13377,6.41028],"type":"Point"}
}