{
  "type": "Feature",
  "properties": {
    "gn:admin1_code":"43.0",
    "gn:admin2_code":"35009.0",
    "gn:asciiname":"Overe",
    "gn:country_code":"NG",
    "gn:dem":253,
    "gn:feature_class":"P",
    "gn:feature_code":"PPL",
    "gn:name":"Overe",
    "gn:population":0,
    "gn:timezone":"Africa/Lagos",
    "iso:country":"NG",
    "wof:name":"Overe",
    "wof:placetype":"locality"
},
  "geometry": {"coordinates":[10.54482,7.33734],"type":"Point"}
}