{
  "type": "Feature",
  "properties": {
    "gn:admin1_code":"52.0",
    "gn:admin2_code":"6007.0",
    "gn:asciiname":"Ekiambiri",
    "gn:country_code":"NG",
    "gn:dem":2,
    "gn:feature_class":"P",
    "gn:feature_code":"PPL",
    "gn:name":"Ekiambiri",
    "gn:population":0,
    "gn:timezone":"Africa/Lagos",
    "iso:country":"NG",
    "name:und_x_variant":[
        "Ikianbiri",
        "Ekiambiri"
    ],
    "wof:name":"Ekiambiri",
    "wof:placetype":"locality"
},
  "geometry": {"coordinates":[6.09551,4.66533],"type":"Point"}
}