{
  "type": "Feature",
  "properties": {
    "gn:admin1_code":"23.0",
    "gn:admin2_code":"19008.0",
    "gn:admin3_code":"KD0803",
    "gn:asciiname":"Awan",
    "gn:country_code":"NG",
    "gn:dem":671,
    "gn:feature_class":"P",
    "gn:feature_code":"PPL",
    "gn:name":"Awan",
    "gn:population":0,
    "gn:timezone":"Africa/Lagos",
    "iso:country":"NG",
    "name:ceb_x_preferred":[
        "Awan"
    ],
    "name:deu_x_preferred":[
        "Awan"
    ],
    "name:nld_x_preferred":[
        "Awan"
    ],
    "name:rus_x_preferred":[
        "\u0410\u0432\u0430\u043d"
    ],
    "name:spa_x_preferred":[
        "Awan"
    ],
    "name:swe_x_preferred":[
        "Awan"
    ],
    "name:und_x_variant":[
        "Awam"
    ],
    "wof:name":"Awan",
    "wof:placetype":"locality"
},
  "geometry": {"coordinates":[7.78376,9.78634],"type":"Point"}
}