{
  "type": "Feature",
  "properties": {
    "gn:admin1_code":"31.0",
    "gn:admin2_code":"27013",
    "gn:asciiname":"Bokungi",
    "gn:country_code":"NG",
    "gn:dem":186,
    "gn:feature_class":"P",
    "gn:feature_code":"PPL",
    "gn:name":"Bokungi",
    "gn:population":0,
    "gn:timezone":"Africa/Lagos",
    "iso:country":"NG",
    "wof:name":"Bokungi",
    "wof:placetype":"locality"
},
  "geometry": {"coordinates":[5.56992,9.14848],"type":"Point"}
}