{
  "type": "Feature",
  "properties": {
    "gn:admin1_code":"39.0",
    "gn:admin2_code":"18024.0",
    "gn:admin3_code":"JI0810",
    "gn:asciiname":"Tagwaye",
    "gn:country_code":"NG",
    "gn:dem":381,
    "gn:feature_class":"P",
    "gn:feature_code":"PPL",
    "gn:name":"Tagwaye",
    "gn:population":0,
    "gn:timezone":"Africa/Lagos",
    "iso:country":"NG",
    "wof:name":"Tagwaye",
    "wof:placetype":"locality"
},
  "geometry": {"coordinates":[9.05039,12.45224],"type":"Point"}
}