{
  "type": "Feature",
  "properties": {
    "gn:admin1_code":"35.0",
    "gn:asciiname":"Tumum Daran",
    "gn:country_code":"NG",
    "gn:dem":239,
    "gn:feature_class":"P",
    "gn:feature_code":"PPL",
    "gn:name":"Tumum Daran",
    "gn:population":0,
    "gn:timezone":"Africa/Lagos",
    "iso:country":"NG",
    "name:eng_x_preferred":[
        "Tumum Daran"
    ],
    "wof:name":"Tumum Daran",
    "wof:placetype":"locality"
},
  "geometry": {"coordinates":[11.93206,9.28939],"type":"Point"}
}