{
  "type": "Feature",
  "properties": {
    "gn:admin1_code":"31.0",
    "gn:admin2_code":"27022.0",
    "gn:asciiname":"Gidan Galadima",
    "gn:country_code":"NG",
    "gn:dem":332,
    "gn:feature_class":"P",
    "gn:feature_code":"PPL",
    "gn:name":"Gidan Galadima",
    "gn:population":0,
    "gn:timezone":"Africa/Lagos",
    "iso:country":"NG",
    "wof:name":"Gidan Galadima",
    "wof:placetype":"locality"
},
  "geometry": {"coordinates":[6.81374,10.01233],"type":"Point"}
}