{
  "type": "Feature",
  "properties": {
    "gn:admin1_code":"30.0",
    "gn:admin2_code":"24002.0",
    "gn:asciiname":"Moshi",
    "gn:country_code":"NG",
    "gn:dem":300,
    "gn:feature_class":"P",
    "gn:feature_code":"PPL",
    "gn:name":"Moshi",
    "gn:population":0,
    "gn:timezone":"Africa/Lagos",
    "iso:country":"NG",
    "name:ceb_x_preferred":[
        "Moshi"
    ],
    "name:swa_x_preferred":[
        "Moshi"
    ],
    "name:swe_x_preferred":[
        "Moshi"
    ],
    "name:ukr_x_preferred":[
        "\u041c\u043e\u0448\u0456"
    ],
    "wof:name":"Moshi",
    "wof:placetype":"locality"
},
  "geometry": {"coordinates":[3.75,9.21667],"type":"Point"}
}