{
  "type": "Feature",
  "properties": {
    "gn:admin1_code":"29.0",
    "gn:admin2_code":"20034.0",
    "gn:admin3_code":"KN2402",
    "gn:asciiname":"Gidan Buhari",
    "gn:country_code":"NG",
    "gn:dem":594,
    "gn:feature_class":"P",
    "gn:feature_code":"PPL",
    "gn:name":"Gidan Buhari",
    "gn:population":0,
    "gn:timezone":"Africa/Lagos",
    "iso:country":"NG",
    "name:und_x_variant":[
        "Buhari",
        "Gidan Buhari"
    ],
    "wof:name":"Gidan Buhari",
    "wof:placetype":"locality"
},
  "geometry": {"coordinates":[8.25082,11.4148],"type":"Point"}
}