{
  "type": "Feature",
  "properties": {
    "gn:admin1_code":"16.0",
    "gn:admin2_code":"28003.0",
    "gn:asciiname":"Olowu",
    "gn:country_code":"NG",
    "gn:dem":46,
    "gn:feature_class":"P",
    "gn:feature_code":"PPL",
    "gn:name":"Olowu",
    "gn:population":0,
    "gn:timezone":"Africa/Lagos",
    "iso:country":"NG",
    "name:deu_x_preferred":[
        "Olowu"
    ],
    "wof:name":"Olowu",
    "wof:placetype":"locality"
},
  "geometry": {"coordinates":[3.02014,6.69066],"type":"Point"}
}