{
  "type": "Feature",
  "properties": {
    "gn:admin1_code":"27.0",
    "gn:admin2_code":"105.0",
    "gn:admin3_code":"10511",
    "gn:asciiname":"Waka",
    "gn:country_code":"NG",
    "gn:dem":711,
    "gn:feature_class":"P",
    "gn:feature_code":"PPL",
    "gn:name":"Waka",
    "gn:population":0,
    "gn:timezone":"Africa/Lagos",
    "iso:country":"NG",
    "name:arg_x_preferred":[
        "Waka"
    ],
    "name:bul_x_preferred":[
        "\u0412\u0430\u043a\u0430"
    ],
    "name:ceb_x_preferred":[
        "Waka"
    ],
    "name:deu_x_preferred":[
        "Waka"
    ],
    "name:fra_x_preferred":[
        "Waka"
    ],
    "name:heb_x_preferred":[
        "\u05d5\u05d0\u05e7\u05d4"
    ],
    "name:ind_x_preferred":[
        "Waka"
    ],
    "name:mri_x_preferred":[
        "Waka"
    ],
    "name:nds_x_preferred":[
        "Waka"
    ],
    "name:nld_x_preferred":[
        "Waka"
    ],
    "name:nor_x_preferred":[
        "Waka"
    ],
    "name:pol_x_preferred":[
        "Waka"
    ],
    "name:por_x_preferred":[
        "Waka"
    ],
    "name:rus_x_preferred":[
        "\u0412\u0430\u043a\u0430"
    ],
    "name:spa_x_preferred":[
        "Waka"
    ],
    "name:swe_x_preferred":[
        "Waka"
    ],
    "name:ukr_x_preferred":[
        "\u0412\u0430\u043a\u0430"
    ],
    "wof:name":"Waka",
    "wof:placetype":"locality"
},
  "geometry": {"coordinates":[12.19741,10.63728],"type":"Point"}
}