{
  "type": "Feature",
  "properties": {
    "gn:admin1_code":"31.0",
    "gn:admin2_code":"27008.0",
    "gn:asciiname":"Yabatagi",
    "gn:country_code":"NG",
    "gn:dem":136,
    "gn:feature_class":"P",
    "gn:feature_code":"PPL",
    "gn:name":"Yabatagi",
    "gn:population":0,
    "gn:timezone":"Africa/Lagos",
    "iso:country":"NG",
    "wof:name":"Yabatagi",
    "wof:placetype":"locality"
},
  "geometry": {"coordinates":[6.03478,9.31439],"type":"Point"}
}