{
  "type": "Feature",
  "properties": {
    "gn:admin1_code":"27.0",
    "gn:admin2_code":"105.0",
    "gn:admin3_code":"10506",
    "gn:asciiname":"Mangada",
    "gn:country_code":"NG",
    "gn:dem":670,
    "gn:feature_class":"P",
    "gn:feature_code":"PPL",
    "gn:name":"Mangada",
    "gn:population":0,
    "gn:timezone":"Africa/Lagos",
    "iso:country":"NG",
    "wof:name":"Mangada",
    "wof:placetype":"locality"
},
  "geometry": {"coordinates":[12.12752,10.81167],"type":"Point"}
}