{
  "type": "Feature",
  "properties": {
    "gn:admin1_code":"16.0",
    "gn:admin2_code":"28006.0",
    "gn:asciiname":"Ogbaga",
    "gn:country_code":"NG",
    "gn:dem":119,
    "gn:feature_class":"P",
    "gn:feature_code":"PPL",
    "gn:name":"Ogbaga",
    "gn:population":0,
    "gn:timezone":"Africa/Lagos",
    "iso:country":"NG",
    "wof:name":"Ogbaga",
    "wof:placetype":"locality"
},
  "geometry": {"coordinates":[3.14662,6.87275],"type":"Point"}
}