{
  "type": "Feature",
  "properties": {
    "gn:admin1_code":"23.0",
    "gn:admin2_code":"19004.0",
    "gn:admin3_code":"KD0401",
    "gn:asciiname":"Turunku",
    "gn:country_code":"NG",
    "gn:dem":614,
    "gn:feature_class":"P",
    "gn:feature_code":"PPL",
    "gn:name":"Turunku",
    "gn:population":0,
    "gn:timezone":"Africa/Lagos",
    "iso:country":"NG",
    "wof:name":"Turunku",
    "wof:placetype":"locality"
},
  "geometry": {"coordinates":[7.34511,10.64621],"type":"Point"}
}