{
  "type": "Feature",
  "properties": {
    "gn:country":"NG",
    "gn:fcode":"PPL",
    "gn:pop":6123,
    "iso:country":"NG",
    "name:unk_x_variant":[
        "Bununu"
    ],
    "qs:name":"Bununu Kasa",
    "qs:photos_9r":0,
    "qs:photos_sr":0,
    "qs:pop_sr":"5",
    "wof:name":"Bununu Kasa",
    "wof:placetype":"locality",
    "wof:population":6123
},
  "geometry": {"coordinates":[9.66278,9.86806],"type":"Point"}
}