{
  "type": "Feature",
  "properties": {
    "gn:admin1_code":"48.0",
    "gn:admin2_code":"29016.0",
    "gn:asciiname":"Igunsin",
    "gn:country_code":"NG",
    "gn:dem":262,
    "gn:feature_class":"P",
    "gn:feature_code":"PPL",
    "gn:name":"Igunsin",
    "gn:population":0,
    "gn:timezone":"Africa/Lagos",
    "iso:country":"NG",
    "name:und_x_variant":[
        "Igunshin",
        "Igunsin"
    ],
    "wof:name":"Igunsin",
    "wof:placetype":"locality"
},
  "geometry": {"coordinates":[4.85601,6.9574],"type":"Point"}
}