{
  "type": "Feature",
  "properties": {
    "gn:admin1_code":"48.0",
    "gn:admin2_code":"29002.0",
    "gn:asciiname":"Ibarram",
    "gn:country_code":"NG",
    "gn:dem":364,
    "gn:feature_class":"P",
    "gn:feature_code":"PPL",
    "gn:name":"Ibarram",
    "gn:population":0,
    "gn:timezone":"Africa/Lagos",
    "iso:country":"NG",
    "wof:name":"Ibarram",
    "wof:placetype":"locality"
},
  "geometry": {"coordinates":[5.84729,7.59752],"type":"Point"}
}