{
  "type": "Feature",
  "properties": {
    "gn:admin1_code":"27.0",
    "gn:admin2_code":"120.0",
    "gn:admin3_code":"12001",
    "gn:asciiname":"Ligagin",
    "gn:country_code":"NG",
    "gn:dem":329,
    "gn:feature_class":"P",
    "gn:feature_code":"PPL",
    "gn:name":"Ligagin",
    "gn:population":0,
    "gn:timezone":"Africa/Lagos",
    "iso:country":"NG",
    "wof:name":"Ligagin",
    "wof:placetype":"locality"
},
  "geometry": {"coordinates":[12.72443,12.16404],"type":"Point"}
}