{
  "type": "Feature",
  "properties": {
    "gn:admin1_code":"26.0",
    "gn:admin2_code":"7011.0",
    "gn:asciiname":"Asham",
    "gn:country_code":"NG",
    "gn:dem":248,
    "gn:feature_class":"P",
    "gn:feature_code":"PPL",
    "gn:name":"Asham",
    "gn:population":0,
    "gn:timezone":"Africa/Lagos",
    "iso:country":"NG",
    "name:deu_x_preferred":[
        "Asham"
    ],
    "wof:name":"Asham",
    "wof:placetype":"locality"
},
  "geometry": {"coordinates":[9.22089,6.70733],"type":"Point"}
}