{
  "type": "Feature",
  "properties": {
    "gn:admin1_code":"44.0",
    "gn:admin2_code":"705.0",
    "gn:admin3_code":"70514",
    "gn:asciiname":"Ngarbia",
    "gn:country_code":"NG",
    "gn:dem":380,
    "gn:feature_class":"P",
    "gn:feature_code":"PPL",
    "gn:name":"Ngarbia",
    "gn:population":0,
    "gn:timezone":"Africa/Lagos",
    "iso:country":"NG",
    "wof:name":"Ngarbia",
    "wof:placetype":"locality"
},
  "geometry": {"coordinates":[11.2324,11.9754],"type":"Point"}
}