{
  "type": "Feature",
  "properties": {
    "gn:admin1_code":"29.0",
    "gn:admin2_code":"20025.0",
    "gn:admin3_code":"KN0407",
    "gn:asciiname":"Dundu",
    "gn:country_code":"NG",
    "gn:dem":589,
    "gn:feature_class":"P",
    "gn:feature_code":"PPL",
    "gn:name":"Dundu",
    "gn:population":0,
    "gn:timezone":"Africa/Lagos",
    "iso:country":"NG",
    "wof:name":"Dundu",
    "wof:placetype":"locality"
},
  "geometry": {"coordinates":[8.22851,11.45523],"type":"Point"}
}