{
  "type": "Feature",
  "properties": {
    "gn:admin1_code":"5.0",
    "gn:admin2_code":"25012.0",
    "gn:asciiname":"Igbopa",
    "gn:country_code":"NG",
    "gn:dem":3,
    "gn:feature_class":"P",
    "gn:feature_code":"PPL",
    "gn:name":"Igbopa",
    "gn:population":0,
    "gn:timezone":"Africa/Lagos",
    "iso:country":"NG",
    "name:und_x_variant":[
        "Ibopa",
        "Igbopa"
    ],
    "wof:name":"Igbopa",
    "wof:placetype":"neighbourhood"
},
  "geometry": {"coordinates":[3.5192,6.54608],"type":"Point"}
}