{
  "type": "Feature",
  "properties": {
    "gn:admin1_code":"39.0",
    "gn:admin2_code":"18026.0",
    "gn:admin3_code":"JI1411",
    "gn:asciiname":"Kanwa",
    "gn:country_code":"NG",
    "gn:dem":390,
    "gn:feature_class":"P",
    "gn:feature_code":"PPL",
    "gn:name":"Kanwa",
    "gn:population":0,
    "gn:timezone":"Africa/Lagos",
    "iso:country":"NG",
    "wof:name":"Kanwa",
    "wof:placetype":"locality"
},
  "geometry": {"coordinates":[9.45,11.95],"type":"Point"}
}