{
  "type": "Feature",
  "properties": {
    "gn:admin1_code":"55.0",
    "gn:admin2_code":"16004.0",
    "gn:asciiname":"Shuwe",
    "gn:country_code":"NG",
    "gn:dem":486,
    "gn:feature_class":"P",
    "gn:feature_code":"PPL",
    "gn:name":"Shuwe",
    "gn:population":0,
    "gn:timezone":"Africa/Lagos",
    "iso:country":"NG",
    "name:eng_x_preferred":[
        "Shuwe"
    ],
    "wof:name":"Shuwe",
    "wof:placetype":"locality"
},
  "geometry": {"coordinates":[10.87658,10.70532],"type":"Point"}
}