{
  "type": "Feature",
  "properties": {
    "gn:admin1_code":"26.0",
    "gn:admin2_code":"7009",
    "gn:asciiname":"Tse Animbe",
    "gn:country_code":"NG",
    "gn:dem":206,
    "gn:feature_class":"P",
    "gn:feature_code":"PPL",
    "gn:name":"Tse Animbe",
    "gn:population":0,
    "gn:timezone":"Africa/Lagos",
    "iso:country":"NG",
    "wof:name":"Tse Animbe",
    "wof:placetype":"locality"
},
  "geometry": {"coordinates":[9.49742,7.45113],"type":"Point"}
}