{
  "type": "Feature",
  "properties": {
    "gn:admin1_code":"32.0",
    "gn:admin2_code":"31013.0",
    "gn:asciiname":"Itobalogo Iju",
    "gn:country_code":"NG",
    "gn:dem":186,
    "gn:feature_class":"P",
    "gn:feature_code":"PPL",
    "gn:name":"Itobalogo Iju",
    "gn:population":0,
    "gn:timezone":"Africa/Lagos",
    "iso:country":"NG",
    "wof:name":"Itobalogo Iju",
    "wof:placetype":"locality"
},
  "geometry": {"coordinates":[3.33333,7.65],"type":"Point"}
}