{
  "type": "Feature",
  "properties": {
    "gn:admin1_code":"29.0",
    "gn:admin2_code":"20008.0",
    "gn:admin3_code":"KN4003",
    "gn:asciiname":"Katsalle",
    "gn:country_code":"NG",
    "gn:dem":515,
    "gn:feature_class":"P",
    "gn:feature_code":"PPL",
    "gn:name":"Katsalle",
    "gn:population":0,
    "gn:timezone":"Africa/Lagos",
    "iso:country":"NG",
    "wof:name":"Katsalle",
    "wof:placetype":"locality"
},
  "geometry": {"coordinates":[8.09294,12.19386],"type":"Point"}
}