{
  "type": "Feature",
  "properties": {
    "gn:admin1_code":"52.0",
    "gn:admin2_code":"6007.0",
    "gn:asciiname":"Betterland",
    "gn:country_code":"NG",
    "gn:dem":2,
    "gn:feature_class":"P",
    "gn:feature_code":"PPL",
    "gn:name":"Betterland",
    "gn:population":0,
    "gn:timezone":"Africa/Lagos",
    "iso:country":"NG",
    "name:eng_x_preferred":[
        "Betterland"
    ],
    "name:eng_x_variant":[
        "Beterland"
    ],
    "wof:name":"Betterland",
    "wof:placetype":"locality"
},
  "geometry": {"coordinates":[5.95818,4.57402],"type":"Point"}
}