{
  "type": "Feature",
  "properties": {
    "gn:admin1_code":"35.0",
    "gn:admin2_code":"2008",
    "gn:asciiname":"Dajugum",
    "gn:country_code":"NG",
    "gn:dem":443,
    "gn:feature_class":"P",
    "gn:feature_code":"PPL",
    "gn:name":"Dajugum",
    "gn:population":0,
    "gn:timezone":"Africa/Lagos",
    "iso:country":"NG",
    "wof:name":"Dajugum",
    "wof:placetype":"locality"
},
  "geometry": {"coordinates":[12.27997,8.54933],"type":"Point"}
}