{
  "type": "Feature",
  "properties": {
    "gn:admin1_code":"36.0",
    "gn:admin2_code":"10007.0",
    "gn:asciiname":"Uteh-Okpu",
    "gn:country_code":"NG",
    "gn:dem":160,
    "gn:feature_class":"P",
    "gn:feature_code":"PPL",
    "gn:name":"Uteh-Okpu",
    "gn:population":0,
    "gn:timezone":"Africa/Lagos",
    "iso:country":"NG",
    "name:eng_x_preferred":[
        "Uteh-Okpu"
    ],
    "name:eng_x_variant":[
        "Ute Okpo"
    ],
    "wof:name":"Uteh-Okpu",
    "wof:placetype":"locality"
},
  "geometry": {"coordinates":[6.26962,6.19135],"type":"Point"}
}