{
  "type": "Feature",
  "properties": {
    "gn:admin1_code":"23.0",
    "gn:admin2_code":"19020",
    "gn:admin3_code":"KD2011",
    "gn:asciiname":"Ungwan Idah",
    "gn:country_code":"NG",
    "gn:dem":488,
    "gn:feature_class":"P",
    "gn:feature_code":"PPL",
    "gn:name":"Ungwan Idah",
    "gn:population":0,
    "gn:timezone":"Africa/Lagos",
    "iso:country":"NG",
    "wof:name":"Ungwan Idah",
    "wof:placetype":"locality"
},
  "geometry": {"coordinates":[8.15207,9.20288],"type":"Point"}
}