{
  "type": "Feature",
  "properties": {
    "gn:admin1_code":"37.0",
    "gn:admin2_code":"12004",
    "gn:asciiname":"Ibhiolulu",
    "gn:country_code":"NG",
    "gn:dem":268,
    "gn:feature_class":"P",
    "gn:feature_code":"PPL",
    "gn:name":"Ibhiolulu",
    "gn:population":0,
    "gn:timezone":"Africa/Lagos",
    "iso:country":"NG",
    "name:und_x_variant":[
        "Ibiololo",
        "Ihiolo"
    ],
    "wof:name":"Ibhiolulu",
    "wof:placetype":"locality"
},
  "geometry": {"coordinates":[6.35848,6.78484],"type":"Point"}
}