{
  "type": "Feature",
  "properties": {
    "gn:admin1_code":"26.0",
    "gn:admin2_code":"7008",
    "gn:asciiname":"Pancho",
    "gn:country_code":"NG",
    "gn:dem":103,
    "gn:feature_class":"P",
    "gn:feature_code":"PPL",
    "gn:name":"Pancho",
    "gn:population":0,
    "gn:timezone":"Africa/Lagos",
    "iso:country":"NG",
    "name:bre_x_preferred":[
        "Pancho"
    ],
    "wof:name":"Pancho",
    "wof:placetype":"locality"
},
  "geometry": {"coordinates":[8.12836,7.67204],"type":"Point"}
}