{
  "type": "Feature",
  "properties": {
    "gn:admin1_code":"46.0",
    "gn:admin2_code":"5008.0",
    "gn:admin3_code":"BA0807",
    "gn:asciiname":"Burako",
    "gn:country_code":"NG",
    "gn:dem":521,
    "gn:feature_class":"P",
    "gn:feature_code":"PPL",
    "gn:name":"Burako",
    "gn:population":0,
    "gn:timezone":"Africa/Lagos",
    "iso:country":"NG",
    "wof:name":"Burako",
    "wof:placetype":"locality"
},
  "geometry": {"coordinates":[9.98004,10.9409],"type":"Point"}
}