{
  "type": "Feature",
  "properties": {
    "gn:admin1_code":"31.0",
    "gn:admin2_code":"27010.0",
    "gn:asciiname":"Kpakara",
    "gn:country_code":"NG",
    "gn:dem":131,
    "gn:feature_class":"P",
    "gn:feature_code":"PPL",
    "gn:name":"Kpakara",
    "gn:population":0,
    "gn:timezone":"Africa/Lagos",
    "iso:country":"NG",
    "name:und_x_variant":[
        "Kparaka",
        "Kpakara"
    ],
    "wof:name":"Kpakara",
    "wof:placetype":"locality"
},
  "geometry": {"coordinates":[6.23492,9.33238],"type":"Point"}
}