{
  "type": "Feature",
  "properties": {
    "gn:admin1_code":"47.0",
    "gn:admin2_code":"14002.0",
    "gn:asciiname":"Amaowele",
    "gn:country_code":"NG",
    "gn:dem":284,
    "gn:feature_class":"P",
    "gn:feature_code":"PPL",
    "gn:name":"Amaowele",
    "gn:population":0,
    "gn:timezone":"Africa/Lagos",
    "iso:country":"NG",
    "wof:name":"Amaowele",
    "wof:placetype":"locality"
},
  "geometry": {"coordinates":[7.42448,6.17937],"type":"Point"}
}