{
  "type": "Feature",
  "properties": {
    "gn:admin1_code":"32.0",
    "gn:admin2_code":"31025.0",
    "gn:asciiname":"Gande",
    "gn:country_code":"NG",
    "gn:dem":75,
    "gn:feature_class":"P",
    "gn:feature_code":"PPL",
    "gn:name":"Gande",
    "gn:population":0,
    "gn:timezone":"Africa/Lagos",
    "iso:country":"NG",
    "name:ceb_x_preferred":[
        "Gande"
    ],
    "name:nor_x_preferred":[
        "Gande"
    ],
    "name:swe_x_preferred":[
        "Gande"
    ],
    "wof:name":"Gande",
    "wof:placetype":"locality"
},
  "geometry": {"coordinates":[3.96667,7.11667],"type":"Point"}
}