{
  "type": "Feature",
  "properties": {
    "gn:admin1_code":"48.0",
    "gn:admin2_code":"29013.0",
    "gn:asciiname":"Fajo",
    "gn:country_code":"NG",
    "gn:dem":77,
    "gn:feature_class":"P",
    "gn:feature_code":"PPL",
    "gn:name":"Fajo",
    "gn:population":0,
    "gn:timezone":"Africa/Lagos",
    "iso:country":"NG",
    "name:und_x_variant":[
        "Fajaw",
        "Fajo"
    ],
    "wof:name":"Fajo",
    "wof:placetype":"locality"
},
  "geometry": {"coordinates":[4.58439,6.7245],"type":"Point"}
}