{
  "type": "Feature",
  "properties": {
    "gn:admin1_code":"35.0",
    "gn:asciiname":"Jimen",
    "gn:country_code":"NG",
    "gn:dem":460,
    "gn:feature_class":"P",
    "gn:feature_code":"PPL",
    "gn:name":"Jimen",
    "gn:population":0,
    "gn:timezone":"Africa/Lagos",
    "iso:country":"NG",
    "wof:name":"Jimen",
    "wof:placetype":"locality"
},
  "geometry": {"coordinates":[12.41372,8.5808],"type":"Point"}
}