{
  "type": "Feature",
  "properties": {
    "gn:admin1_code":"51.0",
    "gn:admin2_code":"614.0",
    "gn:admin3_code":"61402",
    "gn:asciiname":"Tunga Dorowa",
    "gn:cc2":"NG",
    "gn:country_code":"NG",
    "gn:dem":283,
    "gn:feature_class":"P",
    "gn:feature_code":"PPL",
    "gn:name":"Tunga Dorowa",
    "gn:population":0,
    "gn:timezone":"Africa/Lagos",
    "iso:country":"NG",
    "name:und_x_variant":[
        "Gidan Dorowa",
        "Tunga Dorowa"
    ],
    "wof:name":"Tunga Dorowa",
    "wof:placetype":"locality"
},
  "geometry": {"coordinates":[5.06667,12.53333],"type":"Point"}
}