{
  "type": "Feature",
  "properties": {
    "gn:admin1_code":"41.0",
    "gn:admin2_code":"23012.0",
    "gn:asciiname":"Ohinki",
    "gn:country_code":"NG",
    "gn:dem":76,
    "gn:feature_class":"P",
    "gn:feature_code":"PPL",
    "gn:name":"Ohinki",
    "gn:population":0,
    "gn:timezone":"Africa/Lagos",
    "iso:country":"NG",
    "wof:name":"Ohinki",
    "wof:placetype":"locality"
},
  "geometry": {"coordinates":[6.76667,8.05],"type":"Point"}
}