{
  "type": "Feature",
  "properties": {
    "gn:admin1_code":"24.0",
    "gn:admin2_code":"405.0",
    "gn:admin3_code":"40509",
    "gn:asciiname":"Shibdawa",
    "gn:country_code":"NG",
    "gn:dem":509,
    "gn:feature_class":"P",
    "gn:feature_code":"PPL",
    "gn:name":"Shibdawa",
    "gn:population":0,
    "gn:timezone":"Africa/Lagos",
    "iso:country":"NG",
    "wof:name":"Shibdawa",
    "wof:placetype":"locality"
},
  "geometry": {"coordinates":[7.82127,12.75275],"type":"Point"}
}