{
  "type": "Feature",
  "properties": {
    "gn:admin1_code":"53.0",
    "gn:admin2_code":"11010.0",
    "gn:asciiname":"Inyinba",
    "gn:country_code":"NG",
    "gn:dem":74,
    "gn:feature_class":"P",
    "gn:feature_code":"PPL",
    "gn:name":"Inyinba",
    "gn:population":0,
    "gn:timezone":"Africa/Lagos",
    "iso:country":"NG",
    "name:und_x_variant":[
        "Inyiniba",
        "Inyinba"
    ],
    "wof:name":"Inyinba",
    "wof:placetype":"locality"
},
  "geometry": {"coordinates":[8.28511,6.4801],"type":"Point"}
}