{
  "type": "Feature",
  "properties": {
    "gn:admin1_code":"27.0",
    "gn:admin2_code":"101.0",
    "gn:admin3_code":"10101",
    "gn:asciiname":"Kangarwa",
    "gn:country_code":"NG",
    "gn:dem":289,
    "gn:feature_class":"P",
    "gn:feature_code":"PPL",
    "gn:name":"Kangarwa",
    "gn:population":0,
    "gn:timezone":"Africa/Lagos",
    "iso:country":"NG",
    "wof:name":"Kangarwa",
    "wof:placetype":"locality"
},
  "geometry": {"coordinates":[13.45417,13.29854],"type":"Point"}
}