{
  "type": "Feature",
  "properties": {
    "gn:admin1_code":"26.0",
    "gn:admin2_code":"7007.0",
    "gn:asciiname":"Tvortswan",
    "gn:country_code":"NG",
    "gn:dem":167,
    "gn:feature_class":"P",
    "gn:feature_code":"PPL",
    "gn:name":"Tvortswan",
    "gn:population":0,
    "gn:timezone":"Africa/Lagos",
    "iso:country":"NG",
    "wof:name":"Tvortswan",
    "wof:placetype":"locality"
},
  "geometry": {"coordinates":[8.45574,7.26824],"type":"Point"}
}