{
  "type": "Feature",
  "properties": {
    "gn:admin1_code":"22.0",
    "gn:admin2_code":"9016",
    "gn:asciiname":"Abuakpu",
    "gn:country_code":"NG",
    "gn:dem":121,
    "gn:feature_class":"P",
    "gn:feature_code":"PPL",
    "gn:name":"Abuakpu",
    "gn:population":0,
    "gn:timezone":"Africa/Lagos",
    "iso:country":"NG",
    "wof:name":"Abuakpu",
    "wof:placetype":"locality"
},
  "geometry": {"coordinates":[8.87775,6.52295],"type":"Point"}
}