{
  "type": "Feature",
  "properties": {
    "gn:admin1_code":"28.0",
    "gn:admin2_code":"17005.0",
    "gn:asciiname":"Nduche",
    "gn:country_code":"NG",
    "gn:dem":129,
    "gn:feature_class":"P",
    "gn:feature_code":"PPL",
    "gn:name":"Nduche",
    "gn:population":0,
    "gn:timezone":"Africa/Lagos",
    "iso:country":"NG",
    "wof:name":"Nduche",
    "wof:placetype":"locality"
},
  "geometry": {"coordinates":[7.18333,5.83333],"type":"Point"}
}