{
  "type": "Feature",
  "properties": {
    "gn:admin1_code":"53.0",
    "gn:admin2_code":"11004.0",
    "gn:asciiname":"Egwudinagu",
    "gn:country_code":"NG",
    "gn:dem":74,
    "gn:feature_class":"P",
    "gn:feature_code":"PPL",
    "gn:name":"Egwudinagu",
    "gn:population":0,
    "gn:timezone":"Africa/Lagos",
    "iso:country":"NG",
    "name:und_x_variant":[
        "Egwuduiagu",
        "Egwudinagu"
    ],
    "wof:name":"Egwudinagu",
    "wof:placetype":"locality"
},
  "geometry": {"coordinates":[8.08968,6.49521],"type":"Point"}
}