{
  "type": "Feature",
  "properties": {
    "gn:admin1_code":"27.0",
    "gn:admin2_code":"125.0",
    "gn:admin3_code":"12509",
    "gn:asciiname":"Wurge",
    "gn:country_code":"NG",
    "gn:dem":290,
    "gn:feature_class":"P",
    "gn:feature_code":"PPL",
    "gn:name":"Wurge",
    "gn:population":0,
    "gn:timezone":"Africa/Lagos",
    "iso:country":"NG",
    "wof:name":"Wurge",
    "wof:placetype":"locality"
},
  "geometry": {"coordinates":[14.09639,12.1364],"type":"Point"}
}