{
  "type": "Feature",
  "properties": {
    "gn:admin1_code":"40.0",
    "gn:admin2_code":"509.0",
    "gn:admin3_code":"50907",
    "gn:asciiname":"Kurama Suko",
    "gn:country_code":"NG",
    "gn:dem":202,
    "gn:feature_class":"P",
    "gn:feature_code":"PPL",
    "gn:name":"Kurama Suko",
    "gn:population":0,
    "gn:timezone":"Africa/Lagos",
    "iso:country":"NG",
    "name:und_x_variant":[
        "Kangi"
    ],
    "wof:name":"Kurama Suko",
    "wof:placetype":"locality"
},
  "geometry": {"coordinates":[4.61308,11.58544],"type":"Point"}
}