{
  "type": "Feature",
  "properties": {
    "gn:admin1_code":"41.0",
    "gn:admin2_code":"23006.0",
    "gn:asciiname":"Ijankuta",
    "gn:country_code":"NG",
    "gn:dem":31,
    "gn:feature_class":"P",
    "gn:feature_code":"PPL",
    "gn:name":"Ijankuta",
    "gn:population":0,
    "gn:timezone":"Africa/Lagos",
    "iso:country":"NG",
    "name:eng_x_preferred":[
        "Ijankuta"
    ],
    "wof:name":"Ijankuta",
    "wof:placetype":"locality"
},
  "geometry": {"coordinates":[6.64039,6.71511],"type":"Point"}
}