{
  "type": "Feature",
  "properties": {
    "gn:admin1_code":"21.0",
    "gn:admin2_code":"3030.0",
    "gn:asciiname":"Ate",
    "gn:country_code":"NG",
    "gn:dem":40,
    "gn:feature_class":"P",
    "gn:feature_code":"PPL",
    "gn:name":"Ate",
    "gn:population":0,
    "gn:timezone":"Africa/Lagos",
    "iso:country":"NG",
    "wof:name":"Ate",
    "wof:placetype":"locality"
},
  "geometry": {"coordinates":[8.153,4.7492],"type":"Point"}
}