{
  "type": "Feature",
  "properties": {
    "gn:admin1_code":"53.0",
    "gn:admin2_code":"11001",
    "gn:asciiname":"Nwidogu",
    "gn:country_code":"NG",
    "gn:dem":62,
    "gn:feature_class":"P",
    "gn:feature_code":"PPL",
    "gn:name":"Nwidogu",
    "gn:population":0,
    "gn:timezone":"Africa/Lagos",
    "iso:country":"NG",
    "name:und_x_variant":[
        "Nwedogu"
    ],
    "wof:name":"Nwidogu",
    "wof:placetype":"locality"
},
  "geometry": {"coordinates":[8.26947,6.25572],"type":"Point"}
}