{
  "type": "Feature",
  "properties": {
    "gn:admin1_code":"50.0",
    "gn:admin2_code":"33015.0",
    "gn:asciiname":"Alozo",
    "gn:country_code":"NG",
    "gn:dem":20,
    "gn:feature_class":"P",
    "gn:feature_code":"PPL",
    "gn:name":"Alozo",
    "gn:population":0,
    "gn:timezone":"Africa/Lagos",
    "iso:country":"NG",
    "wof:name":"Alozo",
    "wof:placetype":"locality"
},
  "geometry": {"coordinates":[6.97773,4.88065],"type":"Point"}
}