{
  "type": "Feature",
  "properties": {
    "gn:admin1_code":"55.0",
    "gn:admin2_code":"16008.0",
    "gn:asciiname":"Wurin Dule",
    "gn:country_code":"NG",
    "gn:dem":355,
    "gn:feature_class":"P",
    "gn:feature_code":"PPL",
    "gn:name":"Wurin Dule",
    "gn:population":0,
    "gn:timezone":"Africa/Lagos",
    "iso:country":"NG",
    "wof:name":"Wurin Dule",
    "wof:placetype":"locality"
},
  "geometry": {"coordinates":[11.25458,10.38038],"type":"Point"}
}