{
  "type": "Feature",
  "properties": {
    "gn:admin1_code":"41.0",
    "gn:admin2_code":"23005.0",
    "gn:asciiname":"Acharu",
    "gn:country_code":"NG",
    "gn:dem":383,
    "gn:feature_class":"P",
    "gn:feature_code":"PPL",
    "gn:name":"Acharu",
    "gn:population":0,
    "gn:timezone":"Africa/Lagos",
    "iso:country":"NG",
    "wof:name":"Acharu",
    "wof:placetype":"locality"
},
  "geometry": {"coordinates":[7.30725,7.51277],"type":"Point"}
}