{
  "type": "Feature",
  "properties": {
    "gn:admin1_code":"56.0",
    "gn:admin2_code":"26004",
    "gn:asciiname":"Rafin",
    "gn:country_code":"NG",
    "gn:dem":398,
    "gn:feature_class":"P",
    "gn:feature_code":"PPL",
    "gn:name":"Rafin",
    "gn:population":0,
    "gn:timezone":"Africa/Lagos",
    "iso:country":"NG",
    "name:und_x_variant":[
        "Rafin-Pa"
    ],
    "wof:name":"Rafin",
    "wof:placetype":"locality"
},
  "geometry": {"coordinates":[7.86768,9.1974],"type":"Point"}
}