{
  "type": "Feature",
  "properties": {
    "gn:admin1_code":"23.0",
    "gn:admin2_code":"19008.0",
    "gn:admin3_code":"KD0801",
    "gn:asciiname":"Gidan Sarkin-Katul",
    "gn:country_code":"NG",
    "gn:dem":719,
    "gn:feature_class":"P",
    "gn:feature_code":"PPL",
    "gn:name":"Gidan Sarkin-Katul",
    "gn:population":0,
    "gn:timezone":"Africa/Lagos",
    "iso:country":"NG",
    "name:und_x_variant":[
        "Gidan Sarikin Katul",
        "Gidan Sarkin-Katul"
    ],
    "wof:name":"Gidan Sarkin-Katul",
    "wof:placetype":"locality"
},
  "geometry": {"coordinates":[8.02383,9.91246],"type":"Point"}
}