{
  "type": "Feature",
  "properties": {
    "gn:admin1_code":"36.0",
    "gn:admin2_code":"10008.0",
    "gn:asciiname":"Ozarra",
    "gn:country_code":"NG",
    "gn:dem":189,
    "gn:feature_class":"P",
    "gn:feature_code":"PPL",
    "gn:name":"Ozarra",
    "gn:population":0,
    "gn:timezone":"Africa/Lagos",
    "iso:country":"NG",
    "name:eng_x_preferred":[
        "Ozarra"
    ],
    "wof:name":"Ozarra",
    "wof:placetype":"locality"
},
  "geometry": {"coordinates":[6.12588,6.31525],"type":"Point"}
}