{
  "type": "Feature",
  "properties": {
    "gn:admin1_code":"39.0",
    "gn:admin2_code":"18010.0",
    "gn:admin3_code":"JI1702",
    "gn:asciiname":"Tudunwayo",
    "gn:country_code":"NG",
    "gn:dem":416,
    "gn:feature_class":"P",
    "gn:feature_code":"PPL",
    "gn:name":"Tudunwayo",
    "gn:population":0,
    "gn:timezone":"Africa/Lagos",
    "iso:country":"NG",
    "wof:name":"Tudunwayo",
    "wof:placetype":"locality"
},
  "geometry": {"coordinates":[8.52822,12.60875],"type":"Point"}
}