{
  "type": "Feature",
  "properties": {
    "gn:admin1_code":"21.0",
    "gn:admin2_code":"3019.0",
    "gn:asciiname":"Ikot Ekpot",
    "gn:country_code":"NG",
    "gn:dem":28,
    "gn:feature_class":"P",
    "gn:feature_code":"PPL",
    "gn:name":"Ikot Ekpot",
    "gn:population":0,
    "gn:timezone":"Africa/Lagos",
    "iso:country":"NG",
    "wof:name":"Ikot Ekpot",
    "wof:placetype":"locality"
},
  "geometry": {"coordinates":[8.0029,4.7829],"type":"Point"}
}