{
  "type": "Feature",
  "properties": {
    "gn:admin1_code":"39.0",
    "gn:admin2_code":"18025.0",
    "gn:admin3_code":"JI1907",
    "gn:asciiname":"Rimi",
    "gn:country_code":"NG",
    "gn:dem":387,
    "gn:feature_class":"P",
    "gn:feature_code":"PPL",
    "gn:name":"Rimi",
    "gn:population":0,
    "gn:timezone":"Africa/Lagos",
    "iso:country":"NG",
    "name:ceb_x_preferred":[
        "Rimi"
    ],
    "name:deu_x_preferred":[
        "Rimi"
    ],
    "name:ita_x_preferred":[
        "Rimi"
    ],
    "name:swe_x_preferred":[
        "Rimi"
    ],
    "wof:name":"Rimi",
    "wof:placetype":"locality"
},
  "geometry": {"coordinates":[9.67339,11.81629],"type":"Point"}
}