{
  "type": "Feature",
  "properties": {
    "gn:admin1_code":"35.0",
    "gn:admin2_code":"2002.0",
    "gn:asciiname":"Dumayo",
    "gn:country_code":"NG",
    "gn:dem":220,
    "gn:feature_class":"P",
    "gn:feature_code":"PPL",
    "gn:name":"Dumayo",
    "gn:population":0,
    "gn:timezone":"Africa/Lagos",
    "iso:country":"NG",
    "name:und_x_variant":[
        "Mayo",
        "Dumayo"
    ],
    "wof:name":"Dumayo",
    "wof:placetype":"locality"
},
  "geometry": {"coordinates":[12.39598,9.12343],"type":"Point"}
}