{
  "type": "Feature",
  "properties": {
    "gn:admin1_code":"35.0",
    "gn:admin2_code":"2002.0",
    "gn:asciiname":"Dakin Kowa",
    "gn:country_code":"NG",
    "gn:dem":234,
    "gn:feature_class":"P",
    "gn:feature_code":"PPL",
    "gn:name":"Dakin Kowa",
    "gn:population":0,
    "gn:timezone":"Africa/Lagos",
    "iso:country":"NG",
    "name:eng_x_preferred":[
        "Dakin Kowa"
    ],
    "name:eng_x_variant":[
        "Dadin Kowa"
    ],
    "wof:name":"Dakin Kowa",
    "wof:placetype":"locality"
},
  "geometry": {"coordinates":[12.29321,9.02215],"type":"Point"}
}