{
  "type": "Feature",
  "properties": {
    "gn:admin1_code":"39.0",
    "gn:admin2_code":"18030.0",
    "gn:admin3_code":"JI2503",
    "gn:asciiname":"Chikia",
    "gn:country_code":"NG",
    "gn:dem":377,
    "gn:feature_class":"P",
    "gn:feature_code":"PPL",
    "gn:name":"Chikia",
    "gn:population":0,
    "gn:timezone":"Africa/Lagos",
    "iso:country":"NG",
    "wof:name":"Chikia",
    "wof:placetype":"locality"
},
  "geometry": {"coordinates":[9.22631,12.80868],"type":"Point"}
}