{
  "type": "Feature",
  "properties": {
    "gn:admin1_code":"35.0",
    "gn:admin2_code":"2001.0",
    "gn:asciiname":"Kpakmiagi",
    "gn:country_code":"NG",
    "gn:dem":154,
    "gn:feature_class":"P",
    "gn:feature_code":"PPL",
    "gn:name":"Kpakmiagi",
    "gn:population":0,
    "gn:timezone":"Africa/Lagos",
    "iso:country":"NG",
    "name:eng_x_preferred":[
        "Kpakmiagi"
    ],
    "wof:name":"Kpakmiagi",
    "wof:placetype":"locality"
},
  "geometry": {"coordinates":[12.26791,9.49413],"type":"Point"}
}