{
  "type": "Feature",
  "properties": {
    "gn:admin1_code":"40.0",
    "gn:admin2_code":"509.0",
    "gn:admin3_code":"50909",
    "gn:asciiname":"Darko",
    "gn:country_code":"NG",
    "gn:dem":262,
    "gn:feature_class":"P",
    "gn:feature_code":"PPL",
    "gn:name":"Darko",
    "gn:population":0,
    "gn:timezone":"Africa/Lagos",
    "iso:country":"NG",
    "name:ceb_x_preferred":[
        "Darko"
    ],
    "name:ces_x_preferred":[
        "Darko"
    ],
    "name:fra_x_preferred":[
        "Darko"
    ],
    "name:por_x_preferred":[
        "Darko"
    ],
    "name:rus_x_preferred":[
        "\u0414\u0430\u0440\u043a\u043e"
    ],
    "wof:name":"Darko",
    "wof:placetype":"locality"
},
  "geometry": {"coordinates":[4.75559,11.47017],"type":"Point"}
}