{
  "type": "Feature",
  "properties": {
    "gn:admin1_code":"16.0",
    "gn:admin2_code":"28003.0",
    "gn:asciiname":"Singiokolo Creek",
    "gn:country_code":"NG",
    "gn:dem":48,
    "gn:feature_class":"P",
    "gn:feature_code":"PPL",
    "gn:name":"Singiokolo Creek",
    "gn:population":0,
    "gn:timezone":"Africa/Lagos",
    "iso:country":"NG",
    "name:und_x_variant":[
        "Alagba",
        "Singiokolo Creek"
    ],
    "wof:name":"Singiokolo Creek",
    "wof:placetype":"locality"
},
  "geometry": {"coordinates":[3.0361,6.62135],"type":"Point"}
}