{
  "type": "Feature",
  "properties": {
    "gn:admin1_code":"49.0",
    "gn:admin2_code":"32007.0",
    "gn:asciiname":"Kafyel",
    "gn:country_code":"NG",
    "gn:dem":263,
    "gn:feature_class":"P",
    "gn:feature_code":"PPL",
    "gn:name":"Kafyel",
    "gn:population":0,
    "gn:timezone":"Africa/Lagos",
    "iso:country":"NG",
    "name:eng_x_preferred":[
        "Kafyel"
    ],
    "name:eng_x_variant":[
        "Karfel"
    ],
    "wof:name":"Kafyel",
    "wof:placetype":"locality"
},
  "geometry": {"coordinates":[9.91526,9.2262],"type":"Point"}
}