{
  "type": "Feature",
  "properties": {
    "gn:admin1_code":"16.0",
    "gn:admin2_code":"28001.0",
    "gn:asciiname":"Ibara Orile",
    "gn:cc2":"NG",
    "gn:country_code":"NG",
    "gn:dem":122,
    "gn:feature_class":"P",
    "gn:feature_code":"PPL",
    "gn:name":"Ibara Orile",
    "gn:population":0,
    "gn:timezone":"Africa/Lagos",
    "iso:country":"NG",
    "name:und_x_variant":[
        "Ibara-Oko",
        "Ibara Orile"
    ],
    "wof:name":"Ibara Orile",
    "wof:placetype":"locality"
},
  "geometry": {"coordinates":[3.25,7.13333],"type":"Point"}
}