{
  "type": "Feature",
  "properties": {
    "gn:admin1_code":"22.0",
    "gn:admin2_code":"9016.0",
    "gn:asciiname":"Eja",
    "gn:country_code":"NG",
    "gn:dem":108,
    "gn:feature_class":"P",
    "gn:feature_code":"PPL",
    "gn:name":"Eja",
    "gn:population":0,
    "gn:timezone":"Africa/Lagos",
    "iso:country":"NG",
    "wof:name":"Eja",
    "wof:placetype":"locality"
},
  "geometry": {"coordinates":[8.66752,6.44209],"type":"Point"}
}