{
  "type": "Feature",
  "properties": {
    "gn:admin1_code":"46.0",
    "gn:admin2_code":"5018.0",
    "gn:admin3_code":"BA1814",
    "gn:asciiname":"Ririwan Dalma",
    "gn:country_code":"NG",
    "gn:dem":867,
    "gn:feature_class":"P",
    "gn:feature_code":"PPL",
    "gn:name":"Ririwan Dalma",
    "gn:population":0,
    "gn:timezone":"Africa/Lagos",
    "iso:country":"NG",
    "wof:name":"Ririwan Dalma",
    "wof:placetype":"locality"
},
  "geometry": {"coordinates":[8.97811,10.28294],"type":"Point"}
}