{
  "type": "Feature",
  "properties": {
    "gn:admin1_code":"37.0",
    "gn:admin2_code":"12009.0",
    "gn:asciiname":"Alashio",
    "gn:country_code":"NG",
    "gn:dem":297,
    "gn:feature_class":"P",
    "gn:feature_code":"PPL",
    "gn:name":"Alashio",
    "gn:population":0,
    "gn:timezone":"Africa/Lagos",
    "iso:country":"NG",
    "wof:name":"Alashio",
    "wof:placetype":"locality"
},
  "geometry": {"coordinates":[6.3093,7.1026],"type":"Point"}
}