{
  "type": "Feature",
  "properties": {
    "gn:admin1_code":"31.0",
    "gn:admin2_code":"27014.0",
    "gn:asciiname":"Keriko",
    "gn:country_code":"NG",
    "gn:dem":233,
    "gn:feature_class":"P",
    "gn:feature_code":"PPL",
    "gn:name":"Keriko",
    "gn:population":0,
    "gn:timezone":"Africa/Lagos",
    "iso:country":"NG",
    "name:und_x_variant":[
        "Keniko",
        "Keriko"
    ],
    "wof:name":"Keriko",
    "wof:placetype":"locality"
},
  "geometry": {"coordinates":[4.80479,10.18736],"type":"Point"}
}