{
  "type": "Feature",
  "properties": {
    "gn:admin1_code":"39.0",
    "gn:admin2_code":"18024.0",
    "gn:admin3_code":"JI0809",
    "gn:asciiname":"Gidan Maja",
    "gn:country_code":"NG",
    "gn:dem":388,
    "gn:feature_class":"P",
    "gn:feature_code":"PPL",
    "gn:name":"Gidan Maja",
    "gn:population":0,
    "gn:timezone":"Africa/Lagos",
    "iso:country":"NG",
    "wof:name":"Gidan Maja",
    "wof:placetype":"locality"
},
  "geometry": {"coordinates":[8.95916,12.57255],"type":"Point"}
}