{
  "type": "Feature",
  "properties": {
    "gn:admin1_code":"27.0",
    "gn:admin2_code":"118.0",
    "gn:admin3_code":"11806",
    "gn:asciiname":"Gashina",
    "gn:country_code":"NG",
    "gn:dem":395,
    "gn:feature_class":"P",
    "gn:feature_code":"PPL",
    "gn:name":"Gashina",
    "gn:population":0,
    "gn:timezone":"Africa/Lagos",
    "iso:country":"NG",
    "wof:name":"Gashina",
    "wof:placetype":"locality"
},
  "geometry": {"coordinates":[11.86007,10.52329],"type":"Point"}
}