{
  "type": "Feature",
  "properties": {
    "gn:admin1_code":"37.0",
    "gn:admin2_code":"12010.0",
    "gn:asciiname":"Ekehen",
    "gn:country_code":"NG",
    "gn:dem":307,
    "gn:feature_class":"P",
    "gn:feature_code":"PPL",
    "gn:name":"Ekehen",
    "gn:population":0,
    "gn:timezone":"Africa/Lagos",
    "iso:country":"NG",
    "name:eng_x_preferred":[
        "Ekekhen"
    ],
    "name:eng_x_variant":[
        "Ekehen"
    ],
    "wof:name":"Ekehen",
    "wof:placetype":"locality"
},
  "geometry": {"coordinates":[6.24957,6.62361],"type":"Point"}
}