{
  "type": "Feature",
  "properties": {
    "gn:admin1_code":"49.0",
    "gn:admin2_code":"32009.0",
    "gn:asciiname":"Zamko",
    "gn:country_code":"NG",
    "gn:dem":226,
    "gn:feature_class":"P",
    "gn:feature_code":"PPL",
    "gn:name":"Zamko",
    "gn:population":0,
    "gn:timezone":"Africa/Lagos",
    "iso:country":"NG",
    "name:eng_x_preferred":[
        "Zamko"
    ],
    "wof:name":"Zamko",
    "wof:placetype":"locality"
},
  "geometry": {"coordinates":[9.84858,9.00689],"type":"Point"}
}