{
  "type": "Feature",
  "properties": {
    "gn:admin1_code":"26.0",
    "gn:admin2_code":"7005",
    "gn:asciiname":"Akpoughol",
    "gn:country_code":"NG",
    "gn:dem":215,
    "gn:feature_class":"P",
    "gn:feature_code":"PPL",
    "gn:name":"Akpoughol",
    "gn:population":0,
    "gn:timezone":"Africa/Lagos",
    "iso:country":"NG",
    "wof:name":"Akpoughol",
    "wof:placetype":"neighbourhood"
},
  "geometry": {"coordinates":[9.01224,7.36061],"type":"Point"}
}