{
  "type": "Feature",
  "properties": {
    "gn:admin1_code":"52.0",
    "gn:admin2_code":"6001.0",
    "gn:asciiname":"Okoroba",
    "gn:country_code":"NG",
    "gn:dem":9,
    "gn:feature_class":"P",
    "gn:feature_code":"PPL",
    "gn:name":"Okoroba",
    "gn:population":0,
    "gn:timezone":"Africa/Lagos",
    "iso:country":"NG",
    "wof:name":"Okoroba",
    "wof:placetype":"locality"
},
  "geometry": {"coordinates":[6.42376,4.63035],"type":"Point"}
}