{
  "type": "Feature",
  "properties": {
    "gn:admin1_code":"23.0",
    "gn:admin2_code":"19020",
    "gn:admin3_code":"KD2006",
    "gn:asciiname":"Kurindoo",
    "gn:country_code":"NG",
    "gn:dem":530,
    "gn:feature_class":"P",
    "gn:feature_code":"PPL",
    "gn:name":"Kurindoo",
    "gn:population":0,
    "gn:timezone":"Africa/Lagos",
    "iso:country":"NG",
    "wof:name":"Kurindoo",
    "wof:placetype":"locality"
},
  "geometry": {"coordinates":[8.53695,9.37871],"type":"Point"}
}