{
  "type": "Feature",
  "properties": {
    "gn:admin1_code":"40.0",
    "gn:admin2_code":"502.0",
    "gn:admin3_code":"50201",
    "gn:asciiname":"Tumbo",
    "gn:country_code":"NG",
    "gn:dem":225,
    "gn:feature_class":"P",
    "gn:feature_code":"PPL",
    "gn:name":"Tumbo",
    "gn:population":0,
    "gn:timezone":"Africa/Lagos",
    "iso:country":"NG",
    "wof:name":"Tumbo",
    "wof:placetype":"locality"
},
  "geometry": {"coordinates":[4.13786,13.15742],"type":"Point"}
}