{
  "type": "Feature",
  "properties": {
    "gn:admin1_code":"46.0",
    "gn:admin2_code":"5001.0",
    "gn:admin3_code":"BA0115",
    "gn:asciiname":"Machido",
    "gn:country_code":"NG",
    "gn:dem":345,
    "gn:feature_class":"P",
    "gn:feature_code":"PPL",
    "gn:name":"Machido",
    "gn:population":0,
    "gn:timezone":"Africa/Lagos",
    "iso:country":"NG",
    "name:eng_x_preferred":[
        "Machido"
    ],
    "wof:name":"Machido",
    "wof:placetype":"locality"
},
  "geometry": {"coordinates":[10.31648,10.05516],"type":"Point"}
}