{
  "type": "Feature",
  "properties": {
    "gn:admin1_code":"22.0",
    "gn:admin2_code":"9002.0",
    "gn:asciiname":"Awai Ifunkpa",
    "gn:country_code":"NG",
    "gn:dem":138,
    "gn:feature_class":"P",
    "gn:feature_code":"PPL",
    "gn:name":"Awai Ifunkpa",
    "gn:population":0,
    "gn:timezone":"Africa/Lagos",
    "iso:country":"NG",
    "name:und_x_variant":[
        "Awailfunkpa",
        "Awai Ifunkpa"
    ],
    "wof:name":"Awai Ifunkpa",
    "wof:placetype":"locality"
},
  "geometry": {"coordinates":[8.26756,5.56671],"type":"Point"}
}