{
  "type": "Feature",
  "properties": {
    "gn:admin1_code":"31.0",
    "gn:admin2_code":"27008",
    "gn:asciiname":"Gendegi",
    "gn:country_code":"NG",
    "gn:dem":95,
    "gn:feature_class":"P",
    "gn:feature_code":"PPL",
    "gn:name":"Gendegi",
    "gn:population":0,
    "gn:timezone":"Africa/Lagos",
    "iso:country":"NG",
    "wof:name":"Gendegi",
    "wof:placetype":"locality"
},
  "geometry": {"coordinates":[5.83249,9.04192],"type":"Point"}
}