{
  "type": "Feature",
  "properties": {
    "gn:admin1_code":"27.0",
    "gn:admin2_code":"112.0",
    "gn:admin3_code":"11209",
    "gn:asciiname":"Laksheri",
    "gn:country_code":"NG",
    "gn:dem":324,
    "gn:feature_class":"P",
    "gn:feature_code":"PPL",
    "gn:name":"Laksheri",
    "gn:population":0,
    "gn:timezone":"Africa/Lagos",
    "iso:country":"NG",
    "wof:name":"Laksheri",
    "wof:placetype":"locality"
},
  "geometry": {"coordinates":[12.24265,10.42894],"type":"Point"}
}