{
  "type": "Feature",
  "properties": {
    "gn:admin1_code":"40.0",
    "gn:admin2_code":"514.0",
    "gn:admin3_code":"51402",
    "gn:asciiname":"Giwatazo",
    "gn:country_code":"NG",
    "gn:dem":246,
    "gn:feature_class":"P",
    "gn:feature_code":"PPL",
    "gn:name":"Giwatazo",
    "gn:population":0,
    "gn:timezone":"Africa/Lagos",
    "iso:country":"NG",
    "wof:name":"Giwatazo",
    "wof:placetype":"locality"
},
  "geometry": {"coordinates":[4.37995,12.13929],"type":"Point"}
}