{
  "type": "Feature",
  "properties": {
    "gn:admin1_code":"47.0",
    "gn:admin2_code":"14006.0",
    "gn:asciiname":"Igbenu",
    "gn:country_code":"NG",
    "gn:dem":39,
    "gn:feature_class":"P",
    "gn:feature_code":"PPL",
    "gn:name":"Igbenu",
    "gn:population":0,
    "gn:timezone":"Africa/Lagos",
    "iso:country":"NG",
    "name:und_x_variant":[
        "Ugbenu",
        "Igbenu"
    ],
    "wof:name":"Igbenu",
    "wof:placetype":"locality"
},
  "geometry": {"coordinates":[7.1356,6.38267],"type":"Point"}
}