{
  "type": "Feature",
  "properties": {
    "gn:admin1_code":"24.0",
    "gn:admin2_code":"401.0",
    "gn:admin3_code":"40105",
    "gn:asciiname":"Ungwan Dan Shuni",
    "gn:country_code":"NG",
    "gn:dem":597,
    "gn:feature_class":"P",
    "gn:feature_code":"PPL",
    "gn:name":"Ungwan Dan Shuni",
    "gn:population":0,
    "gn:timezone":"Africa/Lagos",
    "iso:country":"NG",
    "wof:name":"Ungwan Dan Shuni",
    "wof:placetype":"locality"
},
  "geometry": {"coordinates":[7.29739,11.73877],"type":"Point"}
}