{
  "type": "Feature",
  "properties": {
    "gn:admin1_code":"26.0",
    "gn:admin2_code":"7006",
    "gn:asciiname":"Hingir",
    "gn:country_code":"NG",
    "gn:dem":92,
    "gn:feature_class":"P",
    "gn:feature_code":"PPL",
    "gn:name":"Hingir",
    "gn:population":0,
    "gn:timezone":"Africa/Lagos",
    "iso:country":"NG",
    "wof:name":"Hingir",
    "wof:placetype":"locality"
},
  "geometry": {"coordinates":[9.00638,7.64033],"type":"Point"}
}