{
  "type": "Feature",
  "properties": {
    "gn:admin1_code":"22.0",
    "gn:admin2_code":"9016",
    "gn:asciiname":"Mpambeku",
    "gn:country_code":"NG",
    "gn:dem":120,
    "gn:feature_class":"P",
    "gn:feature_code":"PPL",
    "gn:name":"Mpambeku",
    "gn:population":0,
    "gn:timezone":"Africa/Lagos",
    "iso:country":"NG",
    "name:und_x_variant":[
        "Mpumbeku"
    ],
    "wof:name":"Mpambeku",
    "wof:placetype":"locality"
},
  "geometry": {"coordinates":[8.85669,6.53191],"type":"Point"}
}