{
  "type": "Feature",
  "properties": {
    "gn:admin1_code":"27.0",
    "gn:admin2_code":"115.0",
    "gn:admin3_code":"11506",
    "gn:asciiname":"Ngaje",
    "gn:country_code":"NG",
    "gn:dem":301,
    "gn:feature_class":"P",
    "gn:feature_code":"PPL",
    "gn:name":"Ngaje",
    "gn:population":0,
    "gn:timezone":"Africa/Lagos",
    "iso:country":"NG",
    "name:und_x_variant":[
        "Koutelaha",
        "Kutelaha",
        "Ngaje"
    ],
    "wof:name":"Ngaje",
    "wof:placetype":"locality"
},
  "geometry": {"coordinates":[14.56537,11.74382],"type":"Point"}
}