{
  "type": "Feature",
  "properties": {
    "gn:admin1_code":"26.0",
    "gn:admin2_code":"7021",
    "gn:asciiname":"Bako",
    "gn:country_code":"NG",
    "gn:dem":178,
    "gn:feature_class":"P",
    "gn:feature_code":"PPL",
    "gn:name":"Bako",
    "gn:population":0,
    "gn:timezone":"Africa/Lagos",
    "iso:country":"NG",
    "name:ceb_x_preferred":[
        "Bako"
    ],
    "name:deu_x_preferred":[
        "Bako"
    ],
    "name:fra_x_preferred":[
        "Bako"
    ],
    "name:hun_x_preferred":[
        "Bak\u00f3"
    ],
    "name:hye_x_preferred":[
        "\u0532\u0561\u056f\u0578"
    ],
    "name:ita_x_preferred":[
        "Bako"
    ],
    "name:rus_x_preferred":[
        "\u0411\u0430\u043a\u043e"
    ],
    "name:swe_x_preferred":[
        "Bako"
    ],
    "wof:name":"Bako",
    "wof:placetype":"locality"
},
  "geometry": {"coordinates":[9.48008,7.64996],"type":"Point"}
}