{
  "type": "Feature",
  "properties": {
    "gn:admin1_code":"23.0",
    "gn:admin2_code":"19005.0",
    "gn:admin3_code":"KD0504",
    "gn:asciiname":"Ungwan Golo",
    "gn:country_code":"NG",
    "gn:dem":666,
    "gn:feature_class":"P",
    "gn:feature_code":"PPL",
    "gn:name":"Ungwan Golo",
    "gn:population":0,
    "gn:timezone":"Africa/Lagos",
    "iso:country":"NG",
    "name:und_x_variant":[
        "Golo",
        "Ungwan Golo"
    ],
    "wof:name":"Ungwan Golo",
    "wof:placetype":"locality"
},
  "geometry": {"coordinates":[8.10842,11.20797],"type":"Point"}
}