{
  "type": "Feature",
  "properties": {
    "gn:admin1_code":"28.0",
    "gn:admin2_code":"17017.0",
    "gn:asciiname":"Osoji",
    "gn:country_code":"NG",
    "gn:dem":22,
    "gn:feature_class":"P",
    "gn:feature_code":"PPL",
    "gn:name":"Osoji",
    "gn:population":0,
    "gn:timezone":"Africa/Lagos",
    "iso:country":"NG",
    "wof:name":"Osoji",
    "wof:placetype":"locality"
},
  "geometry": {"coordinates":[6.75254,5.6235],"type":"Point"}
}