{
  "type": "Feature",
  "properties": {
    "gn:admin1_code":"24.0",
    "gn:admin2_code":"404.0",
    "gn:admin3_code":"40404",
    "gn:asciiname":"Ungwar Kaura",
    "gn:country_code":"NG",
    "gn:dem":407,
    "gn:feature_class":"P",
    "gn:feature_code":"PPL",
    "gn:name":"Ungwar Kaura",
    "gn:population":0,
    "gn:timezone":"Africa/Lagos",
    "iso:country":"NG",
    "name:und_x_variant":[
        "Ungua Kaura",
        "Ungwar Kaura"
    ],
    "wof:name":"Ungwar Kaura",
    "wof:placetype":"locality"
},
  "geometry": {"coordinates":[8.73943,12.88385],"type":"Point"}
}