{
  "type": "Feature",
  "properties": {
    "gn:admin1_code":"46.0",
    "gn:admin2_code":"5020.0",
    "gn:admin3_code":"BA2001",
    "gn:asciiname":"Machari",
    "gn:country_code":"NG",
    "gn:dem":355,
    "gn:feature_class":"P",
    "gn:feature_code":"PPL",
    "gn:name":"Machari",
    "gn:population":0,
    "gn:timezone":"Africa/Lagos",
    "iso:country":"NG",
    "wof:name":"Machari",
    "wof:placetype":"locality"
},
  "geometry": {"coordinates":[10.6664,12.43576],"type":"Point"}
}