{
  "type": "Feature",
  "properties": {
    "gn:admin1_code":"21.0",
    "gn:admin2_code":"3012.0",
    "gn:asciiname":"Ndiya-Nfia",
    "gn:country_code":"NG",
    "gn:dem":126,
    "gn:feature_class":"P",
    "gn:feature_code":"PPL",
    "gn:name":"Ndiya-Nfia",
    "gn:population":0,
    "gn:timezone":"Africa/Lagos",
    "iso:country":"NG",
    "name:und_x_variant":[
        "Ndinya Mfia",
        "Ndiya-Nfia"
    ],
    "wof:name":"Ndiya-Nfia",
    "wof:placetype":"locality"
},
  "geometry": {"coordinates":[7.71162,5.28656],"type":"Point"}
}