{
  "type": "Feature",
  "properties": {
    "gn:admin1_code":"21.0",
    "gn:admin2_code":"3019.0",
    "gn:asciiname":"Ikot Inyang",
    "gn:country_code":"NG",
    "gn:dem":45,
    "gn:feature_class":"P",
    "gn:feature_code":"PPL",
    "gn:name":"Ikot Inyang",
    "gn:population":0,
    "gn:timezone":"Africa/Lagos",
    "iso:country":"NG",
    "wof:name":"Ikot Inyang",
    "wof:placetype":"locality"
},
  "geometry": {"coordinates":[8.0592,4.8507],"type":"Point"}
}