{
  "type": "Feature",
  "properties": {
    "gn:admin1_code":"49.0",
    "gn:admin2_code":"32005.0",
    "gn:asciiname":"Gamajigo",
    "gn:country_code":"NG",
    "gn:dem":1152,
    "gn:feature_class":"P",
    "gn:feature_code":"PPL",
    "gn:name":"Gamajigo",
    "gn:population":0,
    "gn:timezone":"Africa/Lagos",
    "iso:country":"NG",
    "wof:name":"Gamajigo",
    "wof:placetype":"locality"
},
  "geometry": {"coordinates":[8.8535,9.98261],"type":"Point"}
}