{
  "type": "Feature",
  "properties": {
    "gn:admin1_code":"23.0",
    "gn:admin2_code":"19022",
    "gn:admin3_code":"KD2202",
    "gn:asciiname":"Pifak",
    "gn:country_code":"NG",
    "gn:dem":823,
    "gn:feature_class":"P",
    "gn:feature_code":"PPL",
    "gn:name":"Pifak",
    "gn:population":0,
    "gn:timezone":"Africa/Lagos",
    "iso:country":"NG",
    "wof:name":"Pifak",
    "wof:placetype":"locality"
},
  "geometry": {"coordinates":[8.29355,9.91621],"type":"Point"}
}