{
  "type": "Feature",
  "properties": {
    "gn:admin1_code":"57.0",
    "gn:admin2_code":"810.0",
    "gn:admin3_code":"81006",
    "gn:asciiname":"Tjebili",
    "gn:country_code":"NG",
    "gn:dem":356,
    "gn:feature_class":"P",
    "gn:feature_code":"PPL",
    "gn:name":"Tjebili",
    "gn:population":0,
    "gn:timezone":"Africa/Lagos",
    "iso:country":"NG",
    "wof:name":"Tjebili",
    "wof:placetype":"locality"
},
  "geometry": {"coordinates":[6.14121,12.14862],"type":"Point"}
}