{
  "type": "Feature",
  "properties": {
    "gn:admin1_code":"23.0",
    "gn:admin2_code":"19008.0",
    "gn:admin3_code":"KD0801",
    "gn:asciiname":"Pesa",
    "gn:country_code":"NG",
    "gn:dem":772,
    "gn:feature_class":"P",
    "gn:feature_code":"PPL",
    "gn:name":"Pesa",
    "gn:population":0,
    "gn:timezone":"Africa/Lagos",
    "iso:country":"NG",
    "wof:name":"Pesa",
    "wof:placetype":"locality"
},
  "geometry": {"coordinates":[7.91959,9.95417],"type":"Point"}
}