{
  "type": "Feature",
  "properties": {
    "gn:admin1_code":"39.0",
    "gn:admin2_code":"18004.0",
    "gn:admin3_code":"JI0208",
    "gn:asciiname":"Muna",
    "gn:country_code":"NG",
    "gn:dem":403,
    "gn:feature_class":"P",
    "gn:feature_code":"PPL",
    "gn:name":"Muna",
    "gn:population":0,
    "gn:timezone":"Africa/Lagos",
    "iso:country":"NG",
    "name:bel_x_preferred":[
        "\u041c\u0443\u043d\u0430"
    ],
    "name:ceb_x_preferred":[
        "Muna"
    ],
    "name:ces_x_preferred":[
        "Muna"
    ],
    "name:deu_x_preferred":[
        "Muna"
    ],
    "name:est_x_preferred":[
        "Muna"
    ],
    "name:fin_x_preferred":[
        "Muna"
    ],
    "name:fra_x_preferred":[
        "Muna"
    ],
    "name:ind_x_preferred":[
        "Muna"
    ],
    "name:ita_x_preferred":[
        "Muna"
    ],
    "name:lit_x_preferred":[
        "Muna"
    ],
    "name:nld_x_preferred":[
        "Muna"
    ],
    "name:rus_x_preferred":[
        "\u041c\u0443\u043d\u0430"
    ],
    "name:srp_x_preferred":[
        "\u041c\u0443\u043d\u0430"
    ],
    "name:swe_x_preferred":[
        "Muna"
    ],
    "name:ukr_x_preferred":[
        "\u041c\u0443\u043d\u0430"
    ],
    "wof:name":"Muna",
    "wof:placetype":"locality"
},
  "geometry": {"coordinates":[8.8066,12.41455],"type":"Point"}
}