{
  "type": "Feature",
  "properties": {
    "gn:admin1_code":"50.0",
    "gn:admin2_code":"33005.0",
    "gn:asciiname":"Aganna",
    "gn:country_code":"NG",
    "gn:dem":11,
    "gn:feature_class":"P",
    "gn:feature_code":"PPL",
    "gn:name":"Aganna",
    "gn:population":0,
    "gn:timezone":"Africa/Lagos",
    "iso:country":"NG",
    "wof:name":"Aganna",
    "wof:placetype":"locality"
},
  "geometry": {"coordinates":[7.39008,4.47943],"type":"Point"}
}