{
  "type": "Feature",
  "properties": {
    "gn:admin1_code":"35.0",
    "gn:admin2_code":"2007.0",
    "gn:asciiname":"Zum",
    "gn:country_code":"NG",
    "gn:dem":550,
    "gn:feature_class":"P",
    "gn:feature_code":"PPL",
    "gn:name":"Zum",
    "gn:population":0,
    "gn:timezone":"Africa/Lagos",
    "iso:country":"NG",
    "name:und_x_variant":[
        "Zum Ahmadu"
    ],
    "wof:name":"Zum",
    "wof:placetype":"locality"
},
  "geometry": {"coordinates":[13.04785,10.11457],"type":"Point"}
}