{
  "type": "Feature",
  "properties": {
    "gn:admin1_code":"49.0",
    "gn:admin2_code":"32005.0",
    "gn:asciiname":"Passa Bonga",
    "gn:country_code":"NG",
    "gn:dem":1330,
    "gn:feature_class":"P",
    "gn:feature_code":"PPL",
    "gn:name":"Passa Bonga",
    "gn:population":0,
    "gn:timezone":"Africa/Lagos",
    "iso:country":"NG",
    "wof:name":"Passa Bonga",
    "wof:placetype":"locality"
},
  "geometry": {"coordinates":[8.95136,9.93299],"type":"Point"}
}