{
  "type": "Feature",
  "properties": {
    "gn:admin1_code":"27.0",
    "gn:admin2_code":"112.0",
    "gn:admin3_code":"11207",
    "gn:asciiname":"Kwanba",
    "gn:country_code":"NG",
    "gn:dem":604,
    "gn:feature_class":"P",
    "gn:feature_code":"PPL",
    "gn:name":"Kwanba",
    "gn:population":0,
    "gn:timezone":"Africa/Lagos",
    "iso:country":"NG",
    "wof:name":"Kwanba",
    "wof:placetype":"locality"
},
  "geometry": {"coordinates":[12.10002,10.47692],"type":"Point"}
}