{
  "type": "Feature",
  "properties": {
    "gn:admin1_code":"23.0",
    "gn:admin2_code":"19022",
    "gn:admin3_code":"KD2211",
    "gn:asciiname":"Sabon Kaura",
    "gn:country_code":"NG",
    "gn:dem":769,
    "gn:feature_class":"P",
    "gn:feature_code":"PPL",
    "gn:name":"Sabon Kaura",
    "gn:population":0,
    "gn:timezone":"Africa/Lagos",
    "iso:country":"NG",
    "wof:name":"Sabon Kaura",
    "wof:placetype":"locality"
},
  "geometry": {"coordinates":[8.41868,9.92403],"type":"Point"}
}