{
  "type": "Feature",
  "properties": {
    "gn:admin1_code":"26.0",
    "gn:admin2_code":"7004",
    "gn:asciiname":"Mamadu",
    "gn:country_code":"NG",
    "gn:dem":141,
    "gn:feature_class":"P",
    "gn:feature_code":"PPL",
    "gn:name":"Mamadu",
    "gn:population":0,
    "gn:timezone":"Africa/Lagos",
    "iso:country":"NG",
    "wof:name":"Mamadu",
    "wof:placetype":"locality"
},
  "geometry": {"coordinates":[9.12982,7.38512],"type":"Point"}
}