{
  "type": "Feature",
  "properties": {
    "gn:admin1_code":"21.0",
    "gn:admin2_code":"3024.0",
    "gn:asciiname":"Atiamkpat",
    "gn:country_code":"NG",
    "gn:dem":36,
    "gn:feature_class":"P",
    "gn:feature_code":"PPL",
    "gn:name":"Atiamkpat",
    "gn:population":0,
    "gn:timezone":"Africa/Lagos",
    "iso:country":"NG",
    "wof:name":"Atiamkpat",
    "wof:placetype":"locality"
},
  "geometry": {"coordinates":[7.85017,4.69078],"type":"Point"}
}