{
  "type": "Feature",
  "properties": {
    "gn:admin1_code":"46.0",
    "gn:admin2_code":"5001.0",
    "gn:admin3_code":"BA0112",
    "gn:asciiname":"Kasachia",
    "gn:country_code":"NG",
    "gn:dem":408,
    "gn:feature_class":"P",
    "gn:feature_code":"PPL",
    "gn:name":"Kasachia",
    "gn:population":0,
    "gn:timezone":"Africa/Lagos",
    "iso:country":"NG",
    "name:eng_x_preferred":[
        "Kasachia"
    ],
    "wof:name":"Kasachia",
    "wof:placetype":"locality"
},
  "geometry": {"coordinates":[10.32042,10.26225],"type":"Point"}
}