{
  "type": "Feature",
  "properties": {
    "gn:admin1_code":"45.0",
    "gn:asciiname":"Iwuo-Ukem",
    "gn:country_code":"NG",
    "gn:dem":51,
    "gn:feature_class":"P",
    "gn:feature_code":"PPL",
    "gn:name":"Iwuo-Ukem",
    "gn:population":0,
    "gn:timezone":"Africa/Lagos",
    "iso:country":"NG",
    "wof:name":"Iwuo-Ukem",
    "wof:placetype":"locality"
},
  "geometry": {"coordinates":[7.49138,4.94348],"type":"Point"}
}