{
  "type": "Feature",
  "properties": {
    "gn:admin1_code":"16.0",
    "gn:admin2_code":"28013.0",
    "gn:asciiname":"Imala Asipa",
    "gn:cc2":"NG",
    "gn:country_code":"NG",
    "gn:dem":194,
    "gn:feature_class":"P",
    "gn:feature_code":"PPL",
    "gn:name":"Imala Asipa",
    "gn:population":0,
    "gn:timezone":"Africa/Lagos",
    "iso:country":"NG",
    "name:und_x_variant":[
        "Ashipa",
        "Imala Asipa"
    ],
    "wof:name":"Imala Asipa",
    "wof:placetype":"locality"
},
  "geometry": {"coordinates":[3.01667,7.41667],"type":"Point"}
}