{
  "type": "Feature",
  "properties": {
    "gn:admin1_code":"46.0",
    "gn:admin2_code":"5013.0",
    "gn:admin3_code":"BA1312",
    "gn:asciiname":"Arawa",
    "gn:country_code":"NG",
    "gn:dem":377,
    "gn:feature_class":"P",
    "gn:feature_code":"PPL",
    "gn:name":"Arawa",
    "gn:population":0,
    "gn:timezone":"Africa/Lagos",
    "iso:country":"NG",
    "name:ara_x_preferred":[
        "\u0623\u0631\u0627\u0648\u0627"
    ],
    "name:ben_x_preferred":[
        "\u0986\u09b0\u09be\u0993\u09df\u09be"
    ],
    "name:ceb_x_preferred":[
        "Arawa"
    ],
    "name:deu_x_preferred":[
        "Arawa"
    ],
    "name:ell_x_preferred":[
        "\u0391\u03c1\u03ac\u03b2\u03b1"
    ],
    "name:eng_x_preferred":[
        "Arawa"
    ],
    "name:heb_x_preferred":[
        "\u05d0\u05e8\u05d5\u05d5\u05d4"
    ],
    "name:hin_x_preferred":[
        "\u0905\u0930\u093e\u0935\u093e"
    ],
    "name:hun_x_preferred":[
        "Arawa"
    ],
    "name:ind_x_preferred":[
        "Arawa"
    ],
    "name:rus_x_preferred":[
        "\u0410\u0440\u0430\u0432\u0430"
    ],
    "name:swe_x_preferred":[
        "Arawa"
    ],
    "name:tur_x_preferred":[
        "Arawa"
    ],
    "name:ukr_x_preferred":[
        "\u0410\u0440\u0430\u0432\u0430"
    ],
    "name:vie_x_preferred":[
        "Arawa"
    ],
    "wof:name":"Arawa",
    "wof:placetype":"locality"
},
  "geometry": {"coordinates":[10.41538,10.29034],"type":"Point"}
}