{
  "type": "Feature",
  "properties": {
    "gn:admin1_code":"46.0",
    "gn:admin2_code":"5013.0",
    "gn:admin3_code":"BA1312",
    "gn:asciiname":"Arawa",
    "gn:country_code":"NG",
    "gn:dem":377,
    "gn:feature_class":"P",
    "gn:feature_code":"PPL",
    "gn:name":"Arawa",
    "gn:population":0,
    "gn:timezone":"Africa/Lagos",
    "iso:country":"NG",
    "name:ceb_x_preferred":[
        "Arawa"
    ],
    "name:deu_x_preferred":[
        "Arawa"
    ],
    "name:eng_x_preferred":[
        "Arawa"
    ],
    "name:rus_x_preferred":[
        "\u0410\u0440\u0430\u0432\u0430"
    ],
    "name:swe_x_preferred":[
        "Arawa"
    ],
    "name:ukr_x_preferred":[
        "\u0410\u0440\u0430\u0432\u0430"
    ],
    "wof:name":"Arawa",
    "wof:placetype":"locality"
},
  "geometry": {"coordinates":[10.41538,10.29034],"type":"Point"}
}