{
  "type": "Feature",
  "properties": {
    "gn:admin1_code":"27.0",
    "gn:admin2_code":"117",
    "gn:admin3_code":"11701",
    "gn:asciiname":"Ali-Kannori",
    "gn:country_code":"NG",
    "gn:dem":293,
    "gn:feature_class":"P",
    "gn:feature_code":"PPL",
    "gn:name":"Ali-Kannori",
    "gn:population":0,
    "gn:timezone":"Africa/Lagos",
    "iso:country":"NG",
    "wof:name":"Ali-Kannori",
    "wof:placetype":"locality"
},
  "geometry": {"coordinates":[13.58132,13.13172],"type":"Point"}
}