{
  "type": "Feature",
  "properties": {
    "gn:admin1_code":"52.0",
    "gn:asciiname":"Odoigbene",
    "gn:country_code":"NG",
    "gn:dem":6,
    "gn:feature_class":"P",
    "gn:feature_code":"PPL",
    "gn:name":"Odoigbene",
    "gn:population":0,
    "gn:timezone":"Africa/Lagos",
    "iso:country":"NG",
    "name:eng_x_preferred":[
        "Odoigbene"
    ],
    "wof:name":"Odoigbene",
    "wof:placetype":"locality"
},
  "geometry": {"coordinates":[5.6639,4.65867],"type":"Point"}
}