{
  "type": "Feature",
  "properties": {
    "gn:admin1_code":"35.0",
    "gn:admin2_code":"2019.0",
    "gn:asciiname":"Tuduri",
    "gn:country_code":"NG",
    "gn:dem":428,
    "gn:feature_class":"P",
    "gn:feature_code":"PPL",
    "gn:name":"Tuduri",
    "gn:population":0,
    "gn:timezone":"Africa/Lagos",
    "iso:country":"NG",
    "wof:name":"Tuduri",
    "wof:placetype":"locality"
},
  "geometry": {"coordinates":[11.45,8.13333],"type":"Point"}
}