{
  "type": "Feature",
  "properties": {
    "gn:admin1_code":"5.0",
    "gn:admin2_code":"25003.0",
    "gn:asciiname":"Cardoso",
    "gn:country_code":"NG",
    "gn:dem":25,
    "gn:feature_class":"P",
    "gn:feature_code":"PPL",
    "gn:name":"Cardoso",
    "gn:population":0,
    "gn:timezone":"Africa/Lagos",
    "iso:country":"NG",
    "wof:name":"Cardoso",
    "wof:placetype":"locality"
},
  "geometry": {"coordinates":[3.26811,6.58115],"type":"Point"}
}