{
  "type": "Feature",
  "properties": {
    "gn:admin1_code":"40.0",
    "gn:admin2_code":"516.0",
    "gn:admin3_code":"51608",
    "gn:asciiname":"Sakaba",
    "gn:country_code":"NG",
    "gn:dem":356,
    "gn:feature_class":"P",
    "gn:feature_code":"PPLA2",
    "gn:name":"Sakaba",
    "gn:population":0,
    "gn:timezone":"Africa/Lagos",
    "iso:country":"NG",
    "wof:name":"Sakaba",
    "wof:placetype":"locality"
},
  "geometry": {"coordinates":[5.5961,11.06513],"type":"Point"}
}