{
  "type": "Feature",
  "properties": {
    "gn:admin1_code":"50.0",
    "gn:admin2_code":"33002.0",
    "gn:asciiname":"Idoke",
    "gn:country_code":"NG",
    "gn:dem":14,
    "gn:feature_class":"P",
    "gn:feature_code":"PPL",
    "gn:name":"Idoke",
    "gn:population":0,
    "gn:timezone":"Africa/Lagos",
    "iso:country":"NG",
    "wof:name":"Idoke",
    "wof:placetype":"locality"
},
  "geometry": {"coordinates":[6.66641,5.02667],"type":"Point"}
}