{
  "type": "Feature",
  "properties": {
    "gn:admin1_code":"55.0",
    "gn:admin2_code":"16007.0",
    "gn:asciiname":"Kamo",
    "gn:cc2":"NG",
    "gn:country_code":"NG",
    "gn:dem":436,
    "gn:feature_class":"P",
    "gn:feature_code":"PPL",
    "gn:name":"Kamo",
    "gn:population":0,
    "gn:timezone":"Africa/Lagos",
    "iso:country":"NG",
    "name:ceb_x_preferred":[
        "Kamo"
    ],
    "name:ces_x_preferred":[
        "Kamo"
    ],
    "name:deu_x_preferred":[
        "Kamo"
    ],
    "name:epo_x_preferred":[
        "Kamo"
    ],
    "name:est_x_preferred":[
        "Kamo"
    ],
    "name:fra_x_preferred":[
        "Kamo"
    ],
    "name:hye_x_preferred":[
        "\u053f\u0561\u0574\u0578"
    ],
    "name:ind_x_preferred":[
        "Kamo"
    ],
    "name:kat_x_preferred":[
        "\u10d9\u10d0\u10db\u10dd"
    ],
    "name:lav_x_preferred":[
        "Kamo"
    ],
    "name:mlg_x_preferred":[
        "Kamo"
    ],
    "name:nld_x_preferred":[
        "Kamo"
    ],
    "name:rus_x_preferred":[
        "\u041a\u0430\u043c\u043e"
    ],
    "name:spa_x_preferred":[
        "Kamo"
    ],
    "name:swe_x_preferred":[
        "Kamo"
    ],
    "name:ukr_x_preferred":[
        "\u041a\u0430\u043c\u043e"
    ],
    "name:und_x_variant":[
        "Kamu",
        "Kamo"
    ],
    "wof:name":"Kamo",
    "wof:placetype":"locality"
},
  "geometry": {"coordinates":[11.35,9.91667],"type":"Point"}
}