{
  "type": "Feature",
  "properties": {
    "gn:admin1_code":"16.0",
    "gn:admin2_code":"28013.0",
    "gn:asciiname":"Ogunte",
    "gn:country_code":"NG",
    "gn:dem":150,
    "gn:feature_class":"P",
    "gn:feature_code":"PPL",
    "gn:name":"Ogunte",
    "gn:population":0,
    "gn:timezone":"Africa/Lagos",
    "iso:country":"NG",
    "wof:name":"Ogunte",
    "wof:placetype":"locality"
},
  "geometry": {"coordinates":[3.05,7.51667],"type":"Point"}
}