{
  "type": "Feature",
  "properties": {
    "gn:admin1_code":"26.0",
    "gn:admin2_code":"7010.0",
    "gn:asciiname":"Huna",
    "gn:country_code":"NG",
    "gn:dem":171,
    "gn:feature_class":"P",
    "gn:feature_code":"PPL",
    "gn:name":"Huna",
    "gn:population":0,
    "gn:timezone":"Africa/Lagos",
    "iso:country":"NG",
    "name:deu_x_preferred":[
        "Huna"
    ],
    "name:swe_x_preferred":[
        "Huna"
    ],
    "wof:name":"Huna",
    "wof:placetype":"locality"
},
  "geometry": {"coordinates":[8.84258,7.02954],"type":"Point"}
}