{
  "type": "Feature",
  "properties": {
    "gn:admin1_code":"26.0",
    "gn:admin2_code":"7010.0",
    "gn:asciiname":"Kungu",
    "gn:country_code":"NG",
    "gn:dem":110,
    "gn:feature_class":"P",
    "gn:feature_code":"PPL",
    "gn:name":"Kungu",
    "gn:population":0,
    "gn:timezone":"Africa/Lagos",
    "iso:country":"NG",
    "name:ceb_x_preferred":[
        "Kungu"
    ],
    "name:fra_x_preferred":[
        "Kungu"
    ],
    "name:ron_x_preferred":[
        "Kungu"
    ],
    "name:swe_x_preferred":[
        "Kungu"
    ],
    "wof:name":"Kungu",
    "wof:placetype":"locality"
},
  "geometry": {"coordinates":[8.53175,7.03729],"type":"Point"}
}