{
  "type": "Feature",
  "properties": {
    "gn:admin1_code":"23.0",
    "gn:admin2_code":"19017.0",
    "gn:admin3_code":"KD1706",
    "gn:asciiname":"Old Kudaru",
    "gn:country_code":"NG",
    "gn:dem":735,
    "gn:feature_class":"P",
    "gn:feature_code":"PPL",
    "gn:name":"Old Kudaru",
    "gn:population":0,
    "gn:timezone":"Africa/Lagos",
    "iso:country":"NG",
    "name:und_x_variant":[
        "Kudaru Station",
        "Old Kudaru"
    ],
    "wof:name":"Old Kudaru",
    "wof:placetype":"locality"
},
  "geometry": {"coordinates":[8.48361,10.65027],"type":"Point"}
}