{
  "type": "Feature",
  "properties": {
    "gn:admin1_code":"45.0",
    "gn:admin2_code":"1011.0",
    "gn:asciiname":"Mboko Umu Ocha",
    "gn:country_code":"NG",
    "gn:dem":83,
    "gn:feature_class":"P",
    "gn:feature_code":"PPL",
    "gn:name":"Mboko Umu Ocha",
    "gn:population":0,
    "gn:timezone":"Africa/Lagos",
    "iso:country":"NG",
    "name:und_x_variant":[
        "Umu Ocha",
        "Mboko Umu Ocha"
    ],
    "wof:name":"Mboko Umu Ocha",
    "wof:placetype":"locality"
},
  "geometry": {"coordinates":[7.38505,5.19616],"type":"Point"}
}