{
  "type": "Feature",
  "properties": {
    "gn:admin1_code":"26.0",
    "gn:admin2_code":"7014.0",
    "gn:asciiname":"Okpaga",
    "gn:country_code":"NG",
    "gn:dem":92,
    "gn:feature_class":"P",
    "gn:feature_code":"PPL",
    "gn:name":"Okpaga",
    "gn:population":0,
    "gn:timezone":"Africa/Lagos",
    "iso:country":"NG",
    "wof:name":"Okpaga",
    "wof:placetype":"locality"
},
  "geometry": {"coordinates":[8.27387,7.08105],"type":"Point"}
}