{
  "type": "Feature",
  "properties": {
    "gn:admin1_code":"27.0",
    "gn:admin2_code":"107.0",
    "gn:admin3_code":"10711",
    "gn:asciiname":"Kaimari",
    "gn:country_code":"NG",
    "gn:dem":416,
    "gn:feature_class":"P",
    "gn:feature_code":"PPL",
    "gn:name":"Kaimari",
    "gn:population":0,
    "gn:timezone":"Africa/Lagos",
    "iso:country":"NG",
    "wof:name":"Kaimari",
    "wof:placetype":"locality"
},
  "geometry": {"coordinates":[12.3901,11.30924],"type":"Point"}
}