{
  "type": "Feature",
  "properties": {
    "gn:admin1_code":"35.0",
    "gn:admin2_code":"2011.0",
    "gn:asciiname":"Kubaje Wamngo",
    "gn:country_code":"NG",
    "gn:dem":532,
    "gn:feature_class":"P",
    "gn:feature_code":"PPL",
    "gn:name":"Kubaje Wamngo",
    "gn:population":0,
    "gn:timezone":"Africa/Lagos",
    "iso:country":"NG",
    "wof:name":"Kubaje Wamngo",
    "wof:placetype":"locality"
},
  "geometry": {"coordinates":[13.13008,10.00606],"type":"Point"}
}