{
  "type": "Feature",
  "properties": {
    "gn:admin1_code":"32.0",
    "gn:admin2_code":"31013.0",
    "gn:asciiname":"Baba Gbawu",
    "gn:country_code":"NG",
    "gn:dem":164,
    "gn:feature_class":"P",
    "gn:feature_code":"PPL",
    "gn:name":"Baba Gbawu",
    "gn:population":0,
    "gn:timezone":"Africa/Lagos",
    "iso:country":"NG",
    "wof:name":"Baba Gbawu",
    "wof:placetype":"locality"
},
  "geometry": {"coordinates":[3.06667,7.56667],"type":"Point"}
}