{
  "type": "Feature",
  "properties": {
    "gn:admin1_code":"47.0",
    "gn:admin2_code":"14016.0",
    "gn:asciiname":"Omudi",
    "gn:country_code":"NG",
    "gn:dem":370,
    "gn:feature_class":"P",
    "gn:feature_code":"PPL",
    "gn:name":"Omudi",
    "gn:population":0,
    "gn:timezone":"Africa/Lagos",
    "iso:country":"NG",
    "wof:name":"Omudi",
    "wof:placetype":"locality"
},
  "geometry": {"coordinates":[7.3586,6.54368],"type":"Point"}
}