{
  "type": "Feature",
  "properties": {
    "gn:admin1_code":"44.0",
    "gn:admin2_code":"707.0",
    "gn:admin3_code":"70701",
    "gn:asciiname":"Bijur",
    "gn:country_code":"NG",
    "gn:dem":417,
    "gn:feature_class":"P",
    "gn:feature_code":"PPL",
    "gn:name":"Bijur",
    "gn:population":0,
    "gn:timezone":"Africa/Lagos",
    "iso:country":"NG",
    "wof:name":"Bijur",
    "wof:placetype":"locality"
},
  "geometry": {"coordinates":[12.11948,11.40777],"type":"Point"}
}