{
  "type": "Feature",
  "properties": {
    "gn:admin1_code":"35.0",
    "gn:admin2_code":"2013",
    "gn:asciiname":"Watsila",
    "gn:country_code":"NG",
    "gn:dem":512,
    "gn:feature_class":"P",
    "gn:feature_code":"PPL",
    "gn:name":"Watsila",
    "gn:population":0,
    "gn:timezone":"Africa/Lagos",
    "iso:country":"NG",
    "name:eng_x_preferred":[
        "Watsila"
    ],
    "wof:name":"Watsila",
    "wof:placetype":"locality"
},
  "geometry": {"coordinates":[13.33033,10.5376],"type":"Point"}
}