{
  "type": "Feature",
  "properties": {
    "gn:country":"NG",
    "gn:fcode":"PPL",
    "gn:pop":8627,
    "iso:country":"NG",
    "name:unk_x_variant":[
        "Meko"
    ],
    "qs:name":"Mekkaw",
    "qs:photos_9r":0,
    "qs:photos_sr":0,
    "qs:pop_sr":"5",
    "wof:name":"Mekkaw",
    "wof:placetype":"locality",
    "wof:population":8627
},
  "geometry": {"coordinates":[2.85,7.45],"type":"Point"}
}