{
  "type": "Feature",
  "properties": {
    "gn:admin1_code":"21.0",
    "gn:admin2_code":"3029.0",
    "gn:asciiname":"Ekpene Ukim",
    "gn:country_code":"NG",
    "gn:dem":48,
    "gn:feature_class":"P",
    "gn:feature_code":"PPL",
    "gn:name":"Ekpene Ukim",
    "gn:population":0,
    "gn:timezone":"Africa/Lagos",
    "iso:country":"NG",
    "wof:name":"Ekpene Ukim",
    "wof:placetype":"locality"
},
  "geometry": {"coordinates":[8.03639,4.90511],"type":"Point"}
}