{
  "type": "Feature",
  "properties": {
    "gn:admin1_code":"43.0",
    "gn:admin2_code":"35003.0",
    "gn:asciiname":"Gidan Kaduna",
    "gn:country_code":"NG",
    "gn:dem":210,
    "gn:feature_class":"P",
    "gn:feature_code":"PPL",
    "gn:name":"Gidan Kaduna",
    "gn:population":0,
    "gn:timezone":"Africa/Lagos",
    "iso:country":"NG",
    "wof:name":"Gidan Kaduna",
    "wof:placetype":"locality"
},
  "geometry": {"coordinates":[10.37638,7.53688],"type":"Point"}
}