{
  "type": "Feature",
  "properties": {
    "gn:admin1_code":"27.0",
    "gn:admin2_code":"107.0",
    "gn:admin3_code":"10710",
    "gn:asciiname":"Kulari Hamlets",
    "gn:country_code":"NG",
    "gn:dem":434,
    "gn:feature_class":"P",
    "gn:feature_code":"PPL",
    "gn:name":"Kulari Hamlets",
    "gn:population":0,
    "gn:timezone":"Africa/Lagos",
    "iso:country":"NG",
    "wof:name":"Kulari Hamlets",
    "wof:placetype":"locality"
},
  "geometry": {"coordinates":[12.93432,10.97941],"type":"Point"}
}