{
  "type": "Feature",
  "properties": {
    "gn:admin1_code":"23.0",
    "gn:asciiname":"Yarfulani",
    "gn:country_code":"NG",
    "gn:dem":629,
    "gn:feature_class":"P",
    "gn:feature_code":"PPL",
    "gn:name":"Yarfulani",
    "gn:population":0,
    "gn:timezone":"Africa/Lagos",
    "iso:country":"NG",
    "wof:name":"Yarfulani",
    "wof:placetype":"locality"
},
  "geometry": {"coordinates":[8.47043,11.18348],"type":"Point"}
}