{
  "type": "Feature",
  "properties": {
    "gn:admin1_code":"22.0",
    "gn:admin2_code":"9015.0",
    "gn:asciiname":"Ikot Ekanem Inyang",
    "gn:country_code":"NG",
    "gn:dem":26,
    "gn:feature_class":"P",
    "gn:feature_code":"PPL",
    "gn:name":"Ikot Ekanem Inyang",
    "gn:population":0,
    "gn:timezone":"Africa/Lagos",
    "iso:country":"NG",
    "wof:name":"Ikot Ekanem Inyang",
    "wof:placetype":"locality"
},
  "geometry": {"coordinates":[8.23668,5.21578],"type":"Point"}
}