{
  "type": "Feature",
  "properties": {
    "iso:country":"NG",
    "qs:gn_country":"NG",
    "qs:gn_fcode":"PPL",
    "qs:gn_pop":12665,
    "qs:name":"Runka",
    "qs:name_adm0":"Nigeria",
    "qs:name_adm1":"Katsina",
    "qs:photos":0,
    "qs:photos_1k":0,
    "qs:photos_9k":0,
    "qs:photos_9r":0,
    "qs:photos_all":0,
    "qs:photos_sr":0,
    "qs:placetype":"Town",
    "qs:pop_sr":"6",
    "qs:woe_adm0":23424908,
    "wof:name":"Runka",
    "wof:placetype":"locality",
    "wof:population":12665
},
  "geometry": {"coordinates":[7.30918,12.44788],"type":"Point"}
}