{
  "type": "Feature",
  "properties": {
    "gn:admin1_code":"45.0",
    "gn:admin2_code":"1011.0",
    "gn:asciiname":"Abayi",
    "gn:country_code":"NG",
    "gn:dem":64,
    "gn:feature_class":"P",
    "gn:feature_code":"PPL",
    "gn:name":"Abayi",
    "gn:population":0,
    "gn:timezone":"Africa/Lagos",
    "iso:country":"NG",
    "name:aze_x_preferred":[
        "Abay\u0131"
    ],
    "name:fas_x_preferred":[
        "\u0631\u0642\u0635 \u0622\u0628\u0627\u06cc\u06cc"
    ],
    "name:tur_x_preferred":[
        "Abay\u0131"
    ],
    "wof:name":"Abayi",
    "wof:placetype":"neighbourhood"
},
  "geometry": {"coordinates":[7.33777,5.13979],"type":"Point"}
}