{
  "type": "Feature",
  "properties": {
    "gn:admin1_code":"22.0",
    "gn:admin2_code":"9015.0",
    "gn:asciiname":"Idere",
    "gn:country_code":"NG",
    "gn:dem":29,
    "gn:feature_class":"P",
    "gn:feature_code":"PPL",
    "gn:name":"Idere",
    "gn:population":0,
    "gn:timezone":"Africa/Lagos",
    "iso:country":"NG",
    "wof:name":"Idere",
    "wof:placetype":"locality"
},
  "geometry": {"coordinates":[8.0109,5.3529],"type":"Point"}
}