{
  "type": "Feature",
  "properties": {
    "gn:admin1_code":"23.0",
    "gn:admin2_code":"19003.0",
    "gn:admin3_code":"KD0307",
    "gn:asciiname":"Kusharki",
    "gn:country_code":"NG",
    "gn:dem":618,
    "gn:feature_class":"P",
    "gn:feature_code":"PPL",
    "gn:name":"Kusharki",
    "gn:population":0,
    "gn:timezone":"Africa/Lagos",
    "iso:country":"NG",
    "wof:name":"Kusharki",
    "wof:placetype":"locality"
},
  "geometry": {"coordinates":[7.15,10.81667],"type":"Point"}
}