{
  "type": "Feature",
  "properties": {
    "gn:admin1_code":"44.0",
    "gn:admin2_code":"708.0",
    "gn:admin3_code":"70804",
    "gn:asciiname":"Allagarno",
    "gn:country_code":"NG",
    "gn:dem":362,
    "gn:feature_class":"P",
    "gn:feature_code":"PPL",
    "gn:name":"Allagarno",
    "gn:population":0,
    "gn:timezone":"Africa/Lagos",
    "iso:country":"NG",
    "wof:name":"Allagarno",
    "wof:placetype":"locality"
},
  "geometry": {"coordinates":[11.77844,11.03845],"type":"Point"}
}