{
  "type": "Feature",
  "properties": {
    "gn:admin1_code":"43.0",
    "gn:admin2_code":"35014",
    "gn:asciiname":"Dauda",
    "gn:country_code":"NG",
    "gn:dem":178,
    "gn:feature_class":"P",
    "gn:feature_code":"PPL",
    "gn:name":"Dauda",
    "gn:population":0,
    "gn:timezone":"Africa/Lagos",
    "iso:country":"NG",
    "name:deu_x_preferred":[
        "Dauda"
    ],
    "wof:name":"Dauda",
    "wof:placetype":"locality"
},
  "geometry": {"coordinates":[9.79224,7.72146],"type":"Point"}
}