{
  "type": "Feature",
  "properties": {
    "gn:admin1_code":"26.0",
    "gn:admin2_code":"7010.0",
    "gn:asciiname":"Agenor",
    "gn:country_code":"NG",
    "gn:dem":105,
    "gn:feature_class":"P",
    "gn:feature_code":"PPL",
    "gn:name":"Agenor",
    "gn:population":0,
    "gn:timezone":"Africa/Lagos",
    "iso:country":"NG",
    "name:ara_x_preferred":[
        "\u0622\u062c\u064a\u0646\u0648\u0631"
    ],
    "name:bel_x_preferred":[
        "\u0410\u0433\u0435\u043d\u043e\u0440"
    ],
    "name:bre_x_preferred":[
        "Agenor"
    ],
    "name:bul_x_preferred":[
        "\u0410\u0433\u0435\u043d\u043e\u0440"
    ],
    "name:ces_x_preferred":[
        "Ag\u00e9nor"
    ],
    "name:dan_x_preferred":[
        "Agenor"
    ],
    "name:deu_x_preferred":[
        "Agenor"
    ],
    "name:epo_x_preferred":[
        "Agenoro"
    ],
    "name:fas_x_preferred":[
        "\u0622\u06af\u0646\u0648\u0631"
    ],
    "name:fin_x_preferred":[
        "Agenor"
    ],
    "name:glg_x_preferred":[
        "Axenor"
    ],
    "name:hat_x_preferred":[
        "Agenor"
    ],
    "name:hun_x_preferred":[
        "Ag\u00e9n\u00f3r"
    ],
    "name:hye_x_preferred":[
        "\u0531\u0563\u0565\u0576\u0578\u0580"
    ],
    "name:ina_x_preferred":[
        "Agenor"
    ],
    "name:jpn_x_preferred":[
        "\u30a2\u30b2\u30fc\u30ce\u30fc\u30eb"
    ],
    "name:kat_x_preferred":[
        "\u10d0\u10d2\u10d4\u10dc\u10dd\u10e0\u10d8"
    ],
    "name:kor_x_preferred":[
        "\uc544\uac8c\ub178\ub974"
    ],
    "name:lat_x_preferred":[
        "Agenor"
    ],
    "name:lit_x_preferred":[
        "Agenoras"
    ],
    "name:ltz_x_preferred":[
        "Agenor"
    ],
    "name:nld_x_preferred":[
        "Agenor"
    ],
    "name:pol_x_preferred":[
        "Agenor"
    ],
    "name:por_x_preferred":[
        "Agenor"
    ],
    "name:rus_x_preferred":[
        "\u0410\u0433\u0435\u043d\u043e\u0440"
    ],
    "name:slk_x_preferred":[
        "Ag\u00e9nor"
    ],
    "name:slv_x_preferred":[
        "Agenor"
    ],
    "name:spa_x_preferred":[
        "Ag\u00e9nor"
    ],
    "name:srp_x_preferred":[
        "\u0410\u0433\u0435\u043d\u043e\u0440"
    ],
    "name:swe_x_preferred":[
        "Agenor"
    ],
    "name:ukr_x_preferred":[
        "\u0410\u0433\u0435\u043d\u043e\u0440 \u0424\u0456\u043d\u0456\u043a\u0456\u0439\u0441\u044c\u043a\u0438\u0439"
    ],
    "wof:name":"Agenor",
    "wof:placetype":"locality"
},
  "geometry": {"coordinates":[8.55131,7.1306],"type":"Point"}
}