{
  "type": "Feature",
  "properties": {
    "gn:admin1_code":"56.0",
    "gn:admin2_code":"26001.0",
    "gn:asciiname":"Gona",
    "gn:country_code":"NG",
    "gn:dem":509,
    "gn:feature_class":"P",
    "gn:feature_code":"PPL",
    "gn:name":"Gona",
    "gn:population":0,
    "gn:timezone":"Africa/Lagos",
    "iso:country":"NG",
    "name:fra_x_preferred":[
        "Gona"
    ],
    "name:und_x_variant":[
        "Nindam Daji"
    ],
    "wof:name":"Gona",
    "wof:placetype":"locality"
},
  "geometry": {"coordinates":[8.37712,9.13465],"type":"Point"}
}