{
  "type": "Feature",
  "properties": {
    "gn:admin1_code":"35.0",
    "gn:admin2_code":"2007.0",
    "gn:asciiname":"Gu-Cika",
    "gn:country_code":"NG",
    "gn:dem":483,
    "gn:feature_class":"P",
    "gn:feature_code":"PPL",
    "gn:name":"Gu-Cika",
    "gn:population":0,
    "gn:timezone":"Africa/Lagos",
    "iso:country":"NG",
    "wof:name":"Gu-Cika",
    "wof:placetype":"locality"
},
  "geometry": {"coordinates":[13.04192,10.40731],"type":"Point"}
}