{
  "type": "Feature",
  "properties": {
    "gn:admin1_code":"35.0",
    "gn:asciiname":"Gashu",
    "gn:country_code":"NG",
    "gn:dem":434,
    "gn:feature_class":"P",
    "gn:feature_code":"PPL",
    "gn:name":"Gashu",
    "gn:population":0,
    "gn:timezone":"Africa/Lagos",
    "iso:country":"NG",
    "name:eng_x_preferred":[
        "Gashu"
    ],
    "wof:name":"Gashu",
    "wof:placetype":"locality"
},
  "geometry": {"coordinates":[11.85577,9.07415],"type":"Point"}
}