{
  "type": "Feature",
  "properties": {
    "gn:admin1_code":"22.0",
    "gn:admin2_code":"9015.0",
    "gn:asciiname":"Nyakasang",
    "gn:country_code":"NG",
    "gn:dem":78,
    "gn:feature_class":"P",
    "gn:feature_code":"PPL",
    "gn:name":"Nyakasang",
    "gn:population":0,
    "gn:timezone":"Africa/Lagos",
    "iso:country":"NG",
    "name:und_x_variant":[
        "Ayakasang",
        "Nyakasang"
    ],
    "wof:name":"Nyakasang",
    "wof:placetype":"locality"
},
  "geometry": {"coordinates":[8.2116,5.1395],"type":"Point"}
}