{
  "type": "Feature",
  "properties": {
    "gn:admin1_code":"44.0",
    "gn:admin2_code":"712.0",
    "gn:admin3_code":"71214",
    "gn:asciiname":"Madeniye",
    "gn:country_code":"NG",
    "gn:dem":413,
    "gn:feature_class":"P",
    "gn:feature_code":"PPL",
    "gn:name":"Madeniye",
    "gn:population":0,
    "gn:timezone":"Africa/Lagos",
    "iso:country":"NG",
    "wof:name":"Madeniye",
    "wof:placetype":"locality"
},
  "geometry": {"coordinates":[11.16976,11.78559],"type":"Point"}
}