{
  "type": "Feature",
  "properties": {
    "gn:admin1_code":"29.0",
    "gn:admin2_code":"20033.0",
    "gn:admin3_code":"KN2303",
    "gn:asciiname":"Zongo",
    "gn:country_code":"NG",
    "gn:dem":590,
    "gn:feature_class":"P",
    "gn:feature_code":"PPL",
    "gn:name":"Zongo",
    "gn:population":0,
    "gn:timezone":"Africa/Lagos",
    "iso:country":"NG",
    "wof:name":"Zongo",
    "wof:placetype":"locality"
},
  "geometry": {"coordinates":[8.63911,11.38685],"type":"Point"}
}