{
  "type": "Feature",
  "properties": {
    "gn:admin1_code":"45.0",
    "gn:admin2_code":"1004.0",
    "gn:asciiname":"Elugwu Akanu",
    "gn:country_code":"NG",
    "gn:dem":64,
    "gn:feature_class":"P",
    "gn:feature_code":"PPL",
    "gn:name":"Elugwu Akanu",
    "gn:population":0,
    "gn:timezone":"Africa/Lagos",
    "iso:country":"NG",
    "wof:name":"Elugwu Akanu",
    "wof:placetype":"locality"
},
  "geometry": {"coordinates":[7.68838,5.79849],"type":"Point"}
}