{
  "type": "Feature",
  "properties": {
    "gn:admin1_code":"5.0",
    "gn:admin2_code":"25015.0",
    "gn:asciiname":"Ojo",
    "gn:country_code":"NG",
    "gn:dem":8,
    "gn:feature_class":"P",
    "gn:feature_code":"PPL",
    "gn:name":"Ojo",
    "gn:population":0,
    "gn:timezone":"Africa/Lagos",
    "iso:country":"NG",
    "name:und_x_variant":[
        "Awjaw",
        "Ojoh",
        "Ojo"
    ],
    "wof:name":"Ojo",
    "wof:placetype":"locality"
},
  "geometry": {"coordinates":[3.18329,6.46841],"type":"Point"}
}