{
  "type": "Feature",
  "properties": {
    "gn:admin1_code":"26.0",
    "gn:admin2_code":"7021",
    "gn:asciiname":"Hundu",
    "gn:country_code":"NG",
    "gn:dem":175,
    "gn:feature_class":"P",
    "gn:feature_code":"PPL",
    "gn:name":"Hundu",
    "gn:population":0,
    "gn:timezone":"Africa/Lagos",
    "iso:country":"NG",
    "wof:name":"Hundu",
    "wof:placetype":"locality"
},
  "geometry": {"coordinates":[9.58219,7.75821],"type":"Point"}
}