{
  "type": "Feature",
  "properties": {
    "gn:admin1_code":"26.0",
    "gn:admin2_code":"7010",
    "gn:asciiname":"Hon",
    "gn:country_code":"NG",
    "gn:dem":105,
    "gn:feature_class":"P",
    "gn:feature_code":"PPL",
    "gn:name":"Hon",
    "gn:population":0,
    "gn:timezone":"Africa/Lagos",
    "iso:country":"NG",
    "wof:name":"Hon",
    "wof:placetype":"locality"
},
  "geometry": {"coordinates":[8.56165,7.10406],"type":"Point"}
}