{
  "type": "Feature",
  "properties": {
    "gn:admin1_code":"53.0",
    "gn:admin2_code":"11012.0",
    "gn:asciiname":"Okporo",
    "gn:country_code":"NG",
    "gn:dem":128,
    "gn:feature_class":"P",
    "gn:feature_code":"PPL",
    "gn:name":"Okporo",
    "gn:population":0,
    "gn:timezone":"Africa/Lagos",
    "iso:country":"NG",
    "name:und_x_variant":[
        "Okpora",
        "Okporo"
    ],
    "wof:name":"Okporo",
    "wof:placetype":"locality"
},
  "geometry": {"coordinates":[8.03766,6.61096],"type":"Point"}
}