{
  "type": "Feature",
  "properties": {
    "gn:admin1_code":"26.0",
    "gn:admin2_code":"7019",
    "gn:asciiname":"Agee",
    "gn:country_code":"NG",
    "gn:dem":108,
    "gn:feature_class":"P",
    "gn:feature_code":"PPL",
    "gn:name":"Agee",
    "gn:population":0,
    "gn:timezone":"Africa/Lagos",
    "iso:country":"NG",
    "wof:name":"Agee",
    "wof:placetype":"locality"
},
  "geometry": {"coordinates":[8.23938,7.18187],"type":"Point"}
}