{
  "type": "Feature",
  "properties": {
    "gn:admin1_code":"26.0",
    "gn:admin2_code":"7019",
    "gn:asciiname":"Agee",
    "gn:country_code":"NG",
    "gn:dem":108,
    "gn:feature_class":"P",
    "gn:feature_code":"PPL",
    "gn:name":"Agee",
    "gn:population":0,
    "gn:timezone":"Africa/Lagos",
    "iso:country":"NG",
    "name:deu_x_preferred":[
        "Agee"
    ],
    "name:pol_x_preferred":[
        "Agee"
    ],
    "name:rus_x_preferred":[
        "\u042d\u0439\u0434\u0436\u0438"
    ],
    "name:swe_x_preferred":[
        "Agee"
    ],
    "wof:name":"Agee",
    "wof:placetype":"locality"
},
  "geometry": {"coordinates":[8.23938,7.18187],"type":"Point"}
}