{
  "type": "Feature",
  "properties": {
    "gn:admin1_code":"43.0",
    "gn:admin2_code":"35005",
    "gn:asciiname":"Shakamidari",
    "gn:country_code":"NG",
    "gn:dem":211,
    "gn:feature_class":"P",
    "gn:feature_code":"PPL",
    "gn:name":"Shakamidari",
    "gn:population":0,
    "gn:timezone":"Africa/Lagos",
    "iso:country":"NG",
    "wof:name":"Shakamidari",
    "wof:placetype":"locality"
},
  "geometry": {"coordinates":[10.99217,8.55781],"type":"Point"}
}