{
  "type": "Feature",
  "properties": {
    "gn:admin1_code":"46.0",
    "gn:admin2_code":"5003.0",
    "gn:admin3_code":"BA0302",
    "gn:asciiname":"Bakodak",
    "gn:country_code":"NG",
    "gn:dem":656,
    "gn:feature_class":"P",
    "gn:feature_code":"PPL",
    "gn:name":"Bakodak",
    "gn:population":0,
    "gn:timezone":"Africa/Lagos",
    "iso:country":"NG",
    "name:eng_x_preferred":[
        "Bakodak"
    ],
    "wof:name":"Bakodak",
    "wof:placetype":"locality"
},
  "geometry": {"coordinates":[9.57978,9.71223],"type":"Point"}
}