{
  "type": "Feature",
  "properties": {
    "gn:admin1_code":"39.0",
    "gn:admin2_code":"18010.0",
    "gn:admin3_code":"JI1704",
    "gn:asciiname":"Maigero",
    "gn:country_code":"NG",
    "gn:dem":412,
    "gn:feature_class":"P",
    "gn:feature_code":"PPL",
    "gn:name":"Maigero",
    "gn:population":0,
    "gn:timezone":"Africa/Lagos",
    "iso:country":"NG",
    "wof:name":"Maigero",
    "wof:placetype":"locality"
},
  "geometry": {"coordinates":[8.62978,12.6747],"type":"Point"}
}