{
  "type": "Feature",
  "properties": {
    "gn:admin1_code":"57.0",
    "gn:admin2_code":"803.0",
    "gn:admin3_code":"80301",
    "gn:asciiname":"Kofa",
    "gn:country_code":"NG",
    "gn:dem":442,
    "gn:feature_class":"P",
    "gn:feature_code":"PPL",
    "gn:name":"Kofa",
    "gn:population":0,
    "gn:timezone":"Africa/Lagos",
    "iso:country":"NG",
    "name:ceb_x_preferred":[
        "Kofa"
    ],
    "name:deu_x_preferred":[
        "Kofa"
    ],
    "wof:name":"Kofa",
    "wof:placetype":"locality"
},
  "geometry": {"coordinates":[6.7845,12.4533],"type":"Point"}
}