{
  "type": "Feature",
  "properties": {
    "gn:admin1_code":"5.0",
    "gn:admin2_code":"25016.0",
    "gn:asciiname":"Ewu",
    "gn:country_code":"NG",
    "gn:dem":15,
    "gn:feature_class":"P",
    "gn:feature_code":"PPL",
    "gn:name":"Ewu",
    "gn:population":0,
    "gn:timezone":"Africa/Lagos",
    "iso:country":"NG",
    "wof:name":"Ewu",
    "wof:placetype":"neighbourhood"
},
  "geometry": {"coordinates":[3.32333,6.55917],"type":"Point"}
}