{
  "type": "Feature",
  "properties": {
    "gn:admin1_code":"23.0",
    "gn:admin2_code":"19006.0",
    "gn:admin3_code":"KD0601",
    "gn:asciiname":"Chori",
    "gn:country_code":"NG",
    "gn:dem":742,
    "gn:feature_class":"P",
    "gn:feature_code":"PPL",
    "gn:name":"Chori",
    "gn:population":0,
    "gn:timezone":"Africa/Lagos",
    "iso:country":"NG",
    "wof:name":"Chori",
    "wof:placetype":"locality"
},
  "geometry": {"coordinates":[8.07203,9.53251],"type":"Point"}
}