{
  "type": "Feature",
  "properties": {
    "gn:admin1_code":"26.0",
    "gn:admin2_code":"7005.0",
    "gn:asciiname":"Kaso",
    "gn:country_code":"NG",
    "gn:dem":156,
    "gn:feature_class":"P",
    "gn:feature_code":"PPL",
    "gn:name":"Kaso",
    "gn:population":0,
    "gn:timezone":"Africa/Lagos",
    "iso:country":"NG",
    "name:ceb_x_preferred":[
        "Kaso"
    ],
    "name:swe_x_preferred":[
        "Kaso"
    ],
    "wof:name":"Kaso",
    "wof:placetype":"locality"
},
  "geometry": {"coordinates":[8.69992,7.2919],"type":"Point"}
}