{
  "type": "Feature",
  "properties": {
    "gn:admin1_code":"23.0",
    "gn:admin2_code":"19022.0",
    "gn:admin3_code":"KD2206",
    "gn:asciiname":"Mabushi II",
    "gn:country_code":"NG",
    "gn:dem":884,
    "gn:feature_class":"P",
    "gn:feature_code":"PPL",
    "gn:name":"Mabushi II",
    "gn:population":0,
    "gn:timezone":"Africa/Lagos",
    "iso:country":"NG",
    "name:und_x_variant":[
        "Moroa"
    ],
    "wof:name":"Mabushi II",
    "wof:placetype":"locality"
},
  "geometry": {"coordinates":[8.39869,9.7334],"type":"Point"}
}