{
  "type": "Feature",
  "properties": {
    "gn:admin1_code":"48.0",
    "gn:admin2_code":"29016.0",
    "gn:asciiname":"Ajegunle",
    "gn:country_code":"NG",
    "gn:dem":214,
    "gn:feature_class":"P",
    "gn:feature_code":"PPL",
    "gn:name":"Ajegunle",
    "gn:population":0,
    "gn:timezone":"Africa/Lagos",
    "iso:country":"NG",
    "wof:name":"Ajegunle",
    "wof:placetype":"locality"
},
  "geometry": {"coordinates":[4.78364,6.95386],"type":"Point"}
}