{
  "type": "Feature",
  "properties": {
    "gn:admin1_code":"31.0",
    "gn:admin2_code":"27004.0",
    "gn:asciiname":"Yangweso",
    "gn:cc2":"NG",
    "gn:country_code":"NG",
    "gn:dem":290,
    "gn:feature_class":"P",
    "gn:feature_code":"PPL",
    "gn:name":"Yangweso",
    "gn:population":0,
    "gn:timezone":"Africa/Lagos",
    "iso:country":"NG",
    "name:und_x_variant":[
        "Yangbessu",
        "Yangweso"
    ],
    "wof:name":"Yangweso",
    "wof:placetype":"locality"
},
  "geometry": {"coordinates":[3.78333,10.36667],"type":"Point"}
}