{
  "type": "Feature",
  "properties": {
    "gn:admin1_code":"31.0",
    "gn:admin2_code":"27010",
    "gn:asciiname":"Masantali",
    "gn:country_code":"NG",
    "gn:dem":128,
    "gn:feature_class":"P",
    "gn:feature_code":"PPL",
    "gn:name":"Masantali",
    "gn:population":0,
    "gn:timezone":"Africa/Lagos",
    "iso:country":"NG",
    "wof:name":"Masantali",
    "wof:placetype":"locality"
},
  "geometry": {"coordinates":[6.23965,9.06311],"type":"Point"}
}