{
  "type": "Feature",
  "properties": {
    "gn:admin1_code":"43.0",
    "gn:admin2_code":"35014.0",
    "gn:asciiname":"Wotire",
    "gn:country_code":"NG",
    "gn:dem":130,
    "gn:feature_class":"P",
    "gn:feature_code":"PPL",
    "gn:name":"Wotire",
    "gn:population":0,
    "gn:timezone":"Africa/Lagos",
    "iso:country":"NG",
    "wof:name":"Wotire",
    "wof:placetype":"locality"
},
  "geometry": {"coordinates":[10.00561,7.81468],"type":"Point"}
}