{
  "type": "Feature",
  "properties": {
    "gn:admin1_code":"29.0",
    "gn:admin2_code":"20003.0",
    "gn:admin3_code":"KN1510",
    "gn:asciiname":"Dan Maura",
    "gn:country_code":"NG",
    "gn:dem":483,
    "gn:feature_class":"P",
    "gn:feature_code":"PPL",
    "gn:name":"Dan Maura",
    "gn:population":0,
    "gn:timezone":"Africa/Lagos",
    "iso:country":"NG",
    "wof:name":"Dan Maura",
    "wof:placetype":"locality"
},
  "geometry": {"coordinates":[8.4109,11.71201],"type":"Point"}
}