{
  "type": "Feature",
  "properties": {
    "gn:admin1_code":"46.0",
    "gn:admin2_code":"5001.0",
    "gn:admin3_code":"BA0117",
    "gn:asciiname":"Zambu",
    "gn:country_code":"NG",
    "gn:dem":289,
    "gn:feature_class":"P",
    "gn:feature_code":"PPL",
    "gn:name":"Zambu",
    "gn:population":0,
    "gn:timezone":"Africa/Lagos",
    "iso:country":"NG",
    "name:eng_x_preferred":[
        "Zambu"
    ],
    "wof:name":"Zambu",
    "wof:placetype":"locality"
},
  "geometry": {"coordinates":[10.42204,10.02172],"type":"Point"}
}