{
  "type": "Feature",
  "properties": {
    "gn:admin1_code":"26.0",
    "gn:admin2_code":"7021",
    "gn:asciiname":"Tseanshiva",
    "gn:country_code":"NG",
    "gn:dem":120,
    "gn:feature_class":"P",
    "gn:feature_code":"PPL",
    "gn:name":"Tseanshiva",
    "gn:population":0,
    "gn:timezone":"Africa/Lagos",
    "iso:country":"NG",
    "name:und_x_variant":[
        "Tsewanshiva"
    ],
    "wof:name":"Tseanshiva",
    "wof:placetype":"locality"
},
  "geometry": {"coordinates":[9.46964,7.81898],"type":"Point"}
}