{
  "type": "Feature",
  "properties": {
    "gn:admin1_code":"36.0",
    "gn:asciiname":"Ugbegin",
    "gn:country_code":"NG",
    "gn:dem":6,
    "gn:feature_class":"P",
    "gn:feature_code":"PPL",
    "gn:name":"Ugbegin",
    "gn:population":0,
    "gn:timezone":"Africa/Lagos",
    "iso:country":"NG",
    "name:eng_x_preferred":[
        "Ugbegin"
    ],
    "wof:name":"Ugbegin",
    "wof:placetype":"locality"
},
  "geometry": {"coordinates":[5.11618,5.66267],"type":"Point"}
}