{
  "type": "Feature",
  "properties": {
    "gn:admin1_code":"43.0",
    "gn:admin2_code":"35005",
    "gn:asciiname":"Baba Nyamde",
    "gn:country_code":"NG",
    "gn:dem":176,
    "gn:feature_class":"P",
    "gn:feature_code":"PPL",
    "gn:name":"Baba Nyamde",
    "gn:population":0,
    "gn:timezone":"Africa/Lagos",
    "iso:country":"NG",
    "wof:name":"Baba Nyamde",
    "wof:placetype":"locality"
},
  "geometry": {"coordinates":[10.68656,8.4502],"type":"Point"}
}