{
  "type": "Feature",
  "properties": {
    "gn:admin1_code":"11.0",
    "gn:admin2_code":"15002.0",
    "gn:asciiname":"Igu",
    "gn:country_code":"NG",
    "gn:dem":664,
    "gn:feature_class":"P",
    "gn:feature_code":"PPL",
    "gn:name":"Igu",
    "gn:population":0,
    "gn:timezone":"Africa/Lagos",
    "iso:country":"NG",
    "wof:name":"Igu",
    "wof:placetype":"locality"
},
  "geometry": {"coordinates":[7.47379,9.27628],"type":"Point"}
}