{
  "type": "Feature",
  "properties": {
    "gn:admin1_code":"44.0",
    "gn:admin2_code":"705",
    "gn:admin3_code":"70515",
    "gn:asciiname":"Dindiwai",
    "gn:country_code":"NG",
    "gn:dem":415,
    "gn:feature_class":"P",
    "gn:feature_code":"PPL",
    "gn:name":"Dindiwai",
    "gn:population":0,
    "gn:timezone":"Africa/Lagos",
    "iso:country":"NG",
    "wof:name":"Dindiwai",
    "wof:placetype":"locality"
},
  "geometry": {"coordinates":[11.72184,11.74984],"type":"Point"}
}