{
  "type": "Feature",
  "properties": {
    "gn:admin1_code":"56.0",
    "gn:admin2_code":"26003.0",
    "gn:asciiname":"Gidan Bassa",
    "gn:country_code":"NG",
    "gn:dem":106,
    "gn:feature_class":"P",
    "gn:feature_code":"PPL",
    "gn:name":"Gidan Bassa",
    "gn:population":0,
    "gn:timezone":"Africa/Lagos",
    "iso:country":"NG",
    "wof:name":"Gidan Bassa",
    "wof:placetype":"locality"
},
  "geometry": {"coordinates":[8.1847,7.9737],"type":"Point"}
}