{
  "type": "Feature",
  "properties": {
    "gn:admin1_code":"50.0",
    "gn:admin2_code":"33008.0",
    "gn:asciiname":"Diepreye",
    "gn:country_code":"NG",
    "gn:dem":20,
    "gn:feature_class":"P",
    "gn:feature_code":"PPL",
    "gn:name":"Diepreye",
    "gn:population":0,
    "gn:timezone":"Africa/Lagos",
    "iso:country":"NG",
    "wof:name":"Diepreye",
    "wof:placetype":"locality"
},
  "geometry": {"coordinates":[6.76519,4.7772],"type":"Point"}
}