{
  "type": "Feature",
  "properties": {
    "gn:admin1_code":"49.0",
    "gn:admin2_code":"32017",
    "gn:asciiname":"Bang",
    "gn:country_code":"NG",
    "gn:dem":199,
    "gn:feature_class":"P",
    "gn:feature_code":"PPL",
    "gn:name":"Bang",
    "gn:population":0,
    "gn:timezone":"Africa/Lagos",
    "iso:country":"NG",
    "name:ces_x_preferred":[
        "Bang"
    ],
    "name:deu_x_preferred":[
        "Bang"
    ],
    "name:est_x_preferred":[
        "Bang"
    ],
    "name:fra_x_preferred":[
        "Bang"
    ],
    "name:ita_x_preferred":[
        "Bang"
    ],
    "name:nld_x_preferred":[
        "Bang"
    ],
    "name:por_x_preferred":[
        "Bang"
    ],
    "name:rus_x_preferred":[
        "\u0411\u044d\u043d\u0433"
    ],
    "name:slv_x_preferred":[
        "Bang"
    ],
    "name:spa_x_preferred":[
        "Bang"
    ],
    "name:swe_x_preferred":[
        "Bang"
    ],
    "name:ukr_x_preferred":[
        "\u0411\u0430\u043d\u0433"
    ],
    "wof:name":"Bang",
    "wof:placetype":"locality"
},
  "geometry": {"coordinates":[9.95553,8.91778],"type":"Point"}
}