{
  "type": "Feature",
  "properties": {
    "gn:admin1_code":"43.0",
    "gn:admin2_code":"35003",
    "gn:asciiname":"Tyonge",
    "gn:country_code":"NG",
    "gn:dem":140,
    "gn:feature_class":"P",
    "gn:feature_code":"PPL",
    "gn:name":"Tyonge",
    "gn:population":0,
    "gn:timezone":"Africa/Lagos",
    "iso:country":"NG",
    "wof:name":"Tyonge",
    "wof:placetype":"locality"
},
  "geometry": {"coordinates":[10.08224,7.64195],"type":"Point"}
}