{
  "type": "Feature",
  "properties": {
    "gn:admin1_code":"31.0",
    "gn:admin2_code":"27008",
    "gn:asciiname":"Nnashiru",
    "gn:country_code":"NG",
    "gn:dem":175,
    "gn:feature_class":"P",
    "gn:feature_code":"PPL",
    "gn:name":"Nnashiru",
    "gn:population":0,
    "gn:timezone":"Africa/Lagos",
    "iso:country":"NG",
    "wof:name":"Nnashiru",
    "wof:placetype":"locality"
},
  "geometry": {"coordinates":[5.9491,9.04819],"type":"Point"}
}