{
  "type": "Feature",
  "properties": {
    "gn:admin1_code":"51.0",
    "gn:admin2_code":"605.0",
    "gn:admin3_code":"60503",
    "gn:asciiname":"Dansulba",
    "gn:country_code":"NG",
    "gn:dem":264,
    "gn:feature_class":"P",
    "gn:feature_code":"PPL",
    "gn:name":"Dansulba",
    "gn:population":0,
    "gn:timezone":"Africa/Lagos",
    "iso:country":"NG",
    "wof:name":"Dansulba",
    "wof:placetype":"locality"
},
  "geometry": {"coordinates":[5.51592,13.33144],"type":"Point"}
}