{
  "type": "Feature",
  "properties": {
    "gn:admin1_code":"50.0",
    "gn:asciiname":"Ogbiriasa Camp",
    "gn:country_code":"NG",
    "gn:dem":23,
    "gn:feature_class":"P",
    "gn:feature_code":"PPL",
    "gn:name":"Ogbiriasa Camp",
    "gn:population":0,
    "gn:timezone":"Africa/Lagos",
    "iso:country":"NG",
    "wof:name":"Ogbiriasa Camp",
    "wof:placetype":"locality"
},
  "geometry": {"coordinates":[6.32036,5.29112],"type":"Point"}
}