{
  "type": "Feature",
  "properties": {
    "gn:admin1_code":"44.0",
    "gn:admin2_code":"705.0",
    "gn:admin3_code":"70503",
    "gn:asciiname":"Bulawoni",
    "gn:country_code":"NG",
    "gn:dem":406,
    "gn:feature_class":"P",
    "gn:feature_code":"PPL",
    "gn:name":"Bulawoni",
    "gn:population":0,
    "gn:timezone":"Africa/Lagos",
    "iso:country":"NG",
    "name:und_x_variant":[
        "Bulawone"
    ],
    "wof:name":"Bulawoni",
    "wof:placetype":"locality"
},
  "geometry": {"coordinates":[11.48813,11.52476],"type":"Point"}
}