{
  "type": "Feature",
  "properties": {
    "gn:admin1_code":"43.0",
    "gn:admin2_code":"35015.0",
    "gn:asciiname":"Zampa",
    "gn:country_code":"NG",
    "gn:dem":318,
    "gn:feature_class":"P",
    "gn:feature_code":"PPL",
    "gn:name":"Zampa",
    "gn:population":0,
    "gn:timezone":"Africa/Lagos",
    "iso:country":"NG",
    "name:cat_x_preferred":[
        "Zampa"
    ],
    "name:deu_x_preferred":[
        "Zampa"
    ],
    "name:fra_x_preferred":[
        "Zampa"
    ],
    "name:spa_x_preferred":[
        "Zampa"
    ],
    "name:swe_x_preferred":[
        "Zampa"
    ],
    "wof:name":"Zampa",
    "wof:placetype":"locality"
},
  "geometry": {"coordinates":[11.51046,8.82138],"type":"Point"}
}