{
  "type": "Feature",
  "properties": {
    "iso:country":"NG",
    "name:ceb_x_preferred":[
        "Lame"
    ],
    "name:deu_x_preferred":[
        "Lame"
    ],
    "name:fra_x_preferred":[
        "Lame"
    ],
    "name:rus_x_preferred":[
        "\u041b\u0430\u043c\u0435"
    ],
    "name:srp_x_preferred":[
        "Lame"
    ],
    "name:swe_x_preferred":[
        "Lame"
    ],
    "name:und_x_variant":[
        "Lemmi"
    ],
    "qs:gn_country":"NG",
    "qs:gn_fcode":"PPL",
    "qs:gn_pop":6705,
    "qs:name":"Lame",
    "qs:name_adm0":"Nigeria",
    "qs:name_adm1":"Bauchi",
    "qs:photos":0,
    "qs:photos_1k":0,
    "qs:photos_9k":0,
    "qs:photos_9r":0,
    "qs:photos_all":0,
    "qs:photos_sr":0,
    "qs:placetype":"Town",
    "qs:pop_sr":"5",
    "qs:woe_adm0":23424908,
    "wof:name":"Lame",
    "wof:placetype":"locality",
    "wof:population":6705
},
  "geometry": {"coordinates":[9.23955,10.44154],"type":"Point"}
}