{
  "type": "Feature",
  "properties": {
    "gn:admin1_code":"51.0",
    "gn:admin2_code":"619.0",
    "gn:admin3_code":"61909",
    "gn:asciiname":"Kwarka",
    "gn:country_code":"NG",
    "gn:dem":282,
    "gn:feature_class":"P",
    "gn:feature_code":"PPL",
    "gn:name":"Kwarka",
    "gn:population":0,
    "gn:timezone":"Africa/Lagos",
    "iso:country":"NG",
    "wof:name":"Kwarka",
    "wof:placetype":"locality"
},
  "geometry": {"coordinates":[5.05237,13.33101],"type":"Point"}
}