{
  "type": "Feature",
  "properties": {
    "gn:admin1_code":"51.0",
    "gn:admin2_code":"612.0",
    "gn:admin3_code":"61205",
    "gn:asciiname":"Marinawa",
    "gn:country_code":"NG",
    "gn:dem":279,
    "gn:feature_class":"P",
    "gn:feature_code":"PPL",
    "gn:name":"Marinawa",
    "gn:population":0,
    "gn:timezone":"Africa/Lagos",
    "iso:country":"NG",
    "wof:name":"Marinawa",
    "wof:placetype":"locality"
},
  "geometry": {"coordinates":[5.50596,13.07858],"type":"Point"}
}