{
  "type": "Feature",
  "properties": {
    "gn:admin1_code":"40.0",
    "gn:admin2_code":"517.0",
    "gn:admin3_code":"51705",
    "gn:asciiname":"Sangara",
    "gn:country_code":"NG",
    "gn:dem":198,
    "gn:feature_class":"P",
    "gn:feature_code":"PPL",
    "gn:name":"Sangara",
    "gn:population":0,
    "gn:timezone":"Africa/Lagos",
    "iso:country":"NG",
    "name:ita_x_preferred":[
        "Sangara"
    ],
    "wof:name":"Sangara",
    "wof:placetype":"locality"
},
  "geometry": {"coordinates":[4.60468,11.37659],"type":"Point"}
}