{
  "type": "Feature",
  "properties": {
    "gn:admin1_code":"22.0",
    "gn:admin2_code":"9006.0",
    "gn:asciiname":"Akunakuna",
    "gn:country_code":"NG",
    "gn:dem":10,
    "gn:feature_class":"P",
    "gn:feature_code":"PPL",
    "gn:name":"Akunakuna",
    "gn:population":0,
    "gn:timezone":"Africa/Lagos",
    "iso:country":"NG",
    "name:fra_x_preferred":[
        "Akunakuna"
    ],
    "wof:name":"Akunakuna",
    "wof:placetype":"locality"
},
  "geometry": {"coordinates":[8.0287,5.6554],"type":"Point"}
}