{
  "type": "Feature",
  "properties": {
    "gn:admin1_code":"35.0",
    "gn:admin2_code":"2008",
    "gn:asciiname":"Tapare Jangla",
    "gn:country_code":"NG",
    "gn:dem":449,
    "gn:feature_class":"P",
    "gn:feature_code":"PPL",
    "gn:name":"Tapare Jangla",
    "gn:population":0,
    "gn:timezone":"Africa/Lagos",
    "iso:country":"NG",
    "wof:name":"Tapare Jangla",
    "wof:placetype":"locality"
},
  "geometry": {"coordinates":[12.44529,8.66023],"type":"Point"}
}