{
  "type": "Feature",
  "properties": {
    "gn:admin1_code":"23.0",
    "gn:admin2_code":"19004.0",
    "gn:admin3_code":"KD0411",
    "gn:asciiname":"Dusa Ma",
    "gn:country_code":"NG",
    "gn:dem":677,
    "gn:feature_class":"P",
    "gn:feature_code":"PPL",
    "gn:name":"Dusa Ma",
    "gn:population":0,
    "gn:timezone":"Africa/Lagos",
    "iso:country":"NG",
    "name:und_x_variant":[
        "Dusa Mai",
        "Dusa Ma"
    ],
    "wof:name":"Dusa Ma",
    "wof:placetype":"locality"
},
  "geometry": {"coordinates":[7.69764,10.85136],"type":"Point"}
}