{
  "type": "Feature",
  "properties": {
    "gn:admin1_code":"37.0",
    "gn:admin2_code":"12009.0",
    "gn:asciiname":"Ikpe",
    "gn:country_code":"NG",
    "gn:dem":287,
    "gn:feature_class":"P",
    "gn:feature_code":"PPL",
    "gn:name":"Ikpe",
    "gn:population":0,
    "gn:timezone":"Africa/Lagos",
    "iso:country":"NG",
    "wof:name":"Ikpe",
    "wof:placetype":"neighbourhood"
},
  "geometry": {"coordinates":[6.3098,7.0947],"type":"Point"}
}