{
  "type": "Feature",
  "properties": {
    "gn:admin1_code":"51.0",
    "gn:admin2_code":"618.0",
    "gn:admin3_code":"61811",
    "gn:asciiname":"Kaurari",
    "gn:country_code":"NG",
    "gn:dem":265,
    "gn:feature_class":"P",
    "gn:feature_code":"PPL",
    "gn:name":"Kaurari",
    "gn:population":0,
    "gn:timezone":"Africa/Lagos",
    "iso:country":"NG",
    "wof:name":"Kaurari",
    "wof:placetype":"locality"
},
  "geometry": {"coordinates":[4.63782,12.35278],"type":"Point"}
}