{
  "type": "Feature",
  "properties": {
    "gn:admin1_code":"11.0",
    "gn:admin2_code":"15002",
    "gn:asciiname":"Baban-Rafi",
    "gn:country_code":"NG",
    "gn:dem":713,
    "gn:feature_class":"P",
    "gn:feature_code":"PPL",
    "gn:name":"Baban-Rafi",
    "gn:population":0,
    "gn:timezone":"Africa/Lagos",
    "iso:country":"NG",
    "wof:name":"Baban-Rafi",
    "wof:placetype":"locality"
},
  "geometry": {"coordinates":[7.58694,9.29931],"type":"Point"}
}