{
  "type": "Feature",
  "properties": {
    "gn:admin1_code":"52.0",
    "gn:admin2_code":"6001.0",
    "gn:asciiname":"Kurugbaba",
    "gn:country_code":"NG",
    "gn:dem":8,
    "gn:feature_class":"P",
    "gn:feature_code":"PPL",
    "gn:name":"Kurugbaba",
    "gn:population":0,
    "gn:timezone":"Africa/Lagos",
    "iso:country":"NG",
    "name:und_x_variant":[
        "Korugbaba",
        "Kurugbaba"
    ],
    "wof:name":"Kurugbaba",
    "wof:placetype":"locality"
},
  "geometry": {"coordinates":[6.26788,4.35672],"type":"Point"}
}