{
  "type": "Feature",
  "properties": {
    "gn:admin1_code":"29.0",
    "gn:admin2_code":"20010.0",
    "gn:admin3_code":"KN1706",
    "gn:asciiname":"Dage",
    "gn:country_code":"NG",
    "gn:dem":443,
    "gn:feature_class":"P",
    "gn:feature_code":"PPL",
    "gn:name":"Dage",
    "gn:population":0,
    "gn:timezone":"Africa/Lagos",
    "iso:country":"NG",
    "wof:name":"Dage",
    "wof:placetype":"locality"
},
  "geometry": {"coordinates":[8.73598,12.10013],"type":"Point"}
}