{
  "type": "Feature",
  "properties": {
    "gn:admin1_code":"43.0",
    "gn:asciiname":"Ungwar Toro",
    "gn:country_code":"NG",
    "gn:dem":129,
    "gn:feature_class":"P",
    "gn:feature_code":"PPL",
    "gn:name":"Ungwar Toro",
    "gn:population":0,
    "gn:timezone":"Africa/Lagos",
    "iso:country":"NG",
    "name:eng_x_preferred":[
        "Ungwar Toro"
    ],
    "wof:name":"Ungwar Toro",
    "wof:placetype":"locality"
},
  "geometry": {"coordinates":[11.05266,9.1767],"type":"Point"}
}