{
  "type": "Feature",
  "properties": {
    "gn:admin1_code":"44.0",
    "gn:admin2_code":"710.0",
    "gn:admin3_code":"71001",
    "gn:asciiname":"Bukarti",
    "gn:country_code":"NG",
    "gn:dem":342,
    "gn:feature_class":"P",
    "gn:feature_code":"PPL",
    "gn:name":"Bukarti",
    "gn:population":0,
    "gn:timezone":"Africa/Lagos",
    "iso:country":"NG",
    "wof:name":"Bukarti",
    "wof:placetype":"locality"
},
  "geometry": {"coordinates":[10.9076,12.89432],"type":"Point"}
}