{
  "type": "Feature",
  "properties": {
    "gn:admin1_code":"27.0",
    "gn:admin2_code":"127.0",
    "gn:admin3_code":"12704",
    "gn:asciiname":"Mada",
    "gn:country_code":"NG",
    "gn:dem":198,
    "gn:feature_class":"P",
    "gn:feature_code":"PPL",
    "gn:name":"Mada",
    "gn:population":0,
    "gn:timezone":"Africa/Lagos",
    "iso:country":"NG",
    "name:fra_x_preferred":[
        "Mada"
    ],
    "wof:name":"Mada",
    "wof:placetype":"locality"
},
  "geometry": {"coordinates":[11.96529,10.02723],"type":"Point"}
}