{
  "type": "Feature",
  "properties": {
    "gn:admin1_code":"40.0",
    "gn:admin2_code":"512.0",
    "gn:admin3_code":"51202",
    "gn:asciiname":"Nyanga Hausawa",
    "gn:country_code":"NG",
    "gn:dem":242,
    "gn:feature_class":"P",
    "gn:feature_code":"PPL",
    "gn:name":"Nyanga Hausawa",
    "gn:population":0,
    "gn:timezone":"Africa/Lagos",
    "iso:country":"NG",
    "wof:name":"Nyanga Hausawa",
    "wof:placetype":"locality"
},
  "geometry": {"coordinates":[4.05174,12.30863],"type":"Point"}
}