{
  "type": "Feature",
  "properties": {
    "gn:admin1_code":"43.0",
    "gn:admin2_code":"35008.0",
    "gn:asciiname":"Kwade",
    "gn:country_code":"NG",
    "gn:dem":230,
    "gn:feature_class":"P",
    "gn:feature_code":"PPL",
    "gn:name":"Kwade",
    "gn:population":0,
    "gn:timezone":"Africa/Lagos",
    "iso:country":"NG",
    "name:eng_x_preferred":[
        "Kwade"
    ],
    "name:eng_x_variant":[
        "Kode Kassa"
    ],
    "wof:name":"Kwade",
    "wof:placetype":"locality"
},
  "geometry": {"coordinates":[11.18377,9.43373],"type":"Point"}
}