{
  "type": "Feature",
  "properties": {
    "gn:admin1_code":"48.0",
    "gn:admin2_code":"29008.0",
    "gn:asciiname":"Igbo-Olokun",
    "gn:country_code":"NG",
    "gn:dem":267,
    "gn:feature_class":"P",
    "gn:feature_code":"PPL",
    "gn:name":"Igbo-Olokun",
    "gn:population":0,
    "gn:timezone":"Africa/Lagos",
    "iso:country":"NG",
    "wof:name":"Igbo-Olokun",
    "wof:placetype":"locality"
},
  "geometry": {"coordinates":[5.139,7.057],"type":"Point"}
}