{
  "type": "Feature",
  "properties": {
    "gn:admin1_code":"31.0",
    "gn:admin2_code":"27018.0",
    "gn:asciiname":"Adnami",
    "gn:country_code":"NG",
    "gn:dem":429,
    "gn:feature_class":"P",
    "gn:feature_code":"PPL",
    "gn:name":"Adnami",
    "gn:population":0,
    "gn:timezone":"Africa/Lagos",
    "iso:country":"NG",
    "name:und_x_variant":[
        "Adami",
        "Adnami"
    ],
    "wof:name":"Adnami",
    "wof:placetype":"locality"
},
  "geometry": {"coordinates":[7.0817,10.00922],"type":"Point"}
}