{
  "type": "Feature",
  "properties": {
    "gn:admin1_code":"5.0",
    "gn:asciiname":"Oke Ogbe",
    "gn:country_code":"NG",
    "gn:dem":35,
    "gn:feature_class":"P",
    "gn:feature_code":"PPL",
    "gn:name":"Oke Ogbe",
    "gn:population":0,
    "gn:timezone":"Africa/Lagos",
    "iso:country":"NG",
    "name:und_x_variant":[
        "Abekkun",
        "Oko Agbo",
        "Abagbo",
        "Oke Ogbe"
    ],
    "wof:name":"Oke Ogbe",
    "wof:placetype":"neighbourhood"
},
  "geometry": {"coordinates":[3.38141,6.40737],"type":"Point"}
}