{
  "type": "Feature",
  "properties": {
    "gn:admin1_code":"31.0",
    "gn:admin2_code":"27005",
    "gn:asciiname":"New Gurusupe",
    "gn:country_code":"NG",
    "gn:dem":323,
    "gn:feature_class":"P",
    "gn:feature_code":"PPL",
    "gn:name":"New Gurusupe",
    "gn:population":0,
    "gn:timezone":"Africa/Lagos",
    "iso:country":"NG",
    "wof:name":"New Gurusupe",
    "wof:placetype":"locality"
},
  "geometry": {"coordinates":[6.63096,9.63652],"type":"Point"}
}