{
  "type": "Feature",
  "properties": {
    "gn:admin1_code":"32.0",
    "gn:admin2_code":"31025.0",
    "gn:asciiname":"Abada",
    "gn:country_code":"NG",
    "gn:dem":176,
    "gn:feature_class":"P",
    "gn:feature_code":"PPL",
    "gn:name":"Abada",
    "gn:population":0,
    "gn:timezone":"Africa/Lagos",
    "iso:country":"NG",
    "name:ceb_x_preferred":[
        "Abada"
    ],
    "name:deu_x_preferred":[
        "Abada"
    ],
    "name:fra_x_preferred":[
        "Abada"
    ],
    "wof:name":"Abada",
    "wof:placetype":"locality"
},
  "geometry": {"coordinates":[3.81722,7.305],"type":"Point"}
}