{
  "type": "Feature",
  "properties": {
    "gn:admin1_code":"27.0",
    "gn:admin2_code":"119",
    "gn:admin3_code":"11901",
    "gn:asciiname":"Gujuri",
    "gn:country_code":"NG",
    "gn:dem":307,
    "gn:feature_class":"P",
    "gn:feature_code":"PPL",
    "gn:name":"Gujuri",
    "gn:population":0,
    "gn:timezone":"Africa/Lagos",
    "iso:country":"NG",
    "wof:name":"Gujuri",
    "wof:placetype":"locality"
},
  "geometry": {"coordinates":[13.68996,11.80529],"type":"Point"}
}