{
  "type": "Feature",
  "properties": {
    "gn:admin1_code":"48.0",
    "gn:admin2_code":"29007.0",
    "gn:asciiname":"Lalate",
    "gn:country_code":"NG",
    "gn:dem":15,
    "gn:feature_class":"P",
    "gn:feature_code":"PPL",
    "gn:name":"Lalate",
    "gn:population":0,
    "gn:timezone":"Africa/Lagos",
    "iso:country":"NG",
    "wof:name":"Lalate",
    "wof:placetype":"locality"
},
  "geometry": {"coordinates":[4.95733,6.16517],"type":"Point"}
}