{
  "type": "Feature",
  "properties": {
    "gn:country":"NG",
    "gn:fcode":"PPL",
    "gn:population":15538,
    "iso:country":"NG",
    "qs_pg:aaroncc":"NG",
    "qs_pg:gn_country":"NG",
    "qs_pg:gn_fcode":"PPL",
    "qs_pg:gn_pop":15538,
    "qs_pg:name":"Anchau",
    "qs_pg:photos_9r":0,
    "qs_pg:photos_sr":0,
    "qs_pg:pop_sr":6,
    "qs_pg:qs_pg_placetype":"locality",
    "wof:name":"Anchau",
    "wof:placetype":"locality",
    "wof:population":15538
},
  "geometry": {"coordinates":[8.39155,10.95967],"type":"Point"}
}