{
  "type": "Feature",
  "properties": {
    "gn:admin1_code":"35.0",
    "gn:admin2_code":"2002",
    "gn:asciiname":"Gidou",
    "gn:country_code":"NG",
    "gn:dem":411,
    "gn:feature_class":"P",
    "gn:feature_code":"PPL",
    "gn:name":"Gidou",
    "gn:population":0,
    "gn:timezone":"Africa/Lagos",
    "iso:country":"NG",
    "wof:name":"Gidou",
    "wof:placetype":"locality"
},
  "geometry": {"coordinates":[12.40171,8.94607],"type":"Point"}
}