{
  "type": "Feature",
  "properties": {
    "gn:admin1_code":"45.0",
    "gn:asciiname":"Ohaobu",
    "gn:country_code":"NG",
    "gn:dem":36,
    "gn:feature_class":"P",
    "gn:feature_code":"PPL",
    "gn:name":"Ohaobu",
    "gn:population":0,
    "gn:timezone":"Africa/Lagos",
    "iso:country":"NG",
    "wof:name":"Ohaobu",
    "wof:placetype":"locality"
},
  "geometry": {"coordinates":[7.49809,4.8823],"type":"Point"}
}