{
  "type": "Feature",
  "properties": {
    "gn:admin1_code":"46.0",
    "gn:admin2_code":"5014.0",
    "gn:admin3_code":"BA1406",
    "gn:asciiname":"Sebore",
    "gn:country_code":"NG",
    "gn:dem":453,
    "gn:feature_class":"P",
    "gn:feature_code":"PPL",
    "gn:name":"Sebore",
    "gn:population":0,
    "gn:timezone":"Africa/Lagos",
    "iso:country":"NG",
    "wof:name":"Sebore",
    "wof:placetype":"locality"
},
  "geometry": {"coordinates":[10.45071,11.41319],"type":"Point"}
}