{
  "type": "Feature",
  "properties": {
    "gn:admin1_code":"31.0",
    "gn:admin2_code":"27008",
    "gn:asciiname":"Gidan Yarbawa",
    "gn:country_code":"NG",
    "gn:dem":118,
    "gn:feature_class":"P",
    "gn:feature_code":"PPL",
    "gn:name":"Gidan Yarbawa",
    "gn:population":0,
    "gn:timezone":"Africa/Lagos",
    "iso:country":"NG",
    "wof:name":"Gidan Yarbawa",
    "wof:placetype":"locality"
},
  "geometry": {"coordinates":[6.04799,9.34532],"type":"Point"}
}