{
  "type": "Feature",
  "properties": {
    "gn:admin1_code":"23.0",
    "gn:admin2_code":"19007.0",
    "gn:admin3_code":"KD0705",
    "gn:asciiname":"Godogodo",
    "gn:country_code":"NG",
    "gn:dem":545,
    "gn:feature_class":"P",
    "gn:feature_code":"PPL",
    "gn:name":"Godogodo",
    "gn:population":0,
    "gn:timezone":"Africa/Lagos",
    "iso:country":"NG",
    "wof:name":"Godogodo",
    "wof:placetype":"locality"
},
  "geometry": {"coordinates":[8.35371,9.43251],"type":"Point"}
}