{
  "type": "Feature",
  "properties": {
    "gn:admin1_code":"28.0",
    "gn:admin2_code":"17003.0",
    "gn:asciiname":"Umuchiokwa Agbaja",
    "gn:country_code":"NG",
    "gn:dem":92,
    "gn:feature_class":"P",
    "gn:feature_code":"PPL",
    "gn:name":"Umuchiokwa Agbaja",
    "gn:population":0,
    "gn:timezone":"Africa/Lagos",
    "iso:country":"NG",
    "wof:name":"Umuchiokwa Agbaja",
    "wof:placetype":"locality"
},
  "geometry": {"coordinates":[7.32355,5.69274],"type":"Point"}
}