{
  "type": "Feature",
  "properties": {
    "gn:admin1_code":"51.0",
    "gn:admin2_code":"611.0",
    "gn:admin3_code":"61110",
    "gn:asciiname":"Walake",
    "gn:country_code":"NG",
    "gn:dem":316,
    "gn:feature_class":"P",
    "gn:feature_code":"PPL",
    "gn:name":"Walake",
    "gn:population":0,
    "gn:timezone":"Africa/Lagos",
    "iso:country":"NG",
    "wof:name":"Walake",
    "wof:placetype":"locality"
},
  "geometry": {"coordinates":[5.34607,12.99305],"type":"Point"}
}