{
  "type": "Feature",
  "properties": {
    "gn:admin1_code":"27.0",
    "gn:admin2_code":"106.0",
    "gn:admin3_code":"10608",
    "gn:asciiname":"Mbowa Paiyagarga",
    "gn:country_code":"NG",
    "gn:dem":458,
    "gn:feature_class":"P",
    "gn:feature_code":"PPL",
    "gn:name":"Mbowa Paiyagarga",
    "gn:population":0,
    "gn:timezone":"Africa/Lagos",
    "iso:country":"NG",
    "wof:name":"Mbowa Paiyagarga",
    "wof:placetype":"locality"
},
  "geometry": {"coordinates":[12.76975,10.92869],"type":"Point"}
}