{
  "type": "Feature",
  "properties": {
    "gn:admin1_code":"51.0",
    "gn:admin2_code":"601.0",
    "gn:admin3_code":"60102",
    "gn:asciiname":"Gidan Dulo",
    "gn:country_code":"NG",
    "gn:dem":271,
    "gn:feature_class":"P",
    "gn:feature_code":"PPL",
    "gn:name":"Gidan Dulo",
    "gn:population":0,
    "gn:timezone":"Africa/Lagos",
    "iso:country":"NG",
    "wof:name":"Gidan Dulo",
    "wof:placetype":"locality"
},
  "geometry": {"coordinates":[4.94921,13.123],"type":"Point"}
}