{
  "type": "Feature",
  "properties": {
    "gn:admin1_code":"48.0",
    "gn:admin2_code":"29010.0",
    "gn:asciiname":"Ugbene",
    "gn:cc2":"NG",
    "gn:country_code":"NG",
    "gn:dem":8,
    "gn:feature_class":"P",
    "gn:feature_code":"PPL",
    "gn:name":"Ugbene",
    "gn:population":0,
    "gn:timezone":"Africa/Lagos",
    "iso:country":"NG",
    "name:und_x_variant":[
        "Italuwa",
        "Ugbene"
    ],
    "wof:name":"Ugbene",
    "wof:placetype":"locality"
},
  "geometry": {"coordinates":[4.86667,6.41667],"type":"Point"}
}