{
  "type": "Feature",
  "properties": {
    "gn:admin1_code":"26.0",
    "gn:admin2_code":"7005",
    "gn:asciiname":"Sorakaa",
    "gn:country_code":"NG",
    "gn:dem":200,
    "gn:feature_class":"P",
    "gn:feature_code":"PPL",
    "gn:name":"Sorakaa",
    "gn:population":0,
    "gn:timezone":"Africa/Lagos",
    "iso:country":"NG",
    "wof:name":"Sorakaa",
    "wof:placetype":"locality"
},
  "geometry": {"coordinates":[8.92006,7.36104],"type":"Point"}
}