{
  "type": "Feature",
  "properties": {
    "gn:admin1_code":"29.0",
    "gn:admin2_code":"20041.0",
    "gn:admin3_code":"KN2210",
    "gn:asciiname":"Ma",
    "gn:country_code":"NG",
    "gn:dem":533,
    "gn:feature_class":"P",
    "gn:feature_code":"PPL",
    "gn:name":"Ma",
    "gn:population":0,
    "gn:timezone":"Africa/Lagos",
    "iso:country":"NG",
    "wof:name":"Ma",
    "wof:placetype":"locality"
},
  "geometry": {"coordinates":[7.95046,11.68833],"type":"Point"}
}