{
  "type": "Feature",
  "properties": {
    "gn:admin1_code":"35.0",
    "gn:asciiname":"Kugama",
    "gn:country_code":"NG",
    "gn:dem":373,
    "gn:feature_class":"P",
    "gn:feature_code":"PPL",
    "gn:name":"Kugama",
    "gn:population":0,
    "gn:timezone":"Africa/Lagos",
    "iso:country":"NG",
    "name:eng_x_preferred":[
        "Kugama"
    ],
    "wof:name":"Kugama",
    "wof:placetype":"locality"
},
  "geometry": {"coordinates":[11.89967,9.11318],"type":"Point"}
}