{
  "type": "Feature",
  "properties": {
    "gn:admin1_code":"51.0",
    "gn:admin2_code":"608.0",
    "gn:admin3_code":"60808",
    "gn:asciiname":"Jaima",
    "gn:country_code":"NG",
    "gn:dem":285,
    "gn:feature_class":"P",
    "gn:feature_code":"PPL",
    "gn:name":"Jaima",
    "gn:population":0,
    "gn:timezone":"Africa/Lagos",
    "iso:country":"NG",
    "wof:name":"Jaima",
    "wof:placetype":"locality"
},
  "geometry": {"coordinates":[5.18446,13.73425],"type":"Point"}
}