{
  "type": "Feature",
  "properties": {
    "gn:admin1_code":"46.0",
    "gn:admin2_code":"5014.0",
    "gn:admin3_code":"BA1416",
    "gn:asciiname":"Sarma",
    "gn:country_code":"NG",
    "gn:dem":390,
    "gn:feature_class":"P",
    "gn:feature_code":"PPL",
    "gn:name":"Sarma",
    "gn:population":0,
    "gn:timezone":"Africa/Lagos",
    "iso:country":"NG",
    "name:ceb_x_preferred":[
        "Sarma"
    ],
    "name:deu_x_preferred":[
        "Sarma"
    ],
    "name:fra_x_preferred":[
        "Sarma"
    ],
    "name:ita_x_preferred":[
        "Sarma"
    ],
    "name:jpn_x_preferred":[
        "\u30b5\u30eb\u30de"
    ],
    "name:lav_x_preferred":[
        "Sarma"
    ],
    "name:nld_x_preferred":[
        "Sarma"
    ],
    "name:pol_x_preferred":[
        "Sarma"
    ],
    "name:scn_x_preferred":[
        "Sarma"
    ],
    "name:swe_x_preferred":[
        "Dolmar#Sarma"
    ],
    "wof:name":"Sarma",
    "wof:placetype":"locality"
},
  "geometry": {"coordinates":[10.63333,11.43333],"type":"Point"}
}