{
  "type": "Feature",
  "properties": {
    "gn:admin1_code":"27.0",
    "gn:admin2_code":"112.0",
    "gn:admin3_code":"11203",
    "gn:asciiname":"Bila Azi",
    "gn:country_code":"NG",
    "gn:dem":425,
    "gn:feature_class":"P",
    "gn:feature_code":"PPL",
    "gn:name":"Bila Azi",
    "gn:population":0,
    "gn:timezone":"Africa/Lagos",
    "iso:country":"NG",
    "wof:name":"Bila Azi",
    "wof:placetype":"locality"
},
  "geometry": {"coordinates":[12.04785,10.3705],"type":"Point"}
}