{
  "type": "Feature",
  "properties": {
    "gn:admin1_code":"26.0",
    "gn:admin2_code":"7012",
    "gn:asciiname":"Andyar",
    "gn:country_code":"NG",
    "gn:dem":161,
    "gn:feature_class":"P",
    "gn:feature_code":"PPL",
    "gn:name":"Andyar",
    "gn:population":0,
    "gn:timezone":"Africa/Lagos",
    "iso:country":"NG",
    "wof:name":"Andyar",
    "wof:placetype":"locality"
},
  "geometry": {"coordinates":[9.04314,7.75692],"type":"Point"}
}