{
  "type": "Feature",
  "properties": {
    "gn:admin1_code":"26.0",
    "gn:admin2_code":"7014.0",
    "gn:asciiname":"Ameka",
    "gn:country_code":"NG",
    "gn:dem":84,
    "gn:feature_class":"P",
    "gn:feature_code":"PPL",
    "gn:name":"Ameka",
    "gn:population":0,
    "gn:timezone":"Africa/Lagos",
    "iso:country":"NG",
    "name:und_x_variant":[
        "Angmekka",
        "Ameke",
        "Ameka"
    ],
    "wof:name":"Ameka",
    "wof:placetype":"locality"
},
  "geometry": {"coordinates":[8.29025,7.08874],"type":"Point"}
}