{
  "type": "Feature",
  "properties": {
    "gn:admin1_code":"52.0",
    "gn:admin2_code":"6008.0",
    "gn:asciiname":"Obina",
    "gn:country_code":"NG",
    "gn:dem":12,
    "gn:feature_class":"P",
    "gn:feature_code":"PPL",
    "gn:name":"Obina",
    "gn:population":0,
    "gn:timezone":"Africa/Lagos",
    "iso:country":"NG",
    "name:azb_x_preferred":[
        "\u0627\u0648\u0628\u06cc\u0646\u0627"
    ],
    "name:deu_x_preferred":[
        "Obina"
    ],
    "name:fas_x_preferred":[
        "\u0627\u0648\u0628\u06cc\u0646\u0627"
    ],
    "name:fra_x_preferred":[
        "Obina"
    ],
    "name:ita_x_preferred":[
        "Obina"
    ],
    "name:jpn_x_preferred":[
        "\u30aa\u30d3\u30ca"
    ],
    "name:por_x_preferred":[
        "Obina"
    ],
    "name:tgk_x_preferred":[
        "\u041e\u0431\u0438\u043d\u0430"
    ],
    "name:zho_x_preferred":[
        "\u5965\u6bd4\u7eb3"
    ],
    "wof:name":"Obina",
    "wof:placetype":"locality"
},
  "geometry": {"coordinates":[6.31105,5.03147],"type":"Point"}
}