{
  "type": "Feature",
  "properties": {
    "gn:admin1_code":"27.0",
    "gn:admin2_code":"108.0",
    "gn:admin3_code":"10807",
    "gn:asciiname":"Badiri",
    "gn:country_code":"NG",
    "gn:dem":297,
    "gn:feature_class":"P",
    "gn:feature_code":"PPL",
    "gn:name":"Badiri",
    "gn:population":0,
    "gn:timezone":"Africa/Lagos",
    "iso:country":"NG",
    "wof:name":"Badiri",
    "wof:placetype":"locality"
},
  "geometry": {"coordinates":[14.25616,11.88935],"type":"Point"}
}