{
  "type": "Feature",
  "properties": {
    "gn:admin1_code":"35.0",
    "gn:admin2_code":"2007.0",
    "gn:asciiname":"Burra",
    "gn:country_code":"NG",
    "gn:dem":576,
    "gn:feature_class":"P",
    "gn:feature_code":"PPL",
    "gn:name":"Burra",
    "gn:population":0,
    "gn:timezone":"Africa/Lagos",
    "iso:country":"NG",
    "name:ceb_x_preferred":[
        "Burra"
    ],
    "name:deu_x_preferred":[
        "Burra"
    ],
    "name:fra_x_preferred":[
        "Burra"
    ],
    "name:ita_x_preferred":[
        "Burra"
    ],
    "name:pol_x_preferred":[
        "Burra"
    ],
    "name:swe_x_preferred":[
        "Burra"
    ],
    "wof:name":"Burra",
    "wof:placetype":"locality"
},
  "geometry": {"coordinates":[13.1637,10.29839],"type":"Point"}
}