{
  "type": "Feature",
  "properties": {
    "gn:admin1_code":"27.0",
    "gn:asciiname":"Sadigo",
    "gn:country_code":"NG",
    "gn:dem":292,
    "gn:feature_class":"P",
    "gn:feature_code":"PPL",
    "gn:name":"Sadigo",
    "gn:population":0,
    "gn:timezone":"Africa/Lagos",
    "iso:country":"NG",
    "wof:name":"Sadigo",
    "wof:placetype":"locality"
},
  "geometry": {"coordinates":[14.51782,12.31728],"type":"Point"}
}