{
  "type": "Feature",
  "properties": {
    "gn:admin1_code":"29.0",
    "gn:admin2_code":"20025.0",
    "gn:admin3_code":"KN0409",
    "gn:asciiname":"Kargo",
    "gn:country_code":"NG",
    "gn:dem":532,
    "gn:feature_class":"P",
    "gn:feature_code":"PPL",
    "gn:name":"Kargo",
    "gn:population":0,
    "gn:timezone":"Africa/Lagos",
    "iso:country":"NG",
    "name:deu_x_preferred":[
        "Kargo"
    ],
    "name:fas_x_preferred":[
        "\u06a9\u0627\u0631\u06af\u0648"
    ],
    "name:fra_x_preferred":[
        "Kargo"
    ],
    "name:hun_x_preferred":[
        "Kargo"
    ],
    "name:rus_x_preferred":[
        "Kargo"
    ],
    "name:tur_x_preferred":[
        "Kargo"
    ],
    "wof:name":"Kargo",
    "wof:placetype":"locality"
},
  "geometry": {"coordinates":[8.37115,11.39605],"type":"Point"}
}