{
  "type": "Feature",
  "properties": {
    "gn:admin1_code":"35.0",
    "gn:admin2_code":"2004.0",
    "gn:asciiname":"Wuro Bajam",
    "gn:cc2":"NG",
    "gn:country_code":"NG",
    "gn:dem":230,
    "gn:feature_class":"P",
    "gn:feature_code":"PPL",
    "gn:name":"Wuro Bajam",
    "gn:population":0,
    "gn:timezone":"Africa/Lagos",
    "iso:country":"NG",
    "name:und_x_variant":[
        "Baijam",
        "Wuro Bajam"
    ],
    "wof:name":"Wuro Bajam",
    "wof:placetype":"locality"
},
  "geometry": {"coordinates":[12.46667,9.58333],"type":"Point"}
}