{
  "type": "Feature",
  "properties": {
    "gn:admin1_code":"39.0",
    "gn:admin2_code":"18001.0",
    "gn:admin3_code":"JI1601",
    "gn:asciiname":"Dumbari",
    "gn:country_code":"NG",
    "gn:dem":361,
    "gn:feature_class":"P",
    "gn:feature_code":"PPL",
    "gn:name":"Dumbari",
    "gn:population":0,
    "gn:timezone":"Africa/Lagos",
    "iso:country":"NG",
    "wof:name":"Dumbari",
    "wof:placetype":"locality"
},
  "geometry": {"coordinates":[9.79473,12.53382],"type":"Point"}
}