{
  "type": "Feature",
  "properties": {
    "gn:admin1_code":"26.0",
    "gn:admin2_code":"7012",
    "gn:asciiname":"Uchar",
    "gn:country_code":"NG",
    "gn:dem":182,
    "gn:feature_class":"P",
    "gn:feature_code":"PPL",
    "gn:name":"Uchar",
    "gn:population":0,
    "gn:timezone":"Africa/Lagos",
    "iso:country":"NG",
    "name:est_x_preferred":[
        "Ut\u0161ar"
    ],
    "name:fas_x_preferred":[
        "\u0627\u0648\u0686\u0627\u0631"
    ],
    "name:kir_x_preferred":[
        "\u0423\u0447\u0430\u0440"
    ],
    "name:urd_x_preferred":[
        "\u0627\u0686\u0631"
    ],
    "name:uzb_x_preferred":[
        "Uchar"
    ],
    "wof:name":"Uchar",
    "wof:placetype":"locality"
},
  "geometry": {"coordinates":[9.16853,7.74256],"type":"Point"}
}