{
  "type": "Feature",
  "properties": {
    "gn:admin1_code":"55.0",
    "gn:admin2_code":"16009.0",
    "gn:asciiname":"Dadin Kowa",
    "gn:country_code":"NG",
    "gn:dem":340,
    "gn:feature_class":"P",
    "gn:feature_code":"PPL",
    "gn:name":"Dadin Kowa",
    "gn:population":0,
    "gn:timezone":"Africa/Lagos",
    "iso:country":"NG",
    "wof:name":"Dadin Kowa",
    "wof:placetype":"locality"
},
  "geometry": {"coordinates":[11.18826,11.12209],"type":"Point"}
}