{
  "type": "Feature",
  "properties": {
    "gn:admin1_code":"29.0",
    "gn:admin2_code":"20040.0",
    "gn:admin3_code":"KN3002",
    "gn:asciiname":"Sabon Gari Fako",
    "gn:country_code":"NG",
    "gn:dem":456,
    "gn:feature_class":"P",
    "gn:feature_code":"PPL",
    "gn:name":"Sabon Gari Fako",
    "gn:population":0,
    "gn:timezone":"Africa/Lagos",
    "iso:country":"NG",
    "wof:name":"Sabon Gari Fako",
    "wof:placetype":"locality"
},
  "geometry": {"coordinates":[8.61934,12.15935],"type":"Point"}
}