{
  "type": "Feature",
  "properties": {
    "gn:admin1_code":"23.0",
    "gn:asciiname":"Kuguru",
    "gn:country_code":"NG",
    "gn:dem":635,
    "gn:feature_class":"P",
    "gn:feature_code":"PPL",
    "gn:name":"Kuguru",
    "gn:population":0,
    "gn:timezone":"Africa/Lagos",
    "iso:country":"NG",
    "wof:name":"Kuguru",
    "wof:placetype":"locality"
},
  "geometry": {"coordinates":[8.46454,11.22155],"type":"Point"}
}