{
  "type": "Feature",
  "properties": {
    "gn:admin1_code":"56.0",
    "gn:admin2_code":"26003.0",
    "gn:asciiname":"Bofowo",
    "gn:country_code":"NG",
    "gn:dem":193,
    "gn:feature_class":"P",
    "gn:feature_code":"PPL",
    "gn:name":"Bofowo",
    "gn:population":0,
    "gn:timezone":"Africa/Lagos",
    "iso:country":"NG",
    "wof:name":"Bofowo",
    "wof:placetype":"locality"
},
  "geometry": {"coordinates":[8.25,8.31667],"type":"Point"}
}