{
  "type": "Feature",
  "properties": {
    "gn:admin1_code":"27.0",
    "gn:admin2_code":"109.0",
    "gn:admin3_code":"10908",
    "gn:asciiname":"Mellaram",
    "gn:country_code":"NG",
    "gn:dem":301,
    "gn:feature_class":"P",
    "gn:feature_code":"PPL",
    "gn:name":"Mellaram",
    "gn:population":0,
    "gn:timezone":"Africa/Lagos",
    "iso:country":"NG",
    "wof:name":"Mellaram",
    "wof:placetype":"locality"
},
  "geometry": {"coordinates":[12.88852,12.6938],"type":"Point"}
}