{
  "type": "Feature",
  "properties": {
    "gn:admin1_code":"25.0",
    "gn:admin2_code":"4002.0",
    "gn:asciiname":"Ikenga-Nando",
    "gn:country_code":"NG",
    "gn:dem":72,
    "gn:feature_class":"P",
    "gn:feature_code":"PPL",
    "gn:name":"Ikenga-Nando",
    "gn:population":0,
    "gn:timezone":"Africa/Lagos",
    "iso:country":"NG",
    "name:eng_x_preferred":[
        "Ikenga-Nando"
    ],
    "wof:name":"Ikenga-Nando",
    "wof:placetype":"locality"
},
  "geometry": {"coordinates":[6.93342,6.32972],"type":"Point"}
}