{
  "type": "Feature",
  "properties": {
    "gn:admin1_code":"31.0",
    "gn:admin2_code":"27002.0",
    "gn:asciiname":"Mogo Ndaji",
    "gn:country_code":"NG",
    "gn:dem":205,
    "gn:feature_class":"P",
    "gn:feature_code":"PPL",
    "gn:name":"Mogo Ndaji",
    "gn:population":0,
    "gn:timezone":"Africa/Lagos",
    "iso:country":"NG",
    "wof:name":"Mogo Ndaji",
    "wof:placetype":"locality"
},
  "geometry": {"coordinates":[4.39767,10.82825],"type":"Point"}
}