{
  "type": "Feature",
  "properties": {
    "gn:admin1_code":"27.0",
    "gn:admin2_code":"106.0",
    "gn:admin3_code":"10605",
    "gn:asciiname":"Chiha",
    "gn:country_code":"NG",
    "gn:dem":442,
    "gn:feature_class":"P",
    "gn:feature_code":"PPL",
    "gn:name":"Chiha",
    "gn:population":0,
    "gn:timezone":"Africa/Lagos",
    "iso:country":"NG",
    "wof:name":"Chiha",
    "wof:placetype":"locality"
},
  "geometry": {"coordinates":[12.75082,10.8441],"type":"Point"}
}