{
  "type": "Feature",
  "properties": {
    "gn:admin1_code":"29.0",
    "gn:admin2_code":"20040.0",
    "gn:admin3_code":"KN3011",
    "gn:asciiname":"Gurjia",
    "gn:country_code":"NG",
    "gn:dem":435,
    "gn:feature_class":"P",
    "gn:feature_code":"PPL",
    "gn:name":"Gurjia",
    "gn:population":0,
    "gn:timezone":"Africa/Lagos",
    "iso:country":"NG",
    "name:und_x_variant":[
        "Garjiya",
        "Gurjiya",
        "Gurjia"
    ],
    "wof:name":"Gurjia",
    "wof:placetype":"locality"
},
  "geometry": {"coordinates":[8.71051,12.22157],"type":"Point"}
}