{
  "type": "Feature",
  "properties": {
    "gn:admin1_code":"51.0",
    "gn:admin2_code":"615.0",
    "gn:admin3_code":"61506",
    "gn:asciiname":"Maji",
    "gn:country_code":"NG",
    "gn:dem":230,
    "gn:feature_class":"P",
    "gn:feature_code":"PPL",
    "gn:name":"Maji",
    "gn:population":0,
    "gn:timezone":"Africa/Lagos",
    "iso:country":"NG",
    "wof:name":"Maji",
    "wof:placetype":"locality"
},
  "geometry": {"coordinates":[4.74303,13.00426],"type":"Point"}
}