{
  "type": "Feature",
  "properties": {
    "gn:admin1_code":"42.0",
    "gn:admin2_code":"30002.0",
    "gn:asciiname":"Adenlere",
    "gn:cc2":"NG",
    "gn:country_code":"NG",
    "gn:dem":261,
    "gn:feature_class":"P",
    "gn:feature_code":"PPL",
    "gn:name":"Adenlere",
    "gn:population":0,
    "gn:timezone":"Africa/Lagos",
    "iso:country":"NG",
    "name:und_x_variant":[
        "Adenilare",
        "Adenlere"
    ],
    "wof:name":"Adenlere",
    "wof:placetype":"locality"
},
  "geometry": {"coordinates":[4.23333,7.58333],"type":"Point"}
}