{
  "type": "Feature",
  "properties": {
    "gn:admin1_code":"42.0",
    "gn:admin2_code":"30004.0",
    "gn:asciiname":"Oke Osin",
    "gn:country_code":"NG",
    "gn:dem":308,
    "gn:feature_class":"P",
    "gn:feature_code":"PPL",
    "gn:name":"Oke Osin",
    "gn:population":0,
    "gn:timezone":"Africa/Lagos",
    "iso:country":"NG",
    "wof:name":"Oke Osin",
    "wof:placetype":"locality"
},
  "geometry": {"coordinates":[4.61667,7.66667],"type":"Point"}
}