{
  "type": "Feature",
  "properties": {
    "gn:admin1_code":"30.0",
    "gn:admin2_code":"24004.0",
    "gn:asciiname":"Obo Ile",
    "gn:cc2":"NG",
    "gn:country_code":"NG",
    "gn:dem":386,
    "gn:feature_class":"P",
    "gn:feature_code":"PPL",
    "gn:name":"Obo Ile",
    "gn:population":0,
    "gn:timezone":"Africa/Lagos",
    "iso:country":"NG",
    "name:und_x_variant":[
        "Old-Obo",
        "Obo Ile"
    ],
    "wof:name":"Obo Ile",
    "wof:placetype":"locality"
},
  "geometry": {"coordinates":[5.33333,8.08333],"type":"Point"}
}