{
  "type": "Feature",
  "properties": {
    "gn:admin1_code":"35.0",
    "gn:admin2_code":"2002.0",
    "gn:asciiname":"Tsulo",
    "gn:country_code":"NG",
    "gn:dem":243,
    "gn:feature_class":"P",
    "gn:feature_code":"PPL",
    "gn:name":"Tsulo",
    "gn:population":0,
    "gn:timezone":"Africa/Lagos",
    "iso:country":"NG",
    "wof:name":"Tsulo",
    "wof:placetype":"locality"
},
  "geometry": {"coordinates":[12.27609,8.96433],"type":"Point"}
}