{
  "type": "Feature",
  "properties": {
    "gn:admin1_code":"26.0",
    "gn:admin2_code":"7007",
    "gn:asciiname":"Korsha",
    "gn:country_code":"NG",
    "gn:dem":138,
    "gn:feature_class":"P",
    "gn:feature_code":"PPL",
    "gn:name":"Korsha",
    "gn:population":0,
    "gn:timezone":"Africa/Lagos",
    "iso:country":"NG",
    "wof:name":"Korsha",
    "wof:placetype":"locality"
},
  "geometry": {"coordinates":[8.37674,7.29508],"type":"Point"}
}