{
  "type": "Feature",
  "properties": {
    "gn:admin1_code":"16.0",
    "gn:admin2_code":"28015.0",
    "gn:asciiname":"Magado",
    "gn:country_code":"NG",
    "gn:dem":8,
    "gn:feature_class":"P",
    "gn:feature_code":"PPL",
    "gn:name":"Magado",
    "gn:population":0,
    "gn:timezone":"Africa/Lagos",
    "iso:country":"NG",
    "name:und_x_variant":[
        "Magboro-Shofolarin",
        "Magado"
    ],
    "wof:name":"Magado",
    "wof:placetype":"neighbourhood"
},
  "geometry": {"coordinates":[3.41022,6.73862],"type":"Point"}
}