{
  "type": "Feature",
  "properties": {
    "gn:admin1_code":"40.0",
    "gn:admin2_code":"512.0",
    "gn:admin3_code":"51208",
    "gn:asciiname":"Sandare Baban",
    "gn:country_code":"NG",
    "gn:dem":243,
    "gn:feature_class":"P",
    "gn:feature_code":"PPL",
    "gn:name":"Sandare Baban",
    "gn:population":0,
    "gn:timezone":"Africa/Lagos",
    "iso:country":"NG",
    "wof:name":"Sandare Baban",
    "wof:placetype":"locality"
},
  "geometry": {"coordinates":[4.03357,12.48828],"type":"Point"}
}