{
  "type": "Feature",
  "properties": {
    "gn:admin1_code":"30.0",
    "gn:admin2_code":"24003.0",
    "gn:asciiname":"Manfu",
    "gn:country_code":"NG",
    "gn:dem":110,
    "gn:feature_class":"P",
    "gn:feature_code":"PPL",
    "gn:name":"Manfu",
    "gn:population":0,
    "gn:timezone":"Africa/Lagos",
    "iso:country":"NG",
    "wof:name":"Manfu",
    "wof:placetype":"locality"
},
  "geometry": {"coordinates":[4.96667,9.05],"type":"Point"}
}