{
  "type": "Feature",
  "properties": {
    "gn:admin1_code":"51.0",
    "gn:admin2_code":"620.0",
    "gn:admin3_code":"62002",
    "gn:asciiname":"Kaura Mulun",
    "gn:country_code":"NG",
    "gn:dem":262,
    "gn:feature_class":"P",
    "gn:feature_code":"PPL",
    "gn:name":"Kaura Mulun",
    "gn:population":0,
    "gn:timezone":"Africa/Lagos",
    "iso:country":"NG",
    "name:und_x_variant":[
        "Kaura Malun",
        "Kauran Mallam",
        "Kaura Mulun"
    ],
    "wof:name":"Kaura Mulun",
    "wof:placetype":"locality"
},
  "geometry": {"coordinates":[5.27625,12.58342],"type":"Point"}
}