{
  "type": "Feature",
  "properties": {
    "gn:admin1_code":"48.0",
    "gn:admin2_code":"29005.0",
    "gn:asciiname":"Adekunle",
    "gn:country_code":"NG",
    "gn:dem":335,
    "gn:feature_class":"P",
    "gn:feature_code":"PPL",
    "gn:name":"Adekunle",
    "gn:population":0,
    "gn:timezone":"Africa/Lagos",
    "iso:country":"NG",
    "wof:name":"Adekunle",
    "wof:placetype":"locality"
},
  "geometry": {"coordinates":[5.3835,7.2165],"type":"Point"}
}