{
  "type": "Feature",
  "properties": {
    "gn:admin1_code":"44.0",
    "gn:admin2_code":"717",
    "gn:admin3_code":"71705",
    "gn:asciiname":"Jogua",
    "gn:country_code":"NG",
    "gn:dem":341,
    "gn:feature_class":"P",
    "gn:feature_code":"PPL",
    "gn:name":"Jogua",
    "gn:population":0,
    "gn:timezone":"Africa/Lagos",
    "iso:country":"NG",
    "wof:name":"Jogua",
    "wof:placetype":"locality"
},
  "geometry": {"coordinates":[10.94311,13.03814],"type":"Point"}
}