{
  "type": "Feature",
  "properties": {
    "gn:admin1_code":"16.0",
    "gn:admin2_code":"28019.0",
    "gn:asciiname":"Akaka",
    "gn:country_code":"NG",
    "gn:dem":84,
    "gn:feature_class":"P",
    "gn:feature_code":"PPL",
    "gn:name":"Akaka",
    "gn:population":0,
    "gn:timezone":"Africa/Lagos",
    "iso:country":"NG",
    "wof:name":"Akaka",
    "wof:placetype":"locality"
},
  "geometry": {"coordinates":[3.72475,6.96311],"type":"Point"}
}