{
  "type": "Feature",
  "properties": {
    "gn:admin1_code":"53.0",
    "gn:admin2_code":"11010.0",
    "gn:asciiname":"Akpatakpa",
    "gn:country_code":"NG",
    "gn:dem":65,
    "gn:feature_class":"P",
    "gn:feature_code":"PPL",
    "gn:name":"Akpatakpa",
    "gn:population":0,
    "gn:timezone":"Africa/Lagos",
    "iso:country":"NG",
    "name:und_x_variant":[
        "Akpatakpaba",
        "Akpatakpa"
    ],
    "wof:name":"Akpatakpa",
    "wof:placetype":"locality"
},
  "geometry": {"coordinates":[8.18108,6.39407],"type":"Point"}
}