{
  "type": "Feature",
  "properties": {
    "gn:admin1_code":"16.0",
    "gn:admin2_code":"28003.0",
    "gn:asciiname":"Isola",
    "gn:cc2":"NG",
    "gn:country_code":"NG",
    "gn:dem":46,
    "gn:feature_class":"P",
    "gn:feature_code":"PPL",
    "gn:name":"Isola",
    "gn:population":0,
    "gn:timezone":"Africa/Lagos",
    "iso:country":"NG",
    "name:und_x_variant":[
        "Ishola",
        "Isola"
    ],
    "wof:name":"Isola",
    "wof:placetype":"locality"
},
  "geometry": {"coordinates":[3.05,6.61667],"type":"Point"}
}