{
  "type": "Feature",
  "properties": {
    "gn:admin1_code":"49.0",
    "gn:asciiname":"Barakin Babele",
    "gn:country_code":"NG",
    "gn:dem":914,
    "gn:feature_class":"P",
    "gn:feature_code":"PPL",
    "gn:name":"Barakin Babele",
    "gn:population":0,
    "gn:timezone":"Africa/Lagos",
    "iso:country":"NG",
    "name:und_x_variant":[
        "Babelli",
        "Barakin Babele"
    ],
    "wof:name":"Barakin Babele",
    "wof:placetype":"locality"
},
  "geometry": {"coordinates":[8.93889,10.02085],"type":"Point"}
}