{
  "type": "Feature",
  "properties": {
    "gn:admin1_code":"23.0",
    "gn:admin2_code":"19003.0",
    "gn:admin3_code":"KD0301",
    "gn:asciiname":"Maje",
    "gn:country_code":"NG",
    "gn:dem":684,
    "gn:feature_class":"P",
    "gn:feature_code":"PPL",
    "gn:name":"Maje",
    "gn:population":0,
    "gn:timezone":"Africa/Lagos",
    "iso:country":"NG",
    "name:ceb_x_preferred":[
        "Maje"
    ],
    "wof:name":"Maje",
    "wof:placetype":"locality"
},
  "geometry": {"coordinates":[7.54917,11.27645],"type":"Point"}
}