{
  "type": "Feature",
  "properties": {
    "gn:admin1_code":"29.0",
    "gn:admin2_code":"20040.0",
    "gn:admin3_code":"KN3003",
    "gn:asciiname":"Garke",
    "gn:country_code":"NG",
    "gn:dem":469,
    "gn:feature_class":"P",
    "gn:feature_code":"PPL",
    "gn:name":"Garke",
    "gn:population":0,
    "gn:timezone":"Africa/Lagos",
    "iso:country":"NG",
    "name:und_x_variant":[
        "Gorrike",
        "Garke"
    ],
    "wof:name":"Garke",
    "wof:placetype":"locality"
},
  "geometry": {"coordinates":[8.59124,12.20851],"type":"Point"}
}