{
  "type": "Feature",
  "properties": {
    "gn:admin1_code":"26.0",
    "gn:admin2_code":"7003.0",
    "gn:asciiname":"Hoche",
    "gn:country_code":"NG",
    "gn:dem":260,
    "gn:feature_class":"P",
    "gn:feature_code":"PPL",
    "gn:name":"Hoche",
    "gn:population":0,
    "gn:timezone":"Africa/Lagos",
    "iso:country":"NG",
    "name:und_x_variant":[
        "Hache",
        "Hoche"
    ],
    "wof:name":"Hoche",
    "wof:placetype":"locality"
},
  "geometry": {"coordinates":[7.77959,7.45036],"type":"Point"}
}