{
  "type": "Feature",
  "properties": {
    "gn:admin1_code":"31.0",
    "gn:admin2_code":"27019.0",
    "gn:asciiname":"Kotoma",
    "gn:country_code":"NG",
    "gn:dem":337,
    "gn:feature_class":"P",
    "gn:feature_code":"PPL",
    "gn:name":"Kotoma",
    "gn:population":0,
    "gn:timezone":"Africa/Lagos",
    "iso:country":"NG",
    "wof:name":"Kotoma",
    "wof:placetype":"locality"
},
  "geometry": {"coordinates":[6.69754,9.4643],"type":"Point"}
}