{
  "type": "Feature",
  "properties": {
    "gn:admin1_code":"35.0",
    "gn:asciiname":"Mayo Jage",
    "gn:country_code":"NG",
    "gn:dem":254,
    "gn:feature_class":"P",
    "gn:feature_code":"PPL",
    "gn:name":"Mayo Jage",
    "gn:population":0,
    "gn:timezone":"Africa/Lagos",
    "iso:country":"NG",
    "name:eng_x_preferred":[
        "Mayo Jage"
    ],
    "wof:name":"Mayo Jage",
    "wof:placetype":"locality"
},
  "geometry": {"coordinates":[12.20476,9.01443],"type":"Point"}
}