{
  "type": "Feature",
  "properties": {
    "gn:admin1_code":"29.0",
    "gn:admin2_code":"20026.0",
    "gn:admin3_code":"KN2008",
    "gn:asciiname":"Unguwan Larawa",
    "gn:country_code":"NG",
    "gn:dem":494,
    "gn:feature_class":"P",
    "gn:feature_code":"PPL",
    "gn:name":"Unguwan Larawa",
    "gn:population":0,
    "gn:timezone":"Africa/Lagos",
    "iso:country":"NG",
    "wof:name":"Unguwan Larawa",
    "wof:placetype":"locality"
},
  "geometry": {"coordinates":[8.17643,11.82845],"type":"Point"}
}