{
  "type": "Feature",
  "properties": {
    "gn:admin1_code":"24.0",
    "gn:admin2_code":"408.0",
    "gn:admin3_code":"40804",
    "gn:asciiname":"Ungwan Dan Zaki",
    "gn:country_code":"NG",
    "gn:dem":706,
    "gn:feature_class":"P",
    "gn:feature_code":"PPL",
    "gn:name":"Ungwan Dan Zaki",
    "gn:population":0,
    "gn:timezone":"Africa/Lagos",
    "iso:country":"NG",
    "wof:name":"Ungwan Dan Zaki",
    "wof:placetype":"locality"
},
  "geometry": {"coordinates":[7.41068,11.454],"type":"Point"}
}