{
  "type": "Feature",
  "properties": {
    "gn:admin1_code":"35.0",
    "gn:admin2_code":"2012.0",
    "gn:asciiname":"Jebeni",
    "gn:country_code":"NG",
    "gn:dem":478,
    "gn:feature_class":"P",
    "gn:feature_code":"PPL",
    "gn:name":"Jebeni",
    "gn:population":0,
    "gn:timezone":"Africa/Lagos",
    "iso:country":"NG",
    "wof:name":"Jebeni",
    "wof:placetype":"locality"
},
  "geometry": {"coordinates":[11.94969,8.7424],"type":"Point"}
}