{
  "type": "Feature",
  "properties": {
    "gn:admin1_code":"23.0",
    "gn:admin2_code":"19003.0",
    "gn:admin3_code":"KD0310",
    "gn:asciiname":"Ungwan Buda",
    "gn:country_code":"NG",
    "gn:dem":648,
    "gn:feature_class":"P",
    "gn:feature_code":"PPL",
    "gn:name":"Ungwan Buda",
    "gn:population":0,
    "gn:timezone":"Africa/Lagos",
    "iso:country":"NG",
    "name:und_x_variant":[
        "Buda",
        "Ungwan Buda"
    ],
    "wof:name":"Ungwan Buda",
    "wof:placetype":"locality"
},
  "geometry": {"coordinates":[7.46558,11.11067],"type":"Point"}
}