{
  "type": "Feature",
  "properties": {
    "gn:admin1_code":"16.0",
    "gn:admin2_code":"28008.0",
    "gn:asciiname":"Imobi",
    "gn:country_code":"NG",
    "gn:dem":11,
    "gn:feature_class":"P",
    "gn:feature_code":"PPL",
    "gn:name":"Imobi",
    "gn:population":0,
    "gn:timezone":"Africa/Lagos",
    "iso:country":"NG",
    "name:und_x_variant":[
        "Mobi",
        "Imobi"
    ],
    "wof:name":"Imobi",
    "wof:placetype":"locality"
},
  "geometry": {"coordinates":[4.16712,6.59998],"type":"Point"}
}