{
  "type": "Feature",
  "properties": {
    "gn:admin1_code":"40.0",
    "gn:admin2_code":"502.0",
    "gn:admin3_code":"50207",
    "gn:asciiname":"Gumke-Gari",
    "gn:country_code":"NG",
    "gn:dem":229,
    "gn:feature_class":"P",
    "gn:feature_code":"PPL",
    "gn:name":"Gumke-Gari",
    "gn:population":0,
    "gn:timezone":"Africa/Lagos",
    "iso:country":"NG",
    "wof:name":"Gumke-Gari",
    "wof:placetype":"locality"
},
  "geometry": {"coordinates":[3.68348,12.23822],"type":"Point"}
}