{
  "type": "Feature",
  "properties": {
    "gn:admin1_code":"43.0",
    "gn:admin2_code":"35013.0",
    "gn:asciiname":"Abago",
    "gn:country_code":"NG",
    "gn:dem":170,
    "gn:feature_class":"P",
    "gn:feature_code":"PPL",
    "gn:name":"Abago",
    "gn:population":0,
    "gn:timezone":"Africa/Lagos",
    "iso:country":"NG",
    "wof:name":"Abago",
    "wof:placetype":"locality"
},
  "geometry": {"coordinates":[10.2322,7.33888],"type":"Point"}
}