{
  "type": "Feature",
  "properties": {
    "gn:admin1_code":"29.0",
    "gn:admin2_code":"20003.0",
    "gn:admin3_code":"KN1504",
    "gn:asciiname":"Yanaba",
    "gn:country_code":"NG",
    "gn:dem":494,
    "gn:feature_class":"P",
    "gn:feature_code":"PPL",
    "gn:name":"Yanaba",
    "gn:population":0,
    "gn:timezone":"Africa/Lagos",
    "iso:country":"NG",
    "wof:name":"Yanaba",
    "wof:placetype":"locality"
},
  "geometry": {"coordinates":[8.3728,11.65444],"type":"Point"}
}