{
  "type": "Feature",
  "properties": {
    "gn:admin1_code":"51.0",
    "gn:admin2_code":"619.0",
    "gn:admin3_code":"61902",
    "gn:asciiname":"Maburgami",
    "gn:country_code":"NG",
    "gn:dem":300,
    "gn:feature_class":"P",
    "gn:feature_code":"PPL",
    "gn:name":"Maburgami",
    "gn:population":0,
    "gn:timezone":"Africa/Lagos",
    "iso:country":"NG",
    "wof:name":"Maburgami",
    "wof:placetype":"locality"
},
  "geometry": {"coordinates":[5.06742,13.26711],"type":"Point"}
}