{
  "type": "Feature",
  "properties": {
    "gn:admin1_code":"26.0",
    "gn:admin2_code":"7006",
    "gn:asciiname":"N.A.R. Camp Number One",
    "gn:country_code":"NG",
    "gn:dem":138,
    "gn:feature_class":"P",
    "gn:feature_code":"PPL",
    "gn:name":"N.A.R. Camp Number One",
    "gn:population":0,
    "gn:timezone":"Africa/Lagos",
    "iso:country":"NG",
    "wof:name":"N.A.R. Camp Number One",
    "wof:placetype":"locality"
},
  "geometry": {"coordinates":[8.60649,7.93471],"type":"Point"}
}