{
  "type": "Feature",
  "properties": {
    "gn:admin1_code":"51.0",
    "gn:admin2_code":"612.0",
    "gn:admin3_code":"61209",
    "gn:asciiname":"Rikaka Magaji",
    "gn:country_code":"NG",
    "gn:dem":277,
    "gn:feature_class":"P",
    "gn:feature_code":"PPL",
    "gn:name":"Rikaka Magaji",
    "gn:population":0,
    "gn:timezone":"Africa/Lagos",
    "iso:country":"NG",
    "wof:name":"Rikaka Magaji",
    "wof:placetype":"locality"
},
  "geometry": {"coordinates":[5.66089,13.20045],"type":"Point"}
}