{
  "type": "Feature",
  "properties": {
    "gn:admin1_code":"27.0",
    "gn:admin2_code":"114.0",
    "gn:admin3_code":"11405",
    "gn:asciiname":"Fulatari",
    "gn:country_code":"NG",
    "gn:dem":376,
    "gn:feature_class":"P",
    "gn:feature_code":"PPL",
    "gn:name":"Fulatari",
    "gn:population":0,
    "gn:timezone":"Africa/Lagos",
    "iso:country":"NG",
    "name:und_x_variant":[
        "Fellatari",
        "Fulatari"
    ],
    "wof:name":"Fulatari",
    "wof:placetype":"locality"
},
  "geometry": {"coordinates":[12.67885,11.36303],"type":"Point"}
}