{
  "type": "Feature",
  "properties": {
    "gn:admin1_code":"21.0",
    "gn:admin2_code":"3016.0",
    "gn:asciiname":"Ikot Ukono",
    "gn:country_code":"NG",
    "gn:dem":73,
    "gn:feature_class":"P",
    "gn:feature_code":"PPL",
    "gn:name":"Ikot Ukono",
    "gn:population":0,
    "gn:timezone":"Africa/Lagos",
    "iso:country":"NG",
    "wof:name":"Ikot Ukono",
    "wof:placetype":"locality"
},
  "geometry": {"coordinates":[7.94611,5.10792],"type":"Point"}
}