{
  "type": "Feature",
  "properties": {
    "gn:admin1_code":"30.0",
    "gn:admin2_code":"24001.0",
    "gn:asciiname":"Elewetu",
    "gn:country_code":"NG",
    "gn:dem":346,
    "gn:feature_class":"P",
    "gn:feature_code":"PPL",
    "gn:name":"Elewetu",
    "gn:population":0,
    "gn:timezone":"Africa/Lagos",
    "iso:country":"NG",
    "wof:name":"Elewetu",
    "wof:placetype":"locality"
},
  "geometry": {"coordinates":[4.36667,8.48333],"type":"Point"}
}