{
  "type": "Feature",
  "properties": {
    "gn:admin1_code":"36.0",
    "gn:asciiname":"Kuku Camps",
    "gn:country_code":"NG",
    "gn:dem":4,
    "gn:feature_class":"P",
    "gn:feature_code":"PPL",
    "gn:name":"Kuku Camps",
    "gn:population":0,
    "gn:timezone":"Africa/Lagos",
    "iso:country":"NG",
    "name:eng_x_preferred":[
        "Kuku Camps"
    ],
    "wof:name":"Kuku Camps",
    "wof:placetype":"locality"
},
  "geometry": {"coordinates":[5.31418,5.62513],"type":"Point"}
}