{
  "type": "Feature",
  "properties": {
    "gn:admin1_code":"40.0",
    "gn:admin2_code":"514.0",
    "gn:admin3_code":"51409",
    "gn:asciiname":"Rafin-Naginai",
    "gn:country_code":"NG",
    "gn:dem":231,
    "gn:feature_class":"P",
    "gn:feature_code":"PPL",
    "gn:name":"Rafin-Naginai",
    "gn:population":0,
    "gn:timezone":"Africa/Lagos",
    "iso:country":"NG",
    "name:und_x_variant":[
        "Rafin Baura",
        "Rafin Nagindi"
    ],
    "wof:name":"Rafin-Naginai",
    "wof:placetype":"locality"
},
  "geometry": {"coordinates":[4.22155,12.09751],"type":"Point"}
}