{
  "type": "Feature",
  "properties": {
    "gn:admin1_code":"31.0",
    "gn:admin2_code":"27018.0",
    "gn:asciiname":"Gidan-Bakai",
    "gn:country_code":"NG",
    "gn:dem":420,
    "gn:feature_class":"P",
    "gn:feature_code":"PPL",
    "gn:name":"Gidan-Bakai",
    "gn:population":0,
    "gn:timezone":"Africa/Lagos",
    "iso:country":"NG",
    "name:und_x_variant":[
        "Baka",
        "Gidan-Bakai"
    ],
    "wof:name":"Gidan-Bakai",
    "wof:placetype":"locality"
},
  "geometry": {"coordinates":[7.05466,9.75383],"type":"Point"}
}