{
  "type": "Feature",
  "properties": {
    "gn:admin1_code":"40.0",
    "gn:admin2_code":"504.0",
    "gn:admin3_code":"50406",
    "gn:asciiname":"Kimbawa",
    "gn:country_code":"NG",
    "gn:dem":229,
    "gn:feature_class":"P",
    "gn:feature_code":"PPL",
    "gn:name":"Kimbawa",
    "gn:population":0,
    "gn:timezone":"Africa/Lagos",
    "iso:country":"NG",
    "wof:name":"Kimbawa",
    "wof:placetype":"locality"
},
  "geometry": {"coordinates":[4.68387,12.86814],"type":"Point"}
}