{
  "type": "Feature",
  "properties": {
    "gn:admin1_code":"46.0",
    "gn:admin2_code":"5018.0",
    "gn:admin3_code":"BA1804",
    "gn:asciiname":"Tambila",
    "gn:country_code":"NG",
    "gn:dem":747,
    "gn:feature_class":"P",
    "gn:feature_code":"PPL",
    "gn:name":"Tambila",
    "gn:population":0,
    "gn:timezone":"Africa/Lagos",
    "iso:country":"NG",
    "wof:name":"Tambila",
    "wof:placetype":"locality"
},
  "geometry": {"coordinates":[9.28774,10.16543],"type":"Point"}
}