{
  "type": "Feature",
  "properties": {
    "gn:admin1_code":"39.0",
    "gn:admin2_code":"18012.0",
    "gn:admin3_code":"JI0602",
    "gn:asciiname":"Isari",
    "gn:country_code":"NG",
    "gn:dem":386,
    "gn:feature_class":"P",
    "gn:feature_code":"PPL",
    "gn:name":"Isari",
    "gn:population":0,
    "gn:timezone":"Africa/Lagos",
    "iso:country":"NG",
    "wof:name":"Isari",
    "wof:placetype":"locality"
},
  "geometry": {"coordinates":[9.30867,12.02524],"type":"Point"}
}