{
  "type": "Feature",
  "properties": {
    "gn:admin1_code":"28.0",
    "gn:admin2_code":"17025.0",
    "gn:asciiname":"Egbu",
    "gn:country_code":"NG",
    "gn:dem":89,
    "gn:feature_class":"P",
    "gn:feature_code":"PPL",
    "gn:name":"Egbu",
    "gn:population":0,
    "gn:timezone":"Africa/Lagos",
    "iso:country":"NG",
    "wof:name":"Egbu",
    "wof:placetype":"locality"
},
  "geometry": {"coordinates":[7.06667,5.48333],"type":"Point"}
}