{
  "type": "Feature",
  "properties": {
    "gn:admin1_code":"50.0",
    "gn:asciiname":"Ininokiribi",
    "gn:country_code":"NG",
    "gn:dem":413,
    "gn:feature_class":"P",
    "gn:feature_code":"PPL",
    "gn:name":"Ininokiribi",
    "gn:population":0,
    "gn:timezone":"Africa/Lagos",
    "iso:country":"NG",
    "wof:name":"Ininokiribi",
    "wof:placetype":"locality"
},
  "geometry": {"coordinates":[7.16667,4.61667],"type":"Point"}
}