{
  "type": "Feature",
  "properties": {
    "gn:admin1_code":"27.0",
    "gn:admin2_code":"110.0",
    "gn:admin3_code":"11004",
    "gn:asciiname":"Bulabulin",
    "gn:country_code":"NG",
    "gn:dem":296,
    "gn:feature_class":"P",
    "gn:feature_code":"PPL",
    "gn:name":"Bulabulin",
    "gn:population":0,
    "gn:timezone":"Africa/Lagos",
    "iso:country":"NG",
    "name:und_x_variant":[
        "Bilabirin",
        "Bulabulin"
    ],
    "wof:name":"Bulabulin",
    "wof:placetype":"locality"
},
  "geometry": {"coordinates":[13.27846,12.66208],"type":"Point"}
}