{
  "type": "Feature",
  "properties": {
    "gn:admin1_code":"51.0",
    "gn:admin2_code":"605.0",
    "gn:admin3_code":"60505",
    "gn:asciiname":"Kawadata",
    "gn:country_code":"NG",
    "gn:dem":271,
    "gn:feature_class":"P",
    "gn:feature_code":"PPL",
    "gn:name":"Kawadata",
    "gn:population":0,
    "gn:timezone":"Africa/Lagos",
    "iso:country":"NG",
    "wof:name":"Kawadata",
    "wof:placetype":"locality"
},
  "geometry": {"coordinates":[5.64288,13.38114],"type":"Point"}
}