{
  "type": "Feature",
  "properties": {
    "gn:admin1_code":"30.0",
    "gn:admin2_code":"24015.0",
    "gn:asciiname":"Igbodun",
    "gn:country_code":"NG",
    "gn:dem":394,
    "gn:feature_class":"P",
    "gn:feature_code":"PPL",
    "gn:name":"Igbodun",
    "gn:population":0,
    "gn:timezone":"Africa/Lagos",
    "iso:country":"NG",
    "wof:name":"Igbodun",
    "wof:placetype":"locality"
},
  "geometry": {"coordinates":[4.66667,8.21667],"type":"Point"}
}