{
  "type": "Feature",
  "properties": {
    "gn:admin1_code":"16.0",
    "gn:admin2_code":"28015.0",
    "gn:asciiname":"Oluwo",
    "gn:country_code":"NG",
    "gn:dem":98,
    "gn:feature_class":"P",
    "gn:feature_code":"PPL",
    "gn:name":"Oluwo",
    "gn:population":0,
    "gn:timezone":"Africa/Lagos",
    "iso:country":"NG",
    "wof:name":"Oluwo",
    "wof:placetype":"locality"
},
  "geometry": {"coordinates":[3.61675,6.97799],"type":"Point"}
}