{
  "type": "Feature",
  "properties": {
    "gn:admin1_code":"31.0",
    "gn:admin2_code":"27019",
    "gn:asciiname":"Malam Gwari",
    "gn:country_code":"NG",
    "gn:dem":255,
    "gn:feature_class":"P",
    "gn:feature_code":"PPL",
    "gn:name":"Malam Gwari",
    "gn:population":0,
    "gn:timezone":"Africa/Lagos",
    "iso:country":"NG",
    "wof:name":"Malam Gwari",
    "wof:placetype":"locality"
},
  "geometry": {"coordinates":[6.5847,9.32279],"type":"Point"}
}