{
  "type": "Feature",
  "properties": {
    "gn:admin1_code":"36.0",
    "gn:admin2_code":"10009.0",
    "gn:asciiname":"Iwre-Grigri",
    "gn:country_code":"NG",
    "gn:dem":15,
    "gn:feature_class":"P",
    "gn:feature_code":"PPL",
    "gn:name":"Iwre-Grigri",
    "gn:population":0,
    "gn:timezone":"Africa/Lagos",
    "iso:country":"NG",
    "wof:name":"Iwre-Grigri",
    "wof:placetype":"locality"
},
  "geometry": {"coordinates":[6.10907,5.52957],"type":"Point"}
}