{
  "type": "Feature",
  "properties": {
    "gn:admin1_code":"22.0",
    "gn:admin2_code":"9011.0",
    "gn:asciiname":"Elegabor",
    "gn:country_code":"NG",
    "gn:dem":47,
    "gn:feature_class":"P",
    "gn:feature_code":"PPL",
    "gn:name":"Elegabor",
    "gn:population":0,
    "gn:timezone":"Africa/Lagos",
    "iso:country":"NG",
    "wof:name":"Elegabor",
    "wof:placetype":"locality"
},
  "geometry": {"coordinates":[8.57985,6.33674],"type":"Point"}
}