{
  "type": "Feature",
  "properties": {
    "gn:admin1_code":"55.0",
    "gn:admin2_code":"16001.0",
    "gn:asciiname":"Dolen Sarki",
    "gn:country_code":"NG",
    "gn:dem":478,
    "gn:feature_class":"P",
    "gn:feature_code":"PPL",
    "gn:name":"Dolen Sarki",
    "gn:population":0,
    "gn:timezone":"Africa/Lagos",
    "iso:country":"NG",
    "name:eng_x_preferred":[
        "Dolen Sarki"
    ],
    "wof:name":"Dolen Sarki",
    "wof:placetype":"locality"
},
  "geometry": {"coordinates":[10.88072,10.26189],"type":"Point"}
}