{
  "type": "Feature",
  "properties": {
    "gn:admin1_code":"26.0",
    "gn:admin2_code":"7022",
    "gn:asciiname":"Cayura",
    "gn:country_code":"NG",
    "gn:dem":196,
    "gn:feature_class":"P",
    "gn:feature_code":"PPL",
    "gn:name":"Cayura",
    "gn:population":0,
    "gn:timezone":"Africa/Lagos",
    "iso:country":"NG",
    "wof:name":"Cayura",
    "wof:placetype":"locality"
},
  "geometry": {"coordinates":[8.97831,7.26352],"type":"Point"}
}