{
  "type": "Feature",
  "properties": {
    "gn:admin1_code":"26.0",
    "gn:admin2_code":"7005",
    "gn:asciiname":"Ane",
    "gn:country_code":"NG",
    "gn:dem":217,
    "gn:feature_class":"P",
    "gn:feature_code":"PPL",
    "gn:name":"Ane",
    "gn:population":0,
    "gn:timezone":"Africa/Lagos",
    "iso:country":"NG",
    "name:ceb_x_preferred":[
        "Ane"
    ],
    "name:eus_x_preferred":[
        "Ane"
    ],
    "name:pol_x_preferred":[
        "Ane"
    ],
    "name:swe_x_preferred":[
        "Ane"
    ],
    "wof:name":"Ane",
    "wof:placetype":"neighbourhood"
},
  "geometry": {"coordinates":[9.00933,7.36349],"type":"Point"}
}