{
  "type": "Feature",
  "properties": {
    "gn:admin1_code":"31.0",
    "gn:admin2_code":"27005",
    "gn:asciiname":"Gidan Sugbi",
    "gn:country_code":"NG",
    "gn:dem":282,
    "gn:feature_class":"P",
    "gn:feature_code":"PPL",
    "gn:name":"Gidan Sugbi",
    "gn:population":0,
    "gn:timezone":"Africa/Lagos",
    "iso:country":"NG",
    "wof:name":"Gidan Sugbi",
    "wof:placetype":"locality"
},
  "geometry": {"coordinates":[6.62306,9.71613],"type":"Point"}
}