{
  "type": "Feature",
  "properties": {
    "gn:admin1_code":"22.0",
    "gn:admin2_code":"9002.0",
    "gn:asciiname":"Okarara",
    "gn:country_code":"NG",
    "gn:dem":152,
    "gn:feature_class":"P",
    "gn:feature_code":"PPL",
    "gn:name":"Okarara",
    "gn:population":0,
    "gn:timezone":"Africa/Lagos",
    "iso:country":"NG",
    "wof:name":"Okarara",
    "wof:placetype":"locality"
},
  "geometry": {"coordinates":[8.7136,5.3595],"type":"Point"}
}