{
  "type": "Feature",
  "properties": {
    "gn:admin1_code":"49.0",
    "gn:asciiname":"Karambama",
    "gn:country_code":"NG",
    "gn:dem":841,
    "gn:feature_class":"P",
    "gn:feature_code":"PPL",
    "gn:name":"Karambama",
    "gn:population":0,
    "gn:timezone":"Africa/Lagos",
    "iso:country":"NG",
    "name:und_x_variant":[
        "Karambana"
    ],
    "wof:name":"Karambama",
    "wof:placetype":"locality"
},
  "geometry": {"coordinates":[8.65529,10.12131],"type":"Point"}
}