{
  "type": "Feature",
  "properties": {
    "gn:admin1_code":"51.0",
    "gn:admin2_code":"602.0",
    "gn:admin3_code":"60209",
    "gn:asciiname":"Maro Marum Tonka",
    "gn:country_code":"NG",
    "gn:dem":297,
    "gn:feature_class":"P",
    "gn:feature_code":"PPL",
    "gn:name":"Maro Marum Tonka",
    "gn:population":0,
    "gn:timezone":"Africa/Lagos",
    "iso:country":"NG",
    "name:und_x_variant":[
        "Maro Marun Tonka",
        "Maro Marum Tonka"
    ],
    "wof:name":"Maro Marum Tonka",
    "wof:placetype":"locality"
},
  "geometry": {"coordinates":[5.17794,12.9221],"type":"Point"}
}