{
  "type": "Feature",
  "properties": {
    "gn:admin1_code":"43.0",
    "gn:admin2_code":"35015.0",
    "gn:asciiname":"Yasabazi",
    "gn:country_code":"NG",
    "gn:dem":257,
    "gn:feature_class":"P",
    "gn:feature_code":"PPL",
    "gn:name":"Yasabazi",
    "gn:population":0,
    "gn:timezone":"Africa/Lagos",
    "iso:country":"NG",
    "wof:name":"Yasabazi",
    "wof:placetype":"locality"
},
  "geometry": {"coordinates":[11.36584,8.98142],"type":"Point"}
}