{
  "type": "Feature",
  "properties": {
    "gn:admin1_code":"21.0",
    "gn:admin2_code":"3012.0",
    "gn:asciiname":"Ikot Onwon",
    "gn:country_code":"NG",
    "gn:dem":82,
    "gn:feature_class":"P",
    "gn:feature_code":"PPL",
    "gn:name":"Ikot Onwon",
    "gn:population":0,
    "gn:timezone":"Africa/Lagos",
    "iso:country":"NG",
    "wof:name":"Ikot Onwon",
    "wof:placetype":"locality"
},
  "geometry": {"coordinates":[7.80819,5.2301],"type":"Point"}
}