{
  "type": "Feature",
  "properties": {
    "gn:admin1_code":"41.0",
    "gn:admin2_code":"23013.0",
    "gn:asciiname":"Aiyede",
    "gn:country_code":"NG",
    "gn:dem":290,
    "gn:feature_class":"P",
    "gn:feature_code":"PPL",
    "gn:name":"Aiyede",
    "gn:population":0,
    "gn:timezone":"Africa/Lagos",
    "iso:country":"NG",
    "wof:name":"Aiyede",
    "wof:placetype":"locality"
},
  "geometry": {"coordinates":[5.96667,8.16667],"type":"Point"}
}