{
  "type": "Feature",
  "properties": {
    "gn:admin1_code":"31.0",
    "gn:admin2_code":"27018",
    "gn:asciiname":"Koye",
    "gn:country_code":"NG",
    "gn:dem":429,
    "gn:feature_class":"P",
    "gn:feature_code":"PPL",
    "gn:name":"Koye",
    "gn:population":0,
    "gn:timezone":"Africa/Lagos",
    "iso:country":"NG",
    "wof:name":"Koye",
    "wof:placetype":"locality"
},
  "geometry": {"coordinates":[7.0031,9.71194],"type":"Point"}
}