{
  "type": "Feature",
  "properties": {
    "gn:admin1_code":"46.0",
    "gn:admin2_code":"5013.0",
    "gn:admin3_code":"BA1313",
    "gn:asciiname":"Nahuta",
    "gn:country_code":"NG",
    "gn:dem":364,
    "gn:feature_class":"P",
    "gn:feature_code":"PPL",
    "gn:name":"Nahuta",
    "gn:population":0,
    "gn:timezone":"Africa/Lagos",
    "iso:country":"NG",
    "name:eng_x_preferred":[
        "Nahuta"
    ],
    "wof:name":"Nahuta",
    "wof:placetype":"locality"
},
  "geometry": {"coordinates":[10.81622,10.38795],"type":"Point"}
}