{
  "type": "Feature",
  "properties": {
    "gn:admin1_code":"35.0",
    "gn:admin2_code":"2008",
    "gn:asciiname":"Kamanda",
    "gn:country_code":"NG",
    "gn:dem":416,
    "gn:feature_class":"P",
    "gn:feature_code":"PPL",
    "gn:name":"Kamanda",
    "gn:population":0,
    "gn:timezone":"Africa/Lagos",
    "iso:country":"NG",
    "wof:name":"Kamanda",
    "wof:placetype":"locality"
},
  "geometry": {"coordinates":[12.42163,8.62889],"type":"Point"}
}