{
  "type": "Feature",
  "properties": {
    "gn:admin1_code":"51.0",
    "gn:admin2_code":"614.0",
    "gn:admin3_code":"61401",
    "gn:asciiname":"Rugar Magaji",
    "gn:country_code":"NG",
    "gn:dem":304,
    "gn:feature_class":"P",
    "gn:feature_code":"PPL",
    "gn:name":"Rugar Magaji",
    "gn:population":0,
    "gn:timezone":"Africa/Lagos",
    "iso:country":"NG",
    "name:und_x_variant":[
        "Rogan Magaji",
        "Rugar Magaji"
    ],
    "wof:name":"Rugar Magaji",
    "wof:placetype":"locality"
},
  "geometry": {"coordinates":[5.12661,12.68942],"type":"Point"}
}