{
  "type": "Feature",
  "properties": {
    "gn:admin1_code":"27.0",
    "gn:admin2_code":"103",
    "gn:admin3_code":"10307",
    "gn:asciiname":"Malum Dalari",
    "gn:country_code":"NG",
    "gn:dem":318,
    "gn:feature_class":"P",
    "gn:feature_code":"PPL",
    "gn:name":"Malum Dalari",
    "gn:population":0,
    "gn:timezone":"Africa/Lagos",
    "iso:country":"NG",
    "wof:name":"Malum Dalari",
    "wof:placetype":"locality"
},
  "geometry": {"coordinates":[13.93029,11.36122],"type":"Point"}
}