{
  "type": "Feature",
  "properties": {
    "gn:admin1_code":"31.0",
    "gn:admin2_code":"27007.0",
    "gn:asciiname":"Kpatagi",
    "gn:country_code":"NG",
    "gn:dem":116,
    "gn:feature_class":"P",
    "gn:feature_code":"PPL",
    "gn:name":"Kpatagi",
    "gn:population":0,
    "gn:timezone":"Africa/Lagos",
    "iso:country":"NG",
    "wof:name":"Kpatagi",
    "wof:placetype":"locality"
},
  "geometry": {"coordinates":[5.78333,8.98333],"type":"Point"}
}