{
  "type": "Feature",
  "properties": {
    "gn:admin1_code":"51.0",
    "gn:admin2_code":"621.0",
    "gn:admin3_code":"62108",
    "gn:asciiname":"Girawsi",
    "gn:country_code":"NG",
    "gn:dem":258,
    "gn:feature_class":"P",
    "gn:feature_code":"PPL",
    "gn:name":"Girawsi",
    "gn:population":0,
    "gn:timezone":"Africa/Lagos",
    "iso:country":"NG",
    "wof:name":"Girawsi",
    "wof:placetype":"locality"
},
  "geometry": {"coordinates":[5.18757,13.06843],"type":"Point"}
}