{
  "type": "Feature",
  "properties": {
    "gn:admin1_code":"48.0",
    "gn:admin2_code":"29002.0",
    "gn:asciiname":"Efifa",
    "gn:country_code":"NG",
    "gn:dem":386,
    "gn:feature_class":"P",
    "gn:feature_code":"PPL",
    "gn:name":"Efifa",
    "gn:population":0,
    "gn:timezone":"Africa/Lagos",
    "iso:country":"NG",
    "name:und_x_variant":[
        "Efife",
        "Effa",
        "Efifa"
    ],
    "wof:name":"Efifa",
    "wof:placetype":"locality"
},
  "geometry": {"coordinates":[5.90738,7.70641],"type":"Point"}
}