{
  "type": "Feature",
  "properties": {
    "gn:admin1_code":"56.0",
    "gn:admin2_code":"26013.0",
    "gn:asciiname":"Massenge",
    "gn:country_code":"NG",
    "gn:dem":461,
    "gn:feature_class":"P",
    "gn:feature_code":"PPL",
    "gn:name":"Massenge",
    "gn:population":0,
    "gn:timezone":"Africa/Lagos",
    "iso:country":"NG",
    "wof:name":"Massenge",
    "wof:placetype":"locality"
},
  "geometry": {"coordinates":[8.73841,9.10146],"type":"Point"}
}