{
  "type": "Feature",
  "properties": {
    "gn:admin1_code":"26.0",
    "gn:admin2_code":"7012",
    "gn:asciiname":"Tsehoon",
    "gn:country_code":"NG",
    "gn:dem":162,
    "gn:feature_class":"P",
    "gn:feature_code":"PPL",
    "gn:name":"Tsehoon",
    "gn:population":0,
    "gn:timezone":"Africa/Lagos",
    "iso:country":"NG",
    "wof:name":"Tsehoon",
    "wof:placetype":"locality"
},
  "geometry": {"coordinates":[9.19147,7.76543],"type":"Point"}
}