{
  "type": "Feature",
  "properties": {
    "gn:admin1_code":"25.0",
    "gn:admin2_code":"4006.0",
    "gn:asciiname":"Umuokpo",
    "gn:country_code":"NG",
    "gn:dem":125,
    "gn:feature_class":"P",
    "gn:feature_code":"PPL",
    "gn:name":"Umuokpo",
    "gn:population":0,
    "gn:timezone":"Africa/Lagos",
    "iso:country":"NG",
    "name:und_x_variant":[
        "Umuokpu",
        "Umukpu",
        "Umuokpo"
    ],
    "wof:name":"Umuokpo",
    "wof:placetype":"locality"
},
  "geometry": {"coordinates":[7.04774,6.19866],"type":"Point"}
}