{
  "type": "Feature",
  "properties": {
    "gn:admin1_code":"31.0",
    "gn:admin2_code":"27008",
    "gn:asciiname":"Kuchigi Nakuyi",
    "gn:country_code":"NG",
    "gn:dem":98,
    "gn:feature_class":"P",
    "gn:feature_code":"PPL",
    "gn:name":"Kuchigi Nakuyi",
    "gn:population":0,
    "gn:timezone":"Africa/Lagos",
    "iso:country":"NG",
    "wof:name":"Kuchigi Nakuyi",
    "wof:placetype":"locality"
},
  "geometry": {"coordinates":[6.10512,9.1466],"type":"Point"}
}