{
  "type": "Feature",
  "properties": {
    "gn:admin1_code":"24.0",
    "gn:admin2_code":"405.0",
    "gn:admin3_code":"40501",
    "gn:asciiname":"Baure",
    "gn:country_code":"NG",
    "gn:dem":491,
    "gn:feature_class":"P",
    "gn:feature_code":"PPL",
    "gn:name":"Baure",
    "gn:population":0,
    "gn:timezone":"Africa/Lagos",
    "iso:country":"NG",
    "name:ceb_x_preferred":[
        "Baure"
    ],
    "name:ita_x_preferred":[
        "Baure"
    ],
    "wof:name":"Baure",
    "wof:placetype":"locality"
},
  "geometry": {"coordinates":[7.87292,12.77699],"type":"Point"}
}