{
  "type": "Feature",
  "properties": {
    "gn:admin1_code":"52.0",
    "gn:admin2_code":"6007.0",
    "gn:asciiname":"Kamborra",
    "gn:country_code":"NG",
    "gn:dem":0,
    "gn:feature_class":"P",
    "gn:feature_code":"PPL",
    "gn:name":"Kamborra",
    "gn:population":0,
    "gn:timezone":"Africa/Lagos",
    "iso:country":"NG",
    "name:und_x_variant":[
        "Kambora",
        "Kamborra"
    ],
    "wof:name":"Kamborra",
    "wof:placetype":"locality"
},
  "geometry": {"coordinates":[5.91556,4.47861],"type":"Point"}
}