{
  "type": "Feature",
  "properties": {
    "gn:admin1_code":"40.0",
    "gn:admin2_code":"512.0",
    "gn:admin3_code":"51206",
    "gn:asciiname":"Kokane",
    "gn:country_code":"NG",
    "gn:dem":205,
    "gn:feature_class":"P",
    "gn:feature_code":"PPL",
    "gn:name":"Kokane",
    "gn:population":0,
    "gn:timezone":"Africa/Lagos",
    "iso:country":"NG",
    "name:ces_x_preferred":[
        "Kokane"
    ],
    "name:deu_x_preferred":[
        "Kokane"
    ],
    "name:fra_x_preferred":[
        "Kokane"
    ],
    "name:hrv_x_preferred":[
        "Kokane"
    ],
    "name:ita_x_preferred":[
        "Kokane"
    ],
    "name:nld_x_preferred":[
        "Kokane"
    ],
    "name:pol_x_preferred":[
        "Kokane"
    ],
    "name:spa_x_preferred":[
        "Kokane"
    ],
    "wof:name":"Kokane",
    "wof:placetype":"locality"
},
  "geometry": {"coordinates":[3.9576,12.43847],"type":"Point"}
}