{
  "type": "Feature",
  "properties": {
    "gn:admin1_code":"42.0",
    "gn:admin2_code":"30019.0",
    "gn:asciiname":"Ila",
    "gn:cc2":"NG",
    "gn:country_code":"NG",
    "gn:dem":343,
    "gn:feature_class":"P",
    "gn:feature_code":"PPL",
    "gn:name":"Ila",
    "gn:population":0,
    "gn:timezone":"Africa/Lagos",
    "iso:country":"NG",
    "name:ceb_x_preferred":[
        "Ila"
    ],
    "name:dan_x_preferred":[
        "Ila"
    ],
    "name:deu_x_preferred":[
        "Ila"
    ],
    "name:fra_x_preferred":[
        "Ila"
    ],
    "name:ind_x_preferred":[
        "Ila"
    ],
    "name:lit_x_preferred":[
        "Ila"
    ],
    "name:nld_x_preferred":[
        "Ila"
    ],
    "name:nor_x_preferred":[
        "Ila"
    ],
    "name:por_x_preferred":[
        "Ila"
    ],
    "name:rus_x_preferred":[
        "\u0418\u043b\u0430"
    ],
    "name:swe_x_preferred":[
        "Ila"
    ],
    "name:tam_x_preferred":[
        "\u0b87\u0bb2\u0bbe"
    ],
    "name:und_x_variant":[
        "Illa",
        "Ila"
    ],
    "name:vol_x_preferred":[
        "Ila"
    ],
    "wof:name":"Ila",
    "wof:placetype":"locality"
},
  "geometry": {"coordinates":[4.66667,7.66667],"type":"Point"}
}