{
  "type": "Feature",
  "properties": {
    "gn:admin1_code":"22.0",
    "gn:admin2_code":"9011",
    "gn:asciiname":"Nsele",
    "gn:country_code":"NG",
    "gn:dem":42,
    "gn:feature_class":"P",
    "gn:feature_code":"PPL",
    "gn:name":"Nsele",
    "gn:population":0,
    "gn:timezone":"Africa/Lagos",
    "iso:country":"NG",
    "name:eus_x_preferred":[
        "Nsele"
    ],
    "name:fra_x_preferred":[
        "Nsele"
    ],
    "name:lin_x_preferred":[
        "Ns\u025bl\u025b"
    ],
    "wof:name":"Nsele",
    "wof:placetype":"locality"
},
  "geometry": {"coordinates":[8.5221,6.26527],"type":"Point"}
}