{
  "type": "Feature",
  "properties": {
    "gn:admin1_code":"35.0",
    "gn:admin2_code":"2004.0",
    "gn:asciiname":"Damare",
    "gn:country_code":"NG",
    "gn:dem":169,
    "gn:feature_class":"P",
    "gn:feature_code":"PPL",
    "gn:name":"Damare",
    "gn:population":0,
    "gn:timezone":"Africa/Lagos",
    "iso:country":"NG",
    "name:eng_x_preferred":[
        "Damare"
    ],
    "wof:name":"Damare",
    "wof:placetype":"locality"
},
  "geometry": {"coordinates":[12.44385,9.31654],"type":"Point"}
}