{
  "type": "Feature",
  "properties": {
    "gn:admin1_code":"24.0",
    "gn:admin2_code":"420.0",
    "gn:admin3_code":"42002",
    "gn:asciiname":"Gaci",
    "gn:country_code":"NG",
    "gn:dem":554,
    "gn:feature_class":"P",
    "gn:feature_code":"PPL",
    "gn:name":"Gaci",
    "gn:population":0,
    "gn:timezone":"Africa/Lagos",
    "iso:country":"NG",
    "wof:name":"Gaci",
    "wof:placetype":"locality"
},
  "geometry": {"coordinates":[7.84053,12.55023],"type":"Point"}
}