{
  "type": "Feature",
  "properties": {
    "gn:admin1_code":"29.0",
    "gn:admin2_code":"20034.0",
    "gn:admin3_code":"KN2401",
    "gn:asciiname":"Kankan",
    "gn:country_code":"NG",
    "gn:dem":554,
    "gn:feature_class":"P",
    "gn:feature_code":"PPL",
    "gn:name":"Kankan",
    "gn:population":0,
    "gn:timezone":"Africa/Lagos",
    "iso:country":"NG",
    "name:ara_x_preferred":[
        "\u0643\u0627\u0646\u0643\u0627\u0646"
    ],
    "name:bel_x_preferred":[
        "\u041a\u0430\u043d\u043a\u0430\u043d"
    ],
    "name:bul_x_preferred":[
        "\u041a\u0430\u043d\u043a\u0430\u043d"
    ],
    "name:cat_x_preferred":[
        "Kankan"
    ],
    "name:ceb_x_preferred":[
        "Kankan"
    ],
    "name:ces_x_preferred":[
        "Kankan"
    ],
    "name:dan_x_preferred":[
        "Kankan"
    ],
    "name:deu_x_preferred":[
        "Kankan"
    ],
    "name:epo_x_preferred":[
        "Kankan"
    ],
    "name:eus_x_preferred":[
        "Kankan"
    ],
    "name:fas_x_preferred":[
        "\u06a9\u0627\u0646\u06a9\u0646"
    ],
    "name:fin_x_preferred":[
        "Kankan"
    ],
    "name:fra_x_preferred":[
        "Kankan"
    ],
    "name:frr_x_preferred":[
        "Kankan"
    ],
    "name:fry_x_preferred":[
        "Kankan"
    ],
    "name:hrv_x_preferred":[
        "Kankan"
    ],
    "name:hun_x_preferred":[
        "Kankan"
    ],
    "name:ind_x_preferred":[
        "Kankan"
    ],
    "name:ita_x_preferred":[
        "Kankan"
    ],
    "name:jpn_x_preferred":[
        "\u30ab\u30f3\u30ab\u30f3"
    ],
    "name:lit_x_preferred":[
        "Kankanas"
    ],
    "name:mkd_x_preferred":[
        "\u041a\u0430\u043d\u043a\u0430\u043d"
    ],
    "name:mon_x_preferred":[
        "\u041a\u0430\u043d\u043a\u0430\u043d"
    ],
    "name:msa_x_preferred":[
        "Kankan"
    ],
    "name:nld_x_preferred":[
        "Kankan"
    ],
    "name:pol_x_preferred":[
        "Kankan"
    ],
    "name:ron_x_preferred":[
        "Kankan"
    ],
    "name:rus_x_preferred":[
        "\u041a\u0430\u043d\u043a\u0430\u043d"
    ],
    "name:spa_x_preferred":[
        "Kankan"
    ],
    "name:swe_x_preferred":[
        "Kankan"
    ],
    "name:ukr_x_preferred":[
        "\u041a\u0430\u043d\u043a\u0430\u043d"
    ],
    "name:urd_x_preferred":[
        "\u06a9\u0627\u0646\u06a9\u0627\u0646"
    ],
    "wof:name":"Kankan",
    "wof:placetype":"locality"
},
  "geometry": {"coordinates":[8.05427,11.60866],"type":"Point"}
}