{
  "type": "Feature",
  "properties": {
    "gn:admin1_code":"56.0",
    "gn:admin2_code":"26008.0",
    "gn:asciiname":"Yelwata",
    "gn:country_code":"NG",
    "gn:dem":168,
    "gn:feature_class":"P",
    "gn:feature_code":"PPL",
    "gn:name":"Yelwata",
    "gn:population":0,
    "gn:timezone":"Africa/Lagos",
    "iso:country":"NG",
    "wof:name":"Yelwata",
    "wof:placetype":"locality"
},
  "geometry": {"coordinates":[8.71667,8.53333],"type":"Point"}
}