{
  "type": "Feature",
  "properties": {
    "gn:admin1_code":"37.0",
    "gn:admin2_code":"12015.0",
    "gn:asciiname":"Iguatakpa",
    "gn:country_code":"NG",
    "gn:dem":120,
    "gn:feature_class":"P",
    "gn:feature_code":"PPL",
    "gn:name":"Iguatakpa",
    "gn:population":0,
    "gn:timezone":"Africa/Lagos",
    "iso:country":"NG",
    "name:und_x_variant":[
        "Iguatakpo",
        "Iguatakpa"
    ],
    "wof:name":"Iguatakpa",
    "wof:placetype":"locality"
},
  "geometry": {"coordinates":[5.30393,6.56526],"type":"Point"}
}