{
  "type": "Feature",
  "properties": {
    "gn:admin1_code":"57.0",
    "gn:admin2_code":"810.0",
    "gn:admin3_code":"81005",
    "gn:asciiname":"Angwan-Maiwasa",
    "gn:country_code":"NG",
    "gn:dem":500,
    "gn:feature_class":"P",
    "gn:feature_code":"PPL",
    "gn:name":"Angwan-Maiwasa",
    "gn:population":0,
    "gn:timezone":"Africa/Lagos",
    "iso:country":"NG",
    "wof:name":"Angwan-Maiwasa",
    "wof:placetype":"locality"
},
  "geometry": {"coordinates":[6.57821,11.30004],"type":"Point"}
}