{
  "type": "Feature",
  "properties": {
    "gn:admin1_code":"35.0",
    "gn:admin2_code":"2011",
    "gn:asciiname":"Wuro Gortode",
    "gn:country_code":"NG",
    "gn:dem":469,
    "gn:feature_class":"P",
    "gn:feature_code":"PPL",
    "gn:name":"Wuro Gortode",
    "gn:population":0,
    "gn:timezone":"Africa/Lagos",
    "iso:country":"NG",
    "wof:name":"Wuro Gortode",
    "wof:placetype":"locality"
},
  "geometry": {"coordinates":[13.10741,9.80225],"type":"Point"}
}