{
  "type": "Feature",
  "properties": {
    "gn:admin1_code":"51.0",
    "gn:admin2_code":"606.0",
    "gn:admin3_code":"60608",
    "gn:asciiname":"Tudu",
    "gn:country_code":"NG",
    "gn:dem":298,
    "gn:feature_class":"P",
    "gn:feature_code":"PPL",
    "gn:name":"Tudu",
    "gn:population":0,
    "gn:timezone":"Africa/Lagos",
    "iso:country":"NG",
    "name:ceb_x_preferred":[
        "Tudu"
    ],
    "wof:name":"Tudu",
    "wof:placetype":"locality"
},
  "geometry": {"coordinates":[4.25353,13.46329],"type":"Point"}
}