{
  "type": "Feature",
  "properties": {
    "gn:admin1_code":"41.0",
    "gn:admin2_code":"23008.0",
    "gn:asciiname":"Afagba",
    "gn:country_code":"NG",
    "gn:dem":57,
    "gn:feature_class":"P",
    "gn:feature_code":"PPL",
    "gn:name":"Afagba",
    "gn:population":0,
    "gn:timezone":"Africa/Lagos",
    "iso:country":"NG",
    "name:und_x_variant":[
        "Afogba",
        "Afagba"
    ],
    "wof:name":"Afagba",
    "wof:placetype":"locality"
},
  "geometry": {"coordinates":[7.11667,7.03333],"type":"Point"}
}