{
  "type": "Feature",
  "properties": {
    "gn:admin1_code":"31.0",
    "gn:admin2_code":"27010.0",
    "gn:asciiname":"Bobo",
    "gn:country_code":"NG",
    "gn:dem":172,
    "gn:feature_class":"P",
    "gn:feature_code":"PPL",
    "gn:name":"Bobo",
    "gn:population":0,
    "gn:timezone":"Africa/Lagos",
    "iso:country":"NG",
    "name:ceb_x_preferred":[
        "Bobo"
    ],
    "name:deu_x_preferred":[
        "Bobo"
    ],
    "name:fin_x_preferred":[
        "Bobo"
    ],
    "name:fra_x_preferred":[
        "Bobo"
    ],
    "name:hun_x_preferred":[
        "Bobo"
    ],
    "name:ita_x_preferred":[
        "Bobo"
    ],
    "name:nld_x_preferred":[
        "Bobo"
    ],
    "name:pol_x_preferred":[
        "Bobo"
    ],
    "name:por_x_preferred":[
        "Bobo"
    ],
    "name:rus_x_preferred":[
        "\u0411\u043e\u0431\u043e"
    ],
    "name:spa_x_preferred":[
        "Bobo"
    ],
    "name:zho_x_preferred":[
        "Bobo"
    ],
    "wof:name":"Bobo",
    "wof:placetype":"locality"
},
  "geometry": {"coordinates":[6.47309,9.39278],"type":"Point"}
}