{
  "type": "Feature",
  "properties": {
    "gn:admin1_code":"26.0",
    "gn:admin2_code":"7019.0",
    "gn:asciiname":"Boju-Ega",
    "gn:country_code":"NG",
    "gn:dem":179,
    "gn:feature_class":"P",
    "gn:feature_code":"PPL",
    "gn:name":"Boju-Ega",
    "gn:population":0,
    "gn:timezone":"Africa/Lagos",
    "iso:country":"NG",
    "name:und_x_variant":[
        "Ogobia",
        "Boju-Ega"
    ],
    "wof:name":"Boju-Ega",
    "wof:placetype":"locality"
},
  "geometry": {"coordinates":[8.0447,7.34815],"type":"Point"}
}