{
  "type": "Feature",
  "properties": {
    "gn:admin1_code":"26.0",
    "gn:admin2_code":"7003.0",
    "gn:asciiname":"Okpoku",
    "gn:country_code":"NG",
    "gn:dem":142,
    "gn:feature_class":"P",
    "gn:feature_code":"PPL",
    "gn:name":"Okpoku",
    "gn:population":0,
    "gn:timezone":"Africa/Lagos",
    "iso:country":"NG",
    "name:und_x_variant":[
        "Okpogu",
        "Okpoku"
    ],
    "wof:name":"Okpoku",
    "wof:placetype":"locality"
},
  "geometry": {"coordinates":[7.93145,7.6158],"type":"Point"}
}