{
  "type": "Feature",
  "properties": {
    "gn:admin1_code":"57.0",
    "gn:admin2_code":"805.0",
    "gn:admin3_code":"80506",
    "gn:asciiname":"Karakai",
    "gn:country_code":"NG",
    "gn:dem":405,
    "gn:feature_class":"P",
    "gn:feature_code":"PPL",
    "gn:name":"Karakai",
    "gn:population":0,
    "gn:timezone":"Africa/Lagos",
    "iso:country":"NG",
    "wof:name":"Karakai",
    "wof:placetype":"locality"
},
  "geometry": {"coordinates":[6.44968,12.37376],"type":"Point"}
}