{
  "type": "Feature",
  "properties": {
    "gn:admin1_code":"35.0",
    "gn:admin2_code":"2002",
    "gn:asciiname":"Jauro Mahamudu",
    "gn:country_code":"NG",
    "gn:dem":337,
    "gn:feature_class":"P",
    "gn:feature_code":"PPL",
    "gn:name":"Jauro Mahamudu",
    "gn:population":0,
    "gn:timezone":"Africa/Lagos",
    "iso:country":"NG",
    "wof:name":"Jauro Mahamudu",
    "wof:placetype":"locality"
},
  "geometry": {"coordinates":[12.46482,8.77827],"type":"Point"}
}