{
  "type": "Feature",
  "properties": {
    "gn:admin1_code":"5.0",
    "gn:admin2_code":"25008.0",
    "gn:asciiname":"Bamgbose",
    "gn:cc2":"NG",
    "gn:country_code":"NG",
    "gn:dem":8,
    "gn:feature_class":"P",
    "gn:feature_code":"PPL",
    "gn:name":"Bamgbose",
    "gn:population":0,
    "gn:timezone":"Africa/Lagos",
    "iso:country":"NG",
    "name:und_x_variant":[
        "Bamgboshe",
        "Bamgbose"
    ],
    "wof:name":"Bamgbose",
    "wof:placetype":"locality"
},
  "geometry": {"coordinates":[3.45,6.45],"type":"Point"}
}