{
  "type": "Feature",
  "properties": {
    "gn:admin1_code":"43.0",
    "gn:admin2_code":"35012",
    "gn:asciiname":"Hundu",
    "gn:country_code":"NG",
    "gn:dem":180,
    "gn:feature_class":"P",
    "gn:feature_code":"PPL",
    "gn:name":"Hundu",
    "gn:population":0,
    "gn:timezone":"Africa/Lagos",
    "iso:country":"NG",
    "wof:name":"Hundu",
    "wof:placetype":"locality"
},
  "geometry": {"coordinates":[9.89371,7.51774],"type":"Point"}
}