{
  "type": "Feature",
  "properties": {
    "gn:admin1_code":"32.0",
    "gn:admin2_code":"31002.0",
    "gn:asciiname":"Araro",
    "gn:country_code":"NG",
    "gn:dem":244,
    "gn:feature_class":"P",
    "gn:feature_code":"PPL",
    "gn:name":"Araro",
    "gn:population":0,
    "gn:timezone":"Africa/Lagos",
    "iso:country":"NG",
    "wof:name":"Araro",
    "wof:placetype":"locality"
},
  "geometry": {"coordinates":[3.84528,7.5225],"type":"Point"}
}