{
  "type": "Feature",
  "properties": {
    "gn:admin1_code":"21.0",
    "gn:admin2_code":"3002.0",
    "gn:asciiname":"Okoro Inyong",
    "gn:country_code":"NG",
    "gn:dem":7,
    "gn:feature_class":"P",
    "gn:feature_code":"PPL",
    "gn:name":"Okoro Inyong",
    "gn:population":0,
    "gn:timezone":"Africa/Lagos",
    "iso:country":"NG",
    "wof:name":"Okoro Inyong",
    "wof:placetype":"locality"
},
  "geometry": {"coordinates":[7.6199,4.52298],"type":"Point"}
}