{
  "type": "Feature",
  "properties": {
    "gn:admin1_code":"35.0",
    "gn:admin2_code":"2002",
    "gn:asciiname":"Tomse",
    "gn:country_code":"NG",
    "gn:dem":379,
    "gn:feature_class":"P",
    "gn:feature_code":"PPL",
    "gn:name":"Tomse",
    "gn:population":0,
    "gn:timezone":"Africa/Lagos",
    "iso:country":"NG",
    "wof:name":"Tomse",
    "wof:placetype":"locality"
},
  "geometry": {"coordinates":[12.42056,8.83335],"type":"Point"}
}