{
  "type": "Feature",
  "properties": {
    "gn:admin1_code":"26.0",
    "gn:admin2_code":"7005",
    "gn:asciiname":"Tiona",
    "gn:country_code":"NG",
    "gn:dem":151,
    "gn:feature_class":"P",
    "gn:feature_code":"PPL",
    "gn:name":"Tiona",
    "gn:population":0,
    "gn:timezone":"Africa/Lagos",
    "iso:country":"NG",
    "wof:name":"Tiona",
    "wof:placetype":"locality"
},
  "geometry": {"coordinates":[8.86525,7.42438],"type":"Point"}
}