{
  "type": "Feature",
  "properties": {
    "gn:admin1_code":"43.0",
    "gn:admin2_code":"35007",
    "gn:asciiname":"Wuro Alhaji Umaru",
    "gn:country_code":"NG",
    "gn:dem":191,
    "gn:feature_class":"P",
    "gn:feature_code":"PPL",
    "gn:name":"Wuro Alhaji Umaru",
    "gn:population":0,
    "gn:timezone":"Africa/Lagos",
    "iso:country":"NG",
    "wof:name":"Wuro Alhaji Umaru",
    "wof:placetype":"locality"
},
  "geometry": {"coordinates":[11.29462,8.91754],"type":"Point"}
}