{
  "type": "Feature",
  "properties": {
    "gn:admin1_code":"31.0",
    "gn:admin2_code":"27005",
    "gn:asciiname":"Tungan Alade",
    "gn:country_code":"NG",
    "gn:dem":254,
    "gn:feature_class":"P",
    "gn:feature_code":"PPL",
    "gn:name":"Tungan Alade",
    "gn:population":0,
    "gn:timezone":"Africa/Lagos",
    "iso:country":"NG",
    "wof:name":"Tungan Alade",
    "wof:placetype":"locality"
},
  "geometry": {"coordinates":[6.59514,9.57053],"type":"Point"}
}