{
  "type": "Feature",
  "properties": {
    "gn:admin1_code":"28.0",
    "gn:admin2_code":"17004.0",
    "gn:asciiname":"Ife",
    "gn:country_code":"NG",
    "gn:dem":106,
    "gn:feature_class":"P",
    "gn:feature_code":"PPL",
    "gn:name":"Ife",
    "gn:population":0,
    "gn:timezone":"Africa/Lagos",
    "iso:country":"NG",
    "name:ara_x_preferred":[
        "\u0627\u064a\u0641\u064a"
    ],
    "name:ben_x_preferred":[
        "\u0987\u09ab\u09c7"
    ],
    "name:bul_x_preferred":[
        "\u0418\u0444\u0435"
    ],
    "name:cat_x_preferred":[
        "Ife"
    ],
    "name:ceb_x_preferred":[
        "Ile-Ife"
    ],
    "name:deu_x_preferred":[
        "Ile-Ife"
    ],
    "name:epo_x_preferred":[
        "Ife"
    ],
    "name:fin_x_preferred":[
        "Ife"
    ],
    "name:fra_x_preferred":[
        "Ife"
    ],
    "name:hun_x_preferred":[
        "Ife"
    ],
    "name:ita_x_preferred":[
        "Ife"
    ],
    "name:jpn_x_preferred":[
        "\u30a4\u30d5\u30a7"
    ],
    "name:lit_x_preferred":[
        "If\u0117"
    ],
    "name:nor_x_preferred":[
        "Ife"
    ],
    "name:pol_x_preferred":[
        "Ife"
    ],
    "name:por_x_preferred":[
        "If\u00e9"
    ],
    "name:ron_x_preferred":[
        "Ife"
    ],
    "name:rus_x_preferred":[
        "\u0418\u0444\u0435"
    ],
    "name:spa_x_preferred":[
        "Ife"
    ],
    "name:swe_x_preferred":[
        "Ife"
    ],
    "name:ukr_x_preferred":[
        "\u0406\u0444\u0435"
    ],
    "name:war_x_preferred":[
        "Ife"
    ],
    "name:yor_x_preferred":[
        "Il\u00e9-If\u1eb9\u0300"
    ],
    "wof:name":"Ife",
    "wof:placetype":"locality"
},
  "geometry": {"coordinates":[7.31031,5.41283],"type":"Point"}
}