{
  "type": "Feature",
  "properties": {
    "gn:admin1_code":"31.0",
    "gn:admin2_code":"27022.0",
    "gn:asciiname":"Sofon Kushaka",
    "gn:cc2":"NG",
    "gn:country_code":"NG",
    "gn:dem":581,
    "gn:feature_class":"P",
    "gn:feature_code":"PPL",
    "gn:name":"Sofon Kushaka",
    "gn:population":0,
    "gn:timezone":"Africa/Lagos",
    "iso:country":"NG",
    "name:und_x_variant":[
        "Kushaka",
        "Sofon Kushaka"
    ],
    "wof:name":"Sofon Kushaka",
    "wof:placetype":"locality"
},
  "geometry": {"coordinates":[6.75,10.55],"type":"Point"}
}