{
  "type": "Feature",
  "properties": {
    "gn:admin1_code":"54.0",
    "gn:admin2_code":"13011.0",
    "gn:asciiname":"Oke Igbira",
    "gn:country_code":"NG",
    "gn:dem":557,
    "gn:feature_class":"P",
    "gn:feature_code":"PPL",
    "gn:name":"Oke Igbira",
    "gn:population":0,
    "gn:timezone":"Africa/Lagos",
    "iso:country":"NG",
    "wof:name":"Oke Igbira",
    "wof:placetype":"locality"
},
  "geometry": {"coordinates":[5.56412,7.81328],"type":"Point"}
}