{
  "type": "Feature",
  "properties": {
    "gn:admin1_code":"26.0",
    "gn:admin2_code":"7004",
    "gn:asciiname":"Ankpyo",
    "gn:country_code":"NG",
    "gn:dem":203,
    "gn:feature_class":"P",
    "gn:feature_code":"PPL",
    "gn:name":"Ankpyo",
    "gn:population":0,
    "gn:timezone":"Africa/Lagos",
    "iso:country":"NG",
    "wof:name":"Ankpyo",
    "wof:placetype":"locality"
},
  "geometry": {"coordinates":[9.17775,7.25325],"type":"Point"}
}