{
  "type": "Feature",
  "properties": {
    "gn:admin1_code":"36.0",
    "gn:admin2_code":"10010.0",
    "gn:asciiname":"Olomoro",
    "gn:country_code":"NG",
    "gn:dem":17,
    "gn:feature_class":"P",
    "gn:feature_code":"PPL",
    "gn:name":"Olomoro",
    "gn:population":0,
    "gn:timezone":"Africa/Lagos",
    "iso:country":"NG",
    "wof:name":"Olomoro",
    "wof:placetype":"locality"
},
  "geometry": {"coordinates":[6.13941,5.4121],"type":"Point"}
}