{
  "type": "Feature",
  "properties": {
    "gn:admin1_code":"22.0",
    "gn:admin2_code":"9006.0",
    "gn:asciiname":"Agbangana",
    "gn:country_code":"NG",
    "gn:dem":94,
    "gn:feature_class":"P",
    "gn:feature_code":"PPL",
    "gn:name":"Agbangana",
    "gn:population":0,
    "gn:timezone":"Africa/Lagos",
    "iso:country":"NG",
    "name:und_x_variant":[
        "Agbangara",
        "Agbangana"
    ],
    "wof:name":"Agbangana",
    "wof:placetype":"locality"
},
  "geometry": {"coordinates":[8.16574,5.37345],"type":"Point"}
}