{
  "type": "Feature",
  "properties": {
    "gn:admin1_code":"0.0",
    "gn:asciiname":"Osubi",
    "gn:country_code":"NG",
    "gn:dem":60,
    "gn:feature_class":"P",
    "gn:feature_code":"PPL",
    "gn:name":"Osubi",
    "gn:population":0,
    "gn:timezone":"Africa/Lagos",
    "iso:country":"NG",
    "wof:name":"Osubi",
    "wof:placetype":"locality"
},
  "geometry": {"coordinates":[2.76667,7.13333],"type":"Point"}
}