{
  "type": "Feature",
  "properties": {
    "gn:admin1_code":"43.0",
    "gn:admin2_code":"35008.0",
    "gn:asciiname":"Kirim",
    "gn:country_code":"NG",
    "gn:dem":343,
    "gn:feature_class":"P",
    "gn:feature_code":"PPL",
    "gn:name":"Kirim",
    "gn:population":0,
    "gn:timezone":"Africa/Lagos",
    "iso:country":"NG",
    "name:eng_x_preferred":[
        "Kirim"
    ],
    "wof:name":"Kirim",
    "wof:placetype":"locality"
},
  "geometry": {"coordinates":[10.90514,9.33626],"type":"Point"}
}