{
  "type": "Feature",
  "properties": {
    "gn:admin1_code":"36.0",
    "gn:admin2_code":"10010.0",
    "gn:asciiname":"Anisa I",
    "gn:country_code":"NG",
    "gn:dem":6,
    "gn:feature_class":"P",
    "gn:feature_code":"PPL",
    "gn:name":"Anisa I",
    "gn:population":0,
    "gn:timezone":"Africa/Lagos",
    "iso:country":"NG",
    "wof:name":"Anisa I",
    "wof:placetype":"locality"
},
  "geometry": {"coordinates":[6.22183,5.24013],"type":"Point"}
}