{
  "type": "Feature",
  "properties": {
    "gn:admin1_code":"21.0",
    "gn:admin2_code":"3015.0",
    "gn:asciiname":"Odoro Ikpe",
    "gn:country_code":"NG",
    "gn:dem":121,
    "gn:feature_class":"P",
    "gn:feature_code":"PPLA2",
    "gn:name":"Odoro Ikpe",
    "gn:population":0,
    "gn:timezone":"Africa/Lagos",
    "iso:country":"NG",
    "name:und_x_variant":[
        "Ududu Ikpe",
        "Odoro Ikpe"
    ],
    "wof:name":"Odoro Ikpe",
    "wof:placetype":"locality"
},
  "geometry": {"coordinates":[7.75184,5.35835],"type":"Point"}
}