{
  "type": "Feature",
  "properties": {
    "gn:admin1_code":"31.0",
    "gn:admin2_code":"27004.0",
    "gn:asciiname":"New Yunmu",
    "gn:country_code":"NG",
    "gn:dem":152,
    "gn:feature_class":"P",
    "gn:feature_code":"PPL",
    "gn:name":"New Yunmu",
    "gn:population":0,
    "gn:timezone":"Africa/Lagos",
    "iso:country":"NG",
    "name:und_x_variant":[
        "Yunu",
        "New Yunmu"
    ],
    "wof:name":"New Yunmu",
    "wof:placetype":"locality"
},
  "geometry": {"coordinates":[4.45473,10.43234],"type":"Point"}
}