{
  "type": "Feature",
  "properties": {
    "gn:admin1_code":"26.0",
    "gn:admin2_code":"7014",
    "gn:asciiname":"Aboko",
    "gn:country_code":"NG",
    "gn:dem":92,
    "gn:feature_class":"P",
    "gn:feature_code":"PPL",
    "gn:name":"Aboko",
    "gn:population":0,
    "gn:timezone":"Africa/Lagos",
    "iso:country":"NG",
    "wof:name":"Aboko",
    "wof:placetype":"locality"
},
  "geometry": {"coordinates":[8.2707,7.13992],"type":"Point"}
}