{
  "type": "Feature",
  "properties": {
    "gn:admin1_code":"49.0",
    "gn:admin2_code":"32001.0",
    "gn:asciiname":"Soki Kafuta",
    "gn:country_code":"NG",
    "gn:dem":1266,
    "gn:feature_class":"P",
    "gn:feature_code":"PPL",
    "gn:name":"Soki Kafuta",
    "gn:population":0,
    "gn:timezone":"Africa/Lagos",
    "iso:country":"NG",
    "name:und_x_variant":[
        "Soka ca Futa",
        "Soki Kafuta"
    ],
    "wof:name":"Soki Kafuta",
    "wof:placetype":"locality"
},
  "geometry": {"coordinates":[8.99589,9.53055],"type":"Point"}
}