{
  "type": "Feature",
  "properties": {
    "gn:admin1_code":"57.0",
    "gn:admin2_code":"813.0",
    "gn:admin3_code":"81309",
    "gn:asciiname":"Mallam Dodo",
    "gn:country_code":"NG",
    "gn:dem":559,
    "gn:feature_class":"P",
    "gn:feature_code":"PPL",
    "gn:name":"Mallam Dodo",
    "gn:population":0,
    "gn:timezone":"Africa/Lagos",
    "iso:country":"NG",
    "wof:name":"Mallam Dodo",
    "wof:placetype":"locality"
},
  "geometry": {"coordinates":[7.10814,11.91999],"type":"Point"}
}