{
  "type": "Feature",
  "properties": {
    "gn:admin1_code":"40.0",
    "gn:admin2_code":"517.0",
    "gn:admin3_code":"51703",
    "gn:asciiname":"Zabarma",
    "gn:country_code":"NG",
    "gn:dem":148,
    "gn:feature_class":"P",
    "gn:feature_code":"PPL",
    "gn:name":"Zabarma",
    "gn:population":0,
    "gn:timezone":"Africa/Lagos",
    "iso:country":"NG",
    "wof:name":"Zabarma",
    "wof:placetype":"locality"
},
  "geometry": {"coordinates":[4.60141,11.11118],"type":"Point"}
}