{
  "type": "Feature",
  "properties": {
    "gn:admin1_code":"39.0",
    "gn:admin2_code":"18025.0",
    "gn:admin3_code":"JI1911",
    "gn:asciiname":"Tsirma",
    "gn:country_code":"NG",
    "gn:dem":391,
    "gn:feature_class":"P",
    "gn:feature_code":"PPL",
    "gn:name":"Tsirma",
    "gn:population":0,
    "gn:timezone":"Africa/Lagos",
    "iso:country":"NG",
    "wof:name":"Tsirma",
    "wof:placetype":"locality"
},
  "geometry": {"coordinates":[9.53333,11.86667],"type":"Point"}
}