{
  "type": "Feature",
  "properties": {
    "gn:admin1_code":"21.0",
    "gn:admin2_code":"3003.0",
    "gn:asciiname":"Ofriyo",
    "gn:country_code":"NG",
    "gn:dem":27,
    "gn:feature_class":"P",
    "gn:feature_code":"PPL",
    "gn:name":"Ofriyo",
    "gn:population":0,
    "gn:timezone":"Africa/Lagos",
    "iso:country":"NG",
    "name:und_x_variant":[
        "Efriyo",
        "Ofriyo"
    ],
    "wof:name":"Ofriyo",
    "wof:placetype":"locality"
},
  "geometry": {"coordinates":[7.94768,4.67393],"type":"Point"}
}