{
  "type": "Feature",
  "properties": {
    "gn:admin1_code":"21.0",
    "gn:admin2_code":"3009.0",
    "gn:asciiname":"Ikot Oku Ubo",
    "gn:country_code":"NG",
    "gn:dem":51,
    "gn:feature_class":"P",
    "gn:feature_code":"PPL",
    "gn:name":"Ikot Oku Ubo",
    "gn:population":0,
    "gn:timezone":"Africa/Lagos",
    "iso:country":"NG",
    "wof:name":"Ikot Oku Ubo",
    "wof:placetype":"locality"
},
  "geometry": {"coordinates":[7.93984,4.94323],"type":"Point"}
}