{
  "type": "Feature",
  "properties": {
    "gn:admin1_code":"24.0",
    "gn:admin2_code":"404.0",
    "gn:admin3_code":"40412",
    "gn:asciiname":"Haruna Buba",
    "gn:country_code":"NG",
    "gn:dem":391,
    "gn:feature_class":"P",
    "gn:feature_code":"PPL",
    "gn:name":"Haruna Buba",
    "gn:population":0,
    "gn:timezone":"Africa/Lagos",
    "iso:country":"NG",
    "wof:name":"Haruna Buba",
    "wof:placetype":"locality"
},
  "geometry": {"coordinates":[8.87072,12.70728],"type":"Point"}
}