{
  "type": "Feature",
  "properties": {
    "gn:admin1_code":"41.0",
    "gn:admin2_code":"23003.0",
    "gn:asciiname":"Abache",
    "gn:country_code":"NG",
    "gn:dem":398,
    "gn:feature_class":"P",
    "gn:feature_code":"PPL",
    "gn:name":"Abache",
    "gn:population":0,
    "gn:timezone":"Africa/Lagos",
    "iso:country":"NG",
    "name:und_x_variant":[
        "Agbachi",
        "Abachi",
        "Abache"
    ],
    "wof:name":"Abache",
    "wof:placetype":"locality"
},
  "geometry": {"coordinates":[7.64949,7.38058],"type":"Point"}
}