{
  "type": "Feature",
  "properties": {
    "gn:admin1_code":"30.0",
    "gn:admin2_code":"24002.0",
    "gn:asciiname":"Kuntubaro",
    "gn:country_code":"NG",
    "gn:dem":357,
    "gn:feature_class":"P",
    "gn:feature_code":"PPL",
    "gn:name":"Kuntubaro",
    "gn:population":0,
    "gn:timezone":"Africa/Lagos",
    "iso:country":"NG",
    "wof:name":"Kuntubaro",
    "wof:placetype":"locality"
},
  "geometry": {"coordinates":[3.18333,8.91667],"type":"Point"}
}