{
  "type": "Feature",
  "properties": {
    "gn:admin1_code":"22.0",
    "gn:admin2_code":"9001.0",
    "gn:asciiname":"Emin Ekpon",
    "gn:country_code":"NG",
    "gn:dem":19,
    "gn:feature_class":"P",
    "gn:feature_code":"PPL",
    "gn:name":"Emin Ekpon",
    "gn:population":0,
    "gn:timezone":"Africa/Lagos",
    "iso:country":"NG",
    "wof:name":"Emin Ekpon",
    "wof:placetype":"locality"
},
  "geometry": {"coordinates":[8.0263,5.92883],"type":"Point"}
}