{
  "type": "Feature",
  "properties": {
    "gn:admin1_code":"16.0",
    "gn:admin2_code":"28006.0",
    "gn:asciiname":"Sepeti",
    "gn:country_code":"NG",
    "gn:dem":25,
    "gn:feature_class":"P",
    "gn:feature_code":"PPL",
    "gn:name":"Sepeti",
    "gn:population":0,
    "gn:timezone":"Africa/Lagos",
    "iso:country":"NG",
    "name:und_x_variant":[
        "Sapeti",
        "Sepeti"
    ],
    "wof:name":"Sepeti",
    "wof:placetype":"locality"
},
  "geometry": {"coordinates":[3.25301,6.90425],"type":"Point"}
}