{
  "type": "Feature",
  "properties": {
    "gn:admin1_code":"26.0",
    "gn:admin2_code":"7004",
    "gn:asciiname":"Iornongo",
    "gn:country_code":"NG",
    "gn:dem":172,
    "gn:feature_class":"P",
    "gn:feature_code":"PPL",
    "gn:name":"Iornongo",
    "gn:population":0,
    "gn:timezone":"Africa/Lagos",
    "iso:country":"NG",
    "wof:name":"Iornongo",
    "wof:placetype":"locality"
},
  "geometry": {"coordinates":[9.0801,7.20985],"type":"Point"}
}