{
  "type": "Feature",
  "properties": {
    "gn:admin1_code":"24.0",
    "gn:admin2_code":"414.0",
    "gn:admin3_code":"41405",
    "gn:asciiname":"Ungwan Rabo Baduku",
    "gn:country_code":"NG",
    "gn:dem":685,
    "gn:feature_class":"P",
    "gn:feature_code":"PPL",
    "gn:name":"Ungwan Rabo Baduku",
    "gn:population":0,
    "gn:timezone":"Africa/Lagos",
    "iso:country":"NG",
    "wof:name":"Ungwan Rabo Baduku",
    "wof:placetype":"locality"
},
  "geometry": {"coordinates":[7.35782,11.39487],"type":"Point"}
}