{
  "type": "Feature",
  "properties": {
    "gn:admin1_code":"51.0",
    "gn:admin2_code":"606.0",
    "gn:admin3_code":"60604",
    "gn:asciiname":"Parakam",
    "gn:country_code":"NG",
    "gn:dem":248,
    "gn:feature_class":"P",
    "gn:feature_code":"PPL",
    "gn:name":"Parakam",
    "gn:population":0,
    "gn:timezone":"Africa/Lagos",
    "iso:country":"NG",
    "name:und_x_variant":[
        "Parakum",
        "Parakam"
    ],
    "wof:name":"Parakam",
    "wof:placetype":"locality"
},
  "geometry": {"coordinates":[4.39536,13.22642],"type":"Point"}
}