{
  "type": "Feature",
  "properties": {
    "gn:admin1_code":"16.0",
    "gn:admin2_code":"28018.0",
    "gn:asciiname":"Zion",
    "gn:country_code":"NG",
    "gn:dem":20,
    "gn:feature_class":"P",
    "gn:feature_code":"PPL",
    "gn:name":"Zion",
    "gn:population":0,
    "gn:timezone":"Africa/Lagos",
    "iso:country":"NG",
    "name:ara_x_preferred":[
        "\u0635\u0647\u064a\u0648\u0646"
    ],
    "name:ckb_x_preferred":[
        "\u0632\u0627\u06cc\u06c6\u0646"
    ],
    "name:cym_x_preferred":[
        "Seion"
    ],
    "name:dan_x_preferred":[
        "Zion"
    ],
    "name:deu_x_preferred":[
        "Zion"
    ],
    "name:epo_x_preferred":[
        "Ciono"
    ],
    "name:fas_x_preferred":[
        "\u0635\u0647\u06cc\u0648\u0646"
    ],
    "name:fin_x_preferred":[
        "Siion"
    ],
    "name:fra_x_preferred":[
        "Sion"
    ],
    "name:hat_x_preferred":[
        "Zion"
    ],
    "name:heb_x_preferred":[
        "\u05e6\u05d9\u05d5\u05df"
    ],
    "name:hun_x_preferred":[
        "Sion"
    ],
    "name:ind_x_preferred":[
        "Zion"
    ],
    "name:jpn_x_preferred":[
        "\u30b7\u30aa\u30f3"
    ],
    "name:nno_x_preferred":[
        "Sion"
    ],
    "name:nor_x_preferred":[
        "Sion"
    ],
    "name:pol_x_preferred":[
        "Syjon"
    ],
    "name:por_x_preferred":[
        "Si\u00e3o"
    ],
    "name:ron_x_preferred":[
        "Sion"
    ],
    "name:slk_x_preferred":[
        "Sion"
    ],
    "name:spa_x_preferred":[
        "Sion"
    ],
    "name:swe_x_preferred":[
        "Sion"
    ],
    "name:tam_x_preferred":[
        "\u0b9a\u0bc0\u0baf\u0bcb\u0ba9\u0bcd"
    ],
    "name:tgl_x_preferred":[
        "Sion"
    ],
    "name:vie_x_preferred":[
        "Zion"
    ],
    "wof:name":"Zion",
    "wof:placetype":"locality"
},
  "geometry": {"coordinates":[4.39802,6.53388],"type":"Point"}
}