{
  "type": "Feature",
  "properties": {
    "gn:admin1_code":"35.0",
    "gn:admin2_code":"2007.0",
    "gn:asciiname":"Ndakambawa",
    "gn:country_code":"NG",
    "gn:dem":560,
    "gn:feature_class":"P",
    "gn:feature_code":"PPL",
    "gn:name":"Ndakambawa",
    "gn:population":0,
    "gn:timezone":"Africa/Lagos",
    "iso:country":"NG",
    "wof:name":"Ndakambawa",
    "wof:placetype":"locality"
},
  "geometry": {"coordinates":[13.00761,10.22908],"type":"Point"}
}