{
  "type": "Feature",
  "properties": {
    "gn:admin1_code":"21.0",
    "gn:admin2_code":"3026.0",
    "gn:asciiname":"Enuek",
    "gn:country_code":"NG",
    "gn:dem":35,
    "gn:feature_class":"P",
    "gn:feature_code":"PPL",
    "gn:name":"Enuek",
    "gn:population":0,
    "gn:timezone":"Africa/Lagos",
    "iso:country":"NG",
    "wof:name":"Enuek",
    "wof:placetype":"locality"
},
  "geometry": {"coordinates":[7.66319,4.69629],"type":"Point"}
}