{
  "type": "Feature",
  "properties": {
    "gn:admin1_code":"26.0",
    "gn:admin2_code":"7008",
    "gn:asciiname":"Michael",
    "gn:country_code":"NG",
    "gn:dem":153,
    "gn:feature_class":"P",
    "gn:feature_code":"PPL",
    "gn:name":"Michael",
    "gn:population":0,
    "gn:timezone":"Africa/Lagos",
    "iso:country":"NG",
    "name:afr_x_preferred":[
        "Michael"
    ],
    "name:arc_x_preferred":[
        "\u0721\u071d\u071f\u0710\u071d\u0720"
    ],
    "name:bre_x_preferred":[
        "Michael"
    ],
    "name:chr_x_preferred":[
        "\u13b9\u13f1\u13a9\u13b5"
    ],
    "name:dan_x_preferred":[
        "Michael"
    ],
    "name:deu_x_preferred":[
        "Michael"
    ],
    "name:fas_x_preferred":[
        "\u0645\u0627\u06cc\u06a9\u0644"
    ],
    "name:fra_x_preferred":[
        "Michael"
    ],
    "name:isl_x_preferred":[
        "Michael"
    ],
    "name:jpn_x_preferred":[
        "\u30de\u30a4\u30b1\u30eb"
    ],
    "name:lat_x_preferred":[
        "Michael"
    ],
    "name:nor_x_preferred":[
        "Michael"
    ],
    "name:slv_x_preferred":[
        "Michael"
    ],
    "wof:name":"Michael",
    "wof:placetype":"locality"
},
  "geometry": {"coordinates":[8.19821,7.55661],"type":"Point"}
}