{
  "type": "Feature",
  "properties": {
    "gn:admin1_code":"21.0",
    "gn:admin2_code":"3009.0",
    "gn:asciiname":"Mbiere Ebe",
    "gn:country_code":"NG",
    "gn:dem":67,
    "gn:feature_class":"P",
    "gn:feature_code":"PPL",
    "gn:name":"Mbiere Ebe",
    "gn:population":0,
    "gn:timezone":"Africa/Lagos",
    "iso:country":"NG",
    "wof:name":"Mbiere Ebe",
    "wof:placetype":"neighbourhood"
},
  "geometry": {"coordinates":[7.90083,4.99735],"type":"Point"}
}