{
  "type": "Feature",
  "properties": {
    "gn:admin1_code":"36.0",
    "gn:admin2_code":"10009.0",
    "gn:asciiname":"Ofagbe",
    "gn:country_code":"NG",
    "gn:dem":18,
    "gn:feature_class":"P",
    "gn:feature_code":"PPL",
    "gn:name":"Ofagbe",
    "gn:population":0,
    "gn:timezone":"Africa/Lagos",
    "iso:country":"NG",
    "wof:name":"Ofagbe",
    "wof:placetype":"locality"
},
  "geometry": {"coordinates":[6.3427,5.54928],"type":"Point"}
}