{
  "type": "Feature",
  "properties": {
    "gn:admin1_code":"24.0",
    "gn:admin2_code":"425.0",
    "gn:admin3_code":"42507",
    "gn:asciiname":"Tsaunin",
    "gn:country_code":"NG",
    "gn:dem":640,
    "gn:feature_class":"P",
    "gn:feature_code":"PPL",
    "gn:name":"Tsaunin",
    "gn:population":0,
    "gn:timezone":"Africa/Lagos",
    "iso:country":"NG",
    "wof:name":"Tsaunin",
    "wof:placetype":"locality"
},
  "geometry": {"coordinates":[7.6397,11.77215],"type":"Point"}
}