{
  "type": "Feature",
  "properties": {
    "gn:admin1_code":"27.0",
    "gn:admin2_code":"105.0",
    "gn:admin3_code":"10504",
    "gn:asciiname":"Tsahuyam",
    "gn:country_code":"NG",
    "gn:dem":600,
    "gn:feature_class":"P",
    "gn:feature_code":"PPL",
    "gn:name":"Tsahuyam",
    "gn:population":0,
    "gn:timezone":"Africa/Lagos",
    "iso:country":"NG",
    "wof:name":"Tsahuyam",
    "wof:placetype":"locality"
},
  "geometry": {"coordinates":[12.00389,10.77983],"type":"Point"}
}