{
  "type": "Feature",
  "properties": {
    "gn:admin1_code":"45.0",
    "gn:admin2_code":"1003.0",
    "gn:asciiname":"Ozu-Abam",
    "gn:country_code":"NG",
    "gn:dem":111,
    "gn:feature_class":"P",
    "gn:feature_code":"PPL",
    "gn:name":"Ozu-Abam",
    "gn:population":0,
    "gn:timezone":"Africa/Lagos",
    "iso:country":"NG",
    "wof:name":"Ozu-Abam",
    "wof:placetype":"locality"
},
  "geometry": {"coordinates":[7.74526,5.59344],"type":"Point"}
}