{
  "type": "Feature",
  "properties": {
    "gn:admin1_code":"32.0",
    "gn:admin2_code":"31012.0",
    "gn:asciiname":"Alapa Market",
    "gn:country_code":"NG",
    "gn:dem":173,
    "gn:feature_class":"P",
    "gn:feature_code":"PPL",
    "gn:name":"Alapa Market",
    "gn:population":0,
    "gn:timezone":"Africa/Lagos",
    "iso:country":"NG",
    "wof:name":"Alapa Market",
    "wof:placetype":"locality"
},
  "geometry": {"coordinates":[3.53333,7.65],"type":"Point"}
}