{
  "type": "Feature",
  "properties": {
    "gn:admin1_code":"43.0",
    "gn:admin2_code":"35015.0",
    "gn:asciiname":"Kolayang-Jauro Bending",
    "gn:country_code":"NG",
    "gn:dem":432,
    "gn:feature_class":"P",
    "gn:feature_code":"PPL",
    "gn:name":"Kolayang-Jauro Bending",
    "gn:population":0,
    "gn:timezone":"Africa/Lagos",
    "iso:country":"NG",
    "name:eng_x_preferred":[
        "Kolayang-Jauro Bending"
    ],
    "name:eng_x_variant":[
        "Kwoliar"
    ],
    "wof:name":"Kolayang-Jauro Bending",
    "wof:placetype":"locality"
},
  "geometry": {"coordinates":[11.62131,9.05253],"type":"Point"}
}