{
  "type": "Feature",
  "properties": {
    "gn:admin1_code":"56.0",
    "gn:admin2_code":"26012.0",
    "gn:asciiname":"Garagwa",
    "gn:country_code":"NG",
    "gn:dem":195,
    "gn:feature_class":"P",
    "gn:feature_code":"PPL",
    "gn:name":"Garagwa",
    "gn:population":0,
    "gn:timezone":"Africa/Lagos",
    "iso:country":"NG",
    "wof:name":"Garagwa",
    "wof:placetype":"locality"
},
  "geometry": {"coordinates":[7.32806,8.46778],"type":"Point"}
}