{
  "type": "Feature",
  "properties": {
    "gn:admin1_code":"49.0",
    "gn:admin2_code":"32007.0",
    "gn:asciiname":"Namuran",
    "gn:country_code":"NG",
    "gn:dem":285,
    "gn:feature_class":"P",
    "gn:feature_code":"PPL",
    "gn:name":"Namuran",
    "gn:population":0,
    "gn:timezone":"Africa/Lagos",
    "iso:country":"NG",
    "name:eng_x_preferred":[
        "Namuran"
    ],
    "wof:name":"Namuran",
    "wof:placetype":"locality"
},
  "geometry": {"coordinates":[9.88869,9.27746],"type":"Point"}
}