{
  "type": "Feature",
  "properties": {
    "gn:admin1_code":"55.0",
    "gn:admin2_code":"16006.0",
    "gn:asciiname":"Wuro Shiji",
    "gn:country_code":"NG",
    "gn:dem":459,
    "gn:feature_class":"P",
    "gn:feature_code":"PPL",
    "gn:name":"Wuro Shiji",
    "gn:population":0,
    "gn:timezone":"Africa/Lagos",
    "iso:country":"NG",
    "wof:name":"Wuro Shiji",
    "wof:placetype":"locality"
},
  "geometry": {"coordinates":[11.16637,10.25801],"type":"Point"}
}