{
  "type": "Feature",
  "properties": {
    "gn:admin1_code":"49.0",
    "gn:admin2_code":"32015",
    "gn:asciiname":"Hawan Kibu",
    "gn:country_code":"NG",
    "gn:dem":1014,
    "gn:feature_class":"P",
    "gn:feature_code":"PPL",
    "gn:name":"Hawan Kibu",
    "gn:population":0,
    "gn:timezone":"Africa/Lagos",
    "iso:country":"NG",
    "wof:name":"Hawan Kibu",
    "wof:placetype":"locality"
},
  "geometry": {"coordinates":[8.64665,9.541],"type":"Point"}
}