{
  "type": "Feature",
  "properties": {
    "gn:admin1_code":"31.0",
    "gn:admin2_code":"27020.0",
    "gn:asciiname":"Zambugga",
    "gn:country_code":"NG",
    "gn:dem":294,
    "gn:feature_class":"P",
    "gn:feature_code":"PPL",
    "gn:name":"Zambugga",
    "gn:population":0,
    "gn:timezone":"Africa/Lagos",
    "iso:country":"NG",
    "wof:name":"Zambugga",
    "wof:placetype":"locality"
},
  "geometry": {"coordinates":[6.16667,10.28333],"type":"Point"}
}