{
  "type": "Feature",
  "properties": {
    "gn:admin1_code":"21.0",
    "gn:admin2_code":"3018.0",
    "gn:asciiname":"Ikot Ekpow",
    "gn:country_code":"NG",
    "gn:dem":50,
    "gn:feature_class":"P",
    "gn:feature_code":"PPL",
    "gn:name":"Ikot Ekpow",
    "gn:population":0,
    "gn:timezone":"Africa/Lagos",
    "iso:country":"NG",
    "wof:name":"Ikot Ekpow",
    "wof:placetype":"locality"
},
  "geometry": {"coordinates":[7.78367,4.84507],"type":"Point"}
}