{
  "type": "Feature",
  "properties": {
    "gn:admin1_code":"51.0",
    "gn:admin2_code":"606.0",
    "gn:admin3_code":"60606",
    "gn:asciiname":"Karfin Chana",
    "gn:country_code":"NG",
    "gn:dem":226,
    "gn:feature_class":"P",
    "gn:feature_code":"PPL",
    "gn:name":"Karfin Chana",
    "gn:population":0,
    "gn:timezone":"Africa/Lagos",
    "iso:country":"NG",
    "wof:name":"Karfin Chana",
    "wof:placetype":"locality"
},
  "geometry": {"coordinates":[4.50304,13.24542],"type":"Point"}
}