{
  "type": "Feature",
  "properties": {
    "gn:admin1_code":"49.0",
    "gn:admin2_code":"32015.0",
    "gn:asciiname":"Akwat",
    "gn:country_code":"NG",
    "gn:dem":593,
    "gn:feature_class":"P",
    "gn:feature_code":"PPL",
    "gn:name":"Akwat",
    "gn:population":0,
    "gn:timezone":"Africa/Lagos",
    "iso:country":"NG",
    "wof:name":"Akwat",
    "wof:placetype":"locality"
},
  "geometry": {"coordinates":[8.5688,9.54411],"type":"Point"}
}