{
  "type": "Feature",
  "properties": {
    "gn:admin1_code":"27.0",
    "gn:admin2_code":"103.0",
    "gn:admin3_code":"10302",
    "gn:asciiname":"Jinneri",
    "gn:country_code":"NG",
    "gn:dem":308,
    "gn:feature_class":"P",
    "gn:feature_code":"PPL",
    "gn:name":"Jinneri",
    "gn:population":0,
    "gn:timezone":"Africa/Lagos",
    "iso:country":"NG",
    "name:und_x_variant":[
        "Jenere",
        "Jinneri"
    ],
    "wof:name":"Jinneri",
    "wof:placetype":"locality"
},
  "geometry": {"coordinates":[14.28619,11.43023],"type":"Point"}
}