{
  "type": "Feature",
  "properties": {
    "gn:admin1_code":"51.0",
    "gn:admin2_code":"606.0",
    "gn:admin3_code":"60610",
    "gn:asciiname":"Kwararap",
    "gn:country_code":"NG",
    "gn:dem":263,
    "gn:feature_class":"P",
    "gn:feature_code":"PPL",
    "gn:name":"Kwararap",
    "gn:population":0,
    "gn:timezone":"Africa/Lagos",
    "iso:country":"NG",
    "wof:name":"Kwararap",
    "wof:placetype":"locality"
},
  "geometry": {"coordinates":[4.30183,13.47474],"type":"Point"}
}