{
  "type": "Feature",
  "properties": {
    "gn:admin1_code":"27.0",
    "gn:admin2_code":"112.0",
    "gn:admin3_code":"11202",
    "gn:asciiname":"Minta",
    "gn:country_code":"NG",
    "gn:dem":585,
    "gn:feature_class":"P",
    "gn:feature_code":"PPL",
    "gn:name":"Minta",
    "gn:population":0,
    "gn:timezone":"Africa/Lagos",
    "iso:country":"NG",
    "wof:name":"Minta",
    "wof:placetype":"locality"
},
  "geometry": {"coordinates":[11.98629,10.56106],"type":"Point"}
}