{
  "type": "Feature",
  "properties": {
    "gn:admin1_code":"27.0",
    "gn:admin2_code":"104.0",
    "gn:admin3_code":"10405",
    "gn:asciiname":"Gulan Bubu",
    "gn:country_code":"NG",
    "gn:dem":245,
    "gn:feature_class":"P",
    "gn:feature_code":"PPL",
    "gn:name":"Gulan Bubu",
    "gn:population":0,
    "gn:timezone":"Africa/Lagos",
    "iso:country":"NG",
    "name:und_x_variant":[
        "Gulan",
        "Gulan Bubu"
    ],
    "wof:name":"Gulan Bubu",
    "wof:placetype":"locality"
},
  "geometry": {"coordinates":[11.73402,10.26214],"type":"Point"}
}