{
  "type": "Feature",
  "properties": {
    "gn:admin1_code":"46.0",
    "gn:admin2_code":"5008.0",
    "gn:admin3_code":"BA0809",
    "gn:asciiname":"Gokaka",
    "gn:country_code":"NG",
    "gn:dem":537,
    "gn:feature_class":"P",
    "gn:feature_code":"PPL",
    "gn:name":"Gokaka",
    "gn:population":0,
    "gn:timezone":"Africa/Lagos",
    "iso:country":"NG",
    "wof:name":"Gokaka",
    "wof:placetype":"locality"
},
  "geometry": {"coordinates":[9.86021,10.64926],"type":"Point"}
}