{
  "type": "Feature",
  "properties": {
    "gn:admin1_code":"40.0",
    "gn:admin2_code":"518.0",
    "gn:admin3_code":"51806",
    "gn:asciiname":"Baban Kwari",
    "gn:country_code":"NG",
    "gn:dem":196,
    "gn:feature_class":"P",
    "gn:feature_code":"PPL",
    "gn:name":"Baban Kwari",
    "gn:population":0,
    "gn:timezone":"Africa/Lagos",
    "iso:country":"NG",
    "name:und_x_variant":[
        "Babban Kwari"
    ],
    "wof:name":"Baban Kwari",
    "wof:placetype":"locality"
},
  "geometry": {"coordinates":[4.14878,12.00066],"type":"Point"}
}