{
  "type": "Feature",
  "properties": {
    "gn:admin1_code":"40.0",
    "gn:admin2_code":"508.0",
    "gn:admin3_code":"50804",
    "gn:asciiname":"Tunga",
    "gn:country_code":"NG",
    "gn:dem":172,
    "gn:feature_class":"P",
    "gn:feature_code":"PPL",
    "gn:name":"Tunga",
    "gn:population":0,
    "gn:timezone":"Africa/Lagos",
    "iso:country":"NG",
    "name:und_x_variant":[
        "Tungan Noma",
        "Tunga"
    ],
    "wof:name":"Tunga",
    "wof:placetype":"locality"
},
  "geometry": {"coordinates":[3.81675,11.71614],"type":"Point"}
}