{
  "type": "Feature",
  "properties": {
    "gn:admin1_code":"40.0",
    "gn:admin2_code":"508.0",
    "gn:admin3_code":"50804",
    "gn:asciiname":"Tunga",
    "gn:country_code":"NG",
    "gn:dem":172,
    "gn:feature_class":"P",
    "gn:feature_code":"PPL",
    "gn:name":"Tunga",
    "gn:population":0,
    "gn:timezone":"Africa/Lagos",
    "iso:country":"NG",
    "name:ceb_x_preferred":[
        "Tunga"
    ],
    "name:deu_x_preferred":[
        "Tunga"
    ],
    "name:fra_x_preferred":[
        "Tunga"
    ],
    "name:nld_x_preferred":[
        "Tunga"
    ],
    "name:nor_x_preferred":[
        "Tunga"
    ],
    "name:por_x_preferred":[
        "Tunga"
    ],
    "name:que_x_preferred":[
        "Tunga"
    ],
    "name:swe_x_preferred":[
        "Tunga"
    ],
    "name:und_x_variant":[
        "Tungan Noma"
    ],
    "wof:name":"Tunga",
    "wof:placetype":"locality"
},
  "geometry": {"coordinates":[3.81675,11.71614],"type":"Point"}
}