{
  "type": "Feature",
  "properties": {
    "gn:admin1_code":"36.0",
    "gn:asciiname":"Utagbo",
    "gn:country_code":"NG",
    "gn:dem":23,
    "gn:feature_class":"P",
    "gn:feature_code":"PPL",
    "gn:name":"Utagbo",
    "gn:population":0,
    "gn:timezone":"Africa/Lagos",
    "iso:country":"NG",
    "name:eng_x_preferred":[
        "Utagbo"
    ],
    "wof:name":"Utagbo",
    "wof:placetype":"locality"
},
  "geometry": {"coordinates":[5.1629,5.8549],"type":"Point"}
}