{
  "type": "Feature",
  "properties": {
    "gn:admin1_code":"32.0",
    "gn:admin2_code":"31014.0",
    "gn:asciiname":"Olugbemi",
    "gn:country_code":"NG",
    "gn:dem":195,
    "gn:feature_class":"P",
    "gn:feature_code":"PPL",
    "gn:name":"Olugbemi",
    "gn:population":0,
    "gn:timezone":"Africa/Lagos",
    "iso:country":"NG",
    "wof:name":"Olugbemi",
    "wof:placetype":"locality"
},
  "geometry": {"coordinates":[3.79139,7.32028],"type":"Point"}
}