{
  "type": "Feature",
  "properties": {
    "gn:admin1_code":"35.0",
    "gn:admin2_code":"2014",
    "gn:asciiname":"Wuro Kauwa",
    "gn:country_code":"NG",
    "gn:dem":566,
    "gn:feature_class":"P",
    "gn:feature_code":"PPL",
    "gn:name":"Wuro Kauwa",
    "gn:population":0,
    "gn:timezone":"Africa/Lagos",
    "iso:country":"NG",
    "name:eng_x_preferred":[
        "Wuro Kauwa"
    ],
    "wof:name":"Wuro Kauwa",
    "wof:placetype":"neighbourhood"
},
  "geometry": {"coordinates":[13.24915,10.28834],"type":"Point"}
}