{
  "type": "Feature",
  "properties": {
    "gn:admin1_code":"52.0",
    "gn:admin2_code":"6005.0",
    "gn:asciiname":"Waribugoama",
    "gn:country_code":"NG",
    "gn:dem":6,
    "gn:feature_class":"P",
    "gn:feature_code":"PPL",
    "gn:name":"Waribugoama",
    "gn:population":0,
    "gn:timezone":"Africa/Lagos",
    "iso:country":"NG",
    "name:und_x_variant":[
        "Waribugama",
        "Waribugoama"
    ],
    "wof:name":"Waribugoama",
    "wof:placetype":"locality"
},
  "geometry": {"coordinates":[6.34548,4.71537],"type":"Point"}
}