{
  "type": "Feature",
  "properties": {
    "gn:admin1_code":"23.0",
    "gn:admin2_code":"19023.0",
    "gn:admin3_code":"KD2301",
    "gn:asciiname":"Ungwan Audi",
    "gn:country_code":"NG",
    "gn:dem":654,
    "gn:feature_class":"P",
    "gn:feature_code":"PPL",
    "gn:name":"Ungwan Audi",
    "gn:population":0,
    "gn:timezone":"Africa/Lagos",
    "iso:country":"NG",
    "wof:name":"Ungwan Audi",
    "wof:placetype":"locality"
},
  "geometry": {"coordinates":[7.5756,11.02979],"type":"Point"}
}