{
  "type": "Feature",
  "properties": {
    "gn:admin1_code":"46.0",
    "gn:admin2_code":"5008.0",
    "gn:admin3_code":"BA0810",
    "gn:asciiname":"Gilliri",
    "gn:country_code":"NG",
    "gn:dem":593,
    "gn:feature_class":"P",
    "gn:feature_code":"PPL",
    "gn:name":"Gilliri",
    "gn:population":0,
    "gn:timezone":"Africa/Lagos",
    "iso:country":"NG",
    "name:eng_x_preferred":[
        "Gilliri"
    ],
    "wof:name":"Gilliri",
    "wof:placetype":"locality"
},
  "geometry": {"coordinates":[10.08834,10.55906],"type":"Point"}
}