{
  "type": "Feature",
  "properties": {
    "gn:admin1_code":"25.0",
    "gn:admin2_code":"4016.0",
    "gn:asciiname":"Oguaniocho",
    "gn:country_code":"NG",
    "gn:dem":18,
    "gn:feature_class":"P",
    "gn:feature_code":"PPL",
    "gn:name":"Oguaniocho",
    "gn:population":0,
    "gn:timezone":"Africa/Lagos",
    "iso:country":"NG",
    "wof:name":"Oguaniocho",
    "wof:placetype":"locality"
},
  "geometry": {"coordinates":[6.75465,5.796],"type":"Point"}
}