{
  "type": "Feature",
  "properties": {
    "gn:admin1_code":"35.0",
    "gn:admin2_code":"2013",
    "gn:asciiname":"Wurkuvi",
    "gn:country_code":"NG",
    "gn:dem":628,
    "gn:feature_class":"P",
    "gn:feature_code":"PPL",
    "gn:name":"Wurkuvi",
    "gn:population":0,
    "gn:timezone":"Africa/Lagos",
    "iso:country":"NG",
    "wof:name":"Wurkuvi",
    "wof:placetype":"locality"
},
  "geometry": {"coordinates":[13.50098,10.59826],"type":"Point"}
}