{
  "type": "Feature",
  "properties": {
    "gn:admin1_code":"39.0",
    "gn:admin2_code":"18021.0",
    "gn:admin3_code":"JI0403",
    "gn:asciiname":"Kwakwarasa",
    "gn:country_code":"NG",
    "gn:dem":353,
    "gn:feature_class":"P",
    "gn:feature_code":"PPL",
    "gn:name":"Kwakwarasa",
    "gn:population":0,
    "gn:timezone":"Africa/Lagos",
    "iso:country":"NG",
    "wof:name":"Kwakwarasa",
    "wof:placetype":"locality"
},
  "geometry": {"coordinates":[9.92342,12.72659],"type":"Point"}
}