{
  "type": "Feature",
  "properties": {
    "gn:admin1_code":"55.0",
    "gn:admin2_code":"16001.0",
    "gn:asciiname":"Owaru",
    "gn:country_code":"NG",
    "gn:dem":413,
    "gn:feature_class":"P",
    "gn:feature_code":"PPL",
    "gn:name":"Owaru",
    "gn:population":0,
    "gn:timezone":"Africa/Lagos",
    "iso:country":"NG",
    "wof:name":"Owaru",
    "wof:placetype":"locality"
},
  "geometry": {"coordinates":[11.00732,10.1419],"type":"Point"}
}