{
  "type": "Feature",
  "properties": {
    "gn:admin1_code":"11.0",
    "gn:admin2_code":"15003.0",
    "gn:asciiname":"Gwagwalada",
    "gn:country_code":"NG",
    "gn:dem":186,
    "gn:feature_class":"P",
    "gn:feature_code":"PPLA2",
    "gn:name":"Gwagwalada",
    "gn:population":0,
    "gn:timezone":"Africa/Lagos",
    "iso:country":"NG",
    "name:fra_x_preferred":[
        "Gwagwalada"
    ],
    "name:nld_x_preferred":[
        "Gwagwalada"
    ],
    "name:por_x_preferred":[
        "Gwagwalada"
    ],
    "name:und_x_variant":[
        "Gwagwaldda"
    ],
    "wof:name":"Gwagwalada",
    "wof:placetype":"locality"
},
  "geometry": {"coordinates":[7.08165,8.94342],"type":"Point"}
}