{
  "type": "Feature",
  "properties": {
    "gn:admin1_code":"21.0",
    "gn:admin2_code":"3017.0",
    "gn:asciiname":"Ibuot Ikot",
    "gn:country_code":"NG",
    "gn:dem":5,
    "gn:feature_class":"P",
    "gn:feature_code":"PPL",
    "gn:name":"Ibuot Ikot",
    "gn:population":0,
    "gn:timezone":"Africa/Lagos",
    "iso:country":"NG",
    "wof:name":"Ibuot Ikot",
    "wof:placetype":"locality"
},
  "geometry": {"coordinates":[8.3379,4.6217],"type":"Point"}
}