{
  "type": "Feature",
  "properties": {
    "gn:admin1_code":"31.0",
    "gn:admin2_code":"27007.0",
    "gn:asciiname":"Sosa",
    "gn:country_code":"NG",
    "gn:dem":56,
    "gn:feature_class":"P",
    "gn:feature_code":"PPL",
    "gn:name":"Sosa",
    "gn:population":0,
    "gn:timezone":"Africa/Lagos",
    "iso:country":"NG",
    "wof:name":"Sosa",
    "wof:placetype":"locality"
},
  "geometry": {"coordinates":[5.86667,8.83333],"type":"Point"}
}