{
  "type": "Feature",
  "properties": {
    "gn:admin1_code":"35.0",
    "gn:asciiname":"Njorowe",
    "gn:country_code":"NG",
    "gn:dem":160,
    "gn:feature_class":"P",
    "gn:feature_code":"PPL",
    "gn:name":"Njorowe",
    "gn:population":0,
    "gn:timezone":"Africa/Lagos",
    "iso:country":"NG",
    "name:eng_x_preferred":[
        "Njorowe"
    ],
    "wof:name":"Njorowe",
    "wof:placetype":"locality"
},
  "geometry": {"coordinates":[11.90516,9.43937],"type":"Point"}
}