{
  "type": "Feature",
  "properties": {
    "gn:admin1_code":"36.0",
    "gn:admin2_code":"10011.0",
    "gn:asciiname":"Obom Camp",
    "gn:country_code":"NG",
    "gn:dem":26,
    "gn:feature_class":"P",
    "gn:feature_code":"PPL",
    "gn:name":"Obom Camp",
    "gn:population":0,
    "gn:timezone":"Africa/Lagos",
    "iso:country":"NG",
    "wof:name":"Obom Camp",
    "wof:placetype":"locality"
},
  "geometry": {"coordinates":[6.64377,5.96332],"type":"Point"}
}