{
  "type": "Feature",
  "properties": {
    "gn:admin1_code":"37.0",
    "gn:admin2_code":"12018.0",
    "gn:asciiname":"Ekoarmufua",
    "gn:country_code":"NG",
    "gn:dem":154,
    "gn:feature_class":"P",
    "gn:feature_code":"PPL",
    "gn:name":"Ekoarmufua",
    "gn:population":0,
    "gn:timezone":"Africa/Lagos",
    "iso:country":"NG",
    "wof:name":"Ekoarmufua",
    "wof:placetype":"locality"
},
  "geometry": {"coordinates":[5.75272,6.53736],"type":"Point"}
}