{
  "type": "Feature",
  "properties": {
    "gn:admin1_code":"44.0",
    "gn:admin2_code":"717.0",
    "gn:admin3_code":"71707",
    "gn:asciiname":"Adin",
    "gn:country_code":"NG",
    "gn:dem":340,
    "gn:feature_class":"P",
    "gn:feature_code":"PPL",
    "gn:name":"Adin",
    "gn:population":0,
    "gn:timezone":"Africa/Lagos",
    "iso:country":"NG",
    "wof:name":"Adin",
    "wof:placetype":"locality"
},
  "geometry": {"coordinates":[11.04551,13.26533],"type":"Point"}
}