{
  "type": "Feature",
  "properties": {
    "gn:admin1_code":"24.0",
    "gn:admin2_code":"424.0",
    "gn:admin3_code":"42407",
    "gn:asciiname":"Mefaru",
    "gn:country_code":"NG",
    "gn:dem":474,
    "gn:feature_class":"P",
    "gn:feature_code":"PPL",
    "gn:name":"Mefaru",
    "gn:population":0,
    "gn:timezone":"Africa/Lagos",
    "iso:country":"NG",
    "wof:name":"Mefaru",
    "wof:placetype":"locality"
},
  "geometry": {"coordinates":[8.22601,13.18565],"type":"Point"}
}