{
  "type": "Feature",
  "properties": {
    "gn:admin1_code":"35.0",
    "gn:admin2_code":"2019.0",
    "gn:asciiname":"Sarkin Baka",
    "gn:country_code":"NG",
    "gn:dem":610,
    "gn:feature_class":"P",
    "gn:feature_code":"PPL",
    "gn:name":"Sarkin Baka",
    "gn:population":0,
    "gn:timezone":"Africa/Lagos",
    "iso:country":"NG",
    "wof:name":"Sarkin Baka",
    "wof:placetype":"locality"
},
  "geometry": {"coordinates":[12.03333,7.93333],"type":"Point"}
}