{
  "type": "Feature",
  "properties": {
    "gn:admin1_code":"44.0",
    "gn:admin2_code":"707.0",
    "gn:admin3_code":"70703",
    "gn:asciiname":"Gotumba",
    "gn:country_code":"NG",
    "gn:dem":389,
    "gn:feature_class":"P",
    "gn:feature_code":"PPL",
    "gn:name":"Gotumba",
    "gn:population":0,
    "gn:timezone":"Africa/Lagos",
    "iso:country":"NG",
    "name:und_x_variant":[
        "Gotumboa",
        "Gotumba"
    ],
    "wof:name":"Gotumba",
    "wof:placetype":"locality"
},
  "geometry": {"coordinates":[12.24678,11.57782],"type":"Point"}
}