{
  "type": "Feature",
  "properties": {
    "gn:admin1_code":"35.0",
    "gn:admin2_code":"2004.0",
    "gn:asciiname":"Jiberu",
    "gn:country_code":"NG",
    "gn:dem":240,
    "gn:feature_class":"P",
    "gn:feature_code":"PPL",
    "gn:name":"Jiberu",
    "gn:population":0,
    "gn:timezone":"Africa/Lagos",
    "iso:country":"NG",
    "wof:name":"Jiberu",
    "wof:placetype":"locality"
},
  "geometry": {"coordinates":[12.57667,9.50278],"type":"Point"}
}