{
  "type": "Feature",
  "properties": {
    "gn:admin1_code":"52.0",
    "gn:admin2_code":"6004.0",
    "gn:asciiname":"Ewokiri",
    "gn:country_code":"NG",
    "gn:dem":12,
    "gn:feature_class":"P",
    "gn:feature_code":"PPL",
    "gn:name":"Ewokiri",
    "gn:population":0,
    "gn:timezone":"Africa/Lagos",
    "iso:country":"NG",
    "wof:name":"Ewokiri",
    "wof:placetype":"locality"
},
  "geometry": {"coordinates":[6.28029,4.61299],"type":"Point"}
}