{
  "type": "Feature",
  "properties": {
    "gn:admin1_code":"27.0",
    "gn:admin2_code":"112.0",
    "gn:admin3_code":"11209",
    "gn:asciiname":"Ngwalangwalam",
    "gn:country_code":"NG",
    "gn:dem":290,
    "gn:feature_class":"P",
    "gn:feature_code":"PPL",
    "gn:name":"Ngwalangwalam",
    "gn:population":0,
    "gn:timezone":"Africa/Lagos",
    "iso:country":"NG",
    "wof:name":"Ngwalangwalam",
    "wof:placetype":"locality"
},
  "geometry": {"coordinates":[12.26256,10.40447],"type":"Point"}
}