{
  "type": "Feature",
  "properties": {
    "gn:admin1_code":"29.0",
    "gn:admin2_code":"20034.0",
    "gn:admin3_code":"KN2414",
    "gn:asciiname":"Ungwan Almajiri",
    "gn:country_code":"NG",
    "gn:dem":625,
    "gn:feature_class":"P",
    "gn:feature_code":"PPL",
    "gn:name":"Ungwan Almajiri",
    "gn:population":0,
    "gn:timezone":"Africa/Lagos",
    "iso:country":"NG",
    "name:und_x_variant":[
        "Almajiri",
        "Ungwan Almajiri"
    ],
    "wof:name":"Ungwan Almajiri",
    "wof:placetype":"locality"
},
  "geometry": {"coordinates":[8.20353,11.44355],"type":"Point"}
}