{
  "type": "Feature",
  "properties": {
    "gn:admin1_code":"48.0",
    "gn:admin2_code":"29008.0",
    "gn:asciiname":"Mobolorunduro",
    "gn:country_code":"NG",
    "gn:dem":277,
    "gn:feature_class":"P",
    "gn:feature_code":"PPL",
    "gn:name":"Mobolorunduro",
    "gn:population":0,
    "gn:timezone":"Africa/Lagos",
    "iso:country":"NG",
    "wof:name":"Mobolorunduro",
    "wof:placetype":"locality"
},
  "geometry": {"coordinates":[5.1613,7.0237],"type":"Point"}
}