{
  "type": "Feature",
  "properties": {
    "gn:admin1_code":"27.0",
    "gn:admin2_code":"103.0",
    "gn:admin3_code":"10312",
    "gn:asciiname":"Daweri",
    "gn:country_code":"NG",
    "gn:dem":318,
    "gn:feature_class":"P",
    "gn:feature_code":"PPL",
    "gn:name":"Daweri",
    "gn:population":0,
    "gn:timezone":"Africa/Lagos",
    "iso:country":"NG",
    "name:und_x_variant":[
        "Darasalam",
        "Daweri"
    ],
    "wof:name":"Daweri",
    "wof:placetype":"locality"
},
  "geometry": {"coordinates":[13.87968,11.39966],"type":"Point"}
}