{
  "type": "Feature",
  "properties": {
    "gn:admin1_code":"35.0",
    "gn:admin2_code":"2011.0",
    "gn:asciiname":"Fureima",
    "gn:country_code":"NG",
    "gn:dem":680,
    "gn:feature_class":"P",
    "gn:feature_code":"PPL",
    "gn:name":"Fureima",
    "gn:population":0,
    "gn:timezone":"Africa/Lagos",
    "iso:country":"NG",
    "wof:name":"Fureima",
    "wof:placetype":"locality"
},
  "geometry": {"coordinates":[13.22158,10.02994],"type":"Point"}
}