{
  "type": "Feature",
  "properties": {
    "gn:admin1_code":"39.0",
    "gn:admin2_code":"18030.0",
    "gn:admin3_code":"JI2505",
    "gn:asciiname":"Falomi",
    "gn:country_code":"NG",
    "gn:dem":370,
    "gn:feature_class":"P",
    "gn:feature_code":"PPL",
    "gn:name":"Falomi",
    "gn:population":0,
    "gn:timezone":"Africa/Lagos",
    "iso:country":"NG",
    "wof:name":"Falomi",
    "wof:placetype":"locality"
},
  "geometry": {"coordinates":[9.34883,12.52047],"type":"Point"}
}