{
  "type": "Feature",
  "properties": {
    "gn:admin1_code":"56.0",
    "gn:admin2_code":"26004.0",
    "gn:asciiname":"Gidan Rago",
    "gn:country_code":"NG",
    "gn:dem":378,
    "gn:feature_class":"P",
    "gn:feature_code":"PPL",
    "gn:name":"Gidan Rago",
    "gn:population":0,
    "gn:timezone":"Africa/Lagos",
    "iso:country":"NG",
    "wof:name":"Gidan Rago",
    "wof:placetype":"locality"
},
  "geometry": {"coordinates":[7.71602,9.11206],"type":"Point"}
}