{
  "type": "Feature",
  "properties": {
    "gn:admin1_code":"16.0",
    "gn:admin2_code":"28017.0",
    "gn:asciiname":"Ala",
    "gn:country_code":"NG",
    "gn:dem":27,
    "gn:feature_class":"P",
    "gn:feature_code":"PPL",
    "gn:name":"Ala",
    "gn:population":0,
    "gn:timezone":"Africa/Lagos",
    "iso:country":"NG",
    "wof:name":"Ala",
    "wof:placetype":"locality"
},
  "geometry": {"coordinates":[3.87798,6.75482],"type":"Point"}
}