{
  "type": "Feature",
  "properties": {
    "gn:admin1_code":"39.0",
    "gn:admin2_code":"18016.0",
    "gn:admin3_code":"JI0707",
    "gn:asciiname":"Maikilili",
    "gn:country_code":"NG",
    "gn:dem":366,
    "gn:feature_class":"P",
    "gn:feature_code":"PPL",
    "gn:name":"Maikilili",
    "gn:population":0,
    "gn:timezone":"Africa/Lagos",
    "iso:country":"NG",
    "wof:name":"Maikilili",
    "wof:placetype":"locality"
},
  "geometry": {"coordinates":[9.59805,12.55137],"type":"Point"}
}