{
  "type": "Feature",
  "properties": {
    "gn:admin1_code":"27.0",
    "gn:admin2_code":"120.0",
    "gn:admin3_code":"12003",
    "gn:asciiname":"Gombarambo",
    "gn:country_code":"NG",
    "gn:dem":342,
    "gn:feature_class":"P",
    "gn:feature_code":"PPL",
    "gn:name":"Gombarambo",
    "gn:population":0,
    "gn:timezone":"Africa/Lagos",
    "iso:country":"NG",
    "name:und_x_variant":[
        "Gombaram"
    ],
    "wof:name":"Gombarambo",
    "wof:placetype":"locality"
},
  "geometry": {"coordinates":[12.49314,12.2193],"type":"Point"}
}