{
  "type": "Feature",
  "properties": {
    "gn:admin1_code":"36.0",
    "gn:asciiname":"Ogula",
    "gn:country_code":"NG",
    "gn:dem":8,
    "gn:feature_class":"P",
    "gn:feature_code":"PPL",
    "gn:name":"Ogula",
    "gn:population":0,
    "gn:timezone":"Africa/Lagos",
    "iso:country":"NG",
    "name:und_x_variant":[
        "Ogulagha I",
        "Ogula"
    ],
    "wof:name":"Ogula",
    "wof:placetype":"locality"
},
  "geometry": {"coordinates":[5.35259,5.35699],"type":"Point"}
}