{
  "type": "Feature",
  "properties": {
    "gn:admin1_code":"35.0",
    "gn:asciiname":"Kobon Waragiri",
    "gn:country_code":"NG",
    "gn:dem":216,
    "gn:feature_class":"P",
    "gn:feature_code":"PPL",
    "gn:name":"Kobon Waragiri",
    "gn:population":0,
    "gn:timezone":"Africa/Lagos",
    "iso:country":"NG",
    "name:eng_x_preferred":[
        "Kobon Waragiri"
    ],
    "wof:name":"Kobon Waragiri",
    "wof:placetype":"locality"
},
  "geometry": {"coordinates":[11.91607,9.30657],"type":"Point"}
}