{
  "type": "Feature",
  "properties": {
    "gn:admin1_code":"46.0",
    "gn:admin2_code":"5010.0",
    "gn:admin3_code":"BA1002",
    "gn:asciiname":"Mashamo",
    "gn:country_code":"NG",
    "gn:dem":387,
    "gn:feature_class":"P",
    "gn:feature_code":"PPL",
    "gn:name":"Mashamo",
    "gn:population":0,
    "gn:timezone":"Africa/Lagos",
    "iso:country":"NG",
    "wof:name":"Mashamo",
    "wof:placetype":"locality"
},
  "geometry": {"coordinates":[9.94275,11.78226],"type":"Point"}
}