{
  "type": "Feature",
  "properties": {
    "gn:admin1_code":"31.0",
    "gn:admin2_code":"27007",
    "gn:asciiname":"Gondongi",
    "gn:country_code":"NG",
    "gn:dem":135,
    "gn:feature_class":"P",
    "gn:feature_code":"PPL",
    "gn:name":"Gondongi",
    "gn:population":0,
    "gn:timezone":"Africa/Lagos",
    "iso:country":"NG",
    "wof:name":"Gondongi",
    "wof:placetype":"locality"
},
  "geometry": {"coordinates":[5.57718,9.08849],"type":"Point"}
}