{
  "type": "Feature",
  "properties": {
    "gn:admin1_code":"31.0",
    "gn:admin2_code":"27019.0",
    "gn:asciiname":"Ndayma",
    "gn:country_code":"NG",
    "gn:dem":220,
    "gn:feature_class":"P",
    "gn:feature_code":"PPL",
    "gn:name":"Ndayma",
    "gn:population":0,
    "gn:timezone":"Africa/Lagos",
    "iso:country":"NG",
    "wof:name":"Ndayma",
    "wof:placetype":"locality"
},
  "geometry": {"coordinates":[6.5365,9.34795],"type":"Point"}
}