{
  "type": "Feature",
  "properties": {
    "gn:admin1_code":"35.0",
    "gn:admin2_code":"2007.0",
    "gn:asciiname":"Dilkanda",
    "gn:country_code":"NG",
    "gn:dem":484,
    "gn:feature_class":"P",
    "gn:feature_code":"PPL",
    "gn:name":"Dilkanda",
    "gn:population":0,
    "gn:timezone":"Africa/Lagos",
    "iso:country":"NG",
    "wof:name":"Dilkanda",
    "wof:placetype":"locality"
},
  "geometry": {"coordinates":[12.98571,10.04799],"type":"Point"}
}