{
  "type": "Feature",
  "properties": {
    "gn:admin1_code":"23.0",
    "gn:admin2_code":"19007.0",
    "gn:admin3_code":"KD0705",
    "gn:asciiname":"Nidem",
    "gn:country_code":"NG",
    "gn:dem":546,
    "gn:feature_class":"P",
    "gn:feature_code":"PPL",
    "gn:name":"Nidem",
    "gn:population":0,
    "gn:timezone":"Africa/Lagos",
    "iso:country":"NG",
    "name:und_x_variant":[
        "Nindam"
    ],
    "wof:name":"Nidem",
    "wof:placetype":"locality"
},
  "geometry": {"coordinates":[8.33379,9.42903],"type":"Point"}
}