{
  "type": "Feature",
  "properties": {
    "gn:admin1_code":"56.0",
    "gn:admin2_code":"26009.0",
    "gn:asciiname":"Gidan Musa",
    "gn:country_code":"NG",
    "gn:dem":63,
    "gn:feature_class":"P",
    "gn:feature_code":"PPL",
    "gn:name":"Gidan Musa",
    "gn:population":0,
    "gn:timezone":"Africa/Lagos",
    "iso:country":"NG",
    "wof:name":"Gidan Musa",
    "wof:placetype":"locality"
},
  "geometry": {"coordinates":[8.02092,7.96346],"type":"Point"}
}