{
  "type": "Feature",
  "properties": {
    "gn:admin1_code":"23.0",
    "gn:admin2_code":"19011.0",
    "gn:admin3_code":"KD1102",
    "gn:asciiname":"Kpomo",
    "gn:country_code":"NG",
    "gn:dem":541,
    "gn:feature_class":"P",
    "gn:feature_code":"PPL",
    "gn:name":"Kpomo",
    "gn:population":0,
    "gn:timezone":"Africa/Lagos",
    "iso:country":"NG",
    "wof:name":"Kpomo",
    "wof:placetype":"locality"
},
  "geometry": {"coordinates":[7.32511,9.45312],"type":"Point"}
}