{
  "type": "Feature",
  "properties": {
    "gn:admin1_code":"43.0",
    "gn:admin2_code":"35011.0",
    "gn:asciiname":"Wakili Goma",
    "gn:country_code":"NG",
    "gn:dem":1770,
    "gn:feature_class":"P",
    "gn:feature_code":"PPL",
    "gn:name":"Wakili Goma",
    "gn:population":0,
    "gn:timezone":"Africa/Lagos",
    "iso:country":"NG",
    "wof:name":"Wakili Goma",
    "wof:placetype":"locality"
},
  "geometry": {"coordinates":[11.13333,6.95],"type":"Point"}
}