{
  "type": "Feature",
  "properties": {
    "gn:admin1_code":"23.0",
    "gn:admin2_code":"19003.0",
    "gn:admin3_code":"KD0305",
    "gn:asciiname":"Kurumi-Sausi",
    "gn:country_code":"NG",
    "gn:dem":662,
    "gn:feature_class":"P",
    "gn:feature_code":"PPL",
    "gn:name":"Kurumi-Sausi",
    "gn:population":0,
    "gn:timezone":"Africa/Lagos",
    "iso:country":"NG",
    "name:und_x_variant":[
        "Kurmin Sauchi",
        "Kurumi-Sausi"
    ],
    "wof:name":"Kurumi-Sausi",
    "wof:placetype":"locality"
},
  "geometry": {"coordinates":[6.98777,11.28769],"type":"Point"}
}