{
  "type": "Feature",
  "properties": {
    "gn:admin1_code":"40.0",
    "gn:admin2_code":"515.0",
    "gn:admin3_code":"51507",
    "gn:asciiname":"Makawa",
    "gn:country_code":"NG",
    "gn:dem":152,
    "gn:feature_class":"P",
    "gn:feature_code":"PPL",
    "gn:name":"Makawa",
    "gn:population":0,
    "gn:timezone":"Africa/Lagos",
    "iso:country":"NG",
    "wof:name":"Makawa",
    "wof:placetype":"locality"
},
  "geometry": {"coordinates":[4.72199,10.56416],"type":"Point"}
}