{
  "type": "Feature",
  "properties": {
    "gn:admin1_code":"39.0",
    "gn:admin2_code":"18022.0",
    "gn:admin3_code":"JI0308",
    "gn:asciiname":"Bodinga",
    "gn:country_code":"NG",
    "gn:dem":435,
    "gn:feature_class":"P",
    "gn:feature_code":"PPL",
    "gn:name":"Bodinga",
    "gn:population":0,
    "gn:timezone":"Africa/Lagos",
    "iso:country":"NG",
    "name:und_x_variant":[
        "Bodinga (1)",
        "Bodinga"
    ],
    "wof:name":"Bodinga",
    "wof:placetype":"locality"
},
  "geometry": {"coordinates":[9.52094,11.34511],"type":"Point"}
}