{
  "type": "Feature",
  "properties": {
    "gn:admin1_code":"35.0",
    "gn:asciiname":"Bobbore",
    "gn:country_code":"NG",
    "gn:dem":206,
    "gn:feature_class":"P",
    "gn:feature_code":"PPL",
    "gn:name":"Bobbore",
    "gn:population":0,
    "gn:timezone":"Africa/Lagos",
    "iso:country":"NG",
    "name:eng_x_preferred":[
        "Bobbore"
    ],
    "wof:name":"Bobbore",
    "wof:placetype":"locality"
},
  "geometry": {"coordinates":[12.14902,9.29608],"type":"Point"}
}