{
  "type": "Feature",
  "properties": {
    "gn:admin1_code":"51.0",
    "gn:admin2_code":"608.0",
    "gn:admin3_code":"60809",
    "gn:asciiname":"Lafani-Tudu",
    "gn:country_code":"NG",
    "gn:dem":320,
    "gn:feature_class":"P",
    "gn:feature_code":"PPL",
    "gn:name":"Lafani-Tudu",
    "gn:population":0,
    "gn:timezone":"Africa/Lagos",
    "iso:country":"NG",
    "wof:name":"Lafani-Tudu",
    "wof:placetype":"locality"
},
  "geometry": {"coordinates":[5.40711,13.77384],"type":"Point"}
}