{
  "type": "Feature",
  "properties": {
    "gn:admin1_code":"36.0",
    "gn:admin2_code":"10008.0",
    "gn:asciiname":"Idumu-Isogba",
    "gn:country_code":"NG",
    "gn:dem":128,
    "gn:feature_class":"P",
    "gn:feature_code":"PPL",
    "gn:name":"Idumu-Isogba",
    "gn:population":0,
    "gn:timezone":"Africa/Lagos",
    "iso:country":"NG",
    "name:eng_x_preferred":[
        "Idumu-Isogba"
    ],
    "wof:name":"Idumu-Isogba",
    "wof:placetype":"locality"
},
  "geometry": {"coordinates":[6.14036,6.12808],"type":"Point"}
}