{
  "type": "Feature",
  "properties": {
    "gn:admin1_code":"35.0",
    "gn:admin2_code":"2013",
    "gn:asciiname":"Kubur Jibje",
    "gn:country_code":"NG",
    "gn:dem":453,
    "gn:feature_class":"P",
    "gn:feature_code":"PPL",
    "gn:name":"Kubur Jibje",
    "gn:population":0,
    "gn:timezone":"Africa/Lagos",
    "iso:country":"NG",
    "name:eng_x_preferred":[
        "Kubur Jibje"
    ],
    "name:eng_x_variant":[
        "Kubur-Jibje"
    ],
    "wof:name":"Kubur Jibje",
    "wof:placetype":"locality"
},
  "geometry": {"coordinates":[13.32868,10.6749],"type":"Point"}
}