{
  "type": "Feature",
  "properties": {
    "gn:admin1_code":"37.0",
    "gn:admin2_code":"12008.0",
    "gn:asciiname":"Ofugbo",
    "gn:country_code":"NG",
    "gn:dem":28,
    "gn:feature_class":"P",
    "gn:feature_code":"PPL",
    "gn:name":"Ofugbo",
    "gn:population":0,
    "gn:timezone":"Africa/Lagos",
    "iso:country":"NG",
    "wof:name":"Ofugbo",
    "wof:placetype":"locality"
},
  "geometry": {"coordinates":[6.6712,7.0363],"type":"Point"}
}