{
  "type": "Feature",
  "properties": {
    "gn:admin1_code":"48.0",
    "gn:admin2_code":"29010.0",
    "gn:asciiname":"Bateru",
    "gn:country_code":"NG",
    "gn:dem":11,
    "gn:feature_class":"P",
    "gn:feature_code":"PPL",
    "gn:name":"Bateru",
    "gn:population":0,
    "gn:timezone":"Africa/Lagos",
    "iso:country":"NG",
    "wof:name":"Bateru",
    "wof:placetype":"locality"
},
  "geometry": {"coordinates":[4.65411,6.41014],"type":"Point"}
}