{
  "type": "Feature",
  "properties": {
    "gn:admin1_code":"22.0",
    "gn:admin2_code":"9012.0",
    "gn:asciiname":"Sankwala",
    "gn:country_code":"NG",
    "gn:dem":295,
    "gn:feature_class":"P",
    "gn:feature_code":"PPLA2",
    "gn:name":"Sankwala",
    "gn:population":0,
    "gn:timezone":"Africa/Lagos",
    "iso:country":"NG",
    "wof:name":"Sankwala",
    "wof:placetype":"locality"
},
  "geometry": {"coordinates":[9.22258,6.54753],"type":"Point"}
}