{
  "type": "Feature",
  "properties": {
    "gn:admin1_code":"16.0",
    "gn:admin2_code":"28011.0",
    "gn:asciiname":"Isonyin",
    "gn:country_code":"NG",
    "gn:dem":107,
    "gn:feature_class":"P",
    "gn:feature_code":"PPL",
    "gn:name":"Isonyin",
    "gn:population":0,
    "gn:timezone":"Africa/Lagos",
    "iso:country":"NG",
    "wof:name":"Isonyin",
    "wof:placetype":"locality"
},
  "geometry": {"coordinates":[3.98333,6.83333],"type":"Point"}
}