{
  "type": "Feature",
  "properties": {
    "gn:admin1_code":"46.0",
    "gn:admin2_code":"5008.0",
    "gn:admin3_code":"BA0812",
    "gn:asciiname":"Kafin Galadima",
    "gn:country_code":"NG",
    "gn:dem":493,
    "gn:feature_class":"P",
    "gn:feature_code":"PPL",
    "gn:name":"Kafin Galadima",
    "gn:population":0,
    "gn:timezone":"Africa/Lagos",
    "iso:country":"NG",
    "name:eng_x_preferred":[
        "Kafin Galadima"
    ],
    "wof:name":"Kafin Galadima",
    "wof:placetype":"locality"
},
  "geometry": {"coordinates":[10.25649,10.76256],"type":"Point"}
}