{
  "type": "Feature",
  "properties": {
    "gn:admin1_code":"31.0",
    "gn:admin2_code":"27019.0",
    "gn:asciiname":"Gidan Amale",
    "gn:country_code":"NG",
    "gn:dem":537,
    "gn:feature_class":"P",
    "gn:feature_code":"PPL",
    "gn:name":"Gidan Amale",
    "gn:population":0,
    "gn:timezone":"Africa/Lagos",
    "iso:country":"NG",
    "wof:name":"Gidan Amale",
    "wof:placetype":"locality"
},
  "geometry": {"coordinates":[7.23058,9.57279],"type":"Point"}
}