{
  "type": "Feature",
  "properties": {
    "gn:admin1_code":"36.0",
    "gn:admin2_code":"10010.0",
    "gn:asciiname":"Abero",
    "gn:country_code":"NG",
    "gn:dem":15,
    "gn:feature_class":"P",
    "gn:feature_code":"PPL",
    "gn:name":"Abero",
    "gn:population":0,
    "gn:timezone":"Africa/Lagos",
    "iso:country":"NG",
    "wof:name":"Abero",
    "wof:placetype":"locality"
},
  "geometry": {"coordinates":[6.30181,5.3531],"type":"Point"}
}