{
  "type": "Feature",
  "properties": {
    "gn:admin1_code":"44.0",
    "gn:admin2_code":"703",
    "gn:admin3_code":"70305",
    "gn:asciiname":"Kulugu Tamsuwa",
    "gn:country_code":"NG",
    "gn:dem":374,
    "gn:feature_class":"P",
    "gn:feature_code":"PPL",
    "gn:name":"Kulugu Tamsuwa",
    "gn:population":0,
    "gn:timezone":"Africa/Lagos",
    "iso:country":"NG",
    "wof:name":"Kulugu Tamsuwa",
    "wof:placetype":"locality"
},
  "geometry": {"coordinates":[11.76506,11.95815],"type":"Point"}
}