{
  "type": "Feature",
  "properties": {
    "gn:admin1_code":"36.0",
    "gn:admin2_code":"10010.0",
    "gn:asciiname":"Oruabe",
    "gn:country_code":"NG",
    "gn:dem":14,
    "gn:feature_class":"P",
    "gn:feature_code":"PPL",
    "gn:name":"Oruabe",
    "gn:population":0,
    "gn:timezone":"Africa/Lagos",
    "iso:country":"NG",
    "name:und_x_variant":[
        "Oreba",
        "Oruabe"
    ],
    "wof:name":"Oruabe",
    "wof:placetype":"locality"
},
  "geometry": {"coordinates":[6.13566,5.42148],"type":"Point"}
}