{
  "type": "Feature",
  "properties": {
    "gn:admin1_code":"56.0",
    "gn:admin2_code":"26008.0",
    "gn:asciiname":"Shabu",
    "gn:country_code":"NG",
    "gn:dem":151,
    "gn:feature_class":"P",
    "gn:feature_code":"PPL",
    "gn:name":"Shabu",
    "gn:population":0,
    "gn:timezone":"Africa/Lagos",
    "iso:country":"NG",
    "name:ceb_x_preferred":[
        "Shabu"
    ],
    "name:swe_x_preferred":[
        "Shabu"
    ],
    "wof:name":"Shabu",
    "wof:placetype":"locality"
},
  "geometry": {"coordinates":[8.55,8.56667],"type":"Point"}
}