{
  "type": "Feature",
  "properties": {
    "gn:admin1_code":"51.0",
    "gn:admin2_code":"601.0",
    "gn:admin3_code":"60109",
    "gn:asciiname":"Aleta",
    "gn:country_code":"NG",
    "gn:dem":244,
    "gn:feature_class":"P",
    "gn:feature_code":"PPL",
    "gn:name":"Aleta",
    "gn:population":0,
    "gn:timezone":"Africa/Lagos",
    "iso:country":"NG",
    "name:cat_x_preferred":[
        "Aleta"
    ],
    "name:glg_x_preferred":[
        "Aleta"
    ],
    "name:spa_x_preferred":[
        "Aleta"
    ],
    "wof:name":"Aleta",
    "wof:placetype":"locality"
},
  "geometry": {"coordinates":[4.69821,13.07758],"type":"Point"}
}