{
  "type": "Feature",
  "properties": {
    "gn:admin1_code":"29.0",
    "gn:admin2_code":"20016.0",
    "gn:admin3_code":"KN1305",
    "gn:asciiname":"Gagarawa",
    "gn:country_code":"NG",
    "gn:dem":408,
    "gn:feature_class":"P",
    "gn:feature_code":"PPL",
    "gn:name":"Gagarawa",
    "gn:population":0,
    "gn:timezone":"Africa/Lagos",
    "iso:country":"NG",
    "name:fra_x_preferred":[
        "Gagarawa"
    ],
    "name:hau_x_preferred":[
        "Gagarawa"
    ],
    "name:ita_x_preferred":[
        "Gagarawa"
    ],
    "name:spa_x_preferred":[
        "Gagarawa"
    ],
    "name:und_x_variant":[
        "Kerihi"
    ],
    "wof:name":"Gagarawa",
    "wof:placetype":"locality"
},
  "geometry": {"coordinates":[8.93071,12.22744],"type":"Point"}
}