{
  "type": "Feature",
  "properties": {
    "gn:admin1_code":"40.0",
    "gn:admin2_code":"502.0",
    "gn:admin3_code":"50204",
    "gn:asciiname":"Ungwan Malamawa",
    "gn:country_code":"NG",
    "gn:dem":228,
    "gn:feature_class":"P",
    "gn:feature_code":"PPL",
    "gn:name":"Ungwan Malamawa",
    "gn:population":0,
    "gn:timezone":"Africa/Lagos",
    "iso:country":"NG",
    "wof:name":"Ungwan Malamawa",
    "wof:placetype":"locality"
},
  "geometry": {"coordinates":[3.9086,12.54413],"type":"Point"}
}