{
  "type": "Feature",
  "properties": {
    "gn:admin1_code":"50.0",
    "gn:asciiname":"Okoka",
    "gn:country_code":"NG",
    "gn:dem":7,
    "gn:feature_class":"P",
    "gn:feature_code":"PPL",
    "gn:name":"Okoka",
    "gn:population":0,
    "gn:timezone":"Africa/Lagos",
    "iso:country":"NG",
    "name:und_x_variant":[
        "Okikiri"
    ],
    "wof:name":"Okoka",
    "wof:placetype":"locality"
},
  "geometry": {"coordinates":[6.83083,4.49283],"type":"Point"}
}