{
  "type": "Feature",
  "properties": {
    "gn:admin1_code":"32.0",
    "gn:admin2_code":"31005.0",
    "gn:asciiname":"Egbeda",
    "gn:country_code":"NG",
    "gn:dem":194,
    "gn:feature_class":"P",
    "gn:feature_code":"PPLA2",
    "gn:name":"Egbeda",
    "gn:population":0,
    "gn:timezone":"Africa/Lagos",
    "iso:country":"NG",
    "name:fra_x_preferred":[
        "Egbeda"
    ],
    "name:hau_x_preferred":[
        "Egbeda"
    ],
    "name:ita_x_preferred":[
        "Egbeda"
    ],
    "name:spa_x_preferred":[
        "Egbeda"
    ],
    "wof:name":"Egbeda",
    "wof:placetype":"neighbourhood"
},
  "geometry": {"coordinates":[4.04975,7.3772],"type":"Point"}
}