{
  "type": "Feature",
  "properties": {
    "gn:admin1_code":"40.0",
    "gn:admin2_code":"502.0",
    "gn:admin3_code":"50201",
    "gn:asciiname":"Sakwabe",
    "gn:country_code":"NG",
    "gn:dem":216,
    "gn:feature_class":"P",
    "gn:feature_code":"PPL",
    "gn:name":"Sakwabe",
    "gn:population":0,
    "gn:timezone":"Africa/Lagos",
    "iso:country":"NG",
    "name:und_x_variant":[
        "Sakwabi",
        "Sakwabe"
    ],
    "wof:name":"Sakwabe",
    "wof:placetype":"locality"
},
  "geometry": {"coordinates":[4.21339,13.15661],"type":"Point"}
}