{
  "type": "Feature",
  "properties": {
    "gn:admin1_code":"40.0",
    "gn:admin2_code":"502.0",
    "gn:admin3_code":"50202",
    "gn:asciiname":"Masama",
    "gn:country_code":"NG",
    "gn:dem":229,
    "gn:feature_class":"P",
    "gn:feature_code":"PPL",
    "gn:name":"Masama",
    "gn:population":0,
    "gn:timezone":"Africa/Lagos",
    "iso:country":"NG",
    "name:run_x_preferred":[
        "Masama"
    ],
    "name:und_x_variant":[
        "Massama",
        "Cibiki Baba",
        "Masama"
    ],
    "wof:name":"Masama",
    "wof:placetype":"locality"
},
  "geometry": {"coordinates":[3.8428,12.47422],"type":"Point"}
}