{
  "type": "Feature",
  "properties": {
    "gn:admin1_code":"43.0",
    "gn:admin2_code":"35003.0",
    "gn:asciiname":"Abokpa",
    "gn:country_code":"NG",
    "gn:dem":158,
    "gn:feature_class":"P",
    "gn:feature_code":"PPL",
    "gn:name":"Abokpa",
    "gn:population":0,
    "gn:timezone":"Africa/Lagos",
    "iso:country":"NG",
    "name:und_x_variant":[
        "Abokpa Tyav"
    ],
    "wof:name":"Abokpa",
    "wof:placetype":"locality"
},
  "geometry": {"coordinates":[10.04665,7.60252],"type":"Point"}
}