{
  "type": "Feature",
  "properties": {
    "gn:admin1_code":"11.0",
    "gn:admin2_code":"15004.0",
    "gn:asciiname":"Kashimoro",
    "gn:country_code":"NG",
    "gn:dem":276,
    "gn:feature_class":"P",
    "gn:feature_code":"PPL",
    "gn:name":"Kashimoro",
    "gn:population":0,
    "gn:timezone":"Africa/Lagos",
    "iso:country":"NG",
    "wof:name":"Kashimoro",
    "wof:placetype":"locality"
},
  "geometry": {"coordinates":[7.36889,8.57167],"type":"Point"}
}