{
  "type": "Feature",
  "properties": {
    "gn:admin1_code":"45.0",
    "gn:admin2_code":"1010.0",
    "gn:asciiname":"Amurie",
    "gn:country_code":"NG",
    "gn:dem":115,
    "gn:feature_class":"P",
    "gn:feature_code":"PPL",
    "gn:name":"Amurie",
    "gn:population":0,
    "gn:timezone":"Africa/Lagos",
    "iso:country":"NG",
    "wof:name":"Amurie",
    "wof:placetype":"locality"
},
  "geometry": {"coordinates":[7.76006,5.76859],"type":"Point"}
}