{
  "type": "Feature",
  "properties": {
    "gn:admin1_code":"39.0",
    "gn:admin2_code":"18014.0",
    "gn:admin3_code":"JI2206",
    "gn:asciiname":"Miga",
    "gn:country_code":"NG",
    "gn:dem":372,
    "gn:feature_class":"P",
    "gn:feature_code":"PPLA2",
    "gn:name":"Miga",
    "gn:population":0,
    "gn:timezone":"Africa/Lagos",
    "iso:country":"NG",
    "wof:name":"Miga",
    "wof:placetype":"locality"
},
  "geometry": {"coordinates":[9.71362,12.2388],"type":"Point"}
}