{
  "type": "Feature",
  "properties": {
    "gn:admin1_code":"55.0",
    "gn:admin2_code":"16005.0",
    "gn:asciiname":"Daniski",
    "gn:country_code":"NG",
    "gn:dem":275,
    "gn:feature_class":"P",
    "gn:feature_code":"PPL",
    "gn:name":"Daniski",
    "gn:population":0,
    "gn:timezone":"Africa/Lagos",
    "iso:country":"NG",
    "wof:name":"Daniski",
    "wof:placetype":"locality"
},
  "geometry": {"coordinates":[11.44249,10.7084],"type":"Point"}
}