{
  "type": "Feature",
  "properties": {
    "gn:admin1_code":"26.0",
    "gn:admin2_code":"7005",
    "gn:asciiname":"Tso-Kaa",
    "gn:country_code":"NG",
    "gn:dem":114,
    "gn:feature_class":"P",
    "gn:feature_code":"PPL",
    "gn:name":"Tso-Kaa",
    "gn:population":0,
    "gn:timezone":"Africa/Lagos",
    "iso:country":"NG",
    "wof:name":"Tso-Kaa",
    "wof:placetype":"locality"
},
  "geometry": {"coordinates":[8.75805,7.43167],"type":"Point"}
}