{
  "type": "Feature",
  "properties": {
    "gn:admin1_code":"36.0",
    "gn:admin2_code":"10020.0",
    "gn:asciiname":"Oghrughru",
    "gn:country_code":"NG",
    "gn:dem":18,
    "gn:feature_class":"P",
    "gn:feature_code":"PPL",
    "gn:name":"Oghrughru",
    "gn:population":0,
    "gn:timezone":"Africa/Lagos",
    "iso:country":"NG",
    "wof:name":"Oghrughru",
    "wof:placetype":"locality"
},
  "geometry": {"coordinates":[5.92397,5.22386],"type":"Point"}
}