{
  "type": "Feature",
  "properties": {
    "gn:admin1_code":"24.0",
    "gn:admin2_code":"412.0",
    "gn:admin3_code":"41209",
    "gn:asciiname":"Takasaba",
    "gn:country_code":"NG",
    "gn:dem":503,
    "gn:feature_class":"P",
    "gn:feature_code":"PPL",
    "gn:name":"Takasaba",
    "gn:population":0,
    "gn:timezone":"Africa/Lagos",
    "iso:country":"NG",
    "wof:name":"Takasaba",
    "wof:placetype":"locality"
},
  "geometry": {"coordinates":[7.4764,12.39298],"type":"Point"}
}