{
  "type": "Feature",
  "properties": {
    "gn:admin1_code":"43.0",
    "gn:admin2_code":"35014",
    "gn:asciiname":"Aye",
    "gn:country_code":"NG",
    "gn:dem":195,
    "gn:feature_class":"P",
    "gn:feature_code":"PPL",
    "gn:name":"Aye",
    "gn:population":0,
    "gn:timezone":"Africa/Lagos",
    "iso:country":"NG",
    "name:ceb_x_preferred":[
        "Aye"
    ],
    "name:deu_x_preferred":[
        "Aye"
    ],
    "name:nld_x_preferred":[
        "Aye"
    ],
    "name:swe_x_preferred":[
        "Aye"
    ],
    "wof:name":"Aye",
    "wof:placetype":"locality"
},
  "geometry": {"coordinates":[9.82638,7.91349],"type":"Point"}
}