{
  "type": "Feature",
  "properties": {
    "gn:admin1_code":"26.0",
    "gn:admin2_code":"7004",
    "gn:asciiname":"Agher",
    "gn:country_code":"NG",
    "gn:dem":174,
    "gn:feature_class":"P",
    "gn:feature_code":"PPL",
    "gn:name":"Agher",
    "gn:population":0,
    "gn:timezone":"Africa/Lagos",
    "iso:country":"NG",
    "name:eus_x_preferred":[
        "Agher"
    ],
    "name:fas_x_preferred":[
        "\u0627\u0642\u0631"
    ],
    "name:gle_x_preferred":[
        "Achair"
    ],
    "name:glv_x_preferred":[
        "Achair"
    ],
    "name:rus_x_preferred":[
        "\u0410\u0445\u0435\u0440"
    ],
    "name:urd_x_preferred":[
        "\u0627\u0642\u0631"
    ],
    "wof:name":"Agher",
    "wof:placetype":"locality"
},
  "geometry": {"coordinates":[9.14335,7.18896],"type":"Point"}
}