{
  "type": "Feature",
  "properties": {
    "gn:admin1_code":"52.0",
    "gn:admin2_code":"6002.0",
    "gn:asciiname":"Ogbotobo",
    "gn:country_code":"NG",
    "gn:dem":0,
    "gn:feature_class":"P",
    "gn:feature_code":"PPL",
    "gn:name":"Ogbotobo",
    "gn:population":0,
    "gn:timezone":"Africa/Lagos",
    "iso:country":"NG",
    "name:eng_x_preferred":[
        "Ogbotobo"
    ],
    "wof:name":"Ogbotobo",
    "wof:placetype":"locality"
},
  "geometry": {"coordinates":[5.45069,5.10897],"type":"Point"}
}