{
  "type": "Feature",
  "properties": {
    "gn:admin1_code":"43.0",
    "gn:asciiname":"Bamekin",
    "gn:country_code":"NG",
    "gn:dem":172,
    "gn:feature_class":"P",
    "gn:feature_code":"PPL",
    "gn:name":"Bamekin",
    "gn:population":0,
    "gn:timezone":"Africa/Lagos",
    "iso:country":"NG",
    "name:eng_x_preferred":[
        "Bamekin"
    ],
    "wof:name":"Bamekin",
    "wof:placetype":"locality"
},
  "geometry": {"coordinates":[11.05875,9.32192],"type":"Point"}
}