{
  "type": "Feature",
  "properties": {
    "gn:admin1_code":"48.0",
    "gn:admin2_code":"29018.0",
    "gn:asciiname":"Alasha",
    "gn:country_code":"NG",
    "gn:dem":282,
    "gn:feature_class":"P",
    "gn:feature_code":"PPL",
    "gn:name":"Alasha",
    "gn:population":0,
    "gn:timezone":"Africa/Lagos",
    "iso:country":"NG",
    "wof:name":"Alasha",
    "wof:placetype":"locality"
},
  "geometry": {"coordinates":[5.5191,7.1531],"type":"Point"}
}