{
  "type": "Feature",
  "properties": {
    "gn:admin1_code":"51.0",
    "gn:admin2_code":"618.0",
    "gn:admin3_code":"61803",
    "gn:asciiname":"Dandutchi",
    "gn:country_code":"NG",
    "gn:dem":257,
    "gn:feature_class":"P",
    "gn:feature_code":"PPL",
    "gn:name":"Dandutchi",
    "gn:population":0,
    "gn:timezone":"Africa/Lagos",
    "iso:country":"NG",
    "wof:name":"Dandutchi",
    "wof:placetype":"locality"
},
  "geometry": {"coordinates":[4.72871,12.34781],"type":"Point"}
}