{
  "type": "Feature",
  "properties": {
    "gn:admin1_code":"39.0",
    "gn:admin2_code":"18014.0",
    "gn:admin3_code":"JI2211",
    "gn:asciiname":"Gora",
    "gn:country_code":"NG",
    "gn:dem":368,
    "gn:feature_class":"P",
    "gn:feature_code":"PPL",
    "gn:name":"Gora",
    "gn:population":0,
    "gn:timezone":"Africa/Lagos",
    "iso:country":"NG",
    "wof:name":"Gora",
    "wof:placetype":"locality"
},
  "geometry": {"coordinates":[9.78002,12.1921],"type":"Point"}
}