{
  "type": "Feature",
  "properties": {
    "gn:admin1_code":"24.0",
    "gn:admin2_code":"404.0",
    "gn:admin3_code":"40412",
    "gn:asciiname":"Yan Maulu",
    "gn:country_code":"NG",
    "gn:dem":395,
    "gn:feature_class":"P",
    "gn:feature_code":"PPL",
    "gn:name":"Yan Maulu",
    "gn:population":0,
    "gn:timezone":"Africa/Lagos",
    "iso:country":"NG",
    "name:und_x_variant":[
        "Yan Molo",
        "Yan Maulu"
    ],
    "wof:name":"Yan Maulu",
    "wof:placetype":"locality"
},
  "geometry": {"coordinates":[8.857,12.77271],"type":"Point"}
}