{
  "type": "Feature",
  "properties": {
    "gn:admin1_code":"41.0",
    "gn:admin2_code":"23006.0",
    "gn:asciiname":"Odobu",
    "gn:country_code":"NG",
    "gn:dem":32,
    "gn:feature_class":"P",
    "gn:feature_code":"PPL",
    "gn:name":"Odobu",
    "gn:population":0,
    "gn:timezone":"Africa/Lagos",
    "iso:country":"NG",
    "wof:name":"Odobu",
    "wof:placetype":"locality"
},
  "geometry": {"coordinates":[6.85,6.95],"type":"Point"}
}