{
  "type": "Feature",
  "properties": {
    "gn:admin1_code":"26.0",
    "gn:admin2_code":"7005.0",
    "gn:asciiname":"Agboikyor",
    "gn:country_code":"NG",
    "gn:dem":139,
    "gn:feature_class":"P",
    "gn:feature_code":"PPL",
    "gn:name":"Agboikyor",
    "gn:population":0,
    "gn:timezone":"Africa/Lagos",
    "iso:country":"NG",
    "wof:name":"Agboikyor",
    "wof:placetype":"locality"
},
  "geometry": {"coordinates":[8.73606,7.27101],"type":"Point"}
}