{
  "type": "Feature",
  "properties": {
    "gn:admin1_code":"57.0",
    "gn:admin2_code":"807.0",
    "gn:admin3_code":"80704",
    "gn:asciiname":"Unguwar Sarkin Pawa",
    "gn:country_code":"NG",
    "gn:dem":569,
    "gn:feature_class":"P",
    "gn:feature_code":"PPL",
    "gn:name":"Unguwar Sarkin Pawa",
    "gn:population":0,
    "gn:timezone":"Africa/Lagos",
    "iso:country":"NG",
    "name:und_x_variant":[
        "Ungwan Sarkin Pawa",
        "Unguwar Sarkin Pawa"
    ],
    "wof:name":"Unguwar Sarkin Pawa",
    "wof:placetype":"locality"
},
  "geometry": {"coordinates":[6.60904,11.59294],"type":"Point"}
}