{
  "type": "Feature",
  "properties": {
    "gn:admin1_code":"27.0",
    "gn:admin2_code":"106.0",
    "gn:admin3_code":"10604",
    "gn:asciiname":"Bulabam Hamlets",
    "gn:country_code":"NG",
    "gn:dem":490,
    "gn:feature_class":"P",
    "gn:feature_code":"PPL",
    "gn:name":"Bulabam Hamlets",
    "gn:population":0,
    "gn:timezone":"Africa/Lagos",
    "iso:country":"NG",
    "name:und_x_variant":[
        "Bulabum Hamlets",
        "Bulabam Hamlets"
    ],
    "wof:name":"Bulabam Hamlets",
    "wof:placetype":"locality"
},
  "geometry": {"coordinates":[12.91279,10.8407],"type":"Point"}
}