{
  "type": "Feature",
  "properties": {
    "gn:admin1_code":"32.0",
    "gn:admin2_code":"31029.0",
    "gn:asciiname":"Isale Apata",
    "gn:country_code":"NG",
    "gn:dem":305,
    "gn:feature_class":"P",
    "gn:feature_code":"PPL",
    "gn:name":"Isale Apata",
    "gn:population":0,
    "gn:timezone":"Africa/Lagos",
    "iso:country":"NG",
    "wof:name":"Isale Apata",
    "wof:placetype":"locality"
},
  "geometry": {"coordinates":[4.03333,7.85],"type":"Point"}
}