{
  "type": "Feature",
  "properties": {
    "gn:admin1_code":"35.0",
    "gn:admin2_code":"2018.0",
    "gn:asciiname":"Sigire Gudu",
    "gn:country_code":"NG",
    "gn:dem":496,
    "gn:feature_class":"P",
    "gn:feature_code":"PPL",
    "gn:name":"Sigire Gudu",
    "gn:population":0,
    "gn:timezone":"Africa/Lagos",
    "iso:country":"NG",
    "wof:name":"Sigire Gudu",
    "wof:placetype":"locality"
},
  "geometry": {"coordinates":[12.58333,9.95],"type":"Point"}
}