{
  "type": "Feature",
  "properties": {
    "gn:admin1_code":"44.0",
    "gn:admin2_code":"714.0",
    "gn:admin3_code":"71403",
    "gn:asciiname":"Gaka",
    "gn:country_code":"NG",
    "gn:dem":425,
    "gn:feature_class":"P",
    "gn:feature_code":"PPL",
    "gn:name":"Gaka",
    "gn:population":0,
    "gn:timezone":"Africa/Lagos",
    "iso:country":"NG",
    "wof:name":"Gaka",
    "wof:placetype":"locality"
},
  "geometry": {"coordinates":[11.19229,11.74654],"type":"Point"}
}