{
  "type": "Feature",
  "properties": {
    "gn:admin1_code":"27.0",
    "gn:admin2_code":"116.0",
    "gn:admin3_code":"11604",
    "gn:asciiname":"Mulgwe-Mayirima",
    "gn:country_code":"NG",
    "gn:dem":344,
    "gn:feature_class":"P",
    "gn:feature_code":"PPL",
    "gn:name":"Mulgwe-Mayirima",
    "gn:population":0,
    "gn:timezone":"Africa/Lagos",
    "iso:country":"NG",
    "name:und_x_variant":[
        "Mulgwe Mayirima"
    ],
    "wof:name":"Mulgwe-Mayirima",
    "wof:placetype":"locality"
},
  "geometry": {"coordinates":[13.29298,11.45391],"type":"Point"}
}