{
  "type": "Feature",
  "properties": {
    "gn:admin1_code":"56.0",
    "gn:admin2_code":"26010.0",
    "gn:asciiname":"Lezin Lafia",
    "gn:country_code":"NG",
    "gn:dem":527,
    "gn:feature_class":"P",
    "gn:feature_code":"PPL",
    "gn:name":"Lezin Lafia",
    "gn:population":0,
    "gn:timezone":"Africa/Lagos",
    "iso:country":"NG",
    "wof:name":"Lezin Lafia",
    "wof:placetype":"locality"
},
  "geometry": {"coordinates":[8.38333,8.73333],"type":"Point"}
}