{
  "type": "Feature",
  "properties": {
    "gn:admin1_code":"30.0",
    "gn:admin2_code":"24012.0",
    "gn:asciiname":"Aga",
    "gn:country_code":"NG",
    "gn:dem":310,
    "gn:feature_class":"P",
    "gn:feature_code":"PPL",
    "gn:name":"Aga",
    "gn:population":0,
    "gn:timezone":"Africa/Lagos",
    "iso:country":"NG",
    "name:ceb_x_preferred":[
        "Aga"
    ],
    "name:che_x_preferred":[
        "\u0410\u0433\u0430"
    ],
    "name:deu_x_preferred":[
        "Aga"
    ],
    "name:est_x_preferred":[
        "AGA"
    ],
    "name:fin_x_preferred":[
        "Aga"
    ],
    "name:fra_x_preferred":[
        "Aga"
    ],
    "name:hrv_x_preferred":[
        "Aga"
    ],
    "name:hun_x_preferred":[
        "Aga"
    ],
    "name:lav_x_preferred":[
        "Aga"
    ],
    "name:lit_x_preferred":[
        "Aga"
    ],
    "name:nld_x_preferred":[
        "Aga"
    ],
    "name:nno_x_preferred":[
        "Aga"
    ],
    "name:nor_x_preferred":[
        "Aga"
    ],
    "name:pol_x_preferred":[
        "Aga"
    ],
    "name:por_x_preferred":[
        "Aga"
    ],
    "name:ron_x_preferred":[
        "Aga"
    ],
    "name:rus_x_preferred":[
        "\u0410\u0433\u0430"
    ],
    "name:slk_x_preferred":[
        "Aga"
    ],
    "name:slv_x_preferred":[
        "Aga"
    ],
    "name:srp_x_preferred":[
        "AGA"
    ],
    "name:ukr_x_preferred":[
        "\u0410\u0433\u0430"
    ],
    "wof:name":"Aga",
    "wof:placetype":"locality"
},
  "geometry": {"coordinates":[4.48333,8.61667],"type":"Point"}
}