{
  "type": "Feature",
  "properties": {
    "gn:admin1_code":"11.0",
    "gn:admin2_code":"15006.0",
    "gn:asciiname":"Kwaye",
    "gn:country_code":"NG",
    "gn:dem":657,
    "gn:feature_class":"P",
    "gn:feature_code":"PPL",
    "gn:name":"Kwaye",
    "gn:population":0,
    "gn:timezone":"Africa/Lagos",
    "iso:country":"NG",
    "wof:name":"Kwaye",
    "wof:placetype":"locality"
},
  "geometry": {"coordinates":[7.50028,8.84389],"type":"Point"}
}