{
  "type": "Feature",
  "properties": {
    "gn:admin1_code":"57.0",
    "gn:admin2_code":"813.0",
    "gn:admin3_code":"81307",
    "gn:asciiname":"Rucca Na Ali",
    "gn:country_code":"NG",
    "gn:dem":542,
    "gn:feature_class":"P",
    "gn:feature_code":"PPL",
    "gn:name":"Rucca Na Ali",
    "gn:population":0,
    "gn:timezone":"Africa/Lagos",
    "iso:country":"NG",
    "wof:name":"Rucca Na Ali",
    "wof:placetype":"locality"
},
  "geometry": {"coordinates":[6.88612,11.99105],"type":"Point"}
}