{
  "type": "Feature",
  "properties": {
    "gn:admin1_code":"43.0",
    "gn:admin2_code":"35005.0",
    "gn:asciiname":"Garin Mallam Babba",
    "gn:country_code":"NG",
    "gn:dem":143,
    "gn:feature_class":"P",
    "gn:feature_code":"PPL",
    "gn:name":"Garin Mallam Babba",
    "gn:population":0,
    "gn:timezone":"Africa/Lagos",
    "iso:country":"NG",
    "wof:name":"Garin Mallam Babba",
    "wof:placetype":"locality"
},
  "geometry": {"coordinates":[10.60619,8.29294],"type":"Point"}
}