{
  "type": "Feature",
  "properties": {
    "gn:admin1_code":"35.0",
    "gn:asciiname":"Gondobi",
    "gn:country_code":"NG",
    "gn:dem":351,
    "gn:feature_class":"P",
    "gn:feature_code":"PPL",
    "gn:name":"Gondobi",
    "gn:population":0,
    "gn:timezone":"Africa/Lagos",
    "iso:country":"NG",
    "name:eng_x_preferred":[
        "Gondobi"
    ],
    "wof:name":"Gondobi",
    "wof:placetype":"locality"
},
  "geometry": {"coordinates":[11.77196,9.13155],"type":"Point"}
}