{
  "type": "Feature",
  "properties": {
    "gn:admin1_code":"35.0",
    "gn:admin2_code":"2018",
    "gn:asciiname":"Sabongari Madela",
    "gn:country_code":"NG",
    "gn:dem":260,
    "gn:feature_class":"P",
    "gn:feature_code":"PPL",
    "gn:name":"Sabongari Madela",
    "gn:population":0,
    "gn:timezone":"Africa/Lagos",
    "iso:country":"NG",
    "wof:name":"Sabongari Madela",
    "wof:placetype":"locality"
},
  "geometry": {"coordinates":[13.01621,9.60127],"type":"Point"}
}