{
  "type": "Feature",
  "properties": {
    "gn:admin1_code":"31.0",
    "gn:admin2_code":"27016.0",
    "gn:asciiname":"Mogu",
    "gn:country_code":"NG",
    "gn:dem":223,
    "gn:feature_class":"P",
    "gn:feature_code":"PPL",
    "gn:name":"Mogu",
    "gn:population":0,
    "gn:timezone":"Africa/Lagos",
    "iso:country":"NG",
    "name:fra_x_preferred":[
        "Mogu"
    ],
    "name:nld_x_preferred":[
        "Mogu"
    ],
    "wof:name":"Mogu",
    "wof:placetype":"locality"
},
  "geometry": {"coordinates":[4.60417,9.55028],"type":"Point"}
}