{
  "type": "Feature",
  "properties": {
    "gn:admin1_code":"32.0",
    "gn:admin2_code":"31031.0",
    "gn:asciiname":"Ogboro",
    "gn:cc2":"NG",
    "gn:country_code":"NG",
    "gn:dem":391,
    "gn:feature_class":"P",
    "gn:feature_code":"PPL",
    "gn:name":"Ogboro",
    "gn:population":0,
    "gn:timezone":"Africa/Lagos",
    "iso:country":"NG",
    "name:und_x_variant":[
        "Awgbawraw",
        "Ogboro"
    ],
    "wof:name":"Ogboro",
    "wof:placetype":"locality"
},
  "geometry": {"coordinates":[3.61667,8.76667],"type":"Point"}
}