{
  "type": "Feature",
  "properties": {
    "gn:admin1_code":"48.0",
    "gn:admin2_code":"29005.0",
    "gn:asciiname":"Orita",
    "gn:country_code":"NG",
    "gn:dem":336,
    "gn:feature_class":"P",
    "gn:feature_code":"PPL",
    "gn:name":"Orita",
    "gn:population":0,
    "gn:timezone":"Africa/Lagos",
    "iso:country":"NG",
    "wof:name":"Orita",
    "wof:placetype":"locality"
},
  "geometry": {"coordinates":[5.3598,7.2529],"type":"Point"}
}