{
  "type": "Feature",
  "properties": {
    "gn:admin1_code":"41.0",
    "gn:admin2_code":"23006",
    "gn:asciiname":"Unale",
    "gn:country_code":"NG",
    "gn:dem":32,
    "gn:feature_class":"P",
    "gn:feature_code":"PPL",
    "gn:name":"Unale",
    "gn:population":0,
    "gn:timezone":"Africa/Lagos",
    "iso:country":"NG",
    "wof:name":"Unale",
    "wof:placetype":"locality"
},
  "geometry": {"coordinates":[6.74927,6.86629],"type":"Point"}
}