{
  "type": "Feature",
  "properties": {
    "gn:admin1_code":"27.0",
    "gn:admin2_code":"127.0",
    "gn:admin3_code":"12706",
    "gn:asciiname":"Duka",
    "gn:country_code":"NG",
    "gn:dem":197,
    "gn:feature_class":"P",
    "gn:feature_code":"PPL",
    "gn:name":"Duka",
    "gn:population":0,
    "gn:timezone":"Africa/Lagos",
    "iso:country":"NG",
    "name:ces_x_preferred":[
        "Duka"
    ],
    "name:deu_x_preferred":[
        "Duka"
    ],
    "name:epo_x_preferred":[
        "Duka"
    ],
    "name:fas_x_preferred":[
        "\u062f\u0648\u06a9\u0627"
    ],
    "name:fra_x_preferred":[
        "Duka"
    ],
    "name:hun_x_preferred":[
        "Duka"
    ],
    "name:ita_x_preferred":[
        "Duka"
    ],
    "name:kat_x_preferred":[
        "\u10d3\u10e3\u10d9\u10d0"
    ],
    "name:msa_x_preferred":[
        "Duka"
    ],
    "name:nld_x_preferred":[
        "Duka"
    ],
    "name:ron_x_preferred":[
        "Duka"
    ],
    "name:slk_x_preferred":[
        "Duka"
    ],
    "name:slv_x_preferred":[
        "Duka"
    ],
    "name:vie_x_preferred":[
        "Duka"
    ],
    "wof:name":"Duka",
    "wof:placetype":"locality"
},
  "geometry": {"coordinates":[12.05007,10.13702],"type":"Point"}
}