{
  "type": "Feature",
  "properties": {
    "gn:admin1_code":"32.0",
    "gn:admin2_code":"31021.0",
    "gn:asciiname":"Ajeja",
    "gn:country_code":"NG",
    "gn:dem":348,
    "gn:feature_class":"P",
    "gn:feature_code":"PPL",
    "gn:name":"Ajeja",
    "gn:population":0,
    "gn:timezone":"Africa/Lagos",
    "iso:country":"NG",
    "wof:name":"Ajeja",
    "wof:placetype":"locality"
},
  "geometry": {"coordinates":[4.28333,8.11667],"type":"Point"}
}