{
  "type": "Feature",
  "properties": {
    "gn:admin1_code":"22.0",
    "gn:admin2_code":"9015.0",
    "gn:asciiname":"Ekpri Adiabo",
    "gn:country_code":"NG",
    "gn:dem":18,
    "gn:feature_class":"P",
    "gn:feature_code":"PPL",
    "gn:name":"Ekpri Adiabo",
    "gn:population":0,
    "gn:timezone":"Africa/Lagos",
    "iso:country":"NG",
    "wof:name":"Ekpri Adiabo",
    "wof:placetype":"locality"
},
  "geometry": {"coordinates":[8.23845,5.11499],"type":"Point"}
}