{
  "type": "Feature",
  "properties": {
    "gn:admin1_code":"47.0",
    "gn:admin2_code":"14012.0",
    "gn:asciiname":"Ngine",
    "gn:country_code":"NG",
    "gn:dem":158,
    "gn:feature_class":"P",
    "gn:feature_code":"PPL",
    "gn:name":"Ngine",
    "gn:population":0,
    "gn:timezone":"Africa/Lagos",
    "iso:country":"NG",
    "wof:name":"Ngine",
    "wof:placetype":"neighbourhood"
},
  "geometry": {"coordinates":[7.53061,6.36797],"type":"Point"}
}