{
  "type": "Feature",
  "properties": {
    "gn:admin1_code":"24.0",
    "gn:admin2_code":"432.0",
    "gn:admin3_code":"43207",
    "gn:asciiname":"Sarkin Lambu",
    "gn:country_code":"NG",
    "gn:dem":516,
    "gn:feature_class":"P",
    "gn:feature_code":"PPL",
    "gn:name":"Sarkin Lambu",
    "gn:population":0,
    "gn:timezone":"Africa/Lagos",
    "iso:country":"NG",
    "wof:name":"Sarkin Lambu",
    "wof:placetype":"locality"
},
  "geometry": {"coordinates":[7.41313,12.4243],"type":"Point"}
}