{
  "type": "Feature",
  "properties": {
    "gn:admin1_code":"40.0",
    "gn:admin2_code":"514.0",
    "gn:admin3_code":"51402",
    "gn:asciiname":"Tsalibi",
    "gn:country_code":"NG",
    "gn:dem":234,
    "gn:feature_class":"P",
    "gn:feature_code":"PPL",
    "gn:name":"Tsalibi",
    "gn:population":0,
    "gn:timezone":"Africa/Lagos",
    "iso:country":"NG",
    "wof:name":"Tsalibi",
    "wof:placetype":"locality"
},
  "geometry": {"coordinates":[4.31557,12.08986],"type":"Point"}
}