{
  "type": "Feature",
  "properties": {
    "gn:admin1_code":"36.0",
    "gn:admin2_code":"10014.0",
    "gn:asciiname":"Ngegwu",
    "gn:country_code":"NG",
    "gn:dem":56,
    "gn:feature_class":"P",
    "gn:feature_code":"PPL",
    "gn:name":"Ngegwu",
    "gn:population":0,
    "gn:timezone":"Africa/Lagos",
    "iso:country":"NG",
    "name:eng_x_preferred":[
        "Ngegwu"
    ],
    "name:eng_x_variant":[
        "Ngegu"
    ],
    "name:und_x_variant":[
        "Ngegu"
    ],
    "wof:name":"Ngegwu",
    "wof:placetype":"locality"
},
  "geometry": {"coordinates":[6.66521,6.37021],"type":"Point"}
}