{
  "type": "Feature",
  "properties": {
    "gn:admin1_code":"57.0",
    "gn:admin2_code":"810.0",
    "gn:admin3_code":"81004",
    "gn:asciiname":"Matan Kari",
    "gn:country_code":"NG",
    "gn:dem":404,
    "gn:feature_class":"P",
    "gn:feature_code":"PPL",
    "gn:name":"Matan Kari",
    "gn:population":0,
    "gn:timezone":"Africa/Lagos",
    "iso:country":"NG",
    "wof:name":"Matan Kari",
    "wof:placetype":"locality"
},
  "geometry": {"coordinates":[6.04387,11.64011],"type":"Point"}
}