{
  "type": "Feature",
  "properties": {
    "gn:admin1_code":"26.0",
    "gn:admin2_code":"7004",
    "gn:asciiname":"Anyorba",
    "gn:country_code":"NG",
    "gn:dem":140,
    "gn:feature_class":"P",
    "gn:feature_code":"PPL",
    "gn:name":"Anyorba",
    "gn:population":0,
    "gn:timezone":"Africa/Lagos",
    "iso:country":"NG",
    "wof:name":"Anyorba",
    "wof:placetype":"locality"
},
  "geometry": {"coordinates":[9.23636,7.34074],"type":"Point"}
}