{
  "type": "Feature",
  "properties": {
    "gn:admin1_code":"24.0",
    "gn:asciiname":"Gwibi",
    "gn:country_code":"NG",
    "gn:dem":656,
    "gn:feature_class":"P",
    "gn:feature_code":"PPL",
    "gn:name":"Gwibi",
    "gn:population":0,
    "gn:timezone":"Africa/Lagos",
    "iso:country":"NG",
    "wof:name":"Gwibi",
    "wof:placetype":"locality"
},
  "geometry": {"coordinates":[7.78724,11.32734],"type":"Point"}
}