{
  "type": "Feature",
  "properties": {
    "gn:admin1_code":"5.0",
    "gn:admin2_code":"25007.0",
    "gn:asciiname":"Oba-Oyinbo",
    "gn:country_code":"NG",
    "gn:dem":9,
    "gn:feature_class":"P",
    "gn:feature_code":"PPL",
    "gn:name":"Oba-Oyinbo",
    "gn:population":0,
    "gn:timezone":"Africa/Lagos",
    "iso:country":"NG",
    "wof:name":"Oba-Oyinbo",
    "wof:placetype":"locality"
},
  "geometry": {"coordinates":[4.09324,6.50705],"type":"Point"}
}