{
  "type": "Feature",
  "properties": {
    "gn:admin1_code":"23.0",
    "gn:admin2_code":"19020",
    "gn:admin3_code":"KD2007",
    "gn:asciiname":"Kormi",
    "gn:country_code":"NG",
    "gn:dem":506,
    "gn:feature_class":"P",
    "gn:feature_code":"PPL",
    "gn:name":"Kormi",
    "gn:population":0,
    "gn:timezone":"Africa/Lagos",
    "iso:country":"NG",
    "wof:name":"Kormi",
    "wof:placetype":"locality"
},
  "geometry": {"coordinates":[8.49745,9.28093],"type":"Point"}
}