{
  "type": "Feature",
  "properties": {
    "gn:admin1_code":"36.0",
    "gn:admin2_code":"10014.0",
    "gn:asciiname":"Ugumoeke",
    "gn:country_code":"NG",
    "gn:dem":74,
    "gn:feature_class":"P",
    "gn:feature_code":"PPL",
    "gn:name":"Ugumoeke",
    "gn:population":0,
    "gn:timezone":"Africa/Lagos",
    "iso:country":"NG",
    "name:eng_x_preferred":[
        "Ugumoeke"
    ],
    "wof:name":"Ugumoeke",
    "wof:placetype":"locality"
},
  "geometry": {"coordinates":[6.63166,6.40282],"type":"Point"}
}