{
  "type": "Feature",
  "properties": {
    "gn:admin1_code":"43.0",
    "gn:admin2_code":"35003.0",
    "gn:asciiname":"Mai Dakin Sama",
    "gn:country_code":"NG",
    "gn:dem":120,
    "gn:feature_class":"P",
    "gn:feature_code":"PPL",
    "gn:name":"Mai Dakin Sama",
    "gn:population":0,
    "gn:timezone":"Africa/Lagos",
    "iso:country":"NG",
    "name:und_x_variant":[
        "Mai Darkin Sama"
    ],
    "wof:name":"Mai Dakin Sama",
    "wof:placetype":"locality"
},
  "geometry": {"coordinates":[10.03409,7.78705],"type":"Point"}
}