{
  "type": "Feature",
  "properties": {
    "gn:admin1_code":"26.0",
    "gn:admin2_code":"7004",
    "gn:asciiname":"See",
    "gn:country_code":"NG",
    "gn:dem":100,
    "gn:feature_class":"P",
    "gn:feature_code":"PPL",
    "gn:name":"See",
    "gn:population":0,
    "gn:timezone":"Africa/Lagos",
    "iso:country":"NG",
    "name:ceb_x_preferred":[
        "See"
    ],
    "name:deu_x_preferred":[
        "See"
    ],
    "name:fra_x_preferred":[
        "See"
    ],
    "name:nds_x_preferred":[
        "See"
    ],
    "name:nld_x_preferred":[
        "See"
    ],
    "name:pol_x_preferred":[
        "See"
    ],
    "name:por_x_preferred":[
        "See"
    ],
    "name:swe_x_preferred":[
        "See"
    ],
    "wof:name":"See",
    "wof:placetype":"locality"
},
  "geometry": {"coordinates":[9.11251,7.56093],"type":"Point"}
}