{
  "type": "Feature",
  "properties": {
    "gn:admin1_code":"31.0",
    "gn:admin2_code":"27015.0",
    "gn:asciiname":"Kwanje",
    "gn:country_code":"NG",
    "gn:dem":386,
    "gn:feature_class":"P",
    "gn:feature_code":"PPL",
    "gn:name":"Kwanje",
    "gn:population":0,
    "gn:timezone":"Africa/Lagos",
    "iso:country":"NG",
    "wof:name":"Kwanje",
    "wof:placetype":"locality"
},
  "geometry": {"coordinates":[6.11758,10.68293],"type":"Point"}
}