{
  "type": "Feature",
  "properties": {
    "gn:admin1_code":"31.0",
    "gn:admin2_code":"27009",
    "gn:asciiname":"Piakuchi",
    "gn:country_code":"NG",
    "gn:dem":413,
    "gn:feature_class":"P",
    "gn:feature_code":"PPL",
    "gn:name":"Piakuchi",
    "gn:population":0,
    "gn:timezone":"Africa/Lagos",
    "iso:country":"NG",
    "wof:name":"Piakuchi",
    "wof:placetype":"locality"
},
  "geometry": {"coordinates":[7.11675,9.2751],"type":"Point"}
}