{
  "type": "Feature",
  "properties": {
    "gn:admin1_code":"43.0",
    "gn:admin2_code":"35015.0",
    "gn:asciiname":"Gang Sati",
    "gn:country_code":"NG",
    "gn:dem":1391,
    "gn:feature_class":"P",
    "gn:feature_code":"PPL",
    "gn:name":"Gang Sati",
    "gn:population":0,
    "gn:timezone":"Africa/Lagos",
    "iso:country":"NG",
    "wof:name":"Gang Sati",
    "wof:placetype":"locality"
},
  "geometry": {"coordinates":[11.74841,8.6321],"type":"Point"}
}