{
  "type": "Feature",
  "properties": {
    "gn:admin1_code":"46.0",
    "gn:admin2_code":"5012.0",
    "gn:admin3_code":"BA1205",
    "gn:asciiname":"Jugga",
    "gn:country_code":"NG",
    "gn:dem":394,
    "gn:feature_class":"P",
    "gn:feature_code":"PPL",
    "gn:name":"Jugga",
    "gn:population":0,
    "gn:timezone":"Africa/Lagos",
    "iso:country":"NG",
    "wof:name":"Jugga",
    "wof:placetype":"locality"
},
  "geometry": {"coordinates":[10.3805,11.7253],"type":"Point"}
}