{
  "type": "Feature",
  "properties": {
    "gn:admin1_code":"52.0",
    "gn:admin2_code":"6007.0",
    "gn:asciiname":"Obeleli",
    "gn:country_code":"NG",
    "gn:dem":6,
    "gn:feature_class":"P",
    "gn:feature_code":"PPL",
    "gn:name":"Obeleli",
    "gn:population":0,
    "gn:timezone":"Africa/Lagos",
    "iso:country":"NG",
    "wof:name":"Obeleli",
    "wof:placetype":"locality"
},
  "geometry": {"coordinates":[6.2115,4.82845],"type":"Point"}
}