{
  "type": "Feature",
  "properties": {
    "gn:admin1_code":"24.0",
    "gn:admin2_code":"404.0",
    "gn:admin3_code":"40405",
    "gn:asciiname":"Ungua Maza",
    "gn:country_code":"NG",
    "gn:dem":392,
    "gn:feature_class":"P",
    "gn:feature_code":"PPL",
    "gn:name":"Ungua Maza",
    "gn:population":0,
    "gn:timezone":"Africa/Lagos",
    "iso:country":"NG",
    "name:und_x_variant":[
        "Gladimawa",
        "Ungua Maza"
    ],
    "wof:name":"Ungua Maza",
    "wof:placetype":"locality"
},
  "geometry": {"coordinates":[8.85665,12.80624],"type":"Point"}
}