{
  "type": "Feature",
  "properties": {
    "gn:admin1_code":"27.0",
    "gn:admin2_code":"102.0",
    "gn:admin3_code":"10202",
    "gn:asciiname":"Kwang",
    "gn:country_code":"NG",
    "gn:dem":419,
    "gn:feature_class":"P",
    "gn:feature_code":"PPL",
    "gn:name":"Kwang",
    "gn:population":0,
    "gn:timezone":"Africa/Lagos",
    "iso:country":"NG",
    "name:und_x_variant":[
        "Kona",
        "Kong",
        "Kwang"
    ],
    "wof:name":"Kwang",
    "wof:placetype":"locality"
},
  "geometry": {"coordinates":[13.22478,10.84372],"type":"Point"}
}