{
  "type": "Feature",
  "properties": {
    "gn:admin1_code":"5.0",
    "gn:admin2_code":"25009.0",
    "gn:asciiname":"Efiran",
    "gn:country_code":"NG",
    "gn:dem":7,
    "gn:feature_class":"P",
    "gn:feature_code":"PPL",
    "gn:name":"Efiran",
    "gn:population":0,
    "gn:timezone":"Africa/Lagos",
    "iso:country":"NG",
    "wof:name":"Efiran",
    "wof:placetype":"neighbourhood"
},
  "geometry": {"coordinates":[3.80719,6.48216],"type":"Point"}
}