{
  "type": "Feature",
  "properties": {
    "gn:admin1_code":"37.0",
    "gn:admin2_code":"12009",
    "gn:asciiname":"Ayegbe",
    "gn:country_code":"NG",
    "gn:dem":83,
    "gn:feature_class":"P",
    "gn:feature_code":"PPL",
    "gn:name":"Ayegbe",
    "gn:population":0,
    "gn:timezone":"Africa/Lagos",
    "iso:country":"NG",
    "wof:name":"Ayegbe",
    "wof:placetype":"locality"
},
  "geometry": {"coordinates":[6.36068,6.91131],"type":"Point"}
}