{
  "type": "Feature",
  "properties": {
    "gn:admin1_code":"35.0",
    "gn:asciiname":"Oula",
    "gn:country_code":"NG",
    "gn:dem":983,
    "gn:feature_class":"P",
    "gn:feature_code":"PPL",
    "gn:name":"Oula",
    "gn:population":0,
    "gn:timezone":"Africa/Lagos",
    "iso:country":"NG",
    "wof:name":"Oula",
    "wof:placetype":"locality"
},
  "geometry": {"coordinates":[13.55871,10.61217],"type":"Point"}
}