{
  "type": "Feature",
  "properties": {
    "gn:admin1_code":"51.0",
    "gn:admin2_code":"606.0",
    "gn:admin3_code":"60604",
    "gn:asciiname":"Kulhi Kondo",
    "gn:country_code":"NG",
    "gn:dem":252,
    "gn:feature_class":"P",
    "gn:feature_code":"PPL",
    "gn:name":"Kulhi Kondo",
    "gn:population":0,
    "gn:timezone":"Africa/Lagos",
    "iso:country":"NG",
    "wof:name":"Kulhi Kondo",
    "wof:placetype":"locality"
},
  "geometry": {"coordinates":[4.38706,13.24186],"type":"Point"}
}