{
  "type": "Feature",
  "properties": {
    "gn:admin1_code":"43.0",
    "gn:admin2_code":"35015",
    "gn:asciiname":"Gbatu",
    "gn:country_code":"NG",
    "gn:dem":272,
    "gn:feature_class":"P",
    "gn:feature_code":"PPL",
    "gn:name":"Gbatu",
    "gn:population":0,
    "gn:timezone":"Africa/Lagos",
    "iso:country":"NG",
    "wof:name":"Gbatu",
    "wof:placetype":"locality"
},
  "geometry": {"coordinates":[11.47521,8.844],"type":"Point"}
}