{
  "type": "Feature",
  "properties": {
    "gn:admin1_code":"35.0",
    "gn:admin2_code":"2012.0",
    "gn:asciiname":"Kubbi",
    "gn:country_code":"NG",
    "gn:dem":549,
    "gn:feature_class":"P",
    "gn:feature_code":"PPL",
    "gn:name":"Kubbi",
    "gn:population":0,
    "gn:timezone":"Africa/Lagos",
    "iso:country":"NG",
    "wof:name":"Kubbi",
    "wof:placetype":"locality"
},
  "geometry": {"coordinates":[11.84931,8.62365],"type":"Point"}
}