{
  "type": "Feature",
  "properties": {
    "gn:admin1_code":"46.0",
    "gn:admin2_code":"5017.0",
    "gn:admin3_code":"BA1709",
    "gn:asciiname":"Kusinawa",
    "gn:country_code":"NG",
    "gn:dem":671,
    "gn:feature_class":"P",
    "gn:feature_code":"PPL",
    "gn:name":"Kusinawa",
    "gn:population":0,
    "gn:timezone":"Africa/Lagos",
    "iso:country":"NG",
    "wof:name":"Kusinawa",
    "wof:placetype":"locality"
},
  "geometry": {"coordinates":[9.59971,10.20981],"type":"Point"}
}