{
  "type": "Feature",
  "properties": {
    "gn:admin1_code":"23.0",
    "gn:admin2_code":"19017.0",
    "gn:admin3_code":"KD1707",
    "gn:asciiname":"Tudun Fulani",
    "gn:country_code":"NG",
    "gn:dem":818,
    "gn:feature_class":"P",
    "gn:feature_code":"PPL",
    "gn:name":"Tudun Fulani",
    "gn:population":0,
    "gn:timezone":"Africa/Lagos",
    "iso:country":"NG",
    "wof:name":"Tudun Fulani",
    "wof:placetype":"locality"
},
  "geometry": {"coordinates":[8.70422,10.36385],"type":"Point"}
}