{
  "type": "Feature",
  "properties": {
    "gn:admin1_code":"41.0",
    "gn:admin2_code":"23010.0",
    "gn:asciiname":"Kakun",
    "gn:country_code":"NG",
    "gn:dem":453,
    "gn:feature_class":"P",
    "gn:feature_code":"PPL",
    "gn:name":"Kakun",
    "gn:population":0,
    "gn:timezone":"Africa/Lagos",
    "iso:country":"NG",
    "wof:name":"Kakun",
    "wof:placetype":"locality"
},
  "geometry": {"coordinates":[6.125,7.7419],"type":"Point"}
}