{
  "type": "Feature",
  "properties": {
    "gn:admin1_code":"11.0",
    "gn:admin2_code":"15006.0",
    "gn:asciiname":"Karsana",
    "gn:country_code":"NG",
    "gn:dem":429,
    "gn:feature_class":"P",
    "gn:feature_code":"PPL",
    "gn:name":"Karsana",
    "gn:population":0,
    "gn:timezone":"Africa/Lagos",
    "iso:country":"NG",
    "wof:name":"Karsana",
    "wof:placetype":"neighbourhood"
},
  "geometry": {"coordinates":[7.33696,9.12483],"type":"Point"}
}