{
  "type": "Feature",
  "properties": {
    "gn:admin1_code":"24.0",
    "gn:admin2_code":"434.0",
    "gn:admin3_code":"43405",
    "gn:asciiname":"Bidawa",
    "gn:country_code":"NG",
    "gn:dem":445,
    "gn:feature_class":"P",
    "gn:feature_code":"PPL",
    "gn:name":"Bidawa",
    "gn:population":0,
    "gn:timezone":"Africa/Lagos",
    "iso:country":"NG",
    "wof:name":"Bidawa",
    "wof:placetype":"locality"
},
  "geometry": {"coordinates":[8.58349,12.89089],"type":"Point"}
}