{
  "type": "Feature",
  "properties": {
    "gn:admin1_code":"24.0",
    "gn:admin2_code":"434.0",
    "gn:admin3_code":"43403",
    "gn:asciiname":"Gwamba",
    "gn:country_code":"NG",
    "gn:dem":429,
    "gn:feature_class":"P",
    "gn:feature_code":"PPL",
    "gn:name":"Gwamba",
    "gn:population":0,
    "gn:timezone":"Africa/Lagos",
    "iso:country":"NG",
    "name:und_x_variant":[
        "Gomba",
        "Gwamba"
    ],
    "wof:name":"Gwamba",
    "wof:placetype":"locality"
},
  "geometry": {"coordinates":[8.63142,12.91224],"type":"Point"}
}