{
  "type": "Feature",
  "properties": {
    "gn:admin1_code":"28.0",
    "gn:admin2_code":"17004.0",
    "gn:asciiname":"Eziudo",
    "gn:country_code":"NG",
    "gn:dem":117,
    "gn:feature_class":"P",
    "gn:feature_code":"PPL",
    "gn:name":"Eziudo",
    "gn:population":0,
    "gn:timezone":"Africa/Lagos",
    "iso:country":"NG",
    "wof:name":"Eziudo",
    "wof:placetype":"locality"
},
  "geometry": {"coordinates":[7.35,5.48333],"type":"Point"}
}