{
  "type": "Feature",
  "properties": {
    "gn:admin1_code":"36.0",
    "gn:admin2_code":"10004.0",
    "gn:asciiname":"Nikoragba",
    "gn:cc2":"NG",
    "gn:country_code":"NG",
    "gn:dem":13,
    "gn:feature_class":"P",
    "gn:feature_code":"PPL",
    "gn:name":"Nikoragba",
    "gn:population":0,
    "gn:timezone":"Africa/Lagos",
    "iso:country":"NG",
    "name:und_x_variant":[
        "Nikorogha",
        "Nikoragba"
    ],
    "wof:name":"Nikoragba",
    "wof:placetype":"locality"
},
  "geometry": {"coordinates":[5.76667,5.18333],"type":"Point"}
}