{
  "type": "Feature",
  "properties": {
    "gn:admin1_code":"26.0",
    "gn:admin2_code":"7013.0",
    "gn:asciiname":"Kponch Amu",
    "gn:country_code":"NG",
    "gn:dem":119,
    "gn:feature_class":"P",
    "gn:feature_code":"PPL",
    "gn:name":"Kponch Amu",
    "gn:population":0,
    "gn:timezone":"Africa/Lagos",
    "iso:country":"NG",
    "wof:name":"Kponch Amu",
    "wof:placetype":"locality"
},
  "geometry": {"coordinates":[8.64586,7.68314],"type":"Point"}
}