{
  "type": "Feature",
  "properties": {
    "gn:admin1_code":"35.0",
    "gn:asciiname":"Gimpawo",
    "gn:country_code":"NG",
    "gn:dem":228,
    "gn:feature_class":"P",
    "gn:feature_code":"PPL",
    "gn:name":"Gimpawo",
    "gn:population":0,
    "gn:timezone":"Africa/Lagos",
    "iso:country":"NG",
    "name:eng_x_preferred":[
        "Gimpawo"
    ],
    "wof:name":"Gimpawo",
    "wof:placetype":"locality"
},
  "geometry": {"coordinates":[12.4967,9.33552],"type":"Point"}
}