{
  "type": "Feature",
  "properties": {
    "gn:admin1_code":"51.0",
    "gn:admin2_code":"611.0",
    "gn:admin3_code":"61105",
    "gn:asciiname":"Karande",
    "gn:country_code":"NG",
    "gn:dem":262,
    "gn:feature_class":"P",
    "gn:feature_code":"PPL",
    "gn:name":"Karande",
    "gn:population":0,
    "gn:timezone":"Africa/Lagos",
    "iso:country":"NG",
    "wof:name":"Karande",
    "wof:placetype":"locality"
},
  "geometry": {"coordinates":[5.30656,13.17749],"type":"Point"}
}