{
  "type": "Feature",
  "properties": {
    "gn:admin1_code":"22.0",
    "gn:admin2_code":"9006.0",
    "gn:asciiname":"Amaruran",
    "gn:country_code":"NG",
    "gn:dem":17,
    "gn:feature_class":"P",
    "gn:feature_code":"PPL",
    "gn:name":"Amaruran",
    "gn:population":0,
    "gn:timezone":"Africa/Lagos",
    "iso:country":"NG",
    "wof:name":"Amaruran",
    "wof:placetype":"locality"
},
  "geometry": {"coordinates":[8.0975,5.3698],"type":"Point"}
}