{
  "type": "Feature",
  "properties": {
    "gn:admin1_code":"27.0",
    "gn:admin2_code":"106.0",
    "gn:admin3_code":"10607",
    "gn:asciiname":"Ngadarma Bulayahi",
    "gn:country_code":"NG",
    "gn:dem":464,
    "gn:feature_class":"P",
    "gn:feature_code":"PPL",
    "gn:name":"Ngadarma Bulayahi",
    "gn:population":0,
    "gn:timezone":"Africa/Lagos",
    "iso:country":"NG",
    "wof:name":"Ngadarma Bulayahi",
    "wof:placetype":"locality"
},
  "geometry": {"coordinates":[12.87173,10.71278],"type":"Point"}
}