{
  "type": "Feature",
  "properties": {
    "gn:admin1_code":"43.0",
    "gn:admin2_code":"35005",
    "gn:asciiname":"Garin Madaki",
    "gn:country_code":"NG",
    "gn:dem":164,
    "gn:feature_class":"P",
    "gn:feature_code":"PPL",
    "gn:name":"Garin Madaki",
    "gn:population":0,
    "gn:timezone":"Africa/Lagos",
    "iso:country":"NG",
    "wof:name":"Garin Madaki",
    "wof:placetype":"locality"
},
  "geometry": {"coordinates":[10.74504,8.61188],"type":"Point"}
}