{
  "type": "Feature",
  "properties": {
    "gn:admin1_code":"40.0",
    "gn:admin2_code":"502.0",
    "gn:admin3_code":"50209",
    "gn:asciiname":"Kuham Gaika",
    "gn:country_code":"NG",
    "gn:dem":253,
    "gn:feature_class":"P",
    "gn:feature_code":"PPL",
    "gn:name":"Kuham Gaika",
    "gn:population":0,
    "gn:timezone":"Africa/Lagos",
    "iso:country":"NG",
    "wof:name":"Kuham Gaika",
    "wof:placetype":"locality"
},
  "geometry": {"coordinates":[4.12854,12.9476],"type":"Point"}
}