{
  "type": "Feature",
  "properties": {
    "gn:admin1_code":"26.0",
    "gn:admin2_code":"7021",
    "gn:asciiname":"Ikpeabee",
    "gn:country_code":"NG",
    "gn:dem":204,
    "gn:feature_class":"P",
    "gn:feature_code":"PPL",
    "gn:name":"Ikpeabee",
    "gn:population":0,
    "gn:timezone":"Africa/Lagos",
    "iso:country":"NG",
    "wof:name":"Ikpeabee",
    "wof:placetype":"locality"
},
  "geometry": {"coordinates":[9.77383,7.61559],"type":"Point"}
}