{
  "type": "Feature",
  "properties": {
    "gn:admin1_code":"37.0",
    "gn:admin2_code":"12001.0",
    "gn:asciiname":"Ojirami",
    "gn:country_code":"NG",
    "gn:dem":305,
    "gn:feature_class":"P",
    "gn:feature_code":"PPL",
    "gn:name":"Ojirami",
    "gn:population":0,
    "gn:timezone":"Africa/Lagos",
    "iso:country":"NG",
    "wof:name":"Ojirami",
    "wof:placetype":"locality"
},
  "geometry": {"coordinates":[6.1801,7.3124],"type":"Point"}
}