{
  "type": "Feature",
  "properties": {
    "gn:admin1_code":"44.0",
    "gn:admin2_code":"704.0",
    "gn:admin3_code":"70403",
    "gn:asciiname":"Shembire",
    "gn:country_code":"NG",
    "gn:dem":459,
    "gn:feature_class":"P",
    "gn:feature_code":"PPL",
    "gn:name":"Shembire",
    "gn:population":0,
    "gn:timezone":"Africa/Lagos",
    "iso:country":"NG",
    "wof:name":"Shembire",
    "wof:placetype":"locality"
},
  "geometry": {"coordinates":[11.26425,11.40082],"type":"Point"}
}