{
  "type": "Feature",
  "properties": {
    "gn:admin1_code":"43.0",
    "gn:asciiname":"Akwana",
    "gn:country_code":"NG",
    "gn:dem":112,
    "gn:feature_class":"P",
    "gn:feature_code":"PPL",
    "gn:name":"Akwana",
    "gn:population":0,
    "gn:timezone":"Africa/Lagos",
    "iso:country":"NG",
    "wof:name":"Akwana",
    "wof:placetype":"locality"
},
  "geometry": {"coordinates":[9.16898,7.78597],"type":"Point"}
}