{
  "type": "Feature",
  "properties": {
    "gn:admin1_code":"27.0",
    "gn:admin2_code":"114.0",
    "gn:admin3_code":"11402",
    "gn:asciiname":"Borozo",
    "gn:country_code":"NG",
    "gn:dem":357,
    "gn:feature_class":"P",
    "gn:feature_code":"PPL",
    "gn:name":"Borozo",
    "gn:population":0,
    "gn:timezone":"Africa/Lagos",
    "iso:country":"NG",
    "name:und_x_variant":[
        "Bargozo",
        "Borozo"
    ],
    "wof:name":"Borozo",
    "wof:placetype":"locality"
},
  "geometry": {"coordinates":[12.6009,11.66242],"type":"Point"}
}