{
  "type": "Feature",
  "properties": {
    "gn:admin1_code":"42.0",
    "gn:admin2_code":"30023.0",
    "gn:asciiname":"Papa",
    "gn:country_code":"NG",
    "gn:dem":357,
    "gn:feature_class":"P",
    "gn:feature_code":"PPL",
    "gn:name":"Papa",
    "gn:population":0,
    "gn:timezone":"Africa/Lagos",
    "iso:country":"NG",
    "name:bos_x_preferred":[
        "Papa"
    ],
    "name:cat_x_preferred":[
        "Papa"
    ],
    "name:ceb_x_preferred":[
        "Papa"
    ],
    "name:dan_x_preferred":[
        "Papa"
    ],
    "name:deu_x_preferred":[
        "Papa"
    ],
    "name:est_x_preferred":[
        "Papa"
    ],
    "name:fra_x_preferred":[
        "Papa"
    ],
    "name:heb_x_preferred":[
        "\u05e4\u05e4\u05d0"
    ],
    "name:ita_x_preferred":[
        "Papa"
    ],
    "name:lat_x_preferred":[
        "Papa"
    ],
    "name:nor_x_preferred":[
        "Papa"
    ],
    "name:por_x_preferred":[
        "Papa"
    ],
    "name:rus_x_preferred":[
        "\u041f\u0430\u043f\u0430"
    ],
    "name:slk_x_preferred":[
        "Papa"
    ],
    "name:spa_x_preferred":[
        "Papa"
    ],
    "name:srp_x_preferred":[
        "\u041f\u0430\u043f\u0430"
    ],
    "name:swe_x_preferred":[
        "Papa"
    ],
    "name:tgl_x_preferred":[
        "Papa"
    ],
    "name:tur_x_preferred":[
        "Papa"
    ],
    "name:ukr_x_preferred":[
        "\u041f\u0430\u043f\u0430"
    ],
    "name:war_x_preferred":[
        "Papa"
    ],
    "wof:name":"Papa",
    "wof:placetype":"locality"
},
  "geometry": {"coordinates":[4.08333,7.75],"type":"Point"}
}