{
  "type": "Feature",
  "properties": {
    "gn:admin1_code":"42.0",
    "gn:admin2_code":"30023.0",
    "gn:asciiname":"Papa",
    "gn:country_code":"NG",
    "gn:dem":357,
    "gn:feature_class":"P",
    "gn:feature_code":"PPL",
    "gn:name":"Papa",
    "gn:population":0,
    "gn:timezone":"Africa/Lagos",
    "iso:country":"NG",
    "wof:name":"Papa",
    "wof:placetype":"locality"
},
  "geometry": {"coordinates":[4.08333,7.75],"type":"Point"}
}