{
  "type": "Feature",
  "properties": {
    "gn:admin1_code":"31.0",
    "gn:admin2_code":"27004.0",
    "gn:asciiname":"New Dugga",
    "gn:cc2":"NG",
    "gn:country_code":"NG",
    "gn:dem":160,
    "gn:feature_class":"P",
    "gn:feature_code":"PPL",
    "gn:name":"New Dugga",
    "gn:population":0,
    "gn:timezone":"Africa/Lagos",
    "iso:country":"NG",
    "name:und_x_variant":[
        "Dugga",
        "Old Dugga",
        "New Dugga"
    ],
    "wof:name":"New Dugga",
    "wof:placetype":"locality"
},
  "geometry": {"coordinates":[4.45,10.46667],"type":"Point"}
}