{
  "type": "Feature",
  "properties": {
    "gn:admin1_code":"57.0",
    "gn:admin2_code":"807.0",
    "gn:admin3_code":"80707",
    "gn:asciiname":"Guidan Mai-Jatau",
    "gn:country_code":"NG",
    "gn:dem":472,
    "gn:feature_class":"P",
    "gn:feature_code":"PPL",
    "gn:name":"Guidan Mai-Jatau",
    "gn:population":0,
    "gn:timezone":"Africa/Lagos",
    "iso:country":"NG",
    "name:und_x_variant":[
        "Gidan Mai Jatau",
        "Guidan Mai-Jatau"
    ],
    "wof:name":"Guidan Mai-Jatau",
    "wof:placetype":"locality"
},
  "geometry": {"coordinates":[6.96475,12.16656],"type":"Point"}
}