{
  "type": "Feature",
  "properties": {
    "gn:admin1_code":"23.0",
    "gn:admin2_code":"19019.0",
    "gn:admin3_code":"KD1911",
    "gn:asciiname":"Ungwan Mijin Goggo",
    "gn:country_code":"NG",
    "gn:dem":631,
    "gn:feature_class":"P",
    "gn:feature_code":"PPL",
    "gn:name":"Ungwan Mijin Goggo",
    "gn:population":0,
    "gn:timezone":"Africa/Lagos",
    "iso:country":"NG",
    "wof:name":"Ungwan Mijin Goggo",
    "wof:placetype":"locality"
},
  "geometry": {"coordinates":[7.75005,11.15454],"type":"Point"}
}