{
  "type": "Feature",
  "properties": {
    "gn:admin1_code":"53.0",
    "gn:admin2_code":"11002.0",
    "gn:asciiname":"Ndibe Beach",
    "gn:country_code":"NG",
    "gn:dem":21,
    "gn:feature_class":"P",
    "gn:feature_code":"PPL",
    "gn:name":"Ndibe Beach",
    "gn:population":0,
    "gn:timezone":"Africa/Lagos",
    "iso:country":"NG",
    "wof:name":"Ndibe Beach",
    "wof:placetype":"locality"
},
  "geometry": {"coordinates":[7.94748,5.84292],"type":"Point"}
}