{
  "type": "Feature",
  "properties": {
    "gn:admin1_code":"44.0",
    "gn:admin2_code":"711.0",
    "gn:admin3_code":"71103",
    "gn:asciiname":"Kirgamu",
    "gn:country_code":"NG",
    "gn:dem":357,
    "gn:feature_class":"P",
    "gn:feature_code":"PPL",
    "gn:name":"Kirgamu",
    "gn:population":0,
    "gn:timezone":"Africa/Lagos",
    "iso:country":"NG",
    "wof:name":"Kirgamu",
    "wof:placetype":"locality"
},
  "geometry": {"coordinates":[9.88197,12.8541],"type":"Point"}
}