{
  "type": "Feature",
  "properties": {
    "gn:admin1_code":"39.0",
    "gn:admin2_code":"18022.0",
    "gn:admin3_code":"JI0308",
    "gn:asciiname":"Gunguama",
    "gn:country_code":"NG",
    "gn:dem":441,
    "gn:feature_class":"P",
    "gn:feature_code":"PPL",
    "gn:name":"Gunguama",
    "gn:population":0,
    "gn:timezone":"Africa/Lagos",
    "iso:country":"NG",
    "wof:name":"Gunguama",
    "wof:placetype":"locality"
},
  "geometry": {"coordinates":[9.5353,11.34473],"type":"Point"}
}