{
  "type": "Feature",
  "properties": {
    "gn:admin1_code":"47.0",
    "gn:admin2_code":"14006.0",
    "gn:asciiname":"Umudim",
    "gn:country_code":"NG",
    "gn:dem":48,
    "gn:feature_class":"P",
    "gn:feature_code":"PPL",
    "gn:name":"Umudim",
    "gn:population":0,
    "gn:timezone":"Africa/Lagos",
    "iso:country":"NG",
    "wof:name":"Umudim",
    "wof:placetype":"locality"
},
  "geometry": {"coordinates":[7.17099,6.38689],"type":"Point"}
}