{
  "type": "Feature",
  "properties": {
    "gn:admin1_code":"26.0",
    "gn:admin2_code":"7007",
    "gn:asciiname":"Chive",
    "gn:country_code":"NG",
    "gn:dem":104,
    "gn:feature_class":"P",
    "gn:feature_code":"PPL",
    "gn:name":"Chive",
    "gn:population":0,
    "gn:timezone":"Africa/Lagos",
    "iso:country":"NG",
    "wof:name":"Chive",
    "wof:placetype":"locality"
},
  "geometry": {"coordinates":[8.28707,7.2744],"type":"Point"}
}