{
  "type": "Feature",
  "properties": {
    "gn:admin1_code":"48.0",
    "gn:admin2_code":"29005.0",
    "gn:asciiname":"Saribi",
    "gn:country_code":"NG",
    "gn:dem":333,
    "gn:feature_class":"P",
    "gn:feature_code":"PPL",
    "gn:name":"Saribi",
    "gn:population":0,
    "gn:timezone":"Africa/Lagos",
    "iso:country":"NG",
    "wof:name":"Saribi",
    "wof:placetype":"locality"
},
  "geometry": {"coordinates":[5.305,7.2537],"type":"Point"}
}