{
  "type": "Feature",
  "properties": {
    "gn:admin1_code":"49.0",
    "gn:admin2_code":"32003.0",
    "gn:asciiname":"Passa Kai",
    "gn:country_code":"NG",
    "gn:dem":1277,
    "gn:feature_class":"P",
    "gn:feature_code":"PPL",
    "gn:name":"Passa Kai",
    "gn:population":0,
    "gn:timezone":"Africa/Lagos",
    "iso:country":"NG",
    "wof:name":"Passa Kai",
    "wof:placetype":"locality"
},
  "geometry": {"coordinates":[8.81422,9.1472],"type":"Point"}
}