{
  "type": "Feature",
  "properties": {
    "gn:admin1_code":"25.0",
    "gn:admin2_code":"4012.0",
    "gn:asciiname":"Ayinneji",
    "gn:country_code":"NG",
    "gn:dem":69,
    "gn:feature_class":"P",
    "gn:feature_code":"PPL",
    "gn:name":"Ayinneji",
    "gn:population":0,
    "gn:timezone":"Africa/Lagos",
    "iso:country":"NG",
    "wof:name":"Ayinneji",
    "wof:placetype":"locality"
},
  "geometry": {"coordinates":[6.86451,5.77934],"type":"Point"}
}