{
  "type": "Feature",
  "properties": {
    "gn:admin1_code":"16.0",
    "gn:admin2_code":"28009.0",
    "gn:asciiname":"Ajede Balogun",
    "gn:country_code":"NG",
    "gn:dem":129,
    "gn:feature_class":"P",
    "gn:feature_code":"PPL",
    "gn:name":"Ajede Balogun",
    "gn:population":0,
    "gn:timezone":"Africa/Lagos",
    "iso:country":"NG",
    "wof:name":"Ajede Balogun",
    "wof:placetype":"locality"
},
  "geometry": {"coordinates":[4.06667,7.11667],"type":"Point"}
}