{
  "type": "Feature",
  "properties": {
    "gn:admin1_code":"43.0",
    "gn:admin2_code":"35014.0",
    "gn:asciiname":"Anzwa",
    "gn:country_code":"NG",
    "gn:dem":171,
    "gn:feature_class":"P",
    "gn:feature_code":"PPL",
    "gn:name":"Anzwa",
    "gn:population":0,
    "gn:timezone":"Africa/Lagos",
    "iso:country":"NG",
    "wof:name":"Anzwa",
    "wof:placetype":"locality"
},
  "geometry": {"coordinates":[9.99484,8.03587],"type":"Point"}
}