{
  "type": "Feature",
  "properties": {
    "gn:admin1_code":"46.0",
    "gn:admin2_code":"5014.0",
    "gn:admin3_code":"BA1406",
    "gn:asciiname":"Dallari",
    "gn:country_code":"NG",
    "gn:dem":444,
    "gn:feature_class":"P",
    "gn:feature_code":"PPL",
    "gn:name":"Dallari",
    "gn:population":0,
    "gn:timezone":"Africa/Lagos",
    "iso:country":"NG",
    "wof:name":"Dallari",
    "wof:placetype":"locality"
},
  "geometry": {"coordinates":[10.4488,11.3993],"type":"Point"}
}