{
  "type": "Feature",
  "properties": {
    "gn:admin1_code":"52.0",
    "gn:admin2_code":"6007.0",
    "gn:asciiname":"Gbaran-Market",
    "gn:country_code":"NG",
    "gn:dem":19,
    "gn:feature_class":"P",
    "gn:feature_code":"PPL",
    "gn:name":"Gbaran-Market",
    "gn:population":0,
    "gn:timezone":"Africa/Lagos",
    "iso:country":"NG",
    "name:eng_x_preferred":[
        "Gbaran-Market"
    ],
    "name:eng_x_variant":[
        "Gbaran"
    ],
    "wof:name":"Gbaran-Market",
    "wof:placetype":"locality"
},
  "geometry": {"coordinates":[5.86757,4.77249],"type":"Point"}
}