{
  "type": "Feature",
  "properties": {
    "gn:admin1_code":"40.0",
    "gn:admin2_code":"508.0",
    "gn:admin3_code":"50801",
    "gn:asciiname":"Tungan Maji",
    "gn:country_code":"NG",
    "gn:dem":162,
    "gn:feature_class":"P",
    "gn:feature_code":"PPL",
    "gn:name":"Tungan Maji",
    "gn:population":0,
    "gn:timezone":"Africa/Lagos",
    "iso:country":"NG",
    "wof:name":"Tungan Maji",
    "wof:placetype":"locality"
},
  "geometry": {"coordinates":[3.82694,11.63057],"type":"Point"}
}