{
  "type": "Feature",
  "properties": {
    "gn:admin1_code":"51.0",
    "gn:admin2_code":"618.0",
    "gn:admin3_code":"61805",
    "gn:asciiname":"Samo Birni",
    "gn:country_code":"NG",
    "gn:dem":237,
    "gn:feature_class":"P",
    "gn:feature_code":"PPL",
    "gn:name":"Samo Birni",
    "gn:population":0,
    "gn:timezone":"Africa/Lagos",
    "iso:country":"NG",
    "wof:name":"Samo Birni",
    "wof:placetype":"locality"
},
  "geometry": {"coordinates":[4.59127,12.38822],"type":"Point"}
}