{
  "type": "Feature",
  "properties": {
    "gn:admin1_code":"24.0",
    "gn:admin2_code":"430.0",
    "gn:admin3_code":"43004",
    "gn:asciiname":"Yana",
    "gn:country_code":"NG",
    "gn:dem":541,
    "gn:feature_class":"P",
    "gn:feature_code":"PPL",
    "gn:name":"Yana",
    "gn:population":0,
    "gn:timezone":"Africa/Lagos",
    "iso:country":"NG",
    "wof:name":"Yana",
    "wof:placetype":"locality"
},
  "geometry": {"coordinates":[7.64842,12.75707],"type":"Point"}
}