{
  "type": "Feature",
  "properties": {
    "gn:admin1_code":"24.0",
    "gn:admin2_code":"430.0",
    "gn:admin3_code":"43004",
    "gn:asciiname":"Yana",
    "gn:country_code":"NG",
    "gn:dem":541,
    "gn:feature_class":"P",
    "gn:feature_code":"PPL",
    "gn:name":"Yana",
    "gn:population":0,
    "gn:timezone":"Africa/Lagos",
    "iso:country":"NG",
    "name:aze_x_preferred":[
        "Yana"
    ],
    "name:bul_x_preferred":[
        "\u042f\u043d\u0430"
    ],
    "name:ceb_x_preferred":[
        "Yana"
    ],
    "name:chv_x_preferred":[
        "\u042f\u043d\u0430"
    ],
    "name:deu_x_preferred":[
        "Yana"
    ],
    "name:fra_x_preferred":[
        "Yana"
    ],
    "name:nld_x_preferred":[
        "Yana"
    ],
    "name:rus_x_preferred":[
        "\u042f\u043d\u0430"
    ],
    "name:sah_x_preferred":[
        "\u0414\u044c\u0430\u0430\u04a5\u044b"
    ],
    "name:spa_x_preferred":[
        "Yana"
    ],
    "name:swe_x_preferred":[
        "Yana"
    ],
    "name:tur_x_preferred":[
        "Yana"
    ],
    "name:ukr_x_preferred":[
        "\u042f\u043d\u0430"
    ],
    "wof:name":"Yana",
    "wof:placetype":"locality"
},
  "geometry": {"coordinates":[7.64842,12.75707],"type":"Point"}
}