{
  "type": "Feature",
  "properties": {
    "gn:admin1_code":"23.0",
    "gn:admin2_code":"19002.0",
    "gn:admin3_code":"KD0201",
    "gn:asciiname":"Badna",
    "gn:country_code":"NG",
    "gn:dem":572,
    "gn:feature_class":"P",
    "gn:feature_code":"PPL",
    "gn:name":"Badna",
    "gn:population":0,
    "gn:timezone":"Africa/Lagos",
    "iso:country":"NG",
    "wof:name":"Badna",
    "wof:placetype":"locality"
},
  "geometry": {"coordinates":[6.95565,10.39616],"type":"Point"}
}