{
  "type": "Feature",
  "properties": {
    "gn:admin1_code":"51.0",
    "gn:admin2_code":"622.0",
    "gn:admin3_code":"62206",
    "gn:asciiname":"Sabon Gari",
    "gn:country_code":"NG",
    "gn:dem":273,
    "gn:feature_class":"P",
    "gn:feature_code":"PPL",
    "gn:name":"Sabon Gari",
    "gn:population":0,
    "gn:timezone":"Africa/Lagos",
    "iso:country":"NG",
    "name:pol_x_preferred":[
        "Sabon Gari"
    ],
    "wof:name":"Sabon Gari",
    "wof:placetype":"locality"
},
  "geometry": {"coordinates":[5.4753,13.276],"type":"Point"}
}