{
  "type": "Feature",
  "properties": {
    "gn:admin1_code":"40.0",
    "gn:admin2_code":"505.0",
    "gn:admin3_code":"50510",
    "gn:asciiname":"Tunga-Damalu",
    "gn:country_code":"NG",
    "gn:dem":175,
    "gn:feature_class":"P",
    "gn:feature_code":"PPL",
    "gn:name":"Tunga-Damalu",
    "gn:population":0,
    "gn:timezone":"Africa/Lagos",
    "iso:country":"NG",
    "wof:name":"Tunga-Damalu",
    "wof:placetype":"locality"
},
  "geometry": {"coordinates":[4.31983,11.54955],"type":"Point"}
}