{
  "type": "Feature",
  "properties": {
    "gn:admin1_code":"24.0",
    "gn:admin2_code":"417.0",
    "gn:admin3_code":"41707",
    "gn:asciiname":"Dan Kwara",
    "gn:country_code":"NG",
    "gn:dem":552,
    "gn:feature_class":"P",
    "gn:feature_code":"PPL",
    "gn:name":"Dan Kwara",
    "gn:population":0,
    "gn:timezone":"Africa/Lagos",
    "iso:country":"NG",
    "wof:name":"Dan Kwara",
    "wof:placetype":"locality"
},
  "geometry": {"coordinates":[7.77386,11.63935],"type":"Point"}
}