{
  "type": "Feature",
  "properties": {
    "gn:admin1_code":"43.0",
    "gn:admin2_code":"35004.0",
    "gn:asciiname":"Mayo Juji",
    "gn:country_code":"NG",
    "gn:dem":389,
    "gn:feature_class":"P",
    "gn:feature_code":"PPL",
    "gn:name":"Mayo Juji",
    "gn:population":0,
    "gn:timezone":"Africa/Lagos",
    "iso:country":"NG",
    "wof:name":"Mayo Juji",
    "wof:placetype":"locality"
},
  "geometry": {"coordinates":[11.18333,7.41667],"type":"Point"}
}