{
  "type": "Feature",
  "properties": {
    "gn:admin1_code":"35.0",
    "gn:admin2_code":"2002.0",
    "gn:asciiname":"Temrashi",
    "gn:country_code":"NG",
    "gn:dem":554,
    "gn:feature_class":"P",
    "gn:feature_code":"PPL",
    "gn:name":"Temrashi",
    "gn:population":0,
    "gn:timezone":"Africa/Lagos",
    "iso:country":"NG",
    "name:eng_x_preferred":[
        "Temrashi"
    ],
    "wof:name":"Temrashi",
    "wof:placetype":"locality"
},
  "geometry": {"coordinates":[12.45499,8.99849],"type":"Point"}
}