{
  "type": "Feature",
  "properties": {
    "gn:admin1_code":"42.0",
    "gn:admin2_code":"30014.0",
    "gn:asciiname":"Akinloye",
    "gn:country_code":"NG",
    "gn:dem":168,
    "gn:feature_class":"P",
    "gn:feature_code":"PPL",
    "gn:name":"Akinloye",
    "gn:population":0,
    "gn:timezone":"Africa/Lagos",
    "iso:country":"NG",
    "wof:name":"Akinloye",
    "wof:placetype":"locality"
},
  "geometry": {"coordinates":[4.53333,7.23333],"type":"Point"}
}