{
  "type": "Feature",
  "properties": {
    "gn:admin1_code":"36.0",
    "gn:admin2_code":"10012.0",
    "gn:asciiname":"Ogbagu Ogume",
    "gn:country_code":"NG",
    "gn:dem":20,
    "gn:feature_class":"P",
    "gn:feature_code":"PPL",
    "gn:name":"Ogbagu Ogume",
    "gn:population":0,
    "gn:timezone":"Africa/Lagos",
    "iso:country":"NG",
    "wof:name":"Ogbagu Ogume",
    "wof:placetype":"locality"
},
  "geometry": {"coordinates":[6.33494,5.76915],"type":"Point"}
}