{
  "type": "Feature",
  "properties": {
    "gn:admin1_code":"52.0",
    "gn:admin2_code":"6007.0",
    "gn:asciiname":"Biotu",
    "gn:country_code":"NG",
    "gn:dem":-9999,
    "gn:feature_class":"P",
    "gn:feature_code":"PPL",
    "gn:name":"Biotu",
    "gn:population":0,
    "gn:timezone":"Africa/Lagos",
    "iso:country":"NG",
    "name:eng_x_preferred":[
        "Biotu"
    ],
    "wof:name":"Biotu",
    "wof:placetype":"locality"
},
  "geometry": {"coordinates":[5.6372,4.59655],"type":"Point"}
}