{
  "type": "Feature",
  "properties": {
    "gn:admin1_code":"55.0",
    "gn:admin2_code":"16004.0",
    "gn:asciiname":"Jangira",
    "gn:country_code":"NG",
    "gn:dem":475,
    "gn:feature_class":"P",
    "gn:feature_code":"PPL",
    "gn:name":"Jangira",
    "gn:population":0,
    "gn:timezone":"Africa/Lagos",
    "iso:country":"NG",
    "name:eng_x_preferred":[
        "Jangira"
    ],
    "wof:name":"Jangira",
    "wof:placetype":"locality"
},
  "geometry": {"coordinates":[10.61032,10.67524],"type":"Point"}
}