{
  "type": "Feature",
  "properties": {
    "gn:admin1_code":"27.0",
    "gn:admin2_code":"112.0",
    "gn:admin3_code":"11201",
    "gn:asciiname":"Gbengel",
    "gn:country_code":"NG",
    "gn:dem":828,
    "gn:feature_class":"P",
    "gn:feature_code":"PPL",
    "gn:name":"Gbengel",
    "gn:population":0,
    "gn:timezone":"Africa/Lagos",
    "iso:country":"NG",
    "wof:name":"Gbengel",
    "wof:placetype":"locality"
},
  "geometry": {"coordinates":[12.25848,10.50322],"type":"Point"}
}