{
  "type": "Feature",
  "properties": {
    "gn:admin1_code":"50.0",
    "gn:admin2_code":"33001.0",
    "gn:asciiname":"Omoraka",
    "gn:country_code":"NG",
    "gn:dem":5,
    "gn:feature_class":"P",
    "gn:feature_code":"PPL",
    "gn:name":"Omoraka",
    "gn:population":0,
    "gn:timezone":"Africa/Lagos",
    "iso:country":"NG",
    "wof:name":"Omoraka",
    "wof:placetype":"locality"
},
  "geometry": {"coordinates":[6.65611,4.86429],"type":"Point"}
}