{
  "type": "Feature",
  "properties": {
    "gn:admin1_code":"49.0",
    "gn:admin2_code":"32013.0",
    "gn:asciiname":"Gwolong",
    "gn:country_code":"NG",
    "gn:dem":1252,
    "gn:feature_class":"P",
    "gn:feature_code":"PPL",
    "gn:name":"Gwolong",
    "gn:population":0,
    "gn:timezone":"Africa/Lagos",
    "iso:country":"NG",
    "wof:name":"Gwolong",
    "wof:placetype":"locality"
},
  "geometry": {"coordinates":[9.43983,9.33666],"type":"Point"}
}