{
  "type": "Feature",
  "properties": {
    "gn:country":"NG",
    "gn:fcode":"PPL",
    "gn:population":10470,
    "iso:country":"NG",
    "name:und_x_variant":[
        "Zaki Biyem"
    ],
    "qs_pg:aaroncc":"NG",
    "qs_pg:gn_country":"NG",
    "qs_pg:gn_fcode":"PPL",
    "qs_pg:gn_pop":10470,
    "qs_pg:name":"Zaki Biam",
    "qs_pg:photos_9r":0,
    "qs_pg:photos_sr":0,
    "qs_pg:pop_sr":6,
    "qs_pg:qs_pg_placetype":"locality",
    "wof:name":"Zaki Biam",
    "wof:placetype":"locality",
    "wof:population":10470
},
  "geometry": {"coordinates":[9.61667,7.51667],"type":"Point"}
}