{
  "type": "Feature",
  "properties": {
    "gn:admin1_code":"5.0",
    "gn:admin2_code":"25007.0",
    "gn:asciiname":"Owode-Ise",
    "gn:country_code":"NG",
    "gn:dem":4,
    "gn:feature_class":"P",
    "gn:feature_code":"PPL",
    "gn:name":"Owode-Ise",
    "gn:population":0,
    "gn:timezone":"Africa/Lagos",
    "iso:country":"NG",
    "wof:name":"Owode-Ise",
    "wof:placetype":"locality"
},
  "geometry": {"coordinates":[4.23125,6.40796],"type":"Point"}
}