{
  "type": "Feature",
  "properties": {
    "gn:admin1_code":"23.0",
    "gn:admin2_code":"19007.0",
    "gn:admin3_code":"KD0710",
    "gn:asciiname":"Bakin Kogi",
    "gn:country_code":"NG",
    "gn:dem":767,
    "gn:feature_class":"P",
    "gn:feature_code":"PPL",
    "gn:name":"Bakin Kogi",
    "gn:population":0,
    "gn:timezone":"Africa/Lagos",
    "iso:country":"NG",
    "wof:name":"Bakin Kogi",
    "wof:placetype":"locality"
},
  "geometry": {"coordinates":[8.2729,9.49213],"type":"Point"}
}