{
  "type": "Feature",
  "properties": {
    "gn:admin1_code":"49.0",
    "gn:asciiname":"Loko",
    "gn:country_code":"NG",
    "gn:dem":217,
    "gn:feature_class":"P",
    "gn:feature_code":"PPL",
    "gn:name":"Loko",
    "gn:population":0,
    "gn:timezone":"Africa/Lagos",
    "iso:country":"NG",
    "name:ceb_x_preferred":[
        "Loko"
    ],
    "name:deu_x_preferred":[
        "Loko"
    ],
    "name:fra_x_preferred":[
        "Loko"
    ],
    "name:kaz_x_preferred":[
        "\u041b\u043e\u043a\u043e"
    ],
    "name:por_x_preferred":[
        "Loko"
    ],
    "name:ron_x_preferred":[
        "Loko"
    ],
    "name:rus_x_preferred":[
        "\u041b\u043e\u043a\u043e"
    ],
    "name:swe_x_preferred":[
        "Loko"
    ],
    "wof:name":"Loko",
    "wof:placetype":"locality"
},
  "geometry": {"coordinates":[9.25855,8.7581],"type":"Point"}
}