{
  "type": "Feature",
  "properties": {
    "gn:country":"NG",
    "gn:fcode":"PPL",
    "gn:pop":11673,
    "iso:country":"NG",
    "qs:name":"Goniri",
    "qs:photos_9r":0,
    "qs:photos_sr":0,
    "qs:pop_sr":"6",
    "wof:name":"Goniri",
    "wof:placetype":"locality",
    "wof:population":11673
},
  "geometry": {"coordinates":[12.31444,11.48333],"type":"Point"}
}