{
  "type": "Feature",
  "properties": {
    "gn:admin1_code":"16.0",
    "gn:admin2_code":"28004.0",
    "gn:asciiname":"Anga",
    "gn:country_code":"NG",
    "gn:dem":56,
    "gn:feature_class":"P",
    "gn:feature_code":"PPL",
    "gn:name":"Anga",
    "gn:population":0,
    "gn:timezone":"Africa/Lagos",
    "iso:country":"NG",
    "wof:name":"Anga",
    "wof:placetype":"locality"
},
  "geometry": {"coordinates":[2.81667,6.88333],"type":"Point"}
}