{
  "type": "Feature",
  "properties": {
    "gn:admin1_code":"16.0",
    "gn:admin2_code":"28004.0",
    "gn:asciiname":"Anga",
    "gn:country_code":"NG",
    "gn:dem":56,
    "gn:feature_class":"P",
    "gn:feature_code":"PPL",
    "gn:name":"Anga",
    "gn:population":0,
    "gn:timezone":"Africa/Lagos",
    "iso:country":"NG",
    "name:ben_x_preferred":[
        "\u0985\u0999\u09cd\u0997"
    ],
    "name:cat_x_preferred":[
        "Anga"
    ],
    "name:ces_x_preferred":[
        "Anga"
    ],
    "name:fin_x_preferred":[
        "Anga"
    ],
    "name:fra_x_preferred":[
        "Anga"
    ],
    "name:glg_x_preferred":[
        "Anga"
    ],
    "name:hin_x_preferred":[
        "\u0905\u0902\u0917 \u092e\u0939\u093e\u091c\u0928\u092a\u0926"
    ],
    "name:jpn_x_preferred":[
        "\u30a2\u30f3\u30ac\u56fd"
    ],
    "name:kan_x_preferred":[
        "\u0c85\u0c82\u0c97 \u0cb0\u0cbe\u0c9c\u0ccd\u0caf"
    ],
    "name:lit_x_preferred":[
        "Anga"
    ],
    "name:mal_x_preferred":[
        "\u0d05\u0d02\u0d17\u0d02"
    ],
    "name:mar_x_preferred":[
        "\u0905\u0902\u0917"
    ],
    "name:nno_x_preferred":[
        "Anga"
    ],
    "name:pnb_x_preferred":[
        "\u0627\u0646\u06af"
    ],
    "name:por_x_preferred":[
        "Anga"
    ],
    "name:rus_x_preferred":[
        "\u0410\u043d\u0433\u0430"
    ],
    "name:san_x_preferred":[
        "\u0905\u0919\u094d\u0917\u0903"
    ],
    "name:spa_x_preferred":[
        "Anga"
    ],
    "name:tam_x_preferred":[
        "\u0b85\u0b99\u0bcd\u0b95\u0bae\u0bcd"
    ],
    "name:tel_x_preferred":[
        "\u0c05\u0c02\u0c17\u0c26\u0c47\u0c36\u0c2e\u0c41"
    ],
    "name:ukr_x_preferred":[
        "\u0410\u043d\u0433\u0430"
    ],
    "wof:name":"Anga",
    "wof:placetype":"locality"
},
  "geometry": {"coordinates":[2.81667,6.88333],"type":"Point"}
}