{
  "type": "Feature",
  "properties": {
    "gn:admin1_code":"26.0",
    "gn:admin2_code":"7010.0",
    "gn:asciiname":"Tse-Jime",
    "gn:country_code":"NG",
    "gn:dem":127,
    "gn:feature_class":"P",
    "gn:feature_code":"PPL",
    "gn:name":"Tse-Jime",
    "gn:population":0,
    "gn:timezone":"Africa/Lagos",
    "iso:country":"NG",
    "wof:name":"Tse-Jime",
    "wof:placetype":"locality"
},
  "geometry": {"coordinates":[8.52488,7.08414],"type":"Point"}
}