{
  "type": "Feature",
  "properties": {
    "gn:admin1_code":"48.0",
    "gn:admin2_code":"29014.0",
    "gn:asciiname":"Odulawo",
    "gn:country_code":"NG",
    "gn:dem":16,
    "gn:feature_class":"P",
    "gn:feature_code":"PPL",
    "gn:name":"Odulawo",
    "gn:population":0,
    "gn:timezone":"Africa/Lagos",
    "iso:country":"NG",
    "wof:name":"Odulawo",
    "wof:placetype":"locality"
},
  "geometry": {"coordinates":[4.70865,6.44943],"type":"Point"}
}