{
  "type": "Feature",
  "properties": {
    "gn:admin1_code":"53.0",
    "gn:admin2_code":"11010.0",
    "gn:asciiname":"Adumu-Igbadu",
    "gn:country_code":"NG",
    "gn:dem":79,
    "gn:feature_class":"P",
    "gn:feature_code":"PPL",
    "gn:name":"Adumu-Igbadu",
    "gn:population":0,
    "gn:timezone":"Africa/Lagos",
    "iso:country":"NG",
    "name:und_x_variant":[
        "Adumu Igbagu"
    ],
    "wof:name":"Adumu-Igbadu",
    "wof:placetype":"locality"
},
  "geometry": {"coordinates":[8.25636,6.36775],"type":"Point"}
}