{
  "type": "Feature",
  "properties": {
    "gn:admin1_code":"36.0",
    "gn:admin2_code":"10011.0",
    "gn:asciiname":"Aguetiti IV",
    "gn:country_code":"NG",
    "gn:dem":22,
    "gn:feature_class":"P",
    "gn:feature_code":"PPL",
    "gn:name":"Aguetiti IV",
    "gn:population":0,
    "gn:timezone":"Africa/Lagos",
    "iso:country":"NG",
    "wof:name":"Aguetiti IV",
    "wof:placetype":"locality"
},
  "geometry": {"coordinates":[6.63904,5.84966],"type":"Point"}
}