{
  "type": "Feature",
  "properties": {
    "gn:admin1_code":"23.0",
    "gn:admin2_code":"19001.0",
    "gn:admin3_code":"KD0106",
    "gn:asciiname":"Kuki",
    "gn:country_code":"NG",
    "gn:dem":357,
    "gn:feature_class":"P",
    "gn:feature_code":"PPL",
    "gn:name":"Kuki",
    "gn:population":0,
    "gn:timezone":"Africa/Lagos",
    "iso:country":"NG",
    "name:ceb_x_preferred":[
        "Kuki"
    ],
    "name:deu_x_preferred":[
        "Kuki"
    ],
    "name:fas_x_preferred":[
        "\u06a9\u0648\u06a9\u06cc"
    ],
    "name:ita_x_preferred":[
        "Kuki"
    ],
    "name:rus_x_preferred":[
        "\u041a\u0443\u043a\u0438"
    ],
    "name:swe_x_preferred":[
        "Kuki"
    ],
    "name:tgl_x_preferred":[
        "Kuki"
    ],
    "name:ukr_x_preferred":[
        "\u041a\u0443\u043a\u0456"
    ],
    "wof:name":"Kuki",
    "wof:placetype":"locality"
},
  "geometry": {"coordinates":[6.19292,10.40858],"type":"Point"}
}