{
  "type": "Feature",
  "properties": {
    "gn:admin1_code":"29.0",
    "gn:admin2_code":"20034.0",
    "gn:admin3_code":"KN2415",
    "gn:asciiname":"Acilafiya",
    "gn:country_code":"NG",
    "gn:dem":487,
    "gn:feature_class":"P",
    "gn:feature_code":"PPL",
    "gn:name":"Acilafiya",
    "gn:population":0,
    "gn:timezone":"Africa/Lagos",
    "iso:country":"NG",
    "wof:name":"Acilafiya",
    "wof:placetype":"locality"
},
  "geometry": {"coordinates":[8.15125,11.77801],"type":"Point"}
}