{
  "type": "Feature",
  "properties": {
    "gn:admin1_code":"30.0",
    "gn:admin2_code":"24003.0",
    "gn:asciiname":"Chita",
    "gn:cc2":"NG",
    "gn:country_code":"NG",
    "gn:dem":176,
    "gn:feature_class":"P",
    "gn:feature_code":"PPL",
    "gn:name":"Chita",
    "gn:population":0,
    "gn:timezone":"Africa/Lagos",
    "iso:country":"NG",
    "name:ceb_x_preferred":[
        "Chita"
    ],
    "name:deu_x_preferred":[
        "Chita"
    ],
    "name:fas_x_preferred":[
        "\u0686\u06cc\u062a\u0627"
    ],
    "name:glg_x_preferred":[
        "Chita"
    ],
    "name:heb_x_preferred":[
        "\u05e6'\u05d9\u05d8\u05d4"
    ],
    "name:ita_x_preferred":[
        "Chita"
    ],
    "name:kor_x_preferred":[
        "\uce58\ud0c0"
    ],
    "name:lat_x_preferred":[
        "Tschita"
    ],
    "name:nds_x_preferred":[
        "Chita"
    ],
    "name:nld_x_preferred":[
        "Chita"
    ],
    "name:por_x_preferred":[
        "Chita"
    ],
    "name:rus_x_preferred":[
        "\u0427\u0438\u0442\u0430"
    ],
    "name:sco_x_preferred":[
        "Chita"
    ],
    "name:spa_x_preferred":[
        "Chita"
    ],
    "name:swe_x_preferred":[
        "Chita"
    ],
    "name:und_x_variant":[
        "Chitta",
        "Chita"
    ],
    "wof:name":"Chita",
    "wof:placetype":"locality"
},
  "geometry": {"coordinates":[5.15,8.91667],"type":"Point"}
}