{
  "type": "Feature",
  "properties": {
    "gn:admin1_code":"30.0",
    "gn:admin2_code":"24003.0",
    "gn:asciiname":"Chita",
    "gn:cc2":"NG",
    "gn:country_code":"NG",
    "gn:dem":176,
    "gn:feature_class":"P",
    "gn:feature_code":"PPL",
    "gn:name":"Chita",
    "gn:population":0,
    "gn:timezone":"Africa/Lagos",
    "iso:country":"NG",
    "name:und_x_variant":[
        "Chitta",
        "Chita"
    ],
    "wof:name":"Chita",
    "wof:placetype":"locality"
},
  "geometry": {"coordinates":[5.15,8.91667],"type":"Point"}
}