{
  "type": "Feature",
  "properties": {
    "gn:admin1_code":"26.0",
    "gn:admin2_code":"7020.0",
    "gn:asciiname":"Mpangu",
    "gn:country_code":"NG",
    "gn:dem":117,
    "gn:feature_class":"P",
    "gn:feature_code":"PPL",
    "gn:name":"Mpangu",
    "gn:population":0,
    "gn:timezone":"Africa/Lagos",
    "iso:country":"NG",
    "wof:name":"Mpangu",
    "wof:placetype":"locality"
},
  "geometry": {"coordinates":[8.79176,7.54313],"type":"Point"}
}