{
  "type": "Feature",
  "properties": {
    "gn:admin1_code":"35.0",
    "gn:admin2_code":"2003.0",
    "gn:asciiname":"Gang Pokani",
    "gn:country_code":"NG",
    "gn:dem":471,
    "gn:feature_class":"P",
    "gn:feature_code":"PPL",
    "gn:name":"Gang Pokani",
    "gn:population":0,
    "gn:timezone":"Africa/Lagos",
    "iso:country":"NG",
    "wof:name":"Gang Pokani",
    "wof:placetype":"locality"
},
  "geometry": {"coordinates":[12.11667,8.31667],"type":"Point"}
}