{
  "type": "Feature",
  "properties": {
    "gn:admin1_code":"37.0",
    "gn:admin2_code":"12013.0",
    "gn:asciiname":"Consin Camp",
    "gn:country_code":"NG",
    "gn:dem":52,
    "gn:feature_class":"P",
    "gn:feature_code":"PPL",
    "gn:name":"Consin Camp",
    "gn:population":0,
    "gn:timezone":"Africa/Lagos",
    "iso:country":"NG",
    "name:eng_x_preferred":[
        "Consin Camp"
    ],
    "wof:name":"Consin Camp",
    "wof:placetype":"locality"
},
  "geometry": {"coordinates":[6.06777,6.32169],"type":"Point"}
}