{
  "type": "Feature",
  "properties": {
    "gn:admin1_code":"31.0",
    "gn:admin2_code":"27009.0",
    "gn:asciiname":"Jariga",
    "gn:country_code":"NG",
    "gn:dem":306,
    "gn:feature_class":"P",
    "gn:feature_code":"PPL",
    "gn:name":"Jariga",
    "gn:population":0,
    "gn:timezone":"Africa/Lagos",
    "iso:country":"NG",
    "wof:name":"Jariga",
    "wof:placetype":"locality"
},
  "geometry": {"coordinates":[6.7545,9.31455],"type":"Point"}
}