{
  "type": "Feature",
  "properties": {
    "gn:admin1_code":"50.0",
    "gn:admin2_code":"33023.0",
    "gn:asciiname":"Gbene Ue",
    "gn:country_code":"NG",
    "gn:dem":22,
    "gn:feature_class":"P",
    "gn:feature_code":"PPL",
    "gn:name":"Gbene Ue",
    "gn:population":0,
    "gn:timezone":"Africa/Lagos",
    "iso:country":"NG",
    "wof:name":"Gbene Ue",
    "wof:placetype":"locality"
},
  "geometry": {"coordinates":[7.28341,4.74435],"type":"Point"}
}