{
  "type": "Feature",
  "properties": {
    "gn:admin1_code":"26.0",
    "gn:admin2_code":"7005",
    "gn:asciiname":"Iorkohol",
    "gn:country_code":"NG",
    "gn:dem":190,
    "gn:feature_class":"P",
    "gn:feature_code":"PPL",
    "gn:name":"Iorkohol",
    "gn:population":0,
    "gn:timezone":"Africa/Lagos",
    "iso:country":"NG",
    "wof:name":"Iorkohol",
    "wof:placetype":"locality"
},
  "geometry": {"coordinates":[8.95745,7.46339],"type":"Point"}
}