{
  "type": "Feature",
  "properties": {
    "gn:admin1_code":"27.0",
    "gn:admin2_code":"107.0",
    "gn:admin3_code":"10707",
    "gn:asciiname":"Gardiri",
    "gn:country_code":"NG",
    "gn:dem":441,
    "gn:feature_class":"P",
    "gn:feature_code":"PPL",
    "gn:name":"Gardiri",
    "gn:population":0,
    "gn:timezone":"Africa/Lagos",
    "iso:country":"NG",
    "wof:name":"Gardiri",
    "wof:placetype":"locality"
},
  "geometry": {"coordinates":[12.39631,11.19771],"type":"Point"}
}