{
  "type": "Feature",
  "properties": {
    "gn:admin1_code":"47.0",
    "gn:admin2_code":"14013.0",
    "gn:asciiname":"Okuje",
    "gn:country_code":"NG",
    "gn:dem":248,
    "gn:feature_class":"P",
    "gn:feature_code":"PPL",
    "gn:name":"Okuje",
    "gn:population":0,
    "gn:timezone":"Africa/Lagos",
    "iso:country":"NG",
    "name:und_x_variant":[
        "Okuji",
        "Okuje"
    ],
    "wof:name":"Okuje",
    "wof:placetype":"locality"
},
  "geometry": {"coordinates":[7.29598,6.90197],"type":"Point"}
}