{
  "type": "Feature",
  "properties": {
    "gn:admin1_code":"47.0",
    "gn:admin2_code":"14013.0",
    "gn:asciiname":"Okuje",
    "gn:country_code":"NG",
    "gn:dem":248,
    "gn:feature_class":"P",
    "gn:feature_code":"PPL",
    "gn:name":"Okuje",
    "gn:population":0,
    "gn:timezone":"Africa/Lagos",
    "iso:country":"NG",
    "name:bos_x_preferred":[
        "Okuje"
    ],
    "name:glg_x_preferred":[
        "Okuje"
    ],
    "name:hrv_x_preferred":[
        "Okuje"
    ],
    "name:hun_x_preferred":[
        "Okuje"
    ],
    "name:nld_x_preferred":[
        "Okuje"
    ],
    "name:slv_x_preferred":[
        "Okuje"
    ],
    "name:srp_x_preferred":[
        "\u041e\u043a\u0443\u0458\u0435"
    ],
    "name:ukr_x_preferred":[
        "\u041e\u043a\u0443\u0454"
    ],
    "name:und_x_variant":[
        "Okuji"
    ],
    "wof:name":"Okuje",
    "wof:placetype":"locality"
},
  "geometry": {"coordinates":[7.29598,6.90197],"type":"Point"}
}