{
  "type": "Feature",
  "properties": {
    "gn:admin1_code":"46.0",
    "gn:admin2_code":"5018.0",
    "gn:admin3_code":"BA1809",
    "gn:asciiname":"Gumamai",
    "gn:country_code":"NG",
    "gn:dem":694,
    "gn:feature_class":"P",
    "gn:feature_code":"PPL",
    "gn:name":"Gumamai",
    "gn:population":0,
    "gn:timezone":"Africa/Lagos",
    "iso:country":"NG",
    "wof:name":"Gumamai",
    "wof:placetype":"locality"
},
  "geometry": {"coordinates":[8.83933,10.83206],"type":"Point"}
}