{
  "type": "Feature",
  "properties": {
    "gn:admin1_code":"43.0",
    "gn:admin2_code":"35001.0",
    "gn:asciiname":"Tabari Jauro Manu",
    "gn:country_code":"NG",
    "gn:dem":225,
    "gn:feature_class":"P",
    "gn:feature_code":"PPL",
    "gn:name":"Tabari Jauro Manu",
    "gn:population":0,
    "gn:timezone":"Africa/Lagos",
    "iso:country":"NG",
    "wof:name":"Tabari Jauro Manu",
    "wof:placetype":"locality"
},
  "geometry": {"coordinates":[11.26152,8.71629],"type":"Point"}
}