{
  "type": "Feature",
  "properties": {
    "gn:admin1_code":"45.0",
    "gn:admin2_code":"1009.0",
    "gn:asciiname":"Umu Obiakwa",
    "gn:country_code":"NG",
    "gn:dem":78,
    "gn:feature_class":"P",
    "gn:feature_code":"PPL",
    "gn:name":"Umu Obiakwa",
    "gn:population":0,
    "gn:timezone":"Africa/Lagos",
    "iso:country":"NG",
    "wof:name":"Umu Obiakwa",
    "wof:placetype":"locality"
},
  "geometry": {"coordinates":[7.45779,5.15212],"type":"Point"}
}