{
  "type": "Feature",
  "properties": {
    "gn:admin1_code":"57.0",
    "gn:admin2_code":"811.0",
    "gn:admin3_code":"81101",
    "gn:asciiname":"Bula",
    "gn:country_code":"NG",
    "gn:dem":349,
    "gn:feature_class":"P",
    "gn:feature_code":"PPL",
    "gn:name":"Bula",
    "gn:population":0,
    "gn:timezone":"Africa/Lagos",
    "iso:country":"NG",
    "wof:name":"Bula",
    "wof:placetype":"locality"
},
  "geometry": {"coordinates":[6.28203,13.08736],"type":"Point"}
}