{
  "type": "Feature",
  "properties": {
    "gn:admin1_code":"36.0",
    "gn:admin2_code":"10023.0",
    "gn:asciiname":"Abevgborode",
    "gn:country_code":"NG",
    "gn:dem":7,
    "gn:feature_class":"P",
    "gn:feature_code":"PPL",
    "gn:name":"Abevgborode",
    "gn:population":0,
    "gn:timezone":"Africa/Lagos",
    "iso:country":"NG",
    "name:und_x_variant":[
        "Abigborodo",
        "Abeugborode",
        "Abigborudu",
        "Abevgborode"
    ],
    "wof:name":"Abevgborode",
    "wof:placetype":"locality"
},
  "geometry": {"coordinates":[5.53558,5.89341],"type":"Point"}
}