{
  "type": "Feature",
  "properties": {
    "gn:admin1_code":"16.0",
    "gn:admin2_code":"28014.0",
    "gn:asciiname":"Iganmi",
    "gn:cc2":"NG",
    "gn:country_code":"NG",
    "gn:dem":55,
    "gn:feature_class":"P",
    "gn:feature_code":"PPL",
    "gn:name":"Iganmi",
    "gn:population":0,
    "gn:timezone":"Africa/Lagos",
    "iso:country":"NG",
    "name:und_x_variant":[
        "Igami",
        "Iganmi"
    ],
    "wof:name":"Iganmi",
    "wof:placetype":"locality"
},
  "geometry": {"coordinates":[2.78333,6.65],"type":"Point"}
}