{
  "type": "Feature",
  "properties": {
    "gn:admin1_code":"56.0",
    "gn:asciiname":"Girgo",
    "gn:country_code":"NG",
    "gn:dem":426,
    "gn:feature_class":"P",
    "gn:feature_code":"PPL",
    "gn:name":"Girgo",
    "gn:population":0,
    "gn:timezone":"Africa/Lagos",
    "iso:country":"NG",
    "wof:name":"Girgo",
    "wof:placetype":"locality"
},
  "geometry": {"coordinates":[7.86225,9.31097],"type":"Point"}
}