{
  "type": "Feature",
  "properties": {
    "gn:admin1_code":"57.0",
    "gn:admin2_code":"813.0",
    "gn:admin3_code":"81301",
    "gn:asciiname":"Magazu",
    "gn:country_code":"NG",
    "gn:dem":612,
    "gn:feature_class":"P",
    "gn:feature_code":"PPL",
    "gn:name":"Magazu",
    "gn:population":0,
    "gn:timezone":"Africa/Lagos",
    "iso:country":"NG",
    "wof:name":"Magazu",
    "wof:placetype":"locality"
},
  "geometry": {"coordinates":[6.95385,11.9116],"type":"Point"}
}