{
  "type": "Feature",
  "properties": {
    "gn:admin1_code":"24.0",
    "gn:admin2_code":"402.0",
    "gn:admin3_code":"40210",
    "gn:asciiname":"Alumu",
    "gn:country_code":"NG",
    "gn:dem":525,
    "gn:feature_class":"P",
    "gn:feature_code":"PPL",
    "gn:name":"Alumu",
    "gn:population":0,
    "gn:timezone":"Africa/Lagos",
    "iso:country":"NG",
    "wof:name":"Alumu",
    "wof:placetype":"locality"
},
  "geometry": {"coordinates":[7.54811,12.76247],"type":"Point"}
}