{
  "type": "Feature",
  "properties": {
    "gn:admin1_code":"27.0",
    "gn:admin2_code":"103.0",
    "gn:admin3_code":"10302",
    "gn:asciiname":"Bula Kafie",
    "gn:country_code":"NG",
    "gn:dem":307,
    "gn:feature_class":"P",
    "gn:feature_code":"PPL",
    "gn:name":"Bula Kafie",
    "gn:population":0,
    "gn:timezone":"Africa/Lagos",
    "iso:country":"NG",
    "wof:name":"Bula Kafie",
    "wof:placetype":"locality"
},
  "geometry": {"coordinates":[14.26699,11.46775],"type":"Point"}
}