{
  "type": "Feature",
  "properties": {
    "gn:admin1_code":"25.0",
    "gn:admin2_code":"4021",
    "gn:asciiname":"Owele",
    "gn:country_code":"NG",
    "gn:dem":139,
    "gn:feature_class":"P",
    "gn:feature_code":"PPL",
    "gn:name":"Owele",
    "gn:population":0,
    "gn:timezone":"Africa/Lagos",
    "iso:country":"NG",
    "wof:name":"Owele",
    "wof:placetype":"locality"
},
  "geometry": {"coordinates":[6.87114,6.19743],"type":"Point"}
}