{
  "type": "Feature",
  "properties": {
    "gn:admin1_code":"26.0",
    "gn:admin2_code":"7008.0",
    "gn:asciiname":"Chorun",
    "gn:country_code":"NG",
    "gn:dem":112,
    "gn:feature_class":"P",
    "gn:feature_code":"PPL",
    "gn:name":"Chorun",
    "gn:population":0,
    "gn:timezone":"Africa/Lagos",
    "iso:country":"NG",
    "wof:name":"Chorun",
    "wof:placetype":"locality"
},
  "geometry": {"coordinates":[8.1129,7.6427],"type":"Point"}
}