{
  "type": "Feature",
  "properties": {
    "gn:admin1_code":"23.0",
    "gn:admin2_code":"19005.0",
    "gn:admin3_code":"KD0509",
    "gn:asciiname":"Ungwan Baribare",
    "gn:country_code":"NG",
    "gn:dem":618,
    "gn:feature_class":"P",
    "gn:feature_code":"PPL",
    "gn:name":"Ungwan Baribare",
    "gn:population":0,
    "gn:timezone":"Africa/Lagos",
    "iso:country":"NG",
    "name:und_x_variant":[
        "Baribare",
        "Ungwan Baribare"
    ],
    "wof:name":"Ungwan Baribare",
    "wof:placetype":"locality"
},
  "geometry": {"coordinates":[8.1219,11.3093],"type":"Point"}
}