{
  "type": "Feature",
  "properties": {
    "gn:admin1_code":"48.0",
    "gn:asciiname":"Odofin",
    "gn:country_code":"NG",
    "gn:dem":344,
    "gn:feature_class":"P",
    "gn:feature_code":"PPL",
    "gn:name":"Odofin",
    "gn:population":0,
    "gn:timezone":"Africa/Lagos",
    "iso:country":"NG",
    "wof:name":"Odofin",
    "wof:placetype":"locality"
},
  "geometry": {"coordinates":[5.37099,7.33556],"type":"Point"}
}