{
  "type": "Feature",
  "properties": {
    "gn:admin1_code":"27.0",
    "gn:admin2_code":"119",
    "gn:admin3_code":"11908",
    "gn:asciiname":"Manawaji",
    "gn:country_code":"NG",
    "gn:dem":302,
    "gn:feature_class":"P",
    "gn:feature_code":"PPL",
    "gn:name":"Manawaji",
    "gn:population":0,
    "gn:timezone":"Africa/Lagos",
    "iso:country":"NG",
    "wof:name":"Manawaji",
    "wof:placetype":"locality"
},
  "geometry": {"coordinates":[13.58107,11.85487],"type":"Point"}
}