{
  "type": "Feature",
  "properties": {
    "gn:admin1_code":"50.0",
    "gn:admin2_code":"33009.0",
    "gn:asciiname":"Aabom",
    "gn:country_code":"NG",
    "gn:dem":21,
    "gn:feature_class":"P",
    "gn:feature_code":"PPL",
    "gn:name":"Aabom",
    "gn:population":0,
    "gn:timezone":"Africa/Lagos",
    "iso:country":"NG",
    "wof:name":"Aabom",
    "wof:placetype":"locality"
},
  "geometry": {"coordinates":[7.1936,4.79123],"type":"Point"}
}