{
  "type": "Feature",
  "properties": {
    "gn:admin1_code":"46.0",
    "gn:asciiname":"Mallam Jemo",
    "gn:country_code":"NG",
    "gn:dem":358,
    "gn:feature_class":"P",
    "gn:feature_code":"PPL",
    "gn:name":"Mallam Jemo",
    "gn:population":0,
    "gn:timezone":"Africa/Lagos",
    "iso:country":"NG",
    "name:eng_x_preferred":[
        "Mallam Jemo"
    ],
    "wof:name":"Mallam Jemo",
    "wof:placetype":"locality"
},
  "geometry": {"coordinates":[10.85989,9.75691],"type":"Point"}
}