{
  "type": "Feature",
  "properties": {
    "gn:admin1_code":"16.0",
    "gn:admin2_code":"28006.0",
    "gn:asciiname":"Papalanto",
    "gn:country_code":"NG",
    "gn:dem":28,
    "gn:feature_class":"P",
    "gn:feature_code":"PPL",
    "gn:name":"Papalanto",
    "gn:population":0,
    "gn:timezone":"Africa/Lagos",
    "iso:country":"NG",
    "name:und_x_variant":[
        "Papa Alanto",
        "Papalanto"
    ],
    "wof:name":"Papalanto",
    "wof:placetype":"locality"
},
  "geometry": {"coordinates":[3.19788,6.88672],"type":"Point"}
}