{
  "type": "Feature",
  "properties": {
    "gn:admin1_code":"57.0",
    "gn:admin2_code":"805.0",
    "gn:admin3_code":"80502",
    "gn:asciiname":"Masagu",
    "gn:country_code":"NG",
    "gn:dem":476,
    "gn:feature_class":"P",
    "gn:feature_code":"PPL",
    "gn:name":"Masagu",
    "gn:population":0,
    "gn:timezone":"Africa/Lagos",
    "iso:country":"NG",
    "name:und_x_variant":[
        "Masagu (2)",
        "Masagu"
    ],
    "wof:name":"Masagu",
    "wof:placetype":"locality"
},
  "geometry": {"coordinates":[6.44606,12.12578],"type":"Point"}
}