{
  "type": "Feature",
  "properties": {
    "gn:admin1_code":"21.0",
    "gn:admin2_code":"3004.0",
    "gn:asciiname":"Ntete",
    "gn:country_code":"NG",
    "gn:dem":16,
    "gn:feature_class":"P",
    "gn:feature_code":"PPL",
    "gn:name":"Ntete",
    "gn:population":0,
    "gn:timezone":"Africa/Lagos",
    "iso:country":"NG",
    "name:und_x_variant":[
        "Ntete\u2019s",
        "Ntete"
    ],
    "wof:name":"Ntete",
    "wof:placetype":"locality"
},
  "geometry": {"coordinates":[8.0845,4.627],"type":"Point"}
}