{
  "type": "Feature",
  "properties": {
    "gn:admin1_code":"24.0",
    "gn:admin2_code":"409.0",
    "gn:admin3_code":"40910",
    "gn:asciiname":"Shaya",
    "gn:country_code":"NG",
    "gn:dem":545,
    "gn:feature_class":"P",
    "gn:feature_code":"PPL",
    "gn:name":"Shaya",
    "gn:population":0,
    "gn:timezone":"Africa/Lagos",
    "iso:country":"NG",
    "wof:name":"Shaya",
    "wof:placetype":"locality"
},
  "geometry": {"coordinates":[7.48644,12.17573],"type":"Point"}
}