{
  "type": "Feature",
  "properties": {
    "gn:admin1_code":"21.0",
    "gn:admin2_code":"3012.0",
    "gn:asciiname":"Etip Ediene",
    "gn:country_code":"NG",
    "gn:dem":88,
    "gn:feature_class":"P",
    "gn:feature_code":"PPL",
    "gn:name":"Etip Ediene",
    "gn:population":0,
    "gn:timezone":"Africa/Lagos",
    "iso:country":"NG",
    "wof:name":"Etip Ediene",
    "wof:placetype":"locality"
},
  "geometry": {"coordinates":[7.80101,5.191],"type":"Point"}
}