{
  "type": "Feature",
  "properties": {
    "gn:admin1_code":"44.0",
    "gn:admin2_code":"705.0",
    "gn:admin3_code":"70512",
    "gn:asciiname":"Katatuwal",
    "gn:country_code":"NG",
    "gn:dem":369,
    "gn:feature_class":"P",
    "gn:feature_code":"PPL",
    "gn:name":"Katatuwal",
    "gn:population":0,
    "gn:timezone":"Africa/Lagos",
    "iso:country":"NG",
    "wof:name":"Katatuwal",
    "wof:placetype":"locality"
},
  "geometry": {"coordinates":[11.46952,11.96188],"type":"Point"}
}