{
  "type": "Feature",
  "properties": {
    "gn:admin1_code":"26.0",
    "gn:admin2_code":"7021",
    "gn:asciiname":"Tse Akanga",
    "gn:country_code":"NG",
    "gn:dem":145,
    "gn:feature_class":"P",
    "gn:feature_code":"PPL",
    "gn:name":"Tse Akanga",
    "gn:population":0,
    "gn:timezone":"Africa/Lagos",
    "iso:country":"NG",
    "wof:name":"Tse Akanga",
    "wof:placetype":"locality"
},
  "geometry": {"coordinates":[9.51261,7.73649],"type":"Point"}
}