{
  "type": "Feature",
  "properties": {
    "gn:admin1_code":"52.0",
    "gn:asciiname":"Sesumogbene",
    "gn:country_code":"NG",
    "gn:dem":7,
    "gn:feature_class":"P",
    "gn:feature_code":"PPL",
    "gn:name":"Sesumogbene",
    "gn:population":0,
    "gn:timezone":"Africa/Lagos",
    "iso:country":"NG",
    "name:eng_x_preferred":[
        "Sesumogbene"
    ],
    "wof:name":"Sesumogbene",
    "wof:placetype":"locality"
},
  "geometry": {"coordinates":[5.80693,4.61765],"type":"Point"}
}