{
  "type": "Feature",
  "properties": {
    "gn:admin1_code":"55.0",
    "gn:admin2_code":"16008.0",
    "gn:asciiname":"Gafara",
    "gn:country_code":"NG",
    "gn:dem":278,
    "gn:feature_class":"P",
    "gn:feature_code":"PPL",
    "gn:name":"Gafara",
    "gn:population":0,
    "gn:timezone":"Africa/Lagos",
    "iso:country":"NG",
    "wof:name":"Gafara",
    "wof:placetype":"locality"
},
  "geometry": {"coordinates":[11.42297,10.61283],"type":"Point"}
}