{
  "type": "Feature",
  "properties": {
    "gn:admin1_code":"27.0",
    "gn:admin2_code":"112.0",
    "gn:admin3_code":"11209",
    "gn:asciiname":"Posura",
    "gn:country_code":"NG",
    "gn:dem":335,
    "gn:feature_class":"P",
    "gn:feature_code":"PPL",
    "gn:name":"Posura",
    "gn:population":0,
    "gn:timezone":"Africa/Lagos",
    "iso:country":"NG",
    "wof:name":"Posura",
    "wof:placetype":"locality"
},
  "geometry": {"coordinates":[12.19445,10.41733],"type":"Point"}
}