{
  "type": "Feature",
  "properties": {
    "gn:admin1_code":"57.0",
    "gn:admin2_code":"810.0",
    "gn:admin3_code":"81005",
    "gn:asciiname":"Han-Han",
    "gn:country_code":"NG",
    "gn:dem":508,
    "gn:feature_class":"P",
    "gn:feature_code":"PPL",
    "gn:name":"Han-Han",
    "gn:population":0,
    "gn:timezone":"Africa/Lagos",
    "iso:country":"NG",
    "wof:name":"Han-Han",
    "wof:placetype":"locality"
},
  "geometry": {"coordinates":[6.45997,11.4036],"type":"Point"}
}