{
  "type": "Feature",
  "properties": {
    "gn:admin1_code":"27.0",
    "gn:admin2_code":"122.0",
    "gn:admin3_code":"12206",
    "gn:asciiname":"Barre",
    "gn:country_code":"NG",
    "gn:dem":305,
    "gn:feature_class":"P",
    "gn:feature_code":"PPL",
    "gn:name":"Barre",
    "gn:population":0,
    "gn:timezone":"Africa/Lagos",
    "iso:country":"NG",
    "wof:name":"Barre",
    "wof:placetype":"locality"
},
  "geometry": {"coordinates":[12.7906,13.2703],"type":"Point"}
}