{
  "type": "Feature",
  "properties": {
    "gn:admin1_code":"27.0",
    "gn:admin2_code":"102.0",
    "gn:admin3_code":"10208",
    "gn:asciiname":"Wawataku",
    "gn:country_code":"NG",
    "gn:dem":490,
    "gn:feature_class":"P",
    "gn:feature_code":"PPL",
    "gn:name":"Wawataku",
    "gn:population":0,
    "gn:timezone":"Africa/Lagos",
    "iso:country":"NG",
    "wof:name":"Wawataku",
    "wof:placetype":"locality"
},
  "geometry": {"coordinates":[12.51822,10.66281],"type":"Point"}
}