{
  "type": "Feature",
  "properties": {
    "gn:admin1_code":"29.0",
    "gn:asciiname":"Dundubus",
    "gn:country_code":"NG",
    "gn:dem":432,
    "gn:feature_class":"P",
    "gn:feature_code":"PPL",
    "gn:name":"Dundubus",
    "gn:population":0,
    "gn:timezone":"Africa/Lagos",
    "iso:country":"NG",
    "name:und_x_variant":[
        "Dundubis",
        "Dundubus"
    ],
    "wof:name":"Dundubus",
    "wof:placetype":"locality"
},
  "geometry": {"coordinates":[9.19717,11.8458],"type":"Point"}
}