{
  "type": "Feature",
  "properties": {
    "gn:admin1_code":"57.0",
    "gn:admin2_code":"809.0",
    "gn:admin3_code":"80902",
    "gn:asciiname":"Dambaza",
    "gn:country_code":"NG",
    "gn:dem":346,
    "gn:feature_class":"P",
    "gn:feature_code":"PPL",
    "gn:name":"Dambaza",
    "gn:population":0,
    "gn:timezone":"Africa/Lagos",
    "iso:country":"NG",
    "wof:name":"Dambaza",
    "wof:placetype":"locality"
},
  "geometry": {"coordinates":[6.16039,12.49035],"type":"Point"}
}