{
  "type": "Feature",
  "properties": {
    "gn:admin1_code":"44.0",
    "gn:admin2_code":"710.0",
    "gn:admin3_code":"71007",
    "gn:asciiname":"Asto",
    "gn:country_code":"NG",
    "gn:dem":347,
    "gn:feature_class":"P",
    "gn:feature_code":"PPL",
    "gn:name":"Asto",
    "gn:population":0,
    "gn:timezone":"Africa/Lagos",
    "iso:country":"NG",
    "wof:name":"Asto",
    "wof:placetype":"locality"
},
  "geometry": {"coordinates":[10.63701,12.91755],"type":"Point"}
}