{
  "type": "Feature",
  "properties": {
    "gn:admin1_code":"27.0",
    "gn:admin2_code":"112.0",
    "gn:admin3_code":"11207",
    "gn:asciiname":"Pashi",
    "gn:country_code":"NG",
    "gn:dem":693,
    "gn:feature_class":"P",
    "gn:feature_code":"PPL",
    "gn:name":"Pashi",
    "gn:population":0,
    "gn:timezone":"Africa/Lagos",
    "iso:country":"NG",
    "wof:name":"Pashi",
    "wof:placetype":"locality"
},
  "geometry": {"coordinates":[12.11115,10.48186],"type":"Point"}
}