{
  "type": "Feature",
  "properties": {
    "gn:admin1_code":"22.0",
    "gn:admin2_code":"9006.0",
    "gn:asciiname":"Biakpan Beach",
    "gn:country_code":"NG",
    "gn:dem":10,
    "gn:feature_class":"P",
    "gn:feature_code":"PPL",
    "gn:name":"Biakpan Beach",
    "gn:population":0,
    "gn:timezone":"Africa/Lagos",
    "iso:country":"NG",
    "name:und_x_variant":[
        "Biakpai Beach",
        "Biakpaii Beach",
        "Biakpan Beach"
    ],
    "wof:name":"Biakpan Beach",
    "wof:placetype":"locality"
},
  "geometry": {"coordinates":[7.99467,5.5689],"type":"Point"}
}