{
  "type": "Feature",
  "properties": {
    "gn:admin1_code":"39.0",
    "gn:admin2_code":"18019.0",
    "gn:admin3_code":"JI2705",
    "gn:asciiname":"Jama'a Malamai",
    "gn:country_code":"NG",
    "gn:dem":480,
    "gn:feature_class":"P",
    "gn:feature_code":"PPL",
    "gn:name":"Jama\u2019a Malamai",
    "gn:population":0,
    "gn:timezone":"Africa/Lagos",
    "iso:country":"NG",
    "wof:name":"Jama'a Malamai",
    "wof:placetype":"locality"
},
  "geometry": {"coordinates":[8.51352,12.79528],"type":"Point"}
}