{
  "type": "Feature",
  "properties": {
    "gn:admin1_code":"39.0",
    "gn:admin2_code":"18014.0",
    "gn:admin3_code":"JI2202",
    "gn:asciiname":"Garbo",
    "gn:country_code":"NG",
    "gn:dem":370,
    "gn:feature_class":"P",
    "gn:feature_code":"PPL",
    "gn:name":"Garbo",
    "gn:population":0,
    "gn:timezone":"Africa/Lagos",
    "iso:country":"NG",
    "wof:name":"Garbo",
    "wof:placetype":"locality"
},
  "geometry": {"coordinates":[9.76367,12.17488],"type":"Point"}
}