{
  "type": "Feature",
  "properties": {
    "gn:admin1_code":"39.0",
    "gn:admin2_code":"18014.0",
    "gn:admin3_code":"JI2202",
    "gn:asciiname":"Garbo",
    "gn:country_code":"NG",
    "gn:dem":370,
    "gn:feature_class":"P",
    "gn:feature_code":"PPL",
    "gn:name":"Garbo",
    "gn:population":0,
    "gn:timezone":"Africa/Lagos",
    "iso:country":"NG",
    "name:cat_x_preferred":[
        "Garbo"
    ],
    "name:ceb_x_preferred":[
        "Garbo"
    ],
    "name:deu_x_preferred":[
        "Garbo"
    ],
    "name:fin_x_preferred":[
        "Garbo"
    ],
    "name:fra_x_preferred":[
        "Garbo"
    ],
    "name:hun_x_preferred":[
        "Garbo"
    ],
    "name:ita_x_preferred":[
        "Garbo"
    ],
    "name:jpn_x_preferred":[
        "\u30ac\u30eb\u30dc"
    ],
    "name:nds_x_preferred":[
        "Garbo"
    ],
    "name:pol_x_preferred":[
        "Garbo"
    ],
    "name:rus_x_preferred":[
        "\u0413\u0430\u0440\u0431\u043e"
    ],
    "name:spa_x_preferred":[
        "Garbo"
    ],
    "name:swe_x_preferred":[
        "Garbo"
    ],
    "wof:name":"Garbo",
    "wof:placetype":"locality"
},
  "geometry": {"coordinates":[9.76367,12.17488],"type":"Point"}
}