{
  "type": "Feature",
  "properties": {
    "gn:admin1_code":"50.0",
    "gn:admin2_code":"33002.0",
    "gn:asciiname":"Ogbo",
    "gn:country_code":"NG",
    "gn:dem":17,
    "gn:feature_class":"P",
    "gn:feature_code":"PPL",
    "gn:name":"Ogbo",
    "gn:population":0,
    "gn:timezone":"Africa/Lagos",
    "iso:country":"NG",
    "wof:name":"Ogbo",
    "wof:placetype":"locality"
},
  "geometry": {"coordinates":[6.62894,5.13031],"type":"Point"}
}