{
  "type": "Feature",
  "properties": {
    "gn:admin1_code":"40.0",
    "gn:admin2_code":"519.0",
    "gn:admin3_code":"51902",
    "gn:asciiname":"Ungwa Boye",
    "gn:country_code":"NG",
    "gn:dem":466,
    "gn:feature_class":"P",
    "gn:feature_code":"PPL",
    "gn:name":"Ungwa Boye",
    "gn:population":0,
    "gn:timezone":"Africa/Lagos",
    "iso:country":"NG",
    "wof:name":"Ungwa Boye",
    "wof:placetype":"locality"
},
  "geometry": {"coordinates":[6.0004,11.23915],"type":"Point"}
}