{
  "type": "Feature",
  "properties": {
    "gn:admin1_code":"37.0",
    "gn:admin2_code":"12018.0",
    "gn:asciiname":"Evbuohuan",
    "gn:country_code":"NG",
    "gn:dem":153,
    "gn:feature_class":"P",
    "gn:feature_code":"PPL",
    "gn:name":"Evbuohuan",
    "gn:population":0,
    "gn:timezone":"Africa/Lagos",
    "iso:country":"NG",
    "name:und_x_variant":[
        "Evbouhuan",
        "Evbuohuan"
    ],
    "wof:name":"Evbuohuan",
    "wof:placetype":"locality"
},
  "geometry": {"coordinates":[5.90141,6.42714],"type":"Point"}
}