{
  "type": "Feature",
  "properties": {
    "gn:admin1_code":"46.0",
    "gn:admin2_code":"5005.0",
    "gn:admin3_code":"BA0501",
    "gn:asciiname":"Lafiyaru",
    "gn:country_code":"NG",
    "gn:dem":506,
    "gn:feature_class":"P",
    "gn:feature_code":"PPL",
    "gn:name":"Lafiyaru",
    "gn:population":0,
    "gn:timezone":"Africa/Lagos",
    "iso:country":"NG",
    "name:eng_x_preferred":[
        "Lafiyaru"
    ],
    "wof:name":"Lafiyaru",
    "wof:placetype":"locality"
},
  "geometry": {"coordinates":[10.4371,11.0002],"type":"Point"}
}