{
  "type": "Feature",
  "properties": {
    "gn:admin1_code":"35.0",
    "gn:admin2_code":"2008",
    "gn:asciiname":"Gambakeki",
    "gn:country_code":"NG",
    "gn:dem":486,
    "gn:feature_class":"P",
    "gn:feature_code":"PPL",
    "gn:name":"Gambakeki",
    "gn:population":0,
    "gn:timezone":"Africa/Lagos",
    "iso:country":"NG",
    "wof:name":"Gambakeki",
    "wof:placetype":"locality"
},
  "geometry": {"coordinates":[11.92022,8.67283],"type":"Point"}
}