{
  "type": "Feature",
  "properties": {
    "gn:admin1_code":"51.0",
    "gn:admin2_code":"612.0",
    "gn:admin3_code":"61208",
    "gn:asciiname":"Gawakoke",
    "gn:country_code":"NG",
    "gn:dem":267,
    "gn:feature_class":"P",
    "gn:feature_code":"PPL",
    "gn:name":"Gawakoke",
    "gn:population":0,
    "gn:timezone":"Africa/Lagos",
    "iso:country":"NG",
    "name:und_x_variant":[
        "Gawakuke",
        "Gawakoke"
    ],
    "wof:name":"Gawakoke",
    "wof:placetype":"locality"
},
  "geometry": {"coordinates":[5.40734,13.11292],"type":"Point"}
}