{
  "type": "Feature",
  "properties": {
    "gn:admin1_code":"23.0",
    "gn:admin2_code":"19003.0",
    "gn:admin3_code":"KD0307",
    "gn:asciiname":"Sofon Kazage",
    "gn:country_code":"NG",
    "gn:dem":640,
    "gn:feature_class":"P",
    "gn:feature_code":"PPL",
    "gn:name":"Sofon Kazage",
    "gn:population":0,
    "gn:timezone":"Africa/Lagos",
    "iso:country":"NG",
    "name:und_x_variant":[
        "Sabon Kazage",
        "Sofon Kazage"
    ],
    "wof:name":"Sofon Kazage",
    "wof:placetype":"locality"
},
  "geometry": {"coordinates":[6.98313,11.06259],"type":"Point"}
}