{
  "type": "Feature",
  "properties": {
    "gn:admin1_code":"41.0",
    "gn:admin2_code":"23008.0",
    "gn:asciiname":"Ojiri",
    "gn:country_code":"NG",
    "gn:dem":150,
    "gn:feature_class":"P",
    "gn:feature_code":"PPL",
    "gn:name":"Ojiri",
    "gn:population":0,
    "gn:timezone":"Africa/Lagos",
    "iso:country":"NG",
    "wof:name":"Ojiri",
    "wof:placetype":"locality"
},
  "geometry": {"coordinates":[7.06805,7.18269],"type":"Point"}
}