{
  "type": "Feature",
  "properties": {
    "gn:admin1_code":"39.0",
    "gn:admin2_code":"18027.0",
    "gn:admin3_code":"JI1509",
    "gn:asciiname":"Dummadummi Kyaure",
    "gn:country_code":"NG",
    "gn:dem":373,
    "gn:feature_class":"P",
    "gn:feature_code":"PPL",
    "gn:name":"Dummadummi Kyaure",
    "gn:population":0,
    "gn:timezone":"Africa/Lagos",
    "iso:country":"NG",
    "wof:name":"Dummadummi Kyaure",
    "wof:placetype":"locality"
},
  "geometry": {"coordinates":[9.84024,12.00302],"type":"Point"}
}