{
  "type": "Feature",
  "properties": {
    "gn:admin1_code":"23.0",
    "gn:admin2_code":"19020.0",
    "gn:admin3_code":"KD2009",
    "gn:asciiname":"Abu",
    "gn:country_code":"NG",
    "gn:dem":442,
    "gn:feature_class":"P",
    "gn:feature_code":"PPL",
    "gn:name":"Abu",
    "gn:population":0,
    "gn:timezone":"Africa/Lagos",
    "iso:country":"NG",
    "name:ara_x_preferred":[
        "\u0623\u0628\u0648"
    ],
    "name:aze_x_preferred":[
        "Abu"
    ],
    "name:ceb_x_preferred":[
        "Abu"
    ],
    "name:che_x_preferred":[
        "\u0410\u0431\u0443"
    ],
    "name:dan_x_preferred":[
        "Abu"
    ],
    "name:deu_x_preferred":[
        "Abu"
    ],
    "name:est_x_preferred":[
        "Abu"
    ],
    "name:glg_x_preferred":[
        "Abu"
    ],
    "name:hye_x_preferred":[
        "\u0531\u0562\u0578\u0582"
    ],
    "name:ind_x_preferred":[
        "Abu"
    ],
    "name:jpn_x_preferred":[
        "\u30a2\u30d6"
    ],
    "name:kaz_x_preferred":[
        "\u0410\u0431\u0443"
    ],
    "name:nld_x_preferred":[
        "Abu"
    ],
    "name:pol_x_preferred":[
        "Abu"
    ],
    "name:rus_x_preferred":[
        "\u0410\u0431\u0443"
    ],
    "name:slk_x_preferred":[
        "Abu"
    ],
    "name:slv_x_preferred":[
        "Abu"
    ],
    "name:spa_x_preferred":[
        "Abu"
    ],
    "name:swe_x_preferred":[
        "Abu"
    ],
    "name:ukr_x_preferred":[
        "\u0410\u0431\u0443"
    ],
    "name:uzb_x_preferred":[
        "Abu"
    ],
    "wof:name":"Abu",
    "wof:placetype":"locality"
},
  "geometry": {"coordinates":[8.55414,9.05707],"type":"Point"}
}