{
  "type": "Feature",
  "properties": {
    "gn:admin1_code":"23.0",
    "gn:admin2_code":"19020.0",
    "gn:admin3_code":"KD2009",
    "gn:asciiname":"Abu",
    "gn:country_code":"NG",
    "gn:dem":442,
    "gn:feature_class":"P",
    "gn:feature_code":"PPL",
    "gn:name":"Abu",
    "gn:population":0,
    "gn:timezone":"Africa/Lagos",
    "iso:country":"NG",
    "wof:name":"Abu",
    "wof:placetype":"locality"
},
  "geometry": {"coordinates":[8.55414,9.05707],"type":"Point"}
}