{
  "type": "Feature",
  "properties": {
    "gn:admin1_code":"26.0",
    "gn:admin2_code":"7018.0",
    "gn:asciiname":"Idobe",
    "gn:country_code":"NG",
    "gn:dem":192,
    "gn:feature_class":"P",
    "gn:feature_code":"PPL",
    "gn:name":"Idobe",
    "gn:population":0,
    "gn:timezone":"Africa/Lagos",
    "iso:country":"NG",
    "wof:name":"Idobe",
    "wof:placetype":"locality"
},
  "geometry": {"coordinates":[7.77865,7.02792],"type":"Point"}
}