{
  "type": "Feature",
  "properties": {
    "gn:admin1_code":"36.0",
    "gn:admin2_code":"10020.0",
    "gn:asciiname":"Oforigbala",
    "gn:country_code":"NG",
    "gn:dem":7,
    "gn:feature_class":"P",
    "gn:feature_code":"PPL",
    "gn:name":"Oforigbala",
    "gn:population":0,
    "gn:timezone":"Africa/Lagos",
    "iso:country":"NG",
    "name:und_x_variant":[
        "Ovhorigbata",
        "Oforigbala"
    ],
    "wof:name":"Oforigbala",
    "wof:placetype":"locality"
},
  "geometry": {"coordinates":[5.92797,5.46612],"type":"Point"}
}