{
  "type": "Feature",
  "properties": {
    "gn:admin1_code":"31.0",
    "gn:admin2_code":"27008.0",
    "gn:asciiname":"Twata",
    "gn:country_code":"NG",
    "gn:dem":122,
    "gn:feature_class":"P",
    "gn:feature_code":"PPL",
    "gn:name":"Twata",
    "gn:population":0,
    "gn:timezone":"Africa/Lagos",
    "iso:country":"NG",
    "wof:name":"Twata",
    "wof:placetype":"locality"
},
  "geometry": {"coordinates":[6.09592,9.16334],"type":"Point"}
}