{
  "type": "Feature",
  "properties": {
    "gn:admin1_code":"31.0",
    "gn:admin2_code":"27022",
    "gn:asciiname":"Gidan Kuwlo",
    "gn:country_code":"NG",
    "gn:dem":385,
    "gn:feature_class":"P",
    "gn:feature_code":"PPL",
    "gn:name":"Gidan Kuwlo",
    "gn:population":0,
    "gn:timezone":"Africa/Lagos",
    "iso:country":"NG",
    "wof:name":"Gidan Kuwlo",
    "wof:placetype":"locality"
},
  "geometry": {"coordinates":[6.81587,9.67946],"type":"Point"}
}