{
  "type": "Feature",
  "properties": {
    "gn:admin1_code":"49.0",
    "gn:asciiname":"Wangkum",
    "gn:country_code":"NG",
    "gn:dem":536,
    "gn:feature_class":"P",
    "gn:feature_code":"PPL",
    "gn:name":"Wangkum",
    "gn:population":0,
    "gn:timezone":"Africa/Lagos",
    "iso:country":"NG",
    "wof:name":"Wangkum",
    "wof:placetype":"locality"
},
  "geometry": {"coordinates":[9.2301,8.97303],"type":"Point"}
}