{
  "type": "Feature",
  "properties": {
    "gn:admin1_code":"35.0",
    "gn:admin2_code":"2013.0",
    "gn:asciiname":"Nyibiri",
    "gn:country_code":"NG",
    "gn:dem":661,
    "gn:feature_class":"P",
    "gn:feature_code":"PPL",
    "gn:name":"Nyibiri",
    "gn:population":0,
    "gn:timezone":"Africa/Lagos",
    "iso:country":"NG",
    "name:und_x_variant":[
        "N\u00e9bri",
        "Nyibiri"
    ],
    "wof:name":"Nyibiri",
    "wof:placetype":"locality"
},
  "geometry": {"coordinates":[13.53494,10.60401],"type":"Point"}
}