{
  "type": "Feature",
  "properties": {
    "gn:admin1_code":"40.0",
    "gn:admin2_code":"508.0",
    "gn:admin3_code":"50809",
    "gn:asciiname":"Tungan Ladan",
    "gn:country_code":"NG",
    "gn:dem":159,
    "gn:feature_class":"P",
    "gn:feature_code":"PPL",
    "gn:name":"Tungan Ladan",
    "gn:population":0,
    "gn:timezone":"Africa/Lagos",
    "iso:country":"NG",
    "wof:name":"Tungan Ladan",
    "wof:placetype":"locality"
},
  "geometry": {"coordinates":[3.69735,11.68891],"type":"Point"}
}