{
  "type": "Feature",
  "properties": {
    "gn:admin1_code":"46.0",
    "gn:asciiname":"Zange",
    "gn:country_code":"NG",
    "gn:dem":334,
    "gn:feature_class":"P",
    "gn:feature_code":"PPL",
    "gn:name":"Zange",
    "gn:population":0,
    "gn:timezone":"Africa/Lagos",
    "iso:country":"NG",
    "name:eng_x_preferred":[
        "Zange"
    ],
    "name:eng_x_variant":[
        "Jenge"
    ],
    "wof:name":"Zange",
    "wof:placetype":"locality"
},
  "geometry": {"coordinates":[10.86497,9.74396],"type":"Point"}
}