{
  "type": "Feature",
  "properties": {
    "gn:admin1_code":"5.0",
    "gn:admin2_code":"25007.0",
    "gn:asciiname":"Igbogun",
    "gn:country_code":"NG",
    "gn:dem":3,
    "gn:feature_class":"P",
    "gn:feature_code":"PPL",
    "gn:name":"Igbogun",
    "gn:population":0,
    "gn:timezone":"Africa/Lagos",
    "iso:country":"NG",
    "wof:name":"Igbogun",
    "wof:placetype":"locality"
},
  "geometry": {"coordinates":[4.2692,6.39623],"type":"Point"}
}