{
  "type": "Feature",
  "properties": {
    "gn:admin1_code":"42.0",
    "gn:admin2_code":"30001.0",
    "gn:asciiname":"Araromi Owu",
    "gn:cc2":"NG",
    "gn:country_code":"NG",
    "gn:dem":166,
    "gn:feature_class":"P",
    "gn:feature_code":"PPL",
    "gn:name":"Araromi Owu",
    "gn:population":0,
    "gn:timezone":"Africa/Lagos",
    "iso:country":"NG",
    "name:und_x_variant":[
        "Araromi",
        "Araromi Owu"
    ],
    "wof:name":"Araromi Owu",
    "wof:placetype":"locality"
},
  "geometry": {"coordinates":[4.36667,7.16667],"type":"Point"}
}