{
  "type": "Feature",
  "properties": {
    "gn:admin1_code":"35.0",
    "gn:admin2_code":"2007.0",
    "gn:asciiname":"Dadawoloji",
    "gn:country_code":"NG",
    "gn:dem":510,
    "gn:feature_class":"P",
    "gn:feature_code":"PPL",
    "gn:name":"Dadawoloji",
    "gn:population":0,
    "gn:timezone":"Africa/Lagos",
    "iso:country":"NG",
    "wof:name":"Dadawoloji",
    "wof:placetype":"locality"
},
  "geometry": {"coordinates":[13.12836,10.22341],"type":"Point"}
}