{
  "type": "Feature",
  "properties": {
    "gn:admin1_code":"21.0",
    "gn:admin2_code":"3021.0",
    "gn:asciiname":"Ikot Nko",
    "gn:country_code":"NG",
    "gn:dem":41,
    "gn:feature_class":"P",
    "gn:feature_code":"PPL",
    "gn:name":"Ikot Nko",
    "gn:population":0,
    "gn:timezone":"Africa/Lagos",
    "iso:country":"NG",
    "wof:name":"Ikot Nko",
    "wof:placetype":"locality"
},
  "geometry": {"coordinates":[8.0128,4.745],"type":"Point"}
}