{
  "type": "Feature",
  "properties": {
    "gn:admin1_code":"26.0",
    "gn:admin2_code":"7007",
    "gn:asciiname":"Ungbea",
    "gn:country_code":"NG",
    "gn:dem":100,
    "gn:feature_class":"P",
    "gn:feature_code":"PPL",
    "gn:name":"Ungbea",
    "gn:population":0,
    "gn:timezone":"Africa/Lagos",
    "iso:country":"NG",
    "wof:name":"Ungbea",
    "wof:placetype":"locality"
},
  "geometry": {"coordinates":[8.4017,7.61924],"type":"Point"}
}