{
  "type": "Feature",
  "properties": {
    "gn:admin1_code":"31.0",
    "gn:admin2_code":"27024.0",
    "gn:asciiname":"Kwalada",
    "gn:country_code":"NG",
    "gn:dem":528,
    "gn:feature_class":"P",
    "gn:feature_code":"PPL",
    "gn:name":"Kwalada",
    "gn:population":0,
    "gn:timezone":"Africa/Lagos",
    "iso:country":"NG",
    "wof:name":"Kwalada",
    "wof:placetype":"locality"
},
  "geometry": {"coordinates":[7.28191,9.3276],"type":"Point"}
}