{
  "type": "Feature",
  "properties": {
    "gn:admin1_code":"39.0",
    "gn:asciiname":"Sabon Gari",
    "gn:country_code":"NG",
    "gn:dem":421,
    "gn:feature_class":"P",
    "gn:feature_code":"PPL",
    "gn:name":"Sabon Gari",
    "gn:population":0,
    "gn:timezone":"Africa/Lagos",
    "iso:country":"NG",
    "wof:name":"Sabon Gari",
    "wof:placetype":"locality"
},
  "geometry": {"coordinates":[8.5267,12.58973],"type":"Point"}
}