{
  "type": "Feature",
  "properties": {
    "gn:admin1_code":"23.0",
    "gn:admin2_code":"19015.0",
    "gn:admin3_code":"KD1506",
    "gn:asciiname":"Ungwan Dan Juma",
    "gn:country_code":"NG",
    "gn:dem":613,
    "gn:feature_class":"P",
    "gn:feature_code":"PPL",
    "gn:name":"Ungwan Dan Juma",
    "gn:population":0,
    "gn:timezone":"Africa/Lagos",
    "iso:country":"NG",
    "name:und_x_variant":[
        "Dan Juma",
        "Ungwan Dan Juma"
    ],
    "wof:name":"Ungwan Dan Juma",
    "wof:placetype":"locality"
},
  "geometry": {"coordinates":[8.30974,11.16277],"type":"Point"}
}