{
  "type": "Feature",
  "properties": {
    "gn:admin1_code":"11.0",
    "gn:admin2_code":"15005.0",
    "gn:asciiname":"Kwaita",
    "gn:country_code":"NG",
    "gn:dem":124,
    "gn:feature_class":"P",
    "gn:feature_code":"PPL",
    "gn:name":"Kwaita",
    "gn:population":0,
    "gn:timezone":"Africa/Lagos",
    "iso:country":"NG",
    "wof:name":"Kwaita",
    "wof:placetype":"locality"
},
  "geometry": {"coordinates":[6.96667,8.66667],"type":"Point"}
}