{
  "type": "Feature",
  "properties": {
    "gn:admin1_code":"39.0",
    "gn:admin2_code":"18012.0",
    "gn:admin3_code":"JI0604",
    "gn:asciiname":"Duru",
    "gn:country_code":"NG",
    "gn:dem":405,
    "gn:feature_class":"P",
    "gn:feature_code":"PPL",
    "gn:name":"Duru",
    "gn:population":0,
    "gn:timezone":"Africa/Lagos",
    "iso:country":"NG",
    "name:ita_x_preferred":[
        "Duru"
    ],
    "name:swa_x_preferred":[
        "Duru"
    ],
    "wof:name":"Duru",
    "wof:placetype":"locality"
},
  "geometry": {"coordinates":[9.2601,11.84924],"type":"Point"}
}