{
  "type": "Feature",
  "properties": {
    "gn:admin1_code":"29.0",
    "gn:admin2_code":"20010.0",
    "gn:admin3_code":"KN1709",
    "gn:asciiname":"Rimi",
    "gn:country_code":"NG",
    "gn:dem":441,
    "gn:feature_class":"P",
    "gn:feature_code":"PPL",
    "gn:name":"Rimi",
    "gn:population":0,
    "gn:timezone":"Africa/Lagos",
    "iso:country":"NG",
    "name:ceb_x_preferred":[
        "Rimi"
    ],
    "name:deu_x_preferred":[
        "Rimi"
    ],
    "name:ita_x_preferred":[
        "Rimi"
    ],
    "name:swe_x_preferred":[
        "Rimi"
    ],
    "wof:name":"Rimi",
    "wof:placetype":"locality"
},
  "geometry": {"coordinates":[8.77879,11.99978],"type":"Point"}
}