{
  "type": "Feature",
  "properties": {
    "gn:admin1_code":"35.0",
    "gn:asciiname":"Dembiri",
    "gn:country_code":"NG",
    "gn:dem":250,
    "gn:feature_class":"P",
    "gn:feature_code":"PPL",
    "gn:name":"Dembiri",
    "gn:population":0,
    "gn:timezone":"Africa/Lagos",
    "iso:country":"NG",
    "name:eng_x_preferred":[
        "Dembiri"
    ],
    "wof:name":"Dembiri",
    "wof:placetype":"locality"
},
  "geometry": {"coordinates":[12.3154,9.02301],"type":"Point"}
}