{
  "type": "Feature",
  "properties": {
    "gn:admin1_code":"50.0",
    "gn:admin2_code":"33015.0",
    "gn:asciiname":"Rumukoroshe",
    "gn:country_code":"NG",
    "gn:dem":21,
    "gn:feature_class":"P",
    "gn:feature_code":"PPL",
    "gn:name":"Rumukoroshe",
    "gn:population":0,
    "gn:timezone":"Africa/Lagos",
    "iso:country":"NG",
    "name:und_x_variant":[
        "Umukoroshe",
        "Rumuokwurusi",
        "Umu Kososhe",
        "Rumukoroshe"
    ],
    "wof:name":"Rumukoroshe",
    "wof:placetype":"locality"
},
  "geometry": {"coordinates":[7.04856,4.85104],"type":"Point"}
}