{
  "type": "Feature",
  "properties": {
    "gn:admin1_code":"43.0",
    "gn:admin2_code":"35001",
    "gn:asciiname":"Dogo",
    "gn:country_code":"NG",
    "gn:dem":152,
    "gn:feature_class":"P",
    "gn:feature_code":"PPL",
    "gn:name":"Dogo",
    "gn:population":0,
    "gn:timezone":"Africa/Lagos",
    "iso:country":"NG",
    "name:ceb_x_preferred":[
        "Dogo"
    ],
    "name:deu_x_preferred":[
        "Dogo"
    ],
    "name:ita_x_preferred":[
        "Dogo"
    ],
    "name:msa_x_preferred":[
        "Dogo"
    ],
    "name:ron_x_preferred":[
        "Dogo"
    ],
    "name:spa_x_preferred":[
        "Dogo"
    ],
    "name:swe_x_preferred":[
        "Dogo"
    ],
    "wof:name":"Dogo",
    "wof:placetype":"locality"
},
  "geometry": {"coordinates":[11.04933,8.74998],"type":"Point"}
}