{
  "type": "Feature",
  "properties": {
    "gn:admin1_code":"36.0",
    "gn:admin2_code":"10012.0",
    "gn:asciiname":"Abbi",
    "gn:country_code":"NG",
    "gn:dem":19,
    "gn:feature_class":"P",
    "gn:feature_code":"PPL",
    "gn:name":"Abbi",
    "gn:population":0,
    "gn:timezone":"Africa/Lagos",
    "iso:country":"NG",
    "wof:name":"Abbi",
    "wof:placetype":"locality"
},
  "geometry": {"coordinates":[6.21247,5.67272],"type":"Point"}
}