{
  "type": "Feature",
  "properties": {
    "gn:admin1_code":"35.0",
    "gn:admin2_code":"2015.0",
    "gn:asciiname":"Begere Duba",
    "gn:country_code":"NG",
    "gn:dem":615,
    "gn:feature_class":"P",
    "gn:feature_code":"PPL",
    "gn:name":"Begere Duba",
    "gn:population":0,
    "gn:timezone":"Africa/Lagos",
    "iso:country":"NG",
    "wof:name":"Begere Duba",
    "wof:placetype":"locality"
},
  "geometry": {"coordinates":[13.36083,10.24803],"type":"Point"}
}