{
  "type": "Feature",
  "properties": {
    "gn:admin1_code":"25.0",
    "gn:admin2_code":"4010",
    "gn:asciiname":"Ugwuagba- Obosi",
    "gn:country_code":"NG",
    "gn:dem":95,
    "gn:feature_class":"P",
    "gn:feature_code":"PPL",
    "gn:name":"Ugwuagba- Obosi",
    "gn:population":0,
    "gn:timezone":"Africa/Lagos",
    "iso:country":"NG",
    "wof:name":"Ugwuagba- Obosi",
    "wof:placetype":"neighbourhood"
},
  "geometry": {"coordinates":[6.81207,6.10341],"type":"Point"}
}