{
  "type": "Feature",
  "properties": {
    "gn:admin1_code":"56.0",
    "gn:admin2_code":"26001.0",
    "gn:asciiname":"Kola",
    "gn:country_code":"NG",
    "gn:dem":466,
    "gn:feature_class":"P",
    "gn:feature_code":"PPL",
    "gn:name":"Kola",
    "gn:population":0,
    "gn:timezone":"Africa/Lagos",
    "iso:country":"NG",
    "name:und_x_variant":[
        "Wanse"
    ],
    "wof:name":"Kola",
    "wof:placetype":"locality"
},
  "geometry": {"coordinates":[8.44441,9.00874],"type":"Point"}
}