{
  "type": "Feature",
  "properties": {
    "gn:admin1_code":"35.0",
    "gn:admin2_code":"2009.0",
    "gn:asciiname":"Tignon",
    "gn:country_code":"NG",
    "gn:dem":137,
    "gn:feature_class":"P",
    "gn:feature_code":"PPL",
    "gn:name":"Tignon",
    "gn:population":0,
    "gn:timezone":"Africa/Lagos",
    "iso:country":"NG",
    "wof:name":"Tignon",
    "wof:placetype":"locality"
},
  "geometry": {"coordinates":[11.68333,9.53333],"type":"Point"}
}