{
  "type": "Feature",
  "properties": {
    "gn:admin1_code":"56.0",
    "gn:admin2_code":"26009.0",
    "gn:asciiname":"Oja",
    "gn:country_code":"NG",
    "gn:dem":99,
    "gn:feature_class":"P",
    "gn:feature_code":"PPL",
    "gn:name":"Oja",
    "gn:population":0,
    "gn:timezone":"Africa/Lagos",
    "iso:country":"NG",
    "name:ceb_x_preferred":[
        "Oja"
    ],
    "name:deu_x_preferred":[
        "Oja"
    ],
    "name:est_x_preferred":[
        "Oja"
    ],
    "name:fra_x_preferred":[
        "Oja"
    ],
    "name:lav_x_preferred":[
        "Oja"
    ],
    "name:nds_x_preferred":[
        "Oja"
    ],
    "name:pol_x_preferred":[
        "Oja"
    ],
    "name:por_x_preferred":[
        "Oja"
    ],
    "name:swe_x_preferred":[
        "Oja"
    ],
    "wof:name":"Oja",
    "wof:placetype":"locality"
},
  "geometry": {"coordinates":[7.88083,8.29611],"type":"Point"}
}