{
  "type": "Feature",
  "properties": {
    "gn:admin1_code":"46.0",
    "gn:admin2_code":"5005.0",
    "gn:admin3_code":"BA0512",
    "gn:asciiname":"Gidan Gwano",
    "gn:country_code":"NG",
    "gn:dem":470,
    "gn:feature_class":"P",
    "gn:feature_code":"PPL",
    "gn:name":"Gidan Gwano",
    "gn:population":0,
    "gn:timezone":"Africa/Lagos",
    "iso:country":"NG",
    "name:eng_x_preferred":[
        "Gidan Gwano"
    ],
    "wof:name":"Gidan Gwano",
    "wof:placetype":"locality"
},
  "geometry": {"coordinates":[10.37296,10.98753],"type":"Point"}
}