{
  "type": "Feature",
  "properties": {
    "gn:admin1_code":"29.0",
    "gn:admin2_code":"20004.0",
    "gn:admin3_code":"KN0108",
    "gn:asciiname":"Kunkurawa",
    "gn:country_code":"NG",
    "gn:dem":425,
    "gn:feature_class":"P",
    "gn:feature_code":"PPL",
    "gn:name":"Kunkurawa",
    "gn:population":0,
    "gn:timezone":"Africa/Lagos",
    "iso:country":"NG",
    "wof:name":"Kunkurawa",
    "wof:placetype":"locality"
},
  "geometry": {"coordinates":[9.06667,11.96667],"type":"Point"}
}