{
  "type": "Feature",
  "properties": {
    "gn:admin1_code":"44.0",
    "gn:admin2_code":"709.0",
    "gn:admin3_code":"70905",
    "gn:asciiname":"Daifa",
    "gn:country_code":"NG",
    "gn:dem":355,
    "gn:feature_class":"P",
    "gn:feature_code":"PPL",
    "gn:name":"Daifa",
    "gn:population":0,
    "gn:timezone":"Africa/Lagos",
    "iso:country":"NG",
    "wof:name":"Daifa",
    "wof:placetype":"locality"
},
  "geometry": {"coordinates":[11.21355,12.35216],"type":"Point"}
}