{
  "type": "Feature",
  "properties": {
    "gn:admin1_code":"32.0",
    "gn:admin2_code":"31002.0",
    "gn:asciiname":"Anilelerin",
    "gn:country_code":"NG",
    "gn:dem":250,
    "gn:feature_class":"P",
    "gn:feature_code":"PPL",
    "gn:name":"Anilelerin",
    "gn:population":0,
    "gn:timezone":"Africa/Lagos",
    "iso:country":"NG",
    "wof:name":"Anilelerin",
    "wof:placetype":"locality"
},
  "geometry": {"coordinates":[3.95333,7.50639],"type":"Point"}
}