{
  "type": "Feature",
  "properties": {
    "gn:admin1_code":"43.0",
    "gn:admin2_code":"35003",
    "gn:asciiname":"Zaka",
    "gn:country_code":"NG",
    "gn:dem":215,
    "gn:feature_class":"P",
    "gn:feature_code":"PPL",
    "gn:name":"Zaka",
    "gn:population":0,
    "gn:timezone":"Africa/Lagos",
    "iso:country":"NG",
    "wof:name":"Zaka",
    "wof:placetype":"locality"
},
  "geometry": {"coordinates":[9.90223,7.61664],"type":"Point"}
}