{
  "type": "Feature",
  "properties": {
    "gn:admin1_code":"51.0",
    "gn:admin2_code":"615.0",
    "gn:admin3_code":"61501",
    "gn:asciiname":"Jeringo",
    "gn:country_code":"NG",
    "gn:dem":243,
    "gn:feature_class":"P",
    "gn:feature_code":"PPL",
    "gn:name":"Jeringo",
    "gn:population":0,
    "gn:timezone":"Africa/Lagos",
    "iso:country":"NG",
    "wof:name":"Jeringo",
    "wof:placetype":"locality"
},
  "geometry": {"coordinates":[4.84473,13.11394],"type":"Point"}
}