{
  "type": "Feature",
  "properties": {
    "gn:admin1_code":"52.0",
    "gn:admin2_code":"6008.0",
    "gn:asciiname":"Agudama",
    "gn:country_code":"NG",
    "gn:dem":16,
    "gn:feature_class":"P",
    "gn:feature_code":"PPL",
    "gn:name":"Agudama",
    "gn:population":0,
    "gn:timezone":"Africa/Lagos",
    "iso:country":"NG",
    "wof:name":"Agudama",
    "wof:placetype":"locality"
},
  "geometry": {"coordinates":[6.36611,4.98139],"type":"Point"}
}