{
  "type": "Feature",
  "properties": {
    "gn:admin1_code":"23.0",
    "gn:admin2_code":"19006.0",
    "gn:admin3_code":"KD0602",
    "gn:asciiname":"Koryas",
    "gn:country_code":"NG",
    "gn:dem":755,
    "gn:feature_class":"P",
    "gn:feature_code":"PPL",
    "gn:name":"Koryas",
    "gn:population":0,
    "gn:timezone":"Africa/Lagos",
    "iso:country":"NG",
    "name:und_x_variant":[
        "Kurya"
    ],
    "wof:name":"Koryas",
    "wof:placetype":"locality"
},
  "geometry": {"coordinates":[8.10832,9.54129],"type":"Point"}
}