{
  "type": "Feature",
  "properties": {
    "gn:admin1_code":"32.0",
    "gn:admin2_code":"31017.0",
    "gn:asciiname":"Budo Ago",
    "gn:country_code":"NG",
    "gn:dem":371,
    "gn:feature_class":"P",
    "gn:feature_code":"PPL",
    "gn:name":"Budo Ago",
    "gn:population":0,
    "gn:timezone":"Africa/Lagos",
    "iso:country":"NG",
    "wof:name":"Budo Ago",
    "wof:placetype":"locality"
},
  "geometry": {"coordinates":[3.51667,8.08333],"type":"Point"}
}