{
  "type": "Feature",
  "properties": {
    "gn:admin1_code":"57.0",
    "gn:asciiname":"Unguwar Tabkin Fili",
    "gn:country_code":"NG",
    "gn:dem":344,
    "gn:feature_class":"P",
    "gn:feature_code":"PPL",
    "gn:name":"Unguwar Tabkin Fili",
    "gn:population":0,
    "gn:timezone":"Africa/Lagos",
    "iso:country":"NG",
    "name:und_x_variant":[
        "Ungwan Tabkin Fili",
        "Unguwar Tabkin Fili"
    ],
    "wof:name":"Unguwar Tabkin Fili",
    "wof:placetype":"locality"
},
  "geometry": {"coordinates":[6.70033,13.29858],"type":"Point"}
}