{
  "type": "Feature",
  "properties": {
    "gn:admin1_code":"5.0",
    "gn:admin2_code":"25003.0",
    "gn:asciiname":"Mosan",
    "gn:country_code":"NG",
    "gn:dem":38,
    "gn:feature_class":"P",
    "gn:feature_code":"PPL",
    "gn:name":"Mosan",
    "gn:population":0,
    "gn:timezone":"Africa/Lagos",
    "iso:country":"NG",
    "name:ceb_x_preferred":[
        "Mosan"
    ],
    "name:swe_x_preferred":[
        "Mosan"
    ],
    "wof:name":"Mosan",
    "wof:placetype":"neighbourhood"
},
  "geometry": {"coordinates":[3.27722,6.61194],"type":"Point"}
}