{
  "type": "Feature",
  "properties": {
    "gn:admin1_code":"53.0",
    "gn:admin2_code":"11001.0",
    "gn:asciiname":"Ndi-Udara",
    "gn:country_code":"NG",
    "gn:dem":51,
    "gn:feature_class":"P",
    "gn:feature_code":"PPL",
    "gn:name":"Ndi-Udara",
    "gn:population":0,
    "gn:timezone":"Africa/Lagos",
    "iso:country":"NG",
    "wof:name":"Ndi-Udara",
    "wof:placetype":"locality"
},
  "geometry": {"coordinates":[8.20291,6.2978],"type":"Point"}
}