{
  "type": "Feature",
  "properties": {
    "gn:admin1_code":"39.0",
    "gn:admin2_code":"18004.0",
    "gn:admin3_code":"JI0203",
    "gn:asciiname":"Sabon Gari Dan Dinyan",
    "gn:country_code":"NG",
    "gn:dem":400,
    "gn:feature_class":"P",
    "gn:feature_code":"PPL",
    "gn:name":"Sabon Gari Dan Dinyan",
    "gn:population":0,
    "gn:timezone":"Africa/Lagos",
    "iso:country":"NG",
    "wof:name":"Sabon Gari Dan Dinyan",
    "wof:placetype":"locality"
},
  "geometry": {"coordinates":[8.81425,12.53113],"type":"Point"}
}