{
  "type": "Feature",
  "properties": {
    "gn:admin1_code":"22.0",
    "gn:admin2_code":"9011.0",
    "gn:asciiname":"Itekpe",
    "gn:country_code":"NG",
    "gn:dem":134,
    "gn:feature_class":"P",
    "gn:feature_code":"PPL",
    "gn:name":"Itekpe",
    "gn:population":0,
    "gn:timezone":"Africa/Lagos",
    "iso:country":"NG",
    "wof:name":"Itekpe",
    "wof:placetype":"locality"
},
  "geometry": {"coordinates":[8.73808,6.33403],"type":"Point"}
}