{
  "type": "Feature",
  "properties": {
    "gn:admin1_code":"50.0",
    "gn:asciiname":"Bonny-Owuwukiri",
    "gn:country_code":"NG",
    "gn:dem":399,
    "gn:feature_class":"P",
    "gn:feature_code":"PPL",
    "gn:name":"Bonny-Owuwukiri",
    "gn:population":0,
    "gn:timezone":"Africa/Lagos",
    "iso:country":"NG",
    "wof:name":"Bonny-Owuwukiri",
    "wof:placetype":"locality"
},
  "geometry": {"coordinates":[7.2393,4.55888],"type":"Point"}
}