{
  "type": "Feature",
  "properties": {
    "gn:admin1_code":"29.0",
    "gn:admin2_code":"20032.0",
    "gn:admin3_code":"KN3410",
    "gn:asciiname":"Dayi",
    "gn:country_code":"NG",
    "gn:dem":529,
    "gn:feature_class":"P",
    "gn:feature_code":"PPL",
    "gn:name":"Dayi",
    "gn:population":0,
    "gn:timezone":"Africa/Lagos",
    "iso:country":"NG",
    "name:ceb_x_preferred":[
        "Dayi"
    ],
    "name:deu_x_preferred":[
        "Dayi"
    ],
    "name:spa_x_preferred":[
        "Dayi"
    ],
    "name:swe_x_preferred":[
        "Dayi"
    ],
    "wof:name":"Dayi",
    "wof:placetype":"locality"
},
  "geometry": {"coordinates":[7.93333,11.63333],"type":"Point"}
}