{
  "type": "Feature",
  "properties": {
    "gn:admin1_code":"37.0",
    "gn:admin2_code":"12010.0",
    "gn:asciiname":"Obodeko",
    "gn:country_code":"NG",
    "gn:dem":209,
    "gn:feature_class":"P",
    "gn:feature_code":"PPL",
    "gn:name":"Obodeko",
    "gn:population":0,
    "gn:timezone":"Africa/Lagos",
    "iso:country":"NG",
    "name:eng_x_preferred":[
        "Obodeko"
    ],
    "wof:name":"Obodeko",
    "wof:placetype":"locality"
},
  "geometry": {"coordinates":[6.21864,6.4584],"type":"Point"}
}