{
  "type": "Feature",
  "properties": {
    "gn:admin1_code":"27.0",
    "gn:admin2_code":"106.0",
    "gn:admin3_code":"10603",
    "gn:asciiname":"Kwamjilari Kura",
    "gn:country_code":"NG",
    "gn:dem":433,
    "gn:feature_class":"P",
    "gn:feature_code":"PPL",
    "gn:name":"Kwamjilari Kura",
    "gn:population":0,
    "gn:timezone":"Africa/Lagos",
    "iso:country":"NG",
    "wof:name":"Kwamjilari Kura",
    "wof:placetype":"locality"
},
  "geometry": {"coordinates":[13.06643,10.91489],"type":"Point"}
}