{
  "type": "Feature",
  "properties": {
    "gn:admin1_code":"31.0",
    "gn:admin2_code":"27022.0",
    "gn:asciiname":"Gidan Magayaki",
    "gn:country_code":"NG",
    "gn:dem":319,
    "gn:feature_class":"P",
    "gn:feature_code":"PPL",
    "gn:name":"Gidan Magayaki",
    "gn:population":0,
    "gn:timezone":"Africa/Lagos",
    "iso:country":"NG",
    "wof:name":"Gidan Magayaki",
    "wof:placetype":"locality"
},
  "geometry": {"coordinates":[6.58898,10.31984],"type":"Point"}
}