{
  "type": "Feature",
  "properties": {
    "gn:admin1_code":"51.0",
    "gn:admin2_code":"621.0",
    "gn:admin3_code":"62107",
    "gn:asciiname":"Mankeri",
    "gn:country_code":"NG",
    "gn:dem":248,
    "gn:feature_class":"P",
    "gn:feature_code":"PPL",
    "gn:name":"Mankeri",
    "gn:population":0,
    "gn:timezone":"Africa/Lagos",
    "iso:country":"NG",
    "name:und_x_variant":[
        "Mankera",
        "Mankeri"
    ],
    "wof:name":"Mankeri",
    "wof:placetype":"locality"
},
  "geometry": {"coordinates":[5.07429,13.01321],"type":"Point"}
}