{
  "type": "Feature",
  "properties": {
    "gn:admin1_code":"43.0",
    "gn:admin2_code":"35004.0",
    "gn:asciiname":"Betsesere",
    "gn:country_code":"NG",
    "gn:dem":577,
    "gn:feature_class":"P",
    "gn:feature_code":"PPL",
    "gn:name":"Betsesere",
    "gn:population":0,
    "gn:timezone":"Africa/Lagos",
    "iso:country":"NG",
    "wof:name":"Betsesere",
    "wof:placetype":"locality"
},
  "geometry": {"coordinates":[11.38333,7.91667],"type":"Point"}
}