{
  "type": "Feature",
  "properties": {
    "gn:admin1_code":"23.0",
    "gn:admin2_code":"19004.0",
    "gn:admin3_code":"KD0412",
    "gn:asciiname":"Iruga",
    "gn:country_code":"NG",
    "gn:dem":624,
    "gn:feature_class":"P",
    "gn:feature_code":"PPL",
    "gn:name":"Iruga",
    "gn:population":0,
    "gn:timezone":"Africa/Lagos",
    "iso:country":"NG",
    "wof:name":"Iruga",
    "wof:placetype":"locality"
},
  "geometry": {"coordinates":[7.75837,10.95591],"type":"Point"}
}