{
  "type": "Feature",
  "properties": {
    "gn:admin1_code":"24.0",
    "gn:admin2_code":"433.0",
    "gn:admin3_code":"43304",
    "gn:asciiname":"Birji",
    "gn:country_code":"NG",
    "gn:dem":459,
    "gn:feature_class":"P",
    "gn:feature_code":"PPL",
    "gn:name":"Birji",
    "gn:population":0,
    "gn:timezone":"Africa/Lagos",
    "iso:country":"NG",
    "wof:name":"Birji",
    "wof:placetype":"locality"
},
  "geometry": {"coordinates":[8.43545,12.82256],"type":"Point"}
}