{
  "type": "Feature",
  "properties": {
    "gn:admin1_code":"31.0",
    "gn:admin2_code":"27020.0",
    "gn:asciiname":"Tungan Makeri",
    "gn:country_code":"NG",
    "gn:dem":363,
    "gn:elevation":"1380.0",
    "gn:feature_class":"P",
    "gn:feature_code":"PPL",
    "gn:name":"Tungan Makeri",
    "gn:population":0,
    "gn:timezone":"Africa/Lagos",
    "iso:country":"NG",
    "wof:name":"Tungan Makeri",
    "wof:placetype":"locality"
},
  "geometry": {"coordinates":[6.32006,10.31381],"type":"Point"}
}