{
  "type": "Feature",
  "properties": {
    "gn:admin1_code":"54.0",
    "gn:admin2_code":"13015.0",
    "gn:asciiname":"Erinmope Ekiti",
    "gn:cc2":"NG",
    "gn:country_code":"NG",
    "gn:dem":526,
    "gn:feature_class":"P",
    "gn:feature_code":"PPL",
    "gn:name":"Erinmope Ekiti",
    "gn:population":0,
    "gn:timezone":"Africa/Lagos",
    "iso:country":"NG",
    "name:und_x_variant":[
        "Erimope",
        "Erinmope",
        "Erinnope",
        "Erinmope Ekiti"
    ],
    "wof:name":"Erinmope Ekiti",
    "wof:placetype":"locality"
},
  "geometry": {"coordinates":[5.15,8.03333],"type":"Point"}
}