{
  "type": "Feature",
  "properties": {
    "gn:admin1_code":"31.0",
    "gn:admin2_code":"27024.0",
    "gn:asciiname":"Tunga Gwuntu",
    "gn:country_code":"NG",
    "gn:dem":464,
    "gn:feature_class":"P",
    "gn:feature_code":"PPL",
    "gn:name":"Tunga Gwuntu",
    "gn:population":0,
    "gn:timezone":"Africa/Lagos",
    "iso:country":"NG",
    "wof:name":"Tunga Gwuntu",
    "wof:placetype":"locality"
},
  "geometry": {"coordinates":[7.22366,9.21767],"type":"Point"}
}