{
  "type": "Feature",
  "properties": {
    "gn:admin1_code":"57.0",
    "gn:admin2_code":"805.0",
    "gn:admin3_code":"80503",
    "gn:asciiname":"Sabon Gari",
    "gn:country_code":"NG",
    "gn:dem":511,
    "gn:feature_class":"P",
    "gn:feature_code":"PPL",
    "gn:name":"Sabon Gari",
    "gn:population":0,
    "gn:timezone":"Africa/Lagos",
    "iso:country":"NG",
    "name:pol_x_preferred":[
        "Sabon Gari"
    ],
    "wof:name":"Sabon Gari",
    "wof:placetype":"locality"
},
  "geometry": {"coordinates":[6.55492,11.79734],"type":"Point"}
}