{
  "type": "Feature",
  "properties": {
    "gn:admin1_code":"41.0",
    "gn:admin2_code":"23008.0",
    "gn:asciiname":"Akpata-Ebe",
    "gn:country_code":"NG",
    "gn:dem":115,
    "gn:feature_class":"P",
    "gn:feature_code":"PPL",
    "gn:name":"Akpata-Ebe",
    "gn:population":0,
    "gn:timezone":"Africa/Lagos",
    "iso:country":"NG",
    "name:und_x_variant":[
        "Akpatebe",
        "Agbatebe"
    ],
    "wof:name":"Akpata-Ebe",
    "wof:placetype":"locality"
},
  "geometry": {"coordinates":[7.10837,6.8652],"type":"Point"}
}