{
  "type": "Feature",
  "properties": {
    "gn:admin1_code":"43.0",
    "gn:admin2_code":"35009.0",
    "gn:asciiname":"Ambo",
    "gn:country_code":"NG",
    "gn:dem":279,
    "gn:feature_class":"P",
    "gn:feature_code":"PPL",
    "gn:name":"Ambo",
    "gn:population":0,
    "gn:timezone":"Africa/Lagos",
    "iso:country":"NG",
    "name:cat_x_preferred":[
        "Ambo"
    ],
    "name:ceb_x_preferred":[
        "Ambo"
    ],
    "name:deu_x_preferred":[
        "Ambo"
    ],
    "name:fra_x_preferred":[
        "Ambo"
    ],
    "name:ita_x_preferred":[
        "Ambo"
    ],
    "name:nld_x_preferred":[
        "Ambo"
    ],
    "name:pol_x_preferred":[
        "Ambo"
    ],
    "name:spa_x_preferred":[
        "Ambo"
    ],
    "name:swe_x_preferred":[
        "Ambo"
    ],
    "wof:name":"Ambo",
    "wof:placetype":"locality"
},
  "geometry": {"coordinates":[10.76773,7.07592],"type":"Point"}
}