{
  "type": "Feature",
  "properties": {
    "gn:admin1_code":"30.0",
    "gn:admin2_code":"24005.0",
    "gn:asciiname":"Alabe",
    "gn:country_code":"NG",
    "gn:dem":277,
    "gn:feature_class":"P",
    "gn:feature_code":"PPL",
    "gn:name":"Alabe",
    "gn:population":0,
    "gn:timezone":"Africa/Lagos",
    "iso:country":"NG",
    "wof:name":"Alabe",
    "wof:placetype":"locality"
},
  "geometry": {"coordinates":[5.13333,8.48333],"type":"Point"}
}