{
  "type": "Feature",
  "properties": {
    "gn:admin1_code":"51.0",
    "gn:admin2_code":"623.0",
    "gn:admin3_code":"62303",
    "gn:asciiname":"Binjin Muza",
    "gn:country_code":"NG",
    "gn:dem":250,
    "gn:feature_class":"P",
    "gn:feature_code":"PPL",
    "gn:name":"Binjin Muza",
    "gn:population":0,
    "gn:timezone":"Africa/Lagos",
    "iso:country":"NG",
    "wof:name":"Binjin Muza",
    "wof:placetype":"locality"
},
  "geometry": {"coordinates":[4.82831,12.79714],"type":"Point"}
}