{
  "type": "Feature",
  "properties": {
    "gn:admin1_code":"35.0",
    "gn:admin2_code":"2014",
    "gn:asciiname":"Ngabda",
    "gn:country_code":"NG",
    "gn:dem":597,
    "gn:feature_class":"P",
    "gn:feature_code":"PPL",
    "gn:name":"Ngabda",
    "gn:population":0,
    "gn:timezone":"Africa/Lagos",
    "iso:country":"NG",
    "name:eng_x_preferred":[
        "Ngabda"
    ],
    "wof:name":"Ngabda",
    "wof:placetype":"locality"
},
  "geometry": {"coordinates":[13.33267,10.26684],"type":"Point"}
}