{
  "type": "Feature",
  "properties": {
    "gn:admin1_code":"50.0",
    "gn:asciiname":"Ogbesu Camp II",
    "gn:country_code":"NG",
    "gn:dem":16,
    "gn:feature_class":"P",
    "gn:feature_code":"PPL",
    "gn:name":"Ogbesu Camp II",
    "gn:population":0,
    "gn:timezone":"Africa/Lagos",
    "iso:country":"NG",
    "wof:name":"Ogbesu Camp II",
    "wof:placetype":"locality"
},
  "geometry": {"coordinates":[6.41676,5.27643],"type":"Point"}
}