{
  "type": "Feature",
  "properties": {
    "gn:admin1_code":"35.0",
    "gn:asciiname":"Gwassala",
    "gn:country_code":"NG",
    "gn:dem":152,
    "gn:feature_class":"P",
    "gn:feature_code":"PPL",
    "gn:name":"Gwassala",
    "gn:population":0,
    "gn:timezone":"Africa/Lagos",
    "iso:country":"NG",
    "name:eng_x_preferred":[
        "Gwassala"
    ],
    "wof:name":"Gwassala",
    "wof:placetype":"locality"
},
  "geometry": {"coordinates":[12.13175,9.49156],"type":"Point"}
}