{
  "type": "Feature",
  "properties": {
    "gn:admin1_code":"21.0",
    "gn:admin2_code":"3011.0",
    "gn:asciiname":"Ikot Akpan Ekwure",
    "gn:country_code":"NG",
    "gn:dem":68,
    "gn:feature_class":"P",
    "gn:feature_code":"PPL",
    "gn:name":"Ikot Akpan Ekwure",
    "gn:population":0,
    "gn:timezone":"Africa/Lagos",
    "iso:country":"NG",
    "wof:name":"Ikot Akpan Ekwure",
    "wof:placetype":"locality"
},
  "geometry": {"coordinates":[7.57768,5.01745],"type":"Point"}
}