{
  "type": "Feature",
  "properties": {
    "gn:admin1_code":"35.0",
    "gn:admin2_code":"2003.0",
    "gn:asciiname":"Arnado Dogo",
    "gn:country_code":"NG",
    "gn:dem":555,
    "gn:feature_class":"P",
    "gn:feature_code":"PPL",
    "gn:name":"Arnado Dogo",
    "gn:population":0,
    "gn:timezone":"Africa/Lagos",
    "iso:country":"NG",
    "wof:name":"Arnado Dogo",
    "wof:placetype":"locality"
},
  "geometry": {"coordinates":[12.03333,8.21667],"type":"Point"}
}