{
  "type": "Feature",
  "properties": {
    "gn:admin1_code":"56.0",
    "gn:admin2_code":"26007.0",
    "gn:asciiname":"Bagaji",
    "gn:country_code":"NG",
    "gn:dem":346,
    "gn:feature_class":"P",
    "gn:feature_code":"PPL",
    "gn:name":"Bagaji",
    "gn:population":0,
    "gn:timezone":"Africa/Lagos",
    "iso:country":"NG",
    "wof:name":"Bagaji",
    "wof:placetype":"locality"
},
  "geometry": {"coordinates":[7.82,8.92556],"type":"Point"}
}