{
  "type": "Feature",
  "properties": {
    "gn:admin1_code":"40.0",
    "gn:admin2_code":"506.0",
    "gn:admin3_code":"50604",
    "gn:asciiname":"Malam",
    "gn:country_code":"NG",
    "gn:dem":205,
    "gn:feature_class":"P",
    "gn:feature_code":"PPL",
    "gn:name":"Malam",
    "gn:population":0,
    "gn:timezone":"Africa/Lagos",
    "iso:country":"NG",
    "wof:name":"Malam",
    "wof:placetype":"locality"
},
  "geometry": {"coordinates":[4.21574,12.56474],"type":"Point"}
}