{
  "type": "Feature",
  "properties": {
    "gn:admin1_code":"27.0",
    "gn:admin2_code":"103",
    "gn:admin3_code":"10312",
    "gn:asciiname":"Bula Gayemaye",
    "gn:country_code":"NG",
    "gn:dem":320,
    "gn:feature_class":"P",
    "gn:feature_code":"PPL",
    "gn:name":"Bula Gayemaye",
    "gn:population":0,
    "gn:timezone":"Africa/Lagos",
    "iso:country":"NG",
    "name:und_x_variant":[
        "Asambye"
    ],
    "wof:name":"Bula Gayemaye",
    "wof:placetype":"locality"
},
  "geometry": {"coordinates":[13.86715,11.42684],"type":"Point"}
}