{
  "type": "Feature",
  "properties": {
    "gn:admin1_code":"55.0",
    "gn:admin2_code":"16004.0",
    "gn:asciiname":"Bokkiru",
    "gn:country_code":"NG",
    "gn:dem":491,
    "gn:feature_class":"P",
    "gn:feature_code":"PPL",
    "gn:name":"Bokkiru",
    "gn:population":0,
    "gn:timezone":"Africa/Lagos",
    "iso:country":"NG",
    "name:eng_x_preferred":[
        "Bokkiru"
    ],
    "wof:name":"Bokkiru",
    "wof:placetype":"locality"
},
  "geometry": {"coordinates":[10.96383,10.40941],"type":"Point"}
}