{
  "type": "Feature",
  "properties": {
    "gn:admin1_code":"27.0",
    "gn:admin2_code":"111.0",
    "gn:admin3_code":"11110",
    "gn:asciiname":"Tulu Watuya",
    "gn:country_code":"NG",
    "gn:dem":1043,
    "gn:feature_class":"P",
    "gn:feature_code":"PPL",
    "gn:name":"Tulu Watuya",
    "gn:population":0,
    "gn:timezone":"Africa/Lagos",
    "iso:country":"NG",
    "wof:name":"Tulu Watuya",
    "wof:placetype":"locality"
},
  "geometry": {"coordinates":[13.73102,10.92488],"type":"Point"}
}