{
  "type": "Feature",
  "properties": {
    "gn:admin1_code":"23.0",
    "gn:asciiname":"Unguwan Lato",
    "gn:country_code":"NG",
    "gn:dem":581,
    "gn:feature_class":"P",
    "gn:feature_code":"PPL",
    "gn:name":"Unguwan Lato",
    "gn:population":0,
    "gn:timezone":"Africa/Lagos",
    "iso:country":"NG",
    "wof:name":"Unguwan Lato",
    "wof:placetype":"locality"
},
  "geometry": {"coordinates":[8.7666,11.38799],"type":"Point"}
}