{
  "type": "Feature",
  "properties": {
    "gn:admin1_code":"46.0",
    "gn:admin2_code":"5015.0",
    "gn:admin3_code":"BA1514",
    "gn:asciiname":"Kyeta",
    "gn:country_code":"NG",
    "gn:dem":666,
    "gn:feature_class":"P",
    "gn:feature_code":"PPL",
    "gn:name":"Kyeta",
    "gn:population":0,
    "gn:timezone":"Africa/Lagos",
    "iso:country":"NG",
    "name:und_x_variant":[
        "Keta",
        "Kyeta"
    ],
    "wof:name":"Kyeta",
    "wof:placetype":"locality"
},
  "geometry": {"coordinates":[8.90727,10.94864],"type":"Point"}
}