{
  "type": "Feature",
  "properties": {
    "gn:admin1_code":"22.0",
    "gn:admin2_code":"9013.0",
    "gn:asciiname":"Okpechi",
    "gn:country_code":"NG",
    "gn:dem":57,
    "gn:feature_class":"P",
    "gn:feature_code":"PPL",
    "gn:name":"Okpechi",
    "gn:population":0,
    "gn:timezone":"Africa/Lagos",
    "iso:country":"NG",
    "wof:name":"Okpechi",
    "wof:placetype":"locality"
},
  "geometry": {"coordinates":[8.39196,6.06217],"type":"Point"}
}