{
  "type": "Feature",
  "properties": {
    "gn:admin1_code":"49.0",
    "gn:admin2_code":"32006.0",
    "gn:asciiname":"Rafin Bauna",
    "gn:country_code":"NG",
    "gn:dem":1282,
    "gn:feature_class":"P",
    "gn:feature_code":"PPL",
    "gn:name":"Rafin Bauna",
    "gn:population":0,
    "gn:timezone":"Africa/Lagos",
    "iso:country":"NG",
    "wof:name":"Rafin Bauna",
    "wof:placetype":"locality"
},
  "geometry": {"coordinates":[8.82601,9.8681],"type":"Point"}
}