{
  "type": "Feature",
  "properties": {
    "gn:admin1_code":"52.0",
    "gn:admin2_code":"6002.0",
    "gn:asciiname":"Bumianeba",
    "gn:country_code":"NG",
    "gn:dem":3,
    "gn:feature_class":"P",
    "gn:feature_code":"PPL",
    "gn:name":"Bumianeba",
    "gn:population":0,
    "gn:timezone":"Africa/Lagos",
    "iso:country":"NG",
    "name:eng_x_preferred":[
        "Bumianeba"
    ],
    "wof:name":"Bumianeba",
    "wof:placetype":"locality"
},
  "geometry": {"coordinates":[5.64495,4.84903],"type":"Point"}
}