{
  "type": "Feature",
  "properties": {
    "gn:admin1_code":"22.0",
    "gn:admin2_code":"9003.0",
    "gn:asciiname":"Ifeta Beach",
    "gn:country_code":"NG",
    "gn:dem":34,
    "gn:feature_class":"P",
    "gn:feature_code":"PPL",
    "gn:name":"Ifeta Beach",
    "gn:population":0,
    "gn:timezone":"Africa/Lagos",
    "iso:country":"NG",
    "name:und_x_variant":[
        "Ifeta",
        "Ifeta Beach"
    ],
    "wof:name":"Ifeta Beach",
    "wof:placetype":"locality"
},
  "geometry": {"coordinates":[8.4187,5.07249],"type":"Point"}
}