{
  "type": "Feature",
  "properties": {
    "gn:admin1_code":"26.0",
    "gn:admin2_code":"7008",
    "gn:asciiname":"Ati",
    "gn:country_code":"NG",
    "gn:dem":141,
    "gn:feature_class":"P",
    "gn:feature_code":"PPL",
    "gn:name":"Ati",
    "gn:population":0,
    "gn:timezone":"Africa/Lagos",
    "iso:country":"NG",
    "name:cat_x_preferred":[
        "Ati"
    ],
    "name:ceb_x_preferred":[
        "Ati"
    ],
    "name:deu_x_preferred":[
        "Ati"
    ],
    "name:fin_x_preferred":[
        "Ati"
    ],
    "name:fra_x_preferred":[
        "ATI"
    ],
    "name:jpn_x_preferred":[
        "Ati"
    ],
    "name:nld_x_preferred":[
        "Ati"
    ],
    "name:nor_x_preferred":[
        "Ati"
    ],
    "name:pol_x_preferred":[
        "Ati"
    ],
    "name:por_x_preferred":[
        "Ati"
    ],
    "name:rus_x_preferred":[
        "ATI"
    ],
    "name:spa_x_preferred":[
        "Ati"
    ],
    "wof:name":"Ati",
    "wof:placetype":"locality"
},
  "geometry": {"coordinates":[8.09993,7.6004],"type":"Point"}
}