{
  "type": "Feature",
  "properties": {
    "gn:admin1_code":"36.0",
    "gn:admin2_code":"10009.0",
    "gn:asciiname":"Ewusagba",
    "gn:country_code":"NG",
    "gn:dem":12,
    "gn:feature_class":"P",
    "gn:feature_code":"PPL",
    "gn:name":"Ewusagba",
    "gn:population":0,
    "gn:timezone":"Africa/Lagos",
    "iso:country":"NG",
    "wof:name":"Ewusagba",
    "wof:placetype":"locality"
},
  "geometry": {"coordinates":[6.08248,5.45592],"type":"Point"}
}