{
  "type": "Feature",
  "properties": {
    "gn:admin1_code":"45.0",
    "gn:admin2_code":"1014.0",
    "gn:asciiname":"Umeku",
    "gn:country_code":"NG",
    "gn:dem":37,
    "gn:feature_class":"P",
    "gn:feature_code":"PPL",
    "gn:name":"Umeku",
    "gn:population":0,
    "gn:timezone":"Africa/Lagos",
    "iso:country":"NG",
    "wof:name":"Umeku",
    "wof:placetype":"locality"
},
  "geometry": {"coordinates":[7.30752,4.9261],"type":"Point"}
}