{
  "type": "Feature",
  "properties": {
    "gn:admin1_code":"56.0",
    "gn:admin2_code":"26007.0",
    "gn:asciiname":"Kenye",
    "gn:country_code":"NG",
    "gn:dem":338,
    "gn:feature_class":"P",
    "gn:feature_code":"PPL",
    "gn:name":"Kenye",
    "gn:population":0,
    "gn:timezone":"Africa/Lagos",
    "iso:country":"NG",
    "wof:name":"Kenye",
    "wof:placetype":"locality"
},
  "geometry": {"coordinates":[7.92278,8.92722],"type":"Point"}
}