{
  "type": "Feature",
  "properties": {
    "gn:admin1_code":"35.0",
    "gn:admin2_code":"2003.0",
    "gn:asciiname":"Dayiri",
    "gn:country_code":"NG",
    "gn:dem":544,
    "gn:feature_class":"P",
    "gn:feature_code":"PPL",
    "gn:name":"Dayiri",
    "gn:population":0,
    "gn:timezone":"Africa/Lagos",
    "iso:country":"NG",
    "name:und_x_variant":[
        "Dayeri",
        "Dayiri"
    ],
    "wof:name":"Dayiri",
    "wof:placetype":"locality"
},
  "geometry": {"coordinates":[11.94143,8.5136],"type":"Point"}
}