{
  "type": "Feature",
  "properties": {
    "gn:admin1_code":"31.0",
    "gn:admin2_code":"27020.0",
    "gn:asciiname":"Makuri",
    "gn:country_code":"NG",
    "gn:dem":264,
    "gn:feature_class":"P",
    "gn:feature_code":"PPL",
    "gn:name":"Makuri",
    "gn:population":0,
    "gn:timezone":"Africa/Lagos",
    "iso:country":"NG",
    "name:und_x_variant":[
        "Kakuri",
        "Makuri"
    ],
    "wof:name":"Makuri",
    "wof:placetype":"locality"
},
  "geometry": {"coordinates":[6.45686,10.00839],"type":"Point"}
}