{
  "type": "Feature",
  "properties": {
    "gn:admin1_code":"50.0",
    "gn:admin2_code":"33013.0",
    "gn:asciiname":"Rumu-Ogwu",
    "gn:country_code":"NG",
    "gn:dem":29,
    "gn:feature_class":"P",
    "gn:feature_code":"PPL",
    "gn:name":"Rumu-Ogwu",
    "gn:population":0,
    "gn:timezone":"Africa/Lagos",
    "iso:country":"NG",
    "name:und_x_variant":[
        "Umu-Ogwu"
    ],
    "wof:name":"Rumu-Ogwu",
    "wof:placetype":"locality"
},
  "geometry": {"coordinates":[6.9155,4.99326],"type":"Point"}
}