{
  "type": "Feature",
  "properties": {
    "gn:admin1_code":"26.0",
    "gn:admin2_code":"7009",
    "gn:asciiname":"Tseajia",
    "gn:country_code":"NG",
    "gn:dem":212,
    "gn:feature_class":"P",
    "gn:feature_code":"PPL",
    "gn:name":"Tseajia",
    "gn:population":0,
    "gn:timezone":"Africa/Lagos",
    "iso:country":"NG",
    "wof:name":"Tseajia",
    "wof:placetype":"locality"
},
  "geometry": {"coordinates":[9.47021,7.45717],"type":"Point"}
}