{
  "type": "Feature",
  "properties": {
    "gn:admin1_code":"35.0",
    "gn:admin2_code":"2017.0",
    "gn:asciiname":"Tanga",
    "gn:country_code":"NG",
    "gn:dem":555,
    "gn:feature_class":"P",
    "gn:feature_code":"PPL",
    "gn:name":"Tanga",
    "gn:population":0,
    "gn:timezone":"Africa/Lagos",
    "iso:country":"NG",
    "wof:name":"Tanga",
    "wof:placetype":"locality"
},
  "geometry": {"coordinates":[12.16667,9.96667],"type":"Point"}
}