{
  "type": "Feature",
  "properties": {
    "gn:admin1_code":"36.0",
    "gn:asciiname":"Yokri Egbe",
    "gn:country_code":"NG",
    "gn:dem":10,
    "gn:feature_class":"P",
    "gn:feature_code":"PPL",
    "gn:name":"Yokri Egbe",
    "gn:population":0,
    "gn:timezone":"Africa/Lagos",
    "iso:country":"NG",
    "name:eng_x_preferred":[
        "Yokri Egbe"
    ],
    "wof:name":"Yokri Egbe",
    "wof:placetype":"locality"
},
  "geometry": {"coordinates":[5.30335,5.41488],"type":"Point"}
}