{
  "type": "Feature",
  "properties": {
    "gn:admin1_code":"26.0",
    "gn:admin2_code":"7005",
    "gn:asciiname":"Msenge",
    "gn:country_code":"NG",
    "gn:dem":187,
    "gn:feature_class":"P",
    "gn:feature_code":"PPL",
    "gn:name":"Msenge",
    "gn:population":0,
    "gn:timezone":"Africa/Lagos",
    "iso:country":"NG",
    "wof:name":"Msenge",
    "wof:placetype":"locality"
},
  "geometry": {"coordinates":[9.00611,7.26439],"type":"Point"}
}