{
  "type": "Feature",
  "properties": {
    "gn:admin1_code":"21.0",
    "gn:admin2_code":"3018.0",
    "gn:asciiname":"Ibiaku Esa Ekpo",
    "gn:country_code":"NG",
    "gn:dem":30,
    "gn:feature_class":"P",
    "gn:feature_code":"PPL",
    "gn:name":"Ibiaku Esa Ekpo",
    "gn:population":0,
    "gn:timezone":"Africa/Lagos",
    "iso:country":"NG",
    "wof:name":"Ibiaku Esa Ekpo",
    "wof:placetype":"locality"
},
  "geometry": {"coordinates":[7.78273,4.70113],"type":"Point"}
}