{
  "type": "Feature",
  "properties": {
    "gn:admin1_code":"35.0",
    "gn:admin2_code":"2017.0",
    "gn:asciiname":"Jilim",
    "gn:country_code":"NG",
    "gn:dem":537,
    "gn:feature_class":"P",
    "gn:feature_code":"PPL",
    "gn:name":"Jilim",
    "gn:population":0,
    "gn:timezone":"Africa/Lagos",
    "iso:country":"NG",
    "wof:name":"Jilim",
    "wof:placetype":"locality"
},
  "geometry": {"coordinates":[12.17276,10.16052],"type":"Point"}
}