{
  "type": "Feature",
  "properties": {
    "gn:admin1_code":"28.0",
    "gn:admin2_code":"17012.0",
    "gn:asciiname":"Umuonhie",
    "gn:country_code":"NG",
    "gn:dem":65,
    "gn:feature_class":"P",
    "gn:feature_code":"PPL",
    "gn:name":"Umuonhie",
    "gn:population":0,
    "gn:timezone":"Africa/Lagos",
    "iso:country":"NG",
    "wof:name":"Umuonhie",
    "wof:placetype":"locality"
},
  "geometry": {"coordinates":[7.17889,5.3093],"type":"Point"}
}