{
  "type": "Feature",
  "properties": {
    "gn:admin1_code":"27.0",
    "gn:admin2_code":"127.0",
    "gn:admin3_code":"12707",
    "gn:asciiname":"Bulu",
    "gn:country_code":"NG",
    "gn:dem":203,
    "gn:feature_class":"P",
    "gn:feature_code":"PPL",
    "gn:name":"Bulu",
    "gn:population":0,
    "gn:timezone":"Africa/Lagos",
    "iso:country":"NG",
    "name:ceb_x_preferred":[
        "Bulu"
    ],
    "name:deu_x_preferred":[
        "Bulu"
    ],
    "name:fra_x_preferred":[
        "Bulu"
    ],
    "name:ind_x_preferred":[
        "Bulu"
    ],
    "name:ita_x_preferred":[
        "Bulu"
    ],
    "name:nld_x_preferred":[
        "Bulu"
    ],
    "name:srp_x_preferred":[
        "\u0411\u0443\u043b\u0443"
    ],
    "name:swe_x_preferred":[
        "Bulu"
    ],
    "wof:name":"Bulu",
    "wof:placetype":"locality"
},
  "geometry": {"coordinates":[12.0355,10.12804],"type":"Point"}
}