{
  "type": "Feature",
  "properties": {
    "gn:admin1_code":"46.0",
    "gn:admin2_code":"5020",
    "gn:admin3_code":"BA2003",
    "gn:asciiname":"Maikin Tari",
    "gn:country_code":"NG",
    "gn:dem":365,
    "gn:feature_class":"P",
    "gn:feature_code":"PPL",
    "gn:name":"Maikin Tari",
    "gn:population":0,
    "gn:timezone":"Africa/Lagos",
    "iso:country":"NG",
    "wof:name":"Maikin Tari",
    "wof:placetype":"locality"
},
  "geometry": {"coordinates":[10.25001,12.18664],"type":"Point"}
}