{
  "type": "Feature",
  "properties": {
    "gn:admin1_code":"27.0",
    "gn:asciiname":"Amsaburu",
    "gn:country_code":"NG",
    "gn:dem":293,
    "gn:feature_class":"P",
    "gn:feature_code":"PPL",
    "gn:name":"Amsaburu",
    "gn:population":0,
    "gn:timezone":"Africa/Douala",
    "iso:country":"NG",
    "wof:name":"Amsaburu",
    "wof:placetype":"locality"
},
  "geometry": {"coordinates":[14.4775,12.34499],"type":"Point"}
}