{
  "type": "Feature",
  "properties": {
    "gn:admin1_code":"24.0",
    "gn:admin2_code":"405.0",
    "gn:admin3_code":"40505",
    "gn:asciiname":"Makera",
    "gn:country_code":"NG",
    "gn:dem":508,
    "gn:feature_class":"P",
    "gn:feature_code":"PPL",
    "gn:name":"Makera",
    "gn:population":0,
    "gn:timezone":"Africa/Lagos",
    "iso:country":"NG",
    "wof:name":"Makera",
    "wof:placetype":"locality"
},
  "geometry": {"coordinates":[7.92431,12.65407],"type":"Point"}
}