{
  "type": "Feature",
  "properties": {
    "gn:admin1_code":"35.0",
    "gn:asciiname":"Dampire",
    "gn:country_code":"NG",
    "gn:dem":206,
    "gn:feature_class":"P",
    "gn:feature_code":"PPL",
    "gn:name":"Dampire",
    "gn:population":0,
    "gn:timezone":"Africa/Lagos",
    "iso:country":"NG",
    "name:eng_x_preferred":[
        "Dampire"
    ],
    "wof:name":"Dampire",
    "wof:placetype":"locality"
},
  "geometry": {"coordinates":[12.2213,9.10999],"type":"Point"}
}