{
  "type": "Feature",
  "properties": {
    "gn:admin1_code":"35.0",
    "gn:admin2_code":"2007.0",
    "gn:asciiname":"Kwashafa",
    "gn:country_code":"NG",
    "gn:dem":518,
    "gn:feature_class":"P",
    "gn:feature_code":"PPL",
    "gn:name":"Kwashafa",
    "gn:population":0,
    "gn:timezone":"Africa/Lagos",
    "iso:country":"NG",
    "wof:name":"Kwashafa",
    "wof:placetype":"locality"
},
  "geometry": {"coordinates":[13.0814,10.41602],"type":"Point"}
}