{
  "type": "Feature",
  "properties": {
    "gn:admin1_code":"29.0",
    "gn:admin2_code":"20011.0",
    "gn:admin3_code":"KN3610",
    "gn:asciiname":"Sitti",
    "gn:country_code":"NG",
    "gn:dem":590,
    "gn:feature_class":"P",
    "gn:feature_code":"PPL",
    "gn:name":"Sitti",
    "gn:population":0,
    "gn:timezone":"Africa/Lagos",
    "iso:country":"NG",
    "name:msa_x_preferred":[
        "Sitti Navarro"
    ],
    "name:por_x_preferred":[
        "Sitti Navarro"
    ],
    "name:spa_x_preferred":[
        "Sitti Navarro"
    ],
    "name:tgl_x_preferred":[
        "Sitti Navarro"
    ],
    "wof:name":"Sitti",
    "wof:placetype":"locality"
},
  "geometry": {"coordinates":[8.78279,11.28308],"type":"Point"}
}