{
  "type": "Feature",
  "properties": {
    "gn:admin1_code":"50.0",
    "gn:admin2_code":"33003.0",
    "gn:asciiname":"Akinima",
    "gn:country_code":"NG",
    "gn:dem":5,
    "gn:feature_class":"P",
    "gn:feature_code":"PPLA2",
    "gn:name":"Akinima",
    "gn:population":0,
    "gn:timezone":"Africa/Lagos",
    "iso:country":"NG",
    "wof:name":"Akinima",
    "wof:placetype":"locality"
},
  "geometry": {"coordinates":[6.46633,5.08536],"type":"Point"}
}