{
  "type": "Feature",
  "properties": {
    "gn:admin1_code":"16.0",
    "gn:admin2_code":"28020.0",
    "gn:asciiname":"Erefu",
    "gn:country_code":"NG",
    "gn:dem":46,
    "gn:feature_class":"P",
    "gn:feature_code":"PPL",
    "gn:name":"Erefu",
    "gn:population":0,
    "gn:timezone":"Africa/Lagos",
    "iso:country":"NG",
    "wof:name":"Erefu",
    "wof:placetype":"neighbourhood"
},
  "geometry": {"coordinates":[3.48497,6.72495],"type":"Point"}
}