{
  "type": "Feature",
  "properties": {
    "gn:admin1_code":"28.0",
    "gn:admin2_code":"17009.0",
    "gn:asciiname":"Umuohiri",
    "gn:cc2":"NG",
    "gn:country_code":"NG",
    "gn:dem":134,
    "gn:feature_class":"P",
    "gn:feature_code":"PPL",
    "gn:name":"Umuohiri",
    "gn:population":0,
    "gn:timezone":"Africa/Lagos",
    "iso:country":"NG",
    "name:und_x_variant":[
        "Umuohir",
        "Umuohiri"
    ],
    "wof:name":"Umuohiri",
    "wof:placetype":"locality"
},
  "geometry": {"coordinates":[7.21667,5.73333],"type":"Point"}
}