{
  "type": "Feature",
  "properties": {
    "gn:admin1_code":"23.0",
    "gn:admin2_code":"19014",
    "gn:admin3_code":"KD1401",
    "gn:asciiname":"Kirachi",
    "gn:country_code":"NG",
    "gn:dem":771,
    "gn:feature_class":"P",
    "gn:feature_code":"PPL",
    "gn:name":"Kirachi",
    "gn:population":0,
    "gn:timezone":"Africa/Lagos",
    "iso:country":"NG",
    "wof:name":"Kirachi",
    "wof:placetype":"locality"
},
  "geometry": {"coordinates":[8.47638,9.89626],"type":"Point"}
}