{
  "type": "Feature",
  "properties": {
    "gn:admin1_code":"26.0",
    "gn:admin2_code":"7011.0",
    "gn:asciiname":"Gesa",
    "gn:country_code":"NG",
    "gn:dem":382,
    "gn:feature_class":"P",
    "gn:feature_code":"PPL",
    "gn:name":"Gesa",
    "gn:population":0,
    "gn:timezone":"Africa/Lagos",
    "iso:country":"NG",
    "wof:name":"Gesa",
    "wof:placetype":"locality"
},
  "geometry": {"coordinates":[9.51716,6.58791],"type":"Point"}
}