{
  "type": "Feature",
  "properties": {
    "gn:admin1_code":"36.0",
    "gn:admin2_code":"10006.0",
    "gn:asciiname":"Okueka",
    "gn:country_code":"NG",
    "gn:dem":26,
    "gn:feature_class":"P",
    "gn:feature_code":"PPL",
    "gn:name":"Okueka",
    "gn:population":0,
    "gn:timezone":"Africa/Lagos",
    "iso:country":"NG",
    "name:und_x_variant":[
        "Okweka",
        "Okueka"
    ],
    "wof:name":"Okueka",
    "wof:placetype":"locality"
},
  "geometry": {"coordinates":[5.79413,5.90951],"type":"Point"}
}