{
  "type": "Feature",
  "properties": {
    "gn:admin1_code":"22.0",
    "gn:admin2_code":"9016",
    "gn:asciiname":"Zaria",
    "gn:country_code":"NG",
    "gn:dem":132,
    "gn:feature_class":"P",
    "gn:feature_code":"PPL",
    "gn:name":"Zaria",
    "gn:population":0,
    "gn:timezone":"Africa/Lagos",
    "iso:country":"NG",
    "name:afr_x_preferred":[
        "Zaria"
    ],
    "name:ara_x_preferred":[
        "\u0632\u0627\u0631\u064a\u0627"
    ],
    "name:azb_x_preferred":[
        "\u0632\u0627\u0631\u06cc\u0627"
    ],
    "name:bel_x_preferred":[
        "\u0417\u0430\u0440\u044b\u044f"
    ],
    "name:cat_x_preferred":[
        "Zaria"
    ],
    "name:ces_x_preferred":[
        "Zaria"
    ],
    "name:dan_x_preferred":[
        "Zaria"
    ],
    "name:deu_x_preferred":[
        "Zaria"
    ],
    "name:epo_x_preferred":[
        "Zaria"
    ],
    "name:eus_x_preferred":[
        "Zaria"
    ],
    "name:fas_x_preferred":[
        "\u0632\u0627\u0631\u06cc\u0627"
    ],
    "name:fin_x_preferred":[
        "Zaria"
    ],
    "name:fra_x_preferred":[
        "Zaria"
    ],
    "name:glg_x_preferred":[
        "Zaria"
    ],
    "name:hau_x_preferred":[
        "Zariya"
    ],
    "name:hrv_x_preferred":[
        "Zaria"
    ],
    "name:hun_x_preferred":[
        "Zaria"
    ],
    "name:ita_x_preferred":[
        "Zaria"
    ],
    "name:jpn_x_preferred":[
        "\u30b6\u30ea\u30a2"
    ],
    "name:kor_x_preferred":[
        "\uc790\ub9ac\uc544"
    ],
    "name:lit_x_preferred":[
        "Zarija"
    ],
    "name:mal_x_preferred":[
        "\u0d38\u0d30\u0d3f\u0d2f"
    ],
    "name:nld_x_preferred":[
        "Zaria"
    ],
    "name:nno_x_preferred":[
        "Zaria"
    ],
    "name:pan_x_preferred":[
        "\u0a1c\u0a3c\u0a3e\u0a30\u0a40\u0a06"
    ],
    "name:pol_x_preferred":[
        "Zaria"
    ],
    "name:por_x_preferred":[
        "Zaria"
    ],
    "name:ron_x_preferred":[
        "Zaria"
    ],
    "name:rus_x_preferred":[
        "\u0417\u0430\u0440\u0438\u0430"
    ],
    "name:sco_x_preferred":[
        "Zaria"
    ],
    "name:spa_x_preferred":[
        "Zaria"
    ],
    "name:swe_x_preferred":[
        "Zaria"
    ],
    "name:ukr_x_preferred":[
        "\u0417\u0430\u0440\u0456\u044f"
    ],
    "name:urd_x_preferred":[
        "\u0632\u0627\u0631\u06cc\u0627"
    ],
    "name:vep_x_preferred":[
        "Zaria"
    ],
    "name:war_x_preferred":[
        "Zaria"
    ],
    "name:yor_x_preferred":[
        "Zaria"
    ],
    "name:zho_x_preferred":[
        "\u624e\u91cc\u4e9a"
    ],
    "wof:name":"Zaria",
    "wof:placetype":"locality"
},
  "geometry": {"coordinates":[8.89613,6.53],"type":"Point"}
}