{
  "type": "Feature",
  "properties": {
    "gn:admin1_code":"21.0",
    "gn:admin2_code":"3024.0",
    "gn:asciiname":"Abat",
    "gn:country_code":"NG",
    "gn:dem":23,
    "gn:feature_class":"P",
    "gn:feature_code":"PPLA2",
    "gn:name":"Abat",
    "gn:population":0,
    "gn:timezone":"Africa/Lagos",
    "iso:country":"NG",
    "wof:name":"Abat",
    "wof:placetype":"locality"
},
  "geometry": {"coordinates":[7.86639,4.61712],"type":"Point"}
}