{
  "type": "Feature",
  "properties": {
    "gn:country":"NG",
    "gn:fcode":"PPL",
    "gn:population":7340,
    "iso:country":"NG",
    "name:eng_x_preferred":[
        "Illushi"
    ],
    "qs:name":"Illushi",
    "qs:photos_9r":0,
    "qs:photos_sr":0,
    "qs:pop_sr":"5",
    "wof:name":"Illushi",
    "wof:placetype":"locality",
    "wof:population":7340
},
  "geometry": {"coordinates":[6.63076,6.6667],"type":"Point"}
}