{
  "type": "Feature",
  "properties": {
    "gn:admin1_code":"44.0",
    "gn:admin2_code":"703.0",
    "gn:admin3_code":"70305",
    "gn:asciiname":"Garin Maisaje",
    "gn:country_code":"NG",
    "gn:dem":399,
    "gn:feature_class":"P",
    "gn:feature_code":"PPL",
    "gn:name":"Garin Maisaje",
    "gn:population":0,
    "gn:timezone":"Africa/Lagos",
    "iso:country":"NG",
    "name:und_x_variant":[
        "Garin Maisae",
        "Garin Maisaje"
    ],
    "wof:name":"Garin Maisaje",
    "wof:placetype":"locality"
},
  "geometry": {"coordinates":[11.90893,11.81974],"type":"Point"}
}