{
  "type": "Feature",
  "properties": {
    "gn:admin1_code":"32.0",
    "gn:admin2_code":"31013.0",
    "gn:asciiname":"Fedegbo",
    "gn:country_code":"NG",
    "gn:dem":135,
    "gn:feature_class":"P",
    "gn:feature_code":"PPL",
    "gn:name":"Fedegbo",
    "gn:population":0,
    "gn:timezone":"Africa/Lagos",
    "iso:country":"NG",
    "wof:name":"Fedegbo",
    "wof:placetype":"locality"
},
  "geometry": {"coordinates":[3.13333,7.48333],"type":"Point"}
}