{
  "type": "Feature",
  "properties": {
    "gn:admin1_code":"23.0",
    "gn:admin2_code":"19022",
    "gn:admin3_code":"KD2211",
    "gn:asciiname":"Sako",
    "gn:country_code":"NG",
    "gn:dem":763,
    "gn:feature_class":"P",
    "gn:feature_code":"PPL",
    "gn:name":"Sako",
    "gn:population":0,
    "gn:timezone":"Africa/Lagos",
    "iso:country":"NG",
    "name:ceb_x_preferred":[
        "Sako"
    ],
    "name:deu_x_preferred":[
        "Sako"
    ],
    "name:fra_x_preferred":[
        "Sako"
    ],
    "name:ido_x_preferred":[
        "Sako"
    ],
    "name:nld_x_preferred":[
        "Sako"
    ],
    "name:rus_x_preferred":[
        "\u0421\u0430\u043a\u043e"
    ],
    "name:srp_x_preferred":[
        "\u0421\u0430\u043a\u043e"
    ],
    "name:swe_x_preferred":[
        "Sako"
    ],
    "name:ukr_x_preferred":[
        "\u0421\u0430\u043a\u043e"
    ],
    "wof:name":"Sako",
    "wof:placetype":"locality"
},
  "geometry": {"coordinates":[8.40234,9.88925],"type":"Point"}
}