{
  "type": "Feature",
  "properties": {
    "gn:admin1_code":"26.0",
    "gn:admin2_code":"7019.0",
    "gn:asciiname":"Otada",
    "gn:country_code":"NG",
    "gn:dem":145,
    "gn:feature_class":"P",
    "gn:feature_code":"PPL",
    "gn:name":"Otada",
    "gn:population":0,
    "gn:timezone":"Africa/Lagos",
    "iso:country":"NG",
    "wof:name":"Otada",
    "wof:placetype":"locality"
},
  "geometry": {"coordinates":[8.15393,7.23339],"type":"Point"}
}