{
  "type": "Feature",
  "properties": {
    "gn:admin1_code":"22.0",
    "gn:admin2_code":"9017.0",
    "gn:asciiname":"Ikpalagwa",
    "gn:country_code":"NG",
    "gn:dem":43,
    "gn:feature_class":"P",
    "gn:feature_code":"PPL",
    "gn:name":"Ikpalagwa",
    "gn:population":0,
    "gn:timezone":"Africa/Lagos",
    "iso:country":"NG",
    "wof:name":"Ikpalagwa",
    "wof:placetype":"locality"
},
  "geometry": {"coordinates":[8.11777,5.9348],"type":"Point"}
}