{
  "type": "Feature",
  "properties": {
    "gn:admin1_code":"35.0",
    "gn:admin2_code":"2005.0",
    "gn:asciiname":"Ukushiwura",
    "gn:country_code":"NG",
    "gn:dem":480,
    "gn:feature_class":"P",
    "gn:feature_code":"PPL",
    "gn:name":"Ukushiwura",
    "gn:population":0,
    "gn:timezone":"Africa/Lagos",
    "iso:country":"NG",
    "wof:name":"Ukushiwura",
    "wof:placetype":"locality"
},
  "geometry": {"coordinates":[12.60157,10.13572],"type":"Point"}
}