{
  "type": "Feature",
  "properties": {
    "gn:admin1_code":"27.0",
    "gn:admin2_code":"105.0",
    "gn:admin3_code":"10504",
    "gn:asciiname":"Jimbaru",
    "gn:country_code":"NG",
    "gn:dem":554,
    "gn:feature_class":"P",
    "gn:feature_code":"PPL",
    "gn:name":"Jimbaru",
    "gn:population":0,
    "gn:timezone":"Africa/Lagos",
    "iso:country":"NG",
    "wof:name":"Jimbaru",
    "wof:placetype":"locality"
},
  "geometry": {"coordinates":[11.97802,10.68127],"type":"Point"}
}