{
  "type": "Feature",
  "properties": {
    "gn:admin1_code":"23.0",
    "gn:admin2_code":"19004.0",
    "gn:admin3_code":"KD0411",
    "gn:asciiname":"Ibada",
    "gn:country_code":"NG",
    "gn:dem":656,
    "gn:feature_class":"P",
    "gn:feature_code":"PPL",
    "gn:name":"Ibada",
    "gn:population":0,
    "gn:timezone":"Africa/Lagos",
    "iso:country":"NG",
    "wof:name":"Ibada",
    "wof:placetype":"locality"
},
  "geometry": {"coordinates":[7.66658,10.83297],"type":"Point"}
}