{
  "type": "Feature",
  "properties": {
    "gn:admin1_code":"50.0",
    "gn:admin2_code":"33013.0",
    "gn:asciiname":"Elelele",
    "gn:country_code":"NG",
    "gn:dem":44,
    "gn:feature_class":"P",
    "gn:feature_code":"PPL",
    "gn:name":"Elelele",
    "gn:population":0,
    "gn:timezone":"Africa/Lagos",
    "iso:country":"NG",
    "wof:name":"Elelele",
    "wof:placetype":"locality"
},
  "geometry": {"coordinates":[6.9596,5.08993],"type":"Point"}
}