{
  "type": "Feature",
  "properties": {
    "gn:admin1_code":"31.0",
    "gn:admin2_code":"27011.0",
    "gn:asciiname":"Kagara",
    "gn:country_code":"NG",
    "gn:dem":329,
    "gn:feature_class":"P",
    "gn:feature_code":"PPL",
    "gn:name":"Kagara",
    "gn:population":0,
    "gn:timezone":"Africa/Lagos",
    "iso:country":"NG",
    "name:ceb_x_preferred":[
        "Kagara"
    ],
    "name:swe_x_preferred":[
        "Kagara"
    ],
    "wof:name":"Kagara",
    "wof:placetype":"locality"
},
  "geometry": {"coordinates":[5.38487,10.34697],"type":"Point"}
}