{
  "type": "Feature",
  "properties": {
    "gn:admin1_code":"31.0",
    "gn:admin2_code":"27010.0",
    "gn:asciiname":"Kafa",
    "gn:country_code":"NG",
    "gn:dem":110,
    "gn:feature_class":"P",
    "gn:feature_code":"PPL",
    "gn:name":"Kafa",
    "gn:population":0,
    "gn:timezone":"Africa/Lagos",
    "iso:country":"NG",
    "name:cat_x_preferred":[
        "Kafa"
    ],
    "name:ceb_x_preferred":[
        "Kafa"
    ],
    "name:swe_x_preferred":[
        "Kafa"
    ],
    "name:tur_x_preferred":[
        "Kafa"
    ],
    "wof:name":"Kafa",
    "wof:placetype":"locality"
},
  "geometry": {"coordinates":[6.2505,9.18543],"type":"Point"}
}