{
  "type": "Feature",
  "properties": {
    "gn:admin1_code":"29.0",
    "gn:admin2_code":"20034.0",
    "gn:admin3_code":"KN2409",
    "gn:asciiname":"Kwan Goro",
    "gn:country_code":"NG",
    "gn:dem":552,
    "gn:feature_class":"P",
    "gn:feature_code":"PPL",
    "gn:name":"Kwan Goro",
    "gn:population":0,
    "gn:timezone":"Africa/Lagos",
    "iso:country":"NG",
    "wof:name":"Kwan Goro",
    "wof:placetype":"locality"
},
  "geometry": {"coordinates":[8.12396,11.62522],"type":"Point"}
}