{
  "type": "Feature",
  "properties": {
    "gn:admin1_code":"0.0",
    "gn:asciiname":"Ilara",
    "gn:cc2":"NG",
    "gn:country_code":"NG",
    "gn:dem":189,
    "gn:feature_class":"P",
    "gn:feature_code":"PPL",
    "gn:name":"Ilara",
    "gn:population":0,
    "gn:timezone":"Africa/Lagos",
    "iso:country":"NG",
    "name:und_x_variant":[
        "Illara",
        "Ilara"
    ],
    "wof:name":"Ilara",
    "wof:placetype":"locality"
},
  "geometry": {"coordinates":[2.75,7.41667],"type":"Point"}
}