{
  "type": "Feature",
  "properties": {
    "gn:admin1_code":"27.0",
    "gn:admin2_code":"101",
    "gn:admin3_code":"10102",
    "gn:asciiname":"Malum Bukarti",
    "gn:country_code":"NG",
    "gn:dem":297,
    "gn:feature_class":"P",
    "gn:feature_code":"PPL",
    "gn:name":"Malum Bukarti",
    "gn:population":0,
    "gn:timezone":"Africa/Lagos",
    "iso:country":"NG",
    "wof:name":"Malum Bukarti",
    "wof:placetype":"locality"
},
  "geometry": {"coordinates":[13.25446,13.06241],"type":"Point"}
}