{
  "type": "Feature",
  "properties": {
    "gn:admin1_code":"53.0",
    "gn:admin2_code":"11013.0",
    "gn:asciiname":"Agbabor-Isu",
    "gn:country_code":"NG",
    "gn:dem":90,
    "gn:feature_class":"P",
    "gn:feature_code":"PPL",
    "gn:name":"Agbabor-Isu",
    "gn:population":0,
    "gn:timezone":"Africa/Lagos",
    "iso:country":"NG",
    "name:und_x_variant":[
        "Agbabo",
        "Agbabor-Isu"
    ],
    "wof:name":"Agbabor-Isu",
    "wof:placetype":"locality"
},
  "geometry": {"coordinates":[7.83314,6.16772],"type":"Point"}
}