{
  "type": "Feature",
  "properties": {
    "gn:admin1_code":"5.0",
    "gn:admin2_code":"9485474.0",
    "gn:asciiname":"Ebute-Metta",
    "gn:country_code":"NG",
    "gn:dem":10,
    "gn:feature_class":"P",
    "gn:feature_code":"PPLA2",
    "gn:name":"Ebute-Metta",
    "gn:population":0,
    "gn:timezone":"Africa/Lagos",
    "iso:country":"NG",
    "name:und_x_variant":[
        "Ebute Meta",
        "Ebute-Metta"
    ],
    "name:yor_x_preferred":[
        "Ebute Metta"
    ],
    "wof:name":"Ebute-Metta",
    "wof:placetype":"locality"
},
  "geometry": {"coordinates":[3.38166,6.48799],"type":"Point"}
}