{
  "type": "Feature",
  "properties": {
    "gn:country":"NG",
    "gn:fcode":"PPL",
    "gn:pop":8139,
    "iso:country":"NG",
    "name:eng_x_preferred":[
        "Ngurore"
    ],
    "qs:name":"Ngurore",
    "qs:photos_9r":0,
    "qs:photos_sr":0,
    "qs:pop_sr":"5",
    "wof:name":"Ngurore",
    "wof:placetype":"locality",
    "wof:population":8139
},
  "geometry": {"coordinates":[12.23333,9.28333],"type":"Point"}
}