{
  "type": "Feature",
  "properties": {
    "gn:admin1_code":"36.0",
    "gn:admin2_code":"10011.0",
    "gn:asciiname":"Osi Mili",
    "gn:country_code":"NG",
    "gn:dem":16,
    "gn:feature_class":"P",
    "gn:feature_code":"PPL",
    "gn:name":"Osi Mili",
    "gn:population":0,
    "gn:timezone":"Africa/Lagos",
    "iso:country":"NG",
    "wof:name":"Osi Mili",
    "wof:placetype":"locality"
},
  "geometry": {"coordinates":[6.69494,5.94262],"type":"Point"}
}