{
  "type": "Feature",
  "properties": {
    "gn:admin1_code":"51.0",
    "gn:admin2_code":"611.0",
    "gn:admin3_code":"61106",
    "gn:asciiname":"Walka",
    "gn:country_code":"NG",
    "gn:dem":298,
    "gn:feature_class":"P",
    "gn:feature_code":"PPL",
    "gn:name":"Walka",
    "gn:population":0,
    "gn:timezone":"Africa/Lagos",
    "iso:country":"NG",
    "name:fra_x_preferred":[
        "Walka"
    ],
    "wof:name":"Walka",
    "wof:placetype":"locality"
},
  "geometry": {"coordinates":[5.45,12.96667],"type":"Point"}
}