{
  "type": "Feature",
  "properties": {
    "gn:admin1_code":"48.0",
    "gn:admin2_code":"29017.0",
    "gn:asciiname":"Falodun",
    "gn:cc2":"NG",
    "gn:country_code":"NG",
    "gn:dem":42,
    "gn:feature_class":"P",
    "gn:feature_code":"PPL",
    "gn:name":"Falodun",
    "gn:population":0,
    "gn:timezone":"Africa/Lagos",
    "iso:country":"NG",
    "name:und_x_variant":[
        "Faloden",
        "Falodun"
    ],
    "wof:name":"Falodun",
    "wof:placetype":"locality"
},
  "geometry": {"coordinates":[5.56667,6.75],"type":"Point"}
}