{
  "type": "Feature",
  "properties": {
    "gn:admin1_code":"16.0",
    "gn:admin2_code":"28001.0",
    "gn:asciiname":"Idiya",
    "gn:country_code":"NG",
    "gn:dem":82,
    "gn:feature_class":"P",
    "gn:feature_code":"PPL",
    "gn:name":"Idiya",
    "gn:population":0,
    "gn:timezone":"Africa/Lagos",
    "iso:country":"NG",
    "wof:name":"Idiya",
    "wof:placetype":"locality"
},
  "geometry": {"coordinates":[3.28333,7.18333],"type":"Point"}
}