{
  "type": "Feature",
  "properties": {
    "gn:admin1_code":"27.0",
    "gn:admin2_code":"103.0",
    "gn:admin3_code":"10313",
    "gn:asciiname":"Garji",
    "gn:country_code":"NG",
    "gn:dem":311,
    "gn:feature_class":"P",
    "gn:feature_code":"PPL",
    "gn:name":"Garji",
    "gn:population":0,
    "gn:timezone":"Africa/Lagos",
    "iso:country":"NG",
    "wof:name":"Garji",
    "wof:placetype":"locality"
},
  "geometry": {"coordinates":[14.03333,11.45],"type":"Point"}
}