{
  "type": "Feature",
  "properties": {
    "gn:admin1_code":"23.0",
    "gn:admin2_code":"19007.0",
    "gn:admin3_code":"KD0709",
    "gn:asciiname":"Gakiya",
    "gn:country_code":"NG",
    "gn:dem":721,
    "gn:feature_class":"P",
    "gn:feature_code":"PPL",
    "gn:name":"Gakiya",
    "gn:population":0,
    "gn:timezone":"Africa/Lagos",
    "iso:country":"NG",
    "name:und_x_variant":[
        "Gaskiya"
    ],
    "wof:name":"Gakiya",
    "wof:placetype":"locality"
},
  "geometry": {"coordinates":[8.12472,9.46036],"type":"Point"}
}