{
  "type": "Feature",
  "properties": {
    "gn:admin1_code":"26.0",
    "gn:admin2_code":"7006",
    "gn:asciiname":"Nomsu",
    "gn:country_code":"NG",
    "gn:dem":142,
    "gn:feature_class":"P",
    "gn:feature_code":"PPL",
    "gn:name":"Nomsu",
    "gn:population":0,
    "gn:timezone":"Africa/Lagos",
    "iso:country":"NG",
    "wof:name":"Nomsu",
    "wof:placetype":"locality"
},
  "geometry": {"coordinates":[8.49978,7.89682],"type":"Point"}
}