{
  "type": "Feature",
  "properties": {
    "gn:admin1_code":"24.0",
    "gn:admin2_code":"434.0",
    "gn:admin3_code":"43403",
    "gn:asciiname":"Unguwar Kanya",
    "gn:country_code":"NG",
    "gn:dem":434,
    "gn:feature_class":"P",
    "gn:feature_code":"PPL",
    "gn:name":"Unguwar Kanya",
    "gn:population":0,
    "gn:timezone":"Africa/Lagos",
    "iso:country":"NG",
    "wof:name":"Unguwar Kanya",
    "wof:placetype":"locality"
},
  "geometry": {"coordinates":[8.61582,12.93571],"type":"Point"}
}