{
  "type": "Feature",
  "properties": {
    "gn:admin1_code":"23.0",
    "gn:admin2_code":"19013",
    "gn:admin3_code":"KD1301",
    "gn:asciiname":"Agban",
    "gn:country_code":"NG",
    "gn:dem":786,
    "gn:feature_class":"P",
    "gn:feature_code":"PPL",
    "gn:name":"Agban",
    "gn:population":0,
    "gn:timezone":"Africa/Lagos",
    "iso:country":"NG",
    "wof:name":"Agban",
    "wof:placetype":"locality"
},
  "geometry": {"coordinates":[8.36954,9.58494],"type":"Point"}
}