{
  "type": "Feature",
  "properties": {
    "gn:admin1_code":"44.0",
    "gn:asciiname":"Masakali",
    "gn:country_code":"NG",
    "gn:dem":312,
    "gn:feature_class":"P",
    "gn:feature_code":"PPL",
    "gn:name":"Masakali",
    "gn:population":0,
    "gn:timezone":"Africa/Lagos",
    "iso:country":"NG",
    "wof:name":"Masakali",
    "wof:placetype":"locality"
},
  "geometry": {"coordinates":[12.48695,13.08222],"type":"Point"}
}