{
  "type": "Feature",
  "properties": {
    "gn:admin1_code":"32.0",
    "gn:admin2_code":"31027.0",
    "gn:asciiname":"Abule Soro",
    "gn:country_code":"NG",
    "gn:dem":413,
    "gn:feature_class":"P",
    "gn:feature_code":"PPL",
    "gn:name":"Abule Soro",
    "gn:population":0,
    "gn:timezone":"Africa/Lagos",
    "iso:country":"NG",
    "wof:name":"Abule Soro",
    "wof:placetype":"locality"
},
  "geometry": {"coordinates":[3.78333,8.95],"type":"Point"}
}