{
  "type": "Feature",
  "properties": {
    "gn:admin1_code":"27.0",
    "gn:admin2_code":"112.0",
    "gn:admin3_code":"11208",
    "gn:asciiname":"Azare",
    "gn:country_code":"NG",
    "gn:dem":722,
    "gn:feature_class":"P",
    "gn:feature_code":"PPL",
    "gn:name":"Azare",
    "gn:population":0,
    "gn:timezone":"Africa/Lagos",
    "iso:country":"NG",
    "name:ara_x_preferred":[
        "\u0623\u0632\u0627\u0631\u064a"
    ],
    "name:ben_x_preferred":[
        "\u0986\u099c\u09be\u09b0\u09c7"
    ],
    "name:ceb_x_preferred":[
        "Azare"
    ],
    "name:deu_x_preferred":[
        "Azare"
    ],
    "name:ell_x_preferred":[
        "\u0391\u03b6\u03ac\u03c1\u03b5"
    ],
    "name:fas_x_preferred":[
        "\u0622\u0632\u0627\u0631\u0647"
    ],
    "name:fra_x_preferred":[
        "Azare"
    ],
    "name:heb_x_preferred":[
        "\u05d0\u05d6\u05e8\u05d4"
    ],
    "name:hin_x_preferred":[
        "\u0905\u091c\u093c\u093e\u0930\u0947"
    ],
    "name:hun_x_preferred":[
        "Azare"
    ],
    "name:ind_x_preferred":[
        "Azare"
    ],
    "name:ita_x_preferred":[
        "Azare"
    ],
    "name:kor_x_preferred":[
        "\uc544\uc790\ub808"
    ],
    "name:mlg_x_preferred":[
        "Azare"
    ],
    "name:pol_x_preferred":[
        "Azare"
    ],
    "name:por_x_preferred":[
        "Azare"
    ],
    "name:ron_x_preferred":[
        "Azare"
    ],
    "name:rus_x_preferred":[
        "\u0410\u0437\u0430\u0440\u0435"
    ],
    "name:spa_x_preferred":[
        "Azare"
    ],
    "name:swe_x_preferred":[
        "Azare"
    ],
    "name:tur_x_preferred":[
        "Azare"
    ],
    "name:ukr_x_preferred":[
        "\u0410\u0437\u0430\u0440\u0435"
    ],
    "name:urd_x_preferred":[
        "\u0622\u0632\u0627\u0631\u06d2"
    ],
    "name:vie_x_preferred":[
        "Azare"
    ],
    "name:yor_x_preferred":[
        "Azare"
    ],
    "name:zho_cn_x_preferred":[
        "\u963f\u624e\u96f7"
    ],
    "name:zho_tw_x_preferred":[
        "\u963f\u624e\u96f7"
    ],
    "wof:name":"Azare",
    "wof:placetype":"locality"
},
  "geometry": {"coordinates":[12.11721,10.44247],"type":"Point"}
}