{
  "type": "Feature",
  "properties": {
    "gn:admin1_code":"27.0",
    "gn:admin2_code":"112.0",
    "gn:admin3_code":"11208",
    "gn:asciiname":"Azare",
    "gn:country_code":"NG",
    "gn:dem":722,
    "gn:feature_class":"P",
    "gn:feature_code":"PPL",
    "gn:name":"Azare",
    "gn:population":0,
    "gn:timezone":"Africa/Lagos",
    "iso:country":"NG",
    "wof:name":"Azare",
    "wof:placetype":"locality"
},
  "geometry": {"coordinates":[12.11721,10.44247],"type":"Point"}
}