{
  "type": "Feature",
  "properties": {
    "gn:admin1_code":"16.0",
    "gn:admin2_code":"28016.0",
    "gn:asciiname":"Fami",
    "gn:country_code":"NG",
    "gn:dem":128,
    "gn:feature_class":"P",
    "gn:feature_code":"PPL",
    "gn:name":"Fami",
    "gn:population":0,
    "gn:timezone":"Africa/Lagos",
    "iso:country":"NG",
    "wof:name":"Fami",
    "wof:placetype":"locality"
},
  "geometry": {"coordinates":[3.48333,7.26667],"type":"Point"}
}