{
  "type": "Feature",
  "properties": {
    "gn:admin1_code":"5.0",
    "gn:admin2_code":"25012.0",
    "gn:asciiname":"Ewu Ebi",
    "gn:cc2":"NG",
    "gn:country_code":"NG",
    "gn:dem":5,
    "gn:feature_class":"P",
    "gn:feature_code":"PPL",
    "gn:name":"Ewu Ebi",
    "gn:population":0,
    "gn:timezone":"Africa/Lagos",
    "iso:country":"NG",
    "name:und_x_variant":[
        "Ajebaw",
        "Ewu Ebi"
    ],
    "wof:name":"Ewu Ebi",
    "wof:placetype":"neighbourhood"
},
  "geometry": {"coordinates":[3.51667,6.55],"type":"Point"}
}