{
  "type": "Feature",
  "properties": {
    "gn:admin1_code":"23.0",
    "gn:admin2_code":"19012.0",
    "gn:admin3_code":"KD1210",
    "gn:asciiname":"Kutura",
    "gn:country_code":"NG",
    "gn:dem":597,
    "gn:feature_class":"P",
    "gn:feature_code":"PPL",
    "gn:name":"Kutura",
    "gn:population":0,
    "gn:timezone":"Africa/Lagos",
    "iso:country":"NG",
    "name:und_x_variant":[
        "Kutura Station",
        "Kutura"
    ],
    "wof:name":"Kutura",
    "wof:placetype":"locality"
},
  "geometry": {"coordinates":[7.69319,10.1921],"type":"Point"}
}