{
  "type": "Feature",
  "properties": {
    "gn:admin1_code":"16.0",
    "gn:admin2_code":"28015.0",
    "gn:asciiname":"Ibafo",
    "gn:country_code":"NG",
    "gn:dem":14,
    "gn:feature_class":"P",
    "gn:feature_code":"PPL",
    "gn:name":"Ibafo",
    "gn:population":0,
    "gn:timezone":"Africa/Lagos",
    "iso:country":"NG",
    "name:und_x_variant":[
        "Bafo",
        "Ibafo"
    ],
    "wof:name":"Ibafo",
    "wof:placetype":"locality"
},
  "geometry": {"coordinates":[3.42187,6.74244],"type":"Point"}
}