{
  "type": "Feature",
  "properties": {
    "gn:admin1_code":"36.0",
    "gn:admin2_code":"10024.0",
    "gn:asciiname":"Ughotor",
    "gn:country_code":"NG",
    "gn:dem":8,
    "gn:feature_class":"P",
    "gn:feature_code":"PPL",
    "gn:name":"Ughotor",
    "gn:population":0,
    "gn:timezone":"Africa/Lagos",
    "iso:country":"NG",
    "name:und_x_variant":[
        "Ughoton",
        "Ughotor"
    ],
    "wof:name":"Ughotor",
    "wof:placetype":"locality"
},
  "geometry": {"coordinates":[5.66299,5.61018],"type":"Point"}
}