{
  "type": "Feature",
  "properties": {
    "gn:admin1_code":"49.0",
    "gn:admin2_code":"32009",
    "gn:asciiname":"Talbut",
    "gn:country_code":"NG",
    "gn:dem":207,
    "gn:feature_class":"P",
    "gn:feature_code":"PPL",
    "gn:name":"Talbut",
    "gn:population":0,
    "gn:timezone":"Africa/Lagos",
    "iso:country":"NG",
    "wof:name":"Talbut",
    "wof:placetype":"locality"
},
  "geometry": {"coordinates":[9.84939,8.90716],"type":"Point"}
}