{
  "type": "Feature",
  "properties": {
    "gn:admin1_code":"49.0",
    "gn:asciiname":"Joula",
    "gn:country_code":"NG",
    "gn:dem":904,
    "gn:feature_class":"P",
    "gn:feature_code":"PPL",
    "gn:name":"Joula",
    "gn:population":0,
    "gn:timezone":"Africa/Lagos",
    "iso:country":"NG",
    "wof:name":"Joula",
    "wof:placetype":"locality"
},
  "geometry": {"coordinates":[8.94831,10.05547],"type":"Point"}
}