{
  "type": "Feature",
  "properties": {
    "gn:admin1_code":"36.0",
    "gn:admin2_code":"10024.0",
    "gn:asciiname":"Asagba",
    "gn:country_code":"NG",
    "gn:dem":9,
    "gn:feature_class":"P",
    "gn:feature_code":"PPL",
    "gn:name":"Asagba",
    "gn:population":0,
    "gn:timezone":"Africa/Lagos",
    "iso:country":"NG",
    "name:eng_x_preferred":[
        "Asagba"
    ],
    "wof:name":"Asagba",
    "wof:placetype":"locality"
},
  "geometry": {"coordinates":[5.78338,5.50108],"type":"Point"}
}