{
  "type": "Feature",
  "properties": {
    "gn:admin1_code":"27.0",
    "gn:admin2_code":"110.0",
    "gn:admin3_code":"11008",
    "gn:asciiname":"Korochara",
    "gn:country_code":"NG",
    "gn:dem":289,
    "gn:feature_class":"P",
    "gn:feature_code":"PPL",
    "gn:name":"Korochara",
    "gn:population":0,
    "gn:timezone":"Africa/Lagos",
    "iso:country":"NG",
    "wof:name":"Korochara",
    "wof:placetype":"locality"
},
  "geometry": {"coordinates":[13.75629,13.03367],"type":"Point"}
}