{
  "type": "Feature",
  "properties": {
    "gn:admin1_code":"44.0",
    "gn:admin2_code":"706.0",
    "gn:admin3_code":"70612",
    "gn:asciiname":"Gajiga",
    "gn:country_code":"NG",
    "gn:dem":321,
    "gn:feature_class":"P",
    "gn:feature_code":"PPL",
    "gn:name":"Gajiga",
    "gn:population":0,
    "gn:timezone":"Africa/Lagos",
    "iso:country":"NG",
    "wof:name":"Gajiga",
    "wof:placetype":"locality"
},
  "geometry": {"coordinates":[12.33206,12.72959],"type":"Point"}
}