{
  "type": "Feature",
  "properties": {
    "gn:admin1_code":"56.0",
    "gn:admin2_code":"26012.0",
    "gn:asciiname":"Ogusu",
    "gn:country_code":"NG",
    "gn:dem":82,
    "gn:feature_class":"P",
    "gn:feature_code":"PPL",
    "gn:name":"Ogusu",
    "gn:population":0,
    "gn:timezone":"Africa/Lagos",
    "iso:country":"NG",
    "wof:name":"Ogusu",
    "wof:placetype":"locality"
},
  "geometry": {"coordinates":[7.15111,8.02278],"type":"Point"}
}