{
  "type": "Feature",
  "properties": {
    "gn:admin1_code":"21.0",
    "gn:admin2_code":"3029.0",
    "gn:asciiname":"Nung Ikono Obio",
    "gn:country_code":"NG",
    "gn:dem":54,
    "gn:feature_class":"P",
    "gn:feature_code":"PPL",
    "gn:name":"Nung Ikono Obio",
    "gn:population":0,
    "gn:timezone":"Africa/Lagos",
    "iso:country":"NG",
    "wof:name":"Nung Ikono Obio",
    "wof:placetype":"locality"
},
  "geometry": {"coordinates":[8.06184,4.94724],"type":"Point"}
}