{
  "type": "Feature",
  "properties": {
    "gn:admin1_code":"26.0",
    "gn:admin2_code":"7012",
    "gn:asciiname":"Ande",
    "gn:country_code":"NG",
    "gn:dem":186,
    "gn:feature_class":"P",
    "gn:feature_code":"PPL",
    "gn:name":"Ande",
    "gn:population":0,
    "gn:timezone":"Africa/Lagos",
    "iso:country":"NG",
    "name:ceb_x_preferred":[
        "Ande"
    ],
    "name:deu_x_preferred":[
        "Ande"
    ],
    "name:est_x_preferred":[
        "Ande"
    ],
    "name:fra_x_preferred":[
        "Ande"
    ],
    "name:spa_x_preferred":[
        "Ande"
    ],
    "name:swe_x_preferred":[
        "Ande"
    ],
    "wof:name":"Ande",
    "wof:placetype":"locality"
},
  "geometry": {"coordinates":[9.24457,7.80266],"type":"Point"}
}