{
  "type": "Feature",
  "properties": {
    "gn:admin1_code":"40.0",
    "gn:admin2_code":"513.0",
    "gn:admin3_code":"51312",
    "gn:asciiname":"Tungan Gimba",
    "gn:country_code":"NG",
    "gn:dem":160,
    "gn:feature_class":"P",
    "gn:feature_code":"PPL",
    "gn:name":"Tungan Gimba",
    "gn:population":0,
    "gn:timezone":"Africa/Lagos",
    "iso:country":"NG",
    "wof:name":"Tungan Gimba",
    "wof:placetype":"locality"
},
  "geometry": {"coordinates":[4.27426,11.34768],"type":"Point"}
}