{
  "type": "Feature",
  "properties": {
    "gn:admin1_code":"49.0",
    "gn:admin2_code":"32006.0",
    "gn:asciiname":"Zawan",
    "gn:country_code":"NG",
    "gn:dem":1291,
    "gn:feature_class":"P",
    "gn:feature_code":"PPL",
    "gn:name":"Zawan",
    "gn:population":0,
    "gn:timezone":"Africa/Lagos",
    "iso:country":"NG",
    "wof:name":"Zawan",
    "wof:placetype":"locality"
},
  "geometry": {"coordinates":[8.87473,9.75494],"type":"Point"}
}