{
  "type": "Feature",
  "properties": {
    "gn:admin1_code":"51.0",
    "gn:admin2_code":"607.0",
    "gn:admin3_code":"60703",
    "gn:asciiname":"Lukpo",
    "gn:country_code":"NG",
    "gn:dem":286,
    "gn:feature_class":"P",
    "gn:feature_code":"PPL",
    "gn:name":"Lukpo",
    "gn:population":0,
    "gn:timezone":"Africa/Lagos",
    "iso:country":"NG",
    "wof:name":"Lukpo",
    "wof:placetype":"locality"
},
  "geometry": {"coordinates":[5.31255,13.37743],"type":"Point"}
}