{
  "type": "Feature",
  "properties": {
    "gn:admin1_code":"24.0",
    "gn:admin2_code":"420.0",
    "gn:admin3_code":"42001",
    "gn:asciiname":"Kafin Dangi",
    "gn:country_code":"NG",
    "gn:dem":542,
    "gn:feature_class":"P",
    "gn:feature_code":"PPL",
    "gn:name":"Kafin Dangi",
    "gn:population":0,
    "gn:timezone":"Africa/Lagos",
    "iso:country":"NG",
    "wof:name":"Kafin Dangi",
    "wof:placetype":"locality"
},
  "geometry": {"coordinates":[7.82131,12.60505],"type":"Point"}
}