{
  "type": "Feature",
  "properties": {
    "gn:admin1_code":"31.0",
    "gn:admin2_code":"27010",
    "gn:asciiname":"Nagya",
    "gn:country_code":"NG",
    "gn:dem":116,
    "gn:feature_class":"P",
    "gn:feature_code":"PPL",
    "gn:name":"Nagya",
    "gn:population":0,
    "gn:timezone":"Africa/Lagos",
    "iso:country":"NG",
    "wof:name":"Nagya",
    "wof:placetype":"locality"
},
  "geometry": {"coordinates":[6.23499,9.18035],"type":"Point"}
}