{
  "type": "Feature",
  "properties": {
    "gn:admin1_code":"31.0",
    "gn:admin2_code":"27008",
    "gn:asciiname":"Lafiagi",
    "gn:country_code":"NG",
    "gn:dem":163,
    "gn:feature_class":"P",
    "gn:feature_code":"PPL",
    "gn:name":"Lafiagi",
    "gn:population":0,
    "gn:timezone":"Africa/Lagos",
    "iso:country":"NG",
    "wof:name":"Lafiagi",
    "wof:placetype":"locality"
},
  "geometry": {"coordinates":[5.97697,9.22326],"type":"Point"}
}