{
  "type": "Feature",
  "properties": {
    "gn:admin1_code":"37.0",
    "gn:admin2_code":"12012.0",
    "gn:asciiname":"Ebo",
    "gn:country_code":"NG",
    "gn:dem":63,
    "gn:feature_class":"P",
    "gn:feature_code":"PPL",
    "gn:name":"Ebo",
    "gn:population":0,
    "gn:timezone":"Africa/Lagos",
    "iso:country":"NG",
    "name:ceb_x_preferred":[
        "Ebo"
    ],
    "name:por_x_preferred":[
        "Ebo"
    ],
    "name:swe_x_preferred":[
        "Ebo"
    ],
    "name:und_x_variant":[
        "Ebowe",
        "Ebo"
    ],
    "wof:name":"Ebo",
    "wof:placetype":"locality"
},
  "geometry": {"coordinates":[5.58555,6.26425],"type":"Point"}
}