{
  "type": "Feature",
  "properties": {
    "gn:admin1_code":"44.0",
    "gn:admin2_code":"715.0",
    "gn:admin3_code":"71507",
    "gn:asciiname":"Lantewa",
    "gn:country_code":"NG",
    "gn:dem":349,
    "gn:feature_class":"P",
    "gn:feature_code":"PPL",
    "gn:name":"Lantewa",
    "gn:population":0,
    "gn:timezone":"Africa/Lagos",
    "iso:country":"NG",
    "wof:name":"Lantewa",
    "wof:placetype":"locality"
},
  "geometry": {"coordinates":[11.73292,12.26457],"type":"Point"}
}