{
  "type": "Feature",
  "properties": {
    "gn:admin1_code":"41.0",
    "gn:admin2_code":"23006.0",
    "gn:asciiname":"Agbagbojo",
    "gn:country_code":"NG",
    "gn:dem":34,
    "gn:feature_class":"P",
    "gn:feature_code":"PPL",
    "gn:name":"Agbagbojo",
    "gn:population":0,
    "gn:timezone":"Africa/Lagos",
    "iso:country":"NG",
    "name:eng_x_preferred":[
        "Agbagbojo"
    ],
    "wof:name":"Agbagbojo",
    "wof:placetype":"locality"
},
  "geometry": {"coordinates":[6.64549,6.85372],"type":"Point"}
}