{
  "type": "Feature",
  "properties": {
    "gn:admin1_code":"43.0",
    "gn:admin2_code":"35006",
    "gn:asciiname":"Kogi Wase",
    "gn:country_code":"NG",
    "gn:dem":114,
    "gn:feature_class":"P",
    "gn:feature_code":"PPL",
    "gn:name":"Kogi Wase",
    "gn:population":0,
    "gn:timezone":"Africa/Lagos",
    "iso:country":"NG",
    "wof:name":"Kogi Wase",
    "wof:placetype":"locality"
},
  "geometry": {"coordinates":[10.09809,8.52956],"type":"Point"}
}