{
  "type": "Feature",
  "properties": {
    "gn:admin1_code":"35.0",
    "gn:admin2_code":"2007.0",
    "gn:asciiname":"Wuro Kadiri",
    "gn:country_code":"NG",
    "gn:dem":551,
    "gn:feature_class":"P",
    "gn:feature_code":"PPL",
    "gn:name":"Wuro Kadiri",
    "gn:population":0,
    "gn:timezone":"Africa/Lagos",
    "iso:country":"NG",
    "wof:name":"Wuro Kadiri",
    "wof:placetype":"locality"
},
  "geometry": {"coordinates":[12.83145,10.17529],"type":"Point"}
}