{
  "type": "Feature",
  "properties": {
    "gn:admin1_code":"29.0",
    "gn:admin2_code":"20023.0",
    "gn:admin3_code":"KN0810",
    "gn:asciiname":"Kwasauri",
    "gn:country_code":"NG",
    "gn:dem":409,
    "gn:feature_class":"P",
    "gn:feature_code":"PPL",
    "gn:name":"Kwasauri",
    "gn:population":0,
    "gn:timezone":"Africa/Lagos",
    "iso:country":"NG",
    "wof:name":"Kwasauri",
    "wof:placetype":"locality"
},
  "geometry": {"coordinates":[8.67633,12.42795],"type":"Point"}
}