{
  "type": "Feature",
  "properties": {
    "gn:admin1_code":"45.0",
    "gn:admin2_code":"1007.0",
    "gn:asciiname":"Umu-Ezegu",
    "gn:country_code":"NG",
    "gn:dem":121,
    "gn:feature_class":"P",
    "gn:feature_code":"PPL",
    "gn:name":"Umu-Ezegu",
    "gn:population":0,
    "gn:timezone":"Africa/Lagos",
    "iso:country":"NG",
    "wof:name":"Umu-Ezegu",
    "wof:placetype":"locality"
},
  "geometry": {"coordinates":[7.409,5.39576],"type":"Point"}
}