{
  "type": "Feature",
  "properties": {
    "gn:admin1_code":"51.0",
    "gn:admin2_code":"618.0",
    "gn:admin3_code":"61804",
    "gn:asciiname":"Rugar Shaudu",
    "gn:cc2":"NG",
    "gn:country_code":"NG",
    "gn:dem":259,
    "gn:feature_class":"P",
    "gn:feature_code":"PPL",
    "gn:name":"Rugar Shaudu",
    "gn:population":0,
    "gn:timezone":"Africa/Lagos",
    "iso:country":"NG",
    "name:und_x_variant":[
        "Ruggar Shaudu",
        "Rugar Shaudu"
    ],
    "wof:name":"Rugar Shaudu",
    "wof:placetype":"locality"
},
  "geometry": {"coordinates":[4.81667,12.46667],"type":"Point"}
}