{
  "type": "Feature",
  "properties": {
    "gn:admin1_code":"11.0",
    "gn:admin2_code":"15006.0",
    "gn:asciiname":"Kubwa Suburban District",
    "gn:country_code":"NG",
    "gn:dem":445,
    "gn:elevation":"445.0",
    "gn:feature_class":"P",
    "gn:feature_code":"PPL",
    "gn:name":"Kubwa Suburban District",
    "gn:population":0,
    "gn:timezone":"Africa/Lagos",
    "iso:country":"NG",
    "wof:name":"Kubwa Suburban District",
    "wof:placetype":"locality"
},
  "geometry": {"coordinates":[7.35257,9.1413],"type":"Point"}
}