{
  "type": "Feature",
  "properties": {
    "gn:admin1_code":"52.0",
    "gn:admin2_code":"6007.0",
    "gn:asciiname":"Akpobeleiowei",
    "gn:country_code":"NG",
    "gn:dem":18,
    "gn:feature_class":"P",
    "gn:feature_code":"PPL",
    "gn:name":"Akpobeleiowei",
    "gn:population":0,
    "gn:timezone":"Africa/Lagos",
    "iso:country":"NG",
    "name:eng_x_preferred":[
        "Akpobeleiowei"
    ],
    "wof:name":"Akpobeleiowei",
    "wof:placetype":"locality"
},
  "geometry": {"coordinates":[5.8845,4.74613],"type":"Point"}
}