{
  "type": "Feature",
  "properties": {
    "gn:admin1_code":"56.0",
    "gn:admin2_code":"26004",
    "gn:asciiname":"Gidan Obaro",
    "gn:country_code":"NG",
    "gn:dem":404,
    "gn:feature_class":"P",
    "gn:feature_code":"PPL",
    "gn:name":"Gidan Obaro",
    "gn:population":0,
    "gn:timezone":"Africa/Lagos",
    "iso:country":"NG",
    "wof:name":"Gidan Obaro",
    "wof:placetype":"locality"
},
  "geometry": {"coordinates":[7.79841,9.08708],"type":"Point"}
}