{
  "type": "Feature",
  "properties": {
    "gn:admin1_code":"11.0",
    "gn:admin2_code":"15003.0",
    "gn:asciiname":"Ledi",
    "gn:country_code":"NG",
    "gn:dem":226,
    "gn:feature_class":"P",
    "gn:feature_code":"PPL",
    "gn:name":"Ledi",
    "gn:population":0,
    "gn:timezone":"Africa/Lagos",
    "iso:country":"NG",
    "wof:name":"Ledi",
    "wof:placetype":"locality"
},
  "geometry": {"coordinates":[6.99456,9.1176],"type":"Point"}
}