{
  "type": "Feature",
  "properties": {
    "gn:admin1_code":"42.0",
    "gn:admin2_code":"30001.0",
    "gn:asciiname":"Osoko",
    "gn:country_code":"NG",
    "gn:dem":197,
    "gn:feature_class":"P",
    "gn:feature_code":"PPL",
    "gn:name":"Osoko",
    "gn:population":0,
    "gn:timezone":"Africa/Lagos",
    "iso:country":"NG",
    "wof:name":"Osoko",
    "wof:placetype":"locality"
},
  "geometry": {"coordinates":[4.26667,7.23333],"type":"Point"}
}