{
  "type": "Feature",
  "properties": {
    "gn:admin1_code":"50.0",
    "gn:asciiname":"Trapukiri",
    "gn:country_code":"NG",
    "gn:dem":433,
    "gn:feature_class":"P",
    "gn:feature_code":"PPL",
    "gn:name":"Trapukiri",
    "gn:population":0,
    "gn:timezone":"Africa/Lagos",
    "iso:country":"NG",
    "wof:name":"Trapukiri",
    "wof:placetype":"locality"
},
  "geometry": {"coordinates":[7.08861,4.67985],"type":"Point"}
}