{
  "type": "Feature",
  "properties": {
    "gn:admin1_code":"23.0",
    "gn:admin2_code":"19005.0",
    "gn:admin3_code":"KD0507",
    "gn:asciiname":"Kawuri",
    "gn:country_code":"NG",
    "gn:dem":645,
    "gn:feature_class":"P",
    "gn:feature_code":"PPL",
    "gn:name":"Kawuri",
    "gn:population":0,
    "gn:timezone":"Africa/Lagos",
    "iso:country":"NG",
    "wof:name":"Kawuri",
    "wof:placetype":"locality"
},
  "geometry": {"coordinates":[8.44435,11.19024],"type":"Point"}
}