{
  "type": "Feature",
  "properties": {
    "gn:admin1_code":"26.0",
    "gn:admin2_code":"7017.0",
    "gn:asciiname":"Wori Obotu",
    "gn:country_code":"NG",
    "gn:dem":135,
    "gn:feature_class":"P",
    "gn:feature_code":"PPL",
    "gn:name":"Wori Obotu",
    "gn:population":0,
    "gn:timezone":"Africa/Lagos",
    "iso:country":"NG",
    "wof:name":"Wori Obotu",
    "wof:placetype":"locality"
},
  "geometry": {"coordinates":[8.37568,6.73017],"type":"Point"}
}