{
  "type": "Feature",
  "properties": {
    "gn:admin1_code":"23.0",
    "gn:admin2_code":"19020",
    "gn:admin3_code":"KD2003",
    "gn:asciiname":"Yabama",
    "gn:country_code":"NG",
    "gn:dem":581,
    "gn:feature_class":"P",
    "gn:feature_code":"PPL",
    "gn:name":"Yabama",
    "gn:population":0,
    "gn:timezone":"Africa/Lagos",
    "iso:country":"NG",
    "wof:name":"Yabama",
    "wof:placetype":"locality"
},
  "geometry": {"coordinates":[8.58561,9.26005],"type":"Point"}
}