{
  "type": "Feature",
  "properties": {
    "gn:admin1_code":"29.0",
    "gn:admin2_code":"20041.0",
    "gn:admin3_code":"KN2202",
    "gn:asciiname":"Matankari",
    "gn:country_code":"NG",
    "gn:dem":504,
    "gn:feature_class":"P",
    "gn:feature_code":"PPL",
    "gn:name":"Matankari",
    "gn:population":0,
    "gn:timezone":"Africa/Lagos",
    "iso:country":"NG",
    "name:deu_x_preferred":[
        "Matankari"
    ],
    "name:fra_x_preferred":[
        "Matankari"
    ],
    "name:ita_x_preferred":[
        "Matankari"
    ],
    "name:msa_x_preferred":[
        "Matankari"
    ],
    "name:ron_x_preferred":[
        "Matankari"
    ],
    "name:spa_x_preferred":[
        "Matankari"
    ],
    "wof:name":"Matankari",
    "wof:placetype":"locality"
},
  "geometry": {"coordinates":[8.09561,11.77643],"type":"Point"}
}