{
  "type": "Feature",
  "properties": {
    "gn:admin1_code":"29.0",
    "gn:admin2_code":"20017.0",
    "gn:admin3_code":"KN1904",
    "gn:asciiname":"Koya",
    "gn:country_code":"NG",
    "gn:dem":597,
    "gn:feature_class":"P",
    "gn:feature_code":"PPL",
    "gn:name":"Koya",
    "gn:population":0,
    "gn:timezone":"Africa/Lagos",
    "iso:country":"NG",
    "name:und_x_variant":[
        "Ungwelo-ta-Koyia",
        "Ungwelo-te-Koyia",
        "Koya"
    ],
    "wof:name":"Koya",
    "wof:placetype":"locality"
},
  "geometry": {"coordinates":[7.95708,11.87802],"type":"Point"}
}