{
  "type": "Feature",
  "properties": {
    "gn:admin1_code":"32.0",
    "gn:admin2_code":"31002.0",
    "gn:asciiname":"Jeje",
    "gn:cc2":"NG",
    "gn:country_code":"NG",
    "gn:dem":271,
    "gn:feature_class":"P",
    "gn:feature_code":"PPL",
    "gn:name":"Jeje",
    "gn:population":0,
    "gn:timezone":"Africa/Lagos",
    "iso:country":"NG",
    "name:und_x_variant":[
        "Ajayi",
        "Jeje"
    ],
    "wof:name":"Jeje",
    "wof:placetype":"locality"
},
  "geometry": {"coordinates":[3.91667,7.58333],"type":"Point"}
}