{
  "type": "Feature",
  "properties": {
    "gn:admin1_code":"30.0",
    "gn:admin2_code":"24012.0",
    "gn:asciiname":"Elewure",
    "gn:country_code":"NG",
    "gn:dem":390,
    "gn:feature_class":"P",
    "gn:feature_code":"PPL",
    "gn:name":"Elewure",
    "gn:population":0,
    "gn:timezone":"Africa/Lagos",
    "iso:country":"NG",
    "wof:name":"Elewure",
    "wof:placetype":"locality"
},
  "geometry": {"coordinates":[4.25,8.83333],"type":"Point"}
}