{
  "type": "Feature",
  "properties": {
    "gn:admin1_code":"28.0",
    "gn:admin2_code":"17015.0",
    "gn:asciiname":"Agbaja-Isu",
    "gn:country_code":"NG",
    "gn:dem":226,
    "gn:feature_class":"P",
    "gn:feature_code":"PPL",
    "gn:name":"Agbaja-Isu",
    "gn:population":0,
    "gn:timezone":"Africa/Lagos",
    "iso:country":"NG",
    "wof:name":"Agbaja-Isu",
    "wof:placetype":"locality"
},
  "geometry": {"coordinates":[7.13565,5.69152],"type":"Point"}
}