{
  "type": "Feature",
  "properties": {
    "gn:admin1_code":"44.0",
    "gn:admin2_code":"705.0",
    "gn:admin3_code":"70502",
    "gn:asciiname":"Damagum",
    "gn:country_code":"NG",
    "gn:dem":416,
    "gn:feature_class":"P",
    "gn:feature_code":"PPLA2",
    "gn:name":"Damagum",
    "gn:population":0,
    "gn:timezone":"Africa/Lagos",
    "iso:country":"NG",
    "name:und_x_variant":[
        "Damagun"
    ],
    "wof:name":"Damagum",
    "wof:placetype":"locality"
},
  "geometry": {"coordinates":[11.33517,11.67824],"type":"Point"}
}