{
  "type": "Feature",
  "properties": {
    "gn:admin1_code":"24.0",
    "gn:admin2_code":"431.0",
    "gn:admin3_code":"43109",
    "gn:asciiname":"Mai Ungwan",
    "gn:country_code":"NG",
    "gn:dem":688,
    "gn:feature_class":"P",
    "gn:feature_code":"PPL",
    "gn:name":"Mai Ungwan",
    "gn:population":0,
    "gn:timezone":"Africa/Lagos",
    "iso:country":"NG",
    "wof:name":"Mai Ungwan",
    "wof:placetype":"locality"
},
  "geometry": {"coordinates":[7.11116,11.20697],"type":"Point"}
}