{
  "type": "Feature",
  "properties": {
    "gn:admin1_code":"23.0",
    "gn:admin2_code":"19003.0",
    "gn:admin3_code":"KD0309",
    "gn:asciiname":"Tsibiri",
    "gn:country_code":"NG",
    "gn:dem":668,
    "gn:feature_class":"P",
    "gn:feature_code":"PPL",
    "gn:name":"Tsibiri",
    "gn:population":0,
    "gn:timezone":"Africa/Lagos",
    "iso:country":"NG",
    "wof:name":"Tsibiri",
    "wof:placetype":"locality"
},
  "geometry": {"coordinates":[7.53642,11.19192],"type":"Point"}
}