{
  "type": "Feature",
  "properties": {
    "gn:admin1_code":"27.0",
    "gn:admin2_code":"103.0",
    "gn:admin3_code":"10309",
    "gn:asciiname":"Bula Andimibe",
    "gn:country_code":"NG",
    "gn:dem":303,
    "gn:feature_class":"P",
    "gn:feature_code":"PPL",
    "gn:name":"Bula Andimibe",
    "gn:population":0,
    "gn:timezone":"Africa/Lagos",
    "iso:country":"NG",
    "wof:name":"Bula Andimibe",
    "wof:placetype":"locality"
},
  "geometry": {"coordinates":[14.05078,11.66472],"type":"Point"}
}