{
  "type": "Feature",
  "properties": {
    "gn:admin1_code":"45.0",
    "gn:admin2_code":"1009.0",
    "gn:asciiname":"Umu Aja",
    "gn:country_code":"NG",
    "gn:dem":74,
    "gn:feature_class":"P",
    "gn:feature_code":"PPL",
    "gn:name":"Umu Aja",
    "gn:population":0,
    "gn:timezone":"Africa/Lagos",
    "iso:country":"NG",
    "name:und_x_variant":[
        "Akata",
        "Aja",
        "Umu Aja"
    ],
    "wof:name":"Umu Aja",
    "wof:placetype":"locality"
},
  "geometry": {"coordinates":[7.52546,5.11273],"type":"Point"}
}