{
  "type": "Feature",
  "properties": {
    "gn:admin1_code":"36.0",
    "gn:admin2_code":"10019.0",
    "gn:asciiname":"Ododegbo",
    "gn:country_code":"NG",
    "gn:dem":12,
    "gn:feature_class":"P",
    "gn:feature_code":"PPL",
    "gn:name":"Ododegbo",
    "gn:population":0,
    "gn:timezone":"Africa/Lagos",
    "iso:country":"NG",
    "name:und_x_variant":[
        "Ododegho"
    ],
    "wof:name":"Ododegbo",
    "wof:placetype":"locality"
},
  "geometry": {"coordinates":[5.96333,5.53671],"type":"Point"}
}