{
  "type": "Feature",
  "properties": {
    "gn:admin1_code":"24.0",
    "gn:admin2_code":"431.0",
    "gn:admin3_code":"43105",
    "gn:asciiname":"Chido",
    "gn:country_code":"NG",
    "gn:dem":674,
    "gn:feature_class":"P",
    "gn:feature_code":"PPL",
    "gn:name":"Chido",
    "gn:population":0,
    "gn:timezone":"Africa/Lagos",
    "iso:country":"NG",
    "name:und_x_variant":[
        "Anquwan Chido",
        "Chido"
    ],
    "wof:name":"Chido",
    "wof:placetype":"locality"
},
  "geometry": {"coordinates":[7.05045,11.51939],"type":"Point"}
}