{
  "type": "Feature",
  "properties": {
    "gn:admin1_code":"51.0",
    "gn:admin2_code":"619.0",
    "gn:admin3_code":"61907",
    "gn:asciiname":"Lilingo",
    "gn:country_code":"NG",
    "gn:dem":265,
    "gn:feature_class":"P",
    "gn:feature_code":"PPL",
    "gn:name":"Lilingo",
    "gn:population":0,
    "gn:timezone":"Africa/Lagos",
    "iso:country":"NG",
    "name:und_x_variant":[
        "Dilingo",
        "Lilingo"
    ],
    "wof:name":"Lilingo",
    "wof:placetype":"locality"
},
  "geometry": {"coordinates":[4.94364,13.60678],"type":"Point"}
}