{
  "type": "Feature",
  "properties": {
    "gn:admin1_code":"32.0",
    "gn:admin2_code":"31030.0",
    "gn:asciiname":"Babi",
    "gn:country_code":"NG",
    "gn:dem":244,
    "gn:feature_class":"P",
    "gn:feature_code":"PPL",
    "gn:name":"Babi",
    "gn:population":0,
    "gn:timezone":"Africa/Lagos",
    "iso:country":"NG",
    "wof:name":"Babi",
    "wof:placetype":"locality"
},
  "geometry": {"coordinates":[3.75,8.06667],"type":"Point"}
}