{
  "type": "Feature",
  "properties": {
    "gn:admin1_code":"25.0",
    "gn:admin2_code":"4003.0",
    "gn:asciiname":"Obodola",
    "gn:country_code":"NG",
    "gn:dem":24,
    "gn:feature_class":"P",
    "gn:feature_code":"PPL",
    "gn:name":"Obodola",
    "gn:population":0,
    "gn:timezone":"Africa/Lagos",
    "iso:country":"NG",
    "name:eng_x_preferred":[
        "Obodola"
    ],
    "name:und_x_variant":[
        "Obadola"
    ],
    "wof:name":"Obodola",
    "wof:placetype":"locality"
},
  "geometry": {"coordinates":[6.81973,6.53364],"type":"Point"}
}