{
  "type": "Feature",
  "properties": {
    "gn:admin1_code":"21.0",
    "gn:admin2_code":"3031.0",
    "gn:asciiname":"Itiam Ikot Ebia",
    "gn:country_code":"NG",
    "gn:dem":62,
    "gn:feature_class":"P",
    "gn:feature_code":"PPL",
    "gn:name":"Itiam Ikot Ebia",
    "gn:population":0,
    "gn:timezone":"Africa/Lagos",
    "iso:country":"NG",
    "wof:name":"Itiam Ikot Ebia",
    "wof:placetype":"locality"
},
  "geometry": {"coordinates":[7.94046,5.00155],"type":"Point"}
}