{
  "type": "Feature",
  "properties": {
    "gn:admin1_code":"23.0",
    "gn:asciiname":"Magangani",
    "gn:country_code":"NG",
    "gn:dem":774,
    "gn:feature_class":"P",
    "gn:feature_code":"PPL",
    "gn:name":"Magangani",
    "gn:population":0,
    "gn:timezone":"Africa/Lagos",
    "iso:country":"NG",
    "wof:name":"Magangani",
    "wof:placetype":"locality"
},
  "geometry": {"coordinates":[8.68624,10.7055],"type":"Point"}
}