{
  "type": "Feature",
  "properties": {
    "gn:admin1_code":"44.0",
    "gn:admin2_code":"712.0",
    "gn:admin3_code":"71209",
    "gn:asciiname":"Langawa",
    "gn:country_code":"NG",
    "gn:dem":439,
    "gn:feature_class":"P",
    "gn:feature_code":"PPL",
    "gn:name":"Langawa",
    "gn:population":0,
    "gn:timezone":"Africa/Lagos",
    "iso:country":"NG",
    "wof:name":"Langawa",
    "wof:placetype":"locality"
},
  "geometry": {"coordinates":[10.9876,11.6414],"type":"Point"}
}