{
  "type": "Feature",
  "properties": {
    "gn:admin1_code":"48.0",
    "gn:admin2_code":"29001.0",
    "gn:asciiname":"Akunnu",
    "gn:country_code":"NG",
    "gn:dem":373,
    "gn:feature_class":"P",
    "gn:feature_code":"PPL",
    "gn:name":"Akunnu",
    "gn:population":0,
    "gn:timezone":"Africa/Lagos",
    "iso:country":"NG",
    "wof:name":"Akunnu",
    "wof:placetype":"locality"
},
  "geometry": {"coordinates":[5.94019,7.62632],"type":"Point"}
}