{
  "type": "Feature",
  "properties": {
    "gn:admin1_code":"27.0",
    "gn:admin2_code":"107",
    "gn:admin3_code":"10702",
    "gn:asciiname":"Njaba",
    "gn:country_code":"NG",
    "gn:dem":383,
    "gn:feature_class":"P",
    "gn:feature_code":"PPL",
    "gn:name":"Njaba",
    "gn:population":0,
    "gn:timezone":"Africa/Lagos",
    "iso:country":"NG",
    "wof:name":"Njaba",
    "wof:placetype":"locality"
},
  "geometry": {"coordinates":[12.95302,11.13503],"type":"Point"}
}