{
  "type": "Feature",
  "properties": {
    "gn:admin1_code":"36.0",
    "gn:admin2_code":"10018.0",
    "gn:asciiname":"Oghior",
    "gn:country_code":"NG",
    "gn:dem":12,
    "gn:feature_class":"P",
    "gn:feature_code":"PPL",
    "gn:name":"Oghior",
    "gn:population":0,
    "gn:timezone":"Africa/Lagos",
    "iso:country":"NG",
    "wof:name":"Oghior",
    "wof:placetype":"locality"
},
  "geometry": {"coordinates":[5.85036,5.42589],"type":"Point"}
}