{
  "type": "Feature",
  "properties": {
    "gn:admin1_code":"50.0",
    "gn:admin2_code":"33004.0",
    "gn:asciiname":"Olomabokokin",
    "gn:country_code":"NG",
    "gn:dem":6,
    "gn:feature_class":"P",
    "gn:feature_code":"PPL",
    "gn:name":"Olomabokokin",
    "gn:population":0,
    "gn:timezone":"Africa/Lagos",
    "iso:country":"NG",
    "wof:name":"Olomabokokin",
    "wof:placetype":"locality"
},
  "geometry": {"coordinates":[6.71336,4.40414],"type":"Point"}
}