{
  "type": "Feature",
  "properties": {
    "gn:admin1_code":"26.0",
    "gn:admin2_code":"7022",
    "gn:asciiname":"Iorhemen",
    "gn:country_code":"NG",
    "gn:dem":214,
    "gn:feature_class":"P",
    "gn:feature_code":"PPL",
    "gn:name":"Iorhemen",
    "gn:population":0,
    "gn:timezone":"Africa/Lagos",
    "iso:country":"NG",
    "wof:name":"Iorhemen",
    "wof:placetype":"locality"
},
  "geometry": {"coordinates":[9.03871,7.06203],"type":"Point"}
}