{
  "type": "Feature",
  "properties": {
    "gn:admin1_code":"51.0",
    "gn:admin2_code":"611.0",
    "gn:admin3_code":"61103",
    "gn:asciiname":"Durbawa",
    "gn:country_code":"NG",
    "gn:dem":269,
    "gn:feature_class":"P",
    "gn:feature_code":"PPL",
    "gn:name":"Durbawa",
    "gn:population":0,
    "gn:timezone":"Africa/Lagos",
    "iso:country":"NG",
    "name:und_x_variant":[
        "Durbal",
        "Durbawa"
    ],
    "wof:name":"Durbawa",
    "wof:placetype":"locality"
},
  "geometry": {"coordinates":[5.33997,13.06391],"type":"Point"}
}