{
  "type": "Feature",
  "properties": {
    "gn:admin1_code":"23.0",
    "gn:admin2_code":"19004.0",
    "gn:admin3_code":"KD0411",
    "gn:asciiname":"Mazagamo",
    "gn:country_code":"NG",
    "gn:dem":645,
    "gn:feature_class":"P",
    "gn:feature_code":"PPL",
    "gn:name":"Mazagamo",
    "gn:population":0,
    "gn:timezone":"Africa/Lagos",
    "iso:country":"NG",
    "name:und_x_variant":[
        "Mazangamo",
        "Mazagamo"
    ],
    "wof:name":"Mazagamo",
    "wof:placetype":"locality"
},
  "geometry": {"coordinates":[7.71285,10.84709],"type":"Point"}
}