{
  "type": "Feature",
  "properties": {
    "gn:admin1_code":"23.0",
    "gn:admin2_code":"19014.0",
    "gn:admin3_code":"KD1402",
    "gn:asciiname":"Kusamani",
    "gn:country_code":"NG",
    "gn:dem":768,
    "gn:feature_class":"P",
    "gn:feature_code":"PPL",
    "gn:name":"Kusamani",
    "gn:population":0,
    "gn:timezone":"Africa/Lagos",
    "iso:country":"NG",
    "wof:name":"Kusamani",
    "wof:placetype":"locality"
},
  "geometry": {"coordinates":[8.27162,10.1654],"type":"Point"}
}