{
  "type": "Feature",
  "properties": {
    "gn:admin1_code":"47.0",
    "gn:admin2_code":"14014.0",
    "gn:asciiname":"Ehuhe",
    "gn:country_code":"NG",
    "gn:dem":201,
    "gn:feature_class":"P",
    "gn:feature_code":"PPL",
    "gn:name":"Ehuhe",
    "gn:population":0,
    "gn:timezone":"Africa/Lagos",
    "iso:country":"NG",
    "wof:name":"Ehuhe",
    "wof:placetype":"locality"
},
  "geometry": {"coordinates":[7.35648,6.19855],"type":"Point"}
}