{
  "type": "Feature",
  "properties": {
    "gn:admin1_code":"26.0",
    "gn:admin2_code":"7004",
    "gn:asciiname":"Tsau",
    "gn:country_code":"NG",
    "gn:dem":200,
    "gn:feature_class":"P",
    "gn:feature_code":"PPL",
    "gn:name":"Tsau",
    "gn:population":0,
    "gn:timezone":"Africa/Lagos",
    "iso:country":"NG",
    "name:ara_x_preferred":[
        "\u062a\u0633\u0627\u0648"
    ],
    "name:ben_x_preferred":[
        "\u09b8\u09be\u0989"
    ],
    "name:deu_x_preferred":[
        "Tsau"
    ],
    "name:ell_x_preferred":[
        "\u03a4\u03c3\u03ac\u03bf\u03c5"
    ],
    "name:fas_x_preferred":[
        "\u062a\u06cc\u0633\u0627\u0626\u0648"
    ],
    "name:heb_x_preferred":[
        "\u05d8\u05e1\u05d0\u05d5"
    ],
    "name:hin_x_preferred":[
        "\u0924\u094d\u0938\u093e\u090a"
    ],
    "name:hun_x_preferred":[
        "Tsau"
    ],
    "name:ind_x_preferred":[
        "Tsau"
    ],
    "name:kor_x_preferred":[
        "\ucc60\uc6b0"
    ],
    "name:spa_x_preferred":[
        "Tsau"
    ],
    "name:tur_x_preferred":[
        "Tsau"
    ],
    "name:ukr_x_preferred":[
        "\u0422\u0441\u0430\u0443"
    ],
    "name:urd_x_preferred":[
        "\u0679\u0633\u0627\u0624"
    ],
    "name:vie_x_preferred":[
        "Tsau"
    ],
    "name:zho_cn_x_preferred":[
        "\u5bdf\u5965"
    ],
    "name:zho_tw_x_preferred":[
        "\u7279\u5716"
    ],
    "wof:name":"Tsau",
    "wof:placetype":"locality"
},
  "geometry": {"coordinates":[9.04696,7.17175],"type":"Point"}
}