{
  "type": "Feature",
  "properties": {
    "gn:admin1_code":"41.0",
    "gn:admin2_code":"23009.0",
    "gn:asciiname":"Aiyegunle",
    "gn:country_code":"NG",
    "gn:dem":565,
    "gn:feature_class":"P",
    "gn:feature_code":"PPL",
    "gn:name":"Aiyegunle",
    "gn:population":0,
    "gn:timezone":"Africa/Lagos",
    "iso:country":"NG",
    "wof:name":"Aiyegunle",
    "wof:placetype":"locality"
},
  "geometry": {"coordinates":[6.0556,7.9923],"type":"Point"}
}