{
  "type": "Feature",
  "properties": {
    "gn:admin1_code":"16.0",
    "gn:admin2_code":"28004.0",
    "gn:asciiname":"Akerun Fade",
    "gn:cc2":"NG",
    "gn:country_code":"NG",
    "gn:dem":97,
    "gn:feature_class":"P",
    "gn:feature_code":"PPL",
    "gn:name":"Akerun Fade",
    "gn:population":0,
    "gn:timezone":"Africa/Lagos",
    "iso:country":"NG",
    "name:und_x_variant":[
        "Fade",
        "Akerun Fade"
    ],
    "wof:name":"Akerun Fade",
    "wof:placetype":"locality"
},
  "geometry": {"coordinates":[2.81667,6.86667],"type":"Point"}
}