{
  "type": "Feature",
  "properties": {
    "gn:admin1_code":"27.0",
    "gn:asciiname":"Washim",
    "gn:country_code":"NG",
    "gn:dem":441,
    "gn:feature_class":"P",
    "gn:feature_code":"PPL",
    "gn:name":"Washim",
    "gn:population":0,
    "gn:timezone":"Africa/Lagos",
    "iso:country":"NG",
    "name:ben_x_preferred":[
        "\u0993\u09af\u09bc\u09be\u09b8\u09bf\u09ae"
    ],
    "name:bpy_x_preferred":[
        "\u09f1\u09be\u09b8\u09bf\u09ae"
    ],
    "name:cat_x_preferred":[
        "Washim"
    ],
    "name:ceb_x_preferred":[
        "W\u0101sh\u012bm"
    ],
    "name:guj_x_preferred":[
        "\u0ab5\u0abe\u0ab6\u0ac0\u0aae"
    ],
    "name:hin_x_preferred":[
        "\u0935\u093e\u0936\u093f\u092e"
    ],
    "name:ita_x_preferred":[
        "Washim"
    ],
    "name:mar_x_preferred":[
        "\u0935\u093e\u0936\u093f\u092e"
    ],
    "name:mlg_x_preferred":[
        "Washim"
    ],
    "name:msa_x_preferred":[
        "Washim"
    ],
    "name:new_x_preferred":[
        "\u0935\u093e\u0936\u093f\u092e"
    ],
    "name:rus_x_preferred":[
        "\u0412\u0430\u0448\u0438\u043c"
    ],
    "name:san_x_preferred":[
        "\u0935\u093e\u0936\u093f\u092e"
    ],
    "name:swe_x_preferred":[
        "Washim"
    ],
    "name:urd_x_preferred":[
        "\u0648\u0627\u0634\u0645"
    ],
    "name:vie_x_preferred":[
        "Washim"
    ],
    "name:zho_x_preferred":[
        "\u74e6\u65af\u5e0c\u59c6"
    ],
    "wof:name":"Washim",
    "wof:placetype":"locality"
},
  "geometry": {"coordinates":[12.69302,10.44979],"type":"Point"}
}