{
  "type": "Feature",
  "properties": {
    "gn:admin1_code":"43.0",
    "gn:admin2_code":"35011.0",
    "gn:asciiname":"Njawai",
    "gn:cc2":"NG",
    "gn:country_code":"NG",
    "gn:dem":1588,
    "gn:feature_class":"P",
    "gn:feature_code":"PPL",
    "gn:name":"Njawai",
    "gn:population":0,
    "gn:timezone":"Africa/Lagos",
    "iso:country":"NG",
    "name:und_x_variant":[
        "Djaw\u00e9",
        "Njawai"
    ],
    "wof:name":"Njawai",
    "wof:placetype":"locality"
},
  "geometry": {"coordinates":[11.56667,6.91667],"type":"Point"}
}