{
  "type": "Feature",
  "properties": {
    "gn:admin1_code":"40.0",
    "gn:admin2_code":"515.0",
    "gn:admin3_code":"51503",
    "gn:asciiname":"Tungan Mogaji",
    "gn:country_code":"NG",
    "gn:dem":162,
    "gn:feature_class":"P",
    "gn:feature_code":"PPL",
    "gn:name":"Tungan Mogaji",
    "gn:population":0,
    "gn:timezone":"Africa/Lagos",
    "iso:country":"NG",
    "wof:name":"Tungan Mogaji",
    "wof:placetype":"locality"
},
  "geometry": {"coordinates":[4.76522,10.55762],"type":"Point"}
}