{
  "type": "Feature",
  "properties": {
    "gn:admin1_code":"43.0",
    "gn:admin2_code":"35001.0",
    "gn:asciiname":"Garin Mallam Yaya",
    "gn:country_code":"NG",
    "gn:dem":218,
    "gn:feature_class":"P",
    "gn:feature_code":"PPL",
    "gn:name":"Garin Mallam Yaya",
    "gn:population":0,
    "gn:timezone":"Africa/Lagos",
    "iso:country":"NG",
    "wof:name":"Garin Mallam Yaya",
    "wof:placetype":"locality"
},
  "geometry": {"coordinates":[11.37011,8.73199],"type":"Point"}
}