{
  "type": "Feature",
  "properties": {
    "gn:admin1_code":"26.0",
    "gn:admin2_code":"7022",
    "gn:asciiname":"Anongu",
    "gn:country_code":"NG",
    "gn:dem":147,
    "gn:feature_class":"P",
    "gn:feature_code":"PPL",
    "gn:name":"Anongu",
    "gn:population":0,
    "gn:timezone":"Africa/Lagos",
    "iso:country":"NG",
    "wof:name":"Anongu",
    "wof:placetype":"locality"
},
  "geometry": {"coordinates":[8.9155,7.26375],"type":"Point"}
}