{
  "type": "Feature",
  "properties": {
    "gn:admin1_code":"35.0",
    "gn:admin2_code":"2008.0",
    "gn:asciiname":"Jauro Kubura",
    "gn:country_code":"NG",
    "gn:dem":472,
    "gn:feature_class":"P",
    "gn:feature_code":"PPL",
    "gn:name":"Jauro Kubura",
    "gn:population":0,
    "gn:timezone":"Africa/Lagos",
    "iso:country":"NG",
    "wof:name":"Jauro Kubura",
    "wof:placetype":"locality"
},
  "geometry": {"coordinates":[12.29814,8.51404],"type":"Point"}
}