{
  "type": "Feature",
  "properties": {
    "gn:admin1_code":"46.0",
    "gn:admin2_code":"5010.0",
    "gn:admin3_code":"BA1015",
    "gn:asciiname":"Maio",
    "gn:country_code":"NG",
    "gn:dem":390,
    "gn:feature_class":"P",
    "gn:feature_code":"PPL",
    "gn:name":"Maio",
    "gn:population":0,
    "gn:timezone":"Africa/Lagos",
    "iso:country":"NG",
    "name:ben_x_preferred":[
        "\u09ae\u09be\u0987\u0993"
    ],
    "name:ceb_x_preferred":[
        "Maio"
    ],
    "name:deu_x_preferred":[
        "Maio"
    ],
    "name:ell_x_preferred":[
        "\u039c\u03ac\u03b9\u03bf"
    ],
    "name:fas_x_preferred":[
        "\u0645\u0627\u0626\u06cc\u0648"
    ],
    "name:fra_x_preferred":[
        "Maio"
    ],
    "name:heb_x_preferred":[
        "\u05de\u05d0\u05d9\u05e9\u05e4\u05e8\u05e7"
    ],
    "name:hin_x_preferred":[
        "\u092e\u093e\u092f\u0913"
    ],
    "name:hun_x_preferred":[
        "Maio"
    ],
    "name:ind_x_preferred":[
        "Maio"
    ],
    "name:ita_x_preferred":[
        "Maio"
    ],
    "name:por_x_preferred":[
        "Maio"
    ],
    "name:rus_x_preferred":[
        "\u041c\u0430\u044e"
    ],
    "name:swe_x_preferred":[
        "Maio"
    ],
    "name:tur_x_preferred":[
        "Maio"
    ],
    "name:ukr_x_preferred":[
        "\u041c\u0430\u0439\u043e"
    ],
    "name:vie_x_preferred":[
        "\u0110\u1ea3o Maio"
    ],
    "wof:name":"Maio",
    "wof:placetype":"locality"
},
  "geometry": {"coordinates":[9.96667,11.76667],"type":"Point"}
}