{
  "type": "Feature",
  "properties": {
    "gn:admin1_code":"24.0",
    "gn:admin2_code":"405.0",
    "gn:admin3_code":"40510",
    "gn:asciiname":"Shadawa",
    "gn:country_code":"NG",
    "gn:dem":528,
    "gn:feature_class":"P",
    "gn:feature_code":"PPL",
    "gn:name":"Shadawa",
    "gn:population":0,
    "gn:timezone":"Africa/Lagos",
    "iso:country":"NG",
    "wof:name":"Shadawa",
    "wof:placetype":"locality"
},
  "geometry": {"coordinates":[7.87655,12.61175],"type":"Point"}
}