{
  "type": "Feature",
  "properties": {
    "gn:admin1_code":"46.0",
    "gn:admin2_code":"5013.0",
    "gn:admin3_code":"BA1313",
    "gn:asciiname":"Bure",
    "gn:country_code":"NG",
    "gn:dem":351,
    "gn:feature_class":"P",
    "gn:feature_code":"PPL",
    "gn:name":"Bure",
    "gn:population":0,
    "gn:timezone":"Africa/Lagos",
    "iso:country":"NG",
    "name:eng_x_preferred":[
        "Bure"
    ],
    "wof:name":"Bure",
    "wof:placetype":"locality"
},
  "geometry": {"coordinates":[10.78421,10.30818],"type":"Point"}
}