{
  "type": "Feature",
  "properties": {
    "gn:admin1_code":"46.0",
    "gn:admin2_code":"5013.0",
    "gn:admin3_code":"BA1313",
    "gn:asciiname":"Bure",
    "gn:country_code":"NG",
    "gn:dem":351,
    "gn:feature_class":"P",
    "gn:feature_code":"PPL",
    "gn:name":"Bure",
    "gn:population":0,
    "gn:timezone":"Africa/Lagos",
    "iso:country":"NG",
    "name:als_x_preferred":[
        "Bure"
    ],
    "name:bre_x_preferred":[
        "Bure"
    ],
    "name:cat_x_preferred":[
        "Bure"
    ],
    "name:ceb_x_preferred":[
        "Bure"
    ],
    "name:ces_x_preferred":[
        "Bou\u0159e"
    ],
    "name:deu_x_preferred":[
        "Bure"
    ],
    "name:eng_x_preferred":[
        "Bure"
    ],
    "name:epo_x_preferred":[
        "Bure"
    ],
    "name:fra_x_preferred":[
        "Bure"
    ],
    "name:ita_x_preferred":[
        "Bure"
    ],
    "name:ltz_x_preferred":[
        "Bure"
    ],
    "name:nld_x_preferred":[
        "Bure"
    ],
    "name:oci_x_preferred":[
        "Bure"
    ],
    "name:pol_x_preferred":[
        "Bure"
    ],
    "name:por_x_preferred":[
        "Bure"
    ],
    "name:scn_x_preferred":[
        "Bure"
    ],
    "name:spa_x_preferred":[
        "Bure"
    ],
    "name:swe_x_preferred":[
        "Bure"
    ],
    "name:ukr_x_preferred":[
        "\u0411\u044e\u0440"
    ],
    "wof:name":"Bure",
    "wof:placetype":"locality"
},
  "geometry": {"coordinates":[10.78421,10.30818],"type":"Point"}
}