{
  "type": "Feature",
  "properties": {
    "gn:admin1_code":"29.0",
    "gn:admin2_code":"20031.0",
    "gn:admin3_code":"KN0507",
    "gn:asciiname":"Chiromawa",
    "gn:country_code":"NG",
    "gn:dem":548,
    "gn:feature_class":"P",
    "gn:feature_code":"PPL",
    "gn:name":"Chiromawa",
    "gn:population":0,
    "gn:timezone":"Africa/Lagos",
    "iso:country":"NG",
    "wof:name":"Chiromawa",
    "wof:placetype":"locality"
},
  "geometry": {"coordinates":[8.16049,12.31679],"type":"Point"}
}