{
  "type": "Feature",
  "properties": {
    "gn:admin1_code":"21.0",
    "gn:admin2_code":"3010.0",
    "gn:asciiname":"Ibiaku Ikot Oku",
    "gn:country_code":"NG",
    "gn:dem":79,
    "gn:feature_class":"P",
    "gn:feature_code":"PPL",
    "gn:name":"Ibiaku Ikot Oku",
    "gn:population":0,
    "gn:timezone":"Africa/Lagos",
    "iso:country":"NG",
    "wof:name":"Ibiaku Ikot Oku",
    "wof:placetype":"locality"
},
  "geometry": {"coordinates":[7.87244,5.1846],"type":"Point"}
}