{
  "type": "Feature",
  "properties": {
    "gn:admin1_code":"26.0",
    "gn:admin2_code":"7005",
    "gn:asciiname":"Ngbegha",
    "gn:country_code":"NG",
    "gn:dem":157,
    "gn:feature_class":"P",
    "gn:feature_code":"PPL",
    "gn:name":"Ngbegha",
    "gn:population":0,
    "gn:timezone":"Africa/Lagos",
    "iso:country":"NG",
    "wof:name":"Ngbegha",
    "wof:placetype":"locality"
},
  "geometry": {"coordinates":[9.09265,7.27112],"type":"Point"}
}