{
  "type": "Feature",
  "properties": {
    "gn:admin1_code":"16.0",
    "gn:admin2_code":"28016.0",
    "gn:asciiname":"Abo",
    "gn:country_code":"NG",
    "gn:dem":165,
    "gn:feature_class":"P",
    "gn:feature_code":"PPL",
    "gn:name":"Abo",
    "gn:population":0,
    "gn:timezone":"Africa/Lagos",
    "iso:country":"NG",
    "name:ceb_x_preferred":[
        "Abo"
    ],
    "name:ces_x_preferred":[
        "Abo"
    ],
    "name:deu_x_preferred":[
        "Abo"
    ],
    "name:fin_x_preferred":[
        "Abo"
    ],
    "name:fra_x_preferred":[
        "Abo"
    ],
    "name:hye_x_preferred":[
        "\u0531\u0562\u0578"
    ],
    "name:nld_x_preferred":[
        "Abo"
    ],
    "name:rus_x_preferred":[
        "\u0410\u0431\u043e"
    ],
    "name:swe_x_preferred":[
        "Abo"
    ],
    "name:tgl_x_preferred":[
        "Abo"
    ],
    "name:uzb_x_preferred":[
        "Abo"
    ],
    "wof:name":"Abo",
    "wof:placetype":"locality"
},
  "geometry": {"coordinates":[3.46667,7.25],"type":"Point"}
}