{
  "type": "Feature",
  "properties": {
    "gn:admin1_code":"22.0",
    "gn:admin2_code":"9011.0",
    "gn:asciiname":"Nkum Plantation",
    "gn:country_code":"NG",
    "gn:dem":52,
    "gn:feature_class":"P",
    "gn:feature_code":"PPL",
    "gn:name":"Nkum Plantation",
    "gn:population":0,
    "gn:timezone":"Africa/Lagos",
    "iso:country":"NG",
    "wof:name":"Nkum Plantation",
    "wof:placetype":"locality"
},
  "geometry": {"coordinates":[8.6645,5.9852],"type":"Point"}
}