{
  "type": "Feature",
  "properties": {
    "gn:admin1_code":"21.0",
    "gn:admin2_code":"3030.0",
    "gn:asciiname":"Akai Ate",
    "gn:country_code":"NG",
    "gn:dem":38,
    "gn:feature_class":"P",
    "gn:feature_code":"PPL",
    "gn:name":"Akai Ate",
    "gn:population":0,
    "gn:timezone":"Africa/Lagos",
    "iso:country":"NG",
    "wof:name":"Akai Ate",
    "wof:placetype":"locality"
},
  "geometry": {"coordinates":[8.1963,4.719],"type":"Point"}
}