{
  "type": "Feature",
  "properties": {
    "gn:admin1_code":"43.0",
    "gn:asciiname":"Kodong-Jauro",
    "gn:country_code":"NG",
    "gn:dem":221,
    "gn:feature_class":"P",
    "gn:feature_code":"PPL",
    "gn:name":"Kodong-Jauro",
    "gn:population":0,
    "gn:timezone":"Africa/Lagos",
    "iso:country":"NG",
    "name:eng_x_preferred":[
        "Kodong-Jauro"
    ],
    "wof:name":"Kodong-Jauro",
    "wof:placetype":"locality"
},
  "geometry": {"coordinates":[11.55747,9.19855],"type":"Point"}
}