{
  "type": "Feature",
  "properties": {
    "gn:admin1_code":"36.0",
    "gn:admin2_code":"10017.0",
    "gn:asciiname":"Ugbukurusu",
    "gn:country_code":"NG",
    "gn:dem":9,
    "gn:feature_class":"P",
    "gn:feature_code":"PPL",
    "gn:name":"Ugbukurusu",
    "gn:population":0,
    "gn:timezone":"Africa/Lagos",
    "iso:country":"NG",
    "name:und_x_variant":[
        "Bukurusu",
        "Gbukurusu",
        "Ugbukurusu"
    ],
    "wof:name":"Ugbukurusu",
    "wof:placetype":"locality"
},
  "geometry": {"coordinates":[5.60282,5.81884],"type":"Point"}
}