{
  "type": "Feature",
  "properties": {
    "gn:admin1_code":"51.0",
    "gn:admin2_code":"622.0",
    "gn:admin3_code":"62205",
    "gn:asciiname":"Saketa",
    "gn:country_code":"NG",
    "gn:dem":297,
    "gn:feature_class":"P",
    "gn:feature_code":"PPL",
    "gn:name":"Saketa",
    "gn:population":0,
    "gn:timezone":"Africa/Lagos",
    "iso:country":"NG",
    "wof:name":"Saketa",
    "wof:placetype":"locality"
},
  "geometry": {"coordinates":[5.40644,13.20162],"type":"Point"}
}