{
  "type": "Feature",
  "properties": {
    "gn:admin1_code":"31.0",
    "gn:admin2_code":"27009.0",
    "gn:asciiname":"Dado",
    "gn:country_code":"NG",
    "gn:dem":322,
    "gn:feature_class":"P",
    "gn:feature_code":"PPL",
    "gn:name":"Dado",
    "gn:population":0,
    "gn:timezone":"Africa/Lagos",
    "iso:country":"NG",
    "name:ceb_x_preferred":[
        "Dado"
    ],
    "name:deu_x_preferred":[
        "Dado"
    ],
    "name:fas_x_preferred":[
        "\u062f\u0627\u062f\u0648"
    ],
    "name:ita_x_preferred":[
        "Dado"
    ],
    "name:por_x_preferred":[
        "Dado"
    ],
    "name:spa_x_preferred":[
        "Dado"
    ],
    "name:swe_x_preferred":[
        "Dado"
    ],
    "wof:name":"Dado",
    "wof:placetype":"locality"
},
  "geometry": {"coordinates":[6.86755,9.3514],"type":"Point"}
}