{
  "type": "Feature",
  "properties": {
    "gn:admin1_code":"50.0",
    "gn:admin2_code":"33016.0",
    "gn:asciiname":"Idia",
    "gn:country_code":"NG",
    "gn:dem":22,
    "gn:feature_class":"P",
    "gn:feature_code":"PPL",
    "gn:name":"Idia",
    "gn:population":0,
    "gn:timezone":"Africa/Lagos",
    "iso:country":"NG",
    "name:cat_x_preferred":[
        "Idia"
    ],
    "name:fra_x_preferred":[
        "Idia"
    ],
    "name:ibo_x_preferred":[
        "Idia"
    ],
    "name:ind_x_preferred":[
        "Idia"
    ],
    "name:vie_x_preferred":[
        "Idia"
    ],
    "wof:name":"Idia",
    "wof:placetype":"locality"
},
  "geometry": {"coordinates":[6.62216,5.41857],"type":"Point"}
}