{
  "type": "Feature",
  "properties": {
    "gn:admin1_code":"27.0",
    "gn:admin2_code":"120.0",
    "gn:admin3_code":"12006",
    "gn:asciiname":"Kingoa",
    "gn:country_code":"NG",
    "gn:dem":333,
    "gn:feature_class":"P",
    "gn:feature_code":"PPL",
    "gn:name":"Kingoa",
    "gn:population":0,
    "gn:timezone":"Africa/Lagos",
    "iso:country":"NG",
    "wof:name":"Kingoa",
    "wof:placetype":"locality"
},
  "geometry": {"coordinates":[12.89561,12.06464],"type":"Point"}
}