{
  "type": "Feature",
  "properties": {
    "gn:country":"NG",
    "gn:fcode":"PPL",
    "gn:pop":19223,
    "iso:country":"NG",
    "name:eng_x_preferred":[
        "Degema"
    ],
    "qs:name":"Degema Hulk",
    "qs:photos_9r":0,
    "qs:photos_sr":0,
    "qs:pop_sr":"6",
    "wof:name":"Degema Hulk",
    "wof:placetype":"locality",
    "wof:population":19223
},
  "geometry": {"coordinates":[6.752,4.76254],"type":"Point"}
}