{
  "type": "Feature",
  "properties": {
    "gn:admin1_code":"24.0",
    "gn:admin2_code":"408.0",
    "gn:admin3_code":"40810",
    "gn:asciiname":"Pankau",
    "gn:country_code":"NG",
    "gn:dem":658,
    "gn:feature_class":"P",
    "gn:feature_code":"PPL",
    "gn:name":"Pankau",
    "gn:population":0,
    "gn:timezone":"Africa/Lagos",
    "iso:country":"NG",
    "wof:name":"Pankau",
    "wof:placetype":"locality"
},
  "geometry": {"coordinates":[7.61629,11.32494],"type":"Point"}
}