{
  "type": "Feature",
  "properties": {
    "gn:admin1_code":"35.0",
    "gn:admin2_code":"2008",
    "gn:asciiname":"Taso Korkai",
    "gn:country_code":"NG",
    "gn:dem":403,
    "gn:feature_class":"P",
    "gn:feature_code":"PPL",
    "gn:name":"Taso Korkai",
    "gn:population":0,
    "gn:timezone":"Africa/Lagos",
    "iso:country":"NG",
    "wof:name":"Taso Korkai",
    "wof:placetype":"locality"
},
  "geometry": {"coordinates":[12.07694,8.76266],"type":"Point"}
}