{
  "type": "Feature",
  "properties": {
    "gn:admin1_code":"55.0",
    "gn:admin2_code":"16002.0",
    "gn:asciiname":"Mona",
    "gn:country_code":"NG",
    "gn:dem":362,
    "gn:feature_class":"P",
    "gn:feature_code":"PPL",
    "gn:name":"Mona",
    "gn:population":0,
    "gn:timezone":"Africa/Lagos",
    "iso:country":"NG",
    "name:bel_x_preferred":[
        "\u041c\u043e\u043d\u0430"
    ],
    "name:bul_x_preferred":[
        "\u041c\u043e\u043d\u0430"
    ],
    "name:cat_x_preferred":[
        "Mona"
    ],
    "name:ceb_x_preferred":[
        "Mona"
    ],
    "name:ces_x_preferred":[
        "Mona"
    ],
    "name:deu_x_preferred":[
        "Mona"
    ],
    "name:fas_x_preferred":[
        "\u0645\u0648\u0646\u0627"
    ],
    "name:fra_x_preferred":[
        "Mona"
    ],
    "name:heb_x_preferred":[
        "\u05de\u05d5\u05e0\u05d4"
    ],
    "name:ita_x_preferred":[
        "Mona"
    ],
    "name:jpn_x_preferred":[
        "Mona"
    ],
    "name:nld_x_preferred":[
        "Mona"
    ],
    "name:pol_x_preferred":[
        "Mona"
    ],
    "name:por_x_preferred":[
        "Mona"
    ],
    "name:rus_x_preferred":[
        "\u041c\u043e\u043d\u0430"
    ],
    "name:spa_x_preferred":[
        "Mona"
    ],
    "name:srp_x_preferred":[
        "\u041c\u043e\u043d\u0430"
    ],
    "name:swe_x_preferred":[
        "Mona"
    ],
    "name:szl_x_preferred":[
        "Mona"
    ],
    "name:ukr_x_preferred":[
        "\u041c\u043e\u043d\u0430"
    ],
    "wof:name":"Mona",
    "wof:placetype":"locality"
},
  "geometry": {"coordinates":[11.63333,9.68333],"type":"Point"}
}