{
  "type": "Feature",
  "properties": {
    "gn:admin1_code":"43.0",
    "gn:admin2_code":"35014",
    "gn:asciiname":"Gidan Adibatu",
    "gn:country_code":"NG",
    "gn:dem":196,
    "gn:feature_class":"P",
    "gn:feature_code":"PPL",
    "gn:name":"Gidan Adibatu",
    "gn:population":0,
    "gn:timezone":"Africa/Lagos",
    "iso:country":"NG",
    "wof:name":"Gidan Adibatu",
    "wof:placetype":"locality"
},
  "geometry": {"coordinates":[9.8747,7.95318],"type":"Point"}
}