{
  "type": "Feature",
  "properties": {
    "gn:admin1_code":"35.0",
    "gn:asciiname":"Whahemi",
    "gn:country_code":"NG",
    "gn:dem":711,
    "gn:feature_class":"P",
    "gn:feature_code":"PPL",
    "gn:name":"Whahemi",
    "gn:population":0,
    "gn:timezone":"Africa/Lagos",
    "iso:country":"NG",
    "wof:name":"Whahemi",
    "wof:placetype":"locality"
},
  "geometry": {"coordinates":[13.54715,10.59503],"type":"Point"}
}