{
  "type": "Feature",
  "properties": {
    "gn:admin1_code":"40.0",
    "gn:admin2_code":"505.0",
    "gn:admin3_code":"50509",
    "gn:asciiname":"Dabaga",
    "gn:country_code":"NG",
    "gn:dem":219,
    "gn:feature_class":"P",
    "gn:feature_code":"PPL",
    "gn:name":"Dabaga",
    "gn:population":0,
    "gn:timezone":"Africa/Lagos",
    "iso:country":"NG",
    "name:ceb_x_preferred":[
        "Dabaga"
    ],
    "name:deu_x_preferred":[
        "Dabaga"
    ],
    "name:ita_x_preferred":[
        "Dabaga"
    ],
    "name:msa_x_preferred":[
        "Dabaga"
    ],
    "name:ron_x_preferred":[
        "Dabaga"
    ],
    "name:spa_x_preferred":[
        "Dabaga"
    ],
    "wof:name":"Dabaga",
    "wof:placetype":"locality"
},
  "geometry": {"coordinates":[4.31667,11.46667],"type":"Point"}
}