{
  "type": "Feature",
  "properties": {
    "gn:admin1_code":"26.0",
    "gn:asciiname":"Ukwodoko",
    "gn:country_code":"NG",
    "gn:dem":248,
    "gn:feature_class":"P",
    "gn:feature_code":"PPL",
    "gn:name":"Ukwodoko",
    "gn:population":0,
    "gn:timezone":"Africa/Lagos",
    "iso:country":"NG",
    "name:und_x_variant":[
        "Okodoko",
        "Ukwodoko"
    ],
    "wof:name":"Ukwodoko",
    "wof:placetype":"locality"
},
  "geometry": {"coordinates":[7.85159,7.40444],"type":"Point"}
}