{
  "type": "Feature",
  "properties": {
    "gn:admin1_code":"26.0",
    "gn:admin2_code":"7005.0",
    "gn:asciiname":"Iortiel",
    "gn:country_code":"NG",
    "gn:dem":168,
    "gn:feature_class":"P",
    "gn:feature_code":"PPL",
    "gn:name":"Iortiel",
    "gn:population":0,
    "gn:timezone":"Africa/Lagos",
    "iso:country":"NG",
    "name:und_x_variant":[
        "Orban"
    ],
    "wof:name":"Iortiel",
    "wof:placetype":"locality"
},
  "geometry": {"coordinates":[8.95721,7.48211],"type":"Point"}
}