{
  "type": "Feature",
  "properties": {
    "gn:admin1_code":"32.0",
    "gn:admin2_code":"31029.0",
    "gn:asciiname":"Olola",
    "gn:country_code":"NG",
    "gn:dem":302,
    "gn:feature_class":"P",
    "gn:feature_code":"PPL",
    "gn:name":"Olola",
    "gn:population":0,
    "gn:timezone":"Africa/Lagos",
    "iso:country":"NG",
    "wof:name":"Olola",
    "wof:placetype":"locality"
},
  "geometry": {"coordinates":[4.03333,7.86667],"type":"Point"}
}