{
  "type": "Feature",
  "properties": {
    "gn:admin1_code":"40.0",
    "gn:admin2_code":"502.0",
    "gn:admin3_code":"50207",
    "gn:asciiname":"Ungwan Mato",
    "gn:country_code":"NG",
    "gn:dem":218,
    "gn:feature_class":"P",
    "gn:feature_code":"PPL",
    "gn:name":"Ungwan Mato",
    "gn:population":0,
    "gn:timezone":"Africa/Lagos",
    "iso:country":"NG",
    "wof:name":"Ungwan Mato",
    "wof:placetype":"locality"
},
  "geometry": {"coordinates":[3.76093,12.37012],"type":"Point"}
}