{
  "type": "Feature",
  "properties": {
    "gn:admin1_code":"23.0",
    "gn:admin2_code":"19011.0",
    "gn:admin3_code":"KD1102",
    "gn:asciiname":"Kwamdna",
    "gn:country_code":"NG",
    "gn:dem":557,
    "gn:feature_class":"P",
    "gn:feature_code":"PPL",
    "gn:name":"Kwamdna",
    "gn:population":0,
    "gn:timezone":"Africa/Lagos",
    "iso:country":"NG",
    "name:und_x_variant":[
        "Kwaradna"
    ],
    "wof:name":"Kwamdna",
    "wof:placetype":"locality"
},
  "geometry": {"coordinates":[7.30457,9.45367],"type":"Point"}
}