{
  "type": "Feature",
  "properties": {
    "gn:admin1_code":"24.0",
    "gn:admin2_code":"422.0",
    "gn:admin3_code":"42202",
    "gn:asciiname":"Cediya",
    "gn:country_code":"NG",
    "gn:dem":530,
    "gn:feature_class":"P",
    "gn:feature_code":"PPL",
    "gn:name":"Cediya",
    "gn:population":0,
    "gn:timezone":"Africa/Lagos",
    "iso:country":"NG",
    "wof:name":"Cediya",
    "wof:placetype":"locality"
},
  "geometry": {"coordinates":[7.52347,12.62773],"type":"Point"}
}