{
  "type": "Feature",
  "properties": {
    "gn:admin1_code":"29.0",
    "gn:admin2_code":"20011.0",
    "gn:admin3_code":"KN3602",
    "gn:asciiname":"Gidan Gala",
    "gn:country_code":"NG",
    "gn:dem":573,
    "gn:feature_class":"P",
    "gn:feature_code":"PPL",
    "gn:name":"Gidan Gala",
    "gn:population":0,
    "gn:timezone":"Africa/Lagos",
    "iso:country":"NG",
    "wof:name":"Gidan Gala",
    "wof:placetype":"locality"
},
  "geometry": {"coordinates":[8.84903,11.38481],"type":"Point"}
}