{
  "type": "Feature",
  "properties": {
    "gn:admin1_code":"51.0",
    "gn:admin2_code":"604.0",
    "gn:admin3_code":"60401",
    "gn:asciiname":"Almudu",
    "gn:country_code":"NG",
    "gn:dem":287,
    "gn:feature_class":"P",
    "gn:feature_code":"PPL",
    "gn:name":"Almudu",
    "gn:population":0,
    "gn:timezone":"Africa/Lagos",
    "iso:country":"NG",
    "wof:name":"Almudu",
    "wof:placetype":"locality"
},
  "geometry": {"coordinates":[5.85727,13.71497],"type":"Point"}
}