{
  "type": "Feature",
  "properties": {
    "gn:admin1_code":"30.0",
    "gn:admin2_code":"24001.0",
    "gn:asciiname":"Akasekun",
    "gn:country_code":"NG",
    "gn:dem":348,
    "gn:feature_class":"P",
    "gn:feature_code":"PPL",
    "gn:name":"Akasekun",
    "gn:population":0,
    "gn:timezone":"Africa/Lagos",
    "iso:country":"NG",
    "wof:name":"Akasekun",
    "wof:placetype":"locality"
},
  "geometry": {"coordinates":[4.36667,8.41667],"type":"Point"}
}