{
  "type": "Feature",
  "properties": {
    "gn:admin1_code":"40.0",
    "gn:admin2_code":"506.0",
    "gn:admin3_code":"50603",
    "gn:asciiname":"Gwadan Gaji",
    "gn:country_code":"NG",
    "gn:dem":208,
    "gn:feature_class":"P",
    "gn:feature_code":"PPL",
    "gn:name":"Gwadan Gaji",
    "gn:population":0,
    "gn:timezone":"Africa/Lagos",
    "iso:country":"NG",
    "name:und_x_variant":[
        "Gwadandaji",
        "Gwadan Gaji"
    ],
    "wof:name":"Gwadan Gaji",
    "wof:placetype":"locality"
},
  "geometry": {"coordinates":[4.24952,12.48009],"type":"Point"}
}