{
  "type": "Feature",
  "properties": {
    "gn:admin1_code":"24.0",
    "gn:admin2_code":"419.0",
    "gn:admin3_code":"41911",
    "gn:asciiname":"Dakamawa",
    "gn:country_code":"NG",
    "gn:dem":568,
    "gn:feature_class":"P",
    "gn:feature_code":"PPL",
    "gn:name":"Dakamawa",
    "gn:population":0,
    "gn:timezone":"Africa/Lagos",
    "iso:country":"NG",
    "wof:name":"Dakamawa",
    "wof:placetype":"locality"
},
  "geometry": {"coordinates":[7.32196,11.89213],"type":"Point"}
}