{
  "type": "Feature",
  "properties": {
    "gn:admin1_code":"25.0",
    "gn:admin2_code":"4003.0",
    "gn:asciiname":"Oronia-Utu",
    "gn:country_code":"NG",
    "gn:dem":24,
    "gn:feature_class":"P",
    "gn:feature_code":"PPL",
    "gn:name":"Oronia-Utu",
    "gn:population":0,
    "gn:timezone":"Africa/Lagos",
    "iso:country":"NG",
    "name:eng_x_preferred":[
        "Orania-Otu"
    ],
    "name:eng_x_variant":[
        "Oronia-Utu",
        "Oroma Otu"
    ],
    "name:und_x_variant":[
        "Oroma Otu"
    ],
    "wof:name":"Oronia-Utu",
    "wof:placetype":"locality"
},
  "geometry": {"coordinates":[6.86111,6.50987],"type":"Point"}
}