{
  "type": "Feature",
  "properties": {
    "gn:admin1_code":"5.0",
    "gn:admin2_code":"25018.0",
    "gn:asciiname":"Iponri",
    "gn:country_code":"NG",
    "gn:dem":6,
    "gn:feature_class":"P",
    "gn:feature_code":"PPL",
    "gn:name":"Iponri",
    "gn:population":0,
    "gn:timezone":"Africa/Lagos",
    "iso:country":"NG",
    "wof:name":"Iponri",
    "wof:placetype":"neighbourhood"
},
  "geometry": {"coordinates":[3.36611,6.4875],"type":"Point"}
}