{
  "type": "Feature",
  "properties": {
    "gn:admin1_code":"35.0",
    "gn:admin2_code":"2018.0",
    "gn:asciiname":"Wuro Jauro Jabbo",
    "gn:cc2":"NG",
    "gn:country_code":"NG",
    "gn:dem":447,
    "gn:feature_class":"P",
    "gn:feature_code":"PPL",
    "gn:name":"Wuro Jauro Jabbo",
    "gn:population":0,
    "gn:timezone":"Africa/Lagos",
    "iso:country":"NG",
    "name:und_x_variant":[
        "Goila",
        "Wuro Jauro Jabbo"
    ],
    "wof:name":"Wuro Jauro Jabbo",
    "wof:placetype":"locality"
},
  "geometry": {"coordinates":[12.71667,9.96667],"type":"Point"}
}