{
  "type": "Feature",
  "properties": {
    "gn:admin1_code":"43.0",
    "gn:admin2_code":"35016.0",
    "gn:asciiname":"Sobi",
    "gn:country_code":"NG",
    "gn:dem":409,
    "gn:feature_class":"P",
    "gn:feature_code":"PPL",
    "gn:name":"Sobi",
    "gn:population":0,
    "gn:timezone":"Africa/Lagos",
    "iso:country":"NG",
    "wof:name":"Sobi",
    "wof:placetype":"locality"
},
  "geometry": {"coordinates":[11.90209,8.90208],"type":"Point"}
}