{
  "type": "Feature",
  "properties": {
    "gn:admin1_code":"23.0",
    "gn:admin2_code":"19017.0",
    "gn:admin3_code":"KD1707",
    "gn:asciiname":"Ganji",
    "gn:country_code":"NG",
    "gn:dem":826,
    "gn:feature_class":"P",
    "gn:feature_code":"PPL",
    "gn:name":"Ganji",
    "gn:population":0,
    "gn:timezone":"Africa/Lagos",
    "iso:country":"NG",
    "name:ceb_x_preferred":[
        "Ganji"
    ],
    "name:fas_x_preferred":[
        "\u06af\u0646\u062c\u06cc"
    ],
    "name:swe_x_preferred":[
        "Ganji"
    ],
    "wof:name":"Ganji",
    "wof:placetype":"locality"
},
  "geometry": {"coordinates":[8.73481,10.34469],"type":"Point"}
}