{
  "type": "Feature",
  "properties": {
    "gn:admin1_code":"26.0",
    "gn:admin2_code":"7020.0",
    "gn:asciiname":"Angii",
    "gn:country_code":"NG",
    "gn:dem":173,
    "gn:feature_class":"P",
    "gn:feature_code":"PPL",
    "gn:name":"Angii",
    "gn:population":0,
    "gn:timezone":"Africa/Lagos",
    "iso:country":"NG",
    "wof:name":"Angii",
    "wof:placetype":"locality"
},
  "geometry": {"coordinates":[8.82018,7.64422],"type":"Point"}
}