{
  "type": "Feature",
  "properties": {
    "gn:admin1_code":"43.0",
    "gn:admin2_code":"35005.0",
    "gn:asciiname":"Jubu",
    "gn:country_code":"NG",
    "gn:dem":109,
    "gn:feature_class":"P",
    "gn:feature_code":"PPL",
    "gn:name":"Jubu",
    "gn:population":0,
    "gn:timezone":"Africa/Lagos",
    "iso:country":"NG",
    "name:und_x_variant":[
        "Jibu",
        "Jubu"
    ],
    "wof:name":"Jubu",
    "wof:placetype":"locality"
},
  "geometry": {"coordinates":[9.97791,8.29903],"type":"Point"}
}