{
  "type": "Feature",
  "properties": {
    "gn:admin1_code":"35.0",
    "gn:admin2_code":"2018.0",
    "gn:asciiname":"Gwembe",
    "gn:country_code":"NG",
    "gn:dem":398,
    "gn:feature_class":"P",
    "gn:feature_code":"PPL",
    "gn:name":"Gwembe",
    "gn:population":0,
    "gn:timezone":"Africa/Lagos",
    "iso:country":"NG",
    "name:ceb_x_preferred":[
        "Gwembe"
    ],
    "name:deu_x_preferred":[
        "Gwembe"
    ],
    "name:mrj_x_preferred":[
        "\u0413\u0432\u0435\u043c\u0431\u0435"
    ],
    "name:por_x_preferred":[
        "Gwembe"
    ],
    "name:ron_x_preferred":[
        "Gwembe"
    ],
    "name:rus_x_preferred":[
        "\u0413\u0432\u0435\u043c\u0431\u0435"
    ],
    "name:zho_x_preferred":[
        "\u683c\u6eab\u8c9d"
    ],
    "wof:name":"Gwembe",
    "wof:placetype":"locality"
},
  "geometry": {"coordinates":[12.35,9.83333],"type":"Point"}
}