{
  "type": "Feature",
  "properties": {
    "gn:admin1_code":"37.0",
    "gn:admin2_code":"12013.0",
    "gn:asciiname":"Iguelebu",
    "gn:country_code":"NG",
    "gn:dem":38,
    "gn:feature_class":"P",
    "gn:feature_code":"PPL",
    "gn:name":"Iguelebu",
    "gn:population":0,
    "gn:timezone":"Africa/Lagos",
    "iso:country":"NG",
    "name:eng_x_preferred":[
        "Iguelebu"
    ],
    "name:eng_x_variant":[
        "Iguelaba"
    ],
    "wof:name":"Iguelebu",
    "wof:placetype":"locality"
},
  "geometry": {"coordinates":[5.85416,5.95619],"type":"Point"}
}