{
  "type": "Feature",
  "properties": {
    "gn:admin1_code":"40.0",
    "gn:admin2_code":"502.0",
    "gn:admin3_code":"50203",
    "gn:asciiname":"Ungwakade",
    "gn:country_code":"NG",
    "gn:dem":242,
    "gn:feature_class":"P",
    "gn:feature_code":"PPL",
    "gn:name":"Ungwakade",
    "gn:population":0,
    "gn:timezone":"Africa/Lagos",
    "iso:country":"NG",
    "wof:name":"Ungwakade",
    "wof:placetype":"locality"
},
  "geometry": {"coordinates":[4.12892,12.77548],"type":"Point"}
}