{
  "type": "Feature",
  "properties": {
    "gn:admin1_code":"50.0",
    "gn:admin2_code":"33004.0",
    "gn:asciiname":"Belem",
    "gn:country_code":"NG",
    "gn:dem":14,
    "gn:feature_class":"P",
    "gn:feature_code":"PPL",
    "gn:name":"Belem",
    "gn:population":0,
    "gn:timezone":"Africa/Lagos",
    "iso:country":"NG",
    "name:und_x_variant":[
        "Belema",
        "Gbelema"
    ],
    "wof:name":"Belem",
    "wof:placetype":"locality"
},
  "geometry": {"coordinates":[6.65411,4.38003],"type":"Point"}
}