{
  "type": "Feature",
  "properties": {
    "gn:admin1_code":"29.0",
    "gn:asciiname":"Jankollawa",
    "gn:country_code":"NG",
    "gn:dem":589,
    "gn:feature_class":"P",
    "gn:feature_code":"PPL",
    "gn:name":"Jankollawa",
    "gn:population":0,
    "gn:timezone":"Africa/Lagos",
    "iso:country":"NG",
    "wof:name":"Jankollawa",
    "wof:placetype":"locality"
},
  "geometry": {"coordinates":[7.83361,11.87925],"type":"Point"}
}