{
  "type": "Feature",
  "properties": {
    "gn:admin1_code":"43.0",
    "gn:admin2_code":"35009.0",
    "gn:asciiname":"Gidan Sarakin Samari",
    "gn:country_code":"NG",
    "gn:dem":255,
    "gn:feature_class":"P",
    "gn:feature_code":"PPL",
    "gn:name":"Gidan Sarakin Samari",
    "gn:population":0,
    "gn:timezone":"Africa/Lagos",
    "iso:country":"NG",
    "name:und_x_variant":[
        "Sarakin Samari",
        "Gidan Sarakin Samari"
    ],
    "wof:name":"Gidan Sarakin Samari",
    "wof:placetype":"locality"
},
  "geometry": {"coordinates":[10.5759,7.313],"type":"Point"}
}