{
  "type": "Feature",
  "properties": {
    "gn:admin1_code":"39.0",
    "gn:admin2_code":"18018.0",
    "gn:admin3_code":"JI0501",
    "gn:asciiname":"Abore",
    "gn:country_code":"NG",
    "gn:dem":411,
    "gn:feature_class":"P",
    "gn:feature_code":"PPL",
    "gn:name":"Abore",
    "gn:population":0,
    "gn:timezone":"Africa/Lagos",
    "iso:country":"NG",
    "wof:name":"Abore",
    "wof:placetype":"locality"
},
  "geometry": {"coordinates":[9.76551,11.61332],"type":"Point"}
}