{
  "type": "Feature",
  "properties": {
    "gn:admin1_code":"42.0",
    "gn:admin2_code":"30010.0",
    "gn:asciiname":"Songbe",
    "gn:cc2":"NG",
    "gn:country_code":"NG",
    "gn:dem":302,
    "gn:feature_class":"P",
    "gn:feature_code":"PPL",
    "gn:name":"Songbe",
    "gn:population":0,
    "gn:timezone":"Africa/Lagos",
    "iso:country":"NG",
    "name:und_x_variant":[
        "Shawmawgbe",
        "Songbe"
    ],
    "wof:name":"Songbe",
    "wof:placetype":"locality"
},
  "geometry": {"coordinates":[4.31667,7.75],"type":"Point"}
}