{
  "type": "Feature",
  "properties": {
    "gn:admin1_code":"43.0",
    "gn:admin2_code":"35010.0",
    "gn:asciiname":"Jirlahi",
    "gn:country_code":"NG",
    "gn:dem":192,
    "gn:feature_class":"P",
    "gn:feature_code":"PPL",
    "gn:name":"Jirlahi",
    "gn:population":0,
    "gn:timezone":"Africa/Lagos",
    "iso:country":"NG",
    "name:eng_x_preferred":[
        "Jirlahi"
    ],
    "name:und_x_variant":[
        "Gidan Jilehi"
    ],
    "wof:name":"Jirlahi",
    "wof:placetype":"locality"
},
  "geometry": {"coordinates":[11.51919,9.22378],"type":"Point"}
}