{
  "type": "Feature",
  "properties": {
    "gn:admin1_code":"21.0",
    "gn:admin2_code":"3023.0",
    "gn:asciiname":"Idua Asan",
    "gn:country_code":"NG",
    "gn:dem":25,
    "gn:feature_class":"P",
    "gn:feature_code":"PPL",
    "gn:name":"Idua Asan",
    "gn:population":0,
    "gn:timezone":"Africa/Lagos",
    "iso:country":"NG",
    "wof:name":"Idua Asan",
    "wof:placetype":"locality"
},
  "geometry": {"coordinates":[8.1868,4.8407],"type":"Point"}
}