{
  "type": "Feature",
  "properties": {
    "gn:admin1_code":"21.0",
    "gn:admin2_code":"3008.0",
    "gn:asciiname":"Okposo",
    "gn:country_code":"NG",
    "gn:dem":-9999,
    "gn:feature_class":"P",
    "gn:feature_code":"PPL",
    "gn:name":"Okposo",
    "gn:population":0,
    "gn:timezone":"Africa/Lagos",
    "iso:country":"NG",
    "name:und_x_variant":[
        "Inua Abasi",
        "Okposo"
    ],
    "wof:name":"Okposo",
    "wof:placetype":"locality"
},
  "geometry": {"coordinates":[8.29475,4.56159],"type":"Point"}
}