{
  "type": "Feature",
  "properties": {
    "gn:admin1_code":"26.0",
    "gn:admin2_code":"7008",
    "gn:asciiname":"Agbede",
    "gn:country_code":"NG",
    "gn:dem":126,
    "gn:feature_class":"P",
    "gn:feature_code":"PPL",
    "gn:name":"Agbede",
    "gn:population":0,
    "gn:timezone":"Africa/Lagos",
    "iso:country":"NG",
    "wof:name":"Agbede",
    "wof:placetype":"locality"
},
  "geometry": {"coordinates":[8.23808,7.62369],"type":"Point"}
}