{
  "type": "Feature",
  "properties": {
    "gn:admin1_code":"40.0",
    "gn:admin2_code":"509.0",
    "gn:admin3_code":"50908",
    "gn:asciiname":"Gari Danteni",
    "gn:country_code":"NG",
    "gn:dem":272,
    "gn:feature_class":"P",
    "gn:feature_code":"PPL",
    "gn:name":"Gari Danteni",
    "gn:population":0,
    "gn:timezone":"Africa/Lagos",
    "iso:country":"NG",
    "wof:name":"Gari Danteni",
    "wof:placetype":"locality"
},
  "geometry": {"coordinates":[4.97168,11.53991],"type":"Point"}
}