{
  "type": "Feature",
  "properties": {
    "gn:admin1_code":"27.0",
    "gn:admin2_code":"127.0",
    "gn:admin3_code":"12710",
    "gn:asciiname":"Galu",
    "gn:country_code":"NG",
    "gn:dem":247,
    "gn:feature_class":"P",
    "gn:feature_code":"PPL",
    "gn:name":"Galu",
    "gn:population":0,
    "gn:timezone":"Africa/Lagos",
    "iso:country":"NG",
    "wof:name":"Galu",
    "wof:placetype":"locality"
},
  "geometry": {"coordinates":[11.97277,10.18875],"type":"Point"}
}