{
  "type": "Feature",
  "properties": {
    "gn:admin1_code":"48.0",
    "gn:admin2_code":"29013.0",
    "gn:asciiname":"Odigbo",
    "gn:country_code":"NG",
    "gn:dem":113,
    "gn:feature_class":"P",
    "gn:feature_code":"PPL",
    "gn:name":"Odigbo",
    "gn:population":0,
    "gn:timezone":"Africa/Lagos",
    "iso:country":"NG",
    "wof:name":"Odigbo",
    "wof:placetype":"locality"
},
  "geometry": {"coordinates":[4.8664,6.78922],"type":"Point"}
}