{
  "type": "Feature",
  "properties": {
    "gn:admin1_code":"43.0",
    "gn:asciiname":"Keru",
    "gn:country_code":"NG",
    "gn:dem":222,
    "gn:feature_class":"P",
    "gn:feature_code":"PPL",
    "gn:name":"Keru",
    "gn:population":0,
    "gn:timezone":"Africa/Lagos",
    "iso:country":"NG",
    "name:ceb_x_preferred":[
        "Kieru"
    ],
    "name:eng_x_preferred":[
        "Keru"
    ],
    "name:fra_x_preferred":[
        "Keru"
    ],
    "name:swe_x_preferred":[
        "Kieru"
    ],
    "wof:name":"Keru",
    "wof:placetype":"locality"
},
  "geometry": {"coordinates":[10.97261,9.41454],"type":"Point"}
}