{
  "type": "Feature",
  "properties": {
    "gn:admin1_code":"32.0",
    "gn:admin2_code":"31033.0",
    "gn:asciiname":"Aho",
    "gn:cc2":"NG",
    "gn:country_code":"NG",
    "gn:dem":366,
    "gn:feature_class":"P",
    "gn:feature_code":"PPL",
    "gn:name":"Aho",
    "gn:population":0,
    "gn:timezone":"Africa/Lagos",
    "iso:country":"NG",
    "name:ceb_x_preferred":[
        "Aho"
    ],
    "name:ces_x_preferred":[
        "Aho"
    ],
    "name:deu_x_preferred":[
        "Aho"
    ],
    "name:fin_x_preferred":[
        "Aho"
    ],
    "name:kaz_x_preferred":[
        "\u0410\u0445\u043e"
    ],
    "name:rus_x_preferred":[
        "\u0410\u0445\u043e"
    ],
    "name:slv_x_preferred":[
        "Aho"
    ],
    "name:swe_x_preferred":[
        "Aho"
    ],
    "name:ukr_x_preferred":[
        "\u0410\u0445\u043e"
    ],
    "name:und_x_variant":[
        "Ahoyaya"
    ],
    "wof:name":"Aho",
    "wof:placetype":"locality"
},
  "geometry": {"coordinates":[4.38333,8.28333],"type":"Point"}
}