{
  "type": "Feature",
  "properties": {
    "gn:admin1_code":"26.0",
    "gn:admin2_code":"7009",
    "gn:asciiname":"Ordorogh",
    "gn:country_code":"NG",
    "gn:dem":202,
    "gn:feature_class":"P",
    "gn:feature_code":"PPL",
    "gn:name":"Ordorogh",
    "gn:population":0,
    "gn:timezone":"Africa/Lagos",
    "iso:country":"NG",
    "wof:name":"Ordorogh",
    "wof:placetype":"locality"
},
  "geometry": {"coordinates":[9.48447,7.16091],"type":"Point"}
}