{
  "type": "Feature",
  "properties": {
    "gn:admin1_code":"46.0",
    "gn:admin2_code":"5007.0",
    "gn:admin3_code":"BA0717",
    "gn:asciiname":"Gilik",
    "gn:country_code":"NG",
    "gn:dem":389,
    "gn:feature_class":"P",
    "gn:feature_code":"PPL",
    "gn:name":"Gilik",
    "gn:population":0,
    "gn:timezone":"Africa/Lagos",
    "iso:country":"NG",
    "wof:name":"Gilik",
    "wof:placetype":"locality"
},
  "geometry": {"coordinates":[10.5561,11.6749],"type":"Point"}
}