{
  "type": "Feature",
  "properties": {
    "gn:admin1_code":"28.0",
    "gn:admin2_code":"17012.0",
    "gn:asciiname":"Amaibo",
    "gn:country_code":"NG",
    "gn:dem":81,
    "gn:feature_class":"P",
    "gn:feature_code":"PPL",
    "gn:name":"Amaibo",
    "gn:population":0,
    "gn:timezone":"Africa/Lagos",
    "iso:country":"NG",
    "wof:name":"Amaibo",
    "wof:placetype":"locality"
},
  "geometry": {"coordinates":[7.12565,5.38242],"type":"Point"}
}