{
  "type": "Feature",
  "properties": {
    "gn:admin1_code":"26.0",
    "gn:admin2_code":"7013",
    "gn:asciiname":"Honge",
    "gn:country_code":"NG",
    "gn:dem":90,
    "gn:feature_class":"P",
    "gn:feature_code":"PPL",
    "gn:name":"Honge",
    "gn:population":0,
    "gn:timezone":"Africa/Lagos",
    "iso:country":"NG",
    "wof:name":"Honge",
    "wof:placetype":"neighbourhood"
},
  "geometry": {"coordinates":[8.49588,7.70059],"type":"Point"}
}