{
  "type": "Feature",
  "properties": {
    "gn:admin1_code":"37.0",
    "gn:admin2_code":"12014.0",
    "gn:asciiname":"Agepanu",
    "gn:country_code":"NG",
    "gn:dem":29,
    "gn:feature_class":"P",
    "gn:feature_code":"PPL",
    "gn:name":"Agepanu",
    "gn:population":0,
    "gn:timezone":"Africa/Lagos",
    "iso:country":"NG",
    "name:und_x_variant":[
        "Agepano",
        "Agepanu"
    ],
    "wof:name":"Agepanu",
    "wof:placetype":"locality"
},
  "geometry": {"coordinates":[5.56798,6.69048],"type":"Point"}
}