{
  "type": "Feature",
  "properties": {
    "gn:admin1_code":"44.0",
    "gn:admin2_code":"705",
    "gn:admin3_code":"70501",
    "gn:asciiname":"Termoa",
    "gn:country_code":"NG",
    "gn:dem":355,
    "gn:feature_class":"P",
    "gn:feature_code":"PPL",
    "gn:name":"Termoa",
    "gn:population":0,
    "gn:timezone":"Africa/Lagos",
    "iso:country":"NG",
    "wof:name":"Termoa",
    "wof:placetype":"locality"
},
  "geometry": {"coordinates":[11.69934,11.57585],"type":"Point"}
}