{
  "type": "Feature",
  "properties": {
    "gn:admin1_code":"31.0",
    "gn:admin2_code":"27004.0",
    "gn:asciiname":"Shafaci",
    "gn:country_code":"NG",
    "gn:dem":195,
    "gn:feature_class":"P",
    "gn:feature_code":"PPL",
    "gn:name":"Shafaci",
    "gn:population":0,
    "gn:timezone":"Africa/Lagos",
    "iso:country":"NG",
    "wof:name":"Shafaci",
    "wof:placetype":"locality"
},
  "geometry": {"coordinates":[4.30746,10.79884],"type":"Point"}
}