{
  "type": "Feature",
  "properties": {
    "gn:admin1_code":"48.0",
    "gn:admin2_code":"29007.0",
    "gn:asciiname":"Shabomi",
    "gn:country_code":"NG",
    "gn:dem":6,
    "gn:feature_class":"P",
    "gn:feature_code":"PPL",
    "gn:name":"Shabomi",
    "gn:population":0,
    "gn:timezone":"Africa/Lagos",
    "iso:country":"NG",
    "wof:name":"Shabomi",
    "wof:placetype":"locality"
},
  "geometry": {"coordinates":[4.89107,6.43808],"type":"Point"}
}