{
  "type": "Feature",
  "properties": {
    "gn:admin1_code":"46.0",
    "gn:admin2_code":"5018.0",
    "gn:admin3_code":"BA1816",
    "gn:asciiname":"Barakin French",
    "gn:country_code":"NG",
    "gn:dem":946,
    "gn:feature_class":"P",
    "gn:feature_code":"PPL",
    "gn:name":"Barakin French",
    "gn:population":0,
    "gn:timezone":"Africa/Lagos",
    "iso:country":"NG",
    "wof:name":"Barakin French",
    "wof:placetype":"locality"
},
  "geometry": {"coordinates":[8.96606,10.44691],"type":"Point"}
}