{
  "type": "Feature",
  "properties": {
    "gn:admin1_code":"40.0",
    "gn:admin2_code":"518.0",
    "gn:admin3_code":"51801",
    "gn:asciiname":"Tungan Daudu",
    "gn:country_code":"NG",
    "gn:dem":159,
    "gn:feature_class":"P",
    "gn:feature_code":"PPL",
    "gn:name":"Tungan Daudu",
    "gn:population":0,
    "gn:timezone":"Africa/Lagos",
    "iso:country":"NG",
    "wof:name":"Tungan Daudu",
    "wof:placetype":"locality"
},
  "geometry": {"coordinates":[3.95077,11.62623],"type":"Point"}
}