{
  "type": "Feature",
  "properties": {
    "gn:admin1_code":"46.0",
    "gn:admin2_code":"5018.0",
    "gn:admin3_code":"BA1814",
    "gn:asciiname":"Mana",
    "gn:country_code":"NG",
    "gn:dem":811,
    "gn:feature_class":"P",
    "gn:feature_code":"PPL",
    "gn:name":"Mana",
    "gn:population":0,
    "gn:timezone":"Africa/Lagos",
    "iso:country":"NG",
    "wof:name":"Mana",
    "wof:placetype":"locality"
},
  "geometry": {"coordinates":[9.09255,10.36917],"type":"Point"}
}