{
  "type": "Feature",
  "properties": {
    "gn:admin1_code":"23.0",
    "gn:admin2_code":"19008.0",
    "gn:admin3_code":"KD0805",
    "gn:asciiname":"Atakfe",
    "gn:country_code":"NG",
    "gn:dem":516,
    "gn:feature_class":"P",
    "gn:feature_code":"PPL",
    "gn:name":"Atakfe",
    "gn:population":0,
    "gn:timezone":"Africa/Lagos",
    "iso:country":"NG",
    "wof:name":"Atakfe",
    "wof:placetype":"locality"
},
  "geometry": {"coordinates":[7.41667,10.11667],"type":"Point"}
}