{
  "type": "Feature",
  "properties": {
    "gn:admin1_code":"35.0",
    "gn:admin2_code":"2003.0",
    "gn:asciiname":"Kotulo",
    "gn:country_code":"NG",
    "gn:dem":515,
    "gn:feature_class":"P",
    "gn:feature_code":"PPL",
    "gn:name":"Kotulo",
    "gn:population":0,
    "gn:timezone":"Africa/Lagos",
    "iso:country":"NG",
    "wof:name":"Kotulo",
    "wof:placetype":"locality"
},
  "geometry": {"coordinates":[11.93522,8.65253],"type":"Point"}
}