{
  "type": "Feature",
  "properties": {
    "gn:admin1_code":"22.0",
    "gn:admin2_code":"9003.0",
    "gn:asciiname":"Akansoko",
    "gn:country_code":"NG",
    "gn:dem":17,
    "gn:feature_class":"P",
    "gn:feature_code":"PPL",
    "gn:name":"Akansoko",
    "gn:population":0,
    "gn:timezone":"Africa/Lagos",
    "iso:country":"NG",
    "wof:name":"Akansoko",
    "wof:placetype":"locality"
},
  "geometry": {"coordinates":[8.46005,5.02143],"type":"Point"}
}