{
  "type": "Feature",
  "properties": {
    "gn:admin1_code":"31.0",
    "gn:admin2_code":"27004.0",
    "gn:asciiname":"Shafaci",
    "gn:country_code":"NG",
    "gn:dem":224,
    "gn:feature_class":"P",
    "gn:feature_code":"PPL",
    "gn:name":"Shafaci",
    "gn:population":0,
    "gn:timezone":"Africa/Lagos",
    "iso:country":"NG",
    "name:und_x_variant":[
        "Shafasiri",
        "Shafaci"
    ],
    "wof:name":"Shafaci",
    "wof:placetype":"locality"
},
  "geometry": {"coordinates":[4.29497,10.89848],"type":"Point"}
}