{
  "type": "Feature",
  "properties": {
    "gn:admin1_code":"24.0",
    "gn:admin2_code":"413.0",
    "gn:admin3_code":"41305",
    "gn:asciiname":"Mai Mashekeri",
    "gn:country_code":"NG",
    "gn:dem":592,
    "gn:feature_class":"P",
    "gn:feature_code":"PPL",
    "gn:name":"Mai Mashekeri",
    "gn:population":0,
    "gn:timezone":"Africa/Lagos",
    "iso:country":"NG",
    "wof:name":"Mai Mashekeri",
    "wof:placetype":"locality"
},
  "geometry": {"coordinates":[7.2822,11.7619],"type":"Point"}
}