{
  "type": "Feature",
  "properties": {
    "gn:admin1_code":"23.0",
    "gn:admin2_code":"19001.0",
    "gn:admin3_code":"KD0106",
    "gn:asciiname":"Kurbau",
    "gn:country_code":"NG",
    "gn:dem":391,
    "gn:feature_class":"P",
    "gn:feature_code":"PPL",
    "gn:name":"Kurbau",
    "gn:population":0,
    "gn:timezone":"Africa/Lagos",
    "iso:country":"NG",
    "wof:name":"Kurbau",
    "wof:placetype":"locality"
},
  "geometry": {"coordinates":[6.18333,10.61667],"type":"Point"}
}