{
  "type": "Feature",
  "properties": {
    "gn:admin1_code":"39.0",
    "gn:admin2_code":"18026.0",
    "gn:admin3_code":"JI1406",
    "gn:asciiname":"Nahuche",
    "gn:country_code":"NG",
    "gn:dem":376,
    "gn:feature_class":"P",
    "gn:feature_code":"PPL",
    "gn:name":"Nahuche",
    "gn:population":0,
    "gn:timezone":"Africa/Lagos",
    "iso:country":"NG",
    "wof:name":"Nahuche",
    "wof:placetype":"locality"
},
  "geometry": {"coordinates":[9.55332,12.12963],"type":"Point"}
}