{
  "type": "Feature",
  "properties": {
    "gn:admin1_code":"21.0",
    "gn:admin2_code":"3012.0",
    "gn:asciiname":"Ukpap-Itak",
    "gn:country_code":"NG",
    "gn:dem":77,
    "gn:feature_class":"P",
    "gn:feature_code":"PPL",
    "gn:name":"Ukpap-Itak",
    "gn:population":0,
    "gn:timezone":"Africa/Lagos",
    "iso:country":"NG",
    "name:und_x_variant":[
        "Ukap Itak",
        "Ukpap-Itak"
    ],
    "wof:name":"Ukpap-Itak",
    "wof:placetype":"locality"
},
  "geometry": {"coordinates":[7.82192,5.07452],"type":"Point"}
}