{
  "type": "Feature",
  "properties": {
    "gn:admin1_code":"26.0",
    "gn:admin2_code":"7019.0",
    "gn:asciiname":"Ogam",
    "gn:country_code":"NG",
    "gn:dem":172,
    "gn:feature_class":"P",
    "gn:feature_code":"PPL",
    "gn:name":"Ogam",
    "gn:population":0,
    "gn:timezone":"Africa/Lagos",
    "iso:country":"NG",
    "wof:name":"Ogam",
    "wof:placetype":"locality"
},
  "geometry": {"coordinates":[8.03554,7.35275],"type":"Point"}
}