{
  "type": "Feature",
  "properties": {
    "gn:admin1_code":"50.0",
    "gn:admin2_code":"33001.0",
    "gn:asciiname":"Okolomade",
    "gn:country_code":"NG",
    "gn:dem":9,
    "gn:feature_class":"P",
    "gn:feature_code":"PPL",
    "gn:name":"Okolomade",
    "gn:population":0,
    "gn:timezone":"Africa/Lagos",
    "iso:country":"NG",
    "name:und_x_variant":[
        "Okolomada",
        "Okolomade"
    ],
    "wof:name":"Okolomade",
    "wof:placetype":"locality"
},
  "geometry": {"coordinates":[6.48868,4.85027],"type":"Point"}
}