{
  "type": "Feature",
  "properties": {
    "gn:admin1_code":"48.0",
    "gn:admin2_code":"29011.0",
    "gn:asciiname":"Awopeju",
    "gn:country_code":"NG",
    "gn:dem":213,
    "gn:feature_class":"P",
    "gn:feature_code":"PPL",
    "gn:name":"Awopeju",
    "gn:population":0,
    "gn:timezone":"Africa/Lagos",
    "iso:country":"NG",
    "wof:name":"Awopeju",
    "wof:placetype":"locality"
},
  "geometry": {"coordinates":[4.76667,7.23333],"type":"Point"}
}