{
  "type": "Feature",
  "properties": {
    "gn:admin1_code":"57.0",
    "gn:admin2_code":"805.0",
    "gn:admin3_code":"80502",
    "gn:asciiname":"Tudun Haki",
    "gn:country_code":"NG",
    "gn:dem":489,
    "gn:feature_class":"P",
    "gn:feature_code":"PPL",
    "gn:name":"Tudun Haki",
    "gn:population":0,
    "gn:timezone":"Africa/Lagos",
    "iso:country":"NG",
    "name:und_x_variant":[
        "Haki",
        "Tungan Haki",
        "Tungar Haki",
        "Tudun Haki"
    ],
    "wof:name":"Tudun Haki",
    "wof:placetype":"locality"
},
  "geometry": {"coordinates":[6.58055,11.96037],"type":"Point"}
}