{
  "type": "Feature",
  "properties": {
    "gn:admin1_code":"57.0",
    "gn:admin2_code":"804.0",
    "gn:admin3_code":"80402",
    "gn:asciiname":"Sadawa",
    "gn:country_code":"NG",
    "gn:dem":269,
    "gn:feature_class":"P",
    "gn:feature_code":"PPL",
    "gn:name":"Sadawa",
    "gn:population":0,
    "gn:timezone":"Africa/Lagos",
    "iso:country":"NG",
    "wof:name":"Sadawa",
    "wof:placetype":"locality"
},
  "geometry": {"coordinates":[5.46403,12.16512],"type":"Point"}
}