{
  "type": "Feature",
  "properties": {
    "gn:admin1_code":"51.0",
    "gn:admin2_code":"609.0",
    "gn:admin3_code":"60910",
    "gn:asciiname":"Gimbama",
    "gn:country_code":"NG",
    "gn:dem":336,
    "gn:feature_class":"P",
    "gn:feature_code":"PPL",
    "gn:name":"Gimbama",
    "gn:population":0,
    "gn:timezone":"Africa/Lagos",
    "iso:country":"NG",
    "wof:name":"Gimbama",
    "wof:placetype":"locality"
},
  "geometry": {"coordinates":[6.01981,13.305],"type":"Point"}
}