{
  "type": "Feature",
  "properties": {
    "gn:admin1_code":"25.0",
    "gn:admin2_code":"4013",
    "gn:asciiname":"Nimo Owele",
    "gn:country_code":"NG",
    "gn:dem":85,
    "gn:feature_class":"P",
    "gn:feature_code":"PPL",
    "gn:name":"Nimo Owele",
    "gn:population":0,
    "gn:timezone":"Africa/Lagos",
    "iso:country":"NG",
    "wof:name":"Nimo Owele",
    "wof:placetype":"locality"
},
  "geometry": {"coordinates":[6.97491,6.13724],"type":"Point"}
}