{
  "type": "Feature",
  "properties": {
    "gn:admin1_code":"50.0",
    "gn:asciiname":"Biriyegbene",
    "gn:country_code":"NG",
    "gn:dem":28,
    "gn:feature_class":"P",
    "gn:feature_code":"PPL",
    "gn:name":"Biriyegbene",
    "gn:population":0,
    "gn:timezone":"Africa/Lagos",
    "iso:country":"NG",
    "wof:name":"Biriyegbene",
    "wof:placetype":"locality"
},
  "geometry": {"coordinates":[6.34989,5.23611],"type":"Point"}
}