{
  "type": "Feature",
  "properties": {
    "gn:admin1_code":"31.0",
    "gn:admin2_code":"27022",
    "gn:asciiname":"Gidan Tawali",
    "gn:country_code":"NG",
    "gn:dem":265,
    "gn:feature_class":"P",
    "gn:feature_code":"PPL",
    "gn:name":"Gidan Tawali",
    "gn:population":0,
    "gn:timezone":"Africa/Lagos",
    "iso:country":"NG",
    "wof:name":"Gidan Tawali",
    "wof:placetype":"locality"
},
  "geometry": {"coordinates":[6.60728,9.8444],"type":"Point"}
}