{
  "type": "Feature",
  "properties": {
    "gn:admin1_code":"26.0",
    "gn:admin2_code":"7021",
    "gn:asciiname":"Uzade",
    "gn:country_code":"NG",
    "gn:dem":184,
    "gn:feature_class":"P",
    "gn:feature_code":"PPL",
    "gn:name":"Uzade",
    "gn:population":0,
    "gn:timezone":"Africa/Lagos",
    "iso:country":"NG",
    "wof:name":"Uzade",
    "wof:placetype":"locality"
},
  "geometry": {"coordinates":[9.51983,7.54214],"type":"Point"}
}