{
  "type": "Feature",
  "properties": {
    "gn:admin1_code":"26.0",
    "gn:admin2_code":"7011.0",
    "gn:asciiname":"Adikpo",
    "gn:country_code":"NG",
    "gn:dem":241,
    "gn:feature_class":"P",
    "gn:feature_code":"PPLA2",
    "gn:name":"Adikpo",
    "gn:population":0,
    "gn:timezone":"Africa/Lagos",
    "iso:country":"NG",
    "wof:name":"Adikpo",
    "wof:placetype":"locality"
},
  "geometry": {"coordinates":[9.23351,6.89002],"type":"Point"}
}