{
  "type": "Feature",
  "properties": {
    "gn:admin1_code":"51.0",
    "gn:admin2_code":"605.0",
    "gn:admin3_code":"60504",
    "gn:asciiname":"Tuluka",
    "gn:country_code":"NG",
    "gn:dem":280,
    "gn:feature_class":"P",
    "gn:feature_code":"PPL",
    "gn:name":"Tuluka",
    "gn:population":0,
    "gn:timezone":"Africa/Lagos",
    "iso:country":"NG",
    "name:und_x_variant":[
        "Taluka",
        "Taloka",
        "Tuluka"
    ],
    "wof:name":"Tuluka",
    "wof:placetype":"locality"
},
  "geometry": {"coordinates":[5.69633,13.44703],"type":"Point"}
}