{
  "type": "Feature",
  "properties": {
    "gn:admin1_code":"43.0",
    "gn:admin2_code":"35015.0",
    "gn:asciiname":"Danwangwore",
    "gn:country_code":"NG",
    "gn:dem":343,
    "gn:feature_class":"P",
    "gn:feature_code":"PPL",
    "gn:name":"Danwangwore",
    "gn:population":0,
    "gn:timezone":"Africa/Lagos",
    "iso:country":"NG",
    "wof:name":"Danwangwore",
    "wof:placetype":"locality"
},
  "geometry": {"coordinates":[11.41248,8.99671],"type":"Point"}
}