{
  "type": "Feature",
  "properties": {
    "gn:admin1_code":"27.0",
    "gn:admin2_code":"105.0",
    "gn:admin3_code":"10504",
    "gn:asciiname":"Bara",
    "gn:country_code":"NG",
    "gn:dem":670,
    "gn:feature_class":"P",
    "gn:feature_code":"PPL",
    "gn:name":"Bara",
    "gn:population":0,
    "gn:timezone":"Africa/Lagos",
    "iso:country":"NG",
    "wof:name":"Bara",
    "wof:placetype":"locality"
},
  "geometry": {"coordinates":[12.09263,10.71939],"type":"Point"}
}