{
  "type": "Feature",
  "properties": {
    "gn:admin1_code":"49.0",
    "gn:asciiname":"Hoton",
    "gn:country_code":"NG",
    "gn:dem":1298,
    "gn:feature_class":"P",
    "gn:feature_code":"PPL",
    "gn:name":"Hoton",
    "gn:population":0,
    "gn:timezone":"Africa/Lagos",
    "iso:country":"NG",
    "name:ceb_x_preferred":[
        "Hoton"
    ],
    "name:cym_x_preferred":[
        "Hoton"
    ],
    "name:nld_x_preferred":[
        "Hoton"
    ],
    "name:pol_x_preferred":[
        "Hoton"
    ],
    "name:swe_x_preferred":[
        "Hoton"
    ],
    "wof:name":"Hoton",
    "wof:placetype":"locality"
},
  "geometry": {"coordinates":[8.83134,9.21727],"type":"Point"}
}