{
  "type": "Feature",
  "properties": {
    "gn:admin1_code":"52.0",
    "gn:admin2_code":"6002.0",
    "gn:asciiname":"Bilabri Ilaje",
    "gn:country_code":"NG",
    "gn:dem":110,
    "gn:feature_class":"P",
    "gn:feature_code":"PPL",
    "gn:name":"Bilabri Ilaje",
    "gn:population":0,
    "gn:timezone":"Africa/Lagos",
    "iso:country":"NG",
    "name:eng_x_preferred":[
        "Bilabri Ilaje"
    ],
    "wof:name":"Bilabri Ilaje",
    "wof:placetype":"locality"
},
  "geometry": {"coordinates":[5.50051,4.81751],"type":"Point"}
}