{
  "type": "Feature",
  "properties": {
    "gn:admin1_code":"48.0",
    "gn:admin2_code":"29017.0",
    "gn:asciiname":"Owojalaye",
    "gn:country_code":"NG",
    "gn:dem":163,
    "gn:feature_class":"P",
    "gn:feature_code":"PPL",
    "gn:name":"Owojalaye",
    "gn:population":0,
    "gn:timezone":"Africa/Lagos",
    "iso:country":"NG",
    "name:und_x_variant":[
        "Owajalaiye",
        "Owojalaye"
    ],
    "wof:name":"Owojalaye",
    "wof:placetype":"locality"
},
  "geometry": {"coordinates":[5.62212,6.93777],"type":"Point"}
}