{
  "type": "Feature",
  "properties": {
    "gn:admin1_code":"31.0",
    "gn:admin2_code":"27018.0",
    "gn:asciiname":"Kuchi",
    "gn:country_code":"NG",
    "gn:dem":420,
    "gn:feature_class":"P",
    "gn:feature_code":"PPL",
    "gn:name":"Kuchi",
    "gn:population":0,
    "gn:timezone":"Africa/Lagos",
    "iso:country":"NG",
    "wof:name":"Kuchi",
    "wof:placetype":"locality"
},
  "geometry": {"coordinates":[6.97853,9.88672],"type":"Point"}
}