{
  "type": "Feature",
  "properties": {
    "gn:admin1_code":"23.0",
    "gn:admin2_code":"19015.0",
    "gn:admin3_code":"KD1501",
    "gn:asciiname":"Jenau",
    "gn:country_code":"NG",
    "gn:dem":684,
    "gn:feature_class":"P",
    "gn:feature_code":"PPL",
    "gn:name":"Jenau",
    "gn:population":0,
    "gn:timezone":"Africa/Lagos",
    "iso:country":"NG",
    "wof:name":"Jenau",
    "wof:placetype":"locality"
},
  "geometry": {"coordinates":[8.32243,10.8959],"type":"Point"}
}