{
  "type": "Feature",
  "properties": {
    "gn:admin1_code":"57.0",
    "gn:admin2_code":"805.0",
    "gn:admin3_code":"80508",
    "gn:asciiname":"Murai",
    "gn:country_code":"NG",
    "gn:dem":426,
    "gn:feature_class":"P",
    "gn:feature_code":"PPL",
    "gn:name":"Murai",
    "gn:population":0,
    "gn:timezone":"Africa/Lagos",
    "iso:country":"NG",
    "name:deu_x_preferred":[
        "Murai"
    ],
    "name:ind_x_preferred":[
        "Murai"
    ],
    "wof:name":"Murai",
    "wof:placetype":"locality"
},
  "geometry": {"coordinates":[6.51507,12.35911],"type":"Point"}
}