{
  "type": "Feature",
  "properties": {
    "gn:admin1_code":"40.0",
    "gn:admin2_code":"509.0",
    "gn:admin3_code":"50901",
    "gn:asciiname":"Ubege",
    "gn:country_code":"NG",
    "gn:dem":233,
    "gn:feature_class":"P",
    "gn:feature_code":"PPL",
    "gn:name":"Ubege",
    "gn:population":0,
    "gn:timezone":"Africa/Lagos",
    "iso:country":"NG",
    "wof:name":"Ubege",
    "wof:placetype":"locality"
},
  "geometry": {"coordinates":[4.93362,11.37544],"type":"Point"}
}