{
  "type": "Feature",
  "properties": {
    "gn:admin1_code":"35.0",
    "gn:asciiname":"Ndakare",
    "gn:country_code":"NG",
    "gn:dem":190,
    "gn:feature_class":"P",
    "gn:feature_code":"PPL",
    "gn:name":"Ndakare",
    "gn:population":0,
    "gn:timezone":"Africa/Lagos",
    "iso:country":"NG",
    "name:eng_x_preferred":[
        "Ndakare"
    ],
    "wof:name":"Ndakare",
    "wof:placetype":"locality"
},
  "geometry": {"coordinates":[12.47589,9.14701],"type":"Point"}
}