{
  "type": "Feature",
  "properties": {
    "gn:admin1_code":"45.0",
    "gn:admin2_code":"1008.0",
    "gn:asciiname":"Umoazi",
    "gn:country_code":"NG",
    "gn:dem":89,
    "gn:feature_class":"P",
    "gn:feature_code":"PPL",
    "gn:name":"Umoazi",
    "gn:population":0,
    "gn:timezone":"Africa/Lagos",
    "iso:country":"NG",
    "wof:name":"Umoazi",
    "wof:placetype":"locality"
},
  "geometry": {"coordinates":[7.53198,5.82307],"type":"Point"}
}