{
  "type": "Feature",
  "properties": {
    "gn:admin1_code":"24.0",
    "gn:admin2_code":"422.0",
    "gn:admin3_code":"42202",
    "gn:asciiname":"Birci",
    "gn:country_code":"NG",
    "gn:dem":559,
    "gn:feature_class":"P",
    "gn:feature_code":"PPL",
    "gn:name":"Birci",
    "gn:population":0,
    "gn:timezone":"Africa/Lagos",
    "iso:country":"NG",
    "name:und_x_variant":[
        "Bichi",
        "Birchi",
        "Birci"
    ],
    "wof:name":"Birci",
    "wof:placetype":"locality"
},
  "geometry": {"coordinates":[7.50088,12.59089],"type":"Point"}
}