{
  "type": "Feature",
  "properties": {
    "gn:admin1_code":"31.0",
    "gn:admin2_code":"27023.0",
    "gn:asciiname":"Kuchiko",
    "gn:country_code":"NG",
    "gn:dem":503,
    "gn:feature_class":"P",
    "gn:feature_code":"PPL",
    "gn:name":"Kuchiko",
    "gn:population":0,
    "gn:timezone":"Africa/Lagos",
    "iso:country":"NG",
    "wof:name":"Kuchiko",
    "wof:placetype":"locality"
},
  "geometry": {"coordinates":[7.18548,9.26644],"type":"Point"}
}