{
  "type": "Feature",
  "properties": {
    "gn:admin1_code":"27.0",
    "gn:admin2_code":"101.0",
    "gn:admin3_code":"10104",
    "gn:asciiname":"Daljiwa",
    "gn:country_code":"NG",
    "gn:dem":295,
    "gn:feature_class":"P",
    "gn:feature_code":"PPL",
    "gn:name":"Daljiwa",
    "gn:population":0,
    "gn:timezone":"Africa/Lagos",
    "iso:country":"NG",
    "wof:name":"Daljiwa",
    "wof:placetype":"locality"
},
  "geometry": {"coordinates":[13.0831,13.38077],"type":"Point"}
}