{
  "type": "Feature",
  "properties": {
    "gn:admin1_code":"21.0",
    "gn:admin2_code":"3017.0",
    "gn:asciiname":"Ebughu",
    "gn:country_code":"NG",
    "gn:dem":9,
    "gn:feature_class":"P",
    "gn:feature_code":"PPL",
    "gn:name":"Ebughu",
    "gn:population":0,
    "gn:timezone":"Africa/Lagos",
    "iso:country":"NG",
    "name:und_x_variant":[
        "Ebuhu",
        "Ebugha",
        "Ebughu"
    ],
    "wof:name":"Ebughu",
    "wof:placetype":"locality"
},
  "geometry": {"coordinates":[8.26515,4.67914],"type":"Point"}
}