{
  "type": "Feature",
  "properties": {
    "gn:admin1_code":"31.0",
    "gn:admin2_code":"27007.0",
    "gn:asciiname":"Tsantsaga",
    "gn:country_code":"NG",
    "gn:dem":77,
    "gn:feature_class":"P",
    "gn:feature_code":"PPL",
    "gn:name":"Tsantsaga",
    "gn:population":0,
    "gn:timezone":"Africa/Lagos",
    "iso:country":"NG",
    "wof:name":"Tsantsaga",
    "wof:placetype":"locality"
},
  "geometry": {"coordinates":[6.107,9.06985],"type":"Point"}
}