{
  "type": "Feature",
  "properties": {
    "gn:admin1_code":"22.0",
    "gn:admin2_code":"9016.0",
    "gn:asciiname":"Eka Ekong",
    "gn:country_code":"NG",
    "gn:dem":48,
    "gn:feature_class":"P",
    "gn:feature_code":"PPL",
    "gn:name":"Eka Ekong",
    "gn:population":0,
    "gn:timezone":"Africa/Lagos",
    "iso:country":"NG",
    "name:und_x_variant":[
        "Ekakong"
    ],
    "wof:name":"Eka Ekong",
    "wof:placetype":"locality"
},
  "geometry": {"coordinates":[8.53082,6.41166],"type":"Point"}
}