{
  "type": "Feature",
  "properties": {
    "gn:admin1_code":"21.0",
    "gn:admin2_code":"3031.0",
    "gn:asciiname":"Iba-Oku",
    "gn:country_code":"NG",
    "gn:dem":25,
    "gn:feature_class":"P",
    "gn:feature_code":"PPL",
    "gn:name":"Iba-Oku",
    "gn:population":0,
    "gn:timezone":"Africa/Lagos",
    "iso:country":"NG",
    "wof:name":"Iba-Oku",
    "wof:placetype":"locality"
},
  "geometry": {"coordinates":[7.95102,5.05797],"type":"Point"}
}