{
  "type": "Feature",
  "properties": {
    "gn:admin1_code":"24.0",
    "gn:admin2_code":"433.0",
    "gn:admin3_code":"43310",
    "gn:asciiname":"Juba",
    "gn:country_code":"NG",
    "gn:dem":474,
    "gn:feature_class":"P",
    "gn:feature_code":"PPL",
    "gn:name":"Juba",
    "gn:population":0,
    "gn:timezone":"Africa/Lagos",
    "iso:country":"NG",
    "wof:name":"Juba",
    "wof:placetype":"locality"
},
  "geometry": {"coordinates":[8.39444,12.85665],"type":"Point"}
}