{
  "type": "Feature",
  "properties": {
    "gn:admin1_code":"57.0",
    "gn:admin2_code":"801.0",
    "gn:admin3_code":"80103",
    "gn:asciiname":"Gargam",
    "gn:country_code":"NG",
    "gn:dem":367,
    "gn:feature_class":"P",
    "gn:feature_code":"PPL",
    "gn:name":"Gargam",
    "gn:population":0,
    "gn:timezone":"Africa/Lagos",
    "iso:country":"NG",
    "wof:name":"Gargam",
    "wof:placetype":"locality"
},
  "geometry": {"coordinates":[5.91109,11.9794],"type":"Point"}
}