{
  "type": "Feature",
  "properties": {
    "gn:admin1_code":"23.0",
    "gn:admin2_code":"19008",
    "gn:admin3_code":"KD0803",
    "gn:asciiname":"Iriyau",
    "gn:country_code":"NG",
    "gn:dem":592,
    "gn:feature_class":"P",
    "gn:feature_code":"PPL",
    "gn:name":"Iriyau",
    "gn:population":0,
    "gn:timezone":"Africa/Lagos",
    "iso:country":"NG",
    "wof:name":"Iriyau",
    "wof:placetype":"locality"
},
  "geometry": {"coordinates":[7.68503,9.73565],"type":"Point"}
}