{
  "type": "Feature",
  "properties": {
    "gn:admin1_code":"31.0",
    "gn:admin2_code":"27013",
    "gn:asciiname":"Ezza",
    "gn:country_code":"NG",
    "gn:dem":157,
    "gn:feature_class":"P",
    "gn:feature_code":"PPL",
    "gn:name":"Ezza",
    "gn:population":0,
    "gn:timezone":"Africa/Lagos",
    "iso:country":"NG",
    "wof:name":"Ezza",
    "wof:placetype":"locality"
},
  "geometry": {"coordinates":[5.55619,9.45288],"type":"Point"}
}