{
  "type": "Feature",
  "properties": {
    "gn:admin1_code":"43.0",
    "gn:admin2_code":"35002",
    "gn:asciiname":"Jengbari",
    "gn:country_code":"NG",
    "gn:dem":1360,
    "gn:feature_class":"P",
    "gn:feature_code":"PPL",
    "gn:name":"Jengbari",
    "gn:population":0,
    "gn:timezone":"Africa/Lagos",
    "iso:country":"NG",
    "wof:name":"Jengbari",
    "wof:placetype":"locality"
},
  "geometry": {"coordinates":[11.75858,8.59102],"type":"Point"}
}