{
  "type": "Feature",
  "properties": {
    "gn:admin1_code":"39.0",
    "gn:admin2_code":"18023.0",
    "gn:admin3_code":"JI2006",
    "gn:asciiname":"Tarana",
    "gn:country_code":"NG",
    "gn:dem":365,
    "gn:feature_class":"P",
    "gn:feature_code":"PPL",
    "gn:name":"Tarana",
    "gn:population":0,
    "gn:timezone":"Africa/Lagos",
    "iso:country":"NG",
    "name:ben_x_preferred":[
        "\u09a4\u09be\u09b0\u09be\u09a8\u09be"
    ],
    "name:bpy_x_preferred":[
        "\u09a4\u09be\u09b0\u09be\u09a8\u09be"
    ],
    "name:ceb_x_preferred":[
        "Tar\u0101na"
    ],
    "name:fra_x_preferred":[
        "Tar\u00e2n\u00e2"
    ],
    "name:ita_x_preferred":[
        "Tarana"
    ],
    "name:mar_x_preferred":[
        "\u0924\u0930\u093e\u0923\u093e"
    ],
    "name:msa_x_preferred":[
        "Tarana"
    ],
    "name:nld_x_preferred":[
        "Tarana"
    ],
    "name:ori_x_preferred":[
        "\u0b24\u0b3e\u0b30\u0b3e\u0b28\u0b3e"
    ],
    "name:por_x_preferred":[
        "Tarana"
    ],
    "name:spa_x_preferred":[
        "Tarana"
    ],
    "name:swe_x_preferred":[
        "Tar\u0101na"
    ],
    "name:urd_x_preferred":[
        "\u062a\u0631\u0627\u0646\u06c1"
    ],
    "name:vie_x_preferred":[
        "Tarana"
    ],
    "wof:name":"Tarana",
    "wof:placetype":"locality"
},
  "geometry": {"coordinates":[9.56405,12.6442],"type":"Point"}
}