{
  "type": "Feature",
  "properties": {
    "gn:admin1_code":"43.0",
    "gn:admin2_code":"35015.0",
    "gn:asciiname":"Dikasa",
    "gn:country_code":"NG",
    "gn:dem":421,
    "gn:feature_class":"P",
    "gn:feature_code":"PPL",
    "gn:name":"Dikasa",
    "gn:population":0,
    "gn:timezone":"Africa/Lagos",
    "iso:country":"NG",
    "wof:name":"Dikasa",
    "wof:placetype":"locality"
},
  "geometry": {"coordinates":[11.5362,8.94872],"type":"Point"}
}