{
  "type": "Feature",
  "properties": {
    "gn:admin1_code":"37.0",
    "gn:admin2_code":"12005",
    "gn:asciiname":"Jobruse",
    "gn:country_code":"NG",
    "gn:dem":269,
    "gn:feature_class":"P",
    "gn:feature_code":"PPL",
    "gn:name":"Jobruse",
    "gn:population":0,
    "gn:timezone":"Africa/Lagos",
    "iso:country":"NG",
    "wof:name":"Jobruse",
    "wof:placetype":"locality"
},
  "geometry": {"coordinates":[6.44436,6.64702],"type":"Point"}
}