{
  "type": "Feature",
  "properties": {
    "gn:admin1_code":"23.0",
    "gn:admin2_code":"19005.0",
    "gn:admin3_code":"KD0502",
    "gn:asciiname":"Ungwan Mai Randa",
    "gn:country_code":"NG",
    "gn:dem":681,
    "gn:feature_class":"P",
    "gn:feature_code":"PPL",
    "gn:name":"Ungwan Mai Randa",
    "gn:population":0,
    "gn:timezone":"Africa/Lagos",
    "iso:country":"NG",
    "wof:name":"Ungwan Mai Randa",
    "wof:placetype":"locality"
},
  "geometry": {"coordinates":[8.19941,11.1532],"type":"Point"}
}