{
  "type": "Feature",
  "properties": {
    "gn:admin1_code":"27.0",
    "gn:admin2_code":"107.0",
    "gn:admin3_code":"10702",
    "gn:asciiname":"Yerwa",
    "gn:country_code":"NG",
    "gn:dem":389,
    "gn:feature_class":"P",
    "gn:feature_code":"PPL",
    "gn:name":"Yerwa",
    "gn:population":0,
    "gn:timezone":"Africa/Lagos",
    "iso:country":"NG",
    "wof:name":"Yerwa",
    "wof:placetype":"locality"
},
  "geometry": {"coordinates":[12.87386,11.21003],"type":"Point"}
}