{
  "type": "Feature",
  "properties": {
    "gn:admin1_code":"43.0",
    "gn:asciiname":"Kawa",
    "gn:country_code":"NG",
    "gn:dem":239,
    "gn:feature_class":"P",
    "gn:feature_code":"PPL",
    "gn:name":"Kawa",
    "gn:population":0,
    "gn:timezone":"Africa/Lagos",
    "iso:country":"NG",
    "name:ceb_x_preferred":[
        "Kawa"
    ],
    "name:deu_x_preferred":[
        "Kawa"
    ],
    "name:eng_x_preferred":[
        "Kawa"
    ],
    "name:fra_x_preferred":[
        "Kawa"
    ],
    "name:kur_x_preferred":[
        "Kawa"
    ],
    "name:pol_x_preferred":[
        "Kawa"
    ],
    "name:swe_x_preferred":[
        "Kawa"
    ],
    "wof:name":"Kawa",
    "wof:placetype":"locality"
},
  "geometry": {"coordinates":[10.92176,9.3379],"type":"Point"}
}