{
  "type": "Feature",
  "properties": {
    "gn:admin1_code":"29.0",
    "gn:admin2_code":"20015.0",
    "gn:admin3_code":"KN3909",
    "gn:asciiname":"Langyal",
    "gn:country_code":"NG",
    "gn:dem":465,
    "gn:feature_class":"P",
    "gn:feature_code":"PPL",
    "gn:name":"Langyal",
    "gn:population":0,
    "gn:timezone":"Africa/Lagos",
    "iso:country":"NG",
    "wof:name":"Langyal",
    "wof:placetype":"locality"
},
  "geometry": {"coordinates":[8.40007,11.9917],"type":"Point"}
}