{
  "type": "Feature",
  "properties": {
    "gn:admin1_code":"21.0",
    "gn:admin2_code":"3005.0",
    "gn:asciiname":"Ukana",
    "gn:country_code":"NG",
    "gn:dem":85,
    "gn:feature_class":"P",
    "gn:feature_code":"PPL",
    "gn:name":"Ukana",
    "gn:population":0,
    "gn:timezone":"Africa/Lagos",
    "iso:country":"NG",
    "wof:name":"Ukana",
    "wof:placetype":"locality"
},
  "geometry": {"coordinates":[7.77334,5.12427],"type":"Point"}
}