{
  "type": "Feature",
  "properties": {
    "gn:admin1_code":"52.0",
    "gn:admin2_code":"6007.0",
    "gn:asciiname":"Okutoroeka",
    "gn:country_code":"NG",
    "gn:dem":2,
    "gn:feature_class":"P",
    "gn:feature_code":"PPL",
    "gn:name":"Okutoroeka",
    "gn:population":0,
    "gn:timezone":"Africa/Lagos",
    "iso:country":"NG",
    "name:eng_x_preferred":[
        "Okutoroeka"
    ],
    "wof:name":"Okutoroeka",
    "wof:placetype":"locality"
},
  "geometry": {"coordinates":[5.72086,4.62497],"type":"Point"}
}