{
  "type": "Feature",
  "properties": {
    "gn:admin1_code":"40.0",
    "gn:admin2_code":"514.0",
    "gn:admin3_code":"51404",
    "gn:asciiname":"Kawaran Manu",
    "gn:country_code":"NG",
    "gn:dem":228,
    "gn:feature_class":"P",
    "gn:feature_code":"PPL",
    "gn:name":"Kawaran Manu",
    "gn:population":0,
    "gn:timezone":"Africa/Lagos",
    "iso:country":"NG",
    "name:und_x_variant":[
        "Kawara Manu",
        "Kawaran Manu",
        "Kwaran Manu"
    ],
    "wof:name":"Kawaran Manu",
    "wof:placetype":"locality"
},
  "geometry": {"coordinates":[4.23482,11.99749],"type":"Point"}
}