{
  "type": "Feature",
  "properties": {
    "gn:admin1_code":"42.0",
    "gn:admin2_code":"30021.0",
    "gn:asciiname":"Oloro",
    "gn:country_code":"NG",
    "gn:dem":183,
    "gn:feature_class":"P",
    "gn:feature_code":"PPL",
    "gn:name":"Oloro",
    "gn:population":0,
    "gn:timezone":"Africa/Lagos",
    "iso:country":"NG",
    "wof:name":"Oloro",
    "wof:placetype":"locality"
},
  "geometry": {"coordinates":[4.16667,7.43333],"type":"Point"}
}