{
  "type": "Feature",
  "properties": {
    "gn:admin1_code":"27.0",
    "gn:admin2_code":"103.0",
    "gn:admin3_code":"10312",
    "gn:asciiname":"Jangurori",
    "gn:country_code":"NG",
    "gn:dem":339,
    "gn:feature_class":"P",
    "gn:feature_code":"PPL",
    "gn:name":"Jangurori",
    "gn:population":0,
    "gn:timezone":"Africa/Lagos",
    "iso:country":"NG",
    "wof:name":"Jangurori",
    "wof:placetype":"locality"
},
  "geometry": {"coordinates":[13.77522,11.4273],"type":"Point"}
}