{
  "type": "Feature",
  "properties": {
    "gn:admin1_code":"35.0",
    "gn:admin2_code":"2007.0",
    "gn:asciiname":"Gashala-Mamuda",
    "gn:country_code":"NG",
    "gn:dem":514,
    "gn:feature_class":"P",
    "gn:feature_code":"PPL",
    "gn:name":"Gashala-Mamuda",
    "gn:population":0,
    "gn:timezone":"Africa/Lagos",
    "iso:country":"NG",
    "wof:name":"Gashala-Mamuda",
    "wof:placetype":"locality"
},
  "geometry": {"coordinates":[13.08731,10.37946],"type":"Point"}
}