{
  "type": "Feature",
  "properties": {
    "gn:admin1_code":"26.0",
    "gn:admin2_code":"7023",
    "gn:asciiname":"Asua",
    "gn:country_code":"NG",
    "gn:dem":218,
    "gn:feature_class":"P",
    "gn:feature_code":"PPL",
    "gn:name":"Asua",
    "gn:population":0,
    "gn:timezone":"Africa/Lagos",
    "iso:country":"NG",
    "wof:name":"Asua",
    "wof:placetype":"locality"
},
  "geometry": {"coordinates":[9.03471,7.02695],"type":"Point"}
}