{
  "type": "Feature",
  "properties": {
    "gn:admin1_code":"29.0",
    "gn:admin2_code":"20008.0",
    "gn:admin3_code":"KN4006",
    "gn:asciiname":"Rage",
    "gn:country_code":"NG",
    "gn:dem":537,
    "gn:feature_class":"P",
    "gn:feature_code":"PPL",
    "gn:name":"Rage",
    "gn:population":0,
    "gn:timezone":"Africa/Lagos",
    "iso:country":"NG",
    "name:ces_x_preferred":[
        "Rage"
    ],
    "name:deu_x_preferred":[
        "Rage"
    ],
    "name:fin_x_preferred":[
        "Rage"
    ],
    "name:fra_x_preferred":[
        "Rage"
    ],
    "name:hun_x_preferred":[
        "Rage"
    ],
    "name:ita_x_preferred":[
        "Rage"
    ],
    "name:jpn_x_preferred":[
        "\u30ec\u30a4\u30b8"
    ],
    "name:kor_x_preferred":[
        "\ub808\uc774\uc9c0"
    ],
    "name:nld_x_preferred":[
        "Rage"
    ],
    "name:pol_x_preferred":[
        "Rage"
    ],
    "name:por_x_preferred":[
        "Rage"
    ],
    "name:rus_x_preferred":[
        "Rage"
    ],
    "name:slk_x_preferred":[
        "Rage"
    ],
    "name:spa_x_preferred":[
        "Rage"
    ],
    "name:swe_x_preferred":[
        "Rage"
    ],
    "name:ukr_x_preferred":[
        "Rage"
    ],
    "wof:name":"Rage",
    "wof:placetype":"locality"
},
  "geometry": {"coordinates":[8.07507,12.27466],"type":"Point"}
}