{
  "type": "Feature",
  "properties": {
    "gn:admin1_code":"29.0",
    "gn:admin2_code":"20008.0",
    "gn:admin3_code":"KN4006",
    "gn:asciiname":"Rage",
    "gn:country_code":"NG",
    "gn:dem":537,
    "gn:feature_class":"P",
    "gn:feature_code":"PPL",
    "gn:name":"Rage",
    "gn:population":0,
    "gn:timezone":"Africa/Lagos",
    "iso:country":"NG",
    "wof:name":"Rage",
    "wof:placetype":"locality"
},
  "geometry": {"coordinates":[8.07507,12.27466],"type":"Point"}
}