{
  "type": "Feature",
  "properties": {
    "gn:admin1_code":"40.0",
    "gn:admin2_code":"505.0",
    "gn:admin3_code":"50501",
    "gn:asciiname":"Tunga Ulu",
    "gn:country_code":"NG",
    "gn:dem":158,
    "gn:feature_class":"P",
    "gn:feature_code":"PPL",
    "gn:name":"Tunga Ulu",
    "gn:population":0,
    "gn:timezone":"Africa/Lagos",
    "iso:country":"NG",
    "wof:name":"Tunga Ulu",
    "wof:placetype":"locality"
},
  "geometry": {"coordinates":[4.22997,11.37878],"type":"Point"}
}