{
  "type": "Feature",
  "properties": {
    "gn:admin1_code":"51.0",
    "gn:admin2_code":"619.0",
    "gn:admin3_code":"61910",
    "gn:asciiname":"Lamsani",
    "gn:country_code":"NG",
    "gn:dem":259,
    "gn:feature_class":"P",
    "gn:feature_code":"PPL",
    "gn:name":"Lamsani",
    "gn:population":0,
    "gn:timezone":"Africa/Lagos",
    "iso:country":"NG",
    "name:und_x_variant":[
        "Labsani",
        "Lamsani"
    ],
    "wof:name":"Lamsani",
    "wof:placetype":"locality"
},
  "geometry": {"coordinates":[4.84768,13.4148],"type":"Point"}
}