{
  "type": "Feature",
  "properties": {
    "gn:admin1_code":"40.0",
    "gn:admin2_code":"507.0",
    "gn:admin3_code":"50710",
    "gn:asciiname":"Banganna",
    "gn:country_code":"NG",
    "gn:dem":203,
    "gn:feature_class":"P",
    "gn:feature_code":"PPL",
    "gn:name":"Banganna",
    "gn:population":0,
    "gn:timezone":"Africa/Lagos",
    "iso:country":"NG",
    "name:und_x_variant":[
        "Tungan Manun Kulu",
        "Banganna"
    ],
    "wof:name":"Banganna",
    "wof:placetype":"locality"
},
  "geometry": {"coordinates":[3.96239,12.29763],"type":"Point"}
}