{
  "type": "Feature",
  "properties": {
    "gn:admin1_code":"16.0",
    "gn:admin2_code":"28005.0",
    "gn:asciiname":"Alapa",
    "gn:country_code":"NG",
    "gn:dem":36,
    "gn:feature_class":"P",
    "gn:feature_code":"PPL",
    "gn:name":"Alapa",
    "gn:population":0,
    "gn:timezone":"Africa/Lagos",
    "iso:country":"NG",
    "wof:name":"Alapa",
    "wof:placetype":"locality"
},
  "geometry": {"coordinates":[2.91667,6.78333],"type":"Point"}
}