{
  "type": "Feature",
  "properties": {
    "gn:admin1_code":"37.0",
    "gn:admin2_code":"12013.0",
    "gn:asciiname":"Akure",
    "gn:country_code":"NG",
    "gn:dem":10,
    "gn:feature_class":"P",
    "gn:feature_code":"PPL",
    "gn:name":"Akure",
    "gn:population":0,
    "gn:timezone":"Africa/Lagos",
    "iso:country":"NG",
    "name:azb_x_preferred":[
        "\u0627\u06a9\u0648\u0631\u0647"
    ],
    "name:cat_x_preferred":[
        "Akure"
    ],
    "name:ceb_x_preferred":[
        "Akure"
    ],
    "name:deu_x_preferred":[
        "Akure"
    ],
    "name:epo_x_preferred":[
        "Akure"
    ],
    "name:fas_x_preferred":[
        "\u0627\u06a9\u0648\u0631\u0647"
    ],
    "name:fin_x_preferred":[
        "Akure"
    ],
    "name:fra_x_preferred":[
        "Akure"
    ],
    "name:hau_x_preferred":[
        "Akure"
    ],
    "name:heb_x_preferred":[
        "\u05d0\u05e7\u05d5\u05e8\u05d4"
    ],
    "name:hrv_x_preferred":[
        "Akure"
    ],
    "name:hun_x_preferred":[
        "Akure"
    ],
    "name:ibo_x_preferred":[
        "Akure"
    ],
    "name:ita_x_preferred":[
        "Akure"
    ],
    "name:jpn_x_preferred":[
        "\u30a2\u30af\u30ec"
    ],
    "name:kor_x_preferred":[
        "\uc544\ucfe0\ub808"
    ],
    "name:lav_x_preferred":[
        "Akure"
    ],
    "name:lit_x_preferred":[
        "Akur\u0117"
    ],
    "name:nld_x_preferred":[
        "Akure"
    ],
    "name:nor_x_preferred":[
        "Akure"
    ],
    "name:pol_x_preferred":[
        "Akure"
    ],
    "name:por_x_preferred":[
        "Akure"
    ],
    "name:ron_x_preferred":[
        "Akure"
    ],
    "name:rus_x_preferred":[
        "\u0410\u043a\u0443\u0440\u0435"
    ],
    "name:spa_x_preferred":[
        "Akure"
    ],
    "name:swe_x_preferred":[
        "Akure"
    ],
    "name:ukr_x_preferred":[
        "\u0410\u043a\u0443\u0440\u0435"
    ],
    "name:urd_x_preferred":[
        "\u0627\u06a9\u0648\u0631\u06d2"
    ],
    "name:yor_x_preferred":[
        "\u00c0k\u00far\u1eb9\u0301"
    ],
    "name:zho_x_preferred":[
        "\u963f\u5eab\u96f7"
    ],
    "wof:name":"Akure",
    "wof:placetype":"locality"
},
  "geometry": {"coordinates":[6.01484,5.77156],"type":"Point"}
}