{
  "type": "Feature",
  "properties": {
    "gn:admin1_code":"40.0",
    "gn:admin2_code":"508.0",
    "gn:admin3_code":"50806",
    "gn:asciiname":"Tungan Bajida",
    "gn:country_code":"NG",
    "gn:dem":195,
    "gn:feature_class":"P",
    "gn:feature_code":"PPL",
    "gn:name":"Tungan Bajida",
    "gn:population":0,
    "gn:timezone":"Africa/Lagos",
    "iso:country":"NG",
    "wof:name":"Tungan Bajida",
    "wof:placetype":"locality"
},
  "geometry": {"coordinates":[3.67295,11.90686],"type":"Point"}
}