{
  "type": "Feature",
  "properties": {
    "gn:admin1_code":"44.0",
    "gn:admin2_code":"705.0",
    "gn:admin3_code":"70513",
    "gn:asciiname":"Madi",
    "gn:country_code":"NG",
    "gn:dem":378,
    "gn:feature_class":"P",
    "gn:feature_code":"PPL",
    "gn:name":"Madi",
    "gn:population":0,
    "gn:timezone":"Africa/Lagos",
    "iso:country":"NG",
    "name:cat_x_preferred":[
        "Madi"
    ],
    "name:ceb_x_preferred":[
        "Madi"
    ],
    "name:deu_x_preferred":[
        "Madi"
    ],
    "name:fra_x_preferred":[
        "Madi"
    ],
    "name:swe_x_preferred":[
        "Madi"
    ],
    "wof:name":"Madi",
    "wof:placetype":"locality"
},
  "geometry": {"coordinates":[11.04058,11.96],"type":"Point"}
}