{
  "type": "Feature",
  "properties": {
    "gn:admin1_code":"35.0",
    "gn:admin2_code":"2005.0",
    "gn:asciiname":"Umuara",
    "gn:country_code":"NG",
    "gn:dem":349,
    "gn:feature_class":"P",
    "gn:feature_code":"PPL",
    "gn:name":"Umuara",
    "gn:population":0,
    "gn:timezone":"Africa/Lagos",
    "iso:country":"NG",
    "name:ceb_x_preferred":[
        "Umuara"
    ],
    "name:fra_x_preferred":[
        "Umuara"
    ],
    "name:nld_x_preferred":[
        "Umuara"
    ],
    "name:spa_x_preferred":[
        "Umuara"
    ],
    "name:swe_x_preferred":[
        "Umuara"
    ],
    "name:vie_x_preferred":[
        "Umuara"
    ],
    "name:war_x_preferred":[
        "Umuara"
    ],
    "wof:name":"Umuara",
    "wof:placetype":"locality"
},
  "geometry": {"coordinates":[12.44276,10.29138],"type":"Point"}
}