{
  "type": "Feature",
  "properties": {
    "gn:admin1_code":"46.0",
    "gn:admin2_code":"5018.0",
    "gn:admin3_code":"BA1810",
    "gn:asciiname":"Barakin Wundi",
    "gn:country_code":"NG",
    "gn:dem":875,
    "gn:feature_class":"P",
    "gn:feature_code":"PPL",
    "gn:name":"Barakin Wundi",
    "gn:population":0,
    "gn:timezone":"Africa/Lagos",
    "iso:country":"NG",
    "wof:name":"Barakin Wundi",
    "wof:placetype":"locality"
},
  "geometry": {"coordinates":[8.9058,10.47319],"type":"Point"}
}