{
  "type": "Feature",
  "properties": {
    "gn:admin1_code":"29.0",
    "gn:admin2_code":"20004.0",
    "gn:admin3_code":"KN0107",
    "gn:asciiname":"Paima",
    "gn:country_code":"NG",
    "gn:dem":405,
    "gn:feature_class":"P",
    "gn:feature_code":"PPL",
    "gn:name":"Paima",
    "gn:population":0,
    "gn:timezone":"Africa/Lagos",
    "iso:country":"NG",
    "wof:name":"Paima",
    "wof:placetype":"locality"
},
  "geometry": {"coordinates":[8.9409,12.04276],"type":"Point"}
}