{
  "type": "Feature",
  "properties": {
    "gn:admin1_code":"29.0",
    "gn:admin2_code":"20016.0",
    "gn:admin3_code":"KN1301",
    "gn:asciiname":"Asayaya",
    "gn:country_code":"NG",
    "gn:dem":405,
    "gn:feature_class":"P",
    "gn:feature_code":"PPL",
    "gn:name":"Asayaya",
    "gn:population":0,
    "gn:timezone":"Africa/Lagos",
    "iso:country":"NG",
    "wof:name":"Asayaya",
    "wof:placetype":"locality"
},
  "geometry": {"coordinates":[8.9132,12.15689],"type":"Point"}
}