{
  "type": "Feature",
  "properties": {
    "gn:admin1_code":"29.0",
    "gn:admin2_code":"20041.0",
    "gn:admin3_code":"KN2204",
    "gn:asciiname":"Kadare",
    "gn:country_code":"NG",
    "gn:dem":569,
    "gn:feature_class":"P",
    "gn:feature_code":"PPL",
    "gn:name":"Kadare",
    "gn:population":0,
    "gn:timezone":"Africa/Lagos",
    "iso:country":"NG",
    "wof:name":"Kadare",
    "wof:placetype":"locality"
},
  "geometry": {"coordinates":[7.94369,11.81167],"type":"Point"}
}