{
  "type": "Feature",
  "properties": {
    "gn:admin1_code":"26.0",
    "gn:admin2_code":"7004",
    "gn:asciiname":"Imor",
    "gn:country_code":"NG",
    "gn:dem":156,
    "gn:feature_class":"P",
    "gn:feature_code":"PPL",
    "gn:name":"Imor",
    "gn:population":0,
    "gn:timezone":"Africa/Lagos",
    "iso:country":"NG",
    "wof:name":"Imor",
    "wof:placetype":"locality"
},
  "geometry": {"coordinates":[9.24044,7.21277],"type":"Point"}
}