{
  "type": "Feature",
  "properties": {
    "gn:admin1_code":"51.0",
    "gn:admin2_code":"614.0",
    "gn:admin3_code":"61405",
    "gn:asciiname":"Kajiji",
    "gn:country_code":"NG",
    "gn:dem":284,
    "gn:feature_class":"P",
    "gn:feature_code":"PPL",
    "gn:name":"Kajiji",
    "gn:population":0,
    "gn:timezone":"Africa/Lagos",
    "iso:country":"NG",
    "wof:name":"Kajiji",
    "wof:placetype":"locality"
},
  "geometry": {"coordinates":[4.93952,12.53418],"type":"Point"}
}