{
  "type": "Feature",
  "properties": {
    "gn:admin1_code":"27.0",
    "gn:admin2_code":"108.0",
    "gn:admin3_code":"10807",
    "gn:asciiname":"Burimari",
    "gn:country_code":"NG",
    "gn:dem":296,
    "gn:feature_class":"P",
    "gn:feature_code":"PPL",
    "gn:name":"Burimari",
    "gn:population":0,
    "gn:timezone":"Africa/Lagos",
    "iso:country":"NG",
    "wof:name":"Burimari",
    "wof:placetype":"locality"
},
  "geometry": {"coordinates":[14.14174,11.97406],"type":"Point"}
}