{
  "type": "Feature",
  "properties": {
    "gn:admin1_code":"36.0",
    "gn:admin2_code":"10020.0",
    "gn:asciiname":"Ugbevbughe",
    "gn:country_code":"NG",
    "gn:dem":12,
    "gn:feature_class":"P",
    "gn:feature_code":"PPL",
    "gn:name":"Ugbevbughe",
    "gn:population":0,
    "gn:timezone":"Africa/Lagos",
    "iso:country":"NG",
    "name:und_x_variant":[
        "Ughevbughe",
        "Ugbevbughe"
    ],
    "wof:name":"Ugbevbughe",
    "wof:placetype":"locality"
},
  "geometry": {"coordinates":[5.91119,5.49465],"type":"Point"}
}