{
  "type": "Feature",
  "properties": {
    "gn:admin1_code":"24.0",
    "gn:admin2_code":"415.0",
    "gn:admin3_code":"41502",
    "gn:asciiname":"Bauje",
    "gn:country_code":"NG",
    "gn:dem":516,
    "gn:feature_class":"P",
    "gn:feature_code":"PPL",
    "gn:name":"Bauje",
    "gn:population":0,
    "gn:timezone":"Africa/Lagos",
    "iso:country":"NG",
    "wof:name":"Bauje",
    "wof:placetype":"locality"
},
  "geometry": {"coordinates":[8.1676,12.61467],"type":"Point"}
}