{
  "type": "Feature",
  "properties": {
    "gn:admin1_code":"27.0",
    "gn:asciiname":"Yawa",
    "gn:country_code":"NG",
    "gn:dem":293,
    "gn:feature_class":"P",
    "gn:feature_code":"PPL",
    "gn:name":"Yawa",
    "gn:population":0,
    "gn:timezone":"Africa/Lagos",
    "iso:country":"NG",
    "name:ceb_x_preferred":[
        "Yawa"
    ],
    "name:deu_x_preferred":[
        "Yawa"
    ],
    "name:swe_x_preferred":[
        "Yawa"
    ],
    "wof:name":"Yawa",
    "wof:placetype":"locality"
},
  "geometry": {"coordinates":[13.28065,13.65118],"type":"Point"}
}