{
  "type": "Feature",
  "properties": {
    "gn:admin1_code":"31.0",
    "gn:asciiname":"Tundun Wada",
    "gn:country_code":"NG",
    "gn:dem":255,
    "gn:feature_class":"P",
    "gn:feature_code":"PPL",
    "gn:name":"Tundun Wada",
    "gn:population":0,
    "gn:timezone":"Africa/Lagos",
    "iso:country":"NG",
    "wof:name":"Tundun Wada",
    "wof:placetype":"locality"
},
  "geometry": {"coordinates":[7.00526,9.25496],"type":"Point"}
}