{
  "type": "Feature",
  "properties": {
    "gn:admin1_code":"40.0",
    "gn:admin2_code":"502.0",
    "gn:admin3_code":"50202",
    "gn:asciiname":"Ungwan Zarmakwoi",
    "gn:country_code":"NG",
    "gn:dem":201,
    "gn:feature_class":"P",
    "gn:feature_code":"PPL",
    "gn:name":"Ungwan Zarmakwoi",
    "gn:population":0,
    "gn:timezone":"Africa/Lagos",
    "iso:country":"NG",
    "wof:name":"Ungwan Zarmakwoi",
    "wof:placetype":"locality"
},
  "geometry": {"coordinates":[3.92612,12.491],"type":"Point"}
}