{
  "type": "Feature",
  "properties": {
    "gn:admin1_code":"40.0",
    "gn:admin2_code":"512.0",
    "gn:admin3_code":"51206",
    "gn:asciiname":"Ungwan Bawa",
    "gn:country_code":"NG",
    "gn:dem":239,
    "gn:feature_class":"P",
    "gn:feature_code":"PPL",
    "gn:name":"Ungwan Bawa",
    "gn:population":0,
    "gn:timezone":"Africa/Lagos",
    "iso:country":"NG",
    "wof:name":"Ungwan Bawa",
    "wof:placetype":"locality"
},
  "geometry": {"coordinates":[3.92821,12.41962],"type":"Point"}
}