{
  "type": "Feature",
  "properties": {
    "gn:admin1_code":"26.0",
    "gn:admin2_code":"7021",
    "gn:asciiname":"Ibavel",
    "gn:country_code":"NG",
    "gn:dem":186,
    "gn:feature_class":"P",
    "gn:feature_code":"PPL",
    "gn:name":"Ibavel",
    "gn:population":0,
    "gn:timezone":"Africa/Lagos",
    "iso:country":"NG",
    "wof:name":"Ibavel",
    "wof:placetype":"locality"
},
  "geometry": {"coordinates":[9.61015,7.62448],"type":"Point"}
}