{
  "type": "Feature",
  "properties": {
    "gn:admin1_code":"28.0",
    "gn:admin2_code":"17005.0",
    "gn:asciiname":"Owerri Akokwa",
    "gn:country_code":"NG",
    "gn:dem":169,
    "gn:feature_class":"P",
    "gn:feature_code":"PPL",
    "gn:name":"Owerri Akokwa",
    "gn:population":0,
    "gn:timezone":"Africa/Lagos",
    "iso:country":"NG",
    "wof:name":"Owerri Akokwa",
    "wof:placetype":"locality"
},
  "geometry": {"coordinates":[7.14815,5.90458],"type":"Point"}
}