{
  "type": "Feature",
  "properties": {
    "gn:admin1_code":"26.0",
    "gn:admin2_code":"7016.0",
    "gn:asciiname":"Ugene",
    "gn:country_code":"NG",
    "gn:dem":202,
    "gn:feature_class":"P",
    "gn:feature_code":"PPL",
    "gn:name":"Ugene",
    "gn:population":0,
    "gn:timezone":"Africa/Lagos",
    "iso:country":"NG",
    "name:und_x_variant":[
        "Ogenni",
        "Ugenni",
        "Ugene"
    ],
    "wof:name":"Ugene",
    "wof:placetype":"locality"
},
  "geometry": {"coordinates":[7.93778,7.31015],"type":"Point"}
}