{
  "type": "Feature",
  "properties": {
    "gn:admin1_code":"43.0",
    "gn:admin2_code":"35007",
    "gn:asciiname":"Yali",
    "gn:country_code":"NG",
    "gn:dem":192,
    "gn:feature_class":"P",
    "gn:feature_code":"PPL",
    "gn:name":"Yali",
    "gn:population":0,
    "gn:timezone":"Africa/Lagos",
    "iso:country":"NG",
    "name:ceb_x_preferred":[
        "Yali"
    ],
    "name:deu_x_preferred":[
        "Yali"
    ],
    "name:ita_x_preferred":[
        "Yali"
    ],
    "name:nld_x_preferred":[
        "Yali"
    ],
    "name:nor_x_preferred":[
        "Yali"
    ],
    "name:pol_x_preferred":[
        "Yali"
    ],
    "name:slk_x_preferred":[
        "Yali"
    ],
    "name:swe_x_preferred":[
        "Yali"
    ],
    "name:tur_x_preferred":[
        "Yal\u0131"
    ],
    "wof:name":"Yali",
    "wof:placetype":"neighbourhood"
},
  "geometry": {"coordinates":[11.34927,8.91545],"type":"Point"}
}