{
  "type": "Feature",
  "properties": {
    "gn:admin1_code":"56.0",
    "gn:admin2_code":"26009.0",
    "gn:asciiname":"Kuri",
    "gn:country_code":"NG",
    "gn:dem":424,
    "gn:feature_class":"P",
    "gn:feature_code":"PPL",
    "gn:name":"Kuri",
    "gn:population":0,
    "gn:timezone":"Africa/Lagos",
    "iso:country":"NG",
    "name:ceb_x_preferred":[
        "Kuri"
    ],
    "name:ces_x_preferred":[
        "Kuri"
    ],
    "name:deu_x_preferred":[
        "Kuri"
    ],
    "name:fra_x_preferred":[
        "Kuri"
    ],
    "name:spa_x_preferred":[
        "Kuri"
    ],
    "name:swe_x_preferred":[
        "Kuri"
    ],
    "wof:name":"Kuri",
    "wof:placetype":"locality"
},
  "geometry": {"coordinates":[7.90528,8.48222],"type":"Point"}
}