{
  "type": "Feature",
  "properties": {
    "gn:admin1_code":"37.0",
    "gn:admin2_code":"12006",
    "gn:asciiname":"Ekhuere",
    "gn:country_code":"NG",
    "gn:dem":203,
    "gn:feature_class":"P",
    "gn:feature_code":"PPL",
    "gn:name":"Ekhuere",
    "gn:population":0,
    "gn:timezone":"Africa/Lagos",
    "iso:country":"NG",
    "wof:name":"Ekhuere",
    "wof:placetype":"locality"
},
  "geometry": {"coordinates":[6.10058,6.60765],"type":"Point"}
}