{
  "type": "Feature",
  "properties": {
    "gn:admin1_code":"28.0",
    "gn:admin2_code":"17018.0",
    "gn:asciiname":"Opete",
    "gn:country_code":"NG",
    "gn:dem":50,
    "gn:feature_class":"P",
    "gn:feature_code":"PPL",
    "gn:name":"Opete",
    "gn:population":0,
    "gn:timezone":"Africa/Lagos",
    "iso:country":"NG",
    "wof:name":"Opete",
    "wof:placetype":"locality"
},
  "geometry": {"coordinates":[6.82371,5.31707],"type":"Point"}
}