{
  "type": "Feature",
  "properties": {
    "gn:admin1_code":"57.0",
    "gn:admin2_code":"807.0",
    "gn:admin3_code":"80710",
    "gn:asciiname":"Jan Gemi",
    "gn:country_code":"NG",
    "gn:dem":531,
    "gn:feature_class":"P",
    "gn:feature_code":"PPL",
    "gn:name":"Jan Gemi",
    "gn:population":0,
    "gn:timezone":"Africa/Lagos",
    "iso:country":"NG",
    "name:und_x_variant":[
        "Jangemi",
        "Jam-Gemi",
        "Jan Gemi"
    ],
    "wof:name":"Jan Gemi",
    "wof:placetype":"locality"
},
  "geometry": {"coordinates":[6.61123,11.91432],"type":"Point"}
}