{
  "type": "Feature",
  "properties": {
    "gn:admin1_code":"43.0",
    "gn:admin2_code":"35010.0",
    "gn:asciiname":"Lau Fulani",
    "gn:country_code":"NG",
    "gn:dem":132,
    "gn:feature_class":"P",
    "gn:feature_code":"PPL",
    "gn:name":"Lau Fulani",
    "gn:population":0,
    "gn:timezone":"Africa/Lagos",
    "iso:country":"NG",
    "name:eng_x_preferred":[
        "Lau Fulani"
    ],
    "wof:name":"Lau Fulani",
    "wof:placetype":"locality"
},
  "geometry": {"coordinates":[11.3014,9.22157],"type":"Point"}
}