{
  "type": "Feature",
  "properties": {
    "gn:admin1_code":"57.0",
    "gn:admin2_code":"813.0",
    "gn:admin3_code":"81308",
    "gn:asciiname":"Guidan Awala",
    "gn:country_code":"NG",
    "gn:dem":504,
    "gn:feature_class":"P",
    "gn:feature_code":"PPL",
    "gn:name":"Guidan Awala",
    "gn:population":0,
    "gn:timezone":"Africa/Lagos",
    "iso:country":"NG",
    "name:und_x_variant":[
        "Gidan Awala",
        "Guidan Awala"
    ],
    "wof:name":"Guidan Awala",
    "wof:placetype":"locality"
},
  "geometry": {"coordinates":[6.91794,12.06124],"type":"Point"}
}