{
  "type": "Feature",
  "properties": {
    "gn:admin1_code":"51.0",
    "gn:admin2_code":"606.0",
    "gn:admin3_code":"60606",
    "gn:asciiname":"Giliodi",
    "gn:country_code":"NG",
    "gn:dem":257,
    "gn:feature_class":"P",
    "gn:feature_code":"PPL",
    "gn:name":"Giliodi",
    "gn:population":0,
    "gn:timezone":"Africa/Lagos",
    "iso:country":"NG",
    "wof:name":"Giliodi",
    "wof:placetype":"locality"
},
  "geometry": {"coordinates":[4.39044,13.20586],"type":"Point"}
}