{
  "type": "Feature",
  "properties": {
    "gn:admin1_code":"35.0",
    "gn:asciiname":"Wuro Yaungo",
    "gn:country_code":"NG",
    "gn:dem":244,
    "gn:feature_class":"P",
    "gn:feature_code":"PPL",
    "gn:name":"Wuro Yaungo",
    "gn:population":0,
    "gn:timezone":"Africa/Lagos",
    "iso:country":"NG",
    "name:eng_x_preferred":[
        "Wuro Yaungo"
    ],
    "wof:name":"Wuro Yaungo",
    "wof:placetype":"locality"
},
  "geometry": {"coordinates":[12.02483,9.14083],"type":"Point"}
}