{
  "type": "Feature",
  "properties": {
    "gn:admin1_code":"47.0",
    "gn:admin2_code":"14014.0",
    "gn:asciiname":"Ugwuoba",
    "gn:country_code":"NG",
    "gn:dem":80,
    "gn:feature_class":"P",
    "gn:feature_code":"PPL",
    "gn:name":"Ugwuoba",
    "gn:population":0,
    "gn:timezone":"Africa/Lagos",
    "iso:country":"NG",
    "wof:name":"Ugwuoba",
    "wof:placetype":"locality"
},
  "geometry": {"coordinates":[7.15931,6.25469],"type":"Point"}
}