{
  "type": "Feature",
  "properties": {
    "gn:admin1_code":"49.0",
    "gn:admin2_code":"32015.0",
    "gn:asciiname":"Bachit",
    "gn:country_code":"NG",
    "gn:dem":1021,
    "gn:feature_class":"P",
    "gn:feature_code":"PPL",
    "gn:name":"Bachit",
    "gn:population":0,
    "gn:timezone":"Africa/Lagos",
    "iso:country":"NG",
    "wof:name":"Bachit",
    "wof:placetype":"locality"
},
  "geometry": {"coordinates":[8.69142,9.50432],"type":"Point"}
}