{
  "type": "Feature",
  "properties": {
    "gn:admin1_code":"28.0",
    "gn:admin2_code":"17012.0",
    "gn:asciiname":"Umu Ekwune",
    "gn:country_code":"NG",
    "gn:dem":53,
    "gn:feature_class":"P",
    "gn:feature_code":"PPL",
    "gn:name":"Umu Ekwune",
    "gn:population":0,
    "gn:timezone":"Africa/Lagos",
    "iso:country":"NG",
    "wof:name":"Umu Ekwune",
    "wof:placetype":"locality"
},
  "geometry": {"coordinates":[7.03232,5.29031],"type":"Point"}
}