{
  "type": "Feature",
  "properties": {
    "gn:admin1_code":"32.0",
    "gn:admin2_code":"31004.0",
    "gn:asciiname":"Mangoro",
    "gn:country_code":"NG",
    "gn:dem":348,
    "gn:feature_class":"P",
    "gn:feature_code":"PPL",
    "gn:name":"Mangoro",
    "gn:population":0,
    "gn:timezone":"Africa/Lagos",
    "iso:country":"NG",
    "wof:name":"Mangoro",
    "wof:placetype":"locality"
},
  "geometry": {"coordinates":[3.23333,8.43333],"type":"Point"}
}