{
  "type": "Feature",
  "properties": {
    "gn:admin1_code":"21.0",
    "gn:admin2_code":"3014.0",
    "gn:asciiname":"Ikot Abia",
    "gn:country_code":"NG",
    "gn:dem":104,
    "gn:feature_class":"P",
    "gn:feature_code":"PPL",
    "gn:name":"Ikot Abia",
    "gn:population":0,
    "gn:timezone":"Africa/Lagos",
    "iso:country":"NG",
    "name:und_x_variant":[
        "Ikot Abia Idem",
        "Ikot Abia"
    ],
    "wof:name":"Ikot Abia",
    "wof:placetype":"locality"
},
  "geometry": {"coordinates":[7.69537,5.20772],"type":"Point"}
}