{
  "type": "Feature",
  "properties": {
    "gn:admin1_code":"26.0",
    "gn:admin2_code":"7017.0",
    "gn:asciiname":"Oye",
    "gn:country_code":"NG",
    "gn:dem":71,
    "gn:feature_class":"P",
    "gn:feature_code":"PPL",
    "gn:name":"Oye",
    "gn:population":0,
    "gn:timezone":"Africa/Lagos",
    "iso:country":"NG",
    "wof:name":"Oye",
    "wof:placetype":"locality"
},
  "geometry": {"coordinates":[8.1607,6.9048],"type":"Point"}
}