{
  "type": "Feature",
  "properties": {
    "gn:admin1_code":"27.0",
    "gn:admin2_code":"121",
    "gn:admin3_code":"12109",
    "gn:asciiname":"Bukkari",
    "gn:country_code":"NG",
    "gn:dem":293,
    "gn:feature_class":"P",
    "gn:feature_code":"PPL",
    "gn:name":"Bukkari",
    "gn:population":0,
    "gn:timezone":"Africa/Lagos",
    "iso:country":"NG",
    "wof:name":"Bukkari",
    "wof:placetype":"locality"
},
  "geometry": {"coordinates":[13.85069,12.42153],"type":"Point"}
}