{
  "type": "Feature",
  "properties": {
    "gn:admin1_code":"5.0",
    "gn:asciiname":"Langbasa",
    "gn:country_code":"NG",
    "gn:dem":1,
    "gn:feature_class":"P",
    "gn:feature_code":"PPL",
    "gn:name":"Langbasa",
    "gn:population":0,
    "gn:timezone":"Africa/Lagos",
    "iso:country":"NG",
    "name:und_x_variant":[
        "Langbassa",
        "Langbasa"
    ],
    "wof:name":"Langbasa",
    "wof:placetype":"locality"
},
  "geometry": {"coordinates":[3.57873,6.50773],"type":"Point"}
}