{
  "type": "Feature",
  "properties": {
    "gn:admin1_code":"51.0",
    "gn:asciiname":"Gidan Shekaro",
    "gn:country_code":"NG",
    "gn:dem":301,
    "gn:feature_class":"P",
    "gn:feature_code":"PPL",
    "gn:name":"Gidan Shekaro",
    "gn:population":0,
    "gn:timezone":"Africa/Lagos",
    "iso:country":"NG",
    "wof:name":"Gidan Shekaro",
    "wof:placetype":"locality"
},
  "geometry": {"coordinates":[5.98391,13.71953],"type":"Point"}
}