{
  "type": "Feature",
  "properties": {
    "gn:admin1_code":"27.0",
    "gn:admin2_code":"106.0",
    "gn:admin3_code":"10606",
    "gn:asciiname":"Gagelam",
    "gn:country_code":"NG",
    "gn:dem":453,
    "gn:feature_class":"P",
    "gn:feature_code":"PPL",
    "gn:name":"Gagelam",
    "gn:population":0,
    "gn:timezone":"Africa/Lagos",
    "iso:country":"NG",
    "wof:name":"Gagelam",
    "wof:placetype":"locality"
},
  "geometry": {"coordinates":[12.87774,10.90999],"type":"Point"}
}