{
  "type": "Feature",
  "properties": {
    "gn:admin1_code":"50.0",
    "gn:admin2_code":"33004.0",
    "gn:asciiname":"Nangwoma",
    "gn:country_code":"NG",
    "gn:dem":7,
    "gn:feature_class":"P",
    "gn:feature_code":"PPL",
    "gn:name":"Nangwoma",
    "gn:population":0,
    "gn:timezone":"Africa/Lagos",
    "iso:country":"NG",
    "wof:name":"Nangwoma",
    "wof:placetype":"locality"
},
  "geometry": {"coordinates":[6.7313,4.43726],"type":"Point"}
}