{
  "type": "Feature",
  "properties": {
    "gn:admin1_code":"31.0",
    "gn:admin2_code":"27001.0",
    "gn:asciiname":"Kadan",
    "gn:country_code":"NG",
    "gn:dem":127,
    "gn:feature_class":"P",
    "gn:feature_code":"PPL",
    "gn:name":"Kadan",
    "gn:population":0,
    "gn:timezone":"Africa/Lagos",
    "iso:country":"NG",
    "name:fra_x_preferred":[
        "Khadan"
    ],
    "name:ita_x_preferred":[
        "Kadan"
    ],
    "name:jpn_x_preferred":[
        "\u30ab\u30c0\u30a2\u30f3\u30fb\u30aa\u30b0\u30eb"
    ],
    "name:mon_x_preferred":[
        "\u0425\u0430\u0434\u0430\u043d"
    ],
    "name:nld_x_preferred":[
        "Kaidan"
    ],
    "name:rus_x_preferred":[
        "\u041a\u0430\u0434\u0430\u043d"
    ],
    "name:spa_x_preferred":[
        "Kadan"
    ],
    "name:ukr_x_preferred":[
        "\u041a\u0430\u0434\u0430'\u0430\u043d"
    ],
    "name:und_x_variant":[
        "Kapagi",
        "Kadan"
    ],
    "name:vie_x_preferred":[
        "Kadan"
    ],
    "wof:name":"Kadan",
    "wof:placetype":"locality"
},
  "geometry": {"coordinates":[6.40813,9.17643],"type":"Point"}
}