{
  "type": "Feature",
  "properties": {
    "gn:admin1_code":"36.0",
    "gn:admin2_code":"10004.0",
    "gn:asciiname":"Ogodogodo",
    "gn:country_code":"NG",
    "gn:dem":1,
    "gn:feature_class":"P",
    "gn:feature_code":"PPL",
    "gn:name":"Ogodogodo",
    "gn:population":0,
    "gn:timezone":"Africa/Lagos",
    "iso:country":"NG",
    "wof:name":"Ogodogodo",
    "wof:placetype":"locality"
},
  "geometry": {"coordinates":[5.53836,5.3787],"type":"Point"}
}