{
  "type": "Feature",
  "properties": {
    "gn:admin1_code":"26.0",
    "gn:admin2_code":"7021",
    "gn:asciiname":"Pawa",
    "gn:country_code":"NG",
    "gn:dem":161,
    "gn:feature_class":"P",
    "gn:feature_code":"PPL",
    "gn:name":"Pawa",
    "gn:population":0,
    "gn:timezone":"Africa/Lagos",
    "iso:country":"NG",
    "name:ceb_x_preferred":[
        "Pawa"
    ],
    "name:deu_x_preferred":[
        "Pawa"
    ],
    "wof:name":"Pawa",
    "wof:placetype":"locality"
},
  "geometry": {"coordinates":[9.70864,7.64954],"type":"Point"}
}