{
  "type": "Feature",
  "properties": {
    "gn:admin1_code":"16.0",
    "gn:admin2_code":"28003.0",
    "gn:asciiname":"Ilasa",
    "gn:country_code":"NG",
    "gn:dem":8,
    "gn:feature_class":"P",
    "gn:feature_code":"PPL",
    "gn:name":"Ilasa",
    "gn:population":0,
    "gn:timezone":"Africa/Lagos",
    "iso:country":"NG",
    "wof:name":"Ilasa",
    "wof:placetype":"locality"
},
  "geometry": {"coordinates":[3.15,6.61667],"type":"Point"}
}