{
  "type": "Feature",
  "properties": {
    "gn:admin1_code":"27.0",
    "gn:admin2_code":"122.0",
    "gn:admin3_code":"12205",
    "gn:asciiname":"Kabela",
    "gn:country_code":"NG",
    "gn:dem":309,
    "gn:feature_class":"P",
    "gn:feature_code":"PPL",
    "gn:name":"Kabela",
    "gn:population":0,
    "gn:timezone":"Africa/Lagos",
    "iso:country":"NG",
    "wof:name":"Kabela",
    "wof:placetype":"locality"
},
  "geometry": {"coordinates":[12.65318,13.19962],"type":"Point"}
}