{
  "type": "Feature",
  "properties": {
    "gn:admin1_code":"37.0",
    "gn:admin2_code":"12011.0",
    "gn:asciiname":"Ironegbo Ogbesan",
    "gn:country_code":"NG",
    "gn:dem":90,
    "gn:feature_class":"P",
    "gn:feature_code":"PPL",
    "gn:name":"Ironegbo Ogbesan",
    "gn:population":0,
    "gn:timezone":"Africa/Lagos",
    "iso:country":"NG",
    "name:und_x_variant":[
        "Ogbesan",
        "Ironegbo Ogbesan"
    ],
    "wof:name":"Ironegbo Ogbesan",
    "wof:placetype":"locality"
},
  "geometry": {"coordinates":[5.70896,6.33757],"type":"Point"}
}