{
  "type": "Feature",
  "properties": {
    "gn:admin1_code":"51.0",
    "gn:admin2_code":"608.0",
    "gn:admin3_code":"60803",
    "gn:asciiname":"Marake",
    "gn:country_code":"NG",
    "gn:dem":300,
    "gn:feature_class":"P",
    "gn:feature_code":"PPL",
    "gn:name":"Marake",
    "gn:population":0,
    "gn:timezone":"Africa/Lagos",
    "iso:country":"NG",
    "wof:name":"Marake",
    "wof:placetype":"locality"
},
  "geometry": {"coordinates":[5.4245,13.51056],"type":"Point"}
}