{
  "type": "Feature",
  "properties": {
    "gn:admin1_code":"21.0",
    "gn:admin2_code":"3010.0",
    "gn:asciiname":"Use Nten",
    "gn:country_code":"NG",
    "gn:dem":83,
    "gn:feature_class":"P",
    "gn:feature_code":"PPL",
    "gn:name":"Use Nten",
    "gn:population":0,
    "gn:timezone":"Africa/Lagos",
    "iso:country":"NG",
    "wof:name":"Use Nten",
    "wof:placetype":"locality"
},
  "geometry": {"coordinates":[7.87379,5.07381],"type":"Point"}
}