{
  "type": "Feature",
  "properties": {
    "gn:admin1_code":"29.0",
    "gn:admin2_code":"20038.0",
    "gn:admin3_code":"KN0301",
    "gn:asciiname":"Bagwai",
    "gn:country_code":"NG",
    "gn:dem":518,
    "gn:feature_class":"P",
    "gn:feature_code":"PPLA2",
    "gn:name":"Bagwai",
    "gn:population":0,
    "gn:timezone":"Africa/Lagos",
    "iso:country":"NG",
    "name:ceb_x_preferred":[
        "Bagwai"
    ],
    "name:fra_x_preferred":[
        "Bagwai"
    ],
    "name:hau_x_preferred":[
        "\u0181agwai"
    ],
    "name:ita_x_preferred":[
        "Bagwai"
    ],
    "name:por_x_preferred":[
        "Bagwai"
    ],
    "name:spa_x_preferred":[
        "Bagwai"
    ],
    "wof:name":"Bagwai",
    "wof:placetype":"locality"
},
  "geometry": {"coordinates":[8.1358,12.1577],"type":"Point"}
}