{
  "type": "Feature",
  "properties": {
    "gn:admin1_code":"45.0",
    "gn:admin2_code":"1011.0",
    "gn:asciiname":"Mgbede Ala",
    "gn:country_code":"NG",
    "gn:dem":99,
    "gn:feature_class":"P",
    "gn:feature_code":"PPL",
    "gn:name":"Mgbede Ala",
    "gn:population":0,
    "gn:timezone":"Africa/Lagos",
    "iso:country":"NG",
    "wof:name":"Mgbede Ala",
    "wof:placetype":"locality"
},
  "geometry": {"coordinates":[7.34788,5.28283],"type":"Point"}
}