{
  "type": "Feature",
  "properties": {
    "gn:admin1_code":"31.0",
    "gn:admin2_code":"27010",
    "gn:asciiname":"Natenu",
    "gn:country_code":"NG",
    "gn:dem":113,
    "gn:feature_class":"P",
    "gn:feature_code":"PPL",
    "gn:name":"Natenu",
    "gn:population":0,
    "gn:timezone":"Africa/Lagos",
    "iso:country":"NG",
    "wof:name":"Natenu",
    "wof:placetype":"locality"
},
  "geometry": {"coordinates":[6.29307,9.19212],"type":"Point"}
}