{
  "type": "Feature",
  "properties": {
    "gn:admin1_code":"49.0",
    "gn:asciiname":"Kwoor",
    "gn:country_code":"NG",
    "gn:dem":284,
    "gn:feature_class":"P",
    "gn:feature_code":"PPL",
    "gn:name":"Kwoor",
    "gn:population":0,
    "gn:timezone":"Africa/Lagos",
    "iso:country":"NG",
    "name:ind_x_preferred":[
        "Kwoor"
    ],
    "name:jav_x_preferred":[
        "Kwoor"
    ],
    "name:msa_x_preferred":[
        "Kwoor"
    ],
    "wof:name":"Kwoor",
    "wof:placetype":"locality"
},
  "geometry": {"coordinates":[9.26181,8.90838],"type":"Point"}
}