{
  "type": "Feature",
  "properties": {
    "gn:admin1_code":"57.0",
    "gn:admin2_code":"808.0",
    "gn:admin3_code":"80801",
    "gn:asciiname":"Dan Makulu",
    "gn:country_code":"NG",
    "gn:dem":406,
    "gn:feature_class":"P",
    "gn:feature_code":"PPL",
    "gn:name":"Dan Makulu",
    "gn:population":0,
    "gn:timezone":"Africa/Lagos",
    "iso:country":"NG",
    "wof:name":"Dan Makulu",
    "wof:placetype":"locality"
},
  "geometry": {"coordinates":[6.62557,12.48493],"type":"Point"}
}