{
  "type": "Feature",
  "properties": {
    "gn:admin1_code":"56.0",
    "gn:admin2_code":"26002.0",
    "gn:asciiname":"Buna",
    "gn:country_code":"NG",
    "gn:dem":199,
    "gn:feature_class":"P",
    "gn:feature_code":"PPL",
    "gn:name":"Buna",
    "gn:population":0,
    "gn:timezone":"Africa/Lagos",
    "iso:country":"NG",
    "wof:name":"Buna",
    "wof:placetype":"locality"
},
  "geometry": {"coordinates":[9.01667,8.36667],"type":"Point"}
}