{
  "type": "Feature",
  "properties": {
    "gn:admin1_code":"43.0",
    "gn:admin2_code":"35004.0",
    "gn:asciiname":"Gidan Nduna",
    "gn:country_code":"NG",
    "gn:dem":918,
    "gn:feature_class":"P",
    "gn:feature_code":"PPL",
    "gn:name":"Gidan Nduna",
    "gn:population":0,
    "gn:timezone":"Africa/Lagos",
    "iso:country":"NG",
    "wof:name":"Gidan Nduna",
    "wof:placetype":"locality"
},
  "geometry": {"coordinates":[10.87571,7.67677],"type":"Point"}
}