{
  "type": "Feature",
  "properties": {
    "gn:admin1_code":"46.0",
    "gn:admin2_code":"5016.0",
    "gn:admin3_code":"BA1606",
    "gn:asciiname":"Zerami",
    "gn:country_code":"NG",
    "gn:dem":404,
    "gn:feature_class":"P",
    "gn:feature_code":"PPL",
    "gn:name":"Zerami",
    "gn:population":0,
    "gn:timezone":"Africa/Lagos",
    "iso:country":"NG",
    "wof:name":"Zerami",
    "wof:placetype":"locality"
},
  "geometry": {"coordinates":[10.0311,11.5769],"type":"Point"}
}