{
  "type": "Feature",
  "properties": {
    "gn:admin1_code":"24.0",
    "gn:admin2_code":"409.0",
    "gn:admin3_code":"40902",
    "gn:asciiname":"Dandire",
    "gn:country_code":"NG",
    "gn:dem":476,
    "gn:feature_class":"P",
    "gn:feature_code":"PPL",
    "gn:name":"Dandire",
    "gn:population":0,
    "gn:timezone":"Africa/Lagos",
    "iso:country":"NG",
    "name:und_x_variant":[
        "Dandare",
        "Dandire"
    ],
    "wof:name":"Dandire",
    "wof:placetype":"locality"
},
  "geometry": {"coordinates":[7.25171,12.31793],"type":"Point"}
}