{
  "type": "Feature",
  "properties": {
    "gn:admin1_code":"49.0",
    "gn:admin2_code":"32009",
    "gn:asciiname":"Nyer",
    "gn:country_code":"NG",
    "gn:dem":195,
    "gn:feature_class":"P",
    "gn:feature_code":"PPL",
    "gn:name":"Nyer",
    "gn:population":0,
    "gn:timezone":"Africa/Lagos",
    "iso:country":"NG",
    "wof:name":"Nyer",
    "wof:placetype":"locality"
},
  "geometry": {"coordinates":[9.81587,8.89847],"type":"Point"}
}