{
  "type": "Feature",
  "properties": {
    "gn:admin1_code":"52.0",
    "gn:admin2_code":"6007.0",
    "gn:asciiname":"Eniwari",
    "gn:country_code":"NG",
    "gn:dem":8,
    "gn:feature_class":"P",
    "gn:feature_code":"PPL",
    "gn:name":"Eniwari",
    "gn:population":0,
    "gn:timezone":"Africa/Lagos",
    "iso:country":"NG",
    "name:und_x_variant":[
        "Enuwari",
        "Eniwari"
    ],
    "wof:name":"Eniwari",
    "wof:placetype":"locality"
},
  "geometry": {"coordinates":[6.13026,4.74398],"type":"Point"}
}