{
  "type": "Feature",
  "properties": {
    "gn:admin1_code":"32.0",
    "gn:admin2_code":"31023.0",
    "gn:asciiname":"Aje",
    "gn:cc2":"NG",
    "gn:country_code":"NG",
    "gn:dem":365,
    "gn:feature_class":"P",
    "gn:feature_code":"PPL",
    "gn:name":"Aje",
    "gn:population":0,
    "gn:timezone":"Africa/Lagos",
    "iso:country":"NG",
    "name:und_x_variant":[
        "Bemiro",
        "Aje"
    ],
    "wof:name":"Aje",
    "wof:placetype":"locality"
},
  "geometry": {"coordinates":[4.21667,8.01667],"type":"Point"}
}