{
  "type": "Feature",
  "properties": {
    "gn:admin1_code":"43.0",
    "gn:admin2_code":"35010.0",
    "gn:asciiname":"Mnbamnga-Ardido",
    "gn:country_code":"NG",
    "gn:dem":249,
    "gn:feature_class":"P",
    "gn:feature_code":"PPL",
    "gn:name":"Mnbamnga-Ardido",
    "gn:population":0,
    "gn:timezone":"Africa/Lagos",
    "iso:country":"NG",
    "name:eng_x_preferred":[
        "Mnbamnga-Ardido"
    ],
    "name:eng_x_variant":[
        "Bamga"
    ],
    "wof:name":"Mnbamnga-Ardido",
    "wof:placetype":"locality"
},
  "geometry": {"coordinates":[11.58333,9.18333],"type":"Point"}
}