{
  "type": "Feature",
  "properties": {
    "gn:admin1_code":"39.0",
    "gn:admin2_code":"18022.0",
    "gn:admin3_code":"JI0306",
    "gn:asciiname":"Gurmina",
    "gn:country_code":"NG",
    "gn:dem":439,
    "gn:feature_class":"P",
    "gn:feature_code":"PPL",
    "gn:name":"Gurmina",
    "gn:population":0,
    "gn:timezone":"Africa/Lagos",
    "iso:country":"NG",
    "wof:name":"Gurmina",
    "wof:placetype":"locality"
},
  "geometry": {"coordinates":[9.47392,11.40557],"type":"Point"}
}