{
  "type": "Feature",
  "properties": {
    "gn:admin1_code":"26.0",
    "gn:admin2_code":"7021",
    "gn:asciiname":"Usman",
    "gn:country_code":"NG",
    "gn:dem":191,
    "gn:feature_class":"P",
    "gn:feature_code":"PPL",
    "gn:name":"Usman",
    "gn:population":0,
    "gn:timezone":"Africa/Lagos",
    "iso:country":"NG",
    "name:bel_x_preferred":[
        "\u0423\u0441\u043c\u0430\u043d\u044c"
    ],
    "name:ben_x_preferred":[
        "\u0989\u09b8\u09ae\u09be\u09a8"
    ],
    "name:ceb_x_preferred":[
        "Usman"
    ],
    "name:deu_x_preferred":[
        "Usman"
    ],
    "name:ron_x_preferred":[
        "Usman"
    ],
    "name:rus_x_preferred":[
        "\u0423\u0441\u043c\u0430\u043d\u044c"
    ],
    "name:ukr_x_preferred":[
        "\u0423\u0441\u043c\u0430\u043d\u044c"
    ],
    "wof:name":"Usman",
    "wof:placetype":"locality"
},
  "geometry": {"coordinates":[9.72531,7.64767],"type":"Point"}
}