{
  "type": "Feature",
  "properties": {
    "gn:admin1_code":"16.0",
    "gn:admin2_code":"28007.0",
    "gn:asciiname":"Lani Olaogun",
    "gn:country_code":"NG",
    "gn:dem":108,
    "gn:feature_class":"P",
    "gn:feature_code":"PPL",
    "gn:name":"Lani Olaogun",
    "gn:population":0,
    "gn:timezone":"Africa/Lagos",
    "iso:country":"NG",
    "wof:name":"Lani Olaogun",
    "wof:placetype":"locality"
},
  "geometry": {"coordinates":[3.11667,6.83333],"type":"Point"}
}