{
  "type": "Feature",
  "properties": {
    "gn:admin1_code":"47.0",
    "gn:admin2_code":"14017.0",
    "gn:asciiname":"Adaba",
    "gn:country_code":"NG",
    "gn:dem":104,
    "gn:feature_class":"P",
    "gn:feature_code":"PPL",
    "gn:name":"Adaba",
    "gn:population":0,
    "gn:timezone":"Africa/Lagos",
    "iso:country":"NG",
    "wof:name":"Adaba",
    "wof:placetype":"locality"
},
  "geometry": {"coordinates":[7.12951,6.57557],"type":"Point"}
}