{
  "type": "Feature",
  "properties": {
    "gn:admin1_code":"40.0",
    "gn:admin2_code":"505.0",
    "gn:admin3_code":"50504",
    "gn:asciiname":"Balalangu",
    "gn:country_code":"NG",
    "gn:dem":179,
    "gn:feature_class":"P",
    "gn:feature_code":"PPL",
    "gn:name":"Balalangu",
    "gn:population":0,
    "gn:timezone":"Africa/Lagos",
    "iso:country":"NG",
    "wof:name":"Balalangu",
    "wof:placetype":"locality"
},
  "geometry": {"coordinates":[3.67637,11.47137],"type":"Point"}
}