{
  "type": "Feature",
  "properties": {
    "gn:admin1_code":"24.0",
    "gn:admin2_code":"413.0",
    "gn:admin3_code":"41303",
    "gn:asciiname":"Dan Baba",
    "gn:country_code":"NG",
    "gn:dem":631,
    "gn:feature_class":"P",
    "gn:feature_code":"PPL",
    "gn:name":"Dan Baba",
    "gn:population":0,
    "gn:timezone":"Africa/Lagos",
    "iso:country":"NG",
    "wof:name":"Dan Baba",
    "wof:placetype":"locality"
},
  "geometry": {"coordinates":[7.1227,11.5914],"type":"Point"}
}