{
  "type": "Feature",
  "properties": {
    "gn:admin1_code":"31.0",
    "gn:admin2_code":"27007",
    "gn:asciiname":"Makamatsado",
    "gn:country_code":"NG",
    "gn:dem":272,
    "gn:feature_class":"P",
    "gn:feature_code":"PPL",
    "gn:name":"Makamatsado",
    "gn:population":0,
    "gn:timezone":"Africa/Lagos",
    "iso:country":"NG",
    "wof:name":"Makamatsado",
    "wof:placetype":"locality"
},
  "geometry": {"coordinates":[5.67594,9.03886],"type":"Point"}
}