{
  "type": "Feature",
  "properties": {
    "gn:admin1_code":"50.0",
    "gn:admin2_code":"33001.0",
    "gn:asciiname":"Orikiri",
    "gn:country_code":"NG",
    "gn:dem":11,
    "gn:feature_class":"P",
    "gn:feature_code":"PPL",
    "gn:name":"Orikiri",
    "gn:population":0,
    "gn:timezone":"Africa/Lagos",
    "iso:country":"NG",
    "wof:name":"Orikiri",
    "wof:placetype":"locality"
},
  "geometry": {"coordinates":[6.71833,4.82539],"type":"Point"}
}