{
  "type": "Feature",
  "properties": {
    "gn:admin1_code":"31.0",
    "gn:admin2_code":"27014.0",
    "gn:asciiname":"Komi",
    "gn:country_code":"NG",
    "gn:dem":102,
    "gn:feature_class":"P",
    "gn:feature_code":"PPL",
    "gn:name":"Komi",
    "gn:population":0,
    "gn:timezone":"Africa/Lagos",
    "iso:country":"NG",
    "wof:name":"Komi",
    "wof:placetype":"locality"
},
  "geometry": {"coordinates":[4.61667,9.85],"type":"Point"}
}