{
  "type": "Feature",
  "properties": {
    "gn:admin1_code":"27.0",
    "gn:admin2_code":"104.0",
    "gn:admin3_code":"10410",
    "gn:asciiname":"Warma",
    "gn:country_code":"NG",
    "gn:dem":430,
    "gn:feature_class":"P",
    "gn:feature_code":"PPL",
    "gn:name":"Warma",
    "gn:population":0,
    "gn:timezone":"Africa/Lagos",
    "iso:country":"NG",
    "wof:name":"Warma",
    "wof:placetype":"locality"
},
  "geometry": {"coordinates":[11.79774,10.721],"type":"Point"}
}