{
  "type": "Feature",
  "properties": {
    "gn:admin1_code":"46.0",
    "gn:admin2_code":"5020.0",
    "gn:admin3_code":"BA2013",
    "gn:asciiname":"Mainari",
    "gn:country_code":"NG",
    "gn:dem":365,
    "gn:feature_class":"P",
    "gn:feature_code":"PPL",
    "gn:name":"Mainari",
    "gn:population":0,
    "gn:timezone":"Africa/Lagos",
    "iso:country":"NG",
    "wof:name":"Mainari",
    "wof:placetype":"locality"
},
  "geometry": {"coordinates":[10.43217,12.08585],"type":"Point"}
}