{
  "type": "Feature",
  "properties": {
    "gn:admin1_code":"35.0",
    "gn:asciiname":"Ako",
    "gn:country_code":"NG",
    "gn:dem":349,
    "gn:feature_class":"P",
    "gn:feature_code":"PPL",
    "gn:name":"Ako",
    "gn:population":0,
    "gn:timezone":"Africa/Lagos",
    "iso:country":"NG",
    "name:eng_x_preferred":[
        "Ako"
    ],
    "wof:name":"Ako",
    "wof:placetype":"locality"
},
  "geometry": {"coordinates":[11.77102,9.165],"type":"Point"}
}