{
  "type": "Feature",
  "properties": {
    "gn:admin1_code":"16.0",
    "gn:admin2_code":"28020.0",
    "gn:asciiname":"Shimawa",
    "gn:country_code":"NG",
    "gn:dem":31,
    "gn:feature_class":"P",
    "gn:feature_code":"PPL",
    "gn:name":"Shimawa",
    "gn:population":0,
    "gn:timezone":"Africa/Lagos",
    "iso:country":"NG",
    "name:und_x_variant":[
        "Simawa",
        "Shimawa"
    ],
    "wof:name":"Shimawa",
    "wof:placetype":"locality"
},
  "geometry": {"coordinates":[3.48842,6.76413],"type":"Point"}
}