{
  "type": "Feature",
  "properties": {
    "gn:admin1_code":"35.0",
    "gn:admin2_code":"2002.0",
    "gn:asciiname":"Rumnde",
    "gn:country_code":"NG",
    "gn:dem":206,
    "gn:feature_class":"P",
    "gn:feature_code":"PPL",
    "gn:name":"Rumnde",
    "gn:population":0,
    "gn:timezone":"Africa/Lagos",
    "iso:country":"NG",
    "wof:name":"Rumnde",
    "wof:placetype":"locality"
},
  "geometry": {"coordinates":[12.71667,9.23333],"type":"Point"}
}