{
  "type": "Feature",
  "properties": {
    "gn:admin1_code":"31.0",
    "gn:admin2_code":"27010.0",
    "gn:asciiname":"Kutigi",
    "gn:country_code":"NG",
    "gn:dem":102,
    "gn:feature_class":"P",
    "gn:feature_code":"PPL",
    "gn:name":"Kutigi",
    "gn:population":0,
    "gn:timezone":"Africa/Lagos",
    "iso:country":"NG",
    "wof:name":"Kutigi",
    "wof:placetype":"locality"
},
  "geometry": {"coordinates":[6.18114,9.42786],"type":"Point"}
}