{
  "type": "Feature",
  "properties": {
    "gn:admin1_code":"16.0",
    "gn:admin2_code":"28004.0",
    "gn:asciiname":"Ishukun",
    "gn:country_code":"NG",
    "gn:dem":101,
    "gn:feature_class":"P",
    "gn:feature_code":"PPL",
    "gn:name":"Ishukun",
    "gn:population":0,
    "gn:timezone":"Africa/Lagos",
    "iso:country":"NG",
    "wof:name":"Ishukun",
    "wof:placetype":"locality"
},
  "geometry": {"coordinates":[2.81667,7.38333],"type":"Point"}
}