{
  "type": "Feature",
  "properties": {
    "gn:admin1_code":"42.0",
    "gn:admin2_code":"30013.0",
    "gn:asciiname":"Oyo",
    "gn:country_code":"NG",
    "gn:dem":239,
    "gn:feature_class":"P",
    "gn:feature_code":"PPL",
    "gn:name":"Oyo",
    "gn:population":0,
    "gn:timezone":"Africa/Lagos",
    "iso:country":"NG",
    "wof:name":"Oyo",
    "wof:placetype":"locality"
},
  "geometry": {"coordinates":[4.48333,7.35],"type":"Point"}
}