{
  "type": "Feature",
  "properties": {
    "gn:admin1_code":"51.0",
    "gn:admin2_code":"621.0",
    "gn:admin3_code":"62111",
    "gn:asciiname":"Gidan Badanfari",
    "gn:country_code":"NG",
    "gn:dem":258,
    "gn:feature_class":"P",
    "gn:feature_code":"PPL",
    "gn:name":"Gidan Badanfari",
    "gn:population":0,
    "gn:timezone":"Africa/Lagos",
    "iso:country":"NG",
    "name:und_x_variant":[
        "Gidan Badamfari",
        "Gidan Badanfari"
    ],
    "wof:name":"Gidan Badanfari",
    "wof:placetype":"locality"
},
  "geometry": {"coordinates":[5.11501,13.03513],"type":"Point"}
}