{
  "type": "Feature",
  "properties": {
    "gn:admin1_code":"46.0",
    "gn:admin2_code":"5002.0",
    "gn:admin3_code":"BA0220",
    "gn:asciiname":"Kumgas",
    "gn:country_code":"NG",
    "gn:dem":519,
    "gn:feature_class":"P",
    "gn:feature_code":"PPL",
    "gn:name":"Kumgas",
    "gn:population":0,
    "gn:timezone":"Africa/Lagos",
    "iso:country":"NG",
    "wof:name":"Kumgas",
    "wof:placetype":"locality"
},
  "geometry": {"coordinates":[9.89333,10.06045],"type":"Point"}
}