{
  "type": "Feature",
  "properties": {
    "gn:admin1_code":"16.0",
    "gn:admin2_code":"28016.0",
    "gn:asciiname":"Olajogun",
    "gn:cc2":"NG",
    "gn:country_code":"NG",
    "gn:dem":102,
    "gn:feature_class":"P",
    "gn:feature_code":"PPL",
    "gn:name":"Olajogun",
    "gn:population":0,
    "gn:timezone":"Africa/Lagos",
    "iso:country":"NG",
    "name:und_x_variant":[
        "Alajogun",
        "Olajogun"
    ],
    "wof:name":"Olajogun",
    "wof:placetype":"locality"
},
  "geometry": {"coordinates":[3.41667,7.38333],"type":"Point"}
}