{
  "type": "Feature",
  "properties": {
    "gn:admin1_code":"39.0",
    "gn:admin2_code":"18026.0",
    "gn:admin3_code":"JI1405",
    "gn:asciiname":"Malam Atuman",
    "gn:country_code":"NG",
    "gn:dem":381,
    "gn:feature_class":"P",
    "gn:feature_code":"PPL",
    "gn:name":"Malam Atuman",
    "gn:population":0,
    "gn:timezone":"Africa/Lagos",
    "iso:country":"NG",
    "name:und_x_variant":[
        "Atuman",
        "Mallam Atuman",
        "Malam Atuman"
    ],
    "wof:name":"Malam Atuman",
    "wof:placetype":"locality"
},
  "geometry": {"coordinates":[9.49317,12.08002],"type":"Point"}
}