{
  "type": "Feature",
  "properties": {
    "gn:admin1_code":"43.0",
    "gn:asciiname":"Buno",
    "gn:country_code":"NG",
    "gn:dem":186,
    "gn:feature_class":"P",
    "gn:feature_code":"PPL",
    "gn:name":"Buno",
    "gn:population":0,
    "gn:timezone":"Africa/Lagos",
    "iso:country":"NG",
    "name:eng_x_preferred":[
        "Buno"
    ],
    "name:ind_x_preferred":[
        "Buno"
    ],
    "name:spa_x_preferred":[
        "Buno"
    ],
    "wof:name":"Buno",
    "wof:placetype":"locality"
},
  "geometry": {"coordinates":[11.61582,9.26471],"type":"Point"}
}