{
  "type": "Feature",
  "properties": {
    "gn:admin1_code":"27.0",
    "gn:admin2_code":"112.0",
    "gn:admin3_code":"11203",
    "gn:asciiname":"Luma",
    "gn:country_code":"NG",
    "gn:dem":545,
    "gn:feature_class":"P",
    "gn:feature_code":"PPL",
    "gn:name":"Luma",
    "gn:population":0,
    "gn:timezone":"Africa/Lagos",
    "iso:country":"NG",
    "name:ceb_x_preferred":[
        "Luma"
    ],
    "name:deu_x_preferred":[
        "Luma"
    ],
    "name:fin_x_preferred":[
        "Luma"
    ],
    "name:fra_x_preferred":[
        "Luma"
    ],
    "name:mar_x_preferred":[
        "\u0906\u0930\u094d\u092e\u0947\u0928\u093f\u092f\u0928 \u0932\u0941\u092e\u093e"
    ],
    "name:por_x_preferred":[
        "Luma"
    ],
    "name:rus_x_preferred":[
        "\u041b\u0443\u043c\u0430"
    ],
    "name:spa_x_preferred":[
        "Luma"
    ],
    "name:swe_x_preferred":[
        "Luma"
    ],
    "wof:name":"Luma",
    "wof:placetype":"locality"
},
  "geometry": {"coordinates":[12.10277,10.36082],"type":"Point"}
}