{
  "type": "Feature",
  "properties": {
    "gn:admin1_code":"40.0",
    "gn:admin2_code":"510.0",
    "gn:admin3_code":"51007",
    "gn:asciiname":"Kambaza-Hausawa",
    "gn:country_code":"NG",
    "gn:dem":231,
    "gn:feature_class":"P",
    "gn:feature_code":"PPL",
    "gn:name":"Kambaza-Hausawa",
    "gn:population":0,
    "gn:timezone":"Africa/Lagos",
    "iso:country":"NG",
    "name:und_x_variant":[
        "Kambaza",
        "Kambaza-Hausawa"
    ],
    "wof:name":"Kambaza-Hausawa",
    "wof:placetype":"locality"
},
  "geometry": {"coordinates":[4.56667,12.4527],"type":"Point"}
}