{
  "type": "Feature",
  "properties": {
    "gn:admin1_code":"25.0",
    "gn:admin2_code":"4016.0",
    "gn:asciiname":"Akiti-Ogidi",
    "gn:country_code":"NG",
    "gn:dem":21,
    "gn:feature_class":"P",
    "gn:feature_code":"PPL",
    "gn:name":"Akiti-Ogidi",
    "gn:population":0,
    "gn:timezone":"Africa/Lagos",
    "iso:country":"NG",
    "name:und_x_variant":[
        "Akri Ugidi",
        "Akri-Ogidi",
        "Akiti-Ogidi"
    ],
    "wof:name":"Akiti-Ogidi",
    "wof:placetype":"locality"
},
  "geometry": {"coordinates":[6.65706,5.75364],"type":"Point"}
}