{
  "type": "Feature",
  "properties": {
    "gn:admin1_code":"51.0",
    "gn:admin2_code":"621.0",
    "gn:admin3_code":"62110",
    "gn:asciiname":"Mesiji",
    "gn:country_code":"NG",
    "gn:dem":256,
    "gn:feature_class":"P",
    "gn:feature_code":"PPL",
    "gn:name":"Mesiji",
    "gn:population":0,
    "gn:timezone":"Africa/Lagos",
    "iso:country":"NG",
    "wof:name":"Mesiji",
    "wof:placetype":"locality"
},
  "geometry": {"coordinates":[5.11349,13.07388],"type":"Point"}
}