{
  "type": "Feature",
  "properties": {
    "gn:admin1_code":"41.0",
    "gn:admin2_code":"23004.0",
    "gn:asciiname":"Kipi",
    "gn:country_code":"NG",
    "gn:dem":90,
    "gn:feature_class":"P",
    "gn:feature_code":"PPL",
    "gn:name":"Kipi",
    "gn:population":0,
    "gn:timezone":"Africa/Lagos",
    "iso:country":"NG",
    "name:und_x_variant":[
        "Chikpi",
        "Kipi"
    ],
    "wof:name":"Kipi",
    "wof:placetype":"locality"
},
  "geometry": {"coordinates":[7.1189,7.85478],"type":"Point"}
}