{
  "type": "Feature",
  "properties": {
    "gn:admin1_code":"22.0",
    "gn:admin2_code":"9018.0",
    "gn:asciiname":"Mbur",
    "gn:country_code":"NG",
    "gn:dem":129,
    "gn:feature_class":"P",
    "gn:feature_code":"PPL",
    "gn:name":"Mbur",
    "gn:population":0,
    "gn:timezone":"Africa/Lagos",
    "iso:country":"NG",
    "name:und_x_variant":[
        "Mbor",
        "Mbur"
    ],
    "wof:name":"Mbur",
    "wof:placetype":"locality"
},
  "geometry": {"coordinates":[8.79044,6.85971],"type":"Point"}
}