{
  "type": "Feature",
  "properties": {
    "gn:admin1_code":"35.0",
    "gn:admin2_code":"2020.0",
    "gn:asciiname":"Kulango",
    "gn:country_code":"NG",
    "gn:dem":167,
    "gn:feature_class":"P",
    "gn:feature_code":"PPL",
    "gn:name":"Kulango",
    "gn:population":0,
    "gn:timezone":"Africa/Lagos",
    "iso:country":"NG",
    "name:und_x_variant":[
        "Kalangu",
        "Kulangu",
        "Kulango"
    ],
    "wof:name":"Kulango",
    "wof:placetype":"locality"
},
  "geometry": {"coordinates":[12.29647,9.3615],"type":"Point"}
}