{
  "type": "Feature",
  "properties": {
    "gn:admin1_code":"50.0",
    "gn:admin2_code":"33007.0",
    "gn:asciiname":"Egelebie-Jumbo",
    "gn:country_code":"NG",
    "gn:dem":8,
    "gn:feature_class":"P",
    "gn:feature_code":"PPL",
    "gn:name":"Egelebie-Jumbo",
    "gn:population":0,
    "gn:timezone":"Africa/Lagos",
    "iso:country":"NG",
    "wof:name":"Egelebie-Jumbo",
    "wof:placetype":"locality"
},
  "geometry": {"coordinates":[7.28652,4.43448],"type":"Point"}
}