{
  "type": "Feature",
  "properties": {
    "gn:admin1_code":"27.0",
    "gn:admin2_code":"127.0",
    "gn:admin3_code":"12703",
    "gn:asciiname":"Gasi",
    "gn:country_code":"NG",
    "gn:dem":251,
    "gn:feature_class":"P",
    "gn:feature_code":"PPL",
    "gn:name":"Gasi",
    "gn:population":0,
    "gn:timezone":"Africa/Lagos",
    "iso:country":"NG",
    "name:ceb_x_preferred":[
        "Gazi"
    ],
    "name:swe_x_preferred":[
        "Gazi"
    ],
    "wof:name":"Gasi",
    "wof:placetype":"locality"
},
  "geometry": {"coordinates":[11.80039,10.21352],"type":"Point"}
}