{
  "type": "Feature",
  "properties": {
    "gn:admin1_code":"23.0",
    "gn:admin2_code":"19022",
    "gn:admin3_code":"KD2204",
    "gn:asciiname":"Balet",
    "gn:country_code":"NG",
    "gn:dem":757,
    "gn:feature_class":"P",
    "gn:feature_code":"PPL",
    "gn:name":"Balet",
    "gn:population":0,
    "gn:timezone":"Africa/Lagos",
    "iso:country":"NG",
    "wof:name":"Balet",
    "wof:placetype":"locality"
},
  "geometry": {"coordinates":[8.16302,9.67656],"type":"Point"}
}