{
  "type": "Feature",
  "properties": {
    "gn:admin1_code":"31.0",
    "gn:admin2_code":"27019.0",
    "gn:asciiname":"Yida",
    "gn:country_code":"NG",
    "gn:dem":289,
    "gn:feature_class":"P",
    "gn:feature_code":"PPL",
    "gn:name":"Yida",
    "gn:population":0,
    "gn:timezone":"Africa/Lagos",
    "iso:country":"NG",
    "name:und_x_variant":[
        "Yidna",
        "Yida"
    ],
    "wof:name":"Yida",
    "wof:placetype":"locality"
},
  "geometry": {"coordinates":[6.6301,9.36547],"type":"Point"}
}