{
  "type": "Feature",
  "properties": {
    "gn:admin1_code":"49.0",
    "gn:admin2_code":"32015.0",
    "gn:asciiname":"Kwi",
    "gn:country_code":"NG",
    "gn:dem":1276,
    "gn:feature_class":"P",
    "gn:feature_code":"PPL",
    "gn:name":"Kwi",
    "gn:population":0,
    "gn:timezone":"Africa/Lagos",
    "iso:country":"NG",
    "wof:name":"Kwi",
    "wof:placetype":"locality"
},
  "geometry": {"coordinates":[8.84827,9.6243],"type":"Point"}
}