{
  "type": "Feature",
  "properties": {
    "gn:admin1_code":"26.0",
    "gn:admin2_code":"7007",
    "gn:asciiname":"Uzer",
    "gn:country_code":"NG",
    "gn:dem":177,
    "gn:feature_class":"P",
    "gn:feature_code":"PPL",
    "gn:name":"Uzer",
    "gn:population":0,
    "gn:timezone":"Africa/Lagos",
    "iso:country":"NG",
    "name:arg_x_preferred":[
        "Uzer"
    ],
    "name:ceb_x_preferred":[
        "Uzer"
    ],
    "name:deu_x_preferred":[
        "Uzer"
    ],
    "name:fra_x_preferred":[
        "Uzer"
    ],
    "name:ita_x_preferred":[
        "Uzer"
    ],
    "name:nds_x_preferred":[
        "Uzer"
    ],
    "name:nld_x_preferred":[
        "Uzer"
    ],
    "name:pms_x_preferred":[
        "Uzer"
    ],
    "name:pol_x_preferred":[
        "Uzer"
    ],
    "name:por_x_preferred":[
        "Uzer"
    ],
    "name:rus_x_preferred":[
        "\u042e\u0437\u0435"
    ],
    "name:scn_x_preferred":[
        "Uzer"
    ],
    "name:slk_x_preferred":[
        "Uzer"
    ],
    "name:spa_x_preferred":[
        "Uzer"
    ],
    "name:swe_x_preferred":[
        "Uzer"
    ],
    "name:ukr_x_preferred":[
        "\u042e\u0437\u0435"
    ],
    "wof:name":"Uzer",
    "wof:placetype":"locality"
},
  "geometry": {"coordinates":[8.45001,7.29535],"type":"Point"}
}