{
  "type": "Feature",
  "properties": {
    "gn:admin1_code":"29.0",
    "gn:admin2_code":"20025.0",
    "gn:admin3_code":"KN0410",
    "gn:asciiname":"Chutar Buki",
    "gn:country_code":"NG",
    "gn:dem":570,
    "gn:feature_class":"P",
    "gn:feature_code":"PPL",
    "gn:name":"Chutar Buki",
    "gn:population":0,
    "gn:timezone":"Africa/Lagos",
    "iso:country":"NG",
    "wof:name":"Chutar Buki",
    "wof:placetype":"locality"
},
  "geometry": {"coordinates":[8.31261,11.4261],"type":"Point"}
}