{
  "type": "Feature",
  "properties": {
    "gn:admin1_code":"29.0",
    "gn:admin2_code":"20016.0",
    "gn:admin3_code":"KN1309",
    "gn:asciiname":"Seyi",
    "gn:country_code":"NG",
    "gn:dem":406,
    "gn:feature_class":"P",
    "gn:feature_code":"PPL",
    "gn:name":"Seyi",
    "gn:population":0,
    "gn:timezone":"Africa/Lagos",
    "iso:country":"NG",
    "name:und_x_variant":[
        "Badawa",
        "Seyi"
    ],
    "wof:name":"Seyi",
    "wof:placetype":"locality"
},
  "geometry": {"coordinates":[8.89542,12.26486],"type":"Point"}
}