{
  "type": "Feature",
  "properties": {
    "gn:admin1_code":"26.0",
    "gn:admin2_code":"7008.0",
    "gn:asciiname":"Abe",
    "gn:country_code":"NG",
    "gn:dem":102,
    "gn:feature_class":"P",
    "gn:feature_code":"PPL",
    "gn:name":"Abe",
    "gn:population":0,
    "gn:timezone":"Africa/Lagos",
    "iso:country":"NG",
    "name:cat_x_preferred":[
        "Abe"
    ],
    "name:ceb_x_preferred":[
        "Abe"
    ],
    "name:ces_x_preferred":[
        "Abe"
    ],
    "name:dan_x_preferred":[
        "Abe"
    ],
    "name:deu_x_preferred":[
        "Abe"
    ],
    "name:est_x_preferred":[
        "Abe"
    ],
    "name:fin_x_preferred":[
        "Abe"
    ],
    "name:fra_x_preferred":[
        "Abe"
    ],
    "name:kat_x_preferred":[
        "\u10d0\u10d1\u10d4"
    ],
    "name:nld_x_preferred":[
        "Abe"
    ],
    "name:pol_x_preferred":[
        "Abe"
    ],
    "name:por_x_preferred":[
        "Abe"
    ],
    "name:spa_x_preferred":[
        "Abe"
    ],
    "name:swe_x_preferred":[
        "Abe"
    ],
    "wof:name":"Abe",
    "wof:placetype":"locality"
},
  "geometry": {"coordinates":[8.26917,7.66945],"type":"Point"}
}