{
  "type": "Feature",
  "properties": {
    "gn:admin1_code":"43.0",
    "gn:asciiname":"Kindang",
    "gn:country_code":"NG",
    "gn:dem":175,
    "gn:feature_class":"P",
    "gn:feature_code":"PPL",
    "gn:name":"Kindang",
    "gn:population":0,
    "gn:timezone":"Africa/Lagos",
    "iso:country":"NG",
    "name:eng_x_preferred":[
        "Kindang"
    ],
    "wof:name":"Kindang",
    "wof:placetype":"locality"
},
  "geometry": {"coordinates":[11.20846,9.11629],"type":"Point"}
}