{
  "type": "Feature",
  "properties": {
    "gn:admin1_code":"51.0",
    "gn:admin2_code":"607.0",
    "gn:admin3_code":"60708",
    "gn:asciiname":"Makina",
    "gn:country_code":"NG",
    "gn:dem":265,
    "gn:feature_class":"P",
    "gn:feature_code":"PPL",
    "gn:name":"Makina",
    "gn:population":0,
    "gn:timezone":"Africa/Lagos",
    "iso:country":"NG",
    "wof:name":"Makina",
    "wof:placetype":"locality"
},
  "geometry": {"coordinates":[5.28722,13.58441],"type":"Point"}
}