{
  "type": "Feature",
  "properties": {
    "gn:admin1_code":"46.0",
    "gn:admin2_code":"5010.0",
    "gn:admin3_code":"BA1015",
    "gn:asciiname":"Katambus",
    "gn:country_code":"NG",
    "gn:dem":385,
    "gn:feature_class":"P",
    "gn:feature_code":"PPL",
    "gn:name":"Katambus",
    "gn:population":0,
    "gn:timezone":"Africa/Lagos",
    "iso:country":"NG",
    "wof:name":"Katambus",
    "wof:placetype":"locality"
},
  "geometry": {"coordinates":[9.95,11.81667],"type":"Point"}
}