{
  "type": "Feature",
  "properties": {
    "gn:admin1_code":"51.0",
    "gn:admin2_code":"614.0",
    "gn:admin3_code":"61401",
    "gn:asciiname":"Rugar Fako",
    "gn:country_code":"NG",
    "gn:dem":279,
    "gn:feature_class":"P",
    "gn:feature_code":"PPL",
    "gn:name":"Rugar Fako",
    "gn:population":0,
    "gn:timezone":"Africa/Lagos",
    "iso:country":"NG",
    "wof:name":"Rugar Fako",
    "wof:placetype":"locality"
},
  "geometry": {"coordinates":[5.10084,12.70232],"type":"Point"}
}