{
  "type": "Feature",
  "properties": {
    "gn:admin1_code":"21.0",
    "gn:admin2_code":"3012.0",
    "gn:asciiname":"Ndiya Etuk",
    "gn:country_code":"NG",
    "gn:dem":110,
    "gn:feature_class":"P",
    "gn:feature_code":"PPL",
    "gn:name":"Ndiya Etuk",
    "gn:population":0,
    "gn:timezone":"Africa/Lagos",
    "iso:country":"NG",
    "wof:name":"Ndiya Etuk",
    "wof:placetype":"locality"
},
  "geometry": {"coordinates":[7.72854,5.22697],"type":"Point"}
}