{
  "type": "Feature",
  "properties": {
    "gn:admin1_code":"27.0",
    "gn:admin2_code":"112.0",
    "gn:admin3_code":"11211",
    "gn:asciiname":"Tasha Ngwa",
    "gn:country_code":"NG",
    "gn:dem":840,
    "gn:feature_class":"P",
    "gn:feature_code":"PPL",
    "gn:name":"Tasha Ngwa",
    "gn:population":0,
    "gn:timezone":"Africa/Lagos",
    "iso:country":"NG",
    "wof:name":"Tasha Ngwa",
    "wof:placetype":"locality"
},
  "geometry": {"coordinates":[12.20664,10.53057],"type":"Point"}
}