{
  "type": "Feature",
  "properties": {
    "gn:admin1_code":"52.0",
    "gn:admin2_code":"6002.0",
    "gn:asciiname":"Ufort Camp",
    "gn:country_code":"NG",
    "gn:dem":17,
    "gn:feature_class":"P",
    "gn:feature_code":"PPL",
    "gn:name":"Ufort Camp",
    "gn:population":0,
    "gn:timezone":"Africa/Lagos",
    "iso:country":"NG",
    "name:eng_x_preferred":[
        "Ufort Camp"
    ],
    "name:eng_x_variant":[
        "Ufort"
    ],
    "wof:name":"Ufort Camp",
    "wof:placetype":"locality"
},
  "geometry": {"coordinates":[5.7102,4.9732],"type":"Point"}
}