{
  "type": "Feature",
  "properties": {
    "gn:admin1_code":"44.0",
    "gn:admin2_code":"705.0",
    "gn:admin3_code":"70502",
    "gn:asciiname":"Alhaji",
    "gn:country_code":"NG",
    "gn:dem":407,
    "gn:feature_class":"P",
    "gn:feature_code":"PPL",
    "gn:name":"Alhaji",
    "gn:population":0,
    "gn:timezone":"Africa/Lagos",
    "iso:country":"NG",
    "wof:name":"Alhaji",
    "wof:placetype":"locality"
},
  "geometry": {"coordinates":[11.3494,11.67973],"type":"Point"}
}