{
  "type": "Feature",
  "properties": {
    "gn:admin1_code":"29.0",
    "gn:admin2_code":"20040.0",
    "gn:admin3_code":"KN3011",
    "gn:asciiname":"Kaleko",
    "gn:country_code":"NG",
    "gn:dem":445,
    "gn:feature_class":"P",
    "gn:feature_code":"PPL",
    "gn:name":"Kaleko",
    "gn:population":0,
    "gn:timezone":"Africa/Lagos",
    "iso:country":"NG",
    "wof:name":"Kaleko",
    "wof:placetype":"locality"
},
  "geometry": {"coordinates":[8.66894,12.15993],"type":"Point"}
}