{
  "type": "Feature",
  "properties": {
    "gn:admin1_code":"43.0",
    "gn:admin2_code":"35014",
    "gn:asciiname":"Tsehambar",
    "gn:country_code":"NG",
    "gn:dem":169,
    "gn:feature_class":"P",
    "gn:feature_code":"PPL",
    "gn:name":"Tsehambar",
    "gn:population":0,
    "gn:timezone":"Africa/Lagos",
    "iso:country":"NG",
    "name:und_x_variant":[
        "Tsehamber"
    ],
    "wof:name":"Tsehambar",
    "wof:placetype":"locality"
},
  "geometry": {"coordinates":[9.88981,7.79077],"type":"Point"}
}