{
  "type": "Feature",
  "properties": {
    "iso:country":"NG",
    "name:eng_x_preferred":[
        "Jega"
    ],
    "name:hau_x_preferred":[
        "Jega"
    ],
    "name:ita_x_preferred":[
        "Jega"
    ],
    "name:jpn_x_preferred":[
        "\u30b8\u30a7\u30ac"
    ],
    "name:nan_x_preferred":[
        "Jega"
    ],
    "name:nld_x_preferred":[
        "Jega"
    ],
    "name:pol_x_preferred":[
        "Jega"
    ],
    "name:ron_x_preferred":[
        "Jega"
    ],
    "name:spa_x_preferred":[
        "Jega"
    ],
    "name:yor_x_preferred":[
        "Jega"
    ],
    "qs:gn_country":"NG",
    "qs:gn_fcode":"PPL",
    "qs:gn_pop":73495,
    "qs:name":"Jega",
    "qs:name_adm0":"Nigeria",
    "qs:name_adm1":"Kebbi",
    "qs:photos":0,
    "qs:photos_1k":0,
    "qs:photos_9k":0,
    "qs:photos_9r":0,
    "qs:photos_all":0,
    "qs:photos_sr":0,
    "qs:placetype":"Town",
    "qs:pop_sr":"8",
    "qs:woe_adm0":23424908,
    "wd:wordcount":23,
    "wof:name":"Jega",
    "wof:placetype":"locality",
    "wof:population":73495
},
  "geometry": {"coordinates":[4.37917,12.2175],"type":"Point"}
}