{
  "type": "Feature",
  "properties": {
    "gn:admin1_code":"46.0",
    "gn:admin2_code":"5018.0",
    "gn:admin3_code":"BA1809",
    "gn:asciiname":"Doka",
    "gn:country_code":"NG",
    "gn:dem":796,
    "gn:feature_class":"P",
    "gn:feature_code":"PPL",
    "gn:name":"Doka",
    "gn:population":0,
    "gn:timezone":"Africa/Lagos",
    "iso:country":"NG",
    "name:ceb_x_preferred":[
        "Doka"
    ],
    "name:deu_x_preferred":[
        "Doka"
    ],
    "name:swe_x_preferred":[
        "Doka"
    ],
    "wof:name":"Doka",
    "wof:placetype":"locality"
},
  "geometry": {"coordinates":[8.99314,10.65045],"type":"Point"}
}