{
  "type": "Feature",
  "properties": {
    "gn:admin1_code":"23.0",
    "gn:admin2_code":"19020.0",
    "gn:admin3_code":"KD2009",
    "gn:asciiname":"Babaru",
    "gn:country_code":"NG",
    "gn:dem":584,
    "gn:feature_class":"P",
    "gn:feature_code":"PPL",
    "gn:name":"Babaru",
    "gn:population":0,
    "gn:timezone":"Africa/Lagos",
    "iso:country":"NG",
    "wof:name":"Babaru",
    "wof:placetype":"locality"
},
  "geometry": {"coordinates":[8.58119,9.1125],"type":"Point"}
}