{
  "type": "Feature",
  "properties": {
    "gn:admin1_code":"36.0",
    "gn:admin2_code":"10009.0",
    "gn:asciiname":"Ilue-Ologbo",
    "gn:country_code":"NG",
    "gn:dem":15,
    "gn:feature_class":"P",
    "gn:feature_code":"PPL",
    "gn:name":"Ilue-Ologbo",
    "gn:population":0,
    "gn:timezone":"Africa/Lagos",
    "iso:country":"NG",
    "name:und_x_variant":[
        "Ilueologbo Owe",
        "Ilue-Ologbo"
    ],
    "wof:name":"Ilue-Ologbo",
    "wof:placetype":"locality"
},
  "geometry": {"coordinates":[6.19705,5.59294],"type":"Point"}
}