{
  "type": "Feature",
  "properties": {
    "gn:admin1_code":"23.0",
    "gn:admin2_code":"19005.0",
    "gn:admin3_code":"KD0501",
    "gn:asciiname":"Gidan Sani",
    "gn:country_code":"NG",
    "gn:dem":653,
    "gn:feature_class":"P",
    "gn:feature_code":"PPL",
    "gn:name":"Gidan Sani",
    "gn:population":0,
    "gn:timezone":"Africa/Lagos",
    "iso:country":"NG",
    "name:und_x_variant":[
        "Sani",
        "Gidan Sani"
    ],
    "wof:name":"Gidan Sani",
    "wof:placetype":"locality"
},
  "geometry": {"coordinates":[8.04035,11.40806],"type":"Point"}
}