{
  "type": "Feature",
  "properties": {
    "gn:admin1_code":"39.0",
    "gn:admin2_code":"18019.0",
    "gn:admin3_code":"JI2701",
    "gn:asciiname":"Achilafia",
    "gn:country_code":"NG",
    "gn:dem":475,
    "gn:feature_class":"P",
    "gn:feature_code":"PPL",
    "gn:name":"Achilafia",
    "gn:population":0,
    "gn:timezone":"Africa/Lagos",
    "iso:country":"NG",
    "wof:name":"Achilafia",
    "wof:placetype":"locality"
},
  "geometry": {"coordinates":[8.39602,12.80055],"type":"Point"}
}