{
  "type": "Feature",
  "properties": {
    "gn:admin1_code":"37.0",
    "gn:admin2_code":"12012.0",
    "gn:asciiname":"Ureghin",
    "gn:country_code":"NG",
    "gn:dem":28,
    "gn:feature_class":"P",
    "gn:feature_code":"PPL",
    "gn:name":"Ureghin",
    "gn:population":0,
    "gn:timezone":"Africa/Lagos",
    "iso:country":"NG",
    "wof:name":"Ureghin",
    "wof:placetype":"locality"
},
  "geometry": {"coordinates":[5.51667,6.18333],"type":"Point"}
}