{
  "type": "Feature",
  "properties": {
    "gn:admin1_code":"51.0",
    "gn:admin2_code":"604.0",
    "gn:admin3_code":"60405",
    "gn:asciiname":"Gidan Jado",
    "gn:country_code":"NG",
    "gn:dem":292,
    "gn:feature_class":"P",
    "gn:feature_code":"PPL",
    "gn:name":"Gidan Jado",
    "gn:population":0,
    "gn:timezone":"Africa/Lagos",
    "iso:country":"NG",
    "wof:name":"Gidan Jado",
    "wof:placetype":"locality"
},
  "geometry": {"coordinates":[5.73561,13.64471],"type":"Point"}
}