{
  "type": "Feature",
  "properties": {
    "gn:admin1_code":"43.0",
    "gn:admin2_code":"35008.0",
    "gn:asciiname":"Wiang",
    "gn:country_code":"NG",
    "gn:dem":260,
    "gn:feature_class":"P",
    "gn:feature_code":"PPL",
    "gn:name":"Wiang",
    "gn:population":0,
    "gn:timezone":"Africa/Lagos",
    "iso:country":"NG",
    "name:eng_x_preferred":[
        "Wiang"
    ],
    "name:tha_x_preferred":[
        "\u0e40\u0e27\u0e35\u0e22\u0e07"
    ],
    "wof:name":"Wiang",
    "wof:placetype":"locality"
},
  "geometry": {"coordinates":[10.92306,9.37173],"type":"Point"}
}