{
  "type": "Feature",
  "properties": {
    "gn:admin1_code":"42.0",
    "gn:admin2_code":"30029.0",
    "gn:asciiname":"Ikolo",
    "gn:country_code":"NG",
    "gn:dem":356,
    "gn:feature_class":"P",
    "gn:feature_code":"PPL",
    "gn:name":"Ikolo",
    "gn:population":0,
    "gn:timezone":"Africa/Lagos",
    "iso:country":"NG",
    "name:swa_x_preferred":[
        "Ikolo"
    ],
    "wof:name":"Ikolo",
    "wof:placetype":"locality"
},
  "geometry": {"coordinates":[4.45,7.88333],"type":"Point"}
}