{
  "type": "Feature",
  "properties": {
    "gn:admin1_code":"36.0",
    "gn:admin2_code":"10011.0",
    "gn:asciiname":"Okoroafor",
    "gn:country_code":"NG",
    "gn:dem":18,
    "gn:feature_class":"P",
    "gn:feature_code":"PPL",
    "gn:name":"Okoroafor",
    "gn:population":0,
    "gn:timezone":"Africa/Lagos",
    "iso:country":"NG",
    "wof:name":"Okoroafor",
    "wof:placetype":"locality"
},
  "geometry": {"coordinates":[6.38669,5.49038],"type":"Point"}
}