{
  "type": "Feature",
  "properties": {
    "gn:admin1_code":"56.0",
    "gn:admin2_code":"26013.0",
    "gn:asciiname":"Gimba",
    "gn:country_code":"NG",
    "gn:dem":468,
    "gn:feature_class":"P",
    "gn:feature_code":"PPL",
    "gn:name":"Gimba",
    "gn:population":0,
    "gn:timezone":"Africa/Lagos",
    "iso:country":"NG",
    "wof:name":"Gimba",
    "wof:placetype":"locality"
},
  "geometry": {"coordinates":[8.62005,9.012],"type":"Point"}
}