{
  "type": "Feature",
  "properties": {
    "gn:admin1_code":"50.0",
    "gn:asciiname":"Finima",
    "gn:country_code":"NG",
    "gn:dem":459,
    "gn:feature_class":"P",
    "gn:feature_code":"PPL",
    "gn:name":"Finima",
    "gn:population":0,
    "gn:timezone":"Africa/Lagos",
    "iso:country":"NG",
    "wof:name":"Finima",
    "wof:placetype":"locality"
},
  "geometry": {"coordinates":[7.13652,4.41273],"type":"Point"}
}