{
  "type": "Feature",
  "properties": {
    "gn:admin1_code":"26.0",
    "gn:admin2_code":"7021",
    "gn:asciiname":"Ate",
    "gn:country_code":"NG",
    "gn:dem":174,
    "gn:feature_class":"P",
    "gn:feature_code":"PPL",
    "gn:name":"Ate",
    "gn:population":0,
    "gn:timezone":"Africa/Lagos",
    "iso:country":"NG",
    "name:cat_x_preferred":[
        "Ate"
    ],
    "name:ceb_x_preferred":[
        "Ate"
    ],
    "name:deu_x_preferred":[
        "Ate"
    ],
    "name:eus_x_preferred":[
        "Ate"
    ],
    "name:hun_x_preferred":[
        "ATE"
    ],
    "name:lat_x_preferred":[
        "Ate"
    ],
    "name:nds_x_preferred":[
        "Ate"
    ],
    "name:por_x_preferred":[
        "Ate"
    ],
    "name:spa_x_preferred":[
        "Ate"
    ],
    "wof:name":"Ate",
    "wof:placetype":"locality"
},
  "geometry": {"coordinates":[9.54987,7.71705],"type":"Point"}
}