{
  "type": "Feature",
  "properties": {
    "gn:admin1_code":"46.0",
    "gn:admin2_code":"5001.0",
    "gn:admin3_code":"BA0105",
    "gn:asciiname":"Shugu",
    "gn:country_code":"NG",
    "gn:dem":370,
    "gn:feature_class":"P",
    "gn:feature_code":"PPL",
    "gn:name":"Shugu",
    "gn:population":0,
    "gn:timezone":"Africa/Lagos",
    "iso:country":"NG",
    "name:eng_x_preferred":[
        "Shugu"
    ],
    "name:eng_x_variant":[
        "Shuga"
    ],
    "wof:name":"Shugu",
    "wof:placetype":"locality"
},
  "geometry": {"coordinates":[10.76657,10.22398],"type":"Point"}
}