{
  "type": "Feature",
  "properties": {
    "gn:admin1_code":"31.0",
    "gn:admin2_code":"27014.0",
    "gn:asciiname":"Lagumo",
    "gn:country_code":"NG",
    "gn:dem":291,
    "gn:feature_class":"P",
    "gn:feature_code":"PPL",
    "gn:name":"Lagumo",
    "gn:population":0,
    "gn:timezone":"Africa/Lagos",
    "iso:country":"NG",
    "wof:name":"Lagumo",
    "wof:placetype":"locality"
},
  "geometry": {"coordinates":[5.17586,10.40046],"type":"Point"}
}