{
  "type": "Feature",
  "properties": {
    "gn:admin1_code":"43.0",
    "gn:admin2_code":"35003",
    "gn:asciiname":"Gwahemba",
    "gn:country_code":"NG",
    "gn:dem":165,
    "gn:feature_class":"P",
    "gn:feature_code":"PPL",
    "gn:name":"Gwahemba",
    "gn:population":0,
    "gn:timezone":"Africa/Lagos",
    "iso:country":"NG",
    "wof:name":"Gwahemba",
    "wof:placetype":"locality"
},
  "geometry": {"coordinates":[9.97399,7.61569],"type":"Point"}
}