{
  "type": "Feature",
  "properties": {
    "gn:admin1_code":"24.0",
    "gn:admin2_code":"432.0",
    "gn:admin3_code":"43205",
    "gn:asciiname":"Sabawa",
    "gn:country_code":"NG",
    "gn:dem":475,
    "gn:feature_class":"P",
    "gn:feature_code":"PPL",
    "gn:name":"Sabawa",
    "gn:population":0,
    "gn:timezone":"Africa/Lagos",
    "iso:country":"NG",
    "wof:name":"Sabawa",
    "wof:placetype":"locality"
},
  "geometry": {"coordinates":[7.29277,12.4301],"type":"Point"}
}