{
  "type": "Feature",
  "properties": {
    "gn:admin1_code":"37.0",
    "gn:admin2_code":"12016.0",
    "gn:asciiname":"Isokka",
    "gn:country_code":"NG",
    "gn:dem":163,
    "gn:feature_class":"P",
    "gn:feature_code":"PPL",
    "gn:name":"Isokka",
    "gn:population":0,
    "gn:timezone":"Africa/Lagos",
    "iso:country":"NG",
    "wof:name":"Isokka",
    "wof:placetype":"locality"
},
  "geometry": {"coordinates":[6.1003,7.0788],"type":"Point"}
}