{
  "type": "Feature",
  "properties": {
    "gn:admin1_code":"26.0",
    "gn:admin2_code":"7004",
    "gn:asciiname":"Yaga",
    "gn:country_code":"NG",
    "gn:dem":125,
    "gn:feature_class":"P",
    "gn:feature_code":"PPL",
    "gn:name":"Yaga",
    "gn:population":0,
    "gn:timezone":"Africa/Lagos",
    "iso:country":"NG",
    "name:ceb_x_preferred":[
        "Yaga"
    ],
    "name:fra_x_preferred":[
        "Yaga"
    ],
    "name:swe_x_preferred":[
        "Yaga"
    ],
    "wof:name":"Yaga",
    "wof:placetype":"locality"
},
  "geometry": {"coordinates":[9.09327,7.53414],"type":"Point"}
}