{
  "type": "Feature",
  "properties": {
    "gn:admin1_code":"27.0",
    "gn:admin2_code":"115.0",
    "gn:admin3_code":"11506",
    "gn:asciiname":"Abulkuri",
    "gn:country_code":"NG",
    "gn:dem":298,
    "gn:feature_class":"P",
    "gn:feature_code":"PPL",
    "gn:name":"Abulkuri",
    "gn:population":0,
    "gn:timezone":"Africa/Lagos",
    "iso:country":"NG",
    "wof:name":"Abulkuri",
    "wof:placetype":"locality"
},
  "geometry": {"coordinates":[14.34558,11.68858],"type":"Point"}
}