{
  "type": "Feature",
  "properties": {
    "gn:admin1_code":"46.0",
    "gn:admin2_code":"5020",
    "gn:admin3_code":"BA2013",
    "gn:asciiname":"Buzukwa",
    "gn:country_code":"NG",
    "gn:dem":366,
    "gn:feature_class":"P",
    "gn:feature_code":"PPL",
    "gn:name":"Buzukwa",
    "gn:population":0,
    "gn:timezone":"Africa/Lagos",
    "iso:country":"NG",
    "wof:name":"Buzukwa",
    "wof:placetype":"locality"
},
  "geometry": {"coordinates":[10.3534,12.16576],"type":"Point"}
}