{
  "type": "Feature",
  "properties": {
    "gn:admin1_code":"41.0",
    "gn:admin2_code":"23021.0",
    "gn:asciiname":"Odo-Ere",
    "gn:country_code":"NG",
    "gn:dem":311,
    "gn:feature_class":"P",
    "gn:feature_code":"PPLA2",
    "gn:name":"Odo-Ere",
    "gn:population":0,
    "gn:timezone":"Africa/Lagos",
    "iso:country":"NG",
    "name:und_x_variant":[
        "Eri",
        "Odo-Ere",
        "Odo Ore"
    ],
    "wof:name":"Odo-Ere",
    "wof:placetype":"locality"
},
  "geometry": {"coordinates":[5.54979,8.25057],"type":"Point"}
}