{
  "type": "Feature",
  "properties": {
    "gn:admin1_code":"51.0",
    "gn:admin2_code":"623.0",
    "gn:admin3_code":"62303",
    "gn:asciiname":"Tili",
    "gn:country_code":"NG",
    "gn:dem":241,
    "gn:feature_class":"P",
    "gn:feature_code":"PPL",
    "gn:name":"Tili",
    "gn:population":0,
    "gn:timezone":"Africa/Lagos",
    "iso:country":"NG",
    "wof:name":"Tili",
    "wof:placetype":"locality"
},
  "geometry": {"coordinates":[4.86272,12.82575],"type":"Point"}
}