{
  "type": "Feature",
  "properties": {
    "gn:admin1_code":"56.0",
    "gn:admin2_code":"26001",
    "gn:asciiname":"Ungwan Koshun",
    "gn:country_code":"NG",
    "gn:dem":477,
    "gn:feature_class":"P",
    "gn:feature_code":"PPL",
    "gn:name":"Ungwan Koshun",
    "gn:population":0,
    "gn:timezone":"Africa/Lagos",
    "iso:country":"NG",
    "wof:name":"Ungwan Koshun",
    "wof:placetype":"locality"
},
  "geometry": {"coordinates":[8.1884,9.00898],"type":"Point"}
}