{
  "type": "Feature",
  "properties": {
    "gn:admin1_code":"49.0",
    "gn:admin2_code":"32003.0",
    "gn:asciiname":"William Camp",
    "gn:country_code":"NG",
    "gn:dem":1241,
    "gn:feature_class":"P",
    "gn:feature_code":"PPL",
    "gn:name":"William Camp",
    "gn:population":0,
    "gn:timezone":"Africa/Lagos",
    "iso:country":"NG",
    "wof:name":"William Camp",
    "wof:placetype":"locality"
},
  "geometry": {"coordinates":[8.73159,9.20917],"type":"Point"}
}