{
  "type": "Feature",
  "properties": {
    "gn:admin1_code":"32.0",
    "gn:admin2_code":"31016.0",
    "gn:asciiname":"Abolohunko",
    "gn:country_code":"NG",
    "gn:dem":173,
    "gn:feature_class":"P",
    "gn:feature_code":"PPL",
    "gn:name":"Abolohunko",
    "gn:population":0,
    "gn:timezone":"Africa/Lagos",
    "iso:country":"NG",
    "wof:name":"Abolohunko",
    "wof:placetype":"locality"
},
  "geometry": {"coordinates":[3.35,7.66667],"type":"Point"}
}