{
  "type": "Feature",
  "properties": {
    "gn:admin1_code":"49.0",
    "gn:admin2_code":"32010",
    "gn:asciiname":"Takalafia",
    "gn:country_code":"NG",
    "gn:dem":181,
    "gn:feature_class":"P",
    "gn:feature_code":"PPL",
    "gn:name":"Takalafia",
    "gn:population":0,
    "gn:timezone":"Africa/Lagos",
    "iso:country":"NG",
    "wof:name":"Takalafia",
    "wof:placetype":"locality"
},
  "geometry": {"coordinates":[9.7991,8.64551],"type":"Point"}
}