{
  "type": "Feature",
  "properties": {
    "gn:admin1_code":"27.0",
    "gn:admin2_code":"117",
    "gn:admin3_code":"11706",
    "gn:asciiname":"Kukiliya",
    "gn:country_code":"NG",
    "gn:dem":284,
    "gn:feature_class":"P",
    "gn:feature_code":"PPL",
    "gn:name":"Kukiliya",
    "gn:population":0,
    "gn:timezone":"Africa/Lagos",
    "iso:country":"NG",
    "name:und_x_variant":[
        "Dodo"
    ],
    "wof:name":"Kukiliya",
    "wof:placetype":"locality"
},
  "geometry": {"coordinates":[13.77154,13.28264],"type":"Point"}
}