{
  "type": "Feature",
  "properties": {
    "gn:admin1_code":"42.0",
    "gn:admin2_code":"30026.0",
    "gn:asciiname":"Aro",
    "gn:country_code":"NG",
    "gn:dem":303,
    "gn:feature_class":"P",
    "gn:feature_code":"PPL",
    "gn:name":"Aro",
    "gn:population":0,
    "gn:timezone":"Africa/Lagos",
    "iso:country":"NG",
    "name:ceb_x_preferred":[
        "Aro"
    ],
    "name:epo_x_preferred":[
        "Aro"
    ],
    "name:eus_x_preferred":[
        "Aro"
    ],
    "name:fin_x_preferred":[
        "Aro"
    ],
    "name:fra_x_preferred":[
        "Aro"
    ],
    "name:glg_x_preferred":[
        "Aro"
    ],
    "name:hye_x_preferred":[
        "\u0531\u0580\u0578"
    ],
    "name:ind_x_preferred":[
        "Aro"
    ],
    "name:nld_x_preferred":[
        "Aro"
    ],
    "name:pol_x_preferred":[
        "Aro"
    ],
    "name:por_x_preferred":[
        "Aro"
    ],
    "name:ron_x_preferred":[
        "ARO"
    ],
    "name:rus_x_preferred":[
        "\u0410\u0440\u043e"
    ],
    "name:spa_x_preferred":[
        "Aro"
    ],
    "name:srp_x_preferred":[
        "\u0410\u0440\u043e"
    ],
    "name:swe_x_preferred":[
        "Aro"
    ],
    "name:ukr_x_preferred":[
        "\u0410\u0440\u043e"
    ],
    "wof:name":"Aro",
    "wof:placetype":"locality"
},
  "geometry": {"coordinates":[4.26667,7.75],"type":"Point"}
}