{
  "type": "Feature",
  "properties": {
    "gn:admin1_code":"40.0",
    "gn:admin2_code":"519.0",
    "gn:admin3_code":"51909",
    "gn:asciiname":"Ranko",
    "gn:country_code":"NG",
    "gn:dem":415,
    "gn:feature_class":"P",
    "gn:feature_code":"PPL",
    "gn:name":"Ranko",
    "gn:population":0,
    "gn:timezone":"Africa/Lagos",
    "iso:country":"NG",
    "name:fra_x_preferred":[
        "Ranko"
    ],
    "name:srp_x_preferred":[
        "\u0420\u0430\u043d\u043a\u043e"
    ],
    "wof:name":"Ranko",
    "wof:placetype":"locality"
},
  "geometry": {"coordinates":[5.88505,11.48675],"type":"Point"}
}