{
  "type": "Feature",
  "properties": {
    "gn:admin1_code":"26.0",
    "gn:admin2_code":"7005",
    "gn:asciiname":"Tyokegh",
    "gn:country_code":"NG",
    "gn:dem":198,
    "gn:feature_class":"P",
    "gn:feature_code":"PPL",
    "gn:name":"Tyokegh",
    "gn:population":0,
    "gn:timezone":"Africa/Lagos",
    "iso:country":"NG",
    "wof:name":"Tyokegh",
    "wof:placetype":"locality"
},
  "geometry": {"coordinates":[9.09946,7.37916],"type":"Point"}
}