{
  "type": "Feature",
  "properties": {
    "gn:admin1_code":"23.0",
    "gn:admin2_code":"19008.0",
    "gn:admin3_code":"KD0801",
    "gn:asciiname":"Gidan Gona",
    "gn:country_code":"NG",
    "gn:dem":812,
    "gn:feature_class":"P",
    "gn:feature_code":"PPL",
    "gn:name":"Gidan Gona",
    "gn:population":0,
    "gn:timezone":"Africa/Lagos",
    "iso:country":"NG",
    "wof:name":"Gidan Gona",
    "wof:placetype":"locality"
},
  "geometry": {"coordinates":[7.90025,9.98359],"type":"Point"}
}