{
  "type": "Feature",
  "properties": {
    "gn:admin1_code":"52.0",
    "gn:admin2_code":"6001.0",
    "gn:asciiname":"Shellkiri",
    "gn:country_code":"NG",
    "gn:dem":6,
    "gn:feature_class":"P",
    "gn:feature_code":"PPL",
    "gn:name":"Shellkiri",
    "gn:population":0,
    "gn:timezone":"Africa/Lagos",
    "iso:country":"NG",
    "name:und_x_variant":[
        "Cartonkiri",
        "Shellkiri"
    ],
    "wof:name":"Shellkiri",
    "wof:placetype":"locality"
},
  "geometry": {"coordinates":[6.53153,4.54327],"type":"Point"}
}