{
  "type": "Feature",
  "properties": {
    "gn:admin1_code":"32.0",
    "gn:admin2_code":"31002.0",
    "gn:asciiname":"Babasango",
    "gn:cc2":"NG",
    "gn:country_code":"NG",
    "gn:dem":267,
    "gn:feature_class":"P",
    "gn:feature_code":"PPL",
    "gn:name":"Babasango",
    "gn:population":0,
    "gn:timezone":"Africa/Lagos",
    "iso:country":"NG",
    "name:und_x_variant":[
        "Baba Shango",
        "Babasango"
    ],
    "wof:name":"Babasango",
    "wof:placetype":"neighbourhood"
},
  "geometry": {"coordinates":[3.87778,7.60889],"type":"Point"}
}