{
  "type": "Feature",
  "properties": {
    "gn:admin1_code":"35.0",
    "gn:admin2_code":"2020.0",
    "gn:asciiname":"Bomu",
    "gn:country_code":"NG",
    "gn:dem":166,
    "gn:feature_class":"P",
    "gn:feature_code":"PPL",
    "gn:name":"Bomu",
    "gn:population":0,
    "gn:timezone":"Africa/Lagos",
    "iso:country":"NG",
    "name:und_x_variant":[
        "Wumu",
        "Bomu"
    ],
    "wof:name":"Bomu",
    "wof:placetype":"locality"
},
  "geometry": {"coordinates":[12.32151,9.37463],"type":"Point"}
}