{
  "type": "Feature",
  "properties": {
    "gn:admin1_code":"35.0",
    "gn:admin2_code":"2020.0",
    "gn:asciiname":"Bomu",
    "gn:country_code":"NG",
    "gn:dem":166,
    "gn:feature_class":"P",
    "gn:feature_code":"PPL",
    "gn:name":"Bomu",
    "gn:population":0,
    "gn:timezone":"Africa/Lagos",
    "iso:country":"NG",
    "name:ara_x_preferred":[
        "\u0628\u0648\u0645\u0648"
    ],
    "name:ben_x_preferred":[
        "\u09ac\u09cb\u09ae\u09c1"
    ],
    "name:ceb_x_preferred":[
        "Bomu"
    ],
    "name:ell_x_preferred":[
        "\u039c\u03c0\u03cc\u03bc\u03bf\u03c5"
    ],
    "name:fas_x_preferred":[
        "\u0628\u0648\u0645\u0648"
    ],
    "name:fra_x_preferred":[
        "Bomu"
    ],
    "name:heb_x_preferred":[
        "\u05d1\u05d5\u05de\u05d5"
    ],
    "name:ind_x_preferred":[
        "Bomu"
    ],
    "name:kor_x_preferred":[
        "\ubcf4\ubb34"
    ],
    "name:swe_x_preferred":[
        "Bomu"
    ],
    "name:tur_x_preferred":[
        "Bomu"
    ],
    "name:und_x_variant":[
        "Wumu"
    ],
    "name:urd_x_preferred":[
        "\u0628\u0648\u0645\u0648"
    ],
    "wof:name":"Bomu",
    "wof:placetype":"locality"
},
  "geometry": {"coordinates":[12.32151,9.37463],"type":"Point"}
}