{
  "type": "Feature",
  "properties": {
    "gn:admin1_code":"31.0",
    "gn:admin2_code":"27008",
    "gn:asciiname":"Emiworogi Umaru",
    "gn:country_code":"NG",
    "gn:dem":112,
    "gn:feature_class":"P",
    "gn:feature_code":"PPL",
    "gn:name":"Emiworogi Umaru",
    "gn:population":0,
    "gn:timezone":"Africa/Lagos",
    "iso:country":"NG",
    "wof:name":"Emiworogi Umaru",
    "wof:placetype":"locality"
},
  "geometry": {"coordinates":[6.11426,9.36401],"type":"Point"}
}