{
  "type": "Feature",
  "properties": {
    "gn:admin1_code":"40.0",
    "gn:asciiname":"Seteku",
    "gn:country_code":"NG",
    "gn:dem":139,
    "gn:feature_class":"P",
    "gn:feature_code":"PPL",
    "gn:name":"Seteku",
    "gn:population":0,
    "gn:timezone":"Africa/Lagos",
    "iso:country":"NG",
    "name:und_x_variant":[
        "Suteku",
        "Seteku"
    ],
    "wof:name":"Seteku",
    "wof:placetype":"locality"
},
  "geometry": {"coordinates":[4.67711,10.64421],"type":"Point"}
}