{
  "type": "Feature",
  "properties": {
    "gn:admin1_code":"21.0",
    "gn:admin2_code":"3011.0",
    "gn:asciiname":"Itung",
    "gn:country_code":"NG",
    "gn:dem":74,
    "gn:feature_class":"P",
    "gn:feature_code":"PPL",
    "gn:name":"Itung",
    "gn:population":0,
    "gn:timezone":"Africa/Lagos",
    "iso:country":"NG",
    "wof:name":"Itung",
    "wof:placetype":"locality"
},
  "geometry": {"coordinates":[7.59587,5.04026],"type":"Point"}
}