{
  "type": "Feature",
  "properties": {
    "gn:admin1_code":"35.0",
    "gn:admin2_code":"2013.0",
    "gn:asciiname":"Futu Clan",
    "gn:country_code":"NG",
    "gn:dem":715,
    "gn:feature_class":"P",
    "gn:feature_code":"PPL",
    "gn:name":"Futu Clan",
    "gn:population":0,
    "gn:timezone":"Africa/Lagos",
    "iso:country":"NG",
    "name:und_x_variant":[
        "Futu",
        "Futu Clan"
    ],
    "wof:name":"Futu Clan",
    "wof:placetype":"locality"
},
  "geometry": {"coordinates":[13.45318,10.56758],"type":"Point"}
}