{
  "type": "Feature",
  "properties": {
    "gn:admin1_code":"43.0",
    "gn:admin2_code":"35015",
    "gn:asciiname":"Mazan",
    "gn:country_code":"NG",
    "gn:dem":217,
    "gn:feature_class":"P",
    "gn:feature_code":"PPL",
    "gn:name":"Mazan",
    "gn:population":0,
    "gn:timezone":"Africa/Lagos",
    "iso:country":"NG",
    "name:cat_x_preferred":[
        "Masan"
    ],
    "name:ceb_x_preferred":[
        "Mazan"
    ],
    "name:deu_x_preferred":[
        "Mazan"
    ],
    "name:eus_x_preferred":[
        "Mazan"
    ],
    "name:fra_x_preferred":[
        "Mazan"
    ],
    "name:hun_x_preferred":[
        "Mazan"
    ],
    "name:ita_x_preferred":[
        "Mazan"
    ],
    "name:lat_x_preferred":[
        "Mazan"
    ],
    "name:mlg_x_preferred":[
        "Mazan"
    ],
    "name:msa_x_preferred":[
        "Mazan"
    ],
    "name:nld_x_preferred":[
        "Mazan"
    ],
    "name:oci_x_preferred":[
        "Masan"
    ],
    "name:pol_x_preferred":[
        "Mazan"
    ],
    "name:ron_x_preferred":[
        "Mazan"
    ],
    "name:rus_x_preferred":[
        "\u041c\u0430\u0437\u0430\u043d"
    ],
    "name:slk_x_preferred":[
        "Mazan"
    ],
    "name:spa_x_preferred":[
        "Mazan"
    ],
    "name:swe_x_preferred":[
        "Mazan"
    ],
    "name:ukr_x_preferred":[
        "\u041c\u0430\u0437\u0430\u043d"
    ],
    "name:vie_x_preferred":[
        "Mazan"
    ],
    "name:vol_x_preferred":[
        "Mazan"
    ],
    "name:war_x_preferred":[
        "Mazan"
    ],
    "name:zho_x_preferred":[
        "\u9a6c\u85cf"
    ],
    "wof:name":"Mazan",
    "wof:placetype":"locality"
},
  "geometry": {"coordinates":[11.37736,8.93078],"type":"Point"}
}