{
  "type": "Feature",
  "properties": {
    "gn:admin1_code":"50.0",
    "gn:admin2_code":"33018.0",
    "gn:asciiname":"Peterside",
    "gn:country_code":"NG",
    "gn:dem":7,
    "gn:feature_class":"P",
    "gn:feature_code":"PPL",
    "gn:name":"Peterside",
    "gn:population":0,
    "gn:timezone":"Africa/Lagos",
    "iso:country":"NG",
    "wof:name":"Peterside",
    "wof:placetype":"locality"
},
  "geometry": {"coordinates":[7.16051,4.48226],"type":"Point"}
}