{
  "type": "Feature",
  "properties": {
    "gn:admin1_code":"27.0",
    "gn:admin2_code":"105.0",
    "gn:admin3_code":"10511",
    "gn:asciiname":"Yamarkumi",
    "gn:country_code":"NG",
    "gn:dem":683,
    "gn:feature_class":"P",
    "gn:feature_code":"PPL",
    "gn:name":"Yamarkumi",
    "gn:population":0,
    "gn:timezone":"Africa/Lagos",
    "iso:country":"NG",
    "wof:name":"Yamarkumi",
    "wof:placetype":"locality"
},
  "geometry": {"coordinates":[12.1628,10.65808],"type":"Point"}
}