{
  "type": "Feature",
  "properties": {
    "gn:admin1_code":"37.0",
    "gn:admin2_code":"12003",
    "gn:asciiname":"Ubierumu-Nowa",
    "gn:country_code":"NG",
    "gn:dem":409,
    "gn:feature_class":"P",
    "gn:feature_code":"PPL",
    "gn:name":"Ubierumu-Nowa",
    "gn:population":0,
    "gn:timezone":"Africa/Lagos",
    "iso:country":"NG",
    "wof:name":"Ubierumu-Nowa",
    "wof:placetype":"neighbourhood"
},
  "geometry": {"coordinates":[6.30026,6.71062],"type":"Point"}
}