{
  "type": "Feature",
  "properties": {
    "gn:admin1_code":"23.0",
    "gn:admin2_code":"19003.0",
    "gn:admin3_code":"KD0305",
    "gn:asciiname":"Kutemeshi",
    "gn:country_code":"NG",
    "gn:dem":668,
    "gn:feature_class":"P",
    "gn:feature_code":"PPL",
    "gn:name":"Kutemeshi",
    "gn:population":0,
    "gn:timezone":"Africa/Lagos",
    "iso:country":"NG",
    "wof:name":"Kutemeshi",
    "wof:placetype":"locality"
},
  "geometry": {"coordinates":[7.03306,11.17207],"type":"Point"}
}