{
  "type": "Feature",
  "properties": {
    "gn:admin1_code":"30.0",
    "gn:admin2_code":"24003.0",
    "gn:asciiname":"Kusomono",
    "gn:country_code":"NG",
    "gn:dem":235,
    "gn:feature_class":"P",
    "gn:feature_code":"PPL",
    "gn:name":"Kusomono",
    "gn:population":0,
    "gn:timezone":"Africa/Lagos",
    "iso:country":"NG",
    "wof:name":"Kusomono",
    "wof:placetype":"locality"
},
  "geometry": {"coordinates":[5.03333,8.91667],"type":"Point"}
}