{
  "type": "Feature",
  "properties": {
    "gn:admin1_code":"24.0",
    "gn:admin2_code":"417.0",
    "gn:admin3_code":"41706",
    "gn:asciiname":"Kufantanbu",
    "gn:country_code":"NG",
    "gn:dem":627,
    "gn:feature_class":"P",
    "gn:feature_code":"PPL",
    "gn:name":"Kufantanbu",
    "gn:population":0,
    "gn:timezone":"Africa/Lagos",
    "iso:country":"NG",
    "wof:name":"Kufantanbu",
    "wof:placetype":"locality"
},
  "geometry": {"coordinates":[7.58333,11.69005],"type":"Point"}
}