{
  "type": "Feature",
  "properties": {
    "gn:admin1_code":"31.0",
    "gn:admin2_code":"27020",
    "gn:asciiname":"Old Yakila",
    "gn:country_code":"NG",
    "gn:dem":204,
    "gn:feature_class":"P",
    "gn:feature_code":"PPL",
    "gn:name":"Old Yakila",
    "gn:population":0,
    "gn:timezone":"Africa/Lagos",
    "iso:country":"NG",
    "wof:name":"Old Yakila",
    "wof:placetype":"locality"
},
  "geometry": {"coordinates":[6.15015,9.9418],"type":"Point"}
}