{
  "type": "Feature",
  "properties": {
    "gn:admin1_code":"30.0",
    "gn:admin2_code":"24005.0",
    "gn:asciiname":"Araromi",
    "gn:country_code":"NG",
    "gn:dem":353,
    "gn:feature_class":"P",
    "gn:feature_code":"PPL",
    "gn:name":"Araromi",
    "gn:population":0,
    "gn:timezone":"Africa/Lagos",
    "iso:country":"NG",
    "wof:name":"Araromi",
    "wof:placetype":"locality"
},
  "geometry": {"coordinates":[4.96667,8.43333],"type":"Point"}
}