{
  "type": "Feature",
  "properties": {
    "gn:admin1_code":"31.0",
    "gn:admin2_code":"27006",
    "gn:asciiname":"Anguwamadake",
    "gn:country_code":"NG",
    "gn:dem":225,
    "gn:feature_class":"P",
    "gn:feature_code":"PPL",
    "gn:name":"Anguwamadake",
    "gn:population":0,
    "gn:timezone":"Africa/Lagos",
    "iso:country":"NG",
    "wof:name":"Anguwamadake",
    "wof:placetype":"neighbourhood"
},
  "geometry": {"coordinates":[6.50539,9.59679],"type":"Point"}
}