{
  "type": "Feature",
  "properties": {
    "gn:admin1_code":"23.0",
    "gn:asciiname":"Tagwaye",
    "gn:country_code":"NG",
    "gn:dem":748,
    "gn:feature_class":"P",
    "gn:feature_code":"PPL",
    "gn:name":"Tagwaye",
    "gn:population":0,
    "gn:timezone":"Africa/Lagos",
    "iso:country":"NG",
    "wof:name":"Tagwaye",
    "wof:placetype":"locality"
},
  "geometry": {"coordinates":[8.59818,10.78061],"type":"Point"}
}