{
  "type": "Feature",
  "properties": {
    "gn:admin1_code":"54.0",
    "gn:admin2_code":"13011.0",
    "gn:asciiname":"Ire-Ekiti",
    "gn:country_code":"NG",
    "gn:dem":545,
    "gn:feature_class":"P",
    "gn:feature_code":"PPL",
    "gn:name":"Ire-Ekiti",
    "gn:population":0,
    "gn:timezone":"Africa/Lagos",
    "iso:country":"NG",
    "name:und_x_variant":[
        "Ire",
        "Ire-Ekiti"
    ],
    "wof:name":"Ire-Ekiti",
    "wof:placetype":"locality"
},
  "geometry": {"coordinates":[5.3966,7.73885],"type":"Point"}
}