{
  "type": "Feature",
  "properties": {
    "gn:admin1_code":"50.0",
    "gn:admin2_code":"33015.0",
    "gn:asciiname":"Rumuoqonoma",
    "gn:country_code":"NG",
    "gn:dem":22,
    "gn:feature_class":"P",
    "gn:feature_code":"PPL",
    "gn:name":"Rumuoqonoma",
    "gn:population":0,
    "gn:timezone":"Africa/Lagos",
    "iso:country":"NG",
    "name:und_x_variant":[
        "Umuoqonnama",
        "Umuoqonoma",
        "Rumuoqonoma"
    ],
    "wof:name":"Rumuoqonoma",
    "wof:placetype":"locality"
},
  "geometry": {"coordinates":[7.03813,4.89577],"type":"Point"}
}