{
  "type": "Feature",
  "properties": {
    "gn:admin1_code":"56.0",
    "gn:admin2_code":"26004",
    "gn:asciiname":"Zanzara",
    "gn:country_code":"NG",
    "gn:dem":444,
    "gn:feature_class":"P",
    "gn:feature_code":"PPL",
    "gn:name":"Zanzara",
    "gn:population":0,
    "gn:timezone":"Africa/Lagos",
    "iso:country":"NG",
    "wof:name":"Zanzara",
    "wof:placetype":"locality"
},
  "geometry": {"coordinates":[7.93056,9.2625],"type":"Point"}
}