{
  "type": "Feature",
  "properties": {
    "gn:admin1_code":"35.0",
    "gn:admin2_code":"2002.0",
    "gn:asciiname":"Wuro Jubawo",
    "gn:cc2":"NG",
    "gn:country_code":"NG",
    "gn:dem":222,
    "gn:feature_class":"P",
    "gn:feature_code":"PPL",
    "gn:name":"Wuro Jubawo",
    "gn:population":0,
    "gn:timezone":"Africa/Lagos",
    "iso:country":"NG",
    "name:und_x_variant":[
        "Dutsin Jubawo",
        "Jubawo",
        "Wuro Jubawo"
    ],
    "wof:name":"Wuro Jubawo",
    "wof:placetype":"locality"
},
  "geometry": {"coordinates":[12.65,9.35],"type":"Point"}
}