{
  "type": "Feature",
  "properties": {
    "gn:admin1_code":"35.0",
    "gn:admin2_code":"2007.0",
    "gn:asciiname":"Dilvwa",
    "gn:country_code":"NG",
    "gn:dem":568,
    "gn:feature_class":"P",
    "gn:feature_code":"PPL",
    "gn:name":"Dilvwa",
    "gn:population":0,
    "gn:timezone":"Africa/Lagos",
    "iso:country":"NG",
    "wof:name":"Dilvwa",
    "wof:placetype":"locality"
},
  "geometry": {"coordinates":[12.92858,10.16143],"type":"Point"}
}