{
  "type": "Feature",
  "properties": {
    "gn:admin1_code":"36.0",
    "gn:admin2_code":"10019.0",
    "gn:asciiname":"Ovhororo",
    "gn:country_code":"NG",
    "gn:dem":14,
    "gn:feature_class":"P",
    "gn:feature_code":"PPL",
    "gn:name":"Ovhororo",
    "gn:population":0,
    "gn:timezone":"Africa/Lagos",
    "iso:country":"NG",
    "wof:name":"Ovhororo",
    "wof:placetype":"locality"
},
  "geometry": {"coordinates":[6.05208,5.29487],"type":"Point"}
}