{
  "type": "Feature",
  "properties": {
    "gn:admin1_code":"24.0",
    "gn:admin2_code":"423.0",
    "gn:admin3_code":"42308",
    "gn:asciiname":"Mawashi",
    "gn:country_code":"NG",
    "gn:dem":522,
    "gn:feature_class":"P",
    "gn:feature_code":"PPL",
    "gn:name":"Mawashi",
    "gn:population":0,
    "gn:timezone":"Africa/Lagos",
    "iso:country":"NG",
    "name:bul_x_preferred":[
        "\u041c\u0430\u0432\u0430\u0448\u0438"
    ],
    "name:cat_x_preferred":[
        "Mawashi"
    ],
    "name:deu_x_preferred":[
        "Mawashi"
    ],
    "name:fra_x_preferred":[
        "Mawashi"
    ],
    "name:heb_x_preferred":[
        "\u05de\u05d0\u05d5\u05d5\u05d0\u05e9\u05d9"
    ],
    "name:ita_x_preferred":[
        "Mawashi"
    ],
    "name:por_x_preferred":[
        "Mawashi"
    ],
    "name:spa_x_preferred":[
        "Mawashi"
    ],
    "wof:name":"Mawashi",
    "wof:placetype":"locality"
},
  "geometry": {"coordinates":[8.04717,12.5184],"type":"Point"}
}