{
  "type": "Feature",
  "properties": {
    "gn:admin1_code":"36.0",
    "gn:asciiname":"Uba-Tailor",
    "gn:country_code":"NG",
    "gn:dem":9,
    "gn:feature_class":"P",
    "gn:feature_code":"PPL",
    "gn:name":"Uba-Tailor",
    "gn:population":0,
    "gn:timezone":"Africa/Lagos",
    "iso:country":"NG",
    "name:eng_x_preferred":[
        "Uba-Tailor"
    ],
    "wof:name":"Uba-Tailor",
    "wof:placetype":"locality"
},
  "geometry": {"coordinates":[5.48585,5.97815],"type":"Point"}
}