{
  "type": "Feature",
  "properties": {
    "gn:admin1_code":"31.0",
    "gn:admin2_code":"27015.0",
    "gn:asciiname":"Gidan Obiza",
    "gn:country_code":"NG",
    "gn:dem":267,
    "gn:feature_class":"P",
    "gn:feature_code":"PPL",
    "gn:name":"Gidan Obiza",
    "gn:population":0,
    "gn:timezone":"Africa/Lagos",
    "iso:country":"NG",
    "wof:name":"Gidan Obiza",
    "wof:placetype":"locality"
},
  "geometry": {"coordinates":[6.01023,10.40801],"type":"Point"}
}