{
  "type": "Feature",
  "properties": {
    "gn:admin1_code":"26.0",
    "gn:admin2_code":"7010.0",
    "gn:asciiname":"Toho",
    "gn:country_code":"NG",
    "gn:dem":184,
    "gn:feature_class":"P",
    "gn:feature_code":"PPL",
    "gn:name":"Toho",
    "gn:population":0,
    "gn:timezone":"Africa/Lagos",
    "iso:country":"NG",
    "name:ara_x_preferred":[
        "\u062a\u0648\u0647\u0648"
    ],
    "name:azb_x_preferred":[
        "\u062a\u0648\u0647\u0648"
    ],
    "name:ben_x_preferred":[
        "\u09a4\u09cb\u09b9\u09cb"
    ],
    "name:bul_x_preferred":[
        "\u0422\u043e\u0445\u043e"
    ],
    "name:cat_x_preferred":[
        "T\u014dh\u014d"
    ],
    "name:deu_x_preferred":[
        "T\u014dh\u014d"
    ],
    "name:fas_x_preferred":[
        "\u062a\u0648\u0647\u0648"
    ],
    "name:fin_x_preferred":[
        "T\u014dh\u014d"
    ],
    "name:fra_x_preferred":[
        "T\u014dh\u014d"
    ],
    "name:glg_x_preferred":[
        "Toho"
    ],
    "name:heb_x_preferred":[
        "\u05d8\u05d5\u05d4\u05d5"
    ],
    "name:ind_x_preferred":[
        "Toho"
    ],
    "name:ita_x_preferred":[
        "Toho"
    ],
    "name:lav_x_preferred":[
        "Toho"
    ],
    "name:lit_x_preferred":[
        "Toho"
    ],
    "name:msa_x_preferred":[
        "Toho"
    ],
    "name:nld_x_preferred":[
        "Toho"
    ],
    "name:nor_x_preferred":[
        "Toho"
    ],
    "name:pol_x_preferred":[
        "T\u014dh\u014d"
    ],
    "name:por_x_preferred":[
        "T\u014dh\u014d"
    ],
    "name:rus_x_preferred":[
        "Toho"
    ],
    "name:spa_x_preferred":[
        "T\u014dh\u014d"
    ],
    "name:swe_x_preferred":[
        "T\u014dh\u014d"
    ],
    "name:tgl_x_preferred":[
        "Toho"
    ],
    "name:tur_x_preferred":[
        "Toho"
    ],
    "name:ukr_x_preferred":[
        "Toho"
    ],
    "name:vie_x_preferred":[
        "Toho"
    ],
    "wof:name":"Toho",
    "wof:placetype":"locality"
},
  "geometry": {"coordinates":[8.58263,7.35376],"type":"Point"}
}