{
  "type": "Feature",
  "properties": {
    "gn:admin1_code":"29.0",
    "gn:admin2_code":"20021.0",
    "gn:admin3_code":"KN1006",
    "gn:asciiname":"Kunnawa",
    "gn:country_code":"NG",
    "gn:dem":508,
    "gn:feature_class":"P",
    "gn:feature_code":"PPL",
    "gn:name":"Kunnawa",
    "gn:population":0,
    "gn:timezone":"Africa/Lagos",
    "iso:country":"NG",
    "wof:name":"Kunnawa",
    "wof:placetype":"locality"
},
  "geometry": {"coordinates":[8.35131,12.16758],"type":"Point"}
}