{
  "type": "Feature",
  "properties": {
    "gn:admin1_code":"24.0",
    "gn:admin2_code":"417.0",
    "gn:admin3_code":"41703",
    "gn:asciiname":"Ungwan Dutsi",
    "gn:country_code":"NG",
    "gn:dem":584,
    "gn:feature_class":"P",
    "gn:feature_code":"PPL",
    "gn:name":"Ungwan Dutsi",
    "gn:population":0,
    "gn:timezone":"Africa/Lagos",
    "iso:country":"NG",
    "wof:name":"Ungwan Dutsi",
    "wof:placetype":"locality"
},
  "geometry": {"coordinates":[7.81258,11.8193],"type":"Point"}
}