{
  "type": "Feature",
  "properties": {
    "gn:admin1_code":"26.0",
    "gn:admin2_code":"7021",
    "gn:asciiname":"Anza",
    "gn:country_code":"NG",
    "gn:dem":194,
    "gn:feature_class":"P",
    "gn:feature_code":"PPL",
    "gn:name":"Anza",
    "gn:population":0,
    "gn:timezone":"Africa/Lagos",
    "iso:country":"NG",
    "name:ara_x_preferred":[
        "\u0639\u0646\u0632\u0629"
    ],
    "name:ceb_x_preferred":[
        "Anza"
    ],
    "name:deu_x_preferred":[
        "Anza"
    ],
    "name:hrv_x_preferred":[
        "Anza"
    ],
    "name:ita_x_preferred":[
        "Anza"
    ],
    "name:nld_x_preferred":[
        "Anza"
    ],
    "name:pol_x_preferred":[
        "Anza"
    ],
    "name:rus_x_preferred":[
        "\u0410\u043d\u0437\u0430"
    ],
    "name:swe_x_preferred":[
        "Anza"
    ],
    "wof:name":"Anza",
    "wof:placetype":"locality"
},
  "geometry": {"coordinates":[9.66746,7.6022],"type":"Point"}
}