{
  "type": "Feature",
  "properties": {
    "gn:country":"NG",
    "gn:fcode":"PPL",
    "gn:pop":89990,
    "iso:country":"NG",
    "name:bul_x_preferred":[
        "\u0418\u0441\u0438\u0435\u043a\u0435"
    ],
    "name:dut_x_preferred":[
        "Isieke"
    ],
    "name:eng_x_preferred":[
        "Isieke"
    ],
    "qs:name":"Isieke",
    "qs:photos_9r":0,
    "qs:photos_sr":0,
    "qs:pop_sr":"8",
    "wd:wordcount":39,
    "wof:name":"Isieke",
    "wof:placetype":"locality",
    "wof:population":89990
},
  "geometry": {"coordinates":[8.03524,6.37831],"type":"Point"}
}