{
  "type": "Feature",
  "properties": {
    "gn:admin1_code":"26.0",
    "gn:admin2_code":"7010",
    "gn:asciiname":"Andura",
    "gn:country_code":"NG",
    "gn:dem":148,
    "gn:feature_class":"P",
    "gn:feature_code":"PPL",
    "gn:name":"Andura",
    "gn:population":0,
    "gn:timezone":"Africa/Lagos",
    "iso:country":"NG",
    "name:spa_x_preferred":[
        "Andura"
    ],
    "name:vie_x_preferred":[
        "Andura"
    ],
    "wof:name":"Andura",
    "wof:placetype":"locality"
},
  "geometry": {"coordinates":[8.46158,7.0346],"type":"Point"}
}