{
  "type": "Feature",
  "properties": {
    "gn:admin1_code":"32.0",
    "gn:admin2_code":"31012.0",
    "gn:asciiname":"Ilado",
    "gn:country_code":"NG",
    "gn:dem":188,
    "gn:feature_class":"P",
    "gn:feature_code":"PPL",
    "gn:name":"Ilado",
    "gn:population":0,
    "gn:timezone":"Africa/Lagos",
    "iso:country":"NG",
    "wof:name":"Ilado",
    "wof:placetype":"locality"
},
  "geometry": {"coordinates":[3.51667,7.56667],"type":"Point"}
}