{
  "type": "Feature",
  "properties": {
    "gn:admin1_code":"52.0",
    "gn:admin2_code":"6007.0",
    "gn:asciiname":"Ekinigbene",
    "gn:country_code":"NG",
    "gn:dem":5,
    "gn:feature_class":"P",
    "gn:feature_code":"PPL",
    "gn:name":"Ekinigbene",
    "gn:population":0,
    "gn:timezone":"Africa/Lagos",
    "iso:country":"NG",
    "name:eng_x_preferred":[
        "Ekinigbene"
    ],
    "wof:name":"Ekinigbene",
    "wof:placetype":"locality"
},
  "geometry": {"coordinates":[5.68253,4.6825],"type":"Point"}
}