{
  "type": "Feature",
  "properties": {
    "gn:admin1_code":"35.0",
    "gn:asciiname":"Balayafi",
    "gn:country_code":"NG",
    "gn:dem":155,
    "gn:feature_class":"P",
    "gn:feature_code":"PPL",
    "gn:name":"Balayafi",
    "gn:population":0,
    "gn:timezone":"Africa/Lagos",
    "iso:country":"NG",
    "name:eng_x_preferred":[
        "Balayafi"
    ],
    "wof:name":"Balayafi",
    "wof:placetype":"locality"
},
  "geometry": {"coordinates":[11.52475,9.48243],"type":"Point"}
}