{
  "type": "Feature",
  "properties": {
    "gn:admin1_code":"51.0",
    "gn:admin2_code":"603.0",
    "gn:admin3_code":"60303",
    "gn:asciiname":"Illela",
    "gn:country_code":"NG",
    "gn:dem":315,
    "gn:feature_class":"P",
    "gn:feature_code":"PPL",
    "gn:name":"Illela",
    "gn:population":0,
    "gn:timezone":"Africa/Lagos",
    "iso:country":"NG",
    "name:fra_x_preferred":[
        "Ill\u00e9la"
    ],
    "name:ita_x_preferred":[
        "Ill\u00e9la"
    ],
    "name:und_x_variant":[
        "Illela Fajelu",
        "Illela"
    ],
    "wof:name":"Illela",
    "wof:placetype":"locality"
},
  "geometry": {"coordinates":[5.3718,12.82094],"type":"Point"}
}