{
  "type": "Feature",
  "properties": {
    "gn:admin1_code":"36.0",
    "gn:admin2_code":"10004.0",
    "gn:asciiname":"Alumagbene",
    "gn:country_code":"NG",
    "gn:dem":4,
    "gn:feature_class":"P",
    "gn:feature_code":"PPL",
    "gn:name":"Alumagbene",
    "gn:population":0,
    "gn:timezone":"Africa/Lagos",
    "iso:country":"NG",
    "wof:name":"Alumagbene",
    "wof:placetype":"locality"
},
  "geometry": {"coordinates":[5.52801,5.31794],"type":"Point"}
}