{
  "type": "Feature",
  "properties": {
    "gn:admin1_code":"25.0",
    "gn:admin2_code":"4016.0",
    "gn:asciiname":"Iyiowa Odek",
    "gn:country_code":"NG",
    "gn:dem":24,
    "gn:feature_class":"P",
    "gn:feature_code":"PPL",
    "gn:name":"Iyiowa Odek",
    "gn:population":0,
    "gn:timezone":"Africa/Lagos",
    "iso:country":"NG",
    "name:eng_x_preferred":[
        "Iyiowa-Odekpa"
    ],
    "name:eng_x_variant":[
        "Oyiowa Odekpa"
    ],
    "wof:name":"Iyiowa Odek",
    "wof:placetype":"locality"
},
  "geometry": {"coordinates":[6.75716,6.09179],"type":"Point"}
}