{
  "type": "Feature",
  "properties": {
    "gn:admin1_code":"48.0",
    "gn:admin2_code":"29006.0",
    "gn:asciiname":"Ajegunle-Opa",
    "gn:country_code":"NG",
    "gn:dem":324,
    "gn:feature_class":"P",
    "gn:feature_code":"PPL",
    "gn:name":"Ajegunle-Opa",
    "gn:population":0,
    "gn:timezone":"Africa/Lagos",
    "iso:country":"NG",
    "wof:name":"Ajegunle-Opa",
    "wof:placetype":"locality"
},
  "geometry": {"coordinates":[5.1073,7.2311],"type":"Point"}
}