{
  "type": "Feature",
  "properties": {
    "gn:admin1_code":"44.0",
    "gn:admin2_code":"704",
    "gn:admin3_code":"70403",
    "gn:asciiname":"Sabolayi",
    "gn:country_code":"NG",
    "gn:dem":400,
    "gn:feature_class":"P",
    "gn:feature_code":"PPL",
    "gn:name":"Sabolayi",
    "gn:population":0,
    "gn:timezone":"Africa/Lagos",
    "iso:country":"NG",
    "wof:name":"Sabolayi",
    "wof:placetype":"locality"
},
  "geometry": {"coordinates":[11.24361,11.32795],"type":"Point"}
}