{
  "type": "Feature",
  "properties": {
    "gn:admin1_code":"48.0",
    "gn:admin2_code":"29008.0",
    "gn:asciiname":"Legbira",
    "gn:country_code":"NG",
    "gn:dem":239,
    "gn:feature_class":"P",
    "gn:feature_code":"PPL",
    "gn:name":"Legbira",
    "gn:population":0,
    "gn:timezone":"Africa/Lagos",
    "iso:country":"NG",
    "name:und_x_variant":[
        "Opa",
        "Legbira"
    ],
    "wof:name":"Legbira",
    "wof:placetype":"locality"
},
  "geometry": {"coordinates":[5.17101,7.02981],"type":"Point"}
}