{
  "type": "Feature",
  "properties": {
    "gn:admin1_code":"29.0",
    "gn:asciiname":"Ungwan Giwa",
    "gn:country_code":"NG",
    "gn:dem":672,
    "gn:feature_class":"P",
    "gn:feature_code":"PPL",
    "gn:name":"Ungwan Giwa",
    "gn:population":0,
    "gn:timezone":"Africa/Lagos",
    "iso:country":"NG",
    "name:und_x_variant":[
        "Giwa",
        "Ungwan Giwa"
    ],
    "wof:name":"Ungwan Giwa",
    "wof:placetype":"locality"
},
  "geometry": {"coordinates":[7.8144,11.34691],"type":"Point"}
}