{
  "type": "Feature",
  "properties": {
    "gn:admin1_code":"37.0",
    "gn:admin2_code":"12012.0",
    "gn:asciiname":"Utonbubu",
    "gn:country_code":"NG",
    "gn:dem":22,
    "gn:feature_class":"P",
    "gn:feature_code":"PPL",
    "gn:name":"Utonbubu",
    "gn:population":0,
    "gn:timezone":"Africa/Lagos",
    "iso:country":"NG",
    "wof:name":"Utonbubu",
    "wof:placetype":"locality"
},
  "geometry": {"coordinates":[5.51182,6.11505],"type":"Point"}
}