{
  "type": "Feature",
  "properties": {
    "gn:admin1_code":"32.0",
    "gn:admin2_code":"31002.0",
    "gn:asciiname":"Oke",
    "gn:country_code":"NG",
    "gn:dem":253,
    "gn:feature_class":"P",
    "gn:feature_code":"PPL",
    "gn:name":"Oke",
    "gn:population":0,
    "gn:timezone":"Africa/Lagos",
    "iso:country":"NG",
    "name:ceb_x_preferred":[
        "Oke"
    ],
    "name:deu_x_preferred":[
        "Oke"
    ],
    "name:swe_x_preferred":[
        "Oke"
    ],
    "wof:name":"Oke",
    "wof:placetype":"neighbourhood"
},
  "geometry": {"coordinates":[3.96833,7.53889],"type":"Point"}
}