{
  "type": "Feature",
  "properties": {
    "gn:admin1_code":"53.0",
    "gn:admin2_code":"11007",
    "gn:asciiname":"Ndiagu",
    "gn:country_code":"NG",
    "gn:dem":33,
    "gn:feature_class":"P",
    "gn:feature_code":"PPL",
    "gn:name":"Ndiagu",
    "gn:population":0,
    "gn:timezone":"Africa/Lagos",
    "iso:country":"NG",
    "wof:name":"Ndiagu",
    "wof:placetype":"locality"
},
  "geometry": {"coordinates":[8.27512,6.09611],"type":"Point"}
}