{
  "type": "Feature",
  "properties": {
    "gn:admin1_code":"21.0",
    "gn:admin2_code":"3005.0",
    "gn:asciiname":"Obo-Ukana Iba",
    "gn:country_code":"NG",
    "gn:dem":83,
    "gn:feature_class":"P",
    "gn:feature_code":"PPL",
    "gn:name":"Obo-Ukana Iba",
    "gn:population":0,
    "gn:timezone":"Africa/Lagos",
    "iso:country":"NG",
    "wof:name":"Obo-Ukana Iba",
    "wof:placetype":"locality"
},
  "geometry": {"coordinates":[7.70951,5.08667],"type":"Point"}
}