{
  "type": "Feature",
  "properties": {
    "gn:admin1_code":"36.0",
    "gn:admin2_code":"10025.0",
    "gn:asciiname":"Disiwe",
    "gn:country_code":"NG",
    "gn:dem":9,
    "gn:feature_class":"P",
    "gn:feature_code":"PPL",
    "gn:name":"Disiwe",
    "gn:population":0,
    "gn:timezone":"Africa/Lagos",
    "iso:country":"NG",
    "name:eng_x_preferred":[
        "Disiwe"
    ],
    "wof:name":"Disiwe",
    "wof:placetype":"locality"
},
  "geometry": {"coordinates":[5.41205,5.42828],"type":"Point"}
}