{
  "type": "Feature",
  "properties": {
    "gn:admin1_code":"27.0",
    "gn:admin2_code":"116.0",
    "gn:admin3_code":"11609",
    "gn:asciiname":"Yaleri Kurnawa",
    "gn:country_code":"NG",
    "gn:dem":329,
    "gn:feature_class":"P",
    "gn:feature_code":"PPL",
    "gn:name":"Yaleri Kurnawa",
    "gn:population":0,
    "gn:timezone":"Africa/Lagos",
    "iso:country":"NG",
    "wof:name":"Yaleri Kurnawa",
    "wof:placetype":"locality"
},
  "geometry": {"coordinates":[13.3925,11.66885],"type":"Point"}
}