{
  "type": "Feature",
  "properties": {
    "gn:admin1_code":"40.0",
    "gn:admin2_code":"509.0",
    "gn:admin3_code":"50908",
    "gn:asciiname":"Gidan-Gabsa",
    "gn:country_code":"NG",
    "gn:dem":261,
    "gn:feature_class":"P",
    "gn:feature_code":"PPL",
    "gn:name":"Gidan-Gabsa",
    "gn:population":0,
    "gn:timezone":"Africa/Lagos",
    "iso:country":"NG",
    "wof:name":"Gidan-Gabsa",
    "wof:placetype":"locality"
},
  "geometry": {"coordinates":[4.94326,11.54367],"type":"Point"}
}