{
  "type": "Feature",
  "properties": {
    "gn:admin1_code":"5.0",
    "gn:asciiname":"Ladeba",
    "gn:country_code":"NG",
    "gn:dem":3,
    "gn:feature_class":"P",
    "gn:feature_code":"PPL",
    "gn:name":"Ladeba",
    "gn:population":0,
    "gn:timezone":"Africa/Lagos",
    "iso:country":"NG",
    "name:und_x_variant":[
        "Labada",
        "Labada Ebute",
        "Ladeba",
        "Ladaba Oke",
        "Ledaba"
    ],
    "wof:name":"Ladeba",
    "wof:placetype":"locality"
},
  "geometry": {"coordinates":[3.71386,6.52659],"type":"Point"}
}