{
  "type": "Feature",
  "properties": {
    "gn:admin1_code":"31.0",
    "gn:admin2_code":"27022",
    "gn:asciiname":"Tawali",
    "gn:country_code":"NG",
    "gn:dem":327,
    "gn:feature_class":"P",
    "gn:feature_code":"PPL",
    "gn:name":"Tawali",
    "gn:population":0,
    "gn:timezone":"Africa/Lagos",
    "iso:country":"NG",
    "wof:name":"Tawali",
    "wof:placetype":"locality"
},
  "geometry": {"coordinates":[6.72642,9.85417],"type":"Point"}
}