{
  "type": "Feature",
  "properties": {
    "gn:admin1_code":"51.0",
    "gn:admin2_code":"615.0",
    "gn:admin3_code":"61507",
    "gn:asciiname":"Gudam",
    "gn:country_code":"NG",
    "gn:dem":236,
    "gn:feature_class":"P",
    "gn:feature_code":"PPL",
    "gn:name":"Gudam",
    "gn:population":0,
    "gn:timezone":"Africa/Lagos",
    "iso:country":"NG",
    "name:und_x_variant":[
        "Gudambe",
        "Gudam"
    ],
    "wof:name":"Gudam",
    "wof:placetype":"locality"
},
  "geometry": {"coordinates":[4.77378,12.92061],"type":"Point"}
}