{
  "type": "Feature",
  "properties": {
    "gn:admin1_code":"40.0",
    "gn:admin2_code":"513.0",
    "gn:admin3_code":"51307",
    "gn:asciiname":"Tunga Kane",
    "gn:country_code":"NG",
    "gn:dem":152,
    "gn:feature_class":"P",
    "gn:feature_code":"PPL",
    "gn:name":"Tunga Kane",
    "gn:population":0,
    "gn:timezone":"Africa/Lagos",
    "iso:country":"NG",
    "wof:name":"Tunga Kane",
    "wof:placetype":"locality"
},
  "geometry": {"coordinates":[4.38876,11.27843],"type":"Point"}
}