{
  "type": "Feature",
  "properties": {
    "gn:admin1_code":"32.0",
    "gn:admin2_code":"31002.0",
    "gn:asciiname":"Arinago",
    "gn:country_code":"NG",
    "gn:dem":227,
    "gn:feature_class":"P",
    "gn:feature_code":"PPL",
    "gn:name":"Arinago",
    "gn:population":0,
    "gn:timezone":"Africa/Lagos",
    "iso:country":"NG",
    "wof:name":"Arinago",
    "wof:placetype":"neighbourhood"
},
  "geometry": {"coordinates":[3.93611,7.50611],"type":"Point"}
}