{
  "type": "Feature",
  "properties": {
    "gn:admin1_code":"31.0",
    "gn:admin2_code":"27013",
    "gn:asciiname":"Mawoji",
    "gn:country_code":"NG",
    "gn:dem":128,
    "gn:feature_class":"P",
    "gn:feature_code":"PPL",
    "gn:name":"Mawoji",
    "gn:population":0,
    "gn:timezone":"Africa/Lagos",
    "iso:country":"NG",
    "wof:name":"Mawoji",
    "wof:placetype":"locality"
},
  "geometry": {"coordinates":[5.85364,9.46894],"type":"Point"}
}