{
  "type": "Feature",
  "properties": {
    "gn:admin1_code":"56.0",
    "gn:admin2_code":"26011.0",
    "gn:asciiname":"Agudu",
    "gn:country_code":"NG",
    "gn:dem":228,
    "gn:feature_class":"P",
    "gn:feature_code":"PPL",
    "gn:name":"Agudu",
    "gn:population":0,
    "gn:timezone":"Africa/Lagos",
    "iso:country":"NG",
    "wof:name":"Agudu",
    "wof:placetype":"locality"
},
  "geometry": {"coordinates":[8.63333,8.46667],"type":"Point"}
}