{
  "type": "Feature",
  "properties": {
    "gn:admin1_code":"29.0",
    "gn:admin2_code":"20038.0",
    "gn:admin3_code":"KN0303",
    "gn:asciiname":"Jobin Gadanya",
    "gn:country_code":"NG",
    "gn:dem":561,
    "gn:feature_class":"P",
    "gn:feature_code":"PPL",
    "gn:name":"Jobin Gadanya",
    "gn:population":0,
    "gn:timezone":"Africa/Lagos",
    "iso:country":"NG",
    "wof:name":"Jobin Gadanya",
    "wof:placetype":"locality"
},
  "geometry": {"coordinates":[8.05333,12.07872],"type":"Point"}
}