{
  "type": "Feature",
  "properties": {
    "gn:admin1_code":"27.0",
    "gn:admin2_code":"125.0",
    "gn:admin3_code":"12501",
    "gn:asciiname":"Wulgo",
    "gn:country_code":"NG",
    "gn:dem":291,
    "gn:feature_class":"P",
    "gn:feature_code":"PPL",
    "gn:name":"Wulgo",
    "gn:population":0,
    "gn:timezone":"Africa/Lagos",
    "iso:country":"NG",
    "name:und_x_variant":[
        "Wulgo Momaduri",
        "Wulgo",
        "Wulgo Momaduru"
    ],
    "wof:name":"Wulgo",
    "wof:placetype":"locality"
},
  "geometry": {"coordinates":[14.18126,12.48398],"type":"Point"}
}