{
  "type": "Feature",
  "properties": {
    "gn:admin1_code":"45.0",
    "gn:admin2_code":"1004.0",
    "gn:asciiname":"Amabanta",
    "gn:country_code":"NG",
    "gn:dem":108,
    "gn:feature_class":"P",
    "gn:feature_code":"PPL",
    "gn:name":"Amabanta",
    "gn:population":0,
    "gn:timezone":"Africa/Lagos",
    "iso:country":"NG",
    "wof:name":"Amabanta",
    "wof:placetype":"locality"
},
  "geometry": {"coordinates":[7.60489,5.73486],"type":"Point"}
}