{
  "type": "Feature",
  "properties": {
    "gn:admin1_code":"53.0",
    "gn:admin2_code":"11007",
    "gn:asciiname":"Agalagu-Amagu",
    "gn:country_code":"NG",
    "gn:dem":41,
    "gn:feature_class":"P",
    "gn:feature_code":"PPL",
    "gn:name":"Agalagu-Amagu",
    "gn:population":0,
    "gn:timezone":"Africa/Lagos",
    "iso:country":"NG",
    "wof:name":"Agalagu-Amagu",
    "wof:placetype":"locality"
},
  "geometry": {"coordinates":[8.14449,6.02544],"type":"Point"}
}