{
  "type": "Feature",
  "properties": {
    "gn:admin1_code":"35.0",
    "gn:admin2_code":"2013",
    "gn:asciiname":"Kiriya",
    "gn:country_code":"NG",
    "gn:dem":560,
    "gn:feature_class":"P",
    "gn:feature_code":"PPL",
    "gn:name":"Kiriya",
    "gn:population":0,
    "gn:timezone":"Africa/Lagos",
    "iso:country":"NG",
    "name:eng_x_preferred":[
        "Kiriya"
    ],
    "wof:name":"Kiriya",
    "wof:placetype":"locality"
},
  "geometry": {"coordinates":[13.40148,10.45819],"type":"Point"}
}