{
  "type": "Feature",
  "properties": {
    "gn:admin1_code":"26.0",
    "gn:admin2_code":"7010.0",
    "gn:asciiname":"Agrigbe",
    "gn:country_code":"NG",
    "gn:dem":147,
    "gn:feature_class":"P",
    "gn:feature_code":"PPL",
    "gn:name":"Agrigbe",
    "gn:population":0,
    "gn:timezone":"Africa/Lagos",
    "iso:country":"NG",
    "wof:name":"Agrigbe",
    "wof:placetype":"locality"
},
  "geometry": {"coordinates":[8.5867,7.31417],"type":"Point"}
}