{
  "type": "Feature",
  "properties": {
    "gn:admin1_code":"31.0",
    "gn:admin2_code":"27015.0",
    "gn:asciiname":"Gidan Kwabura",
    "gn:country_code":"NG",
    "gn:dem":238,
    "gn:feature_class":"P",
    "gn:feature_code":"PPL",
    "gn:name":"Gidan Kwabura",
    "gn:population":0,
    "gn:timezone":"Africa/Lagos",
    "iso:country":"NG",
    "wof:name":"Gidan Kwabura",
    "wof:placetype":"locality"
},
  "geometry": {"coordinates":[6.04275,10.4191],"type":"Point"}
}