{
  "type": "Feature",
  "properties": {
    "iso:country":"NG",
    "name:ast_x_preferred":[
        "Ikere-Ekiti"
    ],
    "name:cat_x_preferred":[
        "Ikere"
    ],
    "name:ceb_x_preferred":[
        "Ikere-Ekiti"
    ],
    "name:eng_x_preferred":[
        "Ikere-Ekiti"
    ],
    "name:eng_x_variant":[
        "Ikere"
    ],
    "name:fas_x_preferred":[
        "\u0627\u06cc\u06a9\u0631\u0647-\u0627\u06a9\u06cc\u062a\u06cc"
    ],
    "name:fra_x_preferred":[
        "Ikere"
    ],
    "name:hau_x_preferred":[
        "Ikere"
    ],
    "name:ita_x_preferred":[
        "Ikere"
    ],
    "name:lit_x_preferred":[
        "Ikere Ekitis"
    ],
    "name:mlg_x_preferred":[
        "Ikere-Ekiti"
    ],
    "name:nan_x_preferred":[
        "Ikere-Ekiti"
    ],
    "name:pcm_x_preferred":[
        "Ikere-Ekiti"
    ],
    "name:pol_x_preferred":[
        "Ikere-Ekiti"
    ],
    "name:por_x_preferred":[
        "Ikerre"
    ],
    "name:ron_x_preferred":[
        "Ikerre"
    ],
    "name:spa_x_preferred":[
        "Ikere"
    ],
    "name:war_x_preferred":[
        "Ikere-Ekiti"
    ],
    "name:yor_x_preferred":[
        "Ikerre"
    ],
    "name:zho_min_nan_x_preferred":[
        "Ikere-Ekiti"
    ],
    "qs:gn_country":"NG",
    "qs:gn_fcode":"PPL",
    "qs:gn_pop":103054,
    "qs:name":"Ikerre",
    "qs:name_adm0":"Nigeria",
    "qs:name_adm1":"Ekiti",
    "qs:photos":0,
    "qs:photos_1k":0,
    "qs:photos_9k":1,
    "qs:photos_9r":1,
    "qs:photos_all":1,
    "qs:photos_sr":0,
    "qs:placetype":"Town",
    "qs:pop_sr":"9",
    "qs:woe_adm0":23424908,
    "wd:wordcount":91,
    "wof:name":"Ikerre",
    "wof:placetype":"locality",
    "wof:population":103054
},
  "geometry": {"coordinates":[5.23225,7.49133],"type":"Point"}
}