{
  "type": "Feature",
  "properties": {
    "gn:admin1_code":"49.0",
    "gn:admin2_code":"32004.0",
    "gn:asciiname":"Durbi",
    "gn:country_code":"NG",
    "gn:dem":967,
    "gn:feature_class":"P",
    "gn:feature_code":"PPL",
    "gn:name":"Durbi",
    "gn:population":0,
    "gn:timezone":"Africa/Lagos",
    "iso:country":"NG",
    "wof:name":"Durbi",
    "wof:placetype":"locality"
},
  "geometry": {"coordinates":[8.98925,9.97046],"type":"Point"}
}