{
  "type": "Feature",
  "properties": {
    "gn:admin1_code":"23.0",
    "gn:admin2_code":"19003.0",
    "gn:admin3_code":"KD0305",
    "gn:asciiname":"Tudun",
    "gn:country_code":"NG",
    "gn:dem":656,
    "gn:feature_class":"P",
    "gn:feature_code":"PPL",
    "gn:name":"Tudun",
    "gn:population":0,
    "gn:timezone":"Africa/Lagos",
    "iso:country":"NG",
    "name:azb_x_preferred":[
        "\u062a\u0648\u062f\u0648\u0646"
    ],
    "name:aze_x_preferred":[
        "Tudun"
    ],
    "name:bul_x_preferred":[
        "\u0422\u0443\u0434\u0443\u043d"
    ],
    "name:cat_x_preferred":[
        "Tudun"
    ],
    "name:hun_x_preferred":[
        "Tudun"
    ],
    "name:pol_x_preferred":[
        "Tudun"
    ],
    "name:rus_x_preferred":[
        "\u0422\u0443\u0434\u0443\u043d"
    ],
    "name:slv_x_preferred":[
        "Tudun"
    ],
    "name:tur_x_preferred":[
        "Tudun"
    ],
    "name:ukr_x_preferred":[
        "\u0422\u0443\u0434\u0443\u043d"
    ],
    "wof:name":"Tudun",
    "wof:placetype":"locality"
},
  "geometry": {"coordinates":[7.28953,11.20461],"type":"Point"}
}