{
  "type": "Feature",
  "properties": {
    "gn:admin1_code":"24.0",
    "gn:admin2_code":"401.0",
    "gn:admin3_code":"40109",
    "gn:asciiname":"Bawa",
    "gn:country_code":"NG",
    "gn:dem":639,
    "gn:feature_class":"P",
    "gn:feature_code":"PPL",
    "gn:name":"Bawa",
    "gn:population":0,
    "gn:timezone":"Africa/Lagos",
    "iso:country":"NG",
    "name:ceb_x_preferred":[
        "Bawa"
    ],
    "name:deu_x_preferred":[
        "Bawa"
    ],
    "name:fra_x_preferred":[
        "Bawa"
    ],
    "name:swe_x_preferred":[
        "Bawa"
    ],
    "wof:name":"Bawa",
    "wof:placetype":"locality"
},
  "geometry": {"coordinates":[7.38418,11.71874],"type":"Point"}
}