{
  "type": "Feature",
  "properties": {
    "gn:admin1_code":"51.0",
    "gn:admin2_code":"607.0",
    "gn:admin3_code":"60710",
    "gn:asciiname":"Guberu",
    "gn:country_code":"NG",
    "gn:dem":289,
    "gn:feature_class":"P",
    "gn:feature_code":"PPL",
    "gn:name":"Guberu",
    "gn:population":0,
    "gn:timezone":"Africa/Lagos",
    "iso:country":"NG",
    "wof:name":"Guberu",
    "wof:placetype":"locality"
},
  "geometry": {"coordinates":[5.40763,13.44478],"type":"Point"}
}