{
  "type": "Feature",
  "properties": {
    "gn:admin1_code":"53.0",
    "gn:admin2_code":"11007.0",
    "gn:asciiname":"Odomowo",
    "gn:country_code":"NG",
    "gn:dem":39,
    "gn:feature_class":"P",
    "gn:feature_code":"PPL",
    "gn:name":"Odomowo",
    "gn:population":0,
    "gn:timezone":"Africa/Lagos",
    "iso:country":"NG",
    "name:und_x_variant":[
        "Udomowo",
        "Udimowo",
        "Odomowo"
    ],
    "wof:name":"Odomowo",
    "wof:placetype":"locality"
},
  "geometry": {"coordinates":[8.23788,6.05772],"type":"Point"}
}