{
  "type": "Feature",
  "properties": {
    "gn:admin1_code":"27.0",
    "gn:admin2_code":"127.0",
    "gn:admin3_code":"12702",
    "gn:asciiname":"Labigi",
    "gn:country_code":"NG",
    "gn:dem":250,
    "gn:feature_class":"P",
    "gn:feature_code":"PPL",
    "gn:name":"Labigi",
    "gn:population":0,
    "gn:timezone":"Africa/Lagos",
    "iso:country":"NG",
    "wof:name":"Labigi",
    "wof:placetype":"locality"
},
  "geometry": {"coordinates":[12.18747,10.31246],"type":"Point"}
}