{
  "type": "Feature",
  "properties": {
    "gn:admin1_code":"51.0",
    "gn:admin2_code":"607.0",
    "gn:admin3_code":"60704",
    "gn:asciiname":"Kaura Dodu",
    "gn:country_code":"NG",
    "gn:dem":287,
    "gn:feature_class":"P",
    "gn:feature_code":"PPL",
    "gn:name":"Kaura Dodu",
    "gn:population":0,
    "gn:timezone":"Africa/Lagos",
    "iso:country":"NG",
    "wof:name":"Kaura Dodu",
    "wof:placetype":"locality"
},
  "geometry": {"coordinates":[5.33335,13.23085],"type":"Point"}
}