{
  "type": "Feature",
  "properties": {
    "gn:admin1_code":"51.0",
    "gn:admin2_code":"621.0",
    "gn:admin3_code":"62103",
    "gn:asciiname":"Gidan Sala",
    "gn:country_code":"NG",
    "gn:dem":286,
    "gn:feature_class":"P",
    "gn:feature_code":"PPL",
    "gn:name":"Gidan Sala",
    "gn:population":0,
    "gn:timezone":"Africa/Lagos",
    "iso:country":"NG",
    "wof:name":"Gidan Sala",
    "wof:placetype":"locality"
},
  "geometry": {"coordinates":[5.25023,13.16898],"type":"Point"}
}