{
  "type": "Feature",
  "properties": {
    "gn:admin1_code":"37.0",
    "gn:admin2_code":"12013.0",
    "gn:asciiname":"Obanaghoro",
    "gn:country_code":"NG",
    "gn:dem":13,
    "gn:feature_class":"P",
    "gn:feature_code":"PPL",
    "gn:name":"Obanaghoro",
    "gn:population":0,
    "gn:timezone":"Africa/Lagos",
    "iso:country":"NG",
    "name:und_x_variant":[
        "Obanagboro",
        "Obanaghoro"
    ],
    "wof:name":"Obanaghoro",
    "wof:placetype":"locality"
},
  "geometry": {"coordinates":[5.90872,5.80779],"type":"Point"}
}