{
  "type": "Feature",
  "properties": {
    "gn:admin1_code":"31.0",
    "gn:admin2_code":"27008.0",
    "gn:asciiname":"Kuchigi",
    "gn:country_code":"NG",
    "gn:dem":154,
    "gn:feature_class":"P",
    "gn:feature_code":"PPL",
    "gn:name":"Kuchigi",
    "gn:population":0,
    "gn:timezone":"Africa/Lagos",
    "iso:country":"NG",
    "wof:name":"Kuchigi",
    "wof:placetype":"locality"
},
  "geometry": {"coordinates":[5.93333,9.05],"type":"Point"}
}