{
  "type": "Feature",
  "properties": {
    "gn:admin1_code":"23.0",
    "gn:admin2_code":"19017.0",
    "gn:admin3_code":"KD1707",
    "gn:asciiname":"Ishem",
    "gn:country_code":"NG",
    "gn:dem":819,
    "gn:feature_class":"P",
    "gn:feature_code":"PPL",
    "gn:name":"Ishem",
    "gn:population":0,
    "gn:timezone":"Africa/Lagos",
    "iso:country":"NG",
    "name:und_x_variant":[
        "Ishemi"
    ],
    "wof:name":"Ishem",
    "wof:placetype":"locality"
},
  "geometry": {"coordinates":[8.59411,10.28519],"type":"Point"}
}