{
  "type": "Feature",
  "properties": {
    "gn:admin1_code":"43.0",
    "gn:admin2_code":"35010.0",
    "gn:asciiname":"Dobelli",
    "gn:country_code":"NG",
    "gn:dem":133,
    "gn:feature_class":"P",
    "gn:feature_code":"PPL",
    "gn:name":"Dobelli",
    "gn:population":0,
    "gn:timezone":"Africa/Lagos",
    "iso:country":"NG",
    "name:und_x_variant":[
        "Dobeli",
        "Dobelli"
    ],
    "wof:name":"Dobelli",
    "wof:placetype":"locality"
},
  "geometry": {"coordinates":[11.1801,9.15301],"type":"Point"}
}