{
  "type": "Feature",
  "properties": {
    "gn:admin1_code":"35.0",
    "gn:admin2_code":"2007.0",
    "gn:asciiname":"Kwapatahu",
    "gn:country_code":"NG",
    "gn:dem":505,
    "gn:feature_class":"P",
    "gn:feature_code":"PPL",
    "gn:name":"Kwapatahu",
    "gn:population":0,
    "gn:timezone":"Africa/Lagos",
    "iso:country":"NG",
    "wof:name":"Kwapatahu",
    "wof:placetype":"locality"
},
  "geometry": {"coordinates":[12.89934,10.27033],"type":"Point"}
}