{
  "type": "Feature",
  "properties": {
    "gn:admin1_code":"53.0",
    "gn:admin2_code":"11007.0",
    "gn:asciiname":"Umuta",
    "gn:country_code":"NG",
    "gn:dem":60,
    "gn:feature_class":"P",
    "gn:feature_code":"PPL",
    "gn:name":"Umuta",
    "gn:population":0,
    "gn:timezone":"Africa/Lagos",
    "iso:country":"NG",
    "wof:name":"Umuta",
    "wof:placetype":"locality"
},
  "geometry": {"coordinates":[8.069,6.06603],"type":"Point"}
}