{
  "type": "Feature",
  "properties": {
    "gn:admin1_code":"32.0",
    "gn:admin2_code":"31032.0",
    "gn:asciiname":"Aiyekale",
    "gn:country_code":"NG",
    "gn:dem":370,
    "gn:feature_class":"P",
    "gn:feature_code":"PPL",
    "gn:name":"Aiyekale",
    "gn:population":0,
    "gn:timezone":"Africa/Lagos",
    "iso:country":"NG",
    "wof:name":"Aiyekale",
    "wof:placetype":"locality"
},
  "geometry": {"coordinates":[3.36667,8.65],"type":"Point"}
}