{
  "type": "Feature",
  "properties": {
    "gn:admin1_code":"40.0",
    "gn:admin2_code":"510.0",
    "gn:admin3_code":"51005",
    "gn:asciiname":"Ungwa Enwu",
    "gn:country_code":"NG",
    "gn:dem":263,
    "gn:feature_class":"P",
    "gn:feature_code":"PPL",
    "gn:name":"Ungwa Enwu",
    "gn:population":0,
    "gn:timezone":"Africa/Lagos",
    "iso:country":"NG",
    "wof:name":"Ungwa Enwu",
    "wof:placetype":"locality"
},
  "geometry": {"coordinates":[4.60859,12.56117],"type":"Point"}
}