{
  "type": "Feature",
  "properties": {
    "gn:admin1_code":"57.0",
    "gn:asciiname":"Kursa",
    "gn:country_code":"NG",
    "gn:dem":275,
    "gn:feature_class":"P",
    "gn:feature_code":"PPL",
    "gn:name":"Kursa",
    "gn:population":0,
    "gn:timezone":"Africa/Lagos",
    "iso:country":"NG",
    "name:lav_x_preferred":[
        "Kursa"
    ],
    "wof:name":"Kursa",
    "wof:placetype":"locality"
},
  "geometry": {"coordinates":[5.87644,13.00421],"type":"Point"}
}