{
  "type": "Feature",
  "properties": {
    "gn:admin1_code":"21.0",
    "gn:admin2_code":"3018.0",
    "gn:asciiname":"Ikot Ekong",
    "gn:country_code":"NG",
    "gn:dem":23,
    "gn:feature_class":"P",
    "gn:feature_code":"PPL",
    "gn:name":"Ikot Ekong",
    "gn:population":0,
    "gn:timezone":"Africa/Lagos",
    "iso:country":"NG",
    "wof:name":"Ikot Ekong",
    "wof:placetype":"locality"
},
  "geometry": {"coordinates":[7.79284,4.62604],"type":"Point"}
}