{
  "type": "Feature",
  "properties": {
    "gn:admin1_code":"21.0",
    "gn:admin2_code":"3026.0",
    "gn:asciiname":"Mbon Ebre",
    "gn:country_code":"NG",
    "gn:dem":47,
    "gn:feature_class":"P",
    "gn:feature_code":"PPL",
    "gn:name":"Mbon Ebre",
    "gn:population":0,
    "gn:timezone":"Africa/Lagos",
    "iso:country":"NG",
    "wof:name":"Mbon Ebre",
    "wof:placetype":"locality"
},
  "geometry": {"coordinates":[7.73865,4.86446],"type":"Point"}
}