{
  "type": "Feature",
  "properties": {
    "gn:admin1_code":"32.0",
    "gn:admin2_code":"31017.0",
    "gn:asciiname":"Ago Fulani",
    "gn:country_code":"NG",
    "gn:dem":299,
    "gn:feature_class":"P",
    "gn:feature_code":"PPL",
    "gn:name":"Ago Fulani",
    "gn:population":0,
    "gn:timezone":"Africa/Lagos",
    "iso:country":"NG",
    "wof:name":"Ago Fulani",
    "wof:placetype":"locality"
},
  "geometry": {"coordinates":[3.35,8.21667],"type":"Point"}
}