{
  "type": "Feature",
  "properties": {
    "gn:admin1_code":"51.0",
    "gn:admin2_code":"618.0",
    "gn:admin3_code":"61805",
    "gn:asciiname":"Fagga",
    "gn:country_code":"NG",
    "gn:dem":263,
    "gn:feature_class":"P",
    "gn:feature_code":"PPL",
    "gn:name":"Fagga",
    "gn:population":0,
    "gn:timezone":"Africa/Lagos",
    "iso:country":"NG",
    "name:und_x_variant":[
        "Faga",
        "Fagga"
    ],
    "wof:name":"Fagga",
    "wof:placetype":"locality"
},
  "geometry": {"coordinates":[4.59923,12.32236],"type":"Point"}
}