{
  "type": "Feature",
  "properties": {
    "gn:admin1_code":"49.0",
    "gn:admin2_code":"32017",
    "gn:asciiname":"Kadarko",
    "gn:country_code":"NG",
    "gn:dem":183,
    "gn:feature_class":"P",
    "gn:feature_code":"PPL",
    "gn:name":"Kadarko",
    "gn:population":0,
    "gn:timezone":"Africa/Lagos",
    "iso:country":"NG",
    "wof:name":"Kadarko",
    "wof:placetype":"locality"
},
  "geometry": {"coordinates":[10.02176,8.90757],"type":"Point"}
}