{
  "type": "Feature",
  "properties": {
    "gn:admin1_code":"57.0",
    "gn:admin2_code":"810.0",
    "gn:admin3_code":"81007",
    "gn:asciiname":"Ungwan Sarkin Makera",
    "gn:country_code":"NG",
    "gn:dem":466,
    "gn:feature_class":"P",
    "gn:feature_code":"PPL",
    "gn:name":"Ungwan Sarkin Makera",
    "gn:population":0,
    "gn:timezone":"Africa/Lagos",
    "iso:country":"NG",
    "wof:name":"Ungwan Sarkin Makera",
    "wof:placetype":"locality"
},
  "geometry": {"coordinates":[6.45,11.24964],"type":"Point"}
}