{
  "type": "Feature",
  "properties": {
    "gn:admin1_code":"51.0",
    "gn:admin2_code":"611.0",
    "gn:admin3_code":"61104",
    "gn:asciiname":"Hausawa",
    "gn:country_code":"NG",
    "gn:dem":304,
    "gn:feature_class":"P",
    "gn:feature_code":"PPL",
    "gn:name":"Hausawa",
    "gn:population":0,
    "gn:timezone":"Africa/Lagos",
    "iso:country":"NG",
    "wof:name":"Hausawa",
    "wof:placetype":"locality"
},
  "geometry": {"coordinates":[5.30128,13.12766],"type":"Point"}
}