{
  "type": "Feature",
  "properties": {
    "gn:admin1_code":"24.0",
    "gn:admin2_code":"407.0",
    "gn:admin3_code":"40707",
    "gn:asciiname":"Mahuta",
    "gn:country_code":"NG",
    "gn:dem":713,
    "gn:feature_class":"P",
    "gn:feature_code":"PPL",
    "gn:name":"Mahuta",
    "gn:population":0,
    "gn:timezone":"Africa/Lagos",
    "iso:country":"NG",
    "wof:name":"Mahuta",
    "wof:placetype":"locality"
},
  "geometry": {"coordinates":[7.26857,11.44301],"type":"Point"}
}