{
  "type": "Feature",
  "properties": {
    "gn:admin1_code":"31.0",
    "gn:admin2_code":"27007",
    "gn:asciiname":"Kusodu",
    "gn:country_code":"NG",
    "gn:dem":202,
    "gn:feature_class":"P",
    "gn:feature_code":"PPL",
    "gn:name":"Kusodu",
    "gn:population":0,
    "gn:timezone":"Africa/Lagos",
    "iso:country":"NG",
    "wof:name":"Kusodu",
    "wof:placetype":"locality"
},
  "geometry": {"coordinates":[5.52307,9.08729],"type":"Point"}
}