{
  "type": "Feature",
  "properties": {
    "gn:admin1_code":"21.0",
    "gn:admin2_code":"3007.0",
    "gn:asciiname":"Ikot Ante",
    "gn:country_code":"NG",
    "gn:dem":47,
    "gn:feature_class":"P",
    "gn:feature_code":"PPL",
    "gn:name":"Ikot Ante",
    "gn:population":0,
    "gn:timezone":"Africa/Lagos",
    "iso:country":"NG",
    "wof:name":"Ikot Ante",
    "wof:placetype":"locality"
},
  "geometry": {"coordinates":[7.85465,4.74459],"type":"Point"}
}