{
  "type": "Feature",
  "properties": {
    "gn:admin1_code":"46.0",
    "gn:admin2_code":"5018.0",
    "gn:admin3_code":"BA1804",
    "gn:asciiname":"Takabundu",
    "gn:country_code":"NG",
    "gn:dem":758,
    "gn:feature_class":"P",
    "gn:feature_code":"PPL",
    "gn:name":"Takabundu",
    "gn:population":0,
    "gn:timezone":"Africa/Lagos",
    "iso:country":"NG",
    "wof:name":"Takabundu",
    "wof:placetype":"locality"
},
  "geometry": {"coordinates":[9.30895,10.20818],"type":"Point"}
}