{
  "type": "Feature",
  "properties": {
    "gn:admin1_code":"16.0",
    "gn:admin2_code":"28003.0",
    "gn:asciiname":"Isale",
    "gn:country_code":"NG",
    "gn:dem":49,
    "gn:feature_class":"P",
    "gn:feature_code":"PPL",
    "gn:name":"Isale",
    "gn:population":0,
    "gn:timezone":"Africa/Lagos",
    "iso:country":"NG",
    "wof:name":"Isale",
    "wof:placetype":"locality"
},
  "geometry": {"coordinates":[3.14133,6.69725],"type":"Point"}
}