{
  "type": "Feature",
  "properties": {
    "gn:admin1_code":"44.0",
    "gn:admin2_code":"712.0",
    "gn:admin3_code":"71214",
    "gn:asciiname":"Bade",
    "gn:country_code":"NG",
    "gn:dem":433,
    "gn:feature_class":"P",
    "gn:feature_code":"PPL",
    "gn:name":"Bade",
    "gn:population":0,
    "gn:timezone":"Africa/Lagos",
    "iso:country":"NG",
    "name:ceb_x_preferred":[
        "Bade"
    ],
    "name:deu_x_preferred":[
        "Bade"
    ],
    "name:fra_x_preferred":[
        "Bade"
    ],
    "name:glg_x_preferred":[
        "Bade"
    ],
    "name:ita_x_preferred":[
        "Bade"
    ],
    "name:kat_x_preferred":[
        "\u10d1\u10d0\u10d3\u10d4"
    ],
    "name:nld_x_preferred":[
        "Bade"
    ],
    "name:rus_x_preferred":[
        "\u0411\u0430\u0434\u0435"
    ],
    "name:swe_x_preferred":[
        "Bade"
    ],
    "wof:name":"Bade",
    "wof:placetype":"locality"
},
  "geometry": {"coordinates":[11.16555,11.7451],"type":"Point"}
}