{
  "type": "Feature",
  "properties": {
    "gn:admin1_code":"44.0",
    "gn:admin2_code":"712.0",
    "gn:admin3_code":"71214",
    "gn:asciiname":"Bade",
    "gn:country_code":"NG",
    "gn:dem":433,
    "gn:feature_class":"P",
    "gn:feature_code":"PPL",
    "gn:name":"Bade",
    "gn:population":0,
    "gn:timezone":"Africa/Lagos",
    "iso:country":"NG",
    "name:ara_x_preferred":[
        "\u0628\u064a\u062f"
    ],
    "name:ben_x_preferred":[
        "\u09ac\u09a1\u09c7"
    ],
    "name:ceb_x_preferred":[
        "Bade"
    ],
    "name:deu_x_preferred":[
        "Bade"
    ],
    "name:ell_x_preferred":[
        "\u039c\u03c0\u03ac\u03bd\u03c4\u03b5"
    ],
    "name:fas_x_preferred":[
        "\u0628\u0627\u062f\u0647"
    ],
    "name:fra_x_preferred":[
        "Bade"
    ],
    "name:glg_x_preferred":[
        "Bade"
    ],
    "name:heb_x_preferred":[
        "\u05d1\u05d3\u05d4"
    ],
    "name:hin_x_preferred":[
        "\u092c\u0947\u0921"
    ],
    "name:hun_x_preferred":[
        "Bade"
    ],
    "name:ind_x_preferred":[
        "Bade"
    ],
    "name:ita_x_preferred":[
        "Bade"
    ],
    "name:kat_x_preferred":[
        "\u10d1\u10d0\u10d3\u10d4"
    ],
    "name:nld_x_preferred":[
        "Bade"
    ],
    "name:rus_x_preferred":[
        "\u0411\u0430\u0434\u0435"
    ],
    "name:spa_x_preferred":[
        "Bade"
    ],
    "name:swe_x_preferred":[
        "Bade"
    ],
    "name:tur_x_preferred":[
        "Bade"
    ],
    "name:ukr_x_preferred":[
        "\u0411\u0430\u0434\u0435"
    ],
    "name:urd_x_preferred":[
        "\u0628\u06cc\u0688\u06d2"
    ],
    "wof:name":"Bade",
    "wof:placetype":"locality"
},
  "geometry": {"coordinates":[11.16555,11.7451],"type":"Point"}
}