{
  "type": "Feature",
  "properties": {
    "gn:admin1_code":"35.0",
    "gn:admin2_code":"2013.0",
    "gn:asciiname":"Mandara",
    "gn:country_code":"NG",
    "gn:dem":517,
    "gn:feature_class":"P",
    "gn:feature_code":"PPL",
    "gn:name":"Mandara",
    "gn:population":0,
    "gn:timezone":"Africa/Lagos",
    "iso:country":"NG",
    "name:bar_x_preferred":[
        "Mandara"
    ],
    "name:cat_x_preferred":[
        "Mandara"
    ],
    "name:deu_x_preferred":[
        "Mandara"
    ],
    "name:fra_x_preferred":[
        "Mandara"
    ],
    "name:ita_x_preferred":[
        "Mandara"
    ],
    "name:nld_x_preferred":[
        "Mandara"
    ],
    "name:rus_x_preferred":[
        "\u041c\u0430\u043d\u0434\u0430\u0440\u0430"
    ],
    "wof:name":"Mandara",
    "wof:placetype":"locality"
},
  "geometry": {"coordinates":[13.42503,10.65976],"type":"Point"}
}