{
  "type": "Feature",
  "properties": {
    "gn:admin1_code":"16.0",
    "gn:admin2_code":"28004.0",
    "gn:asciiname":"Imule Amos",
    "gn:cc2":"NG",
    "gn:country_code":"NG",
    "gn:dem":89,
    "gn:feature_class":"P",
    "gn:feature_code":"PPL",
    "gn:name":"Imule Amos",
    "gn:population":0,
    "gn:timezone":"Africa/Lagos",
    "iso:country":"NG",
    "name:und_x_variant":[
        "Imule",
        "Imule Amos"
    ],
    "wof:name":"Imule Amos",
    "wof:placetype":"locality"
},
  "geometry": {"coordinates":[2.78333,6.85],"type":"Point"}
}