{
  "type": "Feature",
  "properties": {
    "gn:admin1_code":"35.0",
    "gn:admin2_code":"2012",
    "gn:asciiname":"Maisiyare",
    "gn:country_code":"NG",
    "gn:dem":519,
    "gn:feature_class":"P",
    "gn:feature_code":"PPL",
    "gn:name":"Maisiyare",
    "gn:population":0,
    "gn:timezone":"Africa/Lagos",
    "iso:country":"NG",
    "wof:name":"Maisiyare",
    "wof:placetype":"locality"
},
  "geometry": {"coordinates":[11.89268,8.67105],"type":"Point"}
}