{
  "type": "Feature",
  "properties": {
    "gn:admin1_code":"35.0",
    "gn:admin2_code":"2007.0",
    "gn:asciiname":"Kokitsa",
    "gn:country_code":"NG",
    "gn:dem":617,
    "gn:feature_class":"P",
    "gn:feature_code":"PPL",
    "gn:name":"Kokitsa",
    "gn:population":0,
    "gn:timezone":"Africa/Lagos",
    "iso:country":"NG",
    "wof:name":"Kokitsa",
    "wof:placetype":"locality"
},
  "geometry": {"coordinates":[12.98374,10.205],"type":"Point"}
}