{
  "type": "Feature",
  "properties": {
    "gn:admin1_code":"40.0",
    "gn:admin2_code":"502.0",
    "gn:admin3_code":"50208",
    "gn:asciiname":"Baraya",
    "gn:country_code":"NG",
    "gn:dem":222,
    "gn:feature_class":"P",
    "gn:feature_code":"PPL",
    "gn:name":"Baraya",
    "gn:population":0,
    "gn:timezone":"Africa/Lagos",
    "iso:country":"NG",
    "name:ceb_x_preferred":[
        "Baraya"
    ],
    "name:fra_x_preferred":[
        "Baraya"
    ],
    "name:ita_x_preferred":[
        "Baraya"
    ],
    "name:kat_x_preferred":[
        "\u10d1\u10d0\u10e0\u10d0\u10d8\u10d0"
    ],
    "name:msa_x_preferred":[
        "Baraya"
    ],
    "name:nld_x_preferred":[
        "Baraya"
    ],
    "name:por_x_preferred":[
        "Baraya"
    ],
    "name:sco_x_preferred":[
        "Baraya"
    ],
    "name:spa_x_preferred":[
        "Baraya"
    ],
    "name:swe_x_preferred":[
        "Baraya"
    ],
    "name:tgl_x_preferred":[
        "Baraya"
    ],
    "name:vie_x_preferred":[
        "Baraya"
    ],
    "name:war_x_preferred":[
        "Baraya"
    ],
    "name:zho_x_preferred":[
        "\u5df4\u62c9\u4e9e"
    ],
    "wof:name":"Baraya",
    "wof:placetype":"locality"
},
  "geometry": {"coordinates":[3.8365,12.59005],"type":"Point"}
}