{
  "type": "Feature",
  "properties": {
    "gn:admin1_code":"26.0",
    "gn:admin2_code":"7007.0",
    "gn:asciiname":"Tsetange",
    "gn:country_code":"NG",
    "gn:dem":139,
    "gn:feature_class":"P",
    "gn:feature_code":"PPL",
    "gn:name":"Tsetange",
    "gn:population":0,
    "gn:timezone":"Africa/Lagos",
    "iso:country":"NG",
    "wof:name":"Tsetange",
    "wof:placetype":"locality"
},
  "geometry": {"coordinates":[8.40737,7.23179],"type":"Point"}
}