{
  "type": "Feature",
  "properties": {
    "gn:admin1_code":"36.0",
    "gn:asciiname":"Tongafa",
    "gn:country_code":"NG",
    "gn:dem":10,
    "gn:feature_class":"P",
    "gn:feature_code":"PPL",
    "gn:name":"Tongafa",
    "gn:population":0,
    "gn:timezone":"Africa/Lagos",
    "iso:country":"NG",
    "name:eng_x_preferred":[
        "Tongafa"
    ],
    "wof:name":"Tongafa",
    "wof:placetype":"locality"
},
  "geometry": {"coordinates":[5.16195,5.8696],"type":"Point"}
}