{
  "type": "Feature",
  "properties": {
    "gn:admin1_code":"42.0",
    "gn:admin2_code":"30028.0",
    "gn:asciiname":"Erimo",
    "gn:country_code":"NG",
    "gn:dem":409,
    "gn:feature_class":"P",
    "gn:feature_code":"PPL",
    "gn:name":"Erimo",
    "gn:population":0,
    "gn:timezone":"Africa/Lagos",
    "iso:country":"NG",
    "wof:name":"Erimo",
    "wof:placetype":"locality"
},
  "geometry": {"coordinates":[4.85,7.63333],"type":"Point"}
}