{
  "type": "Feature",
  "properties": {
    "gn:admin1_code":"57.0",
    "gn:admin2_code":"808.0",
    "gn:admin3_code":"80802",
    "gn:asciiname":"Kwolo",
    "gn:country_code":"NG",
    "gn:dem":402,
    "gn:feature_class":"P",
    "gn:feature_code":"PPL",
    "gn:name":"Kwolo",
    "gn:population":0,
    "gn:timezone":"Africa/Lagos",
    "iso:country":"NG",
    "name:und_x_variant":[
        "Unguwar Kwolo",
        "Kwolo"
    ],
    "wof:name":"Kwolo",
    "wof:placetype":"locality"
},
  "geometry": {"coordinates":[6.74383,12.38674],"type":"Point"}
}