{
  "type": "Feature",
  "properties": {
    "gn:admin1_code":"26.0",
    "gn:admin2_code":"7004",
    "gn:asciiname":"Ahula",
    "gn:country_code":"NG",
    "gn:dem":126,
    "gn:feature_class":"P",
    "gn:feature_code":"PPL",
    "gn:name":"Ahula",
    "gn:population":0,
    "gn:timezone":"Africa/Lagos",
    "iso:country":"NG",
    "name:ceb_x_preferred":[
        "Ahula"
    ],
    "name:est_x_preferred":[
        "Ahula"
    ],
    "name:fas_x_preferred":[
        "\u0627\u0647\u0648\u0644\u0627"
    ],
    "name:fra_x_preferred":[
        "Ahula"
    ],
    "name:hye_x_preferred":[
        "\u0531\u0570\u0578\u0582\u056c\u0561"
    ],
    "name:pol_x_preferred":[
        "Ahula"
    ],
    "name:spa_x_preferred":[
        "Ahula"
    ],
    "name:swe_x_preferred":[
        "Ahula"
    ],
    "name:ukr_x_preferred":[
        "\u0410\u0433\u0443\u043b\u0430"
    ],
    "name:vol_x_preferred":[
        "Ahula"
    ],
    "wof:name":"Ahula",
    "wof:placetype":"locality"
},
  "geometry": {"coordinates":[9.09903,7.52211],"type":"Point"}
}