{
  "type": "Feature",
  "properties": {
    "gn:admin1_code":"23.0",
    "gn:admin2_code":"19014",
    "gn:admin3_code":"KD1401",
    "gn:asciiname":"Kurmin Ruwa",
    "gn:country_code":"NG",
    "gn:dem":806,
    "gn:feature_class":"P",
    "gn:feature_code":"PPL",
    "gn:name":"Kurmin Ruwa",
    "gn:population":0,
    "gn:timezone":"Africa/Lagos",
    "iso:country":"NG",
    "wof:name":"Kurmin Ruwa",
    "wof:placetype":"locality"
},
  "geometry": {"coordinates":[8.4724,9.92002],"type":"Point"}
}