{
  "type": "Feature",
  "properties": {
    "gn:admin1_code":"35.0",
    "gn:asciiname":"Biri",
    "gn:country_code":"NG",
    "gn:dem":225,
    "gn:feature_class":"P",
    "gn:feature_code":"PPL",
    "gn:name":"Biri",
    "gn:population":0,
    "gn:timezone":"Africa/Lagos",
    "iso:country":"NG",
    "name:ceb_x_preferred":[
        "Biri"
    ],
    "name:ces_x_preferred":[
        "Biri"
    ],
    "name:deu_x_preferred":[
        "Biri"
    ],
    "name:eng_x_preferred":[
        "Biri"
    ],
    "name:eng_x_variant":[
        "Diri"
    ],
    "name:fra_x_preferred":[
        "Biri"
    ],
    "name:hun_x_preferred":[
        "Biri"
    ],
    "name:ita_x_preferred":[
        "Biri"
    ],
    "name:swe_x_preferred":[
        "Biri"
    ],
    "name:tgl_x_preferred":[
        "Biri"
    ],
    "wof:name":"Biri",
    "wof:placetype":"locality"
},
  "geometry": {"coordinates":[12.21933,9.09133],"type":"Point"}
}