{
  "type": "Feature",
  "properties": {
    "gn:admin1_code":"26.0",
    "gn:admin2_code":"7007",
    "gn:asciiname":"Ichelun",
    "gn:country_code":"NG",
    "gn:dem":127,
    "gn:feature_class":"P",
    "gn:feature_code":"PPL",
    "gn:name":"Ichelun",
    "gn:population":0,
    "gn:timezone":"Africa/Lagos",
    "iso:country":"NG",
    "wof:name":"Ichelun",
    "wof:placetype":"locality"
},
  "geometry": {"coordinates":[8.34953,7.33086],"type":"Point"}
}