{
  "type": "Feature",
  "properties": {
    "gn:admin1_code":"27.0",
    "gn:admin2_code":"103",
    "gn:admin3_code":"10312",
    "gn:asciiname":"Garno",
    "gn:country_code":"NG",
    "gn:dem":321,
    "gn:feature_class":"P",
    "gn:feature_code":"PPL",
    "gn:name":"Garno",
    "gn:population":0,
    "gn:timezone":"Africa/Lagos",
    "iso:country":"NG",
    "name:fra_x_preferred":[
        "Garno"
    ],
    "name:pol_x_preferred":[
        "Garno"
    ],
    "name:ukr_x_preferred":[
        "\u0490\u0430\u0440\u043d\u043e"
    ],
    "wof:name":"Garno",
    "wof:placetype":"locality"
},
  "geometry": {"coordinates":[13.82203,11.45382],"type":"Point"}
}