{
  "type": "Feature",
  "properties": {
    "gn:admin1_code":"43.0",
    "gn:admin2_code":"35002.0",
    "gn:asciiname":"Ebba",
    "gn:country_code":"NG",
    "gn:dem":214,
    "gn:feature_class":"P",
    "gn:feature_code":"PPL",
    "gn:name":"Ebba",
    "gn:population":0,
    "gn:timezone":"Africa/Lagos",
    "iso:country":"NG",
    "name:bre_x_preferred":[
        "Ebba"
    ],
    "name:deu_x_preferred":[
        "Ebba"
    ],
    "name:fao_x_preferred":[
        "Ebba"
    ],
    "name:fin_x_preferred":[
        "Ebba"
    ],
    "name:isl_x_preferred":[
        "Ebba"
    ],
    "name:ita_x_preferred":[
        "Ebba"
    ],
    "name:nor_x_preferred":[
        "Ebba"
    ],
    "name:swe_x_preferred":[
        "Ebba"
    ],
    "wof:name":"Ebba",
    "wof:placetype":"locality"
},
  "geometry": {"coordinates":[10.62663,7.86506],"type":"Point"}
}