{
  "type": "Feature",
  "properties": {
    "gn:admin1_code":"45.0",
    "gn:asciiname":"Ishiagu",
    "gn:country_code":"NG",
    "gn:dem":82,
    "gn:feature_class":"P",
    "gn:feature_code":"PPL",
    "gn:name":"Ishiagu",
    "gn:population":0,
    "gn:timezone":"Africa/Lagos",
    "iso:country":"NG",
    "wof:name":"Ishiagu",
    "wof:placetype":"locality"
},
  "geometry": {"coordinates":[7.56011,5.95293],"type":"Point"}
}