{
  "type": "Feature",
  "properties": {
    "gn:admin1_code":"43.0",
    "gn:asciiname":"Gabatahe",
    "gn:country_code":"NG",
    "gn:dem":164,
    "gn:feature_class":"P",
    "gn:feature_code":"PPL",
    "gn:name":"Gabatahe",
    "gn:population":0,
    "gn:timezone":"Africa/Lagos",
    "iso:country":"NG",
    "name:eng_x_preferred":[
        "Gabatahe"
    ],
    "wof:name":"Gabatahe",
    "wof:placetype":"locality"
},
  "geometry": {"coordinates":[11.06986,9.31118],"type":"Point"}
}