{
  "type": "Feature",
  "properties": {
    "gn:admin1_code":"37.0",
    "gn:admin2_code":"12006",
    "gn:asciiname":"Ekpoma",
    "gn:country_code":"NG",
    "gn:dem":167,
    "gn:feature_class":"P",
    "gn:feature_code":"PPLF",
    "gn:name":"Ekpoma",
    "gn:population":0,
    "gn:timezone":"Africa/Lagos",
    "iso:country":"NG",
    "wof:name":"Ekpoma",
    "wof:placetype":"locality"
},
  "geometry": {"coordinates":[6.14112,6.8221],"type":"Point"}
}