{
  "type": "Feature",
  "properties": {
    "gn:admin1_code":"40.0",
    "gn:admin2_code":"512.0",
    "gn:admin3_code":"51206",
    "gn:asciiname":"Ungwan Bawaci",
    "gn:country_code":"NG",
    "gn:dem":213,
    "gn:feature_class":"P",
    "gn:feature_code":"PPL",
    "gn:name":"Ungwan Bawaci",
    "gn:population":0,
    "gn:timezone":"Africa/Lagos",
    "iso:country":"NG",
    "wof:name":"Ungwan Bawaci",
    "wof:placetype":"locality"
},
  "geometry": {"coordinates":[3.95458,12.42855],"type":"Point"}
}