{
  "type": "Feature",
  "properties": {
    "gn:admin1_code":"46.0",
    "gn:admin2_code":"5012.0",
    "gn:admin3_code":"BA1205",
    "gn:asciiname":"Gabai",
    "gn:country_code":"NG",
    "gn:dem":395,
    "gn:feature_class":"P",
    "gn:feature_code":"PPL",
    "gn:name":"Gabai",
    "gn:population":0,
    "gn:timezone":"Africa/Lagos",
    "iso:country":"NG",
    "wof:name":"Gabai",
    "wof:placetype":"locality"
},
  "geometry": {"coordinates":[10.3222,11.7092],"type":"Point"}
}