{
  "type": "Feature",
  "properties": {
    "gn:admin1_code":"35.0",
    "gn:asciiname":"Gondil",
    "gn:country_code":"NG",
    "gn:dem":223,
    "gn:feature_class":"P",
    "gn:feature_code":"PPL",
    "gn:name":"Gondil",
    "gn:population":0,
    "gn:timezone":"Africa/Lagos",
    "iso:country":"NG",
    "name:eng_x_preferred":[
        "Gondil"
    ],
    "wof:name":"Gondil",
    "wof:placetype":"locality"
},
  "geometry": {"coordinates":[11.86362,9.32911],"type":"Point"}
}