{
  "type": "Feature",
  "properties": {
    "gn:admin1_code":"26.0",
    "gn:admin2_code":"7007.0",
    "gn:asciiname":"Nev",
    "gn:country_code":"NG",
    "gn:dem":188,
    "gn:feature_class":"P",
    "gn:feature_code":"PPL",
    "gn:name":"Nev",
    "gn:population":0,
    "gn:timezone":"Africa/Lagos",
    "iso:country":"NG",
    "name:und_x_variant":[
        "Nov",
        "Nev"
    ],
    "wof:name":"Nev",
    "wof:placetype":"locality"
},
  "geometry": {"coordinates":[8.60007,7.57155],"type":"Point"}
}