{
  "type": "Feature",
  "properties": {
    "gn:admin1_code":"36.0",
    "gn:admin2_code":"10015.0",
    "gn:asciiname":"Abala",
    "gn:country_code":"NG",
    "gn:dem":25,
    "gn:feature_class":"P",
    "gn:feature_code":"PPL",
    "gn:name":"Abala",
    "gn:population":0,
    "gn:timezone":"Africa/Lagos",
    "iso:country":"NG",
    "name:ceb_x_preferred":[
        "Abala"
    ],
    "name:deu_x_preferred":[
        "Abala"
    ],
    "name:eng_x_preferred":[
        "Abala"
    ],
    "name:fra_x_preferred":[
        "Abala"
    ],
    "name:ita_x_preferred":[
        "Abala"
    ],
    "name:srp_x_preferred":[
        "\u0410\u0431\u0430\u043b\u0430"
    ],
    "name:swe_x_preferred":[
        "Abala"
    ],
    "wof:name":"Abala",
    "wof:placetype":"locality"
},
  "geometry": {"coordinates":[6.62999,6.01413],"type":"Point"}
}