{
  "type": "Feature",
  "properties": {
    "gn:admin1_code":"40.0",
    "gn:asciiname":"Tungan Makeri",
    "gn:country_code":"NG",
    "gn:dem":207,
    "gn:feature_class":"P",
    "gn:feature_code":"PPL",
    "gn:name":"Tungan Makeri",
    "gn:population":0,
    "gn:timezone":"Africa/Lagos",
    "iso:country":"NG",
    "wof:name":"Tungan Makeri",
    "wof:placetype":"locality"
},
  "geometry": {"coordinates":[4.84962,10.52086],"type":"Point"}
}