{
  "type": "Feature",
  "properties": {
    "gn:admin1_code":"37.0",
    "gn:admin2_code":"12016.0",
    "gn:asciiname":"Elneye",
    "gn:country_code":"NG",
    "gn:dem":272,
    "gn:feature_class":"P",
    "gn:feature_code":"PPL",
    "gn:name":"Elneye",
    "gn:population":0,
    "gn:timezone":"Africa/Lagos",
    "iso:country":"NG",
    "wof:name":"Elneye",
    "wof:placetype":"locality"
},
  "geometry": {"coordinates":[6.141,7.0689],"type":"Point"}
}