{
  "type": "Feature",
  "properties": {
    "gn:admin1_code":"31.0",
    "gn:admin2_code":"27005",
    "gn:asciiname":"Manhapi",
    "gn:country_code":"NG",
    "gn:dem":223,
    "gn:feature_class":"P",
    "gn:feature_code":"PPL",
    "gn:name":"Manhapi",
    "gn:population":0,
    "gn:timezone":"Africa/Lagos",
    "iso:country":"NG",
    "wof:name":"Manhapi",
    "wof:placetype":"locality"
},
  "geometry": {"coordinates":[6.51811,9.56951],"type":"Point"}
}