{
  "type": "Feature",
  "properties": {
    "gn:admin1_code":"11.0",
    "gn:admin2_code":"15004.0",
    "gn:asciiname":"Zango",
    "gn:country_code":"NG",
    "gn:dem":380,
    "gn:feature_class":"P",
    "gn:feature_code":"PPL",
    "gn:name":"Zango",
    "gn:population":0,
    "gn:timezone":"Africa/Lagos",
    "iso:country":"NG",
    "wof:name":"Zango",
    "wof:placetype":"locality"
},
  "geometry": {"coordinates":[7.34583,8.81028],"type":"Point"}
}