{
  "type": "Feature",
  "properties": {
    "gn:admin1_code":"32.0",
    "gn:admin2_code":"31033.0",
    "gn:asciiname":"Oniju",
    "gn:country_code":"NG",
    "gn:dem":388,
    "gn:feature_class":"P",
    "gn:feature_code":"PPL",
    "gn:name":"Oniju",
    "gn:population":0,
    "gn:timezone":"Africa/Lagos",
    "iso:country":"NG",
    "wof:name":"Oniju",
    "wof:placetype":"locality"
},
  "geometry": {"coordinates":[4.36667,8.23333],"type":"Point"}
}