{
  "type": "Feature",
  "properties": {
    "gn:admin1_code":"40.0",
    "gn:admin2_code":"515.0",
    "gn:admin3_code":"51501",
    "gn:asciiname":"Tungan Tankara",
    "gn:country_code":"NG",
    "gn:dem":256,
    "gn:feature_class":"P",
    "gn:feature_code":"PPL",
    "gn:name":"Tungan Tankara",
    "gn:population":0,
    "gn:timezone":"Africa/Lagos",
    "iso:country":"NG",
    "wof:name":"Tungan Tankara",
    "wof:placetype":"locality"
},
  "geometry": {"coordinates":[4.94489,10.77223],"type":"Point"}
}