{
  "type": "Feature",
  "properties": {
    "gn:admin1_code":"23.0",
    "gn:admin2_code":"19021.0",
    "gn:admin3_code":"KD2101",
    "gn:asciiname":"Ungwan Dan Kande",
    "gn:country_code":"NG",
    "gn:dem":665,
    "gn:feature_class":"P",
    "gn:feature_code":"PPL",
    "gn:name":"Ungwan Dan Kande",
    "gn:population":0,
    "gn:timezone":"Africa/Lagos",
    "iso:country":"NG",
    "name:und_x_variant":[
        "Dan Kande",
        "Ungwan Dan Kande"
    ],
    "wof:name":"Ungwan Dan Kande",
    "wof:placetype":"locality"
},
  "geometry": {"coordinates":[8.14832,11.04055],"type":"Point"}
}