{
  "type": "Feature",
  "properties": {
    "gn:admin1_code":"5.0",
    "gn:admin2_code":"25018.0",
    "gn:asciiname":"Agani",
    "gn:cc2":"NG",
    "gn:country_code":"NG",
    "gn:dem":4,
    "gn:feature_class":"P",
    "gn:feature_code":"PPL",
    "gn:name":"Agani",
    "gn:population":0,
    "gn:timezone":"Africa/Lagos",
    "iso:country":"NG",
    "name:und_x_variant":[
        "Aqani",
        "Aganni",
        "Agani"
    ],
    "name:vie_x_preferred":[
        "Agani"
    ],
    "wof:name":"Agani",
    "wof:placetype":"locality"
},
  "geometry": {"coordinates":[3.35,6.48333],"type":"Point"}
}