{
  "type": "Feature",
  "properties": {
    "gn:admin1_code":"36.0",
    "gn:admin2_code":"10008.0",
    "gn:asciiname":"Alihagun",
    "gn:country_code":"NG",
    "gn:dem":160,
    "gn:feature_class":"P",
    "gn:feature_code":"PPL",
    "gn:name":"Alihagun",
    "gn:population":0,
    "gn:timezone":"Africa/Lagos",
    "iso:country":"NG",
    "name:eng_x_preferred":[
        "Alihagun"
    ],
    "name:eng_x_variant":[
        "Alihagu"
    ],
    "name:und_x_variant":[
        "Alihagu"
    ],
    "wof:name":"Alihagun",
    "wof:placetype":"locality"
},
  "geometry": {"coordinates":[6.08954,6.27634],"type":"Point"}
}