{
  "type": "Feature",
  "properties": {
    "gn:admin1_code":"43.0",
    "gn:admin2_code":"35016.0",
    "gn:asciiname":"Bidako",
    "gn:country_code":"NG",
    "gn:dem":563,
    "gn:feature_class":"P",
    "gn:feature_code":"PPL",
    "gn:name":"Bidako",
    "gn:population":0,
    "gn:timezone":"Africa/Lagos",
    "iso:country":"NG",
    "wof:name":"Bidako",
    "wof:placetype":"locality"
},
  "geometry": {"coordinates":[11.73393,8.97965],"type":"Point"}
}