{
  "type": "Feature",
  "properties": {
    "gn:admin1_code":"57.0",
    "gn:admin2_code":"813.0",
    "gn:admin3_code":"81310",
    "gn:asciiname":"Hayin Alhaji",
    "gn:country_code":"NG",
    "gn:dem":487,
    "gn:feature_class":"P",
    "gn:feature_code":"PPL",
    "gn:name":"Hayin Alhaji",
    "gn:population":0,
    "gn:timezone":"Africa/Lagos",
    "iso:country":"NG",
    "wof:name":"Hayin Alhaji",
    "wof:placetype":"locality"
},
  "geometry": {"coordinates":[7.11423,12.05981],"type":"Point"}
}