{
  "type": "Feature",
  "properties": {
    "gn:admin1_code":"53.0",
    "gn:admin2_code":"11010.0",
    "gn:asciiname":"Odareko",
    "gn:country_code":"NG",
    "gn:dem":68,
    "gn:feature_class":"P",
    "gn:feature_code":"PPL",
    "gn:name":"Odareko",
    "gn:population":0,
    "gn:timezone":"Africa/Lagos",
    "iso:country":"NG",
    "name:und_x_variant":[
        "Odariko"
    ],
    "wof:name":"Odareko",
    "wof:placetype":"locality"
},
  "geometry": {"coordinates":[8.40195,6.40261],"type":"Point"}
}