{
  "type": "Feature",
  "properties": {
    "gn:admin1_code":"21.0",
    "gn:admin2_code":"3026.0",
    "gn:asciiname":"Ekeffe",
    "gn:country_code":"NG",
    "gn:dem":21,
    "gn:feature_class":"P",
    "gn:feature_code":"PPL",
    "gn:name":"Ekeffe",
    "gn:population":0,
    "gn:timezone":"Africa/Lagos",
    "iso:country":"NG",
    "wof:name":"Ekeffe",
    "wof:placetype":"locality"
},
  "geometry": {"coordinates":[7.54726,4.77476],"type":"Point"}
}