{
  "type": "Feature",
  "properties": {
    "gn:admin1_code":"43.0",
    "gn:admin2_code":"35001.0",
    "gn:asciiname":"Nemnei",
    "gn:country_code":"NG",
    "gn:dem":136,
    "gn:feature_class":"P",
    "gn:feature_code":"PPL",
    "gn:name":"Nemnei",
    "gn:population":0,
    "gn:timezone":"Africa/Lagos",
    "iso:country":"NG",
    "name:und_x_variant":[
        "Namnai",
        "Nemnei"
    ],
    "wof:name":"Nemnei",
    "wof:placetype":"locality"
},
  "geometry": {"coordinates":[10.94843,8.76619],"type":"Point"}
}