{
  "type": "Feature",
  "properties": {
    "gn:admin1_code":"47.0",
    "gn:admin2_code":"14006.0",
    "gn:asciiname":"Akama-Oghe",
    "gn:country_code":"NG",
    "gn:dem":264,
    "gn:feature_class":"P",
    "gn:feature_code":"PPL",
    "gn:name":"Akama-Oghe",
    "gn:population":0,
    "gn:timezone":"Africa/Lagos",
    "iso:country":"NG",
    "name:und_x_variant":[
        "Akama-Oye"
    ],
    "wof:name":"Akama-Oghe",
    "wof:placetype":"locality"
},
  "geometry": {"coordinates":[7.31826,6.44223],"type":"Point"}
}