{
  "type": "Feature",
  "properties": {
    "gn:admin1_code":"26.0",
    "gn:admin2_code":"7007",
    "gn:asciiname":"Yeva",
    "gn:country_code":"NG",
    "gn:dem":150,
    "gn:feature_class":"P",
    "gn:feature_code":"PPL",
    "gn:name":"Yeva",
    "gn:population":0,
    "gn:timezone":"Africa/Lagos",
    "iso:country":"NG",
    "name:fas_x_preferred":[
        "\u06cc\u0647\u200c\u0648\u0627"
    ],
    "name:hye_x_preferred":[
        "\u0535\u057e\u0561"
    ],
    "name:por_x_preferred":[
        "Yeva"
    ],
    "name:tur_x_preferred":[
        "Yeva"
    ],
    "wof:name":"Yeva",
    "wof:placetype":"locality"
},
  "geometry": {"coordinates":[8.39969,7.24126],"type":"Point"}
}