{
  "type": "Feature",
  "properties": {
    "gn:admin1_code":"27.0",
    "gn:admin2_code":"117",
    "gn:admin3_code":"11706",
    "gn:asciiname":"Tanbun Masarram",
    "gn:country_code":"NG",
    "gn:dem":280,
    "gn:feature_class":"P",
    "gn:feature_code":"PPL",
    "gn:name":"Tanbun Masarram",
    "gn:population":0,
    "gn:timezone":"Africa/Lagos",
    "iso:country":"NG",
    "wof:name":"Tanbun Masarram",
    "wof:placetype":"locality"
},
  "geometry": {"coordinates":[13.89694,13.30127],"type":"Point"}
}