{
  "type": "Feature",
  "properties": {
    "gn:admin1_code":"29.0",
    "gn:admin2_code":"20041.0",
    "gn:admin3_code":"KN2203",
    "gn:asciiname":"Tunfafi",
    "gn:country_code":"NG",
    "gn:dem":529,
    "gn:feature_class":"P",
    "gn:feature_code":"PPL",
    "gn:name":"Tunfafi",
    "gn:population":0,
    "gn:timezone":"Africa/Lagos",
    "iso:country":"NG",
    "wof:name":"Tunfafi",
    "wof:placetype":"locality"
},
  "geometry": {"coordinates":[8.02221,11.82845],"type":"Point"}
}