{
  "type": "Feature",
  "properties": {
    "gn:admin1_code":"5.0",
    "gn:admin2_code":"25012.0",
    "gn:asciiname":"Oke-Lisa",
    "gn:country_code":"NG",
    "gn:dem":11,
    "gn:feature_class":"P",
    "gn:feature_code":"PPL",
    "gn:name":"Oke-Lisa",
    "gn:population":0,
    "gn:timezone":"Africa/Lagos",
    "iso:country":"NG",
    "name:und_x_variant":[
        "Oke Odo",
        "Oke-Lisa"
    ],
    "wof:name":"Oke-Lisa",
    "wof:placetype":"locality"
},
  "geometry": {"coordinates":[3.66026,6.59789],"type":"Point"}
}