{
  "type": "Feature",
  "properties": {
    "gn:admin1_code":"57.0",
    "gn:admin2_code":"807.0",
    "gn:admin3_code":"80709",
    "gn:asciiname":"Guidan Goje",
    "gn:country_code":"NG",
    "gn:dem":486,
    "gn:feature_class":"P",
    "gn:feature_code":"PPL",
    "gn:name":"Guidan Goje",
    "gn:population":0,
    "gn:timezone":"Africa/Lagos",
    "iso:country":"NG",
    "name:und_x_variant":[
        "Gidan Goje",
        "Guidan Goje"
    ],
    "wof:name":"Guidan Goje",
    "wof:placetype":"locality"
},
  "geometry": {"coordinates":[6.76528,12.10394],"type":"Point"}
}