{
  "type": "Feature",
  "properties": {
    "gn:admin1_code":"27.0",
    "gn:admin2_code":"119.0",
    "gn:admin3_code":"11902",
    "gn:asciiname":"Kofe",
    "gn:country_code":"NG",
    "gn:dem":303,
    "gn:feature_class":"P",
    "gn:feature_code":"PPL",
    "gn:name":"Kofe",
    "gn:population":0,
    "gn:timezone":"Africa/Lagos",
    "iso:country":"NG",
    "name:und_x_variant":[
        "Kobe",
        "Kofe"
    ],
    "wof:name":"Kofe",
    "wof:placetype":"locality"
},
  "geometry": {"coordinates":[13.82454,11.8515],"type":"Point"}
}