{
  "type": "Feature",
  "properties": {
    "gn:admin1_code":"40.0",
    "gn:admin2_code":"505.0",
    "gn:admin3_code":"50511",
    "gn:asciiname":"Kwasara",
    "gn:country_code":"NG",
    "gn:dem":170,
    "gn:feature_class":"P",
    "gn:feature_code":"PPL",
    "gn:name":"Kwasara",
    "gn:population":0,
    "gn:timezone":"Africa/Lagos",
    "iso:country":"NG",
    "wof:name":"Kwasara",
    "wof:placetype":"locality"
},
  "geometry": {"coordinates":[4.13983,11.52661],"type":"Point"}
}