{
  "type": "Feature",
  "properties": {
    "gn:admin1_code":"46.0",
    "gn:admin2_code":"5001.0",
    "gn:admin3_code":"BA0102",
    "gn:asciiname":"Dagarau",
    "gn:country_code":"NG",
    "gn:dem":367,
    "gn:feature_class":"P",
    "gn:feature_code":"PPL",
    "gn:name":"Dagarau",
    "gn:population":0,
    "gn:timezone":"Africa/Lagos",
    "iso:country":"NG",
    "name:eng_x_preferred":[
        "Dagarau"
    ],
    "wof:name":"Dagarau",
    "wof:placetype":"locality"
},
  "geometry": {"coordinates":[10.56722,10.20836],"type":"Point"}
}