{
  "type": "Feature",
  "properties": {
    "gn:admin1_code":"35.0",
    "gn:asciiname":"Ndikajam",
    "gn:country_code":"NG",
    "gn:dem":151,
    "gn:feature_class":"P",
    "gn:feature_code":"PPL",
    "gn:name":"Ndikajam",
    "gn:population":0,
    "gn:timezone":"Africa/Lagos",
    "iso:country":"NG",
    "name:eng_x_preferred":[
        "Ndikajam"
    ],
    "wof:name":"Ndikajam",
    "wof:placetype":"locality"
},
  "geometry": {"coordinates":[12.33461,9.46043],"type":"Point"}
}