{
  "type": "Feature",
  "properties": {
    "gn:admin1_code":"31.0",
    "gn:admin2_code":"27001.0",
    "gn:asciiname":"Tudun Wada",
    "gn:country_code":"NG",
    "gn:dem":191,
    "gn:feature_class":"P",
    "gn:feature_code":"PPL",
    "gn:name":"Tudun Wada",
    "gn:population":0,
    "gn:timezone":"Africa/Lagos",
    "iso:country":"NG",
    "wof:name":"Tudun Wada",
    "wof:placetype":"locality"
},
  "geometry": {"coordinates":[6.56264,9.07951],"type":"Point"}
}