{
  "type": "Feature",
  "properties": {
    "gn:admin1_code":"29.0",
    "gn:admin2_code":"20005.0",
    "gn:admin3_code":"KN3306",
    "gn:asciiname":"Juli",
    "gn:country_code":"NG",
    "gn:dem":483,
    "gn:feature_class":"P",
    "gn:feature_code":"PPL",
    "gn:name":"Juli",
    "gn:population":0,
    "gn:timezone":"Africa/Lagos",
    "iso:country":"NG",
    "name:als_x_preferred":[
        "Juli"
    ],
    "name:bar_x_preferred":[
        "Juli"
    ],
    "name:ceb_x_preferred":[
        "Juli"
    ],
    "name:deu_x_preferred":[
        "Juli"
    ],
    "name:fra_x_preferred":[
        "Juli"
    ],
    "name:ita_x_preferred":[
        "Juli"
    ],
    "name:jpn_x_preferred":[
        "\u30e6\u30fc\u30ea"
    ],
    "name:nld_x_preferred":[
        "Juli"
    ],
    "name:spa_x_preferred":[
        "Juli"
    ],
    "name:swe_x_preferred":[
        "Juli"
    ],
    "wof:name":"Juli",
    "wof:placetype":"locality"
},
  "geometry": {"coordinates":[8.2948,11.89313],"type":"Point"}
}