{
  "type": "Feature",
  "properties": {
    "gn:admin1_code":"26.0",
    "gn:admin2_code":"7023.0",
    "gn:asciiname":"Otegbo",
    "gn:country_code":"NG",
    "gn:dem":135,
    "gn:feature_class":"P",
    "gn:feature_code":"PPL",
    "gn:name":"Otegbo",
    "gn:population":0,
    "gn:timezone":"Africa/Lagos",
    "iso:country":"NG",
    "wof:name":"Otegbo",
    "wof:placetype":"locality"
},
  "geometry": {"coordinates":[8.99527,6.7099],"type":"Point"}
}