{
  "type": "Feature",
  "properties": {
    "gn:admin1_code":"36.0",
    "gn:admin2_code":"10023.0",
    "gn:asciiname":"Ogbabin",
    "gn:country_code":"NG",
    "gn:dem":16,
    "gn:feature_class":"P",
    "gn:feature_code":"PPL",
    "gn:name":"Ogbabin",
    "gn:population":0,
    "gn:timezone":"Africa/Lagos",
    "iso:country":"NG",
    "wof:name":"Ogbabin",
    "wof:placetype":"locality"
},
  "geometry": {"coordinates":[5.14156,6.04884],"type":"Point"}
}