{
  "type": "Feature",
  "properties": {
    "gn:admin1_code":"27.0",
    "gn:admin2_code":"115.0",
    "gn:admin3_code":"11510",
    "gn:asciiname":"Tilam",
    "gn:country_code":"NG",
    "gn:dem":296,
    "gn:feature_class":"P",
    "gn:feature_code":"PPL",
    "gn:name":"Tilam",
    "gn:population":0,
    "gn:timezone":"Africa/Lagos",
    "iso:country":"NG",
    "name:fas_x_preferred":[
        "\u062a\u06cc\u0644\u0645"
    ],
    "name:und_x_variant":[
        "Telam",
        "Tilam"
    ],
    "wof:name":"Tilam",
    "wof:placetype":"locality"
},
  "geometry": {"coordinates":[14.43079,12.29671],"type":"Point"}
}