{
  "type": "Feature",
  "properties": {
    "gn:admin1_code":"24.0",
    "gn:admin2_code":"404.0",
    "gn:admin3_code":"40408",
    "gn:asciiname":"Baushi",
    "gn:country_code":"NG",
    "gn:dem":399,
    "gn:feature_class":"P",
    "gn:feature_code":"PPL",
    "gn:name":"Baushi",
    "gn:population":0,
    "gn:timezone":"Africa/Lagos",
    "iso:country":"NG",
    "wof:name":"Baushi",
    "wof:placetype":"locality"
},
  "geometry": {"coordinates":[8.78327,12.76098],"type":"Point"}
}