{
  "type": "Feature",
  "properties": {
    "gn:admin1_code":"5.0",
    "gn:admin2_code":"25005.0",
    "gn:asciiname":"Dankaka",
    "gn:country_code":"NG",
    "gn:dem":0,
    "gn:feature_class":"P",
    "gn:feature_code":"PPL",
    "gn:name":"Dankaka",
    "gn:population":0,
    "gn:timezone":"Africa/Lagos",
    "iso:country":"NG",
    "wof:name":"Dankaka",
    "wof:placetype":"locality"
},
  "geometry": {"coordinates":[3.33333,6.43333],"type":"Point"}
}