{
  "type": "Feature",
  "properties": {
    "iso:country":"NG",
    "name:cat_x_preferred":[
        "Kwali"
    ],
    "name:eng_x_preferred":[
        "Kwali"
    ],
    "name:fra_x_preferred":[
        "Kwali"
    ],
    "name:nld_x_preferred":[
        "Kwali"
    ],
    "name:por_x_preferred":[
        "Kwali"
    ],
    "qs:gn_country":"NG",
    "qs:gn_fcode":"PPL",
    "qs:gn_pop":6229,
    "qs:name":"Kwali",
    "qs:name_adm0":"Nigeria",
    "qs:name_adm1":"Federal Capital Territory",
    "qs:photos":0,
    "qs:photos_1k":0,
    "qs:photos_9k":0,
    "qs:photos_9r":0,
    "qs:photos_all":0,
    "qs:photos_sr":0,
    "qs:placetype":"Town",
    "qs:pop_sr":"5",
    "qs:woe_adm0":23424908,
    "wof:name":"Kwali",
    "wof:placetype":"locality",
    "wof:population":6229
},
  "geometry": {"coordinates":[7.005,8.86722],"type":"Point"}
}