{
  "type": "Feature",
  "properties": {
    "gn:admin1_code":"51.0",
    "gn:admin2_code":"611.0",
    "gn:admin3_code":"61109",
    "gn:asciiname":"Gidan Karma",
    "gn:country_code":"NG",
    "gn:dem":268,
    "gn:feature_class":"P",
    "gn:feature_code":"PPL",
    "gn:name":"Gidan Karma",
    "gn:population":0,
    "gn:timezone":"Africa/Lagos",
    "iso:country":"NG",
    "wof:name":"Gidan Karma",
    "wof:placetype":"locality"
},
  "geometry": {"coordinates":[5.21102,13.31582],"type":"Point"}
}