{
  "type": "Feature",
  "properties": {
    "gn:admin1_code":"40.0",
    "gn:admin2_code":"511.0",
    "gn:admin3_code":"51110",
    "gn:asciiname":"Fagada",
    "gn:country_code":"NG",
    "gn:dem":218,
    "gn:feature_class":"P",
    "gn:feature_code":"PPL",
    "gn:name":"Fagada",
    "gn:population":0,
    "gn:timezone":"Africa/Lagos",
    "iso:country":"NG",
    "name:und_x_variant":[
        "Gwarazo",
        "Fagada"
    ],
    "wof:name":"Fagada",
    "wof:placetype":"locality"
},
  "geometry": {"coordinates":[4.45931,12.08932],"type":"Point"}
}