{
  "type": "Feature",
  "properties": {
    "gn:admin1_code":"23.0",
    "gn:admin2_code":"19022",
    "gn:admin3_code":"KD2210",
    "gn:asciiname":"Ramai Gida",
    "gn:country_code":"NG",
    "gn:dem":872,
    "gn:feature_class":"P",
    "gn:feature_code":"PPL",
    "gn:name":"Ramai Gida",
    "gn:population":0,
    "gn:timezone":"Africa/Lagos",
    "iso:country":"NG",
    "wof:name":"Ramai Gida",
    "wof:placetype":"locality"
},
  "geometry": {"coordinates":[8.28049,9.76428],"type":"Point"}
}