{
  "type": "Feature",
  "properties": {
    "gn:admin1_code":"29.0",
    "gn:admin2_code":"20016.0",
    "gn:admin3_code":"KN1301",
    "gn:asciiname":"Dadin Duniya",
    "gn:country_code":"NG",
    "gn:dem":419,
    "gn:feature_class":"P",
    "gn:feature_code":"PPL",
    "gn:name":"Dadin Duniya",
    "gn:population":0,
    "gn:timezone":"Africa/Lagos",
    "iso:country":"NG",
    "wof:name":"Dadin Duniya",
    "wof:placetype":"locality"
},
  "geometry": {"coordinates":[8.89295,12.16037],"type":"Point"}
}