{
  "type": "Feature",
  "properties": {
    "gn:admin1_code":"26.0",
    "gn:admin2_code":"7022.0",
    "gn:asciiname":"Gwa",
    "gn:country_code":"NG",
    "gn:dem":182,
    "gn:feature_class":"P",
    "gn:feature_code":"PPL",
    "gn:name":"Gwa",
    "gn:population":0,
    "gn:timezone":"Africa/Lagos",
    "iso:country":"NG",
    "name:und_x_variant":[
        "Kua"
    ],
    "wof:name":"Gwa",
    "wof:placetype":"locality"
},
  "geometry": {"coordinates":[8.96078,7.25975],"type":"Point"}
}