{
  "type": "Feature",
  "properties": {
    "gn:admin1_code":"36.0",
    "gn:admin2_code":"10014.0",
    "gn:asciiname":"Anikoko",
    "gn:country_code":"NG",
    "gn:dem":171,
    "gn:feature_class":"P",
    "gn:feature_code":"PPL",
    "gn:name":"Anikoko",
    "gn:population":0,
    "gn:timezone":"Africa/Lagos",
    "iso:country":"NG",
    "name:eng_x_preferred":[
        "Anikoko"
    ],
    "wof:name":"Anikoko",
    "wof:placetype":"locality"
},
  "geometry": {"coordinates":[6.62086,6.33638],"type":"Point"}
}