{
  "type": "Feature",
  "properties": {
    "gn:admin1_code":"51.0",
    "gn:admin2_code":"611.0",
    "gn:admin3_code":"61108",
    "gn:asciiname":"Dabage",
    "gn:country_code":"NG",
    "gn:dem":265,
    "gn:feature_class":"P",
    "gn:feature_code":"PPL",
    "gn:name":"Dabage",
    "gn:population":0,
    "gn:timezone":"Africa/Lagos",
    "iso:country":"NG",
    "wof:name":"Dabage",
    "wof:placetype":"locality"
},
  "geometry": {"coordinates":[5.27948,13.09861],"type":"Point"}
}