{
  "type": "Feature",
  "properties": {
    "gn:admin1_code":"22.0",
    "gn:admin2_code":"9016.0",
    "gn:asciiname":"Ukpe",
    "gn:country_code":"NG",
    "gn:dem":102,
    "gn:feature_class":"P",
    "gn:feature_code":"PPL",
    "gn:name":"Ukpe",
    "gn:population":0,
    "gn:timezone":"Africa/Lagos",
    "iso:country":"NG",
    "wof:name":"Ukpe",
    "wof:placetype":"locality"
},
  "geometry": {"coordinates":[8.76346,6.54059],"type":"Point"}
}