{
  "type": "Feature",
  "properties": {
    "gn:admin1_code":"43.0",
    "gn:admin2_code":"35002.0",
    "gn:asciiname":"Tafida Gwani",
    "gn:country_code":"NG",
    "gn:dem":208,
    "gn:feature_class":"P",
    "gn:feature_code":"PPL",
    "gn:name":"Tafida Gwani",
    "gn:population":0,
    "gn:timezone":"Africa/Lagos",
    "iso:country":"NG",
    "wof:name":"Tafida Gwani",
    "wof:placetype":"locality"
},
  "geometry": {"coordinates":[11.11667,8.23333],"type":"Point"}
}