{
  "type": "Feature",
  "properties": {
    "gn:admin1_code":"16.0",
    "gn:admin2_code":"28006.0",
    "gn:asciiname":"Isoku",
    "gn:country_code":"NG",
    "gn:dem":37,
    "gn:feature_class":"P",
    "gn:feature_code":"PPL",
    "gn:name":"Isoku",
    "gn:population":0,
    "gn:timezone":"Africa/Lagos",
    "iso:country":"NG",
    "name:und_x_variant":[
        "Ishoku",
        "Isoku"
    ],
    "wof:name":"Isoku",
    "wof:placetype":"locality"
},
  "geometry": {"coordinates":[3.29044,6.90796],"type":"Point"}
}