{
  "type": "Feature",
  "properties": {
    "gn:admin1_code":"27.0",
    "gn:admin2_code":"103.0",
    "gn:admin3_code":"10308",
    "gn:asciiname":"Kungare",
    "gn:country_code":"NG",
    "gn:dem":337,
    "gn:feature_class":"P",
    "gn:feature_code":"PPL",
    "gn:name":"Kungare",
    "gn:population":0,
    "gn:timezone":"Africa/Lagos",
    "iso:country":"NG",
    "wof:name":"Kungare",
    "wof:placetype":"locality"
},
  "geometry": {"coordinates":[13.56217,11.50178],"type":"Point"}
}