{
  "type": "Feature",
  "properties": {
    "gn:admin1_code":"49.0",
    "gn:admin2_code":"32007.0",
    "gn:asciiname":"Gogdi",
    "gn:country_code":"NG",
    "gn:dem":708,
    "gn:feature_class":"P",
    "gn:feature_code":"PPL",
    "gn:name":"Gogdi",
    "gn:population":0,
    "gn:timezone":"Africa/Lagos",
    "iso:country":"NG",
    "wof:name":"Gogdi",
    "wof:placetype":"locality"
},
  "geometry": {"coordinates":[10.03333,9.66667],"type":"Point"}
}