{
  "type": "Feature",
  "properties": {
    "gn:admin1_code":"35.0",
    "gn:asciiname":"Ruga Fulani",
    "gn:country_code":"NG",
    "gn:dem":218,
    "gn:feature_class":"P",
    "gn:feature_code":"PPL",
    "gn:name":"Ruga Fulani",
    "gn:population":0,
    "gn:timezone":"Africa/Lagos",
    "iso:country":"NG",
    "name:eng_x_preferred":[
        "Ruga Fulani"
    ],
    "wof:name":"Ruga Fulani",
    "wof:placetype":"locality"
},
  "geometry": {"coordinates":[12.01405,9.25242],"type":"Point"}
}