{
  "type": "Feature",
  "properties": {
    "gn:admin1_code":"27.0",
    "gn:admin2_code":"114",
    "gn:admin3_code":"11415",
    "gn:asciiname":"Labamiri",
    "gn:country_code":"NG",
    "gn:dem":384,
    "gn:feature_class":"P",
    "gn:feature_code":"PPL",
    "gn:name":"Labamiri",
    "gn:population":0,
    "gn:timezone":"Africa/Lagos",
    "iso:country":"NG",
    "wof:name":"Labamiri",
    "wof:placetype":"locality"
},
  "geometry": {"coordinates":[12.38631,11.69412],"type":"Point"}
}