{
  "type": "Feature",
  "properties": {
    "gn:admin1_code":"26.0",
    "gn:admin2_code":"7019",
    "gn:asciiname":"Ijar",
    "gn:country_code":"NG",
    "gn:dem":103,
    "gn:feature_class":"P",
    "gn:feature_code":"PPL",
    "gn:name":"Ijar",
    "gn:population":0,
    "gn:timezone":"Africa/Lagos",
    "iso:country":"NG",
    "wof:name":"Ijar",
    "wof:placetype":"locality"
},
  "geometry": {"coordinates":[8.2181,7.16333],"type":"Point"}
}