{
  "type": "Feature",
  "properties": {
    "gn:admin1_code":"26.0",
    "gn:admin2_code":"7006.0",
    "gn:asciiname":"Camp",
    "gn:country_code":"NG",
    "gn:dem":129,
    "gn:feature_class":"P",
    "gn:feature_code":"PPL",
    "gn:name":"Camp",
    "gn:population":0,
    "gn:timezone":"Africa/Lagos",
    "iso:country":"NG",
    "wof:name":"Camp",
    "wof:placetype":"locality"
},
  "geometry": {"coordinates":[8.4871,7.89934],"type":"Point"}
}