{
  "type": "Feature",
  "properties": {
    "gn:admin1_code":"31.0",
    "gn:admin2_code":"27008",
    "gn:asciiname":"Kusotukpa",
    "gn:country_code":"NG",
    "gn:dem":106,
    "gn:feature_class":"P",
    "gn:feature_code":"PPL",
    "gn:name":"Kusotukpa",
    "gn:population":0,
    "gn:timezone":"Africa/Lagos",
    "iso:country":"NG",
    "wof:name":"Kusotukpa",
    "wof:placetype":"locality"
},
  "geometry": {"coordinates":[5.88795,9.21883],"type":"Point"}
}