{
  "type": "Feature",
  "properties": {
    "gn:admin1_code":"39.0",
    "gn:admin2_code":"18020.0",
    "gn:admin3_code":"JI2308",
    "gn:asciiname":"Gabarun",
    "gn:country_code":"NG",
    "gn:dem":390,
    "gn:feature_class":"P",
    "gn:feature_code":"PPL",
    "gn:name":"Gabarun",
    "gn:population":0,
    "gn:timezone":"Africa/Lagos",
    "iso:country":"NG",
    "wof:name":"Gabarun",
    "wof:placetype":"locality"
},
  "geometry": {"coordinates":[9.15564,12.09577],"type":"Point"}
}