{
  "type": "Feature",
  "properties": {
    "gn:admin1_code":"53.0",
    "gn:admin2_code":"11012.0",
    "gn:asciiname":"Odomoke",
    "gn:country_code":"NG",
    "gn:dem":90,
    "gn:feature_class":"P",
    "gn:feature_code":"PPL",
    "gn:name":"Odomoke",
    "gn:population":0,
    "gn:timezone":"Africa/Lagos",
    "iso:country":"NG",
    "wof:name":"Odomoke",
    "wof:placetype":"locality"
},
  "geometry": {"coordinates":[8.06129,6.48851],"type":"Point"}
}