{
  "type": "Feature",
  "properties": {
    "gn:admin1_code":"35.0",
    "gn:asciiname":"Labbare",
    "gn:country_code":"NG",
    "gn:dem":247,
    "gn:feature_class":"P",
    "gn:feature_code":"PPL",
    "gn:name":"Labbare",
    "gn:population":0,
    "gn:timezone":"Africa/Lagos",
    "iso:country":"NG",
    "name:eng_x_preferred":[
        "Labbare"
    ],
    "wof:name":"Labbare",
    "wof:placetype":"locality"
},
  "geometry": {"coordinates":[12.05357,9.1363],"type":"Point"}
}