{
  "type": "Feature",
  "properties": {
    "gn:admin1_code":"49.0",
    "gn:admin2_code":"32017",
    "gn:asciiname":"Nahuta",
    "gn:country_code":"NG",
    "gn:dem":184,
    "gn:feature_class":"P",
    "gn:feature_code":"PPL",
    "gn:name":"Nahuta",
    "gn:population":0,
    "gn:timezone":"Africa/Lagos",
    "iso:country":"NG",
    "wof:name":"Nahuta",
    "wof:placetype":"locality"
},
  "geometry": {"coordinates":[9.90069,8.82118],"type":"Point"}
}