{
  "type": "Feature",
  "properties": {
    "gn:admin1_code":"51.0",
    "gn:admin2_code":"621.0",
    "gn:admin3_code":"62106",
    "gn:asciiname":"Gidan Ali",
    "gn:country_code":"NG",
    "gn:dem":267,
    "gn:feature_class":"P",
    "gn:feature_code":"PPL",
    "gn:name":"Gidan Ali",
    "gn:population":0,
    "gn:timezone":"Africa/Lagos",
    "iso:country":"NG",
    "wof:name":"Gidan Ali",
    "wof:placetype":"locality"
},
  "geometry": {"coordinates":[5.15446,13.00169],"type":"Point"}
}