{
  "type": "Feature",
  "properties": {
    "gn:admin1_code":"48.0",
    "gn:asciiname":"Ago-Sasere",
    "gn:country_code":"NG",
    "gn:dem":350,
    "gn:feature_class":"P",
    "gn:feature_code":"PPL",
    "gn:name":"Ago-Sasere",
    "gn:population":0,
    "gn:timezone":"Africa/Lagos",
    "iso:country":"NG",
    "wof:name":"Ago-Sasere",
    "wof:placetype":"locality"
},
  "geometry": {"coordinates":[5.4513,7.3349],"type":"Point"}
}