{
  "type": "Feature",
  "properties": {
    "gn:admin1_code":"26.0",
    "gn:admin2_code":"7022",
    "gn:asciiname":"Orga",
    "gn:country_code":"NG",
    "gn:dem":199,
    "gn:feature_class":"P",
    "gn:feature_code":"PPL",
    "gn:name":"Orga",
    "gn:population":0,
    "gn:timezone":"Africa/Lagos",
    "iso:country":"NG",
    "name:spa_x_preferred":[
        "Orga"
    ],
    "name:swe_x_preferred":[
        "Orga"
    ],
    "name:zho_x_preferred":[
        "\u6b50\u9b6f\u5361"
    ],
    "wof:name":"Orga",
    "wof:placetype":"locality"
},
  "geometry": {"coordinates":[9.02885,7.15465],"type":"Point"}
}