{
  "type": "Feature",
  "properties": {
    "gn:admin1_code":"21.0",
    "gn:admin2_code":"3012.0",
    "gn:asciiname":"Ekwuot-Edem-Edet",
    "gn:country_code":"NG",
    "gn:dem":127,
    "gn:feature_class":"P",
    "gn:feature_code":"PPL",
    "gn:name":"Ekwuot-Edem-Edet",
    "gn:population":0,
    "gn:timezone":"Africa/Lagos",
    "iso:country":"NG",
    "wof:name":"Ekwuot-Edem-Edet",
    "wof:placetype":"locality"
},
  "geometry": {"coordinates":[7.75561,5.27812],"type":"Point"}
}