{
  "type": "Feature",
  "properties": {
    "gn:admin1_code":"24.0",
    "gn:admin2_code":"434.0",
    "gn:admin3_code":"43408",
    "gn:asciiname":"Malawa",
    "gn:country_code":"NG",
    "gn:dem":470,
    "gn:feature_class":"P",
    "gn:feature_code":"PPL",
    "gn:name":"Malawa",
    "gn:population":0,
    "gn:timezone":"Africa/Lagos",
    "iso:country":"NG",
    "name:ceb_x_preferred":[
        "Malawa"
    ],
    "name:deu_x_preferred":[
        "Malawa"
    ],
    "name:pol_x_preferred":[
        "Malawa"
    ],
    "name:swe_x_preferred":[
        "Malawa"
    ],
    "name:ukr_x_preferred":[
        "\u041c\u0430\u043b\u044f\u0432\u0430"
    ],
    "wof:name":"Malawa",
    "wof:placetype":"locality"
},
  "geometry": {"coordinates":[8.51711,12.99193],"type":"Point"}
}