{
  "type": "Feature",
  "properties": {
    "gn:admin1_code":"23.0",
    "gn:admin2_code":"19007",
    "gn:admin3_code":"KD0710",
    "gn:asciiname":"Ungwan Rana",
    "gn:country_code":"NG",
    "gn:dem":738,
    "gn:feature_class":"P",
    "gn:feature_code":"PPL",
    "gn:name":"Ungwan Rana",
    "gn:population":0,
    "gn:timezone":"Africa/Lagos",
    "iso:country":"NG",
    "wof:name":"Ungwan Rana",
    "wof:placetype":"locality"
},
  "geometry": {"coordinates":[8.28304,9.56292],"type":"Point"}
}