{
  "type": "Feature",
  "properties": {
    "gn:admin1_code":"27.0",
    "gn:admin2_code":"102.0",
    "gn:admin3_code":"10213",
    "gn:asciiname":"Kohuma",
    "gn:country_code":"NG",
    "gn:dem":502,
    "gn:feature_class":"P",
    "gn:feature_code":"PPL",
    "gn:name":"Kohuma",
    "gn:population":0,
    "gn:timezone":"Africa/Lagos",
    "iso:country":"NG",
    "wof:name":"Kohuma",
    "wof:placetype":"locality"
},
  "geometry": {"coordinates":[13.17214,10.54181],"type":"Point"}
}