{
  "type": "Feature",
  "properties": {
    "gn:admin1_code":"23.0",
    "gn:asciiname":"Unguwar Turai",
    "gn:country_code":"NG",
    "gn:dem":755,
    "gn:feature_class":"P",
    "gn:feature_code":"PPL",
    "gn:name":"Unguwar Turai",
    "gn:population":0,
    "gn:timezone":"Africa/Lagos",
    "iso:country":"NG",
    "name:und_x_variant":[
        "Turai",
        "Unguwar Turai"
    ],
    "wof:name":"Unguwar Turai",
    "wof:placetype":"locality"
},
  "geometry": {"coordinates":[8.61067,10.70877],"type":"Point"}
}