{
  "type": "Feature",
  "properties": {
    "gn:admin1_code":"24.0",
    "gn:admin2_code":"432.0",
    "gn:admin3_code":"43207",
    "gn:asciiname":"Mejora",
    "gn:country_code":"NG",
    "gn:dem":500,
    "gn:feature_class":"P",
    "gn:feature_code":"PPL",
    "gn:name":"Mejora",
    "gn:population":0,
    "gn:timezone":"Africa/Lagos",
    "iso:country":"NG",
    "wof:name":"Mejora",
    "wof:placetype":"locality"
},
  "geometry": {"coordinates":[7.35782,12.36172],"type":"Point"}
}