{
  "type": "Feature",
  "properties": {
    "gn:admin1_code":"31.0",
    "gn:admin2_code":"27005",
    "gn:asciiname":"Sharipata",
    "gn:country_code":"NG",
    "gn:dem":351,
    "gn:feature_class":"P",
    "gn:feature_code":"PPL",
    "gn:name":"Sharipata",
    "gn:population":0,
    "gn:timezone":"Africa/Lagos",
    "iso:country":"NG",
    "wof:name":"Sharipata",
    "wof:placetype":"locality"
},
  "geometry": {"coordinates":[6.55757,9.66634],"type":"Point"}
}