{
  "type": "Feature",
  "properties": {
    "gn:admin1_code":"45.0",
    "gn:admin2_code":"1011.0",
    "gn:asciiname":"Mgboko",
    "gn:country_code":"NG",
    "gn:dem":74,
    "gn:feature_class":"P",
    "gn:feature_code":"PPL",
    "gn:name":"Mgboko",
    "gn:population":0,
    "gn:timezone":"Africa/Lagos",
    "iso:country":"NG",
    "name:und_x_variant":[
        "Mboko Umuete",
        "Mboko"
    ],
    "wof:name":"Mgboko",
    "wof:placetype":"locality"
},
  "geometry": {"coordinates":[7.35862,5.16955],"type":"Point"}
}