{
  "type": "Feature",
  "properties": {
    "gn:admin1_code":"39.0",
    "gn:admin2_code":"18024.0",
    "gn:admin3_code":"JI0807",
    "gn:asciiname":"Kafin Kaya",
    "gn:country_code":"NG",
    "gn:dem":377,
    "gn:feature_class":"P",
    "gn:feature_code":"PPL",
    "gn:name":"Kafin Kaya",
    "gn:population":0,
    "gn:timezone":"Africa/Lagos",
    "iso:country":"NG",
    "wof:name":"Kafin Kaya",
    "wof:placetype":"locality"
},
  "geometry": {"coordinates":[9.17076,12.48567],"type":"Point"}
}