{
  "type": "Feature",
  "properties": {
    "gn:admin1_code":"27.0",
    "gn:admin2_code":"112.0",
    "gn:admin3_code":"11206",
    "gn:asciiname":"Babalwada",
    "gn:country_code":"NG",
    "gn:dem":453,
    "gn:feature_class":"P",
    "gn:feature_code":"PPL",
    "gn:name":"Babalwada",
    "gn:population":0,
    "gn:timezone":"Africa/Lagos",
    "iso:country":"NG",
    "wof:name":"Babalwada",
    "wof:placetype":"locality"
},
  "geometry": {"coordinates":[12.50099,10.62024],"type":"Point"}
}