{
  "type": "Feature",
  "properties": {
    "gn:admin1_code":"24.0",
    "gn:admin2_code":"413.0",
    "gn:admin3_code":"41307",
    "gn:asciiname":"Alikeai",
    "gn:country_code":"NG",
    "gn:dem":670,
    "gn:feature_class":"P",
    "gn:feature_code":"PPL",
    "gn:name":"Alikeai",
    "gn:population":0,
    "gn:timezone":"Africa/Lagos",
    "iso:country":"NG",
    "wof:name":"Alikeai",
    "wof:placetype":"locality"
},
  "geometry": {"coordinates":[7.09905,11.77805],"type":"Point"}
}