{
  "type": "Feature",
  "properties": {
    "gn:admin1_code":"39.0",
    "gn:admin2_code":"18004.0",
    "gn:admin3_code":"JI0208",
    "gn:asciiname":"Sabon Naira",
    "gn:country_code":"NG",
    "gn:dem":403,
    "gn:feature_class":"P",
    "gn:feature_code":"PPL",
    "gn:name":"Sabon Naira",
    "gn:population":0,
    "gn:timezone":"Africa/Lagos",
    "iso:country":"NG",
    "wof:name":"Sabon Naira",
    "wof:placetype":"locality"
},
  "geometry": {"coordinates":[8.79541,12.43673],"type":"Point"}
}