{
  "type": "Feature",
  "properties": {
    "gn:admin1_code":"22.0",
    "gn:admin2_code":"9015.0",
    "gn:asciiname":"Urua Etak Uyo",
    "gn:country_code":"NG",
    "gn:dem":87,
    "gn:feature_class":"P",
    "gn:feature_code":"PPL",
    "gn:name":"Urua Etak Uyo",
    "gn:population":0,
    "gn:timezone":"Africa/Lagos",
    "iso:country":"NG",
    "wof:name":"Urua Etak Uyo",
    "wof:placetype":"locality"
},
  "geometry": {"coordinates":[8.21509,5.07667],"type":"Point"}
}