{
  "type": "Feature",
  "properties": {
    "gn:admin1_code":"35.0",
    "gn:admin2_code":"2007.0",
    "gn:asciiname":"Fafaponja",
    "gn:country_code":"NG",
    "gn:dem":480,
    "gn:feature_class":"P",
    "gn:feature_code":"PPL",
    "gn:name":"Fafaponja",
    "gn:population":0,
    "gn:timezone":"Africa/Lagos",
    "iso:country":"NG",
    "wof:name":"Fafaponja",
    "wof:placetype":"locality"
},
  "geometry": {"coordinates":[12.79265,10.44908],"type":"Point"}
}