{
  "type": "Feature",
  "properties": {
    "gn:admin1_code":"35.0",
    "gn:asciiname":"Wuro Bokki Dakusun",
    "gn:country_code":"NG",
    "gn:dem":283,
    "gn:feature_class":"P",
    "gn:feature_code":"PPL",
    "gn:name":"Wuro Bokki Dakusun",
    "gn:population":0,
    "gn:timezone":"Africa/Lagos",
    "iso:country":"NG",
    "name:eng_x_preferred":[
        "Wuro Bokki Dakusun"
    ],
    "wof:name":"Wuro Bokki Dakusun",
    "wof:placetype":"locality"
},
  "geometry": {"coordinates":[11.92104,9.20981],"type":"Point"}
}