{
  "type": "Feature",
  "properties": {
    "gn:admin1_code":"51.0",
    "gn:admin2_code":"603.0",
    "gn:admin3_code":"60311",
    "gn:asciiname":"Yakum",
    "gn:country_code":"NG",
    "gn:dem":348,
    "gn:feature_class":"P",
    "gn:feature_code":"PPL",
    "gn:name":"Yakum",
    "gn:population":0,
    "gn:timezone":"Africa/Lagos",
    "iso:country":"NG",
    "name:und_x_variant":[
        "Yakunu",
        "Yakum"
    ],
    "wof:name":"Yakum",
    "wof:placetype":"locality"
},
  "geometry": {"coordinates":[5.38927,12.86906],"type":"Point"}
}