{
  "type": "Feature",
  "properties": {
    "gn:admin1_code":"51.0",
    "gn:admin2_code":"603.0",
    "gn:admin3_code":"60311",
    "gn:asciiname":"Yakum",
    "gn:country_code":"NG",
    "gn:dem":348,
    "gn:feature_class":"P",
    "gn:feature_code":"PPL",
    "gn:name":"Yakum",
    "gn:population":0,
    "gn:timezone":"Africa/Lagos",
    "iso:country":"NG",
    "name:ceb_x_preferred":[
        "Yaqum"
    ],
    "name:ces_x_preferred":[
        "Jakum"
    ],
    "name:heb_x_preferred":[
        "\u05d9\u05e7\u05d5\u05dd"
    ],
    "name:nno_x_preferred":[
        "Yakum"
    ],
    "name:nor_x_preferred":[
        "Yakum"
    ],
    "name:pol_x_preferred":[
        "Jakum"
    ],
    "name:spa_x_preferred":[
        "Yakum"
    ],
    "name:swe_x_preferred":[
        "Yaqum"
    ],
    "name:und_x_variant":[
        "Yakunu"
    ],
    "name:urd_x_preferred":[
        "\u06cc\u06a9\u0645"
    ],
    "wof:name":"Yakum",
    "wof:placetype":"locality"
},
  "geometry": {"coordinates":[5.38927,12.86906],"type":"Point"}
}