{
  "type": "Feature",
  "properties": {
    "gn:admin1_code":"29.0",
    "gn:admin2_code":"20033.0",
    "gn:admin3_code":"KN2303",
    "gn:asciiname":"Saya Saya",
    "gn:country_code":"NG",
    "gn:dem":591,
    "gn:feature_class":"P",
    "gn:feature_code":"PPL",
    "gn:name":"Saya Saya",
    "gn:population":0,
    "gn:timezone":"Africa/Lagos",
    "iso:country":"NG",
    "wof:name":"Saya Saya",
    "wof:placetype":"locality"
},
  "geometry": {"coordinates":[8.66568,11.38933],"type":"Point"}
}