{
  "type": "Feature",
  "properties": {
    "gn:admin1_code":"32.0",
    "gn:admin2_code":"31004.0",
    "gn:asciiname":"Asaju",
    "gn:country_code":"NG",
    "gn:dem":295,
    "gn:feature_class":"P",
    "gn:feature_code":"PPL",
    "gn:name":"Asaju",
    "gn:population":0,
    "gn:timezone":"Africa/Lagos",
    "iso:country":"NG",
    "wof:name":"Asaju",
    "wof:placetype":"locality"
},
  "geometry": {"coordinates":[3.43333,8.31667],"type":"Point"}
}