{
  "type": "Feature",
  "properties": {
    "gn:admin1_code":"24.0",
    "gn:admin2_code":"434.0",
    "gn:admin3_code":"43405",
    "gn:asciiname":"Dasha",
    "gn:country_code":"NG",
    "gn:dem":448,
    "gn:feature_class":"P",
    "gn:feature_code":"PPL",
    "gn:name":"Dasha",
    "gn:population":0,
    "gn:timezone":"Africa/Lagos",
    "iso:country":"NG",
    "name:ceb_x_preferred":[
        "Dasha"
    ],
    "name:deu_x_preferred":[
        "Dasha"
    ],
    "name:ita_x_preferred":[
        "Dasha"
    ],
    "name:swe_x_preferred":[
        "Dasha"
    ],
    "wof:name":"Dasha",
    "wof:placetype":"locality"
},
  "geometry": {"coordinates":[8.5773,12.87604],"type":"Point"}
}