{
  "type": "Feature",
  "properties": {
    "gn:admin1_code":"51.0",
    "gn:admin2_code":"604.0",
    "gn:admin3_code":"60403",
    "gn:asciiname":"Gidan Tambari",
    "gn:country_code":"NG",
    "gn:dem":312,
    "gn:feature_class":"P",
    "gn:feature_code":"PPL",
    "gn:name":"Gidan Tambari",
    "gn:population":0,
    "gn:timezone":"Africa/Lagos",
    "iso:country":"NG",
    "wof:name":"Gidan Tambari",
    "wof:placetype":"locality"
},
  "geometry": {"coordinates":[5.88016,13.65308],"type":"Point"}
}