{
  "type": "Feature",
  "properties": {
    "gn:admin1_code":"23.0",
    "gn:admin2_code":"19004.0",
    "gn:admin3_code":"KD0401",
    "gn:asciiname":"Ungwan Magawata",
    "gn:country_code":"NG",
    "gn:dem":598,
    "gn:feature_class":"P",
    "gn:feature_code":"PPL",
    "gn:name":"Ungwan Magawata",
    "gn:population":0,
    "gn:timezone":"Africa/Lagos",
    "iso:country":"NG",
    "wof:name":"Ungwan Magawata",
    "wof:placetype":"locality"
},
  "geometry": {"coordinates":[7.27232,10.72316],"type":"Point"}
}