{
  "type": "Feature",
  "properties": {
    "gn:admin1_code":"21.0",
    "gn:admin2_code":"3029.0",
    "gn:asciiname":"Nwaniba",
    "gn:country_code":"NG",
    "gn:dem":14,
    "gn:feature_class":"P",
    "gn:feature_code":"PPL",
    "gn:name":"Nwaniba",
    "gn:population":0,
    "gn:timezone":"Africa/Lagos",
    "iso:country":"NG",
    "wof:name":"Nwaniba",
    "wof:placetype":"locality"
},
  "geometry": {"coordinates":[8.03851,5.04154],"type":"Point"}
}