{
  "type": "Feature",
  "properties": {
    "gn:admin1_code":"57.0",
    "gn:admin2_code":"805.0",
    "gn:admin3_code":"80505",
    "gn:asciiname":"Augi",
    "gn:country_code":"NG",
    "gn:dem":472,
    "gn:feature_class":"P",
    "gn:feature_code":"PPL",
    "gn:name":"Augi",
    "gn:population":0,
    "gn:timezone":"Africa/Lagos",
    "iso:country":"NG",
    "wof:name":"Augi",
    "wof:placetype":"locality"
},
  "geometry": {"coordinates":[6.49447,12.15755],"type":"Point"}
}