{
  "type": "Feature",
  "properties": {
    "gn:admin1_code":"21.0",
    "gn:admin2_code":"3024.0",
    "gn:asciiname":"Ikot Ankang",
    "gn:country_code":"NG",
    "gn:dem":30,
    "gn:feature_class":"P",
    "gn:feature_code":"PPL",
    "gn:name":"Ikot Ankang",
    "gn:population":0,
    "gn:timezone":"Africa/Lagos",
    "iso:country":"NG",
    "name:und_x_variant":[
        "Ikot Ankan",
        "Ikot Ankang"
    ],
    "wof:name":"Ikot Ankang",
    "wof:placetype":"locality"
},
  "geometry": {"coordinates":[7.83517,4.63952],"type":"Point"}
}