{
  "type": "Feature",
  "properties": {
    "gn:admin1_code":"16.0",
    "gn:admin2_code":"28015.0",
    "gn:asciiname":"Kajola",
    "gn:country_code":"NG",
    "gn:dem":70,
    "gn:feature_class":"P",
    "gn:feature_code":"PPL",
    "gn:name":"Kajola",
    "gn:population":0,
    "gn:timezone":"Africa/Lagos",
    "iso:country":"NG",
    "name:fra_x_preferred":[
        "Kajola"
    ],
    "name:hau_x_preferred":[
        "Kajola"
    ],
    "name:ita_x_preferred":[
        "Kajola"
    ],
    "name:spa_x_preferred":[
        "Kajola"
    ],
    "wof:name":"Kajola",
    "wof:placetype":"locality"
},
  "geometry": {"coordinates":[3.41667,6.96667],"type":"Point"}
}