{
  "type": "Feature",
  "properties": {
    "gn:admin1_code":"43.0",
    "gn:admin2_code":"35016",
    "gn:asciiname":"Baro",
    "gn:country_code":"NG",
    "gn:dem":444,
    "gn:feature_class":"P",
    "gn:feature_code":"PPL",
    "gn:name":"Baro",
    "gn:population":0,
    "gn:timezone":"Africa/Lagos",
    "iso:country":"NG",
    "wof:name":"Baro",
    "wof:placetype":"locality"
},
  "geometry": {"coordinates":[11.86254,8.83957],"type":"Point"}
}