{
  "type": "Feature",
  "properties": {
    "gn:admin1_code":"21.0",
    "gn:admin2_code":"3014.0",
    "gn:asciiname":"Ikot Ata Osung",
    "gn:country_code":"NG",
    "gn:dem":108,
    "gn:feature_class":"P",
    "gn:feature_code":"PPL",
    "gn:name":"Ikot Ata Osung",
    "gn:population":0,
    "gn:timezone":"Africa/Lagos",
    "iso:country":"NG",
    "wof:name":"Ikot Ata Osung",
    "wof:placetype":"locality"
},
  "geometry": {"coordinates":[7.68515,5.24463],"type":"Point"}
}