{
  "type": "Feature",
  "properties": {
    "gn:admin1_code":"23.0",
    "gn:admin2_code":"19012.0",
    "gn:admin3_code":"KD1203",
    "gn:asciiname":"Idon",
    "gn:country_code":"NG",
    "gn:dem":770,
    "gn:feature_class":"P",
    "gn:feature_code":"PPL",
    "gn:name":"Idon",
    "gn:population":0,
    "gn:timezone":"Africa/Lagos",
    "iso:country":"NG",
    "wof:name":"Idon",
    "wof:placetype":"locality"
},
  "geometry": {"coordinates":[7.90554,10.10291],"type":"Point"}
}