{
  "type": "Feature",
  "properties": {
    "gn:admin1_code":"50.0",
    "gn:admin2_code":"33016.0",
    "gn:asciiname":"Osiakpu",
    "gn:country_code":"NG",
    "gn:dem":16,
    "gn:feature_class":"P",
    "gn:feature_code":"PPL",
    "gn:name":"Osiakpu",
    "gn:population":0,
    "gn:timezone":"Africa/Lagos",
    "iso:country":"NG",
    "wof:name":"Osiakpu",
    "wof:placetype":"locality"
},
  "geometry": {"coordinates":[6.68532,5.31778],"type":"Point"}
}