{
  "type": "Feature",
  "properties": {
    "gn:admin1_code":"55.0",
    "gn:admin2_code":"16011.0",
    "gn:asciiname":"Kwadon",
    "gn:country_code":"NG",
    "gn:dem":347,
    "gn:feature_class":"P",
    "gn:feature_code":"PPL",
    "gn:name":"Kwadon",
    "gn:population":0,
    "gn:timezone":"Africa/Lagos",
    "iso:country":"NG",
    "name:und_x_variant":[
        "Gwodun",
        "Kwondom",
        "Kwodun",
        "Kwadon"
    ],
    "wof:name":"Kwadon",
    "wof:placetype":"locality"
},
  "geometry": {"coordinates":[11.28392,10.271],"type":"Point"}
}