{
  "type": "Feature",
  "properties": {
    "gn:admin1_code":"37.0",
    "gn:admin2_code":"12004",
    "gn:asciiname":"Usenu-Irrua",
    "gn:country_code":"NG",
    "gn:dem":411,
    "gn:feature_class":"P",
    "gn:feature_code":"PPL",
    "gn:name":"Usenu-Irrua",
    "gn:population":0,
    "gn:timezone":"Africa/Lagos",
    "iso:country":"NG",
    "wof:name":"Usenu-Irrua",
    "wof:placetype":"locality"
},
  "geometry": {"coordinates":[6.21401,6.73821],"type":"Point"}
}