{
  "type": "Feature",
  "properties": {
    "gn:admin1_code":"26.0",
    "gn:admin2_code":"7011.0",
    "gn:asciiname":"Ukeyima",
    "gn:country_code":"NG",
    "gn:dem":230,
    "gn:feature_class":"P",
    "gn:feature_code":"PPL",
    "gn:name":"Ukeyima",
    "gn:population":0,
    "gn:timezone":"Africa/Lagos",
    "iso:country":"NG",
    "wof:name":"Ukeyima",
    "wof:placetype":"locality"
},
  "geometry": {"coordinates":[9.5655,6.58878],"type":"Point"}
}