{
  "type": "Feature",
  "properties": {
    "gn:admin1_code":"46.0",
    "gn:admin2_code":"5008.0",
    "gn:admin3_code":"BA0802",
    "gn:asciiname":"Kediya",
    "gn:country_code":"NG",
    "gn:dem":344,
    "gn:feature_class":"P",
    "gn:feature_code":"PPL",
    "gn:name":"Kediya",
    "gn:population":0,
    "gn:timezone":"Africa/Lagos",
    "iso:country":"NG",
    "name:eng_x_preferred":[
        "Kediya"
    ],
    "wof:name":"Kediya",
    "wof:placetype":"locality"
},
  "geometry": {"coordinates":[10.46153,10.64102],"type":"Point"}
}