{
  "type": "Feature",
  "properties": {
    "gn:admin1_code":"43.0",
    "gn:asciiname":"Jegang Ardido",
    "gn:country_code":"NG",
    "gn:dem":203,
    "gn:feature_class":"P",
    "gn:feature_code":"PPL",
    "gn:name":"Jegang Ardido",
    "gn:population":0,
    "gn:timezone":"Africa/Lagos",
    "iso:country":"NG",
    "name:eng_x_preferred":[
        "Jegang Ardido"
    ],
    "wof:name":"Jegang Ardido",
    "wof:placetype":"locality"
},
  "geometry": {"coordinates":[11.53764,9.22747],"type":"Point"}
}