{
  "type": "Feature",
  "properties": {
    "gn:admin1_code":"40.0",
    "gn:admin2_code":"511.0",
    "gn:admin3_code":"51103",
    "gn:asciiname":"Gumuzo",
    "gn:country_code":"NG",
    "gn:dem":245,
    "gn:feature_class":"P",
    "gn:feature_code":"PPL",
    "gn:name":"Gumuzo",
    "gn:population":0,
    "gn:timezone":"Africa/Lagos",
    "iso:country":"NG",
    "wof:name":"Gumuzo",
    "wof:placetype":"locality"
},
  "geometry": {"coordinates":[4.36041,12.33002],"type":"Point"}
}