{
  "type": "Feature",
  "properties": {
    "gn:admin1_code":"30.0",
    "gn:admin2_code":"24005.0",
    "gn:asciiname":"Olorunjare",
    "gn:cc2":"NG",
    "gn:country_code":"NG",
    "gn:dem":377,
    "gn:feature_class":"P",
    "gn:feature_code":"PPL",
    "gn:name":"Olorunjare",
    "gn:population":0,
    "gn:timezone":"Africa/Lagos",
    "iso:country":"NG",
    "name:und_x_variant":[
        "Elenjere",
        "Olorunjare"
    ],
    "wof:name":"Olorunjare",
    "wof:placetype":"locality"
},
  "geometry": {"coordinates":[4.68333,8.35],"type":"Point"}
}