{
  "type": "Feature",
  "properties": {
    "gn:admin1_code":"35.0",
    "gn:admin2_code":"2015.0",
    "gn:asciiname":"Malinda",
    "gn:country_code":"NG",
    "gn:dem":826,
    "gn:feature_class":"P",
    "gn:feature_code":"PPL",
    "gn:name":"Malinda",
    "gn:population":0,
    "gn:timezone":"Africa/Lagos",
    "iso:country":"NG",
    "wof:name":"Malinda",
    "wof:placetype":"locality"
},
  "geometry": {"coordinates":[13.28904,10.15804],"type":"Point"}
}