{
  "type": "Feature",
  "properties": {
    "gn:admin1_code":"48.0",
    "gn:admin2_code":"29012.0",
    "gn:asciiname":"Araromi",
    "gn:country_code":"NG",
    "gn:dem":7,
    "gn:feature_class":"P",
    "gn:feature_code":"PPL",
    "gn:name":"Araromi",
    "gn:population":0,
    "gn:timezone":"Africa/Lagos",
    "iso:country":"NG",
    "wof:name":"Araromi",
    "wof:placetype":"locality"
},
  "geometry": {"coordinates":[5.13333,6.48333],"type":"Point"}
}