{
  "type": "Feature",
  "properties": {
    "gn:admin1_code":"35.0",
    "gn:admin2_code":"2002",
    "gn:asciiname":"Gera",
    "gn:country_code":"NG",
    "gn:dem":387,
    "gn:feature_class":"P",
    "gn:feature_code":"PPL",
    "gn:name":"Gera",
    "gn:population":0,
    "gn:timezone":"Africa/Lagos",
    "iso:country":"NG",
    "wof:name":"Gera",
    "wof:placetype":"locality"
},
  "geometry": {"coordinates":[12.42367,8.85835],"type":"Point"}
}