{
  "type": "Feature",
  "properties": {
    "gn:admin1_code":"47.0",
    "gn:admin2_code":"14001.0",
    "gn:asciiname":"Obinefu-Nenwe",
    "gn:country_code":"NG",
    "gn:dem":68,
    "gn:feature_class":"P",
    "gn:feature_code":"PPL",
    "gn:name":"Obinefu-Nenwe",
    "gn:population":0,
    "gn:timezone":"Africa/Lagos",
    "iso:country":"NG",
    "wof:name":"Obinefu-Nenwe",
    "wof:placetype":"locality"
},
  "geometry": {"coordinates":[7.58096,6.0932],"type":"Point"}
}