{
  "type": "Feature",
  "properties": {
    "gn:admin1_code":"26.0",
    "gn:admin2_code":"7007.0",
    "gn:asciiname":"Ukuse",
    "gn:country_code":"NG",
    "gn:dem":121,
    "gn:feature_class":"P",
    "gn:feature_code":"PPL",
    "gn:name":"Ukuse",
    "gn:population":0,
    "gn:timezone":"Africa/Lagos",
    "iso:country":"NG",
    "wof:name":"Ukuse",
    "wof:placetype":"locality"
},
  "geometry": {"coordinates":[8.3398,7.2662],"type":"Point"}
}