{
  "type": "Feature",
  "properties": {
    "gn:admin1_code":"37.0",
    "gn:admin2_code":"12013.0",
    "gn:asciiname":"Iguohan",
    "gn:country_code":"NG",
    "gn:dem":63,
    "gn:feature_class":"P",
    "gn:feature_code":"PPL",
    "gn:name":"Iguohan",
    "gn:population":0,
    "gn:timezone":"Africa/Lagos",
    "iso:country":"NG",
    "wof:name":"Iguohan",
    "wof:placetype":"locality"
},
  "geometry": {"coordinates":[5.81027,6.18917],"type":"Point"}
}