{
  "type": "Feature",
  "properties": {
    "gn:admin1_code":"46.0",
    "gn:admin2_code":"5015.0",
    "gn:admin3_code":"BA1514",
    "gn:asciiname":"Jerkoya",
    "gn:country_code":"NG",
    "gn:dem":678,
    "gn:feature_class":"P",
    "gn:feature_code":"PPL",
    "gn:name":"Jerkoya",
    "gn:population":0,
    "gn:timezone":"Africa/Lagos",
    "iso:country":"NG",
    "wof:name":"Jerkoya",
    "wof:placetype":"locality"
},
  "geometry": {"coordinates":[8.97311,10.90163],"type":"Point"}
}