{
  "type": "Feature",
  "properties": {
    "gn:admin1_code":"44.0",
    "gn:admin2_code":"705.0",
    "gn:admin3_code":"70505",
    "gn:asciiname":"Gudbo",
    "gn:country_code":"NG",
    "gn:dem":435,
    "gn:feature_class":"P",
    "gn:feature_code":"PPL",
    "gn:name":"Gudbo",
    "gn:population":0,
    "gn:timezone":"Africa/Lagos",
    "iso:country":"NG",
    "name:und_x_variant":[
        "Gubdo"
    ],
    "wof:name":"Gudbo",
    "wof:placetype":"locality"
},
  "geometry": {"coordinates":[11.32608,11.58697],"type":"Point"}
}