{
  "type": "Feature",
  "properties": {
    "gn:admin1_code":"57.0",
    "gn:admin2_code":"812.0",
    "gn:admin3_code":"81205",
    "gn:asciiname":"Matona",
    "gn:country_code":"NG",
    "gn:dem":385,
    "gn:feature_class":"P",
    "gn:feature_code":"PPL",
    "gn:name":"Matona",
    "gn:population":0,
    "gn:timezone":"Africa/Lagos",
    "iso:country":"NG",
    "wof:name":"Matona",
    "wof:placetype":"locality"
},
  "geometry": {"coordinates":[6.0606,12.26794],"type":"Point"}
}