{
  "type": "Feature",
  "properties": {
    "gn:admin1_code":"43.0",
    "gn:admin2_code":"35014.0",
    "gn:asciiname":"Uro Tukun",
    "gn:country_code":"NG",
    "gn:dem":167,
    "gn:feature_class":"P",
    "gn:feature_code":"PPL",
    "gn:name":"Uro Tukun",
    "gn:population":0,
    "gn:timezone":"Africa/Lagos",
    "iso:country":"NG",
    "wof:name":"Uro Tukun",
    "wof:placetype":"locality"
},
  "geometry": {"coordinates":[9.90719,8.04219],"type":"Point"}
}