{
  "type": "Feature",
  "properties": {
    "gn:admin1_code":"52.0",
    "gn:admin2_code":"6007.0",
    "gn:asciiname":"Kugbogbene",
    "gn:country_code":"NG",
    "gn:dem":15,
    "gn:feature_class":"P",
    "gn:feature_code":"PPL",
    "gn:name":"Kugbogbene",
    "gn:population":0,
    "gn:timezone":"Africa/Lagos",
    "iso:country":"NG",
    "name:eng_x_preferred":[
        "Kugbogbene"
    ],
    "wof:name":"Kugbogbene",
    "wof:placetype":"locality"
},
  "geometry": {"coordinates":[5.94507,4.6241],"type":"Point"}
}