{
  "type": "Feature",
  "properties": {
    "gn:admin1_code":"36.0",
    "gn:admin2_code":"10005.0",
    "gn:asciiname":"Oke",
    "gn:country_code":"NG",
    "gn:dem":11,
    "gn:feature_class":"P",
    "gn:feature_code":"PPL",
    "gn:name":"Oke",
    "gn:population":0,
    "gn:timezone":"Africa/Lagos",
    "iso:country":"NG",
    "name:und_x_variant":[
        "Eko",
        "Oke"
    ],
    "wof:name":"Oke",
    "wof:placetype":"locality"
},
  "geometry": {"coordinates":[5.89616,5.72954],"type":"Point"}
}