{
  "type": "Feature",
  "properties": {
    "gn:admin1_code":"32.0",
    "gn:admin2_code":"31021.0",
    "gn:asciiname":"Ogbomoso",
    "gn:country_code":"NG",
    "gn:dem":361,
    "gn:feature_class":"P",
    "gn:feature_code":"PPLA2",
    "gn:name":"Ogbomoso",
    "gn:population":0,
    "gn:timezone":"Africa/Lagos",
    "iso:country":"NG",
    "name:afr_x_preferred":[
        "Ogbomosho"
    ],
    "name:azb_x_preferred":[
        "\u0627\u0648\u0642\u0628\u0648\u0645\u0648\u0634\u0648"
    ],
    "name:bul_x_preferred":[
        "\u041e\u0433\u0431\u043e\u043c\u043e\u0448\u043e"
    ],
    "name:dan_x_preferred":[
        "Ogbomoso"
    ],
    "name:deu_x_preferred":[
        "Ogbomosho"
    ],
    "name:epo_x_preferred":[
        "Ogbomo\u015do"
    ],
    "name:fas_x_preferred":[
        "\u0627\u0648\u06af\u0628\u0648\u0645\u0648\u0634\u0648"
    ],
    "name:fra_x_preferred":[
        "Ogbomoso"
    ],
    "name:hun_x_preferred":[
        "Ogbomosho"
    ],
    "name:ita_x_preferred":[
        "Ogbomosho"
    ],
    "name:jpn_x_preferred":[
        "\u30aa\u30b0\u30dc\u30e2\u30b7\u30e7"
    ],
    "name:kor_x_preferred":[
        "\uc624\uadf8\ubcf4\ubaa8\uc1fc"
    ],
    "name:lit_x_preferred":[
        "Ogbomo\u0161as"
    ],
    "name:mkd_x_preferred":[
        "\u041e\u0433\u0431\u043e\u043c\u043e\u0448\u043e"
    ],
    "name:nds_x_preferred":[
        "Ogbomosho"
    ],
    "name:nld_x_preferred":[
        "Ogbomosho"
    ],
    "name:pol_x_preferred":[
        "Ogbomosho"
    ],
    "name:por_x_preferred":[
        "Ogbomoso"
    ],
    "name:ron_x_preferred":[
        "Ogbomoso"
    ],
    "name:rus_x_preferred":[
        "\u041e\u0433\u0431\u043e\u043c\u043e\u0448\u043e"
    ],
    "name:spa_x_preferred":[
        "Ogbomosho"
    ],
    "name:swe_x_preferred":[
        "Ogbomosho"
    ],
    "name:ukr_x_preferred":[
        "\u041e\u0433\u0431\u043e\u043c\u043e\u0448\u043e"
    ],
    "name:und_x_variant":[
        "Ogbomocho",
        "Ogbomosho",
        "Ogbomoso"
    ],
    "name:uzb_x_preferred":[
        "Ogbomosho"
    ],
    "name:war_x_preferred":[
        "Ogbomosho"
    ],
    "name:yor_x_preferred":[
        "\u00d2gb\u00f3m\u1ecd\u0300s\u1ecd\u0301"
    ],
    "name:zho_x_preferred":[
        "\u5967\u535a\u83ab\u7d39"
    ],
    "wof:name":"Ogbomoso",
    "wof:placetype":"locality"
},
  "geometry": {"coordinates":[4.24014,8.13373],"type":"Point"}
}