{
  "type": "Feature",
  "properties": {
    "gn:admin1_code":"32.0",
    "gn:admin2_code":"31021.0",
    "gn:asciiname":"Ogbomoso",
    "gn:country_code":"NG",
    "gn:dem":361,
    "gn:feature_class":"P",
    "gn:feature_code":"PPLA2",
    "gn:name":"Ogbomoso",
    "gn:population":0,
    "gn:timezone":"Africa/Lagos",
    "iso:country":"NG",
    "name:und_x_variant":[
        "Ogbomocho",
        "Ogbomosho",
        "Ogbomoso"
    ],
    "wof:name":"Ogbomoso",
    "wof:placetype":"locality"
},
  "geometry": {"coordinates":[4.24014,8.13373],"type":"Point"}
}