{
  "type": "Feature",
  "properties": {
    "gn:admin1_code":"46.0",
    "gn:admin2_code":"5008.0",
    "gn:admin3_code":"BA0805",
    "gn:asciiname":"Kakuma",
    "gn:country_code":"NG",
    "gn:dem":542,
    "gn:feature_class":"P",
    "gn:feature_code":"PPL",
    "gn:name":"Kakuma",
    "gn:population":0,
    "gn:timezone":"Africa/Lagos",
    "iso:country":"NG",
    "name:eng_x_preferred":[
        "Kakuma"
    ],
    "wof:name":"Kakuma",
    "wof:placetype":"locality"
},
  "geometry": {"coordinates":[10.19826,10.62872],"type":"Point"}
}