{
  "type": "Feature",
  "properties": {
    "gn:admin1_code":"46.0",
    "gn:admin2_code":"5008.0",
    "gn:admin3_code":"BA0805",
    "gn:asciiname":"Kakuma",
    "gn:country_code":"NG",
    "gn:dem":542,
    "gn:feature_class":"P",
    "gn:feature_code":"PPL",
    "gn:name":"Kakuma",
    "gn:population":0,
    "gn:timezone":"Africa/Lagos",
    "iso:country":"NG",
    "name:ben_x_preferred":[
        "\u0995\u09be\u0995\u09c1\u09ae\u09be"
    ],
    "name:dan_x_preferred":[
        "Kakuma"
    ],
    "name:deu_x_preferred":[
        "Kakuma"
    ],
    "name:eng_x_preferred":[
        "Kakuma"
    ],
    "name:fin_x_preferred":[
        "Kakuma"
    ],
    "name:fra_x_preferred":[
        "Kakuma"
    ],
    "name:ita_x_preferred":[
        "Kakuma"
    ],
    "name:jpn_x_preferred":[
        "\u30ab\u30af\u30de"
    ],
    "name:ron_x_preferred":[
        "Kakuma"
    ],
    "name:spa_x_preferred":[
        "Kakuma"
    ],
    "name:swa_x_preferred":[
        "Kakuma"
    ],
    "name:swe_x_preferred":[
        "Kakuma"
    ],
    "name:zho_x_preferred":[
        "\u5361\u5eab\u99ac"
    ],
    "wof:name":"Kakuma",
    "wof:placetype":"locality"
},
  "geometry": {"coordinates":[10.19826,10.62872],"type":"Point"}
}