{
  "type": "Feature",
  "properties": {
    "gn:admin1_code":"43.0",
    "gn:admin2_code":"35015",
    "gn:asciiname":"Santi",
    "gn:country_code":"NG",
    "gn:dem":287,
    "gn:feature_class":"P",
    "gn:feature_code":"PPL",
    "gn:name":"Santi",
    "gn:population":0,
    "gn:timezone":"Africa/Lagos",
    "iso:country":"NG",
    "name:bre_x_preferred":[
        "Santi"
    ],
    "name:ceb_x_preferred":[
        "Santi"
    ],
    "name:deu_x_preferred":[
        "Santi"
    ],
    "name:fra_x_preferred":[
        "Santi"
    ],
    "name:ita_x_preferred":[
        "Santi"
    ],
    "name:jpn_x_preferred":[
        "\u30b5\u30f3\u30c6\u30a3"
    ],
    "name:por_x_preferred":[
        "Santi"
    ],
    "name:srp_x_preferred":[
        "Santi"
    ],
    "name:swe_x_preferred":[
        "Santi"
    ],
    "wof:name":"Santi",
    "wof:placetype":"locality"
},
  "geometry": {"coordinates":[11.37852,8.98635],"type":"Point"}
}