{
  "type": "Feature",
  "properties": {
    "gn:admin1_code":"26.0",
    "gn:admin2_code":"7006.0",
    "gn:asciiname":"Akpu",
    "gn:country_code":"NG",
    "gn:dem":107,
    "gn:feature_class":"P",
    "gn:feature_code":"PPL",
    "gn:name":"Akpu",
    "gn:population":0,
    "gn:timezone":"Africa/Lagos",
    "iso:country":"NG",
    "wof:name":"Akpu",
    "wof:placetype":"locality"
},
  "geometry": {"coordinates":[8.65738,7.80714],"type":"Point"}
}