{
  "type": "Feature",
  "properties": {
    "gn:admin1_code":"26.0",
    "gn:admin2_code":"7013.0",
    "gn:asciiname":"Yaor Caro",
    "gn:country_code":"NG",
    "gn:dem":80,
    "gn:feature_class":"P",
    "gn:feature_code":"PPL",
    "gn:name":"Yaor Caro",
    "gn:population":0,
    "gn:timezone":"Africa/Lagos",
    "iso:country":"NG",
    "name:und_x_variant":[
        "Yaro Caro",
        "Yaor Caro"
    ],
    "wof:name":"Yaor Caro",
    "wof:placetype":"locality"
},
  "geometry": {"coordinates":[8.65515,7.7078],"type":"Point"}
}