{
  "type": "Feature",
  "properties": {
    "gn:admin1_code":"24.0",
    "gn:admin2_code":"428.0",
    "gn:admin3_code":"42801",
    "gn:asciiname":"Rijin Gora",
    "gn:country_code":"NG",
    "gn:dem":557,
    "gn:feature_class":"P",
    "gn:feature_code":"PPL",
    "gn:name":"Rijin Gora",
    "gn:population":0,
    "gn:timezone":"Africa/Lagos",
    "iso:country":"NG",
    "wof:name":"Rijin Gora",
    "wof:placetype":"locality"
},
  "geometry": {"coordinates":[7.68723,12.1736],"type":"Point"}
}