{
  "type": "Feature",
  "properties": {
    "gn:admin1_code":"24.0",
    "gn:admin2_code":"419.0",
    "gn:admin3_code":"41907",
    "gn:asciiname":"Ungwan Kwabo",
    "gn:country_code":"NG",
    "gn:dem":608,
    "gn:feature_class":"P",
    "gn:feature_code":"PPL",
    "gn:name":"Ungwan Kwabo",
    "gn:population":0,
    "gn:timezone":"Africa/Lagos",
    "iso:country":"NG",
    "wof:name":"Ungwan Kwabo",
    "wof:placetype":"locality"
},
  "geometry": {"coordinates":[7.58813,11.81908],"type":"Point"}
}