{
  "type": "Feature",
  "properties": {
    "gn:admin1_code":"21.0",
    "gn:admin2_code":"3010.0",
    "gn:asciiname":"Ikot Ekpene",
    "gn:country_code":"NG",
    "gn:dem":76,
    "gn:feature_class":"P",
    "gn:feature_code":"PPL",
    "gn:name":"Ikot Ekpene",
    "gn:population":0,
    "gn:timezone":"Africa/Lagos",
    "iso:country":"NG",
    "wof:name":"Ikot Ekpene",
    "wof:placetype":"locality"
},
  "geometry": {"coordinates":[7.93419,5.18147],"type":"Point"}
}