{
  "type": "Feature",
  "properties": {
    "gn:admin1_code":"21.0",
    "gn:admin2_code":"3010.0",
    "gn:asciiname":"Ikot Ekpene",
    "gn:country_code":"NG",
    "gn:dem":76,
    "gn:feature_class":"P",
    "gn:feature_code":"PPL",
    "gn:name":"Ikot Ekpene",
    "gn:population":0,
    "gn:timezone":"Africa/Lagos",
    "iso:country":"NG",
    "name:ceb_x_preferred":[
        "Ikot Ekpene"
    ],
    "name:fra_x_preferred":[
        "Ikot Ekpene"
    ],
    "name:hau_x_preferred":[
        "Ikot Ekpene"
    ],
    "name:ita_x_preferred":[
        "Ikot Ekpene"
    ],
    "name:nld_x_preferred":[
        "Ikot Ekpene"
    ],
    "name:pol_x_preferred":[
        "Ikot Ekpene"
    ],
    "name:por_x_preferred":[
        "Ikot Ekpene"
    ],
    "name:ron_x_preferred":[
        "Ikot Ekpene"
    ],
    "name:spa_x_preferred":[
        "Ikot Ekpene"
    ],
    "name:yor_x_preferred":[
        "Ikot Ekpene"
    ],
    "name:zho_x_preferred":[
        "\u4f0a\u79d1\u7279\u57c3\u4f69\u5167"
    ],
    "wof:name":"Ikot Ekpene",
    "wof:placetype":"locality"
},
  "geometry": {"coordinates":[7.93419,5.18147],"type":"Point"}
}