{
  "type": "Feature",
  "properties": {
    "gn:admin1_code":"27.0",
    "gn:admin2_code":"103.0",
    "gn:admin3_code":"10311",
    "gn:asciiname":"Bula Ngubdoye",
    "gn:country_code":"NG",
    "gn:dem":303,
    "gn:feature_class":"P",
    "gn:feature_code":"PPL",
    "gn:name":"Bula Ngubdoye",
    "gn:population":0,
    "gn:timezone":"Africa/Lagos",
    "iso:country":"NG",
    "wof:name":"Bula Ngubdoye",
    "wof:placetype":"locality"
},
  "geometry": {"coordinates":[14.22622,11.50768],"type":"Point"}
}