{
  "type": "Feature",
  "properties": {
    "gn:admin1_code":"40.0",
    "gn:admin2_code":"507.0",
    "gn:admin3_code":"50708",
    "gn:asciiname":"Ungwan Gao",
    "gn:country_code":"NG",
    "gn:dem":231,
    "gn:feature_class":"P",
    "gn:feature_code":"PPL",
    "gn:name":"Ungwan Gao",
    "gn:population":0,
    "gn:timezone":"Africa/Lagos",
    "iso:country":"NG",
    "wof:name":"Ungwan Gao",
    "wof:placetype":"locality"
},
  "geometry": {"coordinates":[3.90874,12.34391],"type":"Point"}
}