{
  "type": "Feature",
  "properties": {
    "gn:admin1_code":"48.0",
    "gn:admin2_code":"29010.0",
    "gn:asciiname":"Kurugbene",
    "gn:country_code":"NG",
    "gn:dem":5,
    "gn:feature_class":"P",
    "gn:feature_code":"PPL",
    "gn:name":"Kurugbene",
    "gn:population":0,
    "gn:timezone":"Africa/Lagos",
    "iso:country":"NG",
    "name:und_x_variant":[
        "Krugbene",
        "Kurugbene"
    ],
    "wof:name":"Kurugbene",
    "wof:placetype":"locality"
},
  "geometry": {"coordinates":[4.80414,6.35945],"type":"Point"}
}