{
  "type": "Feature",
  "properties": {
    "gn:admin1_code":"24.0",
    "gn:admin2_code":"419.0",
    "gn:admin3_code":"41911",
    "gn:asciiname":"Maigezo",
    "gn:country_code":"NG",
    "gn:dem":554,
    "gn:feature_class":"P",
    "gn:feature_code":"PPL",
    "gn:name":"Maigezo",
    "gn:population":0,
    "gn:timezone":"Africa/Lagos",
    "iso:country":"NG",
    "wof:name":"Maigezo",
    "wof:placetype":"locality"
},
  "geometry": {"coordinates":[7.31345,11.87703],"type":"Point"}
}