{
  "type": "Feature",
  "properties": {
    "gn:admin1_code":"39.0",
    "gn:admin2_code":"18010.0",
    "gn:admin3_code":"JI1701",
    "gn:asciiname":"Gizo Baladi",
    "gn:country_code":"NG",
    "gn:dem":425,
    "gn:feature_class":"P",
    "gn:feature_code":"PPL",
    "gn:name":"Gizo Baladi",
    "gn:population":0,
    "gn:timezone":"Africa/Lagos",
    "iso:country":"NG",
    "wof:name":"Gizo Baladi",
    "wof:placetype":"locality"
},
  "geometry": {"coordinates":[8.52055,12.69634],"type":"Point"}
}