{
  "type": "Feature",
  "properties": {
    "gn:admin1_code":"27.0",
    "gn:admin2_code":"112.0",
    "gn:admin3_code":"11207",
    "gn:asciiname":"Degri",
    "gn:country_code":"NG",
    "gn:dem":697,
    "gn:feature_class":"P",
    "gn:feature_code":"PPL",
    "gn:name":"Degri",
    "gn:population":0,
    "gn:timezone":"Africa/Lagos",
    "iso:country":"NG",
    "wof:name":"Degri",
    "wof:placetype":"locality"
},
  "geometry": {"coordinates":[12.12182,10.47569],"type":"Point"}
}