{
  "type": "Feature",
  "properties": {
    "gn:admin1_code":"28.0",
    "gn:admin2_code":"17012.0",
    "gn:asciiname":"Amala",
    "gn:country_code":"NG",
    "gn:dem":65,
    "gn:feature_class":"P",
    "gn:feature_code":"PPL",
    "gn:name":"Amala",
    "gn:population":0,
    "gn:timezone":"Africa/Lagos",
    "iso:country":"NG",
    "name:mal_x_preferred":[
        "\u0d05\u0d2e\u0d32"
    ],
    "name:swe_x_preferred":[
        "Amala"
    ],
    "wof:name":"Amala",
    "wof:placetype":"locality"
},
  "geometry": {"coordinates":[7.19788,5.22383],"type":"Point"}
}