{
  "type": "Feature",
  "properties": {
    "gn:admin1_code":"56.0",
    "gn:admin2_code":"26001.0",
    "gn:asciiname":"Andaha-Daji",
    "gn:country_code":"NG",
    "gn:dem":548,
    "gn:feature_class":"P",
    "gn:feature_code":"PPL",
    "gn:name":"Andaha-Daji",
    "gn:population":0,
    "gn:timezone":"Africa/Lagos",
    "iso:country":"NG",
    "name:und_x_variant":[
        "Andahan Daji"
    ],
    "wof:name":"Andaha-Daji",
    "wof:placetype":"locality"
},
  "geometry": {"coordinates":[8.41259,9.11552],"type":"Point"}
}