{
  "type": "Feature",
  "properties": {
    "gn:admin1_code":"24.0",
    "gn:admin2_code":"427.0",
    "gn:admin3_code":"42706",
    "gn:asciiname":"Tudu",
    "gn:country_code":"NG",
    "gn:dem":481,
    "gn:feature_class":"P",
    "gn:feature_code":"PPL",
    "gn:name":"Tudu",
    "gn:population":0,
    "gn:timezone":"Africa/Lagos",
    "iso:country":"NG",
    "name:ceb_x_preferred":[
        "Tudu"
    ],
    "wof:name":"Tudu",
    "wof:placetype":"locality"
},
  "geometry": {"coordinates":[8.07444,13.09172],"type":"Point"}
}