{
  "type": "Feature",
  "properties": {
    "gn:admin1_code":"55.0",
    "gn:asciiname":"Garin Gamu",
    "gn:country_code":"NG",
    "gn:dem":409,
    "gn:feature_class":"P",
    "gn:feature_code":"PPL",
    "gn:name":"Garin Gamu",
    "gn:population":0,
    "gn:timezone":"Africa/Lagos",
    "iso:country":"NG",
    "wof:name":"Garin Gamu",
    "wof:placetype":"locality"
},
  "geometry": {"coordinates":[11.11344,11.2754],"type":"Point"}
}