{
  "type": "Feature",
  "properties": {
    "gn:admin1_code":"24.0",
    "gn:admin2_code":"404.0",
    "gn:admin3_code":"40401",
    "gn:asciiname":"Garin Cinai",
    "gn:country_code":"NG",
    "gn:dem":387,
    "gn:feature_class":"P",
    "gn:feature_code":"PPL",
    "gn:name":"Garin Cinai",
    "gn:population":0,
    "gn:timezone":"Africa/Lagos",
    "iso:country":"NG",
    "wof:name":"Garin Cinai",
    "wof:placetype":"locality"
},
  "geometry": {"coordinates":[8.94966,12.83313],"type":"Point"}
}