{
  "type": "Feature",
  "properties": {
    "gn:admin1_code":"32.0",
    "gn:admin2_code":"31005.0",
    "gn:asciiname":"Olode",
    "gn:country_code":"NG",
    "gn:dem":202,
    "gn:feature_class":"P",
    "gn:feature_code":"PPL",
    "gn:name":"Olode",
    "gn:population":0,
    "gn:timezone":"Africa/Lagos",
    "iso:country":"NG",
    "wof:name":"Olode",
    "wof:placetype":"neighbourhood"
},
  "geometry": {"coordinates":[3.99444,7.38417],"type":"Point"}
}