{
  "type": "Feature",
  "properties": {
    "gn:admin1_code":"31.0",
    "gn:admin2_code":"27024.0",
    "gn:asciiname":"Tunga Yalwa",
    "gn:country_code":"NG",
    "gn:dem":490,
    "gn:feature_class":"P",
    "gn:feature_code":"PPL",
    "gn:name":"Tunga Yalwa",
    "gn:population":0,
    "gn:timezone":"Africa/Lagos",
    "iso:country":"NG",
    "wof:name":"Tunga Yalwa",
    "wof:placetype":"locality"
},
  "geometry": {"coordinates":[7.21324,9.22876],"type":"Point"}
}