{
  "type": "Feature",
  "properties": {
    "gn:admin1_code":"29.0",
    "gn:admin2_code":"20018.0",
    "gn:admin3_code":"KN4203",
    "gn:asciiname":"Nakurewa",
    "gn:country_code":"NG",
    "gn:dem":450,
    "gn:feature_class":"P",
    "gn:feature_code":"PPL",
    "gn:name":"Nakurewa",
    "gn:population":0,
    "gn:timezone":"Africa/Lagos",
    "iso:country":"NG",
    "wof:name":"Nakurewa",
    "wof:placetype":"locality"
},
  "geometry": {"coordinates":[8.56641,12.10152],"type":"Point"}
}