{
  "type": "Feature",
  "properties": {
    "gn:admin1_code":"43.0",
    "gn:admin2_code":"35012.0",
    "gn:asciiname":"Nbada",
    "gn:country_code":"NG",
    "gn:dem":224,
    "gn:feature_class":"P",
    "gn:feature_code":"PPL",
    "gn:name":"Nbada",
    "gn:population":0,
    "gn:timezone":"Africa/Lagos",
    "iso:country":"NG",
    "wof:name":"Nbada",
    "wof:placetype":"locality"
},
  "geometry": {"coordinates":[10.13592,7.35719],"type":"Point"}
}