{
  "type": "Feature",
  "properties": {
    "gn:admin1_code":"55.0",
    "gn:admin2_code":"16001.0",
    "gn:asciiname":"Shulto",
    "gn:country_code":"NG",
    "gn:dem":434,
    "gn:feature_class":"P",
    "gn:feature_code":"PPL",
    "gn:name":"Shulto",
    "gn:population":0,
    "gn:timezone":"Africa/Lagos",
    "iso:country":"NG",
    "name:eng_x_preferred":[
        "Shulto"
    ],
    "wof:name":"Shulto",
    "wof:placetype":"locality"
},
  "geometry": {"coordinates":[10.87418,10.18675],"type":"Point"}
}