{
  "type": "Feature",
  "properties": {
    "gn:admin1_code":"39.0",
    "gn:admin2_code":"18020.0",
    "gn:admin3_code":"JI2304",
    "gn:asciiname":"Ungwar Kanya",
    "gn:country_code":"NG",
    "gn:dem":395,
    "gn:feature_class":"P",
    "gn:feature_code":"PPL",
    "gn:name":"Ungwar Kanya",
    "gn:population":0,
    "gn:timezone":"Africa/Lagos",
    "iso:country":"NG",
    "wof:name":"Ungwar Kanya",
    "wof:placetype":"locality"
},
  "geometry": {"coordinates":[8.98914,12.22117],"type":"Point"}
}