{
  "type": "Feature",
  "properties": {
    "gn:admin1_code":"39.0",
    "gn:admin2_code":"18005.0",
    "gn:admin3_code":"JI1006",
    "gn:asciiname":"Tazga",
    "gn:country_code":"NG",
    "gn:dem":353,
    "gn:feature_class":"P",
    "gn:feature_code":"PPL",
    "gn:name":"Tazga",
    "gn:population":0,
    "gn:timezone":"Africa/Lagos",
    "iso:country":"NG",
    "wof:name":"Tazga",
    "wof:placetype":"locality"
},
  "geometry": {"coordinates":[10.5947,12.60524],"type":"Point"}
}