{
  "type": "Feature",
  "properties": {
    "gn:admin1_code":"37.0",
    "gn:admin2_code":"12003",
    "gn:asciiname":"Eko-Omon",
    "gn:country_code":"NG",
    "gn:dem":404,
    "gn:feature_class":"P",
    "gn:feature_code":"PPL",
    "gn:name":"Eko-Omon",
    "gn:population":0,
    "gn:timezone":"Africa/Lagos",
    "iso:country":"NG",
    "wof:name":"Eko-Omon",
    "wof:placetype":"locality"
},
  "geometry": {"coordinates":[6.2991,6.70026],"type":"Point"}
}