{
  "type": "Feature",
  "properties": {
    "gn:country":"NG",
    "gn:fcode":"PPL",
    "gn:pop":135404,
    "iso:country":"NG",
    "name:dut_x_preferred":[
        "Buguma"
    ],
    "name:eng_x_preferred":[
        "Buguma"
    ],
    "name:unk_x_variant":[
        "Bugama"
    ],
    "qs:name":"Buguma",
    "qs:photos_9r":0,
    "qs:photos_sr":0,
    "qs:pop_sr":"9",
    "wd:wordcount":97,
    "wof:name":"Buguma",
    "wof:placetype":"locality",
    "wof:population":135404
},
  "geometry": {"coordinates":[6.86345,4.73407],"type":"Point"}
}