{
  "type": "Feature",
  "properties": {
    "gn:admin1_code":"45.0",
    "gn:asciiname":"Mkpu",
    "gn:country_code":"NG",
    "gn:dem":104,
    "gn:feature_class":"P",
    "gn:feature_code":"PPL",
    "gn:name":"Mkpu",
    "gn:population":0,
    "gn:timezone":"Africa/Lagos",
    "iso:country":"NG",
    "name:und_x_variant":[
        "Nkpu",
        "Mkpu"
    ],
    "wof:name":"Mkpu",
    "wof:placetype":"locality"
},
  "geometry": {"coordinates":[7.73121,5.46879],"type":"Point"}
}