{
  "type": "Feature",
  "properties": {
    "gn:admin1_code":"31.0",
    "gn:admin2_code":"27005.0",
    "gn:asciiname":"Marikishi",
    "gn:country_code":"NG",
    "gn:dem":232,
    "gn:feature_class":"P",
    "gn:feature_code":"PPL",
    "gn:name":"Marikishi",
    "gn:population":0,
    "gn:timezone":"Africa/Lagos",
    "iso:country":"NG",
    "name:und_x_variant":[
        "Sabon Gida",
        "Marikishi"
    ],
    "wof:name":"Marikishi",
    "wof:placetype":"locality"
},
  "geometry": {"coordinates":[6.64714,9.55346],"type":"Point"}
}