{
  "type": "Feature",
  "properties": {
    "gn:admin1_code":"40.0",
    "gn:admin2_code":"510.0",
    "gn:admin3_code":"51009",
    "gn:asciiname":"Ilela",
    "gn:country_code":"NG",
    "gn:dem":286,
    "gn:feature_class":"P",
    "gn:feature_code":"PPL",
    "gn:name":"Ilela",
    "gn:population":0,
    "gn:timezone":"Africa/Lagos",
    "iso:country":"NG",
    "name:und_x_variant":[
        "Illela Kunyu",
        "Ilela"
    ],
    "wof:name":"Ilela",
    "wof:placetype":"locality"
},
  "geometry": {"coordinates":[4.72236,12.56474],"type":"Point"}
}