{
  "type": "Feature",
  "properties": {
    "gn:admin1_code":"26.0",
    "gn:admin2_code":"7006",
    "gn:asciiname":"Adamawa",
    "gn:country_code":"NG",
    "gn:dem":109,
    "gn:feature_class":"P",
    "gn:feature_code":"PPL",
    "gn:name":"Adamawa",
    "gn:population":0,
    "gn:timezone":"Africa/Lagos",
    "iso:country":"NG",
    "name:bel_x_preferred":[
        "\u0410\u0434\u0430\u043c\u0430\u0432\u0430"
    ],
    "name:cat_x_preferred":[
        "Adamawa"
    ],
    "name:ceb_x_preferred":[
        "Adamawa"
    ],
    "name:deu_x_preferred":[
        "Adamaua"
    ],
    "name:est_x_preferred":[
        "Adamawa"
    ],
    "name:fin_x_preferred":[
        "Adamaoua"
    ],
    "name:fra_x_preferred":[
        "Adamawa"
    ],
    "name:glg_x_preferred":[
        "Adamawa"
    ],
    "name:hun_x_preferred":[
        "Adamawa"
    ],
    "name:jpn_x_preferred":[
        "\u30a2\u30c0\u30de\u30ef"
    ],
    "name:kor_x_preferred":[
        "\uc544\ub2e4\ub9c8\uc640"
    ],
    "name:lit_x_preferred":[
        "Adamava"
    ],
    "name:nld_x_preferred":[
        "Adamawa"
    ],
    "name:nno_x_preferred":[
        "Adamawa"
    ],
    "name:pol_x_preferred":[
        "Adamawa"
    ],
    "name:por_x_preferred":[
        "Adamawa"
    ],
    "name:rus_x_preferred":[
        "\u0410\u0434\u0430\u043c\u0430\u0432\u0430"
    ],
    "name:slk_x_preferred":[
        "Adamawa"
    ],
    "name:spa_x_preferred":[
        "Adamawa"
    ],
    "name:ukr_x_preferred":[
        "\u0410\u0434\u0430\u043c\u0430\u0443\u0430"
    ],
    "wof:name":"Adamawa",
    "wof:placetype":"locality"
},
  "geometry": {"coordinates":[9.00798,7.62928],"type":"Point"}
}