{
  "type": "Feature",
  "properties": {
    "gn:admin1_code":"32.0",
    "gn:admin2_code":"31020.0",
    "gn:asciiname":"Oloja Oke",
    "gn:country_code":"NG",
    "gn:dem":240,
    "gn:feature_class":"P",
    "gn:feature_code":"PPL",
    "gn:name":"Oloja Oke",
    "gn:population":0,
    "gn:timezone":"Africa/Lagos",
    "iso:country":"NG",
    "wof:name":"Oloja Oke",
    "wof:placetype":"locality"
},
  "geometry": {"coordinates":[4.03333,7.53333],"type":"Point"}
}