{
  "type": "Feature",
  "properties": {
    "gn:admin1_code":"56.0",
    "gn:admin2_code":"26007.0",
    "gn:asciiname":"Kokwana",
    "gn:country_code":"NG",
    "gn:dem":324,
    "gn:feature_class":"P",
    "gn:feature_code":"PPL",
    "gn:name":"Kokwana",
    "gn:population":0,
    "gn:timezone":"Africa/Lagos",
    "iso:country":"NG",
    "wof:name":"Kokwana",
    "wof:placetype":"locality"
},
  "geometry": {"coordinates":[8.0025,8.79417],"type":"Point"}
}