{
  "type": "Feature",
  "properties": {
    "gn:admin1_code":"30.0",
    "gn:admin2_code":"24005",
    "gn:asciiname":"Niakaramadougou",
    "gn:country_code":"NG",
    "gn:dem":389,
    "gn:feature_class":"P",
    "gn:feature_code":"PPLL",
    "gn:name":"Niakaramadougou",
    "gn:population":0,
    "gn:timezone":"Africa/Abidjan",
    "iso:country":"NG",
    "wof:name":"Niakaramadougou",
    "wof:placetype":"locality"
},
  "geometry": {"coordinates":[-5.29111,8.66028],"type":"Point"}
}