{
  "type": "Feature",
  "properties": {
    "gn:admin1_code":"22.0",
    "gn:asciiname":"Itai Idoro",
    "gn:country_code":"NG",
    "gn:dem":22,
    "gn:feature_class":"P",
    "gn:feature_code":"PPL",
    "gn:name":"Itai Idoro",
    "gn:population":0,
    "gn:timezone":"Africa/Lagos",
    "iso:country":"NG",
    "wof:name":"Itai Idoro",
    "wof:placetype":"locality"
},
  "geometry": {"coordinates":[7.92151,5.28132],"type":"Point"}
}