{
  "type": "Feature",
  "properties": {
    "gn:admin1_code":"35.0",
    "gn:admin2_code":"2002.0",
    "gn:asciiname":"Safa",
    "gn:country_code":"NG",
    "gn:dem":380,
    "gn:feature_class":"P",
    "gn:feature_code":"PPL",
    "gn:name":"Safa",
    "gn:population":0,
    "gn:timezone":"Africa/Lagos",
    "iso:country":"NG",
    "name:ara_x_preferred":[
        "\u0635\u0641\u0627\u0621"
    ],
    "name:ceb_x_preferred":[
        "Safa"
    ],
    "name:deu_x_preferred":[
        "Safa"
    ],
    "name:fas_x_preferred":[
        "\u0635\u0641\u0627"
    ],
    "name:msa_x_preferred":[
        "Safa"
    ],
    "name:rus_x_preferred":[
        "\u0421\u0430\u0444\u0430"
    ],
    "name:swe_x_preferred":[
        "Safa"
    ],
    "wof:name":"Safa",
    "wof:placetype":"locality"
},
  "geometry": {"coordinates":[12.42083,8.98757],"type":"Point"}
}