{
  "type": "Feature",
  "properties": {
    "gn:admin1_code":"52.0",
    "gn:admin2_code":"6008.0",
    "gn:asciiname":"Okutukutu",
    "gn:country_code":"NG",
    "gn:dem":11,
    "gn:feature_class":"P",
    "gn:feature_code":"PPL",
    "gn:name":"Okutukutu",
    "gn:population":0,
    "gn:timezone":"Africa/Lagos",
    "iso:country":"NG",
    "wof:name":"Okutukutu",
    "wof:placetype":"neighbourhood"
},
  "geometry": {"coordinates":[6.36842,4.97626],"type":"Point"}
}