{
  "type": "Feature",
  "properties": {
    "gn:admin1_code":"55.0",
    "gn:asciiname":"Bubu",
    "gn:country_code":"NG",
    "gn:dem":301,
    "gn:feature_class":"P",
    "gn:feature_code":"PPL",
    "gn:name":"Bubu",
    "gn:population":0,
    "gn:timezone":"Africa/Lagos",
    "iso:country":"NG",
    "name:eng_x_preferred":[
        "Bubu"
    ],
    "name:eng_x_variant":[
        "Babu"
    ],
    "name:und_x_variant":[
        "Babu"
    ],
    "wof:name":"Bubu",
    "wof:placetype":"locality"
},
  "geometry": {"coordinates":[10.70156,10.04532],"type":"Point"}
}