{
  "type": "Feature",
  "properties": {
    "gn:admin1_code":"48.0",
    "gn:admin2_code":"29006.0",
    "gn:asciiname":"Isagba",
    "gn:country_code":"NG",
    "gn:dem":324,
    "gn:feature_class":"P",
    "gn:feature_code":"PPL",
    "gn:name":"Isagba",
    "gn:population":0,
    "gn:timezone":"Africa/Lagos",
    "iso:country":"NG",
    "wof:name":"Isagba",
    "wof:placetype":"locality"
},
  "geometry": {"coordinates":[5.2748,7.1515],"type":"Point"}
}