{
  "type": "Feature",
  "properties": {
    "gn:admin1_code":"35.0",
    "gn:admin2_code":"2014",
    "gn:asciiname":"Miskiti",
    "gn:country_code":"NG",
    "gn:dem":545,
    "gn:feature_class":"P",
    "gn:feature_code":"PPL",
    "gn:name":"Miskiti",
    "gn:population":0,
    "gn:timezone":"Africa/Lagos",
    "iso:country":"NG",
    "name:eng_x_preferred":[
        "Miskiti"
    ],
    "wof:name":"Miskiti",
    "wof:placetype":"locality"
},
  "geometry": {"coordinates":[13.25861,10.33582],"type":"Point"}
}