{
  "type": "Feature",
  "properties": {
    "gn:admin1_code":"27.0",
    "gn:admin2_code":"115.0",
    "gn:admin3_code":"11510",
    "gn:asciiname":"Abdungus",
    "gn:country_code":"NG",
    "gn:dem":293,
    "gn:feature_class":"P",
    "gn:feature_code":"PPL",
    "gn:name":"Abdungus",
    "gn:population":0,
    "gn:timezone":"Africa/Lagos",
    "iso:country":"NG",
    "name:und_x_variant":[
        "Umm Bok",
        "Mboko",
        "Abdungus"
    ],
    "wof:name":"Abdungus",
    "wof:placetype":"locality"
},
  "geometry": {"coordinates":[14.46576,12.33957],"type":"Point"}
}