{
  "type": "Feature",
  "properties": {
    "gn:admin1_code":"44.0",
    "gn:admin2_code":"702.0",
    "gn:admin3_code":"70207",
    "gn:asciiname":"Guba",
    "gn:country_code":"NG",
    "gn:dem":340,
    "gn:feature_class":"P",
    "gn:feature_code":"PPL",
    "gn:name":"Guba",
    "gn:population":0,
    "gn:timezone":"Africa/Lagos",
    "iso:country":"NG",
    "wof:name":"Guba",
    "wof:placetype":"locality"
},
  "geometry": {"coordinates":[11.42234,12.79484],"type":"Point"}
}