{
  "type": "Feature",
  "properties": {
    "gn:admin1_code":"44.0",
    "gn:admin2_code":"702.0",
    "gn:admin3_code":"70207",
    "gn:asciiname":"Guba",
    "gn:country_code":"NG",
    "gn:dem":340,
    "gn:feature_class":"P",
    "gn:feature_code":"PPL",
    "gn:name":"Guba",
    "gn:population":0,
    "gn:timezone":"Africa/Lagos",
    "iso:country":"NG",
    "name:aze_x_preferred":[
        "Quba"
    ],
    "name:ceb_x_preferred":[
        "Guba"
    ],
    "name:deu_x_preferred":[
        "Guba"
    ],
    "name:rus_x_preferred":[
        "\u0413\u0443\u0431\u0430"
    ],
    "name:sun_x_preferred":[
        "Guba"
    ],
    "name:swe_x_preferred":[
        "Guba"
    ],
    "name:tat_x_preferred":[
        "\u0413\u0443\u0431\u0430"
    ],
    "name:ukr_x_preferred":[
        "\u0413\u0443\u0431\u0430"
    ],
    "wof:name":"Guba",
    "wof:placetype":"locality"
},
  "geometry": {"coordinates":[11.42234,12.79484],"type":"Point"}
}