{
  "type": "Feature",
  "properties": {
    "gn:admin1_code":"48.0",
    "gn:admin2_code":"29014.0",
    "gn:asciiname":"Loipo",
    "gn:country_code":"NG",
    "gn:dem":16,
    "gn:feature_class":"P",
    "gn:feature_code":"PPL",
    "gn:name":"Loipo",
    "gn:population":0,
    "gn:timezone":"Africa/Lagos",
    "iso:country":"NG",
    "wof:name":"Loipo",
    "wof:placetype":"locality"
},
  "geometry": {"coordinates":[4.74492,6.40422],"type":"Point"}
}