{
  "type": "Feature",
  "properties": {
    "gn:admin1_code":"46.0",
    "gn:admin2_code":"5012.0",
    "gn:admin3_code":"BA1211",
    "gn:asciiname":"Gangai",
    "gn:country_code":"NG",
    "gn:dem":418,
    "gn:feature_class":"P",
    "gn:feature_code":"PPL",
    "gn:name":"Gangai",
    "gn:population":0,
    "gn:timezone":"Africa/Lagos",
    "iso:country":"NG",
    "wof:name":"Gangai",
    "wof:placetype":"locality"
},
  "geometry": {"coordinates":[10.48021,11.50292],"type":"Point"}
}