{
  "type": "Feature",
  "properties": {
    "gn:admin1_code":"16.0",
    "gn:admin2_code":"28015.0",
    "gn:asciiname":"Paipai",
    "gn:cc2":"NG",
    "gn:country_code":"NG",
    "gn:dem":123,
    "gn:feature_class":"P",
    "gn:feature_code":"PPL",
    "gn:name":"Paipai",
    "gn:population":0,
    "gn:timezone":"Africa/Lagos",
    "iso:country":"NG",
    "name:cat_x_preferred":[
        "Paipais"
    ],
    "name:hrv_x_preferred":[
        "Akwa\u2019ala Indijanci"
    ],
    "name:rus_x_preferred":[
        "\u041f\u0430\u0439\u043f\u0430\u0439"
    ],
    "name:spa_x_preferred":[
        "Paipai"
    ],
    "name:und_x_variant":[
        "Ategu"
    ],
    "wof:name":"Paipai",
    "wof:placetype":"locality"
},
  "geometry": {"coordinates":[3.61667,7.11667],"type":"Point"}
}