{
  "type": "Feature",
  "properties": {
    "gn:admin1_code":"52.0",
    "gn:admin2_code":"6003.0",
    "gn:asciiname":"Ofonibiri",
    "gn:country_code":"NG",
    "gn:dem":21,
    "gn:feature_class":"P",
    "gn:feature_code":"PPL",
    "gn:name":"Ofonibiri",
    "gn:population":0,
    "gn:timezone":"Africa/Lagos",
    "iso:country":"NG",
    "wof:name":"Ofonibiri",
    "wof:placetype":"locality"
},
  "geometry": {"coordinates":[6.27886,5.07059],"type":"Point"}
}