{
  "type": "Feature",
  "properties": {
    "gn:admin1_code":"23.0",
    "gn:asciiname":"Nasarawa",
    "gn:country_code":"NG",
    "gn:dem":571,
    "gn:feature_class":"P",
    "gn:feature_code":"PPL",
    "gn:name":"Nasarawa",
    "gn:population":0,
    "gn:timezone":"Africa/Lagos",
    "iso:country":"NG",
    "wof:name":"Nasarawa",
    "wof:placetype":"locality"
},
  "geometry": {"coordinates":[8.55042,11.23501],"type":"Point"}
}