{
  "type": "Feature",
  "properties": {
    "gn:admin1_code":"26.0",
    "gn:admin2_code":"7011",
    "gn:asciiname":"Akerigba",
    "gn:country_code":"NG",
    "gn:dem":192,
    "gn:feature_class":"P",
    "gn:feature_code":"PPL",
    "gn:name":"Akerigba",
    "gn:population":0,
    "gn:timezone":"Africa/Lagos",
    "iso:country":"NG",
    "wof:name":"Akerigba",
    "wof:placetype":"locality"
},
  "geometry": {"coordinates":[9.37233,7.0157],"type":"Point"}
}