{
  "type": "Feature",
  "properties": {
    "gn:admin1_code":"39.0",
    "gn:admin2_code":"18009.0",
    "gn:admin3_code":"JI1202",
    "gn:asciiname":"Dabi",
    "gn:country_code":"NG",
    "gn:dem":511,
    "gn:feature_class":"P",
    "gn:feature_code":"PPL",
    "gn:name":"Dabi",
    "gn:population":0,
    "gn:timezone":"Africa/Lagos",
    "iso:country":"NG",
    "wof:name":"Dabi",
    "wof:placetype":"locality"
},
  "geometry": {"coordinates":[8.18707,12.70629],"type":"Point"}
}