{
  "type": "Feature",
  "properties": {
    "gn:admin1_code":"39.0",
    "gn:admin2_code":"18001.0",
    "gn:admin3_code":"JI1607",
    "gn:asciiname":"Morso",
    "gn:country_code":"NG",
    "gn:dem":364,
    "gn:feature_class":"P",
    "gn:feature_code":"PPL",
    "gn:name":"Morso",
    "gn:population":0,
    "gn:timezone":"Africa/Lagos",
    "iso:country":"NG",
    "wof:name":"Morso",
    "wof:placetype":"locality"
},
  "geometry": {"coordinates":[9.65789,12.47379],"type":"Point"}
}