{
  "type": "Feature",
  "properties": {
    "gn:admin1_code":"50.0",
    "gn:admin2_code":"33013.0",
    "gn:asciiname":"Omuokip",
    "gn:country_code":"NG",
    "gn:dem":20,
    "gn:feature_class":"P",
    "gn:feature_code":"PPL",
    "gn:name":"Omuokip",
    "gn:population":0,
    "gn:timezone":"Africa/Lagos",
    "iso:country":"NG",
    "name:und_x_variant":[
        "Omuokiri"
    ],
    "wof:name":"Omuokip",
    "wof:placetype":"locality"
},
  "geometry": {"coordinates":[6.92424,4.92558],"type":"Point"}
}