{
  "type": "Feature",
  "properties": {
    "gn:admin1_code":"22.0",
    "gn:admin2_code":"9012.0",
    "gn:asciiname":"Obanlike",
    "gn:country_code":"NG",
    "gn:dem":266,
    "gn:feature_class":"P",
    "gn:feature_code":"PPL",
    "gn:name":"Obanlike",
    "gn:population":0,
    "gn:timezone":"Africa/Lagos",
    "iso:country":"NG",
    "name:und_x_variant":[
        "Abanliko",
        "Obanliko",
        "Obanlike"
    ],
    "wof:name":"Obanlike",
    "wof:placetype":"locality"
},
  "geometry": {"coordinates":[9.25198,6.60631],"type":"Point"}
}