{
  "type": "Feature",
  "properties": {
    "gn:admin1_code":"29.0",
    "gn:admin2_code":"20038.0",
    "gn:admin3_code":"KN0310",
    "gn:asciiname":"Gozarki",
    "gn:country_code":"NG",
    "gn:dem":512,
    "gn:feature_class":"P",
    "gn:feature_code":"PPL",
    "gn:name":"Gozarki",
    "gn:population":0,
    "gn:timezone":"Africa/Lagos",
    "iso:country":"NG",
    "wof:name":"Gozarki",
    "wof:placetype":"locality"
},
  "geometry": {"coordinates":[8.1276,12.1874],"type":"Point"}
}