{
  "type": "Feature",
  "properties": {
    "gn:admin1_code":"29.0",
    "gn:admin2_code":"20041.0",
    "gn:admin3_code":"KN2206",
    "gn:asciiname":"Tudun Kaya",
    "gn:country_code":"NG",
    "gn:dem":556,
    "gn:feature_class":"P",
    "gn:feature_code":"PPL",
    "gn:name":"Tudun Kaya",
    "gn:population":0,
    "gn:timezone":"Africa/Lagos",
    "iso:country":"NG",
    "wof:name":"Tudun Kaya",
    "wof:placetype":"locality"
},
  "geometry": {"coordinates":[7.93124,11.73161],"type":"Point"}
}