{
  "type": "Feature",
  "properties": {
    "gn:admin1_code":"35.0",
    "gn:admin2_code":"2007",
    "gn:asciiname":"Dadawaloji",
    "gn:country_code":"NG",
    "gn:dem":537,
    "gn:feature_class":"P",
    "gn:feature_code":"PPL",
    "gn:name":"Dadawaloji",
    "gn:population":0,
    "gn:timezone":"Africa/Lagos",
    "iso:country":"NG",
    "name:eng_x_preferred":[
        "Dadawaloji"
    ],
    "wof:name":"Dadawaloji",
    "wof:placetype":"locality"
},
  "geometry": {"coordinates":[13.1427,10.27227],"type":"Point"}
}