{
  "type": "Feature",
  "properties": {
    "gn:admin1_code":"45.0",
    "gn:admin2_code":"1004.0",
    "gn:asciiname":"Ndiokorukwu",
    "gn:country_code":"NG",
    "gn:dem":101,
    "gn:feature_class":"P",
    "gn:feature_code":"PPL",
    "gn:name":"Ndiokorukwu",
    "gn:population":0,
    "gn:timezone":"Africa/Lagos",
    "iso:country":"NG",
    "wof:name":"Ndiokorukwu",
    "wof:placetype":"locality"
},
  "geometry": {"coordinates":[7.62807,5.53251],"type":"Point"}
}