{
  "type": "Feature",
  "properties": {
    "gn:admin1_code":"49.0",
    "gn:admin2_code":"32002.0",
    "gn:asciiname":"Gusu",
    "gn:country_code":"NG",
    "gn:dem":941,
    "gn:feature_class":"P",
    "gn:feature_code":"PPL",
    "gn:name":"Gusu",
    "gn:population":0,
    "gn:timezone":"Africa/Lagos",
    "iso:country":"NG",
    "wof:name":"Gusu",
    "wof:placetype":"locality"
},
  "geometry": {"coordinates":[8.94362,10.18664],"type":"Point"}
}