{
  "type": "Feature",
  "properties": {
    "gn:admin1_code":"23.0",
    "gn:admin2_code":"19021.0",
    "gn:admin3_code":"KD2111",
    "gn:asciiname":"Kurmin Warji",
    "gn:country_code":"NG",
    "gn:dem":674,
    "gn:feature_class":"P",
    "gn:feature_code":"PPL",
    "gn:name":"Kurmin Warji",
    "gn:population":0,
    "gn:timezone":"Africa/Lagos",
    "iso:country":"NG",
    "wof:name":"Kurmin Warji",
    "wof:placetype":"locality"
},
  "geometry": {"coordinates":[8.05518,11.03275],"type":"Point"}
}