{
  "type": "Feature",
  "properties": {
    "gn:admin1_code":"16.0",
    "gn:admin2_code":"28013.0",
    "gn:asciiname":"Wasimi Okuta",
    "gn:country_code":"NG",
    "gn:dem":163,
    "gn:feature_class":"P",
    "gn:feature_code":"PPL",
    "gn:name":"Was\u00edm\u00ed Okuta",
    "gn:population":0,
    "gn:timezone":"Africa/Lagos",
    "iso:country":"NG",
    "wof:name":"Wasimi Okuta",
    "wof:placetype":"locality"
},
  "geometry": {"coordinates":[2.76667,7.53333],"type":"Point"}
}