{
  "type": "Feature",
  "properties": {
    "gn:admin1_code":"25.0",
    "gn:admin2_code":"4003",
    "gn:asciiname":"Iyiora",
    "gn:country_code":"NG",
    "gn:dem":26,
    "gn:feature_class":"P",
    "gn:feature_code":"PPL",
    "gn:name":"Iyiora",
    "gn:population":0,
    "gn:timezone":"Africa/Lagos",
    "iso:country":"NG",
    "wof:name":"Iyiora",
    "wof:placetype":"locality"
},
  "geometry": {"coordinates":[6.7965,6.43943],"type":"Point"}
}