{
  "type": "Feature",
  "properties": {
    "gn:admin1_code":"43.0",
    "gn:admin2_code":"35014",
    "gn:asciiname":"Katsina",
    "gn:country_code":"NG",
    "gn:dem":156,
    "gn:feature_class":"P",
    "gn:feature_code":"PPL",
    "gn:name":"Katsina",
    "gn:population":0,
    "gn:timezone":"Africa/Lagos",
    "iso:country":"NG",
    "name:ara_x_preferred":[
        "\u0643\u0627\u062a\u0633\u064a\u0646\u0627"
    ],
    "name:azb_x_preferred":[
        "\u06a9\u0627\u062a\u0633\u06cc\u0646\u0627"
    ],
    "name:bel_x_preferred":[
        "\u041a\u0430\u0446\u0456\u043d\u0430"
    ],
    "name:ben_x_preferred":[
        "\u0995\u09be\u09a4\u09b8\u09bf\u09a8\u09be"
    ],
    "name:bul_x_preferred":[
        "\u041a\u0430\u0442\u0441\u0438\u043d\u0430"
    ],
    "name:cat_x_preferred":[
        "Katsina"
    ],
    "name:ceb_x_preferred":[
        "Katsina"
    ],
    "name:dan_x_preferred":[
        "Katsina"
    ],
    "name:deu_x_preferred":[
        "Katsina"
    ],
    "name:ell_x_preferred":[
        "\u039a\u03b1\u03c4\u03c3\u03af\u03bd\u03b1"
    ],
    "name:epo_x_preferred":[
        "Katsina"
    ],
    "name:fas_x_preferred":[
        "\u06a9\u0627\u062a\u0633\u06cc\u0646\u0627"
    ],
    "name:fra_x_preferred":[
        "Katsina"
    ],
    "name:hau_x_preferred":[
        "Katsina"
    ],
    "name:heb_x_preferred":[
        "\u05e7\u05d8\u05e1\u05d9\u05e0\u05d4"
    ],
    "name:hin_x_preferred":[
        "\u0915\u0948\u091f\u094d\u0938\u093f\u0928\u093e"
    ],
    "name:hrv_x_preferred":[
        "Katsina"
    ],
    "name:hun_x_preferred":[
        "Katsina"
    ],
    "name:ibo_x_preferred":[
        "Katsina"
    ],
    "name:ile_x_preferred":[
        "Katsina"
    ],
    "name:ind_x_preferred":[
        "Katsina"
    ],
    "name:ita_x_preferred":[
        "Katsina"
    ],
    "name:jpn_x_preferred":[
        "\u30ab\u30c4\u30a3\u30ca"
    ],
    "name:kor_x_preferred":[
        "\uce74\uce58\ub098"
    ],
    "name:lat_x_preferred":[
        "Casena"
    ],
    "name:lit_x_preferred":[
        "Kacina"
    ],
    "name:nld_x_preferred":[
        "Katsina"
    ],
    "name:pol_x_preferred":[
        "Katsina"
    ],
    "name:por_x_preferred":[
        "Katsina"
    ],
    "name:ron_x_preferred":[
        "Katsina"
    ],
    "name:rus_x_preferred":[
        "\u041a\u0430\u0446\u0438\u043d\u0430"
    ],
    "name:spa_x_preferred":[
        "Katsina"
    ],
    "name:swe_x_preferred":[
        "Katsina"
    ],
    "name:tur_x_preferred":[
        "Katsina"
    ],
    "name:ukr_x_preferred":[
        "\u041a\u0430\u0446\u0438\u043d\u0430"
    ],
    "name:urd_x_preferred":[
        "\u06a9\u0627\u0679\u0633\u06cc\u0646\u0627"
    ],
    "name:vie_x_preferred":[
        "Katsina"
    ],
    "name:yor_x_preferred":[
        "K\u00e0ts\u00edn\u00e0"
    ],
    "name:zho_x_preferred":[
        "\u5361\u9f50\u7eb3"
    ],
    "wof:name":"Katsina",
    "wof:placetype":"neighbourhood"
},
  "geometry": {"coordinates":[9.77365,7.8363],"type":"Point"}
}