{
  "type": "Feature",
  "properties": {
    "gn:admin1_code":"40.0",
    "gn:admin2_code":"501.0",
    "gn:admin3_code":"50106",
    "gn:asciiname":"Rugan-Dodo",
    "gn:country_code":"NG",
    "gn:dem":264,
    "gn:feature_class":"P",
    "gn:feature_code":"PPL",
    "gn:name":"Rugan-Dodo",
    "gn:population":0,
    "gn:timezone":"Africa/Lagos",
    "iso:country":"NG",
    "wof:name":"Rugan-Dodo",
    "wof:placetype":"locality"
},
  "geometry": {"coordinates":[4.53059,12.27762],"type":"Point"}
}