{
  "type": "Feature",
  "properties": {
    "gn:admin1_code":"57.0",
    "gn:asciiname":"Gidan-Mallam-Azuka",
    "gn:country_code":"NG",
    "gn:dem":465,
    "gn:feature_class":"P",
    "gn:feature_code":"PPL",
    "gn:name":"Gidan-Mallam-Azuka",
    "gn:population":0,
    "gn:timezone":"Africa/Lagos",
    "iso:country":"NG",
    "wof:name":"Gidan-Mallam-Azuka",
    "wof:placetype":"locality"
},
  "geometry": {"coordinates":[6.06739,11.37909],"type":"Point"}
}