{
  "type": "Feature",
  "properties": {
    "gn:admin1_code":"25.0",
    "gn:admin2_code":"4020.0",
    "gn:asciiname":"Ndiokpalaeke",
    "gn:country_code":"NG",
    "gn:dem":74,
    "gn:feature_class":"P",
    "gn:feature_code":"PPL",
    "gn:name":"Ndiokpalaeke",
    "gn:population":0,
    "gn:timezone":"Africa/Lagos",
    "iso:country":"NG",
    "name:und_x_variant":[
        "Ndiopalaeke"
    ],
    "wof:name":"Ndiokpalaeke",
    "wof:placetype":"locality"
},
  "geometry": {"coordinates":[7.17116,6.03665],"type":"Point"}
}