{
  "type": "Feature",
  "properties": {
    "gn:admin1_code":"21.0",
    "gn:admin2_code":"3026.0",
    "gn:asciiname":"Ikot Abasi Akpan",
    "gn:country_code":"NG",
    "gn:dem":42,
    "gn:feature_class":"P",
    "gn:feature_code":"PPL",
    "gn:name":"Ikot Abasi Akpan",
    "gn:population":0,
    "gn:timezone":"Africa/Lagos",
    "iso:country":"NG",
    "wof:name":"Ikot Abasi Akpan",
    "wof:placetype":"locality"
},
  "geometry": {"coordinates":[7.7538,4.84414],"type":"Point"}
}