{
  "type": "Feature",
  "properties": {
    "gn:admin1_code":"27.0",
    "gn:admin2_code":"110",
    "gn:admin3_code":"11008",
    "gn:asciiname":"Kowori",
    "gn:country_code":"NG",
    "gn:dem":295,
    "gn:feature_class":"P",
    "gn:feature_code":"PPL",
    "gn:name":"Kowori",
    "gn:population":0,
    "gn:timezone":"Africa/Lagos",
    "iso:country":"NG",
    "wof:name":"Kowori",
    "wof:placetype":"locality"
},
  "geometry": {"coordinates":[13.55166,13.0463],"type":"Point"}
}