{
  "type": "Feature",
  "properties": {
    "gn:admin1_code":"23.0",
    "gn:admin2_code":"19022.0",
    "gn:admin3_code":"KD2202",
    "gn:asciiname":"Bato",
    "gn:country_code":"NG",
    "gn:dem":800,
    "gn:feature_class":"P",
    "gn:feature_code":"PPL",
    "gn:name":"Bato",
    "gn:population":0,
    "gn:timezone":"Africa/Lagos",
    "iso:country":"NG",
    "wof:name":"Bato",
    "wof:placetype":"locality"
},
  "geometry": {"coordinates":[8.28245,9.94646],"type":"Point"}
}