{
  "type": "Feature",
  "properties": {
    "gn:admin1_code":"23.0",
    "gn:admin2_code":"19022.0",
    "gn:admin3_code":"KD2202",
    "gn:asciiname":"Bato",
    "gn:country_code":"NG",
    "gn:dem":800,
    "gn:feature_class":"P",
    "gn:feature_code":"PPL",
    "gn:name":"Bato",
    "gn:population":0,
    "gn:timezone":"Africa/Lagos",
    "iso:country":"NG",
    "name:cat_x_preferred":[
        "Bat\u00f3"
    ],
    "name:ceb_x_preferred":[
        "Bato"
    ],
    "name:deu_x_preferred":[
        "Bato"
    ],
    "name:fra_x_preferred":[
        "Bato"
    ],
    "name:ind_x_preferred":[
        "Bato"
    ],
    "name:ita_x_preferred":[
        "Bato"
    ],
    "name:nld_x_preferred":[
        "Bato"
    ],
    "name:spa_x_preferred":[
        "Bato"
    ],
    "name:swe_x_preferred":[
        "Bato"
    ],
    "name:tgl_x_preferred":[
        "Bato"
    ],
    "name:war_x_preferred":[
        "Bato"
    ],
    "wof:name":"Bato",
    "wof:placetype":"locality"
},
  "geometry": {"coordinates":[8.28245,9.94646],"type":"Point"}
}