{
  "type": "Feature",
  "properties": {
    "gn:admin1_code":"35.0",
    "gn:asciiname":"Bahe",
    "gn:country_code":"NG",
    "gn:dem":355,
    "gn:feature_class":"P",
    "gn:feature_code":"PPL",
    "gn:name":"Bahe",
    "gn:population":0,
    "gn:timezone":"Africa/Lagos",
    "iso:country":"NG",
    "name:eng_x_preferred":[
        "Bahe"
    ],
    "wof:name":"Bahe",
    "wof:placetype":"locality"
},
  "geometry": {"coordinates":[11.92722,9.10033],"type":"Point"}
}