{
  "type": "Feature",
  "properties": {
    "gn:admin1_code":"16.0",
    "gn:admin2_code":"28004.0",
    "gn:asciiname":"Araromi",
    "gn:country_code":"NG",
    "gn:dem":84,
    "gn:feature_class":"P",
    "gn:feature_code":"PPL",
    "gn:name":"Araromi",
    "gn:population":0,
    "gn:timezone":"Africa/Lagos",
    "iso:country":"NG",
    "wof:name":"Araromi",
    "wof:placetype":"locality"
},
  "geometry": {"coordinates":[3.02218,6.96171],"type":"Point"}
}