{
  "type": "Feature",
  "properties": {
    "gn:admin1_code":"24.0",
    "gn:admin2_code":"427.0",
    "gn:admin3_code":"42706",
    "gn:asciiname":"Gyarta",
    "gn:country_code":"NG",
    "gn:dem":501,
    "gn:feature_class":"P",
    "gn:feature_code":"PPL",
    "gn:name":"Gyarta",
    "gn:population":0,
    "gn:timezone":"Africa/Lagos",
    "iso:country":"NG",
    "wof:name":"Gyarta",
    "wof:placetype":"locality"
},
  "geometry": {"coordinates":[8.02575,13.06246],"type":"Point"}
}