{
  "type": "Feature",
  "properties": {
    "gn:admin1_code":"31.0",
    "gn:admin2_code":"27010.0",
    "gn:asciiname":"Emijindadi",
    "gn:country_code":"NG",
    "gn:dem":104,
    "gn:feature_class":"P",
    "gn:feature_code":"PPL",
    "gn:name":"Emijindadi",
    "gn:population":0,
    "gn:timezone":"Africa/Lagos",
    "iso:country":"NG",
    "wof:name":"Emijindadi",
    "wof:placetype":"locality"
},
  "geometry": {"coordinates":[6.19843,9.4229],"type":"Point"}
}