{
  "type": "Feature",
  "properties": {
    "gn:admin1_code":"5.0",
    "gn:admin2_code":"25007.0",
    "gn:asciiname":"Sekungba",
    "gn:cc2":"NG",
    "gn:country_code":"NG",
    "gn:dem":31,
    "gn:feature_class":"P",
    "gn:feature_code":"PPL",
    "gn:name":"Sekungba",
    "gn:population":0,
    "gn:timezone":"Africa/Lagos",
    "iso:country":"NG",
    "name:und_x_variant":[
        "Shekungba",
        "Sekungba"
    ],
    "wof:name":"Sekungba",
    "wof:placetype":"locality"
},
  "geometry": {"coordinates":[3.88333,6.63333],"type":"Point"}
}