{
  "type": "Feature",
  "properties": {
    "gn:admin1_code":"45.0",
    "gn:admin2_code":"1013.0",
    "gn:asciiname":"Obunku",
    "gn:country_code":"NG",
    "gn:dem":14,
    "gn:feature_class":"P",
    "gn:feature_code":"PPL",
    "gn:name":"Obunku",
    "gn:population":0,
    "gn:timezone":"Africa/Lagos",
    "iso:country":"NG",
    "wof:name":"Obunku",
    "wof:placetype":"locality"
},
  "geometry": {"coordinates":[7.3799,4.88563],"type":"Point"}
}