{
  "type": "Feature",
  "properties": {
    "gn:admin1_code":"57.0",
    "gn:admin2_code":"805.0",
    "gn:admin3_code":"80503",
    "gn:asciiname":"Ngurmi",
    "gn:country_code":"NG",
    "gn:dem":510,
    "gn:feature_class":"P",
    "gn:feature_code":"PPL",
    "gn:name":"Ngurmi",
    "gn:population":0,
    "gn:timezone":"Africa/Lagos",
    "iso:country":"NG",
    "wof:name":"Ngurmi",
    "wof:placetype":"locality"
},
  "geometry": {"coordinates":[6.55525,11.86804],"type":"Point"}
}