{
  "type": "Feature",
  "properties": {
    "gn:admin1_code":"39.0",
    "gn:asciiname":"Kwarmaso",
    "gn:country_code":"NG",
    "gn:dem":399,
    "gn:feature_class":"P",
    "gn:feature_code":"PPL",
    "gn:name":"Kwarmaso",
    "gn:population":0,
    "gn:timezone":"Africa/Lagos",
    "iso:country":"NG",
    "wof:name":"Kwarmaso",
    "wof:placetype":"locality"
},
  "geometry": {"coordinates":[8.71838,12.56193],"type":"Point"}
}