{
  "type": "Feature",
  "properties": {
    "gn:admin1_code":"55.0",
    "gn:admin2_code":"16009.0",
    "gn:asciiname":"Jauro Baba",
    "gn:country_code":"NG",
    "gn:dem":367,
    "gn:feature_class":"P",
    "gn:feature_code":"PPL",
    "gn:name":"Jauro Baba",
    "gn:population":0,
    "gn:timezone":"Africa/Lagos",
    "iso:country":"NG",
    "wof:name":"Jauro Baba",
    "wof:placetype":"locality"
},
  "geometry": {"coordinates":[11.16789,11.04216],"type":"Point"}
}