{
  "type": "Feature",
  "properties": {
    "gn:admin1_code":"23.0",
    "gn:admin2_code":"19008.0",
    "gn:admin3_code":"KD0811",
    "gn:asciiname":"Kurmin Gwasa",
    "gn:country_code":"NG",
    "gn:dem":741,
    "gn:feature_class":"P",
    "gn:feature_code":"PPL",
    "gn:name":"Kurmin Gwasa",
    "gn:population":0,
    "gn:timezone":"Africa/Lagos",
    "iso:country":"NG",
    "name:und_x_variant":[
        "Kurmin Gwas",
        "Kurmin Gwasa"
    ],
    "wof:name":"Kurmin Gwasa",
    "wof:placetype":"locality"
},
  "geometry": {"coordinates":[7.93992,9.66579],"type":"Point"}
}