{
  "type": "Feature",
  "properties": {
    "gn:admin1_code":"43.0",
    "gn:asciiname":"Jibb Abawo",
    "gn:country_code":"NG",
    "gn:dem":130,
    "gn:feature_class":"P",
    "gn:feature_code":"PPL",
    "gn:name":"Jibb Abawo",
    "gn:population":0,
    "gn:timezone":"Africa/Lagos",
    "iso:country":"NG",
    "name:eng_x_preferred":[
        "Jibb Abawo"
    ],
    "wof:name":"Jibb Abawo",
    "wof:placetype":"locality"
},
  "geometry": {"coordinates":[11.04664,9.16601],"type":"Point"}
}