{
  "type": "Feature",
  "properties": {
    "gn:admin1_code":"29.0",
    "gn:admin2_code":"20011.0",
    "gn:admin3_code":"KN3610",
    "gn:asciiname":"Doka",
    "gn:country_code":"NG",
    "gn:dem":585,
    "gn:feature_class":"P",
    "gn:feature_code":"PPL",
    "gn:name":"Doka",
    "gn:population":0,
    "gn:timezone":"Africa/Lagos",
    "iso:country":"NG",
    "name:ceb_x_preferred":[
        "Doka"
    ],
    "name:deu_x_preferred":[
        "Doka"
    ],
    "name:swe_x_preferred":[
        "Doka"
    ],
    "wof:name":"Doka",
    "wof:placetype":"locality"
},
  "geometry": {"coordinates":[8.80822,11.30153],"type":"Point"}
}