{
  "type": "Feature",
  "properties": {
    "gn:admin1_code":"24.0",
    "gn:admin2_code":"428.0",
    "gn:admin3_code":"42810",
    "gn:asciiname":"Ardawa",
    "gn:country_code":"NG",
    "gn:dem":501,
    "gn:feature_class":"P",
    "gn:feature_code":"PPL",
    "gn:name":"Ardawa",
    "gn:population":0,
    "gn:timezone":"Africa/Lagos",
    "iso:country":"NG",
    "wof:name":"Ardawa",
    "wof:placetype":"locality"
},
  "geometry": {"coordinates":[7.5852,12.34168],"type":"Point"}
}