{
  "type": "Feature",
  "properties": {
    "gn:admin1_code":"55.0",
    "gn:admin2_code":"16001.0",
    "gn:asciiname":"Kombani",
    "gn:country_code":"NG",
    "gn:dem":448,
    "gn:feature_class":"P",
    "gn:feature_code":"PPL",
    "gn:name":"Kombani",
    "gn:population":0,
    "gn:timezone":"Africa/Lagos",
    "iso:country":"NG",
    "name:eng_x_preferred":[
        "Kombani Sarki"
    ],
    "name:eng_x_variant":[
        "Kombani"
    ],
    "wof:name":"Kombani",
    "wof:placetype":"locality"
},
  "geometry": {"coordinates":[10.97884,10.0885],"type":"Point"}
}