{
  "type": "Feature",
  "properties": {
    "gn:admin1_code":"45.0",
    "gn:admin2_code":"1004.0",
    "gn:asciiname":"Umuabia",
    "gn:country_code":"NG",
    "gn:dem":132,
    "gn:feature_class":"P",
    "gn:feature_code":"PPL",
    "gn:name":"Umuabia",
    "gn:population":0,
    "gn:timezone":"Africa/Lagos",
    "iso:country":"NG",
    "wof:name":"Umuabia",
    "wof:placetype":"locality"
},
  "geometry": {"coordinates":[7.58676,5.61596],"type":"Point"}
}