{
  "type": "Feature",
  "properties": {
    "gn:admin1_code":"35.0",
    "gn:asciiname":"Jauro Bakare",
    "gn:country_code":"NG",
    "gn:dem":255,
    "gn:feature_class":"P",
    "gn:feature_code":"PPL",
    "gn:name":"Jauro Bakare",
    "gn:population":0,
    "gn:timezone":"Africa/Lagos",
    "iso:country":"NG",
    "name:eng_x_preferred":[
        "Jauro Bakare"
    ],
    "wof:name":"Jauro Bakare",
    "wof:placetype":"locality"
},
  "geometry": {"coordinates":[12.0034,9.13955],"type":"Point"}
}