{
  "type": "Feature",
  "properties": {
    "gn:admin1_code":"36.0",
    "gn:asciiname":"Okegbe",
    "gn:country_code":"NG",
    "gn:dem":5,
    "gn:feature_class":"P",
    "gn:feature_code":"PPL",
    "gn:name":"Okegbe",
    "gn:population":0,
    "gn:timezone":"Africa/Lagos",
    "iso:country":"NG",
    "name:eng_x_preferred":[
        "Okegbe"
    ],
    "wof:name":"Okegbe",
    "wof:placetype":"locality"
},
  "geometry": {"coordinates":[5.21487,5.60047],"type":"Point"}
}