{
  "type": "Feature",
  "properties": {
    "gn:admin1_code":"50.0",
    "gn:admin2_code":"33004.0",
    "gn:asciiname":"Dannykiri",
    "gn:country_code":"NG",
    "gn:dem":4,
    "gn:feature_class":"P",
    "gn:feature_code":"PPL",
    "gn:name":"Dannykiri",
    "gn:population":0,
    "gn:timezone":"Africa/Lagos",
    "iso:country":"NG",
    "name:und_x_variant":[
        "Ikirikokiri",
        "Dannykiri"
    ],
    "wof:name":"Dannykiri",
    "wof:placetype":"locality"
},
  "geometry": {"coordinates":[6.53375,4.43466],"type":"Point"}
}