{
  "type": "Feature",
  "properties": {
    "gn:admin1_code":"37.0",
    "gn:admin2_code":"12017.0",
    "gn:asciiname":"Ukphototen",
    "gn:cc2":"NG",
    "gn:country_code":"NG",
    "gn:dem":178,
    "gn:feature_class":"P",
    "gn:feature_code":"PPL",
    "gn:name":"Ukphototen",
    "gn:population":0,
    "gn:timezone":"Africa/Lagos",
    "iso:country":"NG",
    "name:und_x_variant":[
        "Ukpototen",
        "Ukphototen"
    ],
    "wof:name":"Ukphototen",
    "wof:placetype":"locality"
},
  "geometry": {"coordinates":[5.86667,6.93333],"type":"Point"}
}