{
  "type": "Feature",
  "properties": {
    "gn:admin1_code":"50.0",
    "gn:admin2_code":"33013.0",
    "gn:asciiname":"Ahia",
    "gn:country_code":"NG",
    "gn:dem":44,
    "gn:feature_class":"P",
    "gn:feature_code":"PPL",
    "gn:name":"Ahia",
    "gn:population":0,
    "gn:timezone":"Africa/Lagos",
    "iso:country":"NG",
    "name:und_x_variant":[
        "Ihia",
        "Ahia"
    ],
    "wof:name":"Ahia",
    "wof:placetype":"locality"
},
  "geometry": {"coordinates":[6.96238,5.17546],"type":"Point"}
}