{
  "type": "Feature",
  "properties": {
    "gn:admin1_code":"43.0",
    "gn:admin2_code":"35002.0",
    "gn:asciiname":"Dukunapo",
    "gn:country_code":"NG",
    "gn:dem":270,
    "gn:feature_class":"P",
    "gn:feature_code":"PPL",
    "gn:name":"Dukunapo",
    "gn:population":0,
    "gn:timezone":"Africa/Lagos",
    "iso:country":"NG",
    "wof:name":"Dukunapo",
    "wof:placetype":"locality"
},
  "geometry": {"coordinates":[11.42334,8.59683],"type":"Point"}
}