{
  "type": "Feature",
  "properties": {
    "gn:admin1_code":"21.0",
    "gn:admin2_code":"3012.0",
    "gn:asciiname":"Iton Mong",
    "gn:country_code":"NG",
    "gn:dem":74,
    "gn:feature_class":"P",
    "gn:feature_code":"PPL",
    "gn:name":"Iton Mong",
    "gn:population":0,
    "gn:timezone":"Africa/Lagos",
    "iso:country":"NG",
    "wof:name":"Iton Mong",
    "wof:placetype":"locality"
},
  "geometry": {"coordinates":[7.79534,5.2897],"type":"Point"}
}