{
  "type": "Feature",
  "properties": {
    "gn:admin1_code":"57.0",
    "gn:admin2_code":"803.0",
    "gn:admin3_code":"80301",
    "gn:asciiname":"Kiyawa",
    "gn:country_code":"NG",
    "gn:dem":444,
    "gn:feature_class":"P",
    "gn:feature_code":"PPL",
    "gn:name":"Kiyawa",
    "gn:population":0,
    "gn:timezone":"Africa/Lagos",
    "iso:country":"NG",
    "name:ceb_x_preferred":[
        "Kiyawa"
    ],
    "name:fra_x_preferred":[
        "Kiyawa"
    ],
    "name:hau_x_preferred":[
        "Kiyawa"
    ],
    "name:ita_x_preferred":[
        "Kiyawa"
    ],
    "name:spa_x_preferred":[
        "Kiyawa"
    ],
    "name:und_x_variant":[
        "Kiawa",
        "Kiyawa"
    ],
    "wof:name":"Kiyawa",
    "wof:placetype":"locality"
},
  "geometry": {"coordinates":[6.80901,12.44149],"type":"Point"}
}