{
  "type": "Feature",
  "properties": {
    "gn:admin1_code":"51.0",
    "gn:admin2_code":"619.0",
    "gn:admin3_code":"61902",
    "gn:asciiname":"Gidima",
    "gn:country_code":"NG",
    "gn:dem":277,
    "gn:feature_class":"P",
    "gn:feature_code":"PPL",
    "gn:name":"Gidima",
    "gn:population":0,
    "gn:timezone":"Africa/Lagos",
    "iso:country":"NG",
    "name:und_x_variant":[
        "Tsalibawa",
        "Gidima"
    ],
    "wof:name":"Gidima",
    "wof:placetype":"locality"
},
  "geometry": {"coordinates":[5.03679,13.2666],"type":"Point"}
}