{
  "type": "Feature",
  "properties": {
    "gn:admin1_code":"23.0",
    "gn:admin2_code":"19001.0",
    "gn:admin3_code":"KD0101",
    "gn:asciiname":"Tandama",
    "gn:country_code":"NG",
    "gn:dem":684,
    "gn:feature_class":"P",
    "gn:feature_code":"PPL",
    "gn:name":"Tandama",
    "gn:population":0,
    "gn:timezone":"Africa/Lagos",
    "iso:country":"NG",
    "wof:name":"Tandama",
    "wof:placetype":"locality"
},
  "geometry": {"coordinates":[6.9408,10.70646],"type":"Point"}
}