{
  "type": "Feature",
  "properties": {
    "gn:admin1_code":"26.0",
    "gn:admin2_code":"7005",
    "gn:asciiname":"Atul",
    "gn:country_code":"NG",
    "gn:dem":202,
    "gn:feature_class":"P",
    "gn:feature_code":"PPL",
    "gn:name":"Atul",
    "gn:population":0,
    "gn:timezone":"Africa/Lagos",
    "iso:country":"NG",
    "name:guj_x_preferred":[
        "\u0a85\u0aa4\u0ac1\u0ab2"
    ],
    "name:tam_x_preferred":[
        "\u0b85\u0ba4\u0bc1\u0bb2\u0bcd"
    ],
    "wof:name":"Atul",
    "wof:placetype":"locality"
},
  "geometry": {"coordinates":[8.93736,7.44222],"type":"Point"}
}