{
  "type": "Feature",
  "properties": {
    "gn:admin1_code":"41.0",
    "gn:admin2_code":"23018.0",
    "gn:asciiname":"Efafo",
    "gn:country_code":"NG",
    "gn:dem":248,
    "gn:feature_class":"P",
    "gn:feature_code":"PPL",
    "gn:name":"Efafo",
    "gn:population":0,
    "gn:timezone":"Africa/Lagos",
    "iso:country":"NG",
    "name:und_x_variant":[
        "Ifa Afaw",
        "Efafo"
    ],
    "wof:name":"Efafo",
    "wof:placetype":"locality"
},
  "geometry": {"coordinates":[7.72352,7.1823],"type":"Point"}
}