{
  "type": "Feature",
  "properties": {
    "gn:admin1_code":"55.0",
    "gn:admin2_code":"16002.0",
    "gn:asciiname":"Unguan Kutare",
    "gn:country_code":"NG",
    "gn:dem":321,
    "gn:feature_class":"P",
    "gn:feature_code":"PPL",
    "gn:name":"Unguan Kutare",
    "gn:population":0,
    "gn:timezone":"Africa/Lagos",
    "iso:country":"NG",
    "wof:name":"Unguan Kutare",
    "wof:placetype":"locality"
},
  "geometry": {"coordinates":[11.61667,9.96667],"type":"Point"}
}