{
  "type": "Feature",
  "properties": {
    "gn:admin1_code":"56.0",
    "gn:admin2_code":"26005.0",
    "gn:asciiname":"Wunde",
    "gn:country_code":"NG",
    "gn:dem":216,
    "gn:feature_class":"P",
    "gn:feature_code":"PPL",
    "gn:name":"Wunde",
    "gn:population":0,
    "gn:timezone":"Africa/Lagos",
    "iso:country":"NG",
    "wof:name":"Wunde",
    "wof:placetype":"locality"
},
  "geometry": {"coordinates":[8.83333,8.28333],"type":"Point"}
}