{
  "type": "Feature",
  "properties": {
    "gn:admin1_code":"49.0",
    "gn:asciiname":"Lanyau",
    "gn:country_code":"NG",
    "gn:dem":272,
    "gn:feature_class":"P",
    "gn:feature_code":"PPL",
    "gn:name":"Lanyau",
    "gn:population":0,
    "gn:timezone":"Africa/Lagos",
    "iso:country":"NG",
    "wof:name":"Lanyau",
    "wof:placetype":"locality"
},
  "geometry": {"coordinates":[9.38422,8.96683],"type":"Point"}
}