{
  "type": "Feature",
  "properties": {
    "gn:admin1_code":"48.0",
    "gn:admin2_code":"29010.0",
    "gn:asciiname":"Upe",
    "gn:country_code":"NG",
    "gn:dem":13,
    "gn:feature_class":"P",
    "gn:feature_code":"PPL",
    "gn:name":"Upe",
    "gn:population":0,
    "gn:timezone":"Africa/Lagos",
    "iso:country":"NG",
    "wof:name":"Upe",
    "wof:placetype":"locality"
},
  "geometry": {"coordinates":[4.95346,6.07729],"type":"Point"}
}