{
  "type": "Feature",
  "properties": {
    "gn:admin1_code":"37.0",
    "gn:admin2_code":"12013.0",
    "gn:asciiname":"Obazagbon-Nugu",
    "gn:country_code":"NG",
    "gn:dem":81,
    "gn:feature_class":"P",
    "gn:feature_code":"PPL",
    "gn:name":"Obazagbon-Nugu",
    "gn:population":0,
    "gn:timezone":"Africa/Lagos",
    "iso:country":"NG",
    "name:eng_x_preferred":[
        "Obazagbon-Nugu"
    ],
    "name:eng_x_variant":[
        "Obazogbon"
    ],
    "name:und_x_variant":[
        "Obazogbon"
    ],
    "wof:name":"Obazagbon-Nugu",
    "wof:placetype":"locality"
},
  "geometry": {"coordinates":[6.08007,6.03585],"type":"Point"}
}