{
  "type": "Feature",
  "properties": {
    "gn:admin1_code":"36.0",
    "gn:admin2_code":"10020.0",
    "gn:asciiname":"Okpari",
    "gn:country_code":"NG",
    "gn:dem":11,
    "gn:feature_class":"P",
    "gn:feature_code":"PPL",
    "gn:name":"Okpari",
    "gn:population":0,
    "gn:timezone":"Africa/Lagos",
    "iso:country":"NG",
    "wof:name":"Okpari",
    "wof:placetype":"locality"
},
  "geometry": {"coordinates":[5.90372,5.45704],"type":"Point"}
}