{
  "type": "Feature",
  "properties": {
    "gn:admin1_code":"43.0",
    "gn:admin2_code":"35008",
    "gn:asciiname":"Gidan Agu",
    "gn:country_code":"NG",
    "gn:dem":113,
    "gn:feature_class":"P",
    "gn:feature_code":"PPL",
    "gn:name":"Gidan Agu",
    "gn:population":0,
    "gn:timezone":"Africa/Lagos",
    "iso:country":"NG",
    "wof:name":"Gidan Agu",
    "wof:placetype":"locality"
},
  "geometry": {"coordinates":[10.5255,8.7364],"type":"Point"}
}