{
  "type": "Feature",
  "properties": {
    "gn:admin1_code":"28.0",
    "gn:admin2_code":"17016.0",
    "gn:asciiname":"Umuoke",
    "gn:country_code":"NG",
    "gn:dem":83,
    "gn:feature_class":"P",
    "gn:feature_code":"PPL",
    "gn:name":"Umuoke",
    "gn:population":0,
    "gn:timezone":"Africa/Lagos",
    "iso:country":"NG",
    "wof:name":"Umuoke",
    "wof:placetype":"locality"
},
  "geometry": {"coordinates":[7.39877,5.56586],"type":"Point"}
}