{
  "type": "Feature",
  "properties": {
    "gn:admin1_code":"40.0",
    "gn:admin2_code":"512.0",
    "gn:admin3_code":"51202",
    "gn:asciiname":"Magarza",
    "gn:country_code":"NG",
    "gn:dem":233,
    "gn:feature_class":"P",
    "gn:feature_code":"PPL",
    "gn:name":"Magarza",
    "gn:population":0,
    "gn:timezone":"Africa/Lagos",
    "iso:country":"NG",
    "wof:name":"Magarza",
    "wof:placetype":"locality"
},
  "geometry": {"coordinates":[4.1707,12.292],"type":"Point"}
}