{
  "type": "Feature",
  "properties": {
    "gn:admin1_code":"52.0",
    "gn:admin2_code":"6004.0",
    "gn:asciiname":"Okokokiri",
    "gn:country_code":"NG",
    "gn:dem":5,
    "gn:feature_class":"P",
    "gn:feature_code":"PPL",
    "gn:name":"Okokokiri",
    "gn:population":0,
    "gn:timezone":"Africa/Lagos",
    "iso:country":"NG",
    "name:und_x_variant":[
        "Olokokiri",
        "Okokokiri"
    ],
    "wof:name":"Okokokiri",
    "wof:placetype":"locality"
},
  "geometry": {"coordinates":[6.31342,4.57167],"type":"Point"}
}