{
  "type": "Feature",
  "properties": {
    "gn:admin1_code":"31.0",
    "gn:admin2_code":"27010.0",
    "gn:asciiname":"Mikwegi",
    "gn:country_code":"NG",
    "gn:dem":195,
    "gn:feature_class":"P",
    "gn:feature_code":"PPL",
    "gn:name":"Mikwegi",
    "gn:population":0,
    "gn:timezone":"Africa/Lagos",
    "iso:country":"NG",
    "wof:name":"Mikwegi",
    "wof:placetype":"locality"
},
  "geometry": {"coordinates":[6.47937,9.27537],"type":"Point"}
}