{
  "type": "Feature",
  "properties": {
    "gn:admin1_code":"31.0",
    "gn:admin2_code":"27005",
    "gn:asciiname":"Bua",
    "gn:country_code":"NG",
    "gn:dem":287,
    "gn:feature_class":"P",
    "gn:feature_code":"PPL",
    "gn:name":"Bua",
    "gn:population":0,
    "gn:timezone":"Africa/Lagos",
    "iso:country":"NG",
    "name:ceb_x_preferred":[
        "Bua"
    ],
    "name:glg_x_preferred":[
        "Bua"
    ],
    "name:ind_x_preferred":[
        "Bua"
    ],
    "name:nld_x_preferred":[
        "Bua"
    ],
    "name:swe_x_preferred":[
        "Bua"
    ],
    "wof:name":"Bua",
    "wof:placetype":"locality"
},
  "geometry": {"coordinates":[6.59734,9.59806],"type":"Point"}
}