{
  "type": "Feature",
  "properties": {
    "gn:admin1_code":"48.0",
    "gn:admin2_code":"29012.0",
    "gn:asciiname":"Ago Oloja",
    "gn:country_code":"NG",
    "gn:dem":37,
    "gn:feature_class":"P",
    "gn:feature_code":"PPL",
    "gn:name":"Ago Oloja",
    "gn:population":0,
    "gn:timezone":"Africa/Lagos",
    "iso:country":"NG",
    "wof:name":"Ago Oloja",
    "wof:placetype":"locality"
},
  "geometry": {"coordinates":[4.96355,6.43168],"type":"Point"}
}