{
  "type": "Feature",
  "properties": {
    "gn:admin1_code":"22.0",
    "gn:asciiname":"Ikot-Uwa",
    "gn:country_code":"NG",
    "gn:dem":79,
    "gn:feature_class":"P",
    "gn:feature_code":"PPL",
    "gn:name":"Ikot-Uwa",
    "gn:population":0,
    "gn:timezone":"Africa/Lagos",
    "iso:country":"NG",
    "wof:name":"Ikot-Uwa",
    "wof:placetype":"locality"
},
  "geometry": {"coordinates":[7.9258,5.26792],"type":"Point"}
}