{
  "type": "Feature",
  "properties": {
    "gn:admin1_code":"11.0",
    "gn:admin2_code":"15004.0",
    "gn:asciiname":"Tagwar",
    "gn:cc2":"NG",
    "gn:country_code":"NG",
    "gn:dem":331,
    "gn:feature_class":"P",
    "gn:feature_code":"PPL",
    "gn:name":"Tagwar",
    "gn:population":0,
    "gn:timezone":"Africa/Lagos",
    "iso:country":"NG",
    "name:und_x_variant":[
        "Tagwai",
        "Tagwar"
    ],
    "wof:name":"Tagwar",
    "wof:placetype":"locality"
},
  "geometry": {"coordinates":[7.325,8.65167],"type":"Point"}
}