{
  "type": "Feature",
  "properties": {
    "gn:admin1_code":"57.0",
    "gn:admin2_code":"805.0",
    "gn:admin3_code":"80506",
    "gn:asciiname":"Guidan Bawa",
    "gn:country_code":"NG",
    "gn:dem":399,
    "gn:feature_class":"P",
    "gn:feature_code":"PPL",
    "gn:name":"Guidan Bawa",
    "gn:population":0,
    "gn:timezone":"Africa/Lagos",
    "iso:country":"NG",
    "name:und_x_variant":[
        "Gidan Bawa",
        "Guidan Bawa"
    ],
    "wof:name":"Guidan Bawa",
    "wof:placetype":"locality"
},
  "geometry": {"coordinates":[6.50443,12.33599],"type":"Point"}
}