{
  "type": "Feature",
  "properties": {
    "gn:admin1_code":"31.0",
    "gn:admin2_code":"27007.0",
    "gn:asciiname":"Ejikonagi",
    "gn:country_code":"NG",
    "gn:dem":84,
    "gn:feature_class":"P",
    "gn:feature_code":"PPL",
    "gn:name":"Ejikonagi",
    "gn:population":0,
    "gn:timezone":"Africa/Lagos",
    "iso:country":"NG",
    "wof:name":"Ejikonagi",
    "wof:placetype":"locality"
},
  "geometry": {"coordinates":[6.01667,8.91667],"type":"Point"}
}