{
  "type": "Feature",
  "properties": {
    "gn:admin1_code":"56.0",
    "gn:admin2_code":"26002.0",
    "gn:asciiname":"Amrana",
    "gn:cc2":"NG",
    "gn:country_code":"NG",
    "gn:dem":135,
    "gn:feature_class":"P",
    "gn:feature_code":"PPL",
    "gn:name":"Amrana",
    "gn:population":0,
    "gn:timezone":"Africa/Lagos",
    "iso:country":"NG",
    "name:und_x_variant":[
        "Amfana",
        "Amrana"
    ],
    "wof:name":"Amrana",
    "wof:placetype":"locality"
},
  "geometry": {"coordinates":[9.16667,8.16667],"type":"Point"}
}