{
  "type": "Feature",
  "properties": {
    "gn:admin1_code":"40.0",
    "gn:admin2_code":"518.0",
    "gn:admin3_code":"51804",
    "gn:asciiname":"Keniki",
    "gn:country_code":"NG",
    "gn:dem":181,
    "gn:feature_class":"P",
    "gn:feature_code":"PPL",
    "gn:name":"Keniki",
    "gn:population":0,
    "gn:timezone":"Africa/Lagos",
    "iso:country":"NG",
    "name:und_x_variant":[
        "Kainiki",
        "Keniki"
    ],
    "wof:name":"Keniki",
    "wof:placetype":"locality"
},
  "geometry": {"coordinates":[4.08696,11.91374],"type":"Point"}
}