{
  "type": "Feature",
  "properties": {
    "gn:admin1_code":"22.0",
    "gn:admin2_code":"9010.0",
    "gn:asciiname":"Mfum",
    "gn:country_code":"NG",
    "gn:dem":78,
    "gn:feature_class":"P",
    "gn:feature_code":"PPL",
    "gn:name":"Mfum",
    "gn:population":0,
    "gn:timezone":"Africa/Lagos",
    "iso:country":"NG",
    "wof:name":"Mfum",
    "wof:placetype":"locality"
},
  "geometry": {"coordinates":[8.8355,5.8362],"type":"Point"}
}