{
  "type": "Feature",
  "properties": {
    "gn:admin1_code":"32.0",
    "gn:admin2_code":"31024.0",
    "gn:asciiname":"Elemere",
    "gn:country_code":"NG",
    "gn:dem":387,
    "gn:feature_class":"P",
    "gn:feature_code":"PPL",
    "gn:name":"Elemere",
    "gn:population":0,
    "gn:timezone":"Africa/Lagos",
    "iso:country":"NG",
    "wof:name":"Elemere",
    "wof:placetype":"locality"
},
  "geometry": {"coordinates":[4.05,8.85],"type":"Point"}
}