{
  "type": "Feature",
  "properties": {
    "gn:admin1_code":"23.0",
    "gn:admin2_code":"19004",
    "gn:admin3_code":"KD0405",
    "gn:asciiname":"Ibago",
    "gn:country_code":"NG",
    "gn:dem":621,
    "gn:feature_class":"P",
    "gn:feature_code":"PPLS",
    "gn:name":"Ibago",
    "gn:population":0,
    "gn:timezone":"Africa/Lagos",
    "iso:country":"NG",
    "wof:name":"Ibago",
    "wof:placetype":"locality"
},
  "geometry": {"coordinates":[7.77476,10.79149],"type":"Point"}
}