{
  "type": "Feature",
  "properties": {
    "gn:admin1_code":"49.0",
    "gn:admin2_code":"32005",
    "gn:asciiname":"Zarazeng",
    "gn:country_code":"NG",
    "gn:dem":1306,
    "gn:feature_class":"P",
    "gn:feature_code":"PPL",
    "gn:name":"Zarazeng",
    "gn:population":0,
    "gn:timezone":"Africa/Lagos",
    "iso:country":"NG",
    "wof:name":"Zarazeng",
    "wof:placetype":"locality"
},
  "geometry": {"coordinates":[8.96154,9.8888],"type":"Point"}
}