{
  "type": "Feature",
  "properties": {
    "gn:admin1_code":"53.0",
    "gn:admin2_code":"11012",
    "gn:asciiname":"Umuezeoka-Iza",
    "gn:country_code":"NG",
    "gn:dem":136,
    "gn:feature_class":"P",
    "gn:feature_code":"PPL",
    "gn:name":"Umuezeoka-Iza",
    "gn:population":0,
    "gn:timezone":"Africa/Lagos",
    "iso:country":"NG",
    "wof:name":"Umuezeoka-Iza",
    "wof:placetype":"locality"
},
  "geometry": {"coordinates":[8.06777,6.67108],"type":"Point"}
}