{
  "type": "Feature",
  "properties": {
    "gn:admin1_code":"21.0",
    "gn:admin2_code":"3008.0",
    "gn:asciiname":"Mkpanak",
    "gn:country_code":"NG",
    "gn:dem":5,
    "gn:feature_class":"P",
    "gn:feature_code":"PPL",
    "gn:name":"Mkpanak",
    "gn:population":0,
    "gn:timezone":"Africa/Lagos",
    "iso:country":"NG",
    "wof:name":"Mkpanak",
    "wof:placetype":"locality"
},
  "geometry": {"coordinates":[7.99077,4.56656],"type":"Point"}
}