{
  "type": "Feature",
  "properties": {
    "gn:admin1_code":"41.0",
    "gn:admin2_code":"23016.0",
    "gn:asciiname":"Ogbono",
    "gn:country_code":"NG",
    "gn:dem":396,
    "gn:feature_class":"P",
    "gn:feature_code":"PPL",
    "gn:name":"Ogbono",
    "gn:population":0,
    "gn:timezone":"Africa/Lagos",
    "iso:country":"NG",
    "wof:name":"Ogbono",
    "wof:placetype":"locality"
},
  "geometry": {"coordinates":[6.15332,7.60298],"type":"Point"}
}