{
  "type": "Feature",
  "properties": {
    "gn:admin1_code":"26.0",
    "gn:admin2_code":"7004",
    "gn:asciiname":"Tyoga",
    "gn:country_code":"NG",
    "gn:dem":171,
    "gn:feature_class":"P",
    "gn:feature_code":"PPL",
    "gn:name":"Tyoga",
    "gn:population":0,
    "gn:timezone":"Africa/Lagos",
    "iso:country":"NG",
    "wof:name":"Tyoga",
    "wof:placetype":"locality"
},
  "geometry": {"coordinates":[9.26719,7.31343],"type":"Point"}
}