{
  "type": "Feature",
  "properties": {
    "gn:admin1_code":"26.0",
    "gn:admin2_code":"7021",
    "gn:asciiname":"Mbasongo",
    "gn:country_code":"NG",
    "gn:dem":188,
    "gn:feature_class":"P",
    "gn:feature_code":"PPL",
    "gn:name":"Mbasongo",
    "gn:population":0,
    "gn:timezone":"Africa/Lagos",
    "iso:country":"NG",
    "wof:name":"Mbasongo",
    "wof:placetype":"locality"
},
  "geometry": {"coordinates":[9.66021,7.62474],"type":"Point"}
}