{
  "type": "Feature",
  "properties": {
    "gn:admin1_code":"32.0",
    "gn:admin2_code":"31028.0",
    "gn:asciiname":"Asileke",
    "gn:cc2":"NG",
    "gn:country_code":"NG",
    "gn:dem":389,
    "gn:feature_class":"P",
    "gn:feature_code":"PPL",
    "gn:name":"Asileke",
    "gn:population":0,
    "gn:timezone":"Africa/Lagos",
    "iso:country":"NG",
    "name:und_x_variant":[
        "Ashelekke",
        "Asileke"
    ],
    "wof:name":"Asileke",
    "wof:placetype":"locality"
},
  "geometry": {"coordinates":[4.33333,8.28333],"type":"Point"}
}