{
  "type": "Feature",
  "properties": {
    "gn:admin1_code":"28.0",
    "gn:admin2_code":"17003.0",
    "gn:asciiname":"Umueze",
    "gn:country_code":"NG",
    "gn:dem":187,
    "gn:feature_class":"P",
    "gn:feature_code":"PPL",
    "gn:name":"Umueze",
    "gn:population":0,
    "gn:timezone":"Africa/Lagos",
    "iso:country":"NG",
    "wof:name":"Umueze",
    "wof:placetype":"locality"
},
  "geometry": {"coordinates":[7.3054,5.63247],"type":"Point"}
}