{
  "type": "Feature",
  "properties": {
    "gn:admin1_code":"57.0",
    "gn:admin2_code":"809.0",
    "gn:admin3_code":"80910",
    "gn:asciiname":"Tsibiri",
    "gn:country_code":"NG",
    "gn:dem":333,
    "gn:feature_class":"P",
    "gn:feature_code":"PPL",
    "gn:name":"Tsibiri",
    "gn:population":0,
    "gn:timezone":"Africa/Lagos",
    "iso:country":"NG",
    "wof:name":"Tsibiri",
    "wof:placetype":"locality"
},
  "geometry": {"coordinates":[6.42061,13.00985],"type":"Point"}
}