{
  "type": "Feature",
  "properties": {
    "gn:admin1_code":"27.0",
    "gn:admin2_code":"123.0",
    "gn:admin3_code":"12308",
    "gn:asciiname":"Kolori",
    "gn:country_code":"NG",
    "gn:dem":283,
    "gn:feature_class":"P",
    "gn:feature_code":"PPL",
    "gn:name":"Kolori",
    "gn:population":0,
    "gn:timezone":"Africa/Lagos",
    "iso:country":"NG",
    "wof:name":"Kolori",
    "wof:placetype":"locality"
},
  "geometry": {"coordinates":[14.02586,12.88944],"type":"Point"}
}