{
  "type": "Feature",
  "properties": {
    "gn:admin1_code":"44.0",
    "gn:admin2_code":"704.0",
    "gn:admin3_code":"70405",
    "gn:asciiname":"Jangasiri",
    "gn:country_code":"NG",
    "gn:dem":447,
    "gn:feature_class":"P",
    "gn:feature_code":"PPL",
    "gn:name":"Jangasiri",
    "gn:population":0,
    "gn:timezone":"Africa/Lagos",
    "iso:country":"NG",
    "name:und_x_variant":[
        "Janga",
        "Jangasiri"
    ],
    "wof:name":"Jangasiri",
    "wof:placetype":"locality"
},
  "geometry": {"coordinates":[11.22779,11.49105],"type":"Point"}
}