{
  "type": "Feature",
  "properties": {
    "gn:admin1_code":"39.0",
    "gn:admin2_code":"18026.0",
    "gn:admin3_code":"JI1402",
    "gn:asciiname":"Doma",
    "gn:country_code":"NG",
    "gn:dem":377,
    "gn:feature_class":"P",
    "gn:feature_code":"PPL",
    "gn:name":"Doma",
    "gn:population":0,
    "gn:timezone":"Africa/Lagos",
    "iso:country":"NG",
    "name:bar_x_preferred":[
        "Doma"
    ],
    "name:cat_x_preferred":[
        "Doma"
    ],
    "name:ceb_x_preferred":[
        "Doma"
    ],
    "name:deu_x_preferred":[
        "Doma"
    ],
    "name:fra_x_preferred":[
        "Doma"
    ],
    "name:ita_x_preferred":[
        "Doma"
    ],
    "name:oci_x_preferred":[
        "Doma"
    ],
    "name:rus_x_preferred":[
        "\u0414\u043e\u043c\u0430"
    ],
    "name:spa_x_preferred":[
        "Doma"
    ],
    "name:swe_x_preferred":[
        "Doma"
    ],
    "wof:name":"Doma",
    "wof:placetype":"locality"
},
  "geometry": {"coordinates":[9.79443,11.98119],"type":"Point"}
}