{
  "type": "Feature",
  "properties": {
    "gn:admin1_code":"39.0",
    "gn:admin2_code":"18026.0",
    "gn:admin3_code":"JI1402",
    "gn:asciiname":"Doma",
    "gn:country_code":"NG",
    "gn:dem":377,
    "gn:feature_class":"P",
    "gn:feature_code":"PPL",
    "gn:name":"Doma",
    "gn:population":0,
    "gn:timezone":"Africa/Lagos",
    "iso:country":"NG",
    "wof:name":"Doma",
    "wof:placetype":"locality"
},
  "geometry": {"coordinates":[9.79443,11.98119],"type":"Point"}
}