{
  "type": "Feature",
  "properties": {
    "gn:admin1_code":"23.0",
    "gn:asciiname":"Karefa",
    "gn:country_code":"NG",
    "gn:dem":559,
    "gn:feature_class":"P",
    "gn:feature_code":"PPL",
    "gn:name":"Karefa",
    "gn:population":0,
    "gn:timezone":"Africa/Lagos",
    "iso:country":"NG",
    "wof:name":"Karefa",
    "wof:placetype":"locality"
},
  "geometry": {"coordinates":[8.43936,11.32226],"type":"Point"}
}