{
  "type": "Feature",
  "properties": {
    "gn:admin1_code":"26.0",
    "gn:admin2_code":"7005.0",
    "gn:asciiname":"Acha",
    "gn:country_code":"NG",
    "gn:dem":122,
    "gn:feature_class":"P",
    "gn:feature_code":"PPL",
    "gn:name":"Acha",
    "gn:population":0,
    "gn:timezone":"Africa/Lagos",
    "iso:country":"NG",
    "name:ceb_x_preferred":[
        "Acha"
    ],
    "name:deu_x_preferred":[
        "Acha"
    ],
    "name:spa_x_preferred":[
        "Acha"
    ],
    "name:swa_x_preferred":[
        "Mto Acha"
    ],
    "name:swe_x_preferred":[
        "Acha"
    ],
    "wof:name":"Acha",
    "wof:placetype":"locality"
},
  "geometry": {"coordinates":[8.77464,7.53847],"type":"Point"}
}