{
  "type": "Feature",
  "properties": {
    "gn:admin1_code":"56.0",
    "gn:admin2_code":"26010.0",
    "gn:asciiname":"Wana",
    "gn:country_code":"NG",
    "gn:dem":669,
    "gn:feature_class":"P",
    "gn:feature_code":"PPL",
    "gn:name":"Wana",
    "gn:population":0,
    "gn:timezone":"Africa/Lagos",
    "iso:country":"NG",
    "name:ceb_x_preferred":[
        "Wana"
    ],
    "name:deu_x_preferred":[
        "Wana"
    ],
    "name:fra_x_preferred":[
        "Wana"
    ],
    "name:rus_x_preferred":[
        "\u0412\u0430\u043d\u0430"
    ],
    "name:spa_x_preferred":[
        "Wana"
    ],
    "name:srp_x_preferred":[
        "\u0412\u0430\u043d\u0430"
    ],
    "name:swe_x_preferred":[
        "Wana"
    ],
    "name:ukr_x_preferred":[
        "\u0412\u0430\u043d\u0430"
    ],
    "wof:name":"Wana",
    "wof:placetype":"locality"
},
  "geometry": {"coordinates":[8.41667,8.78333],"type":"Point"}
}