{
  "type": "Feature",
  "properties": {
    "gn:admin1_code":"24.0",
    "gn:admin2_code":"401.0",
    "gn:admin3_code":"40103",
    "gn:asciiname":"Zagezagi",
    "gn:country_code":"NG",
    "gn:dem":617,
    "gn:feature_class":"P",
    "gn:feature_code":"PPL",
    "gn:name":"Zagezagi",
    "gn:population":0,
    "gn:timezone":"Africa/Lagos",
    "iso:country":"NG",
    "wof:name":"Zagezagi",
    "wof:placetype":"locality"
},
  "geometry": {"coordinates":[7.54918,11.61839],"type":"Point"}
}