{
  "type": "Feature",
  "properties": {
    "gn:admin1_code":"49.0",
    "gn:admin2_code":"32015.0",
    "gn:asciiname":"Ataka",
    "gn:country_code":"NG",
    "gn:dem":1131,
    "gn:feature_class":"P",
    "gn:feature_code":"PPL",
    "gn:name":"Ataka",
    "gn:population":0,
    "gn:timezone":"Africa/Lagos",
    "iso:country":"NG",
    "name:ces_x_preferred":[
        "Ataka"
    ],
    "name:deu_x_preferred":[
        "Ataka"
    ],
    "name:jpn_x_preferred":[
        "\u30a2\u30bf\u30ab"
    ],
    "name:pol_x_preferred":[
        "Ataka"
    ],
    "name:ron_x_preferred":[
        "Atac"
    ],
    "name:rus_x_preferred":[
        "\u0410\u0442\u0430\u043a\u0430"
    ],
    "name:ukr_x_preferred":[
        "\u0410\u0442\u0430\u043a\u0430"
    ],
    "wof:name":"Ataka",
    "wof:placetype":"locality"
},
  "geometry": {"coordinates":[8.6007,9.58407],"type":"Point"}
}