{
  "type": "Feature",
  "properties": {
    "iso:country":"NG",
    "qs:gn_country":"NG",
    "qs:gn_fcode":"PPL",
    "qs:gn_pop":6161,
    "qs:name":"Adani",
    "qs:name_adm0":"Nigeria",
    "qs:name_adm1":"Enugu",
    "qs:photos":0,
    "qs:photos_1k":0,
    "qs:photos_9k":0,
    "qs:photos_9r":0,
    "qs:photos_all":0,
    "qs:photos_sr":0,
    "qs:placetype":"Town",
    "qs:pop_sr":"5",
    "qs:woe_adm0":23424908,
    "wd:wordcount":44,
    "wof:name":"Adani",
    "wof:placetype":"locality",
    "wof:population":6161
},
  "geometry": {"coordinates":[7.01117,6.73971],"type":"Point"}
}