{
  "type": "Feature",
  "properties": {
    "gn:admin1_code":"24.0",
    "gn:admin2_code":"404.0",
    "gn:admin3_code":"40410",
    "gn:asciiname":"Tsamia Lafia",
    "gn:country_code":"NG",
    "gn:dem":389,
    "gn:feature_class":"P",
    "gn:feature_code":"PPL",
    "gn:name":"Tsamia Lafia",
    "gn:population":0,
    "gn:timezone":"Africa/Lagos",
    "iso:country":"NG",
    "wof:name":"Tsamia Lafia",
    "wof:placetype":"locality"
},
  "geometry": {"coordinates":[8.86319,12.67629],"type":"Point"}
}