{
  "type": "Feature",
  "properties": {
    "gn:admin1_code":"26.0",
    "gn:admin2_code":"7011",
    "gn:asciiname":"Tsechima",
    "gn:country_code":"NG",
    "gn:dem":180,
    "gn:feature_class":"P",
    "gn:feature_code":"PPL",
    "gn:name":"Tsechima",
    "gn:population":0,
    "gn:timezone":"Africa/Lagos",
    "iso:country":"NG",
    "wof:name":"Tsechima",
    "wof:placetype":"locality"
},
  "geometry": {"coordinates":[9.49324,7.00973],"type":"Point"}
}