{
  "type": "Feature",
  "properties": {
    "gn:admin1_code":"51.0",
    "gn:admin2_code":"601.0",
    "gn:admin3_code":"60108",
    "gn:asciiname":"Zoro",
    "gn:country_code":"NG",
    "gn:dem":245,
    "gn:feature_class":"P",
    "gn:feature_code":"PPL",
    "gn:name":"Zoro",
    "gn:population":0,
    "gn:timezone":"Africa/Lagos",
    "iso:country":"NG",
    "wof:name":"Zoro",
    "wof:placetype":"locality"
},
  "geometry": {"coordinates":[4.83229,13.14498],"type":"Point"}
}