{
  "type": "Feature",
  "properties": {
    "gn:admin1_code":"27.0",
    "gn:admin2_code":"106.0",
    "gn:admin3_code":"10604",
    "gn:asciiname":"Wannasara",
    "gn:country_code":"NG",
    "gn:dem":468,
    "gn:feature_class":"P",
    "gn:feature_code":"PPL",
    "gn:name":"Wannasara",
    "gn:population":0,
    "gn:timezone":"Africa/Lagos",
    "iso:country":"NG",
    "wof:name":"Wannasara",
    "wof:placetype":"locality"
},
  "geometry": {"coordinates":[12.88628,10.84781],"type":"Point"}
}