{
  "type": "Feature",
  "properties": {
    "gn:admin1_code":"25.0",
    "gn:admin2_code":"4009.0",
    "gn:asciiname":"Orifite",
    "gn:country_code":"NG",
    "gn:dem":115,
    "gn:feature_class":"P",
    "gn:feature_code":"PPL",
    "gn:name":"Orifite",
    "gn:population":0,
    "gn:timezone":"Africa/Lagos",
    "iso:country":"NG",
    "name:eng_x_preferred":[
        "Orifite"
    ],
    "wof:name":"Orifite",
    "wof:placetype":"locality"
},
  "geometry": {"coordinates":[6.84918,6.006],"type":"Point"}
}