{
  "type": "Feature",
  "properties": {
    "gn:admin1_code":"50.0",
    "gn:admin2_code":"33023.0",
    "gn:asciiname":"Bunu Barana",
    "gn:country_code":"NG",
    "gn:dem":24,
    "gn:feature_class":"P",
    "gn:feature_code":"PPL",
    "gn:name":"Bunu Barana",
    "gn:population":0,
    "gn:timezone":"Africa/Lagos",
    "iso:country":"NG",
    "wof:name":"Bunu Barana",
    "wof:placetype":"locality"
},
  "geometry": {"coordinates":[7.24247,4.76213],"type":"Point"}
}