{
  "type": "Feature",
  "properties": {
    "gn:admin1_code":"50.0",
    "gn:admin2_code":"33010.0",
    "gn:asciiname":"Ovogo",
    "gn:country_code":"NG",
    "gn:dem":12,
    "gn:feature_class":"P",
    "gn:feature_code":"PPL",
    "gn:name":"Ovogo",
    "gn:population":0,
    "gn:timezone":"Africa/Lagos",
    "iso:country":"NG",
    "name:und_x_variant":[
        "Obogo"
    ],
    "wof:name":"Ovogo",
    "wof:placetype":"locality"
},
  "geometry": {"coordinates":[6.77227,4.94107],"type":"Point"}
}