{
  "type": "Feature",
  "properties": {
    "gn:admin1_code":"27.0",
    "gn:admin2_code":"102.0",
    "gn:admin3_code":"10206",
    "gn:asciiname":"Dakwama Mussa",
    "gn:country_code":"NG",
    "gn:dem":463,
    "gn:feature_class":"P",
    "gn:feature_code":"PPL",
    "gn:name":"Dakwama Mussa",
    "gn:population":0,
    "gn:timezone":"Africa/Lagos",
    "iso:country":"NG",
    "wof:name":"Dakwama Mussa",
    "wof:placetype":"locality"
},
  "geometry": {"coordinates":[13.09102,10.69839],"type":"Point"}
}