{
  "type": "Feature",
  "properties": {
    "gn:admin1_code":"31.0",
    "gn:admin2_code":"27020.0",
    "gn:asciiname":"Taberima",
    "gn:cc2":"NG",
    "gn:country_code":"NG",
    "gn:dem":414,
    "gn:feature_class":"P",
    "gn:feature_code":"PPL",
    "gn:name":"Taberima",
    "gn:population":0,
    "gn:timezone":"Africa/Lagos",
    "iso:country":"NG",
    "name:und_x_variant":[
        "Taberlma",
        "Taberima"
    ],
    "wof:name":"Taberima",
    "wof:placetype":"locality"
},
  "geometry": {"coordinates":[6.08333,10.41667],"type":"Point"}
}