{
  "type": "Feature",
  "properties": {
    "gn:admin1_code":"53.0",
    "gn:admin2_code":"11006",
    "gn:asciiname":"Inyibichiri",
    "gn:country_code":"NG",
    "gn:dem":62,
    "gn:feature_class":"P",
    "gn:feature_code":"PPL",
    "gn:name":"Inyibichiri",
    "gn:population":0,
    "gn:timezone":"Africa/Lagos",
    "iso:country":"NG",
    "name:und_x_variant":[
        "Iyibichiri"
    ],
    "wof:name":"Inyibichiri",
    "wof:placetype":"locality"
},
  "geometry": {"coordinates":[8.01257,6.07124],"type":"Point"}
}