{
  "type": "Feature",
  "properties": {
    "gn:admin1_code":"55.0",
    "gn:asciiname":"Lugo",
    "gn:country_code":"NG",
    "gn:dem":346,
    "gn:feature_class":"P",
    "gn:feature_code":"PPL",
    "gn:name":"Lugo",
    "gn:population":0,
    "gn:timezone":"Africa/Lagos",
    "iso:country":"NG",
    "name:eng_x_preferred":[
        "Lugo"
    ],
    "wof:name":"Lugo",
    "wof:placetype":"locality"
},
  "geometry": {"coordinates":[10.58148,10.8386],"type":"Point"}
}