{
  "type": "Feature",
  "properties": {
    "gn:admin1_code":"23.0",
    "gn:admin2_code":"19017.0",
    "gn:admin3_code":"KD1703",
    "gn:asciiname":"Nahani",
    "gn:country_code":"NG",
    "gn:dem":807,
    "gn:feature_class":"P",
    "gn:feature_code":"PPL",
    "gn:name":"Nahani",
    "gn:population":0,
    "gn:timezone":"Africa/Lagos",
    "iso:country":"NG",
    "wof:name":"Nahani",
    "wof:placetype":"locality"
},
  "geometry": {"coordinates":[8.58135,10.20953],"type":"Point"}
}