{
  "type": "Feature",
  "properties": {
    "gn:admin1_code":"16.0",
    "gn:admin2_code":"28006.0",
    "gn:asciiname":"Agbesi",
    "gn:country_code":"NG",
    "gn:dem":39,
    "gn:feature_class":"P",
    "gn:feature_code":"PPL",
    "gn:name":"Agbesi",
    "gn:population":0,
    "gn:timezone":"Africa/Lagos",
    "iso:country":"NG",
    "wof:name":"Agbesi",
    "wof:placetype":"neighbourhood"
},
  "geometry": {"coordinates":[3.21667,6.86667],"type":"Point"}
}