{
  "type": "Feature",
  "properties": {
    "gn:admin1_code":"51.0",
    "gn:admin2_code":"618.0",
    "gn:admin3_code":"61806",
    "gn:asciiname":"Tokwacho",
    "gn:country_code":"NG",
    "gn:dem":280,
    "gn:feature_class":"P",
    "gn:feature_code":"PPL",
    "gn:name":"Tokwacho",
    "gn:population":0,
    "gn:timezone":"Africa/Lagos",
    "iso:country":"NG",
    "name:und_x_variant":[
        "Tokwatcho",
        "Tokwacho"
    ],
    "wof:name":"Tokwacho",
    "wof:placetype":"locality"
},
  "geometry": {"coordinates":[5.0461,12.33324],"type":"Point"}
}