{
  "type": "Feature",
  "properties": {
    "gn:admin1_code":"27.0",
    "gn:admin2_code":"108.0",
    "gn:admin3_code":"10810",
    "gn:asciiname":"Magirta",
    "gn:country_code":"NG",
    "gn:dem":300,
    "gn:feature_class":"P",
    "gn:feature_code":"PPL",
    "gn:name":"Magirta",
    "gn:population":0,
    "gn:timezone":"Africa/Lagos",
    "iso:country":"NG",
    "wof:name":"Magirta",
    "wof:placetype":"locality"
},
  "geometry": {"coordinates":[14.15505,11.82032],"type":"Point"}
}