{
  "type": "Feature",
  "properties": {
    "gn:admin1_code":"51.0",
    "gn:admin2_code":"608.0",
    "gn:admin3_code":"60808",
    "gn:asciiname":"Tumbulumkum",
    "gn:country_code":"NG",
    "gn:dem":305,
    "gn:feature_class":"P",
    "gn:feature_code":"PPL",
    "gn:name":"Tumbulumkum",
    "gn:population":0,
    "gn:timezone":"Africa/Lagos",
    "iso:country":"NG",
    "wof:name":"Tumbulumkum",
    "wof:placetype":"locality"
},
  "geometry": {"coordinates":[5.16047,13.6943],"type":"Point"}
}