{
  "type": "Feature",
  "properties": {
    "gn:admin1_code":"24.0",
    "gn:admin2_code":"430.0",
    "gn:admin3_code":"43008",
    "gn:asciiname":"Rimi",
    "gn:country_code":"NG",
    "gn:dem":525,
    "gn:feature_class":"P",
    "gn:feature_code":"PPLA2",
    "gn:name":"Rimi",
    "gn:population":0,
    "gn:timezone":"Africa/Lagos",
    "iso:country":"NG",
    "name:ceb_x_preferred":[
        "Rimi"
    ],
    "name:deu_x_preferred":[
        "Rimi"
    ],
    "name:ita_x_preferred":[
        "Rimi"
    ],
    "name:swe_x_preferred":[
        "Rimi"
    ],
    "wof:name":"Rimi",
    "wof:placetype":"locality"
},
  "geometry": {"coordinates":[7.70974,12.8503],"type":"Point"}
}