{
  "type": "Feature",
  "properties": {
    "gn:admin1_code":"52.0",
    "gn:admin2_code":"6002.0",
    "gn:asciiname":"Raya Camp",
    "gn:country_code":"NG",
    "gn:dem":6,
    "gn:feature_class":"P",
    "gn:feature_code":"PPL",
    "gn:name":"Raya Camp",
    "gn:population":0,
    "gn:timezone":"Africa/Lagos",
    "iso:country":"NG",
    "name:eng_x_preferred":[
        "Raya Camp"
    ],
    "name:eng_x_variant":[
        "Raya"
    ],
    "wof:name":"Raya Camp",
    "wof:placetype":"locality"
},
  "geometry": {"coordinates":[5.56468,4.81324],"type":"Point"}
}