{
  "type": "Feature",
  "properties": {
    "gn:admin1_code":"56.0",
    "gn:admin2_code":"26002.0",
    "gn:asciiname":"Gamough",
    "gn:country_code":"NG",
    "gn:dem":185,
    "gn:feature_class":"P",
    "gn:feature_code":"PPL",
    "gn:name":"Gamough",
    "gn:population":0,
    "gn:timezone":"Africa/Lagos",
    "iso:country":"NG",
    "wof:name":"Gamough",
    "wof:placetype":"locality"
},
  "geometry": {"coordinates":[8.98333,8.28333],"type":"Point"}
}