{
  "type": "Feature",
  "properties": {
    "gn:admin1_code":"27.0",
    "gn:admin2_code":"102.0",
    "gn:admin3_code":"10209",
    "gn:asciiname":"Daggu",
    "gn:country_code":"NG",
    "gn:dem":423,
    "gn:feature_class":"P",
    "gn:feature_code":"PPL",
    "gn:name":"Daggu",
    "gn:population":0,
    "gn:timezone":"Africa/Lagos",
    "iso:country":"NG",
    "wof:name":"Daggu",
    "wof:placetype":"locality"
},
  "geometry": {"coordinates":[13.28069,10.85601],"type":"Point"}
}