{
  "type": "Feature",
  "properties": {
    "gn:admin1_code":"31.0",
    "gn:admin2_code":"27008",
    "gn:asciiname":"Kanko",
    "gn:country_code":"NG",
    "gn:dem":120,
    "gn:feature_class":"P",
    "gn:feature_code":"PPL",
    "gn:name":"Kanko",
    "gn:population":0,
    "gn:timezone":"Africa/Lagos",
    "iso:country":"NG",
    "wof:name":"Kanko",
    "wof:placetype":"locality"
},
  "geometry": {"coordinates":[5.86161,9.05824],"type":"Point"}
}