{
  "type": "Feature",
  "properties": {
    "gn:admin1_code":"35.0",
    "gn:admin2_code":"2011.0",
    "gn:asciiname":"Babalya",
    "gn:country_code":"NG",
    "gn:dem":474,
    "gn:feature_class":"P",
    "gn:feature_code":"PPL",
    "gn:name":"Babalya",
    "gn:population":0,
    "gn:timezone":"Africa/Lagos",
    "iso:country":"NG",
    "wof:name":"Babalya",
    "wof:placetype":"locality"
},
  "geometry": {"coordinates":[13.08486,10.04927],"type":"Point"}
}