{
  "type": "Feature",
  "properties": {
    "gn:admin1_code":"24.0",
    "gn:admin2_code":"419.0",
    "gn:admin3_code":"41904",
    "gn:asciiname":"Sarkin Noma",
    "gn:country_code":"NG",
    "gn:dem":589,
    "gn:feature_class":"P",
    "gn:feature_code":"PPL",
    "gn:name":"Sarkin Noma",
    "gn:population":0,
    "gn:timezone":"Africa/Lagos",
    "iso:country":"NG",
    "wof:name":"Sarkin Noma",
    "wof:placetype":"locality"
},
  "geometry": {"coordinates":[7.35834,11.96324],"type":"Point"}
}