{
  "type": "Feature",
  "properties": {
    "gn:admin1_code":"35.0",
    "gn:admin2_code":"2008.0",
    "gn:asciiname":"Jaranda",
    "gn:country_code":"NG",
    "gn:dem":421,
    "gn:feature_class":"P",
    "gn:feature_code":"PPL",
    "gn:name":"Jaranda",
    "gn:population":0,
    "gn:timezone":"Africa/Lagos",
    "iso:country":"NG",
    "wof:name":"Jaranda",
    "wof:placetype":"locality"
},
  "geometry": {"coordinates":[12.09845,8.59161],"type":"Point"}
}