{
  "type": "Feature",
  "properties": {
    "gn:admin1_code":"40.0",
    "gn:admin2_code":"501.0",
    "gn:admin3_code":"50105",
    "gn:asciiname":"Danwarai",
    "gn:country_code":"NG",
    "gn:dem":245,
    "gn:feature_class":"P",
    "gn:feature_code":"PPL",
    "gn:name":"Danwarai",
    "gn:population":0,
    "gn:timezone":"Africa/Lagos",
    "iso:country":"NG",
    "wof:name":"Danwarai",
    "wof:placetype":"locality"
},
  "geometry": {"coordinates":[4.41412,12.25417],"type":"Point"}
}