{
  "type": "Feature",
  "properties": {
    "gn:admin1_code":"40.0",
    "gn:admin2_code":"510.0",
    "gn:admin3_code":"51010",
    "gn:asciiname":"Bude",
    "gn:country_code":"NG",
    "gn:dem":281,
    "gn:feature_class":"P",
    "gn:feature_code":"PPL",
    "gn:name":"Bude",
    "gn:population":0,
    "gn:timezone":"Africa/Lagos",
    "iso:country":"NG",
    "name:bre_x_preferred":[
        "Porth Bud"
    ],
    "name:ceb_x_preferred":[
        "Bude"
    ],
    "name:cor_x_preferred":[
        "Porthbud"
    ],
    "name:cym_x_preferred":[
        "Bud"
    ],
    "name:deu_x_preferred":[
        "Bude"
    ],
    "name:eus_x_preferred":[
        "Bude"
    ],
    "name:fas_x_preferred":[
        "\u0628\u0648\u062f"
    ],
    "name:fra_x_preferred":[
        "Bude"
    ],
    "name:gle_x_preferred":[
        "Bude"
    ],
    "name:ita_x_preferred":[
        "Bude"
    ],
    "name:lat_x_preferred":[
        "Bude"
    ],
    "name:nld_x_preferred":[
        "Bude"
    ],
    "name:nno_x_preferred":[
        "Bude"
    ],
    "name:oss_x_preferred":[
        "\u0411\u044c\u044e\u0434"
    ],
    "name:pol_x_preferred":[
        "Bude"
    ],
    "name:por_x_preferred":[
        "Bude"
    ],
    "name:ron_x_preferred":[
        "Bude"
    ],
    "name:spa_x_preferred":[
        "Bude"
    ],
    "name:vol_x_preferred":[
        "Bude"
    ],
    "wof:name":"Bude",
    "wof:placetype":"locality"
},
  "geometry": {"coordinates":[4.70711,12.5804],"type":"Point"}
}