{
  "type": "Feature",
  "properties": {
    "gn:admin1_code":"50.0",
    "gn:admin2_code":"33010.0",
    "gn:asciiname":"Ahiaeke",
    "gn:country_code":"NG",
    "gn:dem":11,
    "gn:feature_class":"P",
    "gn:feature_code":"PPL",
    "gn:name":"Ahiaeke",
    "gn:population":0,
    "gn:timezone":"Africa/Lagos",
    "iso:country":"NG",
    "name:und_x_variant":[
        "Ahia-Eke"
    ],
    "wof:name":"Ahiaeke",
    "wof:placetype":"locality"
},
  "geometry": {"coordinates":[6.82686,4.93076],"type":"Point"}
}