{
  "type": "Feature",
  "properties": {
    "gn:admin1_code":"23.0",
    "gn:admin2_code":"19003.0",
    "gn:admin3_code":"KD0307",
    "gn:asciiname":"Muya",
    "gn:country_code":"NG",
    "gn:dem":611,
    "gn:feature_class":"P",
    "gn:feature_code":"PPL",
    "gn:name":"Muya",
    "gn:population":0,
    "gn:timezone":"Africa/Lagos",
    "iso:country":"NG",
    "name:und_x_variant":[
        "Muya Kadaga",
        "Muya"
    ],
    "wof:name":"Muya",
    "wof:placetype":"locality"
},
  "geometry": {"coordinates":[7.11531,10.749],"type":"Point"}
}