{
  "type": "Feature",
  "properties": {
    "gn:admin1_code":"35.0",
    "gn:asciiname":"Yeha",
    "gn:country_code":"NG",
    "gn:dem":383,
    "gn:feature_class":"P",
    "gn:feature_code":"PPL",
    "gn:name":"Yeha",
    "gn:population":0,
    "gn:timezone":"Africa/Lagos",
    "iso:country":"NG",
    "name:deu_x_preferred":[
        "Yeha"
    ],
    "name:eng_x_preferred":[
        "Yeha"
    ],
    "name:fra_x_preferred":[
        "Yeha"
    ],
    "name:heb_x_preferred":[
        "\u05d9\u05d7\u05d0"
    ],
    "name:hun_x_preferred":[
        "Yeha"
    ],
    "name:ita_x_preferred":[
        "Yeha"
    ],
    "name:pol_x_preferred":[
        "Yeha"
    ],
    "name:ron_x_preferred":[
        "Yeha"
    ],
    "name:rus_x_preferred":[
        "\u0419\u0435\u0445\u0430"
    ],
    "name:swa_x_preferred":[
        "Yeha"
    ],
    "name:tur_x_preferred":[
        "Yeha"
    ],
    "name:ukr_x_preferred":[
        "\u0419\u0435\u0445\u0430"
    ],
    "wof:name":"Yeha",
    "wof:placetype":"locality"
},
  "geometry": {"coordinates":[11.89868,9.04407],"type":"Point"}
}