{
  "type": "Feature",
  "properties": {
    "gn:admin1_code":"35.0",
    "gn:asciiname":"Yeha",
    "gn:country_code":"NG",
    "gn:dem":383,
    "gn:feature_class":"P",
    "gn:feature_code":"PPL",
    "gn:name":"Yeha",
    "gn:population":0,
    "gn:timezone":"Africa/Lagos",
    "iso:country":"NG",
    "name:eng_x_preferred":[
        "Yeha"
    ],
    "wof:name":"Yeha",
    "wof:placetype":"locality"
},
  "geometry": {"coordinates":[11.89868,9.04407],"type":"Point"}
}