{
  "type": "Feature",
  "properties": {
    "gn:admin1_code":"51.0",
    "gn:admin2_code":"613.0",
    "gn:admin3_code":"61309",
    "gn:asciiname":"Dan Karmawa",
    "gn:country_code":"NG",
    "gn:dem":308,
    "gn:feature_class":"P",
    "gn:feature_code":"PPL",
    "gn:name":"Dan Karmawa",
    "gn:population":0,
    "gn:timezone":"Africa/Lagos",
    "iso:country":"NG",
    "wof:name":"Dan Karmawa",
    "wof:placetype":"locality"
},
  "geometry": {"coordinates":[6.36667,13.45],"type":"Point"}
}