{
  "type": "Feature",
  "properties": {
    "gn:admin1_code":"24.0",
    "gn:admin2_code":"425.0",
    "gn:admin3_code":"42504",
    "gn:asciiname":"Yan Tashar",
    "gn:country_code":"NG",
    "gn:dem":636,
    "gn:feature_class":"P",
    "gn:feature_code":"PPL",
    "gn:name":"Yan Tashar",
    "gn:population":0,
    "gn:timezone":"Africa/Lagos",
    "iso:country":"NG",
    "wof:name":"Yan Tashar",
    "wof:placetype":"locality"
},
  "geometry": {"coordinates":[7.74564,11.96394],"type":"Point"}
}