{
  "type": "Feature",
  "properties": {
    "gn:admin1_code":"40.0",
    "gn:admin2_code":"503.0",
    "gn:admin3_code":"50301",
    "gn:asciiname":"Tibama",
    "gn:country_code":"NG",
    "gn:dem":209,
    "gn:feature_class":"P",
    "gn:feature_code":"PPL",
    "gn:name":"Tibama",
    "gn:population":0,
    "gn:timezone":"Africa/Lagos",
    "iso:country":"NG",
    "wof:name":"Tibama",
    "wof:placetype":"locality"
},
  "geometry": {"coordinates":[4.40028,12.6139],"type":"Point"}
}