{
  "type": "Feature",
  "properties": {
    "gn:admin1_code":"40.0",
    "gn:admin2_code":"518.0",
    "gn:admin3_code":"51803",
    "gn:asciiname":"Tarawa",
    "gn:country_code":"NG",
    "gn:dem":160,
    "gn:feature_class":"P",
    "gn:feature_code":"PPL",
    "gn:name":"Tarawa",
    "gn:population":0,
    "gn:timezone":"Africa/Lagos",
    "iso:country":"NG",
    "wof:name":"Tarawa",
    "wof:placetype":"locality"
},
  "geometry": {"coordinates":[3.97077,11.58841],"type":"Point"}
}