{
  "type": "Feature",
  "properties": {
    "gn:admin1_code":"46.0",
    "gn:admin2_code":"5008.0",
    "gn:admin3_code":"BA0812",
    "gn:asciiname":"Soro",
    "gn:country_code":"NG",
    "gn:dem":504,
    "gn:feature_class":"P",
    "gn:feature_code":"PPL",
    "gn:name":"Soro",
    "gn:population":0,
    "gn:timezone":"Africa/Lagos",
    "iso:country":"NG",
    "name:eng_x_preferred":[
        "Soro"
    ],
    "wof:name":"Soro",
    "wof:placetype":"locality"
},
  "geometry": {"coordinates":[10.29759,10.77737],"type":"Point"}
}