{
  "type": "Feature",
  "properties": {
    "gn:admin1_code":"46.0",
    "gn:admin2_code":"5008.0",
    "gn:admin3_code":"BA0812",
    "gn:asciiname":"Soro",
    "gn:country_code":"NG",
    "gn:dem":504,
    "gn:feature_class":"P",
    "gn:feature_code":"PPL",
    "gn:name":"Soro",
    "gn:population":0,
    "gn:timezone":"Africa/Lagos",
    "iso:country":"NG",
    "name:ceb_x_preferred":[
        "Soro"
    ],
    "name:deu_x_preferred":[
        "Soro"
    ],
    "name:eng_x_preferred":[
        "Soro"
    ],
    "name:fra_x_preferred":[
        "Soro"
    ],
    "name:glg_x_preferred":[
        "Soro"
    ],
    "name:hrv_x_preferred":[
        "Sor\u00f8"
    ],
    "name:ind_x_preferred":[
        "Soro"
    ],
    "name:ita_x_preferred":[
        "Soro"
    ],
    "name:nld_x_preferred":[
        "Soro"
    ],
    "name:por_x_preferred":[
        "Soro"
    ],
    "name:rus_x_preferred":[
        "\u0421\u043e\u0440\u043e"
    ],
    "name:swe_x_preferred":[
        "Soro"
    ],
    "name:ukr_x_preferred":[
        "\u0421\u043e\u0440\u043e"
    ],
    "wof:name":"Soro",
    "wof:placetype":"locality"
},
  "geometry": {"coordinates":[10.29759,10.77737],"type":"Point"}
}