{
  "type": "Feature",
  "properties": {
    "gn:admin1_code":"35.0",
    "gn:admin2_code":"2010",
    "gn:asciiname":"Humbuli",
    "gn:country_code":"NG",
    "gn:dem":565,
    "gn:feature_class":"P",
    "gn:feature_code":"PPL",
    "gn:name":"Humbuli",
    "gn:population":0,
    "gn:timezone":"Africa/Lagos",
    "iso:country":"NG",
    "name:eng_x_preferred":[
        "Humbuli"
    ],
    "wof:name":"Humbuli",
    "wof:placetype":"locality"
},
  "geometry": {"coordinates":[13.48132,10.80815],"type":"Point"}
}