{
  "type": "Feature",
  "properties": {
    "gn:admin1_code":"32.0",
    "gn:admin2_code":"31025.0",
    "gn:asciiname":"Olojuoro",
    "gn:country_code":"NG",
    "gn:dem":113,
    "gn:feature_class":"P",
    "gn:feature_code":"PPL",
    "gn:name":"Olojuoro",
    "gn:population":0,
    "gn:timezone":"Africa/Lagos",
    "iso:country":"NG",
    "wof:name":"Olojuoro",
    "wof:placetype":"locality"
},
  "geometry": {"coordinates":[3.98333,7.18333],"type":"Point"}
}