{
  "type": "Feature",
  "properties": {
    "gn:admin1_code":"46.0",
    "gn:admin2_code":"5018.0",
    "gn:admin3_code":"BA1807",
    "gn:asciiname":"Dabbo Sarari",
    "gn:country_code":"NG",
    "gn:dem":835,
    "gn:feature_class":"P",
    "gn:feature_code":"PPL",
    "gn:name":"Dabbo Sarari",
    "gn:population":0,
    "gn:timezone":"Africa/Lagos",
    "iso:country":"NG",
    "wof:name":"Dabbo Sarari",
    "wof:placetype":"locality"
},
  "geometry": {"coordinates":[9.20583,10.22758],"type":"Point"}
}