{
  "type": "Feature",
  "properties": {
    "gn:admin1_code":"21.0",
    "gn:admin2_code":"3029.0",
    "gn:asciiname":"Issiet",
    "gn:country_code":"NG",
    "gn:dem":55,
    "gn:feature_class":"P",
    "gn:feature_code":"PPL",
    "gn:name":"Issiet",
    "gn:population":0,
    "gn:timezone":"Africa/Lagos",
    "iso:country":"NG",
    "name:und_x_variant":[
        "Isiel",
        "Issiet"
    ],
    "wof:name":"Issiet",
    "wof:placetype":"locality"
},
  "geometry": {"coordinates":[8.075,4.9398],"type":"Point"}
}