{
  "type": "Feature",
  "properties": {
    "gn:admin1_code":"22.0",
    "gn:admin2_code":"9002.0",
    "gn:asciiname":"Abbiati",
    "gn:country_code":"NG",
    "gn:dem":9,
    "gn:feature_class":"P",
    "gn:feature_code":"PPL",
    "gn:name":"Abbiati",
    "gn:population":0,
    "gn:timezone":"Africa/Lagos",
    "iso:country":"NG",
    "wof:name":"Abbiati",
    "wof:placetype":"locality"
},
  "geometry": {"coordinates":[8.4832,5.094],"type":"Point"}
}