{
  "type": "Feature",
  "properties": {
    "gn:admin1_code":"24.0",
    "gn:admin2_code":"411.0",
    "gn:admin3_code":"41108",
    "gn:asciiname":"Shagalle",
    "gn:country_code":"NG",
    "gn:dem":498,
    "gn:feature_class":"P",
    "gn:feature_code":"PPL",
    "gn:name":"Shagalle",
    "gn:population":0,
    "gn:timezone":"Africa/Lagos",
    "iso:country":"NG",
    "name:und_x_variant":[
        "Shargalle",
        "Shagalle"
    ],
    "wof:name":"Shagalle",
    "wof:placetype":"locality"
},
  "geometry": {"coordinates":[8.10601,12.95803],"type":"Point"}
}