{
  "type": "Feature",
  "properties": {
    "gn:admin1_code":"56.0",
    "gn:admin2_code":"26011.0",
    "gn:asciiname":"Iyorugwa",
    "gn:country_code":"NG",
    "gn:dem":186,
    "gn:feature_class":"P",
    "gn:feature_code":"PPL",
    "gn:name":"Iyorugwa",
    "gn:population":0,
    "gn:timezone":"Africa/Lagos",
    "iso:country":"NG",
    "wof:name":"Iyorugwa",
    "wof:placetype":"locality"
},
  "geometry": {"coordinates":[8.85,8.35],"type":"Point"}
}