{
  "type": "Feature",
  "properties": {
    "gn:admin1_code":"22.0",
    "gn:admin2_code":"9016",
    "gn:asciiname":"Edep",
    "gn:country_code":"NG",
    "gn:dem":125,
    "gn:feature_class":"P",
    "gn:feature_code":"PPL",
    "gn:name":"Edep",
    "gn:population":0,
    "gn:timezone":"Africa/Lagos",
    "iso:country":"NG",
    "wof:name":"Edep",
    "wof:placetype":"locality"
},
  "geometry": {"coordinates":[8.65474,6.4703],"type":"Point"}
}