{
  "type": "Feature",
  "properties": {
    "gn:admin1_code":"27.0",
    "gn:admin2_code":"115.0",
    "gn:admin3_code":"11503",
    "gn:asciiname":"Suwa",
    "gn:country_code":"NG",
    "gn:dem":297,
    "gn:feature_class":"P",
    "gn:feature_code":"PPL",
    "gn:name":"Suwa",
    "gn:population":0,
    "gn:timezone":"Africa/Lagos",
    "iso:country":"NG",
    "name:ceb_x_preferred":[
        "Suwa"
    ],
    "name:deu_x_preferred":[
        "Suwa"
    ],
    "name:epo_x_preferred":[
        "Su\u016da"
    ],
    "name:fra_x_preferred":[
        "Suwa"
    ],
    "name:mlg_x_preferred":[
        "Suwa"
    ],
    "name:pol_x_preferred":[
        "Suwa"
    ],
    "name:por_x_preferred":[
        "Suwa"
    ],
    "name:swe_x_preferred":[
        "Suwa"
    ],
    "name:ukr_x_preferred":[
        "\u0421\u0443\u0432\u0430"
    ],
    "wof:name":"Suwa",
    "wof:placetype":"locality"
},
  "geometry": {"coordinates":[14.28941,11.93152],"type":"Point"}
}