{
  "type": "Feature",
  "properties": {
    "gn:admin1_code":"51.0",
    "gn:admin2_code":"606.0",
    "gn:admin3_code":"60603",
    "gn:asciiname":"Kotohari",
    "gn:country_code":"NG",
    "gn:dem":233,
    "gn:feature_class":"P",
    "gn:feature_code":"PPL",
    "gn:name":"Kotohari",
    "gn:population":0,
    "gn:timezone":"Africa/Lagos",
    "iso:country":"NG",
    "name:und_x_variant":[
        "Kuafuri",
        "Kutufari",
        "Kotohari"
    ],
    "wof:name":"Kotohari",
    "wof:placetype":"locality"
},
  "geometry": {"coordinates":[4.74178,13.48414],"type":"Point"}
}