{
  "type": "Feature",
  "properties": {
    "gn:admin1_code":"39.0",
    "gn:admin2_code":"18008.0",
    "gn:admin3_code":"JI1105",
    "gn:asciiname":"Gadala",
    "gn:country_code":"NG",
    "gn:dem":442,
    "gn:feature_class":"P",
    "gn:feature_code":"PPL",
    "gn:name":"Gadala",
    "gn:population":0,
    "gn:timezone":"Africa/Lagos",
    "iso:country":"NG",
    "wof:name":"Gadala",
    "wof:placetype":"locality"
},
  "geometry": {"coordinates":[9.91903,11.28532],"type":"Point"}
}