{
  "type": "Feature",
  "properties": {
    "gn:admin1_code":"39.0",
    "gn:admin2_code":"18013.0",
    "gn:admin3_code":"JI0101",
    "gn:asciiname":"Banyali",
    "gn:country_code":"NG",
    "gn:dem":362,
    "gn:feature_class":"P",
    "gn:feature_code":"PPL",
    "gn:name":"Banyali",
    "gn:population":0,
    "gn:timezone":"Africa/Lagos",
    "iso:country":"NG",
    "wof:name":"Banyali",
    "wof:placetype":"locality"
},
  "geometry": {"coordinates":[9.98608,12.36075],"type":"Point"}
}