{
  "type": "Feature",
  "properties": {
    "gn:admin1_code":"16.0",
    "gn:admin2_code":"28008.0",
    "gn:asciiname":"Uba",
    "gn:country_code":"NG",
    "gn:dem":22,
    "gn:feature_class":"P",
    "gn:feature_code":"PPL",
    "gn:name":"Uba",
    "gn:population":0,
    "gn:timezone":"Africa/Lagos",
    "iso:country":"NG",
    "name:ceb_x_preferred":[
        "Uba"
    ],
    "name:fra_x_preferred":[
        "Uba"
    ],
    "name:hye_x_preferred":[
        "\u0548\u0582\u0562\u0561"
    ],
    "name:kaz_x_preferred":[
        "\u0423\u0431\u0430"
    ],
    "name:pol_x_preferred":[
        "Uba"
    ],
    "name:spa_x_preferred":[
        "UBA"
    ],
    "name:swe_x_preferred":[
        "Uba"
    ],
    "name:ukr_x_preferred":[
        "\u0423\u0431\u0430"
    ],
    "wof:name":"Uba",
    "wof:placetype":"locality"
},
  "geometry": {"coordinates":[4.15267,6.62896],"type":"Point"}
}