{
  "type": "Feature",
  "properties": {
    "gn:admin1_code":"16.0",
    "gn:admin2_code":"28008.0",
    "gn:asciiname":"Uba",
    "gn:country_code":"NG",
    "gn:dem":22,
    "gn:feature_class":"P",
    "gn:feature_code":"PPL",
    "gn:name":"Uba",
    "gn:population":0,
    "gn:timezone":"Africa/Lagos",
    "iso:country":"NG",
    "wof:name":"Uba",
    "wof:placetype":"locality"
},
  "geometry": {"coordinates":[4.15267,6.62896],"type":"Point"}
}