{
  "type": "Feature",
  "properties": {
    "gn:admin1_code":"47.0",
    "gn:admin2_code":"14014.0",
    "gn:asciiname":"Umualu-Ugwuoba",
    "gn:country_code":"NG",
    "gn:dem":80,
    "gn:feature_class":"P",
    "gn:feature_code":"PPL",
    "gn:name":"Umualu-Ugwuoba",
    "gn:population":0,
    "gn:timezone":"Africa/Lagos",
    "iso:country":"NG",
    "name:und_x_variant":[
        "Umualu-Ugwoioba"
    ],
    "wof:name":"Umualu-Ugwuoba",
    "wof:placetype":"locality"
},
  "geometry": {"coordinates":[7.16258,6.24682],"type":"Point"}
}