{
  "type": "Feature",
  "properties": {
    "gn:admin1_code":"26.0",
    "gn:admin2_code":"7005",
    "gn:asciiname":"Amee",
    "gn:country_code":"NG",
    "gn:dem":110,
    "gn:feature_class":"P",
    "gn:feature_code":"PPL",
    "gn:name":"Amee",
    "gn:population":0,
    "gn:timezone":"Africa/Lagos",
    "iso:country":"NG",
    "wof:name":"Amee",
    "wof:placetype":"locality"
},
  "geometry": {"coordinates":[8.75978,7.45076],"type":"Point"}
}