{
  "type": "Feature",
  "properties": {
    "gn:admin1_code":"30.0",
    "gn:admin2_code":"24001.0",
    "gn:asciiname":"Akunwun",
    "gn:cc2":"NG",
    "gn:country_code":"NG",
    "gn:dem":385,
    "gn:feature_class":"P",
    "gn:feature_code":"PPL",
    "gn:name":"Akunwun",
    "gn:population":0,
    "gn:timezone":"Africa/Lagos",
    "iso:country":"NG",
    "name:und_x_variant":[
        "Awton",
        "Akunwun"
    ],
    "wof:name":"Akunwun",
    "wof:placetype":"locality"
},
  "geometry": {"coordinates":[4.41667,8.35],"type":"Point"}
}