{
  "type": "Feature",
  "properties": {
    "gn:admin1_code":"46.0",
    "gn:admin2_code":"5009.0",
    "gn:admin3_code":"BA0912",
    "gn:asciiname":"Kurba",
    "gn:country_code":"NG",
    "gn:dem":469,
    "gn:feature_class":"P",
    "gn:feature_code":"PPL",
    "gn:name":"Kurba",
    "gn:population":0,
    "gn:timezone":"Africa/Lagos",
    "iso:country":"NG",
    "wof:name":"Kurba",
    "wof:placetype":"locality"
},
  "geometry": {"coordinates":[10.2067,11.2877],"type":"Point"}
}