{
  "type": "Feature",
  "properties": {
    "gn:admin1_code":"26.0",
    "gn:admin2_code":"7005",
    "gn:asciiname":"Uve",
    "gn:country_code":"NG",
    "gn:dem":160,
    "gn:feature_class":"P",
    "gn:feature_code":"PPL",
    "gn:name":"Uve",
    "gn:population":0,
    "gn:timezone":"Africa/Lagos",
    "iso:country":"NG",
    "name:spa_x_preferred":[
        "Uve"
    ],
    "wof:name":"Uve",
    "wof:placetype":"locality"
},
  "geometry": {"coordinates":[8.78709,7.33662],"type":"Point"}
}