{
  "type": "Feature",
  "properties": {
    "gn:admin1_code":"40.0",
    "gn:admin2_code":"508.0",
    "gn:admin3_code":"50808",
    "gn:asciiname":"Finguila",
    "gn:country_code":"NG",
    "gn:dem":220,
    "gn:feature_class":"P",
    "gn:feature_code":"PPL",
    "gn:name":"Finguila",
    "gn:population":0,
    "gn:timezone":"Africa/Lagos",
    "iso:country":"NG",
    "name:und_x_variant":[
        "Fingilla",
        "Finguila"
    ],
    "wof:name":"Finguila",
    "wof:placetype":"locality"
},
  "geometry": {"coordinates":[3.77863,11.89867],"type":"Point"}
}