{
  "type": "Feature",
  "properties": {
    "gn:admin1_code":"43.0",
    "gn:admin2_code":"35013.0",
    "gn:asciiname":"Gidan Isa",
    "gn:country_code":"NG",
    "gn:dem":182,
    "gn:feature_class":"P",
    "gn:feature_code":"PPL",
    "gn:name":"Gidan Isa",
    "gn:population":0,
    "gn:timezone":"Africa/Lagos",
    "iso:country":"NG",
    "wof:name":"Gidan Isa",
    "wof:placetype":"locality"
},
  "geometry": {"coordinates":[9.81423,6.8607],"type":"Point"}
}