{
  "type": "Feature",
  "properties": {
    "gn:admin1_code":"43.0",
    "gn:admin2_code":"35001",
    "gn:asciiname":"Garin Baba Audu Ja",
    "gn:country_code":"NG",
    "gn:dem":192,
    "gn:feature_class":"P",
    "gn:feature_code":"PPL",
    "gn:name":"Garin Baba Audu Ja",
    "gn:population":0,
    "gn:timezone":"Africa/Lagos",
    "iso:country":"NG",
    "wof:name":"Garin Baba Audu Ja",
    "wof:placetype":"locality"
},
  "geometry": {"coordinates":[11.09662,8.82724],"type":"Point"}
}