{
  "type": "Feature",
  "properties": {
    "gn:admin1_code":"45.0",
    "gn:admin2_code":"1003.0",
    "gn:asciiname":"Amuvi",
    "gn:country_code":"NG",
    "gn:dem":27,
    "gn:feature_class":"P",
    "gn:feature_code":"PPL",
    "gn:name":"Amuvi",
    "gn:population":0,
    "gn:timezone":"Africa/Lagos",
    "iso:country":"NG",
    "wof:name":"Amuvi",
    "wof:placetype":"locality"
},
  "geometry": {"coordinates":[7.87393,5.40716],"type":"Point"}
}