{
  "type": "Feature",
  "properties": {
    "gn:admin1_code":"35.0",
    "gn:admin2_code":"2015.0",
    "gn:asciiname":"Girimburum",
    "gn:country_code":"NG",
    "gn:dem":1043,
    "gn:feature_class":"P",
    "gn:feature_code":"PPL",
    "gn:name":"Girimburum",
    "gn:population":0,
    "gn:timezone":"Africa/Lagos",
    "iso:country":"NG",
    "wof:name":"Girimburum",
    "wof:placetype":"locality"
},
  "geometry": {"coordinates":[13.40056,10.12717],"type":"Point"}
}