{
  "type": "Feature",
  "properties": {
    "gn:admin1_code":"27.0",
    "gn:admin2_code":"107.0",
    "gn:admin3_code":"10701",
    "gn:asciiname":"Warawara",
    "gn:country_code":"NG",
    "gn:dem":472,
    "gn:feature_class":"P",
    "gn:feature_code":"PPL",
    "gn:name":"Warawara",
    "gn:population":0,
    "gn:timezone":"Africa/Lagos",
    "iso:country":"NG",
    "wof:name":"Warawara",
    "wof:placetype":"locality"
},
  "geometry": {"coordinates":[12.5093,10.97561],"type":"Point"}
}