{
  "type": "Feature",
  "properties": {
    "gn:admin1_code":"16.0",
    "gn:admin2_code":"28006.0",
    "gn:asciiname":"Ikeja",
    "gn:country_code":"NG",
    "gn:dem":63,
    "gn:feature_class":"P",
    "gn:feature_code":"PPL",
    "gn:name":"Ikeja",
    "gn:population":0,
    "gn:timezone":"Africa/Lagos",
    "iso:country":"NG",
    "name:ast_x_preferred":[
        "Ikeja"
    ],
    "name:azb_x_preferred":[
        "\u0627\u06cc\u06a9\u062c\u0627"
    ],
    "name:cat_x_preferred":[
        "Ikeja"
    ],
    "name:ceb_x_preferred":[
        "Ikeja"
    ],
    "name:deu_x_preferred":[
        "Ikeja"
    ],
    "name:epo_x_preferred":[
        "Ikeja"
    ],
    "name:fas_x_preferred":[
        "\u0627\u06cc\u06a9\u062c\u0627"
    ],
    "name:fra_x_preferred":[
        "Ikeja"
    ],
    "name:hau_x_preferred":[
        "Ikeja"
    ],
    "name:ibo_x_preferred":[
        "Ikeja"
    ],
    "name:ita_x_preferred":[
        "Ikeja"
    ],
    "name:jpn_x_preferred":[
        "\u30a4\u30b1\u30b8\u30e3"
    ],
    "name:kor_x_preferred":[
        "\uc774\ucf00\uc790"
    ],
    "name:nld_x_preferred":[
        "Ikeja"
    ],
    "name:pol_x_preferred":[
        "Ikeja"
    ],
    "name:por_x_preferred":[
        "Ikeja"
    ],
    "name:ron_x_preferred":[
        "Ikeja"
    ],
    "name:rus_x_preferred":[
        "\u0418\u043a\u0435\u0434\u0436\u0430"
    ],
    "name:spa_x_preferred":[
        "Ikeja"
    ],
    "name:swe_x_preferred":[
        "Ikeja"
    ],
    "name:ukr_x_preferred":[
        "\u0406\u043a\u0435\u0434\u0436\u0430"
    ],
    "name:urd_x_preferred":[
        "\u0627\u06a9\u06cc\u062c\u0627"
    ],
    "name:yor_x_preferred":[
        "Ikeja"
    ],
    "name:zho_x_preferred":[
        "\u4f0a\u51f1\u8cc8"
    ],
    "wof:name":"Ikeja",
    "wof:placetype":"locality"
},
  "geometry": {"coordinates":[3.23333,6.95],"type":"Point"}
}