{
  "type": "Feature",
  "properties": {
    "gn:admin1_code":"16.0",
    "gn:admin2_code":"28006.0",
    "gn:asciiname":"Ikeja",
    "gn:country_code":"NG",
    "gn:dem":63,
    "gn:feature_class":"P",
    "gn:feature_code":"PPL",
    "gn:name":"Ikeja",
    "gn:population":0,
    "gn:timezone":"Africa/Lagos",
    "iso:country":"NG",
    "wof:name":"Ikeja",
    "wof:placetype":"locality"
},
  "geometry": {"coordinates":[3.23333,6.95],"type":"Point"}
}