{
  "type": "Feature",
  "properties": {
    "gn:admin1_code":"39.0",
    "gn:admin2_code":"18008.0",
    "gn:admin3_code":"JI1105",
    "gn:asciiname":"Samongara",
    "gn:country_code":"NG",
    "gn:dem":429,
    "gn:feature_class":"P",
    "gn:feature_code":"PPL",
    "gn:name":"Samongara",
    "gn:population":0,
    "gn:timezone":"Africa/Lagos",
    "iso:country":"NG",
    "wof:name":"Samongara",
    "wof:placetype":"locality"
},
  "geometry": {"coordinates":[9.85649,11.2383],"type":"Point"}
}