{
  "type": "Feature",
  "properties": {
    "gn:admin1_code":"23.0",
    "gn:admin2_code":"19002.0",
    "gn:admin3_code":"KD0202",
    "gn:asciiname":"Sheppi",
    "gn:country_code":"NG",
    "gn:dem":602,
    "gn:feature_class":"P",
    "gn:feature_code":"PPL",
    "gn:name":"Sheppi",
    "gn:population":0,
    "gn:timezone":"Africa/Lagos",
    "iso:country":"NG",
    "wof:name":"Sheppi",
    "wof:placetype":"locality"
},
  "geometry": {"coordinates":[7.16667,10.26667],"type":"Point"}
}