{
  "type": "Feature",
  "properties": {
    "gn:admin1_code":"16.0",
    "gn:admin2_code":"28001.0",
    "gn:asciiname":"Lukosi",
    "gn:country_code":"NG",
    "gn:dem":77,
    "gn:feature_class":"P",
    "gn:feature_code":"PPL",
    "gn:name":"Lukosi",
    "gn:population":0,
    "gn:timezone":"Africa/Lagos",
    "iso:country":"NG",
    "wof:name":"Lukosi",
    "wof:placetype":"locality"
},
  "geometry": {"coordinates":[3.25,7.21667],"type":"Point"}
}