{
  "type": "Feature",
  "properties": {
    "gn:admin1_code":"30.0",
    "gn:admin2_code":"24012.0",
    "gn:asciiname":"Jeunkunnu",
    "gn:cc2":"NG",
    "gn:country_code":"NG",
    "gn:dem":335,
    "gn:feature_class":"P",
    "gn:feature_code":"PPL",
    "gn:name":"Jeunkunnu",
    "gn:population":0,
    "gn:timezone":"Africa/Lagos",
    "iso:country":"NG",
    "name:und_x_variant":[
        "Jehunkunu",
        "Jeunkunnu"
    ],
    "wof:name":"Jeunkunnu",
    "wof:placetype":"locality"
},
  "geometry": {"coordinates":[4.45,8.76667],"type":"Point"}
}