{
  "type": "Feature",
  "properties": {
    "gn:admin1_code":"40.0",
    "gn:admin2_code":"508.0",
    "gn:admin3_code":"50811",
    "gn:asciiname":"Tungan-Nuhubanu",
    "gn:country_code":"NG",
    "gn:dem":209,
    "gn:feature_class":"P",
    "gn:feature_code":"PPL",
    "gn:name":"Tungan-Nuhubanu",
    "gn:population":0,
    "gn:timezone":"Africa/Lagos",
    "iso:country":"NG",
    "wof:name":"Tungan-Nuhubanu",
    "wof:placetype":"locality"
},
  "geometry": {"coordinates":[3.92385,11.82711],"type":"Point"}
}