{
  "type": "Feature",
  "properties": {
    "gn:admin1_code":"35.0",
    "gn:admin2_code":"2008.0",
    "gn:asciiname":"Tasso",
    "gn:country_code":"NG",
    "gn:dem":396,
    "gn:feature_class":"P",
    "gn:feature_code":"PPL",
    "gn:name":"Tasso",
    "gn:population":0,
    "gn:timezone":"Africa/Lagos",
    "iso:country":"NG",
    "name:bul_x_preferred":[
        "\u0422\u0430\u0441\u043e"
    ],
    "name:cat_x_preferred":[
        "Tasso"
    ],
    "name:ceb_x_preferred":[
        "Tasso"
    ],
    "name:deu_x_preferred":[
        "Tasso"
    ],
    "name:fin_x_preferred":[
        "Tasso"
    ],
    "name:ita_x_preferred":[
        "Tasso"
    ],
    "name:nld_x_preferred":[
        "Tasso"
    ],
    "name:pol_x_preferred":[
        "Tasso"
    ],
    "name:por_x_preferred":[
        "Tasso"
    ],
    "name:spa_x_preferred":[
        "Tasso"
    ],
    "name:srp_x_preferred":[
        "Taso"
    ],
    "name:swe_x_preferred":[
        "Tasso"
    ],
    "name:ukr_x_preferred":[
        "\u0422\u0430\u0441\u0441\u043e"
    ],
    "wof:name":"Tasso",
    "wof:placetype":"locality"
},
  "geometry": {"coordinates":[12.10611,8.7813],"type":"Point"}
}