{
  "type": "Feature",
  "properties": {
    "gn:admin1_code":"43.0",
    "gn:admin2_code":"35012",
    "gn:asciiname":"Mbayugh",
    "gn:country_code":"NG",
    "gn:dem":171,
    "gn:feature_class":"P",
    "gn:feature_code":"PPL",
    "gn:name":"Mbayugh",
    "gn:population":0,
    "gn:timezone":"Africa/Lagos",
    "iso:country":"NG",
    "wof:name":"Mbayugh",
    "wof:placetype":"locality"
},
  "geometry": {"coordinates":[9.90826,7.50091],"type":"Point"}
}