{
  "type": "Feature",
  "properties": {
    "gn:admin1_code":"32.0",
    "gn:admin2_code":"31002.0",
    "gn:asciiname":"Oloje",
    "gn:country_code":"NG",
    "gn:dem":247,
    "gn:feature_class":"P",
    "gn:feature_code":"PPL",
    "gn:name":"Oloje",
    "gn:population":0,
    "gn:timezone":"Africa/Lagos",
    "iso:country":"NG",
    "wof:name":"Oloje",
    "wof:placetype":"neighbourhood"
},
  "geometry": {"coordinates":[3.91,7.58778],"type":"Point"}
}