{
  "type": "Feature",
  "properties": {
    "gn:admin1_code":"48.0",
    "gn:admin2_code":"29010.0",
    "gn:asciiname":"Ogidigba",
    "gn:country_code":"NG",
    "gn:dem":9,
    "gn:feature_class":"P",
    "gn:feature_code":"PPL",
    "gn:name":"Ogidigba",
    "gn:population":0,
    "gn:timezone":"Africa/Lagos",
    "iso:country":"NG",
    "wof:name":"Ogidigba",
    "wof:placetype":"locality"
},
  "geometry": {"coordinates":[4.89297,6.16473],"type":"Point"}
}