{
  "type": "Feature",
  "properties": {
    "gn:admin1_code":"43.0",
    "gn:admin2_code":"35001",
    "gn:asciiname":"Garin Musa Gauri",
    "gn:country_code":"NG",
    "gn:dem":144,
    "gn:feature_class":"P",
    "gn:feature_code":"PPL",
    "gn:name":"Garin Musa Gauri",
    "gn:population":0,
    "gn:timezone":"Africa/Lagos",
    "iso:country":"NG",
    "wof:name":"Garin Musa Gauri",
    "wof:placetype":"locality"
},
  "geometry": {"coordinates":[10.95983,8.74982],"type":"Point"}
}