{
  "type": "Feature",
  "properties": {
    "gn:admin1_code":"40.0",
    "gn:admin2_code":"518.0",
    "gn:admin3_code":"51809",
    "gn:asciiname":"Labo",
    "gn:country_code":"NG",
    "gn:dem":169,
    "gn:feature_class":"P",
    "gn:feature_code":"PPL",
    "gn:name":"Labo",
    "gn:population":0,
    "gn:timezone":"Africa/Lagos",
    "iso:country":"NG",
    "name:ceb_x_preferred":[
        "Labo"
    ],
    "name:deu_x_preferred":[
        "Labo"
    ],
    "name:fra_x_preferred":[
        "Labo"
    ],
    "name:nld_x_preferred":[
        "Labo"
    ],
    "name:swe_x_preferred":[
        "Labo"
    ],
    "wof:name":"Labo",
    "wof:placetype":"locality"
},
  "geometry": {"coordinates":[4.15672,11.77116],"type":"Point"}
}