{
  "type": "Feature",
  "properties": {
    "gn:admin1_code":"5.0",
    "gn:admin2_code":"25012.0",
    "gn:asciiname":"Falana",
    "gn:country_code":"NG",
    "gn:dem":24,
    "gn:feature_class":"P",
    "gn:feature_code":"PPL",
    "gn:name":"Falana",
    "gn:population":0,
    "gn:timezone":"Africa/Lagos",
    "iso:country":"NG",
    "name:vie_x_preferred":[
        "Falana"
    ],
    "wof:name":"Falana",
    "wof:placetype":"neighbourhood"
},
  "geometry": {"coordinates":[3.52928,6.57104],"type":"Point"}
}