{
  "type": "Feature",
  "properties": {
    "gn:admin1_code":"41.0",
    "gn:admin2_code":"23019.0",
    "gn:asciiname":"Alokuja",
    "gn:country_code":"NG",
    "gn:dem":307,
    "gn:feature_class":"P",
    "gn:feature_code":"PPL",
    "gn:name":"Alokuja",
    "gn:population":0,
    "gn:timezone":"Africa/Lagos",
    "iso:country":"NG",
    "name:und_x_variant":[
        "Alokuya",
        "Alokuja"
    ],
    "wof:name":"Alokuja",
    "wof:placetype":"locality"
},
  "geometry": {"coordinates":[7.49674,7.62036],"type":"Point"}
}