{
  "type": "Feature",
  "properties": {
    "gn:admin1_code":"5.0",
    "gn:admin2_code":"25006.0",
    "gn:asciiname":"Wesere",
    "gn:cc2":"NG",
    "gn:country_code":"NG",
    "gn:dem":2,
    "gn:feature_class":"P",
    "gn:feature_code":"PPL",
    "gn:name":"Wesere",
    "gn:population":0,
    "gn:timezone":"Africa/Lagos",
    "iso:country":"NG",
    "name:und_x_variant":[
        "Weshere",
        "Wesere"
    ],
    "wof:name":"Wesere",
    "wof:placetype":"locality"
},
  "geometry": {"coordinates":[2.76667,6.41667],"type":"Point"}
}