{
  "type": "Feature",
  "properties": {
    "gn:admin1_code":"22.0",
    "gn:admin2_code":"9018.0",
    "gn:asciiname":"Mgbege",
    "gn:country_code":"NG",
    "gn:dem":92,
    "gn:feature_class":"P",
    "gn:feature_code":"PPL",
    "gn:name":"Mgbege",
    "gn:population":0,
    "gn:timezone":"Africa/Lagos",
    "iso:country":"NG",
    "wof:name":"Mgbege",
    "wof:placetype":"locality"
},
  "geometry": {"coordinates":[8.41649,6.64516],"type":"Point"}
}