{
  "type": "Feature",
  "properties": {
    "gn:admin1_code":"24.0",
    "gn:admin2_code":"434.0",
    "gn:admin3_code":"43404",
    "gn:asciiname":"Barangawa",
    "gn:country_code":"NG",
    "gn:dem":417,
    "gn:feature_class":"P",
    "gn:feature_code":"PPL",
    "gn:name":"Barangawa",
    "gn:population":0,
    "gn:timezone":"Africa/Lagos",
    "iso:country":"NG",
    "wof:name":"Barangawa",
    "wof:placetype":"locality"
},
  "geometry": {"coordinates":[8.68184,12.85679],"type":"Point"}
}