{
  "type": "Feature",
  "properties": {
    "gn:admin1_code":"22.0",
    "gn:admin2_code":"9006.0",
    "gn:asciiname":"Agarubo",
    "gn:country_code":"NG",
    "gn:dem":100,
    "gn:feature_class":"P",
    "gn:feature_code":"PPL",
    "gn:name":"Agarubo",
    "gn:population":0,
    "gn:timezone":"Africa/Lagos",
    "iso:country":"NG",
    "wof:name":"Agarubo",
    "wof:placetype":"locality"
},
  "geometry": {"coordinates":[8.144,5.3374],"type":"Point"}
}