{
  "type": "Feature",
  "properties": {
    "gn:admin1_code":"23.0",
    "gn:admin2_code":"19004.0",
    "gn:admin3_code":"KD0411",
    "gn:asciiname":"Bargu",
    "gn:country_code":"NG",
    "gn:dem":675,
    "gn:feature_class":"P",
    "gn:feature_code":"PPL",
    "gn:name":"Bargu",
    "gn:population":0,
    "gn:timezone":"Africa/Lagos",
    "iso:country":"NG",
    "wof:name":"Bargu",
    "wof:placetype":"locality"
},
  "geometry": {"coordinates":[7.66785,10.86485],"type":"Point"}
}