{
  "type": "Feature",
  "properties": {
    "gn:admin1_code":"45.0",
    "gn:admin2_code":"1011.0",
    "gn:asciiname":"Umuimo",
    "gn:country_code":"NG",
    "gn:dem":73,
    "gn:feature_class":"P",
    "gn:feature_code":"PPL",
    "gn:name":"Umuimo",
    "gn:population":0,
    "gn:timezone":"Africa/Lagos",
    "iso:country":"NG",
    "wof:name":"Umuimo",
    "wof:placetype":"locality"
},
  "geometry": {"coordinates":[7.33589,5.18482],"type":"Point"}
}