{
  "type": "Feature",
  "properties": {
    "gn:admin1_code":"23.0",
    "gn:admin2_code":"19008.0",
    "gn:admin3_code":"KD0803",
    "gn:asciiname":"Unguwa Kangarro",
    "gn:country_code":"NG",
    "gn:dem":626,
    "gn:feature_class":"P",
    "gn:feature_code":"PPL",
    "gn:name":"Unguwa Kangarro",
    "gn:population":0,
    "gn:timezone":"Africa/Lagos",
    "iso:country":"NG",
    "wof:name":"Unguwa Kangarro",
    "wof:placetype":"locality"
},
  "geometry": {"coordinates":[7.76608,9.72018],"type":"Point"}
}