{
  "type": "Feature",
  "properties": {
    "gn:admin1_code":"16.0",
    "gn:admin2_code":"28003.0",
    "gn:asciiname":"Alaparu",
    "gn:cc2":"NG",
    "gn:country_code":"NG",
    "gn:dem":56,
    "gn:feature_class":"P",
    "gn:feature_code":"PPL",
    "gn:name":"Alaparu",
    "gn:population":0,
    "gn:timezone":"Africa/Lagos",
    "iso:country":"NG",
    "name:und_x_variant":[
        "Alaparun",
        "Alaparu"
    ],
    "wof:name":"Alaparu",
    "wof:placetype":"locality"
},
  "geometry": {"coordinates":[3.01667,6.65],"type":"Point"}
}