{
  "type": "Feature",
  "properties": {
    "gn:admin1_code":"21.0",
    "gn:admin2_code":"3016.0",
    "gn:asciiname":"Obot Etim",
    "gn:country_code":"NG",
    "gn:dem":22,
    "gn:feature_class":"P",
    "gn:feature_code":"PPL",
    "gn:name":"Obot Etim",
    "gn:population":0,
    "gn:timezone":"Africa/Lagos",
    "iso:country":"NG",
    "wof:name":"Obot Etim",
    "wof:placetype":"locality"
},
  "geometry": {"coordinates":[7.97637,5.19833],"type":"Point"}
}