{
  "type": "Feature",
  "properties": {
    "gn:admin1_code":"57.0",
    "gn:admin2_code":"813.0",
    "gn:admin3_code":"81303",
    "gn:asciiname":"Babompa",
    "gn:country_code":"NG",
    "gn:dem":583,
    "gn:feature_class":"P",
    "gn:feature_code":"PPL",
    "gn:name":"Babompa",
    "gn:population":0,
    "gn:timezone":"Africa/Lagos",
    "iso:country":"NG",
    "name:und_x_variant":[
        "Babampa",
        "Babompa"
    ],
    "wof:name":"Babompa",
    "wof:placetype":"locality"
},
  "geometry": {"coordinates":[6.85343,11.79435],"type":"Point"}
}