{
  "type": "Feature",
  "properties": {
    "gn:admin1_code":"51.0",
    "gn:admin2_code":"620.0",
    "gn:admin3_code":"62007",
    "gn:asciiname":"Numba Tureta",
    "gn:country_code":"NG",
    "gn:dem":288,
    "gn:feature_class":"P",
    "gn:feature_code":"PPL",
    "gn:name":"Numba Tureta",
    "gn:population":0,
    "gn:timezone":"Africa/Lagos",
    "iso:country":"NG",
    "wof:name":"Numba Tureta",
    "wof:placetype":"locality"
},
  "geometry": {"coordinates":[5.55674,12.66754],"type":"Point"}
}