{
  "type": "Feature",
  "properties": {
    "gn:admin1_code":"36.0",
    "gn:admin2_code":"10025.0",
    "gn:asciiname":"Katun",
    "gn:country_code":"NG",
    "gn:dem":4,
    "gn:feature_class":"P",
    "gn:feature_code":"PPL",
    "gn:name":"Katun",
    "gn:population":0,
    "gn:timezone":"Africa/Lagos",
    "iso:country":"NG",
    "name:eng_x_preferred":[
        "Katun"
    ],
    "name:eng_x_variant":[
        "Kantu"
    ],
    "wof:name":"Katun",
    "wof:placetype":"locality"
},
  "geometry": {"coordinates":[5.35942,5.5424],"type":"Point"}
}