{
  "type": "Feature",
  "properties": {
    "gn:admin1_code":"36.0",
    "gn:admin2_code":"10025.0",
    "gn:asciiname":"Katun",
    "gn:country_code":"NG",
    "gn:dem":4,
    "gn:feature_class":"P",
    "gn:feature_code":"PPL",
    "gn:name":"Katun",
    "gn:population":0,
    "gn:timezone":"Africa/Lagos",
    "iso:country":"NG",
    "name:bos_x_preferred":[
        "Katun"
    ],
    "name:bul_x_preferred":[
        "\u041a\u0430\u0442\u0443\u043d"
    ],
    "name:deu_x_preferred":[
        "Katun"
    ],
    "name:eng_x_preferred":[
        "Katun"
    ],
    "name:eng_x_variant":[
        "Kantu"
    ],
    "name:fra_x_preferred":[
        "Katun"
    ],
    "name:hrv_x_preferred":[
        "Katun"
    ],
    "name:hun_x_preferred":[
        "Katun"
    ],
    "name:hye_x_preferred":[
        "\u053f\u0561\u057f\u0578\u0582\u0576"
    ],
    "name:ita_x_preferred":[
        "Katun"
    ],
    "name:nld_x_preferred":[
        "Katun"
    ],
    "name:rus_x_preferred":[
        "\u041a\u0430\u0442\u0443\u043d\u044c"
    ],
    "name:sco_x_preferred":[
        "Katun"
    ],
    "name:slv_x_preferred":[
        "Katun"
    ],
    "name:srp_x_preferred":[
        "\u041a\u0430\u0442\u0443\u043d"
    ],
    "wof:name":"Katun",
    "wof:placetype":"locality"
},
  "geometry": {"coordinates":[5.35942,5.5424],"type":"Point"}
}