{
  "type": "Feature",
  "properties": {
    "gn:admin1_code":"36.0",
    "gn:admin2_code":"10025.0",
    "gn:asciiname":"Katun",
    "gn:country_code":"NG",
    "gn:dem":4,
    "gn:feature_class":"P",
    "gn:feature_code":"PPL",
    "gn:name":"Katun",
    "gn:population":0,
    "gn:timezone":"Africa/Lagos",
    "iso:country":"NG",
    "name:ara_x_preferred":[
        "\u0643\u0627\u062a\u0648\u0646"
    ],
    "name:ben_x_preferred":[
        "\u0995\u09be\u09a4\u09c1\u09a8"
    ],
    "name:bos_x_preferred":[
        "Katun"
    ],
    "name:bul_x_preferred":[
        "\u041a\u0430\u0442\u0443\u043d"
    ],
    "name:deu_x_preferred":[
        "Katun"
    ],
    "name:ell_x_preferred":[
        "\u039a\u03b1\u03c4\u03bf\u03cd\u03bd"
    ],
    "name:eng_x_preferred":[
        "Katun"
    ],
    "name:eng_x_variant":[
        "Kantu"
    ],
    "name:fra_x_preferred":[
        "Katun"
    ],
    "name:heb_x_preferred":[
        "\u05e7\u05d8\u05d5\u05df"
    ],
    "name:hrv_x_preferred":[
        "Katun"
    ],
    "name:hun_x_preferred":[
        "Katun"
    ],
    "name:hye_x_preferred":[
        "\u053f\u0561\u057f\u0578\u0582\u0576"
    ],
    "name:ind_x_preferred":[
        "Katun"
    ],
    "name:ita_x_preferred":[
        "Katun"
    ],
    "name:nld_x_preferred":[
        "Katun"
    ],
    "name:por_x_preferred":[
        "Katun"
    ],
    "name:rus_x_preferred":[
        "\u041a\u0430\u0442\u0443\u043d\u044c"
    ],
    "name:sco_x_preferred":[
        "Katun"
    ],
    "name:slv_x_preferred":[
        "Katun"
    ],
    "name:srp_x_preferred":[
        "\u041a\u0430\u0442\u0443\u043d"
    ],
    "name:swe_x_preferred":[
        "Katunfloden"
    ],
    "name:tur_x_preferred":[
        "Katun"
    ],
    "name:urd_x_preferred":[
        "\u06a9\u0627\u062a\u0648\u0646"
    ],
    "wof:name":"Katun",
    "wof:placetype":"locality"
},
  "geometry": {"coordinates":[5.35942,5.5424],"type":"Point"}
}