{
  "type": "Feature",
  "properties": {
    "gn:admin1_code":"29.0",
    "gn:admin2_code":"20011.0",
    "gn:admin3_code":"KN3601",
    "gn:asciiname":"Rinji",
    "gn:country_code":"NG",
    "gn:dem":506,
    "gn:feature_class":"P",
    "gn:feature_code":"PPL",
    "gn:name":"Rinji",
    "gn:population":0,
    "gn:timezone":"Africa/Lagos",
    "iso:country":"NG",
    "wof:name":"Rinji",
    "wof:placetype":"locality"
},
  "geometry": {"coordinates":[8.93376,11.43476],"type":"Point"}
}