{
  "type": "Feature",
  "properties": {
    "gn:admin1_code":"57.0",
    "gn:admin2_code":"810.0",
    "gn:admin3_code":"81007",
    "gn:asciiname":"Tsofon-Maigama",
    "gn:country_code":"NG",
    "gn:dem":510,
    "gn:feature_class":"P",
    "gn:feature_code":"PPL",
    "gn:name":"Tsofon-Maigama",
    "gn:population":0,
    "gn:timezone":"Africa/Lagos",
    "iso:country":"NG",
    "wof:name":"Tsofon-Maigama",
    "wof:placetype":"locality"
},
  "geometry": {"coordinates":[6.48697,11.44129],"type":"Point"}
}