{
  "type": "Feature",
  "properties": {
    "gn:admin1_code":"24.0",
    "gn:admin2_code":"419.0",
    "gn:admin3_code":"41907",
    "gn:asciiname":"Mashiji",
    "gn:country_code":"NG",
    "gn:dem":597,
    "gn:feature_class":"P",
    "gn:feature_code":"PPL",
    "gn:name":"Mashiji",
    "gn:population":0,
    "gn:timezone":"Africa/Lagos",
    "iso:country":"NG",
    "wof:name":"Mashiji",
    "wof:placetype":"locality"
},
  "geometry": {"coordinates":[7.61222,11.85336],"type":"Point"}
}