{
  "type": "Feature",
  "properties": {
    "gn:admin1_code":"45.0",
    "gn:asciiname":"Ndiba",
    "gn:country_code":"NG",
    "gn:dem":72,
    "gn:feature_class":"P",
    "gn:feature_code":"PPL",
    "gn:name":"Ndiba",
    "gn:population":0,
    "gn:timezone":"Africa/Lagos",
    "iso:country":"NG",
    "wof:name":"Ndiba",
    "wof:placetype":"locality"
},
  "geometry": {"coordinates":[7.83289,5.80249],"type":"Point"}
}