{
  "type": "Feature",
  "properties": {
    "gn:admin1_code":"36.0",
    "gn:admin2_code":"10008.0",
    "gn:asciiname":"Alisor",
    "gn:country_code":"NG",
    "gn:dem":168,
    "gn:feature_class":"P",
    "gn:feature_code":"PPL",
    "gn:name":"Alisor",
    "gn:population":0,
    "gn:timezone":"Africa/Lagos",
    "iso:country":"NG",
    "name:eng_x_preferred":[
        "Alisor"
    ],
    "wof:name":"Alisor",
    "wof:placetype":"locality"
},
  "geometry": {"coordinates":[6.12058,6.29871],"type":"Point"}
}