{
  "type": "Feature",
  "properties": {
    "gn:admin1_code":"43.0",
    "gn:admin2_code":"35002.0",
    "gn:asciiname":"Suntai Bakundi",
    "gn:country_code":"NG",
    "gn:dem":182,
    "gn:feature_class":"P",
    "gn:feature_code":"PPL",
    "gn:name":"Suntai Bakundi",
    "gn:population":0,
    "gn:timezone":"Africa/Lagos",
    "iso:country":"NG",
    "wof:name":"Suntai Bakundi",
    "wof:placetype":"locality"
},
  "geometry": {"coordinates":[10.3961,7.61139],"type":"Point"}
}