{
  "type": "Feature",
  "properties": {
    "gn:admin1_code":"39.0",
    "gn:admin2_code":"18024.0",
    "gn:admin3_code":"JI0807",
    "gn:asciiname":"Mafuta",
    "gn:country_code":"NG",
    "gn:dem":380,
    "gn:feature_class":"P",
    "gn:feature_code":"PPL",
    "gn:name":"Mafuta",
    "gn:population":0,
    "gn:timezone":"Africa/Lagos",
    "iso:country":"NG",
    "wof:name":"Mafuta",
    "wof:placetype":"locality"
},
  "geometry": {"coordinates":[9.10234,12.53246],"type":"Point"}
}