{
  "type": "Feature",
  "properties": {
    "gn:admin1_code":"23.0",
    "gn:admin2_code":"19015.0",
    "gn:admin3_code":"KD1506",
    "gn:asciiname":"Marmara",
    "gn:country_code":"NG",
    "gn:dem":706,
    "gn:feature_class":"P",
    "gn:feature_code":"PPL",
    "gn:name":"Marmara",
    "gn:population":0,
    "gn:timezone":"Africa/Lagos",
    "iso:country":"NG",
    "wof:name":"Marmara",
    "wof:placetype":"locality"
},
  "geometry": {"coordinates":[8.35337,11.06306],"type":"Point"}
}