{
  "type": "Feature",
  "properties": {
    "gn:admin1_code":"23.0",
    "gn:admin2_code":"19015.0",
    "gn:admin3_code":"KD1506",
    "gn:asciiname":"Marmara",
    "gn:country_code":"NG",
    "gn:dem":706,
    "gn:feature_class":"P",
    "gn:feature_code":"PPL",
    "gn:name":"Marmara",
    "gn:population":0,
    "gn:timezone":"Africa/Lagos",
    "iso:country":"NG",
    "name:cat_x_preferred":[
        "M\u00e0rmara"
    ],
    "name:ceb_x_preferred":[
        "Marmara"
    ],
    "name:deu_x_preferred":[
        "Marmara"
    ],
    "name:ell_x_preferred":[
        "\u039c\u03b1\u03c1\u03bc\u03b1\u03c1\u03ac\u03c2"
    ],
    "name:fra_x_preferred":[
        "Marmara"
    ],
    "name:heb_x_preferred":[
        "\u05de\u05e8\u05de\u05e8\u05d4"
    ],
    "name:hun_x_preferred":[
        "Marmara"
    ],
    "name:hye_x_preferred":[
        "\u0544\u0561\u0580\u0574\u0561\u0580\u0561"
    ],
    "name:ita_x_preferred":[
        "Marmara"
    ],
    "name:jpn_x_preferred":[
        "\u30de\u30eb\u30de\u30e9"
    ],
    "name:kor_x_preferred":[
        "\ub9c8\ub974\ub9c8\ub77c"
    ],
    "name:nld_x_preferred":[
        "Marmara"
    ],
    "name:rus_x_preferred":[
        "\u041c\u0430\u0440\u043c\u0430\u0440\u0430"
    ],
    "name:tur_x_preferred":[
        "Marmara"
    ],
    "wof:name":"Marmara",
    "wof:placetype":"locality"
},
  "geometry": {"coordinates":[8.35337,11.06306],"type":"Point"}
}