{
  "type": "Feature",
  "properties": {
    "gn:admin1_code":"31.0",
    "gn:admin2_code":"27016.0",
    "gn:asciiname":"Machuchi",
    "gn:country_code":"NG",
    "gn:dem":240,
    "gn:feature_class":"P",
    "gn:feature_code":"PPL",
    "gn:name":"Machuchi",
    "gn:population":0,
    "gn:timezone":"Africa/Lagos",
    "iso:country":"NG",
    "wof:name":"Machuchi",
    "wof:placetype":"locality"
},
  "geometry": {"coordinates":[5.53603,10.13017],"type":"Point"}
}