{
  "type": "Feature",
  "properties": {
    "gn:admin1_code":"27.0",
    "gn:admin2_code":"111.0",
    "gn:admin3_code":"11101",
    "gn:asciiname":"Kwadela",
    "gn:country_code":"NG",
    "gn:dem":415,
    "gn:feature_class":"P",
    "gn:feature_code":"PPLL",
    "gn:name":"Kwadela",
    "gn:population":0,
    "gn:timezone":"Africa/Lagos",
    "iso:country":"NG",
    "wof:name":"Kwadela",
    "wof:placetype":"locality"
},
  "geometry": {"coordinates":[13.84849,11.14218],"type":"Point"}
}