{
  "type": "Feature",
  "properties": {
    "gn:admin1_code":"51.0",
    "gn:admin2_code":"604.0",
    "gn:admin3_code":"60409",
    "gn:asciiname":"Sahiel Damagori",
    "gn:country_code":"NG",
    "gn:dem":339,
    "gn:feature_class":"P",
    "gn:feature_code":"PPL",
    "gn:name":"Sahiel Damagori",
    "gn:population":0,
    "gn:timezone":"Africa/Lagos",
    "iso:country":"NG",
    "wof:name":"Sahiel Damagori",
    "wof:placetype":"locality"
},
  "geometry": {"coordinates":[5.6627,13.68392],"type":"Point"}
}