{
  "type": "Feature",
  "properties": {
    "gn:admin1_code":"57.0",
    "gn:admin2_code":"807.0",
    "gn:admin3_code":"80710",
    "gn:asciiname":"Guidan Mallam Yaya",
    "gn:country_code":"NG",
    "gn:dem":443,
    "gn:feature_class":"P",
    "gn:feature_code":"PPL",
    "gn:name":"Guidan Mallam Yaya",
    "gn:population":0,
    "gn:timezone":"Africa/Lagos",
    "iso:country":"NG",
    "name:und_x_variant":[
        "Gidan Mallam Yaya",
        "Guidan Mallam Yaya"
    ],
    "wof:name":"Guidan Mallam Yaya",
    "wof:placetype":"locality"
},
  "geometry": {"coordinates":[6.68285,12.11207],"type":"Point"}
}