{
  "type": "Feature",
  "properties": {
    "gn:admin1_code":"32.0",
    "gn:admin2_code":"31002.0",
    "gn:asciiname":"Alugbin",
    "gn:country_code":"NG",
    "gn:dem":256,
    "gn:feature_class":"P",
    "gn:feature_code":"PPL",
    "gn:name":"Alugbin",
    "gn:population":0,
    "gn:timezone":"Africa/Lagos",
    "iso:country":"NG",
    "wof:name":"Alugbin",
    "wof:placetype":"locality"
},
  "geometry": {"coordinates":[4.06667,7.61667],"type":"Point"}
}