{
  "type": "Feature",
  "properties": {
    "gn:admin1_code":"56.0",
    "gn:admin2_code":"26012.0",
    "gn:asciiname":"Langay",
    "gn:country_code":"NG",
    "gn:dem":102,
    "gn:feature_class":"P",
    "gn:feature_code":"PPL",
    "gn:name":"Langay",
    "gn:population":0,
    "gn:timezone":"Africa/Lagos",
    "iso:country":"NG",
    "name:fas_x_preferred":[
        "\u0644\u0646\u06af\u0627\u0647"
    ],
    "name:und_x_variant":[
        "Langayi",
        "Langay"
    ],
    "name:urd_x_preferred":[
        "\u0644\u0646\u06af\u0627\u06c1"
    ],
    "wof:name":"Langay",
    "wof:placetype":"locality"
},
  "geometry": {"coordinates":[7.02669,7.95561],"type":"Point"}
}