{
  "type": "Feature",
  "properties": {
    "gn:admin1_code":"39.0",
    "gn:admin2_code":"18002.0",
    "gn:admin3_code":"JI2610",
    "gn:asciiname":"Mallamawa",
    "gn:country_code":"NG",
    "gn:dem":388,
    "gn:feature_class":"P",
    "gn:feature_code":"PPL",
    "gn:name":"Mallamawa",
    "gn:population":0,
    "gn:timezone":"Africa/Lagos",
    "iso:country":"NG",
    "wof:name":"Mallamawa",
    "wof:placetype":"locality"
},
  "geometry": {"coordinates":[9.27719,12.2039],"type":"Point"}
}