{
  "type": "Feature",
  "properties": {
    "gn:admin1_code":"43.0",
    "gn:asciiname":"Koshi",
    "gn:country_code":"NG",
    "gn:dem":325,
    "gn:feature_class":"P",
    "gn:feature_code":"PPL",
    "gn:name":"Koshi",
    "gn:population":0,
    "gn:timezone":"Africa/Lagos",
    "iso:country":"NG",
    "name:eng_x_preferred":[
        "Koshi"
    ],
    "wof:name":"Koshi",
    "wof:placetype":"locality"
},
  "geometry": {"coordinates":[10.81302,9.41349],"type":"Point"}
}