{
  "type": "Feature",
  "properties": {
    "gn:admin1_code":"43.0",
    "gn:admin2_code":"35015",
    "gn:asciiname":"Garin Mallam Audu",
    "gn:country_code":"NG",
    "gn:dem":261,
    "gn:feature_class":"P",
    "gn:feature_code":"PPL",
    "gn:name":"Garin Mallam Audu",
    "gn:population":0,
    "gn:timezone":"Africa/Lagos",
    "iso:country":"NG",
    "wof:name":"Garin Mallam Audu",
    "wof:placetype":"locality"
},
  "geometry": {"coordinates":[11.44488,8.91395],"type":"Point"}
}