{
  "type": "Feature",
  "properties": {
    "gn:admin1_code":"26.0",
    "gn:admin2_code":"7009",
    "gn:asciiname":"Tse Kosho",
    "gn:country_code":"NG",
    "gn:dem":187,
    "gn:feature_class":"P",
    "gn:feature_code":"PPL",
    "gn:name":"Tse Kosho",
    "gn:population":0,
    "gn:timezone":"Africa/Lagos",
    "iso:country":"NG",
    "wof:name":"Tse Kosho",
    "wof:placetype":"locality"
},
  "geometry": {"coordinates":[9.49614,7.42813],"type":"Point"}
}