{
  "type": "Feature",
  "properties": {
    "gn:admin1_code":"27.0",
    "gn:admin2_code":"110",
    "gn:admin3_code":"11010",
    "gn:asciiname":"Mainari",
    "gn:country_code":"NG",
    "gn:dem":292,
    "gn:feature_class":"P",
    "gn:feature_code":"PPL",
    "gn:name":"Mainari",
    "gn:population":0,
    "gn:timezone":"Africa/Lagos",
    "iso:country":"NG",
    "wof:name":"Mainari",
    "wof:placetype":"locality"
},
  "geometry": {"coordinates":[13.31582,13.01166],"type":"Point"}
}