{
  "type": "Feature",
  "properties": {
    "gn:admin1_code":"48.0",
    "gn:admin2_code":"29011.0",
    "gn:asciiname":"Obado",
    "gn:country_code":"NG",
    "gn:dem":288,
    "gn:feature_class":"P",
    "gn:feature_code":"PPL",
    "gn:name":"Obado",
    "gn:population":0,
    "gn:timezone":"Africa/Lagos",
    "iso:country":"NG",
    "wof:name":"Obado",
    "wof:placetype":"locality"
},
  "geometry": {"coordinates":[5.0025,7.2527],"type":"Point"}
}