{
  "type": "Feature",
  "properties": {
    "gn:admin1_code":"44.0",
    "gn:admin2_code":"705.0",
    "gn:admin3_code":"70513",
    "gn:asciiname":"Kaugyada",
    "gn:country_code":"NG",
    "gn:dem":379,
    "gn:feature_class":"P",
    "gn:feature_code":"PPL",
    "gn:name":"Kaugyada",
    "gn:population":0,
    "gn:timezone":"Africa/Lagos",
    "iso:country":"NG",
    "name:und_x_variant":[
        "Arigana"
    ],
    "wof:name":"Kaugyada",
    "wof:placetype":"locality"
},
  "geometry": {"coordinates":[11.01818,11.98977],"type":"Point"}
}