{
  "type": "Feature",
  "properties": {
    "gn:admin1_code":"40.0",
    "gn:admin2_code":"513.0",
    "gn:admin3_code":"51311",
    "gn:asciiname":"Tungan Alhai Sakar",
    "gn:country_code":"NG",
    "gn:dem":185,
    "gn:feature_class":"P",
    "gn:feature_code":"PPL",
    "gn:name":"Tungan Alhai Sakar",
    "gn:population":0,
    "gn:timezone":"Africa/Lagos",
    "iso:country":"NG",
    "wof:name":"Tungan Alhai Sakar",
    "wof:placetype":"locality"
},
  "geometry": {"coordinates":[4.37373,11.39243],"type":"Point"}
}