{
  "type": "Feature",
  "properties": {
    "gn:admin1_code":"46.0",
    "gn:admin2_code":"5007.0",
    "gn:admin3_code":"BA0710",
    "gn:asciiname":"Koran",
    "gn:country_code":"NG",
    "gn:dem":375,
    "gn:feature_class":"P",
    "gn:feature_code":"PPL",
    "gn:name":"Koran",
    "gn:population":0,
    "gn:timezone":"Africa/Lagos",
    "iso:country":"NG",
    "wof:name":"Koran",
    "wof:placetype":"locality"
},
  "geometry": {"coordinates":[10.575,12.0153],"type":"Point"}
}