{
  "type": "Feature",
  "properties": {
    "gn:admin1_code":"46.0",
    "gn:admin2_code":"5012.0",
    "gn:admin3_code":"BA1204",
    "gn:asciiname":"Konkomeri",
    "gn:country_code":"NG",
    "gn:dem":382,
    "gn:feature_class":"P",
    "gn:feature_code":"PPL",
    "gn:name":"Konkomeri",
    "gn:population":0,
    "gn:timezone":"Africa/Lagos",
    "iso:country":"NG",
    "wof:name":"Konkomeri",
    "wof:placetype":"locality"
},
  "geometry": {"coordinates":[10.4059,11.8176],"type":"Point"}
}