{
  "type": "Feature",
  "properties": {
    "gn:admin1_code":"31.0",
    "gn:admin2_code":"27007.0",
    "gn:asciiname":"Diko Tifin",
    "gn:country_code":"NG",
    "gn:dem":183,
    "gn:feature_class":"P",
    "gn:feature_code":"PPL",
    "gn:name":"Diko Tifin",
    "gn:population":0,
    "gn:timezone":"Africa/Lagos",
    "iso:country":"NG",
    "name:und_x_variant":[
        "Diko"
    ],
    "wof:name":"Diko Tifin",
    "wof:placetype":"locality"
},
  "geometry": {"coordinates":[5.5355,9.10286],"type":"Point"}
}