{
  "type": "Feature",
  "properties": {
    "gn:admin1_code":"36.0",
    "gn:admin2_code":"10010.0",
    "gn:asciiname":"Asaba-Assay",
    "gn:country_code":"NG",
    "gn:dem":7,
    "gn:feature_class":"P",
    "gn:feature_code":"PPL",
    "gn:name":"Asaba-Assay",
    "gn:population":0,
    "gn:timezone":"Africa/Lagos",
    "iso:country":"NG",
    "name:und_x_variant":[
        "Asaba-Ase",
        "Asaba-Assay"
    ],
    "wof:name":"Asaba-Assay",
    "wof:placetype":"locality"
},
  "geometry": {"coordinates":[6.2928,5.29416],"type":"Point"}
}