{
  "type": "Feature",
  "properties": {
    "gn:admin1_code":"32.0",
    "gn:admin2_code":"31013.0",
    "gn:asciiname":"Tobalogo",
    "gn:country_code":"NG",
    "gn:dem":180,
    "gn:feature_class":"P",
    "gn:feature_code":"PPL",
    "gn:name":"Tobalogo",
    "gn:population":0,
    "gn:timezone":"Africa/Lagos",
    "iso:country":"NG",
    "wof:name":"Tobalogo",
    "wof:placetype":"locality"
},
  "geometry": {"coordinates":[3.28333,7.53333],"type":"Point"}
}