{
  "type": "Feature",
  "properties": {
    "gn:admin1_code":"56.0",
    "gn:admin2_code":"26001",
    "gn:asciiname":"Macu",
    "gn:country_code":"NG",
    "gn:dem":497,
    "gn:feature_class":"P",
    "gn:feature_code":"PPL",
    "gn:name":"Macu",
    "gn:population":0,
    "gn:timezone":"Africa/Lagos",
    "iso:country":"NG",
    "wof:name":"Macu",
    "wof:placetype":"locality"
},
  "geometry": {"coordinates":[8.38563,9.06507],"type":"Point"}
}