{
  "type": "Feature",
  "properties": {
    "gn:admin1_code":"35.0",
    "gn:admin2_code":"2014.0",
    "gn:asciiname":"Muhura",
    "gn:country_code":"NG",
    "gn:dem":766,
    "gn:feature_class":"P",
    "gn:feature_code":"PPL",
    "gn:name":"Muhura",
    "gn:population":0,
    "gn:timezone":"Africa/Lagos",
    "iso:country":"NG",
    "wof:name":"Muhura",
    "wof:placetype":"locality"
},
  "geometry": {"coordinates":[13.47456,10.35791],"type":"Point"}
}