{
  "type": "Feature",
  "properties": {
    "gn:admin1_code":"43.0",
    "gn:admin2_code":"35003",
    "gn:asciiname":"Tseahan",
    "gn:country_code":"NG",
    "gn:dem":221,
    "gn:feature_class":"P",
    "gn:feature_code":"PPL",
    "gn:name":"Tseahan",
    "gn:population":0,
    "gn:timezone":"Africa/Lagos",
    "iso:country":"NG",
    "wof:name":"Tseahan",
    "wof:placetype":"locality"
},
  "geometry": {"coordinates":[9.82207,7.62095],"type":"Point"}
}