{
  "type": "Feature",
  "properties": {
    "gn:admin1_code":"31.0",
    "gn:admin2_code":"27016.0",
    "gn:asciiname":"Shankadade",
    "gn:country_code":"NG",
    "gn:dem":109,
    "gn:feature_class":"P",
    "gn:feature_code":"PPL",
    "gn:name":"Shankadade",
    "gn:population":0,
    "gn:timezone":"Africa/Lagos",
    "iso:country":"NG",
    "wof:name":"Shankadade",
    "wof:placetype":"locality"
},
  "geometry": {"coordinates":[4.56667,9.51667],"type":"Point"}
}