{
  "type": "Feature",
  "properties": {
    "gn:admin1_code":"25.0",
    "gn:admin2_code":"4009",
    "gn:asciiname":"Akwukwu",
    "gn:country_code":"NG",
    "gn:dem":64,
    "gn:feature_class":"P",
    "gn:feature_code":"PPL",
    "gn:name":"Akwukwu",
    "gn:population":0,
    "gn:timezone":"Africa/Lagos",
    "iso:country":"NG",
    "wof:name":"Akwukwu",
    "wof:placetype":"locality"
},
  "geometry": {"coordinates":[6.81011,6.03913],"type":"Point"}
}