{
  "type": "Feature",
  "properties": {
    "gn:admin1_code":"26.0",
    "gn:admin2_code":"7022.0",
    "gn:asciiname":"Ausa",
    "gn:country_code":"NG",
    "gn:dem":181,
    "gn:feature_class":"P",
    "gn:feature_code":"PPL",
    "gn:name":"Ausa",
    "gn:population":0,
    "gn:timezone":"Africa/Lagos",
    "iso:country":"NG",
    "name:ben_x_preferred":[
        "\u0994\u09b8\u09be"
    ],
    "name:bpy_x_preferred":[
        "\u0986\u0989\u09b8\u09be"
    ],
    "name:ceb_x_preferred":[
        "Ausa"
    ],
    "name:ces_x_preferred":[
        "Ausa"
    ],
    "name:hin_x_preferred":[
        "\u0914\u0938\u093e"
    ],
    "name:ita_x_preferred":[
        "Ausa"
    ],
    "name:mar_x_preferred":[
        "\u0914\u0938\u093e"
    ],
    "name:msa_x_preferred":[
        "Ausa"
    ],
    "name:nld_x_preferred":[
        "Ausa"
    ],
    "name:swe_x_preferred":[
        "Ausa"
    ],
    "name:urd_x_preferred":[
        "\u0627\u0648\u0633\u0627"
    ],
    "name:vie_x_preferred":[
        "Ausa"
    ],
    "name:zho_x_preferred":[
        "\u5965\u8428"
    ],
    "wof:name":"Ausa",
    "wof:placetype":"locality"
},
  "geometry": {"coordinates":[8.9514,7.09278],"type":"Point"}
}