{
  "type": "Feature",
  "properties": {
    "gn:admin1_code":"26.0",
    "gn:admin2_code":"7022.0",
    "gn:asciiname":"Ausa",
    "gn:country_code":"NG",
    "gn:dem":181,
    "gn:feature_class":"P",
    "gn:feature_code":"PPL",
    "gn:name":"Ausa",
    "gn:population":0,
    "gn:timezone":"Africa/Lagos",
    "iso:country":"NG",
    "wof:name":"Ausa",
    "wof:placetype":"locality"
},
  "geometry": {"coordinates":[8.9514,7.09278],"type":"Point"}
}