{
  "type": "Feature",
  "properties": {
    "gn:admin1_code":"49.0",
    "gn:admin2_code":"32013.0",
    "gn:asciiname":"Tambes",
    "gn:country_code":"NG",
    "gn:dem":1214,
    "gn:feature_class":"P",
    "gn:feature_code":"PPL",
    "gn:name":"Tambes",
    "gn:population":0,
    "gn:timezone":"Africa/Lagos",
    "iso:country":"NG",
    "name:und_x_variant":[
        "Tambus",
        "Tambes"
    ],
    "wof:name":"Tambes",
    "wof:placetype":"locality"
},
  "geometry": {"coordinates":[9.41171,9.37887],"type":"Point"}
}