{
  "type": "Feature",
  "properties": {
    "gn:admin1_code":"16.0",
    "gn:admin2_code":"28020.0",
    "gn:asciiname":"Orita-Odo",
    "gn:country_code":"NG",
    "gn:dem":63,
    "gn:feature_class":"P",
    "gn:feature_code":"PPL",
    "gn:name":"Orita-Odo",
    "gn:population":0,
    "gn:timezone":"Africa/Lagos",
    "iso:country":"NG",
    "wof:name":"Orita-Odo",
    "wof:placetype":"locality"
},
  "geometry": {"coordinates":[3.6437,6.75814],"type":"Point"}
}