{
  "type": "Feature",
  "properties": {
    "gn:admin1_code":"39.0",
    "gn:admin2_code":"18007.0",
    "gn:admin3_code":"JI1805",
    "gn:asciiname":"Melekauri",
    "gn:country_code":"NG",
    "gn:dem":351,
    "gn:feature_class":"P",
    "gn:feature_code":"PPL",
    "gn:name":"Melekauri",
    "gn:population":0,
    "gn:timezone":"Africa/Lagos",
    "iso:country":"NG",
    "wof:name":"Melekauri",
    "wof:placetype":"locality"
},
  "geometry": {"coordinates":[10.2019,12.7056],"type":"Point"}
}