{
  "type": "Feature",
  "properties": {
    "gn:admin1_code":"46.0",
    "gn:admin2_code":"5001.0",
    "gn:admin3_code":"BA0109",
    "gn:asciiname":"Putuk",
    "gn:country_code":"NG",
    "gn:dem":397,
    "gn:feature_class":"P",
    "gn:feature_code":"PPL",
    "gn:name":"Putuk",
    "gn:population":0,
    "gn:timezone":"Africa/Lagos",
    "iso:country":"NG",
    "name:und_x_variant":[
        "Futuk",
        "Putuk"
    ],
    "wof:name":"Putuk",
    "wof:placetype":"locality"
},
  "geometry": {"coordinates":[10.89983,9.83502],"type":"Point"}
}