{
  "type": "Feature",
  "properties": {
    "gn:admin1_code":"27.0",
    "gn:admin2_code":"127.0",
    "gn:admin3_code":"12710",
    "gn:asciiname":"Kwahala",
    "gn:country_code":"NG",
    "gn:dem":247,
    "gn:feature_class":"P",
    "gn:feature_code":"PPL",
    "gn:name":"Kwahala",
    "gn:population":0,
    "gn:timezone":"Africa/Lagos",
    "iso:country":"NG",
    "wof:name":"Kwahala",
    "wof:placetype":"locality"
},
  "geometry": {"coordinates":[12.01036,10.19867],"type":"Point"}
}