{
  "type": "Feature",
  "properties": {
    "gn:admin1_code":"23.0",
    "gn:admin2_code":"19014.0",
    "gn:admin3_code":"KD1405",
    "gn:asciiname":"Geshare",
    "gn:country_code":"NG",
    "gn:dem":834,
    "gn:feature_class":"P",
    "gn:feature_code":"PPL",
    "gn:name":"Geshare",
    "gn:population":0,
    "gn:timezone":"Africa/Lagos",
    "iso:country":"NG",
    "name:und_x_variant":[
        "Gyashare",
        "Geshare"
    ],
    "wof:name":"Geshare",
    "wof:placetype":"locality"
},
  "geometry": {"coordinates":[8.36421,10.12861],"type":"Point"}
}