{
  "type": "Feature",
  "properties": {
    "gn:admin1_code":"31.0",
    "gn:admin2_code":"27013",
    "gn:asciiname":"Sonfada",
    "gn:country_code":"NG",
    "gn:dem":96,
    "gn:feature_class":"P",
    "gn:feature_code":"PPL",
    "gn:name":"Sonfada",
    "gn:population":0,
    "gn:timezone":"Africa/Lagos",
    "iso:country":"NG",
    "wof:name":"Sonfada",
    "wof:placetype":"locality"
},
  "geometry": {"coordinates":[5.82028,9.19767],"type":"Point"}
}