{
  "type": "Feature",
  "properties": {
    "gn:admin1_code":"24.0",
    "gn:admin2_code":"404.0",
    "gn:admin3_code":"40406",
    "gn:asciiname":"Botsotsowar Daura",
    "gn:country_code":"NG",
    "gn:dem":400,
    "gn:feature_class":"P",
    "gn:feature_code":"PPL",
    "gn:name":"Botsotsowar Daura",
    "gn:population":0,
    "gn:timezone":"Africa/Lagos",
    "iso:country":"NG",
    "name:und_x_variant":[
        "Gunji",
        "Botsotsowar Daura"
    ],
    "wof:name":"Botsotsowar Daura",
    "wof:placetype":"locality"
},
  "geometry": {"coordinates":[8.75181,12.67397],"type":"Point"}
}