{
  "type": "Feature",
  "properties": {
    "gn:admin1_code":"24.0",
    "gn:admin2_code":"406.0",
    "gn:admin3_code":"40608",
    "gn:asciiname":"Kandanya",
    "gn:country_code":"NG",
    "gn:dem":520,
    "gn:feature_class":"P",
    "gn:feature_code":"PPL",
    "gn:name":"Kandanya",
    "gn:population":0,
    "gn:timezone":"Africa/Lagos",
    "iso:country":"NG",
    "wof:name":"Kandanya",
    "wof:placetype":"locality"
},
  "geometry": {"coordinates":[7.69813,12.37955],"type":"Point"}
}