{
  "type": "Feature",
  "properties": {
    "gn:admin1_code":"40.0",
    "gn:admin2_code":"506.0",
    "gn:admin3_code":"50608",
    "gn:asciiname":"Bamirunji",
    "gn:country_code":"NG",
    "gn:dem":274,
    "gn:feature_class":"P",
    "gn:feature_code":"PPL",
    "gn:name":"Bamirunji",
    "gn:population":0,
    "gn:timezone":"Africa/Lagos",
    "iso:country":"NG",
    "wof:name":"Bamirunji",
    "wof:placetype":"locality"
},
  "geometry": {"coordinates":[4.41347,12.45238],"type":"Point"}
}