{
  "type": "Feature",
  "properties": {
    "gn:admin1_code":"23.0",
    "gn:admin2_code":"19003.0",
    "gn:admin3_code":"KD0311",
    "gn:asciiname":"Ungwan Na Ikko",
    "gn:country_code":"NG",
    "gn:dem":629,
    "gn:feature_class":"P",
    "gn:feature_code":"PPL",
    "gn:name":"Ungwan Na Ikko",
    "gn:population":0,
    "gn:timezone":"Africa/Lagos",
    "iso:country":"NG",
    "wof:name":"Ungwan Na Ikko",
    "wof:placetype":"locality"
},
  "geometry": {"coordinates":[7.42058,11.1424],"type":"Point"}
}