{
  "type": "Feature",
  "properties": {
    "gn:admin1_code":"29.0",
    "gn:admin2_code":"20021.0",
    "gn:admin3_code":"KN1001",
    "gn:asciiname":"Danguguwa",
    "gn:country_code":"NG",
    "gn:dem":485,
    "gn:feature_class":"P",
    "gn:feature_code":"PPL",
    "gn:name":"Danguguwa",
    "gn:population":0,
    "gn:timezone":"Africa/Lagos",
    "iso:country":"NG",
    "wof:name":"Danguguwa",
    "wof:placetype":"locality"
},
  "geometry": {"coordinates":[8.394,12.05813],"type":"Point"}
}