{
  "type": "Feature",
  "properties": {
    "gn:admin1_code":"55.0",
    "gn:asciiname":"Garin Guda",
    "gn:country_code":"NG",
    "gn:dem":413,
    "gn:feature_class":"P",
    "gn:feature_code":"PPL",
    "gn:name":"Garin Guda",
    "gn:population":0,
    "gn:timezone":"Africa/Lagos",
    "iso:country":"NG",
    "name:eng_x_preferred":[
        "Garin Guda"
    ],
    "wof:name":"Garin Guda",
    "wof:placetype":"locality"
},
  "geometry": {"coordinates":[10.99314,9.96853],"type":"Point"}
}