{
  "type": "Feature",
  "properties": {
    "gn:admin1_code":"43.0",
    "gn:asciiname":"Zaral",
    "gn:country_code":"NG",
    "gn:dem":372,
    "gn:feature_class":"P",
    "gn:feature_code":"PPL",
    "gn:name":"Zaral",
    "gn:population":0,
    "gn:timezone":"Africa/Lagos",
    "iso:country":"NG",
    "name:eng_x_preferred":[
        "Zaral"
    ],
    "wof:name":"Zaral",
    "wof:placetype":"locality"
},
  "geometry": {"coordinates":[11.09998,9.46902],"type":"Point"}
}