{
  "type": "Feature",
  "properties": {
    "gn:admin1_code":"27.0",
    "gn:admin2_code":"120.0",
    "gn:admin3_code":"12012",
    "gn:asciiname":"Suriaretin",
    "gn:country_code":"NG",
    "gn:dem":315,
    "gn:feature_class":"P",
    "gn:feature_code":"PPL",
    "gn:name":"Suriaretin",
    "gn:population":0,
    "gn:timezone":"Africa/Lagos",
    "iso:country":"NG",
    "name:und_x_variant":[
        "Tsuriaretin",
        "Suriaretin"
    ],
    "wof:name":"Suriaretin",
    "wof:placetype":"locality"
},
  "geometry": {"coordinates":[12.96617,12.08754],"type":"Point"}
}