{
  "type": "Feature",
  "properties": {
    "gn:admin1_code":"55.0",
    "gn:admin2_code":"16010",
    "gn:asciiname":"Boh",
    "gn:country_code":"NG",
    "gn:dem":568,
    "gn:feature_class":"P",
    "gn:feature_code":"PPLA2",
    "gn:name":"Boh",
    "gn:population":0,
    "gn:timezone":"Africa/Lagos",
    "iso:country":"NG",
    "wof:name":"Boh",
    "wof:placetype":"locality"
},
  "geometry": {"coordinates":[11.27882,9.78187],"type":"Point"}
}