{
  "type": "Feature",
  "properties": {
    "gn:admin1_code":"23.0",
    "gn:admin2_code":"19008.0",
    "gn:admin3_code":"KD0801",
    "gn:asciiname":"Sabeji",
    "gn:country_code":"NG",
    "gn:dem":787,
    "gn:feature_class":"P",
    "gn:feature_code":"PPL",
    "gn:name":"Sabeji",
    "gn:population":0,
    "gn:timezone":"Africa/Lagos",
    "iso:country":"NG",
    "wof:name":"Sabeji",
    "wof:placetype":"locality"
},
  "geometry": {"coordinates":[7.94069,10.04546],"type":"Point"}
}