{
  "type": "Feature",
  "properties": {
    "gn:admin1_code":"23.0",
    "gn:admin2_code":"19022",
    "gn:admin3_code":"KD2210",
    "gn:asciiname":"Shogwa",
    "gn:country_code":"NG",
    "gn:dem":873,
    "gn:feature_class":"P",
    "gn:feature_code":"PPL",
    "gn:name":"Shogwa",
    "gn:population":0,
    "gn:timezone":"Africa/Lagos",
    "iso:country":"NG",
    "wof:name":"Shogwa",
    "wof:placetype":"locality"
},
  "geometry": {"coordinates":[8.28021,9.74617],"type":"Point"}
}