{
  "type": "Feature",
  "properties": {
    "gn:admin1_code":"24.0",
    "gn:admin2_code":"429.0",
    "gn:admin3_code":"42902",
    "gn:asciiname":"Karchi",
    "gn:country_code":"NG",
    "gn:dem":573,
    "gn:feature_class":"P",
    "gn:feature_code":"PPL",
    "gn:name":"Karchi",
    "gn:population":0,
    "gn:timezone":"Africa/Lagos",
    "iso:country":"NG",
    "wof:name":"Karchi",
    "wof:placetype":"locality"
},
  "geometry": {"coordinates":[7.73745,12.16195],"type":"Point"}
}