{
  "type": "Feature",
  "properties": {
    "gn:admin1_code":"43.0",
    "gn:admin2_code":"35002.0",
    "gn:asciiname":"Gidan Maikudi",
    "gn:country_code":"NG",
    "gn:dem":188,
    "gn:feature_class":"P",
    "gn:feature_code":"PPL",
    "gn:name":"Gidan Maikudi",
    "gn:population":0,
    "gn:timezone":"Africa/Lagos",
    "iso:country":"NG",
    "wof:name":"Gidan Maikudi",
    "wof:placetype":"locality"
},
  "geometry": {"coordinates":[10.48036,7.67386],"type":"Point"}
}