{
  "type": "Feature",
  "properties": {
    "gn:admin1_code":"50.0",
    "gn:asciiname":"Olepoku",
    "gn:country_code":"NG",
    "gn:dem":4,
    "gn:feature_class":"P",
    "gn:feature_code":"PPL",
    "gn:name":"Olepoku",
    "gn:population":0,
    "gn:timezone":"Africa/Lagos",
    "iso:country":"NG",
    "name:und_x_variant":[
        "Owupubo",
        "Owupoku",
        "Oluapoku",
        "Olepoku"
    ],
    "wof:name":"Olepoku",
    "wof:placetype":"locality"
},
  "geometry": {"coordinates":[6.69517,4.38001],"type":"Point"}
}