{
  "type": "Feature",
  "properties": {
    "gn:admin1_code":"31.0",
    "gn:admin2_code":"27001",
    "gn:asciiname":"Mamatsu",
    "gn:country_code":"NG",
    "gn:dem":117,
    "gn:feature_class":"P",
    "gn:feature_code":"PPL",
    "gn:name":"Mamatsu",
    "gn:population":0,
    "gn:timezone":"Africa/Lagos",
    "iso:country":"NG",
    "wof:name":"Mamatsu",
    "wof:placetype":"locality"
},
  "geometry": {"coordinates":[6.41678,9.18113],"type":"Point"}
}