{
  "type": "Feature",
  "properties": {
    "gn:admin1_code":"24.0",
    "gn:admin2_code":"409.0",
    "gn:admin3_code":"40909",
    "gn:asciiname":"Mai Gezogi",
    "gn:country_code":"NG",
    "gn:dem":498,
    "gn:feature_class":"P",
    "gn:feature_code":"PPL",
    "gn:name":"Mai Gezogi",
    "gn:population":0,
    "gn:timezone":"Africa/Lagos",
    "iso:country":"NG",
    "wof:name":"Mai Gezogi",
    "wof:placetype":"locality"
},
  "geometry": {"coordinates":[7.36656,12.22639],"type":"Point"}
}