{
  "type": "Feature",
  "properties": {
    "gn:admin1_code":"48.0",
    "gn:admin2_code":"29015.0",
    "gn:asciiname":"Oke-Igbaro",
    "gn:country_code":"NG",
    "gn:dem":267,
    "gn:feature_class":"P",
    "gn:feature_code":"PPL",
    "gn:name":"Oke-Igbaro",
    "gn:population":0,
    "gn:timezone":"Africa/Lagos",
    "iso:country":"NG",
    "wof:name":"Oke-Igbaro",
    "wof:placetype":"locality"
},
  "geometry": {"coordinates":[5.0044,7.1218],"type":"Point"}
}