{
  "type": "Feature",
  "properties": {
    "gn:admin1_code":"23.0",
    "gn:asciiname":"Pata",
    "gn:country_code":"NG",
    "gn:dem":653,
    "gn:feature_class":"P",
    "gn:feature_code":"PPL",
    "gn:name":"Pata",
    "gn:population":0,
    "gn:timezone":"Africa/Lagos",
    "iso:country":"NG",
    "wof:name":"Pata",
    "wof:placetype":"locality"
},
  "geometry": {"coordinates":[8.46019,11.19698],"type":"Point"}
}