{
  "type": "Feature",
  "properties": {
    "gn:admin1_code":"36.0",
    "gn:admin2_code":"10020.0",
    "gn:asciiname":"Umolo-Olomu",
    "gn:country_code":"NG",
    "gn:dem":9,
    "gn:feature_class":"P",
    "gn:feature_code":"PPL",
    "gn:name":"Umolo-Olomu",
    "gn:population":0,
    "gn:timezone":"Africa/Lagos",
    "iso:country":"NG",
    "name:und_x_variant":[
        "Umolo",
        "Umolo-Olomu"
    ],
    "wof:name":"Umolo-Olomu",
    "wof:placetype":"locality"
},
  "geometry": {"coordinates":[5.904,5.41104],"type":"Point"}
}