{
  "type": "Feature",
  "properties": {
    "gn:admin1_code":"39.0",
    "gn:admin2_code":"18025.0",
    "gn:admin3_code":"JI1911",
    "gn:asciiname":"Gorima",
    "gn:country_code":"NG",
    "gn:dem":393,
    "gn:feature_class":"P",
    "gn:feature_code":"PPL",
    "gn:name":"Gorima",
    "gn:population":0,
    "gn:timezone":"Africa/Lagos",
    "iso:country":"NG",
    "wof:name":"Gorima",
    "wof:placetype":"locality"
},
  "geometry": {"coordinates":[9.47974,11.91293],"type":"Point"}
}