{
  "type": "Feature",
  "properties": {
    "gn:admin1_code":"51.0",
    "gn:admin2_code":"621.0",
    "gn:admin3_code":"62109",
    "gn:asciiname":"Yarume Rafi",
    "gn:country_code":"NG",
    "gn:dem":254,
    "gn:feature_class":"P",
    "gn:feature_code":"PPL",
    "gn:name":"Yarume Rafi",
    "gn:population":0,
    "gn:timezone":"Africa/Lagos",
    "iso:country":"NG",
    "wof:name":"Yarume Rafi",
    "wof:placetype":"locality"
},
  "geometry": {"coordinates":[4.98509,13.00837],"type":"Point"}
}