{
  "type": "Feature",
  "properties": {
    "gn:admin1_code":"31.0",
    "gn:admin2_code":"27021.0",
    "gn:asciiname":"Tukura",
    "gn:country_code":"NG",
    "gn:dem":258,
    "gn:feature_class":"P",
    "gn:feature_code":"PPL",
    "gn:name":"Tukura",
    "gn:population":0,
    "gn:timezone":"Africa/Lagos",
    "iso:country":"NG",
    "wof:name":"Tukura",
    "wof:placetype":"locality"
},
  "geometry": {"coordinates":[4.90977,11.28169],"type":"Point"}
}