{
  "type": "Feature",
  "properties": {
    "gn:admin1_code":"40.0",
    "gn:admin2_code":"520.0",
    "gn:admin3_code":"52004",
    "gn:asciiname":"Tondi",
    "gn:country_code":"NG",
    "gn:dem":166,
    "gn:feature_class":"P",
    "gn:feature_code":"PPL",
    "gn:name":"Tondi",
    "gn:population":0,
    "gn:timezone":"Africa/Lagos",
    "iso:country":"NG",
    "name:deu_x_preferred":[
        "Tondi"
    ],
    "name:est_x_preferred":[
        "Tondi"
    ],
    "name:fin_x_preferred":[
        "Tondi"
    ],
    "name:fra_x_preferred":[
        "Tondi"
    ],
    "name:nld_x_preferred":[
        "Tondi"
    ],
    "name:rus_x_preferred":[
        "\u0422\u043e\u043d\u0434\u0438"
    ],
    "name:swe_x_preferred":[
        "Tondi"
    ],
    "wof:name":"Tondi",
    "wof:placetype":"locality"
},
  "geometry": {"coordinates":[4.75,10.88333],"type":"Point"}
}