{
  "type": "Feature",
  "properties": {
    "gn:admin1_code":"35.0",
    "gn:admin2_code":"2002.0",
    "gn:asciiname":"Pete",
    "gn:country_code":"NG",
    "gn:dem":233,
    "gn:feature_class":"P",
    "gn:feature_code":"PPL",
    "gn:name":"Pete",
    "gn:population":0,
    "gn:timezone":"Africa/Lagos",
    "iso:country":"NG",
    "name:ceb_x_preferred":[
        "Pete"
    ],
    "name:fra_x_preferred":[
        "Pete"
    ],
    "name:hun_x_preferred":[
        "Pete"
    ],
    "name:jpn_x_preferred":[
        "\u30d4\u30fc\u30c8"
    ],
    "name:nld_x_preferred":[
        "Pete"
    ],
    "name:spa_x_preferred":[
        "Pete"
    ],
    "name:swe_x_preferred":[
        "Pete"
    ],
    "wof:name":"Pete",
    "wof:placetype":"locality"
},
  "geometry": {"coordinates":[13.08549,9.56364],"type":"Point"}
}