{
  "type": "Feature",
  "properties": {
    "gn:admin1_code":"24.0",
    "gn:admin2_code":"428.0",
    "gn:admin3_code":"42807",
    "gn:asciiname":"Dugul",
    "gn:country_code":"NG",
    "gn:dem":538,
    "gn:feature_class":"P",
    "gn:feature_code":"PPL",
    "gn:name":"Dugul",
    "gn:population":0,
    "gn:timezone":"Africa/Lagos",
    "iso:country":"NG",
    "wof:name":"Dugul",
    "wof:placetype":"locality"
},
  "geometry": {"coordinates":[7.54604,12.20852],"type":"Point"}
}