{
  "type": "Feature",
  "properties": {
    "gn:admin1_code":"44.0",
    "gn:admin2_code":"711.0",
    "gn:admin3_code":"71107",
    "gn:asciiname":"Karigiri",
    "gn:country_code":"NG",
    "gn:dem":357,
    "gn:feature_class":"P",
    "gn:feature_code":"PPL",
    "gn:name":"Karigiri",
    "gn:population":0,
    "gn:timezone":"Africa/Niamey",
    "iso:country":"NG",
    "wof:name":"Karigiri",
    "wof:placetype":"locality"
},
  "geometry": {"coordinates":[9.84544,13.0244],"type":"Point"}
}