{
  "type": "Feature",
  "properties": {
    "gn:admin1_code":"36.0",
    "gn:admin2_code":"10017.0",
    "gn:asciiname":"Adagbarassa-Amukpe",
    "gn:country_code":"NG",
    "gn:dem":15,
    "gn:feature_class":"P",
    "gn:feature_code":"PPL",
    "gn:name":"Adagbarassa-Amukpe",
    "gn:population":0,
    "gn:timezone":"Africa/Lagos",
    "iso:country":"NG",
    "name:und_x_variant":[
        "Adagbarassa",
        "Adagbarassa-Amukpe"
    ],
    "wof:name":"Adagbarassa-Amukpe",
    "wof:placetype":"locality"
},
  "geometry": {"coordinates":[5.75571,5.85132],"type":"Point"}
}