{
  "type": "Feature",
  "properties": {
    "gn:admin1_code":"37.0",
    "gn:admin2_code":"12008.0",
    "gn:asciiname":"Okugbe",
    "gn:country_code":"NG",
    "gn:dem":354,
    "gn:feature_class":"P",
    "gn:feature_code":"PPL",
    "gn:name":"Okugbe",
    "gn:population":0,
    "gn:timezone":"Africa/Lagos",
    "iso:country":"NG",
    "wof:name":"Okugbe",
    "wof:placetype":"locality"
},
  "geometry": {"coordinates":[6.3261,7.2892],"type":"Point"}
}