{
  "type": "Feature",
  "properties": {
    "gn:admin1_code":"26.0",
    "gn:admin2_code":"7009",
    "gn:asciiname":"Akpa",
    "gn:country_code":"NG",
    "gn:dem":146,
    "gn:feature_class":"P",
    "gn:feature_code":"PPL",
    "gn:name":"Akpa",
    "gn:population":0,
    "gn:timezone":"Africa/Lagos",
    "iso:country":"NG",
    "wof:name":"Akpa",
    "wof:placetype":"locality"
},
  "geometry": {"coordinates":[9.29288,7.33528],"type":"Point"}
}