{
  "type": "Feature",
  "properties": {
    "gn:admin1_code":"35.0",
    "gn:admin2_code":"2018.0",
    "gn:asciiname":"Wafango",
    "gn:country_code":"NG",
    "gn:dem":400,
    "gn:feature_class":"P",
    "gn:feature_code":"PPL",
    "gn:name":"Wafango",
    "gn:population":0,
    "gn:timezone":"Africa/Lagos",
    "iso:country":"NG",
    "wof:name":"Wafango",
    "wof:placetype":"locality"
},
  "geometry": {"coordinates":[12.86667,9.73333],"type":"Point"}
}