{
  "type": "Feature",
  "properties": {
    "gn:admin1_code":"46.0",
    "gn:admin2_code":"5003",
    "gn:admin3_code":"BA0313",
    "gn:asciiname":"Mwari",
    "gn:country_code":"NG",
    "gn:dem":702,
    "gn:feature_class":"P",
    "gn:feature_code":"PPL",
    "gn:name":"Mwari",
    "gn:population":0,
    "gn:timezone":"Africa/Lagos",
    "iso:country":"NG",
    "name:eng_x_preferred":[
        "Mwari"
    ],
    "name:fra_x_preferred":[
        "Mwari"
    ],
    "wof:name":"Mwari",
    "wof:placetype":"locality"
},
  "geometry": {"coordinates":[9.57172,9.67135],"type":"Point"}
}