{
  "type": "Feature",
  "properties": {
    "gn:admin1_code":"35.0",
    "gn:admin2_code":"2010",
    "gn:asciiname":"Namtari Jambuti",
    "gn:country_code":"NG",
    "gn:dem":500,
    "gn:feature_class":"P",
    "gn:feature_code":"PPL",
    "gn:name":"Namtari Jambuti",
    "gn:population":0,
    "gn:timezone":"Africa/Lagos",
    "iso:country":"NG",
    "wof:name":"Namtari Jambuti",
    "wof:placetype":"locality"
},
  "geometry": {"coordinates":[13.63971,10.88095],"type":"Point"}
}