{
  "type": "Feature",
  "properties": {
    "gn:admin1_code":"44.0",
    "gn:admin2_code":"717",
    "gn:admin3_code":"71709",
    "gn:asciiname":"Buku Gana",
    "gn:country_code":"NG",
    "gn:dem":337,
    "gn:feature_class":"P",
    "gn:feature_code":"PPL",
    "gn:name":"Buku Gana",
    "gn:population":0,
    "gn:timezone":"Africa/Lagos",
    "iso:country":"NG",
    "wof:name":"Buku Gana",
    "wof:placetype":"locality"
},
  "geometry": {"coordinates":[11.06089,13.02822],"type":"Point"}
}