{
  "type": "Feature",
  "properties": {
    "gn:admin1_code":"31.0",
    "gn:admin2_code":"27018",
    "gn:asciiname":"Gidan Bidagoy",
    "gn:country_code":"NG",
    "gn:dem":390,
    "gn:feature_class":"P",
    "gn:feature_code":"PPL",
    "gn:name":"Gidan Bidagoy",
    "gn:population":0,
    "gn:timezone":"Africa/Lagos",
    "iso:country":"NG",
    "wof:name":"Gidan Bidagoy",
    "wof:placetype":"locality"
},
  "geometry": {"coordinates":[6.96801,9.78274],"type":"Point"}
}