{
  "type": "Feature",
  "properties": {
    "gn:admin1_code":"51.0",
    "gn:admin2_code":"614.0",
    "gn:admin3_code":"61410",
    "gn:asciiname":"Mareke",
    "gn:country_code":"NG",
    "gn:dem":285,
    "gn:feature_class":"P",
    "gn:feature_code":"PPL",
    "gn:name":"Mareke",
    "gn:population":0,
    "gn:timezone":"Africa/Lagos",
    "iso:country":"NG",
    "wof:name":"Mareke",
    "wof:placetype":"locality"
},
  "geometry": {"coordinates":[4.98442,12.59668],"type":"Point"}
}