{
  "type": "Feature",
  "properties": {
    "gn:admin1_code":"32.0",
    "gn:admin2_code":"31015.0",
    "gn:asciiname":"Soro",
    "gn:country_code":"NG",
    "gn:dem":357,
    "gn:feature_class":"P",
    "gn:feature_code":"PPL",
    "gn:name":"Soro",
    "gn:population":0,
    "gn:timezone":"Africa/Lagos",
    "iso:country":"NG",
    "wof:name":"Soro",
    "wof:placetype":"locality"
},
  "geometry": {"coordinates":[3.95,8.98333],"type":"Point"}
}