{
  "type": "Feature",
  "properties": {
    "gn:admin1_code":"51.0",
    "gn:admin2_code":"602.0",
    "gn:admin3_code":"60204",
    "gn:asciiname":"Toma",
    "gn:country_code":"NG",
    "gn:dem":283,
    "gn:feature_class":"P",
    "gn:feature_code":"PPL",
    "gn:name":"Toma",
    "gn:population":0,
    "gn:timezone":"Africa/Lagos",
    "iso:country":"NG",
    "wof:name":"Toma",
    "wof:placetype":"locality"
},
  "geometry": {"coordinates":[5.16667,12.83333],"type":"Point"}
}