{
  "type": "Feature",
  "properties": {
    "gn:admin1_code":"51.0",
    "gn:admin2_code":"602.0",
    "gn:admin3_code":"60204",
    "gn:asciiname":"Toma",
    "gn:country_code":"NG",
    "gn:dem":283,
    "gn:feature_class":"P",
    "gn:feature_code":"PPL",
    "gn:name":"Toma",
    "gn:population":0,
    "gn:timezone":"Africa/Lagos",
    "iso:country":"NG",
    "name:ceb_x_preferred":[
        "Toma"
    ],
    "name:deu_x_preferred":[
        "Toma"
    ],
    "name:fas_x_preferred":[
        "\u062a\u0648\u0645\u0627"
    ],
    "name:fra_x_preferred":[
        "Toma"
    ],
    "name:heb_x_preferred":[
        "\u05ea\u05d5\u05de\u05d0"
    ],
    "name:hun_x_preferred":[
        "Toma"
    ],
    "name:hye_x_preferred":[
        "\u054f\u0578\u0574\u0561"
    ],
    "name:ita_x_preferred":[
        "Toma"
    ],
    "name:pol_x_preferred":[
        "Toma"
    ],
    "name:por_x_preferred":[
        "Toma"
    ],
    "name:ron_x_preferred":[
        "Toma"
    ],
    "name:rus_x_preferred":[
        "\u0422\u043e\u043c\u0430"
    ],
    "name:spa_x_preferred":[
        "Toma"
    ],
    "name:swe_x_preferred":[
        "Toma"
    ],
    "name:ukr_x_preferred":[
        "\u0422\u043e\u043c\u0430"
    ],
    "wof:name":"Toma",
    "wof:placetype":"locality"
},
  "geometry": {"coordinates":[5.16667,12.83333],"type":"Point"}
}