{
  "type": "Feature",
  "properties": {
    "gn:admin1_code":"31.0",
    "gn:admin2_code":"27019",
    "gn:asciiname":"Lugopi",
    "gn:country_code":"NG",
    "gn:dem":291,
    "gn:feature_class":"P",
    "gn:feature_code":"PPL",
    "gn:name":"Lugopi",
    "gn:population":0,
    "gn:timezone":"Africa/Lagos",
    "iso:country":"NG",
    "wof:name":"Lugopi",
    "wof:placetype":"locality"
},
  "geometry": {"coordinates":[6.76056,9.53022],"type":"Point"}
}