{
  "type": "Feature",
  "properties": {
    "gn:admin1_code":"48.0",
    "gn:admin2_code":"29018.0",
    "gn:asciiname":"Rufus",
    "gn:country_code":"NG",
    "gn:dem":308,
    "gn:feature_class":"P",
    "gn:feature_code":"PPL",
    "gn:name":"Rufus",
    "gn:population":0,
    "gn:timezone":"Africa/Lagos",
    "iso:country":"NG",
    "wof:name":"Rufus",
    "wof:placetype":"locality"
},
  "geometry": {"coordinates":[5.4324,7.1839],"type":"Point"}
}