{
  "type": "Feature",
  "properties": {
    "gn:admin1_code":"48.0",
    "gn:admin2_code":"29018.0",
    "gn:asciiname":"Rufus",
    "gn:country_code":"NG",
    "gn:dem":308,
    "gn:feature_class":"P",
    "gn:feature_code":"PPL",
    "gn:name":"Rufus",
    "gn:population":0,
    "gn:timezone":"Africa/Lagos",
    "iso:country":"NG",
    "name:bul_x_preferred":[
        "\u0420\u0443\u0444"
    ],
    "name:deu_x_preferred":[
        "Rufus"
    ],
    "name:fin_x_preferred":[
        "Rufus"
    ],
    "name:fra_x_preferred":[
        "Rufus"
    ],
    "name:ind_x_preferred":[
        "Rufus"
    ],
    "name:ita_x_preferred":[
        "Rufus"
    ],
    "name:jpn_x_preferred":[
        "\u30eb\u30fc\u30d5\u30a1\u30b9"
    ],
    "name:nld_x_preferred":[
        "Rufus"
    ],
    "name:nno_x_preferred":[
        "Rufus"
    ],
    "name:pol_x_preferred":[
        "Rufus"
    ],
    "name:por_x_preferred":[
        "Rufus"
    ],
    "name:rus_x_preferred":[
        "\u0420\u0443\u0444"
    ],
    "name:spa_x_preferred":[
        "Rufo"
    ],
    "name:vie_x_preferred":[
        "Rufus"
    ],
    "wof:name":"Rufus",
    "wof:placetype":"locality"
},
  "geometry": {"coordinates":[5.4324,7.1839],"type":"Point"}
}