{
  "type": "Feature",
  "properties": {
    "gn:admin1_code":"46.0",
    "gn:admin2_code":"5007.0",
    "gn:admin3_code":"BA0706",
    "gn:asciiname":"Bonamari",
    "gn:country_code":"NG",
    "gn:dem":362,
    "gn:feature_class":"P",
    "gn:feature_code":"PPL",
    "gn:name":"Bonamari",
    "gn:population":0,
    "gn:timezone":"Africa/Lagos",
    "iso:country":"NG",
    "wof:name":"Bonamari",
    "wof:placetype":"locality"
},
  "geometry": {"coordinates":[10.58838,12.26578],"type":"Point"}
}