{
  "type": "Feature",
  "properties": {
    "gn:admin1_code":"41.0",
    "gn:admin2_code":"23011.0",
    "gn:asciiname":"Kusa da Gida",
    "gn:country_code":"NG",
    "gn:dem":167,
    "gn:feature_class":"P",
    "gn:feature_code":"PPL",
    "gn:name":"Kusa da Gida",
    "gn:population":0,
    "gn:timezone":"Africa/Lagos",
    "iso:country":"NG",
    "wof:name":"Kusa da Gida",
    "wof:placetype":"locality"
},
  "geometry": {"coordinates":[6.85,8.25],"type":"Point"}
}