{
  "type": "Feature",
  "properties": {
    "gn:admin1_code":"23.0",
    "gn:admin2_code":"19020.0",
    "gn:admin3_code":"KD2007",
    "gn:asciiname":"Numbu",
    "gn:country_code":"NG",
    "gn:dem":534,
    "gn:feature_class":"P",
    "gn:feature_code":"PPL",
    "gn:name":"Numbu",
    "gn:population":0,
    "gn:timezone":"Africa/Lagos",
    "iso:country":"NG",
    "name:und_x_variant":[
        "Nungbo"
    ],
    "wof:name":"Numbu",
    "wof:placetype":"locality"
},
  "geometry": {"coordinates":[8.43812,9.21246],"type":"Point"}
}