{
  "type": "Feature",
  "properties": {
    "gn:admin1_code":"46.0",
    "gn:admin2_code":"5014.0",
    "gn:admin3_code":"BA1402",
    "gn:asciiname":"Beti",
    "gn:country_code":"NG",
    "gn:dem":438,
    "gn:feature_class":"P",
    "gn:feature_code":"PPL",
    "gn:name":"Beti",
    "gn:population":0,
    "gn:timezone":"Africa/Lagos",
    "iso:country":"NG",
    "name:ceb_x_preferred":[
        "Beti"
    ],
    "name:deu_x_preferred":[
        "Beti"
    ],
    "name:eus_x_preferred":[
        "Beti"
    ],
    "name:rus_x_preferred":[
        "\u0411\u0435\u0442\u0438"
    ],
    "name:swe_x_preferred":[
        "Beti"
    ],
    "wof:name":"Beti",
    "wof:placetype":"locality"
},
  "geometry": {"coordinates":[10.42789,11.27796],"type":"Point"}
}