{
  "type": "Feature",
  "properties": {
    "gn:admin1_code":"50.0",
    "gn:admin2_code":"33011.0",
    "gn:asciiname":"Okomoko",
    "gn:country_code":"NG",
    "gn:dem":20,
    "gn:feature_class":"P",
    "gn:feature_code":"PPL",
    "gn:name":"Okomoko",
    "gn:population":0,
    "gn:timezone":"Africa/Lagos",
    "iso:country":"NG",
    "wof:name":"Okomoko",
    "wof:placetype":"locality"
},
  "geometry": {"coordinates":[7.06344,5.00282],"type":"Point"}
}