{
  "type": "Feature",
  "properties": {
    "gn:admin1_code":"43.0",
    "gn:admin2_code":"35003.0",
    "gn:asciiname":"Nukpo",
    "gn:country_code":"NG",
    "gn:dem":207,
    "gn:feature_class":"P",
    "gn:feature_code":"PPL",
    "gn:name":"Nukpo",
    "gn:population":0,
    "gn:timezone":"Africa/Lagos",
    "iso:country":"NG",
    "wof:name":"Nukpo",
    "wof:placetype":"locality"
},
  "geometry": {"coordinates":[10.54354,7.51739],"type":"Point"}
}