{
  "type": "Feature",
  "properties": {
    "gn:admin1_code":"27.0",
    "gn:admin2_code":"112.0",
    "gn:admin3_code":"11211",
    "gn:asciiname":"Thali",
    "gn:country_code":"NG",
    "gn:dem":675,
    "gn:feature_class":"P",
    "gn:feature_code":"PPL",
    "gn:name":"Thali",
    "gn:population":0,
    "gn:timezone":"Africa/Lagos",
    "iso:country":"NG",
    "wof:name":"Thali",
    "wof:placetype":"locality"
},
  "geometry": {"coordinates":[12.21996,10.47931],"type":"Point"}
}