{
  "type": "Feature",
  "properties": {
    "gn:admin1_code":"26.0",
    "gn:admin2_code":"7006.0",
    "gn:asciiname":"Agber",
    "gn:country_code":"NG",
    "gn:dem":131,
    "gn:feature_class":"P",
    "gn:feature_code":"PPL",
    "gn:name":"Agber",
    "gn:population":0,
    "gn:timezone":"Africa/Lagos",
    "iso:country":"NG",
    "wof:name":"Agber",
    "wof:placetype":"locality"
},
  "geometry": {"coordinates":[8.62996,7.8422],"type":"Point"}
}