{
  "type": "Feature",
  "properties": {
    "gn:admin1_code":"37.0",
    "gn:admin2_code":"12003.0",
    "gn:asciiname":"Olihlin",
    "gn:country_code":"NG",
    "gn:dem":145,
    "gn:feature_class":"P",
    "gn:feature_code":"PPL",
    "gn:name":"Olihlin",
    "gn:population":0,
    "gn:timezone":"Africa/Lagos",
    "iso:country":"NG",
    "name:eng_x_preferred":[
        "Olihlin"
    ],
    "name:eng_x_variant":[
        "Olili"
    ],
    "wof:name":"Olihlin",
    "wof:placetype":"locality"
},
  "geometry": {"coordinates":[6.41263,6.81561],"type":"Point"}
}