{
  "type": "Feature",
  "properties": {
    "gn:admin1_code":"47.0",
    "gn:admin2_code":"14015.0",
    "gn:asciiname":"Ezumo",
    "gn:country_code":"NG",
    "gn:dem":321,
    "gn:feature_class":"P",
    "gn:feature_code":"PPL",
    "gn:name":"Ezumo",
    "gn:population":0,
    "gn:timezone":"Africa/Lagos",
    "iso:country":"NG",
    "name:und_x_variant":[
        "Ezimo",
        "Ezumo"
    ],
    "wof:name":"Ezumo",
    "wof:placetype":"locality"
},
  "geometry": {"coordinates":[7.533,6.8693],"type":"Point"}
}