{
  "type": "Feature",
  "properties": {
    "gn:admin1_code":"29.0",
    "gn:admin2_code":"20023.0",
    "gn:admin3_code":"KN0807",
    "gn:asciiname":"Gwalaida",
    "gn:country_code":"NG",
    "gn:dem":437,
    "gn:feature_class":"P",
    "gn:feature_code":"PPL",
    "gn:name":"Gwalaida",
    "gn:population":0,
    "gn:timezone":"Africa/Lagos",
    "iso:country":"NG",
    "wof:name":"Gwalaida",
    "wof:placetype":"locality"
},
  "geometry": {"coordinates":[8.57241,12.46858],"type":"Point"}
}