{
  "type": "Feature",
  "properties": {
    "gn:admin1_code":"28.0",
    "gn:admin2_code":"17011.0",
    "gn:asciiname":"Eziama-Obiato",
    "gn:country_code":"NG",
    "gn:dem":91,
    "gn:feature_class":"P",
    "gn:feature_code":"PPL",
    "gn:name":"Eziama-Obiato",
    "gn:population":0,
    "gn:timezone":"Africa/Lagos",
    "iso:country":"NG",
    "wof:name":"Eziama-Obiato",
    "wof:placetype":"locality"
},
  "geometry": {"coordinates":[6.95672,5.62482],"type":"Point"}
}