{
  "type": "Feature",
  "properties": {
    "gn:admin1_code":"55.0",
    "gn:admin2_code":"16005.0",
    "gn:asciiname":"Saleri",
    "gn:country_code":"NG",
    "gn:dem":355,
    "gn:feature_class":"P",
    "gn:feature_code":"PPL",
    "gn:name":"Saleri",
    "gn:population":0,
    "gn:timezone":"Africa/Lagos",
    "iso:country":"NG",
    "wof:name":"Saleri",
    "wof:placetype":"locality"
},
  "geometry": {"coordinates":[11.34793,10.77339],"type":"Point"}
}