{
  "type": "Feature",
  "properties": {
    "gn:admin1_code":"24.0",
    "gn:admin2_code":"417.0",
    "gn:admin3_code":"41709",
    "gn:asciiname":"Dan Mairago",
    "gn:country_code":"NG",
    "gn:dem":600,
    "gn:feature_class":"P",
    "gn:feature_code":"PPL",
    "gn:name":"Dan Mairago",
    "gn:population":0,
    "gn:timezone":"Africa/Lagos",
    "iso:country":"NG",
    "wof:name":"Dan Mairago",
    "wof:placetype":"locality"
},
  "geometry": {"coordinates":[7.701,11.72688],"type":"Point"}
}