{
  "type": "Feature",
  "properties": {
    "gn:admin1_code":"46.0",
    "gn:admin2_code":"5017.0",
    "gn:admin3_code":"BA1705",
    "gn:asciiname":"Pem Giji",
    "gn:country_code":"NG",
    "gn:dem":1016,
    "gn:feature_class":"P",
    "gn:feature_code":"PPL",
    "gn:name":"Pem Giji",
    "gn:population":0,
    "gn:timezone":"Africa/Lagos",
    "iso:country":"NG",
    "wof:name":"Pem Giji",
    "wof:placetype":"locality"
},
  "geometry": {"coordinates":[9.31667,9.58333],"type":"Point"}
}