{
  "type": "Feature",
  "properties": {
    "gn:admin1_code":"27.0",
    "gn:admin2_code":"105.0",
    "gn:admin3_code":"10502",
    "gn:asciiname":"Zumta",
    "gn:country_code":"NG",
    "gn:dem":634,
    "gn:feature_class":"P",
    "gn:feature_code":"PPL",
    "gn:name":"Zumta",
    "gn:population":0,
    "gn:timezone":"Africa/Lagos",
    "iso:country":"NG",
    "wof:name":"Zumta",
    "wof:placetype":"locality"
},
  "geometry": {"coordinates":[12.10609,10.64452],"type":"Point"}
}