{
  "type": "Feature",
  "properties": {
    "iso:country":"NG",
    "name:cat_x_preferred":[
        "Gwoza"
    ],
    "name:eng_x_preferred":[
        "Gwoza"
    ],
    "name:fra_x_preferred":[
        "Gwoza"
    ],
    "name:ita_x_preferred":[
        "Gwoza"
    ],
    "name:yor_x_preferred":[
        "Agb\u00e8gb\u00e8 \u00ccj\u1ecdba \u00ccb\u00edl\u1eb9\u0300 Gwoza"
    ],
    "name:zho_min_nan_x_preferred":[
        "Gwoza"
    ],
    "name:zho_x_preferred":[
        "\u679c\u624e"
    ],
    "qs:gn_country":"NG",
    "qs:gn_fcode":"PPL",
    "qs:gn_pop":15176,
    "qs:name":"Gwoza",
    "qs:name_adm0":"Nigeria",
    "qs:name_adm1":"Borno",
    "qs:photos":0,
    "qs:photos_1k":0,
    "qs:photos_9k":1,
    "qs:photos_9r":1,
    "qs:photos_all":1,
    "qs:photos_sr":0,
    "qs:placetype":"Town",
    "qs:pop_sr":"6",
    "qs:woe_adm0":23424908,
    "wd:wordcount":1822,
    "wof:name":"Gwoza",
    "wof:placetype":"locality",
    "wof:population":15176
},
  "geometry": {"coordinates":[13.71298,11.10359],"type":"Point"}
}