{
  "type": "Feature",
  "properties": {
    "gn:admin1_code":"22.0",
    "gn:admin2_code":"9008.0",
    "gn:asciiname":"Ikot Ekpo",
    "gn:country_code":"NG",
    "gn:dem":77,
    "gn:feature_class":"P",
    "gn:feature_code":"PPL",
    "gn:name":"Ikot Ekpo",
    "gn:population":0,
    "gn:timezone":"Africa/Lagos",
    "iso:country":"NG",
    "wof:name":"Ikot Ekpo",
    "wof:placetype":"locality"
},
  "geometry": {"coordinates":[8.34989,5.07632],"type":"Point"}
}