{
  "type": "Feature",
  "properties": {
    "gn:admin1_code":"43.0",
    "gn:asciiname":"Kaluma",
    "gn:country_code":"NG",
    "gn:dem":241,
    "gn:feature_class":"P",
    "gn:feature_code":"PPL",
    "gn:name":"Kaluma",
    "gn:population":0,
    "gn:timezone":"Africa/Lagos",
    "iso:country":"NG",
    "name:eng_x_preferred":[
        "Kaluma"
    ],
    "wof:name":"Kaluma",
    "wof:placetype":"locality"
},
  "geometry": {"coordinates":[10.93936,9.37303],"type":"Point"}
}