{
  "type": "Feature",
  "properties": {
    "gn:admin1_code":"35.0",
    "gn:admin2_code":"2003.0",
    "gn:asciiname":"Gang Larani",
    "gn:country_code":"NG",
    "gn:dem":441,
    "gn:feature_class":"P",
    "gn:feature_code":"PPL",
    "gn:name":"Gang Larani",
    "gn:population":0,
    "gn:timezone":"Africa/Lagos",
    "iso:country":"NG",
    "wof:name":"Gang Larani",
    "wof:placetype":"locality"
},
  "geometry": {"coordinates":[12.21667,8.33333],"type":"Point"}
}