{
  "type": "Feature",
  "properties": {
    "gn:admin1_code":"27.0",
    "gn:admin2_code":"112.0",
    "gn:admin3_code":"11202",
    "gn:asciiname":"Gurum",
    "gn:country_code":"NG",
    "gn:dem":633,
    "gn:feature_class":"P",
    "gn:feature_code":"PPL",
    "gn:name":"Gurum",
    "gn:population":0,
    "gn:timezone":"Africa/Lagos",
    "iso:country":"NG",
    "name:msa_x_preferred":[
        "Gurum"
    ],
    "name:und_x_variant":[
        "Girim"
    ],
    "wof:name":"Gurum",
    "wof:placetype":"locality"
},
  "geometry": {"coordinates":[12.0125,10.58011],"type":"Point"}
}