{
  "type": "Feature",
  "properties": {
    "gn:admin1_code":"39.0",
    "gn:asciiname":"Mamada",
    "gn:country_code":"NG",
    "gn:dem":353,
    "gn:feature_class":"P",
    "gn:feature_code":"PPL",
    "gn:name":"Mamada",
    "gn:population":0,
    "gn:timezone":"Africa/Lagos",
    "iso:country":"NG",
    "wof:name":"Mamada",
    "wof:placetype":"locality"
},
  "geometry": {"coordinates":[10.08856,13.00078],"type":"Point"}
}