{
  "type": "Feature",
  "properties": {
    "gn:admin1_code":"27.0",
    "gn:admin2_code":"112.0",
    "gn:admin3_code":"11202",
    "gn:asciiname":"Lakeri",
    "gn:country_code":"NG",
    "gn:dem":658,
    "gn:feature_class":"P",
    "gn:feature_code":"PPL",
    "gn:name":"Lakeri",
    "gn:population":0,
    "gn:timezone":"Africa/Lagos",
    "iso:country":"NG",
    "wof:name":"Lakeri",
    "wof:placetype":"locality"
},
  "geometry": {"coordinates":[12.03109,10.59843],"type":"Point"}
}