{
  "type": "Feature",
  "properties": {
    "gn:admin1_code":"35.0",
    "gn:admin2_code":"2007.0",
    "gn:asciiname":"Kilim",
    "gn:country_code":"NG",
    "gn:dem":531,
    "gn:feature_class":"P",
    "gn:feature_code":"PPL",
    "gn:name":"Kilim",
    "gn:population":0,
    "gn:timezone":"Africa/Lagos",
    "iso:country":"NG",
    "name:ara_x_preferred":[
        "\u0643\u0644\u064a\u0645"
    ],
    "name:aze_x_preferred":[
        "Kilim"
    ],
    "name:bos_x_preferred":[
        "\u0106ilim"
    ],
    "name:bul_x_preferred":[
        "\u041a\u0438\u043b\u0438\u043c"
    ],
    "name:ces_x_preferred":[
        "Kelim"
    ],
    "name:deu_x_preferred":[
        "Kelim"
    ],
    "name:fas_x_preferred":[
        "\u06af\u0644\u06cc\u0645"
    ],
    "name:fin_x_preferred":[
        "Kelim"
    ],
    "name:fra_x_preferred":[
        "Kilim"
    ],
    "name:hrv_x_preferred":[
        "\u0106ilim"
    ],
    "name:hun_x_preferred":[
        "Kilim"
    ],
    "name:ita_x_preferred":[
        "Kilim"
    ],
    "name:jpn_x_preferred":[
        "\u30ad\u30ea\u30e0"
    ],
    "name:nav_x_preferred":[
        "Kilim"
    ],
    "name:nld_x_preferred":[
        "Kelim"
    ],
    "name:nor_x_preferred":[
        "Kelim"
    ],
    "name:pol_x_preferred":[
        "Kilim"
    ],
    "name:por_x_preferred":[
        "Kilim"
    ],
    "name:rus_x_preferred":[
        "\u041a\u0438\u043b\u0438\u043c"
    ],
    "name:srp_x_preferred":[
        "\u040b\u0438\u043b\u0438\u043c"
    ],
    "name:swe_x_preferred":[
        "Kelim"
    ],
    "name:tur_x_preferred":[
        "Kilim"
    ],
    "wof:name":"Kilim",
    "wof:placetype":"locality"
},
  "geometry": {"coordinates":[13.09303,10.21692],"type":"Point"}
}