{
  "type": "Feature",
  "properties": {
    "gn:admin1_code":"35.0",
    "gn:admin2_code":"2007.0",
    "gn:asciiname":"Kilim",
    "gn:country_code":"NG",
    "gn:dem":531,
    "gn:feature_class":"P",
    "gn:feature_code":"PPL",
    "gn:name":"Kilim",
    "gn:population":0,
    "gn:timezone":"Africa/Lagos",
    "iso:country":"NG",
    "wof:name":"Kilim",
    "wof:placetype":"locality"
},
  "geometry": {"coordinates":[13.09303,10.21692],"type":"Point"}
}