{
  "type": "Feature",
  "properties": {
    "gn:admin1_code":"21.0",
    "gn:admin2_code":"3015.0",
    "gn:asciiname":"Itak-Edem-Isa",
    "gn:country_code":"NG",
    "gn:dem":134,
    "gn:feature_class":"P",
    "gn:feature_code":"PPL",
    "gn:name":"Itak-Edem-Isa",
    "gn:population":0,
    "gn:timezone":"Africa/Lagos",
    "iso:country":"NG",
    "wof:name":"Itak-Edem-Isa",
    "wof:placetype":"locality"
},
  "geometry": {"coordinates":[7.67882,5.31383],"type":"Point"}
}