{
  "type": "Feature",
  "properties": {
    "gn:admin1_code":"22.0",
    "gn:admin2_code":"9005",
    "gn:asciiname":"Ayadie",
    "gn:country_code":"NG",
    "gn:dem":148,
    "gn:feature_class":"P",
    "gn:feature_code":"PPL",
    "gn:name":"Ayadie",
    "gn:population":0,
    "gn:timezone":"Africa/Lagos",
    "iso:country":"NG",
    "wof:name":"Ayadie",
    "wof:placetype":"locality"
},
  "geometry": {"coordinates":[8.95315,6.70077],"type":"Point"}
}