{
  "type": "Feature",
  "properties": {
    "gn:admin1_code":"43.0",
    "gn:admin2_code":"35006.0",
    "gn:asciiname":"Kauyen Sarkin Baka",
    "gn:country_code":"NG",
    "gn:dem":112,
    "gn:feature_class":"P",
    "gn:feature_code":"PPL",
    "gn:name":"Kauyen Sarkin Baka",
    "gn:population":0,
    "gn:timezone":"Africa/Lagos",
    "iso:country":"NG",
    "wof:name":"Kauyen Sarkin Baka",
    "wof:placetype":"locality"
},
  "geometry": {"coordinates":[9.78073,8.15635],"type":"Point"}
}