{
  "type": "Feature",
  "properties": {
    "gn:admin1_code":"24.0",
    "gn:admin2_code":"415.0",
    "gn:admin3_code":"41503",
    "gn:asciiname":"Dara",
    "gn:country_code":"NG",
    "gn:dem":520,
    "gn:feature_class":"P",
    "gn:feature_code":"PPL",
    "gn:name":"Dara",
    "gn:population":0,
    "gn:timezone":"Africa/Lagos",
    "iso:country":"NG",
    "wof:name":"Dara",
    "wof:placetype":"locality"
},
  "geometry": {"coordinates":[8.12759,12.69524],"type":"Point"}
}