{
  "type": "Feature",
  "properties": {
    "gn:admin1_code":"24.0",
    "gn:admin2_code":"430.0",
    "gn:admin3_code":"43003",
    "gn:asciiname":"Bujawa",
    "gn:country_code":"NG",
    "gn:dem":502,
    "gn:feature_class":"P",
    "gn:feature_code":"PPL",
    "gn:name":"Bujawa",
    "gn:population":0,
    "gn:timezone":"Africa/Lagos",
    "iso:country":"NG",
    "wof:name":"Bujawa",
    "wof:placetype":"locality"
},
  "geometry": {"coordinates":[7.75394,12.82586],"type":"Point"}
}