{
  "type": "Feature",
  "properties": {
    "gn:admin1_code":"26.0",
    "gn:admin2_code":"7005",
    "gn:asciiname":"Ugo",
    "gn:country_code":"NG",
    "gn:dem":169,
    "gn:feature_class":"P",
    "gn:feature_code":"PPL",
    "gn:name":"Ugo",
    "gn:population":0,
    "gn:timezone":"Africa/Lagos",
    "iso:country":"NG",
    "name:ces_x_preferred":[
        "Ugo"
    ],
    "name:deu_x_preferred":[
        "Ugo"
    ],
    "name:nld_x_preferred":[
        "Ugo"
    ],
    "name:por_x_preferred":[
        "Ugo"
    ],
    "name:rus_x_preferred":[
        "\u0423\u0433\u043e"
    ],
    "wof:name":"Ugo",
    "wof:placetype":"locality"
},
  "geometry": {"coordinates":[8.85431,7.31461],"type":"Point"}
}