{
  "type": "Feature",
  "properties": {
    "gn:admin1_code":"46.0",
    "gn:admin2_code":"5011.0",
    "gn:admin3_code":"BA1107",
    "gn:asciiname":"Gellar",
    "gn:country_code":"NG",
    "gn:dem":389,
    "gn:feature_class":"P",
    "gn:feature_code":"PPL",
    "gn:name":"Gellar",
    "gn:population":0,
    "gn:timezone":"Africa/Lagos",
    "iso:country":"NG",
    "name:uzb_x_preferred":[
        "Gellar"
    ],
    "wof:name":"Gellar",
    "wof:placetype":"locality"
},
  "geometry": {"coordinates":[9.96667,11.71667],"type":"Point"}
}