{
  "type": "Feature",
  "properties": {
    "gn:admin1_code":"35.0",
    "gn:admin2_code":"2013.0",
    "gn:asciiname":"Jigalambu",
    "gn:country_code":"NG",
    "gn:dem":505,
    "gn:feature_class":"P",
    "gn:feature_code":"PPL",
    "gn:name":"Jigalambu",
    "gn:population":0,
    "gn:timezone":"Africa/Lagos",
    "iso:country":"NG",
    "wof:name":"Jigalambu",
    "wof:placetype":"locality"
},
  "geometry": {"coordinates":[13.32535,10.57176],"type":"Point"}
}