{
  "type": "Feature",
  "properties": {
    "gn:admin1_code":"23.0",
    "gn:admin2_code":"19002.0",
    "gn:admin3_code":"KD0205",
    "gn:asciiname":"Yargunu",
    "gn:country_code":"NG",
    "gn:dem":565,
    "gn:feature_class":"P",
    "gn:feature_code":"PPL",
    "gn:name":"Yargunu",
    "gn:population":0,
    "gn:timezone":"Africa/Lagos",
    "iso:country":"NG",
    "wof:name":"Yargunu",
    "wof:placetype":"locality"
},
  "geometry": {"coordinates":[7.23333,10.51667],"type":"Point"}
}