{
  "type": "Feature",
  "properties": {
    "gn:admin1_code":"30.0",
    "gn:admin2_code":"24016.0",
    "gn:asciiname":"Kpada",
    "gn:country_code":"NG",
    "gn:dem":111,
    "gn:feature_class":"P",
    "gn:feature_code":"PPL",
    "gn:name":"Kpada",
    "gn:population":0,
    "gn:timezone":"Africa/Lagos",
    "iso:country":"NG",
    "name:fra_x_preferred":[
        "Kpada"
    ],
    "name:msa_x_preferred":[
        "Kpada"
    ],
    "name:ron_x_preferred":[
        "Kpada"
    ],
    "wof:name":"Kpada",
    "wof:placetype":"locality"
},
  "geometry": {"coordinates":[6.08333,8.65],"type":"Point"}
}