{
  "type": "Feature",
  "properties": {
    "gn:admin1_code":"23.0",
    "gn:admin2_code":"19022",
    "gn:admin3_code":"KD2202",
    "gn:asciiname":"Bafai",
    "gn:country_code":"NG",
    "gn:dem":850,
    "gn:feature_class":"P",
    "gn:feature_code":"PPL",
    "gn:name":"Bafai",
    "gn:population":0,
    "gn:timezone":"Africa/Lagos",
    "iso:country":"NG",
    "wof:name":"Bafai",
    "wof:placetype":"locality"
},
  "geometry": {"coordinates":[8.29528,9.86481],"type":"Point"}
}