{
  "type": "Feature",
  "properties": {
    "gn:admin1_code":"16.0",
    "gn:admin2_code":"28020.0",
    "gn:asciiname":"Makun",
    "gn:country_code":"NG",
    "gn:dem":63,
    "gn:feature_class":"P",
    "gn:feature_code":"PPL",
    "gn:name":"Makun",
    "gn:population":0,
    "gn:timezone":"Africa/Lagos",
    "iso:country":"NG",
    "name:und_x_variant":[
        "Orile-Makun",
        "Makun"
    ],
    "wof:name":"Makun",
    "wof:placetype":"neighbourhood"
},
  "geometry": {"coordinates":[3.62724,6.8545],"type":"Point"}
}