{
  "type": "Feature",
  "properties": {
    "gn:admin1_code":"22.0",
    "gn:admin2_code":"9007.0",
    "gn:asciiname":"Onya",
    "gn:country_code":"NG",
    "gn:dem":123,
    "gn:feature_class":"P",
    "gn:feature_code":"PPL",
    "gn:name":"Onya",
    "gn:population":0,
    "gn:timezone":"Africa/Lagos",
    "iso:country":"NG",
    "name:und_x_variant":[
        "Onyo",
        "Onya"
    ],
    "wof:name":"Onya",
    "wof:placetype":"locality"
},
  "geometry": {"coordinates":[8.91676,6.48642],"type":"Point"}
}