{
  "type": "Feature",
  "properties": {
    "gn:admin1_code":"24.0",
    "gn:admin2_code":"414.0",
    "gn:admin3_code":"41404",
    "gn:asciiname":"Ungwan Mallam",
    "gn:country_code":"NG",
    "gn:dem":638,
    "gn:feature_class":"P",
    "gn:feature_code":"PPL",
    "gn:name":"Ungwan Mallam",
    "gn:population":0,
    "gn:timezone":"Africa/Lagos",
    "iso:country":"NG",
    "wof:name":"Ungwan Mallam",
    "wof:placetype":"locality"
},
  "geometry": {"coordinates":[7.18418,11.58196],"type":"Point"}
}