{
  "type": "Feature",
  "properties": {
    "gn:admin1_code":"44.0",
    "gn:admin2_code":"710",
    "gn:admin3_code":"71008",
    "gn:asciiname":"Bugu",
    "gn:country_code":"NG",
    "gn:dem":342,
    "gn:feature_class":"P",
    "gn:feature_code":"PPL",
    "gn:name":"Bugu",
    "gn:population":0,
    "gn:timezone":"Africa/Lagos",
    "iso:country":"NG",
    "wof:name":"Bugu",
    "wof:placetype":"locality"
},
  "geometry": {"coordinates":[10.87655,13.08209],"type":"Point"}
}