{
  "type": "Feature",
  "properties": {
    "gn:admin1_code":"29.0",
    "gn:admin2_code":"20004.0",
    "gn:admin3_code":"KN0102",
    "gn:asciiname":"Gedawa",
    "gn:country_code":"NG",
    "gn:dem":404,
    "gn:feature_class":"P",
    "gn:feature_code":"PPL",
    "gn:name":"Gedawa",
    "gn:population":0,
    "gn:timezone":"Africa/Lagos",
    "iso:country":"NG",
    "wof:name":"Gedawa",
    "wof:placetype":"locality"
},
  "geometry": {"coordinates":[8.95049,12.01285],"type":"Point"}
}