{
  "type": "Feature",
  "properties": {
    "gn:admin1_code":"39.0",
    "gn:admin2_code":"18024.0",
    "gn:admin3_code":"JI0806",
    "gn:asciiname":"Hatsi Yekawoni",
    "gn:country_code":"NG",
    "gn:dem":395,
    "gn:feature_class":"P",
    "gn:feature_code":"PPL",
    "gn:name":"Hatsi Yekawoni",
    "gn:population":0,
    "gn:timezone":"Africa/Lagos",
    "iso:country":"NG",
    "wof:name":"Hatsi Yekawoni",
    "wof:placetype":"locality"
},
  "geometry": {"coordinates":[8.91761,12.33486],"type":"Point"}
}