{
  "type": "Feature",
  "properties": {
    "gn:admin1_code":"35.0",
    "gn:admin2_code":"2002.0",
    "gn:asciiname":"Tullabembi",
    "gn:country_code":"NG",
    "gn:dem":256,
    "gn:feature_class":"P",
    "gn:feature_code":"PPL",
    "gn:name":"Tullabembi",
    "gn:population":0,
    "gn:timezone":"Africa/Lagos",
    "iso:country":"NG",
    "wof:name":"Tullabembi",
    "wof:placetype":"locality"
},
  "geometry": {"coordinates":[12.27989,8.94282],"type":"Point"}
}