{
  "type": "Feature",
  "properties": {
    "gn:admin1_code":"45.0",
    "gn:admin2_code":"1016.0",
    "gn:asciiname":"Ajata-Isieke",
    "gn:country_code":"NG",
    "gn:dem":127,
    "gn:feature_class":"P",
    "gn:feature_code":"PPL",
    "gn:name":"Ajata-Isieke",
    "gn:population":0,
    "gn:timezone":"Africa/Lagos",
    "iso:country":"NG",
    "wof:name":"Ajata-Isieke",
    "wof:placetype":"locality"
},
  "geometry": {"coordinates":[7.53041,5.54465],"type":"Point"}
}