{
  "type": "Feature",
  "properties": {
    "gn:admin1_code":"24.0",
    "gn:admin2_code":"422.0",
    "gn:admin3_code":"42203",
    "gn:asciiname":"Yakasai",
    "gn:country_code":"NG",
    "gn:dem":513,
    "gn:feature_class":"P",
    "gn:feature_code":"PPL",
    "gn:name":"Yakasai",
    "gn:population":0,
    "gn:timezone":"Africa/Lagos",
    "iso:country":"NG",
    "wof:name":"Yakasai",
    "wof:placetype":"locality"
},
  "geometry": {"coordinates":[7.51384,12.68989],"type":"Point"}
}