{
  "type": "Feature",
  "properties": {
    "gn:admin1_code":"43.0",
    "gn:admin2_code":"35006",
    "gn:asciiname":"Ruwan-Duse",
    "gn:country_code":"NG",
    "gn:dem":119,
    "gn:feature_class":"P",
    "gn:feature_code":"PPL",
    "gn:name":"Ruwan-Duse",
    "gn:population":0,
    "gn:timezone":"Africa/Lagos",
    "iso:country":"NG",
    "wof:name":"Ruwan-Duse",
    "wof:placetype":"locality"
},
  "geometry": {"coordinates":[10.09297,8.53655],"type":"Point"}
}