{
  "type": "Feature",
  "properties": {
    "gn:admin1_code":"48.0",
    "gn:admin2_code":"29015.0",
    "gn:asciiname":"Kajola",
    "gn:country_code":"NG",
    "gn:dem":267,
    "gn:feature_class":"P",
    "gn:feature_code":"PPL",
    "gn:name":"Kajola",
    "gn:population":0,
    "gn:timezone":"Africa/Lagos",
    "iso:country":"NG",
    "name:fra_x_preferred":[
        "Kajola"
    ],
    "name:hau_x_preferred":[
        "Kajola"
    ],
    "name:ita_x_preferred":[
        "Kajola"
    ],
    "name:spa_x_preferred":[
        "Kajola"
    ],
    "name:und_x_variant":[
        "Kajola Owena"
    ],
    "wof:name":"Kajola",
    "wof:placetype":"locality"
},
  "geometry": {"coordinates":[5.00122,7.17381],"type":"Point"}
}