{
  "type": "Feature",
  "properties": {
    "gn:admin1_code":"57.0",
    "gn:admin2_code":"805.0",
    "gn:admin3_code":"80508",
    "gn:asciiname":"Guidan Buzu",
    "gn:country_code":"NG",
    "gn:dem":424,
    "gn:feature_class":"P",
    "gn:feature_code":"PPL",
    "gn:name":"Guidan Buzu",
    "gn:population":0,
    "gn:timezone":"Africa/Lagos",
    "iso:country":"NG",
    "name:und_x_variant":[
        "Gidan Buzu",
        "Guidan Buzu"
    ],
    "wof:name":"Guidan Buzu",
    "wof:placetype":"locality"
},
  "geometry": {"coordinates":[6.49861,12.34947],"type":"Point"}
}