{
  "type": "Feature",
  "properties": {
    "gn:admin1_code":"40.0",
    "gn:admin2_code":"506.0",
    "gn:admin3_code":"50604",
    "gn:asciiname":"Damana",
    "gn:country_code":"NG",
    "gn:dem":206,
    "gn:feature_class":"P",
    "gn:feature_code":"PPL",
    "gn:name":"Damana",
    "gn:population":0,
    "gn:timezone":"Africa/Lagos",
    "iso:country":"NG",
    "name:ceb_x_preferred":[
        "Damana"
    ],
    "name:fra_x_preferred":[
        "Damana"
    ],
    "name:swe_x_preferred":[
        "Damana"
    ],
    "wof:name":"Damana",
    "wof:placetype":"locality"
},
  "geometry": {"coordinates":[4.24845,12.55046],"type":"Point"}
}