{
  "type": "Feature",
  "properties": {
    "gn:admin1_code":"27.0",
    "gn:admin2_code":"103.0",
    "gn:admin3_code":"10309",
    "gn:asciiname":"Jakana",
    "gn:country_code":"NG",
    "gn:dem":302,
    "gn:feature_class":"P",
    "gn:feature_code":"PPL",
    "gn:name":"Jakana",
    "gn:population":0,
    "gn:timezone":"Africa/Lagos",
    "iso:country":"NG",
    "wof:name":"Jakana",
    "wof:placetype":"locality"
},
  "geometry": {"coordinates":[14.04097,11.66505],"type":"Point"}
}