{
  "type": "Feature",
  "properties": {
    "gn:admin1_code":"46.0",
    "gn:asciiname":"Burabayi",
    "gn:country_code":"NG",
    "gn:dem":306,
    "gn:feature_class":"P",
    "gn:feature_code":"PPL",
    "gn:name":"Burabayi",
    "gn:population":0,
    "gn:timezone":"Africa/Lagos",
    "iso:country":"NG",
    "name:eng_x_preferred":[
        "Burabayi"
    ],
    "wof:name":"Burabayi",
    "wof:placetype":"locality"
},
  "geometry": {"coordinates":[10.77287,9.67188],"type":"Point"}
}