{
  "type": "Feature",
  "properties": {
    "gn:admin1_code":"26.0",
    "gn:admin2_code":"7011.0",
    "gn:asciiname":"Zel",
    "gn:country_code":"NG",
    "gn:dem":223,
    "gn:feature_class":"P",
    "gn:feature_code":"PPL",
    "gn:name":"Zel",
    "gn:population":0,
    "gn:timezone":"Africa/Lagos",
    "iso:country":"NG",
    "wof:name":"Zel",
    "wof:placetype":"locality"
},
  "geometry": {"coordinates":[9.54884,6.75512],"type":"Point"}
}