{
  "type": "Feature",
  "properties": {
    "gn:admin1_code":"31.0",
    "gn:admin2_code":"27023",
    "gn:asciiname":"Bakiku",
    "gn:country_code":"NG",
    "gn:dem":444,
    "gn:feature_class":"P",
    "gn:feature_code":"PPL",
    "gn:name":"Bakiku",
    "gn:population":0,
    "gn:timezone":"Africa/Lagos",
    "iso:country":"NG",
    "wof:name":"Bakiku",
    "wof:placetype":"locality"
},
  "geometry": {"coordinates":[7.2049,9.19495],"type":"Point"}
}