{
  "type": "Feature",
  "properties": {
    "gn:admin1_code":"45.0",
    "gn:admin2_code":"1006.0",
    "gn:asciiname":"Ama Ekpu",
    "gn:country_code":"NG",
    "gn:dem":111,
    "gn:feature_class":"P",
    "gn:feature_code":"PPL",
    "gn:name":"Ama Ekpu",
    "gn:population":0,
    "gn:timezone":"Africa/Lagos",
    "iso:country":"NG",
    "wof:name":"Ama Ekpu",
    "wof:placetype":"locality"
},
  "geometry": {"coordinates":[7.33333,5.33333],"type":"Point"}
}