{
  "type": "Feature",
  "properties": {
    "gn:admin1_code":"27.0",
    "gn:admin2_code":"119.0",
    "gn:admin3_code":"11909",
    "gn:asciiname":"Maga Jayewa",
    "gn:country_code":"NG",
    "gn:dem":301,
    "gn:feature_class":"P",
    "gn:feature_code":"PPL",
    "gn:name":"Maga Jayewa",
    "gn:population":0,
    "gn:timezone":"Africa/Lagos",
    "iso:country":"NG",
    "wof:name":"Maga Jayewa",
    "wof:placetype":"locality"
},
  "geometry": {"coordinates":[13.33739,12.2148],"type":"Point"}
}