{
  "type": "Feature",
  "properties": {
    "gn:admin1_code":"40.0",
    "gn:asciiname":"Madachi",
    "gn:country_code":"NG",
    "gn:dem":210,
    "gn:feature_class":"P",
    "gn:feature_code":"PPL",
    "gn:name":"Madachi",
    "gn:population":0,
    "gn:timezone":"Africa/Lagos",
    "iso:country":"NG",
    "name:und_x_variant":[
        "Mawadachi",
        "Madachi"
    ],
    "wof:name":"Madachi",
    "wof:placetype":"locality"
},
  "geometry": {"coordinates":[4.55982,12.20902],"type":"Point"}
}