{
  "type": "Feature",
  "properties": {
    "gn:admin1_code":"24.0",
    "gn:admin2_code":"401.0",
    "gn:admin3_code":"40102",
    "gn:asciiname":"Kokabo",
    "gn:country_code":"NG",
    "gn:dem":642,
    "gn:feature_class":"P",
    "gn:feature_code":"PPL",
    "gn:name":"Kokabo",
    "gn:population":0,
    "gn:timezone":"Africa/Lagos",
    "iso:country":"NG",
    "wof:name":"Kokabo",
    "wof:placetype":"locality"
},
  "geometry": {"coordinates":[7.45581,11.56488],"type":"Point"}
}