{
  "type": "Feature",
  "properties": {
    "gn:admin1_code":"27.0",
    "gn:admin2_code":"102",
    "gn:admin3_code":"10204",
    "gn:asciiname":"Yerima Madagali",
    "gn:country_code":"NG",
    "gn:dem":478,
    "gn:feature_class":"P",
    "gn:feature_code":"PPL",
    "gn:name":"Yerima Madagali",
    "gn:population":0,
    "gn:timezone":"Africa/Lagos",
    "iso:country":"NG",
    "name:eng_x_preferred":[
        "Yerima Madagali"
    ],
    "wof:name":"Yerima Madagali",
    "wof:placetype":"locality"
},
  "geometry": {"coordinates":[13.23025,10.54243],"type":"Point"}
}