{
  "type": "Feature",
  "properties": {
    "gn:admin1_code":"50.0",
    "gn:admin2_code":"33014.0",
    "gn:asciiname":"Tem Luekon",
    "gn:country_code":"NG",
    "gn:dem":26,
    "gn:feature_class":"P",
    "gn:feature_code":"PPL",
    "gn:name":"Tem Luekon",
    "gn:population":0,
    "gn:timezone":"Africa/Lagos",
    "iso:country":"NG",
    "wof:name":"Tem Luekon",
    "wof:placetype":"locality"
},
  "geometry": {"coordinates":[7.43951,4.74287],"type":"Point"}
}