{
  "type": "Feature",
  "properties": {
    "gn:admin1_code":"54.0",
    "gn:admin2_code":"13009.0",
    "gn:asciiname":"Ikoro",
    "gn:country_code":"NG",
    "gn:dem":480,
    "gn:feature_class":"P",
    "gn:feature_code":"PPL",
    "gn:name":"Ikoro",
    "gn:population":0,
    "gn:timezone":"Africa/Lagos",
    "iso:country":"NG",
    "wof:name":"Ikoro",
    "wof:placetype":"locality"
},
  "geometry": {"coordinates":[5.04074,7.83679],"type":"Point"}
}