{
  "type": "Feature",
  "properties": {
    "gn:admin1_code":"23.0",
    "gn:admin2_code":"19008.0",
    "gn:admin3_code":"KD0803",
    "gn:asciiname":"Awan",
    "gn:country_code":"NG",
    "gn:dem":668,
    "gn:feature_class":"P",
    "gn:feature_code":"PPL",
    "gn:name":"Awan",
    "gn:population":0,
    "gn:timezone":"Africa/Lagos",
    "iso:country":"NG",
    "name:und_x_variant":[
        "Awam",
        "Awan"
    ],
    "wof:name":"Awan",
    "wof:placetype":"locality"
},
  "geometry": {"coordinates":[7.80641,9.78097],"type":"Point"}
}