{
  "type": "Feature",
  "properties": {
    "gn:admin1_code":"21.0",
    "gn:admin2_code":"3026.0",
    "gn:asciiname":"Ikot Akpan Essien",
    "gn:country_code":"NG",
    "gn:dem":34,
    "gn:feature_class":"P",
    "gn:feature_code":"PPL",
    "gn:name":"Ikot Akpan Essien",
    "gn:population":0,
    "gn:timezone":"Africa/Lagos",
    "iso:country":"NG",
    "name:und_x_variant":[
        "Ikot Akpan Esien",
        "Ikot Akpan Essien"
    ],
    "wof:name":"Ikot Akpan Essien",
    "wof:placetype":"locality"
},
  "geometry": {"coordinates":[7.63414,4.72772],"type":"Point"}
}