{
  "type": "Feature",
  "properties": {
    "gn:admin1_code":"46.0",
    "gn:admin2_code":"5008.0",
    "gn:admin3_code":"BA0811",
    "gn:asciiname":"Piru",
    "gn:country_code":"NG",
    "gn:dem":562,
    "gn:feature_class":"P",
    "gn:feature_code":"PPL",
    "gn:name":"Piru",
    "gn:population":0,
    "gn:timezone":"Africa/Lagos",
    "iso:country":"NG",
    "name:ceb_x_preferred":[
        "Piru"
    ],
    "name:nld_x_preferred":[
        "Piru"
    ],
    "name:por_x_preferred":[
        "Piru"
    ],
    "wof:name":"Piru",
    "wof:placetype":"locality"
},
  "geometry": {"coordinates":[9.86683,10.40916],"type":"Point"}
}