{
  "type": "Feature",
  "properties": {
    "gn:admin1_code":"35.0",
    "gn:admin2_code":"2011",
    "gn:asciiname":"Jamtari",
    "gn:country_code":"NG",
    "gn:dem":595,
    "gn:feature_class":"P",
    "gn:feature_code":"PPL",
    "gn:name":"Jamtari",
    "gn:population":0,
    "gn:timezone":"Africa/Lagos",
    "iso:country":"NG",
    "wof:name":"Jamtari",
    "wof:placetype":"locality"
},
  "geometry": {"coordinates":[13.13636,9.88859],"type":"Point"}
}