{
  "type": "Feature",
  "properties": {
    "gn:admin1_code":"24.0",
    "gn:asciiname":"Kudan",
    "gn:country_code":"NG",
    "gn:dem":672,
    "gn:feature_class":"P",
    "gn:feature_code":"PPL",
    "gn:name":"Kudan",
    "gn:population":0,
    "gn:timezone":"Africa/Lagos",
    "iso:country":"NG",
    "name:ceb_x_preferred":[
        "Kudan"
    ],
    "name:ita_x_preferred":[
        "Kudan"
    ],
    "name:spa_x_preferred":[
        "Kudan"
    ],
    "wof:name":"Kudan",
    "wof:placetype":"locality"
},
  "geometry": {"coordinates":[7.73161,11.3069],"type":"Point"}
}