{
  "type": "Feature",
  "properties": {
    "gn:admin1_code":"44.0",
    "gn:admin2_code":"714.0",
    "gn:admin3_code":"71412",
    "gn:asciiname":"Yandiski",
    "gn:country_code":"NG",
    "gn:dem":416,
    "gn:feature_class":"P",
    "gn:feature_code":"PPL",
    "gn:name":"Yandiski",
    "gn:population":0,
    "gn:timezone":"Africa/Lagos",
    "iso:country":"NG",
    "name:und_x_variant":[
        "Yendiski",
        "Yandiski"
    ],
    "wof:name":"Yandiski",
    "wof:placetype":"locality"
},
  "geometry": {"coordinates":[11.09207,11.73113],"type":"Point"}
}