{
  "type": "Feature",
  "properties": {
    "gn:admin1_code":"47.0",
    "gn:admin2_code":"14017.0",
    "gn:asciiname":"Opanda",
    "gn:country_code":"NG",
    "gn:dem":84,
    "gn:feature_class":"P",
    "gn:feature_code":"PPL",
    "gn:name":"Opanda",
    "gn:population":0,
    "gn:timezone":"Africa/Lagos",
    "iso:country":"NG",
    "wof:name":"Opanda",
    "wof:placetype":"locality"
},
  "geometry": {"coordinates":[7.09135,6.7994],"type":"Point"}
}