{
  "type": "Feature",
  "properties": {
    "gn:admin1_code":"29.0",
    "gn:admin2_code":"20019.0",
    "gn:admin3_code":"KN4312",
    "gn:asciiname":"Tanagar",
    "gn:country_code":"NG",
    "gn:dem":461,
    "gn:feature_class":"P",
    "gn:feature_code":"PPL",
    "gn:name":"Tanagar",
    "gn:population":0,
    "gn:timezone":"Africa/Lagos",
    "iso:country":"NG",
    "wof:name":"Tanagar",
    "wof:placetype":"locality"
},
  "geometry": {"coordinates":[8.69178,11.95129],"type":"Point"}
}