{
  "type": "Feature",
  "properties": {
    "gn:admin1_code":"27.0",
    "gn:admin2_code":"105.0",
    "gn:admin3_code":"10508",
    "gn:asciiname":"Darazau",
    "gn:country_code":"NG",
    "gn:dem":687,
    "gn:feature_class":"P",
    "gn:feature_code":"PPL",
    "gn:name":"Darazau",
    "gn:population":0,
    "gn:timezone":"Africa/Lagos",
    "iso:country":"NG",
    "wof:name":"Darazau",
    "wof:placetype":"locality"
},
  "geometry": {"coordinates":[12.15539,10.69031],"type":"Point"}
}