{
  "type": "Feature",
  "properties": {
    "gn:admin1_code":"40.0",
    "gn:admin2_code":"515.0",
    "gn:admin3_code":"51510",
    "gn:asciiname":"Iyakan Kasa",
    "gn:country_code":"NG",
    "gn:dem":195,
    "gn:feature_class":"P",
    "gn:feature_code":"PPL",
    "gn:name":"Iyakan Kasa",
    "gn:population":0,
    "gn:timezone":"Africa/Lagos",
    "iso:country":"NG",
    "wof:name":"Iyakan Kasa",
    "wof:placetype":"locality"
},
  "geometry": {"coordinates":[4.67771,10.24012],"type":"Point"}
}