{
  "type": "Feature",
  "properties": {
    "gn:admin1_code":"27.0",
    "gn:admin2_code":"102.0",
    "gn:admin3_code":"10213",
    "gn:asciiname":"Mungum",
    "gn:country_code":"NG",
    "gn:dem":493,
    "gn:feature_class":"P",
    "gn:feature_code":"PPL",
    "gn:name":"Mungum",
    "gn:population":0,
    "gn:timezone":"Africa/Lagos",
    "iso:country":"NG",
    "wof:name":"Mungum",
    "wof:placetype":"locality"
},
  "geometry": {"coordinates":[13.14955,10.59548],"type":"Point"}
}