{
  "type": "Feature",
  "properties": {
    "gn:admin1_code":"50.0",
    "gn:asciiname":"Egenden",
    "gn:country_code":"NG",
    "gn:dem":10,
    "gn:feature_class":"P",
    "gn:feature_code":"PPL",
    "gn:name":"Egenden",
    "gn:population":0,
    "gn:timezone":"Africa/Lagos",
    "iso:country":"NG",
    "wof:name":"Egenden",
    "wof:placetype":"locality"
},
  "geometry": {"coordinates":[7.45015,4.52916],"type":"Point"}
}