{
  "type": "Feature",
  "properties": {
    "gn:admin1_code":"50.0",
    "gn:asciiname":"Zamara-Yambiri",
    "gn:country_code":"NG",
    "gn:dem":12,
    "gn:feature_class":"P",
    "gn:feature_code":"PPL",
    "gn:name":"Zamara-Yambiri",
    "gn:population":0,
    "gn:timezone":"Africa/Lagos",
    "iso:country":"NG",
    "wof:name":"Zamara-Yambiri",
    "wof:placetype":"locality"
},
  "geometry": {"coordinates":[6.41432,5.10984],"type":"Point"}
}