{
  "type": "Feature",
  "properties": {
    "gn:admin1_code":"57.0",
    "gn:admin2_code":"810.0",
    "gn:admin3_code":"81007",
    "gn:asciiname":"Ungwan Sarikin Taba",
    "gn:country_code":"NG",
    "gn:dem":494,
    "gn:feature_class":"P",
    "gn:feature_code":"PPL",
    "gn:name":"Ungwan Sarikin Taba",
    "gn:population":0,
    "gn:timezone":"Africa/Lagos",
    "iso:country":"NG",
    "wof:name":"Ungwan Sarikin Taba",
    "wof:placetype":"locality"
},
  "geometry": {"coordinates":[6.49273,11.26412],"type":"Point"}
}