{
  "type": "Feature",
  "properties": {
    "gn:admin1_code":"35.0",
    "gn:asciiname":"Mararraba",
    "gn:country_code":"NG",
    "gn:dem":283,
    "gn:feature_class":"P",
    "gn:feature_code":"PPL",
    "gn:name":"Mararraba",
    "gn:population":0,
    "gn:timezone":"Africa/Lagos",
    "iso:country":"NG",
    "name:eng_x_preferred":[
        "Mararraba"
    ],
    "wof:name":"Mararraba",
    "wof:placetype":"locality"
},
  "geometry": {"coordinates":[12.06145,9.02793],"type":"Point"}
}