{
  "type": "Feature",
  "properties": {
    "gn:admin1_code":"26.0",
    "gn:admin2_code":"7010.0",
    "gn:asciiname":"Ive",
    "gn:country_code":"NG",
    "gn:dem":107,
    "gn:feature_class":"P",
    "gn:feature_code":"PPL",
    "gn:name":"Ive",
    "gn:population":0,
    "gn:timezone":"Africa/Lagos",
    "iso:country":"NG",
    "name:ceb_x_preferred":[
        "Ive"
    ],
    "name:deu_x_preferred":[
        "Ive"
    ],
    "name:fra_x_preferred":[
        "Ive"
    ],
    "name:swe_x_preferred":[
        "Ive"
    ],
    "wof:name":"Ive",
    "wof:placetype":"locality"
},
  "geometry": {"coordinates":[8.69275,7.09494],"type":"Point"}
}