{
  "type": "Feature",
  "properties": {
    "gn:admin1_code":"27.0",
    "gn:asciiname":"Vilegwa",
    "gn:country_code":"NG",
    "gn:dem":485,
    "gn:feature_class":"P",
    "gn:feature_code":"PPL",
    "gn:name":"Vilegwa",
    "gn:population":0,
    "gn:timezone":"Africa/Lagos",
    "iso:country":"NG",
    "wof:name":"Vilegwa",
    "wof:placetype":"locality"
},
  "geometry": {"coordinates":[13.35433,10.64015],"type":"Point"}
}