{
  "type": "Feature",
  "properties": {
    "gn:admin1_code":"49.0",
    "gn:admin2_code":"32005.0",
    "gn:asciiname":"Russo",
    "gn:country_code":"NG",
    "gn:dem":1314,
    "gn:feature_class":"P",
    "gn:feature_code":"PPL",
    "gn:name":"Russo",
    "gn:population":0,
    "gn:timezone":"Africa/Lagos",
    "iso:country":"NG",
    "name:ces_x_preferred":[
        "Russo"
    ],
    "name:deu_x_preferred":[
        "Russo"
    ],
    "name:fra_x_preferred":[
        "Russo"
    ],
    "name:ita_x_preferred":[
        "Russo"
    ],
    "name:jpn_x_preferred":[
        "\u30eb\u30c3\u30bd"
    ],
    "name:ron_x_preferred":[
        "Russo"
    ],
    "name:rus_x_preferred":[
        "\u0420\u0443\u0441\u0441\u043e"
    ],
    "name:slv_x_preferred":[
        "Russo"
    ],
    "name:ukr_x_preferred":[
        "\u0420\u0443\u0441\u0441\u043e"
    ],
    "wof:name":"Russo",
    "wof:placetype":"locality"
},
  "geometry": {"coordinates":[8.95234,9.87418],"type":"Point"}
}