{
  "type": "Feature",
  "properties": {
    "gn:admin1_code":"23.0",
    "gn:admin2_code":"19015.0",
    "gn:admin3_code":"KD1509",
    "gn:asciiname":"Pambeguwa",
    "gn:country_code":"NG",
    "gn:dem":714,
    "gn:feature_class":"P",
    "gn:feature_code":"PPL",
    "gn:name":"Pambeguwa",
    "gn:population":0,
    "gn:timezone":"Africa/Lagos",
    "iso:country":"NG",
    "name:und_x_variant":[
        "Anbeguwa",
        "Panbeguwa",
        "Pambeguwa"
    ],
    "wof:name":"Pambeguwa",
    "wof:placetype":"locality"
},
  "geometry": {"coordinates":[8.27761,10.67975],"type":"Point"}
}