{
  "type": "Feature",
  "properties": {
    "gn:admin1_code":"51.0",
    "gn:admin2_code":"605.0",
    "gn:admin3_code":"60501",
    "gn:asciiname":"Birjingo",
    "gn:country_code":"NG",
    "gn:dem":292,
    "gn:feature_class":"P",
    "gn:feature_code":"PPL",
    "gn:name":"Birjingo",
    "gn:population":0,
    "gn:timezone":"Africa/Lagos",
    "iso:country":"NG",
    "name:und_x_variant":[
        "Birzunga",
        "Birjingo"
    ],
    "wof:name":"Birjingo",
    "wof:placetype":"locality"
},
  "geometry": {"coordinates":[5.80134,13.47253],"type":"Point"}
}