{
  "type": "Feature",
  "properties": {
    "gn:admin1_code":"35.0",
    "gn:asciiname":"Tongare",
    "gn:country_code":"NG",
    "gn:dem":174,
    "gn:feature_class":"P",
    "gn:feature_code":"PPL",
    "gn:name":"Tongare",
    "gn:population":0,
    "gn:timezone":"Africa/Lagos",
    "iso:country":"NG",
    "name:eng_x_preferred":[
        "Tongare"
    ],
    "wof:name":"Tongare",
    "wof:placetype":"locality"
},
  "geometry": {"coordinates":[12.25027,9.30932],"type":"Point"}
}