{
  "type": "Feature",
  "properties": {
    "gn:admin1_code":"30.0",
    "gn:admin2_code":"24016.0",
    "gn:asciiname":"Sankwafuji",
    "gn:country_code":"NG",
    "gn:dem":103,
    "gn:feature_class":"P",
    "gn:feature_code":"PPL",
    "gn:name":"Sankwafuji",
    "gn:population":0,
    "gn:timezone":"Africa/Lagos",
    "iso:country":"NG",
    "wof:name":"Sankwafuji",
    "wof:placetype":"locality"
},
  "geometry": {"coordinates":[5.91667,8.61667],"type":"Point"}
}