{
  "type": "Feature",
  "properties": {
    "gn:admin1_code":"23.0",
    "gn:admin2_code":"19022.0",
    "gn:admin3_code":"KD2206",
    "gn:asciiname":"Ungwan Gaya",
    "gn:country_code":"NG",
    "gn:dem":858,
    "gn:feature_class":"P",
    "gn:feature_code":"PPL",
    "gn:name":"Ungwan Gaya",
    "gn:population":0,
    "gn:timezone":"Africa/Lagos",
    "iso:country":"NG",
    "name:und_x_variant":[
        "Unguwar Gaya"
    ],
    "wof:name":"Ungwan Gaya",
    "wof:placetype":"locality"
},
  "geometry": {"coordinates":[8.37459,9.77692],"type":"Point"}
}