{
  "type": "Feature",
  "properties": {
    "gn:admin1_code":"26.0",
    "gn:admin2_code":"7005",
    "gn:asciiname":"Agendu",
    "gn:country_code":"NG",
    "gn:dem":202,
    "gn:feature_class":"P",
    "gn:feature_code":"PPL",
    "gn:name":"Agendu",
    "gn:population":0,
    "gn:timezone":"Africa/Lagos",
    "iso:country":"NG",
    "wof:name":"Agendu",
    "wof:placetype":"neighbourhood"
},
  "geometry": {"coordinates":[8.99096,7.29856],"type":"Point"}
}