{
  "type": "Feature",
  "properties": {
    "gn:admin1_code":"22.0",
    "gn:admin2_code":"9012.0",
    "gn:asciiname":"Bogene",
    "gn:country_code":"NG",
    "gn:dem":303,
    "gn:feature_class":"P",
    "gn:feature_code":"PPL",
    "gn:name":"Bogene",
    "gn:population":0,
    "gn:timezone":"Africa/Lagos",
    "iso:country":"NG",
    "wof:name":"Bogene",
    "wof:placetype":"locality"
},
  "geometry": {"coordinates":[9.291,6.61311],"type":"Point"}
}