{
  "type": "Feature",
  "properties": {
    "gn:admin1_code":"44.0",
    "gn:admin2_code":"717.0",
    "gn:admin3_code":"71709",
    "gn:asciiname":"Garshelek",
    "gn:country_code":"NG",
    "gn:dem":345,
    "gn:feature_class":"P",
    "gn:feature_code":"PPL",
    "gn:name":"Garshelek",
    "gn:population":0,
    "gn:timezone":"Africa/Lagos",
    "iso:country":"NG",
    "wof:name":"Garshelek",
    "wof:placetype":"locality"
},
  "geometry": {"coordinates":[11.01241,13.12036],"type":"Point"}
}