{
  "type": "Feature",
  "properties": {
    "gn:admin1_code":"35.0",
    "gn:admin2_code":"2014.0",
    "gn:asciiname":"Kotoku",
    "gn:country_code":"NG",
    "gn:dem":529,
    "gn:feature_class":"P",
    "gn:feature_code":"PPL",
    "gn:name":"Kotoku",
    "gn:population":0,
    "gn:timezone":"Africa/Lagos",
    "iso:country":"NG",
    "wof:name":"Kotoku",
    "wof:placetype":"locality"
},
  "geometry": {"coordinates":[13.28512,10.37838],"type":"Point"}
}