{
  "type": "Feature",
  "properties": {
    "gn:admin1_code":"16.0",
    "gn:admin2_code":"28020.0",
    "gn:asciiname":"Sogbodun",
    "gn:country_code":"NG",
    "gn:dem":34,
    "gn:feature_class":"P",
    "gn:feature_code":"PPL",
    "gn:name":"Sogbodun",
    "gn:population":0,
    "gn:timezone":"Africa/Lagos",
    "iso:country":"NG",
    "wof:name":"Sogbodun",
    "wof:placetype":"locality"
},
  "geometry": {"coordinates":[3.61667,6.73333],"type":"Point"}
}