{
  "type": "Feature",
  "properties": {
    "gn:admin1_code":"46.0",
    "gn:admin2_code":"5008.0",
    "gn:admin3_code":"BA0813",
    "gn:asciiname":"Maharba",
    "gn:country_code":"NG",
    "gn:dem":436,
    "gn:feature_class":"P",
    "gn:feature_code":"PPL",
    "gn:name":"Maharba",
    "gn:population":0,
    "gn:timezone":"Africa/Lagos",
    "iso:country":"NG",
    "name:eng_x_preferred":[
        "Maharba"
    ],
    "wof:name":"Maharba",
    "wof:placetype":"locality"
},
  "geometry": {"coordinates":[10.4555,10.87188],"type":"Point"}
}