{
  "type": "Feature",
  "properties": {
    "gn:admin1_code":"51.0",
    "gn:admin2_code":"614.0",
    "gn:admin3_code":"61401",
    "gn:asciiname":"Ginga",
    "gn:country_code":"NG",
    "gn:dem":313,
    "gn:feature_class":"P",
    "gn:feature_code":"PPL",
    "gn:name":"Ginga",
    "gn:population":0,
    "gn:timezone":"Africa/Lagos",
    "iso:country":"NG",
    "name:ceb_x_preferred":[
        "Ginga"
    ],
    "name:deu_x_preferred":[
        "Ginga"
    ],
    "name:glg_x_preferred":[
        "Ginga"
    ],
    "name:por_x_preferred":[
        "Ginga"
    ],
    "name:spa_x_preferred":[
        "Ginga"
    ],
    "name:swe_x_preferred":[
        "Ginga"
    ],
    "wof:name":"Ginga",
    "wof:placetype":"locality"
},
  "geometry": {"coordinates":[5.14709,12.68197],"type":"Point"}
}