{
  "type": "Feature",
  "properties": {
    "gn:admin1_code":"46.0",
    "gn:admin2_code":"5017.0",
    "gn:admin3_code":"BA1709",
    "gn:asciiname":"Gawani",
    "gn:country_code":"NG",
    "gn:dem":595,
    "gn:feature_class":"P",
    "gn:feature_code":"PPL",
    "gn:name":"Gawani",
    "gn:population":0,
    "gn:timezone":"Africa/Lagos",
    "iso:country":"NG",
    "name:und_x_variant":[
        "Gwani",
        "Gawani"
    ],
    "wof:name":"Gawani",
    "wof:placetype":"locality"
},
  "geometry": {"coordinates":[9.56551,10.09817],"type":"Point"}
}