{
  "type": "Feature",
  "properties": {
    "gn:admin1_code":"28.0",
    "gn:admin2_code":"17021.0",
    "gn:asciiname":"Afozuru",
    "gn:country_code":"NG",
    "gn:dem":156,
    "gn:feature_class":"P",
    "gn:feature_code":"PPL",
    "gn:name":"Afozuru",
    "gn:population":0,
    "gn:timezone":"Africa/Lagos",
    "iso:country":"NG",
    "wof:name":"Afozuru",
    "wof:placetype":"locality"
},
  "geometry": {"coordinates":[6.98749,5.81709],"type":"Point"}
}