{
  "type": "Feature",
  "properties": {
    "gn:admin1_code":"32.0",
    "gn:admin2_code":"31014.0",
    "gn:asciiname":"Omin Adio",
    "gn:cc2":"NG",
    "gn:country_code":"NG",
    "gn:dem":166,
    "gn:feature_class":"P",
    "gn:feature_code":"PPL",
    "gn:name":"Omin Adio",
    "gn:population":0,
    "gn:timezone":"Africa/Lagos",
    "iso:country":"NG",
    "name:und_x_variant":[
        "Adio Station",
        "Omin Adio"
    ],
    "wof:name":"Omin Adio",
    "wof:placetype":"neighbourhood"
},
  "geometry": {"coordinates":[3.75361,7.39389],"type":"Point"}
}