{
  "type": "Feature",
  "properties": {
    "gn:admin1_code":"50.0",
    "gn:admin2_code":"33014.0",
    "gn:asciiname":"Bianu",
    "gn:country_code":"NG",
    "gn:dem":24,
    "gn:feature_class":"P",
    "gn:feature_code":"PPL",
    "gn:name":"Bianu",
    "gn:population":0,
    "gn:timezone":"Africa/Lagos",
    "iso:country":"NG",
    "wof:name":"Bianu",
    "wof:placetype":"locality"
},
  "geometry": {"coordinates":[7.46415,4.68866],"type":"Point"}
}