{
  "type": "Feature",
  "properties": {
    "gn:admin1_code":"45.0",
    "gn:admin2_code":"1016.0",
    "gn:asciiname":"Ihie-Ndume",
    "gn:country_code":"NG",
    "gn:dem":146,
    "gn:feature_class":"P",
    "gn:feature_code":"PPL",
    "gn:name":"Ihie-Ndume",
    "gn:population":0,
    "gn:timezone":"Africa/Lagos",
    "iso:country":"NG",
    "wof:name":"Ihie-Ndume",
    "wof:placetype":"locality"
},
  "geometry": {"coordinates":[7.51454,5.5152],"type":"Point"}
}