{
  "type": "Feature",
  "properties": {
    "gn:admin1_code":"31.0",
    "gn:admin2_code":"27020.0",
    "gn:asciiname":"Kako",
    "gn:country_code":"NG",
    "gn:dem":163,
    "gn:feature_class":"P",
    "gn:feature_code":"PPL",
    "gn:name":"Kako",
    "gn:population":0,
    "gn:timezone":"Africa/Lagos",
    "iso:country":"NG",
    "name:ceb_x_preferred":[
        "Kako"
    ],
    "name:deu_x_preferred":[
        "Kako"
    ],
    "name:epo_x_preferred":[
        "Kako"
    ],
    "name:est_x_preferred":[
        "Kako"
    ],
    "name:fra_x_preferred":[
        "Kako"
    ],
    "name:ita_x_preferred":[
        "Kako"
    ],
    "name:spa_x_preferred":[
        "Kako"
    ],
    "name:swe_x_preferred":[
        "Kako"
    ],
    "wof:name":"Kako",
    "wof:placetype":"locality"
},
  "geometry": {"coordinates":[6.23672,9.938],"type":"Point"}
}