{
  "type": "Feature",
  "properties": {
    "gn:admin1_code":"31.0",
    "gn:admin2_code":"27015.0",
    "gn:asciiname":"Iferri",
    "gn:country_code":"NG",
    "gn:dem":408,
    "gn:feature_class":"P",
    "gn:feature_code":"PPL",
    "gn:name":"Iferri",
    "gn:population":0,
    "gn:timezone":"Africa/Lagos",
    "iso:country":"NG",
    "wof:name":"Iferri",
    "wof:placetype":"locality"
},
  "geometry": {"coordinates":[5.70204,10.5993],"type":"Point"}
}