{
  "type": "Feature",
  "properties": {
    "gn:admin1_code":"23.0",
    "gn:admin2_code":"19003.0",
    "gn:admin3_code":"KD0311",
    "gn:asciiname":"Ungwan Galadima",
    "gn:country_code":"NG",
    "gn:dem":660,
    "gn:feature_class":"P",
    "gn:feature_code":"PPL",
    "gn:name":"Ungwan Galadima",
    "gn:population":0,
    "gn:timezone":"Africa/Lagos",
    "iso:country":"NG",
    "name:und_x_variant":[
        "Angwan Galadima",
        "Ungwan Galadima"
    ],
    "wof:name":"Ungwan Galadima",
    "wof:placetype":"locality"
},
  "geometry": {"coordinates":[7.29737,11.2376],"type":"Point"}
}