{
  "type": "Feature",
  "properties": {
    "gn:admin1_code":"40.0",
    "gn:admin2_code":"515.0",
    "gn:admin3_code":"51508",
    "gn:asciiname":"Alunguci",
    "gn:country_code":"NG",
    "gn:dem":298,
    "gn:feature_class":"P",
    "gn:feature_code":"PPL",
    "gn:name":"Alunguci",
    "gn:population":0,
    "gn:timezone":"Africa/Lagos",
    "iso:country":"NG",
    "wof:name":"Alunguci",
    "wof:placetype":"locality"
},
  "geometry": {"coordinates":[4.87146,10.35185],"type":"Point"}
}