{
  "type": "Feature",
  "properties": {
    "gn:admin1_code":"31.0",
    "gn:admin2_code":"27025",
    "gn:asciiname":"Zanangphausa",
    "gn:country_code":"NG",
    "gn:dem":106,
    "gn:feature_class":"P",
    "gn:feature_code":"PPL",
    "gn:name":"Zanangphausa",
    "gn:population":0,
    "gn:timezone":"Africa/Lagos",
    "iso:country":"NG",
    "wof:name":"Zanangphausa",
    "wof:placetype":"locality"
},
  "geometry": {"coordinates":[6.04896,9.65394],"type":"Point"}
}