{
  "type": "Feature",
  "properties": {
    "gn:admin1_code":"29.0",
    "gn:admin2_code":"20041.0",
    "gn:admin3_code":"KN2203",
    "gn:asciiname":"Zango",
    "gn:country_code":"NG",
    "gn:dem":527,
    "gn:feature_class":"P",
    "gn:feature_code":"PPL",
    "gn:name":"Zango",
    "gn:population":0,
    "gn:timezone":"Africa/Lagos",
    "iso:country":"NG",
    "name:ceb_x_preferred":[
        "Zango"
    ],
    "name:deu_x_preferred":[
        "Zango"
    ],
    "name:ita_x_preferred":[
        "Zango"
    ],
    "name:swe_x_preferred":[
        "Zango"
    ],
    "name:und_x_variant":[
        "Zangon"
    ],
    "wof:name":"Zango",
    "wof:placetype":"locality"
},
  "geometry": {"coordinates":[8.01038,11.82528],"type":"Point"}
}