{
  "type": "Feature",
  "properties": {
    "gn:admin1_code":"21.0",
    "gn:admin2_code":"3026.0",
    "gn:asciiname":"Ikot Obio Enin",
    "gn:country_code":"NG",
    "gn:dem":24,
    "gn:feature_class":"P",
    "gn:feature_code":"PPL",
    "gn:name":"Ikot Obio Enin",
    "gn:population":0,
    "gn:timezone":"Africa/Lagos",
    "iso:country":"NG",
    "wof:name":"Ikot Obio Enin",
    "wof:placetype":"locality"
},
  "geometry": {"coordinates":[7.65124,4.7041],"type":"Point"}
}