{
  "type": "Feature",
  "properties": {
    "gn:admin1_code":"45.0",
    "gn:admin2_code":"1006.0",
    "gn:asciiname":"Umu Nkpe",
    "gn:country_code":"NG",
    "gn:dem":124,
    "gn:feature_class":"P",
    "gn:feature_code":"PPL",
    "gn:name":"Umu Nkpe",
    "gn:population":0,
    "gn:timezone":"Africa/Lagos",
    "iso:country":"NG",
    "wof:name":"Umu Nkpe",
    "wof:placetype":"locality"
},
  "geometry": {"coordinates":[7.47687,5.32839],"type":"Point"}
}