{
  "type": "Feature",
  "properties": {
    "gn:admin1_code":"50.0",
    "gn:asciiname":"Igbigimina-Senkiri",
    "gn:country_code":"NG",
    "gn:dem":0,
    "gn:feature_class":"P",
    "gn:feature_code":"PPL",
    "gn:name":"Igbigimina-Senkiri",
    "gn:population":0,
    "gn:timezone":"Africa/Lagos",
    "iso:country":"NG",
    "wof:name":"Igbigimina-Senkiri",
    "wof:placetype":"locality"
},
  "geometry": {"coordinates":[7.00812,4.66239],"type":"Point"}
}