{
  "type": "Feature",
  "properties": {
    "gn:admin1_code":"32.0",
    "gn:admin2_code":"31002.0",
    "gn:asciiname":"Iya Offa",
    "gn:country_code":"NG",
    "gn:dem":319,
    "gn:feature_class":"P",
    "gn:feature_code":"PPL",
    "gn:name":"Iya Offa",
    "gn:population":0,
    "gn:timezone":"Africa/Lagos",
    "iso:country":"NG",
    "wof:name":"Iya Offa",
    "wof:placetype":"locality"
},
  "geometry": {"coordinates":[3.96028,7.63722],"type":"Point"}
}