{
  "type": "Feature",
  "properties": {
    "gn:admin1_code":"46.0",
    "gn:admin2_code":"5006.0",
    "gn:admin3_code":"BA0609",
    "gn:asciiname":"Bundila",
    "gn:country_code":"NG",
    "gn:dem":604,
    "gn:feature_class":"P",
    "gn:feature_code":"PPL",
    "gn:name":"Bundila",
    "gn:population":0,
    "gn:timezone":"Africa/Lagos",
    "iso:country":"NG",
    "name:eng_x_preferred":[
        "Bundila"
    ],
    "wof:name":"Bundila",
    "wof:placetype":"locality"
},
  "geometry": {"coordinates":[9.49126,9.98136],"type":"Point"}
}