{
  "type": "Feature",
  "properties": {
    "gn:admin1_code":"35.0",
    "gn:asciiname":"Sarab",
    "gn:country_code":"NG",
    "gn:dem":243,
    "gn:feature_class":"P",
    "gn:feature_code":"PPL",
    "gn:name":"Sarab",
    "gn:population":0,
    "gn:timezone":"Africa/Lagos",
    "iso:country":"NG",
    "name:ceb_x_preferred":[
        "Sarab"
    ],
    "name:eng_x_preferred":[
        "Sarab"
    ],
    "name:fas_x_preferred":[
        "\u0633\u0631\u0627\u0628"
    ],
    "name:msa_x_preferred":[
        "Serab"
    ],
    "name:swe_x_preferred":[
        "Sarab"
    ],
    "wof:name":"Sarab",
    "wof:placetype":"locality"
},
  "geometry": {"coordinates":[12.49475,9.10027],"type":"Point"}
}