{
  "type": "Feature",
  "properties": {
    "gn:admin1_code":"31.0",
    "gn:admin2_code":"27005.0",
    "gn:asciiname":"Zokwogi",
    "gn:country_code":"NG",
    "gn:dem":203,
    "gn:feature_class":"P",
    "gn:feature_code":"PPL",
    "gn:name":"Zokwogi",
    "gn:population":0,
    "gn:timezone":"Africa/Lagos",
    "iso:country":"NG",
    "wof:name":"Zokwogi",
    "wof:placetype":"locality"
},
  "geometry": {"coordinates":[6.21906,9.5934],"type":"Point"}
}