{
  "type": "Feature",
  "properties": {
    "gn:admin1_code":"42.0",
    "gn:admin2_code":"30016.0",
    "gn:asciiname":"Eko Ajala",
    "gn:country_code":"NG",
    "gn:dem":376,
    "gn:feature_class":"P",
    "gn:feature_code":"PPL",
    "gn:name":"Eko Ajala",
    "gn:population":0,
    "gn:timezone":"Africa/Lagos",
    "iso:country":"NG",
    "wof:name":"Eko Ajala",
    "wof:placetype":"locality"
},
  "geometry": {"coordinates":[4.61667,7.95],"type":"Point"}
}