{
  "type": "Feature",
  "properties": {
    "gn:admin1_code":"46.0",
    "gn:admin2_code":"5001.0",
    "gn:admin3_code":"BA0114",
    "gn:asciiname":"Gumau Pelu",
    "gn:country_code":"NG",
    "gn:dem":550,
    "gn:feature_class":"P",
    "gn:feature_code":"PPL",
    "gn:name":"Gumau Pelu",
    "gn:population":0,
    "gn:timezone":"Africa/Lagos",
    "iso:country":"NG",
    "name:eng_x_preferred":[
        "Gumau Pelu"
    ],
    "name:eng_x_variant":[
        "Gumau"
    ],
    "wof:name":"Gumau Pelu",
    "wof:placetype":"locality"
},
  "geometry": {"coordinates":[10.18309,10.14233],"type":"Point"}
}