{
  "type": "Feature",
  "properties": {
    "gn:admin1_code":"43.0",
    "gn:asciiname":"Wuro Shoful",
    "gn:country_code":"NG",
    "gn:dem":127,
    "gn:feature_class":"P",
    "gn:feature_code":"PPL",
    "gn:name":"Wuro Shoful",
    "gn:population":0,
    "gn:timezone":"Africa/Lagos",
    "iso:country":"NG",
    "name:eng_x_preferred":[
        "Wuro Shoful"
    ],
    "wof:name":"Wuro Shoful",
    "wof:placetype":"locality"
},
  "geometry": {"coordinates":[10.87066,9.06591],"type":"Point"}
}