{
  "type": "Feature",
  "properties": {
    "gn:admin1_code":"23.0",
    "gn:admin2_code":"19018.0",
    "gn:admin3_code":"KD1808",
    "gn:asciiname":"Ungwan Kanakargo",
    "gn:country_code":"NG",
    "gn:dem":648,
    "gn:feature_class":"P",
    "gn:feature_code":"PPL",
    "gn:name":"Ungwan Kanakargo",
    "gn:population":0,
    "gn:timezone":"Africa/Lagos",
    "iso:country":"NG",
    "name:und_x_variant":[
        "Kanakargo",
        "Ungwan Kanakargo"
    ],
    "wof:name":"Ungwan Kanakargo",
    "wof:placetype":"locality"
},
  "geometry": {"coordinates":[7.98197,11.26294],"type":"Point"}
}