{
  "type": "Feature",
  "properties": {
    "gn:admin1_code":"23.0",
    "gn:admin2_code":"19003.0",
    "gn:admin3_code":"KD0305",
    "gn:asciiname":"Ungwan Cesa",
    "gn:country_code":"NG",
    "gn:dem":657,
    "gn:feature_class":"P",
    "gn:feature_code":"PPL",
    "gn:name":"Ungwan Cesa",
    "gn:population":0,
    "gn:timezone":"Africa/Lagos",
    "iso:country":"NG",
    "name:und_x_variant":[
        "Kaza",
        "Ungwan Cesa"
    ],
    "wof:name":"Ungwan Cesa",
    "wof:placetype":"locality"
},
  "geometry": {"coordinates":[7.29764,11.18147],"type":"Point"}
}