{
  "type": "Feature",
  "properties": {
    "gn:admin1_code":"24.0",
    "gn:admin2_code":"426.0",
    "gn:admin3_code":"42602",
    "gn:asciiname":"Tsauni",
    "gn:country_code":"NG",
    "gn:dem":523,
    "gn:feature_class":"P",
    "gn:feature_code":"PPL",
    "gn:name":"Tsauni",
    "gn:population":0,
    "gn:timezone":"Africa/Lagos",
    "iso:country":"NG",
    "wof:name":"Tsauni",
    "wof:placetype":"locality"
},
  "geometry": {"coordinates":[8.04822,12.89338],"type":"Point"}
}