{
  "type": "Feature",
  "properties": {
    "gn:admin1_code":"22.0",
    "gn:admin2_code":"9007.0",
    "gn:asciiname":"Nkanya",
    "gn:country_code":"NG",
    "gn:dem":131,
    "gn:feature_class":"P",
    "gn:feature_code":"PPL",
    "gn:name":"Nkanya",
    "gn:population":0,
    "gn:timezone":"Africa/Lagos",
    "iso:country":"NG",
    "wof:name":"Nkanya",
    "wof:placetype":"locality"
},
  "geometry": {"coordinates":[8.9153,6.42762],"type":"Point"}
}