{
  "type": "Feature",
  "properties": {
    "gn:admin1_code":"52.0",
    "gn:admin2_code":"6002.0",
    "gn:asciiname":"Tamogbene",
    "gn:country_code":"NG",
    "gn:dem":5,
    "gn:feature_class":"P",
    "gn:feature_code":"PPL",
    "gn:name":"Tamogbene",
    "gn:population":0,
    "gn:timezone":"Africa/Lagos",
    "iso:country":"NG",
    "name:eng_x_preferred":[
        "Tamogbene"
    ],
    "name:eng_x_variant":[
        "Tomogbene",
        "Ayama"
    ],
    "wof:name":"Tamogbene",
    "wof:placetype":"locality"
},
  "geometry": {"coordinates":[5.74814,4.97549],"type":"Point"}
}