{
  "type": "Feature",
  "properties": {
    "gn:admin1_code":"57.0",
    "gn:admin2_code":"809.0",
    "gn:admin3_code":"80907",
    "gn:asciiname":"Mlela",
    "gn:country_code":"NG",
    "gn:dem":405,
    "gn:feature_class":"P",
    "gn:feature_code":"PPL",
    "gn:name":"Mlela",
    "gn:population":0,
    "gn:timezone":"Africa/Lagos",
    "iso:country":"NG",
    "wof:name":"Mlela",
    "wof:placetype":"locality"
},
  "geometry": {"coordinates":[6.36541,12.7381],"type":"Point"}
}