{
  "type": "Feature",
  "properties": {
    "gn:admin1_code":"35.0",
    "gn:admin2_code":"2018.0",
    "gn:asciiname":"Kesure",
    "gn:country_code":"NG",
    "gn:dem":508,
    "gn:feature_class":"P",
    "gn:feature_code":"PPL",
    "gn:name":"Kesure",
    "gn:population":0,
    "gn:timezone":"Africa/Lagos",
    "iso:country":"NG",
    "wof:name":"Kesure",
    "wof:placetype":"locality"
},
  "geometry": {"coordinates":[12.58333,9.98333],"type":"Point"}
}