{
  "type": "Feature",
  "properties": {
    "gn:admin1_code":"46.0",
    "gn:admin2_code":"5015.0",
    "gn:admin3_code":"BA1509",
    "gn:asciiname":"Birnin Mailafia",
    "gn:country_code":"NG",
    "gn:dem":772,
    "gn:feature_class":"P",
    "gn:feature_code":"PPL",
    "gn:name":"Birnin Mailafia",
    "gn:population":0,
    "gn:timezone":"Africa/Lagos",
    "iso:country":"NG",
    "name:und_x_variant":[
        "Mailafia",
        "Birnin Mailafia"
    ],
    "wof:name":"Birnin Mailafia",
    "wof:placetype":"locality"
},
  "geometry": {"coordinates":[9.05597,10.79227],"type":"Point"}
}