{
  "type": "Feature",
  "properties": {
    "gn:admin1_code":"26.0",
    "gn:admin2_code":"7021",
    "gn:asciiname":"Uke",
    "gn:country_code":"NG",
    "gn:dem":141,
    "gn:feature_class":"P",
    "gn:feature_code":"PPL",
    "gn:name":"Uke",
    "gn:population":0,
    "gn:timezone":"Africa/Lagos",
    "iso:country":"NG",
    "name:ces_x_preferred":[
        "Uke"
    ],
    "name:deu_x_preferred":[
        "Uke"
    ],
    "name:fin_x_preferred":[
        "Uke"
    ],
    "name:fra_x_preferred":[
        "Uke"
    ],
    "name:nor_x_preferred":[
        "Uke"
    ],
    "name:spa_x_preferred":[
        "Uke"
    ],
    "wof:name":"Uke",
    "wof:placetype":"locality"
},
  "geometry": {"coordinates":[9.5013,7.7031],"type":"Point"}
}