{
  "type": "Feature",
  "properties": {
    "gn:admin1_code":"24.0",
    "gn:admin2_code":"419.0",
    "gn:admin3_code":"41905",
    "gn:asciiname":"Mai-Gaterie",
    "gn:country_code":"NG",
    "gn:dem":579,
    "gn:feature_class":"P",
    "gn:feature_code":"PPL",
    "gn:name":"Mai-Gaterie",
    "gn:population":0,
    "gn:timezone":"Africa/Lagos",
    "iso:country":"NG",
    "wof:name":"Mai-Gaterie",
    "wof:placetype":"locality"
},
  "geometry": {"coordinates":[7.39685,11.94437],"type":"Point"}
}