{
  "type": "Feature",
  "properties": {
    "gn:admin1_code":"31.0",
    "gn:admin2_code":"27005.0",
    "gn:asciiname":"Kangwo",
    "gn:country_code":"NG",
    "gn:dem":320,
    "gn:feature_class":"P",
    "gn:feature_code":"PPL",
    "gn:name":"Kangwo",
    "gn:population":0,
    "gn:timezone":"Africa/Lagos",
    "iso:country":"NG",
    "wof:name":"Kangwo",
    "wof:placetype":"locality"
},
  "geometry": {"coordinates":[6.46483,9.74908],"type":"Point"}
}