{
  "type": "Feature",
  "properties": {
    "gn:admin1_code":"48.0",
    "gn:admin2_code":"29012.0",
    "gn:asciiname":"Ago-Isobo",
    "gn:country_code":"NG",
    "gn:dem":56,
    "gn:feature_class":"P",
    "gn:feature_code":"PPL",
    "gn:name":"Ago-Isobo",
    "gn:population":0,
    "gn:timezone":"Africa/Lagos",
    "iso:country":"NG",
    "wof:name":"Ago-Isobo",
    "wof:placetype":"locality"
},
  "geometry": {"coordinates":[5.03893,6.45235],"type":"Point"}
}