{
  "type": "Feature",
  "properties": {
    "gn:admin1_code":"35.0",
    "gn:admin2_code":"2015.0",
    "gn:asciiname":"Jalingo",
    "gn:country_code":"NG",
    "gn:dem":711,
    "gn:feature_class":"P",
    "gn:feature_code":"PPL",
    "gn:name":"Jalingo",
    "gn:population":0,
    "gn:timezone":"Africa/Lagos",
    "iso:country":"NG",
    "name:azb_x_preferred":[
        "\u062c\u0627\u0644\u06cc\u0646\u0642\u0648"
    ],
    "name:cat_x_preferred":[
        "Jalingo"
    ],
    "name:ceb_x_preferred":[
        "Jalingo"
    ],
    "name:dan_x_preferred":[
        "Jalingo"
    ],
    "name:deu_x_preferred":[
        "Jalingo"
    ],
    "name:epo_x_preferred":[
        "Jalingo"
    ],
    "name:fas_x_preferred":[
        "\u062c\u0627\u0644\u06cc\u0646\u06af\u0648"
    ],
    "name:fra_x_preferred":[
        "Jalingo"
    ],
    "name:hau_x_preferred":[
        "Jalingo"
    ],
    "name:hrv_x_preferred":[
        "Jalingo"
    ],
    "name:ibo_x_preferred":[
        "Jalingo"
    ],
    "name:ita_x_preferred":[
        "Jalingo"
    ],
    "name:jpn_x_preferred":[
        "\u30b8\u30e3\u30ea\u30f3\u30b4"
    ],
    "name:kor_x_preferred":[
        "\uc798\ub9c1\uace0"
    ],
    "name:nld_x_preferred":[
        "Jalingo"
    ],
    "name:nor_x_preferred":[
        "Jalingo"
    ],
    "name:pol_x_preferred":[
        "Jalingo"
    ],
    "name:por_x_preferred":[
        "Jalingo"
    ],
    "name:ron_x_preferred":[
        "Jalingo"
    ],
    "name:rus_x_preferred":[
        "\u0414\u0436\u0430\u043b\u0438\u043d\u0433\u043e"
    ],
    "name:spa_x_preferred":[
        "Jalingo"
    ],
    "name:swe_x_preferred":[
        "Jalingo"
    ],
    "name:ukr_x_preferred":[
        "\u0414\u0436\u0430\u043b\u0456\u043d\u0433\u043e"
    ],
    "name:urd_x_preferred":[
        "\u062c\u0644\u06cc\u0646\u06af\u0648"
    ],
    "name:yor_x_preferred":[
        "Jalingo"
    ],
    "wof:name":"Jalingo",
    "wof:placetype":"locality"
},
  "geometry": {"coordinates":[13.3169,10.18125],"type":"Point"}
}