{
  "type": "Feature",
  "properties": {
    "gn:admin1_code":"35.0",
    "gn:admin2_code":"2015.0",
    "gn:asciiname":"Jalingo",
    "gn:country_code":"NG",
    "gn:dem":711,
    "gn:feature_class":"P",
    "gn:feature_code":"PPL",
    "gn:name":"Jalingo",
    "gn:population":0,
    "gn:timezone":"Africa/Lagos",
    "iso:country":"NG",
    "wof:name":"Jalingo",
    "wof:placetype":"locality"
},
  "geometry": {"coordinates":[13.3169,10.18125],"type":"Point"}
}