{
  "type": "Feature",
  "properties": {
    "gn:admin1_code":"23.0",
    "gn:admin2_code":"19014.0",
    "gn:admin3_code":"KD1405",
    "gn:asciiname":"Karkun Biba",
    "gn:country_code":"NG",
    "gn:dem":749,
    "gn:feature_class":"P",
    "gn:feature_code":"PPL",
    "gn:name":"Karkun Biba",
    "gn:population":0,
    "gn:timezone":"Africa/Lagos",
    "iso:country":"NG",
    "name:und_x_variant":[
        "Karkun Bisa",
        "Karkun Biba"
    ],
    "wof:name":"Karkun Biba",
    "wof:placetype":"locality"
},
  "geometry": {"coordinates":[8.38479,10.11331],"type":"Point"}
}