{
  "type": "Feature",
  "properties": {
    "gn:admin1_code":"40.0",
    "gn:admin2_code":"502.0",
    "gn:admin3_code":"50203",
    "gn:asciiname":"Madawachi",
    "gn:country_code":"NG",
    "gn:dem":252,
    "gn:feature_class":"P",
    "gn:feature_code":"PPL",
    "gn:name":"Madawachi",
    "gn:population":0,
    "gn:timezone":"Africa/Lagos",
    "iso:country":"NG",
    "wof:name":"Madawachi",
    "wof:placetype":"locality"
},
  "geometry": {"coordinates":[4.03728,12.81002],"type":"Point"}
}