{
  "type": "Feature",
  "properties": {
    "gn:admin1_code":"55.0",
    "gn:asciiname":"Garin Baba Dala",
    "gn:country_code":"NG",
    "gn:dem":325,
    "gn:feature_class":"P",
    "gn:feature_code":"PPL",
    "gn:name":"Garin Baba Dala",
    "gn:population":0,
    "gn:timezone":"Africa/Lagos",
    "iso:country":"NG",
    "wof:name":"Garin Baba Dala",
    "wof:placetype":"locality"
},
  "geometry": {"coordinates":[11.24618,11.19101],"type":"Point"}
}