{
  "type": "Feature",
  "properties": {
    "gn:admin1_code":"52.0",
    "gn:admin2_code":"6007.0",
    "gn:asciiname":"Fenenegbene",
    "gn:country_code":"NG",
    "gn:dem":4,
    "gn:feature_class":"P",
    "gn:feature_code":"PPL",
    "gn:name":"Fenenegbene",
    "gn:population":0,
    "gn:timezone":"Africa/Lagos",
    "iso:country":"NG",
    "name:eng_x_preferred":[
        "Fenenegbene"
    ],
    "wof:name":"Fenenegbene",
    "wof:placetype":"locality"
},
  "geometry": {"coordinates":[5.74351,4.64874],"type":"Point"}
}