{
  "type": "Feature",
  "properties": {
    "gn:admin1_code":"51.0",
    "gn:admin2_code":"604.0",
    "gn:admin3_code":"60410",
    "gn:asciiname":"Kadasaka Baba",
    "gn:country_code":"NG",
    "gn:dem":343,
    "gn:feature_class":"P",
    "gn:feature_code":"PPL",
    "gn:name":"Kadasaka Baba",
    "gn:population":0,
    "gn:timezone":"Africa/Lagos",
    "iso:country":"NG",
    "wof:name":"Kadasaka Baba",
    "wof:placetype":"locality"
},
  "geometry": {"coordinates":[5.5705,13.67353],"type":"Point"}
}