{
  "type": "Feature",
  "properties": {
    "gn:admin1_code":"27.0",
    "gn:admin2_code":"122.0",
    "gn:admin3_code":"12204",
    "gn:asciiname":"Kairi",
    "gn:country_code":"NG",
    "gn:dem":309,
    "gn:feature_class":"P",
    "gn:feature_code":"PPL",
    "gn:name":"Kairi",
    "gn:population":0,
    "gn:timezone":"Africa/Lagos",
    "iso:country":"NG",
    "wof:name":"Kairi",
    "wof:placetype":"locality"
},
  "geometry": {"coordinates":[12.64245,12.98039],"type":"Point"}
}