{
  "type": "Feature",
  "properties": {
    "gn:admin1_code":"56.0",
    "gn:admin2_code":"26012.0",
    "gn:asciiname":"Kango",
    "gn:country_code":"NG",
    "gn:dem":173,
    "gn:feature_class":"P",
    "gn:feature_code":"PPL",
    "gn:name":"Kango",
    "gn:population":0,
    "gn:timezone":"Africa/Lagos",
    "iso:country":"NG",
    "name:bul_x_preferred":[
        "\u041a\u0430\u043d\u0433\u043e"
    ],
    "name:ceb_x_preferred":[
        "Kango"
    ],
    "name:fra_x_preferred":[
        "Kango"
    ],
    "name:hun_x_preferred":[
        "Kango"
    ],
    "name:ita_x_preferred":[
        "Kango"
    ],
    "name:nld_x_preferred":[
        "Kango"
    ],
    "name:pol_x_preferred":[
        "Kango"
    ],
    "name:rus_x_preferred":[
        "\u041a\u0430\u043d\u0433\u043e"
    ],
    "name:spa_x_preferred":[
        "Kango"
    ],
    "name:swe_x_preferred":[
        "Kango"
    ],
    "wof:name":"Kango",
    "wof:placetype":"locality"
},
  "geometry": {"coordinates":[7.01722,8.07611],"type":"Point"}
}