{
  "type": "Feature",
  "properties": {
    "gn:admin1_code":"48.0",
    "gn:admin2_code":"29008.0",
    "gn:asciiname":"Tejugbola",
    "gn:country_code":"NG",
    "gn:dem":228,
    "gn:feature_class":"P",
    "gn:feature_code":"PPL",
    "gn:name":"Tejugbola",
    "gn:population":0,
    "gn:timezone":"Africa/Lagos",
    "iso:country":"NG",
    "wof:name":"Tejugbola",
    "wof:placetype":"locality"
},
  "geometry": {"coordinates":[5.1376,7.0123],"type":"Point"}
}