{
  "type": "Feature",
  "properties": {
    "gn:admin1_code":"24.0",
    "gn:admin2_code":"401.0",
    "gn:admin3_code":"40107",
    "gn:asciiname":"Kuka",
    "gn:country_code":"NG",
    "gn:dem":670,
    "gn:feature_class":"P",
    "gn:feature_code":"PPL",
    "gn:name":"Kuka",
    "gn:population":0,
    "gn:timezone":"Africa/Lagos",
    "iso:country":"NG",
    "wof:name":"Kuka",
    "wof:placetype":"locality"
},
  "geometry": {"coordinates":[7.46898,11.62537],"type":"Point"}
}