{
  "type": "Feature",
  "properties": {
    "gn:admin1_code":"24.0",
    "gn:admin2_code":"431.0",
    "gn:admin3_code":"43107",
    "gn:asciiname":"Ungwan Daudu",
    "gn:country_code":"NG",
    "gn:dem":656,
    "gn:feature_class":"P",
    "gn:feature_code":"PPL",
    "gn:name":"Ungwan Daudu",
    "gn:population":0,
    "gn:timezone":"Africa/Lagos",
    "iso:country":"NG",
    "wof:name":"Ungwan Daudu",
    "wof:placetype":"locality"
},
  "geometry": {"coordinates":[7.00073,11.26573],"type":"Point"}
}