{
  "type": "Feature",
  "properties": {
    "gn:admin1_code":"56.0",
    "gn:admin2_code":"26004",
    "gn:asciiname":"Gidan Epara",
    "gn:country_code":"NG",
    "gn:dem":417,
    "gn:feature_class":"P",
    "gn:feature_code":"PPL",
    "gn:name":"Gidan Epara",
    "gn:population":0,
    "gn:timezone":"Africa/Lagos",
    "iso:country":"NG",
    "wof:name":"Gidan Epara",
    "wof:placetype":"locality"
},
  "geometry": {"coordinates":[7.85136,9.12759],"type":"Point"}
}