{
  "type": "Feature",
  "properties": {
    "gn:admin1_code":"46.0",
    "gn:admin2_code":"5007.0",
    "gn:admin3_code":"BA0707",
    "gn:asciiname":"Udubo",
    "gn:country_code":"NG",
    "gn:dem":381,
    "gn:feature_class":"P",
    "gn:feature_code":"PPL",
    "gn:name":"Udubo",
    "gn:population":0,
    "gn:timezone":"Africa/Lagos",
    "iso:country":"NG",
    "wof:name":"Udubo",
    "wof:placetype":"locality"
},
  "geometry": {"coordinates":[10.638,11.9389],"type":"Point"}
}