{
  "type": "Feature",
  "properties": {
    "gn:admin1_code":"26.0",
    "gn:admin2_code":"7021",
    "gn:asciiname":"Tse Gyuba",
    "gn:country_code":"NG",
    "gn:dem":158,
    "gn:feature_class":"P",
    "gn:feature_code":"PPL",
    "gn:name":"Tse Gyuba",
    "gn:population":0,
    "gn:timezone":"Africa/Lagos",
    "iso:country":"NG",
    "wof:name":"Tse Gyuba",
    "wof:placetype":"locality"
},
  "geometry": {"coordinates":[9.53025,7.75099],"type":"Point"}
}