{
  "type": "Feature",
  "properties": {
    "gn:admin1_code":"51.0",
    "gn:admin2_code":"611.0",
    "gn:admin3_code":"61111",
    "gn:asciiname":"Gidan Gari",
    "gn:country_code":"NG",
    "gn:dem":256,
    "gn:feature_class":"P",
    "gn:feature_code":"PPL",
    "gn:name":"Gidan Gari",
    "gn:population":0,
    "gn:timezone":"Africa/Lagos",
    "iso:country":"NG",
    "wof:name":"Gidan Gari",
    "wof:placetype":"locality"
},
  "geometry": {"coordinates":[5.41895,13.07656],"type":"Point"}
}