{
  "type": "Feature",
  "properties": {
    "gn:admin1_code":"16.0",
    "gn:admin2_code":"28009.0",
    "gn:asciiname":"Araromi",
    "gn:country_code":"NG",
    "gn:dem":26,
    "gn:feature_class":"P",
    "gn:feature_code":"PPL",
    "gn:name":"Araromi",
    "gn:population":0,
    "gn:timezone":"Africa/Lagos",
    "iso:country":"NG",
    "wof:name":"Araromi",
    "wof:placetype":"locality"
},
  "geometry": {"coordinates":[3.77993,6.93079],"type":"Point"}
}