{
  "type": "Feature",
  "properties": {
    "gn:admin1_code":"31.0",
    "gn:admin2_code":"27020.0",
    "gn:asciiname":"Tungan",
    "gn:country_code":"NG",
    "gn:dem":275,
    "gn:feature_class":"P",
    "gn:feature_code":"PPL",
    "gn:name":"Tungan",
    "gn:population":0,
    "gn:timezone":"Africa/Lagos",
    "iso:country":"NG",
    "name:und_x_variant":[
        "Tungan Dada"
    ],
    "wof:name":"Tungan",
    "wof:placetype":"locality"
},
  "geometry": {"coordinates":[6.38967,9.99719],"type":"Point"}
}