{
  "type": "Feature",
  "properties": {
    "gn:admin1_code":"57.0",
    "gn:admin2_code":"805.0",
    "gn:admin3_code":"80506",
    "gn:asciiname":"Nahutie",
    "gn:country_code":"NG",
    "gn:dem":435,
    "gn:feature_class":"P",
    "gn:feature_code":"PPL",
    "gn:name":"Nahutie",
    "gn:population":0,
    "gn:timezone":"Africa/Lagos",
    "iso:country":"NG",
    "wof:name":"Nahutie",
    "wof:placetype":"locality"
},
  "geometry": {"coordinates":[6.47748,12.41645],"type":"Point"}
}