{
  "type": "Feature",
  "properties": {
    "gn:admin1_code":"40.0",
    "gn:admin2_code":"520.0",
    "gn:admin3_code":"52007",
    "gn:asciiname":"Mai Agumi",
    "gn:country_code":"NG",
    "gn:dem":199,
    "gn:feature_class":"P",
    "gn:feature_code":"PPL",
    "gn:name":"Mai Agumi",
    "gn:population":0,
    "gn:timezone":"Africa/Lagos",
    "iso:country":"NG",
    "wof:name":"Mai Agumi",
    "wof:placetype":"locality"
},
  "geometry": {"coordinates":[4.85,10.88333],"type":"Point"}
}