{
  "type": "Feature",
  "properties": {
    "gn:admin1_code":"24.0",
    "gn:admin2_code":"427.0",
    "gn:admin3_code":"42706",
    "gn:asciiname":"Boji",
    "gn:country_code":"NG",
    "gn:dem":506,
    "gn:feature_class":"P",
    "gn:feature_code":"PPL",
    "gn:name":"Boji",
    "gn:population":0,
    "gn:timezone":"Africa/Lagos",
    "iso:country":"NG",
    "name:fra_x_preferred":[
        "Boji"
    ],
    "name:orm_x_preferred":[
        "Boojjii"
    ],
    "wof:name":"Boji",
    "wof:placetype":"locality"
},
  "geometry": {"coordinates":[8.0065,12.96421],"type":"Point"}
}