{
  "type": "Feature",
  "properties": {
    "gn:admin1_code":"36.0",
    "gn:admin2_code":"10016.0",
    "gn:asciiname":"Koloware",
    "gn:country_code":"NG",
    "gn:dem":14,
    "gn:feature_class":"P",
    "gn:feature_code":"PPL",
    "gn:name":"Koloware",
    "gn:population":0,
    "gn:timezone":"Africa/Lagos",
    "iso:country":"NG",
    "wof:name":"Koloware",
    "wof:placetype":"locality"
},
  "geometry": {"coordinates":[6.15761,5.20809],"type":"Point"}
}