{
  "type": "Feature",
  "properties": {
    "gn:admin1_code":"32.0",
    "gn:admin2_code":"31001.0",
    "gn:asciiname":"Oniyangi",
    "gn:cc2":"NG",
    "gn:country_code":"NG",
    "gn:dem":241,
    "gn:feature_class":"P",
    "gn:feature_code":"PPL",
    "gn:name":"Oniyangi",
    "gn:population":0,
    "gn:timezone":"Africa/Lagos",
    "iso:country":"NG",
    "name:und_x_variant":[
        "Oniyege",
        "Oniyangi"
    ],
    "wof:name":"Oniyangi",
    "wof:placetype":"locality"
},
  "geometry": {"coordinates":[3.82222,7.71111],"type":"Point"}
}