{
  "type": "Feature",
  "properties": {
    "gn:admin1_code":"31.0",
    "gn:admin2_code":"27008",
    "gn:asciiname":"Sonfadako",
    "gn:country_code":"NG",
    "gn:dem":135,
    "gn:feature_class":"P",
    "gn:feature_code":"PPL",
    "gn:name":"Sonfadako",
    "gn:population":0,
    "gn:timezone":"Africa/Lagos",
    "iso:country":"NG",
    "wof:name":"Sonfadako",
    "wof:placetype":"locality"
},
  "geometry": {"coordinates":[6.03413,9.45139],"type":"Point"}
}