{
  "type": "Feature",
  "properties": {
    "gn:admin1_code":"21.0",
    "gn:admin2_code":"3028.0",
    "gn:asciiname":"Ikot Akpan",
    "gn:country_code":"NG",
    "gn:dem":37,
    "gn:feature_class":"P",
    "gn:feature_code":"PPL",
    "gn:name":"Ikot Akpan",
    "gn:population":0,
    "gn:timezone":"Africa/Lagos",
    "iso:country":"NG",
    "wof:name":"Ikot Akpan",
    "wof:placetype":"locality"
},
  "geometry": {"coordinates":[7.52656,4.87445],"type":"Point"}
}