{
  "type": "Feature",
  "properties": {
    "gn:admin1_code":"43.0",
    "gn:admin2_code":"35006",
    "gn:asciiname":"Abdullahi",
    "gn:country_code":"NG",
    "gn:dem":96,
    "gn:feature_class":"P",
    "gn:feature_code":"PPL",
    "gn:name":"Abdullahi",
    "gn:population":0,
    "gn:timezone":"Africa/Lagos",
    "iso:country":"NG",
    "wof:name":"Abdullahi",
    "wof:placetype":"locality"
},
  "geometry": {"coordinates":[9.87445,8.27005],"type":"Point"}
}