{
  "type": "Feature",
  "properties": {
    "gn:admin1_code":"21.0",
    "gn:admin2_code":"3031.0",
    "gn:asciiname":"Idoro",
    "gn:country_code":"NG",
    "gn:dem":77,
    "gn:feature_class":"P",
    "gn:feature_code":"PPL",
    "gn:name":"Idoro",
    "gn:population":0,
    "gn:timezone":"Africa/Lagos",
    "iso:country":"NG",
    "wof:name":"Idoro",
    "wof:placetype":"locality"
},
  "geometry": {"coordinates":[7.87329,5.02852],"type":"Point"}
}