{
  "type": "Feature",
  "properties": {
    "gn:admin1_code":"37.0",
    "gn:admin2_code":"12005",
    "gn:asciiname":"Ibhiodan",
    "gn:country_code":"NG",
    "gn:dem":112,
    "gn:feature_class":"P",
    "gn:feature_code":"PPL",
    "gn:name":"Ibhiodan",
    "gn:population":0,
    "gn:timezone":"Africa/Lagos",
    "iso:country":"NG",
    "wof:name":"Ibhiodan",
    "wof:placetype":"locality"
},
  "geometry": {"coordinates":[6.43393,6.53987],"type":"Point"}
}