{
  "type": "Feature",
  "properties": {
    "gn:admin1_code":"24.0",
    "gn:admin2_code":"401.0",
    "gn:admin3_code":"40109",
    "gn:asciiname":"Soro",
    "gn:country_code":"NG",
    "gn:dem":623,
    "gn:feature_class":"P",
    "gn:feature_code":"PPL",
    "gn:name":"Soro",
    "gn:population":0,
    "gn:timezone":"Africa/Lagos",
    "iso:country":"NG",
    "name:ceb_x_preferred":[
        "Soro"
    ],
    "name:deu_x_preferred":[
        "Soro"
    ],
    "name:fra_x_preferred":[
        "Soro"
    ],
    "name:glg_x_preferred":[
        "Soro"
    ],
    "name:hrv_x_preferred":[
        "Sor\u00f8"
    ],
    "name:ind_x_preferred":[
        "Soro"
    ],
    "name:ita_x_preferred":[
        "Soro"
    ],
    "name:nld_x_preferred":[
        "Soro"
    ],
    "name:por_x_preferred":[
        "Soro"
    ],
    "name:rus_x_preferred":[
        "\u0421\u043e\u0440\u043e"
    ],
    "name:swe_x_preferred":[
        "Soro"
    ],
    "name:ukr_x_preferred":[
        "\u0421\u043e\u0440\u043e"
    ],
    "wof:name":"Soro",
    "wof:placetype":"locality"
},
  "geometry": {"coordinates":[7.40691,11.708],"type":"Point"}
}