{
  "type": "Feature",
  "properties": {
    "gn:admin1_code":"41.0",
    "gn:admin2_code":"23002.0",
    "gn:asciiname":"Onado",
    "gn:country_code":"NG",
    "gn:dem":93,
    "gn:feature_class":"P",
    "gn:feature_code":"PPL",
    "gn:name":"Onado",
    "gn:population":0,
    "gn:timezone":"Africa/Lagos",
    "iso:country":"NG",
    "wof:name":"Onado",
    "wof:placetype":"locality"
},
  "geometry": {"coordinates":[6.66649,7.41755],"type":"Point"}
}