{
  "type": "Feature",
  "properties": {
    "gn:admin1_code":"23.0",
    "gn:asciiname":"Ragada",
    "gn:country_code":"NG",
    "gn:dem":749,
    "gn:feature_class":"P",
    "gn:feature_code":"PPL",
    "gn:name":"Ragada",
    "gn:population":0,
    "gn:timezone":"Africa/Lagos",
    "iso:country":"NG",
    "name:hin_x_preferred":[
        "\u0930\u0917\u093e\u0921\u093e"
    ],
    "name:tel_x_preferred":[
        "\u0c30\u0c17\u0c21"
    ],
    "wof:name":"Ragada",
    "wof:placetype":"locality"
},
  "geometry": {"coordinates":[8.65033,10.67227],"type":"Point"}
}