{
  "type": "Feature",
  "properties": {
    "gn:admin1_code":"21.0",
    "gn:admin2_code":"3003.0",
    "gn:asciiname":"Ebana",
    "gn:country_code":"NG",
    "gn:dem":12,
    "gn:feature_class":"P",
    "gn:feature_code":"PPL",
    "gn:name":"Ebana",
    "gn:population":0,
    "gn:timezone":"Africa/Lagos",
    "iso:country":"NG",
    "name:deu_x_preferred":[
        "Ebana"
    ],
    "name:fra_x_preferred":[
        "Ebana"
    ],
    "name:heb_x_preferred":[
        "\u05d0\u05d1\u05e0\u05d4"
    ],
    "name:ita_x_preferred":[
        "Ebana"
    ],
    "name:vie_x_preferred":[
        "Ebana"
    ],
    "wof:name":"Ebana",
    "wof:placetype":"locality"
},
  "geometry": {"coordinates":[7.9594,4.60466],"type":"Point"}
}