{
  "type": "Feature",
  "properties": {
    "gn:admin1_code":"31.0",
    "gn:admin2_code":"27019",
    "gn:asciiname":"Soita",
    "gn:country_code":"NG",
    "gn:dem":309,
    "gn:feature_class":"P",
    "gn:feature_code":"PPL",
    "gn:name":"Soita",
    "gn:population":0,
    "gn:timezone":"Africa/Lagos",
    "iso:country":"NG",
    "name:ceb_x_preferred":[
        "Soita"
    ],
    "name:ron_x_preferred":[
        "Soita"
    ],
    "name:swe_x_preferred":[
        "Soita"
    ],
    "name:war_x_preferred":[
        "Soita"
    ],
    "wof:name":"Soita",
    "wof:placetype":"locality"
},
  "geometry": {"coordinates":[6.70785,9.47724],"type":"Point"}
}