{
  "type": "Feature",
  "properties": {
    "gn:admin1_code":"27.0",
    "gn:asciiname":"Muzuku",
    "gn:country_code":"NG",
    "gn:dem":441,
    "gn:feature_class":"P",
    "gn:feature_code":"PPL",
    "gn:name":"Muzuku",
    "gn:population":0,
    "gn:timezone":"Africa/Lagos",
    "iso:country":"NG",
    "wof:name":"Muzuku",
    "wof:placetype":"locality"
},
  "geometry": {"coordinates":[13.29647,10.67479],"type":"Point"}
}