{
  "type": "Feature",
  "properties": {
    "gn:admin1_code":"44.0",
    "gn:admin2_code":"709.0",
    "gn:admin3_code":"70902",
    "gn:asciiname":"Fadurga",
    "gn:country_code":"NG",
    "gn:dem":351,
    "gn:feature_class":"P",
    "gn:feature_code":"PPL",
    "gn:name":"Fadurga",
    "gn:population":0,
    "gn:timezone":"Africa/Lagos",
    "iso:country":"NG",
    "name:und_x_variant":[
        "Fadurya"
    ],
    "wof:name":"Fadurga",
    "wof:placetype":"locality"
},
  "geometry": {"coordinates":[10.80357,12.52006],"type":"Point"}
}