{
  "type": "Feature",
  "properties": {
    "gn:admin1_code":"44.0",
    "gn:admin2_code":"717",
    "gn:admin3_code":"71709",
    "gn:asciiname":"Kringini",
    "gn:country_code":"NG",
    "gn:dem":342,
    "gn:feature_class":"P",
    "gn:feature_code":"PPL",
    "gn:name":"Kringini",
    "gn:population":0,
    "gn:timezone":"Africa/Lagos",
    "iso:country":"NG",
    "wof:name":"Kringini",
    "wof:placetype":"locality"
},
  "geometry": {"coordinates":[11.09934,13.14762],"type":"Point"}
}