{
  "type": "Feature",
  "properties": {
    "gn:admin1_code":"36.0",
    "gn:admin2_code":"10013.0",
    "gn:asciiname":"Okwugbogbo",
    "gn:country_code":"NG",
    "gn:dem":9,
    "gn:feature_class":"P",
    "gn:feature_code":"PPL",
    "gn:name":"Okwugbogbo",
    "gn:population":0,
    "gn:timezone":"Africa/Lagos",
    "iso:country":"NG",
    "name:und_x_variant":[
        "Okugbogbo",
        "Okwugbogbo"
    ],
    "wof:name":"Okwugbogbo",
    "wof:placetype":"locality"
},
  "geometry": {"coordinates":[5.73741,5.66977],"type":"Point"}
}