{
  "type": "Feature",
  "properties": {
    "gn:admin1_code":"28.0",
    "gn:admin2_code":"17012.0",
    "gn:asciiname":"Awban",
    "gn:country_code":"NG",
    "gn:dem":104,
    "gn:feature_class":"P",
    "gn:feature_code":"PPL",
    "gn:name":"Awban",
    "gn:population":0,
    "gn:timezone":"Africa/Lagos",
    "iso:country":"NG",
    "wof:name":"Awban",
    "wof:placetype":"locality"
},
  "geometry": {"coordinates":[7.21667,5.38333],"type":"Point"}
}