{
  "type": "Feature",
  "properties": {
    "gn:admin1_code":"43.0",
    "gn:admin2_code":"35001",
    "gn:asciiname":"Kachala Kona",
    "gn:country_code":"NG",
    "gn:dem":204,
    "gn:feature_class":"P",
    "gn:feature_code":"PPL",
    "gn:name":"Kachala Kona",
    "gn:population":0,
    "gn:timezone":"Africa/Lagos",
    "iso:country":"NG",
    "wof:name":"Kachala Kona",
    "wof:placetype":"locality"
},
  "geometry": {"coordinates":[11.2091,8.72866],"type":"Point"}
}