{
  "type": "Feature",
  "properties": {
    "gn:admin1_code":"29.0",
    "gn:admin2_code":"20003.0",
    "gn:admin3_code":"KN1503",
    "gn:asciiname":"Ringimawa",
    "gn:country_code":"NG",
    "gn:dem":492,
    "gn:feature_class":"P",
    "gn:feature_code":"PPL",
    "gn:name":"Ringimawa",
    "gn:population":0,
    "gn:timezone":"Africa/Lagos",
    "iso:country":"NG",
    "wof:name":"Ringimawa",
    "wof:placetype":"locality"
},
  "geometry": {"coordinates":[8.42154,11.66219],"type":"Point"}
}