{
  "type": "Feature",
  "properties": {
    "gn:admin1_code":"27.0",
    "gn:admin2_code":"102",
    "gn:admin3_code":"10206",
    "gn:asciiname":"Dubukwa",
    "gn:country_code":"NG",
    "gn:dem":467,
    "gn:feature_class":"P",
    "gn:feature_code":"PPL",
    "gn:name":"Dubukwa",
    "gn:population":0,
    "gn:timezone":"Africa/Lagos",
    "iso:country":"NG",
    "name:eng_x_preferred":[
        "Dubukwa"
    ],
    "wof:name":"Dubukwa",
    "wof:placetype":"locality"
},
  "geometry": {"coordinates":[13.10437,10.70312],"type":"Point"}
}