{
  "type": "Feature",
  "properties": {
    "gn:admin1_code":"23.0",
    "gn:admin2_code":"19004.0",
    "gn:admin3_code":"KD0408",
    "gn:asciiname":"Mashigi",
    "gn:country_code":"NG",
    "gn:dem":592,
    "gn:feature_class":"P",
    "gn:feature_code":"PPL",
    "gn:name":"Mashigi",
    "gn:population":0,
    "gn:timezone":"Africa/Lagos",
    "iso:country":"NG",
    "wof:name":"Mashigi",
    "wof:placetype":"locality"
},
  "geometry": {"coordinates":[7.47918,10.57612],"type":"Point"}
}