{
  "type": "Feature",
  "properties": {
    "gn:admin1_code":"45.0",
    "gn:admin2_code":"1010.0",
    "gn:asciiname":"Udi-Uduma",
    "gn:country_code":"NG",
    "gn:dem":151,
    "gn:feature_class":"P",
    "gn:feature_code":"PPL",
    "gn:name":"Udi-Uduma",
    "gn:population":0,
    "gn:timezone":"Africa/Lagos",
    "iso:country":"NG",
    "name:und_x_variant":[
        "Ndi-Uduma",
        "Udi-Uduma"
    ],
    "wof:name":"Udi-Uduma",
    "wof:placetype":"locality"
},
  "geometry": {"coordinates":[7.84352,5.53757],"type":"Point"}
}