{
  "type": "Feature",
  "properties": {
    "gn:admin1_code":"11.0",
    "gn:admin2_code":"15006.0",
    "gn:asciiname":"Tungan Daudu",
    "gn:country_code":"NG",
    "gn:dem":396,
    "gn:feature_class":"P",
    "gn:feature_code":"PPL",
    "gn:name":"Tungan Daudu",
    "gn:population":0,
    "gn:timezone":"Africa/Lagos",
    "iso:country":"NG",
    "wof:name":"Tungan Daudu",
    "wof:placetype":"neighbourhood"
},
  "geometry": {"coordinates":[7.33892,9.07667],"type":"Point"}
}