{
  "type": "Feature",
  "properties": {
    "gn:admin1_code":"53.0",
    "gn:admin2_code":"11007",
    "gn:asciiname":"Ukwanyim",
    "gn:country_code":"NG",
    "gn:dem":39,
    "gn:feature_class":"P",
    "gn:feature_code":"PPL",
    "gn:name":"Ukwanyim",
    "gn:population":0,
    "gn:timezone":"Africa/Lagos",
    "iso:country":"NG",
    "wof:name":"Ukwanyim",
    "wof:placetype":"locality"
},
  "geometry": {"coordinates":[8.22615,6.04446],"type":"Point"}
}