{
  "type": "Feature",
  "properties": {
    "gn:admin1_code":"23.0",
    "gn:admin2_code":"19021.0",
    "gn:admin3_code":"KD2109",
    "gn:asciiname":"Ricifa",
    "gn:country_code":"NG",
    "gn:dem":658,
    "gn:feature_class":"P",
    "gn:feature_code":"PPL",
    "gn:name":"Ricifa",
    "gn:population":0,
    "gn:timezone":"Africa/Lagos",
    "iso:country":"NG",
    "name:und_x_variant":[
        "Richifa",
        "Ricifa"
    ],
    "wof:name":"Ricifa",
    "wof:placetype":"locality"
},
  "geometry": {"coordinates":[7.95309,11.16639],"type":"Point"}
}