{
  "type": "Feature",
  "properties": {
    "gn:admin1_code":"56.0",
    "gn:admin2_code":"26008.0",
    "gn:asciiname":"Shimmar",
    "gn:country_code":"NG",
    "gn:dem":190,
    "gn:feature_class":"P",
    "gn:feature_code":"PPL",
    "gn:name":"Shimmar",
    "gn:population":0,
    "gn:timezone":"Africa/Lagos",
    "iso:country":"NG",
    "wof:name":"Shimmar",
    "wof:placetype":"locality"
},
  "geometry": {"coordinates":[8.88333,8.85],"type":"Point"}
}