{
  "type": "Feature",
  "properties": {
    "gn:admin1_code":"37.0",
    "gn:admin2_code":"12009.0",
    "gn:asciiname":"Afana",
    "gn:country_code":"NG",
    "gn:dem":173,
    "gn:feature_class":"P",
    "gn:feature_code":"PPL",
    "gn:name":"Afana",
    "gn:population":0,
    "gn:timezone":"Africa/Lagos",
    "iso:country":"NG",
    "wof:name":"Afana",
    "wof:placetype":"locality"
},
  "geometry": {"coordinates":[6.3932,7.1395],"type":"Point"}
}