{
  "type": "Feature",
  "properties": {
    "gn:admin1_code":"35.0",
    "gn:admin2_code":"2005.0",
    "gn:asciiname":"Kantindla",
    "gn:country_code":"NG",
    "gn:dem":482,
    "gn:feature_class":"P",
    "gn:feature_code":"PPL",
    "gn:name":"Kantindla",
    "gn:population":0,
    "gn:timezone":"Africa/Lagos",
    "iso:country":"NG",
    "wof:name":"Kantindla",
    "wof:placetype":"locality"
},
  "geometry": {"coordinates":[12.48608,10.16868],"type":"Point"}
}