{
  "type": "Feature",
  "properties": {
    "gn:admin1_code":"26.0",
    "gn:admin2_code":"7007.0",
    "gn:asciiname":"Ger",
    "gn:country_code":"NG",
    "gn:dem":154,
    "gn:feature_class":"P",
    "gn:feature_code":"PPL",
    "gn:name":"Ger",
    "gn:population":0,
    "gn:timezone":"Africa/Lagos",
    "iso:country":"NG",
    "name:bre_x_preferred":[
        "Ger"
    ],
    "name:cat_x_preferred":[
        "Ger"
    ],
    "name:ceb_x_preferred":[
        "Ger"
    ],
    "name:ces_x_preferred":[
        "Ger"
    ],
    "name:deu_x_preferred":[
        "Ger"
    ],
    "name:fra_x_preferred":[
        "Ger"
    ],
    "name:glg_x_preferred":[
        "Ger"
    ],
    "name:heb_x_preferred":[
        "\u05d2\u05e8"
    ],
    "name:hun_x_preferred":[
        "Ger"
    ],
    "name:hye_x_preferred":[
        "\u053a\u0565\u0580"
    ],
    "name:msa_x_preferred":[
        "Ger"
    ],
    "name:nds_x_preferred":[
        "Ger"
    ],
    "name:nld_x_preferred":[
        "Ger"
    ],
    "name:oci_x_preferred":[
        "Ger"
    ],
    "name:pms_x_preferred":[
        "Ger"
    ],
    "name:pol_x_preferred":[
        "Ger"
    ],
    "name:por_x_preferred":[
        "Ger"
    ],
    "name:ron_x_preferred":[
        "Ger"
    ],
    "name:rus_x_preferred":[
        "\u0416\u0435\u0440"
    ],
    "name:slk_x_preferred":[
        "Ger"
    ],
    "name:spa_x_preferred":[
        "Ger"
    ],
    "name:swe_x_preferred":[
        "Ger"
    ],
    "name:ukr_x_preferred":[
        "\u0416\u0435\u0440"
    ],
    "name:vie_x_preferred":[
        "Ger"
    ],
    "name:vol_x_preferred":[
        "Ger"
    ],
    "name:war_x_preferred":[
        "Ger"
    ],
    "wof:name":"Ger",
    "wof:placetype":"locality"
},
  "geometry": {"coordinates":[8.14217,7.37076],"type":"Point"}
}