{
  "type": "Feature",
  "properties": {
    "gn:admin1_code":"43.0",
    "gn:admin2_code":"35011.0",
    "gn:asciiname":"Ngikar",
    "gn:country_code":"NG",
    "gn:dem":1368,
    "gn:feature_class":"P",
    "gn:feature_code":"PPL",
    "gn:name":"Ngikar",
    "gn:population":0,
    "gn:timezone":"Africa/Lagos",
    "iso:country":"NG",
    "wof:name":"Ngikar",
    "wof:placetype":"locality"
},
  "geometry": {"coordinates":[11.11667,6.76667],"type":"Point"}
}