{
  "type": "Feature",
  "properties": {
    "gn:admin1_code":"55.0",
    "gn:asciiname":"Tubule",
    "gn:country_code":"NG",
    "gn:dem":350,
    "gn:feature_class":"P",
    "gn:feature_code":"PPL",
    "gn:name":"Tubule",
    "gn:population":0,
    "gn:timezone":"Africa/Lagos",
    "iso:country":"NG",
    "name:eng_x_preferred":[
        "Tubule"
    ],
    "wof:name":"Tubule",
    "wof:placetype":"locality"
},
  "geometry": {"coordinates":[10.67155,10.45712],"type":"Point"}
}