{
  "type": "Feature",
  "properties": {
    "gn:admin1_code":"55.0",
    "gn:admin2_code":"16009.0",
    "gn:asciiname":"Gadum Gabas",
    "gn:country_code":"NG",
    "gn:dem":379,
    "gn:feature_class":"P",
    "gn:feature_code":"PPL",
    "gn:name":"Gadum Gabas",
    "gn:population":0,
    "gn:timezone":"Africa/Lagos",
    "iso:country":"NG",
    "name:und_x_variant":[
        "Mallam Gidado"
    ],
    "wof:name":"Gadum Gabas",
    "wof:placetype":"locality"
},
  "geometry": {"coordinates":[11.16792,11.00665],"type":"Point"}
}