{
  "type": "Feature",
  "properties": {
    "gn:admin1_code":"27.0",
    "gn:admin2_code":"126.0",
    "gn:admin3_code":"12612",
    "gn:asciiname":"Zilum",
    "gn:country_code":"NG",
    "gn:dem":298,
    "gn:feature_class":"P",
    "gn:feature_code":"PPL",
    "gn:name":"Zilum",
    "gn:population":0,
    "gn:timezone":"Africa/Lagos",
    "iso:country":"NG",
    "name:und_x_variant":[
        "Zilumo",
        "Zilum"
    ],
    "wof:name":"Zilum",
    "wof:placetype":"locality"
},
  "geometry": {"coordinates":[13.35366,12.43095],"type":"Point"}
}