{
  "type": "Feature",
  "properties": {
    "gn:admin1_code":"27.0",
    "gn:admin2_code":"107.0",
    "gn:admin3_code":"10709",
    "gn:asciiname":"Talagala",
    "gn:country_code":"NG",
    "gn:dem":443,
    "gn:feature_class":"P",
    "gn:feature_code":"PPL",
    "gn:name":"Talagala",
    "gn:population":0,
    "gn:timezone":"Africa/Lagos",
    "iso:country":"NG",
    "wof:name":"Talagala",
    "wof:placetype":"locality"
},
  "geometry": {"coordinates":[12.31561,11.22824],"type":"Point"}
}