{
  "type": "Feature",
  "properties": {
    "gn:admin1_code":"27.0",
    "gn:admin2_code":"127.0",
    "gn:admin3_code":"12701",
    "gn:asciiname":"Genya",
    "gn:country_code":"NG",
    "gn:dem":221,
    "gn:feature_class":"P",
    "gn:feature_code":"PPL",
    "gn:name":"Genya",
    "gn:population":0,
    "gn:timezone":"Africa/Lagos",
    "iso:country":"NG",
    "name:bul_x_preferred":[
        "\u0413\u0435\u043d\u044f"
    ],
    "name:fas_x_preferred":[
        "\u06af\u0646\u06cc\u0627"
    ],
    "name:kaz_x_preferred":[
        "\u0413\u0435\u043d\u044f"
    ],
    "name:pol_x_preferred":[
        "Genja"
    ],
    "name:ron_x_preferred":[
        "Ghenea"
    ],
    "name:rus_x_preferred":[
        "\u0413\u0435\u043d\u044f"
    ],
    "name:ukr_x_preferred":[
        "\u0413\u0435\u043d\u044f"
    ],
    "wof:name":"Genya",
    "wof:placetype":"locality"
},
  "geometry": {"coordinates":[11.95728,10.10536],"type":"Point"}
}