{
  "type": "Feature",
  "properties": {
    "gn:admin1_code":"45.0",
    "gn:admin2_code":"1009.0",
    "gn:asciiname":"Akanu Okpulo",
    "gn:country_code":"NG",
    "gn:dem":58,
    "gn:feature_class":"P",
    "gn:feature_code":"PPL",
    "gn:name":"Akanu Okpulo",
    "gn:population":0,
    "gn:timezone":"Africa/Lagos",
    "iso:country":"NG",
    "wof:name":"Akanu Okpulo",
    "wof:placetype":"locality"
},
  "geometry": {"coordinates":[7.51137,5.17273],"type":"Point"}
}