{
  "type": "Feature",
  "properties": {
    "gn:admin1_code":"21.0",
    "gn:admin2_code":"3030.0",
    "gn:asciiname":"Udun Uwe",
    "gn:country_code":"NG",
    "gn:dem":25,
    "gn:feature_class":"P",
    "gn:feature_code":"PPL",
    "gn:name":"Udun Uwe",
    "gn:population":0,
    "gn:timezone":"Africa/Lagos",
    "iso:country":"NG",
    "name:und_x_variant":[
        "Udung Uwe",
        "Udun Uwe"
    ],
    "wof:name":"Udun Uwe",
    "wof:placetype":"locality"
},
  "geometry": {"coordinates":[8.16794,4.69524],"type":"Point"}
}