{
  "type": "Feature",
  "properties": {
    "gn:admin1_code":"39.0",
    "gn:admin2_code":"18015.0",
    "gn:admin3_code":"JI2410",
    "gn:asciiname":"Yanzaki",
    "gn:country_code":"NG",
    "gn:dem":427,
    "gn:feature_class":"P",
    "gn:feature_code":"PPL",
    "gn:name":"Yanzaki",
    "gn:population":0,
    "gn:timezone":"Africa/Lagos",
    "iso:country":"NG",
    "wof:name":"Yanzaki",
    "wof:placetype":"locality"
},
  "geometry": {"coordinates":[8.45453,12.58726],"type":"Point"}
}