{
  "type": "Feature",
  "properties": {
    "gn:admin1_code":"54.0",
    "gn:admin2_code":"13015.0",
    "gn:asciiname":"Ikosu",
    "gn:country_code":"NG",
    "gn:dem":538,
    "gn:feature_class":"P",
    "gn:feature_code":"PPL",
    "gn:name":"Ikosu",
    "gn:population":0,
    "gn:timezone":"Africa/Lagos",
    "iso:country":"NG",
    "wof:name":"Ikosu",
    "wof:placetype":"locality"
},
  "geometry": {"coordinates":[5.1778,7.9938],"type":"Point"}
}