{
  "type": "Feature",
  "properties": {
    "gn:admin1_code":"23.0",
    "gn:admin2_code":"19011.0",
    "gn:admin3_code":"KD1110",
    "gn:asciiname":"Kasabari",
    "gn:country_code":"NG",
    "gn:dem":633,
    "gn:feature_class":"P",
    "gn:feature_code":"PPL",
    "gn:name":"Kasabari",
    "gn:population":0,
    "gn:timezone":"Africa/Lagos",
    "iso:country":"NG",
    "name:und_x_variant":[
        "Kasabare",
        "Kasabari"
    ],
    "wof:name":"Kasabari",
    "wof:placetype":"locality"
},
  "geometry": {"coordinates":[7.7717,9.45469],"type":"Point"}
}