{
  "type": "Feature",
  "properties": {
    "gn:admin1_code":"31.0",
    "gn:admin2_code":"27009",
    "gn:asciiname":"Gawu Babangida",
    "gn:country_code":"NG",
    "gn:dem":290,
    "gn:feature_class":"P",
    "gn:feature_code":"PPLA2",
    "gn:name":"Gawu Babangida",
    "gn:population":0,
    "gn:timezone":"Africa/Lagos",
    "iso:country":"NG",
    "name:und_x_variant":[
        "Gawu",
        "Babangida"
    ],
    "wof:name":"Gawu Babangida",
    "wof:placetype":"locality"
},
  "geometry": {"coordinates":[6.99335,9.27827],"type":"Point"}
}