{
  "type": "Feature",
  "properties": {
    "gn:admin1_code":"27.0",
    "gn:admin2_code":"110",
    "gn:admin3_code":"11010",
    "gn:asciiname":"Ka'arra",
    "gn:country_code":"NG",
    "gn:dem":292,
    "gn:feature_class":"P",
    "gn:feature_code":"PPL",
    "gn:name":"Ka\u2019arra",
    "gn:population":0,
    "gn:timezone":"Africa/Lagos",
    "iso:country":"NG",
    "wof:name":"Ka'arra",
    "wof:placetype":"locality"
},
  "geometry": {"coordinates":[13.2585,13.02729],"type":"Point"}
}