{
  "type": "Feature",
  "properties": {
    "gn:admin1_code":"57.0",
    "gn:admin2_code":"810.0",
    "gn:admin3_code":"81007",
    "gn:asciiname":"Shauda",
    "gn:country_code":"NG",
    "gn:dem":474,
    "gn:feature_class":"P",
    "gn:feature_code":"PPL",
    "gn:name":"Shauda",
    "gn:population":0,
    "gn:timezone":"Africa/Lagos",
    "iso:country":"NG",
    "wof:name":"Shauda",
    "wof:placetype":"locality"
},
  "geometry": {"coordinates":[6.30924,11.26921],"type":"Point"}
}