{
  "type": "Feature",
  "properties": {
    "gn:admin1_code":"29.0",
    "gn:admin2_code":"20026.0",
    "gn:admin3_code":"KN2005",
    "gn:asciiname":"Goza",
    "gn:country_code":"NG",
    "gn:dem":520,
    "gn:feature_class":"P",
    "gn:feature_code":"PPL",
    "gn:name":"Goza",
    "gn:population":0,
    "gn:timezone":"Africa/Lagos",
    "iso:country":"NG",
    "wof:name":"Goza",
    "wof:placetype":"locality"
},
  "geometry": {"coordinates":[8.12915,11.93913],"type":"Point"}
}