{
  "type": "Feature",
  "properties": {
    "gn:admin1_code":"23.0",
    "gn:admin2_code":"19005.0",
    "gn:admin3_code":"KD0504",
    "gn:asciiname":"Sansami",
    "gn:country_code":"NG",
    "gn:dem":656,
    "gn:feature_class":"P",
    "gn:feature_code":"PPL",
    "gn:name":"Sansami",
    "gn:population":0,
    "gn:timezone":"Africa/Lagos",
    "iso:country":"NG",
    "wof:name":"Sansami",
    "wof:placetype":"locality"
},
  "geometry": {"coordinates":[8.12914,11.16862],"type":"Point"}
}