{
  "type": "Feature",
  "properties": {
    "gn:admin1_code":"29.0",
    "gn:admin2_code":"20034.0",
    "gn:admin3_code":"KN2401",
    "gn:asciiname":"Ungwan Sha 1",
    "gn:country_code":"NG",
    "gn:dem":531,
    "gn:feature_class":"P",
    "gn:feature_code":"PPL",
    "gn:name":"Ungwan Sha 1",
    "gn:population":0,
    "gn:timezone":"Africa/Lagos",
    "iso:country":"NG",
    "wof:name":"Ungwan Sha 1",
    "wof:placetype":"locality"
},
  "geometry": {"coordinates":[7.98165,11.62373],"type":"Point"}
}