{
  "type": "Feature",
  "properties": {
    "gn:admin1_code":"23.0",
    "gn:admin2_code":"19002.0",
    "gn:admin3_code":"KD0202",
    "gn:asciiname":"Gusako",
    "gn:country_code":"NG",
    "gn:dem":481,
    "gn:feature_class":"P",
    "gn:feature_code":"PPL",
    "gn:name":"Gusako",
    "gn:population":0,
    "gn:timezone":"Africa/Lagos",
    "iso:country":"NG",
    "wof:name":"Gusako",
    "wof:placetype":"locality"
},
  "geometry": {"coordinates":[7.15986,10.21312],"type":"Point"}
}