{
  "type": "Feature",
  "properties": {
    "gn:admin1_code":"22.0",
    "gn:admin2_code":"9016.0",
    "gn:asciiname":"Ashuk",
    "gn:country_code":"NG",
    "gn:dem":83,
    "gn:feature_class":"P",
    "gn:feature_code":"PPL",
    "gn:name":"Ashuk",
    "gn:population":0,
    "gn:timezone":"Africa/Lagos",
    "iso:country":"NG",
    "wof:name":"Ashuk",
    "wof:placetype":"locality"
},
  "geometry": {"coordinates":[8.61064,6.36454],"type":"Point"}
}