{
  "type": "Feature",
  "properties": {
    "gn:admin1_code":"32.0",
    "gn:admin2_code":"31002.0",
    "gn:asciiname":"Age",
    "gn:country_code":"NG",
    "gn:dem":247,
    "gn:feature_class":"P",
    "gn:feature_code":"PPL",
    "gn:name":"Age",
    "gn:population":0,
    "gn:timezone":"Africa/Lagos",
    "iso:country":"NG",
    "name:ara_x_preferred":[
        "\u0627\u0644\u0639\u0645\u0631"
    ],
    "name:bel_x_preferred":[
        "\u0423\u0437\u0440\u043e\u0441\u0442"
    ],
    "name:bul_x_preferred":[
        "\u0412\u044a\u0437\u0440\u0430\u0441\u0442"
    ],
    "name:cat_x_preferred":[
        "Edat biol\u00f2gica"
    ],
    "name:deu_x_preferred":[
        "Lebensalter"
    ],
    "name:epo_x_preferred":[
        "A\u011do"
    ],
    "name:fry_x_preferred":[
        "Alderdom"
    ],
    "name:heb_x_preferred":[
        "\u05d2\u05d9\u05dc"
    ],
    "name:kab_x_preferred":[
        "Addar"
    ],
    "name:lat_x_preferred":[
        "Aevum"
    ],
    "name:lit_x_preferred":[
        "Am\u017eius"
    ],
    "name:nld_x_preferred":[
        "Leeftijd"
    ],
    "name:rus_x_preferred":[
        "\u0412\u043e\u0437\u0440\u0430\u0441\u0442"
    ],
    "name:spa_x_preferred":[
        "Edad biol\u00f3gica"
    ],
    "name:sqi_x_preferred":[
        "Mosha"
    ],
    "name:srp_x_preferred":[
        "\u0423\u0437\u0440\u0430\u0441\u0442"
    ],
    "name:tgl_x_preferred":[
        "Gulang"
    ],
    "name:ukr_x_preferred":[
        "\u0412\u0456\u043a"
    ],
    "wof:name":"Age",
    "wof:placetype":"neighbourhood"
},
  "geometry": {"coordinates":[3.86333,7.52556],"type":"Point"}
}