{
  "type": "Feature",
  "properties": {
    "gn:admin1_code":"44.0",
    "gn:admin2_code":"712",
    "gn:admin3_code":"71205",
    "gn:asciiname":"Sabon Garin Nangere",
    "gn:country_code":"NG",
    "gn:dem":394,
    "gn:feature_class":"P",
    "gn:feature_code":"PPLA2",
    "gn:name":"Sabon Garin Nangere",
    "gn:population":0,
    "gn:timezone":"Africa/Lagos",
    "iso:country":"NG",
    "name:und_x_variant":[
        "Sabon Gari-Nangere",
        "Sabon Gari",
        "Sabon Garin Nangere",
        "Sabon Gari Nanger"
    ],
    "wof:name":"Sabon Garin Nangere",
    "wof:placetype":"locality"
},
  "geometry": {"coordinates":[11.0733,11.84945],"type":"Point"}
}