{
  "type": "Feature",
  "properties": {
    "gn:admin1_code":"43.0",
    "gn:asciiname":"Ungwar Boyi",
    "gn:country_code":"NG",
    "gn:dem":149,
    "gn:feature_class":"P",
    "gn:feature_code":"PPL",
    "gn:name":"Ungwar Boyi",
    "gn:population":0,
    "gn:timezone":"Africa/Lagos",
    "iso:country":"NG",
    "name:eng_x_preferred":[
        "Ungwar Boyi"
    ],
    "wof:name":"Ungwar Boyi",
    "wof:placetype":"locality"
},
  "geometry": {"coordinates":[11.13263,9.30613],"type":"Point"}
}