{
  "type": "Feature",
  "properties": {
    "gn:admin1_code":"16.0",
    "gn:admin2_code":"28008.0",
    "gn:asciiname":"Oko-Makun",
    "gn:country_code":"NG",
    "gn:dem":19,
    "gn:feature_class":"P",
    "gn:feature_code":"PPL",
    "gn:name":"Oko-Makun",
    "gn:population":0,
    "gn:timezone":"Africa/Lagos",
    "iso:country":"NG",
    "name:und_x_variant":[
        "Makun",
        "Oko-Makun"
    ],
    "wof:name":"Oko-Makun",
    "wof:placetype":"locality"
},
  "geometry": {"coordinates":[4.18995,6.62276],"type":"Point"}
}