{
  "type": "Feature",
  "properties": {
    "gn:admin1_code":"45.0",
    "gn:admin2_code":"1007.0",
    "gn:asciiname":"Obiakabi",
    "gn:country_code":"NG",
    "gn:dem":118,
    "gn:feature_class":"P",
    "gn:feature_code":"PPL",
    "gn:name":"Obiakabi",
    "gn:population":0,
    "gn:timezone":"Africa/Lagos",
    "iso:country":"NG",
    "wof:name":"Obiakabi",
    "wof:placetype":"locality"
},
  "geometry": {"coordinates":[7.36747,5.34738],"type":"Point"}
}