{
  "type": "Feature",
  "properties": {
    "gn:admin1_code":"45.0",
    "gn:admin2_code":"1009.0",
    "gn:asciiname":"Umu Agwa",
    "gn:country_code":"NG",
    "gn:dem":70,
    "gn:feature_class":"P",
    "gn:feature_code":"PPL",
    "gn:name":"Umu Agwa",
    "gn:population":0,
    "gn:timezone":"Africa/Lagos",
    "iso:country":"NG",
    "name:und_x_variant":[
        "Ohanze Umu Agwa",
        "Umu Agwa"
    ],
    "wof:name":"Umu Agwa",
    "wof:placetype":"locality"
},
  "geometry": {"coordinates":[7.51508,5.08526],"type":"Point"}
}