{
  "type": "Feature",
  "properties": {
    "gn:admin1_code":"43.0",
    "gn:asciiname":"Madaru",
    "gn:country_code":"NG",
    "gn:dem":215,
    "gn:feature_class":"P",
    "gn:feature_code":"PPL",
    "gn:name":"Madaru",
    "gn:population":0,
    "gn:timezone":"Africa/Lagos",
    "iso:country":"NG",
    "name:eng_x_preferred":[
        "Madaru"
    ],
    "wof:name":"Madaru",
    "wof:placetype":"locality"
},
  "geometry": {"coordinates":[10.90421,9.23686],"type":"Point"}
}