{
  "type": "Feature",
  "properties": {
    "gn:admin1_code":"30.0",
    "gn:admin2_code":"24005.0",
    "gn:asciiname":"Share",
    "gn:country_code":"NG",
    "gn:dem":295,
    "gn:feature_class":"P",
    "gn:feature_code":"PPLA2",
    "gn:name":"Share",
    "gn:population":0,
    "gn:timezone":"Africa/Lagos",
    "iso:country":"NG",
    "name:ara_x_preferred":[
        "\u0628\u0648\u0631\u0635\u0629"
    ],
    "name:ben_x_preferred":[
        "\u09b6\u09c7\u09af\u09bc\u09be\u09b0"
    ],
    "name:ceb_x_preferred":[
        "Share"
    ],
    "name:dan_x_preferred":[
        "Share"
    ],
    "name:deu_x_preferred":[
        "Share"
    ],
    "name:fas_x_preferred":[
        "\u0627\u0634\u062a\u0631\u0627\u06a9 \u06af\u0630\u0627\u0634\u062a\u0646"
    ],
    "name:fra_x_preferred":[
        "Share"
    ],
    "name:heb_x_preferred":[
        "\u05d1\u05d5\u05e8\u05e1\u05d4"
    ],
    "name:ita_x_preferred":[
        "Share"
    ],
    "name:jpn_x_preferred":[
        "Share"
    ],
    "name:pol_x_preferred":[
        "Papier warto\u015bciowy"
    ],
    "name:spa_x_preferred":[
        "Share"
    ],
    "name:swe_x_preferred":[
        "Share"
    ],
    "wof:name":"Share",
    "wof:placetype":"locality"
},
  "geometry": {"coordinates":[4.97342,8.82086],"type":"Point"}
}