{
  "type": "Feature",
  "properties": {
    "gn:admin1_code":"43.0",
    "gn:admin2_code":"35004.0",
    "gn:asciiname":"Kpaa",
    "gn:country_code":"NG",
    "gn:dem":473,
    "gn:feature_class":"P",
    "gn:feature_code":"PPL",
    "gn:name":"Kpaa",
    "gn:population":0,
    "gn:timezone":"Africa/Lagos",
    "iso:country":"NG",
    "wof:name":"Kpaa",
    "wof:placetype":"locality"
},
  "geometry": {"coordinates":[11.43333,7.26667],"type":"Point"}
}