{
  "type": "Feature",
  "properties": {
    "gn:admin1_code":"24.0",
    "gn:admin2_code":"417.0",
    "gn:admin3_code":"41702",
    "gn:asciiname":"Gidan Giwa",
    "gn:country_code":"NG",
    "gn:dem":637,
    "gn:feature_class":"P",
    "gn:feature_code":"PPL",
    "gn:name":"Gidan Giwa",
    "gn:population":0,
    "gn:timezone":"Africa/Lagos",
    "iso:country":"NG",
    "wof:name":"Gidan Giwa",
    "wof:placetype":"locality"
},
  "geometry": {"coordinates":[7.67968,11.47243],"type":"Point"}
}