{
  "type": "Feature",
  "properties": {
    "gn:admin1_code":"27.0",
    "gn:admin2_code":"123.0",
    "gn:admin3_code":"12302",
    "gn:asciiname":"Kirzuma",
    "gn:country_code":"NG",
    "gn:dem":288,
    "gn:feature_class":"P",
    "gn:feature_code":"PPL",
    "gn:name":"Kirzuma",
    "gn:population":0,
    "gn:timezone":"Africa/Lagos",
    "iso:country":"NG",
    "wof:name":"Kirzuma",
    "wof:placetype":"locality"
},
  "geometry": {"coordinates":[13.66257,12.60011],"type":"Point"}
}