{
  "type": "Feature",
  "properties": {
    "gn:admin1_code":"23.0",
    "gn:admin2_code":"19017.0",
    "gn:admin3_code":"KD1702",
    "gn:asciiname":"Mahanga",
    "gn:country_code":"NG",
    "gn:dem":805,
    "gn:feature_class":"P",
    "gn:feature_code":"PPL",
    "gn:name":"Mahanga",
    "gn:population":0,
    "gn:timezone":"Africa/Lagos",
    "iso:country":"NG",
    "name:ceb_x_preferred":[
        "Mahanga"
    ],
    "name:swe_x_preferred":[
        "Mahanga"
    ],
    "wof:name":"Mahanga",
    "wof:placetype":"locality"
},
  "geometry": {"coordinates":[8.66821,10.56303],"type":"Point"}
}