{
  "type": "Feature",
  "properties": {
    "iso:country":"NG",
    "name:pol_x_preferred":[
        "Sabon Gari"
    ],
    "qs:gn_country":"NG",
    "qs:gn_fcode":"PPLX",
    "qs:gn_pop":0,
    "qs:name":"Sabon Gari",
    "qs:name_adm0":"Nigeria",
    "qs:name_adm1":"Kano",
    "qs:photos":20,
    "qs:photos_1k":4,
    "qs:photos_9k":1,
    "qs:photos_9r":1,
    "qs:photos_all":20,
    "qs:photos_sr":1,
    "qs:placetype":"Suburb",
    "qs:pop_sr":"0",
    "qs:woe_adm0":23424908,
    "wd:wordcount":642,
    "wof:name":"Sabon Gari",
    "wof:placetype":"neighbourhood"
},
  "geometry": {"coordinates":[8.52237,12.02182],"type":"Point"}
}