{
  "type": "Feature",
  "properties": {
    "gn:admin1_code":"27.0",
    "gn:admin2_code":"116.0",
    "gn:admin3_code":"11604",
    "gn:asciiname":"Malabi",
    "gn:country_code":"NG",
    "gn:dem":341,
    "gn:feature_class":"P",
    "gn:feature_code":"PPL",
    "gn:name":"Malabi",
    "gn:population":0,
    "gn:timezone":"Africa/Lagos",
    "iso:country":"NG",
    "wof:name":"Malabi",
    "wof:placetype":"locality"
},
  "geometry": {"coordinates":[13.3431,11.51659],"type":"Point"}
}