{
  "type": "Feature",
  "properties": {
    "gn:admin1_code":"43.0",
    "gn:admin2_code":"35007.0",
    "gn:asciiname":"Vosho",
    "gn:country_code":"NG",
    "gn:dem":197,
    "gn:feature_class":"P",
    "gn:feature_code":"PPL",
    "gn:name":"Vosho",
    "gn:population":0,
    "gn:timezone":"Africa/Lagos",
    "iso:country":"NG",
    "wof:name":"Vosho",
    "wof:placetype":"locality"
},
  "geometry": {"coordinates":[11.2841,8.91483],"type":"Point"}
}