{
  "type": "Feature",
  "properties": {
    "gn:admin1_code":"57.0",
    "gn:admin2_code":"807.0",
    "gn:admin3_code":"80710",
    "gn:asciiname":"Guidan Musa",
    "gn:country_code":"NG",
    "gn:dem":471,
    "gn:feature_class":"P",
    "gn:feature_code":"PPL",
    "gn:name":"Guidan Musa",
    "gn:population":0,
    "gn:timezone":"Africa/Lagos",
    "iso:country":"NG",
    "name:und_x_variant":[
        "Gidan Musa",
        "Guidan Musa"
    ],
    "wof:name":"Guidan Musa",
    "wof:placetype":"locality"
},
  "geometry": {"coordinates":[6.59968,12.08833],"type":"Point"}
}