{
  "type": "Feature",
  "properties": {
    "gn:admin1_code":"26.0",
    "gn:admin2_code":"7008.0",
    "gn:asciiname":"Gbakure",
    "gn:country_code":"NG",
    "gn:dem":129,
    "gn:feature_class":"P",
    "gn:feature_code":"PPL",
    "gn:name":"Gbakure",
    "gn:population":0,
    "gn:timezone":"Africa/Lagos",
    "iso:country":"NG",
    "wof:name":"Gbakure",
    "wof:placetype":"locality"
},
  "geometry": {"coordinates":[8.14103,7.55603],"type":"Point"}
}