{
  "type": "Feature",
  "properties": {
    "gn:admin1_code":"41.0",
    "gn:admin2_code":"23004.0",
    "gn:asciiname":"Konu",
    "gn:country_code":"NG",
    "gn:dem":111,
    "gn:feature_class":"P",
    "gn:feature_code":"PPL",
    "gn:name":"Konu",
    "gn:population":0,
    "gn:timezone":"Africa/Lagos",
    "iso:country":"NG",
    "wof:name":"Konu",
    "wof:placetype":"locality"
},
  "geometry": {"coordinates":[6.9469,7.7875],"type":"Point"}
}