{
  "type": "Feature",
  "properties": {
    "gn:admin1_code":"35.0",
    "gn:admin2_code":"2016.0",
    "gn:asciiname":"Vulpi",
    "gn:country_code":"NG",
    "gn:dem":140,
    "gn:feature_class":"P",
    "gn:feature_code":"PPL",
    "gn:name":"Vulpi",
    "gn:population":0,
    "gn:timezone":"Africa/Lagos",
    "iso:country":"NG",
    "name:eng_x_preferred":[
        "Vulpi"
    ],
    "wof:name":"Vulpi",
    "wof:placetype":"locality"
},
  "geometry": {"coordinates":[11.72207,9.45587],"type":"Point"}
}