{
  "type": "Feature",
  "properties": {
    "gn:admin1_code":"43.0",
    "gn:admin2_code":"35009.0",
    "gn:asciiname":"Gidan Dujere",
    "gn:country_code":"NG",
    "gn:dem":1082,
    "gn:feature_class":"P",
    "gn:feature_code":"PPL",
    "gn:name":"Gidan Dujere",
    "gn:population":0,
    "gn:timezone":"Africa/Lagos",
    "iso:country":"NG",
    "name:und_x_variant":[
        "Dujere",
        "Gidan Dujere"
    ],
    "wof:name":"Gidan Dujere",
    "wof:placetype":"locality"
},
  "geometry": {"coordinates":[10.96225,7.15538],"type":"Point"}
}