{
  "type": "Feature",
  "properties": {
    "gn:admin1_code":"47.0",
    "gn:admin2_code":"14001.0",
    "gn:asciiname":"Obeagu",
    "gn:country_code":"NG",
    "gn:dem":54,
    "gn:feature_class":"P",
    "gn:feature_code":"PPL",
    "gn:name":"Obeagu",
    "gn:population":0,
    "gn:timezone":"Africa/Lagos",
    "iso:country":"NG",
    "wof:name":"Obeagu",
    "wof:placetype":"locality"
},
  "geometry": {"coordinates":[7.67005,5.95471],"type":"Point"}
}