{
  "type": "Feature",
  "properties": {
    "gn:admin1_code":"23.0",
    "gn:admin2_code":"19014.0",
    "gn:admin3_code":"KD1402",
    "gn:asciiname":"Rigwallo",
    "gn:country_code":"NG",
    "gn:dem":760,
    "gn:feature_class":"P",
    "gn:feature_code":"PPL",
    "gn:name":"Rigwallo",
    "gn:population":0,
    "gn:timezone":"Africa/Lagos",
    "iso:country":"NG",
    "wof:name":"Rigwallo",
    "wof:placetype":"locality"
},
  "geometry": {"coordinates":[8.26095,10.16276],"type":"Point"}
}