{
  "type": "Feature",
  "properties": {
    "gn:admin1_code":"46.0",
    "gn:asciiname":"Kaltongo",
    "gn:country_code":"NG",
    "gn:dem":307,
    "gn:feature_class":"P",
    "gn:feature_code":"PPL",
    "gn:name":"Kaltongo",
    "gn:population":0,
    "gn:timezone":"Africa/Lagos",
    "iso:country":"NG",
    "name:eng_x_preferred":[
        "Kaltungo"
    ],
    "name:eng_x_variant":[
        "Kaltongo",
        "Kaltonga"
    ],
    "wof:name":"Kaltongo",
    "wof:placetype":"locality"
},
  "geometry": {"coordinates":[10.71969,10.09026],"type":"Point"}
}