{
  "type": "Feature",
  "properties": {
    "gn:admin1_code":"43.0",
    "gn:admin2_code":"35005",
    "gn:asciiname":"Wurubo Yakushamaki",
    "gn:country_code":"NG",
    "gn:dem":138,
    "gn:feature_class":"P",
    "gn:feature_code":"PPL",
    "gn:name":"Wurubo Yakushamaki",
    "gn:population":0,
    "gn:timezone":"Africa/Lagos",
    "iso:country":"NG",
    "wof:name":"Wurubo Yakushamaki",
    "wof:placetype":"locality"
},
  "geometry": {"coordinates":[10.58956,8.21073],"type":"Point"}
}