{
  "type": "Feature",
  "properties": {
    "gn:admin1_code":"56.0",
    "gn:asciiname":"Ungwan Kwara",
    "gn:country_code":"NG",
    "gn:dem":396,
    "gn:feature_class":"P",
    "gn:feature_code":"PPL",
    "gn:name":"Ungwan Kwara",
    "gn:population":0,
    "gn:timezone":"Africa/Lagos",
    "iso:country":"NG",
    "wof:name":"Ungwan Kwara",
    "wof:placetype":"locality"
},
  "geometry": {"coordinates":[8.09512,9.07506],"type":"Point"}
}