{
  "type": "Feature",
  "properties": {
    "gn:admin1_code":"36.0",
    "gn:admin2_code":"10010.0",
    "gn:asciiname":"Evwen",
    "gn:country_code":"NG",
    "gn:dem":16,
    "gn:feature_class":"P",
    "gn:feature_code":"PPL",
    "gn:name":"Evwen",
    "gn:population":0,
    "gn:timezone":"Africa/Lagos",
    "iso:country":"NG",
    "wof:name":"Evwen",
    "wof:placetype":"locality"
},
  "geometry": {"coordinates":[6.1616,5.47305],"type":"Point"}
}