{
  "type": "Feature",
  "properties": {
    "gn:admin1_code":"49.0",
    "gn:admin2_code":"32005.0",
    "gn:asciiname":"Rafin Jaki",
    "gn:country_code":"NG",
    "gn:dem":942,
    "gn:feature_class":"P",
    "gn:feature_code":"PPL",
    "gn:name":"Rafin Jaki",
    "gn:population":0,
    "gn:timezone":"Africa/Lagos",
    "iso:country":"NG",
    "wof:name":"Rafin Jaki",
    "wof:placetype":"locality"
},
  "geometry": {"coordinates":[8.92632,10.0177],"type":"Point"}
}