{
  "type": "Feature",
  "properties": {
    "gn:admin1_code":"50.0",
    "gn:asciiname":"Ojukiri Opuaru",
    "gn:country_code":"NG",
    "gn:dem":2,
    "gn:feature_class":"P",
    "gn:feature_code":"PPL",
    "gn:name":"Ojukiri Opuaru",
    "gn:population":0,
    "gn:timezone":"Africa/Lagos",
    "iso:country":"NG",
    "wof:name":"Ojukiri Opuaru",
    "wof:placetype":"locality"
},
  "geometry": {"coordinates":[7.02141,4.64023],"type":"Point"}
}