{
  "type": "Feature",
  "properties": {
    "gn:admin1_code":"27.0",
    "gn:admin2_code":"103.0",
    "gn:admin3_code":"10306",
    "gn:asciiname":"Kagilmari",
    "gn:country_code":"NG",
    "gn:dem":308,
    "gn:feature_class":"P",
    "gn:feature_code":"PPL",
    "gn:name":"Kagilmari",
    "gn:population":0,
    "gn:timezone":"Africa/Lagos",
    "iso:country":"NG",
    "wof:name":"Kagilmari",
    "wof:placetype":"locality"
},
  "geometry": {"coordinates":[14.11632,11.56443],"type":"Point"}
}