{
  "type": "Feature",
  "properties": {
    "gn:admin1_code":"31.0",
    "gn:admin2_code":"27009.0",
    "gn:asciiname":"Ladan",
    "gn:country_code":"NG",
    "gn:dem":460,
    "gn:feature_class":"P",
    "gn:feature_code":"PPL",
    "gn:name":"Ladan",
    "gn:population":0,
    "gn:timezone":"Africa/Lagos",
    "iso:country":"NG",
    "name:und_x_variant":[
        "Bonu",
        "Ladan"
    ],
    "wof:name":"Ladan",
    "wof:placetype":"locality"
},
  "geometry": {"coordinates":[6.97459,9.36414],"type":"Point"}
}