{
  "type": "Feature",
  "properties": {
    "gn:admin1_code":"21.0",
    "gn:admin2_code":"3014.0",
    "gn:asciiname":"Abiakpo Ikot Obionting",
    "gn:country_code":"NG",
    "gn:dem":110,
    "gn:feature_class":"P",
    "gn:feature_code":"PPL",
    "gn:name":"Abiakpo Ikot Obionting",
    "gn:population":0,
    "gn:timezone":"Africa/Lagos",
    "iso:country":"NG",
    "name:und_x_variant":[
        "Abia Ikot Obionting",
        "Abiakpo Ikot Obionting"
    ],
    "wof:name":"Abiakpo Ikot Obionting",
    "wof:placetype":"locality"
},
  "geometry": {"coordinates":[7.68542,5.24676],"type":"Point"}
}