{
  "type": "Feature",
  "properties": {
    "gn:admin1_code":"29.0",
    "gn:admin2_code":"20041.0",
    "gn:admin3_code":"KN2205",
    "gn:asciiname":"Unguwan Kigo",
    "gn:country_code":"NG",
    "gn:dem":526,
    "gn:feature_class":"P",
    "gn:feature_code":"PPL",
    "gn:name":"Unguwan Kigo",
    "gn:population":0,
    "gn:timezone":"Africa/Lagos",
    "iso:country":"NG",
    "wof:name":"Unguwan Kigo",
    "wof:placetype":"locality"
},
  "geometry": {"coordinates":[8.04817,11.76751],"type":"Point"}
}