{
  "type": "Feature",
  "properties": {
    "gn:admin1_code":"36.0",
    "gn:admin2_code":"10010.0",
    "gn:asciiname":"Umeh",
    "gn:country_code":"NG",
    "gn:dem":12,
    "gn:feature_class":"P",
    "gn:feature_code":"PPL",
    "gn:name":"Umeh",
    "gn:population":0,
    "gn:timezone":"Africa/Lagos",
    "iso:country":"NG",
    "name:und_x_variant":[
        "Ume",
        "Umeh"
    ],
    "wof:name":"Umeh",
    "wof:placetype":"locality"
},
  "geometry": {"coordinates":[6.15297,5.26659],"type":"Point"}
}