{
  "type": "Feature",
  "properties": {
    "gn:admin1_code":"36.0",
    "gn:admin2_code":"10006.0",
    "gn:asciiname":"Obromudu",
    "gn:country_code":"NG",
    "gn:dem":20,
    "gn:feature_class":"P",
    "gn:feature_code":"PPL",
    "gn:name":"Obromudu",
    "gn:population":0,
    "gn:timezone":"Africa/Lagos",
    "iso:country":"NG",
    "name:eng_x_preferred":[
        "Obromudu"
    ],
    "wof:name":"Obromudu",
    "wof:placetype":"locality"
},
  "geometry": {"coordinates":[5.69641,5.96615],"type":"Point"}
}