{
  "type": "Feature",
  "properties": {
    "gn:admin1_code":"41.0",
    "gn:admin2_code":"23005.0",
    "gn:asciiname":"Egudi",
    "gn:country_code":"NG",
    "gn:dem":248,
    "gn:feature_class":"P",
    "gn:feature_code":"PPL",
    "gn:name":"Egudi",
    "gn:population":0,
    "gn:timezone":"Africa/Lagos",
    "iso:country":"NG",
    "wof:name":"Egudi",
    "wof:placetype":"locality"
},
  "geometry": {"coordinates":[7.28333,7.78333],"type":"Point"}
}