{
  "type": "Feature",
  "properties": {
    "gn:admin1_code":"24.0",
    "gn:admin2_code":"417.0",
    "gn:admin3_code":"41704",
    "gn:asciiname":"Mashekarai",
    "gn:country_code":"NG",
    "gn:dem":680,
    "gn:feature_class":"P",
    "gn:feature_code":"PPL",
    "gn:name":"Mashekarai",
    "gn:population":0,
    "gn:timezone":"Africa/Lagos",
    "iso:country":"NG",
    "wof:name":"Mashekarai",
    "wof:placetype":"locality"
},
  "geometry": {"coordinates":[7.62183,11.4144],"type":"Point"}
}