{
  "type": "Feature",
  "properties": {
    "gn:admin1_code":"42.0",
    "gn:admin2_code":"30008.0",
    "gn:asciiname":"Jagun",
    "gn:country_code":"NG",
    "gn:dem":289,
    "gn:feature_class":"P",
    "gn:feature_code":"PPL",
    "gn:name":"Jagun",
    "gn:population":0,
    "gn:timezone":"Africa/Lagos",
    "iso:country":"NG",
    "wof:name":"Jagun",
    "wof:placetype":"locality"
},
  "geometry": {"coordinates":[4.45,7.61667],"type":"Point"}
}