{
  "type": "Feature",
  "properties": {
    "gn:admin1_code":"27.0",
    "gn:admin2_code":"102.0",
    "gn:admin3_code":"10210",
    "gn:asciiname":"Pubagu",
    "gn:country_code":"NG",
    "gn:dem":482,
    "gn:feature_class":"P",
    "gn:feature_code":"PPL",
    "gn:name":"Pubagu",
    "gn:population":0,
    "gn:timezone":"Africa/Lagos",
    "iso:country":"NG",
    "wof:name":"Pubagu",
    "wof:placetype":"locality"
},
  "geometry": {"coordinates":[13.00423,10.53801],"type":"Point"}
}