{
  "type": "Feature",
  "properties": {
    "gn:admin1_code":"16.0",
    "gn:admin2_code":"28009.0",
    "gn:asciiname":"Egundugbo",
    "gn:country_code":"NG",
    "gn:dem":68,
    "gn:feature_class":"P",
    "gn:feature_code":"PPL",
    "gn:name":"Egundugbo",
    "gn:population":0,
    "gn:timezone":"Africa/Lagos",
    "iso:country":"NG",
    "wof:name":"Egundugbo",
    "wof:placetype":"locality"
},
  "geometry": {"coordinates":[3.85608,6.98489],"type":"Point"}
}