{
  "type": "Feature",
  "properties": {
    "gn:admin1_code":"23.0",
    "gn:admin2_code":"19004.0",
    "gn:admin3_code":"KD0410",
    "gn:asciiname":"Baka",
    "gn:country_code":"NG",
    "gn:dem":602,
    "gn:feature_class":"P",
    "gn:feature_code":"PPL",
    "gn:name":"Baka",
    "gn:population":0,
    "gn:timezone":"Africa/Lagos",
    "iso:country":"NG",
    "wof:name":"Baka",
    "wof:placetype":"locality"
},
  "geometry": {"coordinates":[7.29101,10.84737],"type":"Point"}
}