{
  "type": "Feature",
  "properties": {
    "gn:admin1_code":"27.0",
    "gn:admin2_code":"103.0",
    "gn:admin3_code":"10304",
    "gn:asciiname":"Ali Karumiri",
    "gn:country_code":"NG",
    "gn:dem":334,
    "gn:feature_class":"P",
    "gn:feature_code":"PPL",
    "gn:name":"Ali Karumiri",
    "gn:population":0,
    "gn:timezone":"Africa/Lagos",
    "iso:country":"NG",
    "wof:name":"Ali Karumiri",
    "wof:placetype":"locality"
},
  "geometry": {"coordinates":[13.70337,11.48823],"type":"Point"}
}