{
  "type": "Feature",
  "properties": {
    "gn:admin1_code":"40.0",
    "gn:admin2_code":"510.0",
    "gn:admin3_code":"51004",
    "gn:asciiname":"Tari",
    "gn:country_code":"NG",
    "gn:dem":232,
    "gn:feature_class":"P",
    "gn:feature_code":"PPL",
    "gn:name":"Tari",
    "gn:population":0,
    "gn:timezone":"Africa/Lagos",
    "iso:country":"NG",
    "wof:name":"Tari",
    "wof:placetype":"locality"
},
  "geometry": {"coordinates":[4.49157,12.4092],"type":"Point"}
}