{
  "type": "Feature",
  "properties": {
    "gn:admin1_code":"49.0",
    "gn:asciiname":"Jondshakal",
    "gn:country_code":"NG",
    "gn:dem":202,
    "gn:feature_class":"P",
    "gn:feature_code":"PPL",
    "gn:name":"Jondshakal",
    "gn:population":0,
    "gn:timezone":"Africa/Lagos",
    "iso:country":"NG",
    "wof:name":"Jondshakal",
    "wof:placetype":"locality"
},
  "geometry": {"coordinates":[9.23513,8.72832],"type":"Point"}
}