{
  "type": "Feature",
  "properties": {
    "gn:admin1_code":"26.0",
    "gn:admin2_code":"7009",
    "gn:asciiname":"Tsetorkwaor",
    "gn:country_code":"NG",
    "gn:dem":224,
    "gn:feature_class":"P",
    "gn:feature_code":"PPL",
    "gn:name":"Tsetorkwaor",
    "gn:population":0,
    "gn:timezone":"Africa/Lagos",
    "iso:country":"NG",
    "wof:name":"Tsetorkwaor",
    "wof:placetype":"locality"
},
  "geometry": {"coordinates":[9.79089,7.56163],"type":"Point"}
}