{
  "type": "Feature",
  "properties": {
    "gn:admin1_code":"49.0",
    "gn:admin2_code":"32014.0",
    "gn:asciiname":"Kwong",
    "gn:country_code":"NG",
    "gn:dem":373,
    "gn:feature_class":"P",
    "gn:feature_code":"PPL",
    "gn:name":"Kwong",
    "gn:population":0,
    "gn:timezone":"Africa/Lagos",
    "iso:country":"NG",
    "name:und_x_variant":[
        "Kwang"
    ],
    "wof:name":"Kwong",
    "wof:placetype":"locality"
},
  "geometry": {"coordinates":[9.26491,9.02135],"type":"Point"}
}