{
  "type": "Feature",
  "properties": {
    "gn:admin1_code":"43.0",
    "gn:admin2_code":"35007",
    "gn:asciiname":"Longa Yewa",
    "gn:country_code":"NG",
    "gn:dem":210,
    "gn:feature_class":"P",
    "gn:feature_code":"PPL",
    "gn:name":"Longa Yewa",
    "gn:population":0,
    "gn:timezone":"Africa/Lagos",
    "iso:country":"NG",
    "wof:name":"Longa Yewa",
    "wof:placetype":"locality"
},
  "geometry": {"coordinates":[11.38899,8.86687],"type":"Point"}
}