{
  "type": "Feature",
  "properties": {
    "gn:admin1_code":"26.0",
    "gn:admin2_code":"7005.0",
    "gn:asciiname":"Kutu",
    "gn:country_code":"NG",
    "gn:dem":123,
    "gn:feature_class":"P",
    "gn:feature_code":"PPL",
    "gn:name":"Kutu",
    "gn:population":0,
    "gn:timezone":"Africa/Lagos",
    "iso:country":"NG",
    "name:ceb_x_preferred":[
        "Kutu"
    ],
    "name:que_x_preferred":[
        "Kutu"
    ],
    "name:swe_x_preferred":[
        "Kutu"
    ],
    "wof:name":"Kutu",
    "wof:placetype":"locality"
},
  "geometry": {"coordinates":[8.63084,7.2895],"type":"Point"}
}