{
  "type": "Feature",
  "properties": {
    "gn:admin1_code":"42.0",
    "gn:admin2_code":"30002.0",
    "gn:asciiname":"Akinbami",
    "gn:cc2":"NG",
    "gn:country_code":"NG",
    "gn:dem":250,
    "gn:feature_class":"P",
    "gn:feature_code":"PPL",
    "gn:name":"Akinbami",
    "gn:population":0,
    "gn:timezone":"Africa/Lagos",
    "iso:country":"NG",
    "name:und_x_variant":[
        "Akinbunmi",
        "Akinbami"
    ],
    "wof:name":"Akinbami",
    "wof:placetype":"locality"
},
  "geometry": {"coordinates":[4.26667,7.53333],"type":"Point"}
}