{
  "type": "Feature",
  "properties": {
    "gn:admin1_code":"35.0",
    "gn:admin2_code":"2002.0",
    "gn:asciiname":"Karlahi",
    "gn:country_code":"NG",
    "gn:dem":385,
    "gn:feature_class":"P",
    "gn:feature_code":"PPL",
    "gn:name":"Karlahi",
    "gn:population":0,
    "gn:timezone":"Africa/Lagos",
    "iso:country":"NG",
    "name:eng_x_preferred":[
        "Karlahi"
    ],
    "wof:name":"Karlahi",
    "wof:placetype":"locality"
},
  "geometry": {"coordinates":[12.41071,9.00231],"type":"Point"}
}