{
  "type": "Feature",
  "properties": {
    "gn:admin1_code":"22.0",
    "gn:admin2_code":"9006.0",
    "gn:asciiname":"Ikot Ukwak",
    "gn:country_code":"NG",
    "gn:dem":13,
    "gn:feature_class":"P",
    "gn:feature_code":"PPL",
    "gn:name":"Ikot Ukwak",
    "gn:population":0,
    "gn:timezone":"Africa/Lagos",
    "iso:country":"NG",
    "name:und_x_variant":[
        "Ikot Ukwuk",
        "Ikot Ukwak"
    ],
    "wof:name":"Ikot Ukwak",
    "wof:placetype":"locality"
},
  "geometry": {"coordinates":[8.0428,5.3236],"type":"Point"}
}