{
  "type": "Feature",
  "properties": {
    "gn:admin1_code":"35.0",
    "gn:admin2_code":"2012",
    "gn:asciiname":"Gangdon",
    "gn:country_code":"NG",
    "gn:dem":463,
    "gn:feature_class":"P",
    "gn:feature_code":"PPL",
    "gn:name":"Gangdon",
    "gn:population":0,
    "gn:timezone":"Africa/Lagos",
    "iso:country":"NG",
    "wof:name":"Gangdon",
    "wof:placetype":"locality"
},
  "geometry": {"coordinates":[11.90837,8.84756],"type":"Point"}
}