{
  "type": "Feature",
  "properties": {
    "gn:admin1_code":"26.0",
    "gn:admin2_code":"7022.0",
    "gn:asciiname":"Moze",
    "gn:country_code":"NG",
    "gn:dem":115,
    "gn:feature_class":"P",
    "gn:feature_code":"PPL",
    "gn:name":"Moze",
    "gn:population":0,
    "gn:timezone":"Africa/Lagos",
    "iso:country":"NG",
    "wof:name":"Moze",
    "wof:placetype":"locality"
},
  "geometry": {"coordinates":[8.80987,7.09666],"type":"Point"}
}