{
  "type": "Feature",
  "properties": {
    "gn:admin1_code":"26.0",
    "gn:admin2_code":"7021",
    "gn:asciiname":"Tsekasever",
    "gn:country_code":"NG",
    "gn:dem":124,
    "gn:feature_class":"P",
    "gn:feature_code":"PPL",
    "gn:name":"Tsekasever",
    "gn:population":0,
    "gn:timezone":"Africa/Lagos",
    "iso:country":"NG",
    "name:und_x_variant":[
        "Tsekazever"
    ],
    "wof:name":"Tsekasever",
    "wof:placetype":"locality"
},
  "geometry": {"coordinates":[9.4492,7.82252],"type":"Point"}
}