{
  "type": "Feature",
  "properties": {
    "gn:admin1_code":"30.0",
    "gn:admin2_code":"24006.0",
    "gn:asciiname":"Pepele",
    "gn:country_code":"NG",
    "gn:dem":371,
    "gn:feature_class":"P",
    "gn:feature_code":"PPL",
    "gn:name":"Pepele",
    "gn:population":0,
    "gn:timezone":"Africa/Lagos",
    "iso:country":"NG",
    "wof:name":"Pepele",
    "wof:placetype":"locality"
},
  "geometry": {"coordinates":[4.83333,8.58333],"type":"Point"}
}