{
  "type": "Feature",
  "properties": {
    "gn:admin1_code":"26.0",
    "gn:admin2_code":"7005",
    "gn:asciiname":"Jil",
    "gn:country_code":"NG",
    "gn:dem":177,
    "gn:feature_class":"P",
    "gn:feature_code":"PPL",
    "gn:name":"Jil",
    "gn:population":0,
    "gn:timezone":"Africa/Lagos",
    "iso:country":"NG",
    "name:nld_x_preferred":[
        "Jil"
    ],
    "wof:name":"Jil",
    "wof:placetype":"locality"
},
  "geometry": {"coordinates":[8.93292,7.47333],"type":"Point"}
}