{
  "type": "Feature",
  "properties": {
    "gn:admin1_code":"56.0",
    "gn:admin2_code":"26004",
    "gn:asciiname":"Nburzi",
    "gn:country_code":"NG",
    "gn:dem":467,
    "gn:feature_class":"P",
    "gn:feature_code":"PPL",
    "gn:name":"Nburzi",
    "gn:population":0,
    "gn:timezone":"Africa/Lagos",
    "iso:country":"NG",
    "wof:name":"Nburzi",
    "wof:placetype":"locality"
},
  "geometry": {"coordinates":[7.97386,9.15555],"type":"Point"}
}