{
  "type": "Feature",
  "properties": {
    "gn:admin1_code":"21.0",
    "gn:admin2_code":"3003.0",
    "gn:asciiname":"Odoro Enen",
    "gn:country_code":"NG",
    "gn:dem":18,
    "gn:feature_class":"P",
    "gn:feature_code":"PPL",
    "gn:name":"Odoro Enen",
    "gn:population":0,
    "gn:timezone":"Africa/Lagos",
    "iso:country":"NG",
    "wof:name":"Odoro Enen",
    "wof:placetype":"locality"
},
  "geometry": {"coordinates":[7.94838,4.66768],"type":"Point"}
}