{
  "type": "Feature",
  "properties": {
    "gn:admin1_code":"21.0",
    "gn:admin2_code":"3001.0",
    "gn:asciiname":"Ibiakpan",
    "gn:country_code":"NG",
    "gn:dem":86,
    "gn:feature_class":"P",
    "gn:feature_code":"PPL",
    "gn:name":"Ibiakpan",
    "gn:population":0,
    "gn:timezone":"Africa/Lagos",
    "iso:country":"NG",
    "name:und_x_variant":[
        "Ibiakpan No.1",
        "Ibiakpan"
    ],
    "wof:name":"Ibiakpan",
    "wof:placetype":"locality"
},
  "geometry": {"coordinates":[7.79588,5.09829],"type":"Point"}
}