{
  "type": "Feature",
  "properties": {
    "gn:admin1_code":"31.0",
    "gn:admin2_code":"27019",
    "gn:asciiname":"Nugopi",
    "gn:country_code":"NG",
    "gn:dem":247,
    "gn:feature_class":"P",
    "gn:feature_code":"PPL",
    "gn:name":"Nugopi",
    "gn:population":0,
    "gn:timezone":"Africa/Lagos",
    "iso:country":"NG",
    "wof:name":"Nugopi",
    "wof:placetype":"locality"
},
  "geometry": {"coordinates":[6.65527,9.27083],"type":"Point"}
}