{
  "type": "Feature",
  "properties": {
    "gn:admin1_code":"27.0",
    "gn:admin2_code":"107.0",
    "gn:admin3_code":"10705",
    "gn:asciiname":"Karawua",
    "gn:country_code":"NG",
    "gn:dem":371,
    "gn:feature_class":"P",
    "gn:feature_code":"PPL",
    "gn:name":"Karawua",
    "gn:population":0,
    "gn:timezone":"Africa/Lagos",
    "iso:country":"NG",
    "wof:name":"Karawua",
    "wof:placetype":"locality"
},
  "geometry": {"coordinates":[13.02477,11.20592],"type":"Point"}
}