{
  "type": "Feature",
  "properties": {
    "gn:admin1_code":"40.0",
    "gn:asciiname":"Auta",
    "gn:country_code":"NG",
    "gn:dem":201,
    "gn:feature_class":"P",
    "gn:feature_code":"PPL",
    "gn:name":"Auta",
    "gn:population":0,
    "gn:timezone":"Africa/Lagos",
    "iso:country":"NG",
    "wof:name":"Auta",
    "wof:placetype":"locality"
},
  "geometry": {"coordinates":[4.42945,10.85632],"type":"Point"}
}