{
  "type": "Feature",
  "properties": {
    "gn:admin1_code":"39.0",
    "gn:admin2_code":"18002.0",
    "gn:admin3_code":"JI2602",
    "gn:asciiname":"Kanya",
    "gn:country_code":"NG",
    "gn:dem":384,
    "gn:feature_class":"P",
    "gn:feature_code":"PPL",
    "gn:name":"Kanya",
    "gn:population":0,
    "gn:timezone":"Africa/Lagos",
    "iso:country":"NG",
    "name:tel_x_preferred":[
        "\u0c15\u0c28\u0c4d\u0c2f\u0c3e \u0c32\u0c17\u0c4d\u0c28\u0c2e\u0c41"
    ],
    "name:und_x_variant":[
        "Rugar Kanya",
        "Kanya"
    ],
    "wof:name":"Kanya",
    "wof:placetype":"locality"
},
  "geometry": {"coordinates":[9.16354,12.29415],"type":"Point"}
}