{
  "type": "Feature",
  "properties": {
    "gn:admin1_code":"32.0",
    "gn:admin2_code":"31002.0",
    "gn:asciiname":"Akinyele",
    "gn:country_code":"NG",
    "gn:dem":266,
    "gn:feature_class":"P",
    "gn:feature_code":"PPL",
    "gn:name":"Akinyele",
    "gn:population":0,
    "gn:timezone":"Africa/Lagos",
    "iso:country":"NG",
    "name:azb_x_preferred":[
        "\u0627\u06a9\u06cc\u0646\u06cc\u0644"
    ],
    "name:ceb_x_preferred":[
        "Akinyele"
    ],
    "name:fas_x_preferred":[
        "\u0627\u06a9\u06cc\u0646\u06cc\u0644"
    ],
    "name:fra_x_preferred":[
        "Akinyele"
    ],
    "name:hau_x_preferred":[
        "Akinyele"
    ],
    "name:ita_x_preferred":[
        "Akinyele"
    ],
    "name:spa_x_preferred":[
        "Akinyele"
    ],
    "wof:name":"Akinyele",
    "wof:placetype":"neighbourhood"
},
  "geometry": {"coordinates":[3.91639,7.5975],"type":"Point"}
}