{
  "type": "Feature",
  "properties": {
    "gn:admin1_code":"21.0",
    "gn:admin2_code":"3031.0",
    "gn:asciiname":"Obio Offot",
    "gn:country_code":"NG",
    "gn:dem":75,
    "gn:feature_class":"P",
    "gn:feature_code":"PPL",
    "gn:name":"Obio Offot",
    "gn:population":0,
    "gn:timezone":"Africa/Lagos",
    "iso:country":"NG",
    "wof:name":"Obio Offot",
    "wof:placetype":"locality"
},
  "geometry": {"coordinates":[7.86973,5.01512],"type":"Point"}
}