{
  "type": "Feature",
  "properties": {
    "gn:admin1_code":"26.0",
    "gn:admin2_code":"7010.0",
    "gn:asciiname":"Heghel",
    "gn:country_code":"NG",
    "gn:dem":183,
    "gn:feature_class":"P",
    "gn:feature_code":"PPL",
    "gn:name":"Heghel",
    "gn:population":0,
    "gn:timezone":"Africa/Lagos",
    "iso:country":"NG",
    "wof:name":"Heghel",
    "wof:placetype":"locality"
},
  "geometry": {"coordinates":[8.57305,7.33274],"type":"Point"}
}