{
  "type": "Feature",
  "properties": {
    "gn:admin1_code":"31.0",
    "gn:admin2_code":"27017",
    "gn:asciiname":"Yanmigi",
    "gn:country_code":"NG",
    "gn:dem":84,
    "gn:feature_class":"P",
    "gn:feature_code":"PPL",
    "gn:name":"Yanmigi",
    "gn:population":0,
    "gn:timezone":"Africa/Lagos",
    "iso:country":"NG",
    "wof:name":"Yanmigi",
    "wof:placetype":"locality"
},
  "geometry": {"coordinates":[5.90037,9.48682],"type":"Point"}
}