{
  "type": "Feature",
  "properties": {
    "gn:admin1_code":"31.0",
    "gn:admin2_code":"27013",
    "gn:asciiname":"Sheshiylsa",
    "gn:country_code":"NG",
    "gn:dem":135,
    "gn:feature_class":"P",
    "gn:feature_code":"PPL",
    "gn:name":"Sheshiylsa",
    "gn:population":0,
    "gn:timezone":"Africa/Lagos",
    "iso:country":"NG",
    "wof:name":"Sheshiylsa",
    "wof:placetype":"locality"
},
  "geometry": {"coordinates":[5.8153,9.3077],"type":"Point"}
}