{
  "type": "Feature",
  "properties": {
    "gn:admin1_code":"23.0",
    "gn:admin2_code":"19003.0",
    "gn:admin3_code":"KD0310",
    "gn:asciiname":"Karaukarau",
    "gn:country_code":"NG",
    "gn:dem":681,
    "gn:feature_class":"P",
    "gn:feature_code":"PPL",
    "gn:name":"Karaukarau",
    "gn:population":0,
    "gn:timezone":"Africa/Lagos",
    "iso:country":"NG",
    "wof:name":"Karaukarau",
    "wof:placetype":"locality"
},
  "geometry": {"coordinates":[7.49755,11.09337],"type":"Point"}
}