{
  "type": "Feature",
  "properties": {
    "gn:admin1_code":"40.0",
    "gn:admin2_code":"505.0",
    "gn:admin3_code":"50507",
    "gn:asciiname":"Tunga Kade",
    "gn:country_code":"NG",
    "gn:dem":179,
    "gn:feature_class":"P",
    "gn:feature_code":"PPL",
    "gn:name":"Tunga Kade",
    "gn:population":0,
    "gn:timezone":"Africa/Lagos",
    "iso:country":"NG",
    "wof:name":"Tunga Kade",
    "wof:placetype":"locality"
},
  "geometry": {"coordinates":[4.18622,11.16554],"type":"Point"}
}