{
  "type": "Feature",
  "properties": {
    "gn:admin1_code":"51.0",
    "gn:admin2_code":"606.0",
    "gn:admin3_code":"60601",
    "gn:asciiname":"Kokoki",
    "gn:country_code":"NG",
    "gn:dem":252,
    "gn:feature_class":"P",
    "gn:feature_code":"PPL",
    "gn:name":"Kokoki",
    "gn:population":0,
    "gn:timezone":"Africa/Lagos",
    "iso:country":"NG",
    "name:und_x_variant":[
        "Kekoke",
        "Kokoki"
    ],
    "wof:name":"Kokoki",
    "wof:placetype":"locality"
},
  "geometry": {"coordinates":[4.42969,13.60124],"type":"Point"}
}