{
  "type": "Feature",
  "properties": {
    "gn:admin1_code":"27.0",
    "gn:admin2_code":"121",
    "gn:admin3_code":"12112",
    "gn:asciiname":"Maje Sharuwuri",
    "gn:country_code":"NG",
    "gn:dem":296,
    "gn:feature_class":"P",
    "gn:feature_code":"PPL",
    "gn:name":"Maje Sharuwuri",
    "gn:population":0,
    "gn:timezone":"Africa/Lagos",
    "iso:country":"NG",
    "wof:name":"Maje Sharuwuri",
    "wof:placetype":"locality"
},
  "geometry": {"coordinates":[13.82005,12.26598],"type":"Point"}
}