{
  "type": "Feature",
  "properties": {
    "gn:admin1_code":"32.0",
    "gn:admin2_code":"31014.0",
    "gn:asciiname":"Atowada",
    "gn:country_code":"NG",
    "gn:dem":218,
    "gn:feature_class":"P",
    "gn:feature_code":"PPL",
    "gn:name":"Atowada",
    "gn:population":0,
    "gn:timezone":"Africa/Lagos",
    "iso:country":"NG",
    "wof:name":"Atowada",
    "wof:placetype":"locality"
},
  "geometry": {"coordinates":[3.75444,7.51833],"type":"Point"}
}