{
  "type": "Feature",
  "properties": {
    "gn:admin1_code":"25.0",
    "gn:admin2_code":"4016.0",
    "gn:asciiname":"Ogu-Ikpele",
    "gn:country_code":"NG",
    "gn:dem":23,
    "gn:feature_class":"P",
    "gn:feature_code":"PPL",
    "gn:name":"Ogu-Ikpele",
    "gn:population":0,
    "gn:timezone":"Africa/Lagos",
    "iso:country":"NG",
    "wof:name":"Ogu-Ikpele",
    "wof:placetype":"locality"
},
  "geometry": {"coordinates":[6.67835,5.8495],"type":"Point"}
}