{
  "type": "Feature",
  "properties": {
    "gn:admin1_code":"46.0",
    "gn:admin2_code":"5013.0",
    "gn:admin3_code":"BA1313",
    "gn:asciiname":"Lomi",
    "gn:country_code":"NG",
    "gn:dem":344,
    "gn:feature_class":"P",
    "gn:feature_code":"PPL",
    "gn:name":"Lomi",
    "gn:population":0,
    "gn:timezone":"Africa/Lagos",
    "iso:country":"NG",
    "name:eng_x_preferred":[
        "Lomi"
    ],
    "name:tgl_x_preferred":[
        "Lomi"
    ],
    "wof:name":"Lomi",
    "wof:placetype":"locality"
},
  "geometry": {"coordinates":[10.7928,10.40925],"type":"Point"}
}