{
  "type": "Feature",
  "properties": {
    "gn:admin1_code":"46.0",
    "gn:admin2_code":"5016.0",
    "gn:admin3_code":"BA1615",
    "gn:asciiname":"Gabati",
    "gn:country_code":"NG",
    "gn:dem":420,
    "gn:feature_class":"P",
    "gn:feature_code":"PPL",
    "gn:name":"Gabati",
    "gn:population":0,
    "gn:timezone":"Africa/Lagos",
    "iso:country":"NG",
    "name:und_x_variant":[
        "Gabali",
        "Gabati"
    ],
    "wof:name":"Gabati",
    "wof:placetype":"locality"
},
  "geometry": {"coordinates":[9.96041,11.40664],"type":"Point"}
}