{
  "type": "Feature",
  "properties": {
    "gn:admin1_code":"35.0",
    "gn:asciiname":"Geman",
    "gn:country_code":"NG",
    "gn:dem":176,
    "gn:feature_class":"P",
    "gn:feature_code":"PPL",
    "gn:name":"Geman",
    "gn:population":0,
    "gn:timezone":"Africa/Lagos",
    "iso:country":"NG",
    "name:eng_x_preferred":[
        "Geman"
    ],
    "wof:name":"Geman",
    "wof:placetype":"locality"
},
  "geometry": {"coordinates":[11.73799,9.4758],"type":"Point"}
}