{
  "type": "Feature",
  "properties": {
    "gn:admin1_code":"56.0",
    "gn:admin2_code":"26004.0",
    "gn:asciiname":"Kupe",
    "gn:country_code":"NG",
    "gn:dem":607,
    "gn:feature_class":"P",
    "gn:feature_code":"PPL",
    "gn:name":"Kupe",
    "gn:population":0,
    "gn:timezone":"Africa/Lagos",
    "iso:country":"NG",
    "name:deu_x_preferred":[
        "Kupe"
    ],
    "name:fra_x_preferred":[
        "Kupe"
    ],
    "name:ind_x_preferred":[
        "Kupe"
    ],
    "name:kat_x_preferred":[
        "\u10d9\u10e3\u10de\u10d4"
    ],
    "name:mri_x_preferred":[
        "Kupe"
    ],
    "name:nno_x_preferred":[
        "Kupe"
    ],
    "name:nor_x_preferred":[
        "Kupe"
    ],
    "name:spa_x_preferred":[
        "Kupe"
    ],
    "wof:name":"Kupe",
    "wof:placetype":"locality"
},
  "geometry": {"coordinates":[7.62756,9.19679],"type":"Point"}
}