{
  "type": "Feature",
  "properties": {
    "gn:admin1_code":"36.0",
    "gn:admin2_code":"10006.0",
    "gn:asciiname":"Anibon",
    "gn:country_code":"NG",
    "gn:dem":10,
    "gn:feature_class":"P",
    "gn:feature_code":"PPL",
    "gn:name":"Anibon",
    "gn:population":0,
    "gn:timezone":"Africa/Lagos",
    "iso:country":"NG",
    "name:eng_x_preferred":[
        "Anibon"
    ],
    "wof:name":"Anibon",
    "wof:placetype":"locality"
},
  "geometry": {"coordinates":[5.86271,5.79046],"type":"Point"}
}