{
  "type": "Feature",
  "properties": {
    "gn:admin1_code":"52.0",
    "gn:admin2_code":"6008.0",
    "gn:asciiname":"Yenizue Epie",
    "gn:country_code":"NG",
    "gn:dem":10,
    "gn:feature_class":"P",
    "gn:feature_code":"PPL",
    "gn:name":"Yenizue Epie",
    "gn:population":0,
    "gn:timezone":"Africa/Lagos",
    "iso:country":"NG",
    "wof:name":"Yenizue Epie",
    "wof:placetype":"neighbourhood"
},
  "geometry": {"coordinates":[6.30497,4.93063],"type":"Point"}
}