{
  "type": "Feature",
  "properties": {
    "gn:admin1_code":"22.0",
    "gn:admin2_code":"9015.0",
    "gn:asciiname":"Ekim Ito",
    "gn:country_code":"NG",
    "gn:dem":23,
    "gn:feature_class":"P",
    "gn:feature_code":"PPL",
    "gn:name":"Ekim Ito",
    "gn:population":0,
    "gn:timezone":"Africa/Lagos",
    "iso:country":"NG",
    "wof:name":"Ekim Ito",
    "wof:placetype":"locality"
},
  "geometry": {"coordinates":[7.97232,5.33091],"type":"Point"}
}