{
  "type": "Feature",
  "properties": {
    "gn:admin1_code":"21.0",
    "gn:admin2_code":"3031.0",
    "gn:asciiname":"Efiat Ofot",
    "gn:country_code":"NG",
    "gn:dem":69,
    "gn:feature_class":"P",
    "gn:feature_code":"PPL",
    "gn:name":"Efiat Ofot",
    "gn:population":0,
    "gn:timezone":"Africa/Lagos",
    "iso:country":"NG",
    "wof:name":"Efiat Ofot",
    "wof:placetype":"locality"
},
  "geometry": {"coordinates":[7.91828,5.02268],"type":"Point"}
}