{
  "type": "Feature",
  "properties": {
    "gn:admin1_code":"16.0",
    "gn:admin2_code":"28017.0",
    "gn:asciiname":"Iken",
    "gn:country_code":"NG",
    "gn:dem":25,
    "gn:feature_class":"P",
    "gn:feature_code":"PPL",
    "gn:name":"Iken",
    "gn:population":0,
    "gn:timezone":"Africa/Lagos",
    "iso:country":"NG",
    "name:ceb_x_preferred":[
        "Iken"
    ],
    "name:deu_x_preferred":[
        "Iken"
    ],
    "name:fas_x_preferred":[
        "\u0627\u06cc\u06a9\u0646"
    ],
    "name:fra_x_preferred":[
        "Iken"
    ],
    "name:nld_x_preferred":[
        "Iken"
    ],
    "name:pol_x_preferred":[
        "Iken"
    ],
    "name:spa_x_preferred":[
        "Iken"
    ],
    "name:swe_x_preferred":[
        "Iken"
    ],
    "wof:name":"Iken",
    "wof:placetype":"locality"
},
  "geometry": {"coordinates":[3.89297,6.75684],"type":"Point"}
}