{
  "type": "Feature",
  "properties": {
    "gn:admin1_code":"31.0",
    "gn:admin2_code":"27004.0",
    "gn:asciiname":"Kapubara",
    "gn:country_code":"NG",
    "gn:dem":341,
    "gn:feature_class":"P",
    "gn:feature_code":"PPL",
    "gn:name":"Kapubara",
    "gn:population":0,
    "gn:timezone":"Africa/Lagos",
    "iso:country":"NG",
    "name:und_x_variant":[
        "Tungan Madugu",
        "Kapu",
        "Kapubara"
    ],
    "wof:name":"Kapubara",
    "wof:placetype":"locality"
},
  "geometry": {"coordinates":[3.87504,10.6432],"type":"Point"}
}