{
  "type": "Feature",
  "properties": {
    "gn:admin1_code":"48.0",
    "gn:admin2_code":"29008.0",
    "gn:asciiname":"Ododin Odewu",
    "gn:country_code":"NG",
    "gn:dem":289,
    "gn:feature_class":"P",
    "gn:feature_code":"PPL",
    "gn:name":"Ododin Odewu",
    "gn:population":0,
    "gn:timezone":"Africa/Lagos",
    "iso:country":"NG",
    "wof:name":"Ododin Odewu",
    "wof:placetype":"locality"
},
  "geometry": {"coordinates":[5.1717,7.1052],"type":"Point"}
}