{
  "type": "Feature",
  "properties": {
    "gn:admin1_code":"44.0",
    "gn:admin2_code":"705.0",
    "gn:admin3_code":"70506",
    "gn:asciiname":"Karuonguwa",
    "gn:country_code":"NG",
    "gn:dem":398,
    "gn:feature_class":"P",
    "gn:feature_code":"PPL",
    "gn:name":"Karuonguwa",
    "gn:population":0,
    "gn:timezone":"Africa/Lagos",
    "iso:country":"NG",
    "wof:name":"Karuonguwa",
    "wof:placetype":"locality"
},
  "geometry": {"coordinates":[11.68449,11.82181],"type":"Point"}
}