{
  "type": "Feature",
  "properties": {
    "gn:admin1_code":"29.0",
    "gn:admin2_code":"20010.0",
    "gn:admin3_code":"KN1701",
    "gn:asciiname":"Garke",
    "gn:country_code":"NG",
    "gn:dem":447,
    "gn:feature_class":"P",
    "gn:feature_code":"PPL",
    "gn:name":"Garke",
    "gn:population":0,
    "gn:timezone":"Africa/Lagos",
    "iso:country":"NG",
    "wof:name":"Garke",
    "wof:placetype":"locality"
},
  "geometry": {"coordinates":[8.67722,12.0691],"type":"Point"}
}