{
  "type": "Feature",
  "properties": {
    "gn:admin1_code":"27.0",
    "gn:admin2_code":"105.0",
    "gn:admin3_code":"10511",
    "gn:asciiname":"Dula",
    "gn:country_code":"NG",
    "gn:dem":652,
    "gn:feature_class":"P",
    "gn:feature_code":"PPL",
    "gn:name":"Dula",
    "gn:population":0,
    "gn:timezone":"Africa/Lagos",
    "iso:country":"NG",
    "wof:name":"Dula",
    "wof:placetype":"locality"
},
  "geometry": {"coordinates":[12.17935,10.67427],"type":"Point"}
}