{
  "type": "Feature",
  "properties": {
    "gn:admin1_code":"52.0",
    "gn:admin2_code":"6007.0",
    "gn:asciiname":"Ipirigbene",
    "gn:country_code":"NG",
    "gn:dem":4,
    "gn:feature_class":"P",
    "gn:feature_code":"PPL",
    "gn:name":"Ipirigbene",
    "gn:population":0,
    "gn:timezone":"Africa/Lagos",
    "iso:country":"NG",
    "wof:name":"Ipirigbene",
    "wof:placetype":"locality"
},
  "geometry": {"coordinates":[6.15617,4.6895],"type":"Point"}
}