{
  "type": "Feature",
  "properties": {
    "gn:admin1_code":"37.0",
    "gn:admin2_code":"12006.0",
    "gn:asciiname":"Ugiogba",
    "gn:country_code":"NG",
    "gn:dem":169,
    "gn:feature_class":"P",
    "gn:feature_code":"PPL",
    "gn:name":"Ugiogba",
    "gn:population":0,
    "gn:timezone":"Africa/Lagos",
    "iso:country":"NG",
    "name:eng_x_preferred":[
        "Ujiogba"
    ],
    "name:eng_x_variant":[
        "Ugiogba",
        "Ojogba"
    ],
    "name:und_x_variant":[
        "Ojogba",
        "Ugiogba"
    ],
    "wof:name":"Ugiogba",
    "wof:placetype":"locality"
},
  "geometry": {"coordinates":[6.14699,6.53031],"type":"Point"}
}