{
  "type": "Feature",
  "properties": {
    "gn:admin1_code":"28.0",
    "gn:admin2_code":"17007.0",
    "gn:asciiname":"Amakohia",
    "gn:country_code":"NG",
    "gn:dem":168,
    "gn:feature_class":"P",
    "gn:feature_code":"PPL",
    "gn:name":"Amakohia",
    "gn:population":0,
    "gn:timezone":"Africa/Lagos",
    "iso:country":"NG",
    "wof:name":"Amakohia",
    "wof:placetype":"locality"
},
  "geometry": {"coordinates":[7.35333,5.61828],"type":"Point"}
}