{
  "type": "Feature",
  "properties": {
    "gn:admin1_code":"28.0",
    "gn:admin2_code":"17001.0",
    "gn:asciiname":"Ovoro",
    "gn:country_code":"NG",
    "gn:dem":93,
    "gn:feature_class":"P",
    "gn:feature_code":"PPL",
    "gn:name":"Ovoro",
    "gn:population":0,
    "gn:timezone":"Africa/Lagos",
    "iso:country":"NG",
    "wof:name":"Ovoro",
    "wof:placetype":"locality"
},
  "geometry": {"coordinates":[7.25484,5.38485],"type":"Point"}
}