{
  "type": "Feature",
  "properties": {
    "gn:admin1_code":"26.0",
    "gn:admin2_code":"7007.0",
    "gn:asciiname":"Orshiyo",
    "gn:country_code":"NG",
    "gn:dem":166,
    "gn:feature_class":"P",
    "gn:feature_code":"PPL",
    "gn:name":"Orshiyo",
    "gn:population":0,
    "gn:timezone":"Africa/Lagos",
    "iso:country":"NG",
    "wof:name":"Orshiyo",
    "wof:placetype":"locality"
},
  "geometry": {"coordinates":[8.53869,7.37458],"type":"Point"}
}