{
  "type": "Feature",
  "properties": {
    "gn:admin1_code":"31.0",
    "gn:admin2_code":"27007",
    "gn:asciiname":"Kaguo",
    "gn:country_code":"NG",
    "gn:dem":109,
    "gn:feature_class":"P",
    "gn:feature_code":"PPL",
    "gn:name":"Kaguo",
    "gn:population":0,
    "gn:timezone":"Africa/Lagos",
    "iso:country":"NG",
    "wof:name":"Kaguo",
    "wof:placetype":"locality"
},
  "geometry": {"coordinates":[6.0941,9.05451],"type":"Point"}
}