{
  "type": "Feature",
  "properties": {
    "gn:admin1_code":"43.0",
    "gn:admin2_code":"35003.0",
    "gn:asciiname":"Zungwe",
    "gn:country_code":"NG",
    "gn:dem":157,
    "gn:feature_class":"P",
    "gn:feature_code":"PPL",
    "gn:name":"Zungwe",
    "gn:population":0,
    "gn:timezone":"Africa/Lagos",
    "iso:country":"NG",
    "wof:name":"Zungwe",
    "wof:placetype":"locality"
},
  "geometry": {"coordinates":[10.17079,7.49064],"type":"Point"}
}