{
  "type": "Feature",
  "properties": {
    "gn:admin1_code":"35.0",
    "gn:admin2_code":"2014.0",
    "gn:asciiname":"Yaza",
    "gn:country_code":"NG",
    "gn:dem":556,
    "gn:feature_class":"P",
    "gn:feature_code":"PPL",
    "gn:name":"Yaza",
    "gn:population":0,
    "gn:timezone":"Africa/Lagos",
    "iso:country":"NG",
    "wof:name":"Yaza",
    "wof:placetype":"neighbourhood"
},
  "geometry": {"coordinates":[13.25788,10.29498],"type":"Point"}
}