{
  "type": "Feature",
  "properties": {
    "gn:admin1_code":"23.0",
    "gn:admin2_code":"19002.0",
    "gn:admin3_code":"KD0212",
    "gn:asciiname":"Romi",
    "gn:country_code":"NG",
    "gn:dem":601,
    "gn:feature_class":"P",
    "gn:feature_code":"PPL",
    "gn:name":"Romi",
    "gn:population":0,
    "gn:timezone":"Africa/Lagos",
    "iso:country":"NG",
    "name:deu_x_preferred":[
        "Romi"
    ],
    "name:fra_x_preferred":[
        "Romi"
    ],
    "name:jpn_x_preferred":[
        "Romi"
    ],
    "name:por_x_preferred":[
        "Romi"
    ],
    "name:rus_x_preferred":[
        "Romi"
    ],
    "name:slv_x_preferred":[
        "Romi"
    ],
    "wof:name":"Romi",
    "wof:placetype":"neighbourhood"
},
  "geometry": {"coordinates":[7.41821,10.43479],"type":"Point"}
}