{
  "type": "Feature",
  "properties": {
    "gn:admin1_code":"52.0",
    "gn:admin2_code":"6002.0",
    "gn:asciiname":"Egbusuware",
    "gn:country_code":"NG",
    "gn:dem":8,
    "gn:feature_class":"P",
    "gn:feature_code":"PPL",
    "gn:name":"Egbusuware",
    "gn:population":0,
    "gn:timezone":"Africa/Lagos",
    "iso:country":"NG",
    "wof:name":"Egbusuware",
    "wof:placetype":"locality"
},
  "geometry": {"coordinates":[5.86099,5.02698],"type":"Point"}
}