{
  "type": "Feature",
  "properties": {
    "gn:admin1_code":"24.0",
    "gn:admin2_code":"409.0",
    "gn:admin3_code":"40906",
    "gn:asciiname":"Metevino",
    "gn:country_code":"NG",
    "gn:dem":506,
    "gn:feature_class":"P",
    "gn:feature_code":"PPL",
    "gn:name":"Metevino",
    "gn:population":0,
    "gn:timezone":"Africa/Lagos",
    "iso:country":"NG",
    "wof:name":"Metevino",
    "wof:placetype":"locality"
},
  "geometry": {"coordinates":[7.34674,12.19339],"type":"Point"}
}