{
  "type": "Feature",
  "properties": {
    "gn:admin1_code":"23.0",
    "gn:admin2_code":"19002.0",
    "gn:admin3_code":"KD0205",
    "gn:asciiname":"Damba",
    "gn:country_code":"NG",
    "gn:dem":612,
    "gn:feature_class":"P",
    "gn:feature_code":"PPL",
    "gn:name":"Damba",
    "gn:population":0,
    "gn:timezone":"Africa/Lagos",
    "iso:country":"NG",
    "wof:name":"Damba",
    "wof:placetype":"locality"
},
  "geometry": {"coordinates":[7.20323,10.48324],"type":"Point"}
}