{
  "type": "Feature",
  "properties": {
    "gn:admin1_code":"45.0",
    "gn:admin2_code":"1016.0",
    "gn:asciiname":"Umuobiala",
    "gn:country_code":"NG",
    "gn:dem":103,
    "gn:feature_class":"P",
    "gn:feature_code":"PPL",
    "gn:name":"Umuobiala",
    "gn:population":0,
    "gn:timezone":"Africa/Lagos",
    "iso:country":"NG",
    "wof:name":"Umuobiala",
    "wof:placetype":"locality"
},
  "geometry": {"coordinates":[7.45797,5.69738],"type":"Point"}
}