{
  "type": "Feature",
  "properties": {
    "gn:admin1_code":"40.0",
    "gn:admin2_code":"503.0",
    "gn:admin3_code":"50303",
    "gn:asciiname":"Jasha Amadu",
    "gn:country_code":"NG",
    "gn:dem":248,
    "gn:feature_class":"P",
    "gn:feature_code":"PPL",
    "gn:name":"Jasha Amadu",
    "gn:population":0,
    "gn:timezone":"Africa/Lagos",
    "iso:country":"NG",
    "wof:name":"Jasha Amadu",
    "wof:placetype":"locality"
},
  "geometry": {"coordinates":[4.47666,12.64312],"type":"Point"}
}