{
  "type": "Feature",
  "properties": {
    "gn:admin1_code":"40.0",
    "gn:admin2_code":"509.0",
    "gn:admin3_code":"50901",
    "gn:asciiname":"Nasu",
    "gn:country_code":"NG",
    "gn:dem":268,
    "gn:feature_class":"P",
    "gn:feature_code":"PPL",
    "gn:name":"Nasu",
    "gn:population":0,
    "gn:timezone":"Africa/Lagos",
    "iso:country":"NG",
    "wof:name":"Nasu",
    "wof:placetype":"locality"
},
  "geometry": {"coordinates":[4.98147,11.36123],"type":"Point"}
}