{
  "type": "Feature",
  "properties": {
    "gn:admin1_code":"40.0",
    "gn:admin2_code":"509.0",
    "gn:admin3_code":"50901",
    "gn:asciiname":"Nasu",
    "gn:country_code":"NG",
    "gn:dem":268,
    "gn:feature_class":"P",
    "gn:feature_code":"PPL",
    "gn:name":"Nasu",
    "gn:population":0,
    "gn:timezone":"Africa/Lagos",
    "iso:country":"NG",
    "name:ceb_x_preferred":[
        "Nasu"
    ],
    "name:ces_x_preferred":[
        "Nasu"
    ],
    "name:deu_x_preferred":[
        "Nasu"
    ],
    "name:ita_x_preferred":[
        "Nasu"
    ],
    "name:jpn_x_preferred":[
        "\u30ca\u30b9"
    ],
    "name:nld_x_preferred":[
        "Nasu"
    ],
    "name:rus_x_preferred":[
        "\u041d\u0430\u0441\u0443"
    ],
    "name:scn_x_preferred":[
        "Nasu"
    ],
    "name:slk_x_preferred":[
        "Nasu"
    ],
    "name:ukr_x_preferred":[
        "\u041d\u0430\u0441\u0443"
    ],
    "wof:name":"Nasu",
    "wof:placetype":"locality"
},
  "geometry": {"coordinates":[4.98147,11.36123],"type":"Point"}
}