{
  "type": "Feature",
  "properties": {
    "gn:admin1_code":"35.0",
    "gn:admin2_code":"2001.0",
    "gn:asciiname":"Pongno",
    "gn:cc2":"NG",
    "gn:country_code":"NG",
    "gn:dem":336,
    "gn:feature_class":"P",
    "gn:feature_code":"PPL",
    "gn:name":"Pongno",
    "gn:population":0,
    "gn:timezone":"Africa/Lagos",
    "iso:country":"NG",
    "name:und_x_variant":[
        "Pounou",
        "Pongno"
    ],
    "wof:name":"Pongno",
    "wof:placetype":"locality"
},
  "geometry": {"coordinates":[12.23333,9.63333],"type":"Point"}
}