{
  "type": "Feature",
  "properties": {
    "gn:admin1_code":"23.0",
    "gn:admin2_code":"19003.0",
    "gn:admin3_code":"KD0306",
    "gn:asciiname":"Kakangi",
    "gn:country_code":"NG",
    "gn:dem":629,
    "gn:feature_class":"P",
    "gn:feature_code":"PPL",
    "gn:name":"Kakangi",
    "gn:population":0,
    "gn:timezone":"Africa/Lagos",
    "iso:country":"NG",
    "wof:name":"Kakangi",
    "wof:placetype":"locality"
},
  "geometry": {"coordinates":[7.455,11.15118],"type":"Point"}
}