{
  "type": "Feature",
  "properties": {
    "gn:admin1_code":"48.0",
    "gn:admin2_code":"29008.0",
    "gn:asciiname":"Ajegunle Arun",
    "gn:country_code":"NG",
    "gn:dem":191,
    "gn:feature_class":"P",
    "gn:feature_code":"PPL",
    "gn:name":"Ajegunle Arun",
    "gn:population":0,
    "gn:timezone":"Africa/Lagos",
    "iso:country":"NG",
    "wof:name":"Ajegunle Arun",
    "wof:placetype":"locality"
},
  "geometry": {"coordinates":[5.0274,7.0408],"type":"Point"}
}