{
  "type": "Feature",
  "properties": {
    "gn:admin1_code":"36.0",
    "gn:admin2_code":"10014.0",
    "gn:asciiname":"Okpanam",
    "gn:country_code":"NG",
    "gn:dem":174,
    "gn:feature_class":"P",
    "gn:feature_code":"PPL",
    "gn:name":"Okpanam",
    "gn:population":0,
    "gn:timezone":"Africa/Lagos",
    "iso:country":"NG",
    "name:eng_x_preferred":[
        "Okpanam"
    ],
    "wof:name":"Okpanam",
    "wof:placetype":"neighbourhood"
},
  "geometry": {"coordinates":[6.64743,6.23712],"type":"Point"}
}