{
  "type": "Feature",
  "properties": {
    "gn:admin1_code":"26.0",
    "gn:admin2_code":"7007.0",
    "gn:asciiname":"Ukpar",
    "gn:country_code":"NG",
    "gn:dem":175,
    "gn:feature_class":"P",
    "gn:feature_code":"PPL",
    "gn:name":"Ukpar",
    "gn:population":0,
    "gn:timezone":"Africa/Lagos",
    "iso:country":"NG",
    "name:und_x_variant":[
        "Ukpari",
        "Ukpar"
    ],
    "wof:name":"Ukpar",
    "wof:placetype":"locality"
},
  "geometry": {"coordinates":[8.1701,7.34783],"type":"Point"}
}