{
  "type": "Feature",
  "properties": {
    "gn:admin1_code":"56.0",
    "gn:admin2_code":"26001",
    "gn:asciiname":"Anchan",
    "gn:country_code":"NG",
    "gn:dem":478,
    "gn:feature_class":"P",
    "gn:feature_code":"PPL",
    "gn:name":"Anchan",
    "gn:population":0,
    "gn:timezone":"Africa/Lagos",
    "iso:country":"NG",
    "wof:name":"Anchan",
    "wof:placetype":"locality"
},
  "geometry": {"coordinates":[8.29238,9.03744],"type":"Point"}
}