{
  "type": "Feature",
  "properties": {
    "gn:admin1_code":"26.0",
    "gn:admin2_code":"7005",
    "gn:asciiname":"Gor",
    "gn:country_code":"NG",
    "gn:dem":164,
    "gn:feature_class":"P",
    "gn:feature_code":"PPL",
    "gn:name":"Gor",
    "gn:population":0,
    "gn:timezone":"Africa/Lagos",
    "iso:country":"NG",
    "name:nld_x_preferred":[
        "Gor"
    ],
    "name:ron_x_preferred":[
        "Gor"
    ],
    "name:rus_x_preferred":[
        "\u0413\u043e\u0440"
    ],
    "name:tur_x_preferred":[
        "Gor"
    ],
    "name:ukr_x_preferred":[
        "\u0413\u043e\u0440"
    ],
    "name:zho_x_preferred":[
        "Gor"
    ],
    "wof:name":"Gor",
    "wof:placetype":"locality"
},
  "geometry": {"coordinates":[8.80034,7.26571],"type":"Point"}
}