{
  "type": "Feature",
  "properties": {
    "gn:admin1_code":"57.0",
    "gn:admin2_code":"813.0",
    "gn:admin3_code":"81302",
    "gn:asciiname":"Guidan Dan Umoru",
    "gn:country_code":"NG",
    "gn:dem":521,
    "gn:feature_class":"P",
    "gn:feature_code":"PPL",
    "gn:name":"Guidan Dan Umoru",
    "gn:population":0,
    "gn:timezone":"Africa/Lagos",
    "iso:country":"NG",
    "name:und_x_variant":[
        "Gidan Dan Umoru",
        "Guidan Dan Umoru"
    ],
    "wof:name":"Guidan Dan Umoru",
    "wof:placetype":"locality"
},
  "geometry": {"coordinates":[6.94277,12.02833],"type":"Point"}
}