{
  "type": "Feature",
  "properties": {
    "gn:admin1_code":"40.0",
    "gn:admin2_code":"519.0",
    "gn:admin3_code":"51902",
    "gn:asciiname":"Zangero",
    "gn:country_code":"NG",
    "gn:dem":488,
    "gn:feature_class":"P",
    "gn:feature_code":"PPL",
    "gn:name":"Zangero",
    "gn:population":0,
    "gn:timezone":"Africa/Lagos",
    "iso:country":"NG",
    "wof:name":"Zangero",
    "wof:placetype":"locality"
},
  "geometry": {"coordinates":[6.02598,11.22679],"type":"Point"}
}