{
  "type": "Feature",
  "properties": {
    "gn:admin1_code":"35.0",
    "gn:admin2_code":"2012.0",
    "gn:asciiname":"Sebore Wuro Jiji",
    "gn:country_code":"NG",
    "gn:dem":386,
    "gn:feature_class":"P",
    "gn:feature_code":"PPL",
    "gn:name":"Sebore Wuro Jiji",
    "gn:population":0,
    "gn:timezone":"Africa/Lagos",
    "iso:country":"NG",
    "wof:name":"Sebore Wuro Jiji",
    "wof:placetype":"locality"
},
  "geometry": {"coordinates":[12.12267,8.91512],"type":"Point"}
}