{
  "type": "Feature",
  "properties": {
    "gn:admin1_code":"41.0",
    "gn:admin2_code":"23018.0",
    "gn:asciiname":"Ayangba",
    "gn:country_code":"NG",
    "gn:dem":269,
    "gn:feature_class":"P",
    "gn:feature_code":"PPL",
    "gn:name":"Ayangba",
    "gn:population":0,
    "gn:timezone":"Africa/Lagos",
    "iso:country":"NG",
    "wof:name":"Ayangba",
    "wof:placetype":"locality"
},
  "geometry": {"coordinates":[7.4538,7.13936],"type":"Point"}
}