{
  "type": "Feature",
  "properties": {
    "gn:admin1_code":"46.0",
    "gn:admin2_code":"5018.0",
    "gn:admin3_code":"BA1807",
    "gn:asciiname":"Dabbo",
    "gn:country_code":"NG",
    "gn:dem":818,
    "gn:feature_class":"P",
    "gn:feature_code":"PPL",
    "gn:name":"Dabbo",
    "gn:population":0,
    "gn:timezone":"Africa/Lagos",
    "iso:country":"NG",
    "wof:name":"Dabbo",
    "wof:placetype":"locality"
},
  "geometry": {"coordinates":[9.20642,10.25087],"type":"Point"}
}