{
  "type": "Feature",
  "properties": {
    "gn:admin1_code":"23.0",
    "gn:admin2_code":"19003.0",
    "gn:admin3_code":"KD0310",
    "gn:asciiname":"Ungwan Tsauni",
    "gn:country_code":"NG",
    "gn:dem":706,
    "gn:feature_class":"P",
    "gn:feature_code":"PPL",
    "gn:name":"Ungwan Tsauni",
    "gn:population":0,
    "gn:timezone":"Africa/Lagos",
    "iso:country":"NG",
    "name:und_x_variant":[
        "Angwan Tsauni",
        "Ungwan Tsauni"
    ],
    "wof:name":"Ungwan Tsauni",
    "wof:placetype":"locality"
},
  "geometry": {"coordinates":[7.59491,11.09637],"type":"Point"}
}