{
  "type": "Feature",
  "properties": {
    "gn:admin1_code":"47.0",
    "gn:admin2_code":"14013",
    "gn:asciiname":"Ozi-Edem",
    "gn:country_code":"NG",
    "gn:dem":394,
    "gn:feature_class":"P",
    "gn:feature_code":"PPL",
    "gn:name":"Ozi-Edem",
    "gn:population":0,
    "gn:timezone":"Africa/Lagos",
    "iso:country":"NG",
    "wof:name":"Ozi-Edem",
    "wof:placetype":"locality"
},
  "geometry": {"coordinates":[7.33263,6.86275],"type":"Point"}
}