{
  "type": "Feature",
  "properties": {
    "gn:admin1_code":"27.0",
    "gn:admin2_code":"101.0",
    "gn:admin3_code":"10101",
    "gn:asciiname":"Mitile",
    "gn:country_code":"NG",
    "gn:dem":289,
    "gn:feature_class":"P",
    "gn:feature_code":"PPL",
    "gn:name":"Mitile",
    "gn:population":0,
    "gn:timezone":"Africa/Lagos",
    "iso:country":"NG",
    "name:und_x_variant":[
        "Metele"
    ],
    "wof:name":"Mitile",
    "wof:placetype":"locality"
},
  "geometry": {"coordinates":[13.42618,13.35765],"type":"Point"}
}