{
  "type": "Feature",
  "properties": {
    "gn:admin1_code":"37.0",
    "gn:admin2_code":"12011.0",
    "gn:asciiname":"Ogua",
    "gn:country_code":"NG",
    "gn:dem":58,
    "gn:feature_class":"P",
    "gn:feature_code":"PPL",
    "gn:name":"Ogua",
    "gn:population":0,
    "gn:timezone":"Africa/Lagos",
    "iso:country":"NG",
    "wof:name":"Ogua",
    "wof:placetype":"locality"
},
  "geometry": {"coordinates":[5.68464,6.25474],"type":"Point"}
}