{
  "type": "Feature",
  "properties": {
    "gn:admin1_code":"51.0",
    "gn:admin2_code":"606.0",
    "gn:admin3_code":"60603",
    "gn:asciiname":"Balle",
    "gn:country_code":"NG",
    "gn:dem":240,
    "gn:feature_class":"P",
    "gn:feature_code":"PPLA2",
    "gn:name":"Balle",
    "gn:population":0,
    "gn:timezone":"Africa/Lagos",
    "iso:country":"NG",
    "name:ceb_x_preferred":[
        "Balle"
    ],
    "name:dan_x_preferred":[
        "Balle"
    ],
    "name:deu_x_preferred":[
        "Balle"
    ],
    "name:fra_x_preferred":[
        "Balle"
    ],
    "name:hye_x_preferred":[
        "\u0532\u0561\u056c"
    ],
    "name:ind_x_preferred":[
        "Balle"
    ],
    "name:nld_x_preferred":[
        "Balle"
    ],
    "name:nrm_x_preferred":[
        "Balle"
    ],
    "name:por_x_preferred":[
        "Balle"
    ],
    "name:swe_x_preferred":[
        "Balle"
    ],
    "name:und_x_variant":[
        "Bale",
        "Balle"
    ],
    "wof:name":"Balle",
    "wof:placetype":"locality"
},
  "geometry": {"coordinates":[4.68119,13.47029],"type":"Point"}
}