{
  "type": "Feature",
  "properties": {
    "gn:admin1_code":"36.0",
    "gn:admin2_code":"10019.0",
    "gn:asciiname":"Okoh Unoh",
    "gn:country_code":"NG",
    "gn:dem":22,
    "gn:feature_class":"P",
    "gn:feature_code":"PPL",
    "gn:name":"Okoh Unoh",
    "gn:population":0,
    "gn:timezone":"Africa/Lagos",
    "iso:country":"NG",
    "wof:name":"Okoh Unoh",
    "wof:placetype":"locality"
},
  "geometry": {"coordinates":[6.04138,5.732],"type":"Point"}
}