{
  "type": "Feature",
  "properties": {
    "gn:admin1_code":"39.0",
    "gn:admin2_code":"18025.0",
    "gn:admin3_code":"JI1907",
    "gn:asciiname":"Bakin Kanake",
    "gn:country_code":"NG",
    "gn:dem":390,
    "gn:feature_class":"P",
    "gn:feature_code":"PPL",
    "gn:name":"Bakin Kanake",
    "gn:population":0,
    "gn:timezone":"Africa/Lagos",
    "iso:country":"NG",
    "wof:name":"Bakin Kanake",
    "wof:placetype":"locality"
},
  "geometry": {"coordinates":[9.61972,11.80819],"type":"Point"}
}