{
  "type": "Feature",
  "properties": {
    "gn:admin1_code":"27.0",
    "gn:admin2_code":"101",
    "gn:admin3_code":"10102",
    "gn:asciiname":"Goniri",
    "gn:country_code":"NG",
    "gn:dem":294,
    "gn:feature_class":"P",
    "gn:feature_code":"PPL",
    "gn:name":"Goniri",
    "gn:population":0,
    "gn:timezone":"Africa/Lagos",
    "iso:country":"NG",
    "wof:name":"Goniri",
    "wof:placetype":"locality"
},
  "geometry": {"coordinates":[13.26238,13.05728],"type":"Point"}
}