{
  "type": "Feature",
  "properties": {
    "gn:admin1_code":"35.0",
    "gn:admin2_code":"2008.0",
    "gn:asciiname":"Pechar",
    "gn:country_code":"NG",
    "gn:dem":295,
    "gn:feature_class":"P",
    "gn:feature_code":"PPL",
    "gn:name":"Pechar",
    "gn:population":0,
    "gn:timezone":"Africa/Lagos",
    "iso:country":"NG",
    "name:und_x_variant":[
        "Bangafini",
        "Pechar"
    ],
    "wof:name":"Pechar",
    "wof:placetype":"locality"
},
  "geometry": {"coordinates":[12.32093,8.80845],"type":"Point"}
}