{
  "type": "Feature",
  "properties": {
    "gn:admin1_code":"29.0",
    "gn:admin2_code":"20034.0",
    "gn:admin3_code":"KN2401",
    "gn:asciiname":"Wada",
    "gn:country_code":"NG",
    "gn:dem":521,
    "gn:feature_class":"P",
    "gn:feature_code":"PPL",
    "gn:name":"Wada",
    "gn:population":0,
    "gn:timezone":"Africa/Lagos",
    "iso:country":"NG",
    "wof:name":"Wada",
    "wof:placetype":"locality"
},
  "geometry": {"coordinates":[8.0017,11.67739],"type":"Point"}
}