{
  "type": "Feature",
  "properties": {
    "gn:admin1_code":"35.0",
    "gn:admin2_code":"2020.0",
    "gn:asciiname":"Didango",
    "gn:country_code":"NG",
    "gn:dem":223,
    "gn:feature_class":"P",
    "gn:feature_code":"PPL",
    "gn:name":"Didango",
    "gn:population":0,
    "gn:timezone":"Africa/Lagos",
    "iso:country":"NG",
    "name:eng_x_preferred":[
        "Didango"
    ],
    "wof:name":"Didango",
    "wof:placetype":"locality"
},
  "geometry": {"coordinates":[12.48126,9.11027],"type":"Point"}
}