{
  "type": "Feature",
  "properties": {
    "gn:admin1_code":"23.0",
    "gn:admin2_code":"19001.0",
    "gn:admin3_code":"KD0103",
    "gn:asciiname":"Tungan Rafin Taba",
    "gn:country_code":"NG",
    "gn:dem":574,
    "gn:feature_class":"P",
    "gn:feature_code":"PPL",
    "gn:name":"Tungan Rafin Taba",
    "gn:population":0,
    "gn:timezone":"Africa/Lagos",
    "iso:country":"NG",
    "wof:name":"Tungan Rafin Taba",
    "wof:placetype":"locality"
},
  "geometry": {"coordinates":[6.71667,10.71667],"type":"Point"}
}