{
  "type": "Feature",
  "properties": {
    "gn:admin1_code":"35.0",
    "gn:admin2_code":"2011.0",
    "gn:asciiname":"Wurawura",
    "gn:country_code":"NG",
    "gn:dem":582,
    "gn:feature_class":"P",
    "gn:feature_code":"PPL",
    "gn:name":"Wurawura",
    "gn:population":0,
    "gn:timezone":"Africa/Lagos",
    "iso:country":"NG",
    "wof:name":"Wurawura",
    "wof:placetype":"locality"
},
  "geometry": {"coordinates":[13.19718,10.05543],"type":"Point"}
}