{
  "type": "Feature",
  "properties": {
    "gn:admin1_code":"35.0",
    "gn:admin2_code":"2011.0",
    "gn:asciiname":"Wuro Kawu",
    "gn:country_code":"NG",
    "gn:dem":506,
    "gn:feature_class":"P",
    "gn:feature_code":"PPL",
    "gn:name":"Wuro Kawu",
    "gn:population":0,
    "gn:timezone":"Africa/Lagos",
    "iso:country":"NG",
    "name:und_x_variant":[
        "Kawu",
        "Wuro Kawu"
    ],
    "wof:name":"Wuro Kawu",
    "wof:placetype":"locality"
},
  "geometry": {"coordinates":[13.13083,10.0576],"type":"Point"}
}