{
  "type": "Feature",
  "properties": {
    "gn:admin1_code":"29.0",
    "gn:asciiname":"Mundu",
    "gn:country_code":"NG",
    "gn:dem":405,
    "gn:feature_class":"P",
    "gn:feature_code":"PPL",
    "gn:name":"Mundu",
    "gn:population":0,
    "gn:timezone":"Africa/Lagos",
    "iso:country":"NG",
    "name:fra_x_preferred":[
        "Mundu"
    ],
    "name:mal_x_preferred":[
        "\u0d2e\u0d41\u0d23\u0d4d\u0d1f\u0d4d"
    ],
    "name:pol_x_preferred":[
        "Mundu"
    ],
    "wof:name":"Mundu",
    "wof:placetype":"locality"
},
  "geometry": {"coordinates":[8.71298,12.51339],"type":"Point"}
}