{
  "type": "Feature",
  "properties": {
    "gn:admin1_code":"27.0",
    "gn:admin2_code":"122.0",
    "gn:admin3_code":"12210",
    "gn:asciiname":"Dimmerwa",
    "gn:country_code":"NG",
    "gn:dem":306,
    "gn:feature_class":"P",
    "gn:feature_code":"PPL",
    "gn:name":"Dimmerwa",
    "gn:population":0,
    "gn:timezone":"Africa/Lagos",
    "iso:country":"NG",
    "wof:name":"Dimmerwa",
    "wof:placetype":"locality"
},
  "geometry": {"coordinates":[12.72102,13.14173],"type":"Point"}
}