{
  "type": "Feature",
  "properties": {
    "gn:admin1_code":"57.0",
    "gn:admin2_code":"807.0",
    "gn:admin3_code":"80711",
    "gn:asciiname":"Rafi",
    "gn:country_code":"NG",
    "gn:dem":465,
    "gn:feature_class":"P",
    "gn:feature_code":"PPL",
    "gn:name":"Rafi",
    "gn:population":0,
    "gn:timezone":"Africa/Lagos",
    "iso:country":"NG",
    "wof:name":"Rafi",
    "wof:placetype":"locality"
},
  "geometry": {"coordinates":[7.01389,12.21761],"type":"Point"}
}