{
  "type": "Feature",
  "properties": {
    "gn:admin1_code":"57.0",
    "gn:admin2_code":"807.0",
    "gn:admin3_code":"80711",
    "gn:asciiname":"Rafi",
    "gn:country_code":"NG",
    "gn:dem":465,
    "gn:feature_class":"P",
    "gn:feature_code":"PPL",
    "gn:name":"Rafi",
    "gn:population":0,
    "gn:timezone":"Africa/Lagos",
    "iso:country":"NG",
    "name:aze_x_preferred":[
        "R\u0259fi"
    ],
    "name:ceb_x_preferred":[
        "Rafi"
    ],
    "name:deu_x_preferred":[
        "Rafi"
    ],
    "name:fra_x_preferred":[
        "Rafi"
    ],
    "name:ita_x_preferred":[
        "Rafi"
    ],
    "name:pol_x_preferred":[
        "Rafi"
    ],
    "name:rus_x_preferred":[
        "\u0420\u0430\u0444\u0438"
    ],
    "name:ukr_x_preferred":[
        "\u0420\u0430\u0444\u0456"
    ],
    "wof:name":"Rafi",
    "wof:placetype":"locality"
},
  "geometry": {"coordinates":[7.01389,12.21761],"type":"Point"}
}