{
  "type": "Feature",
  "properties": {
    "gn:admin1_code":"39.0",
    "gn:admin2_code":"18009.0",
    "gn:admin3_code":"JI1206",
    "gn:asciiname":"Dadin Sarki",
    "gn:country_code":"NG",
    "gn:dem":474,
    "gn:feature_class":"P",
    "gn:feature_code":"PPL",
    "gn:name":"Dadin Sarki",
    "gn:population":0,
    "gn:timezone":"Africa/Lagos",
    "iso:country":"NG",
    "wof:name":"Dadin Sarki",
    "wof:placetype":"locality"
},
  "geometry": {"coordinates":[8.31447,12.77703],"type":"Point"}
}