{
  "type": "Feature",
  "properties": {
    "gn:admin1_code":"26.0",
    "gn:admin2_code":"7010",
    "gn:asciiname":"Akna",
    "gn:country_code":"NG",
    "gn:dem":164,
    "gn:feature_class":"P",
    "gn:feature_code":"PPL",
    "gn:name":"Akna",
    "gn:population":0,
    "gn:timezone":"Africa/Lagos",
    "iso:country":"NG",
    "name:hun_x_preferred":[
        "Akna"
    ],
    "name:hye_x_preferred":[
        "\u0531\u056f\u0576\u0561"
    ],
    "name:nld_x_preferred":[
        "Akna"
    ],
    "name:rus_x_preferred":[
        "\u0410\u043a\u043d\u0430"
    ],
    "name:tur_x_preferred":[
        "Akna"
    ],
    "wof:name":"Akna",
    "wof:placetype":"locality"
},
  "geometry": {"coordinates":[8.49459,7.08164],"type":"Point"}
}