{
  "type": "Feature",
  "properties": {
    "gn:admin1_code":"26.0",
    "gn:admin2_code":"7010.0",
    "gn:asciiname":"Tse-Agberagba",
    "gn:country_code":"NG",
    "gn:dem":110,
    "gn:feature_class":"P",
    "gn:feature_code":"PPLA2",
    "gn:name":"Tse-Agberagba",
    "gn:population":0,
    "gn:timezone":"Africa/Lagos",
    "iso:country":"NG",
    "name:und_x_variant":[
        "Agbelagba",
        "Ise Agberagba"
    ],
    "wof:name":"Tse-Agberagba",
    "wof:placetype":"locality"
},
  "geometry": {"coordinates":[8.66551,7.07668],"type":"Point"}
}