{
  "type": "Feature",
  "properties": {
    "gn:admin1_code":"26.0",
    "gn:admin2_code":"7022.0",
    "gn:asciiname":"Haanongun",
    "gn:country_code":"NG",
    "gn:dem":123,
    "gn:feature_class":"P",
    "gn:feature_code":"PPL",
    "gn:name":"Haanongun",
    "gn:population":0,
    "gn:timezone":"Africa/Lagos",
    "iso:country":"NG",
    "wof:name":"Haanongun",
    "wof:placetype":"locality"
},
  "geometry": {"coordinates":[8.85807,7.09132],"type":"Point"}
}