{
  "type": "Feature",
  "properties": {
    "gn:admin1_code":"26.0",
    "gn:admin2_code":"7009",
    "gn:asciiname":"Akerchigh",
    "gn:country_code":"NG",
    "gn:dem":226,
    "gn:feature_class":"P",
    "gn:feature_code":"PPL",
    "gn:name":"Akerchigh",
    "gn:population":0,
    "gn:timezone":"Africa/Lagos",
    "iso:country":"NG",
    "wof:name":"Akerchigh",
    "wof:placetype":"locality"
},
  "geometry": {"coordinates":[9.76648,7.55335],"type":"Point"}
}