{
  "type": "Feature",
  "properties": {
    "gn:admin1_code":"43.0",
    "gn:admin2_code":"35011.0",
    "gn:asciiname":"Tamnyar",
    "gn:cc2":"NG",
    "gn:country_code":"NG",
    "gn:dem":1714,
    "gn:feature_class":"P",
    "gn:feature_code":"PPL",
    "gn:name":"Tamnyar",
    "gn:population":0,
    "gn:timezone":"Africa/Lagos",
    "iso:country":"NG",
    "name:und_x_variant":[
        "Tamian",
        "Tamnyar"
    ],
    "wof:name":"Tamnyar",
    "wof:placetype":"locality"
},
  "geometry": {"coordinates":[11.23333,6.53333],"type":"Point"}
}