{
  "type": "Feature",
  "properties": {
    "gn:admin1_code":"46.0",
    "gn:admin2_code":"5005.0",
    "gn:admin3_code":"BA0501",
    "gn:asciiname":"Rampa",
    "gn:country_code":"NG",
    "gn:dem":484,
    "gn:feature_class":"P",
    "gn:feature_code":"PPL",
    "gn:name":"Rampa",
    "gn:population":0,
    "gn:timezone":"Africa/Lagos",
    "iso:country":"NG",
    "name:cat_x_preferred":[
        "Rampa"
    ],
    "name:ces_x_preferred":[
        "Rampa"
    ],
    "name:deu_x_preferred":[
        "Rampa"
    ],
    "name:kaz_x_preferred":[
        "\u0420\u0430\u043c\u043f\u0430"
    ],
    "name:pol_x_preferred":[
        "Rampa"
    ],
    "name:por_x_preferred":[
        "Rampa"
    ],
    "name:rus_x_preferred":[
        "\u0420\u0430\u043c\u043f\u0430"
    ],
    "name:srp_x_preferred":[
        "Rampa"
    ],
    "name:ukr_x_preferred":[
        "\u0420\u0430\u043c\u043f\u0430"
    ],
    "wof:name":"Rampa",
    "wof:placetype":"locality"
},
  "geometry": {"coordinates":[10.4113,11.0283],"type":"Point"}
}