{
  "type": "Feature",
  "properties": {
    "gn:admin1_code":"49.0",
    "gn:asciiname":"Loond",
    "gn:country_code":"NG",
    "gn:dem":335,
    "gn:feature_class":"P",
    "gn:feature_code":"PPL",
    "gn:name":"Loond",
    "gn:population":0,
    "gn:timezone":"Africa/Lagos",
    "iso:country":"NG",
    "wof:name":"Loond",
    "wof:placetype":"locality"
},
  "geometry": {"coordinates":[9.09174,8.98003],"type":"Point"}
}