{
  "type": "Feature",
  "properties": {
    "gn:admin1_code":"29.0",
    "gn:admin2_code":"20011.0",
    "gn:admin3_code":"KN3610",
    "gn:asciiname":"Dorawa",
    "gn:country_code":"NG",
    "gn:dem":592,
    "gn:feature_class":"P",
    "gn:feature_code":"PPL",
    "gn:name":"Dorawa",
    "gn:population":0,
    "gn:timezone":"Africa/Lagos",
    "iso:country":"NG",
    "wof:name":"Dorawa",
    "wof:placetype":"locality"
},
  "geometry": {"coordinates":[8.8061,11.27596],"type":"Point"}
}