{
  "type": "Feature",
  "properties": {
    "gn:admin1_code":"42.0",
    "gn:admin2_code":"30009.0",
    "gn:asciiname":"Ekuro",
    "gn:cc2":"NG",
    "gn:country_code":"NG",
    "gn:dem":280,
    "gn:feature_class":"P",
    "gn:feature_code":"PPL",
    "gn:name":"Ekuro",
    "gn:population":0,
    "gn:timezone":"Africa/Lagos",
    "iso:country":"NG",
    "name:und_x_variant":[
        "Ekuraw",
        "Ekuro"
    ],
    "wof:name":"Ekuro",
    "wof:placetype":"locality"
},
  "geometry": {"coordinates":[4.36667,7.73333],"type":"Point"}
}