{
  "type": "Feature",
  "properties": {
    "gn:admin1_code":"36.0",
    "gn:admin2_code":"10018.0",
    "gn:asciiname":"Igbogidi",
    "gn:country_code":"NG",
    "gn:dem":13,
    "gn:feature_class":"P",
    "gn:feature_code":"PPL",
    "gn:name":"Igbogidi",
    "gn:population":0,
    "gn:timezone":"Africa/Lagos",
    "iso:country":"NG",
    "name:eng_x_preferred":[
        "Igbogidi"
    ],
    "wof:name":"Igbogidi",
    "wof:placetype":"locality"
},
  "geometry": {"coordinates":[5.81985,5.51157],"type":"Point"}
}