{
  "type": "Feature",
  "properties": {
    "gn:admin1_code":"36.0",
    "gn:admin2_code":"10005.0",
    "gn:asciiname":"Okoh Ekrudu",
    "gn:country_code":"NG",
    "gn:dem":18,
    "gn:feature_class":"P",
    "gn:feature_code":"PPL",
    "gn:name":"Okoh Ekrudu",
    "gn:population":0,
    "gn:timezone":"Africa/Lagos",
    "iso:country":"NG",
    "wof:name":"Okoh Ekrudu",
    "wof:placetype":"locality"
},
  "geometry": {"coordinates":[6.01998,5.70786],"type":"Point"}
}