{
  "type": "Feature",
  "properties": {
    "gn:admin1_code":"27.0",
    "gn:admin2_code":"119.0",
    "gn:admin3_code":"11908",
    "gn:asciiname":"Anzamala",
    "gn:country_code":"NG",
    "gn:dem":299,
    "gn:feature_class":"P",
    "gn:feature_code":"PPL",
    "gn:name":"Anzamala",
    "gn:population":0,
    "gn:timezone":"Africa/Lagos",
    "iso:country":"NG",
    "wof:name":"Anzamala",
    "wof:placetype":"locality"
},
  "geometry": {"coordinates":[13.58041,12.09237],"type":"Point"}
}