{
  "type": "Feature",
  "properties": {
    "gn:admin1_code":"51.0",
    "gn:admin2_code":"618.0",
    "gn:admin3_code":"61810",
    "gn:asciiname":"Sainyinan Daji",
    "gn:country_code":"NG",
    "gn:dem":254,
    "gn:feature_class":"P",
    "gn:feature_code":"PPL",
    "gn:name":"Sainyinan Daji",
    "gn:population":0,
    "gn:timezone":"Africa/Lagos",
    "iso:country":"NG",
    "name:und_x_variant":[
        "Sainyman Daji",
        "Sainyinan Daji"
    ],
    "wof:name":"Sainyinan Daji",
    "wof:placetype":"locality"
},
  "geometry": {"coordinates":[4.86037,12.70153],"type":"Point"}
}