{
  "type": "Feature",
  "properties": {
    "gn:admin1_code":"43.0",
    "gn:admin2_code":"35012",
    "gn:asciiname":"Tor",
    "gn:country_code":"NG",
    "gn:dem":163,
    "gn:feature_class":"P",
    "gn:feature_code":"PPL",
    "gn:name":"Tor",
    "gn:population":0,
    "gn:timezone":"Africa/Lagos",
    "iso:country":"NG",
    "wof:name":"Tor",
    "wof:placetype":"locality"
},
  "geometry": {"coordinates":[9.94338,7.50476],"type":"Point"}
}