{
  "type": "Feature",
  "properties": {
    "gn:admin1_code":"32.0",
    "gn:admin2_code":"31003.0",
    "gn:asciiname":"Akodu",
    "gn:country_code":"NG",
    "gn:dem":291,
    "gn:feature_class":"P",
    "gn:feature_code":"PPL",
    "gn:name":"Akodu",
    "gn:population":0,
    "gn:timezone":"Africa/Lagos",
    "iso:country":"NG",
    "wof:name":"Akodu",
    "wof:placetype":"locality"
},
  "geometry": {"coordinates":[3.98333,8.06667],"type":"Point"}
}