{
  "type": "Feature",
  "properties": {
    "gn:admin1_code":"43.0",
    "gn:admin2_code":"35003.0",
    "gn:asciiname":"Damsa",
    "gn:country_code":"NG",
    "gn:dem":132,
    "gn:feature_class":"P",
    "gn:feature_code":"PPL",
    "gn:name":"Damsa",
    "gn:population":0,
    "gn:timezone":"Africa/Lagos",
    "iso:country":"NG",
    "name:und_x_variant":[
        "Damisa"
    ],
    "wof:name":"Damsa",
    "wof:placetype":"locality"
},
  "geometry": {"coordinates":[9.96021,7.71647],"type":"Point"}
}