{
  "type": "Feature",
  "properties": {
    "gn:admin1_code":"44.0",
    "gn:admin2_code":"716.0",
    "gn:admin3_code":"71602",
    "gn:asciiname":"Nganawa",
    "gn:country_code":"NG",
    "gn:dem":333,
    "gn:feature_class":"P",
    "gn:feature_code":"PPL",
    "gn:name":"Nganawa",
    "gn:population":0,
    "gn:timezone":"Africa/Lagos",
    "iso:country":"NG",
    "wof:name":"Nganawa",
    "wof:placetype":"locality"
},
  "geometry": {"coordinates":[11.80723,13.2179],"type":"Point"}
}