{
  "type": "Feature",
  "properties": {
    "gn:admin1_code":"21.0",
    "gn:admin2_code":"3014.0",
    "gn:asciiname":"Abiakpo",
    "gn:country_code":"NG",
    "gn:dem":62,
    "gn:feature_class":"P",
    "gn:feature_code":"PPL",
    "gn:name":"Abiakpo",
    "gn:population":0,
    "gn:timezone":"Africa/Lagos",
    "iso:country":"NG",
    "wof:name":"Abiakpo",
    "wof:placetype":"locality"
},
  "geometry": {"coordinates":[7.6685,5.1603],"type":"Point"}
}