{
  "type": "Feature",
  "properties": {
    "gn:admin1_code":"22.0",
    "gn:admin2_code":"9018.0",
    "gn:asciiname":"Imaje",
    "gn:country_code":"NG",
    "gn:dem":111,
    "gn:feature_class":"P",
    "gn:feature_code":"PPL",
    "gn:name":"Imaje",
    "gn:population":0,
    "gn:timezone":"Africa/Lagos",
    "iso:country":"NG",
    "name:und_x_variant":[
        "Umuaja"
    ],
    "wof:name":"Imaje",
    "wof:placetype":"locality"
},
  "geometry": {"coordinates":[8.82181,6.72739],"type":"Point"}
}