{
  "type": "Feature",
  "properties": {
    "gn:admin1_code":"52.0",
    "gn:asciiname":"Maghogbene",
    "gn:country_code":"NG",
    "gn:dem":6,
    "gn:feature_class":"P",
    "gn:feature_code":"PPL",
    "gn:name":"Maghogbene",
    "gn:population":0,
    "gn:timezone":"Africa/Lagos",
    "iso:country":"NG",
    "name:eng_x_preferred":[
        "Maghogbene"
    ],
    "wof:name":"Maghogbene",
    "wof:placetype":"locality"
},
  "geometry": {"coordinates":[5.76875,4.76877],"type":"Point"}
}