{
  "type": "Feature",
  "properties": {
    "gn:admin1_code":"55.0",
    "gn:asciiname":"Wuro Bunga",
    "gn:country_code":"NG",
    "gn:dem":404,
    "gn:feature_class":"P",
    "gn:feature_code":"PPL",
    "gn:name":"Wuro Bunga",
    "gn:population":0,
    "gn:timezone":"Africa/Lagos",
    "iso:country":"NG",
    "name:eng_x_preferred":[
        "Wuro Bunga"
    ],
    "wof:name":"Wuro Bunga",
    "wof:placetype":"locality"
},
  "geometry": {"coordinates":[10.7353,10.43023],"type":"Point"}
}