{
  "type": "Feature",
  "properties": {
    "gn:admin1_code":"41.0",
    "gn:admin2_code":"23019.0",
    "gn:asciiname":"Agbada",
    "gn:country_code":"NG",
    "gn:dem":221,
    "gn:feature_class":"P",
    "gn:feature_code":"PPL",
    "gn:name":"Agbada",
    "gn:population":0,
    "gn:timezone":"Africa/Lagos",
    "iso:country":"NG",
    "name:deu_x_preferred":[
        "Boubou"
    ],
    "name:fra_x_preferred":[
        "Boubou"
    ],
    "name:kaz_x_preferred":[
        "\u0411\u043e\u0443\u0431\u043e\u0443"
    ],
    "name:pol_x_preferred":[
        "Boubou"
    ],
    "name:urd_x_preferred":[
        "\u0628\u0648\u0628\u0648"
    ],
    "name:yor_x_preferred":[
        "Agb\u00e1d\u00e1"
    ],
    "wof:name":"Agbada",
    "wof:placetype":"locality"
},
  "geometry": {"coordinates":[7.42769,7.80771],"type":"Point"}
}