{
  "type": "Feature",
  "properties": {
    "gn:admin1_code":"22.0",
    "gn:admin2_code":"9007.0",
    "gn:asciiname":"Bamba",
    "gn:country_code":"NG",
    "gn:dem":162,
    "gn:feature_class":"P",
    "gn:feature_code":"PPL",
    "gn:name":"Bamba",
    "gn:population":0,
    "gn:timezone":"Africa/Lagos",
    "iso:country":"NG",
    "wof:name":"Bamba",
    "wof:placetype":"locality"
},
  "geometry": {"coordinates":[9.1142,6.2901],"type":"Point"}
}