{
  "type": "Feature",
  "properties": {
    "gn:admin1_code":"26.0",
    "gn:admin2_code":"7016",
    "gn:asciiname":"Okete-Ipikwu",
    "gn:country_code":"NG",
    "gn:dem":152,
    "gn:feature_class":"P",
    "gn:feature_code":"PPL",
    "gn:name":"Okete-Ipikwu",
    "gn:population":0,
    "gn:timezone":"Africa/Lagos",
    "iso:country":"NG",
    "wof:name":"Okete-Ipikwu",
    "wof:placetype":"locality"
},
  "geometry": {"coordinates":[8.09255,7.23491],"type":"Point"}
}