{
  "type": "Feature",
  "properties": {
    "gn:admin1_code":"24.0",
    "gn:asciiname":"Ungwan Wabi",
    "gn:country_code":"NG",
    "gn:dem":550,
    "gn:feature_class":"P",
    "gn:feature_code":"PPL",
    "gn:name":"Ungwan Wabi",
    "gn:population":0,
    "gn:timezone":"Africa/Lagos",
    "iso:country":"NG",
    "wof:name":"Ungwan Wabi",
    "wof:placetype":"locality"
},
  "geometry": {"coordinates":[7.87139,11.62473],"type":"Point"}
}