{
  "type": "Feature",
  "properties": {
    "gn:admin1_code":"56.0",
    "gn:admin2_code":"26003.0",
    "gn:asciiname":"Dyege",
    "gn:country_code":"NG",
    "gn:dem":108,
    "gn:feature_class":"P",
    "gn:feature_code":"PPL",
    "gn:name":"Dyege",
    "gn:population":0,
    "gn:timezone":"Africa/Lagos",
    "iso:country":"NG",
    "wof:name":"Dyege",
    "wof:placetype":"locality"
},
  "geometry": {"coordinates":[8.20569,7.96652],"type":"Point"}
}