{
  "type": "Feature",
  "properties": {
    "gn:admin1_code":"21.0",
    "gn:admin2_code":"3015.0",
    "gn:asciiname":"Ikot-Offiong",
    "gn:country_code":"NG",
    "gn:dem":122,
    "gn:feature_class":"P",
    "gn:feature_code":"PPL",
    "gn:name":"Ikot-Offiong",
    "gn:population":0,
    "gn:timezone":"Africa/Lagos",
    "iso:country":"NG",
    "wof:name":"Ikot-Offiong",
    "wof:placetype":"locality"
},
  "geometry": {"coordinates":[7.65692,5.40928],"type":"Point"}
}