{
  "type": "Feature",
  "properties": {
    "gn:admin1_code":"27.0",
    "gn:admin2_code":"106.0",
    "gn:admin3_code":"10602",
    "gn:asciiname":"Mbalala Nkyaki",
    "gn:country_code":"NG",
    "gn:dem":474,
    "gn:feature_class":"P",
    "gn:feature_code":"PPL",
    "gn:name":"Mbalala Nkyaki",
    "gn:population":0,
    "gn:timezone":"Africa/Lagos",
    "iso:country":"NG",
    "wof:name":"Mbalala Nkyaki",
    "wof:placetype":"locality"
},
  "geometry": {"coordinates":[12.90883,10.75485],"type":"Point"}
}