{
  "type": "Feature",
  "properties": {
    "gn:admin1_code":"57.0",
    "gn:admin2_code":"813.0",
    "gn:admin3_code":"81309",
    "gn:asciiname":"Nassarawa",
    "gn:country_code":"NG",
    "gn:dem":525,
    "gn:feature_class":"P",
    "gn:feature_code":"PPL",
    "gn:name":"Nassarawa",
    "gn:population":0,
    "gn:timezone":"Africa/Lagos",
    "iso:country":"NG",
    "wof:name":"Nassarawa",
    "wof:placetype":"locality"
},
  "geometry": {"coordinates":[7.07844,11.95569],"type":"Point"}
}