{
  "type": "Feature",
  "properties": {
    "gn:admin1_code":"30.0",
    "gn:admin2_code":"24012.0",
    "gn:asciiname":"Adijale",
    "gn:country_code":"NG",
    "gn:dem":323,
    "gn:feature_class":"P",
    "gn:feature_code":"PPL",
    "gn:name":"Adijale",
    "gn:population":0,
    "gn:timezone":"Africa/Lagos",
    "iso:country":"NG",
    "wof:name":"Adijale",
    "wof:placetype":"locality"
},
  "geometry": {"coordinates":[4.28333,8.75],"type":"Point"}
}