{
  "type": "Feature",
  "properties": {
    "gn:admin1_code":"43.0",
    "gn:admin2_code":"35009.0",
    "gn:asciiname":"Adobe",
    "gn:country_code":"NG",
    "gn:dem":277,
    "gn:feature_class":"P",
    "gn:feature_code":"PPL",
    "gn:name":"Adobe",
    "gn:population":0,
    "gn:timezone":"Africa/Lagos",
    "iso:country":"NG",
    "name:ara_x_preferred":[
        "\u0637\u0648\u0628"
    ],
    "name:arg_x_preferred":[
        "Adoba"
    ],
    "name:ast_x_preferred":[
        "Adobe"
    ],
    "name:aym_x_preferred":[
        "Tika"
    ],
    "name:bel_x_preferred":[
        "\u0421\u0430\u043c\u0430\u043d"
    ],
    "name:bul_x_preferred":[
        "\u041a\u0438\u0440\u043f\u0438\u0447"
    ],
    "name:cat_x_preferred":[
        "Tova"
    ],
    "name:ces_x_preferred":[
        "Vep\u0159ovice"
    ],
    "name:chv_x_preferred":[
        "\u0421\u0430\u043c\u0430\u043d"
    ],
    "name:dan_x_preferred":[
        "Adobe"
    ],
    "name:deu_x_preferred":[
        "Lehmziegel"
    ],
    "name:epo_x_preferred":[
        "Adobo"
    ],
    "name:est_x_preferred":[
        "Mudatellis"
    ],
    "name:eus_x_preferred":[
        "Adobe"
    ],
    "name:fas_x_preferred":[
        "\u062e\u0634\u062a"
    ],
    "name:fin_x_preferred":[
        "Savitiili"
    ],
    "name:fra_x_preferred":[
        "Adobe"
    ],
    "name:glg_x_preferred":[
        "Adobe"
    ],
    "name:hin_x_preferred":[
        "\u090f\u0921\u094b\u092c\u0947"
    ],
    "name:hrv_x_preferred":[
        "\u0106erpi\u010d"
    ],
    "name:hun_x_preferred":[
        "V\u00e1lyog\u00e9p\u00edtkez\u00e9s"
    ],
    "name:ido_x_preferred":[
        "Adobo"
    ],
    "name:ind_x_preferred":[
        "Bata jemuran"
    ],
    "name:ita_x_preferred":[
        "Adobe"
    ],
    "name:jpn_x_preferred":[
        "\u30a2\u30c9\u30d9"
    ],
    "name:kat_x_preferred":[
        "\u10d0\u10da\u10d8\u10d6\u10d8"
    ],
    "name:kaz_x_preferred":[
        "\u0421\u0430\u043c\u0430\u043d"
    ],
    "name:kor_x_preferred":[
        "\uc5b4\ub3c4\ube44"
    ],
    "name:lat_x_preferred":[
        "Later crudus"
    ],
    "name:mal_x_preferred":[
        "\u0d05\u0d21\u0d4b\u0d2c\u0d3f"
    ],
    "name:mkd_x_preferred":[
        "\u040c\u0435\u0440\u043f\u0438\u0447"
    ],
    "name:nah_x_preferred":[
        "Xamitl"
    ],
    "name:nld_x_preferred":[
        "Adobe"
    ],
    "name:nor_x_preferred":[
        "Adobe"
    ],
    "name:pol_x_preferred":[
        "Ceg\u0142a suszona"
    ],
    "name:por_x_preferred":[
        "Adobe"
    ],
    "name:que_x_preferred":[
        "Tika"
    ],
    "name:ron_x_preferred":[
        "Chirpici"
    ],
    "name:rus_x_preferred":[
        "\u0421\u0430\u043c\u0430\u043d"
    ],
    "name:sco_x_preferred":[
        "Adobe"
    ],
    "name:sin_x_preferred":[
        "\u0db8\u0ddd\u0da9 \u0d9c\u0da9\u0ddc\u0dbd\u0dca"
    ],
    "name:spa_x_preferred":[
        "Adobe"
    ],
    "name:srp_x_preferred":[
        "\u040b\u0435\u0440\u043f\u0438\u0447"
    ],
    "name:swe_x_preferred":[
        "Lersten"
    ],
    "name:tat_x_preferred":[
        "\u0421\u0430\u043c\u0430\u043d"
    ],
    "name:tgl_x_preferred":[
        "Adobe"
    ],
    "name:tur_x_preferred":[
        "Kerpi\u00e7"
    ],
    "name:ukr_x_preferred":[
        "\u0421\u0430\u043c\u0430\u043d"
    ],
    "name:war_x_preferred":[
        "P\u00e1l\u00e1nas"
    ],
    "wof:name":"Adobe",
    "wof:placetype":"locality"
},
  "geometry": {"coordinates":[10.76669,7.06522],"type":"Point"}
}