{
  "type": "Feature",
  "properties": {
    "gn:admin1_code":"39.0",
    "gn:admin2_code":"18020.0",
    "gn:admin3_code":"JI2309",
    "gn:asciiname":"Dan Makeri",
    "gn:country_code":"NG",
    "gn:dem":397,
    "gn:feature_class":"P",
    "gn:feature_code":"PPL",
    "gn:name":"Dan Makeri",
    "gn:population":0,
    "gn:timezone":"Africa/Lagos",
    "iso:country":"NG",
    "wof:name":"Dan Makeri",
    "wof:placetype":"locality"
},
  "geometry": {"coordinates":[9.01822,12.16165],"type":"Point"}
}