{
  "type": "Feature",
  "properties": {
    "gn:admin1_code":"43.0",
    "gn:admin2_code":"35001.0",
    "gn:asciiname":"Tua",
    "gn:country_code":"NG",
    "gn:dem":129,
    "gn:feature_class":"P",
    "gn:feature_code":"PPL",
    "gn:name":"Tua",
    "gn:population":0,
    "gn:timezone":"Africa/Lagos",
    "iso:country":"NG",
    "name:ceb_x_preferred":[
        "Tua"
    ],
    "name:deu_x_preferred":[
        "Tua"
    ],
    "name:eng_x_preferred":[
        "Tua"
    ],
    "name:eng_x_variant":[
        "Tau",
        "Jakan"
    ],
    "name:nno_x_preferred":[
        "Tua"
    ],
    "name:nor_x_preferred":[
        "Tua"
    ],
    "name:por_x_preferred":[
        "Tua"
    ],
    "name:swe_x_preferred":[
        "Tua"
    ],
    "wof:name":"Tua",
    "wof:placetype":"locality"
},
  "geometry": {"coordinates":[11.10237,9.06967],"type":"Point"}
}