{
  "type": "Feature",
  "properties": {
    "gn:admin1_code":"24.0",
    "gn:asciiname":"Gangara",
    "gn:country_code":"NG",
    "gn:dem":386,
    "gn:feature_class":"P",
    "gn:feature_code":"PPL",
    "gn:name":"Gangara",
    "gn:population":0,
    "gn:timezone":"Africa/Lagos",
    "iso:country":"NG",
    "wof:name":"Gangara",
    "wof:placetype":"locality"
},
  "geometry": {"coordinates":[8.97307,12.77899],"type":"Point"}
}