{
  "type": "Feature",
  "properties": {
    "gn:admin1_code":"25.0",
    "gn:admin2_code":"4005.0",
    "gn:asciiname":"Amansee",
    "gn:country_code":"NG",
    "gn:dem":43,
    "gn:feature_class":"P",
    "gn:feature_code":"PPL",
    "gn:name":"Amansee",
    "gn:population":0,
    "gn:timezone":"Africa/Lagos",
    "iso:country":"NG",
    "name:und_x_variant":[
        "Amansim",
        "Amansee"
    ],
    "wof:name":"Amansee",
    "wof:placetype":"locality"
},
  "geometry": {"coordinates":[7.14458,6.25345],"type":"Point"}
}