{
  "type": "Feature",
  "properties": {
    "gn:admin1_code":"40.0",
    "gn:admin2_code":"506.0",
    "gn:admin3_code":"50606",
    "gn:asciiname":"Tungan-Goge",
    "gn:country_code":"NG",
    "gn:dem":242,
    "gn:feature_class":"P",
    "gn:feature_code":"PPL",
    "gn:name":"Tungan-Goge",
    "gn:population":0,
    "gn:timezone":"Africa/Lagos",
    "iso:country":"NG",
    "wof:name":"Tungan-Goge",
    "wof:placetype":"locality"
},
  "geometry": {"coordinates":[4.2617,12.34484],"type":"Point"}
}