{
  "type": "Feature",
  "properties": {
    "gn:admin1_code":"56.0",
    "gn:admin2_code":"26004.0",
    "gn:asciiname":"Masaka",
    "gn:country_code":"NG",
    "gn:dem":389,
    "gn:feature_class":"P",
    "gn:feature_code":"PPL",
    "gn:name":"Masaka",
    "gn:population":0,
    "gn:timezone":"Africa/Lagos",
    "iso:country":"NG",
    "name:pol_x_preferred":[
        "Masaka"
    ],
    "wof:name":"Masaka",
    "wof:placetype":"locality"
},
  "geometry": {"coordinates":[7.67361,9.005],"type":"Point"}
}