{
  "type": "Feature",
  "properties": {
    "gn:admin1_code":"27.0",
    "gn:admin2_code":"116.0",
    "gn:admin3_code":"11607",
    "gn:asciiname":"Kellumiri",
    "gn:country_code":"NG",
    "gn:dem":324,
    "gn:feature_class":"P",
    "gn:feature_code":"PPL",
    "gn:name":"Kellumiri",
    "gn:population":0,
    "gn:timezone":"Africa/Lagos",
    "iso:country":"NG",
    "wof:name":"Kellumiri",
    "wof:placetype":"locality"
},
  "geometry": {"coordinates":[13.66815,11.57319],"type":"Point"}
}