{
  "type": "Feature",
  "properties": {
    "gn:admin1_code":"48.0",
    "gn:admin2_code":"29008.0",
    "gn:asciiname":"Oke-Alafia",
    "gn:country_code":"NG",
    "gn:dem":200,
    "gn:feature_class":"P",
    "gn:feature_code":"PPL",
    "gn:name":"Oke-Alafia",
    "gn:population":0,
    "gn:timezone":"Africa/Lagos",
    "iso:country":"NG",
    "wof:name":"Oke-Alafia",
    "wof:placetype":"locality"
},
  "geometry": {"coordinates":[5.0093,7.0671],"type":"Point"}
}