{
  "type": "Feature",
  "properties": {
    "gn:admin1_code":"35.0",
    "gn:asciiname":"Namtariel",
    "gn:country_code":"NG",
    "gn:dem":189,
    "gn:feature_class":"P",
    "gn:feature_code":"PPL",
    "gn:name":"Namtariel",
    "gn:population":0,
    "gn:timezone":"Africa/Lagos",
    "iso:country":"NG",
    "name:eng_x_preferred":[
        "Namtariel"
    ],
    "wof:name":"Namtariel",
    "wof:placetype":"locality"
},
  "geometry": {"coordinates":[12.44086,9.49024],"type":"Point"}
}