{
  "type": "Feature",
  "properties": {
    "gn:admin1_code":"49.0",
    "gn:admin2_code":"32017",
    "gn:asciiname":"Gamji",
    "gn:country_code":"NG",
    "gn:dem":194,
    "gn:feature_class":"P",
    "gn:feature_code":"PPL",
    "gn:name":"Gamji",
    "gn:population":0,
    "gn:timezone":"Africa/Lagos",
    "iso:country":"NG",
    "wof:name":"Gamji",
    "wof:placetype":"locality"
},
  "geometry": {"coordinates":[9.89625,8.95992],"type":"Point"}
}