{
  "type": "Feature",
  "properties": {
    "gn:admin1_code":"36.0",
    "gn:admin2_code":"10006.0",
    "gn:asciiname":"Otefe",
    "gn:country_code":"NG",
    "gn:dem":28,
    "gn:feature_class":"P",
    "gn:feature_code":"PPL",
    "gn:name":"Otefe",
    "gn:population":0,
    "gn:timezone":"Africa/Lagos",
    "iso:country":"NG",
    "name:eng_x_preferred":[
        "Otefe"
    ],
    "wof:name":"Otefe",
    "wof:placetype":"locality"
},
  "geometry": {"coordinates":[5.78172,5.93259],"type":"Point"}
}