{
  "type": "Feature",
  "properties": {
    "gn:admin1_code":"51.0",
    "gn:admin2_code":"619.0",
    "gn:admin3_code":"61904",
    "gn:asciiname":"Wayage",
    "gn:country_code":"NG",
    "gn:dem":244,
    "gn:feature_class":"P",
    "gn:feature_code":"PPL",
    "gn:name":"Wayage",
    "gn:population":0,
    "gn:timezone":"Africa/Lagos",
    "iso:country":"NG",
    "wof:name":"Wayage",
    "wof:placetype":"locality"
},
  "geometry": {"coordinates":[4.84324,13.56016],"type":"Point"}
}