{
  "type": "Feature",
  "properties": {
    "gn:admin1_code":"40.0",
    "gn:admin2_code":"512.0",
    "gn:admin3_code":"51203",
    "gn:asciiname":"Diggi",
    "gn:country_code":"NG",
    "gn:dem":216,
    "gn:feature_class":"P",
    "gn:feature_code":"PPL",
    "gn:name":"Diggi",
    "gn:population":0,
    "gn:timezone":"Africa/Lagos",
    "iso:country":"NG",
    "wof:name":"Diggi",
    "wof:placetype":"locality"
},
  "geometry": {"coordinates":[4.02405,12.35795],"type":"Point"}
}