{
  "type": "Feature",
  "properties": {
    "gn:admin1_code":"32.0",
    "gn:admin2_code":"31024.0",
    "gn:asciiname":"Ago Fulani",
    "gn:country_code":"NG",
    "gn:dem":411,
    "gn:feature_class":"P",
    "gn:feature_code":"PPL",
    "gn:name":"Ago Fulani",
    "gn:population":0,
    "gn:timezone":"Africa/Lagos",
    "iso:country":"NG",
    "wof:name":"Ago Fulani",
    "wof:placetype":"locality"
},
  "geometry": {"coordinates":[4.11667,8.76667],"type":"Point"}
}