{
  "type": "Feature",
  "properties": {
    "gn:admin1_code":"40.0",
    "gn:admin2_code":"506.0",
    "gn:admin3_code":"50615",
    "gn:asciiname":"Zauro",
    "gn:country_code":"NG",
    "gn:dem":213,
    "gn:feature_class":"P",
    "gn:feature_code":"PPL",
    "gn:name":"Zauro",
    "gn:population":0,
    "gn:timezone":"Africa/Lagos",
    "iso:country":"NG",
    "wof:name":"Zauro",
    "wof:placetype":"locality"
},
  "geometry": {"coordinates":[4.3068,12.50169],"type":"Point"}
}