{
  "type": "Feature",
  "properties": {
    "gn:admin1_code":"26.0",
    "gn:admin2_code":"7002.0",
    "gn:asciiname":"Akwu",
    "gn:country_code":"NG",
    "gn:dem":78,
    "gn:feature_class":"P",
    "gn:feature_code":"PPL",
    "gn:name":"Akwu",
    "gn:population":0,
    "gn:timezone":"Africa/Lagos",
    "iso:country":"NG",
    "wof:name":"Akwu",
    "wof:placetype":"locality"
},
  "geometry": {"coordinates":[8.06156,7.86896],"type":"Point"}
}