{
  "type": "Feature",
  "properties": {
    "gn:admin1_code":"56.0",
    "gn:admin2_code":"26010.0",
    "gn:asciiname":"Wulco",
    "gn:country_code":"NG",
    "gn:dem":374,
    "gn:feature_class":"P",
    "gn:feature_code":"PPL",
    "gn:name":"Wulco",
    "gn:population":0,
    "gn:timezone":"Africa/Lagos",
    "iso:country":"NG",
    "wof:name":"Wulco",
    "wof:placetype":"locality"
},
  "geometry": {"coordinates":[8.48333,8.85],"type":"Point"}
}