{
  "type": "Feature",
  "properties": {
    "gn:admin1_code":"35.0",
    "gn:admin2_code":"2007.0",
    "gn:asciiname":"Manza'a",
    "gn:country_code":"NG",
    "gn:dem":557,
    "gn:feature_class":"P",
    "gn:feature_code":"PPL",
    "gn:name":"Manza\u2019a",
    "gn:population":0,
    "gn:timezone":"Africa/Lagos",
    "iso:country":"NG",
    "wof:name":"Manza'a",
    "wof:placetype":"locality"
},
  "geometry": {"coordinates":[12.92899,10.25397],"type":"Point"}
}