{
  "type": "Feature",
  "properties": {
    "gn:admin1_code":"32.0",
    "gn:admin2_code":"31002.0",
    "gn:asciiname":"Gbesinra",
    "gn:cc2":"NG",
    "gn:country_code":"NG",
    "gn:dem":260,
    "gn:feature_class":"P",
    "gn:feature_code":"PPL",
    "gn:name":"Gbesinra",
    "gn:population":0,
    "gn:timezone":"Africa/Lagos",
    "iso:country":"NG",
    "name:und_x_variant":[
        "Agbesinra",
        "Gbesinra"
    ],
    "wof:name":"Gbesinra",
    "wof:placetype":"locality"
},
  "geometry": {"coordinates":[3.85444,7.56417],"type":"Point"}
}