{
  "type": "Feature",
  "properties": {
    "gn:admin1_code":"46.0",
    "gn:admin2_code":"5013.0",
    "gn:admin3_code":"BA1301",
    "gn:asciiname":"Dembori",
    "gn:country_code":"NG",
    "gn:dem":406,
    "gn:feature_class":"P",
    "gn:feature_code":"PPL",
    "gn:name":"Dembori",
    "gn:population":0,
    "gn:timezone":"Africa/Lagos",
    "iso:country":"NG",
    "name:eng_x_preferred":[
        "Dembori"
    ],
    "wof:name":"Dembori",
    "wof:placetype":"locality"
},
  "geometry": {"coordinates":[10.3138,10.27852],"type":"Point"}
}