{
  "type": "Feature",
  "properties": {
    "gn:admin1_code":"44.0",
    "gn:admin2_code":"705",
    "gn:admin3_code":"70501",
    "gn:asciiname":"Walkere Umoru",
    "gn:country_code":"NG",
    "gn:dem":404,
    "gn:feature_class":"P",
    "gn:feature_code":"PPL",
    "gn:name":"Walkere Umoru",
    "gn:population":0,
    "gn:timezone":"Africa/Lagos",
    "iso:country":"NG",
    "wof:name":"Walkere Umoru",
    "wof:placetype":"locality"
},
  "geometry": {"coordinates":[11.72353,11.64244],"type":"Point"}
}