{
  "type": "Feature",
  "properties": {
    "gn:admin1_code":"46.0",
    "gn:admin2_code":"5010.0",
    "gn:admin3_code":"BA1011",
    "gn:asciiname":"Gamji",
    "gn:country_code":"NG",
    "gn:dem":383,
    "gn:feature_class":"P",
    "gn:feature_code":"PPL",
    "gn:name":"Gamji",
    "gn:population":0,
    "gn:timezone":"Africa/Lagos",
    "iso:country":"NG",
    "wof:name":"Gamji",
    "wof:placetype":"locality"
},
  "geometry": {"coordinates":[10.0441,11.859],"type":"Point"}
}