{
  "type": "Feature",
  "properties": {
    "gn:admin1_code":"27.0",
    "gn:admin2_code":"103.0",
    "gn:admin3_code":"10312",
    "gn:asciiname":"Malum Fuhuri",
    "gn:country_code":"NG",
    "gn:dem":318,
    "gn:feature_class":"P",
    "gn:feature_code":"PPL",
    "gn:name":"Malum Fuhuri",
    "gn:population":0,
    "gn:timezone":"Africa/Lagos",
    "iso:country":"NG",
    "wof:name":"Malum Fuhuri",
    "wof:placetype":"locality"
},
  "geometry": {"coordinates":[13.88171,11.42962],"type":"Point"}
}