{
  "type": "Feature",
  "properties": {
    "gn:admin1_code":"47.0",
    "gn:admin2_code":"14014.0",
    "gn:asciiname":"Okposi",
    "gn:country_code":"NG",
    "gn:dem":51,
    "gn:feature_class":"P",
    "gn:feature_code":"PPL",
    "gn:name":"Okposi",
    "gn:population":0,
    "gn:timezone":"Africa/Lagos",
    "iso:country":"NG",
    "name:und_x_variant":[
        "Okposi Obinofia",
        "Okposi"
    ],
    "wof:name":"Okposi",
    "wof:placetype":"locality"
},
  "geometry": {"coordinates":[7.19825,6.27121],"type":"Point"}
}