{
  "type": "Feature",
  "properties": {
    "gn:admin1_code":"27.0",
    "gn:admin2_code":"112.0",
    "gn:admin3_code":"11207",
    "gn:asciiname":"Kidda Fulani",
    "gn:country_code":"NG",
    "gn:dem":687,
    "gn:feature_class":"P",
    "gn:feature_code":"PPL",
    "gn:name":"Kidda Fulani",
    "gn:population":0,
    "gn:timezone":"Africa/Lagos",
    "iso:country":"NG",
    "wof:name":"Kidda Fulani",
    "wof:placetype":"locality"
},
  "geometry": {"coordinates":[12.09295,10.49409],"type":"Point"}
}