{
  "type": "Feature",
  "properties": {
    "gn:admin1_code":"31.0",
    "gn:admin2_code":"27005.0",
    "gn:asciiname":"Beji",
    "gn:country_code":"NG",
    "gn:dem":265,
    "gn:feature_class":"P",
    "gn:feature_code":"PPL",
    "gn:name":"Beji",
    "gn:population":0,
    "gn:timezone":"Africa/Lagos",
    "iso:country":"NG",
    "name:bjn_x_preferred":[
        "Beji"
    ],
    "name:ind_x_preferred":[
        "Beji"
    ],
    "name:jav_x_preferred":[
        "B\u00e8ji"
    ],
    "name:sun_x_preferred":[
        "Beji"
    ],
    "name:und_x_variant":[
        "Beji Station"
    ],
    "wof:name":"Beji",
    "wof:placetype":"locality"
},
  "geometry": {"coordinates":[6.32927,9.63297],"type":"Point"}
}