{
  "type": "Feature",
  "properties": {
    "iso:country":"NG",
    "name:ara_x_preferred":[
        "\u062c\u0627\u064a\u0627"
    ],
    "name:aze_x_preferred":[
        "Qaya"
    ],
    "name:ben_x_preferred":[
        "\u0997\u09be\u09df\u09be"
    ],
    "name:bpy_x_preferred":[
        "\u0997\u09af\u09bc\u09be"
    ],
    "name:cat_x_preferred":[
        "Gaya"
    ],
    "name:ces_x_preferred":[
        "Gaya"
    ],
    "name:deu_x_preferred":[
        "Gaya"
    ],
    "name:ell_x_preferred":[
        "\u0393\u03ba\u03ac\u03b3\u03b9\u03b1"
    ],
    "name:eng_x_preferred":[
        "Gaya"
    ],
    "name:fas_x_preferred":[
        "\u06af\u0627\u06cc\u0627"
    ],
    "name:fra_x_preferred":[
        "Gaya"
    ],
    "name:hau_x_preferred":[
        "Gaya"
    ],
    "name:heb_x_preferred":[
        "\u05d2\u05d0\u05d9\u05d4"
    ],
    "name:hif_x_preferred":[
        "Gaya"
    ],
    "name:hin_x_preferred":[
        "\u0917\u092f\u093e"
    ],
    "name:hun_x_preferred":[
        "Gaya"
    ],
    "name:ind_x_preferred":[
        "Gaya"
    ],
    "name:ita_x_preferred":[
        "Gaya"
    ],
    "name:jpn_x_preferred":[
        "\u30ac\u30e4"
    ],
    "name:kor_x_preferred":[
        "\uac00\uc57c"
    ],
    "name:msa_x_preferred":[
        "Gaya"
    ],
    "name:nan_x_preferred":[
        "Gaya"
    ],
    "name:new_x_preferred":[
        "\u0917\u092f\u093e"
    ],
    "name:nld_x_preferred":[
        "Gaya"
    ],
    "name:nor_x_preferred":[
        "Gaya"
    ],
    "name:pol_x_preferred":[
        "Gaya"
    ],
    "name:por_x_preferred":[
        "Gaya"
    ],
    "name:pus_x_preferred":[
        "\u06af\u0627\u064a\u0627"
    ],
    "name:rus_x_preferred":[
        "\u0413\u0430\u044f"
    ],
    "name:spa_x_preferred":[
        "Gaya"
    ],
    "name:swe_x_preferred":[
        "Gaya"
    ],
    "name:tur_x_preferred":[
        "Gaya"
    ],
    "name:urd_x_preferred":[
        "\u06af\u0627\u06cc\u0627"
    ],
    "name:yor_x_preferred":[
        "Agb\u00e8gb\u00e8 \u00ccj\u1ecdba \u00ccb\u00edl\u1eb9\u0300 Gaya"
    ],
    "qs:gn_country":"NG",
    "qs:gn_fcode":"PPL",
    "qs:gn_pop":20959,
    "qs:name":"Gaya",
    "qs:name_adm0":"Nigeria",
    "qs:name_adm1":"Kano",
    "qs:photos":0,
    "qs:photos_1k":0,
    "qs:photos_9k":0,
    "qs:photos_9r":0,
    "qs:photos_all":0,
    "qs:photos_sr":0,
    "qs:placetype":"Town",
    "qs:pop_sr":"7",
    "qs:woe_adm0":23424908,
    "wd:wordcount":160,
    "wof:name":"Gaya",
    "wof:placetype":"locality",
    "wof:population":20959
},
  "geometry": {"coordinates":[8.99714,11.86136],"type":"Point"}
}