{
  "type": "Feature",
  "properties": {
    "gn:admin1_code":"50.0",
    "gn:admin2_code":"33021.0",
    "gn:asciiname":"Obete",
    "gn:country_code":"NG",
    "gn:dem":31,
    "gn:feature_class":"P",
    "gn:feature_code":"PPL",
    "gn:name":"Obete",
    "gn:population":0,
    "gn:timezone":"Africa/Lagos",
    "iso:country":"NG",
    "wof:name":"Obete",
    "wof:placetype":"locality"
},
  "geometry": {"coordinates":[7.48724,4.81097],"type":"Point"}
}