{
  "type": "Feature",
  "properties": {
    "gn:admin1_code":"24.0",
    "gn:admin2_code":"417.0",
    "gn:admin3_code":"41701",
    "gn:asciiname":"Ungwan Barkono",
    "gn:country_code":"NG",
    "gn:dem":599,
    "gn:feature_class":"P",
    "gn:feature_code":"PPL",
    "gn:name":"Ungwan Barkono",
    "gn:population":0,
    "gn:timezone":"Africa/Lagos",
    "iso:country":"NG",
    "wof:name":"Ungwan Barkono",
    "wof:placetype":"locality"
},
  "geometry": {"coordinates":[7.76667,11.76667],"type":"Point"}
}