{
  "type": "Feature",
  "properties": {
    "gn:admin1_code":"44.0",
    "gn:admin2_code":"713.0",
    "gn:admin3_code":"71313",
    "gn:asciiname":"Majekakuri",
    "gn:country_code":"NG",
    "gn:dem":351,
    "gn:feature_class":"P",
    "gn:feature_code":"PPL",
    "gn:name":"Majekakuri",
    "gn:population":0,
    "gn:timezone":"Africa/Lagos",
    "iso:country":"NG",
    "wof:name":"Majekakuri",
    "wof:placetype":"locality"
},
  "geometry": {"coordinates":[10.32708,12.85884],"type":"Point"}
}