{
  "type": "Feature",
  "properties": {
    "gn:admin1_code":"26.0",
    "gn:admin2_code":"7009",
    "gn:asciiname":"Buku",
    "gn:country_code":"NG",
    "gn:dem":160,
    "gn:feature_class":"P",
    "gn:feature_code":"PPL",
    "gn:name":"Buku",
    "gn:population":0,
    "gn:timezone":"Africa/Lagos",
    "iso:country":"NG",
    "name:ceb_x_preferred":[
        "Buku"
    ],
    "name:swe_x_preferred":[
        "Buku"
    ],
    "wof:name":"Buku",
    "wof:placetype":"locality"
},
  "geometry": {"coordinates":[9.38058,7.23993],"type":"Point"}
}