{
  "type": "Feature",
  "properties": {
    "gn:admin1_code":"27.0",
    "gn:admin2_code":"111",
    "gn:admin3_code":"11102",
    "gn:asciiname":"Gomulu",
    "gn:country_code":"NG",
    "gn:dem":404,
    "gn:feature_class":"P",
    "gn:feature_code":"PPL",
    "gn:name":"Gomulu",
    "gn:population":0,
    "gn:timezone":"Africa/Lagos",
    "iso:country":"NG",
    "name:eng_x_preferred":[
        "Gomulu"
    ],
    "wof:name":"Gomulu",
    "wof:placetype":"locality"
},
  "geometry": {"coordinates":[13.33423,10.94532],"type":"Point"}
}