{
  "type": "Feature",
  "properties": {
    "gn:admin1_code":"43.0",
    "gn:admin2_code":"35005",
    "gn:asciiname":"Garin Mallam Abba",
    "gn:country_code":"NG",
    "gn:dem":147,
    "gn:feature_class":"P",
    "gn:feature_code":"PPL",
    "gn:name":"Garin Mallam Abba",
    "gn:population":0,
    "gn:timezone":"Africa/Lagos",
    "iso:country":"NG",
    "wof:name":"Garin Mallam Abba",
    "wof:placetype":"locality"
},
  "geometry": {"coordinates":[10.79123,8.66032],"type":"Point"}
}