{
  "type": "Feature",
  "properties": {
    "gn:admin1_code":"16.0",
    "gn:admin2_code":"28017.0",
    "gn:asciiname":"Idowa",
    "gn:country_code":"NG",
    "gn:dem":24,
    "gn:feature_class":"P",
    "gn:feature_code":"PPL",
    "gn:name":"Idowa",
    "gn:population":0,
    "gn:timezone":"Africa/Lagos",
    "iso:country":"NG",
    "wof:name":"Idowa",
    "wof:placetype":"locality"
},
  "geometry": {"coordinates":[3.87062,6.76968],"type":"Point"}
}