{
  "type": "Feature",
  "properties": {
    "gn:admin1_code":"51.0",
    "gn:admin2_code":"607.0",
    "gn:admin3_code":"60709",
    "gn:asciiname":"Jema",
    "gn:country_code":"NG",
    "gn:dem":280,
    "gn:feature_class":"P",
    "gn:feature_code":"PPL",
    "gn:name":"Jema",
    "gn:population":0,
    "gn:timezone":"Africa/Lagos",
    "iso:country":"NG",
    "name:deu_x_preferred":[
        "Jema"
    ],
    "name:fra_x_preferred":[
        "Jema"
    ],
    "name:swe_x_preferred":[
        "Jema"
    ],
    "wof:name":"Jema",
    "wof:placetype":"locality"
},
  "geometry": {"coordinates":[5.44226,13.45098],"type":"Point"}
}