{
  "type": "Feature",
  "properties": {
    "gn:admin1_code":"39.0",
    "gn:admin2_code":"18018.0",
    "gn:admin3_code":"JI0510",
    "gn:asciiname":"Kafingara",
    "gn:country_code":"NG",
    "gn:dem":425,
    "gn:feature_class":"P",
    "gn:feature_code":"PPL",
    "gn:name":"Kafingara",
    "gn:population":0,
    "gn:timezone":"Africa/Lagos",
    "iso:country":"NG",
    "wof:name":"Kafingara",
    "wof:placetype":"locality"
},
  "geometry": {"coordinates":[9.78333,11.53333],"type":"Point"}
}