{
  "type": "Feature",
  "properties": {
    "gn:admin1_code":"23.0",
    "gn:admin2_code":"19012.0",
    "gn:admin3_code":"KD1203",
    "gn:asciiname":"Agunu",
    "gn:country_code":"NG",
    "gn:dem":768,
    "gn:feature_class":"P",
    "gn:feature_code":"PPL",
    "gn:name":"Agunu",
    "gn:population":0,
    "gn:timezone":"Africa/Lagos",
    "iso:country":"NG",
    "wof:name":"Agunu",
    "wof:placetype":"locality"
},
  "geometry": {"coordinates":[7.8827,10.07988],"type":"Point"}
}