{
  "type": "Feature",
  "properties": {
    "gn:admin1_code":"40.0",
    "gn:admin2_code":"505.0",
    "gn:admin3_code":"50509",
    "gn:asciiname":"Matsinkai",
    "gn:country_code":"NG",
    "gn:dem":207,
    "gn:feature_class":"P",
    "gn:feature_code":"PPL",
    "gn:name":"Matsinkai",
    "gn:population":0,
    "gn:timezone":"Africa/Lagos",
    "iso:country":"NG",
    "wof:name":"Matsinkai",
    "wof:placetype":"locality"
},
  "geometry": {"coordinates":[4.37614,11.4335],"type":"Point"}
}