{
  "type": "Feature",
  "properties": {
    "gn:admin1_code":"35.0",
    "gn:admin2_code":"2010",
    "gn:asciiname":"Wrochifi",
    "gn:country_code":"NG",
    "gn:dem":499,
    "gn:feature_class":"P",
    "gn:feature_code":"PPL",
    "gn:name":"Wrochifi",
    "gn:population":0,
    "gn:timezone":"Africa/Lagos",
    "iso:country":"NG",
    "name:eng_x_preferred":[
        "Wrochifi"
    ],
    "wof:name":"Wrochifi",
    "wof:placetype":"locality"
},
  "geometry": {"coordinates":[13.47496,10.71934],"type":"Point"}
}