{
  "type": "Feature",
  "properties": {
    "gn:admin1_code":"45.0",
    "gn:admin2_code":"1017.0",
    "gn:asciiname":"Umu Opara",
    "gn:country_code":"NG",
    "gn:dem":111,
    "gn:feature_class":"P",
    "gn:feature_code":"PPL",
    "gn:name":"Umu Opara",
    "gn:population":0,
    "gn:timezone":"Africa/Lagos",
    "iso:country":"NG",
    "wof:name":"Umu Opara",
    "wof:placetype":"locality"
},
  "geometry": {"coordinates":[7.43333,5.55],"type":"Point"}
}