{
  "type": "Feature",
  "properties": {
    "gn:admin1_code":"37.0",
    "gn:admin2_code":"12001.0",
    "gn:asciiname":"Aiyeteju",
    "gn:country_code":"NG",
    "gn:dem":281,
    "gn:feature_class":"P",
    "gn:feature_code":"PPL",
    "gn:name":"Aiyeteju",
    "gn:population":0,
    "gn:timezone":"Africa/Lagos",
    "iso:country":"NG",
    "wof:name":"Aiyeteju",
    "wof:placetype":"locality"
},
  "geometry": {"coordinates":[5.9971,7.3427],"type":"Point"}
}