{
  "type": "Feature",
  "properties": {
    "gn:admin1_code":"40.0",
    "gn:admin2_code":"513.0",
    "gn:admin3_code":"51309",
    "gn:asciiname":"Bunza",
    "gn:country_code":"NG",
    "gn:dem":146,
    "gn:feature_class":"P",
    "gn:feature_code":"PPL",
    "gn:name":"Bunza",
    "gn:population":0,
    "gn:timezone":"Africa/Lagos",
    "iso:country":"NG",
    "name:fra_x_preferred":[
        "Bunza"
    ],
    "name:hau_x_preferred":[
        "Bunza"
    ],
    "name:ita_x_preferred":[
        "Bunza"
    ],
    "name:spa_x_preferred":[
        "Bunza"
    ],
    "wof:name":"Bunza",
    "wof:placetype":"locality"
},
  "geometry": {"coordinates":[4.3489,11.18908],"type":"Point"}
}