{
  "type": "Feature",
  "properties": {
    "gn:admin1_code":"44.0",
    "gn:admin2_code":"707.0",
    "gn:admin3_code":"70708",
    "gn:asciiname":"Bujimirum",
    "gn:country_code":"NG",
    "gn:dem":392,
    "gn:feature_class":"P",
    "gn:feature_code":"PPL",
    "gn:name":"Bujimirum",
    "gn:population":0,
    "gn:timezone":"Africa/Lagos",
    "iso:country":"NG",
    "name:und_x_variant":[
        "Katarko"
    ],
    "wof:name":"Bujimirum",
    "wof:placetype":"locality"
},
  "geometry": {"coordinates":[11.91656,11.56189],"type":"Point"}
}