{
  "type": "Feature",
  "properties": {
    "gn:admin1_code":"52.0",
    "gn:admin2_code":"6007.0",
    "gn:asciiname":"Tipama",
    "gn:country_code":"NG",
    "gn:dem":6,
    "gn:feature_class":"P",
    "gn:feature_code":"PPL",
    "gn:name":"Tipama",
    "gn:population":0,
    "gn:timezone":"Africa/Lagos",
    "iso:country":"NG",
    "name:eng_x_preferred":[
        "Tipama"
    ],
    "name:eng_x_variant":[
        "Tuinpega",
        "Dugbagbene"
    ],
    "name:und_x_variant":[
        "Dugbagbene",
        "Tipama"
    ],
    "wof:name":"Tipama",
    "wof:placetype":"locality"
},
  "geometry": {"coordinates":[5.90065,4.40819],"type":"Point"}
}