{
  "type": "Feature",
  "properties": {
    "gn:admin1_code":"24.0",
    "gn:admin2_code":"428.0",
    "gn:admin3_code":"42810",
    "gn:asciiname":"Zokinbori",
    "gn:country_code":"NG",
    "gn:dem":522,
    "gn:feature_class":"P",
    "gn:feature_code":"PPL",
    "gn:name":"Zokinbori",
    "gn:population":0,
    "gn:timezone":"Africa/Lagos",
    "iso:country":"NG",
    "wof:name":"Zokinbori",
    "wof:placetype":"locality"
},
  "geometry": {"coordinates":[7.6557,12.27363],"type":"Point"}
}