{
  "type": "Feature",
  "properties": {
    "gn:admin1_code":"57.0",
    "gn:admin2_code":"810.0",
    "gn:admin3_code":"81005",
    "gn:asciiname":"Zaman-Lafia",
    "gn:country_code":"NG",
    "gn:dem":489,
    "gn:feature_class":"P",
    "gn:feature_code":"PPL",
    "gn:name":"Zaman-Lafia",
    "gn:population":0,
    "gn:timezone":"Africa/Lagos",
    "iso:country":"NG",
    "wof:name":"Zaman-Lafia",
    "wof:placetype":"locality"
},
  "geometry": {"coordinates":[6.43224,11.34051],"type":"Point"}
}