{
  "type": "Feature",
  "properties": {
    "gn:admin1_code":"35.0",
    "gn:asciiname":"Maham",
    "gn:country_code":"NG",
    "gn:dem":479,
    "gn:feature_class":"P",
    "gn:feature_code":"PPL",
    "gn:name":"Maham",
    "gn:population":0,
    "gn:timezone":"Africa/Lagos",
    "iso:country":"NG",
    "name:ben_x_preferred":[
        "\u09ae\u09be\u09b9\u09be\u09ae"
    ],
    "name:bpy_x_preferred":[
        "\u09ae\u09be\u09b9\u09be\u09ae"
    ],
    "name:ceb_x_preferred":[
        "Maham"
    ],
    "name:eng_x_preferred":[
        "Maham"
    ],
    "name:hin_x_preferred":[
        "\u092e\u0939\u092e"
    ],
    "name:ita_x_preferred":[
        "Maham"
    ],
    "name:msa_x_preferred":[
        "Maham"
    ],
    "name:new_x_preferred":[
        "\u092e\u0939\u092e"
    ],
    "name:nld_x_preferred":[
        "Maham"
    ],
    "name:por_x_preferred":[
        "Maham"
    ],
    "name:spa_x_preferred":[
        "Maham"
    ],
    "name:swe_x_preferred":[
        "Maham"
    ],
    "name:urd_x_preferred":[
        "\u062a\u062d\u0635\u06cc\u0644 \u0645\u06c1\u0645"
    ],
    "name:vie_x_preferred":[
        "Maham"
    ],
    "name:zho_x_preferred":[
        "\u9a6c\u54c8\u59c6"
    ],
    "wof:name":"Maham",
    "wof:placetype":"locality"
},
  "geometry": {"coordinates":[11.73491,9.06465],"type":"Point"}
}