{
  "type": "Feature",
  "properties": {
    "gn:admin1_code":"35.0",
    "gn:asciiname":"Maham",
    "gn:country_code":"NG",
    "gn:dem":479,
    "gn:feature_class":"P",
    "gn:feature_code":"PPL",
    "gn:name":"Maham",
    "gn:population":0,
    "gn:timezone":"Africa/Lagos",
    "iso:country":"NG",
    "name:eng_x_preferred":[
        "Maham"
    ],
    "wof:name":"Maham",
    "wof:placetype":"locality"
},
  "geometry": {"coordinates":[11.73491,9.06465],"type":"Point"}
}