{
  "type": "Feature",
  "properties": {
    "gn:admin1_code":"26.0",
    "gn:admin2_code":"7003.0",
    "gn:asciiname":"Okpaha",
    "gn:country_code":"NG",
    "gn:dem":136,
    "gn:feature_class":"P",
    "gn:feature_code":"PPL",
    "gn:name":"Okpaha",
    "gn:population":0,
    "gn:timezone":"Africa/Lagos",
    "iso:country":"NG",
    "wof:name":"Okpaha",
    "wof:placetype":"locality"
},
  "geometry": {"coordinates":[8.00628,7.62585],"type":"Point"}
}