{
  "type": "Feature",
  "properties": {
    "gn:admin1_code":"51.0",
    "gn:admin2_code":"611.0",
    "gn:admin3_code":"61108",
    "gn:asciiname":"Gidan Roga",
    "gn:country_code":"NG",
    "gn:dem":264,
    "gn:feature_class":"P",
    "gn:feature_code":"PPL",
    "gn:name":"Gidan Roga",
    "gn:population":0,
    "gn:timezone":"Africa/Lagos",
    "iso:country":"NG",
    "wof:name":"Gidan Roga",
    "wof:placetype":"locality"
},
  "geometry": {"coordinates":[5.27588,13.09041],"type":"Point"}
}