{
  "type": "Feature",
  "properties": {
    "gn:admin1_code":"23.0",
    "gn:admin2_code":"19015.0",
    "gn:admin3_code":"KD1508",
    "gn:asciiname":"Ungwan Gauraka",
    "gn:country_code":"NG",
    "gn:dem":675,
    "gn:feature_class":"P",
    "gn:feature_code":"PPL",
    "gn:name":"Ungwan Gauraka",
    "gn:population":0,
    "gn:timezone":"Africa/Lagos",
    "iso:country":"NG",
    "name:und_x_variant":[
        "Gauraka",
        "Ungwan Gauraka"
    ],
    "wof:name":"Ungwan Gauraka",
    "wof:placetype":"locality"
},
  "geometry": {"coordinates":[8.21102,11.12149],"type":"Point"}
}