{
  "type": "Feature",
  "properties": {
    "gn:admin1_code":"40.0",
    "gn:admin2_code":"508.0",
    "gn:admin3_code":"50807",
    "gn:asciiname":"Dogo Daji",
    "gn:country_code":"NG",
    "gn:dem":217,
    "gn:feature_class":"P",
    "gn:feature_code":"PPL",
    "gn:name":"Dogo Daji",
    "gn:population":0,
    "gn:timezone":"Africa/Lagos",
    "iso:country":"NG",
    "wof:name":"Dogo Daji",
    "wof:placetype":"locality"
},
  "geometry": {"coordinates":[3.93589,11.95151],"type":"Point"}
}