{
  "type": "Feature",
  "properties": {
    "gn:admin1_code":"35.0",
    "gn:admin2_code":"2001.0",
    "gn:asciiname":"Wuro Malam Musa",
    "gn:country_code":"NG",
    "gn:dem":218,
    "gn:feature_class":"P",
    "gn:feature_code":"PPL",
    "gn:name":"Wuro Malam Musa",
    "gn:population":0,
    "gn:timezone":"Africa/Lagos",
    "iso:country":"NG",
    "name:und_x_variant":[
        "Wuro Mallam Musa",
        "Wuro Malam Musa"
    ],
    "wof:name":"Wuro Malam Musa",
    "wof:placetype":"locality"
},
  "geometry": {"coordinates":[12.12573,9.3072],"type":"Point"}
}