{
  "type": "Feature",
  "properties": {
    "gn:admin1_code":"28.0",
    "gn:asciiname":"Owu",
    "gn:country_code":"NG",
    "gn:dem":46,
    "gn:feature_class":"P",
    "gn:feature_code":"PPL",
    "gn:name":"Owu",
    "gn:population":0,
    "gn:timezone":"Africa/Lagos",
    "iso:country":"NG",
    "wof:name":"Owu",
    "wof:placetype":"locality"
},
  "geometry": {"coordinates":[6.99747,5.21945],"type":"Point"}
}