{
  "type": "Feature",
  "properties": {
    "gn:admin1_code":"51.0",
    "gn:admin2_code":"610.0",
    "gn:admin3_code":"61007",
    "gn:asciiname":"Karma",
    "gn:country_code":"NG",
    "gn:dem":210,
    "gn:feature_class":"P",
    "gn:feature_code":"PPL",
    "gn:name":"Karma",
    "gn:population":0,
    "gn:timezone":"Africa/Lagos",
    "iso:country":"NG",
    "wof:name":"Karma",
    "wof:placetype":"locality"
},
  "geometry": {"coordinates":[4.72754,12.17854],"type":"Point"}
}