{
  "type": "Feature",
  "properties": {
    "gn:admin1_code":"40.0",
    "gn:admin2_code":"503.0",
    "gn:admin3_code":"50310",
    "gn:asciiname":"Kukadu",
    "gn:country_code":"NG",
    "gn:dem":226,
    "gn:feature_class":"P",
    "gn:feature_code":"PPL",
    "gn:name":"Kukadu",
    "gn:population":0,
    "gn:timezone":"Africa/Lagos",
    "iso:country":"NG",
    "wof:name":"Kukadu",
    "wof:placetype":"locality"
},
  "geometry": {"coordinates":[4.24173,12.61296],"type":"Point"}
}