{
  "type": "Feature",
  "properties": {
    "gn:admin1_code":"39.0",
    "gn:admin2_code":"18022.0",
    "gn:admin3_code":"JI0304",
    "gn:asciiname":"Sabongida",
    "gn:country_code":"NG",
    "gn:dem":452,
    "gn:feature_class":"P",
    "gn:feature_code":"PPL",
    "gn:name":"Sabongida",
    "gn:population":0,
    "gn:timezone":"Africa/Lagos",
    "iso:country":"NG",
    "wof:name":"Sabongida",
    "wof:placetype":"locality"
},
  "geometry": {"coordinates":[9.58119,11.36613],"type":"Point"}
}