{
  "type": "Feature",
  "properties": {
    "gn:admin1_code":"27.0",
    "gn:admin2_code":"120.0",
    "gn:admin3_code":"12003",
    "gn:asciiname":"Kawia",
    "gn:country_code":"NG",
    "gn:dem":352,
    "gn:feature_class":"P",
    "gn:feature_code":"PPL",
    "gn:name":"Kawia",
    "gn:population":0,
    "gn:timezone":"Africa/Lagos",
    "iso:country":"NG",
    "wof:name":"Kawia",
    "wof:placetype":"locality"
},
  "geometry": {"coordinates":[12.44049,12.07215],"type":"Point"}
}