{
  "type": "Feature",
  "properties": {
    "gn:admin1_code":"22.0",
    "gn:admin2_code":"9018",
    "gn:asciiname":"Ijokom",
    "gn:country_code":"NG",
    "gn:dem":60,
    "gn:feature_class":"P",
    "gn:feature_code":"PPL",
    "gn:name":"Ijokom",
    "gn:population":0,
    "gn:timezone":"Africa/Lagos",
    "iso:country":"NG",
    "wof:name":"Ijokom",
    "wof:placetype":"locality"
},
  "geometry": {"coordinates":[8.44884,6.33589],"type":"Point"}
}