{
  "type": "Feature",
  "properties": {
    "gn:admin1_code":"31.0",
    "gn:admin2_code":"27022.0",
    "gn:asciiname":"Kauwuri",
    "gn:country_code":"NG",
    "gn:dem":497,
    "gn:feature_class":"P",
    "gn:feature_code":"PPL",
    "gn:name":"Kauwuri",
    "gn:population":0,
    "gn:timezone":"Africa/Lagos",
    "iso:country":"NG",
    "wof:name":"Kauwuri",
    "wof:placetype":"locality"
},
  "geometry": {"coordinates":[7.03542,10.30754],"type":"Point"}
}