{
  "type": "Feature",
  "properties": {
    "gn:admin1_code":"55.0",
    "gn:admin2_code":"16008.0",
    "gn:asciiname":"Dinawa",
    "gn:country_code":"NG",
    "gn:dem":269,
    "gn:feature_class":"P",
    "gn:feature_code":"PPL",
    "gn:name":"Dinawa",
    "gn:population":0,
    "gn:timezone":"Africa/Lagos",
    "iso:country":"NG",
    "wof:name":"Dinawa",
    "wof:placetype":"locality"
},
  "geometry": {"coordinates":[11.39892,10.5439],"type":"Point"}
}