{
  "type": "Feature",
  "properties": {
    "gn:admin1_code":"41.0",
    "gn:admin2_code":"23005.0",
    "gn:asciiname":"Ate Albaji",
    "gn:country_code":"NG",
    "gn:dem":373,
    "gn:feature_class":"P",
    "gn:feature_code":"PPL",
    "gn:name":"Ate Albaji",
    "gn:population":0,
    "gn:timezone":"Africa/Lagos",
    "iso:country":"NG",
    "wof:name":"Ate Albaji",
    "wof:placetype":"locality"
},
  "geometry": {"coordinates":[7.09419,7.61942],"type":"Point"}
}