{
  "type": "Feature",
  "properties": {
    "gn:admin1_code":"48.0",
    "gn:admin2_code":"29004.0",
    "gn:asciiname":"Okuesi-Oka",
    "gn:country_code":"NG",
    "gn:dem":328,
    "gn:feature_class":"P",
    "gn:feature_code":"PPL",
    "gn:name":"Okuesi-Oka",
    "gn:population":0,
    "gn:timezone":"Africa/Lagos",
    "iso:country":"NG",
    "wof:name":"Okuesi-Oka",
    "wof:placetype":"locality"
},
  "geometry": {"coordinates":[5.7252,7.4209],"type":"Point"}
}