{
  "type": "Feature",
  "properties": {
    "gn:admin1_code":"29.0",
    "gn:admin2_code":"20036.0",
    "gn:admin3_code":"KN2809",
    "gn:asciiname":"Kundurum",
    "gn:country_code":"NG",
    "gn:dem":455,
    "gn:feature_class":"P",
    "gn:feature_code":"PPL",
    "gn:name":"Kundurum",
    "gn:population":0,
    "gn:timezone":"Africa/Lagos",
    "iso:country":"NG",
    "wof:name":"Kundurum",
    "wof:placetype":"locality"
},
  "geometry": {"coordinates":[8.40153,11.81498],"type":"Point"}
}