{
  "type": "Feature",
  "properties": {
    "gn:admin1_code":"31.0",
    "gn:admin2_code":"27021.0",
    "gn:asciiname":"Inana",
    "gn:country_code":"NG",
    "gn:dem":299,
    "gn:feature_class":"P",
    "gn:feature_code":"PPL",
    "gn:name":"Inana",
    "gn:population":0,
    "gn:timezone":"Africa/Lagos",
    "iso:country":"NG",
    "wof:name":"Inana",
    "wof:placetype":"locality"
},
  "geometry": {"coordinates":[5.37034,10.99319],"type":"Point"}
}