{
  "type": "Feature",
  "properties": {
    "gn:admin1_code":"16.0",
    "gn:admin2_code":"28010.0",
    "gn:asciiname":"Okeyejo",
    "gn:country_code":"NG",
    "gn:dem":64,
    "gn:feature_class":"P",
    "gn:feature_code":"PPL",
    "gn:name":"Okeyejo",
    "gn:population":0,
    "gn:timezone":"Africa/Lagos",
    "iso:country":"NG",
    "wof:name":"Okeyejo",
    "wof:placetype":"locality"
},
  "geometry": {"coordinates":[4.0213,6.86761],"type":"Point"}
}