{
  "type": "Feature",
  "properties": {
    "gn:admin1_code":"24.0",
    "gn:admin2_code":"415.0",
    "gn:admin3_code":"41508",
    "gn:asciiname":"Karamanya",
    "gn:country_code":"NG",
    "gn:dem":489,
    "gn:feature_class":"P",
    "gn:feature_code":"PPL",
    "gn:name":"Karamanya",
    "gn:population":0,
    "gn:timezone":"Africa/Lagos",
    "iso:country":"NG",
    "wof:name":"Karamanya",
    "wof:placetype":"locality"
},
  "geometry": {"coordinates":[7.9598,12.68371],"type":"Point"}
}