{
  "type": "Feature",
  "properties": {
    "gn:admin1_code":"27.0",
    "gn:admin2_code":"109.0",
    "gn:admin3_code":"10901",
    "gn:asciiname":"Gaganan",
    "gn:country_code":"NG",
    "gn:dem":315,
    "gn:feature_class":"P",
    "gn:feature_code":"PPL",
    "gn:name":"Gaganan",
    "gn:population":0,
    "gn:timezone":"Africa/Lagos",
    "iso:country":"NG",
    "wof:name":"Gaganan",
    "wof:placetype":"locality"
},
  "geometry": {"coordinates":[12.61676,12.46749],"type":"Point"}
}