{
  "type": "Feature",
  "properties": {
    "gn:admin1_code":"57.0",
    "gn:admin2_code":"813.0",
    "gn:admin3_code":"81311",
    "gn:asciiname":"Mandaba",
    "gn:country_code":"NG",
    "gn:dem":504,
    "gn:feature_class":"P",
    "gn:feature_code":"PPL",
    "gn:name":"Mandaba",
    "gn:population":0,
    "gn:timezone":"Africa/Lagos",
    "iso:country":"NG",
    "wof:name":"Mandaba",
    "wof:placetype":"locality"
},
  "geometry": {"coordinates":[7.07847,12.00484],"type":"Point"}
}