{
  "type": "Feature",
  "properties": {
    "gn:admin1_code":"35.0",
    "gn:admin2_code":"2007.0",
    "gn:asciiname":"Dishibi",
    "gn:country_code":"NG",
    "gn:dem":507,
    "gn:feature_class":"P",
    "gn:feature_code":"PPL",
    "gn:name":"Dishibi",
    "gn:population":0,
    "gn:timezone":"Africa/Lagos",
    "iso:country":"NG",
    "wof:name":"Dishibi",
    "wof:placetype":"locality"
},
  "geometry": {"coordinates":[12.88158,10.23141],"type":"Point"}
}