{
  "type": "Feature",
  "properties": {
    "gn:admin1_code":"16.0",
    "gn:admin2_code":"28016.0",
    "gn:asciiname":"Oja Ituko",
    "gn:country_code":"NG",
    "gn:dem":124,
    "gn:feature_class":"P",
    "gn:feature_code":"PPL",
    "gn:name":"Oja Ituko",
    "gn:population":0,
    "gn:timezone":"Africa/Lagos",
    "iso:country":"NG",
    "wof:name":"Oja Ituko",
    "wof:placetype":"locality"
},
  "geometry": {"coordinates":[3.21667,7.36667],"type":"Point"}
}