{
  "type": "Feature",
  "properties": {
    "gn:admin1_code":"49.0",
    "gn:admin2_code":"32006.0",
    "gn:asciiname":"Barakin Angundi",
    "gn:country_code":"NG",
    "gn:dem":1272,
    "gn:feature_class":"P",
    "gn:feature_code":"PPL",
    "gn:name":"Barakin Angundi",
    "gn:population":0,
    "gn:timezone":"Africa/Lagos",
    "iso:country":"NG",
    "wof:name":"Barakin Angundi",
    "wof:placetype":"locality"
},
  "geometry": {"coordinates":[8.8613,9.76634],"type":"Point"}
}