{
  "type": "Feature",
  "properties": {
    "gn:admin1_code":"47.0",
    "gn:admin2_code":"14002.0",
    "gn:asciiname":"Ituku",
    "gn:country_code":"NG",
    "gn:dem":192,
    "gn:feature_class":"P",
    "gn:feature_code":"PPL",
    "gn:name":"Ituku",
    "gn:population":0,
    "gn:timezone":"Africa/Lagos",
    "iso:country":"NG",
    "wof:name":"Ituku",
    "wof:placetype":"locality"
},
  "geometry": {"coordinates":[7.45428,6.29028],"type":"Point"}
}