{
  "type": "Feature",
  "properties": {
    "gn:admin1_code":"27.0",
    "gn:admin2_code":"115.0",
    "gn:admin3_code":"11506",
    "gn:asciiname":"Mika",
    "gn:country_code":"NG",
    "gn:dem":295,
    "gn:feature_class":"P",
    "gn:feature_code":"PPL",
    "gn:name":"Mika",
    "gn:population":0,
    "gn:timezone":"Africa/Lagos",
    "iso:country":"NG",
    "wof:name":"Mika",
    "wof:placetype":"locality"
},
  "geometry": {"coordinates":[14.44154,11.9465],"type":"Point"}
}