{
  "type": "Feature",
  "properties": {
    "gn:admin1_code":"32.0",
    "gn:admin2_code":"31002.0",
    "gn:asciiname":"Atiba",
    "gn:country_code":"NG",
    "gn:dem":287,
    "gn:feature_class":"P",
    "gn:feature_code":"PPL",
    "gn:name":"Atiba",
    "gn:population":0,
    "gn:timezone":"Africa/Lagos",
    "iso:country":"NG",
    "name:fra_x_preferred":[
        "Atiba"
    ],
    "name:hau_x_preferred":[
        "Atiba"
    ],
    "name:ita_x_preferred":[
        "Atiba"
    ],
    "name:por_x_preferred":[
        "Atiba"
    ],
    "name:spa_x_preferred":[
        "Atiba"
    ],
    "wof:name":"Atiba",
    "wof:placetype":"locality"
},
  "geometry": {"coordinates":[3.99889,7.55778],"type":"Point"}
}