{
  "type": "Feature",
  "properties": {
    "gn:admin1_code":"32.0",
    "gn:admin2_code":"31002.0",
    "gn:asciiname":"Odo",
    "gn:country_code":"NG",
    "gn:dem":298,
    "gn:feature_class":"P",
    "gn:feature_code":"PPL",
    "gn:name":"Odo",
    "gn:population":0,
    "gn:timezone":"Africa/Lagos",
    "iso:country":"NG",
    "name:bre_x_preferred":[
        "Odo"
    ],
    "name:deu_x_preferred":[
        "Odo"
    ],
    "name:por_x_preferred":[
        "Od\u00e3o"
    ],
    "wof:name":"Odo",
    "wof:placetype":"locality"
},
  "geometry": {"coordinates":[3.93417,7.60889],"type":"Point"}
}