{
  "type": "Feature",
  "properties": {
    "gn:admin1_code":"26.0",
    "gn:admin2_code":"7005.0",
    "gn:asciiname":"Asor",
    "gn:country_code":"NG",
    "gn:dem":124,
    "gn:feature_class":"P",
    "gn:feature_code":"PPL",
    "gn:name":"Asor",
    "gn:population":0,
    "gn:timezone":"Africa/Lagos",
    "iso:country":"NG",
    "name:hye_x_preferred":[
        "\u0531\u057d\u0578\u0580"
    ],
    "name:spa_x_preferred":[
        "Asor"
    ],
    "wof:name":"Asor",
    "wof:placetype":"locality"
},
  "geometry": {"coordinates":[8.67804,7.32896],"type":"Point"}
}