{
  "type": "Feature",
  "properties": {
    "gn:admin1_code":"52.0",
    "gn:admin2_code":"6002.0",
    "gn:asciiname":"Azatuta",
    "gn:country_code":"NG",
    "gn:dem":7,
    "gn:feature_class":"P",
    "gn:feature_code":"PPL",
    "gn:name":"Azatuta",
    "gn:population":0,
    "gn:timezone":"Africa/Lagos",
    "iso:country":"NG",
    "name:eng_x_preferred":[
        "Azatuta"
    ],
    "wof:name":"Azatuta",
    "wof:placetype":"locality"
},
  "geometry": {"coordinates":[5.85106,4.83367],"type":"Point"}
}