{
  "type": "Feature",
  "properties": {
    "gn:admin1_code":"48.0",
    "gn:admin2_code":"29008.0",
    "gn:asciiname":"Ago-Gabriel",
    "gn:country_code":"NG",
    "gn:dem":221,
    "gn:feature_class":"P",
    "gn:feature_code":"PPL",
    "gn:name":"Ago-Gabriel",
    "gn:population":0,
    "gn:timezone":"Africa/Lagos",
    "iso:country":"NG",
    "name:und_x_variant":[
        "Ago-Gabriel Ayo",
        "Ago-Gabriel"
    ],
    "wof:name":"Ago-Gabriel",
    "wof:placetype":"locality"
},
  "geometry": {"coordinates":[5.2746,7.0382],"type":"Point"}
}