{
  "type": "Feature",
  "properties": {
    "gn:admin1_code":"40.0",
    "gn:admin2_code":"508.0",
    "gn:admin3_code":"50802",
    "gn:asciiname":"Adamu",
    "gn:country_code":"NG",
    "gn:dem":161,
    "gn:feature_class":"P",
    "gn:feature_code":"PPL",
    "gn:name":"Adamu",
    "gn:population":0,
    "gn:timezone":"Africa/Lagos",
    "iso:country":"NG",
    "wof:name":"Adamu",
    "wof:placetype":"locality"
},
  "geometry": {"coordinates":[3.69184,11.71038],"type":"Point"}
}