{
  "type": "Feature",
  "properties": {
    "gn:admin1_code":"37.0",
    "gn:admin2_code":"12001.0",
    "gn:asciiname":"Semolika",
    "gn:country_code":"NG",
    "gn:dem":457,
    "gn:feature_class":"P",
    "gn:feature_code":"PPL",
    "gn:name":"Semolika",
    "gn:population":0,
    "gn:timezone":"Africa/Lagos",
    "iso:country":"NG",
    "wof:name":"Semolika",
    "wof:placetype":"locality"
},
  "geometry": {"coordinates":[6.1258,7.3173],"type":"Point"}
}