{
  "type": "Feature",
  "properties": {
    "gn:admin1_code":"27.0",
    "gn:admin2_code":"112.0",
    "gn:admin3_code":"11211",
    "gn:asciiname":"Merama",
    "gn:country_code":"NG",
    "gn:dem":761,
    "gn:feature_class":"P",
    "gn:feature_code":"PPL",
    "gn:name":"Merama",
    "gn:population":0,
    "gn:timezone":"Africa/Lagos",
    "iso:country":"NG",
    "wof:name":"Merama",
    "wof:placetype":"locality"
},
  "geometry": {"coordinates":[12.19797,10.48645],"type":"Point"}
}