{
  "type": "Feature",
  "properties": {
    "gn:admin1_code":"23.0",
    "gn:admin2_code":"19003.0",
    "gn:admin3_code":"KD0301",
    "gn:asciiname":"Ungwan Mai Doka",
    "gn:cc2":"NG",
    "gn:country_code":"NG",
    "gn:dem":717,
    "gn:feature_class":"P",
    "gn:feature_code":"PPL",
    "gn:name":"Ungwan Mai Doka",
    "gn:population":0,
    "gn:timezone":"Africa/Lagos",
    "iso:country":"NG",
    "name:und_x_variant":[
        "Mai-Doka",
        "Ungwan Mai Doka"
    ],
    "wof:name":"Ungwan Mai Doka",
    "wof:placetype":"locality"
},
  "geometry": {"coordinates":[7.51667,11.31667],"type":"Point"}
}