{
  "type": "Feature",
  "properties": {
    "gn:admin1_code":"40.0",
    "gn:admin2_code":"507.0",
    "gn:admin3_code":"50708",
    "gn:asciiname":"Ungwan Nakarde",
    "gn:country_code":"NG",
    "gn:dem":191,
    "gn:feature_class":"P",
    "gn:feature_code":"PPL",
    "gn:name":"Ungwan Nakarde",
    "gn:population":0,
    "gn:timezone":"Africa/Lagos",
    "iso:country":"NG",
    "wof:name":"Ungwan Nakarde",
    "wof:placetype":"locality"
},
  "geometry": {"coordinates":[3.9723,12.37346],"type":"Point"}
}