{
  "type": "Feature",
  "properties": {
    "gn:admin1_code":"27.0",
    "gn:admin2_code":"105.0",
    "gn:admin3_code":"10505",
    "gn:asciiname":"Palma",
    "gn:country_code":"NG",
    "gn:dem":523,
    "gn:feature_class":"P",
    "gn:feature_code":"PPL",
    "gn:name":"Palma",
    "gn:population":0,
    "gn:timezone":"Africa/Lagos",
    "iso:country":"NG",
    "name:ast_x_preferred":[
        "Palma"
    ],
    "name:bre_x_preferred":[
        "Palma"
    ],
    "name:cat_x_preferred":[
        "Palma"
    ],
    "name:ceb_x_preferred":[
        "Palma"
    ],
    "name:ces_x_preferred":[
        "Palma"
    ],
    "name:deu_x_preferred":[
        "Palma"
    ],
    "name:ell_x_preferred":[
        "\u03a0\u03ac\u03bb\u03bc\u03b1"
    ],
    "name:epo_x_preferred":[
        "Palma"
    ],
    "name:fas_x_preferred":[
        "\u067e\u0627\u0644\u0645\u0627"
    ],
    "name:fin_x_preferred":[
        "Palma"
    ],
    "name:fra_x_preferred":[
        "Palma"
    ],
    "name:heb_x_preferred":[
        "\u05e4\u05dc\u05de\u05d4"
    ],
    "name:hun_x_preferred":[
        "P\u00e1lma"
    ],
    "name:ita_x_preferred":[
        "Palma"
    ],
    "name:lat_x_preferred":[
        "Palma"
    ],
    "name:lav_x_preferred":[
        "Palma"
    ],
    "name:nld_x_preferred":[
        "Palma"
    ],
    "name:nor_x_preferred":[
        "Palma"
    ],
    "name:oci_x_preferred":[
        "Palma"
    ],
    "name:pol_x_preferred":[
        "Palma"
    ],
    "name:por_x_preferred":[
        "Palma"
    ],
    "name:que_x_preferred":[
        "Palma"
    ],
    "name:rus_x_preferred":[
        "\u041f\u0430\u043b\u044c\u043c\u0430"
    ],
    "name:scn_x_preferred":[
        "Palma"
    ],
    "name:sco_x_preferred":[
        "Palma"
    ],
    "name:slk_x_preferred":[
        "Palma"
    ],
    "name:slv_x_preferred":[
        "Palma"
    ],
    "name:spa_x_preferred":[
        "Palma"
    ],
    "name:swe_x_preferred":[
        "Palma"
    ],
    "name:ukr_x_preferred":[
        "\u041f\u0430\u043b\u044c\u043c\u0430"
    ],
    "name:vie_x_preferred":[
        "Palma"
    ],
    "name:war_x_preferred":[
        "Palma"
    ],
    "wof:name":"Palma",
    "wof:placetype":"locality"
},
  "geometry": {"coordinates":[11.93757,10.79468],"type":"Point"}
}