{
  "type": "Feature",
  "properties": {
    "gn:admin1_code":"27.0",
    "gn:admin2_code":"105.0",
    "gn:admin3_code":"10505",
    "gn:asciiname":"Palma",
    "gn:country_code":"NG",
    "gn:dem":523,
    "gn:feature_class":"P",
    "gn:feature_code":"PPL",
    "gn:name":"Palma",
    "gn:population":0,
    "gn:timezone":"Africa/Lagos",
    "iso:country":"NG",
    "wof:name":"Palma",
    "wof:placetype":"locality"
},
  "geometry": {"coordinates":[11.93757,10.79468],"type":"Point"}
}