{
  "type": "Feature",
  "properties": {
    "gn:admin1_code":"16.0",
    "gn:admin2_code":"28009.0",
    "gn:asciiname":"Agunboye",
    "gn:country_code":"NG",
    "gn:dem":101,
    "gn:feature_class":"P",
    "gn:feature_code":"PPL",
    "gn:name":"Agunboye",
    "gn:population":0,
    "gn:timezone":"Africa/Lagos",
    "iso:country":"NG",
    "wof:name":"Agunboye",
    "wof:placetype":"locality"
},
  "geometry": {"coordinates":[4.02056,6.9325],"type":"Point"}
}