{
  "type": "Feature",
  "properties": {
    "gn:admin1_code":"35.0",
    "gn:admin2_code":"2011.0",
    "gn:asciiname":"Wuro Mallum",
    "gn:country_code":"NG",
    "gn:dem":490,
    "gn:feature_class":"P",
    "gn:feature_code":"PPL",
    "gn:name":"Wuro Mallum",
    "gn:population":0,
    "gn:timezone":"Africa/Lagos",
    "iso:country":"NG",
    "wof:name":"Wuro Mallum",
    "wof:placetype":"locality"
},
  "geometry": {"coordinates":[13.09091,10.01413],"type":"Point"}
}