{
  "type": "Feature",
  "properties": {
    "gn:admin1_code":"29.0",
    "gn:admin2_code":"20004.0",
    "gn:admin3_code":"KN0110",
    "gn:asciiname":"Ungua Bai",
    "gn:country_code":"NG",
    "gn:dem":407,
    "gn:feature_class":"P",
    "gn:feature_code":"PPL",
    "gn:name":"Ungua Bai",
    "gn:population":0,
    "gn:timezone":"Africa/Lagos",
    "iso:country":"NG",
    "wof:name":"Ungua Bai",
    "wof:placetype":"locality"
},
  "geometry": {"coordinates":[8.98258,12.04698],"type":"Point"}
}