{
  "type": "Feature",
  "properties": {
    "gn:admin1_code":"22.0",
    "gn:admin2_code":"9013.0",
    "gn:asciiname":"Ohana",
    "gn:country_code":"NG",
    "gn:dem":83,
    "gn:feature_class":"P",
    "gn:feature_code":"PPL",
    "gn:name":"Ohana",
    "gn:population":0,
    "gn:timezone":"Africa/Lagos",
    "iso:country":"NG",
    "name:ita_x_preferred":[
        "Ohana"
    ],
    "name:jpn_x_preferred":[
        "\u30aa\u30cf\u30ca"
    ],
    "name:kat_x_preferred":[
        "\u10dd\u10ee\u10d0\u10dc\u10d0"
    ],
    "name:nld_x_preferred":[
        "Ohana"
    ],
    "name:por_x_preferred":[
        "Ohana"
    ],
    "name:rus_x_preferred":[
        "\u041e\u0445\u0430\u043d\u0430"
    ],
    "name:spa_x_preferred":[
        "Ohana"
    ],
    "wof:name":"Ohana",
    "wof:placetype":"locality"
},
  "geometry": {"coordinates":[8.36392,5.96818],"type":"Point"}
}