{
  "type": "Feature",
  "properties": {
    "gn:admin1_code":"22.0",
    "gn:admin2_code":"9013.0",
    "gn:asciiname":"Ohana",
    "gn:country_code":"NG",
    "gn:dem":83,
    "gn:feature_class":"P",
    "gn:feature_code":"PPL",
    "gn:name":"Ohana",
    "gn:population":0,
    "gn:timezone":"Africa/Lagos",
    "iso:country":"NG",
    "wof:name":"Ohana",
    "wof:placetype":"locality"
},
  "geometry": {"coordinates":[8.36392,5.96818],"type":"Point"}
}