{
  "type": "Feature",
  "properties": {
    "gn:admin1_code":"57.0",
    "gn:admin2_code":"807.0",
    "gn:admin3_code":"80710",
    "gn:asciiname":"Guidan Dan Mai-Zare",
    "gn:country_code":"NG",
    "gn:dem":489,
    "gn:feature_class":"P",
    "gn:feature_code":"PPL",
    "gn:name":"Guidan Dan Mai-Zare",
    "gn:population":0,
    "gn:timezone":"Africa/Lagos",
    "iso:country":"NG",
    "name:und_x_variant":[
        "Gidan Dan Mai Zare",
        "Guidan Dan Mai-Zare"
    ],
    "wof:name":"Guidan Dan Mai-Zare",
    "wof:placetype":"locality"
},
  "geometry": {"coordinates":[6.66539,12.0361],"type":"Point"}
}