{
  "type": "Feature",
  "properties": {
    "gn:admin1_code":"49.0",
    "gn:admin2_code":"32011.0",
    "gn:asciiname":"Jibilik",
    "gn:country_code":"NG",
    "gn:dem":1127,
    "gn:feature_class":"P",
    "gn:feature_code":"PPL",
    "gn:name":"Jibilik",
    "gn:population":0,
    "gn:timezone":"Africa/Lagos",
    "iso:country":"NG",
    "name:und_x_variant":[
        "Jiplik",
        "Jibilik"
    ],
    "wof:name":"Jibilik",
    "wof:placetype":"locality"
},
  "geometry": {"coordinates":[9.26322,9.28807],"type":"Point"}
}