{
  "type": "Feature",
  "properties": {
    "gn:admin1_code":"46.0",
    "gn:admin2_code":"5020",
    "gn:admin3_code":"BA2005",
    "gn:asciiname":"Fishigwa",
    "gn:country_code":"NG",
    "gn:dem":374,
    "gn:feature_class":"P",
    "gn:feature_code":"PPL",
    "gn:name":"Fishigwa",
    "gn:population":0,
    "gn:timezone":"Africa/Lagos",
    "iso:country":"NG",
    "wof:name":"Fishigwa",
    "wof:placetype":"locality"
},
  "geometry": {"coordinates":[10.26694,12.08968],"type":"Point"}
}