{
  "type": "Feature",
  "properties": {
    "gn:admin1_code":"43.0",
    "gn:asciiname":"Jechi",
    "gn:country_code":"NG",
    "gn:dem":207,
    "gn:feature_class":"P",
    "gn:feature_code":"PPL",
    "gn:name":"Jechi",
    "gn:population":0,
    "gn:timezone":"Africa/Lagos",
    "iso:country":"NG",
    "name:eng_x_preferred":[
        "Jechi"
    ],
    "wof:name":"Jechi",
    "wof:placetype":"locality"
},
  "geometry": {"coordinates":[10.88185,9.20597],"type":"Point"}
}