{
  "type": "Feature",
  "properties": {
    "gn:admin1_code":"57.0",
    "gn:admin2_code":"805.0",
    "gn:admin3_code":"80505",
    "gn:asciiname":"Guidan Yakubu",
    "gn:country_code":"NG",
    "gn:dem":446,
    "gn:feature_class":"P",
    "gn:feature_code":"PPL",
    "gn:name":"Guidan Yakubu",
    "gn:population":0,
    "gn:timezone":"Africa/Lagos",
    "iso:country":"NG",
    "name:und_x_variant":[
        "Gidan Yakubu",
        "Guidan Yakubu"
    ],
    "wof:name":"Guidan Yakubu",
    "wof:placetype":"locality"
},
  "geometry": {"coordinates":[6.53184,12.16996],"type":"Point"}
}