{
  "type": "Feature",
  "properties": {
    "gn:admin1_code":"55.0",
    "gn:admin2_code":"16005.0",
    "gn:asciiname":"Nonowa",
    "gn:country_code":"NG",
    "gn:dem":280,
    "gn:feature_class":"P",
    "gn:feature_code":"PPL",
    "gn:name":"Nonowa",
    "gn:population":0,
    "gn:timezone":"Africa/Lagos",
    "iso:country":"NG",
    "name:und_x_variant":[
        "Ninowo",
        "Ninowa",
        "Nonowa",
        "Nayinawa"
    ],
    "wof:name":"Nonowa",
    "wof:placetype":"locality"
},
  "geometry": {"coordinates":[11.44169,11.01003],"type":"Point"}
}