{
  "type": "Feature",
  "properties": {
    "gn:admin1_code":"46.0",
    "gn:admin2_code":"5018.0",
    "gn:admin3_code":"BA1816",
    "gn:asciiname":"Kulfana",
    "gn:country_code":"NG",
    "gn:dem":917,
    "gn:feature_class":"P",
    "gn:feature_code":"PPL",
    "gn:name":"Kulfana",
    "gn:population":0,
    "gn:timezone":"Africa/Lagos",
    "iso:country":"NG",
    "name:und_x_variant":[
        "Mulfama",
        "Kulfana"
    ],
    "wof:name":"Kulfana",
    "wof:placetype":"locality"
},
  "geometry": {"coordinates":[9.05355,10.39373],"type":"Point"}
}