{
  "type": "Feature",
  "properties": {
    "gn:admin1_code":"55.0",
    "gn:admin2_code":"16004.0",
    "gn:asciiname":"Gabilau",
    "gn:country_code":"NG",
    "gn:dem":491,
    "gn:feature_class":"P",
    "gn:feature_code":"PPL",
    "gn:name":"Gabilau",
    "gn:population":0,
    "gn:timezone":"Africa/Lagos",
    "iso:country":"NG",
    "name:eng_x_preferred":[
        "Gabilau"
    ],
    "wof:name":"Gabilau",
    "wof:placetype":"locality"
},
  "geometry": {"coordinates":[10.82047,10.79298],"type":"Point"}
}