{
  "type": "Feature",
  "properties": {
    "gn:admin1_code":"48.0",
    "gn:admin2_code":"29016.0",
    "gn:asciiname":"Owomama",
    "gn:country_code":"NG",
    "gn:dem":256,
    "gn:feature_class":"P",
    "gn:feature_code":"PPL",
    "gn:name":"Owomama",
    "gn:population":0,
    "gn:timezone":"Africa/Lagos",
    "iso:country":"NG",
    "wof:name":"Owomama",
    "wof:placetype":"locality"
},
  "geometry": {"coordinates":[4.91554,6.9858],"type":"Point"}
}