{
  "type": "Feature",
  "properties": {
    "gn:admin1_code":"37.0",
    "gn:admin2_code":"12018.0",
    "gn:asciiname":"Isievbie",
    "gn:country_code":"NG",
    "gn:dem":179,
    "gn:feature_class":"P",
    "gn:feature_code":"PPL",
    "gn:name":"Isievbie",
    "gn:population":0,
    "gn:timezone":"Africa/Lagos",
    "iso:country":"NG",
    "name:eng_x_preferred":[
        "Adaigievbe"
    ],
    "wof:name":"Isievbie",
    "wof:placetype":"locality"
},
  "geometry": {"coordinates":[6.07394,6.40993],"type":"Point"}
}