{
  "type": "Feature",
  "properties": {
    "gn:admin1_code":"27.0",
    "gn:admin2_code":"104.0",
    "gn:admin3_code":"10410",
    "gn:asciiname":"Zara",
    "gn:country_code":"NG",
    "gn:dem":287,
    "gn:feature_class":"P",
    "gn:feature_code":"PPL",
    "gn:name":"Zara",
    "gn:population":0,
    "gn:timezone":"Africa/Lagos",
    "iso:country":"NG",
    "wof:name":"Zara",
    "wof:placetype":"locality"
},
  "geometry": {"coordinates":[11.7933,10.66512],"type":"Point"}
}