{
  "type": "Feature",
  "properties": {
    "gn:admin1_code":"51.0",
    "gn:admin2_code":"604.0",
    "gn:admin3_code":"60406",
    "gn:asciiname":"Folei",
    "gn:country_code":"NG",
    "gn:dem":341,
    "gn:feature_class":"P",
    "gn:feature_code":"PPL",
    "gn:name":"Folei",
    "gn:population":0,
    "gn:timezone":"Africa/Lagos",
    "iso:country":"NG",
    "name:und_x_variant":[
        "Fole",
        "Folei"
    ],
    "wof:name":"Folei",
    "wof:placetype":"locality"
},
  "geometry": {"coordinates":[5.55079,13.71596],"type":"Point"}
}