{
  "type": "Feature",
  "properties": {
    "gn:admin1_code":"36.0",
    "gn:admin2_code":"10007.0",
    "gn:asciiname":"Owere-Uteokpu",
    "gn:country_code":"NG",
    "gn:dem":161,
    "gn:feature_class":"P",
    "gn:feature_code":"PPL",
    "gn:name":"Owere-Uteokpu",
    "gn:population":0,
    "gn:timezone":"Africa/Lagos",
    "iso:country":"NG",
    "name:eng_x_preferred":[
        "Owere-Uteokpu"
    ],
    "wof:name":"Owere-Uteokpu",
    "wof:placetype":"locality"
},
  "geometry": {"coordinates":[6.28178,6.18808],"type":"Point"}
}