{
  "type": "Feature",
  "properties": {
    "gn:admin1_code":"52.0",
    "gn:admin2_code":"6002.0",
    "gn:asciiname":"Ayeseigbene",
    "gn:country_code":"NG",
    "gn:dem":11,
    "gn:feature_class":"P",
    "gn:feature_code":"PPL",
    "gn:name":"Ayeseigbene",
    "gn:population":0,
    "gn:timezone":"Africa/Lagos",
    "iso:country":"NG",
    "name:eng_x_preferred":[
        "Ayeseigbene"
    ],
    "wof:name":"Ayeseigbene",
    "wof:placetype":"locality"
},
  "geometry": {"coordinates":[5.5234,4.90734],"type":"Point"}
}