{
  "type": "Feature",
  "properties": {
    "gn:admin1_code":"29.0",
    "gn:admin2_code":"20022.0",
    "gn:admin3_code":"KN0903",
    "gn:asciiname":"Dawakin Kudu",
    "gn:country_code":"NG",
    "gn:dem":451,
    "gn:feature_class":"P",
    "gn:feature_code":"PPLA2",
    "gn:name":"Dawakin Kudu",
    "gn:population":0,
    "gn:timezone":"Africa/Lagos",
    "iso:country":"NG",
    "name:ceb_x_preferred":[
        "Dawakin Kudu"
    ],
    "name:fra_x_preferred":[
        "Dawakin Kudu"
    ],
    "name:hau_x_preferred":[
        "Dawakin Kudu"
    ],
    "name:ita_x_preferred":[
        "Dawakin Kudu"
    ],
    "name:spa_x_preferred":[
        "Dawakin Kudu"
    ],
    "name:und_x_variant":[
        "Dawaki Kudu",
        "Dawaki"
    ],
    "wof:name":"Dawakin Kudu",
    "wof:placetype":"locality"
},
  "geometry": {"coordinates":[8.59699,11.83727],"type":"Point"}
}