{
  "type": "Feature",
  "properties": {
    "gn:admin1_code":"26.0",
    "gn:admin2_code":"7004.0",
    "gn:asciiname":"Wanzum Amagwa",
    "gn:country_code":"NG",
    "gn:dem":115,
    "gn:feature_class":"P",
    "gn:feature_code":"PPL",
    "gn:name":"Wanzum Amagwa",
    "gn:population":0,
    "gn:timezone":"Africa/Lagos",
    "iso:country":"NG",
    "wof:name":"Wanzum Amagwa",
    "wof:placetype":"locality"
},
  "geometry": {"coordinates":[8.9504,7.6402],"type":"Point"}
}