{
  "type": "Feature",
  "properties": {
    "gn:admin1_code":"21.0",
    "gn:admin2_code":"3015.0",
    "gn:asciiname":"Ekoi",
    "gn:country_code":"NG",
    "gn:dem":44,
    "gn:feature_class":"P",
    "gn:feature_code":"PPL",
    "gn:name":"Ekoi",
    "gn:population":0,
    "gn:timezone":"Africa/Lagos",
    "iso:country":"NG",
    "name:fra_x_preferred":[
        "Eko\u00ef"
    ],
    "name:por_x_preferred":[
        "Ec\u00f3i"
    ],
    "wof:name":"Ekoi",
    "wof:placetype":"locality"
},
  "geometry": {"coordinates":[7.72334,5.3905],"type":"Point"}
}