{
  "type": "Feature",
  "properties": {
    "gn:admin1_code":"43.0",
    "gn:admin2_code":"35011.0",
    "gn:asciiname":"Kusuku",
    "gn:country_code":"NG",
    "gn:dem":1512,
    "gn:feature_class":"P",
    "gn:feature_code":"PPL",
    "gn:name":"Kusuku",
    "gn:population":0,
    "gn:timezone":"Africa/Lagos",
    "iso:country":"NG",
    "wof:name":"Kusuku",
    "wof:placetype":"locality"
},
  "geometry": {"coordinates":[11.13333,6.88333],"type":"Point"}
}