{
  "type": "Feature",
  "properties": {
    "gn:country":"NG",
    "gn:fcode":"PPL",
    "gn:population":11759,
    "iso:country":"NG",
    "name:ceb_x_preferred":[
        "Toungo"
    ],
    "name:eng_x_preferred":[
        "Toungo"
    ],
    "name:fra_x_preferred":[
        "Toungo"
    ],
    "name:ful_x_preferred":[
        "Toungo"
    ],
    "name:hau_x_preferred":[
        "Toungo"
    ],
    "name:ita_x_preferred":[
        "Toungo"
    ],
    "name:nan_x_preferred":[
        "Toungo"
    ],
    "name:yor_x_preferred":[
        "Agb\u00e8gb\u00e8 \u00ccj\u1ecdba \u00ccb\u00edl\u1eb9\u0300 Toungo"
    ],
    "qs:name":"Toungo",
    "qs:photos_9r":0,
    "qs:photos_sr":0,
    "qs:pop_sr":"6",
    "wd:wordcount":25,
    "wof:name":"Toungo",
    "wof:placetype":"locality",
    "wof:population":11759
},
  "geometry": {"coordinates":[12.05,8.11667],"type":"Point"}
}