{
  "type": "Feature",
  "properties": {
    "gn:admin1_code":"35.0",
    "gn:admin2_code":"2007.0",
    "gn:asciiname":"Tsohon Gari Hong",
    "gn:country_code":"NG",
    "gn:dem":562,
    "gn:feature_class":"P",
    "gn:feature_code":"PPL",
    "gn:name":"Tsohon Gari Hong",
    "gn:population":0,
    "gn:timezone":"Africa/Lagos",
    "iso:country":"NG",
    "wof:name":"Tsohon Gari Hong",
    "wof:placetype":"locality"
},
  "geometry": {"coordinates":[12.95271,10.23823],"type":"Point"}
}