{
  "type": "Feature",
  "properties": {
    "iso:country":"NG",
    "name:deu_x_preferred":[
        "Kende"
    ],
    "name:eng_x_preferred":[
        "Kende"
    ],
    "name:fra_x_preferred":[
        "Kende"
    ],
    "name:hun_x_preferred":[
        "Kende"
    ],
    "name:kor_x_preferred":[
        "\ucf04\ub370"
    ],
    "name:nld_x_preferred":[
        "Kende"
    ],
    "name:slv_x_preferred":[
        "Kende"
    ],
    "qs:gn_country":"NG",
    "qs:gn_fcode":"PPL",
    "qs:gn_pop":7395,
    "qs:name":"Kende",
    "qs:name_adm0":"Nigeria",
    "qs:name_adm1":"Kebbi",
    "qs:photos":0,
    "qs:photos_1k":0,
    "qs:photos_9k":0,
    "qs:photos_9r":0,
    "qs:photos_all":0,
    "qs:photos_sr":0,
    "qs:placetype":"Town",
    "qs:pop_sr":"5",
    "qs:woe_adm0":23424908,
    "wd:wordcount":257,
    "wof:name":"Kende",
    "wof:placetype":"locality",
    "wof:population":7395
},
  "geometry": {"coordinates":[4.2603,11.51966],"type":"Point"}
}