{
  "type": "Feature",
  "properties": {
    "gn:admin1_code":"22.0",
    "gn:admin2_code":"9016.0",
    "gn:asciiname":"Aburumbede",
    "gn:country_code":"NG",
    "gn:dem":100,
    "gn:feature_class":"P",
    "gn:feature_code":"PPL",
    "gn:name":"Aburumbede",
    "gn:population":0,
    "gn:timezone":"Africa/Lagos",
    "iso:country":"NG",
    "wof:name":"Aburumbede",
    "wof:placetype":"locality"
},
  "geometry": {"coordinates":[8.6603,6.49929],"type":"Point"}
}