{
  "type": "Feature",
  "properties": {
    "gn:admin1_code":"39.0",
    "gn:admin2_code":"18027.0",
    "gn:admin3_code":"JI1502",
    "gn:asciiname":"Gafia",
    "gn:country_code":"NG",
    "gn:dem":371,
    "gn:feature_class":"P",
    "gn:feature_code":"PPL",
    "gn:name":"Gafia",
    "gn:population":0,
    "gn:timezone":"Africa/Lagos",
    "iso:country":"NG",
    "wof:name":"Gafia",
    "wof:placetype":"locality"
},
  "geometry": {"coordinates":[9.90642,12.09444],"type":"Point"}
}