{
  "type": "Feature",
  "properties": {
    "gn:admin1_code":"43.0",
    "gn:admin2_code":"35012.0",
    "gn:asciiname":"Chevgo",
    "gn:country_code":"NG",
    "gn:dem":181,
    "gn:feature_class":"P",
    "gn:feature_code":"PPL",
    "gn:name":"Chevgo",
    "gn:population":0,
    "gn:timezone":"Africa/Lagos",
    "iso:country":"NG",
    "wof:name":"Chevgo",
    "wof:placetype":"locality"
},
  "geometry": {"coordinates":[10.03475,7.55508],"type":"Point"}
}