{
  "type": "Feature",
  "properties": {
    "gn:admin1_code":"50.0",
    "gn:admin2_code":"33008.0",
    "gn:asciiname":"Amanga",
    "gn:country_code":"NG",
    "gn:dem":11,
    "gn:feature_class":"P",
    "gn:feature_code":"PPL",
    "gn:name":"Amanga",
    "gn:population":0,
    "gn:timezone":"Africa/Lagos",
    "iso:country":"NG",
    "wof:name":"Amanga",
    "wof:placetype":"locality"
},
  "geometry": {"coordinates":[6.91667,4.75],"type":"Point"}
}