{
  "type": "Feature",
  "properties": {
    "gn:admin1_code":"40.0",
    "gn:admin2_code":"514.0",
    "gn:admin3_code":"51401",
    "gn:asciiname":"Anderai",
    "gn:country_code":"NG",
    "gn:dem":299,
    "gn:feature_class":"P",
    "gn:feature_code":"PPL",
    "gn:name":"Anderai",
    "gn:population":0,
    "gn:timezone":"Africa/Lagos",
    "iso:country":"NG",
    "name:und_x_variant":[
        "Andarai",
        "Anderai"
    ],
    "wof:name":"Anderai",
    "wof:placetype":"locality"
},
  "geometry": {"coordinates":[4.38903,11.89716],"type":"Point"}
}