{
  "type": "Feature",
  "properties": {
    "gn:admin1_code":"27.0",
    "gn:admin2_code":"102.0",
    "gn:admin3_code":"10210",
    "gn:asciiname":"Gombele Miskira",
    "gn:country_code":"NG",
    "gn:dem":509,
    "gn:feature_class":"P",
    "gn:feature_code":"PPL",
    "gn:name":"Gombele Miskira",
    "gn:population":0,
    "gn:timezone":"Africa/Lagos",
    "iso:country":"NG",
    "wof:name":"Gombele Miskira",
    "wof:placetype":"locality"
},
  "geometry": {"coordinates":[13.04477,10.58658],"type":"Point"}
}