{
  "type": "Feature",
  "properties": {
    "gn:admin1_code":"29.0",
    "gn:admin2_code":"20008.0",
    "gn:admin3_code":"KN4003",
    "gn:asciiname":"Jigilawa",
    "gn:country_code":"NG",
    "gn:dem":520,
    "gn:feature_class":"P",
    "gn:feature_code":"PPL",
    "gn:name":"Jigilawa",
    "gn:population":0,
    "gn:timezone":"Africa/Lagos",
    "iso:country":"NG",
    "wof:name":"Jigilawa",
    "wof:placetype":"locality"
},
  "geometry": {"coordinates":[8.08454,12.19119],"type":"Point"}
}