{
  "type": "Feature",
  "properties": {
    "gn:admin1_code":"23.0",
    "gn:admin2_code":"19020",
    "gn:admin3_code":"KD2001",
    "gn:asciiname":"Abaro",
    "gn:country_code":"NG",
    "gn:dem":551,
    "gn:feature_class":"P",
    "gn:feature_code":"PPL",
    "gn:name":"Abaro",
    "gn:population":0,
    "gn:timezone":"Africa/Lagos",
    "iso:country":"NG",
    "wof:name":"Abaro",
    "wof:placetype":"locality"
},
  "geometry": {"coordinates":[8.56986,9.4335],"type":"Point"}
}