{
  "type": "Feature",
  "properties": {
    "gn:admin1_code":"25.0",
    "gn:admin2_code":"4019.0",
    "gn:asciiname":"Ndiopaleze",
    "gn:country_code":"NG",
    "gn:dem":114,
    "gn:feature_class":"P",
    "gn:feature_code":"PPL",
    "gn:name":"Ndiopaleze",
    "gn:population":0,
    "gn:timezone":"Africa/Lagos",
    "iso:country":"NG",
    "wof:name":"Ndiopaleze",
    "wof:placetype":"locality"
},
  "geometry": {"coordinates":[7.16599,6.00651],"type":"Point"}
}