{
  "type": "Feature",
  "properties": {
    "gn:admin1_code":"26.0",
    "gn:admin2_code":"7005.0",
    "gn:asciiname":"Anum",
    "gn:country_code":"NG",
    "gn:dem":198,
    "gn:feature_class":"P",
    "gn:feature_code":"PPL",
    "gn:name":"Anum",
    "gn:population":0,
    "gn:timezone":"Africa/Lagos",
    "iso:country":"NG",
    "name:aka_x_preferred":[
        "Anum"
    ],
    "wof:name":"Anum",
    "wof:placetype":"locality"
},
  "geometry": {"coordinates":[8.91238,7.3269],"type":"Point"}
}