{
  "type": "Feature",
  "properties": {
    "gn:admin1_code":"36.0",
    "gn:admin2_code":"10022.0",
    "gn:asciiname":"Ekpan",
    "gn:country_code":"NG",
    "gn:dem":8,
    "gn:feature_class":"P",
    "gn:feature_code":"PPL",
    "gn:name":"Ekpan",
    "gn:population":0,
    "gn:timezone":"Africa/Lagos",
    "iso:country":"NG",
    "name:eng_x_preferred":[
        "Ekpan"
    ],
    "name:eng_x_variant":[
        "Tori"
    ],
    "wof:name":"Ekpan",
    "wof:placetype":"neighbourhood"
},
  "geometry": {"coordinates":[5.7397,5.56912],"type":"Point"}
}