{
  "type": "Feature",
  "properties": {
    "gn:admin1_code":"49.0",
    "gn:asciiname":"Rume",
    "gn:country_code":"NG",
    "gn:dem":178,
    "gn:feature_class":"P",
    "gn:feature_code":"PPL",
    "gn:name":"Rume",
    "gn:population":0,
    "gn:timezone":"Africa/Lagos",
    "iso:country":"NG",
    "wof:name":"Rume",
    "wof:placetype":"locality"
},
  "geometry": {"coordinates":[9.02112,8.66009],"type":"Point"}
}