{
  "type": "Feature",
  "properties": {
    "gn:admin1_code":"27.0",
    "gn:admin2_code":"108.0",
    "gn:admin3_code":"10801",
    "gn:asciiname":"Jie",
    "gn:country_code":"NG",
    "gn:dem":295,
    "gn:feature_class":"P",
    "gn:feature_code":"PPL",
    "gn:name":"Jie",
    "gn:population":0,
    "gn:timezone":"Africa/Lagos",
    "iso:country":"NG",
    "name:deu_x_preferred":[
        "Jie"
    ],
    "name:fra_x_preferred":[
        "Jie"
    ],
    "wof:name":"Jie",
    "wof:placetype":"locality"
},
  "geometry": {"coordinates":[14.0555,11.96593],"type":"Point"}
}