{
  "type": "Feature",
  "properties": {
    "gn:admin1_code":"24.0",
    "gn:admin2_code":"414.0",
    "gn:admin3_code":"41406",
    "gn:asciiname":"Ungwan Mani",
    "gn:country_code":"NG",
    "gn:dem":722,
    "gn:feature_class":"P",
    "gn:feature_code":"PPL",
    "gn:name":"Ungwan Mani",
    "gn:population":0,
    "gn:timezone":"Africa/Lagos",
    "iso:country":"NG",
    "wof:name":"Ungwan Mani",
    "wof:placetype":"locality"
},
  "geometry": {"coordinates":[7.33394,11.49623],"type":"Point"}
}