{
  "type": "Feature",
  "properties": {
    "gn:admin1_code":"36.0",
    "gn:admin2_code":"10001.0",
    "gn:asciiname":"Umutonu",
    "gn:country_code":"NG",
    "gn:dem":200,
    "gn:feature_class":"P",
    "gn:feature_code":"PPL",
    "gn:name":"Umutonu",
    "gn:population":0,
    "gn:timezone":"Africa/Lagos",
    "iso:country":"NG",
    "name:eng_x_preferred":[
        "Umtonu"
    ],
    "name:eng_x_variant":[
        "Umutonu"
    ],
    "wof:name":"Umutonu",
    "wof:placetype":"locality"
},
  "geometry": {"coordinates":[6.57184,6.4116],"type":"Point"}
}