{
  "type": "Feature",
  "properties": {
    "gn:admin1_code":"39.0",
    "gn:asciiname":"Biyamusu",
    "gn:country_code":"NG",
    "gn:dem":394,
    "gn:feature_class":"P",
    "gn:feature_code":"PPL",
    "gn:name":"Biyamusu",
    "gn:population":0,
    "gn:timezone":"Africa/Lagos",
    "iso:country":"NG",
    "wof:name":"Biyamusu",
    "wof:placetype":"locality"
},
  "geometry": {"coordinates":[9.18933,12.0801],"type":"Point"}
}