{
  "type": "Feature",
  "properties": {
    "gn:admin1_code":"43.0",
    "gn:admin2_code":"35014",
    "gn:asciiname":"Ter",
    "gn:country_code":"NG",
    "gn:dem":162,
    "gn:feature_class":"P",
    "gn:feature_code":"PPL",
    "gn:name":"Ter",
    "gn:population":0,
    "gn:timezone":"Africa/Lagos",
    "iso:country":"NG",
    "name:bos_x_preferred":[
        "Ter"
    ],
    "name:bre_x_preferred":[
        "Ter"
    ],
    "name:ceb_x_preferred":[
        "Ter"
    ],
    "name:deu_x_preferred":[
        "Ter"
    ],
    "name:hrv_x_preferred":[
        "Ter"
    ],
    "name:nld_x_preferred":[
        "Ter"
    ],
    "name:pol_x_preferred":[
        "Ter"
    ],
    "name:slv_x_preferred":[
        "Ter"
    ],
    "name:swe_x_preferred":[
        "Ter"
    ],
    "wof:name":"Ter",
    "wof:placetype":"locality"
},
  "geometry": {"coordinates":[9.86045,7.8412],"type":"Point"}
}