{
  "type": "Feature",
  "properties": {
    "gn:admin1_code":"30.0",
    "gn:admin2_code":"24003.0",
    "gn:asciiname":"Patiko",
    "gn:country_code":"NG",
    "gn:dem":243,
    "gn:feature_class":"P",
    "gn:feature_code":"PPL",
    "gn:name":"Patiko",
    "gn:population":0,
    "gn:timezone":"Africa/Lagos",
    "iso:country":"NG",
    "wof:name":"Patiko",
    "wof:placetype":"locality"
},
  "geometry": {"coordinates":[4.91667,8.91667],"type":"Point"}
}