{
  "type": "Feature",
  "properties": {
    "gn:admin1_code":"57.0",
    "gn:admin2_code":"803.0",
    "gn:admin3_code":"80305",
    "gn:asciiname":"Madambaji",
    "gn:country_code":"NG",
    "gn:dem":418,
    "gn:feature_class":"P",
    "gn:feature_code":"PPL",
    "gn:name":"Madambaji",
    "gn:population":0,
    "gn:timezone":"Africa/Lagos",
    "iso:country":"NG",
    "wof:name":"Madambaji",
    "wof:placetype":"locality"
},
  "geometry": {"coordinates":[6.72369,12.44915],"type":"Point"}
}