{
  "type": "Feature",
  "properties": {
    "gn:admin1_code":"43.0",
    "gn:admin2_code":"35003.0",
    "gn:asciiname":"Nyabe",
    "gn:country_code":"NG",
    "gn:dem":185,
    "gn:feature_class":"P",
    "gn:feature_code":"PPL",
    "gn:name":"Nyabe",
    "gn:population":0,
    "gn:timezone":"Africa/Lagos",
    "iso:country":"NG",
    "wof:name":"Nyabe",
    "wof:placetype":"locality"
},
  "geometry": {"coordinates":[10.29315,7.40163],"type":"Point"}
}