{
  "type": "Feature",
  "properties": {
    "gn:admin1_code":"27.0",
    "gn:admin2_code":"120.0",
    "gn:admin3_code":"12005",
    "gn:asciiname":"Zunfur",
    "gn:country_code":"NG",
    "gn:dem":305,
    "gn:feature_class":"P",
    "gn:feature_code":"PPL",
    "gn:name":"Zunfur",
    "gn:population":0,
    "gn:timezone":"Africa/Lagos",
    "iso:country":"NG",
    "wof:name":"Zunfur",
    "wof:placetype":"locality"
},
  "geometry": {"coordinates":[13.10964,12.25795],"type":"Point"}
}