{
  "type": "Feature",
  "properties": {
    "gn:admin1_code":"31.0",
    "gn:admin2_code":"27012.0",
    "gn:asciiname":"Bachida",
    "gn:country_code":"NG",
    "gn:dem":253,
    "gn:feature_class":"P",
    "gn:feature_code":"PPL",
    "gn:name":"Bachida",
    "gn:population":0,
    "gn:timezone":"Africa/Lagos",
    "iso:country":"NG",
    "name:und_x_variant":[
        "Gbachida",
        "Bachida"
    ],
    "wof:name":"Bachida",
    "wof:placetype":"locality"
},
  "geometry": {"coordinates":[6.68513,9.13042],"type":"Point"}
}