{
  "type": "Feature",
  "properties": {
    "gn:admin1_code":"43.0",
    "gn:admin2_code":"35002.0",
    "gn:asciiname":"Yampina",
    "gn:country_code":"NG",
    "gn:dem":258,
    "gn:feature_class":"P",
    "gn:feature_code":"PPL",
    "gn:name":"Yampina",
    "gn:population":0,
    "gn:timezone":"Africa/Lagos",
    "iso:country":"NG",
    "wof:name":"Yampina",
    "wof:placetype":"locality"
},
  "geometry": {"coordinates":[11.15,8.45],"type":"Point"}
}