{
  "type": "Feature",
  "properties": {
    "gn:admin1_code":"21.0",
    "gn:admin2_code":"3001.0",
    "gn:asciiname":"Ikwek",
    "gn:country_code":"NG",
    "gn:dem":52,
    "gn:feature_class":"P",
    "gn:feature_code":"PPL",
    "gn:name":"Ikwek",
    "gn:population":0,
    "gn:timezone":"Africa/Lagos",
    "iso:country":"NG",
    "wof:name":"Ikwek",
    "wof:placetype":"locality"
},
  "geometry": {"coordinates":[7.75141,5.02859],"type":"Point"}
}