{
  "type": "Feature",
  "properties": {
    "gn:admin1_code":"47.0",
    "gn:admin2_code":"14008",
    "gn:asciiname":"Ogrita",
    "gn:country_code":"NG",
    "gn:dem":326,
    "gn:feature_class":"P",
    "gn:feature_code":"PPL",
    "gn:name":"Ogrita",
    "gn:population":0,
    "gn:timezone":"Africa/Lagos",
    "iso:country":"NG",
    "wof:name":"Ogrita",
    "wof:placetype":"locality"
},
  "geometry": {"coordinates":[7.40237,6.95479],"type":"Point"}
}