{
  "type": "Feature",
  "properties": {
    "gn:admin1_code":"57.0",
    "gn:admin2_code":"810.0",
    "gn:admin3_code":"81007",
    "gn:asciiname":"Ungwan-Dan Baidu",
    "gn:country_code":"NG",
    "gn:dem":531,
    "gn:feature_class":"P",
    "gn:feature_code":"PPL",
    "gn:name":"Ungwan-Dan Baidu",
    "gn:population":0,
    "gn:timezone":"Africa/Lagos",
    "iso:country":"NG",
    "name:und_x_variant":[
        "Dan Baidu",
        "Unguwar Dan Baidu",
        "Ungwan-Dan Baidu"
    ],
    "wof:name":"Ungwan-Dan Baidu",
    "wof:placetype":"locality"
},
  "geometry": {"coordinates":[6.50076,11.55771],"type":"Point"}
}