{
  "type": "Feature",
  "properties": {
    "gn:admin1_code":"32.0",
    "gn:admin2_code":"31007.0",
    "gn:asciiname":"Omiyale",
    "gn:country_code":"NG",
    "gn:dem":208,
    "gn:feature_class":"P",
    "gn:feature_code":"PPL",
    "gn:name":"Omiyale",
    "gn:population":0,
    "gn:timezone":"Africa/Lagos",
    "iso:country":"NG",
    "wof:name":"Omiyale",
    "wof:placetype":"locality"
},
  "geometry": {"coordinates":[3.92583,7.34667],"type":"Point"}
}