{
  "type": "Feature",
  "properties": {
    "gn:admin1_code":"35.0",
    "gn:admin2_code":"2010.0",
    "gn:asciiname":"Sabongari Chambula",
    "gn:country_code":"NG",
    "gn:dem":457,
    "gn:feature_class":"P",
    "gn:feature_code":"PPL",
    "gn:name":"Sabongari Chambula",
    "gn:population":0,
    "gn:timezone":"Africa/Lagos",
    "iso:country":"NG",
    "wof:name":"Sabongari Chambula",
    "wof:placetype":"locality"
},
  "geometry": {"coordinates":[13.51872,10.86645],"type":"Point"}
}