{
  "type": "Feature",
  "properties": {
    "gn:admin1_code":"36.0",
    "gn:admin2_code":"10006.0",
    "gn:asciiname":"Osoguo",
    "gn:country_code":"NG",
    "gn:dem":19,
    "gn:feature_class":"P",
    "gn:feature_code":"PPL",
    "gn:name":"Osoguo",
    "gn:population":0,
    "gn:timezone":"Africa/Lagos",
    "iso:country":"NG",
    "name:eng_x_preferred":[
        "Osoguo"
    ],
    "wof:name":"Osoguo",
    "wof:placetype":"locality"
},
  "geometry": {"coordinates":[5.82858,5.82788],"type":"Point"}
}