{
  "type": "Feature",
  "properties": {
    "gn:admin1_code":"23.0",
    "gn:admin2_code":"19006",
    "gn:admin3_code":"KD0601",
    "gn:asciiname":"Turay",
    "gn:country_code":"NG",
    "gn:dem":727,
    "gn:feature_class":"P",
    "gn:feature_code":"PPL",
    "gn:name":"Turay",
    "gn:population":0,
    "gn:timezone":"Africa/Lagos",
    "iso:country":"NG",
    "wof:name":"Turay",
    "wof:placetype":"locality"
},
  "geometry": {"coordinates":[8.02304,9.56472],"type":"Point"}
}