{
  "type": "Feature",
  "properties": {
    "gn:admin1_code":"16.0",
    "gn:admin2_code":"28008.0",
    "gn:asciiname":"Imobi Junction",
    "gn:country_code":"NG",
    "gn:dem":62,
    "gn:feature_class":"P",
    "gn:feature_code":"PPL",
    "gn:name":"Imobi Junction",
    "gn:population":0,
    "gn:timezone":"Africa/Lagos",
    "iso:country":"NG",
    "wof:name":"Imobi Junction",
    "wof:placetype":"locality"
},
  "geometry": {"coordinates":[4.21395,6.73381],"type":"Point"}
}