{
  "type": "Feature",
  "properties": {
    "gn:admin1_code":"35.0",
    "gn:admin2_code":"2012.0",
    "gn:asciiname":"Wuro Londe",
    "gn:country_code":"NG",
    "gn:dem":410,
    "gn:feature_class":"P",
    "gn:feature_code":"PPL",
    "gn:name":"Wuro Londe",
    "gn:population":0,
    "gn:timezone":"Africa/Lagos",
    "iso:country":"NG",
    "wof:name":"Wuro Londe",
    "wof:placetype":"locality"
},
  "geometry": {"coordinates":[12.09975,8.84653],"type":"Point"}
}