{
  "type": "Feature",
  "properties": {
    "gn:admin1_code":"26.0",
    "gn:admin2_code":"7009",
    "gn:asciiname":"Ji",
    "gn:country_code":"NG",
    "gn:dem":198,
    "gn:feature_class":"P",
    "gn:feature_code":"PPL",
    "gn:name":"Ji",
    "gn:population":0,
    "gn:timezone":"Africa/Lagos",
    "iso:country":"NG",
    "name:rus_x_preferred":[
        "\u0426\u0437\u0438"
    ],
    "wof:name":"Ji",
    "wof:placetype":"locality"
},
  "geometry": {"coordinates":[9.41952,7.13027],"type":"Point"}
}