{
  "type": "Feature",
  "properties": {
    "gn:admin1_code":"30.0",
    "gn:admin2_code":"24001.0",
    "gn:asciiname":"Agboyi Eleja",
    "gn:country_code":"NG",
    "gn:dem":315,
    "gn:feature_class":"P",
    "gn:feature_code":"PPL",
    "gn:name":"Agboyi Eleja",
    "gn:population":0,
    "gn:timezone":"Africa/Lagos",
    "iso:country":"NG",
    "wof:name":"Agboyi Eleja",
    "wof:placetype":"locality"
},
  "geometry": {"coordinates":[4.45,8.26667],"type":"Point"}
}