{
  "type": "Feature",
  "properties": {
    "gn:admin1_code":"56.0",
    "gn:admin2_code":"26003.0",
    "gn:asciiname":"Gidan Mata",
    "gn:country_code":"NG",
    "gn:dem":146,
    "gn:feature_class":"P",
    "gn:feature_code":"PPL",
    "gn:name":"Gidan Mata",
    "gn:population":0,
    "gn:timezone":"Africa/Lagos",
    "iso:country":"NG",
    "wof:name":"Gidan Mata",
    "wof:placetype":"locality"
},
  "geometry": {"coordinates":[8.43333,8.46667],"type":"Point"}
}