{
  "type": "Feature",
  "properties": {
    "gn:admin1_code":"51.0",
    "gn:admin2_code":"623.0",
    "gn:admin3_code":"62303",
    "gn:asciiname":"Kibiare",
    "gn:country_code":"NG",
    "gn:dem":290,
    "gn:feature_class":"P",
    "gn:feature_code":"PPL",
    "gn:name":"Kibiare",
    "gn:population":0,
    "gn:timezone":"Africa/Lagos",
    "iso:country":"NG",
    "wof:name":"Kibiare",
    "wof:placetype":"locality"
},
  "geometry": {"coordinates":[4.89691,12.82259],"type":"Point"}
}