{
  "type": "Feature",
  "properties": {
    "gn:admin1_code":"31.0",
    "gn:admin2_code":"27014.0",
    "gn:asciiname":"Kura",
    "gn:country_code":"NG",
    "gn:dem":261,
    "gn:feature_class":"P",
    "gn:feature_code":"PPL",
    "gn:name":"Kura",
    "gn:population":0,
    "gn:timezone":"Africa/Lagos",
    "iso:country":"NG",
    "name:aze_x_preferred":[
        "K\u00fcr"
    ],
    "name:cat_x_preferred":[
        "Kura"
    ],
    "name:ceb_x_preferred":[
        "Kura"
    ],
    "name:deu_x_preferred":[
        "Kura"
    ],
    "name:est_x_preferred":[
        "Kura"
    ],
    "name:fas_x_preferred":[
        "\u06a9\u0648\u0631\u0627"
    ],
    "name:fra_x_preferred":[
        "Kura"
    ],
    "name:hin_x_preferred":[
        "\u0915\u0941\u0930\u093e"
    ],
    "name:ita_x_preferred":[
        "Kura"
    ],
    "name:lav_x_preferred":[
        "K\u016bra"
    ],
    "name:nld_x_preferred":[
        "Kura"
    ],
    "name:pol_x_preferred":[
        "Kura"
    ],
    "name:slk_x_preferred":[
        "Kura"
    ],
    "name:slv_x_preferred":[
        "Kura"
    ],
    "name:swe_x_preferred":[
        "Kura"
    ],
    "name:urd_x_preferred":[
        "\u06a9\u0648\u0631\u0627\u0628"
    ],
    "wof:name":"Kura",
    "wof:placetype":"locality"
},
  "geometry": {"coordinates":[5.03172,10.248],"type":"Point"}
}