{
  "type": "Feature",
  "properties": {
    "gn:admin1_code":"32.0",
    "gn:admin2_code":"31017.0",
    "gn:asciiname":"Igbo Ijaiye",
    "gn:cc2":"NG",
    "gn:country_code":"NG",
    "gn:dem":300,
    "gn:feature_class":"P",
    "gn:feature_code":"PPL",
    "gn:name":"Igbo Ijaiye",
    "gn:population":0,
    "gn:timezone":"Africa/Lagos",
    "iso:country":"NG",
    "name:und_x_variant":[
        "Ijaiye",
        "Igbo Ijaiye"
    ],
    "wof:name":"Igbo Ijaiye",
    "wof:placetype":"locality"
},
  "geometry": {"coordinates":[3.23333,8.23333],"type":"Point"}
}