{
  "type": "Feature",
  "properties": {
    "gn:admin1_code":"26.0",
    "gn:admin2_code":"7002.0",
    "gn:asciiname":"Oshigbudu",
    "gn:country_code":"NG",
    "gn:dem":125,
    "gn:feature_class":"P",
    "gn:feature_code":"PPL",
    "gn:name":"Oshigbudu",
    "gn:population":0,
    "gn:timezone":"Africa/Lagos",
    "iso:country":"NG",
    "wof:name":"Oshigbudu",
    "wof:placetype":"locality"
},
  "geometry": {"coordinates":[7.87048,7.83008],"type":"Point"}
}