{
  "type": "Feature",
  "properties": {
    "gn:admin1_code":"41.0",
    "gn:admin2_code":"23008.0",
    "gn:asciiname":"Alokura",
    "gn:country_code":"NG",
    "gn:dem":228,
    "gn:feature_class":"P",
    "gn:feature_code":"PPL",
    "gn:name":"Alokura",
    "gn:population":0,
    "gn:timezone":"Africa/Lagos",
    "iso:country":"NG",
    "name:und_x_variant":[
        "Alakura",
        "Alokura"
    ],
    "wof:name":"Alokura",
    "wof:placetype":"locality"
},
  "geometry": {"coordinates":[7.16201,7.23321],"type":"Point"}
}