{
  "type": "Feature",
  "properties": {
    "gn:admin1_code":"36.0",
    "gn:admin2_code":"10007.0",
    "gn:asciiname":"Igbodo",
    "gn:country_code":"NG",
    "gn:dem":224,
    "gn:feature_class":"P",
    "gn:feature_code":"PPL",
    "gn:name":"Igbodo",
    "gn:population":0,
    "gn:timezone":"Africa/Lagos",
    "iso:country":"NG",
    "name:eng_x_preferred":[
        "Igbodo"
    ],
    "wof:name":"Igbodo",
    "wof:placetype":"locality"
},
  "geometry": {"coordinates":[6.37302,6.30187],"type":"Point"}
}