{
  "type": "Feature",
  "properties": {
    "gn:admin1_code":"47.0",
    "gn:admin2_code":"14017.0",
    "gn:asciiname":"Ugwojoro",
    "gn:country_code":"NG",
    "gn:dem":186,
    "gn:feature_class":"P",
    "gn:feature_code":"PPL",
    "gn:name":"Ugwojoro",
    "gn:population":0,
    "gn:timezone":"Africa/Lagos",
    "iso:country":"NG",
    "name:und_x_variant":[
        "Ugwuijoro"
    ],
    "wof:name":"Ugwojoro",
    "wof:placetype":"locality"
},
  "geometry": {"coordinates":[7.15368,6.82825],"type":"Point"}
}