{
  "type": "Feature",
  "properties": {
    "gn:admin1_code":"44.0",
    "gn:admin2_code":"702.0",
    "gn:admin3_code":"70211",
    "gn:asciiname":"Kindilwa",
    "gn:country_code":"NG",
    "gn:dem":333,
    "gn:feature_class":"P",
    "gn:feature_code":"PPL",
    "gn:name":"Kindilwa",
    "gn:population":0,
    "gn:timezone":"Africa/Lagos",
    "iso:country":"NG",
    "wof:name":"Kindilwa",
    "wof:placetype":"locality"
},
  "geometry": {"coordinates":[11.7354,12.6822],"type":"Point"}
}