{
  "type": "Feature",
  "properties": {
    "gn:admin1_code":"16.0",
    "gn:admin2_code":"28017.0",
    "gn:asciiname":"Imodi",
    "gn:country_code":"NG",
    "gn:dem":101,
    "gn:feature_class":"P",
    "gn:feature_code":"PPL",
    "gn:name":"Imodi",
    "gn:population":0,
    "gn:timezone":"Africa/Lagos",
    "iso:country":"NG",
    "wof:name":"Imodi",
    "wof:placetype":"locality"
},
  "geometry": {"coordinates":[3.8797,6.86763],"type":"Point"}
}