{
  "type": "Feature",
  "properties": {
    "gn:admin1_code":"27.0",
    "gn:admin2_code":"109.0",
    "gn:admin3_code":"10904",
    "gn:asciiname":"Gubio",
    "gn:country_code":"NG",
    "gn:dem":305,
    "gn:feature_class":"P",
    "gn:feature_code":"PPLA2",
    "gn:name":"Gubio",
    "gn:population":0,
    "gn:timezone":"Africa/Lagos",
    "iso:country":"NG",
    "name:fra_x_preferred":[
        "Gubio"
    ],
    "name:hau_x_preferred":[
        "Gubio"
    ],
    "name:ita_x_preferred":[
        "Gubio"
    ],
    "name:spa_x_preferred":[
        "Gubio"
    ],
    "name:und_x_variant":[
        "Gubiya",
        "Gubio"
    ],
    "wof:name":"Gubio",
    "wof:placetype":"locality"
},
  "geometry": {"coordinates":[12.78089,12.49749],"type":"Point"}
}