{
  "type": "Feature",
  "properties": {
    "gn:admin1_code":"47.0",
    "gn:admin2_code":"14011.0",
    "gn:asciiname":"Ugboka",
    "gn:country_code":"NG",
    "gn:dem":98,
    "gn:feature_class":"P",
    "gn:feature_code":"PPL",
    "gn:name":"Ugboka",
    "gn:population":0,
    "gn:timezone":"Africa/Lagos",
    "iso:country":"NG",
    "name:und_x_variant":[
        "Obeagu",
        "Ugboka"
    ],
    "wof:name":"Ugboka",
    "wof:placetype":"locality"
},
  "geometry": {"coordinates":[7.58582,6.2302],"type":"Point"}
}