{
  "type": "Feature",
  "properties": {
    "gn:admin1_code":"35.0",
    "gn:admin2_code":"2018.0",
    "gn:asciiname":"Garwa Babba",
    "gn:country_code":"NG",
    "gn:dem":711,
    "gn:feature_class":"P",
    "gn:feature_code":"PPL",
    "gn:name":"Garwa Babba",
    "gn:population":0,
    "gn:timezone":"Africa/Lagos",
    "iso:country":"NG",
    "wof:name":"Garwa Babba",
    "wof:placetype":"locality"
},
  "geometry": {"coordinates":[12.36096,10.00833],"type":"Point"}
}