{
  "type": "Feature",
  "properties": {
    "gn:admin1_code":"45.0",
    "gn:asciiname":"Ogbu",
    "gn:country_code":"NG",
    "gn:dem":49,
    "gn:feature_class":"P",
    "gn:feature_code":"PPL",
    "gn:name":"Ogbu",
    "gn:population":0,
    "gn:timezone":"Africa/Lagos",
    "iso:country":"NG",
    "wof:name":"Ogbu",
    "wof:placetype":"locality"
},
  "geometry": {"coordinates":[7.91061,5.81697],"type":"Point"}
}