{
  "type": "Feature",
  "properties": {
    "gn:admin1_code":"23.0",
    "gn:admin2_code":"19002.0",
    "gn:admin3_code":"KD0203",
    "gn:asciiname":"Gidan Jatto",
    "gn:country_code":"NG",
    "gn:dem":618,
    "gn:feature_class":"P",
    "gn:feature_code":"PPL",
    "gn:name":"Gidan Jatto",
    "gn:population":0,
    "gn:timezone":"Africa/Lagos",
    "iso:country":"NG",
    "wof:name":"Gidan Jatto",
    "wof:placetype":"locality"
},
  "geometry": {"coordinates":[7.4549,10.39964],"type":"Point"}
}