{
  "type": "Feature",
  "properties": {
    "gn:admin1_code":"32.0",
    "gn:admin2_code":"31014.0",
    "gn:asciiname":"Sinko",
    "gn:country_code":"NG",
    "gn:dem":188,
    "gn:feature_class":"P",
    "gn:feature_code":"PPL",
    "gn:name":"Sinko",
    "gn:population":0,
    "gn:timezone":"Africa/Lagos",
    "iso:country":"NG",
    "name:ceb_x_preferred":[
        "Sinko"
    ],
    "name:fra_x_preferred":[
        "Sinko"
    ],
    "wof:name":"Sinko",
    "wof:placetype":"neighbourhood"
},
  "geometry": {"coordinates":[3.75167,7.435],"type":"Point"}
}