{
  "type": "Feature",
  "properties": {
    "gn:admin1_code":"47.0",
    "gn:admin2_code":"14002.0",
    "gn:asciiname":"Nkwe",
    "gn:country_code":"NG",
    "gn:dem":360,
    "gn:feature_class":"P",
    "gn:feature_code":"PPL",
    "gn:name":"Nkwe",
    "gn:population":0,
    "gn:timezone":"Africa/Lagos",
    "iso:country":"NG",
    "name:ceb_x_preferred":[
        "Nkwe"
    ],
    "name:swe_x_preferred":[
        "Nkwe"
    ],
    "wof:name":"Nkwe",
    "wof:placetype":"locality"
},
  "geometry": {"coordinates":[7.42671,6.08441],"type":"Point"}
}