{
  "type": "Feature",
  "properties": {
    "gn:admin1_code":"51.0",
    "gn:admin2_code":"610.0",
    "gn:admin3_code":"61006",
    "gn:asciiname":"Margai",
    "gn:country_code":"NG",
    "gn:dem":218,
    "gn:feature_class":"P",
    "gn:feature_code":"PPL",
    "gn:name":"Margai",
    "gn:population":0,
    "gn:timezone":"Africa/Lagos",
    "iso:country":"NG",
    "wof:name":"Margai",
    "wof:placetype":"locality"
},
  "geometry": {"coordinates":[4.76528,12.17184],"type":"Point"}
}