{
  "type": "Feature",
  "properties": {
    "gn:admin1_code":"44.0",
    "gn:admin2_code":"705.0",
    "gn:admin3_code":"70506",
    "gn:asciiname":"Dusawa",
    "gn:country_code":"NG",
    "gn:dem":386,
    "gn:feature_class":"P",
    "gn:feature_code":"PPL",
    "gn:name":"Dusawa",
    "gn:population":0,
    "gn:timezone":"Africa/Lagos",
    "iso:country":"NG",
    "name:und_x_variant":[
        "Dusuwa",
        "Dusawa"
    ],
    "wof:name":"Dusawa",
    "wof:placetype":"locality"
},
  "geometry": {"coordinates":[11.74039,11.89033],"type":"Point"}
}