{
  "type": "Feature",
  "properties": {
    "gn:admin1_code":"43.0",
    "gn:asciiname":"Kolayana Dangom",
    "gn:country_code":"NG",
    "gn:dem":552,
    "gn:feature_class":"P",
    "gn:feature_code":"PPL",
    "gn:name":"Kolayana Dangom",
    "gn:population":0,
    "gn:timezone":"Africa/Lagos",
    "iso:country":"NG",
    "name:eng_x_preferred":[
        "Kolayana Dangom"
    ],
    "wof:name":"Kolayana Dangom",
    "wof:placetype":"locality"
},
  "geometry": {"coordinates":[11.64322,9.07623],"type":"Point"}
}