{
  "type": "Feature",
  "properties": {
    "gn:admin1_code":"32.0",
    "gn:admin2_code":"31001.0",
    "gn:asciiname":"Ogunleye",
    "gn:country_code":"NG",
    "gn:dem":290,
    "gn:feature_class":"P",
    "gn:feature_code":"PPL",
    "gn:name":"Ogunleye",
    "gn:population":0,
    "gn:timezone":"Africa/Lagos",
    "iso:country":"NG",
    "wof:name":"Ogunleye",
    "wof:placetype":"locality"
},
  "geometry": {"coordinates":[3.88611,7.73361],"type":"Point"}
}