{
  "type": "Feature",
  "properties": {
    "gn:admin1_code":"51.0",
    "gn:admin2_code":"606.0",
    "gn:admin3_code":"60609",
    "gn:asciiname":"Jimojimi-Basansagawa",
    "gn:country_code":"NG",
    "gn:dem":274,
    "gn:feature_class":"P",
    "gn:feature_code":"PPL",
    "gn:name":"Jimojimi-Basansagawa",
    "gn:population":0,
    "gn:timezone":"Africa/Lagos",
    "iso:country":"NG",
    "name:und_x_variant":[
        "Djima Djimi Gaya",
        "Jimajimi",
        "Jimojimi-Basansagawa"
    ],
    "wof:name":"Jimojimi-Basansagawa",
    "wof:placetype":"locality"
},
  "geometry": {"coordinates":[4.75631,13.74556],"type":"Point"}
}