{
  "type": "Feature",
  "properties": {
    "gn:admin1_code":"16.0",
    "gn:admin2_code":"28004.0",
    "gn:asciiname":"Abawo",
    "gn:cc2":"NG",
    "gn:country_code":"NG",
    "gn:dem":92,
    "gn:feature_class":"P",
    "gn:feature_code":"PPL",
    "gn:name":"Abawo",
    "gn:population":0,
    "gn:timezone":"Africa/Lagos",
    "iso:country":"NG",
    "name:und_x_variant":[
        "Agbawo",
        "Abawo"
    ],
    "wof:name":"Abawo",
    "wof:placetype":"locality"
},
  "geometry": {"coordinates":[2.98333,7.13333],"type":"Point"}
}