{
  "type": "Feature",
  "properties": {
    "gn:admin1_code":"40.0",
    "gn:admin2_code":"506.0",
    "gn:admin3_code":"50608",
    "gn:asciiname":"Janzomo",
    "gn:country_code":"NG",
    "gn:dem":260,
    "gn:feature_class":"P",
    "gn:feature_code":"PPL",
    "gn:name":"Janzomo",
    "gn:population":0,
    "gn:timezone":"Africa/Lagos",
    "iso:country":"NG",
    "name:und_x_variant":[
        "Danzomu",
        "Janzomo"
    ],
    "wof:name":"Janzomo",
    "wof:placetype":"locality"
},
  "geometry": {"coordinates":[4.38195,12.44778],"type":"Point"}
}