{
  "type": "Feature",
  "properties": {
    "gn:admin1_code":"24.0",
    "gn:admin2_code":"431.0",
    "gn:admin3_code":"43110",
    "gn:asciiname":"Ungwan Dangaragi",
    "gn:country_code":"NG",
    "gn:dem":669,
    "gn:feature_class":"P",
    "gn:feature_code":"PPL",
    "gn:name":"Ungwan Dangaragi",
    "gn:population":0,
    "gn:timezone":"Africa/Lagos",
    "iso:country":"NG",
    "wof:name":"Ungwan Dangaragi",
    "wof:placetype":"locality"
},
  "geometry": {"coordinates":[7.02852,11.36163],"type":"Point"}
}