{
  "type": "Feature",
  "properties": {
    "gn:admin1_code":"51.0",
    "gn:admin2_code":"608.0",
    "gn:admin3_code":"60802",
    "gn:asciiname":"Sauna",
    "gn:country_code":"NG",
    "gn:dem":278,
    "gn:feature_class":"P",
    "gn:feature_code":"PPL",
    "gn:name":"Sauna",
    "gn:population":0,
    "gn:timezone":"Africa/Lagos",
    "iso:country":"NG",
    "name:und_x_variant":[
        "Zauna",
        "Sauna"
    ],
    "wof:name":"Sauna",
    "wof:placetype":"locality"
},
  "geometry": {"coordinates":[5.18856,13.57055],"type":"Point"}
}