{
  "type": "Feature",
  "properties": {
    "gn:country":"NG",
    "gn:fcode":"PPL",
    "gn:pop":7685,
    "iso:country":"NG",
    "name:unk_x_variant":[
        "Ilara"
    ],
    "qs:name":"Ilare",
    "qs:photos_9r":0,
    "qs:photos_sr":0,
    "qs:pop_sr":"5",
    "wof:name":"Ilare",
    "wof:placetype":"locality",
    "wof:population":7685
},
  "geometry": {"coordinates":[5.11333,7.35067],"type":"Point"}
}