{
  "type": "Feature",
  "properties": {
    "gn:admin1_code":"31.0",
    "gn:admin2_code":"27007.0",
    "gn:asciiname":"Ndaloke",
    "gn:country_code":"NG",
    "gn:dem":80,
    "gn:feature_class":"P",
    "gn:feature_code":"PPL",
    "gn:name":"Ndaloke",
    "gn:population":0,
    "gn:timezone":"Africa/Lagos",
    "iso:country":"NG",
    "name:und_x_variant":[
        "Indaloke",
        "Ndaloke"
    ],
    "wof:name":"Ndaloke",
    "wof:placetype":"locality"
},
  "geometry": {"coordinates":[6.10652,9.0876],"type":"Point"}
}