{
  "type": "Feature",
  "properties": {
    "gn:admin1_code":"45.0",
    "gn:admin2_code":"1005.0",
    "gn:asciiname":"Ogbuebule",
    "gn:country_code":"NG",
    "gn:dem":120,
    "gn:feature_class":"P",
    "gn:feature_code":"PPL",
    "gn:name":"Ogbuebule",
    "gn:population":0,
    "gn:timezone":"Africa/Lagos",
    "iso:country":"NG",
    "wof:name":"Ogbuebule",
    "wof:placetype":"locality"
},
  "geometry": {"coordinates":[7.57121,5.391],"type":"Point"}
}