{
  "type": "Feature",
  "properties": {
    "gn:admin1_code":"16.0",
    "gn:admin2_code":"28020.0",
    "gn:asciiname":"Iki",
    "gn:country_code":"NG",
    "gn:dem":66,
    "gn:feature_class":"P",
    "gn:feature_code":"PPL",
    "gn:name":"Iki",
    "gn:population":0,
    "gn:timezone":"Africa/Lagos",
    "iso:country":"NG",
    "name:ceb_x_preferred":[
        "Iki"
    ],
    "name:deu_x_preferred":[
        "Iki"
    ],
    "name:fin_x_preferred":[
        "Iki"
    ],
    "name:fra_x_preferred":[
        "Iki"
    ],
    "name:lit_x_preferred":[
        "Iki"
    ],
    "name:pol_x_preferred":[
        "Iki"
    ],
    "name:por_x_preferred":[
        "Iki"
    ],
    "name:ron_x_preferred":[
        "Iki"
    ],
    "name:rus_x_preferred":[
        "\u0418\u043a\u0438"
    ],
    "name:spa_x_preferred":[
        "Iki"
    ],
    "wof:name":"Iki",
    "wof:placetype":"locality"
},
  "geometry": {"coordinates":[3.60626,6.71943],"type":"Point"}
}