{
  "type": "Feature",
  "properties": {
    "gn:admin1_code":"44.0",
    "gn:admin2_code":"703.0",
    "gn:admin3_code":"70305",
    "gn:asciiname":"Njolowa",
    "gn:country_code":"NG",
    "gn:dem":386,
    "gn:feature_class":"P",
    "gn:feature_code":"PPL",
    "gn:name":"Njolowa",
    "gn:population":0,
    "gn:timezone":"Africa/Lagos",
    "iso:country":"NG",
    "name:und_x_variant":[
        "Jelawa"
    ],
    "wof:name":"Njolowa",
    "wof:placetype":"locality"
},
  "geometry": {"coordinates":[11.86175,11.92034],"type":"Point"}
}