{
  "type": "Feature",
  "properties": {
    "gn:admin1_code":"36.0",
    "gn:admin2_code":"10022.0",
    "gn:asciiname":"Ugolo",
    "gn:country_code":"NG",
    "gn:dem":12,
    "gn:feature_class":"P",
    "gn:feature_code":"PPL",
    "gn:name":"Ugolo",
    "gn:population":0,
    "gn:timezone":"Africa/Lagos",
    "iso:country":"NG",
    "name:eng_x_preferred":[
        "Ugolo"
    ],
    "wof:name":"Ugolo",
    "wof:placetype":"locality"
},
  "geometry": {"coordinates":[5.8406,5.58826],"type":"Point"}
}