{
  "type": "Feature",
  "properties": {
    "gn:admin1_code":"45.0",
    "gn:asciiname":"Ebo",
    "gn:country_code":"NG",
    "gn:dem":81,
    "gn:feature_class":"P",
    "gn:feature_code":"PPL",
    "gn:name":"Ebo",
    "gn:population":0,
    "gn:timezone":"Africa/Lagos",
    "iso:country":"NG",
    "name:ceb_x_preferred":[
        "Ebo"
    ],
    "name:por_x_preferred":[
        "Ebo"
    ],
    "name:swe_x_preferred":[
        "Ebo"
    ],
    "wof:name":"Ebo",
    "wof:placetype":"locality"
},
  "geometry": {"coordinates":[7.71443,5.45772],"type":"Point"}
}