{
  "type": "Feature",
  "properties": {
    "gn:admin1_code":"39.0",
    "gn:admin2_code":"18019.0",
    "gn:admin3_code":"JI2704",
    "gn:asciiname":"Gurjia",
    "gn:country_code":"NG",
    "gn:dem":412,
    "gn:feature_class":"P",
    "gn:feature_code":"PPL",
    "gn:name":"Gurjia",
    "gn:population":0,
    "gn:timezone":"Africa/Lagos",
    "iso:country":"NG",
    "wof:name":"Gurjia",
    "wof:placetype":"locality"
},
  "geometry": {"coordinates":[8.62151,12.70038],"type":"Point"}
}