{
  "type": "Feature",
  "properties": {
    "gn:admin1_code":"45.0",
    "gn:admin2_code":"1003.0",
    "gn:asciiname":"Eziama",
    "gn:country_code":"NG",
    "gn:dem":28,
    "gn:feature_class":"P",
    "gn:feature_code":"PPL",
    "gn:name":"Eziama",
    "gn:population":0,
    "gn:timezone":"Africa/Lagos",
    "iso:country":"NG",
    "wof:name":"Eziama",
    "wof:placetype":"locality"
},
  "geometry": {"coordinates":[7.83757,5.43858],"type":"Point"}
}