{
  "type": "Feature",
  "properties": {
    "gn:admin1_code":"49.0",
    "gn:admin2_code":"32009",
    "gn:asciiname":"Jarak",
    "gn:country_code":"NG",
    "gn:dem":197,
    "gn:feature_class":"P",
    "gn:feature_code":"PPL",
    "gn:name":"Jarak",
    "gn:population":0,
    "gn:timezone":"Africa/Lagos",
    "iso:country":"NG",
    "wof:name":"Jarak",
    "wof:placetype":"locality"
},
  "geometry": {"coordinates":[9.82204,8.88315],"type":"Point"}
}