{
  "type": "Feature",
  "properties": {
    "gn:admin1_code":"49.0",
    "gn:admin2_code":"32009",
    "gn:asciiname":"Jarak",
    "gn:country_code":"NG",
    "gn:dem":197,
    "gn:feature_class":"P",
    "gn:feature_code":"PPL",
    "gn:name":"Jarak",
    "gn:population":0,
    "gn:timezone":"Africa/Lagos",
    "iso:country":"NG",
    "name:ceb_x_preferred":[
        "Jarak"
    ],
    "name:deu_x_preferred":[
        "Jarak"
    ],
    "name:epo_x_preferred":[
        "Jarak"
    ],
    "name:fra_x_preferred":[
        "Jarak"
    ],
    "name:hrv_x_preferred":[
        "Jarak"
    ],
    "name:hun_x_preferred":[
        "Jarak"
    ],
    "name:msa_x_preferred":[
        "Jarak"
    ],
    "name:rus_x_preferred":[
        "\u042f\u0440\u0430\u043a"
    ],
    "name:slv_x_preferred":[
        "Jarak"
    ],
    "name:srp_x_preferred":[
        "\u0408\u0430\u0440\u0430\u043a"
    ],
    "name:urd_x_preferred":[
        "\u062c\u0631\u06a9"
    ],
    "wof:name":"Jarak",
    "wof:placetype":"locality"
},
  "geometry": {"coordinates":[9.82204,8.88315],"type":"Point"}
}