{
  "type": "Feature",
  "properties": {
    "gn:admin1_code":"44.0",
    "gn:admin2_code":"716.0",
    "gn:admin3_code":"71605",
    "gn:asciiname":"Karigi",
    "gn:country_code":"NG",
    "gn:dem":338,
    "gn:feature_class":"P",
    "gn:feature_code":"PPL",
    "gn:name":"Karigi",
    "gn:population":0,
    "gn:timezone":"Africa/Lagos",
    "iso:country":"NG",
    "wof:name":"Karigi",
    "wof:placetype":"locality"
},
  "geometry": {"coordinates":[11.46456,13.06465],"type":"Point"}
}