{
  "type": "Feature",
  "properties": {
    "gn:admin1_code":"31.0",
    "gn:admin2_code":"27002.0",
    "gn:asciiname":"Ungwan Akara",
    "gn:country_code":"NG",
    "gn:dem":198,
    "gn:feature_class":"P",
    "gn:feature_code":"PPL",
    "gn:name":"Ungwan Akara",
    "gn:population":0,
    "gn:timezone":"Africa/Lagos",
    "iso:country":"NG",
    "wof:name":"Ungwan Akara",
    "wof:placetype":"locality"
},
  "geometry": {"coordinates":[4.34989,10.85944],"type":"Point"}
}