{
  "type": "Feature",
  "properties": {
    "gn:admin1_code":"49.0",
    "gn:admin2_code":"32014.0",
    "gn:asciiname":"Koppar",
    "gn:country_code":"NG",
    "gn:dem":305,
    "gn:feature_class":"P",
    "gn:feature_code":"PPL",
    "gn:name":"Koppar",
    "gn:population":0,
    "gn:timezone":"Africa/Lagos",
    "iso:country":"NG",
    "name:und_x_variant":[
        "Kopar"
    ],
    "wof:name":"Koppar",
    "wof:placetype":"locality"
},
  "geometry": {"coordinates":[9.23909,8.94813],"type":"Point"}
}