{
  "type": "Feature",
  "properties": {
    "gn:admin1_code":"56.0",
    "gn:admin2_code":"26008.0",
    "gn:asciiname":"Barikin Riya",
    "gn:country_code":"NG",
    "gn:dem":227,
    "gn:feature_class":"P",
    "gn:feature_code":"PPL",
    "gn:name":"Barikin Riya",
    "gn:population":0,
    "gn:timezone":"Africa/Lagos",
    "iso:country":"NG",
    "wof:name":"Barikin Riya",
    "wof:placetype":"locality"
},
  "geometry": {"coordinates":[8.61667,8.51667],"type":"Point"}
}