{
  "type": "Feature",
  "properties": {
    "gn:admin1_code":"26.0",
    "gn:admin2_code":"7017.0",
    "gn:asciiname":"Ikache",
    "gn:country_code":"NG",
    "gn:dem":132,
    "gn:feature_class":"P",
    "gn:feature_code":"PPL",
    "gn:name":"Ikache",
    "gn:population":0,
    "gn:timezone":"Africa/Lagos",
    "iso:country":"NG",
    "wof:name":"Ikache",
    "wof:placetype":"locality"
},
  "geometry": {"coordinates":[8.45884,6.85664],"type":"Point"}
}