{
  "type": "Feature",
  "properties": {
    "gn:admin1_code":"5.0",
    "gn:admin2_code":"25014.0",
    "gn:asciiname":"Idi Araba",
    "gn:country_code":"NG",
    "gn:dem":12,
    "gn:feature_class":"P",
    "gn:feature_code":"PPL",
    "gn:name":"Idi Araba",
    "gn:population":0,
    "gn:timezone":"Africa/Lagos",
    "iso:country":"NG",
    "wof:name":"Idi Araba",
    "wof:placetype":"neighbourhood"
},
  "geometry": {"coordinates":[3.35382,6.52028],"type":"Point"}
}