{
  "type": "Feature",
  "properties": {
    "gn:admin1_code":"23.0",
    "gn:admin2_code":"19021.0",
    "gn:admin3_code":"KD2111",
    "gn:asciiname":"Gidan Dan Lami",
    "gn:country_code":"NG",
    "gn:dem":694,
    "gn:feature_class":"P",
    "gn:feature_code":"PPL",
    "gn:name":"Gidan Dan Lami",
    "gn:population":0,
    "gn:timezone":"Africa/Lagos",
    "iso:country":"NG",
    "name:und_x_variant":[
        "Dan Lami (2)",
        "Gidan Dan Lami"
    ],
    "wof:name":"Gidan Dan Lami",
    "wof:placetype":"locality"
},
  "geometry": {"coordinates":[8.06991,11.01184],"type":"Point"}
}