{
  "type": "Feature",
  "properties": {
    "gn:admin1_code":"49.0",
    "gn:admin2_code":"32006.0",
    "gn:asciiname":"Barakin Kuru Baba",
    "gn:country_code":"NG",
    "gn:dem":1246,
    "gn:feature_class":"P",
    "gn:feature_code":"PPL",
    "gn:name":"Barakin Kuru Baba",
    "gn:population":0,
    "gn:timezone":"Africa/Lagos",
    "iso:country":"NG",
    "wof:name":"Barakin Kuru Baba",
    "wof:placetype":"locality"
},
  "geometry": {"coordinates":[8.80268,9.68075],"type":"Point"}
}