{
  "type": "Feature",
  "properties": {
    "gn:admin1_code":"27.0",
    "gn:admin2_code":"113.0",
    "gn:admin3_code":"11302",
    "gn:asciiname":"Dalori",
    "gn:country_code":"NG",
    "gn:dem":325,
    "gn:feature_class":"P",
    "gn:feature_code":"PPL",
    "gn:name":"Dalori",
    "gn:population":0,
    "gn:timezone":"Africa/Lagos",
    "iso:country":"NG",
    "wof:name":"Dalori",
    "wof:placetype":"locality"
},
  "geometry": {"coordinates":[13.26606,11.76002],"type":"Point"}
}