{
  "type": "Feature",
  "properties": {
    "gn:admin1_code":"37.0",
    "gn:admin2_code":"12013.0",
    "gn:asciiname":"Evbobewen Two",
    "gn:country_code":"NG",
    "gn:dem":124,
    "gn:feature_class":"P",
    "gn:feature_code":"PPL",
    "gn:name":"Evbobewen Two",
    "gn:population":0,
    "gn:timezone":"Africa/Lagos",
    "iso:country":"NG",
    "name:eng_x_preferred":[
        "Iduviga"
    ],
    "name:und_x_variant":[
        "Evbobewen II"
    ],
    "wof:name":"Evbobewen Two",
    "wof:placetype":"locality"
},
  "geometry": {"coordinates":[6.06114,6.14152],"type":"Point"}
}