{
  "type": "Feature",
  "properties": {
    "gn:admin1_code":"28.0",
    "gn:admin2_code":"17018",
    "gn:asciiname":"Egbema",
    "gn:country_code":"NG",
    "gn:dem":20,
    "gn:feature_class":"P",
    "gn:feature_code":"PPLA2",
    "gn:name":"Egbema",
    "gn:population":0,
    "gn:timezone":"Africa/Lagos",
    "iso:country":"NG",
    "wof:name":"Egbema",
    "wof:placetype":"locality"
},
  "geometry": {"coordinates":[6.7609,5.54435],"type":"Point"}
}