{
  "type": "Feature",
  "properties": {
    "gn:admin1_code":"26.0",
    "gn:admin2_code":"7009",
    "gn:asciiname":"Ikuray",
    "gn:country_code":"NG",
    "gn:dem":132,
    "gn:feature_class":"P",
    "gn:feature_code":"PPLL",
    "gn:name":"Ikuray",
    "gn:population":0,
    "gn:timezone":"Africa/Lagos",
    "iso:country":"NG",
    "wof:name":"Ikuray",
    "wof:placetype":"locality"
},
  "geometry": {"coordinates":[9.33608,7.18729],"type":"Point"}
}