{
  "type": "Feature",
  "properties": {
    "gn:admin1_code":"32.0",
    "gn:admin2_code":"31033.0",
    "gn:asciiname":"Moro",
    "gn:country_code":"NG",
    "gn:dem":406,
    "gn:feature_class":"P",
    "gn:feature_code":"PPL",
    "gn:name":"Moro",
    "gn:population":0,
    "gn:timezone":"Africa/Lagos",
    "iso:country":"NG",
    "name:cat_x_preferred":[
        "Moro"
    ],
    "name:ceb_x_preferred":[
        "Moro"
    ],
    "name:deu_x_preferred":[
        "Moro"
    ],
    "name:epo_x_preferred":[
        "Moro"
    ],
    "name:fin_x_preferred":[
        "Moro"
    ],
    "name:fra_x_preferred":[
        "Moro"
    ],
    "name:hin_x_preferred":[
        "\u092e\u094b\u0930\u094b"
    ],
    "name:hrv_x_preferred":[
        "Moro"
    ],
    "name:hun_x_preferred":[
        "Moro"
    ],
    "name:ind_x_preferred":[
        "Moro"
    ],
    "name:ita_x_preferred":[
        "Moro"
    ],
    "name:jpn_x_preferred":[
        "\u30e2\u30ed"
    ],
    "name:lav_x_preferred":[
        "Moro"
    ],
    "name:myv_x_preferred":[
        "\u041c\u043e\u0440\u043e"
    ],
    "name:nld_x_preferred":[
        "Moro"
    ],
    "name:pol_x_preferred":[
        "Moro"
    ],
    "name:por_x_preferred":[
        "Moro"
    ],
    "name:rus_x_preferred":[
        "\u041c\u043e\u0440\u043e"
    ],
    "name:spa_x_preferred":[
        "Moro"
    ],
    "name:srp_x_preferred":[
        "\u041c\u043e\u0440\u043e"
    ],
    "name:swe_x_preferred":[
        "Moro"
    ],
    "wof:name":"Moro",
    "wof:placetype":"locality"
},
  "geometry": {"coordinates":[4.36667,8.08333],"type":"Point"}
}