{
  "type": "Feature",
  "properties": {
    "gn:admin1_code":"35.0",
    "gn:admin2_code":"2009.0",
    "gn:asciiname":"Tigno",
    "gn:country_code":"NG",
    "gn:dem":136,
    "gn:feature_class":"P",
    "gn:feature_code":"PPL",
    "gn:name":"Tigno",
    "gn:population":0,
    "gn:timezone":"Africa/Lagos",
    "iso:country":"NG",
    "name:eng_x_preferred":[
        "Tigno"
    ],
    "wof:name":"Tigno",
    "wof:placetype":"locality"
},
  "geometry": {"coordinates":[11.67794,9.49181],"type":"Point"}
}