{
  "type": "Feature",
  "properties": {
    "gn:admin1_code":"22.0",
    "gn:admin2_code":"9003.0",
    "gn:asciiname":"Atim Osam",
    "gn:country_code":"NG",
    "gn:dem":49,
    "gn:feature_class":"P",
    "gn:feature_code":"PPL",
    "gn:name":"Atim Osam",
    "gn:population":0,
    "gn:timezone":"Africa/Lagos",
    "iso:country":"NG",
    "wof:name":"Atim Osam",
    "wof:placetype":"locality"
},
  "geometry": {"coordinates":[8.416,4.9491],"type":"Point"}
}