{
  "type": "Feature",
  "properties": {
    "gn:admin1_code":"55.0",
    "gn:asciiname":"Wuro Kudou",
    "gn:country_code":"NG",
    "gn:dem":384,
    "gn:feature_class":"P",
    "gn:feature_code":"PPL",
    "gn:name":"Wuro Kudou",
    "gn:population":0,
    "gn:timezone":"Africa/Lagos",
    "iso:country":"NG",
    "name:eng_x_preferred":[
        "Wuro Kudou"
    ],
    "wof:name":"Wuro Kudou",
    "wof:placetype":"locality"
},
  "geometry": {"coordinates":[10.82159,10.42502],"type":"Point"}
}