{
  "type": "Feature",
  "properties": {
    "gn:admin1_code":"51.0",
    "gn:admin2_code":"608.0",
    "gn:admin3_code":"60804",
    "gn:asciiname":"Garu",
    "gn:country_code":"NG",
    "gn:dem":302,
    "gn:feature_class":"P",
    "gn:feature_code":"PPL",
    "gn:name":"Garu",
    "gn:population":0,
    "gn:timezone":"Africa/Lagos",
    "iso:country":"NG",
    "name:ceb_x_preferred":[
        "Garu"
    ],
    "name:spa_x_preferred":[
        "Garu"
    ],
    "name:swe_x_preferred":[
        "Garu"
    ],
    "wof:name":"Garu",
    "wof:placetype":"locality"
},
  "geometry": {"coordinates":[5.36172,13.61815],"type":"Point"}
}