{
  "type": "Feature",
  "properties": {
    "gn:admin1_code":"36.0",
    "gn:admin2_code":"10017.0",
    "gn:asciiname":"Okuovwori",
    "gn:country_code":"NG",
    "gn:dem":11,
    "gn:feature_class":"P",
    "gn:feature_code":"PPL",
    "gn:name":"Okuovwori",
    "gn:population":0,
    "gn:timezone":"Africa/Lagos",
    "iso:country":"NG",
    "name:eng_x_preferred":[
        "Okuovwori"
    ],
    "wof:name":"Okuovwori",
    "wof:placetype":"locality"
},
  "geometry": {"coordinates":[5.72526,5.83527],"type":"Point"}
}