{
  "type": "Feature",
  "properties": {
    "gn:admin1_code":"26.0",
    "gn:admin2_code":"7012",
    "gn:asciiname":"Anema",
    "gn:country_code":"NG",
    "gn:dem":184,
    "gn:feature_class":"P",
    "gn:feature_code":"PPL",
    "gn:name":"Anema",
    "gn:population":0,
    "gn:timezone":"Africa/Lagos",
    "iso:country":"NG",
    "name:pol_x_preferred":[
        "Anema"
    ],
    "wof:name":"Anema",
    "wof:placetype":"locality"
},
  "geometry": {"coordinates":[9.09728,7.66379],"type":"Point"}
}