{
  "type": "Feature",
  "properties": {
    "gn:admin1_code":"27.0",
    "gn:admin2_code":"110",
    "gn:admin3_code":"11010",
    "gn:asciiname":"Goniri",
    "gn:country_code":"NG",
    "gn:dem":298,
    "gn:feature_class":"P",
    "gn:feature_code":"PPL",
    "gn:name":"Goniri",
    "gn:population":0,
    "gn:timezone":"Africa/Lagos",
    "iso:country":"NG",
    "wof:name":"Goniri",
    "wof:placetype":"locality"
},
  "geometry": {"coordinates":[13.45875,13.01535],"type":"Point"}
}