{
  "type": "Feature",
  "properties": {
    "gn:admin1_code":"36.0",
    "gn:admin2_code":"10005.0",
    "gn:asciiname":"Urhono",
    "gn:country_code":"NG",
    "gn:dem":11,
    "gn:feature_class":"P",
    "gn:feature_code":"PPL",
    "gn:name":"Urhono",
    "gn:population":0,
    "gn:timezone":"Africa/Lagos",
    "iso:country":"NG",
    "name:und_x_variant":[
        "Urhuno",
        "Urhono"
    ],
    "wof:name":"Urhono",
    "wof:placetype":"locality"
},
  "geometry": {"coordinates":[5.97803,5.72913],"type":"Point"}
}