{
  "type": "Feature",
  "properties": {
    "gn:admin1_code":"55.0",
    "gn:admin2_code":"16001.0",
    "gn:asciiname":"Acowa",
    "gn:country_code":"NG",
    "gn:dem":427,
    "gn:feature_class":"P",
    "gn:feature_code":"PPL",
    "gn:name":"Acowa",
    "gn:population":0,
    "gn:timezone":"Africa/Lagos",
    "iso:country":"NG",
    "wof:name":"Acowa",
    "wof:placetype":"locality"
},
  "geometry": {"coordinates":[11.18491,10.30866],"type":"Point"}
}