{
  "type": "Feature",
  "properties": {
    "gn:admin1_code":"23.0",
    "gn:admin2_code":"19006.0",
    "gn:admin3_code":"KD0607",
    "gn:asciiname":"Nok",
    "gn:country_code":"NG",
    "gn:dem":744,
    "gn:feature_class":"P",
    "gn:feature_code":"PPL",
    "gn:name":"Nok",
    "gn:population":0,
    "gn:timezone":"Africa/Lagos",
    "iso:country":"NG",
    "wof:name":"Nok",
    "wof:placetype":"locality"
},
  "geometry": {"coordinates":[8.02111,9.49024],"type":"Point"}
}