{
  "type": "Feature",
  "properties": {
    "gn:admin1_code":"24.0",
    "gn:admin2_code":"409.0",
    "gn:admin3_code":"40906",
    "gn:asciiname":"Garaji",
    "gn:country_code":"NG",
    "gn:dem":524,
    "gn:feature_class":"P",
    "gn:feature_code":"PPL",
    "gn:name":"Garaji",
    "gn:population":0,
    "gn:timezone":"Africa/Lagos",
    "iso:country":"NG",
    "name:und_x_variant":[
        "Gareri",
        "Garaji"
    ],
    "wof:name":"Garaji",
    "wof:placetype":"locality"
},
  "geometry": {"coordinates":[7.34595,12.13601],"type":"Point"}
}