{
  "type": "Feature",
  "properties": {
    "gn:admin1_code":"51.0",
    "gn:admin2_code":"604.0",
    "gn:admin3_code":"60407",
    "gn:asciiname":"Chingali",
    "gn:country_code":"NG",
    "gn:dem":278,
    "gn:feature_class":"P",
    "gn:feature_code":"PPL",
    "gn:name":"Chingali",
    "gn:population":0,
    "gn:timezone":"Africa/Lagos",
    "iso:country":"NG",
    "wof:name":"Chingali",
    "wof:placetype":"locality"
},
  "geometry": {"coordinates":[5.79224,13.56519],"type":"Point"}
}