{
  "type": "Feature",
  "properties": {
    "gn:admin1_code":"22.0",
    "gn:admin2_code":"9003.0",
    "gn:asciiname":"Ikot Offiong",
    "gn:country_code":"NG",
    "gn:dem":64,
    "gn:feature_class":"P",
    "gn:feature_code":"PPL",
    "gn:name":"Ikot Offiong",
    "gn:population":0,
    "gn:timezone":"Africa/Lagos",
    "iso:country":"NG",
    "name:und_x_variant":[
        "Ikot Offiong Ambai",
        "Ikot Offiong Mbia",
        "Ikot Offiong"
    ],
    "wof:name":"Ikot Offiong",
    "wof:placetype":"locality"
},
  "geometry": {"coordinates":[8.4215,4.9331],"type":"Point"}
}