{
  "type": "Feature",
  "properties": {
    "gn:admin1_code":"23.0",
    "gn:admin2_code":"19002.0",
    "gn:admin3_code":"KD0202",
    "gn:asciiname":"Kubusupe",
    "gn:country_code":"NG",
    "gn:dem":488,
    "gn:feature_class":"P",
    "gn:feature_code":"PPL",
    "gn:name":"Kubusupe",
    "gn:population":0,
    "gn:timezone":"Africa/Lagos",
    "iso:country":"NG",
    "wof:name":"Kubusupe",
    "wof:placetype":"locality"
},
  "geometry": {"coordinates":[7.18333,10.251],"type":"Point"}
}