{
  "type": "Feature",
  "properties": {
    "gn:admin1_code":"26.0",
    "gn:admin2_code":"7005.0",
    "gn:asciiname":"Berka",
    "gn:country_code":"NG",
    "gn:dem":130,
    "gn:feature_class":"P",
    "gn:feature_code":"PPL",
    "gn:name":"Berka",
    "gn:population":0,
    "gn:timezone":"Africa/Lagos",
    "iso:country":"NG",
    "name:ces_x_preferred":[
        "Berka"
    ],
    "name:deu_x_preferred":[
        "Berka"
    ],
    "name:epo_x_preferred":[
        "Berka"
    ],
    "name:fra_x_preferred":[
        "Berka"
    ],
    "name:ita_x_preferred":[
        "Berka"
    ],
    "name:jpn_x_preferred":[
        "\u30d9\u30eb\u30ab"
    ],
    "name:pol_x_preferred":[
        "Berka"
    ],
    "name:srp_x_preferred":[
        "\u0411\u0435\u0440\u043a\u0430"
    ],
    "wof:name":"Berka",
    "wof:placetype":"locality"
},
  "geometry": {"coordinates":[8.82522,7.25461],"type":"Point"}
}