{
  "type": "Feature",
  "properties": {
    "gn:admin1_code":"26.0",
    "gn:admin2_code":"7021",
    "gn:asciiname":"Hwange",
    "gn:country_code":"NG",
    "gn:dem":176,
    "gn:feature_class":"P",
    "gn:feature_code":"PPL",
    "gn:name":"Hwange",
    "gn:population":0,
    "gn:timezone":"Africa/Lagos",
    "iso:country":"NG",
    "name:afr_x_preferred":[
        "Hwange"
    ],
    "name:bar_x_preferred":[
        "Hwange"
    ],
    "name:ceb_x_preferred":[
        "Hwange"
    ],
    "name:dan_x_preferred":[
        "Hwange"
    ],
    "name:deu_x_preferred":[
        "Hwange"
    ],
    "name:fin_x_preferred":[
        "Hwange"
    ],
    "name:fra_x_preferred":[
        "Hwange"
    ],
    "name:ita_x_preferred":[
        "Hwange"
    ],
    "name:lit_x_preferred":[
        "Hvang\u0117"
    ],
    "name:nld_x_preferred":[
        "Hwange"
    ],
    "name:nor_x_preferred":[
        "Hwange"
    ],
    "name:pol_x_preferred":[
        "Hwange"
    ],
    "name:por_x_preferred":[
        "Hwange"
    ],
    "name:ron_x_preferred":[
        "Hwange"
    ],
    "name:rus_x_preferred":[
        "\u0425\u0432\u0430\u043d\u0433\u0435"
    ],
    "name:spa_x_preferred":[
        "Hwange"
    ],
    "name:srp_x_preferred":[
        "\u0425\u0432\u0430\u043d\u0433\u0435"
    ],
    "name:ukr_x_preferred":[
        "\u0425\u0432\u0430\u043d\u0433\u0435"
    ],
    "wof:name":"Hwange",
    "wof:placetype":"locality"
},
  "geometry": {"coordinates":[9.38526,7.73803],"type":"Point"}
}