{
  "type": "Feature",
  "properties": {
    "gn:admin1_code":"26.0",
    "gn:admin2_code":"7021",
    "gn:asciiname":"Hwange",
    "gn:country_code":"NG",
    "gn:dem":176,
    "gn:feature_class":"P",
    "gn:feature_code":"PPL",
    "gn:name":"Hwange",
    "gn:population":0,
    "gn:timezone":"Africa/Lagos",
    "iso:country":"NG",
    "name:afr_x_preferred":[
        "Hwange"
    ],
    "name:bar_x_preferred":[
        "Hwange"
    ],
    "name:ben_x_preferred":[
        "\u09b9\u09cb\u09df\u09be\u0982\u0997\u09c7"
    ],
    "name:ceb_x_preferred":[
        "Hwange"
    ],
    "name:dan_x_preferred":[
        "Hwange"
    ],
    "name:deu_x_preferred":[
        "Hwange"
    ],
    "name:ell_x_preferred":[
        "\u03a7\u03bf\u03c5\u03ac\u03bd\u03b3\u03ba\u03b5"
    ],
    "name:fas_x_preferred":[
        "\u0647\u0648\u0627\u0646\u06af"
    ],
    "name:fin_x_preferred":[
        "Hwange"
    ],
    "name:fra_x_preferred":[
        "Hwange"
    ],
    "name:heb_x_preferred":[
        "\u05d7\u05d5\u05d5\u05e0\u05d2\u05d4"
    ],
    "name:hin_x_preferred":[
        "\u0939\u094d\u0935\u093e\u0902\u0917\u0947"
    ],
    "name:hun_x_preferred":[
        "Hwange"
    ],
    "name:ind_x_preferred":[
        "Hwange"
    ],
    "name:ita_x_preferred":[
        "Hwange"
    ],
    "name:lit_x_preferred":[
        "Hvang\u0117"
    ],
    "name:nld_x_preferred":[
        "Hwange"
    ],
    "name:nor_x_preferred":[
        "Hwange"
    ],
    "name:pol_x_preferred":[
        "Hwange"
    ],
    "name:por_x_preferred":[
        "Hwange"
    ],
    "name:ron_x_preferred":[
        "Hwange"
    ],
    "name:rus_x_preferred":[
        "\u0425\u0432\u0430\u043d\u0433\u0435"
    ],
    "name:spa_x_preferred":[
        "Hwange"
    ],
    "name:srp_x_preferred":[
        "\u0425\u0432\u0430\u043d\u0433\u0435"
    ],
    "name:swe_x_preferred":[
        "Hwange"
    ],
    "name:tur_x_preferred":[
        "Hwange"
    ],
    "name:ukr_x_preferred":[
        "\u0425\u0432\u0430\u043d\u0433\u0435"
    ],
    "name:urd_x_preferred":[
        "\u06c1\u0648\u0627\u0646\u062c\u06d2"
    ],
    "name:vie_x_preferred":[
        "Hwange"
    ],
    "wof:name":"Hwange",
    "wof:placetype":"locality"
},
  "geometry": {"coordinates":[9.38526,7.73803],"type":"Point"}
}