{
  "type": "Feature",
  "properties": {
    "gn:admin1_code":"46.0",
    "gn:admin2_code":"5020.0",
    "gn:admin3_code":"BA2006",
    "gn:asciiname":"Gumai",
    "gn:country_code":"NG",
    "gn:dem":369,
    "gn:feature_class":"P",
    "gn:feature_code":"PPL",
    "gn:name":"Gumai",
    "gn:population":0,
    "gn:timezone":"Africa/Lagos",
    "iso:country":"NG",
    "wof:name":"Gumai",
    "wof:placetype":"locality"
},
  "geometry": {"coordinates":[10.3321,12.0367],"type":"Point"}
}