{
  "type": "Feature",
  "properties": {
    "gn:admin1_code":"43.0",
    "gn:admin2_code":"35009.0",
    "gn:asciiname":"Maiyanga",
    "gn:country_code":"NG",
    "gn:dem":284,
    "gn:feature_class":"P",
    "gn:feature_code":"PPL",
    "gn:name":"Maiyanga",
    "gn:population":0,
    "gn:timezone":"Africa/Lagos",
    "iso:country":"NG",
    "wof:name":"Maiyanga",
    "wof:placetype":"locality"
},
  "geometry": {"coordinates":[10.75651,7.01118],"type":"Point"}
}