{
  "type": "Feature",
  "properties": {
    "gn:admin1_code":"57.0",
    "gn:admin2_code":"805.0",
    "gn:admin3_code":"80508",
    "gn:asciiname":"Tudu",
    "gn:country_code":"NG",
    "gn:dem":428,
    "gn:feature_class":"P",
    "gn:feature_code":"PPL",
    "gn:name":"Tudu",
    "gn:population":0,
    "gn:timezone":"Africa/Lagos",
    "iso:country":"NG",
    "name:und_x_variant":[
        "Unguwar Tudu",
        "Tudu"
    ],
    "wof:name":"Tudu",
    "wof:placetype":"locality"
},
  "geometry": {"coordinates":[6.50454,12.36299],"type":"Point"}
}