{
  "type": "Feature",
  "properties": {
    "gn:admin1_code":"29.0",
    "gn:admin2_code":"20016.0",
    "gn:admin3_code":"KN1308",
    "gn:asciiname":"Yaranchi",
    "gn:country_code":"NG",
    "gn:dem":439,
    "gn:feature_class":"P",
    "gn:feature_code":"PPL",
    "gn:name":"Yaranchi",
    "gn:population":0,
    "gn:timezone":"Africa/Lagos",
    "iso:country":"NG",
    "wof:name":"Yaranchi",
    "wof:placetype":"locality"
},
  "geometry": {"coordinates":[8.75584,12.16779],"type":"Point"}
}