{
  "type": "Feature",
  "properties": {
    "gn:admin1_code":"23.0",
    "gn:admin2_code":"19008.0",
    "gn:admin3_code":"KD0802",
    "gn:asciiname":"Gidana-Yanmu",
    "gn:country_code":"NG",
    "gn:dem":725,
    "gn:feature_class":"P",
    "gn:feature_code":"PPL",
    "gn:name":"Gidana-Yanmu",
    "gn:population":0,
    "gn:timezone":"Africa/Lagos",
    "iso:country":"NG",
    "wof:name":"Gidana-Yanmu",
    "wof:placetype":"locality"
},
  "geometry": {"coordinates":[7.83922,9.87216],"type":"Point"}
}