{
  "type": "Feature",
  "properties": {
    "gn:admin1_code":"21.0",
    "gn:admin2_code":"3012.0",
    "gn:asciiname":"Usuk Obio Ediene",
    "gn:country_code":"NG",
    "gn:dem":78,
    "gn:feature_class":"P",
    "gn:feature_code":"PPL",
    "gn:name":"Usuk Obio Ediene",
    "gn:population":0,
    "gn:timezone":"Africa/Lagos",
    "iso:country":"NG",
    "wof:name":"Usuk Obio Ediene",
    "wof:placetype":"locality"
},
  "geometry": {"coordinates":[7.83082,5.22619],"type":"Point"}
}