{
  "type": "Feature",
  "properties": {
    "gn:admin1_code":"24.0",
    "gn:admin2_code":"430.0",
    "gn:admin3_code":"43008",
    "gn:asciiname":"Yanabu",
    "gn:country_code":"NG",
    "gn:dem":486,
    "gn:feature_class":"P",
    "gn:feature_code":"PPL",
    "gn:name":"Yanabu",
    "gn:population":0,
    "gn:timezone":"Africa/Lagos",
    "iso:country":"NG",
    "wof:name":"Yanabu",
    "wof:placetype":"locality"
},
  "geometry": {"coordinates":[7.73623,12.87809],"type":"Point"}
}