{
  "type": "Feature",
  "properties": {
    "gn:admin1_code":"27.0",
    "gn:admin2_code":"106.0",
    "gn:admin3_code":"10605",
    "gn:asciiname":"Yarchida",
    "gn:country_code":"NG",
    "gn:dem":455,
    "gn:feature_class":"P",
    "gn:feature_code":"PPL",
    "gn:name":"Yarchida",
    "gn:population":0,
    "gn:timezone":"Africa/Lagos",
    "iso:country":"NG",
    "wof:name":"Yarchida",
    "wof:placetype":"locality"
},
  "geometry": {"coordinates":[12.71819,10.90391],"type":"Point"}
}