{
  "type": "Feature",
  "properties": {
    "gn:admin1_code":"45.0",
    "gn:admin2_code":"1001.0",
    "gn:asciiname":"Ariaria",
    "gn:country_code":"NG",
    "gn:dem":54,
    "gn:feature_class":"P",
    "gn:feature_code":"PPL",
    "gn:name":"Ariaria",
    "gn:population":0,
    "gn:timezone":"Africa/Lagos",
    "iso:country":"NG",
    "wof:name":"Ariaria",
    "wof:placetype":"neighbourhood"
},
  "geometry": {"coordinates":[7.33232,5.10636],"type":"Point"}
}