{
  "type": "Feature",
  "properties": {
    "gn:admin1_code":"35.0",
    "gn:admin2_code":"2001.0",
    "gn:asciiname":"Bille",
    "gn:country_code":"NG",
    "gn:dem":252,
    "gn:feature_class":"P",
    "gn:feature_code":"PPL",
    "gn:name":"Bille",
    "gn:population":0,
    "gn:timezone":"Africa/Lagos",
    "iso:country":"NG",
    "name:ceb_x_preferred":[
        "Bille"
    ],
    "name:dan_x_preferred":[
        "Bille"
    ],
    "name:deu_x_preferred":[
        "Bille"
    ],
    "name:eng_x_preferred":[
        "Bille"
    ],
    "name:fra_x_preferred":[
        "Bille"
    ],
    "name:ita_x_preferred":[
        "Bille"
    ],
    "name:nds_x_preferred":[
        "Bille"
    ],
    "name:pol_x_preferred":[
        "Bille"
    ],
    "name:rus_x_preferred":[
        "\u0411\u0438\u043b\u043b\u0435"
    ],
    "wof:name":"Bille",
    "wof:placetype":"locality"
},
  "geometry": {"coordinates":[11.89992,9.26409],"type":"Point"}
}