{
  "type": "Feature",
  "properties": {
    "gn:admin1_code":"35.0",
    "gn:admin2_code":"2007.0",
    "gn:asciiname":"Dzakwa",
    "gn:country_code":"NG",
    "gn:dem":526,
    "gn:feature_class":"P",
    "gn:feature_code":"PPL",
    "gn:name":"Dzakwa",
    "gn:population":0,
    "gn:timezone":"Africa/Lagos",
    "iso:country":"NG",
    "wof:name":"Dzakwa",
    "wof:placetype":"locality"
},
  "geometry": {"coordinates":[13.16084,10.35731],"type":"Point"}
}