{
  "type": "Feature",
  "properties": {
    "gn:admin1_code":"26.0",
    "gn:admin2_code":"7006.0",
    "gn:asciiname":"Jorbuntu",
    "gn:country_code":"NG",
    "gn:dem":155,
    "gn:feature_class":"P",
    "gn:feature_code":"PPL",
    "gn:name":"Jorbuntu",
    "gn:population":0,
    "gn:timezone":"Africa/Lagos",
    "iso:country":"NG",
    "wof:name":"Jorbuntu",
    "wof:placetype":"locality"
},
  "geometry": {"coordinates":[8.63166,7.92753],"type":"Point"}
}