{
  "type": "Feature",
  "properties": {
    "gn:admin1_code":"45.0",
    "gn:admin2_code":"1003.0",
    "gn:asciiname":"Obiakang",
    "gn:country_code":"NG",
    "gn:dem":23,
    "gn:feature_class":"P",
    "gn:feature_code":"PPL",
    "gn:name":"Obiakang",
    "gn:population":0,
    "gn:timezone":"Africa/Lagos",
    "iso:country":"NG",
    "wof:name":"Obiakang",
    "wof:placetype":"locality"
},
  "geometry": {"coordinates":[7.84434,5.45061],"type":"Point"}
}