{
  "type": "Feature",
  "properties": {
    "gn:admin1_code":"46.0",
    "gn:asciiname":"Garin Hamse",
    "gn:country_code":"NG",
    "gn:dem":427,
    "gn:feature_class":"P",
    "gn:feature_code":"PPL",
    "gn:name":"Garin Hamse",
    "gn:population":0,
    "gn:timezone":"Africa/Lagos",
    "iso:country":"NG",
    "name:eng_x_preferred":[
        "Garin Hamse"
    ],
    "name:eng_x_variant":[
        "Garin Hamza",
        "Hamza"
    ],
    "wof:name":"Garin Hamse",
    "wof:placetype":"locality"
},
  "geometry": {"coordinates":[10.91985,9.87858],"type":"Point"}
}