{
  "type": "Feature",
  "properties": {
    "gn:admin1_code":"43.0",
    "gn:admin2_code":"35008.0",
    "gn:asciiname":"Ndela",
    "gn:country_code":"NG",
    "gn:dem":288,
    "gn:feature_class":"P",
    "gn:feature_code":"PPL",
    "gn:name":"Ndela",
    "gn:population":0,
    "gn:timezone":"Africa/Lagos",
    "iso:country":"NG",
    "name:eng_x_preferred":[
        "Ndela"
    ],
    "wof:name":"Ndela",
    "wof:placetype":"locality"
},
  "geometry": {"coordinates":[10.77045,9.391],"type":"Point"}
}