{
  "type": "Feature",
  "properties": {
    "gn:admin1_code":"35.0",
    "gn:admin2_code":"2019.0",
    "gn:asciiname":"Lanzan",
    "gn:country_code":"NG",
    "gn:dem":438,
    "gn:feature_class":"P",
    "gn:feature_code":"PPL",
    "gn:name":"Lanzan",
    "gn:population":0,
    "gn:timezone":"Africa/Lagos",
    "iso:country":"NG",
    "wof:name":"Lanzan",
    "wof:placetype":"locality"
},
  "geometry": {"coordinates":[11.78333,7.61667],"type":"Point"}
}