{
  "type": "Feature",
  "properties": {
    "gn:admin1_code":"53.0",
    "gn:admin2_code":"11010",
    "gn:asciiname":"Ndiabo Isiagu",
    "gn:country_code":"NG",
    "gn:dem":55,
    "gn:feature_class":"P",
    "gn:feature_code":"PPL",
    "gn:name":"Ndiabo Isiagu",
    "gn:population":0,
    "gn:timezone":"Africa/Lagos",
    "iso:country":"NG",
    "wof:name":"Ndiabo Isiagu",
    "wof:placetype":"locality"
},
  "geometry": {"coordinates":[8.18159,6.35624],"type":"Point"}
}