{
  "type": "Feature",
  "properties": {
    "gn:admin1_code":"5.0",
    "gn:admin2_code":"25015.0",
    "gn:asciiname":"Mebamu",
    "gn:country_code":"NG",
    "gn:dem":9,
    "gn:feature_class":"P",
    "gn:feature_code":"PPL",
    "gn:name":"Mebamu",
    "gn:population":0,
    "gn:timezone":"Africa/Lagos",
    "iso:country":"NG",
    "wof:name":"Mebamu",
    "wof:placetype":"neighbourhood"
},
  "geometry": {"coordinates":[3.17299,6.47745],"type":"Point"}
}