{
  "type": "Feature",
  "properties": {
    "gn:admin1_code":"53.0",
    "gn:admin2_code":"11001",
    "gn:asciiname":"Ochobo",
    "gn:country_code":"NG",
    "gn:dem":66,
    "gn:feature_class":"P",
    "gn:feature_code":"PPL",
    "gn:name":"Ochobo",
    "gn:population":0,
    "gn:timezone":"Africa/Lagos",
    "iso:country":"NG",
    "wof:name":"Ochobo",
    "wof:placetype":"locality"
},
  "geometry": {"coordinates":[8.2549,6.27626],"type":"Point"}
}