{
  "type": "Feature",
  "properties": {
    "gn:gn_country":"NG",
    "gn:gn_fcode":"PPL",
    "gn:gn_pop":10602,
    "gn:population":10602,
    "iso:country":"NG",
    "name:cat_x_preferred":[
        "Katagum"
    ],
    "name:eng_x_preferred":[
        "Katagum"
    ],
    "name:fra_x_preferred":[
        "Katagum"
    ],
    "name:ita_x_preferred":[
        "Katagum"
    ],
    "name:yor_x_preferred":[
        "Agb\u00e8gb\u00e8 \u00ccj\u1ecdba \u00ccb\u00edl\u1eb9\u0300 Katagum"
    ],
    "qs_pg:aaroncc":"NG",
    "qs_pg:gn_country":"NG",
    "qs_pg:gn_fcode":"PPL",
    "qs_pg:gn_pop":10602,
    "qs_pg:name":"Katagum",
    "qs_pg:photos_9r":0,
    "qs_pg:photos_sr":0,
    "qs_pg:pop_sr":6,
    "qs_pg:qs_pg_placetype":"locality",
    "wof:name":"Katagum",
    "wof:placetype":"locality",
    "wof:population":10602
},
  "geometry": {"coordinates":[10.3527,12.2867],"type":"Point"}
}