{
  "type": "Feature",
  "properties": {
    "gn:admin1_code":"48.0",
    "gn:admin2_code":"29017.0",
    "gn:asciiname":"Idoani",
    "gn:country_code":"NG",
    "gn:dem":337,
    "gn:feature_class":"P",
    "gn:feature_code":"PPL",
    "gn:name":"Idoani",
    "gn:population":0,
    "gn:timezone":"Africa/Lagos",
    "iso:country":"NG",
    "wof:name":"Idoani",
    "wof:placetype":"locality"
},
  "geometry": {"coordinates":[5.84688,7.29604],"type":"Point"}
}