{
  "type": "Feature",
  "properties": {
    "gn:admin1_code":"28.0",
    "gn:admin2_code":"17019.0",
    "gn:asciiname":"Ihube",
    "gn:country_code":"NG",
    "gn:dem":233,
    "gn:feature_class":"P",
    "gn:feature_code":"PPL",
    "gn:name":"Ihube",
    "gn:population":0,
    "gn:timezone":"Africa/Lagos",
    "iso:country":"NG",
    "wof:name":"Ihube",
    "wof:placetype":"locality"
},
  "geometry": {"coordinates":[7.37373,5.86112],"type":"Point"}
}