{
  "type": "Feature",
  "properties": {
    "gn:admin1_code":"23.0",
    "gn:admin2_code":"19003.0",
    "gn:admin3_code":"KD0305",
    "gn:asciiname":"Daudu Kashabushi",
    "gn:country_code":"NG",
    "gn:dem":651,
    "gn:feature_class":"P",
    "gn:feature_code":"PPL",
    "gn:name":"Daudu Kashabushi",
    "gn:population":0,
    "gn:timezone":"Africa/Lagos",
    "iso:country":"NG",
    "wof:name":"Daudu Kashabushi",
    "wof:placetype":"locality"
},
  "geometry": {"coordinates":[7.00608,11.12596],"type":"Point"}
}