{
  "type": "Feature",
  "properties": {
    "gn:admin1_code":"35.0",
    "gn:asciiname":"Bilale",
    "gn:country_code":"NG",
    "gn:dem":165,
    "gn:feature_class":"P",
    "gn:feature_code":"PPL",
    "gn:name":"Bilale",
    "gn:population":0,
    "gn:timezone":"Africa/Lagos",
    "iso:country":"NG",
    "name:eng_x_preferred":[
        "Bilale"
    ],
    "wof:name":"Bilale",
    "wof:placetype":"locality"
},
  "geometry": {"coordinates":[12.42135,9.35333],"type":"Point"}
}