{
  "type": "Feature",
  "properties": {
    "gn:admin1_code":"35.0",
    "gn:admin2_code":"2012.0",
    "gn:asciiname":"Lamja",
    "gn:country_code":"NG",
    "gn:dem":394,
    "gn:feature_class":"P",
    "gn:feature_code":"PPL",
    "gn:name":"Lamja",
    "gn:population":0,
    "gn:timezone":"Africa/Lagos",
    "iso:country":"NG",
    "name:und_x_variant":[
        "Lamia",
        "Lamja"
    ],
    "wof:name":"Lamja",
    "wof:placetype":"locality"
},
  "geometry": {"coordinates":[12.00414,8.90974],"type":"Point"}
}