{
  "type": "Feature",
  "properties": {
    "gn:admin1_code":"31.0",
    "gn:admin2_code":"27013.0",
    "gn:asciiname":"Dagidda",
    "gn:country_code":"NG",
    "gn:dem":158,
    "gn:feature_class":"P",
    "gn:feature_code":"PPL",
    "gn:name":"Dagidda",
    "gn:population":0,
    "gn:timezone":"Africa/Lagos",
    "iso:country":"NG",
    "wof:name":"Dagidda",
    "wof:placetype":"locality"
},
  "geometry": {"coordinates":[5.53506,9.68704],"type":"Point"}
}