{
  "type": "Feature",
  "properties": {
    "iso:country":"NG",
    "name:chi_x_preferred":[
        "\u5091\u5df4"
    ],
    "name:deu_x_preferred":[
        "Jebba"
    ],
    "name:dut_x_preferred":[
        "Jebba"
    ],
    "name:eng_x_preferred":[
        "Jebba"
    ],
    "name:ger_x_preferred":[
        "Jebba"
    ],
    "name:pol_x_preferred":[
        "Jebba"
    ],
    "name:ron_x_preferred":[
        "Jebba"
    ],
    "name:rum_x_preferred":[
        "Jebba"
    ],
    "name:unk_x_variant":[
        "Djebba"
    ],
    "name:yor_x_preferred":[
        "Jebba"
    ],
    "qs:gn_country":"NG",
    "qs:gn_fcode":"PPL",
    "qs:gn_pop":21488,
    "qs:name":"Jebba",
    "qs:name_adm0":"Nigeria",
    "qs:name_adm1":"Kwara",
    "qs:photos":0,
    "qs:photos_1k":0,
    "qs:photos_9k":1,
    "qs:photos_9r":1,
    "qs:photos_all":4,
    "qs:photos_sr":0,
    "qs:placetype":"Town",
    "qs:pop_sr":"7",
    "qs:woe_adm0":23424908,
    "wd:wordcount":1242,
    "wof:name":"Jebba",
    "wof:placetype":"locality",
    "wof:population":21488
},
  "geometry": {"coordinates":[4.83333,9.13333],"type":"Point"}
}