{
  "type": "Feature",
  "properties": {
    "iso:country":"NG",
    "name:ceb_x_preferred":[
        "Ankpa"
    ],
    "name:eng_x_preferred":[
        "Ankpa"
    ],
    "name:fra_x_preferred":[
        "Ankpa"
    ],
    "name:hau_x_preferred":[
        "Ankpa"
    ],
    "name:ibo_x_preferred":[
        "Ankpa"
    ],
    "name:ita_x_preferred":[
        "Ankpa"
    ],
    "name:nan_x_preferred":[
        "Ankpa"
    ],
    "name:pol_x_preferred":[
        "Ankpa"
    ],
    "name:spa_x_preferred":[
        "Ankpa"
    ],
    "name:und_x_variant":[
        "Ank"
    ],
    "name:yor_x_preferred":[
        "Agb\u00e8gb\u00e8 \u00ccj\u1ecdba \u00ccb\u00edl\u1eb9\u0300 Ankpa"
    ],
    "name:zho_min_nan_x_preferred":[
        "Ankpa"
    ],
    "qs:gn_country":"NG",
    "qs:gn_fcode":"PPL",
    "qs:gn_pop":14630,
    "qs:name":"Ankpa",
    "qs:name_adm0":"Nigeria",
    "qs:name_adm1":"Kogi",
    "qs:photos":0,
    "qs:photos_1k":0,
    "qs:photos_9k":1,
    "qs:photos_9r":1,
    "qs:photos_all":1,
    "qs:photos_sr":0,
    "qs:placetype":"Town",
    "qs:pop_sr":"6",
    "qs:woe_adm0":23424908,
    "wd:wordcount":101,
    "wof:name":"Ankpa",
    "wof:placetype":"locality",
    "wof:population":14630
},
  "geometry": {"coordinates":[7.6253,7.37058],"type":"Point"}
}