{
  "type": "Feature",
  "properties": {
    "gn:admin1_code":"39.0",
    "gn:admin2_code":"18010.0",
    "gn:admin3_code":"JI1704",
    "gn:asciiname":"Ungua Ballami",
    "gn:country_code":"NG",
    "gn:dem":409,
    "gn:feature_class":"P",
    "gn:feature_code":"PPL",
    "gn:name":"Ungua Ballami",
    "gn:population":0,
    "gn:timezone":"Africa/Lagos",
    "iso:country":"NG",
    "wof:name":"Ungua Ballami",
    "wof:placetype":"locality"
},
  "geometry": {"coordinates":[8.63927,12.61466],"type":"Point"}
}