{
  "type": "Feature",
  "properties": {
    "gn:admin1_code":"24.0",
    "gn:asciiname":"Musawa",
    "gn:country_code":"NG",
    "gn:dem":651,
    "gn:feature_class":"P",
    "gn:feature_code":"PPL",
    "gn:name":"Musawa",
    "gn:population":0,
    "gn:timezone":"Africa/Lagos",
    "iso:country":"NG",
    "name:ceb_x_preferred":[
        "Musawa"
    ],
    "name:fra_x_preferred":[
        "Musawa"
    ],
    "name:hau_x_preferred":[
        "Musawa"
    ],
    "name:ita_x_preferred":[
        "Musawa"
    ],
    "name:spa_x_preferred":[
        "Musawa"
    ],
    "wof:name":"Musawa",
    "wof:placetype":"locality"
},
  "geometry": {"coordinates":[7.67293,11.23715],"type":"Point"}
}