{
  "type": "Feature",
  "properties": {
    "gn:admin1_code":"42.0",
    "gn:admin2_code":"30010.0",
    "gn:asciiname":"Iwata",
    "gn:country_code":"NG",
    "gn:dem":322,
    "gn:feature_class":"P",
    "gn:feature_code":"PPL",
    "gn:name":"Iwata",
    "gn:population":0,
    "gn:timezone":"Africa/Lagos",
    "iso:country":"NG",
    "wof:name":"Iwata",
    "wof:placetype":"locality"
},
  "geometry": {"coordinates":[4.28333,7.86667],"type":"Point"}
}