{
  "type": "Feature",
  "properties": {
    "gn:admin1_code":"42.0",
    "gn:admin2_code":"30010.0",
    "gn:asciiname":"Iwata",
    "gn:country_code":"NG",
    "gn:dem":322,
    "gn:feature_class":"P",
    "gn:feature_code":"PPL",
    "gn:name":"Iwata",
    "gn:population":0,
    "gn:timezone":"Africa/Lagos",
    "iso:country":"NG",
    "name:deu_x_preferred":[
        "Iwata"
    ],
    "name:fra_x_preferred":[
        "Iwata"
    ],
    "name:ind_x_preferred":[
        "Iwata"
    ],
    "name:ita_x_preferred":[
        "Iwata"
    ],
    "name:kor_x_preferred":[
        "\uc774\uc640\ud0c0"
    ],
    "name:nld_x_preferred":[
        "Iwata"
    ],
    "name:rus_x_preferred":[
        "\u0418\u0432\u0430\u0442\u0430"
    ],
    "wof:name":"Iwata",
    "wof:placetype":"locality"
},
  "geometry": {"coordinates":[4.28333,7.86667],"type":"Point"}
}