{
  "type": "Feature",
  "properties": {
    "gn:admin1_code":"11.0",
    "gn:admin2_code":"15004.0",
    "gn:asciiname":"Kuje",
    "gn:country_code":"NG",
    "gn:dem":300,
    "gn:feature_class":"P",
    "gn:feature_code":"PPLA2",
    "gn:name":"Kuje",
    "gn:population":97367,
    "gn:timezone":"Africa/Lagos",
    "iso:country":"NG",
    "wof:name":"Kuje",
    "wof:placetype":"locality",
    "wof:population":97367
},
  "geometry": {"coordinates":[7.22756,8.87952],"type":"Point"}
}