{
  "type": "Feature",
  "properties": {
    "gn:admin1_code":"31.0",
    "gn:admin2_code":"27004.0",
    "gn:asciiname":"Tugan Arawa",
    "gn:country_code":"NG",
    "gn:dem":246,
    "gn:feature_class":"P",
    "gn:feature_code":"PPL",
    "gn:name":"Tugan Arawa",
    "gn:population":0,
    "gn:timezone":"Africa/Lagos",
    "iso:country":"NG",
    "wof:name":"Tugan Arawa",
    "wof:placetype":"locality"
},
  "geometry": {"coordinates":[4.25303,10.88034],"type":"Point"}
}