{
  "type": "Feature",
  "properties": {
    "gn:admin1_code":"46.0",
    "gn:admin2_code":"5008.0",
    "gn:admin3_code":"BA0804",
    "gn:asciiname":"Jangu",
    "gn:country_code":"NG",
    "gn:dem":505,
    "gn:feature_class":"P",
    "gn:feature_code":"PPL",
    "gn:name":"Jangu",
    "gn:population":0,
    "gn:timezone":"Africa/Lagos",
    "iso:country":"NG",
    "wof:name":"Jangu",
    "wof:placetype":"locality"
},
  "geometry": {"coordinates":[9.58717,10.78232],"type":"Point"}
}