{
  "type": "Feature",
  "properties": {
    "gn:admin1_code":"16.0",
    "gn:admin2_code":"28014.0",
    "gn:asciiname":"Idomogu",
    "gn:cc2":"NG",
    "gn:country_code":"NG",
    "gn:dem":90,
    "gn:feature_class":"P",
    "gn:feature_code":"PPL",
    "gn:name":"Idomogu",
    "gn:population":0,
    "gn:timezone":"Africa/Lagos",
    "iso:country":"NG",
    "name:und_x_variant":[
        "Dologu",
        "Idomogu"
    ],
    "wof:name":"Idomogu",
    "wof:placetype":"locality"
},
  "geometry": {"coordinates":[2.78333,6.76667],"type":"Point"}
}