{
  "type": "Feature",
  "properties": {
    "gn:admin1_code":"16.0",
    "gn:admin2_code":"28001.0",
    "gn:asciiname":"Idigba Okeata",
    "gn:country_code":"NG",
    "gn:dem":60,
    "gn:feature_class":"P",
    "gn:feature_code":"PPL",
    "gn:name":"Idigba Okeata",
    "gn:population":0,
    "gn:timezone":"Africa/Lagos",
    "iso:country":"NG",
    "wof:name":"Idigba Okeata",
    "wof:placetype":"locality"
},
  "geometry": {"coordinates":[3.26667,7.15],"type":"Point"}
}