{
  "type": "Feature",
  "properties": {
    "gn:admin1_code":"29.0",
    "gn:admin2_code":"20017.0",
    "gn:admin3_code":"KN1908",
    "gn:asciiname":"Zangarmawa",
    "gn:country_code":"NG",
    "gn:dem":585,
    "gn:feature_class":"P",
    "gn:feature_code":"PPL",
    "gn:name":"Zangarmawa",
    "gn:population":0,
    "gn:timezone":"Africa/Lagos",
    "iso:country":"NG",
    "wof:name":"Zangarmawa",
    "wof:placetype":"locality"
},
  "geometry": {"coordinates":[7.88536,11.93421],"type":"Point"}
}