{
  "type": "Feature",
  "properties": {
    "gn:admin1_code":"46.0",
    "gn:admin2_code":"5011.0",
    "gn:admin3_code":"BA1112",
    "gn:asciiname":"Yangamaku",
    "gn:country_code":"NG",
    "gn:dem":404,
    "gn:feature_class":"P",
    "gn:feature_code":"PPL",
    "gn:name":"Yangamaku",
    "gn:population":0,
    "gn:timezone":"Africa/Lagos",
    "iso:country":"NG",
    "wof:name":"Yangamaku",
    "wof:placetype":"locality"
},
  "geometry": {"coordinates":[9.89962,11.66529],"type":"Point"}
}