{
  "type": "Feature",
  "properties": {
    "gn:admin1_code":"51.0",
    "gn:admin2_code":"608.0",
    "gn:admin3_code":"60801",
    "gn:asciiname":"Bakin Dutse",
    "gn:country_code":"NG",
    "gn:dem":286,
    "gn:feature_class":"P",
    "gn:feature_code":"PPL",
    "gn:name":"Bakin Dutse",
    "gn:population":0,
    "gn:timezone":"Africa/Lagos",
    "iso:country":"NG",
    "wof:name":"Bakin Dutse",
    "wof:placetype":"locality"
},
  "geometry": {"coordinates":[5.32592,13.76759],"type":"Point"}
}