{
  "type": "Feature",
  "properties": {
    "gn:admin1_code":"28.0",
    "gn:admin2_code":"17018.0",
    "gn:asciiname":"Abacheke",
    "gn:country_code":"NG",
    "gn:dem":20,
    "gn:feature_class":"P",
    "gn:feature_code":"PPL",
    "gn:name":"Abacheke",
    "gn:population":0,
    "gn:timezone":"Africa/Lagos",
    "iso:country":"NG",
    "wof:name":"Abacheke",
    "wof:placetype":"locality"
},
  "geometry": {"coordinates":[6.72952,5.50372],"type":"Point"}
}