{
  "type": "Feature",
  "properties": {
    "gn:admin1_code":"27.0",
    "gn:admin2_code":"111",
    "gn:admin3_code":"11104",
    "gn:asciiname":"Kughum",
    "gn:country_code":"NG",
    "gn:dem":503,
    "gn:feature_class":"P",
    "gn:feature_code":"PPL",
    "gn:name":"Kughum",
    "gn:population":0,
    "gn:timezone":"Africa/Lagos",
    "iso:country":"NG",
    "wof:name":"Kughum",
    "wof:placetype":"locality"
},
  "geometry": {"coordinates":[13.79582,11.028],"type":"Point"}
}