{
  "type": "Feature",
  "properties": {
    "gn:admin1_code":"46.0",
    "gn:admin2_code":"5016.0",
    "gn:admin3_code":"BA1601",
    "gn:asciiname":"Dindibus",
    "gn:country_code":"NG",
    "gn:dem":423,
    "gn:feature_class":"P",
    "gn:feature_code":"PPL",
    "gn:name":"Dindibus",
    "gn:population":0,
    "gn:timezone":"Africa/Lagos",
    "iso:country":"NG",
    "wof:name":"Dindibus",
    "wof:placetype":"locality"
},
  "geometry": {"coordinates":[9.80244,11.49404],"type":"Point"}
}