{
  "type": "Feature",
  "properties": {
    "gn:admin1_code":"26.0",
    "gn:admin2_code":"7007",
    "gn:asciiname":"Gwar",
    "gn:country_code":"NG",
    "gn:dem":195,
    "gn:feature_class":"P",
    "gn:feature_code":"PPL",
    "gn:name":"Gwar",
    "gn:population":0,
    "gn:timezone":"Africa/Lagos",
    "iso:country":"NG",
    "name:deu_x_preferred":[
        "Gwar"
    ],
    "name:ell_x_preferred":[
        "Gwar"
    ],
    "name:fra_x_preferred":[
        "Gwar"
    ],
    "name:jpn_x_preferred":[
        "\u30b0\u30ef\u30a1\u30fc"
    ],
    "name:pol_x_preferred":[
        "Gwar"
    ],
    "name:por_x_preferred":[
        "Gwar"
    ],
    "name:spa_x_preferred":[
        "Gwar"
    ],
    "wof:name":"Gwar",
    "wof:placetype":"locality"
},
  "geometry": {"coordinates":[8.4866,7.3152],"type":"Point"}
}