{
  "type": "Feature",
  "properties": {
    "gn:admin1_code":"40.0",
    "gn:admin2_code":"515.0",
    "gn:admin3_code":"51510",
    "gn:asciiname":"Tungan Kawo",
    "gn:country_code":"NG",
    "gn:dem":181,
    "gn:feature_class":"P",
    "gn:feature_code":"PPL",
    "gn:name":"Tungan Kawo",
    "gn:population":0,
    "gn:timezone":"Africa/Lagos",
    "iso:country":"NG",
    "wof:name":"Tungan Kawo",
    "wof:placetype":"locality"
},
  "geometry": {"coordinates":[4.65541,10.16743],"type":"Point"}
}