{
  "type": "Feature",
  "properties": {
    "gn:admin1_code":"39.0",
    "gn:admin2_code":"18004.0",
    "gn:admin3_code":"JI0211",
    "gn:asciiname":"Kankare Sarkin Gaya",
    "gn:country_code":"NG",
    "gn:dem":390,
    "gn:feature_class":"P",
    "gn:feature_code":"PPL",
    "gn:name":"Kankare Sarkin Gaya",
    "gn:population":0,
    "gn:timezone":"Africa/Lagos",
    "iso:country":"NG",
    "wof:name":"Kankare Sarkin Gaya",
    "wof:placetype":"locality"
},
  "geometry": {"coordinates":[8.91521,12.51957],"type":"Point"}
}