{
  "type": "Feature",
  "properties": {
    "gn:admin1_code":"50.0",
    "gn:admin2_code":"33011.0",
    "gn:asciiname":"Umu-Etchem",
    "gn:country_code":"NG",
    "gn:dem":29,
    "gn:feature_class":"P",
    "gn:feature_code":"PPL",
    "gn:name":"Umu-Etchem",
    "gn:population":0,
    "gn:timezone":"Africa/Lagos",
    "iso:country":"NG",
    "name:und_x_variant":[
        "Igrtia-Umuechem",
        "Umu-Etchem"
    ],
    "wof:name":"Umu-Etchem",
    "wof:placetype":"locality"
},
  "geometry": {"coordinates":[7.03192,5.00718],"type":"Point"}
}