{
  "type": "Feature",
  "properties": {
    "gn:admin1_code":"44.0",
    "gn:admin2_code":"705",
    "gn:admin3_code":"70510",
    "gn:asciiname":"Daura Kunu",
    "gn:country_code":"NG",
    "gn:dem":418,
    "gn:feature_class":"P",
    "gn:feature_code":"PPL",
    "gn:name":"Daura Kunu",
    "gn:population":0,
    "gn:timezone":"Africa/Lagos",
    "iso:country":"NG",
    "wof:name":"Daura Kunu",
    "wof:placetype":"locality"
},
  "geometry": {"coordinates":[11.29964,11.68194],"type":"Point"}
}