{
  "type": "Feature",
  "properties": {
    "gn:admin1_code":"43.0",
    "gn:admin2_code":"35012.0",
    "gn:asciiname":"Utser",
    "gn:country_code":"NG",
    "gn:dem":183,
    "gn:feature_class":"P",
    "gn:feature_code":"PPL",
    "gn:name":"Utser",
    "gn:population":0,
    "gn:timezone":"Africa/Lagos",
    "iso:country":"NG",
    "wof:name":"Utser",
    "wof:placetype":"locality"
},
  "geometry": {"coordinates":[10.05285,7.43385],"type":"Point"}
}