{
  "type": "Feature",
  "properties": {
    "gn:admin1_code":"35.0",
    "gn:admin2_code":"2018",
    "gn:asciiname":"Didango",
    "gn:country_code":"NG",
    "gn:dem":272,
    "gn:feature_class":"P",
    "gn:feature_code":"PPL",
    "gn:name":"Didango",
    "gn:population":0,
    "gn:timezone":"Africa/Lagos",
    "iso:country":"NG",
    "wof:name":"Didango",
    "wof:placetype":"locality"
},
  "geometry": {"coordinates":[13.02784,9.60689],"type":"Point"}
}