{
  "type": "Feature",
  "properties": {
    "gn:admin1_code":"57.0",
    "gn:admin2_code":"803.0",
    "gn:admin3_code":"80301",
    "gn:asciiname":"Makera",
    "gn:country_code":"NG",
    "gn:dem":439,
    "gn:feature_class":"P",
    "gn:feature_code":"PPL",
    "gn:name":"Makera",
    "gn:population":0,
    "gn:timezone":"Africa/Lagos",
    "iso:country":"NG",
    "name:und_x_variant":[
        "Unguwar Makera",
        "Makera"
    ],
    "wof:name":"Makera",
    "wof:placetype":"locality"
},
  "geometry": {"coordinates":[6.7983,12.42333],"type":"Point"}
}