{
  "type": "Feature",
  "properties": {
    "iso:country":"NG",
    "name:eng_x_preferred":[
        "Rano"
    ],
    "name:fra_x_preferred":[
        "Rano"
    ],
    "name:ita_x_preferred":[
        "Rano"
    ],
    "name:jpn_x_preferred":[
        "\u30e9\u30ce"
    ],
    "name:zho_min_nan_x_preferred":[
        "Rano"
    ],
    "qs:gn_country":"NG",
    "qs:gn_fcode":"PPL",
    "qs:gn_pop":17972,
    "qs:name":"Rano",
    "qs:name_adm0":"Nigeria",
    "qs:name_adm1":"Kano",
    "qs:photos":0,
    "qs:photos_1k":0,
    "qs:photos_9k":1,
    "qs:photos_9r":1,
    "qs:photos_all":4,
    "qs:photos_sr":0,
    "qs:placetype":"Town",
    "qs:pop_sr":"6",
    "qs:woe_adm0":23424908,
    "wd:wordcount":70,
    "wof:name":"Rano",
    "wof:placetype":"locality",
    "wof:population":17972
},
  "geometry": {"coordinates":[8.57464,11.54912],"type":"Point"}
}