{
  "type": "Feature",
  "properties": {
    "gn:admin1_code":"40.0",
    "gn:admin2_code":"505.0",
    "gn:admin3_code":"50501",
    "gn:asciiname":"Tunga Baushe",
    "gn:country_code":"NG",
    "gn:dem":157,
    "gn:feature_class":"P",
    "gn:feature_code":"PPL",
    "gn:name":"Tunga Baushe",
    "gn:population":0,
    "gn:timezone":"Africa/Lagos",
    "iso:country":"NG",
    "wof:name":"Tunga Baushe",
    "wof:placetype":"locality"
},
  "geometry": {"coordinates":[4.18647,11.43326],"type":"Point"}
}