{
  "type": "Feature",
  "properties": {
    "gn:admin1_code":"26.0",
    "gn:admin2_code":"7007.0",
    "gn:asciiname":"Tseushir",
    "gn:country_code":"NG",
    "gn:dem":103,
    "gn:feature_class":"P",
    "gn:feature_code":"PPL",
    "gn:name":"Tseushir",
    "gn:population":0,
    "gn:timezone":"Africa/Lagos",
    "iso:country":"NG",
    "wof:name":"Tseushir",
    "wof:placetype":"locality"
},
  "geometry": {"coordinates":[8.35427,7.56269],"type":"Point"}
}