{
  "type": "Feature",
  "properties": {
    "gn:admin1_code":"35.0",
    "gn:asciiname":"Julde Kolere",
    "gn:country_code":"NG",
    "gn:dem":239,
    "gn:feature_class":"P",
    "gn:feature_code":"PPL",
    "gn:name":"Julde Kolere",
    "gn:population":0,
    "gn:timezone":"Africa/Lagos",
    "iso:country":"NG",
    "name:eng_x_preferred":[
        "Julde Kolere"
    ],
    "wof:name":"Julde Kolere",
    "wof:placetype":"locality"
},
  "geometry": {"coordinates":[12.03674,9.38686],"type":"Point"}
}