{
  "type": "Feature",
  "properties": {
    "gn:admin1_code":"11.0",
    "gn:admin2_code":"15003.0",
    "gn:asciiname":"Gunrafia",
    "gn:country_code":"NG",
    "gn:dem":180,
    "gn:feature_class":"P",
    "gn:feature_code":"PPL",
    "gn:name":"Gunrafia",
    "gn:population":0,
    "gn:timezone":"Africa/Lagos",
    "iso:country":"NG",
    "wof:name":"Gunrafia",
    "wof:placetype":"locality"
},
  "geometry": {"coordinates":[7.03333,8.97444],"type":"Point"}
}