{
  "type": "Feature",
  "properties": {
    "gn:admin1_code":"50.0",
    "gn:admin2_code":"33008.0",
    "gn:asciiname":"Bukuma",
    "gn:country_code":"NG",
    "gn:dem":9,
    "gn:feature_class":"P",
    "gn:feature_code":"PPL",
    "gn:name":"Bukuma",
    "gn:population":0,
    "gn:timezone":"Africa/Lagos",
    "iso:country":"NG",
    "wof:name":"Bukuma",
    "wof:placetype":"locality"
},
  "geometry": {"coordinates":[6.89146,4.76528],"type":"Point"}
}