{
  "type": "Feature",
  "properties": {
    "gn:admin1_code":"35.0",
    "gn:asciiname":"Samari",
    "gn:country_code":"NG",
    "gn:dem":465,
    "gn:feature_class":"P",
    "gn:feature_code":"PPL",
    "gn:name":"Samari",
    "gn:population":0,
    "gn:timezone":"Africa/Lagos",
    "iso:country":"NG",
    "name:ceb_x_preferred":[
        "Samari"
    ],
    "name:deu_x_preferred":[
        "Samari"
    ],
    "name:eng_x_preferred":[
        "Samari"
    ],
    "name:fra_x_preferred":[
        "Samari"
    ],
    "name:swe_x_preferred":[
        "Samari"
    ],
    "wof:name":"Samari",
    "wof:placetype":"locality"
},
  "geometry": {"coordinates":[11.78148,9.05867],"type":"Point"}
}