{
  "type": "Feature",
  "properties": {
    "gn:admin1_code":"43.0",
    "gn:admin2_code":"35007",
    "gn:asciiname":"Lamurde",
    "gn:country_code":"NG",
    "gn:dem":215,
    "gn:feature_class":"P",
    "gn:feature_code":"PPL",
    "gn:name":"Lamurde",
    "gn:population":0,
    "gn:timezone":"Africa/Lagos",
    "iso:country":"NG",
    "name:fra_x_preferred":[
        "Lamurde"
    ],
    "name:hau_x_preferred":[
        "Lamurde"
    ],
    "name:ita_x_preferred":[
        "Lamurde"
    ],
    "name:spa_x_preferred":[
        "Lamurde"
    ],
    "name:urd_x_preferred":[
        "\u0644\u0627\u0645\u0648\u0631\u0688\u06cc"
    ],
    "wof:name":"Lamurde",
    "wof:placetype":"locality"
},
  "geometry": {"coordinates":[11.3212,8.88738],"type":"Point"}
}