{
  "type": "Feature",
  "properties": {
    "gn:admin1_code":"51.0",
    "gn:admin2_code":"620.0",
    "gn:admin3_code":"62010",
    "gn:asciiname":"Tureta",
    "gn:country_code":"NG",
    "gn:dem":274,
    "gn:feature_class":"P",
    "gn:feature_code":"PPLA2",
    "gn:name":"Tureta",
    "gn:population":0,
    "gn:timezone":"Africa/Lagos",
    "iso:country":"NG",
    "name:azb_x_preferred":[
        "\u062a\u0648\u0631\u062a\u0627"
    ],
    "name:fas_x_preferred":[
        "\u062a\u0648\u0631\u062a\u0627"
    ],
    "name:fra_x_preferred":[
        "Tureta"
    ],
    "name:hau_x_preferred":[
        "Tureta"
    ],
    "name:ita_x_preferred":[
        "Tureta"
    ],
    "name:spa_x_preferred":[
        "Tureta"
    ],
    "name:urd_x_preferred":[
        "\u062a\u0648\u0631\u06cc\u062a\u0627"
    ],
    "wof:name":"Tureta",
    "wof:placetype":"locality"
},
  "geometry": {"coordinates":[5.54391,12.59367],"type":"Point"}
}