{
  "type": "Feature",
  "properties": {
    "gn:admin1_code":"43.0",
    "gn:admin2_code":"35012",
    "gn:asciiname":"Tsemaka",
    "gn:country_code":"NG",
    "gn:dem":177,
    "gn:feature_class":"P",
    "gn:feature_code":"PPL",
    "gn:name":"Tsemaka",
    "gn:population":0,
    "gn:timezone":"Africa/Lagos",
    "iso:country":"NG",
    "wof:name":"Tsemaka",
    "wof:placetype":"locality"
},
  "geometry": {"coordinates":[9.92684,7.59887],"type":"Point"}
}