{
  "type": "Feature",
  "properties": {
    "gn:admin1_code":"30.0",
    "gn:admin2_code":"24001.0",
    "gn:asciiname":"Ga Eleko",
    "gn:cc2":"NG",
    "gn:country_code":"NG",
    "gn:dem":350,
    "gn:feature_class":"P",
    "gn:feature_code":"PPL",
    "gn:name":"Ga Eleko",
    "gn:population":0,
    "gn:timezone":"Africa/Lagos",
    "iso:country":"NG",
    "name:und_x_variant":[
        "Elleko",
        "Ellekaw",
        "Ga Eleko"
    ],
    "wof:name":"Ga Eleko",
    "wof:placetype":"locality"
},
  "geometry": {"coordinates":[4.48333,8.33333],"type":"Point"}
}