{
  "type": "Feature",
  "properties": {
    "gn:admin1_code":"55.0",
    "gn:asciiname":"Towal",
    "gn:country_code":"NG",
    "gn:dem":317,
    "gn:feature_class":"P",
    "gn:feature_code":"PPL",
    "gn:name":"Towal",
    "gn:population":0,
    "gn:timezone":"Africa/Lagos",
    "iso:country":"NG",
    "name:eng_x_preferred":[
        "Towal"
    ],
    "wof:name":"Towal",
    "wof:placetype":"locality"
},
  "geometry": {"coordinates":[10.61361,10.83941],"type":"Point"}
}