{
  "type": "Feature",
  "properties": {
    "gn:admin1_code":"45.0",
    "gn:admin2_code":"1003.0",
    "gn:asciiname":"Ama-Uru",
    "gn:country_code":"NG",
    "gn:dem":65,
    "gn:feature_class":"P",
    "gn:feature_code":"PPL",
    "gn:name":"Ama-Uru",
    "gn:population":0,
    "gn:timezone":"Africa/Lagos",
    "iso:country":"NG",
    "wof:name":"Ama-Uru",
    "wof:placetype":"locality"
},
  "geometry": {"coordinates":[7.74405,5.61354],"type":"Point"}
}