{
  "type": "Feature",
  "properties": {
    "gn:admin1_code":"51.0",
    "gn:admin2_code":"610.0",
    "gn:admin3_code":"61006",
    "gn:asciiname":"Tungan Haikim",
    "gn:country_code":"NG",
    "gn:dem":219,
    "gn:feature_class":"P",
    "gn:feature_code":"PPL",
    "gn:name":"Tungan Haikim",
    "gn:population":0,
    "gn:timezone":"Africa/Lagos",
    "iso:country":"NG",
    "wof:name":"Tungan Haikim",
    "wof:placetype":"locality"
},
  "geometry": {"coordinates":[4.79077,12.1953],"type":"Point"}
}