{
  "type": "Feature",
  "properties": {
    "gn:admin1_code":"35.0",
    "gn:asciiname":"Wuro Sidiki",
    "gn:country_code":"NG",
    "gn:dem":239,
    "gn:feature_class":"P",
    "gn:feature_code":"PPL",
    "gn:name":"Wuro Sidiki",
    "gn:population":0,
    "gn:timezone":"Africa/Lagos",
    "iso:country":"NG",
    "name:eng_x_preferred":[
        "Wuro Sidiki"
    ],
    "wof:name":"Wuro Sidiki",
    "wof:placetype":"locality"
},
  "geometry": {"coordinates":[12.19533,9.04011],"type":"Point"}
}