{
  "type": "Feature",
  "properties": {
    "gn:admin1_code":"24.0",
    "gn:admin2_code":"413.0",
    "gn:admin3_code":"41309",
    "gn:asciiname":"Zagami",
    "gn:country_code":"NG",
    "gn:dem":667,
    "gn:feature_class":"P",
    "gn:feature_code":"PPL",
    "gn:name":"Zagami",
    "gn:population":0,
    "gn:timezone":"Africa/Lagos",
    "iso:country":"NG",
    "wof:name":"Zagami",
    "wof:placetype":"locality"
},
  "geometry": {"coordinates":[7.08124,11.73592],"type":"Point"}
}