{
  "type": "Feature",
  "properties": {
    "gn:admin1_code":"26.0",
    "gn:admin2_code":"7023.0",
    "gn:asciiname":"Mbara",
    "gn:country_code":"NG",
    "gn:dem":158,
    "gn:feature_class":"P",
    "gn:feature_code":"PPL",
    "gn:name":"Mbara",
    "gn:population":0,
    "gn:timezone":"Africa/Lagos",
    "iso:country":"NG",
    "name:hrv_x_preferred":[
        "Mbara"
    ],
    "name:und_x_variant":[
        "Mode"
    ],
    "wof:name":"Mbara",
    "wof:placetype":"locality"
},
  "geometry": {"coordinates":[9.07566,6.90497],"type":"Point"}
}