{
  "type": "Feature",
  "properties": {
    "gn:admin1_code":"44.0",
    "gn:admin2_code":"712.0",
    "gn:admin3_code":"71211",
    "gn:asciiname":"Fadawa",
    "gn:country_code":"NG",
    "gn:dem":450,
    "gn:feature_class":"P",
    "gn:feature_code":"PPL",
    "gn:name":"Fadawa",
    "gn:population":0,
    "gn:timezone":"Africa/Lagos",
    "iso:country":"NG",
    "wof:name":"Fadawa",
    "wof:placetype":"locality"
},
  "geometry": {"coordinates":[11.01893,11.60124],"type":"Point"}
}