{
  "type": "Feature",
  "properties": {
    "gn:admin1_code":"24.0",
    "gn:admin2_code":"407.0",
    "gn:admin3_code":"40705",
    "gn:asciiname":"Ungwan Mallam Bako",
    "gn:country_code":"NG",
    "gn:dem":699,
    "gn:feature_class":"P",
    "gn:feature_code":"PPL",
    "gn:name":"Ungwan Mallam Bako",
    "gn:population":0,
    "gn:timezone":"Africa/Lagos",
    "iso:country":"NG",
    "wof:name":"Ungwan Mallam Bako",
    "wof:placetype":"locality"
},
  "geometry": {"coordinates":[7.18481,11.30215],"type":"Point"}
}