{
  "type": "Feature",
  "properties": {
    "gn:admin1_code":"40.0",
    "gn:admin2_code":"506.0",
    "gn:admin3_code":"50607",
    "gn:asciiname":"Alumadi",
    "gn:country_code":"NG",
    "gn:dem":201,
    "gn:feature_class":"P",
    "gn:feature_code":"PPL",
    "gn:name":"Alumadi",
    "gn:population":0,
    "gn:timezone":"Africa/Lagos",
    "iso:country":"NG",
    "wof:name":"Alumadi",
    "wof:placetype":"locality"
},
  "geometry": {"coordinates":[4.16613,12.51489],"type":"Point"}
}