{
  "type": "Feature",
  "properties": {
    "gn:admin1_code":"24.0",
    "gn:admin2_code":"405.0",
    "gn:admin3_code":"40507",
    "gn:asciiname":"Bami",
    "gn:country_code":"NG",
    "gn:dem":501,
    "gn:feature_class":"P",
    "gn:feature_code":"PPL",
    "gn:name":"Bami",
    "gn:population":0,
    "gn:timezone":"Africa/Lagos",
    "iso:country":"NG",
    "wof:name":"Bami",
    "wof:placetype":"locality"
},
  "geometry": {"coordinates":[7.84797,12.72018],"type":"Point"}
}