{
  "type": "Feature",
  "properties": {
    "gn:admin1_code":"24.0",
    "gn:admin2_code":"419.0",
    "gn:admin3_code":"41908",
    "gn:asciiname":"Majegaba",
    "gn:country_code":"NG",
    "gn:dem":593,
    "gn:feature_class":"P",
    "gn:feature_code":"PPL",
    "gn:name":"Majegaba",
    "gn:population":0,
    "gn:timezone":"Africa/Lagos",
    "iso:country":"NG",
    "wof:name":"Majegaba",
    "wof:placetype":"locality"
},
  "geometry": {"coordinates":[7.41843,11.85565],"type":"Point"}
}