{
  "type": "Feature",
  "properties": {
    "gn:admin1_code":"50.0",
    "gn:admin2_code":"33006.0",
    "gn:asciiname":"Sangama",
    "gn:country_code":"NG",
    "gn:dem":4,
    "gn:feature_class":"P",
    "gn:feature_code":"PPL",
    "gn:name":"Sangama",
    "gn:population":0,
    "gn:timezone":"Africa/Lagos",
    "iso:country":"NG",
    "name:und_x_variant":[
        "Sangana",
        "Sangama"
    ],
    "wof:name":"Sangama",
    "wof:placetype":"locality"
},
  "geometry": {"coordinates":[6.8188,4.75889],"type":"Point"}
}