{
  "type": "Feature",
  "properties": {
    "gn:admin1_code":"51.0",
    "gn:admin2_code":"610.0",
    "gn:admin3_code":"61003",
    "gn:asciiname":"Kebbe",
    "gn:country_code":"NG",
    "gn:dem":221,
    "gn:feature_class":"P",
    "gn:feature_code":"PPLA2",
    "gn:name":"Kebbe",
    "gn:population":0,
    "gn:timezone":"Africa/Lagos",
    "iso:country":"NG",
    "name:fra_x_preferred":[
        "Kebbe"
    ],
    "name:hau_x_preferred":[
        "Kebbe"
    ],
    "name:ita_x_preferred":[
        "Kebbe"
    ],
    "name:por_x_preferred":[
        "Kebbe"
    ],
    "name:spa_x_preferred":[
        "Kebbe"
    ],
    "name:und_x_variant":[
        "Kebba",
        "Kebbi"
    ],
    "wof:name":"Kebbe",
    "wof:placetype":"locality"
},
  "geometry": {"coordinates":[4.73433,12.12861],"type":"Point"}
}