{
  "type": "Feature",
  "properties": {
    "gn:admin1_code":"39.0",
    "gn:admin2_code":"18025.0",
    "gn:admin3_code":"JI1907",
    "gn:asciiname":"Yalwa",
    "gn:country_code":"NG",
    "gn:dem":394,
    "gn:feature_class":"P",
    "gn:feature_code":"PPL",
    "gn:name":"Yalwa",
    "gn:population":0,
    "gn:timezone":"Africa/Lagos",
    "iso:country":"NG",
    "wof:name":"Yalwa",
    "wof:placetype":"locality"
},
  "geometry": {"coordinates":[9.57781,11.776],"type":"Point"}
}