{
  "type": "Feature",
  "properties": {
    "gn:admin1_code":"41.0",
    "gn:admin2_code":"23012.0",
    "gn:asciiname":"Agbaja",
    "gn:country_code":"NG",
    "gn:dem":387,
    "gn:feature_class":"P",
    "gn:feature_code":"PPL",
    "gn:name":"Agbaja",
    "gn:population":0,
    "gn:timezone":"Africa/Lagos",
    "iso:country":"NG",
    "wof:name":"Agbaja",
    "wof:placetype":"locality"
},
  "geometry": {"coordinates":[6.6418,7.9893],"type":"Point"}
}