{
  "type": "Feature",
  "properties": {
    "gn:admin1_code":"39.0",
    "gn:admin2_code":"18004.0",
    "gn:admin3_code":"JI0204",
    "gn:asciiname":"Dabbawa",
    "gn:country_code":"NG",
    "gn:dem":397,
    "gn:feature_class":"P",
    "gn:feature_code":"PPL",
    "gn:name":"Dabbawa",
    "gn:population":0,
    "gn:timezone":"Africa/Lagos",
    "iso:country":"NG",
    "wof:name":"Dabbawa",
    "wof:placetype":"locality"
},
  "geometry": {"coordinates":[8.83691,12.58643],"type":"Point"}
}