{
  "type": "Feature",
  "properties": {
    "gn:admin1_code":"24.0",
    "gn:admin2_code":"419.0",
    "gn:admin3_code":"41902",
    "gn:asciiname":"Kalmo",
    "gn:country_code":"NG",
    "gn:dem":565,
    "gn:feature_class":"P",
    "gn:feature_code":"PPL",
    "gn:name":"Kalmo",
    "gn:population":0,
    "gn:timezone":"Africa/Lagos",
    "iso:country":"NG",
    "wof:name":"Kalmo",
    "wof:placetype":"locality"
},
  "geometry": {"coordinates":[7.49892,11.95482],"type":"Point"}
}