{
  "type": "Feature",
  "properties": {
    "gn:admin1_code":"26.0",
    "gn:admin2_code":"7012",
    "gn:asciiname":"Tseanakar",
    "gn:country_code":"NG",
    "gn:dem":142,
    "gn:feature_class":"P",
    "gn:feature_code":"PPL",
    "gn:name":"Tseanakar",
    "gn:population":0,
    "gn:timezone":"Africa/Lagos",
    "iso:country":"NG",
    "wof:name":"Tseanakar",
    "wof:placetype":"locality"
},
  "geometry": {"coordinates":[9.17203,7.68579],"type":"Point"}
}