{
  "type": "Feature",
  "properties": {
    "gn:admin1_code":"24.0",
    "gn:admin2_code":"422.0",
    "gn:admin3_code":"42201",
    "gn:asciiname":"Barkiya",
    "gn:country_code":"NG",
    "gn:dem":518,
    "gn:feature_class":"P",
    "gn:feature_code":"PPL",
    "gn:name":"Barkiya",
    "gn:population":0,
    "gn:timezone":"Africa/Lagos",
    "iso:country":"NG",
    "wof:name":"Barkiya",
    "wof:placetype":"locality"
},
  "geometry": {"coordinates":[7.557,12.64437],"type":"Point"}
}