{
  "type": "Feature",
  "properties": {
    "gn:admin1_code":"35.0",
    "gn:admin2_code":"2013.0",
    "gn:asciiname":"Kankila",
    "gn:country_code":"NG",
    "gn:dem":450,
    "gn:feature_class":"P",
    "gn:feature_code":"PPL",
    "gn:name":"Kankila",
    "gn:population":0,
    "gn:timezone":"Africa/Lagos",
    "iso:country":"NG",
    "wof:name":"Kankila",
    "wof:placetype":"locality"
},
  "geometry": {"coordinates":[13.26216,10.61914],"type":"Point"}
}