{
  "type": "Feature",
  "properties": {
    "gn:admin1_code":"30.0",
    "gn:admin2_code":"24003.0",
    "gn:asciiname":"Muchita",
    "gn:cc2":"NG",
    "gn:country_code":"NG",
    "gn:dem":110,
    "gn:feature_class":"P",
    "gn:feature_code":"PPL",
    "gn:name":"Muchita",
    "gn:population":0,
    "gn:timezone":"Africa/Lagos",
    "iso:country":"NG",
    "name:und_x_variant":[
        "Mashita",
        "Muchita"
    ],
    "wof:name":"Muchita",
    "wof:placetype":"locality"
},
  "geometry": {"coordinates":[5.23333,8.95],"type":"Point"}
}