{
  "type": "Feature",
  "properties": {
    "gn:admin1_code":"49.0",
    "gn:admin2_code":"32010",
    "gn:asciiname":"Gamakai",
    "gn:country_code":"NG",
    "gn:dem":168,
    "gn:feature_class":"P",
    "gn:feature_code":"PPL",
    "gn:name":"Gamakai",
    "gn:population":0,
    "gn:timezone":"Africa/Lagos",
    "iso:country":"NG",
    "wof:name":"Gamakai",
    "wof:placetype":"locality"
},
  "geometry": {"coordinates":[9.84278,8.66726],"type":"Point"}
}