{
  "type": "Feature",
  "properties": {
    "gn:admin1_code":"37.0",
    "gn:admin2_code":"12014.0",
    "gn:asciiname":"Unuame",
    "gn:country_code":"NG",
    "gn:dem":24,
    "gn:feature_class":"P",
    "gn:feature_code":"PPL",
    "gn:name":"Unuame",
    "gn:population":0,
    "gn:timezone":"Africa/Lagos",
    "iso:country":"NG",
    "name:und_x_variant":[
        "Noami",
        "Unuame"
    ],
    "wof:name":"Unuame",
    "wof:placetype":"locality"
},
  "geometry": {"coordinates":[5.44213,6.40829],"type":"Point"}
}