{
  "type": "Feature",
  "properties": {
    "gn:admin1_code":"29.0",
    "gn:admin2_code":"20034.0",
    "gn:admin3_code":"KN2401",
    "gn:asciiname":"Ba'awa",
    "gn:country_code":"NG",
    "gn:dem":557,
    "gn:feature_class":"P",
    "gn:feature_code":"PPL",
    "gn:name":"Ba\u2019awa",
    "gn:population":0,
    "gn:timezone":"Africa/Lagos",
    "iso:country":"NG",
    "wof:name":"Ba'awa",
    "wof:placetype":"locality"
},
  "geometry": {"coordinates":[7.99,11.59631],"type":"Point"}
}