{
  "type": "Feature",
  "properties": {
    "gn:admin1_code":"21.0",
    "gn:admin2_code":"3029.0",
    "gn:asciiname":"Ikot Udo",
    "gn:country_code":"NG",
    "gn:dem":24,
    "gn:feature_class":"P",
    "gn:feature_code":"PPL",
    "gn:name":"Ikot Udo",
    "gn:population":0,
    "gn:timezone":"Africa/Lagos",
    "iso:country":"NG",
    "wof:name":"Ikot Udo",
    "wof:placetype":"locality"
},
  "geometry": {"coordinates":[8.00972,5.11314],"type":"Point"}
}