{
  "type": "Feature",
  "properties": {
    "gn:admin1_code":"37.0",
    "gn:admin2_code":"12013.0",
    "gn:asciiname":"Obayanta",
    "gn:country_code":"NG",
    "gn:dem":114,
    "gn:feature_class":"P",
    "gn:feature_code":"PPL",
    "gn:name":"Obayanta",
    "gn:population":0,
    "gn:timezone":"Africa/Lagos",
    "iso:country":"NG",
    "name:eng_x_preferred":[
        "Obayanta"
    ],
    "wof:name":"Obayanta",
    "wof:placetype":"locality"
},
  "geometry": {"coordinates":[6.03126,6.12928],"type":"Point"}
}