{
  "type": "Feature",
  "properties": {
    "gn:admin1_code":"23.0",
    "gn:asciiname":"Angwandawa",
    "gn:country_code":"NG",
    "gn:dem":604,
    "gn:feature_class":"P",
    "gn:feature_code":"PPL",
    "gn:name":"Angwandawa",
    "gn:population":0,
    "gn:timezone":"Africa/Lagos",
    "iso:country":"NG",
    "wof:name":"Angwandawa",
    "wof:placetype":"locality"
},
  "geometry": {"coordinates":[8.55574,11.12734],"type":"Point"}
}