{
  "type": "Feature",
  "properties": {
    "gn:admin1_code":"50.0",
    "gn:admin2_code":"33022.0",
    "gn:asciiname":"Orogbum",
    "gn:country_code":"NG",
    "gn:dem":18,
    "gn:feature_class":"P",
    "gn:feature_code":"PPL",
    "gn:name":"Orogbum",
    "gn:population":0,
    "gn:timezone":"Africa/Lagos",
    "iso:country":"NG",
    "wof:name":"Orogbum",
    "wof:placetype":"neighbourhood"
},
  "geometry": {"coordinates":[7.01174,4.79071],"type":"Point"}
}