{
  "type": "Feature",
  "properties": {
    "gn:admin1_code":"29.0",
    "gn:admin2_code":"20017.0",
    "gn:admin3_code":"KN1906",
    "gn:asciiname":"Ungwan Shida",
    "gn:country_code":"NG",
    "gn:dem":606,
    "gn:feature_class":"P",
    "gn:feature_code":"PPL",
    "gn:name":"Ungwan Shida",
    "gn:population":0,
    "gn:timezone":"Africa/Lagos",
    "iso:country":"NG",
    "wof:name":"Ungwan Shida",
    "wof:placetype":"locality"
},
  "geometry": {"coordinates":[7.83388,11.96067],"type":"Point"}
}