{
  "type": "Feature",
  "properties": {
    "gn:admin1_code":"35.0",
    "gn:admin2_code":"2012.0",
    "gn:asciiname":"Yelwa",
    "gn:country_code":"NG",
    "gn:dem":317,
    "gn:feature_class":"P",
    "gn:feature_code":"PPL",
    "gn:name":"Yelwa",
    "gn:population":0,
    "gn:timezone":"Africa/Lagos",
    "iso:country":"NG",
    "name:cat_x_preferred":[
        "Yelwa"
    ],
    "name:pol_x_preferred":[
        "Yelwa"
    ],
    "wof:name":"Yelwa",
    "wof:placetype":"locality"
},
  "geometry": {"coordinates":[11.97352,8.96816],"type":"Point"}
}