{
  "type": "Feature",
  "properties": {
    "gn:admin1_code":"22.0",
    "gn:admin2_code":"9018.0",
    "gn:asciiname":"Echimoga",
    "gn:country_code":"NG",
    "gn:dem":89,
    "gn:feature_class":"P",
    "gn:feature_code":"PPL",
    "gn:name":"Echimoga",
    "gn:population":0,
    "gn:timezone":"Africa/Lagos",
    "iso:country":"NG",
    "wof:name":"Echimoga",
    "wof:placetype":"locality"
},
  "geometry": {"coordinates":[8.78796,6.77965],"type":"Point"}
}