{
  "type": "Feature",
  "properties": {
    "gn:admin1_code":"26.0",
    "gn:admin2_code":"7005.0",
    "gn:asciiname":"Bokyaa",
    "gn:country_code":"NG",
    "gn:dem":187,
    "gn:feature_class":"P",
    "gn:feature_code":"PPL",
    "gn:name":"Bokyaa",
    "gn:population":0,
    "gn:timezone":"Africa/Lagos",
    "iso:country":"NG",
    "wof:name":"Bokyaa",
    "wof:placetype":"locality"
},
  "geometry": {"coordinates":[8.98192,7.47537],"type":"Point"}
}