{
  "type": "Feature",
  "properties": {
    "gn:admin1_code":"5.0",
    "gn:admin2_code":"25002",
    "gn:asciiname":"Amukoko",
    "gn:country_code":"NG",
    "gn:dem":9,
    "gn:feature_class":"P",
    "gn:feature_code":"PPL",
    "gn:name":"Amukoko",
    "gn:population":0,
    "gn:timezone":"Africa/Lagos",
    "iso:country":"NG",
    "wof:name":"Amukoko",
    "wof:placetype":"neighbourhood"
},
  "geometry": {"coordinates":[3.34293,6.46509],"type":"Point"}
}