{
  "type": "Feature",
  "properties": {
    "gn:admin1_code":"50.0",
    "gn:admin2_code":"33002.0",
    "gn:asciiname":"Ala-Ahoada",
    "gn:country_code":"NG",
    "gn:dem":20,
    "gn:feature_class":"P",
    "gn:feature_code":"PPL",
    "gn:name":"Ala-Ahoada",
    "gn:population":0,
    "gn:timezone":"Africa/Lagos",
    "iso:country":"NG",
    "name:und_x_variant":[
        "Ogbo",
        "Ala-Ahoada"
    ],
    "wof:name":"Ala-Ahoada",
    "wof:placetype":"locality"
},
  "geometry": {"coordinates":[6.6265,5.10294],"type":"Point"}
}