{
  "type": "Feature",
  "properties": {
    "gn:admin1_code":"31.0",
    "gn:admin2_code":"27010.0",
    "gn:asciiname":"Swodi Woro",
    "gn:country_code":"NG",
    "gn:dem":143,
    "gn:feature_class":"P",
    "gn:feature_code":"PPL",
    "gn:name":"Swodi Woro",
    "gn:population":0,
    "gn:timezone":"Africa/Lagos",
    "iso:country":"NG",
    "wof:name":"Swodi Woro",
    "wof:placetype":"locality"
},
  "geometry": {"coordinates":[6.20825,9.49789],"type":"Point"}
}