{
  "type": "Feature",
  "properties": {
    "gn:admin1_code":"35.0",
    "gn:admin2_code":"2012.0",
    "gn:asciiname":"Kumba",
    "gn:country_code":"NG",
    "gn:dem":299,
    "gn:feature_class":"P",
    "gn:feature_code":"PPL",
    "gn:name":"Kumba",
    "gn:population":0,
    "gn:timezone":"Africa/Lagos",
    "iso:country":"NG",
    "name:eng_x_preferred":[
        "Kumba"
    ],
    "wof:name":"Kumba",
    "wof:placetype":"locality"
},
  "geometry": {"coordinates":[12.00194,9.02975],"type":"Point"}
}