{
  "type": "Feature",
  "properties": {
    "gn:admin1_code":"46.0",
    "gn:admin2_code":"5005.0",
    "gn:admin3_code":"BA0506",
    "gn:asciiname":"Babaye",
    "gn:country_code":"NG",
    "gn:dem":447,
    "gn:feature_class":"P",
    "gn:feature_code":"PPL",
    "gn:name":"Babaye",
    "gn:population":0,
    "gn:timezone":"Africa/Lagos",
    "iso:country":"NG",
    "wof:name":"Babaye",
    "wof:placetype":"locality"
},
  "geometry": {"coordinates":[10.63333,11.31667],"type":"Point"}
}