{
  "type": "Feature",
  "properties": {
    "gn:admin1_code":"23.0",
    "gn:admin2_code":"19021.0",
    "gn:admin3_code":"KD2104",
    "gn:asciiname":"Awai",
    "gn:country_code":"NG",
    "gn:dem":649,
    "gn:feature_class":"P",
    "gn:feature_code":"PPL",
    "gn:name":"Awai",
    "gn:population":0,
    "gn:timezone":"Africa/Lagos",
    "iso:country":"NG",
    "wof:name":"Awai",
    "wof:placetype":"locality"
},
  "geometry": {"coordinates":[7.90309,11.06558],"type":"Point"}
}