{
  "type": "Feature",
  "properties": {
    "gn:admin1_code":"27.0",
    "gn:admin2_code":"101.0",
    "gn:admin3_code":"10105",
    "gn:asciiname":"Daya",
    "gn:country_code":"NG",
    "gn:dem":298,
    "gn:feature_class":"P",
    "gn:feature_code":"PPL",
    "gn:name":"Daya",
    "gn:population":0,
    "gn:timezone":"Africa/Lagos",
    "iso:country":"NG",
    "name:ceb_x_preferred":[
        "Daya"
    ],
    "name:heb_x_preferred":[
        "\u05d3\u05d9\u05d4"
    ],
    "name:pol_x_preferred":[
        "Daya"
    ],
    "name:swe_x_preferred":[
        "Daya"
    ],
    "name:vie_x_preferred":[
        "Daya"
    ],
    "wof:name":"Daya",
    "wof:placetype":"locality"
},
  "geometry": {"coordinates":[13.12161,13.51618],"type":"Point"}
}