{
  "type": "Feature",
  "properties": {
    "gn:admin1_code":"24.0",
    "gn:admin2_code":"411.0",
    "gn:admin3_code":"41110",
    "gn:asciiname":"Gurjiya",
    "gn:country_code":"NG",
    "gn:dem":499,
    "gn:feature_class":"P",
    "gn:feature_code":"PPL",
    "gn:name":"Gurjiya",
    "gn:population":0,
    "gn:timezone":"Africa/Lagos",
    "iso:country":"NG",
    "wof:name":"Gurjiya",
    "wof:placetype":"locality"
},
  "geometry": {"coordinates":[8.08606,12.93576],"type":"Point"}
}