{
  "type": "Feature",
  "properties": {
    "gn:admin1_code":"48.0",
    "gn:admin2_code":"29012.0",
    "gn:asciiname":"Omi",
    "gn:country_code":"NG",
    "gn:dem":51,
    "gn:feature_class":"P",
    "gn:feature_code":"PPL",
    "gn:name":"Omi",
    "gn:population":0,
    "gn:timezone":"Africa/Lagos",
    "iso:country":"NG",
    "name:ita_x_preferred":[
        "Omi"
    ],
    "name:por_x_preferred":[
        "Omi"
    ],
    "name:rus_x_preferred":[
        "\u041e\u043c\u0438"
    ],
    "name:ukr_x_preferred":[
        "\u041e\u043c\u0456"
    ],
    "name:zho_x_preferred":[
        "\u81e3"
    ],
    "wof:name":"Omi",
    "wof:placetype":"locality"
},
  "geometry": {"coordinates":[4.91054,6.48152],"type":"Point"}
}