{
  "type": "Feature",
  "properties": {
    "gn:admin1_code":"35.0",
    "gn:admin2_code":"2015",
    "gn:asciiname":"Lahwha",
    "gn:country_code":"NG",
    "gn:dem":814,
    "gn:feature_class":"P",
    "gn:feature_code":"PPL",
    "gn:name":"Lahwha",
    "gn:population":0,
    "gn:timezone":"Africa/Lagos",
    "iso:country":"NG",
    "name:eng_x_preferred":[
        "Lahwha"
    ],
    "wof:name":"Lahwha",
    "wof:placetype":"locality"
},
  "geometry": {"coordinates":[13.38963,10.15124],"type":"Point"}
}