{
  "type": "Feature",
  "properties": {
    "gn:admin1_code":"5.0",
    "gn:admin2_code":"25015.0",
    "gn:asciiname":"Lemba",
    "gn:country_code":"NG",
    "gn:dem":2,
    "gn:feature_class":"P",
    "gn:feature_code":"PPL",
    "gn:name":"Lemba",
    "gn:population":0,
    "gn:timezone":"Africa/Lagos",
    "iso:country":"NG",
    "name:ceb_x_preferred":[
        "Lemba"
    ],
    "name:deu_x_preferred":[
        "Lemba"
    ],
    "name:fra_x_preferred":[
        "Lemba"
    ],
    "name:lin_x_preferred":[
        "Lemba"
    ],
    "name:nld_x_preferred":[
        "Lemba"
    ],
    "name:swe_x_preferred":[
        "Lemba"
    ],
    "wof:name":"Lemba",
    "wof:placetype":"neighbourhood"
},
  "geometry": {"coordinates":[3.15394,6.45629],"type":"Point"}
}