{
  "type": "Feature",
  "properties": {
    "gn:admin1_code":"35.0",
    "gn:admin2_code":"2012",
    "gn:asciiname":"Teme",
    "gn:country_code":"NG",
    "gn:dem":314,
    "gn:feature_class":"P",
    "gn:feature_code":"PPL",
    "gn:name":"Teme",
    "gn:population":0,
    "gn:timezone":"Africa/Lagos",
    "iso:country":"NG",
    "name:eng_x_preferred":[
        "Teme"
    ],
    "wof:name":"Teme",
    "wof:placetype":"locality"
},
  "geometry": {"coordinates":[12.05027,8.99142],"type":"Point"}
}