{
  "type": "Feature",
  "properties": {
    "gn:admin1_code":"37.0",
    "gn:admin2_code":"12015.0",
    "gn:asciiname":"Ofaye",
    "gn:country_code":"NG",
    "gn:dem":61,
    "gn:feature_class":"P",
    "gn:feature_code":"PPL",
    "gn:name":"Ofaye",
    "gn:population":0,
    "gn:timezone":"Africa/Lagos",
    "iso:country":"NG",
    "wof:name":"Ofaye",
    "wof:placetype":"locality"
},
  "geometry": {"coordinates":[5.43091,6.43091],"type":"Point"}
}