{
  "type": "Feature",
  "properties": {
    "gn:admin1_code":"41.0",
    "gn:admin2_code":"23004.0",
    "gn:asciiname":"Usaman",
    "gn:country_code":"NG",
    "gn:dem":204,
    "gn:feature_class":"P",
    "gn:feature_code":"PPL",
    "gn:name":"Usaman",
    "gn:population":0,
    "gn:timezone":"Africa/Lagos",
    "iso:country":"NG",
    "name:und_x_variant":[
        "Usuman",
        "Usaman"
    ],
    "wof:name":"Usaman",
    "wof:placetype":"locality"
},
  "geometry": {"coordinates":[7.16667,7.86667],"type":"Point"}
}