{
  "type": "Feature",
  "properties": {
    "gn:admin1_code":"43.0",
    "gn:admin2_code":"35004.0",
    "gn:asciiname":"Bahago",
    "gn:country_code":"NG",
    "gn:dem":329,
    "gn:feature_class":"P",
    "gn:feature_code":"PPL",
    "gn:name":"Bahago",
    "gn:population":0,
    "gn:timezone":"Africa/Lagos",
    "iso:country":"NG",
    "wof:name":"Bahago",
    "wof:placetype":"locality"
},
  "geometry": {"coordinates":[11.35,7.53333],"type":"Point"}
}