{
  "type": "Feature",
  "properties": {
    "gn:admin1_code":"32.0",
    "gn:admin2_code":"31021.0",
    "gn:asciiname":"Ajegunle",
    "gn:country_code":"NG",
    "gn:dem":329,
    "gn:feature_class":"P",
    "gn:feature_code":"PPL",
    "gn:name":"Ajegunle",
    "gn:population":0,
    "gn:timezone":"Africa/Lagos",
    "iso:country":"NG",
    "wof:name":"Ajegunle",
    "wof:placetype":"neighbourhood"
},
  "geometry": {"coordinates":[4.21667,8.16667],"type":"Point"}
}