{
  "type": "Feature",
  "properties": {
    "gn:admin1_code":"40.0",
    "gn:admin2_code":"521.0",
    "gn:admin3_code":"52107",
    "gn:asciiname":"Shagiya",
    "gn:country_code":"NG",
    "gn:dem":272,
    "gn:feature_class":"P",
    "gn:feature_code":"PPL",
    "gn:name":"Shagiya",
    "gn:population":0,
    "gn:timezone":"Africa/Lagos",
    "iso:country":"NG",
    "wof:name":"Shagiya",
    "wof:placetype":"locality"
},
  "geometry": {"coordinates":[4.9916,11.39161],"type":"Point"}
}