{
  "type": "Feature",
  "properties": {
    "gn:admin1_code":"57.0",
    "gn:asciiname":"Sani",
    "gn:country_code":"NG",
    "gn:dem":657,
    "gn:feature_class":"P",
    "gn:feature_code":"PPL",
    "gn:name":"Sani",
    "gn:population":0,
    "gn:timezone":"Africa/Lagos",
    "iso:country":"NG",
    "name:ceb_x_preferred":[
        "Sani"
    ],
    "name:deu_x_preferred":[
        "Sani"
    ],
    "name:fra_x_preferred":[
        "Sani"
    ],
    "name:ind_x_preferred":[
        "Sani"
    ],
    "name:ita_x_preferred":[
        "Sani"
    ],
    "name:swe_x_preferred":[
        "Sani"
    ],
    "wof:name":"Sani",
    "wof:placetype":"locality"
},
  "geometry": {"coordinates":[7.07379,11.76538],"type":"Point"}
}