{
  "type": "Feature",
  "properties": {
    "gn:admin1_code":"29.0",
    "gn:admin2_code":"20025.0",
    "gn:admin3_code":"KN0411",
    "gn:asciiname":"Maizaure",
    "gn:country_code":"NG",
    "gn:dem":548,
    "gn:feature_class":"P",
    "gn:feature_code":"PPL",
    "gn:name":"Maizaure",
    "gn:population":0,
    "gn:timezone":"Africa/Lagos",
    "iso:country":"NG",
    "wof:name":"Maizaure",
    "wof:placetype":"locality"
},
  "geometry": {"coordinates":[8.21815,11.56247],"type":"Point"}
}