{
  "type": "Feature",
  "properties": {
    "gn:admin1_code":"51.0",
    "gn:admin2_code":"611.0",
    "gn:admin3_code":"61105",
    "gn:asciiname":"Dan Gwaga",
    "gn:country_code":"NG",
    "gn:dem":255,
    "gn:feature_class":"P",
    "gn:feature_code":"PPL",
    "gn:name":"Dan Gwaga",
    "gn:population":0,
    "gn:timezone":"Africa/Lagos",
    "iso:country":"NG",
    "wof:name":"Dan Gwaga",
    "wof:placetype":"locality"
},
  "geometry": {"coordinates":[5.32376,13.22229],"type":"Point"}
}