{
  "type": "Feature",
  "properties": {
    "gn:admin1_code":"46.0",
    "gn:admin2_code":"5003.0",
    "gn:admin3_code":"BA0305",
    "gn:asciiname":"Gerla",
    "gn:country_code":"NG",
    "gn:dem":567,
    "gn:feature_class":"P",
    "gn:feature_code":"PPL",
    "gn:name":"Gerla",
    "gn:population":0,
    "gn:timezone":"Africa/Lagos",
    "iso:country":"NG",
    "name:deu_x_preferred":[
        "Gerla"
    ],
    "name:eng_x_preferred":[
        "Gerla"
    ],
    "name:hun_x_preferred":[
        "Gerla"
    ],
    "name:ita_x_preferred":[
        "Gerla"
    ],
    "wof:name":"Gerla",
    "wof:placetype":"locality"
},
  "geometry": {"coordinates":[9.7963,9.66048],"type":"Point"}
}