{
  "type": "Feature",
  "properties": {
    "gn:admin1_code":"35.0",
    "gn:asciiname":"Bonbure",
    "gn:country_code":"NG",
    "gn:dem":154,
    "gn:feature_class":"P",
    "gn:feature_code":"PPL",
    "gn:name":"Bonbure",
    "gn:population":0,
    "gn:timezone":"Africa/Lagos",
    "iso:country":"NG",
    "name:eng_x_preferred":[
        "Bonbure"
    ],
    "wof:name":"Bonbure",
    "wof:placetype":"locality"
},
  "geometry": {"coordinates":[11.50247,9.46993],"type":"Point"}
}