{
  "type": "Feature",
  "properties": {
    "iso:country":"NG",
    "name:aze_x_preferred":[
        "K\u00fcr"
    ],
    "name:cat_x_preferred":[
        "Kura"
    ],
    "name:ceb_x_preferred":[
        "Kura"
    ],
    "name:deu_x_preferred":[
        "Kura"
    ],
    "name:eng_x_preferred":[
        "Kura"
    ],
    "name:fas_x_preferred":[
        "\u06a9\u0648\u0631\u0627"
    ],
    "name:fra_x_preferred":[
        "Kura"
    ],
    "name:hau_x_preferred":[
        "Kura"
    ],
    "name:ita_x_preferred":[
        "Kura"
    ],
    "name:lav_x_preferred":[
        "K\u016bra"
    ],
    "name:nan_x_preferred":[
        "Kura"
    ],
    "name:nld_x_preferred":[
        "Kura"
    ],
    "name:rus_x_preferred":[
        "\u041a\u0443\u0440\u0430"
    ],
    "name:slk_x_preferred":[
        "Kura"
    ],
    "name:slv_x_preferred":[
        "Kura"
    ],
    "name:ukr_x_preferred":[
        "\u041a\u0443\u0440\u0430"
    ],
    "name:yor_x_preferred":[
        "Agb\u00e8gb\u00e8 \u00ccj\u1ecdba \u00ccb\u00edl\u1eb9\u0300 Kura"
    ],
    "qs:gn_country":"NG",
    "qs:gn_fcode":"PPL",
    "qs:gn_pop":9537,
    "qs:name":"Kura",
    "qs:name_adm0":"Nigeria",
    "qs:name_adm1":"Kano",
    "qs:photos":0,
    "qs:photos_1k":0,
    "qs:photos_9k":1,
    "qs:photos_9r":1,
    "qs:photos_all":1,
    "qs:photos_sr":0,
    "qs:placetype":"Town",
    "qs:pop_sr":"5",
    "qs:woe_adm0":23424908,
    "wd:wordcount":117,
    "wof:name":"Kura",
    "wof:placetype":"locality",
    "wof:population":9537
},
  "geometry": {"coordinates":[8.43033,11.76969],"type":"Point"}
}