{
  "type": "Feature",
  "properties": {
    "gn:admin1_code":"32.0",
    "gn:admin2_code":"31003.0",
    "gn:asciiname":"Koso",
    "gn:country_code":"NG",
    "gn:dem":295,
    "gn:feature_class":"P",
    "gn:feature_code":"PPL",
    "gn:name":"Koso",
    "gn:population":0,
    "gn:timezone":"Africa/Lagos",
    "iso:country":"NG",
    "name:ceb_x_preferred":[
        "Koso"
    ],
    "name:swe_x_preferred":[
        "Koso"
    ],
    "wof:name":"Koso",
    "wof:placetype":"locality"
},
  "geometry": {"coordinates":[3.93333,8.03333],"type":"Point"}
}