{
  "type": "Feature",
  "properties": {
    "gn:admin1_code":"46.0",
    "gn:admin2_code":"5005.0",
    "gn:admin3_code":"BA0517",
    "gn:asciiname":"Bardafiti",
    "gn:country_code":"NG",
    "gn:dem":348,
    "gn:feature_class":"P",
    "gn:feature_code":"PPL",
    "gn:name":"Bardafiti",
    "gn:population":0,
    "gn:timezone":"Africa/Lagos",
    "iso:country":"NG",
    "name:eng_x_preferred":[
        "Bardafiti"
    ],
    "wof:name":"Bardafiti",
    "wof:placetype":"locality"
},
  "geometry": {"coordinates":[10.56559,10.82397],"type":"Point"}
}