{
  "type": "Feature",
  "properties": {
    "gn:admin1_code":"5.0",
    "gn:admin2_code":"25006.0",
    "gn:asciiname":"Imeke",
    "gn:country_code":"NG",
    "gn:dem":10,
    "gn:feature_class":"P",
    "gn:feature_code":"PPL",
    "gn:name":"Imeke",
    "gn:population":0,
    "gn:timezone":"Africa/Lagos",
    "iso:country":"NG",
    "wof:name":"Imeke",
    "wof:placetype":"neighbourhood"
},
  "geometry": {"coordinates":[2.98333,6.43333],"type":"Point"}
}