{
  "type": "Feature",
  "properties": {
    "gn:admin1_code":"55.0",
    "gn:admin2_code":"16011.0",
    "gn:asciiname":"Nafuta",
    "gn:country_code":"NG",
    "gn:dem":215,
    "gn:feature_class":"P",
    "gn:feature_code":"PPL",
    "gn:name":"Nafuta",
    "gn:population":0,
    "gn:timezone":"Africa/Lagos",
    "iso:country":"NG",
    "wof:name":"Nafuta",
    "wof:placetype":"locality"
},
  "geometry": {"coordinates":[11.60699,10.22011],"type":"Point"}
}