{
  "type": "Feature",
  "properties": {
    "gn:admin1_code":"26.0",
    "gn:admin2_code":"7005",
    "gn:asciiname":"Shilshi",
    "gn:country_code":"NG",
    "gn:dem":180,
    "gn:feature_class":"P",
    "gn:feature_code":"PPL",
    "gn:name":"Shilshi",
    "gn:population":0,
    "gn:timezone":"Africa/Lagos",
    "iso:country":"NG",
    "wof:name":"Shilshi",
    "wof:placetype":"locality"
},
  "geometry": {"coordinates":[8.89133,7.42073],"type":"Point"}
}