{
  "type": "Feature",
  "properties": {
    "gn:admin1_code":"48.0",
    "gn:admin2_code":"29018.0",
    "gn:asciiname":"Emure",
    "gn:country_code":"NG",
    "gn:dem":314,
    "gn:feature_class":"P",
    "gn:feature_code":"PPL",
    "gn:name":"Emure",
    "gn:population":0,
    "gn:timezone":"Africa/Lagos",
    "iso:country":"NG",
    "name:cat_x_preferred":[
        "Emure"
    ],
    "name:fra_x_preferred":[
        "Emure"
    ],
    "name:hau_x_preferred":[
        "Emure"
    ],
    "name:ita_x_preferred":[
        "Emure"
    ],
    "name:spa_x_preferred":[
        "Emure"
    ],
    "name:yor_x_preferred":[
        "Emure"
    ],
    "wof:name":"Emure",
    "wof:placetype":"locality"
},
  "geometry": {"coordinates":[5.5101,7.2438],"type":"Point"}
}