{
  "type": "Feature",
  "properties": {
    "gn:admin1_code":"53.0",
    "gn:admin2_code":"11010.0",
    "gn:asciiname":"Ominyi",
    "gn:country_code":"NG",
    "gn:dem":52,
    "gn:feature_class":"P",
    "gn:feature_code":"PPL",
    "gn:name":"Ominyi",
    "gn:population":0,
    "gn:timezone":"Africa/Lagos",
    "iso:country":"NG",
    "name:und_x_variant":[
        "Ominiyi",
        "Ominyi"
    ],
    "wof:name":"Ominyi",
    "wof:placetype":"locality"
},
  "geometry": {"coordinates":[8.35307,6.51506],"type":"Point"}
}