{
  "type": "Feature",
  "properties": {
    "gn:admin1_code":"22.0",
    "gn:admin2_code":"9010.0",
    "gn:asciiname":"Itaka",
    "gn:country_code":"NG",
    "gn:dem":59,
    "gn:feature_class":"P",
    "gn:feature_code":"PPL",
    "gn:name":"Itaka",
    "gn:population":0,
    "gn:timezone":"Africa/Lagos",
    "iso:country":"NG",
    "wof:name":"Itaka",
    "wof:placetype":"locality"
},
  "geometry": {"coordinates":[8.7555,5.7894],"type":"Point"}
}