{
  "type": "Feature",
  "properties": {
    "gn:admin1_code":"26.0",
    "gn:admin2_code":"7023.0",
    "gn:asciiname":"Liam",
    "gn:country_code":"NG",
    "gn:dem":169,
    "gn:feature_class":"P",
    "gn:feature_code":"PPL",
    "gn:name":"Liam",
    "gn:population":0,
    "gn:timezone":"Africa/Lagos",
    "iso:country":"NG",
    "name:bre_x_preferred":[
        "Liam"
    ],
    "name:deu_x_preferred":[
        "Liam"
    ],
    "name:eus_x_preferred":[
        "Liam"
    ],
    "name:fas_x_preferred":[
        "\u0644\u06cc\u0627\u0645"
    ],
    "name:fin_x_preferred":[
        "Liam"
    ],
    "name:fra_x_preferred":[
        "Liam"
    ],
    "name:jpn_x_preferred":[
        "\u30ea\u30fc\u30a2\u30e0"
    ],
    "name:nld_x_preferred":[
        "Liam"
    ],
    "name:nor_x_preferred":[
        "Liam"
    ],
    "name:rus_x_preferred":[
        "\u041b\u0438\u0430\u043c"
    ],
    "name:spa_x_preferred":[
        "Liam"
    ],
    "name:swe_x_preferred":[
        "Liam"
    ],
    "wof:name":"Liam",
    "wof:placetype":"locality"
},
  "geometry": {"coordinates":[8.98361,7.02963],"type":"Point"}
}