{
  "type": "Feature",
  "properties": {
    "gn:admin1_code":"26.0",
    "gn:admin2_code":"7023.0",
    "gn:asciiname":"Liam",
    "gn:country_code":"NG",
    "gn:dem":169,
    "gn:feature_class":"P",
    "gn:feature_code":"PPL",
    "gn:name":"Liam",
    "gn:population":0,
    "gn:timezone":"Africa/Lagos",
    "iso:country":"NG",
    "wof:name":"Liam",
    "wof:placetype":"locality"
},
  "geometry": {"coordinates":[8.98361,7.02963],"type":"Point"}
}