{
  "type": "Feature",
  "properties": {
    "gn:admin1_code":"49.0",
    "gn:admin2_code":"32008.0",
    "gn:asciiname":"Shiwer",
    "gn:country_code":"NG",
    "gn:dem":497,
    "gn:feature_class":"P",
    "gn:feature_code":"PPL",
    "gn:name":"Shiwer",
    "gn:population":0,
    "gn:timezone":"Africa/Lagos",
    "iso:country":"NG",
    "name:eng_x_preferred":[
        "Shiwer"
    ],
    "wof:name":"Shiwer",
    "wof:placetype":"locality"
},
  "geometry": {"coordinates":[9.67242,9.31631],"type":"Point"}
}