{
  "type": "Feature",
  "properties": {
    "gn:admin1_code":"40.0",
    "gn:admin2_code":"503.0",
    "gn:admin3_code":"50309",
    "gn:asciiname":"Tunga Amani",
    "gn:country_code":"NG",
    "gn:dem":229,
    "gn:feature_class":"P",
    "gn:feature_code":"PPL",
    "gn:name":"Tunga Amani",
    "gn:population":0,
    "gn:timezone":"Africa/Lagos",
    "iso:country":"NG",
    "wof:name":"Tunga Amani",
    "wof:placetype":"locality"
},
  "geometry": {"coordinates":[4.40797,12.75978],"type":"Point"}
}