{
  "type": "Feature",
  "properties": {
    "gn:admin1_code":"44.0",
    "gn:admin2_code":"704.0",
    "gn:admin3_code":"70405",
    "gn:asciiname":"Kufaru",
    "gn:country_code":"NG",
    "gn:dem":446,
    "gn:feature_class":"P",
    "gn:feature_code":"PPL",
    "gn:name":"Kufaru",
    "gn:population":0,
    "gn:timezone":"Africa/Lagos",
    "iso:country":"NG",
    "wof:name":"Kufaru",
    "wof:placetype":"locality"
},
  "geometry": {"coordinates":[11.25722,11.53973],"type":"Point"}
}