{
  "type": "Feature",
  "properties": {
    "gn:admin1_code":"35.0",
    "gn:asciiname":"Rihu",
    "gn:country_code":"NG",
    "gn:dem":275,
    "gn:feature_class":"P",
    "gn:feature_code":"PPL",
    "gn:name":"Rihu",
    "gn:population":0,
    "gn:timezone":"Africa/Lagos",
    "iso:country":"NG",
    "name:eng_x_preferred":[
        "Rihu"
    ],
    "wof:name":"Rihu",
    "wof:placetype":"locality"
},
  "geometry": {"coordinates":[11.88381,9.29782],"type":"Point"}
}