{
  "type": "Feature",
  "properties": {
    "gn:admin1_code":"52.0",
    "gn:asciiname":"Gbaranfor",
    "gn:country_code":"NG",
    "gn:dem":2,
    "gn:feature_class":"P",
    "gn:feature_code":"PPL",
    "gn:name":"Gbaranfor",
    "gn:population":0,
    "gn:timezone":"Africa/Lagos",
    "iso:country":"NG",
    "name:eng_x_preferred":[
        "Gbaranfor"
    ],
    "wof:name":"Gbaranfor",
    "wof:placetype":"locality"
},
  "geometry": {"coordinates":[5.76436,4.76863],"type":"Point"}
}