{
  "type": "Feature",
  "properties": {
    "gn:admin1_code":"26.0",
    "gn:admin2_code":"7007",
    "gn:asciiname":"Shishi",
    "gn:country_code":"NG",
    "gn:dem":108,
    "gn:feature_class":"P",
    "gn:feature_code":"PPL",
    "gn:name":"Shishi",
    "gn:population":0,
    "gn:timezone":"Africa/Lagos",
    "iso:country":"NG",
    "name:ceb_x_preferred":[
        "Shishi"
    ],
    "name:cym_x_preferred":[
        "Shishi"
    ],
    "name:deu_x_preferred":[
        "Shishi"
    ],
    "name:nor_x_preferred":[
        "Shishi"
    ],
    "name:swe_x_preferred":[
        "Shishi"
    ],
    "wof:name":"Shishi",
    "wof:placetype":"locality"
},
  "geometry": {"coordinates":[8.29876,7.25561],"type":"Point"}
}