{
  "type": "Feature",
  "properties": {
    "gn:admin1_code":"49.0",
    "gn:admin2_code":"32006.0",
    "gn:asciiname":"Danbagarmi",
    "gn:country_code":"NG",
    "gn:dem":1270,
    "gn:feature_class":"P",
    "gn:feature_code":"PPL",
    "gn:name":"Danbagarmi",
    "gn:population":0,
    "gn:timezone":"Africa/Lagos",
    "iso:country":"NG",
    "wof:name":"Danbagarmi",
    "wof:placetype":"neighbourhood"
},
  "geometry": {"coordinates":[8.85635,9.82682],"type":"Point"}
}