{
  "type": "Feature",
  "properties": {
    "gn:admin1_code":"55.0",
    "gn:admin2_code":"16004.0",
    "gn:asciiname":"Walowa",
    "gn:country_code":"NG",
    "gn:dem":369,
    "gn:feature_class":"P",
    "gn:feature_code":"PPL",
    "gn:name":"Walowa",
    "gn:population":0,
    "gn:timezone":"Africa/Lagos",
    "iso:country":"NG",
    "name:eng_x_preferred":[
        "Walowa"
    ],
    "wof:name":"Walowa",
    "wof:placetype":"locality"
},
  "geometry": {"coordinates":[10.56862,10.7074],"type":"Point"}
}