{
  "type": "Feature",
  "properties": {
    "gn:admin1_code":"39.0",
    "gn:admin2_code":"18008.0",
    "gn:admin3_code":"JI1110",
    "gn:asciiname":"Tsangarwa",
    "gn:country_code":"NG",
    "gn:dem":418,
    "gn:feature_class":"P",
    "gn:feature_code":"PPL",
    "gn:name":"Tsangarwa",
    "gn:population":0,
    "gn:timezone":"Africa/Lagos",
    "iso:country":"NG",
    "wof:name":"Tsangarwa",
    "wof:placetype":"locality"
},
  "geometry": {"coordinates":[9.76667,11.43333],"type":"Point"}
}