{
  "type": "Feature",
  "properties": {
    "gn:admin1_code":"57.0",
    "gn:admin2_code":"808.0",
    "gn:admin3_code":"80808",
    "gn:asciiname":"Ado Kompani",
    "gn:country_code":"NG",
    "gn:dem":410,
    "gn:feature_class":"P",
    "gn:feature_code":"PPL",
    "gn:name":"Ado Kompani",
    "gn:population":0,
    "gn:timezone":"Africa/Lagos",
    "iso:country":"NG",
    "wof:name":"Ado Kompani",
    "wof:placetype":"locality"
},
  "geometry": {"coordinates":[6.6244,12.42709],"type":"Point"}
}