{
  "type": "Feature",
  "properties": {
    "gn:admin1_code":"51.0",
    "gn:admin2_code":"608.0",
    "gn:admin3_code":"60810",
    "gn:asciiname":"Gidan Makera",
    "gn:country_code":"NG",
    "gn:dem":306,
    "gn:feature_class":"P",
    "gn:feature_code":"PPL",
    "gn:name":"Gidan Makera",
    "gn:population":0,
    "gn:timezone":"Africa/Lagos",
    "iso:country":"NG",
    "wof:name":"Gidan Makera",
    "wof:placetype":"locality"
},
  "geometry": {"coordinates":[5.41738,13.68382],"type":"Point"}
}