{
  "type": "Feature",
  "properties": {
    "gn:admin1_code":"24.0",
    "gn:admin2_code":"425.0",
    "gn:admin3_code":"42511",
    "gn:asciiname":"Burdugau",
    "gn:country_code":"NG",
    "gn:dem":602,
    "gn:feature_class":"P",
    "gn:feature_code":"PPL",
    "gn:name":"Burdugau",
    "gn:population":0,
    "gn:timezone":"Africa/Lagos",
    "iso:country":"NG",
    "wof:name":"Burdugau",
    "wof:placetype":"locality"
},
  "geometry": {"coordinates":[7.47684,11.78588],"type":"Point"}
}