{
  "type": "Feature",
  "properties": {
    "gn:admin1_code":"24.0",
    "gn:admin2_code":"434.0",
    "gn:admin3_code":"43404",
    "gn:asciiname":"Ruwakas Tami",
    "gn:country_code":"NG",
    "gn:dem":428,
    "gn:feature_class":"P",
    "gn:feature_code":"PPL",
    "gn:name":"Ruwakas Tami",
    "gn:population":0,
    "gn:timezone":"Africa/Lagos",
    "iso:country":"NG",
    "wof:name":"Ruwakas Tami",
    "wof:placetype":"locality"
},
  "geometry": {"coordinates":[8.64809,12.90741],"type":"Point"}
}