{
  "type": "Feature",
  "properties": {
    "gn:admin1_code":"35.0",
    "gn:admin2_code":"2005.0",
    "gn:asciiname":"Kurkasi",
    "gn:country_code":"NG",
    "gn:dem":536,
    "gn:feature_class":"P",
    "gn:feature_code":"PPL",
    "gn:name":"Kurkasi",
    "gn:population":0,
    "gn:timezone":"Africa/Lagos",
    "iso:country":"NG",
    "wof:name":"Kurkasi",
    "wof:placetype":"locality"
},
  "geometry": {"coordinates":[12.3091,10.18478],"type":"Point"}
}