{
  "type": "Feature",
  "properties": {
    "gn:admin1_code":"39.0",
    "gn:admin2_code":"18010.0",
    "gn:admin3_code":"JI1708",
    "gn:asciiname":"Bayan Dutsi",
    "gn:country_code":"NG",
    "gn:dem":471,
    "gn:feature_class":"P",
    "gn:feature_code":"PPL",
    "gn:name":"Bayan Dutsi",
    "gn:population":0,
    "gn:timezone":"Africa/Lagos",
    "iso:country":"NG",
    "wof:name":"Bayan Dutsi",
    "wof:placetype":"locality"
},
  "geometry": {"coordinates":[8.40761,12.68011],"type":"Point"}
}