{
  "type": "Feature",
  "properties": {
    "iso:country":"NG",
    "name:ara_x_preferred":[
        "\u0645\u0637\u0627\u0631 \u0635\u062f\u064a\u0642 \u0623\u0628\u0648 \u0628\u0643\u0631 \u0627\u0644\u062b\u0627\u0644\u062b \u0627\u0644\u062f\u0648\u0644\u064a"
    ],
    "name:eng_x_variant":[
        "SKO",
        "DNSO"
    ],
    "name:fas_x_preferred":[
        "\u0641\u0631\u0648\u062f\u06af\u0627\u0647 \u0628\u06cc\u0646\u200c\u0627\u0644\u0645\u0644\u0644\u06cc \u0635\u0627\u062f\u0642 \u0627\u0628\u0648\u0628\u06a9\u0631 \u06f3"
    ],
    "name:fra_x_preferred":[
        "a\u00e9roport international Sultan Aboubakar III"
    ],
    "name:hau_x_preferred":[
        "Filin jirgin saman Sokoto"
    ],
    "name:ind_x_preferred":[
        "Bandar Udara Internasional Sadiq Abubakar III"
    ],
    "name:pol_x_preferred":[
        "Port lotniczy Sokoto"
    ],
    "name:ron_x_preferred":[
        "Aeroportul Interna\u021bional Sadiq Abubakar III"
    ],
    "name:spa_x_preferred":[
        "Aeropuerto Internacional Sadiq Abubakar III"
    ],
    "oa:elevation_ft":"1010",
    "oa:type":"medium_airport",
    "woe:hierarchy":{
        "country_id":23424908,
        "county_id":56057963,
        "planet_id":1,
        "state_id":2346361
    },
    "wof:name":"Sadiq Abubakar Iii Airport",
    "wof:placetype":"campus"
},
  "geometry": {"coordinates":[5.206944,12.916111],"type":"Point"}
}