{
  "type": "Feature",
  "properties": {
    "iso:country":"NG",
    "oa:elevation_ft":"1010",
    "oa:type":"medium_airport",
    "woe:hierarchy":{
        "country_id":23424908,
        "county_id":56057963,
        "planet_id":1,
        "state_id":2346361
    },
    "wof:name":"Sadiq Abubakar Iii Airport",
    "wof:placetype":"campus"
},
  "geometry": {"coordinates":[5.2069444444444,12.916111111111],"type":"Point"}
}