{
  "type": "Feature",
  "properties": {
    "gn:admin1_code":"46.0",
    "gn:admin2_code":"5019.0",
    "gn:admin3_code":"BA1913",
    "gn:asciiname":"Gasna",
    "gn:country_code":"NG",
    "gn:dem":457,
    "gn:feature_class":"P",
    "gn:feature_code":"PPL",
    "gn:name":"Gasna",
    "gn:population":0,
    "gn:timezone":"Africa/Lagos",
    "iso:country":"NG",
    "wof:name":"Gasna",
    "wof:placetype":"locality"
},
  "geometry": {"coordinates":[9.69786,11.06025],"type":"Point"}
}