{
  "type": "Feature",
  "properties": {
    "gn:admin1_code":"32.0",
    "gn:admin2_code":"31024.0",
    "gn:asciiname":"Alawa",
    "gn:country_code":"NG",
    "gn:dem":431,
    "gn:feature_class":"P",
    "gn:feature_code":"PPL",
    "gn:name":"Alawa",
    "gn:population":0,
    "gn:timezone":"Africa/Lagos",
    "iso:country":"NG",
    "wof:name":"Alawa",
    "wof:placetype":"locality"
},
  "geometry": {"coordinates":[4.16667,8.83333],"type":"Point"}
}