{
  "type": "Feature",
  "properties": {
    "gn:admin1_code":"35.0",
    "gn:admin2_code":"2017.0",
    "gn:asciiname":"Bingi",
    "gn:country_code":"NG",
    "gn:dem":466,
    "gn:feature_class":"P",
    "gn:feature_code":"PPL",
    "gn:name":"Bingi",
    "gn:population":0,
    "gn:timezone":"Africa/Lagos",
    "iso:country":"NG",
    "wof:name":"Bingi",
    "wof:placetype":"locality"
},
  "geometry": {"coordinates":[12.15872,10.02229],"type":"Point"}
}