{
  "type": "Feature",
  "properties": {
    "gn:admin1_code":"24.0",
    "gn:admin2_code":"407.0",
    "gn:admin3_code":"40708",
    "gn:asciiname":"Ungwan Daudu Kira",
    "gn:country_code":"NG",
    "gn:dem":680,
    "gn:feature_class":"P",
    "gn:feature_code":"PPL",
    "gn:name":"Ungwan Daudu Kira",
    "gn:population":0,
    "gn:timezone":"Africa/Lagos",
    "iso:country":"NG",
    "wof:name":"Ungwan Daudu Kira",
    "wof:placetype":"locality"
},
  "geometry": {"coordinates":[7.25302,11.47071],"type":"Point"}
}