{
  "type": "Feature",
  "properties": {
    "gn:admin1_code":"55.0",
    "gn:admin2_code":"16002.0",
    "gn:asciiname":"Balabapa",
    "gn:country_code":"NG",
    "gn:dem":306,
    "gn:feature_class":"P",
    "gn:feature_code":"PPL",
    "gn:name":"Balabapa",
    "gn:population":0,
    "gn:timezone":"Africa/Lagos",
    "iso:country":"NG",
    "wof:name":"Balabapa",
    "wof:placetype":"locality"
},
  "geometry": {"coordinates":[11.55,9.93333],"type":"Point"}
}