{
  "type": "Feature",
  "properties": {
    "gn:admin1_code":"31.0",
    "gn:admin2_code":"27002.0",
    "gn:asciiname":"Aota",
    "gn:country_code":"NG",
    "gn:dem":209,
    "gn:feature_class":"P",
    "gn:feature_code":"PPL",
    "gn:name":"Aota",
    "gn:population":0,
    "gn:timezone":"Africa/Lagos",
    "iso:country":"NG",
    "wof:name":"Aota",
    "wof:placetype":"locality"
},
  "geometry": {"coordinates":[4.34658,10.87901],"type":"Point"}
}