{
  "type": "Feature",
  "properties": {
    "gn:admin1_code":"57.0",
    "gn:admin2_code":"810.0",
    "gn:admin3_code":"81009",
    "gn:asciiname":"Maiinchi",
    "gn:country_code":"NG",
    "gn:dem":405,
    "gn:feature_class":"P",
    "gn:feature_code":"PPL",
    "gn:name":"Maiinchi",
    "gn:population":0,
    "gn:timezone":"Africa/Lagos",
    "iso:country":"NG",
    "name:und_x_variant":[
        "Maiinchi (2)",
        "Maiinchi"
    ],
    "wof:name":"Maiinchi",
    "wof:placetype":"locality"
},
  "geometry": {"coordinates":[6.26703,12.34926],"type":"Point"}
}