{
  "type": "Feature",
  "properties": {
    "gn:admin1_code":"55.0",
    "gn:admin2_code":"16004.0",
    "gn:asciiname":"Gidan Bani",
    "gn:country_code":"NG",
    "gn:dem":464,
    "gn:feature_class":"P",
    "gn:feature_code":"PPL",
    "gn:name":"Gidan Bani",
    "gn:population":0,
    "gn:timezone":"Africa/Lagos",
    "iso:country":"NG",
    "name:eng_x_preferred":[
        "Gidan Bani"
    ],
    "wof:name":"Gidan Bani",
    "wof:placetype":"locality"
},
  "geometry": {"coordinates":[10.73441,10.79259],"type":"Point"}
}