{
  "type": "Feature",
  "properties": {
    "gn:admin1_code":"31.0",
    "gn:admin2_code":"27005",
    "gn:asciiname":"Ruku",
    "gn:country_code":"NG",
    "gn:dem":323,
    "gn:feature_class":"P",
    "gn:feature_code":"PPL",
    "gn:name":"Ruku",
    "gn:population":0,
    "gn:timezone":"Africa/Lagos",
    "iso:country":"NG",
    "name:ara_x_preferred":[
        "\u0631\u0643\u0648\u0639"
    ],
    "name:ava_x_preferred":[
        "\u0420\u0443\u043a\u0443\u0433\u0406"
    ],
    "name:aze_x_preferred":[
        "Ruku"
    ],
    "name:bel_x_preferred":[
        "\u0420\u0443\u043a\u0443"
    ],
    "name:ben_x_preferred":[
        "\u09b0\u09c1\u0995\u09c1"
    ],
    "name:bos_x_preferred":[
        "Ruku'"
    ],
    "name:deu_x_preferred":[
        "Ruk\u016b\u02bf"
    ],
    "name:fas_x_preferred":[
        "\u0631\u06a9\u0648\u0639"
    ],
    "name:fra_x_preferred":[
        "Ruku"
    ],
    "name:ind_x_preferred":[
        "Rukuk"
    ],
    "name:jav_x_preferred":[
        "Ruku'"
    ],
    "name:pan_x_preferred":[
        "\u0a30\u0a41\u0a15\u0a42\u0a05"
    ],
    "name:pus_x_preferred":[
        "\u0631\u06a9\u0648\u0639"
    ],
    "name:rus_x_preferred":[
        "\u0420\u0443\u043a\u0443"
    ],
    "name:snd_x_preferred":[
        "\u0631\u06aa\u0648\u0639"
    ],
    "name:tat_x_preferred":[
        "\u0420\u04e9\u043a\u04af\u0433\u044a"
    ],
    "name:tgk_x_preferred":[
        "\u0420\u0443\u043a\u04ef\u044a"
    ],
    "name:tur_x_preferred":[
        "R\u00fck\u00fb"
    ],
    "name:urd_x_preferred":[
        "\u0631\u06a9\u0648\u0639"
    ],
    "wof:name":"Ruku",
    "wof:placetype":"locality"
},
  "geometry": {"coordinates":[6.63397,9.65031],"type":"Point"}
}