{
  "type": "Feature",
  "properties": {
    "gn:admin1_code":"16.0",
    "gn:admin2_code":"28007.0",
    "gn:asciiname":"Isasi",
    "gn:country_code":"NG",
    "gn:dem":14,
    "gn:feature_class":"P",
    "gn:feature_code":"PPL",
    "gn:name":"Isasi",
    "gn:population":0,
    "gn:timezone":"Africa/Lagos",
    "iso:country":"NG",
    "name:und_x_variant":[
        "Ishersi",
        "Isasi"
    ],
    "wof:name":"Isasi",
    "wof:placetype":"neighbourhood"
},
  "geometry": {"coordinates":[3.37563,6.66662],"type":"Point"}
}