{
  "type": "Feature",
  "properties": {
    "gn:admin1_code":"51.0",
    "gn:admin2_code":"604.0",
    "gn:admin3_code":"60405",
    "gn:asciiname":"Gedi",
    "gn:country_code":"NG",
    "gn:dem":307,
    "gn:feature_class":"P",
    "gn:feature_code":"PPL",
    "gn:name":"Gedi",
    "gn:population":0,
    "gn:timezone":"Africa/Lagos",
    "iso:country":"NG",
    "name:ceb_x_preferred":[
        "Gedi"
    ],
    "name:ita_x_preferred":[
        "Gedi"
    ],
    "name:swe_x_preferred":[
        "Gedi"
    ],
    "name:und_x_variant":[
        "Baredi"
    ],
    "wof:name":"Gedi",
    "wof:placetype":"locality"
},
  "geometry": {"coordinates":[5.693,13.7066],"type":"Point"}
}