{
  "type": "Feature",
  "properties": {
    "gn:admin1_code":"32.0",
    "gn:admin2_code":"31020.0",
    "gn:asciiname":"Oyedeji",
    "gn:country_code":"NG",
    "gn:dem":226,
    "gn:feature_class":"P",
    "gn:feature_code":"PPL",
    "gn:name":"Oyedeji",
    "gn:population":0,
    "gn:timezone":"Africa/Lagos",
    "iso:country":"NG",
    "wof:name":"Oyedeji",
    "wof:placetype":"locality"
},
  "geometry": {"coordinates":[4.05,7.55],"type":"Point"}
}