{
  "type": "Feature",
  "properties": {
    "gn:admin1_code":"47.0",
    "gn:admin2_code":"14009.0",
    "gn:asciiname":"Ovoko",
    "gn:country_code":"NG",
    "gn:dem":407,
    "gn:feature_class":"P",
    "gn:feature_code":"PPL",
    "gn:name":"Ovoko",
    "gn:population":0,
    "gn:timezone":"Africa/Lagos",
    "iso:country":"NG",
    "name:und_x_variant":[
        "Ofoko"
    ],
    "wof:name":"Ovoko",
    "wof:placetype":"locality"
},
  "geometry": {"coordinates":[7.45847,6.88583],"type":"Point"}
}