{
  "type": "Feature",
  "properties": {
    "gn:admin1_code":"42.0",
    "gn:admin2_code":"30014.0",
    "gn:asciiname":"Ifetedo",
    "gn:country_code":"NG",
    "gn:dem":217,
    "gn:feature_class":"P",
    "gn:feature_code":"PPLA2",
    "gn:name":"Ifetedo",
    "gn:population":0,
    "gn:timezone":"Africa/Lagos",
    "iso:country":"NG",
    "wof:name":"Ifetedo",
    "wof:placetype":"locality"
},
  "geometry": {"coordinates":[4.70046,7.18419],"type":"Point"}
}