{
  "type": "Feature",
  "properties": {
    "gn:admin1_code":"32.0",
    "gn:admin2_code":"31001.0",
    "gn:asciiname":"Osa",
    "gn:country_code":"NG",
    "gn:dem":290,
    "gn:feature_class":"P",
    "gn:feature_code":"PPL",
    "gn:name":"Osa",
    "gn:population":0,
    "gn:timezone":"Africa/Lagos",
    "iso:country":"NG",
    "wof:name":"Osa",
    "wof:placetype":"locality"
},
  "geometry": {"coordinates":[3.99472,7.68806],"type":"Point"}
}