{
  "type": "Feature",
  "properties": {
    "gn:admin1_code":"31.0",
    "gn:admin2_code":"27015.0",
    "gn:asciiname":"Urudu",
    "gn:cc2":"NG",
    "gn:country_code":"NG",
    "gn:dem":278,
    "gn:feature_class":"P",
    "gn:feature_code":"PPL",
    "gn:name":"Urudu",
    "gn:population":0,
    "gn:timezone":"Africa/Lagos",
    "iso:country":"NG",
    "name:und_x_variant":[
        "Durugu",
        "Urudu"
    ],
    "wof:name":"Urudu",
    "wof:placetype":"locality"
},
  "geometry": {"coordinates":[5.92167,10.18722],"type":"Point"}
}