{
  "type": "Feature",
  "properties": {
    "gn:admin1_code":"50.0",
    "gn:admin2_code":"33023.0",
    "gn:asciiname":"Akporo",
    "gn:country_code":"NG",
    "gn:dem":18,
    "gn:feature_class":"P",
    "gn:feature_code":"PPL",
    "gn:name":"Akporo",
    "gn:population":0,
    "gn:timezone":"Africa/Lagos",
    "iso:country":"NG",
    "wof:name":"Akporo",
    "wof:placetype":"locality"
},
  "geometry": {"coordinates":[7.21144,4.71917],"type":"Point"}
}