{
  "type": "Feature",
  "properties": {
    "gn:admin1_code":"41.0",
    "gn:admin2_code":"23005.0",
    "gn:asciiname":"Kefi",
    "gn:country_code":"NG",
    "gn:dem":379,
    "gn:feature_class":"P",
    "gn:feature_code":"PPL",
    "gn:name":"Kefi",
    "gn:population":0,
    "gn:timezone":"Africa/Lagos",
    "iso:country":"NG",
    "name:und_x_variant":[
        "Keffi",
        "Kefi"
    ],
    "wof:name":"Kefi",
    "wof:placetype":"locality"
},
  "geometry": {"coordinates":[7.05,7.55],"type":"Point"}
}