{
  "type": "Feature",
  "properties": {
    "gn:admin1_code":"36.0",
    "gn:asciiname":"Brisibegbene",
    "gn:country_code":"NG",
    "gn:dem":7,
    "gn:feature_class":"P",
    "gn:feature_code":"PPL",
    "gn:name":"Brisibegbene",
    "gn:population":0,
    "gn:timezone":"Africa/Lagos",
    "iso:country":"NG",
    "name:eng_x_preferred":[
        "Brisibegbene"
    ],
    "wof:name":"Brisibegbene",
    "wof:placetype":"locality"
},
  "geometry": {"coordinates":[5.51432,5.43253],"type":"Point"}
}