{
  "type": "Feature",
  "properties": {
    "gn:admin1_code":"23.0",
    "gn:admin2_code":"19008",
    "gn:admin3_code":"KD0810",
    "gn:asciiname":"Gyani",
    "gn:country_code":"NG",
    "gn:dem":748,
    "gn:feature_class":"P",
    "gn:feature_code":"PPL",
    "gn:name":"Gyani",
    "gn:population":0,
    "gn:timezone":"Africa/Lagos",
    "iso:country":"NG",
    "wof:name":"Gyani",
    "wof:placetype":"locality"
},
  "geometry": {"coordinates":[8.01732,9.61132],"type":"Point"}
}