{
  "type": "Feature",
  "properties": {
    "gn:admin1_code":"24.0",
    "gn:admin2_code":"404.0",
    "gn:admin3_code":"40410",
    "gn:asciiname":"Yan Gagi",
    "gn:country_code":"NG",
    "gn:dem":399,
    "gn:feature_class":"P",
    "gn:feature_code":"PPL",
    "gn:name":"Yan Gagi",
    "gn:population":0,
    "gn:timezone":"Africa/Lagos",
    "iso:country":"NG",
    "name:und_x_variant":[
        "Dan Gagi",
        "Yan Gagi"
    ],
    "wof:name":"Yan Gagi",
    "wof:placetype":"locality"
},
  "geometry": {"coordinates":[8.78152,12.7422],"type":"Point"}
}