{
  "type": "Feature",
  "properties": {
    "gn:admin1_code":"35.0",
    "gn:asciiname":"Buaso",
    "gn:country_code":"NG",
    "gn:dem":141,
    "gn:feature_class":"P",
    "gn:feature_code":"PPL",
    "gn:name":"Buaso",
    "gn:population":0,
    "gn:timezone":"Africa/Lagos",
    "iso:country":"NG",
    "name:eng_x_preferred":[
        "Buaso"
    ],
    "wof:name":"Buaso",
    "wof:placetype":"locality"
},
  "geometry": {"coordinates":[11.51911,9.45708],"type":"Point"}
}