{
  "type": "Feature",
  "properties": {
    "gn:admin1_code":"35.0",
    "gn:admin2_code":"2005.0",
    "gn:asciiname":"Dongo Mutila",
    "gn:country_code":"NG",
    "gn:dem":511,
    "gn:feature_class":"P",
    "gn:feature_code":"PPL",
    "gn:name":"Dongo Mutila",
    "gn:population":0,
    "gn:timezone":"Africa/Lagos",
    "iso:country":"NG",
    "wof:name":"Dongo Mutila",
    "wof:placetype":"locality"
},
  "geometry": {"coordinates":[12.71714,10.22437],"type":"Point"}
}