{
  "type": "Feature",
  "properties": {
    "gn:admin1_code":"57.0",
    "gn:admin2_code":"807.0",
    "gn:admin3_code":"80704",
    "gn:asciiname":"Magami",
    "gn:country_code":"NG",
    "gn:dem":561,
    "gn:feature_class":"P",
    "gn:feature_code":"PPL",
    "gn:name":"Magami",
    "gn:population":0,
    "gn:timezone":"Africa/Lagos",
    "iso:country":"NG",
    "wof:name":"Magami",
    "wof:placetype":"locality"
},
  "geometry": {"coordinates":[6.59011,11.71844],"type":"Point"}
}