{
  "type": "Feature",
  "properties": {
    "gn:admin1_code":"57.0",
    "gn:admin2_code":"803.0",
    "gn:admin3_code":"80307",
    "gn:asciiname":"Tun Kuda",
    "gn:country_code":"NG",
    "gn:dem":463,
    "gn:feature_class":"P",
    "gn:feature_code":"PPL",
    "gn:name":"Tun Kuda",
    "gn:population":0,
    "gn:timezone":"Africa/Lagos",
    "iso:country":"NG",
    "wof:name":"Tun Kuda",
    "wof:placetype":"locality"
},
  "geometry": {"coordinates":[6.85741,12.27759],"type":"Point"}
}