{
  "type": "Feature",
  "properties": {
    "gn:admin1_code":"56.0",
    "gn:admin2_code":"26010.0",
    "gn:asciiname":"Alogani",
    "gn:country_code":"NG",
    "gn:dem":252,
    "gn:feature_class":"P",
    "gn:feature_code":"PPL",
    "gn:name":"Alogani",
    "gn:population":0,
    "gn:timezone":"Africa/Lagos",
    "iso:country":"NG",
    "wof:name":"Alogani",
    "wof:placetype":"locality"
},
  "geometry": {"coordinates":[8.53333,8.71667],"type":"Point"}
}