{
  "type": "Feature",
  "properties": {
    "gn:admin1_code":"43.0",
    "gn:asciiname":"Jambutu",
    "gn:country_code":"NG",
    "gn:dem":174,
    "gn:feature_class":"P",
    "gn:feature_code":"PPL",
    "gn:name":"Jambutu",
    "gn:population":0,
    "gn:timezone":"Africa/Lagos",
    "iso:country":"NG",
    "name:eng_x_preferred":[
        "Jambutu"
    ],
    "wof:name":"Jambutu",
    "wof:placetype":"locality"
},
  "geometry": {"coordinates":[10.92105,9.24662],"type":"Point"}
}