{
  "type": "Feature",
  "properties": {
    "gn:admin1_code":"36.0",
    "gn:admin2_code":"10012.0",
    "gn:asciiname":"Umusa-Dege",
    "gn:country_code":"NG",
    "gn:dem":72,
    "gn:feature_class":"P",
    "gn:feature_code":"PPL",
    "gn:name":"Umusa-Dege",
    "gn:population":0,
    "gn:timezone":"Africa/Lagos",
    "iso:country":"NG",
    "name:eng_x_preferred":[
        "Umusa-Dege"
    ],
    "name:eng_x_variant":[
        "Ekum Osadegbe"
    ],
    "wof:name":"Umusa-Dege",
    "wof:placetype":"locality"
},
  "geometry": {"coordinates":[6.29006,6.01248],"type":"Point"}
}