{
  "type": "Feature",
  "properties": {
    "gn:admin1_code":"24.0",
    "gn:admin2_code":"401.0",
    "gn:admin3_code":"40108",
    "gn:asciiname":"Garau Goje",
    "gn:country_code":"NG",
    "gn:dem":595,
    "gn:feature_class":"P",
    "gn:feature_code":"PPL",
    "gn:name":"Garau Goje",
    "gn:population":0,
    "gn:timezone":"Africa/Lagos",
    "iso:country":"NG",
    "wof:name":"Garau Goje",
    "wof:placetype":"locality"
},
  "geometry": {"coordinates":[7.34818,11.76373],"type":"Point"}
}