{
  "type": "Feature",
  "properties": {
    "gn:admin1_code":"50.0",
    "gn:admin2_code":"33006",
    "gn:asciiname":"Oru Agbalama",
    "gn:country_code":"NG",
    "gn:dem":11,
    "gn:feature_class":"P",
    "gn:feature_code":"PPL",
    "gn:name":"Oru Agbalama",
    "gn:population":0,
    "gn:timezone":"Africa/Lagos",
    "iso:country":"NG",
    "wof:name":"Oru Agbalama",
    "wof:placetype":"locality"
},
  "geometry": {"coordinates":[6.8307,4.77201],"type":"Point"}
}