{
  "type": "Feature",
  "properties": {
    "gn:admin1_code":"21.0",
    "gn:admin2_code":"3018.0",
    "gn:asciiname":"Atanuk",
    "gn:country_code":"NG",
    "gn:dem":27,
    "gn:feature_class":"P",
    "gn:feature_code":"PPL",
    "gn:name":"Atanuk",
    "gn:population":0,
    "gn:timezone":"Africa/Lagos",
    "iso:country":"NG",
    "wof:name":"Atanuk",
    "wof:placetype":"locality"
},
  "geometry": {"coordinates":[7.81886,4.63798],"type":"Point"}
}