{
  "type": "Feature",
  "properties": {
    "gn:admin1_code":"23.0",
    "gn:admin2_code":"19001.0",
    "gn:admin3_code":"KD0104",
    "gn:asciiname":"Pasala",
    "gn:country_code":"NG",
    "gn:dem":503,
    "gn:feature_class":"P",
    "gn:feature_code":"PPL",
    "gn:name":"Pasala",
    "gn:population":0,
    "gn:timezone":"Africa/Lagos",
    "iso:country":"NG",
    "wof:name":"Pasala",
    "wof:placetype":"locality"
},
  "geometry": {"coordinates":[6.52294,10.80505],"type":"Point"}
}