{
  "type": "Feature",
  "properties": {
    "gn:admin1_code":"54.0",
    "gn:admin2_code":"13015.0",
    "gn:asciiname":"Epe",
    "gn:country_code":"NG",
    "gn:dem":551,
    "gn:feature_class":"P",
    "gn:feature_code":"PPL",
    "gn:name":"Epe",
    "gn:population":0,
    "gn:timezone":"Africa/Lagos",
    "iso:country":"NG",
    "wof:name":"Epe",
    "wof:placetype":"locality"
},
  "geometry": {"coordinates":[5.09651,7.98317],"type":"Point"}
}