{
  "type": "Feature",
  "properties": {
    "gn:admin1_code":"25.0",
    "gn:admin2_code":"4001.0",
    "gn:asciiname":"Akpo",
    "gn:country_code":"NG",
    "gn:dem":311,
    "gn:feature_class":"P",
    "gn:feature_code":"PPL",
    "gn:name":"Akpo",
    "gn:population":0,
    "gn:timezone":"Africa/Lagos",
    "iso:country":"NG",
    "name:fra_x_preferred":[
        "Akpo"
    ],
    "wof:name":"Akpo",
    "wof:placetype":"locality"
},
  "geometry": {"coordinates":[7.09909,5.96302],"type":"Point"}
}