{
  "type": "Feature",
  "properties": {
    "gn:admin1_code":"41.0",
    "gn:admin2_code":"23011.0",
    "gn:asciiname":"Igeheko",
    "gn:country_code":"NG",
    "gn:dem":131,
    "gn:feature_class":"P",
    "gn:feature_code":"PPL",
    "gn:name":"Igeheko",
    "gn:population":0,
    "gn:timezone":"Africa/Lagos",
    "iso:country":"NG",
    "wof:name":"Igeheko",
    "wof:placetype":"locality"
},
  "geometry": {"coordinates":[6.88333,8.31667],"type":"Point"}
}