{
  "type": "Feature",
  "properties": {
    "gn:admin1_code":"23.0",
    "gn:admin2_code":"19015.0",
    "gn:admin3_code":"KD1509",
    "gn:asciiname":"Dan Maliki",
    "gn:country_code":"NG",
    "gn:dem":714,
    "gn:feature_class":"P",
    "gn:feature_code":"PPL",
    "gn:name":"Dan Maliki",
    "gn:population":0,
    "gn:timezone":"Africa/Lagos",
    "iso:country":"NG",
    "wof:name":"Dan Maliki",
    "wof:placetype":"locality"
},
  "geometry": {"coordinates":[8.35445,10.58506],"type":"Point"}
}