{
  "type": "Feature",
  "properties": {
    "gn:admin1_code":"40.0",
    "gn:admin2_code":"512.0",
    "gn:admin3_code":"51205",
    "gn:asciiname":"Kalgo",
    "gn:country_code":"NG",
    "gn:dem":204,
    "gn:feature_class":"P",
    "gn:feature_code":"PPLA2",
    "gn:name":"Kalgo",
    "gn:population":0,
    "gn:timezone":"Africa/Lagos",
    "iso:country":"NG",
    "name:fra_x_preferred":[
        "Kalgo"
    ],
    "name:hau_x_preferred":[
        "Kalgo"
    ],
    "name:ita_x_preferred":[
        "Kalgo"
    ],
    "name:spa_x_preferred":[
        "Kalgo"
    ],
    "wof:name":"Kalgo",
    "wof:placetype":"locality"
},
  "geometry": {"coordinates":[4.2004,12.32666],"type":"Point"}
}