{
  "type": "Feature",
  "properties": {
    "gn:admin1_code":"50.0",
    "gn:admin2_code":"33004.0",
    "gn:asciiname":"Dabibikiri",
    "gn:country_code":"NG",
    "gn:dem":15,
    "gn:feature_class":"P",
    "gn:feature_code":"PPL",
    "gn:name":"Dabibikiri",
    "gn:population":0,
    "gn:timezone":"Africa/Lagos",
    "iso:country":"NG",
    "wof:name":"Dabibikiri",
    "wof:placetype":"locality"
},
  "geometry": {"coordinates":[6.71415,4.39706],"type":"Point"}
}