{
  "type": "Feature",
  "properties": {
    "gn:admin1_code":"37.0",
    "gn:admin2_code":"12005.0",
    "gn:asciiname":"Anemene",
    "gn:country_code":"NG",
    "gn:dem":38,
    "gn:feature_class":"P",
    "gn:feature_code":"PPL",
    "gn:name":"Anemene",
    "gn:population":0,
    "gn:timezone":"Africa/Lagos",
    "iso:country":"NG",
    "name:eng_x_preferred":[
        "Anemene"
    ],
    "wof:name":"Anemene",
    "wof:placetype":"locality"
},
  "geometry": {"coordinates":[6.59203,6.7512],"type":"Point"}
}