{
  "type": "Feature",
  "properties": {
    "gn:admin1_code":"27.0",
    "gn:admin2_code":"110",
    "gn:admin3_code":"11010",
    "gn:asciiname":"Nyamaram",
    "gn:country_code":"NG",
    "gn:dem":296,
    "gn:feature_class":"P",
    "gn:feature_code":"PPL",
    "gn:name":"Nyamaram",
    "gn:population":0,
    "gn:timezone":"Africa/Lagos",
    "iso:country":"NG",
    "wof:name":"Nyamaram",
    "wof:placetype":"locality"
},
  "geometry": {"coordinates":[13.39561,13.02202],"type":"Point"}
}