{
  "type": "Feature",
  "properties": {
    "gn:admin1_code":"43.0",
    "gn:admin2_code":"35009.0",
    "gn:asciiname":"Asha",
    "gn:country_code":"NG",
    "gn:dem":306,
    "gn:feature_class":"P",
    "gn:feature_code":"PPL",
    "gn:name":"Asha",
    "gn:population":0,
    "gn:timezone":"Africa/Lagos",
    "iso:country":"NG",
    "name:ben_x_preferred":[
        "\u0986\u09b6\u09be"
    ],
    "name:cat_x_preferred":[
        "Aixa"
    ],
    "name:ces_x_preferred":[
        "A\u0161a"
    ],
    "name:diq_x_preferred":[
        "E\u015fa"
    ],
    "name:ell_x_preferred":[
        "\u0386\u03c3\u03b1"
    ],
    "name:fas_x_preferred":[
        "\u0627\u0634\u0647"
    ],
    "name:fra_x_preferred":[
        "Asha"
    ],
    "name:heb_x_preferred":[
        "\u05d0\u05e9\u05d4"
    ],
    "name:hin_x_preferred":[
        "\u0906\u0936\u093e"
    ],
    "name:hye_x_preferred":[
        "\u0531\u0577\u0561"
    ],
    "name:ind_x_preferred":[
        "Asha"
    ],
    "name:ita_x_preferred":[
        "A\u0161a"
    ],
    "name:jpn_x_preferred":[
        "\u30a2\u30b7\u30e3\u30fb\u30ef\u30d2\u30b7\u30e5\u30bf"
    ],
    "name:kor_x_preferred":[
        "\uc544\uc0e4"
    ],
    "name:mkd_x_preferred":[
        "\u0410\u0448\u0430"
    ],
    "name:pol_x_preferred":[
        "Ardibeheszt"
    ],
    "name:por_x_preferred":[
        "Asha"
    ],
    "name:ron_x_preferred":[
        "A\u0219a"
    ],
    "name:spa_x_preferred":[
        "Asha"
    ],
    "name:swe_x_preferred":[
        "Asja"
    ],
    "name:swe_x_variant":[
        "Asha"
    ],
    "name:zho_x_preferred":[
        "\u963f\u6c99\u00b7\u74e6\u5e0c\u4ec0\u5854"
    ],
    "wof:name":"Asha",
    "wof:placetype":"locality"
},
  "geometry": {"coordinates":[10.78361,7.08881],"type":"Point"}
}