{
  "type": "Feature",
  "properties": {
    "gn:admin1_code":"43.0",
    "gn:admin2_code":"35009.0",
    "gn:asciiname":"Asha",
    "gn:country_code":"NG",
    "gn:dem":306,
    "gn:feature_class":"P",
    "gn:feature_code":"PPL",
    "gn:name":"Asha",
    "gn:population":0,
    "gn:timezone":"Africa/Lagos",
    "iso:country":"NG",
    "wof:name":"Asha",
    "wof:placetype":"locality"
},
  "geometry": {"coordinates":[10.78361,7.08881],"type":"Point"}
}