{
  "type": "Feature",
  "properties": {
    "gn:admin1_code":"36.0",
    "gn:admin2_code":"10019.0",
    "gn:asciiname":"Onidjor Egbo-Uwheru",
    "gn:country_code":"NG",
    "gn:dem":13,
    "gn:feature_class":"P",
    "gn:feature_code":"PPL",
    "gn:name":"Onidjor Egbo-Uwheru",
    "gn:population":0,
    "gn:timezone":"Africa/Lagos",
    "iso:country":"NG",
    "name:und_x_variant":[
        "Onidjor",
        "Egbo-Uwheru",
        "Onidjor Egbo-Uwheru"
    ],
    "wof:name":"Onidjor Egbo-Uwheru",
    "wof:placetype":"locality"
},
  "geometry": {"coordinates":[6.06322,5.34366],"type":"Point"}
}