{
  "type": "Feature",
  "properties": {
    "gn:admin1_code":"25.0",
    "gn:admin2_code":"4006.0",
    "gn:asciiname":"Okpuno-Awka",
    "gn:country_code":"NG",
    "gn:dem":106,
    "gn:feature_class":"P",
    "gn:feature_code":"PPL",
    "gn:name":"Okpuno-Awka",
    "gn:population":0,
    "gn:timezone":"Africa/Lagos",
    "iso:country":"NG",
    "name:und_x_variant":[
        "Okpuno",
        "Okpuno-Awka"
    ],
    "wof:name":"Okpuno-Awka",
    "wof:placetype":"neighbourhood"
},
  "geometry": {"coordinates":[7.07367,6.25546],"type":"Point"}
}