{
  "type": "Feature",
  "properties": {
    "gn:admin1_code":"21.0",
    "gn:admin2_code":"3015.0",
    "gn:asciiname":"Ikot-Ebiasang",
    "gn:country_code":"NG",
    "gn:dem":80,
    "gn:feature_class":"P",
    "gn:feature_code":"PPL",
    "gn:name":"Ikot-Ebiasang",
    "gn:population":0,
    "gn:timezone":"Africa/Lagos",
    "iso:country":"NG",
    "wof:name":"Ikot-Ebiasang",
    "wof:placetype":"locality"
},
  "geometry": {"coordinates":[7.79029,5.30404],"type":"Point"}
}