{
  "type": "Feature",
  "properties": {
    "gn:admin1_code":"57.0",
    "gn:admin2_code":"813.0",
    "gn:admin3_code":"81307",
    "gn:asciiname":"Babban Kauye",
    "gn:country_code":"NG",
    "gn:dem":551,
    "gn:feature_class":"P",
    "gn:feature_code":"PPL",
    "gn:name":"Babban Kauye",
    "gn:population":0,
    "gn:timezone":"Africa/Lagos",
    "iso:country":"NG",
    "wof:name":"Babban Kauye",
    "wof:placetype":"locality"
},
  "geometry": {"coordinates":[6.87466,11.91032],"type":"Point"}
}