{
  "type": "Feature",
  "properties": {
    "gn:admin1_code":"51.0",
    "gn:admin2_code":"620.0",
    "gn:admin3_code":"62008",
    "gn:asciiname":"Modomowa",
    "gn:country_code":"NG",
    "gn:dem":270,
    "gn:feature_class":"P",
    "gn:feature_code":"PPL",
    "gn:name":"Modomowa",
    "gn:population":0,
    "gn:timezone":"Africa/Lagos",
    "iso:country":"NG",
    "name:und_x_variant":[
        "Modomowe",
        "Modoma",
        "Modomowa"
    ],
    "wof:name":"Modomowa",
    "wof:placetype":"locality"
},
  "geometry": {"coordinates":[5.46971,12.57974],"type":"Point"}
}