{
  "type": "Feature",
  "properties": {
    "gn:admin1_code":"41.0",
    "gn:admin2_code":"23010.0",
    "gn:asciiname":"Guguriji",
    "gn:country_code":"NG",
    "gn:dem":264,
    "gn:feature_class":"P",
    "gn:feature_code":"PPL",
    "gn:name":"Guguriji",
    "gn:population":0,
    "gn:timezone":"Africa/Lagos",
    "iso:country":"NG",
    "wof:name":"Guguriji",
    "wof:placetype":"locality"
},
  "geometry": {"coordinates":[6.15,8.38333],"type":"Point"}
}