{
  "type": "Feature",
  "properties": {
    "gn:admin1_code":"44.0",
    "gn:admin2_code":"705.0",
    "gn:admin3_code":"70501",
    "gn:asciiname":"Gula",
    "gn:country_code":"NG",
    "gn:dem":408,
    "gn:feature_class":"P",
    "gn:feature_code":"PPL",
    "gn:name":"Gula",
    "gn:population":0,
    "gn:timezone":"Africa/Lagos",
    "iso:country":"NG",
    "name:ara_x_preferred":[
        "\u063a\u0648\u0644\u0627"
    ],
    "name:ceb_x_preferred":[
        "Gula"
    ],
    "name:deu_x_preferred":[
        "Gula"
    ],
    "name:fra_x_preferred":[
        "Gula"
    ],
    "name:ita_x_preferred":[
        "Gula"
    ],
    "name:pol_x_preferred":[
        "Gula"
    ],
    "name:por_x_preferred":[
        "Gula"
    ],
    "name:slk_x_preferred":[
        "Gula"
    ],
    "name:swe_x_preferred":[
        "Gula"
    ],
    "wof:name":"Gula",
    "wof:placetype":"locality"
},
  "geometry": {"coordinates":[11.56918,11.60671],"type":"Point"}
}