{
  "type": "Feature",
  "properties": {
    "gn:admin1_code":"56.0",
    "gn:admin2_code":"26004.0",
    "gn:asciiname":"Kurafe",
    "gn:country_code":"NG",
    "gn:dem":343,
    "gn:feature_class":"P",
    "gn:feature_code":"PPL",
    "gn:name":"Kurafe",
    "gn:population":0,
    "gn:timezone":"Africa/Lagos",
    "iso:country":"NG",
    "wof:name":"Kurafe",
    "wof:placetype":"locality"
},
  "geometry": {"coordinates":[7.63056,8.80167],"type":"Point"}
}