{
  "type": "Feature",
  "properties": {
    "gn:admin1_code":"37.0",
    "gn:admin2_code":"12014.0",
    "gn:asciiname":"Aihuobabekun",
    "gn:country_code":"NG",
    "gn:dem":155,
    "gn:feature_class":"P",
    "gn:feature_code":"PPL",
    "gn:name":"Aihuobabekun",
    "gn:population":0,
    "gn:timezone":"Africa/Lagos",
    "iso:country":"NG",
    "name:und_x_variant":[
        "Awiwabekun",
        "Aihobabekun",
        "Aihuobabekun"
    ],
    "wof:name":"Aihuobabekun",
    "wof:placetype":"locality"
},
  "geometry": {"coordinates":[5.6783,6.53948],"type":"Point"}
}