{
  "type": "Feature",
  "properties": {
    "gn:admin1_code":"5.0",
    "gn:admin2_code":"25009.0",
    "gn:asciiname":"Ogogoro",
    "gn:country_code":"NG",
    "gn:dem":7,
    "gn:feature_class":"P",
    "gn:feature_code":"PPL",
    "gn:name":"Ogogoro",
    "gn:population":0,
    "gn:timezone":"Africa/Lagos",
    "iso:country":"NG",
    "name:und_x_variant":[
        "Awgawgawraw",
        "Ogogoro"
    ],
    "wof:name":"Ogogoro",
    "wof:placetype":"locality"
},
  "geometry": {"coordinates":[3.93486,6.49809],"type":"Point"}
}