{
  "type": "Feature",
  "properties": {
    "gn:admin1_code":"31.0",
    "gn:admin2_code":"27020.0",
    "gn:asciiname":"Bejagira",
    "gn:country_code":"NG",
    "gn:dem":363,
    "gn:feature_class":"P",
    "gn:feature_code":"PPL",
    "gn:name":"Bejagira",
    "gn:population":0,
    "gn:timezone":"Africa/Lagos",
    "iso:country":"NG",
    "wof:name":"Bejagira",
    "wof:placetype":"locality"
},
  "geometry": {"coordinates":[6.06667,10.41667],"type":"Point"}
}