{
  "type": "Feature",
  "properties": {
    "gn:admin1_code":"40.0",
    "gn:admin2_code":"518.0",
    "gn:admin3_code":"51802",
    "gn:asciiname":"Zakwa",
    "gn:country_code":"NG",
    "gn:dem":188,
    "gn:feature_class":"P",
    "gn:feature_code":"PPL",
    "gn:name":"Zakwa",
    "gn:population":0,
    "gn:timezone":"Africa/Lagos",
    "iso:country":"NG",
    "name:und_x_variant":[
        "Zokwa",
        "Zakwa"
    ],
    "wof:name":"Zakwa",
    "wof:placetype":"locality"
},
  "geometry": {"coordinates":[4.10067,11.86045],"type":"Point"}
}