{
  "type": "Feature",
  "properties": {
    "gn:admin1_code":"23.0",
    "gn:admin2_code":"19020.0",
    "gn:admin3_code":"KD2002",
    "gn:asciiname":"Vagbak",
    "gn:country_code":"NG",
    "gn:dem":507,
    "gn:feature_class":"P",
    "gn:feature_code":"PPL",
    "gn:name":"Vagbak",
    "gn:population":0,
    "gn:timezone":"Africa/Lagos",
    "iso:country":"NG",
    "name:und_x_variant":[
        "Ungwan Mallam Isa"
    ],
    "wof:name":"Vagbak",
    "wof:placetype":"locality"
},
  "geometry": {"coordinates":[8.34444,9.19352],"type":"Point"}
}