{
  "type": "Feature",
  "properties": {
    "gn:admin1_code":"31.0",
    "gn:admin2_code":"27016.0",
    "gn:asciiname":"Sanaga",
    "gn:country_code":"NG",
    "gn:dem":164,
    "gn:feature_class":"P",
    "gn:feature_code":"PPL",
    "gn:name":"Sanaga",
    "gn:population":0,
    "gn:timezone":"Africa/Lagos",
    "iso:country":"NG",
    "name:eus_x_preferred":[
        "Sanaga"
    ],
    "name:rus_x_preferred":[
        "\u0421\u0430\u043d\u0430\u0433\u0430"
    ],
    "wof:name":"Sanaga",
    "wof:placetype":"locality"
},
  "geometry": {"coordinates":[5.26667,9.61667],"type":"Point"}
}