{
  "type": "Feature",
  "properties": {
    "gn:admin1_code":"31.0",
    "gn:admin2_code":"27016.0",
    "gn:asciiname":"Sanaga",
    "gn:country_code":"NG",
    "gn:dem":164,
    "gn:feature_class":"P",
    "gn:feature_code":"PPL",
    "gn:name":"Sanaga",
    "gn:population":0,
    "gn:timezone":"Africa/Lagos",
    "iso:country":"NG",
    "name:ara_x_preferred":[
        "\u0633\u0627\u0646\u0627\u062c\u0627"
    ],
    "name:ben_x_preferred":[
        "\u09b8\u09be\u09a8\u09be\u0997\u09be"
    ],
    "name:ell_x_preferred":[
        "\u03a3\u03b1\u03bd\u03ac\u03b3\u03ba\u03b1"
    ],
    "name:eus_x_preferred":[
        "Sanaga"
    ],
    "name:fas_x_preferred":[
        "\u0633\u0627\u0646\u0627\u06af\u0627"
    ],
    "name:hin_x_preferred":[
        "\u0938\u0928\u093e\u0917\u093e"
    ],
    "name:hun_x_preferred":[
        "Sanaga"
    ],
    "name:ind_x_preferred":[
        "Sanaga"
    ],
    "name:kor_x_preferred":[
        "\uc0ac\ub098\uac00"
    ],
    "name:rus_x_preferred":[
        "\u0421\u0430\u043d\u0430\u0433\u0430"
    ],
    "name:tur_x_preferred":[
        "Sanaga"
    ],
    "name:urd_x_preferred":[
        "\u0633\u0627\u0646\u0627\u06af\u0627"
    ],
    "name:vie_x_preferred":[
        "S\u00f4ng Sanaga"
    ],
    "wof:name":"Sanaga",
    "wof:placetype":"locality"
},
  "geometry": {"coordinates":[5.26667,9.61667],"type":"Point"}
}