{
  "type": "Feature",
  "properties": {
    "gn:admin1_code":"29.0",
    "gn:admin2_code":"20003.0",
    "gn:admin3_code":"KN1506",
    "gn:asciiname":"Garun Malam",
    "gn:country_code":"NG",
    "gn:dem":504,
    "gn:feature_class":"P",
    "gn:feature_code":"PPLA2",
    "gn:name":"Garun Malam",
    "gn:population":0,
    "gn:timezone":"Africa/Lagos",
    "iso:country":"NG",
    "name:und_x_variant":[
        "Garum Mallam",
        "Garum Malam",
        "Garun Malam"
    ],
    "wof:name":"Garun Malam",
    "wof:placetype":"locality"
},
  "geometry": {"coordinates":[8.36986,11.68566],"type":"Point"}
}