{
  "type": "Feature",
  "properties": {
    "gn:admin1_code":"53.0",
    "gn:admin2_code":"11010.0",
    "gn:asciiname":"Okpoduma",
    "gn:country_code":"NG",
    "gn:dem":48,
    "gn:feature_class":"P",
    "gn:feature_code":"PPL",
    "gn:name":"Okpoduma",
    "gn:population":0,
    "gn:timezone":"Africa/Lagos",
    "iso:country":"NG",
    "wof:name":"Okpoduma",
    "wof:placetype":"locality"
},
  "geometry": {"coordinates":[8.37996,6.3573],"type":"Point"}
}