{
  "type": "Feature",
  "properties": {
    "gn:admin1_code":"26.0",
    "gn:admin2_code":"7022",
    "gn:asciiname":"Venge",
    "gn:country_code":"NG",
    "gn:dem":202,
    "gn:feature_class":"P",
    "gn:feature_code":"PPL",
    "gn:name":"Venge",
    "gn:population":0,
    "gn:timezone":"Africa/Lagos",
    "iso:country":"NG",
    "wof:name":"Venge",
    "wof:placetype":"locality"
},
  "geometry": {"coordinates":[9.05895,7.08759],"type":"Point"}
}