{
  "type": "Feature",
  "properties": {
    "gn:admin1_code":"35.0",
    "gn:admin2_code":"2012",
    "gn:asciiname":"Wuro Bayare",
    "gn:country_code":"NG",
    "gn:dem":409,
    "gn:feature_class":"P",
    "gn:feature_code":"PPL",
    "gn:name":"Wuro Bayare",
    "gn:population":0,
    "gn:timezone":"Africa/Lagos",
    "iso:country":"NG",
    "wof:name":"Wuro Bayare",
    "wof:placetype":"locality"
},
  "geometry": {"coordinates":[12.12461,8.87924],"type":"Point"}
}