{
  "type": "Feature",
  "properties": {
    "gn:admin1_code":"36.0",
    "gn:admin2_code":"10011.0",
    "gn:asciiname":"Adaiwai",
    "gn:country_code":"NG",
    "gn:dem":9,
    "gn:feature_class":"P",
    "gn:feature_code":"PPL",
    "gn:name":"Adaiwai",
    "gn:population":0,
    "gn:timezone":"Africa/Lagos",
    "iso:country":"NG",
    "wof:name":"Adaiwai",
    "wof:placetype":"locality"
},
  "geometry": {"coordinates":[6.47613,5.40088],"type":"Point"}
}