{
  "type": "Feature",
  "properties": {
    "gn:admin1_code":"29.0",
    "gn:admin2_code":"20040.0",
    "gn:admin3_code":"KN3002",
    "gn:asciiname":"Gidan Gabbas",
    "gn:country_code":"NG",
    "gn:dem":441,
    "gn:feature_class":"P",
    "gn:feature_code":"PPL",
    "gn:name":"Gidan Gabbas",
    "gn:population":0,
    "gn:timezone":"Africa/Lagos",
    "iso:country":"NG",
    "wof:name":"Gidan Gabbas",
    "wof:placetype":"locality"
},
  "geometry": {"coordinates":[8.63783,12.16649],"type":"Point"}
}