{
  "type": "Feature",
  "properties": {
    "gn:admin1_code":"55.0",
    "gn:admin2_code":"16004.0",
    "gn:asciiname":"Damba",
    "gn:country_code":"NG",
    "gn:dem":480,
    "gn:feature_class":"P",
    "gn:feature_code":"PPL",
    "gn:name":"Damba",
    "gn:population":0,
    "gn:timezone":"Africa/Lagos",
    "iso:country":"NG",
    "name:eng_x_preferred":[
        "Damba"
    ],
    "wof:name":"Damba",
    "wof:placetype":"locality"
},
  "geometry": {"coordinates":[10.71472,10.65164],"type":"Point"}
}