{
  "type": "Feature",
  "properties": {
    "gn:admin1_code":"43.0",
    "gn:admin2_code":"35008.0",
    "gn:asciiname":"Gidan Usuman",
    "gn:country_code":"NG",
    "gn:dem":130,
    "gn:feature_class":"P",
    "gn:feature_code":"PPL",
    "gn:name":"Gidan Usuman",
    "gn:population":0,
    "gn:timezone":"Africa/Lagos",
    "iso:country":"NG",
    "name:eng_x_preferred":[
        "Gidan Usuman"
    ],
    "name:eng_x_variant":[
        "Gidan Usmanu",
        "Usmanu"
    ],
    "wof:name":"Gidan Usuman",
    "wof:placetype":"locality"
},
  "geometry": {"coordinates":[11.10198,9.21504],"type":"Point"}
}