{
  "type": "Feature",
  "properties": {
    "gn:admin1_code":"55.0",
    "gn:admin2_code":"16005.0",
    "gn:asciiname":"Sisi Bako",
    "gn:country_code":"NG",
    "gn:dem":308,
    "gn:feature_class":"P",
    "gn:feature_code":"PPL",
    "gn:name":"Sisi Bako",
    "gn:population":0,
    "gn:timezone":"Africa/Lagos",
    "iso:country":"NG",
    "wof:name":"Sisi Bako",
    "wof:placetype":"locality"
},
  "geometry": {"coordinates":[11.39616,10.72385],"type":"Point"}
}