{
  "type": "Feature",
  "properties": {
    "gn:admin1_code":"26.0",
    "gn:admin2_code":"7013.0",
    "gn:asciiname":"Agana",
    "gn:country_code":"NG",
    "gn:dem":91,
    "gn:feature_class":"P",
    "gn:feature_code":"PPL",
    "gn:name":"Agana",
    "gn:population":0,
    "gn:timezone":"Africa/Lagos",
    "iso:country":"NG",
    "name:ben_x_preferred":[
        "\u0986\u0997\u09be\u09a8\u09be"
    ],
    "wof:name":"Agana",
    "wof:placetype":"locality"
},
  "geometry": {"coordinates":[8.535,7.86906],"type":"Point"}
}