{
  "type": "Feature",
  "properties": {
    "gn:admin1_code":"43.0",
    "gn:admin2_code":"35005.0",
    "gn:asciiname":"Sendirdi",
    "gn:country_code":"NG",
    "gn:dem":113,
    "gn:feature_class":"P",
    "gn:feature_code":"PPL",
    "gn:name":"Sendirdi",
    "gn:population":0,
    "gn:timezone":"Africa/Lagos",
    "iso:country":"NG",
    "name:und_x_variant":[
        "Sendedi"
    ],
    "wof:name":"Sendirdi",
    "wof:placetype":"locality"
},
  "geometry": {"coordinates":[10.36166,8.58743],"type":"Point"}
}