{
  "type": "Feature",
  "properties": {
    "gn:admin1_code":"16.0",
    "gn:admin2_code":"28014.0",
    "gn:asciiname":"Iropo Elefa",
    "gn:country_code":"NG",
    "gn:dem":68,
    "gn:feature_class":"P",
    "gn:feature_code":"PPL",
    "gn:name":"Iropo Elefa",
    "gn:population":0,
    "gn:timezone":"Africa/Lagos",
    "iso:country":"NG",
    "wof:name":"Iropo Elefa",
    "wof:placetype":"locality"
},
  "geometry": {"coordinates":[2.78333,6.83333],"type":"Point"}
}