{
  "type": "Feature",
  "properties": {
    "gn:admin1_code":"23.0",
    "gn:asciiname":"Bayan Dutse",
    "gn:country_code":"NG",
    "gn:dem":578,
    "gn:feature_class":"P",
    "gn:feature_code":"PPL",
    "gn:name":"Bayan Dutse",
    "gn:population":0,
    "gn:timezone":"Africa/Lagos",
    "iso:country":"NG",
    "wof:name":"Bayan Dutse",
    "wof:placetype":"locality"
},
  "geometry": {"coordinates":[8.37067,11.28306],"type":"Point"}
}