{
  "type": "Feature",
  "properties": {
    "gn:admin1_code":"24.0",
    "gn:admin2_code":"431.0",
    "gn:admin3_code":"43103",
    "gn:asciiname":"Ungwan Barau",
    "gn:country_code":"NG",
    "gn:dem":680,
    "gn:feature_class":"P",
    "gn:feature_code":"PPL",
    "gn:name":"Ungwan Barau",
    "gn:population":0,
    "gn:timezone":"Africa/Lagos",
    "iso:country":"NG",
    "wof:name":"Ungwan Barau",
    "wof:placetype":"locality"
},
  "geometry": {"coordinates":[7.11688,11.41376],"type":"Point"}
}