{
  "type": "Feature",
  "properties": {
    "gn:admin1_code":"43.0",
    "gn:admin2_code":"35004.0",
    "gn:asciiname":"Panwai",
    "gn:country_code":"NG",
    "gn:dem":243,
    "gn:feature_class":"P",
    "gn:feature_code":"PPL",
    "gn:name":"Panwai",
    "gn:population":0,
    "gn:timezone":"Africa/Lagos",
    "iso:country":"NG",
    "wof:name":"Panwai",
    "wof:placetype":"locality"
},
  "geometry": {"coordinates":[11.11667,7.81667],"type":"Point"}
}