{
  "type": "Feature",
  "properties": {
    "gn:admin1_code":"40.0",
    "gn:admin2_code":"518.0",
    "gn:admin3_code":"51806",
    "gn:asciiname":"Tungan Jero",
    "gn:country_code":"NG",
    "gn:dem":208,
    "gn:feature_class":"P",
    "gn:feature_code":"PPL",
    "gn:name":"Tungan Jero",
    "gn:population":0,
    "gn:timezone":"Africa/Lagos",
    "iso:country":"NG",
    "wof:name":"Tungan Jero",
    "wof:placetype":"locality"
},
  "geometry": {"coordinates":[4.17264,12.00697],"type":"Point"}
}