{
  "type": "Feature",
  "properties": {
    "gn:admin1_code":"49.0",
    "gn:admin2_code":"32016.0",
    "gn:asciiname":"Ungwan Rina",
    "gn:country_code":"NG",
    "gn:dem":160,
    "gn:feature_class":"P",
    "gn:feature_code":"PPL",
    "gn:name":"Ungwan Rina",
    "gn:population":0,
    "gn:timezone":"Africa/Lagos",
    "iso:country":"NG",
    "name:und_x_variant":[
        "Ungwanrina"
    ],
    "wof:name":"Ungwan Rina",
    "wof:placetype":"locality"
},
  "geometry": {"coordinates":[9.4735,8.6834],"type":"Point"}
}