{
  "type": "Feature",
  "properties": {
    "gn:admin1_code":"36.0",
    "gn:admin2_code":"10014.0",
    "gn:asciiname":"Aniwalo",
    "gn:country_code":"NG",
    "gn:dem":81,
    "gn:feature_class":"P",
    "gn:feature_code":"PPL",
    "gn:name":"Aniwalo",
    "gn:population":0,
    "gn:timezone":"Africa/Lagos",
    "iso:country":"NG",
    "name:eng_x_preferred":[
        "Aniwalo"
    ],
    "wof:name":"Aniwalo",
    "wof:placetype":"locality"
},
  "geometry": {"coordinates":[6.61842,6.37972],"type":"Point"}
}