{
  "type": "Feature",
  "properties": {
    "gn:admin1_code":"35.0",
    "gn:admin2_code":"2018.0",
    "gn:asciiname":"Hutu",
    "gn:country_code":"NG",
    "gn:dem":649,
    "gn:feature_class":"P",
    "gn:feature_code":"PPL",
    "gn:name":"Hutu",
    "gn:population":0,
    "gn:timezone":"Africa/Lagos",
    "iso:country":"NG",
    "name:afr_x_preferred":[
        "Hutu"
    ],
    "name:ara_x_preferred":[
        "\u0647\u0648\u062a\u0648"
    ],
    "name:ast_x_preferred":[
        "Hutu"
    ],
    "name:azb_x_preferred":[
        "\u0647\u0648\u062a\u0648\u200c\u0644\u0627\u0631"
    ],
    "name:aze_x_preferred":[
        "Hutular"
    ],
    "name:bel_x_preferred":[
        "\u0425\u0443\u0442\u0443"
    ],
    "name:ben_x_preferred":[
        "\u09b9\u09c1\u099f\u09c1"
    ],
    "name:bul_x_preferred":[
        "\u0425\u0443\u0442\u0443"
    ],
    "name:cat_x_preferred":[
        "Hutu"
    ],
    "name:ces_x_preferred":[
        "Hutuov\u00e9"
    ],
    "name:cym_x_preferred":[
        "Hutu"
    ],
    "name:dan_x_preferred":[
        "Hutuer"
    ],
    "name:deu_x_preferred":[
        "Hutu"
    ],
    "name:ell_x_preferred":[
        "\u03a7\u03bf\u03cd\u03c4\u03bf\u03c5"
    ],
    "name:epo_x_preferred":[
        "Hutuoj"
    ],
    "name:est_x_preferred":[
        "Hutud"
    ],
    "name:eus_x_preferred":[
        "Hutu"
    ],
    "name:fas_x_preferred":[
        "\u0647\u0648\u062a\u0648"
    ],
    "name:fin_x_preferred":[
        "Hutut"
    ],
    "name:fra_x_preferred":[
        "Hutu"
    ],
    "name:glg_x_preferred":[
        "Pobo hutu"
    ],
    "name:heb_x_preferred":[
        "\u05d4\u05d5\u05d8\u05d5"
    ],
    "name:hrv_x_preferred":[
        "Hutu"
    ],
    "name:ind_x_preferred":[
        "Hutu"
    ],
    "name:ita_x_preferred":[
        "Hutu"
    ],
    "name:kat_x_preferred":[
        "\u10f0\u10e3\u10e2\u10e3"
    ],
    "name:kor_x_preferred":[
        "\ud6c4\ud22c\uc871"
    ],
    "name:lat_x_preferred":[
        "Hutuenses"
    ],
    "name:lit_x_preferred":[
        "Hutai"
    ],
    "name:msa_x_preferred":[
        "Kaum Hutu"
    ],
    "name:nld_x_preferred":[
        "Hutu"
    ],
    "name:pan_x_preferred":[
        "\u0a39\u0a42\u0a24\u0a42"
    ],
    "name:pnb_x_preferred":[
        "\u06c1\u0648\u062a\u0648 \u0644\u0648\u06a9"
    ],
    "name:pol_x_preferred":[
        "Hutu"
    ],
    "name:por_x_preferred":[
        "H\u00fatus"
    ],
    "name:run_x_preferred":[
        "Abahutu"
    ],
    "name:rus_x_preferred":[
        "\u0425\u0443\u0442\u0443"
    ],
    "name:sco_x_preferred":[
        "Hutu"
    ],
    "name:som_x_preferred":[
        "Huutuu"
    ],
    "name:spa_x_preferred":[
        "Hutu"
    ],
    "name:srp_x_preferred":[
        "\u0425\u0443\u0442\u0443"
    ],
    "name:swa_x_preferred":[
        "Wahutu"
    ],
    "name:swe_x_preferred":[
        "Hutuer"
    ],
    "name:tam_x_preferred":[
        "\u0bb9\u0bc2\u0b9f\u0bcd\u0b9f\u0bc1 \u0b87\u0ba9\u0b95\u0bcd\u0b95\u0bc1\u0bb4\u0bc1"
    ],
    "name:tur_x_preferred":[
        "Hutular"
    ],
    "name:ukr_x_preferred":[
        "\u0425\u0443\u0442\u0443"
    ],
    "name:vie_x_preferred":[
        "Ng\u01b0\u1eddi Hutu"
    ],
    "name:yor_x_preferred":[
        "Hutu"
    ],
    "name:zho_x_preferred":[
        "\u80e1\u56fe\u65cf"
    ],
    "wof:name":"Hutu",
    "wof:placetype":"locality"
},
  "geometry": {"coordinates":[12.29165,10.01593],"type":"Point"}
}