{
  "type": "Feature",
  "properties": {
    "gn:admin1_code":"26.0",
    "gn:admin2_code":"7009",
    "gn:asciiname":"Ngor",
    "gn:country_code":"NG",
    "gn:dem":155,
    "gn:feature_class":"P",
    "gn:feature_code":"PPL",
    "gn:name":"Ngor",
    "gn:population":0,
    "gn:timezone":"Africa/Lagos",
    "iso:country":"NG",
    "name:ben_x_preferred":[
        "\u0999\u09cd\u0997\u09cb\u09b0-\u098f-\u09ac\u09be\u09ae-\u099b\u09cb\u09b8-\u09b2\u09cd\u09a6\u09be\u09a8 \u09ac\u09cc\u09a6\u09cd\u09a7\u09ac\u09bf\u09b9\u09be\u09b0"
    ],
    "name:hun_x_preferred":[
        "Ngor kolostor"
    ],
    "name:nld_x_preferred":[
        "Ngor"
    ],
    "name:zho_x_preferred":[
        "\u4fc4\u5c14\u5bfa"
    ],
    "wof:name":"Ngor",
    "wof:placetype":"locality"
},
  "geometry": {"coordinates":[9.4905,7.35838],"type":"Point"}
}