{
  "type": "Feature",
  "properties": {
    "gn:admin1_code":"32.0",
    "gn:admin2_code":"31012.0",
    "gn:asciiname":"Akinwunmi",
    "gn:country_code":"NG",
    "gn:dem":207,
    "gn:feature_class":"P",
    "gn:feature_code":"PPL",
    "gn:name":"Akinwunmi",
    "gn:population":0,
    "gn:timezone":"Africa/Lagos",
    "iso:country":"NG",
    "wof:name":"Akinwunmi",
    "wof:placetype":"locality"
},
  "geometry": {"coordinates":[3.55,7.75],"type":"Point"}
}