{
  "type": "Feature",
  "properties": {
    "gn:admin1_code":"23.0",
    "gn:admin2_code":"19003.0",
    "gn:admin3_code":"KD0306",
    "gn:asciiname":"Ungwan Chitumu",
    "gn:country_code":"NG",
    "gn:dem":662,
    "gn:feature_class":"P",
    "gn:feature_code":"PPL",
    "gn:name":"Ungwan Chitumu",
    "gn:population":0,
    "gn:timezone":"Africa/Lagos",
    "iso:country":"NG",
    "name:und_x_variant":[
        "Angwan Chitumu",
        "Ungwan Chitumu"
    ],
    "wof:name":"Ungwan Chitumu",
    "wof:placetype":"locality"
},
  "geometry": {"coordinates":[7.45154,11.20463],"type":"Point"}
}