{
  "type": "Feature",
  "properties": {
    "gn:admin1_code":"27.0",
    "gn:admin2_code":"107.0",
    "gn:admin3_code":"10701",
    "gn:asciiname":"Aloura",
    "gn:country_code":"NG",
    "gn:dem":455,
    "gn:feature_class":"P",
    "gn:feature_code":"PPL",
    "gn:name":"Aloura",
    "gn:population":0,
    "gn:timezone":"Africa/Lagos",
    "iso:country":"NG",
    "wof:name":"Aloura",
    "wof:placetype":"locality"
},
  "geometry": {"coordinates":[12.57279,10.97291],"type":"Point"}
}