{
  "type": "Feature",
  "properties": {
    "iso:country":"NG",
    "oa:elevation_ft":"1126",
    "oa:type":"medium_airport",
    "woe:hierarchy":{
        "country_id":23424908,
        "county_id":56057896,
        "planet_id":1,
        "state_id":2346358
    },
    "wof:name":"Ilorin Airport",
    "wof:placetype":"campus"
},
  "geometry": {"coordinates":[4.4944444444444,8.4405555555556],"type":"Point"}
}