{
  "type": "Feature",
  "properties": {
    "iso:country":"NG",
    "name:ceb_x_preferred":[
        "Ilorin"
    ],
    "name:eng_x_variant":[
        "ILR",
        "DNIL"
    ],
    "name:fas_x_preferred":[
        "\u0641\u0631\u0648\u062f\u06af\u0627\u0647 \u0628\u06cc\u0646\u200c\u0627\u0644\u0645\u0644\u0644\u06cc \u0627\u06cc\u0644\u0648\u0631\u06cc\u0646"
    ],
    "name:fra_x_preferred":[
        "ILORIN"
    ],
    "name:hau_x_preferred":[
        "Filin jirgin saman Ilorin"
    ],
    "name:ind_x_preferred":[
        "Bandar Udara Internasional Ilorin"
    ],
    "name:jpn_x_preferred":[
        "\u30a4\u30ed\u30ea\u30f3\u56fd\u969b\u7a7a\u6e2f"
    ],
    "name:pol_x_preferred":[
        "Port lotniczy Ilorin"
    ],
    "name:ron_x_preferred":[
        "Aeroportul Ilorin"
    ],
    "name:tgk_x_preferred":[
        "\u0424\u0443\u0440\u0443\u0434\u0433\u043e\u04b3\u0438 \u0431\u0438\u043d\u200c\u0430\u043b\u043c\u0438\u043b\u0430\u043b\u04e3 \u043e\u0438\u043b\u0443\u0440\u0438\u043d"
    ],
    "name:zho_x_preferred":[
        "\u4f0a\u6d1b\u6797"
    ],
    "oa:elevation_ft":"1126",
    "oa:type":"medium_airport",
    "woe:hierarchy":{
        "country_id":23424908,
        "county_id":56057896,
        "planet_id":1,
        "state_id":2346358
    },
    "wof:name":"Ilorin Airport",
    "wof:placetype":"campus"
},
  "geometry": {"coordinates":[4.494444,8.440556],"type":"Point"}
}