{
  "type": "Feature",
  "properties": {
    "gn:admin1_code":"16.0",
    "gn:admin2_code":"28015.0",
    "gn:asciiname":"Isan",
    "gn:cc2":"NG",
    "gn:country_code":"NG",
    "gn:dem":103,
    "gn:feature_class":"P",
    "gn:feature_code":"PPL",
    "gn:name":"Isan",
    "gn:population":0,
    "gn:timezone":"Africa/Lagos",
    "iso:country":"NG",
    "name:und_x_variant":[
        "Ishan",
        "Isan"
    ],
    "wof:name":"Isan",
    "wof:placetype":"locality"
},
  "geometry": {"coordinates":[3.55,7.06667],"type":"Point"}
}