{
  "type": "Feature",
  "properties": {
    "gn:admin1_code":"22.0",
    "gn:asciiname":"Okpetumo",
    "gn:country_code":"NG",
    "gn:dem":28,
    "gn:feature_class":"P",
    "gn:feature_code":"PPL",
    "gn:name":"Okpetumo",
    "gn:population":0,
    "gn:timezone":"Africa/Lagos",
    "iso:country":"NG",
    "name:und_x_variant":[
        "Okpodumu",
        "Okpetumo",
        "Okpoduma"
    ],
    "wof:name":"Okpetumo",
    "wof:placetype":"locality"
},
  "geometry": {"coordinates":[8.31956,6.15444],"type":"Point"}
}