{
  "type": "Feature",
  "properties": {
    "gn:admin1_code":"50.0",
    "gn:admin2_code":"33013.0",
    "gn:asciiname":"Isiokpo",
    "gn:country_code":"NG",
    "gn:dem":18,
    "gn:feature_class":"P",
    "gn:feature_code":"PPL",
    "gn:name":"Isiokpo",
    "gn:population":0,
    "gn:timezone":"Africa/Lagos",
    "iso:country":"NG",
    "wof:name":"Isiokpo",
    "wof:placetype":"locality"
},
  "geometry": {"coordinates":[6.88616,4.9774],"type":"Point"}
}