{
  "type": "Feature",
  "properties": {
    "gn:admin1_code":"16.0",
    "gn:admin2_code":"28011.0",
    "gn:asciiname":"Iloti",
    "gn:country_code":"NG",
    "gn:dem":15,
    "gn:feature_class":"P",
    "gn:feature_code":"PPL",
    "gn:name":"Iloti",
    "gn:population":0,
    "gn:timezone":"Africa/Lagos",
    "iso:country":"NG",
    "wof:name":"Iloti",
    "wof:placetype":"locality"
},
  "geometry": {"coordinates":[4.00339,6.72362],"type":"Point"}
}