{
  "type": "Feature",
  "properties": {
    "gn:admin1_code":"40.0",
    "gn:admin2_code":"504.0",
    "gn:admin3_code":"50406",
    "gn:asciiname":"Dangkel",
    "gn:country_code":"NG",
    "gn:dem":232,
    "gn:feature_class":"P",
    "gn:feature_code":"PPL",
    "gn:name":"Dangkel",
    "gn:population":0,
    "gn:timezone":"Africa/Lagos",
    "iso:country":"NG",
    "name:und_x_variant":[
        "Dankal",
        "Dangkel"
    ],
    "wof:name":"Dangkel",
    "wof:placetype":"locality"
},
  "geometry": {"coordinates":[4.66821,12.87378],"type":"Point"}
}