{
  "type": "Feature",
  "properties": {
    "gn:admin1_code":"51.0",
    "gn:admin2_code":"606.0",
    "gn:admin3_code":"60602",
    "gn:asciiname":"Dangari Adua",
    "gn:country_code":"NG",
    "gn:dem":230,
    "gn:feature_class":"P",
    "gn:feature_code":"PPL",
    "gn:name":"Dangari Adua",
    "gn:population":0,
    "gn:timezone":"Africa/Lagos",
    "iso:country":"NG",
    "wof:name":"Dangari Adua",
    "wof:placetype":"locality"
},
  "geometry": {"coordinates":[4.2007,13.45584],"type":"Point"}
}