{
  "type": "Feature",
  "properties": {
    "gn:admin1_code":"26.0",
    "gn:admin2_code":"7013",
    "gn:asciiname":"Tsepeke",
    "gn:country_code":"NG",
    "gn:dem":104,
    "gn:feature_class":"P",
    "gn:feature_code":"PPL",
    "gn:name":"Tsepeke",
    "gn:population":0,
    "gn:timezone":"Africa/Lagos",
    "iso:country":"NG",
    "wof:name":"Tsepeke",
    "wof:placetype":"locality"
},
  "geometry": {"coordinates":[8.43695,7.68293],"type":"Point"}
}