{
  "type": "Feature",
  "properties": {
    "gn:admin1_code":"35.0",
    "gn:admin2_code":"2011.0",
    "gn:asciiname":"Mayo Vamde",
    "gn:country_code":"NG",
    "gn:dem":431,
    "gn:feature_class":"P",
    "gn:feature_code":"PPL",
    "gn:name":"Mayo Vamde",
    "gn:population":0,
    "gn:timezone":"Africa/Lagos",
    "iso:country":"NG",
    "wof:name":"Mayo Vamde",
    "wof:placetype":"locality"
},
  "geometry": {"coordinates":[13.11667,9.71667],"type":"Point"}
}