{
  "type": "Feature",
  "properties": {
    "gn:admin1_code":"5.0",
    "gn:admin2_code":"25003.0",
    "gn:asciiname":"Fatade",
    "gn:country_code":"NG",
    "gn:dem":38,
    "gn:feature_class":"P",
    "gn:feature_code":"PPL",
    "gn:name":"Fatade",
    "gn:population":0,
    "gn:timezone":"Africa/Lagos",
    "iso:country":"NG",
    "wof:name":"Fatade",
    "wof:placetype":"locality"
},
  "geometry": {"coordinates":[3.26778,6.59806],"type":"Point"}
}