{
  "type": "Feature",
  "properties": {
    "gn:admin1_code":"35.0",
    "gn:admin2_code":"2008.0",
    "gn:asciiname":"Kona Jabe",
    "gn:country_code":"NG",
    "gn:dem":377,
    "gn:feature_class":"P",
    "gn:feature_code":"PPL",
    "gn:name":"Kona Jabe",
    "gn:population":0,
    "gn:timezone":"Africa/Lagos",
    "iso:country":"NG",
    "wof:name":"Kona Jabe",
    "wof:placetype":"locality"
},
  "geometry": {"coordinates":[12.15611,8.84115],"type":"Point"}
}