{
  "type": "Feature",
  "properties": {
    "gn:admin1_code":"46.0",
    "gn:admin2_code":"5015.0",
    "gn:admin3_code":"BA1518",
    "gn:asciiname":"Maidubi",
    "gn:country_code":"NG",
    "gn:dem":657,
    "gn:feature_class":"P",
    "gn:feature_code":"PPL",
    "gn:name":"Maidubi",
    "gn:population":0,
    "gn:timezone":"Africa/Lagos",
    "iso:country":"NG",
    "wof:name":"Maidubi",
    "wof:placetype":"locality"
},
  "geometry": {"coordinates":[9.13441,10.85748],"type":"Point"}
}