{
  "type": "Feature",
  "properties": {
    "gn:admin1_code":"31.0",
    "gn:admin2_code":"27002.0",
    "gn:asciiname":"Ichan",
    "gn:country_code":"NG",
    "gn:dem":139,
    "gn:feature_class":"P",
    "gn:feature_code":"PPL",
    "gn:name":"Ichan",
    "gn:population":0,
    "gn:timezone":"Africa/Lagos",
    "iso:country":"NG",
    "wof:name":"Ichan",
    "wof:placetype":"locality"
},
  "geometry": {"coordinates":[4.70002,10.79609],"type":"Point"}
}