{
  "type": "Feature",
  "properties": {
    "gn:admin1_code":"35.0",
    "gn:admin2_code":"2017.0",
    "gn:asciiname":"Tindirke",
    "gn:country_code":"NG",
    "gn:dem":528,
    "gn:feature_class":"P",
    "gn:feature_code":"PPL",
    "gn:name":"Tindirke",
    "gn:population":0,
    "gn:timezone":"Africa/Lagos",
    "iso:country":"NG",
    "wof:name":"Tindirke",
    "wof:placetype":"locality"
},
  "geometry": {"coordinates":[12.29479,10.22622],"type":"Point"}
}