{
  "type": "Feature",
  "properties": {
    "gn:admin1_code":"51.0",
    "gn:admin2_code":"619.0",
    "gn:admin3_code":"61903",
    "gn:asciiname":"Kuachaw",
    "gn:country_code":"NG",
    "gn:dem":276,
    "gn:feature_class":"P",
    "gn:feature_code":"PPL",
    "gn:name":"Kuachaw",
    "gn:population":0,
    "gn:timezone":"Africa/Lagos",
    "iso:country":"NG",
    "wof:name":"Kuachaw",
    "wof:placetype":"locality"
},
  "geometry": {"coordinates":[5.01051,13.22451],"type":"Point"}
}