{
  "type": "Feature",
  "properties": {
    "gn:admin1_code":"32.0",
    "gn:admin2_code":"31033.0",
    "gn:asciiname":"Baba Egbe",
    "gn:country_code":"NG",
    "gn:dem":379,
    "gn:feature_class":"P",
    "gn:feature_code":"PPL",
    "gn:name":"Baba Egbe",
    "gn:population":0,
    "gn:timezone":"Africa/Lagos",
    "iso:country":"NG",
    "wof:name":"Baba Egbe",
    "wof:placetype":"locality"
},
  "geometry": {"coordinates":[4.41667,8.03333],"type":"Point"}
}