{
  "type": "Feature",
  "properties": {
    "gn:admin1_code":"42.0",
    "gn:admin2_code":"30013.0",
    "gn:asciiname":"Idita",
    "gn:cc2":"NG",
    "gn:country_code":"NG",
    "gn:dem":193,
    "gn:feature_class":"P",
    "gn:feature_code":"PPL",
    "gn:name":"Idita",
    "gn:population":0,
    "gn:timezone":"Africa/Lagos",
    "iso:country":"NG",
    "name:und_x_variant":[
        "Idifa",
        "Idita"
    ],
    "wof:name":"Idita",
    "wof:placetype":"locality"
},
  "geometry": {"coordinates":[4.43333,7.31667],"type":"Point"}
}