{
  "type": "Feature",
  "properties": {
    "gn:admin1_code":"24.0",
    "gn:admin2_code":"404.0",
    "gn:admin3_code":"40412",
    "gn:asciiname":"Korou",
    "gn:country_code":"NG",
    "gn:dem":392,
    "gn:feature_class":"P",
    "gn:feature_code":"PPL",
    "gn:name":"Korou",
    "gn:population":0,
    "gn:timezone":"Africa/Lagos",
    "iso:country":"NG",
    "wof:name":"Korou",
    "wof:placetype":"locality"
},
  "geometry": {"coordinates":[8.87127,12.68779],"type":"Point"}
}