{
  "type": "Feature",
  "properties": {
    "gn:admin1_code":"31.0",
    "gn:admin2_code":"27014.0",
    "gn:asciiname":"Kusaka",
    "gn:country_code":"NG",
    "gn:dem":179,
    "gn:feature_class":"P",
    "gn:feature_code":"PPL",
    "gn:name":"Kusaka",
    "gn:population":0,
    "gn:timezone":"Africa/Lagos",
    "iso:country":"NG",
    "name:fra_x_preferred":[
        "Kusaka"
    ],
    "wof:name":"Kusaka",
    "wof:placetype":"locality"
},
  "geometry": {"coordinates":[4.72771,10.21697],"type":"Point"}
}