{
  "type": "Feature",
  "properties": {
    "gn:admin1_code":"35.0",
    "gn:asciiname":"Wuro Kuturu",
    "gn:country_code":"NG",
    "gn:dem":160,
    "gn:feature_class":"P",
    "gn:feature_code":"PPL",
    "gn:name":"Wuro Kuturu",
    "gn:population":0,
    "gn:timezone":"Africa/Lagos",
    "iso:country":"NG",
    "name:eng_x_preferred":[
        "Wuro Kuturu"
    ],
    "wof:name":"Wuro Kuturu",
    "wof:placetype":"neighbourhood"
},
  "geometry": {"coordinates":[12.44488,9.28571],"type":"Point"}
}