{
  "type": "Feature",
  "properties": {
    "gn:admin1_code":"43.0",
    "gn:admin2_code":"35011.0",
    "gn:asciiname":"Mayo Ndaga",
    "gn:cc2":"NG",
    "gn:country_code":"NG",
    "gn:dem":1557,
    "gn:feature_class":"P",
    "gn:feature_code":"PPL",
    "gn:name":"Mayo Ndaga",
    "gn:population":0,
    "gn:timezone":"Africa/Lagos",
    "iso:country":"NG",
    "name:und_x_variant":[
        "Mayo Daga",
        "Mayo Ndaga"
    ],
    "wof:name":"Mayo Ndaga",
    "wof:placetype":"locality"
},
  "geometry": {"coordinates":[11.43333,6.91667],"type":"Point"}
}