{
  "type": "Feature",
  "properties": {
    "gn:admin1_code":"24.0",
    "gn:admin2_code":"430.0",
    "gn:admin3_code":"43005",
    "gn:asciiname":"Makurda",
    "gn:country_code":"NG",
    "gn:dem":467,
    "gn:feature_class":"P",
    "gn:feature_code":"PPL",
    "gn:name":"Makurda",
    "gn:population":0,
    "gn:timezone":"Africa/Lagos",
    "iso:country":"NG",
    "wof:name":"Makurda",
    "wof:placetype":"locality"
},
  "geometry": {"coordinates":[7.73818,13.01478],"type":"Point"}
}