{
  "type": "Feature",
  "properties": {
    "gn:admin1_code":"5.0",
    "gn:asciiname":"Origele",
    "gn:country_code":"NG",
    "gn:dem":0,
    "gn:feature_class":"P",
    "gn:feature_code":"PPL",
    "gn:name":"Origele",
    "gn:population":0,
    "gn:timezone":"Africa/Lagos",
    "iso:country":"NG",
    "name:und_x_variant":[
        "Ijagba Creek",
        "Origele"
    ],
    "wof:name":"Origele",
    "wof:placetype":"locality"
},
  "geometry": {"coordinates":[4.11938,6.56596],"type":"Point"}
}