{
  "type": "Feature",
  "properties": {
    "gn:admin1_code":"42.0",
    "gn:admin2_code":"30021.0",
    "gn:asciiname":"Olokoko",
    "gn:country_code":"NG",
    "gn:dem":212,
    "gn:feature_class":"P",
    "gn:feature_code":"PPL",
    "gn:name":"Olokoko",
    "gn:population":0,
    "gn:timezone":"Africa/Lagos",
    "iso:country":"NG",
    "wof:name":"Olokoko",
    "wof:placetype":"locality"
},
  "geometry": {"coordinates":[4.31667,7.35],"type":"Point"}
}