{
  "type": "Feature",
  "properties": {
    "gn:admin1_code":"57.0",
    "gn:admin2_code":"805.0",
    "gn:admin3_code":"80506",
    "gn:asciiname":"Sarkin Rafi",
    "gn:country_code":"NG",
    "gn:dem":444,
    "gn:feature_class":"P",
    "gn:feature_code":"PPL",
    "gn:name":"Sarkin Rafi",
    "gn:population":0,
    "gn:timezone":"Africa/Lagos",
    "iso:country":"NG",
    "wof:name":"Sarkin Rafi",
    "wof:placetype":"locality"
},
  "geometry": {"coordinates":[6.50078,12.19872],"type":"Point"}
}