{
  "type": "Feature",
  "properties": {
    "gn:admin1_code":"27.0",
    "gn:admin2_code":"107.0",
    "gn:admin3_code":"10705",
    "gn:asciiname":"Goniri",
    "gn:country_code":"NG",
    "gn:dem":366,
    "gn:feature_class":"P",
    "gn:feature_code":"PPL",
    "gn:name":"Goniri",
    "gn:population":0,
    "gn:timezone":"Africa/Lagos",
    "iso:country":"NG",
    "wof:name":"Goniri",
    "wof:placetype":"locality"
},
  "geometry": {"coordinates":[13.09574,11.29955],"type":"Point"}
}