{
  "type": "Feature",
  "properties": {
    "gn:admin1_code":"40.0",
    "gn:admin2_code":"514.0",
    "gn:admin3_code":"51411",
    "gn:asciiname":"Sarandosa",
    "gn:country_code":"NG",
    "gn:dem":238,
    "gn:feature_class":"P",
    "gn:feature_code":"PPL",
    "gn:name":"Sarandosa",
    "gn:population":0,
    "gn:timezone":"Africa/Lagos",
    "iso:country":"NG",
    "name:und_x_variant":[
        "Sarandose",
        "Sarandosa"
    ],
    "wof:name":"Sarandosa",
    "wof:placetype":"locality"
},
  "geometry": {"coordinates":[4.37215,12.0033],"type":"Point"}
}