{
  "type": "Feature",
  "properties": {
    "gn:admin1_code":"45.0",
    "gn:admin2_code":"1009.0",
    "gn:asciiname":"Aba Ala",
    "gn:country_code":"NG",
    "gn:dem":67,
    "gn:feature_class":"P",
    "gn:feature_code":"PPL",
    "gn:name":"Aba Ala",
    "gn:population":0,
    "gn:timezone":"Africa/Lagos",
    "iso:country":"NG",
    "wof:name":"Aba Ala",
    "wof:placetype":"locality"
},
  "geometry": {"coordinates":[7.48676,5.04405],"type":"Point"}
}