{
  "type": "Feature",
  "properties": {
    "gn:admin1_code":"37.0",
    "gn:admin2_code":"12009.0",
    "gn:asciiname":"Iviotha",
    "gn:country_code":"NG",
    "gn:dem":151,
    "gn:feature_class":"P",
    "gn:feature_code":"PPL",
    "gn:name":"Iviotha",
    "gn:population":0,
    "gn:timezone":"Africa/Lagos",
    "iso:country":"NG",
    "wof:name":"Iviotha",
    "wof:placetype":"locality"
},
  "geometry": {"coordinates":[6.3502,7.1267],"type":"Point"}
}