{
  "type": "Feature",
  "properties": {
    "gn:admin1_code":"55.0",
    "gn:admin2_code":"16004.0",
    "gn:asciiname":"Sayum",
    "gn:country_code":"NG",
    "gn:dem":473,
    "gn:feature_class":"P",
    "gn:feature_code":"PPL",
    "gn:name":"Sayum",
    "gn:population":0,
    "gn:timezone":"Africa/Lagos",
    "iso:country":"NG",
    "name:eng_x_preferred":[
        "Sayum"
    ],
    "wof:name":"Sayum",
    "wof:placetype":"locality"
},
  "geometry": {"coordinates":[10.70673,10.75867],"type":"Point"}
}