{
  "type": "Feature",
  "properties": {
    "gn:admin1_code":"48.0",
    "gn:admin2_code":"29013.0",
    "gn:asciiname":"Origbe",
    "gn:country_code":"NG",
    "gn:dem":34,
    "gn:feature_class":"P",
    "gn:feature_code":"PPL",
    "gn:name":"Origbe",
    "gn:population":0,
    "gn:timezone":"Africa/Lagos",
    "iso:country":"NG",
    "wof:name":"Origbe",
    "wof:placetype":"locality"
},
  "geometry": {"coordinates":[4.44524,6.61574],"type":"Point"}
}