{
  "type": "Feature",
  "properties": {
    "gn:admin1_code":"27.0",
    "gn:admin2_code":"107.0",
    "gn:admin3_code":"10705",
    "gn:asciiname":"Zarameri",
    "gn:country_code":"NG",
    "gn:dem":368,
    "gn:feature_class":"P",
    "gn:feature_code":"PPL",
    "gn:name":"Zarameri",
    "gn:population":0,
    "gn:timezone":"Africa/Lagos",
    "iso:country":"NG",
    "wof:name":"Zarameri",
    "wof:placetype":"locality"
},
  "geometry": {"coordinates":[13.06457,11.25274],"type":"Point"}
}