{
  "type": "Feature",
  "properties": {
    "gn:admin1_code":"35.0",
    "gn:admin2_code":"2020.0",
    "gn:asciiname":"Sebore",
    "gn:country_code":"NG",
    "gn:dem":202,
    "gn:feature_class":"P",
    "gn:feature_code":"PPL",
    "gn:name":"Sebore",
    "gn:population":0,
    "gn:timezone":"Africa/Lagos",
    "iso:country":"NG",
    "wof:name":"Sebore",
    "wof:placetype":"locality"
},
  "geometry": {"coordinates":[12.58333,9.11667],"type":"Point"}
}