{
  "type": "Feature",
  "properties": {
    "gn:admin1_code":"23.0",
    "gn:admin2_code":"19020",
    "gn:admin3_code":"KD2011",
    "gn:asciiname":"Ungwan Dogo",
    "gn:country_code":"NG",
    "gn:dem":501,
    "gn:feature_class":"P",
    "gn:feature_code":"PPL",
    "gn:name":"Ungwan Dogo",
    "gn:population":0,
    "gn:timezone":"Africa/Lagos",
    "iso:country":"NG",
    "name:und_x_variant":[
        "Sabon Buja"
    ],
    "wof:name":"Ungwan Dogo",
    "wof:placetype":"locality"
},
  "geometry": {"coordinates":[8.17595,9.10517],"type":"Point"}
}