{
  "type": "Feature",
  "properties": {
    "gn:admin1_code":"27.0",
    "gn:admin2_code":"107.0",
    "gn:admin3_code":"10710",
    "gn:asciiname":"Bulagarga II",
    "gn:country_code":"NG",
    "gn:dem":428,
    "gn:feature_class":"P",
    "gn:feature_code":"PPL",
    "gn:name":"Bulagarga II",
    "gn:population":0,
    "gn:timezone":"Africa/Lagos",
    "iso:country":"NG",
    "wof:name":"Bulagarga II",
    "wof:placetype":"locality"
},
  "geometry": {"coordinates":[12.97873,10.97495],"type":"Point"}
}