{
  "type": "Feature",
  "properties": {
    "gn:admin1_code":"32.0",
    "gn:admin2_code":"31002.0",
    "gn:asciiname":"Dalegan",
    "gn:country_code":"NG",
    "gn:dem":259,
    "gn:feature_class":"P",
    "gn:feature_code":"PPL",
    "gn:name":"Dalegan",
    "gn:population":0,
    "gn:timezone":"Africa/Lagos",
    "iso:country":"NG",
    "wof:name":"Dalegan",
    "wof:placetype":"locality"
},
  "geometry": {"coordinates":[3.97306,7.52528],"type":"Point"}
}