{
  "type": "Feature",
  "properties": {
    "gn:admin1_code":"37.0",
    "gn:admin2_code":"12018.0",
    "gn:asciiname":"Iguoghae",
    "gn:country_code":"NG",
    "gn:dem":117,
    "gn:feature_class":"P",
    "gn:feature_code":"PPL",
    "gn:name":"Iguoghae",
    "gn:population":0,
    "gn:timezone":"Africa/Lagos",
    "iso:country":"NG",
    "name:und_x_variant":[
        "Igvoghae",
        "Iguoghae"
    ],
    "wof:name":"Iguoghae",
    "wof:placetype":"locality"
},
  "geometry": {"coordinates":[5.88907,6.34627],"type":"Point"}
}