{
  "type": "Feature",
  "properties": {
    "gn:admin1_code":"37.0",
    "gn:admin2_code":"12009.0",
    "gn:asciiname":"Odame",
    "gn:country_code":"NG",
    "gn:dem":65,
    "gn:feature_class":"P",
    "gn:feature_code":"PPL",
    "gn:name":"Odame",
    "gn:population":0,
    "gn:timezone":"Africa/Lagos",
    "iso:country":"NG",
    "name:eng_x_preferred":[
        "Odame"
    ],
    "wof:name":"Odame",
    "wof:placetype":"locality"
},
  "geometry": {"coordinates":[6.37168,6.98503],"type":"Point"}
}