{
  "type": "Feature",
  "properties": {
    "gn:admin1_code":"27.0",
    "gn:admin2_code":"117.0",
    "gn:admin3_code":"11701",
    "gn:asciiname":"Yebi Jemi",
    "gn:country_code":"NG",
    "gn:dem":294,
    "gn:feature_class":"P",
    "gn:feature_code":"PPL",
    "gn:name":"Yebi Jemi",
    "gn:population":0,
    "gn:timezone":"Africa/Lagos",
    "iso:country":"NG",
    "name:und_x_variant":[
        "Yebi-Jemi"
    ],
    "wof:name":"Yebi Jemi",
    "wof:placetype":"locality"
},
  "geometry": {"coordinates":[13.58825,13.12055],"type":"Point"}
}