{
  "type": "Feature",
  "properties": {
    "gn:admin1_code":"24.0",
    "gn:admin2_code":"401.0",
    "gn:admin3_code":"40106",
    "gn:asciiname":"Dan Jatau",
    "gn:country_code":"NG",
    "gn:dem":634,
    "gn:feature_class":"P",
    "gn:feature_code":"PPL",
    "gn:name":"Dan Jatau",
    "gn:population":0,
    "gn:timezone":"Africa/Lagos",
    "iso:country":"NG",
    "name:und_x_variant":[
        "Angwan Danjatau",
        "Dan Jatau"
    ],
    "wof:name":"Dan Jatau",
    "wof:placetype":"locality"
},
  "geometry": {"coordinates":[7.42312,11.64773],"type":"Point"}
}