{
  "type": "Feature",
  "properties": {
    "gn:admin1_code":"11.0",
    "gn:admin2_code":"15006.0",
    "gn:asciiname":"Burum",
    "gn:country_code":"NG",
    "gn:dem":530,
    "gn:feature_class":"P",
    "gn:feature_code":"PPL",
    "gn:name":"Burum",
    "gn:population":0,
    "gn:timezone":"Africa/Lagos",
    "iso:country":"NG",
    "name:ceb_x_preferred":[
        "Burum"
    ],
    "name:deu_x_preferred":[
        "Burum"
    ],
    "name:swe_x_preferred":[
        "Burum"
    ],
    "wof:name":"Burum",
    "wof:placetype":"neighbourhood"
},
  "geometry": {"coordinates":[7.49194,8.91056],"type":"Point"}
}