{
  "type": "Feature",
  "properties": {
    "gn:admin1_code":"50.0",
    "gn:admin2_code":"33013.0",
    "gn:asciiname":"Rumu-Eket",
    "gn:country_code":"NG",
    "gn:dem":27,
    "gn:feature_class":"P",
    "gn:feature_code":"PPL",
    "gn:name":"Rumu-Eket",
    "gn:population":0,
    "gn:timezone":"Africa/Lagos",
    "iso:country":"NG",
    "name:und_x_variant":[
        "Umu-Eket",
        "Rumu-Eke"
    ],
    "wof:name":"Rumu-Eket",
    "wof:placetype":"locality"
},
  "geometry": {"coordinates":[6.92722,4.9857],"type":"Point"}
}