{
  "type": "Feature",
  "properties": {
    "gn:admin1_code":"5.0",
    "gn:admin2_code":"25004.0",
    "gn:asciiname":"Imore",
    "gn:country_code":"NG",
    "gn:dem":8,
    "gn:feature_class":"P",
    "gn:feature_code":"PPL",
    "gn:name":"Imore",
    "gn:population":0,
    "gn:timezone":"Africa/Lagos",
    "iso:country":"NG",
    "wof:name":"Imore",
    "wof:placetype":"neighbourhood"
},
  "geometry": {"coordinates":[3.28042,6.4225],"type":"Point"}
}