{
  "type": "Feature",
  "properties": {
    "gn:admin1_code":"50.0",
    "gn:asciiname":"Ogwati",
    "gn:country_code":"NG",
    "gn:dem":50,
    "gn:feature_class":"P",
    "gn:feature_code":"PPL",
    "gn:name":"Ogwati",
    "gn:population":0,
    "gn:timezone":"Africa/Lagos",
    "iso:country":"NG",
    "wof:name":"Ogwati",
    "wof:placetype":"locality"
},
  "geometry": {"coordinates":[7.27212,5.03303],"type":"Point"}
}