{
  "type": "Feature",
  "properties": {
    "gn:admin1_code":"49.0",
    "gn:admin2_code":"32001.0",
    "gn:asciiname":"Ropp",
    "gn:country_code":"NG",
    "gn:dem":1349,
    "gn:feature_class":"P",
    "gn:feature_code":"PPL",
    "gn:name":"Ropp",
    "gn:population":0,
    "gn:timezone":"Africa/Lagos",
    "iso:country":"NG",
    "name:nds_x_preferred":[
        "Ropp"
    ],
    "name:pol_x_preferred":[
        "Ropp"
    ],
    "name:rus_x_preferred":[
        "\u0420\u043e\u043f\u043f"
    ],
    "name:und_x_variant":[
        "Rop"
    ],
    "wof:name":"Ropp",
    "wof:placetype":"locality"
},
  "geometry": {"coordinates":[8.92788,9.50158],"type":"Point"}
}