{
  "type": "Feature",
  "properties": {
    "gn:admin1_code":"27.0",
    "gn:admin2_code":"104.0",
    "gn:admin3_code":"10401",
    "gn:asciiname":"Gokwa",
    "gn:country_code":"NG",
    "gn:dem":405,
    "gn:feature_class":"P",
    "gn:feature_code":"PPL",
    "gn:name":"Gokwa",
    "gn:population":0,
    "gn:timezone":"Africa/Lagos",
    "iso:country":"NG",
    "name:und_x_variant":[
        "Gokwal",
        "Gokwa"
    ],
    "wof:name":"Gokwa",
    "wof:placetype":"locality"
},
  "geometry": {"coordinates":[11.76795,10.61509],"type":"Point"}
}