{
  "type": "Feature",
  "properties": {
    "gn:admin1_code":"35.0",
    "gn:asciiname":"Alarba",
    "gn:country_code":"NG",
    "gn:dem":196,
    "gn:feature_class":"P",
    "gn:feature_code":"PPL",
    "gn:name":"Alarba",
    "gn:population":0,
    "gn:timezone":"Africa/Lagos",
    "iso:country":"NG",
    "name:eng_x_preferred":[
        "Alarba"
    ],
    "wof:name":"Alarba",
    "wof:placetype":"locality"
},
  "geometry": {"coordinates":[12.48313,9.13176],"type":"Point"}
}