{
  "type": "Feature",
  "properties": {
    "gn:admin1_code":"37.0",
    "gn:admin2_code":"12013.0",
    "gn:asciiname":"Ugbedun",
    "gn:country_code":"NG",
    "gn:dem":149,
    "gn:feature_class":"P",
    "gn:feature_code":"PPL",
    "gn:name":"Ugbedun",
    "gn:population":0,
    "gn:timezone":"Africa/Lagos",
    "iso:country":"NG",
    "name:eng_x_preferred":[
        "Ugbedun"
    ],
    "wof:name":"Ugbedun",
    "wof:placetype":"locality"
},
  "geometry": {"coordinates":[6.07098,6.24362],"type":"Point"}
}