{
  "type": "Feature",
  "properties": {
    "gn:admin1_code":"29.0",
    "gn:asciiname":"Gidan Bagadu",
    "gn:country_code":"NG",
    "gn:dem":585,
    "gn:feature_class":"P",
    "gn:feature_code":"PPL",
    "gn:name":"Gidan Bagadu",
    "gn:population":0,
    "gn:timezone":"Africa/Lagos",
    "iso:country":"NG",
    "name:und_x_variant":[
        "Bagudu",
        "Gidan Bagadu"
    ],
    "wof:name":"Gidan Bagadu",
    "wof:placetype":"locality"
},
  "geometry": {"coordinates":[8.09091,11.47357],"type":"Point"}
}