{
  "type": "Feature",
  "properties": {
    "gn:admin1_code":"40.0",
    "gn:admin2_code":"502.0",
    "gn:admin3_code":"50201",
    "gn:asciiname":"Tambo",
    "gn:country_code":"NG",
    "gn:dem":217,
    "gn:feature_class":"P",
    "gn:feature_code":"PPL",
    "gn:name":"Tambo",
    "gn:population":0,
    "gn:timezone":"Africa/Lagos",
    "iso:country":"NG",
    "name:ceb_x_preferred":[
        "Tambo"
    ],
    "name:deu_x_preferred":[
        "Tambo"
    ],
    "name:fra_x_preferred":[
        "Tambo"
    ],
    "name:hrv_x_preferred":[
        "Tambo"
    ],
    "name:nor_x_preferred":[
        "Tambo"
    ],
    "name:por_x_preferred":[
        "Tambo"
    ],
    "name:rus_x_preferred":[
        "\u0422\u0430\u043c\u0431\u043e"
    ],
    "name:spa_x_preferred":[
        "Tambo"
    ],
    "name:swe_x_preferred":[
        "Tambo"
    ],
    "wof:name":"Tambo",
    "wof:placetype":"locality"
},
  "geometry": {"coordinates":[4.35875,13.16107],"type":"Point"}
}