{
  "type": "Feature",
  "properties": {
    "gn:admin1_code":"31.0",
    "gn:admin2_code":"27012.0",
    "gn:asciiname":"Dobogi",
    "gn:country_code":"NG",
    "gn:dem":180,
    "gn:feature_class":"P",
    "gn:feature_code":"PPL",
    "gn:name":"Dobogi",
    "gn:population":0,
    "gn:timezone":"Africa/Lagos",
    "iso:country":"NG",
    "wof:name":"Dobogi",
    "wof:placetype":"locality"
},
  "geometry": {"coordinates":[6.68333,8.56667],"type":"Point"}
}