{
  "type": "Feature",
  "properties": {
    "gn:admin1_code":"26.0",
    "gn:admin2_code":"7005.0",
    "gn:asciiname":"Mtil",
    "gn:country_code":"NG",
    "gn:dem":147,
    "gn:feature_class":"P",
    "gn:feature_code":"PPL",
    "gn:name":"Mtil",
    "gn:population":0,
    "gn:timezone":"Africa/Lagos",
    "iso:country":"NG",
    "wof:name":"Mtil",
    "wof:placetype":"locality"
},
  "geometry": {"coordinates":[8.69001,7.47317],"type":"Point"}
}