{
  "type": "Feature",
  "properties": {
    "gn:admin1_code":"39.0",
    "gn:admin2_code":"18020.0",
    "gn:admin3_code":"JI2305",
    "gn:asciiname":"Garin Dawa",
    "gn:country_code":"NG",
    "gn:dem":397,
    "gn:feature_class":"P",
    "gn:feature_code":"PPL",
    "gn:name":"Garin Dawa",
    "gn:population":0,
    "gn:timezone":"Africa/Lagos",
    "iso:country":"NG",
    "wof:name":"Garin Dawa",
    "wof:placetype":"locality"
},
  "geometry": {"coordinates":[8.9908,12.21779],"type":"Point"}
}