{
  "type": "Feature",
  "properties": {
    "gn:admin1_code":"56.0",
    "gn:admin2_code":"26004",
    "gn:asciiname":"Gidan Ngeru",
    "gn:country_code":"NG",
    "gn:dem":418,
    "gn:feature_class":"P",
    "gn:feature_code":"PPL",
    "gn:name":"Gidan Ngeru",
    "gn:population":0,
    "gn:timezone":"Africa/Lagos",
    "iso:country":"NG",
    "wof:name":"Gidan Ngeru",
    "wof:placetype":"locality"
},
  "geometry": {"coordinates":[7.90712,9.12201],"type":"Point"}
}