{
  "type": "Feature",
  "properties": {
    "gn:admin1_code":"57.0",
    "gn:admin2_code":"805.0",
    "gn:admin3_code":"80501",
    "gn:asciiname":"Dangau",
    "gn:country_code":"NG",
    "gn:dem":436,
    "gn:feature_class":"P",
    "gn:feature_code":"PPL",
    "gn:name":"Dangau",
    "gn:population":0,
    "gn:timezone":"Africa/Lagos",
    "iso:country":"NG",
    "name:und_x_variant":[
        "Unguwar Dangau",
        "Dangau"
    ],
    "wof:name":"Dangau",
    "wof:placetype":"locality"
},
  "geometry": {"coordinates":[6.71358,12.29397],"type":"Point"}
}