{
  "type": "Feature",
  "properties": {
    "gn:admin1_code":"55.0",
    "gn:admin2_code":"16011.0",
    "gn:asciiname":"Garin Lanotali",
    "gn:country_code":"NG",
    "gn:dem":370,
    "gn:feature_class":"P",
    "gn:feature_code":"PPL",
    "gn:name":"Garin Lanotali",
    "gn:population":0,
    "gn:timezone":"Africa/Lagos",
    "iso:country":"NG",
    "wof:name":"Garin Lanotali",
    "wof:placetype":"locality"
},
  "geometry": {"coordinates":[11.333,10.26155],"type":"Point"}
}