{
  "type": "Feature",
  "properties": {
    "gn:admin1_code":"36.0",
    "gn:admin2_code":"10007.0",
    "gn:asciiname":"Owa-Ofie",
    "gn:country_code":"NG",
    "gn:dem":156,
    "gn:feature_class":"P",
    "gn:feature_code":"PPL",
    "gn:name":"Owa-Ofie",
    "gn:population":0,
    "gn:timezone":"Africa/Lagos",
    "iso:country":"NG",
    "name:eng_x_preferred":[
        "Owa-Ofie"
    ],
    "wof:name":"Owa-Ofie",
    "wof:placetype":"locality"
},
  "geometry": {"coordinates":[6.17805,6.20629],"type":"Point"}
}