{
  "type": "Feature",
  "properties": {
    "gn:admin1_code":"27.0",
    "gn:admin2_code":"117.0",
    "gn:admin3_code":"11708",
    "gn:asciiname":"Kekeno",
    "gn:country_code":"NG",
    "gn:dem":289,
    "gn:feature_class":"P",
    "gn:feature_code":"PPL",
    "gn:name":"Kekeno",
    "gn:population":0,
    "gn:timezone":"Africa/Lagos",
    "iso:country":"NG",
    "name:und_x_variant":[
        "Checheno",
        "Kekeno"
    ],
    "wof:name":"Kekeno",
    "wof:placetype":"locality"
},
  "geometry": {"coordinates":[13.70754,12.76429],"type":"Point"}
}