{
  "type": "Feature",
  "properties": {
    "gn:admin1_code":"23.0",
    "gn:admin2_code":"19020",
    "gn:admin3_code":"KD2002",
    "gn:asciiname":"Agwam",
    "gn:country_code":"NG",
    "gn:dem":526,
    "gn:feature_class":"P",
    "gn:feature_code":"PPL",
    "gn:name":"Agwam",
    "gn:population":0,
    "gn:timezone":"Africa/Lagos",
    "iso:country":"NG",
    "wof:name":"Agwam",
    "wof:placetype":"locality"
},
  "geometry": {"coordinates":[8.3837,9.22124],"type":"Point"}
}