{
  "type": "Feature",
  "properties": {
    "gn:admin1_code":"5.0",
    "gn:admin2_code":"25009.0",
    "gn:asciiname":"Igando",
    "gn:country_code":"NG",
    "gn:dem":14,
    "gn:feature_class":"P",
    "gn:feature_code":"PPL",
    "gn:name":"Igando",
    "gn:population":0,
    "gn:timezone":"Africa/Lagos",
    "iso:country":"NG",
    "name:und_x_variant":[
        "Igando Awlawja",
        "Igando"
    ],
    "wof:name":"Igando",
    "wof:placetype":"neighbourhood"
},
  "geometry": {"coordinates":[3.81603,6.44059],"type":"Point"}
}