{
  "type": "Feature",
  "properties": {
    "gn:admin1_code":"55.0",
    "gn:admin2_code":"16004.0",
    "gn:asciiname":"Tumpuri",
    "gn:country_code":"NG",
    "gn:dem":510,
    "gn:feature_class":"P",
    "gn:feature_code":"PPL",
    "gn:name":"Tumpuri",
    "gn:population":0,
    "gn:timezone":"Africa/Lagos",
    "iso:country":"NG",
    "name:eng_x_preferred":[
        "Tumpuri"
    ],
    "wof:name":"Tumpuri",
    "wof:placetype":"locality"
},
  "geometry": {"coordinates":[10.75366,10.70946],"type":"Point"}
}