{
  "type": "Feature",
  "properties": {
    "gn:admin1_code":"23.0",
    "gn:asciiname":"Kwondo",
    "gn:country_code":"NG",
    "gn:dem":781,
    "gn:feature_class":"P",
    "gn:feature_code":"PPL",
    "gn:name":"Kwondo",
    "gn:population":0,
    "gn:timezone":"Africa/Lagos",
    "iso:country":"NG",
    "wof:name":"Kwondo",
    "wof:placetype":"locality"
},
  "geometry": {"coordinates":[8.69864,10.69173],"type":"Point"}
}