{
  "type": "Feature",
  "properties": {
    "gn:admin1_code":"21.0",
    "gn:admin2_code":"3011.0",
    "gn:asciiname":"Urua Inyang",
    "gn:country_code":"NG",
    "gn:dem":65,
    "gn:feature_class":"P",
    "gn:feature_code":"PPLA2",
    "gn:name":"Urua Inyang",
    "gn:population":0,
    "gn:timezone":"Africa/Lagos",
    "iso:country":"NG",
    "wof:name":"Urua Inyang",
    "wof:placetype":"locality"
},
  "geometry": {"coordinates":[7.53895,5.02309],"type":"Point"}
}