{
  "type": "Feature",
  "properties": {
    "gn:admin1_code":"40.0",
    "gn:admin2_code":"502.0",
    "gn:admin3_code":"50207",
    "gn:asciiname":"Raya",
    "gn:country_code":"NG",
    "gn:dem":236,
    "gn:feature_class":"P",
    "gn:feature_code":"PPL",
    "gn:name":"Raya",
    "gn:population":0,
    "gn:timezone":"Africa/Lagos",
    "iso:country":"NG",
    "name:bpy_x_preferred":[
        "\u09b0\u09be\u09af\u09bc\u09be"
    ],
    "name:ceb_x_preferred":[
        "Raya"
    ],
    "name:deu_x_preferred":[
        "Raya"
    ],
    "name:msa_x_preferred":[
        "Raya"
    ],
    "name:new_x_preferred":[
        "\u0930\u092f\u093e"
    ],
    "name:nld_x_preferred":[
        "Raya"
    ],
    "name:pol_x_preferred":[
        "Raya"
    ],
    "name:spa_x_preferred":[
        "Raya"
    ],
    "name:swe_x_preferred":[
        "Raya"
    ],
    "wof:name":"Raya",
    "wof:placetype":"locality"
},
  "geometry": {"coordinates":[3.67221,12.36581],"type":"Point"}
}