{
  "type": "Feature",
  "properties": {
    "gn:admin1_code":"5.0",
    "gn:admin2_code":"25007.0",
    "gn:asciiname":"Ibonwon",
    "gn:country_code":"NG",
    "gn:dem":22,
    "gn:feature_class":"P",
    "gn:feature_code":"PPL",
    "gn:name":"Ibonwon",
    "gn:population":0,
    "gn:timezone":"Africa/Lagos",
    "iso:country":"NG",
    "wof:name":"Ibonwon",
    "wof:placetype":"locality"
},
  "geometry": {"coordinates":[3.99622,6.67179],"type":"Point"}
}