{
  "type": "Feature",
  "properties": {
    "gn:admin1_code":"22.0",
    "gn:admin2_code":"9016",
    "gn:asciiname":"Itegaokudu",
    "gn:country_code":"NG",
    "gn:dem":76,
    "gn:feature_class":"P",
    "gn:feature_code":"PPL",
    "gn:name":"Itegaokudu",
    "gn:population":0,
    "gn:timezone":"Africa/Lagos",
    "iso:country":"NG",
    "wof:name":"Itegaokudu",
    "wof:placetype":"locality"
},
  "geometry": {"coordinates":[8.66108,6.58449],"type":"Point"}
}