{
  "type": "Feature",
  "properties": {
    "gn:admin1_code":"51.0",
    "gn:admin2_code":"603.0",
    "gn:admin3_code":"60304",
    "gn:asciiname":"Sadingo",
    "gn:country_code":"NG",
    "gn:dem":327,
    "gn:feature_class":"P",
    "gn:feature_code":"PPL",
    "gn:name":"Sadingo",
    "gn:population":0,
    "gn:timezone":"Africa/Lagos",
    "iso:country":"NG",
    "name:und_x_variant":[
        "Sidingu",
        "Sadingo"
    ],
    "wof:name":"Sadingo",
    "wof:placetype":"locality"
},
  "geometry": {"coordinates":[5.41449,12.93656],"type":"Point"}
}