{
  "type": "Feature",
  "properties": {
    "gn:admin1_code":"26.0",
    "gn:admin2_code":"7010.0",
    "gn:asciiname":"Ture",
    "gn:country_code":"NG",
    "gn:dem":113,
    "gn:feature_class":"P",
    "gn:feature_code":"PPL",
    "gn:name":"Ture",
    "gn:population":0,
    "gn:timezone":"Africa/Lagos",
    "iso:country":"NG",
    "name:deu_x_preferred":[
        "Ture"
    ],
    "name:lav_x_preferred":[
        "Ture"
    ],
    "wof:name":"Ture",
    "wof:placetype":"locality"
},
  "geometry": {"coordinates":[8.69978,7.05463],"type":"Point"}
}