{
  "type": "Feature",
  "properties": {
    "gn:admin1_code":"29.0",
    "gn:admin2_code":"20005.0",
    "gn:admin3_code":"KN3312",
    "gn:asciiname":"Akalawa",
    "gn:country_code":"NG",
    "gn:dem":524,
    "gn:feature_class":"P",
    "gn:feature_code":"PPL",
    "gn:name":"Akalawa",
    "gn:population":0,
    "gn:timezone":"Africa/Lagos",
    "iso:country":"NG",
    "wof:name":"Akalawa",
    "wof:placetype":"locality"
},
  "geometry": {"coordinates":[8.22729,11.96968],"type":"Point"}
}