{
  "type": "Feature",
  "properties": {
    "gn:admin1_code":"27.0",
    "gn:admin2_code":"118.0",
    "gn:admin3_code":"11801",
    "gn:asciiname":"Chata",
    "gn:country_code":"NG",
    "gn:dem":364,
    "gn:feature_class":"P",
    "gn:feature_code":"PPL",
    "gn:name":"Chata",
    "gn:population":0,
    "gn:timezone":"Africa/Lagos",
    "iso:country":"NG",
    "name:ind_x_preferred":[
        "Chata"
    ],
    "name:tgl_x_preferred":[
        "Chata"
    ],
    "name:vie_x_preferred":[
        "Chata"
    ],
    "wof:name":"Chata",
    "wof:placetype":"locality"
},
  "geometry": {"coordinates":[12.02304,10.35557],"type":"Point"}
}