{
  "type": "Feature",
  "properties": {
    "gn:admin1_code":"56.0",
    "gn:admin2_code":"26010.0",
    "gn:asciiname":"Alizaga",
    "gn:country_code":"NG",
    "gn:dem":268,
    "gn:feature_class":"P",
    "gn:feature_code":"PPL",
    "gn:name":"Alizaga",
    "gn:population":0,
    "gn:timezone":"Africa/Lagos",
    "iso:country":"NG",
    "name:fas_x_preferred":[
        "\u0627\u0644\u06cc\u0632\u0627\u06af\u0627"
    ],
    "wof:name":"Alizaga",
    "wof:placetype":"locality"
},
  "geometry": {"coordinates":[8.55,8.73333],"type":"Point"}
}