{
  "type": "Feature",
  "properties": {
    "gn:admin1_code":"42.0",
    "gn:admin2_code":"30022.0",
    "gn:asciiname":"Alamo",
    "gn:country_code":"NG",
    "gn:dem":134,
    "gn:feature_class":"P",
    "gn:feature_code":"PPL",
    "gn:name":"Alamo",
    "gn:population":0,
    "gn:timezone":"Africa/Lagos",
    "iso:country":"NG",
    "wof:name":"Alamo",
    "wof:placetype":"locality"
},
  "geometry": {"coordinates":[4.13333,7.25],"type":"Point"}
}