{
  "type": "Feature",
  "properties": {
    "gn:admin1_code":"52.0",
    "gn:admin2_code":"6007.0",
    "gn:asciiname":"Beregbene-Willy",
    "gn:country_code":"NG",
    "gn:dem":12,
    "gn:feature_class":"P",
    "gn:feature_code":"PPL",
    "gn:name":"Beregbene-Willy",
    "gn:population":0,
    "gn:timezone":"Africa/Lagos",
    "iso:country":"NG",
    "name:eng_x_preferred":[
        "Beregbene-Willy"
    ],
    "wof:name":"Beregbene-Willy",
    "wof:placetype":"locality"
},
  "geometry": {"coordinates":[5.63377,4.73987],"type":"Point"}
}