{
  "type": "Feature",
  "properties": {
    "gn:admin1_code":"49.0",
    "gn:admin2_code":"32002.0",
    "gn:asciiname":"Tsofo-n-Bassa",
    "gn:country_code":"NG",
    "gn:dem":1071,
    "gn:feature_class":"P",
    "gn:feature_code":"PPL",
    "gn:name":"Tsofo-n-Bassa",
    "gn:population":0,
    "gn:timezone":"Africa/Lagos",
    "iso:country":"NG",
    "name:und_x_variant":[
        "Tsofon Bassa"
    ],
    "wof:name":"Tsofo-n-Bassa",
    "wof:placetype":"locality"
},
  "geometry": {"coordinates":[8.75248,9.99158],"type":"Point"}
}