{
  "type": "Feature",
  "properties": {
    "gn:admin1_code":"49.0",
    "gn:asciiname":"Wookong",
    "gn:country_code":"NG",
    "gn:dem":168,
    "gn:feature_class":"P",
    "gn:feature_code":"PPL",
    "gn:name":"Wookong",
    "gn:population":0,
    "gn:timezone":"Africa/Lagos",
    "iso:country":"NG",
    "wof:name":"Wookong",
    "wof:placetype":"locality"
},
  "geometry": {"coordinates":[9.36549,8.66169],"type":"Point"}
}