{
  "type": "Feature",
  "properties": {
    "gn:admin1_code":"57.0",
    "gn:admin2_code":"804.0",
    "gn:admin3_code":"80405",
    "gn:asciiname":"Ramfashi",
    "gn:country_code":"NG",
    "gn:dem":329,
    "gn:feature_class":"P",
    "gn:feature_code":"PPL",
    "gn:name":"Ramfashi",
    "gn:population":0,
    "gn:timezone":"Africa/Lagos",
    "iso:country":"NG",
    "wof:name":"Ramfashi",
    "wof:placetype":"locality"
},
  "geometry": {"coordinates":[5.66176,12.04555],"type":"Point"}
}