{
  "type": "Feature",
  "properties": {
    "gn:admin1_code":"49.0",
    "gn:asciiname":"Pedel",
    "gn:country_code":"NG",
    "gn:dem":219,
    "gn:feature_class":"P",
    "gn:feature_code":"PPL",
    "gn:name":"Pedel",
    "gn:population":0,
    "gn:timezone":"Africa/Lagos",
    "iso:country":"NG",
    "wof:name":"Pedel",
    "wof:placetype":"locality"
},
  "geometry": {"coordinates":[9.45687,8.87875],"type":"Point"}
}