{
  "type": "Feature",
  "properties": {
    "gn:admin1_code":"37.0",
    "gn:admin2_code":"12012.0",
    "gn:asciiname":"Egbiri",
    "gn:country_code":"NG",
    "gn:dem":22,
    "gn:feature_class":"P",
    "gn:feature_code":"PPL",
    "gn:name":"Egbiri",
    "gn:population":0,
    "gn:timezone":"Africa/Lagos",
    "iso:country":"NG",
    "wof:name":"Egbiri",
    "wof:placetype":"neighbourhood"
},
  "geometry": {"coordinates":[5.58666,6.22769],"type":"Point"}
}