{
  "type": "Feature",
  "properties": {
    "iso:country":"NG",
    "name:eng_x_preferred":[
        "Etinan"
    ],
    "name:fre_x_preferred":[
        "Etinan"
    ],
    "name:ita_x_preferred":[
        "Etinan"
    ],
    "name:yor_x_preferred":[
        "Etinan"
    ],
    "name:zho_min_nan_x_preferred":[
        "Etinan"
    ],
    "qs:gn_country":"NG",
    "qs:gn_fcode":"PPL",
    "qs:gn_pop":10318,
    "qs:name":"Etinan",
    "qs:name_adm0":"Nigeria",
    "qs:name_adm1":"Akwa Ibom",
    "qs:photos":0,
    "qs:photos_1k":0,
    "qs:photos_9k":0,
    "qs:photos_9r":0,
    "qs:photos_all":0,
    "qs:photos_sr":0,
    "qs:placetype":"Town",
    "qs:pop_sr":"6",
    "qs:woe_adm0":23424908,
    "wd:wordcount":457,
    "wof:name":"Etinan",
    "wof:placetype":"locality",
    "wof:population":10318
},
  "geometry": {"coordinates":[7.85252,4.84262],"type":"Point"}
}