{
  "type": "Feature",
  "properties": {
    "gn:admin1_code":"44.0",
    "gn:admin2_code":"712.0",
    "gn:admin3_code":"71201",
    "gn:asciiname":"Abaredunga",
    "gn:country_code":"NG",
    "gn:dem":433,
    "gn:feature_class":"P",
    "gn:feature_code":"PPL",
    "gn:name":"Abaredunga",
    "gn:population":0,
    "gn:timezone":"Africa/Lagos",
    "iso:country":"NG",
    "wof:name":"Abaredunga",
    "wof:placetype":"locality"
},
  "geometry": {"coordinates":[11.00451,11.66656],"type":"Point"}
}