{
  "type": "Feature",
  "properties": {
    "gn:admin1_code":"27.0",
    "gn:admin2_code":"123",
    "gn:admin3_code":"12307",
    "gn:asciiname":"Langiya Bulabulin",
    "gn:country_code":"NG",
    "gn:dem":295,
    "gn:feature_class":"P",
    "gn:feature_code":"PPL",
    "gn:name":"Langiya Bulabulin",
    "gn:population":0,
    "gn:timezone":"Africa/Lagos",
    "iso:country":"NG",
    "wof:name":"Langiya Bulabulin",
    "wof:placetype":"locality"
},
  "geometry": {"coordinates":[13.53004,12.75879],"type":"Point"}
}