{
  "type": "Feature",
  "properties": {
    "gn:admin1_code":"52.0",
    "gn:admin2_code":"6007.0",
    "gn:asciiname":"Abalagiagbene",
    "gn:country_code":"NG",
    "gn:dem":11,
    "gn:feature_class":"P",
    "gn:feature_code":"PPL",
    "gn:name":"Abalagiagbene",
    "gn:population":0,
    "gn:timezone":"Africa/Lagos",
    "iso:country":"NG",
    "name:eng_x_preferred":[
        "Abalagiagbene"
    ],
    "wof:name":"Abalagiagbene",
    "wof:placetype":"locality"
},
  "geometry": {"coordinates":[5.87868,4.47824],"type":"Point"}
}