{
  "type": "Feature",
  "properties": {
    "gn:admin1_code":"43.0",
    "gn:admin2_code":"35009.0",
    "gn:asciiname":"Nyigan",
    "gn:country_code":"NG",
    "gn:dem":481,
    "gn:feature_class":"P",
    "gn:feature_code":"PPL",
    "gn:name":"Nyigan",
    "gn:population":0,
    "gn:timezone":"Africa/Lagos",
    "iso:country":"NG",
    "wof:name":"Nyigan",
    "wof:placetype":"locality"
},
  "geometry": {"coordinates":[10.71188,7.28301],"type":"Point"}
}