{
  "type": "Feature",
  "properties": {
    "gn:admin1_code":"23.0",
    "gn:admin2_code":"19022",
    "gn:admin3_code":"KD2202",
    "gn:asciiname":"Sazuwat",
    "gn:country_code":"NG",
    "gn:dem":801,
    "gn:feature_class":"P",
    "gn:feature_code":"PPL",
    "gn:name":"Sazuwat",
    "gn:population":0,
    "gn:timezone":"Africa/Lagos",
    "iso:country":"NG",
    "wof:name":"Sazuwat",
    "wof:placetype":"locality"
},
  "geometry": {"coordinates":[8.26448,9.94192],"type":"Point"}
}