{
  "type": "Feature",
  "properties": {
    "gn:admin1_code":"31.0",
    "gn:admin2_code":"27016.0",
    "gn:asciiname":"Adogo",
    "gn:country_code":"NG",
    "gn:dem":260,
    "gn:feature_class":"P",
    "gn:feature_code":"PPL",
    "gn:name":"Adogo",
    "gn:population":0,
    "gn:timezone":"Africa/Lagos",
    "iso:country":"NG",
    "wof:name":"Adogo",
    "wof:placetype":"locality"
},
  "geometry": {"coordinates":[5.24642,10.11385],"type":"Point"}
}