{
  "type": "Feature",
  "properties": {
    "gn:admin1_code":"27.0",
    "gn:admin2_code":"111",
    "gn:admin3_code":"11112",
    "gn:asciiname":"Hidazoka Clan",
    "gn:country_code":"NG",
    "gn:dem":422,
    "gn:feature_class":"P",
    "gn:feature_code":"PPLL",
    "gn:name":"Hidazoka Clan",
    "gn:population":0,
    "gn:timezone":"Africa/Lagos",
    "iso:country":"NG",
    "wof:name":"Hidazoka Clan",
    "wof:placetype":"locality"
},
  "geometry": {"coordinates":[13.80238,11.17576],"type":"Point"}
}