{
  "type": "Feature",
  "properties": {
    "gn:admin1_code":"40.0",
    "gn:admin2_code":"511.0",
    "gn:admin3_code":"51111",
    "gn:asciiname":"Kimba",
    "gn:country_code":"NG",
    "gn:dem":244,
    "gn:feature_class":"P",
    "gn:feature_code":"PPL",
    "gn:name":"Kimba",
    "gn:population":0,
    "gn:timezone":"Africa/Lagos",
    "iso:country":"NG",
    "name:ben_x_preferred":[
        "\u0995\u09bf\u09ae\u09cd\u09ac\u09be"
    ],
    "name:ceb_x_preferred":[
        "Kimba"
    ],
    "name:deu_x_preferred":[
        "Kimba"
    ],
    "name:ell_x_preferred":[
        "\u039a\u03af\u03bc\u03c0\u03b1"
    ],
    "name:heb_x_preferred":[
        "\u05e7\u05d9\u05de\u05d1\u05d4"
    ],
    "name:hin_x_preferred":[
        "\u0915\u093f\u0902\u092c\u093e"
    ],
    "name:hun_x_preferred":[
        "Kimba"
    ],
    "name:ind_x_preferred":[
        "Kimba"
    ],
    "name:ita_x_preferred":[
        "Kimba"
    ],
    "name:jpn_x_preferred":[
        "\u30ad\u30f3\u30d0"
    ],
    "name:kor_x_preferred":[
        "\ud0b4\ubc14"
    ],
    "name:rus_x_preferred":[
        "\u041a\u0438\u043c\u0431\u0430"
    ],
    "name:spa_x_preferred":[
        "Kimba"
    ],
    "name:swe_x_preferred":[
        "Kimba"
    ],
    "name:tur_x_preferred":[
        "Kimba"
    ],
    "name:ukr_x_preferred":[
        "\u041a\u0456\u043c\u0431\u0430"
    ],
    "name:und_x_variant":[
        "Kimbe"
    ],
    "name:urd_x_preferred":[
        "\u06a9\u0645\u0628\u0627"
    ],
    "name:vie_x_preferred":[
        "Kimba"
    ],
    "wof:name":"Kimba",
    "wof:placetype":"locality"
},
  "geometry": {"coordinates":[4.41443,12.1937],"type":"Point"}
}