{
  "type": "Feature",
  "properties": {
    "gn:admin1_code":"40.0",
    "gn:admin2_code":"511.0",
    "gn:admin3_code":"51111",
    "gn:asciiname":"Kimba",
    "gn:country_code":"NG",
    "gn:dem":244,
    "gn:feature_class":"P",
    "gn:feature_code":"PPL",
    "gn:name":"Kimba",
    "gn:population":0,
    "gn:timezone":"Africa/Lagos",
    "iso:country":"NG",
    "name:ceb_x_preferred":[
        "Kimba"
    ],
    "name:deu_x_preferred":[
        "Kimba"
    ],
    "name:ita_x_preferred":[
        "Kimba"
    ],
    "name:swe_x_preferred":[
        "Kimba"
    ],
    "name:und_x_variant":[
        "Kimbe"
    ],
    "wof:name":"Kimba",
    "wof:placetype":"locality"
},
  "geometry": {"coordinates":[4.41443,12.1937],"type":"Point"}
}