{
  "type": "Feature",
  "properties": {
    "gn:admin1_code":"47.0",
    "gn:admin2_code":"14016",
    "gn:asciiname":"Ukume",
    "gn:country_code":"NG",
    "gn:dem":190,
    "gn:feature_class":"P",
    "gn:feature_code":"PPL",
    "gn:name":"Ukume",
    "gn:population":0,
    "gn:timezone":"Africa/Lagos",
    "iso:country":"NG",
    "wof:name":"Ukume",
    "wof:placetype":"locality"
},
  "geometry": {"coordinates":[7.25903,6.54407],"type":"Point"}
}