{
  "type": "Feature",
  "properties": {
    "gn:admin1_code":"26.0",
    "gn:admin2_code":"7010.0",
    "gn:asciiname":"Kor",
    "gn:country_code":"NG",
    "gn:dem":107,
    "gn:feature_class":"P",
    "gn:feature_code":"PPL",
    "gn:name":"Kor",
    "gn:population":0,
    "gn:timezone":"Africa/Lagos",
    "iso:country":"NG",
    "name:cat_x_preferred":[
        "Kor"
    ],
    "name:ceb_x_preferred":[
        "Kor"
    ],
    "name:ces_x_preferred":[
        "Kor"
    ],
    "name:dan_x_preferred":[
        "Kor"
    ],
    "name:hrv_x_preferred":[
        "Kor"
    ],
    "name:hun_x_preferred":[
        "Kor"
    ],
    "name:nld_x_preferred":[
        "Kor"
    ],
    "name:nor_x_preferred":[
        "Kor"
    ],
    "name:slv_x_preferred":[
        "Kor"
    ],
    "name:swe_x_preferred":[
        "Kor"
    ],
    "name:tur_x_preferred":[
        "Kor"
    ],
    "wof:name":"Kor",
    "wof:placetype":"locality"
},
  "geometry": {"coordinates":[8.6048,7.1134],"type":"Point"}
}