{
  "type": "Feature",
  "properties": {
    "gn:admin1_code":"24.0",
    "gn:asciiname":"Dandi",
    "gn:country_code":"NG",
    "gn:dem":407,
    "gn:feature_class":"P",
    "gn:feature_code":"PPL",
    "gn:name":"Dandi",
    "gn:population":0,
    "gn:timezone":"Africa/Lagos",
    "iso:country":"NG",
    "wof:name":"Dandi",
    "wof:placetype":"locality"
},
  "geometry": {"coordinates":[8.66813,12.68369],"type":"Point"}
}