{
  "type": "Feature",
  "properties": {
    "gn:admin1_code":"46.0",
    "gn:admin2_code":"5016.0",
    "gn:admin3_code":"BA1613",
    "gn:asciiname":"Yerimari",
    "gn:country_code":"NG",
    "gn:dem":407,
    "gn:feature_class":"P",
    "gn:feature_code":"PPL",
    "gn:name":"Yerimari",
    "gn:population":0,
    "gn:timezone":"Africa/Lagos",
    "iso:country":"NG",
    "wof:name":"Yerimari",
    "wof:placetype":"locality"
},
  "geometry": {"coordinates":[10.0167,11.5167],"type":"Point"}
}