{
  "type": "Feature",
  "properties": {
    "gn:admin1_code":"46.0",
    "gn:admin2_code":"5001.0",
    "gn:admin3_code":"BA0108",
    "gn:asciiname":"Shafa",
    "gn:country_code":"NG",
    "gn:dem":287,
    "gn:feature_class":"P",
    "gn:feature_code":"PPL",
    "gn:name":"Shafa",
    "gn:population":0,
    "gn:timezone":"Africa/Lagos",
    "iso:country":"NG",
    "wof:name":"Shafa",
    "wof:placetype":"locality"
},
  "geometry": {"coordinates":[10.24038,9.69599],"type":"Point"}
}