{
  "type": "Feature",
  "properties": {
    "gn:admin1_code":"32.0",
    "gn:admin2_code":"31002.0",
    "gn:asciiname":"Kinkinyiun",
    "gn:cc2":"NG",
    "gn:country_code":"NG",
    "gn:dem":269,
    "gn:feature_class":"P",
    "gn:feature_code":"PPL",
    "gn:name":"Kinkinyiun",
    "gn:population":0,
    "gn:timezone":"Africa/Lagos",
    "iso:country":"NG",
    "name:und_x_variant":[
        "Kikiyiwun",
        "Kinkinyiun"
    ],
    "wof:name":"Kinkinyiun",
    "wof:placetype":"locality"
},
  "geometry": {"coordinates":[3.85,7.53333],"type":"Point"}
}