{
  "type": "Feature",
  "properties": {
    "gn:admin1_code":"23.0",
    "gn:admin2_code":"19008.0",
    "gn:admin3_code":"KD0802",
    "gn:asciiname":"Akura",
    "gn:country_code":"NG",
    "gn:dem":748,
    "gn:feature_class":"P",
    "gn:feature_code":"PPL",
    "gn:name":"Akura",
    "gn:population":0,
    "gn:timezone":"Africa/Lagos",
    "iso:country":"NG",
    "name:ceb_x_preferred":[
        "Akura"
    ],
    "wof:name":"Akura",
    "wof:placetype":"locality"
},
  "geometry": {"coordinates":[7.86091,9.87163],"type":"Point"}
}