{
  "type": "Feature",
  "properties": {
    "gn:admin1_code":"37.0",
    "gn:admin2_code":"12003.0",
    "gn:asciiname":"Efandion",
    "gn:country_code":"NG",
    "gn:dem":374,
    "gn:feature_class":"P",
    "gn:feature_code":"PPL",
    "gn:name":"Efandion",
    "gn:population":0,
    "gn:timezone":"Africa/Lagos",
    "iso:country":"NG",
    "name:eng_x_preferred":[
        "Efandion"
    ],
    "name:eng_x_variant":[
        "Ifadion",
        "Efahdion"
    ],
    "wof:name":"Efandion",
    "wof:placetype":"neighbourhood"
},
  "geometry": {"coordinates":[6.34121,6.70229],"type":"Point"}
}