{
  "type": "Feature",
  "properties": {
    "gn:admin1_code":"35.0",
    "gn:admin2_code":"2015.0",
    "gn:asciiname":"Wuro Hesso",
    "gn:country_code":"NG",
    "gn:dem":587,
    "gn:feature_class":"P",
    "gn:feature_code":"PPL",
    "gn:name":"Wuro Hesso",
    "gn:population":0,
    "gn:timezone":"Africa/Lagos",
    "iso:country":"NG",
    "wof:name":"Wuro Hesso",
    "wof:placetype":"locality"
},
  "geometry": {"coordinates":[13.2468,10.21315],"type":"Point"}
}