{
  "type": "Feature",
  "properties": {
    "gn:admin1_code":"35.0",
    "gn:admin2_code":"2001.0",
    "gn:asciiname":"Sangere Sani",
    "gn:country_code":"NG",
    "gn:dem":244,
    "gn:feature_class":"P",
    "gn:feature_code":"PPL",
    "gn:name":"Sangere Sani",
    "gn:population":0,
    "gn:timezone":"Africa/Lagos",
    "iso:country":"NG",
    "name:und_x_variant":[
        "Wuro Mallam Sani",
        "Sangare Sani",
        "Sangere Sani"
    ],
    "wof:name":"Sangere Sani",
    "wof:placetype":"locality"
},
  "geometry": {"coordinates":[12.09749,9.32021],"type":"Point"}
}