{
  "type": "Feature",
  "properties": {
    "gn:admin1_code":"37.0",
    "gn:admin2_code":"12018.0",
    "gn:asciiname":"Ugoneki",
    "gn:country_code":"NG",
    "gn:dem":96,
    "gn:feature_class":"P",
    "gn:feature_code":"PPL",
    "gn:name":"Ugoneki",
    "gn:population":0,
    "gn:timezone":"Africa/Lagos",
    "iso:country":"NG",
    "wof:name":"Ugoneki",
    "wof:placetype":"locality"
},
  "geometry": {"coordinates":[5.87999,6.30252],"type":"Point"}
}