{
  "type": "Feature",
  "properties": {
    "gn:admin1_code":"55.0",
    "gn:admin2_code":"16001.0",
    "gn:asciiname":"Goni",
    "gn:country_code":"NG",
    "gn:dem":397,
    "gn:feature_class":"P",
    "gn:feature_code":"PPL",
    "gn:name":"Goni",
    "gn:population":0,
    "gn:timezone":"Africa/Lagos",
    "iso:country":"NG",
    "name:arg_x_preferred":[
        "Goni"
    ],
    "name:azb_x_preferred":[
        "\u0642\u0648\u0646\u06cc"
    ],
    "name:bel_x_preferred":[
        "\u0413\u043e\u043d\u0456"
    ],
    "name:bul_x_preferred":[
        "\u0413\u043e\u043d\u0438"
    ],
    "name:cat_x_preferred":[
        "Goni"
    ],
    "name:ceb_x_preferred":[
        "Goni"
    ],
    "name:ces_x_preferred":[
        "Goni"
    ],
    "name:dan_x_preferred":[
        "Goni"
    ],
    "name:deu_x_preferred":[
        "Goni"
    ],
    "name:epo_x_preferred":[
        "Goni"
    ],
    "name:eus_x_preferred":[
        "Goni"
    ],
    "name:fas_x_preferred":[
        "\u06af\u0648\u0646\u06cc"
    ],
    "name:fin_x_preferred":[
        "Goni"
    ],
    "name:fra_x_preferred":[
        "Goni"
    ],
    "name:hrv_x_preferred":[
        "Goni"
    ],
    "name:hun_x_preferred":[
        "Goni"
    ],
    "name:hye_x_preferred":[
        "\u0533\u0578\u0576\u056b"
    ],
    "name:ind_x_preferred":[
        "Goni"
    ],
    "name:ita_x_preferred":[
        "Goni"
    ],
    "name:jpn_x_preferred":[
        "\u30b4\u30fc\u30cb"
    ],
    "name:kaz_x_preferred":[
        "\u0413\u043e\u043d\u0438"
    ],
    "name:lat_x_preferred":[
        "Goni"
    ],
    "name:lmo_x_preferred":[
        "Goni"
    ],
    "name:msa_x_preferred":[
        "Goni"
    ],
    "name:nap_x_preferred":[
        "Goni"
    ],
    "name:nld_x_preferred":[
        "Goni"
    ],
    "name:nno_x_preferred":[
        "Goni"
    ],
    "name:nor_x_preferred":[
        "Goni"
    ],
    "name:pms_x_preferred":[
        "Goni"
    ],
    "name:pol_x_preferred":[
        "Goni"
    ],
    "name:por_x_preferred":[
        "Goni"
    ],
    "name:ron_x_preferred":[
        "Goni"
    ],
    "name:rus_x_preferred":[
        "\u0413\u043e\u043d\u0438"
    ],
    "name:scn_x_preferred":[
        "Goni"
    ],
    "name:sco_x_preferred":[
        "Goni"
    ],
    "name:spa_x_preferred":[
        "Goni"
    ],
    "name:sqi_x_preferred":[
        "Goni"
    ],
    "name:srd_x_preferred":[
        "Goni"
    ],
    "name:srp_x_preferred":[
        "\u0413\u043e\u043d\u0438"
    ],
    "name:tgl_x_preferred":[
        "Goni"
    ],
    "name:tur_x_preferred":[
        "Goni"
    ],
    "name:ukr_x_preferred":[
        "\u0413\u043e\u043d\u0456"
    ],
    "name:uzb_x_preferred":[
        "Goni"
    ],
    "name:vec_x_preferred":[
        "Goni"
    ],
    "name:vie_x_preferred":[
        "Goni"
    ],
    "name:vol_x_preferred":[
        "Goni"
    ],
    "name:war_x_preferred":[
        "Goni"
    ],
    "wof:name":"Goni",
    "wof:placetype":"locality"
},
  "geometry": {"coordinates":[11.22111,10.16322],"type":"Point"}
}