{
  "type": "Feature",
  "properties": {
    "gn:admin1_code":"37.0",
    "gn:admin2_code":"12013.0",
    "gn:asciiname":"Ovbiebo Camp",
    "gn:country_code":"NG",
    "gn:dem":127,
    "gn:feature_class":"P",
    "gn:feature_code":"PPL",
    "gn:name":"Ovbiebo Camp",
    "gn:population":0,
    "gn:timezone":"Africa/Lagos",
    "iso:country":"NG",
    "name:eng_x_preferred":[
        "Ovbiebo Camp"
    ],
    "wof:name":"Ovbiebo Camp",
    "wof:placetype":"locality"
},
  "geometry": {"coordinates":[6.15106,6.05674],"type":"Point"}
}