{
  "type": "Feature",
  "properties": {
    "gn:admin1_code":"22.0",
    "gn:admin2_code":"9016.0",
    "gn:asciiname":"Emandak",
    "gn:country_code":"NG",
    "gn:dem":146,
    "gn:feature_class":"P",
    "gn:feature_code":"PPL",
    "gn:name":"Emandak",
    "gn:population":0,
    "gn:timezone":"Africa/Lagos",
    "iso:country":"NG",
    "wof:name":"Emandak",
    "wof:placetype":"locality"
},
  "geometry": {"coordinates":[8.66102,6.38845],"type":"Point"}
}