{
  "type": "Feature",
  "properties": {
    "gn:admin1_code":"57.0",
    "gn:admin2_code":"813.0",
    "gn:admin3_code":"81308",
    "gn:asciiname":"Nabubu",
    "gn:country_code":"NG",
    "gn:dem":525,
    "gn:feature_class":"P",
    "gn:feature_code":"PPL",
    "gn:name":"Nabubu",
    "gn:population":0,
    "gn:timezone":"Africa/Lagos",
    "iso:country":"NG",
    "name:und_x_variant":[
        "Unguwar Nabubu",
        "Nabubu"
    ],
    "wof:name":"Nabubu",
    "wof:placetype":"locality"
},
  "geometry": {"coordinates":[6.89143,12.0798],"type":"Point"}
}