{
  "type": "Feature",
  "properties": {
    "gn:admin1_code":"50.0",
    "gn:admin2_code":"33018.0",
    "gn:asciiname":"Kiriam",
    "gn:country_code":"NG",
    "gn:dem":4,
    "gn:feature_class":"P",
    "gn:feature_code":"PPL",
    "gn:name":"Kiriam",
    "gn:population":0,
    "gn:timezone":"Africa/Lagos",
    "iso:country":"NG",
    "wof:name":"Kiriam",
    "wof:placetype":"locality"
},
  "geometry": {"coordinates":[7.11929,4.70356],"type":"Point"}
}