{
  "type": "Feature",
  "properties": {
    "iso:country":"NG",
    "qs:gn_country":"NG",
    "qs:gn_fcode":"PPL",
    "qs:gn_pop":12000,
    "qs:name":"Vom",
    "qs:name_adm0":"Nigeria",
    "qs:name_adm1":"Plateau",
    "qs:photos":0,
    "qs:photos_1k":0,
    "qs:photos_9k":1,
    "qs:photos_9r":1,
    "qs:photos_all":1,
    "qs:photos_sr":0,
    "qs:placetype":"Town",
    "qs:pop_sr":"6",
    "qs:woe_adm0":23424908,
    "wof:name":"Vom",
    "wof:placetype":"locality",
    "wof:population":12000
},
  "geometry": {"coordinates":[8.78333,9.73333],"type":"Point"}
}