{
  "type": "Feature",
  "properties": {
    "gn:admin1_code":"56.0",
    "gn:admin2_code":"26008.0",
    "gn:asciiname":"Akwiya",
    "gn:cc2":"NG",
    "gn:country_code":"NG",
    "gn:dem":159,
    "gn:feature_class":"P",
    "gn:feature_code":"PPL",
    "gn:name":"Akwiya",
    "gn:population":0,
    "gn:timezone":"Africa/Lagos",
    "iso:country":"NG",
    "name:und_x_variant":[
        "Akwia",
        "Akwiya"
    ],
    "wof:name":"Akwiya",
    "wof:placetype":"locality"
},
  "geometry": {"coordinates":[8.41667,8.53333],"type":"Point"}
}