{
  "type": "Feature",
  "properties": {
    "gn:admin1_code":"39.0",
    "gn:admin2_code":"18012.0",
    "gn:admin3_code":"JI0601",
    "gn:asciiname":"Chamo",
    "gn:country_code":"NG",
    "gn:dem":388,
    "gn:feature_class":"P",
    "gn:feature_code":"PPL",
    "gn:name":"Chamo",
    "gn:population":0,
    "gn:timezone":"Africa/Lagos",
    "iso:country":"NG",
    "wof:name":"Chamo",
    "wof:placetype":"locality"
},
  "geometry": {"coordinates":[9.38501,11.97799],"type":"Point"}
}