{
  "type": "Feature",
  "properties": {
    "gn:admin1_code":"21.0",
    "gn:admin2_code":"3020.0",
    "gn:asciiname":"Mbiaso",
    "gn:country_code":"NG",
    "gn:dem":17,
    "gn:feature_class":"P",
    "gn:feature_code":"PPL",
    "gn:name":"Mbiaso",
    "gn:population":0,
    "gn:timezone":"Africa/Lagos",
    "iso:country":"NG",
    "wof:name":"Mbiaso",
    "wof:placetype":"locality"
},
  "geometry": {"coordinates":[7.89739,4.8171],"type":"Point"}
}