{
  "type": "Feature",
  "properties": {
    "gn:admin1_code":"27.0",
    "gn:admin2_code":"112.0",
    "gn:admin3_code":"11203",
    "gn:asciiname":"Wuyaku",
    "gn:country_code":"NG",
    "gn:dem":583,
    "gn:feature_class":"P",
    "gn:feature_code":"PPL",
    "gn:name":"Wuyaku",
    "gn:population":0,
    "gn:timezone":"Africa/Lagos",
    "iso:country":"NG",
    "wof:name":"Wuyaku",
    "wof:placetype":"locality"
},
  "geometry": {"coordinates":[12.10353,10.37735],"type":"Point"}
}