{
  "type": "Feature",
  "properties": {
    "gn:admin1_code":"45.0",
    "gn:admin2_code":"1010.0",
    "gn:asciiname":"Agu-Eze",
    "gn:country_code":"NG",
    "gn:dem":149,
    "gn:feature_class":"P",
    "gn:feature_code":"PPL",
    "gn:name":"Agu-Eze",
    "gn:population":0,
    "gn:timezone":"Africa/Lagos",
    "iso:country":"NG",
    "wof:name":"Agu-Eze",
    "wof:placetype":"locality"
},
  "geometry": {"coordinates":[7.70444,5.71233],"type":"Point"}
}