{
  "type": "Feature",
  "properties": {
    "gn:admin1_code":"37.0",
    "gn:admin2_code":"12018",
    "gn:asciiname":"Uhimento-Uhi",
    "gn:country_code":"NG",
    "gn:dem":230,
    "gn:feature_class":"P",
    "gn:feature_code":"PPL",
    "gn:name":"Uhimento-Uhi",
    "gn:population":0,
    "gn:timezone":"Africa/Lagos",
    "iso:country":"NG",
    "wof:name":"Uhimento-Uhi",
    "wof:placetype":"locality"
},
  "geometry": {"coordinates":[6.01618,6.57012],"type":"Point"}
}