{
  "type": "Feature",
  "properties": {
    "gn:admin1_code":"30.0",
    "gn:admin2_code":"24007.0",
    "gn:asciiname":"Gamo",
    "gn:country_code":"NG",
    "gn:dem":355,
    "gn:feature_class":"P",
    "gn:feature_code":"PPL",
    "gn:name":"Gamo",
    "gn:population":0,
    "gn:timezone":"Africa/Lagos",
    "iso:country":"NG",
    "name:deu_x_preferred":[
        "Gamo"
    ],
    "name:fra_x_preferred":[
        "Gamo"
    ],
    "name:por_x_preferred":[
        "Gamo"
    ],
    "wof:name":"Gamo",
    "wof:placetype":"neighbourhood"
},
  "geometry": {"coordinates":[4.61667,8.41667],"type":"Point"}
}