{
  "type": "Feature",
  "properties": {
    "gn:admin1_code":"55.0",
    "gn:asciiname":"Teli",
    "gn:country_code":"NG",
    "gn:dem":304,
    "gn:feature_class":"P",
    "gn:feature_code":"PPL",
    "gn:name":"Teli",
    "gn:population":0,
    "gn:timezone":"Africa/Lagos",
    "iso:country":"NG",
    "name:ara_x_preferred":[
        "\u062a\u064a\u0644\u064a"
    ],
    "name:ben_x_preferred":[
        "\u09a4\u09c7\u09b2\u09bf"
    ],
    "name:ell_x_preferred":[
        "\u03a4\u03ad\u03bb\u03b9"
    ],
    "name:fas_x_preferred":[
        "\u062a\u0644\u06cc"
    ],
    "name:fra_x_preferred":[
        "Teli"
    ],
    "name:heb_x_preferred":[
        "\u05d8\u05dc\u05d9"
    ],
    "name:hin_x_preferred":[
        "\u0924\u0947\u0932\u0940"
    ],
    "name:ind_x_preferred":[
        "Teli"
    ],
    "name:ita_x_preferred":[
        "Teli"
    ],
    "name:jpn_x_preferred":[
        "\u30c6\u30ea\u30fc"
    ],
    "name:kor_x_preferred":[
        "\ud154\ub9ac"
    ],
    "name:mai_x_preferred":[
        "\u0924\u0947\u0932\u0940"
    ],
    "name:mar_x_preferred":[
        "\u0924\u0947\u0932\u0940"
    ],
    "name:nep_x_preferred":[
        "\u0924\u0947\u0932\u0940"
    ],
    "name:pol_x_preferred":[
        "Teli"
    ],
    "name:por_x_preferred":[
        "Teli"
    ],
    "name:spa_x_preferred":[
        "Teli"
    ],
    "name:swe_x_preferred":[
        "Teli"
    ],
    "name:ukr_x_preferred":[
        "\u0422\u0435\u043b\u0456"
    ],
    "name:urd_x_preferred":[
        "\u0679\u06cc\u0644\u06cc"
    ],
    "name:vie_x_preferred":[
        "Teli"
    ],
    "wof:name":"Teli",
    "wof:placetype":"locality"
},
  "geometry": {"coordinates":[11.70172,10.44336],"type":"Point"}
}