{
  "type": "Feature",
  "properties": {
    "gn:admin1_code":"55.0",
    "gn:asciiname":"Teli",
    "gn:country_code":"NG",
    "gn:dem":304,
    "gn:feature_class":"P",
    "gn:feature_code":"PPL",
    "gn:name":"Teli",
    "gn:population":0,
    "gn:timezone":"Africa/Lagos",
    "iso:country":"NG",
    "name:hin_x_preferred":[
        "\u0924\u0947\u0932\u0940"
    ],
    "name:mai_x_preferred":[
        "\u0924\u0947\u0932\u0940"
    ],
    "name:mar_x_preferred":[
        "\u0924\u0947\u0932\u0940"
    ],
    "name:nep_x_preferred":[
        "\u0924\u0947\u0932\u0940"
    ],
    "wof:name":"Teli",
    "wof:placetype":"locality"
},
  "geometry": {"coordinates":[11.70172,10.44336],"type":"Point"}
}