{
  "type": "Feature",
  "properties": {
    "gn:admin1_code":"21.0",
    "gn:admin2_code":"3010.0",
    "gn:asciiname":"Inwun-Use",
    "gn:country_code":"NG",
    "gn:dem":78,
    "gn:feature_class":"P",
    "gn:feature_code":"PPL",
    "gn:name":"Inwun-Use",
    "gn:population":0,
    "gn:timezone":"Africa/Lagos",
    "iso:country":"NG",
    "name:und_x_variant":[
        "Inwun Llse",
        "Inwun-Use"
    ],
    "wof:name":"Inwun-Use",
    "wof:placetype":"locality"
},
  "geometry": {"coordinates":[7.81758,5.30813],"type":"Point"}
}