{
  "type": "Feature",
  "properties": {
    "gn:admin1_code":"39.0",
    "gn:admin2_code":"18024.0",
    "gn:admin3_code":"JI0804",
    "gn:asciiname":"Dorai",
    "gn:country_code":"NG",
    "gn:dem":401,
    "gn:feature_class":"P",
    "gn:feature_code":"PPL",
    "gn:name":"Dorai",
    "gn:population":0,
    "gn:timezone":"Africa/Lagos",
    "iso:country":"NG",
    "wof:name":"Dorai",
    "wof:placetype":"locality"
},
  "geometry": {"coordinates":[8.86756,12.41418],"type":"Point"}
}