{
  "type": "Feature",
  "properties": {
    "gn:admin1_code":"31.0",
    "gn:admin2_code":"27020.0",
    "gn:asciiname":"Lelemu",
    "gn:country_code":"NG",
    "gn:dem":133,
    "gn:feature_class":"P",
    "gn:feature_code":"PPL",
    "gn:name":"Lelemu",
    "gn:population":0,
    "gn:timezone":"Africa/Lagos",
    "iso:country":"NG",
    "wof:name":"Lelemu",
    "wof:placetype":"locality"
},
  "geometry": {"coordinates":[6.14324,9.83262],"type":"Point"}
}