{
  "type": "Feature",
  "properties": {
    "gn:admin1_code":"44.0",
    "gn:admin2_code":"706.0",
    "gn:admin3_code":"70613",
    "gn:asciiname":"Garu Kime",
    "gn:country_code":"NG",
    "gn:dem":332,
    "gn:feature_class":"P",
    "gn:feature_code":"PPL",
    "gn:name":"Garu Kime",
    "gn:population":0,
    "gn:timezone":"Africa/Lagos",
    "iso:country":"NG",
    "wof:name":"Garu Kime",
    "wof:placetype":"locality"
},
  "geometry": {"coordinates":[12.0164,12.86061],"type":"Point"}
}