{
  "type": "Feature",
  "properties": {
    "gn:admin1_code":"23.0",
    "gn:admin2_code":"19003.0",
    "gn:admin3_code":"KD0305",
    "gn:asciiname":"Ungwan Kaura",
    "gn:country_code":"NG",
    "gn:dem":681,
    "gn:feature_class":"P",
    "gn:feature_code":"PPL",
    "gn:name":"Ungwan Kaura",
    "gn:population":0,
    "gn:timezone":"Africa/Lagos",
    "iso:country":"NG",
    "name:und_x_variant":[
        "Angwan Kaura",
        "Ungwan Kaura"
    ],
    "wof:name":"Ungwan Kaura",
    "wof:placetype":"locality"
},
  "geometry": {"coordinates":[7.10055,11.15045],"type":"Point"}
}