{
  "type": "Feature",
  "properties": {
    "gn:admin1_code":"21.0",
    "gn:admin2_code":"3010.0",
    "gn:asciiname":"Itu Ndem",
    "gn:country_code":"NG",
    "gn:dem":94,
    "gn:feature_class":"P",
    "gn:feature_code":"PPL",
    "gn:name":"Itu Ndem",
    "gn:population":0,
    "gn:timezone":"Africa/Lagos",
    "iso:country":"NG",
    "wof:name":"Itu Ndem",
    "wof:placetype":"locality"
},
  "geometry": {"coordinates":[7.85194,5.19451],"type":"Point"}
}