{
  "type": "Feature",
  "properties": {
    "gn:admin1_code":"27.0",
    "gn:admin2_code":"103",
    "gn:admin3_code":"10312",
    "gn:asciiname":"Dalagambori",
    "gn:country_code":"NG",
    "gn:dem":316,
    "gn:feature_class":"P",
    "gn:feature_code":"PPL",
    "gn:name":"Dalagambori",
    "gn:population":0,
    "gn:timezone":"Africa/Lagos",
    "iso:country":"NG",
    "wof:name":"Dalagambori",
    "wof:placetype":"locality"
},
  "geometry": {"coordinates":[13.88251,11.39921],"type":"Point"}
}