{
  "type": "Feature",
  "properties": {
    "gn:admin1_code":"26.0",
    "gn:admin2_code":"7002",
    "gn:asciiname":"Kpar",
    "gn:country_code":"NG",
    "gn:dem":71,
    "gn:feature_class":"P",
    "gn:feature_code":"PPL",
    "gn:name":"Kpar",
    "gn:population":0,
    "gn:timezone":"Africa/Lagos",
    "iso:country":"NG",
    "wof:name":"Kpar",
    "wof:placetype":"locality"
},
  "geometry": {"coordinates":[8.14718,7.83143],"type":"Point"}
}