{
  "type": "Feature",
  "properties": {
    "gn:admin1_code":"51.0",
    "gn:admin2_code":"619.0",
    "gn:admin3_code":"61906",
    "gn:asciiname":"Kuradina",
    "gn:country_code":"NG",
    "gn:dem":268,
    "gn:feature_class":"P",
    "gn:feature_code":"PPL",
    "gn:name":"Kuradina",
    "gn:population":0,
    "gn:timezone":"Africa/Lagos",
    "iso:country":"NG",
    "wof:name":"Kuradina",
    "wof:placetype":"locality"
},
  "geometry": {"coordinates":[4.90552,13.73409],"type":"Point"}
}