{
  "type": "Feature",
  "properties": {
    "gn:admin1_code":"51.0",
    "gn:admin2_code":"613.0",
    "gn:admin3_code":"61310",
    "gn:asciiname":"Geyu",
    "gn:country_code":"NG",
    "gn:dem":285,
    "gn:feature_class":"P",
    "gn:feature_code":"PPL",
    "gn:name":"Geyu",
    "gn:population":0,
    "gn:timezone":"Africa/Lagos",
    "iso:country":"NG",
    "name:und_x_variant":[
        "Gyaya",
        "Geyu"
    ],
    "wof:name":"Geyu",
    "wof:placetype":"locality"
},
  "geometry": {"coordinates":[5.92104,13.56272],"type":"Point"}
}