{
  "type": "Feature",
  "properties": {
    "gn:admin1_code":"53.0",
    "gn:admin2_code":"11007",
    "gn:asciiname":"Obuagu-Ohatekwe",
    "gn:country_code":"NG",
    "gn:dem":50,
    "gn:feature_class":"P",
    "gn:feature_code":"PPL",
    "gn:name":"Obuagu-Ohatekwe",
    "gn:population":0,
    "gn:timezone":"Africa/Lagos",
    "iso:country":"NG",
    "wof:name":"Obuagu-Ohatekwe",
    "wof:placetype":"locality"
},
  "geometry": {"coordinates":[8.13995,6.06617],"type":"Point"}
}