{
  "type": "Feature",
  "properties": {
    "gn:admin1_code":"40.0",
    "gn:admin2_code":"508.0",
    "gn:admin3_code":"50808",
    "gn:asciiname":"Godebe",
    "gn:country_code":"NG",
    "gn:dem":201,
    "gn:feature_class":"P",
    "gn:feature_code":"PPL",
    "gn:name":"Godebe",
    "gn:population":0,
    "gn:timezone":"Africa/Lagos",
    "iso:country":"NG",
    "wof:name":"Godebe",
    "wof:placetype":"locality"
},
  "geometry": {"coordinates":[3.88524,11.88267],"type":"Point"}
}