{
  "type": "Feature",
  "properties": {
    "gn:admin1_code":"54.0",
    "gn:admin2_code":"13007.0",
    "gn:asciiname":"Aisegba",
    "gn:country_code":"NG",
    "gn:dem":403,
    "gn:feature_class":"P",
    "gn:feature_code":"PPL",
    "gn:name":"Aisegba",
    "gn:population":0,
    "gn:timezone":"Africa/Lagos",
    "iso:country":"NG",
    "wof:name":"Aisegba",
    "wof:placetype":"locality"
},
  "geometry": {"coordinates":[5.4785,7.6055],"type":"Point"}
}