{
  "type": "Feature",
  "properties": {
    "gn:admin1_code":"35.0",
    "gn:admin2_code":"2008.0",
    "gn:asciiname":"Sabon Layi",
    "gn:country_code":"NG",
    "gn:dem":532,
    "gn:feature_class":"P",
    "gn:feature_code":"PPL",
    "gn:name":"Sabon Layi",
    "gn:population":0,
    "gn:timezone":"Africa/Lagos",
    "iso:country":"NG",
    "wof:name":"Sabon Layi",
    "wof:placetype":"locality"
},
  "geometry": {"coordinates":[12.03333,8.48333],"type":"Point"}
}