{
  "type": "Feature",
  "properties": {
    "gn:admin1_code":"51.0",
    "gn:admin2_code":"623.0",
    "gn:admin3_code":"62302",
    "gn:asciiname":"Baware",
    "gn:country_code":"NG",
    "gn:dem":276,
    "gn:feature_class":"P",
    "gn:feature_code":"PPL",
    "gn:name":"Baware",
    "gn:population":0,
    "gn:timezone":"Africa/Lagos",
    "iso:country":"NG",
    "wof:name":"Baware",
    "wof:placetype":"locality"
},
  "geometry": {"coordinates":[4.96667,12.71141],"type":"Point"}
}