{
  "type": "Feature",
  "properties": {
    "gn:admin1_code":"23.0",
    "gn:admin2_code":"19011.0",
    "gn:admin3_code":"KD1104",
    "gn:asciiname":"Jere",
    "gn:country_code":"NG",
    "gn:dem":561,
    "gn:feature_class":"P",
    "gn:feature_code":"PPL",
    "gn:name":"Jere",
    "gn:population":0,
    "gn:timezone":"Africa/Lagos",
    "iso:country":"NG",
    "name:ceb_x_preferred":[
        "Jere"
    ],
    "name:swe_x_preferred":[
        "Jere"
    ],
    "name:und_x_variant":[
        "Jiri"
    ],
    "wof:name":"Jere",
    "wof:placetype":"locality"
},
  "geometry": {"coordinates":[7.43501,9.56892],"type":"Point"}
}