{
  "type": "Feature",
  "properties": {
    "gn:admin1_code":"39.0",
    "gn:admin2_code":"18001.0",
    "gn:admin3_code":"JI1603",
    "gn:asciiname":"Sharkawa",
    "gn:country_code":"NG",
    "gn:dem":366,
    "gn:feature_class":"P",
    "gn:feature_code":"PPL",
    "gn:name":"Sharkawa",
    "gn:population":0,
    "gn:timezone":"Africa/Lagos",
    "iso:country":"NG",
    "wof:name":"Sharkawa",
    "wof:placetype":"locality"
},
  "geometry": {"coordinates":[9.70953,12.37641],"type":"Point"}
}