{
  "type": "Feature",
  "properties": {
    "gn:admin1_code":"48.0",
    "gn:admin2_code":"29001.0",
    "gn:asciiname":"Ishe",
    "gn:country_code":"NG",
    "gn:dem":316,
    "gn:feature_class":"P",
    "gn:feature_code":"PPL",
    "gn:name":"Ishe",
    "gn:population":0,
    "gn:timezone":"Africa/Lagos",
    "iso:country":"NG",
    "name:und_x_variant":[
        "Nse",
        "Ishe"
    ],
    "wof:name":"Ishe",
    "wof:placetype":"locality"
},
  "geometry": {"coordinates":[5.91745,7.51174],"type":"Point"}
}