{
  "type": "Feature",
  "properties": {
    "gn:admin1_code":"39.0",
    "gn:admin2_code":"18021.0",
    "gn:admin3_code":"JI0401",
    "gn:asciiname":"Kwaga",
    "gn:country_code":"NG",
    "gn:dem":355,
    "gn:feature_class":"P",
    "gn:feature_code":"PPL",
    "gn:name":"Kwaga",
    "gn:population":0,
    "gn:timezone":"Africa/Lagos",
    "iso:country":"NG",
    "wof:name":"Kwaga",
    "wof:placetype":"locality"
},
  "geometry": {"coordinates":[10.01616,12.81383],"type":"Point"}
}