{
  "type": "Feature",
  "properties": {
    "gn:admin1_code":"47.0",
    "gn:admin2_code":"14001.0",
    "gn:asciiname":"Amaogudu",
    "gn:country_code":"NG",
    "gn:dem":56,
    "gn:feature_class":"P",
    "gn:feature_code":"PPL",
    "gn:name":"Amaogudu",
    "gn:population":0,
    "gn:timezone":"Africa/Lagos",
    "iso:country":"NG",
    "wof:name":"Amaogudu",
    "wof:placetype":"locality"
},
  "geometry": {"coordinates":[7.67272,5.94574],"type":"Point"}
}