{
  "type": "Feature",
  "properties": {
    "gn:admin1_code":"48.0",
    "gn:admin2_code":"29011.0",
    "gn:asciiname":"Oluwasola",
    "gn:cc2":"NG",
    "gn:country_code":"NG",
    "gn:dem":261,
    "gn:feature_class":"P",
    "gn:feature_code":"PPL",
    "gn:name":"Oluwasola",
    "gn:population":0,
    "gn:timezone":"Africa/Lagos",
    "iso:country":"NG",
    "name:und_x_variant":[
        "Luwasoli",
        "Oluwasola"
    ],
    "wof:name":"Oluwasola",
    "wof:placetype":"locality"
},
  "geometry": {"coordinates":[4.83333,7.33333],"type":"Point"}
}