{
  "type": "Feature",
  "properties": {
    "gn:admin1_code":"42.0",
    "gn:admin2_code":"30010.0",
    "gn:asciiname":"Ilegun",
    "gn:country_code":"NG",
    "gn:dem":321,
    "gn:feature_class":"P",
    "gn:feature_code":"PPL",
    "gn:name":"Ilegun",
    "gn:population":0,
    "gn:timezone":"Africa/Lagos",
    "iso:country":"NG",
    "wof:name":"Ilegun",
    "wof:placetype":"locality"
},
  "geometry": {"coordinates":[4.31667,7.81667],"type":"Point"}
}