{
  "type": "Feature",
  "properties": {
    "gn:admin1_code":"47.0",
    "gn:admin2_code":"14015.0",
    "gn:asciiname":"Akpoga-Ndiagu",
    "gn:country_code":"NG",
    "gn:dem":217,
    "gn:feature_class":"P",
    "gn:feature_code":"PPL",
    "gn:name":"Akpoga-Ndiagu",
    "gn:population":0,
    "gn:timezone":"Africa/Lagos",
    "iso:country":"NG",
    "wof:name":"Akpoga-Ndiagu",
    "wof:placetype":"locality"
},
  "geometry": {"coordinates":[7.61131,6.82152],"type":"Point"}
}