{
  "type": "Feature",
  "properties": {
    "gn:admin1_code":"40.0",
    "gn:admin2_code":"509.0",
    "gn:admin3_code":"50902",
    "gn:asciiname":"Tugan Suya",
    "gn:country_code":"NG",
    "gn:dem":211,
    "gn:feature_class":"P",
    "gn:feature_code":"PPL",
    "gn:name":"Tugan Suya",
    "gn:population":0,
    "gn:timezone":"Africa/Lagos",
    "iso:country":"NG",
    "wof:name":"Tugan Suya",
    "wof:placetype":"locality"
},
  "geometry": {"coordinates":[4.66625,11.64542],"type":"Point"}
}