{
  "type": "Feature",
  "properties": {
    "gn:admin1_code":"35.0",
    "gn:admin2_code":"2013",
    "gn:asciiname":"Gadan Dilachin",
    "gn:country_code":"NG",
    "gn:dem":480,
    "gn:feature_class":"P",
    "gn:feature_code":"PPL",
    "gn:name":"Gadan Dilachin",
    "gn:population":0,
    "gn:timezone":"Africa/Lagos",
    "iso:country":"NG",
    "name:eng_x_preferred":[
        "Gadan Dilachin"
    ],
    "wof:name":"Gadan Dilachin",
    "wof:placetype":"locality"
},
  "geometry": {"coordinates":[13.29807,10.54196],"type":"Point"}
}