{
  "type": "Feature",
  "properties": {
    "gn:admin1_code":"16.0",
    "gn:admin2_code":"28007.0",
    "gn:asciiname":"Gbokolu",
    "gn:country_code":"NG",
    "gn:dem":71,
    "gn:feature_class":"P",
    "gn:feature_code":"PPL",
    "gn:name":"Gbokolu",
    "gn:population":0,
    "gn:timezone":"Africa/Lagos",
    "iso:country":"NG",
    "wof:name":"Gbokolu",
    "wof:placetype":"locality"
},
  "geometry": {"coordinates":[3.06667,6.86667],"type":"Point"}
}