{
  "type": "Feature",
  "properties": {
    "gn:admin1_code":"24.0",
    "gn:admin2_code":"426.0",
    "gn:admin3_code":"42611",
    "gn:asciiname":"Nbuku",
    "gn:country_code":"NG",
    "gn:dem":477,
    "gn:feature_class":"P",
    "gn:feature_code":"PPL",
    "gn:name":"Nbuku",
    "gn:population":0,
    "gn:timezone":"Africa/Lagos",
    "iso:country":"NG",
    "wof:name":"Nbuku",
    "wof:placetype":"locality"
},
  "geometry": {"coordinates":[7.836,12.99597],"type":"Point"}
}