{
  "type": "Feature",
  "properties": {
    "gn:admin1_code":"32.0",
    "gn:admin2_code":"31026.0",
    "gn:asciiname":"Araromi Aperin",
    "gn:cc2":"NG",
    "gn:country_code":"NG",
    "gn:dem":128,
    "gn:feature_class":"P",
    "gn:feature_code":"PPL",
    "gn:name":"Araromi Aperin",
    "gn:population":0,
    "gn:timezone":"Africa/Lagos",
    "iso:country":"NG",
    "name:und_x_variant":[
        "Araromi",
        "Araromi Aperin"
    ],
    "wof:name":"Araromi Aperin",
    "wof:placetype":"locality"
},
  "geometry": {"coordinates":[4.03333,7.16667],"type":"Point"}
}