{
  "type": "Feature",
  "properties": {
    "gn:admin1_code":"27.0",
    "gn:admin2_code":"111",
    "gn:admin3_code":"11109",
    "gn:asciiname":"Kusha Kucha Clan",
    "gn:country_code":"NG",
    "gn:dem":371,
    "gn:feature_class":"P",
    "gn:feature_code":"PPLL",
    "gn:name":"Kusha Kucha Clan",
    "gn:population":0,
    "gn:timezone":"Africa/Lagos",
    "iso:country":"NG",
    "wof:name":"Kusha Kucha Clan",
    "wof:placetype":"locality"
},
  "geometry": {"coordinates":[13.89468,11.22425],"type":"Point"}
}