{
  "type": "Feature",
  "properties": {
    "gn:admin1_code":"27.0",
    "gn:admin2_code":"110.0",
    "gn:admin3_code":"11005",
    "gn:asciiname":"Kingarwa",
    "gn:country_code":"NG",
    "gn:dem":295,
    "gn:feature_class":"P",
    "gn:feature_code":"PPL",
    "gn:name":"Kingarwa",
    "gn:population":0,
    "gn:timezone":"Africa/Lagos",
    "iso:country":"NG",
    "wof:name":"Kingarwa",
    "wof:placetype":"locality"
},
  "geometry": {"coordinates":[13.36967,12.66013],"type":"Point"}
}