{
  "type": "Feature",
  "properties": {
    "gn:admin1_code":"39.0",
    "gn:admin2_code":"18015.0",
    "gn:admin3_code":"JI2401",
    "gn:asciiname":"Amaryawa",
    "gn:country_code":"NG",
    "gn:dem":506,
    "gn:feature_class":"P",
    "gn:feature_code":"PPL",
    "gn:name":"Amaryawa",
    "gn:population":0,
    "gn:timezone":"Africa/Lagos",
    "iso:country":"NG",
    "wof:name":"Amaryawa",
    "wof:placetype":"locality"
},
  "geometry": {"coordinates":[8.35116,12.56505],"type":"Point"}
}