{
  "type": "Feature",
  "properties": {
    "gn:admin1_code":"22.0",
    "gn:admin2_code":"9012.0",
    "gn:asciiname":"Bayaluga",
    "gn:country_code":"NG",
    "gn:dem":294,
    "gn:feature_class":"P",
    "gn:feature_code":"PPL",
    "gn:name":"Bayaluga",
    "gn:population":0,
    "gn:timezone":"Africa/Lagos",
    "iso:country":"NG",
    "name:und_x_variant":[
        "Bebi",
        "Bayaluga"
    ],
    "wof:name":"Bayaluga",
    "wof:placetype":"locality"
},
  "geometry": {"coordinates":[9.30888,6.61674],"type":"Point"}
}