{
  "type": "Feature",
  "properties": {
    "gn:admin1_code":"35.0",
    "gn:admin2_code":"2016.0",
    "gn:asciiname":"Bolki",
    "gn:country_code":"NG",
    "gn:dem":141,
    "gn:feature_class":"P",
    "gn:feature_code":"PPL",
    "gn:name":"Bolki",
    "gn:population":0,
    "gn:timezone":"Africa/Lagos",
    "iso:country":"NG",
    "name:eng_x_preferred":[
        "Bolki"
    ],
    "wof:name":"Bolki",
    "wof:placetype":"locality"
},
  "geometry": {"coordinates":[11.62305,9.38213],"type":"Point"}
}