{
  "type": "Feature",
  "properties": {
    "gn:admin1_code":"26.0",
    "gn:admin2_code":"7005",
    "gn:asciiname":"Anya",
    "gn:country_code":"NG",
    "gn:dem":156,
    "gn:feature_class":"P",
    "gn:feature_code":"PPL",
    "gn:name":"Anya",
    "gn:population":0,
    "gn:timezone":"Africa/Lagos",
    "iso:country":"NG",
    "name:bre_x_preferred":[
        "Anya"
    ],
    "name:ell_x_preferred":[
        "\u0386\u03bd\u03c5\u03b1"
    ],
    "name:fra_x_preferred":[
        "Anya"
    ],
    "name:jpn_x_preferred":[
        "\u30a2\u30fc\u30cb\u30e3"
    ],
    "name:srp_x_preferred":[
        "\u0410\u045a\u0430"
    ],
    "wof:name":"Anya",
    "wof:placetype":"locality"
},
  "geometry": {"coordinates":[8.81383,7.26871],"type":"Point"}
}