{
  "type": "Feature",
  "properties": {
    "gn:admin1_code":"57.0",
    "gn:admin2_code":"808.0",
    "gn:admin3_code":"80802",
    "gn:asciiname":"Gagere",
    "gn:country_code":"NG",
    "gn:dem":408,
    "gn:feature_class":"P",
    "gn:feature_code":"PPL",
    "gn:name":"Gagere",
    "gn:population":0,
    "gn:timezone":"Africa/Lagos",
    "iso:country":"NG",
    "name:und_x_variant":[
        "Unguwar Gagere",
        "Gagere"
    ],
    "wof:name":"Gagere",
    "wof:placetype":"locality"
},
  "geometry": {"coordinates":[6.77493,12.37018],"type":"Point"}
}