{
  "type": "Feature",
  "properties": {
    "gn:admin1_code":"23.0",
    "gn:admin2_code":"19004.0",
    "gn:admin3_code":"KD0404",
    "gn:asciiname":"Likora",
    "gn:country_code":"NG",
    "gn:dem":607,
    "gn:feature_class":"P",
    "gn:feature_code":"PPL",
    "gn:name":"Likora",
    "gn:population":0,
    "gn:timezone":"Africa/Lagos",
    "iso:country":"NG",
    "wof:name":"Likora",
    "wof:placetype":"locality"
},
  "geometry": {"coordinates":[7.64478,10.61276],"type":"Point"}
}