{
  "type": "Feature",
  "properties": {
    "gn:admin1_code":"26.0",
    "gn:admin2_code":"7008",
    "gn:asciiname":"Akwaga",
    "gn:country_code":"NG",
    "gn:dem":93,
    "gn:feature_class":"P",
    "gn:feature_code":"PPL",
    "gn:name":"Akwaga",
    "gn:population":0,
    "gn:timezone":"Africa/Lagos",
    "iso:country":"NG",
    "wof:name":"Akwaga",
    "wof:placetype":"locality"
},
  "geometry": {"coordinates":[8.30512,7.61892],"type":"Point"}
}