{
  "type": "Feature",
  "properties": {
    "gn:admin1_code":"26.0",
    "gn:admin2_code":"7005",
    "gn:asciiname":"Uanigo",
    "gn:country_code":"NG",
    "gn:dem":213,
    "gn:feature_class":"P",
    "gn:feature_code":"PPL",
    "gn:name":"Uanigo",
    "gn:population":0,
    "gn:timezone":"Africa/Lagos",
    "iso:country":"NG",
    "wof:name":"Uanigo",
    "wof:placetype":"locality"
},
  "geometry": {"coordinates":[8.93182,7.32756],"type":"Point"}
}