{
  "type": "Feature",
  "properties": {
    "gn:admin1_code":"31.0",
    "gn:admin2_code":"27005",
    "gn:asciiname":"Yatayi",
    "gn:country_code":"NG",
    "gn:dem":271,
    "gn:feature_class":"P",
    "gn:feature_code":"PPL",
    "gn:name":"Yatayi",
    "gn:population":0,
    "gn:timezone":"Africa/Lagos",
    "iso:country":"NG",
    "wof:name":"Yatayi",
    "wof:placetype":"locality"
},
  "geometry": {"coordinates":[6.50638,9.6486],"type":"Point"}
}