{
  "type": "Feature",
  "properties": {
    "gn:admin1_code":"27.0",
    "gn:admin2_code":"117",
    "gn:admin3_code":"11708",
    "gn:asciiname":"Mile Ninety",
    "gn:country_code":"NG",
    "gn:dem":291,
    "gn:feature_class":"P",
    "gn:feature_code":"PPL",
    "gn:name":"Mile Ninety",
    "gn:population":0,
    "gn:timezone":"Africa/Lagos",
    "iso:country":"NG",
    "wof:name":"Mile Ninety",
    "wof:placetype":"locality"
},
  "geometry": {"coordinates":[13.66366,12.77737],"type":"Point"}
}