{
  "type": "Feature",
  "properties": {
    "gn:admin1_code":"43.0",
    "gn:admin2_code":"35002.0",
    "gn:asciiname":"Wuro Jatau",
    "gn:country_code":"NG",
    "gn:dem":283,
    "gn:feature_class":"P",
    "gn:feature_code":"PPL",
    "gn:name":"Wuro Jatau",
    "gn:population":0,
    "gn:timezone":"Africa/Lagos",
    "iso:country":"NG",
    "wof:name":"Wuro Jatau",
    "wof:placetype":"locality"
},
  "geometry": {"coordinates":[11.23333,8.33333],"type":"Point"}
}