{
  "type": "Feature",
  "properties": {
    "gn:admin1_code":"51.0",
    "gn:admin2_code":"601.0",
    "gn:admin3_code":"60104",
    "gn:asciiname":"Iname",
    "gn:country_code":"NG",
    "gn:dem":260,
    "gn:feature_class":"P",
    "gn:feature_code":"PPL",
    "gn:name":"Iname",
    "gn:population":0,
    "gn:timezone":"Africa/Lagos",
    "iso:country":"NG",
    "wof:name":"Iname",
    "wof:placetype":"locality"
},
  "geometry": {"coordinates":[4.96349,13.19682],"type":"Point"}
}