{
  "type": "Feature",
  "properties": {
    "gn:admin1_code":"31.0",
    "gn:admin2_code":"27014.0",
    "gn:asciiname":"Gwagwade",
    "gn:country_code":"NG",
    "gn:dem":249,
    "gn:feature_class":"P",
    "gn:feature_code":"PPL",
    "gn:name":"Gwagwade",
    "gn:population":0,
    "gn:timezone":"Africa/Lagos",
    "iso:country":"NG",
    "wof:name":"Gwagwade",
    "wof:placetype":"locality"
},
  "geometry": {"coordinates":[4.93333,10.46667],"type":"Point"}
}