{
  "type": "Feature",
  "properties": {
    "gn:admin1_code":"40.0",
    "gn:admin2_code":"506.0",
    "gn:admin3_code":"50609",
    "gn:asciiname":"Ungwan Sani",
    "gn:country_code":"NG",
    "gn:dem":198,
    "gn:feature_class":"P",
    "gn:feature_code":"PPL",
    "gn:name":"Ungwan Sani",
    "gn:population":0,
    "gn:timezone":"Africa/Lagos",
    "iso:country":"NG",
    "wof:name":"Ungwan Sani",
    "wof:placetype":"locality"
},
  "geometry": {"coordinates":[4.10755,12.50405],"type":"Point"}
}