{
  "type": "Feature",
  "properties": {
    "gn:admin1_code":"31.0",
    "gn:admin2_code":"27017",
    "gn:asciiname":"Kpacita",
    "gn:country_code":"NG",
    "gn:dem":90,
    "gn:feature_class":"P",
    "gn:feature_code":"PPL",
    "gn:name":"Kpacita",
    "gn:population":0,
    "gn:timezone":"Africa/Lagos",
    "iso:country":"NG",
    "wof:name":"Kpacita",
    "wof:placetype":"locality"
},
  "geometry": {"coordinates":[5.85419,9.34485],"type":"Point"}
}