{
  "type": "Feature",
  "properties": {
    "gn:admin1_code":"37.0",
    "gn:admin2_code":"12013.0",
    "gn:asciiname":"Hwohwokpa Camp",
    "gn:country_code":"NG",
    "gn:dem":74,
    "gn:feature_class":"P",
    "gn:feature_code":"PPL",
    "gn:name":"Hwohwokpa Camp",
    "gn:population":0,
    "gn:timezone":"Africa/Lagos",
    "iso:country":"NG",
    "name:eng_x_preferred":[
        "Hwohwokpa Camp"
    ],
    "wof:name":"Hwohwokpa Camp",
    "wof:placetype":"locality"
},
  "geometry": {"coordinates":[6.10932,6.35458],"type":"Point"}
}