{
  "type": "Feature",
  "properties": {
    "gn:admin1_code":"49.0",
    "gn:admin2_code":"32016.0",
    "gn:asciiname":"Agidi",
    "gn:country_code":"NG",
    "gn:dem":126,
    "gn:feature_class":"P",
    "gn:feature_code":"PPL",
    "gn:name":"Agidi",
    "gn:population":0,
    "gn:timezone":"Africa/Lagos",
    "iso:country":"NG",
    "wof:name":"Agidi",
    "wof:placetype":"locality"
},
  "geometry": {"coordinates":[9.69476,8.43884],"type":"Point"}
}