{
  "type": "Feature",
  "properties": {
    "gn:admin1_code":"27.0",
    "gn:admin2_code":"116.0",
    "gn:admin3_code":"11606",
    "gn:asciiname":"Auno",
    "gn:country_code":"NG",
    "gn:dem":338,
    "gn:feature_class":"P",
    "gn:feature_code":"PPL",
    "gn:name":"Auno",
    "gn:population":0,
    "gn:timezone":"Africa/Lagos",
    "iso:country":"NG",
    "wof:name":"Auno",
    "wof:placetype":"locality"
},
  "geometry": {"coordinates":[12.9359,11.84685],"type":"Point"}
}