{
  "type": "Feature",
  "properties": {
    "gn:admin1_code":"51.0",
    "gn:admin2_code":"621.0",
    "gn:admin3_code":"62104",
    "gn:asciiname":"Bakin Gulbe",
    "gn:country_code":"NG",
    "gn:dem":246,
    "gn:feature_class":"P",
    "gn:feature_code":"PPL",
    "gn:name":"Bakin Gulbe",
    "gn:population":0,
    "gn:timezone":"Africa/Lagos",
    "iso:country":"NG",
    "wof:name":"Bakin Gulbe",
    "wof:placetype":"locality"
},
  "geometry": {"coordinates":[5.21633,13.10333],"type":"Point"}
}