{
  "type": "Feature",
  "properties": {
    "gn:admin1_code":"23.0",
    "gn:admin2_code":"19007",
    "gn:admin3_code":"KD0706",
    "gn:asciiname":"Gada",
    "gn:country_code":"NG",
    "gn:dem":510,
    "gn:feature_class":"P",
    "gn:feature_code":"PPL",
    "gn:name":"Gada",
    "gn:population":0,
    "gn:timezone":"Africa/Lagos",
    "iso:country":"NG",
    "name:ceb_x_preferred":[
        "Gada"
    ],
    "name:deu_x_preferred":[
        "Gada"
    ],
    "name:heb_x_preferred":[
        "\u05d2\u05d3\u05d4"
    ],
    "name:swe_x_preferred":[
        "Gada"
    ],
    "name:ukr_x_preferred":[
        "\u0413\u0430\u0434\u0430"
    ],
    "wof:name":"Gada",
    "wof:placetype":"locality"
},
  "geometry": {"coordinates":[8.28059,9.36542],"type":"Point"}
}