{
  "type": "Feature",
  "properties": {
    "gn:admin1_code":"51.0",
    "gn:admin2_code":"604.0",
    "gn:admin3_code":"60411",
    "gn:asciiname":"Kiri",
    "gn:country_code":"NG",
    "gn:dem":300,
    "gn:feature_class":"P",
    "gn:feature_code":"PPL",
    "gn:name":"Kiri",
    "gn:population":0,
    "gn:timezone":"Africa/Lagos",
    "iso:country":"NG",
    "wof:name":"Kiri",
    "wof:placetype":"locality"
},
  "geometry": {"coordinates":[5.56689,13.58286],"type":"Point"}
}