{
  "type": "Feature",
  "properties": {
    "gn:admin1_code":"28.0",
    "gn:admin2_code":"17009.0",
    "gn:asciiname":"Okohia",
    "gn:country_code":"NG",
    "gn:dem":165,
    "gn:feature_class":"P",
    "gn:feature_code":"PPL",
    "gn:name":"Okohia",
    "gn:population":0,
    "gn:timezone":"Africa/Lagos",
    "iso:country":"NG",
    "wof:name":"Okohia",
    "wof:placetype":"locality"
},
  "geometry": {"coordinates":[7.20317,5.68692],"type":"Point"}
}