{
  "type": "Feature",
  "properties": {
    "gn:admin1_code":"39.0",
    "gn:admin2_code":"18004.0",
    "gn:admin3_code":"JI0204",
    "gn:asciiname":"Gutsula",
    "gn:country_code":"NG",
    "gn:dem":398,
    "gn:feature_class":"P",
    "gn:feature_code":"PPL",
    "gn:name":"Gutsula",
    "gn:population":0,
    "gn:timezone":"Africa/Lagos",
    "iso:country":"NG",
    "wof:name":"Gutsula",
    "wof:placetype":"locality"
},
  "geometry": {"coordinates":[8.79846,12.584],"type":"Point"}
}