{
  "type": "Feature",
  "properties": {
    "gn:admin1_code":"24.0",
    "gn:admin2_code":"434.0",
    "gn:admin3_code":"43403",
    "gn:asciiname":"Garaba Ganna",
    "gn:country_code":"NG",
    "gn:dem":435,
    "gn:feature_class":"P",
    "gn:feature_code":"PPL",
    "gn:name":"Garaba Ganna",
    "gn:population":0,
    "gn:timezone":"Africa/Lagos",
    "iso:country":"NG",
    "name:und_x_variant":[
        "Garaba",
        "Garaba Ganna"
    ],
    "wof:name":"Garaba Ganna",
    "wof:placetype":"locality"
},
  "geometry": {"coordinates":[8.58495,12.92951],"type":"Point"}
}