{
  "type": "Feature",
  "properties": {
    "gn:admin1_code":"40.0",
    "gn:admin2_code":"502.0",
    "gn:admin3_code":"50203",
    "gn:asciiname":"Bui",
    "gn:country_code":"NG",
    "gn:dem":214,
    "gn:feature_class":"P",
    "gn:feature_code":"PPL",
    "gn:name":"Bui",
    "gn:population":0,
    "gn:timezone":"Africa/Lagos",
    "iso:country":"NG",
    "name:ceb_x_preferred":[
        "Bui"
    ],
    "name:swe_x_preferred":[
        "Bui"
    ],
    "name:und_x_variant":[
        "Bwi"
    ],
    "wof:name":"Bui",
    "wof:placetype":"locality"
},
  "geometry": {"coordinates":[4.1167,12.72823],"type":"Point"}
}