{
  "type": "Feature",
  "properties": {
    "gn:admin1_code":"32.0",
    "gn:admin2_code":"31019.0",
    "gn:asciiname":"Isemi Ile",
    "gn:cc2":"NG",
    "gn:country_code":"NG",
    "gn:dem":353,
    "gn:feature_class":"P",
    "gn:feature_code":"PPL",
    "gn:name":"Isemi Ile",
    "gn:population":0,
    "gn:timezone":"Africa/Lagos",
    "iso:country":"NG",
    "name:und_x_variant":[
        "Isemi",
        "Isemi Ile"
    ],
    "wof:name":"Isemi Ile",
    "wof:placetype":"locality"
},
  "geometry": {"coordinates":[3.36667,7.98333],"type":"Point"}
}