{
  "type": "Feature",
  "properties": {
    "gn:admin1_code":"23.0",
    "gn:admin2_code":"19022",
    "gn:admin3_code":"KD2204",
    "gn:asciiname":"Kabam",
    "gn:country_code":"NG",
    "gn:dem":761,
    "gn:feature_class":"P",
    "gn:feature_code":"PPL",
    "gn:name":"Kabam",
    "gn:population":0,
    "gn:timezone":"Africa/Lagos",
    "iso:country":"NG",
    "name:deu_x_preferred":[
        "Kabam"
    ],
    "wof:name":"Kabam",
    "wof:placetype":"locality"
},
  "geometry": {"coordinates":[8.1487,9.73448],"type":"Point"}
}