{
  "type": "Feature",
  "properties": {
    "gn:admin1_code":"29.0",
    "gn:admin2_code":"20016.0",
    "gn:admin3_code":"KN1305",
    "gn:asciiname":"Balagaza",
    "gn:country_code":"NG",
    "gn:dem":415,
    "gn:feature_class":"P",
    "gn:feature_code":"PPL",
    "gn:name":"Balagaza",
    "gn:population":0,
    "gn:timezone":"Africa/Lagos",
    "iso:country":"NG",
    "wof:name":"Balagaza",
    "wof:placetype":"locality"
},
  "geometry": {"coordinates":[8.88451,12.2553],"type":"Point"}
}