{
  "type": "Feature",
  "properties": {
    "gn:admin1_code":"43.0",
    "gn:admin2_code":"35016.0",
    "gn:asciiname":"Zandi",
    "gn:country_code":"NG",
    "gn:dem":551,
    "gn:feature_class":"P",
    "gn:feature_code":"PPL",
    "gn:name":"Zandi",
    "gn:population":0,
    "gn:timezone":"Africa/Lagos",
    "iso:country":"NG",
    "name:eng_x_preferred":[
        "Zandi"
    ],
    "wof:name":"Zandi",
    "wof:placetype":"locality"
},
  "geometry": {"coordinates":[11.7342,9.00333],"type":"Point"}
}