{
  "type": "Feature",
  "properties": {
    "gn:admin1_code":"30.0",
    "gn:admin2_code":"24015.0",
    "gn:asciiname":"Oguntedo",
    "gn:country_code":"NG",
    "gn:dem":402,
    "gn:feature_class":"P",
    "gn:feature_code":"PPL",
    "gn:name":"Oguntedo",
    "gn:population":0,
    "gn:timezone":"Africa/Lagos",
    "iso:country":"NG",
    "wof:name":"Oguntedo",
    "wof:placetype":"locality"
},
  "geometry": {"coordinates":[4.53333,8.11667],"type":"Point"}
}