{
  "type": "Feature",
  "properties": {
    "gn:admin1_code":"21.0",
    "gn:admin2_code":"3018.0",
    "gn:asciiname":"Mkpat Enin",
    "gn:country_code":"NG",
    "gn:dem":38,
    "gn:feature_class":"P",
    "gn:feature_code":"PPLA2",
    "gn:name":"Mkpat Enin",
    "gn:population":0,
    "gn:timezone":"Africa/Lagos",
    "iso:country":"NG",
    "name:und_x_variant":[
        "Nkpat Enin"
    ],
    "wof:name":"Mkpat Enin",
    "wof:placetype":"locality"
},
  "geometry": {"coordinates":[7.74897,4.73478],"type":"Point"}
}