{
  "type": "Feature",
  "properties": {
    "gn:admin1_code":"40.0",
    "gn:admin2_code":"509.0",
    "gn:admin3_code":"50906",
    "gn:asciiname":"Tungan-Gamji",
    "gn:country_code":"NG",
    "gn:dem":263,
    "gn:feature_class":"P",
    "gn:feature_code":"PPL",
    "gn:name":"Tungan-Gamji",
    "gn:population":0,
    "gn:timezone":"Africa/Lagos",
    "iso:country":"NG",
    "wof:name":"Tungan-Gamji",
    "wof:placetype":"locality"
},
  "geometry": {"coordinates":[4.88103,11.6696],"type":"Point"}
}