{
  "type": "Feature",
  "properties": {
    "gn:admin1_code":"51.0",
    "gn:admin2_code":"604.0",
    "gn:admin3_code":"60406",
    "gn:asciiname":"Biyangadi",
    "gn:country_code":"NG",
    "gn:dem":349,
    "gn:feature_class":"P",
    "gn:feature_code":"PPL",
    "gn:name":"Biyangadi",
    "gn:population":0,
    "gn:timezone":"Africa/Lagos",
    "iso:country":"NG",
    "wof:name":"Biyangadi",
    "wof:placetype":"locality"
},
  "geometry": {"coordinates":[5.60314,13.75535],"type":"Point"}
}