{
  "type": "Feature",
  "properties": {
    "gn:admin1_code":"31.0",
    "gn:admin2_code":"27014.0",
    "gn:asciiname":"Busuru",
    "gn:country_code":"NG",
    "gn:dem":283,
    "gn:feature_class":"P",
    "gn:feature_code":"PPL",
    "gn:name":"Busuru",
    "gn:population":0,
    "gn:timezone":"Africa/Lagos",
    "iso:country":"NG",
    "name:und_x_variant":[
        "Bussara",
        "Busuru"
    ],
    "wof:name":"Busuru",
    "wof:placetype":"locality"
},
  "geometry": {"coordinates":[4.98077,10.3951],"type":"Point"}
}