{
  "type": "Feature",
  "properties": {
    "gn:admin1_code":"22.0",
    "gn:admin2_code":"9003.0",
    "gn:asciiname":"Ikot Edem Ita",
    "gn:country_code":"NG",
    "gn:dem":56,
    "gn:feature_class":"P",
    "gn:feature_code":"PPL",
    "gn:name":"Ikot Edem Ita",
    "gn:population":0,
    "gn:timezone":"Africa/Lagos",
    "iso:country":"NG",
    "name:und_x_variant":[
        "Ikot Edm Ita",
        "Ikot Edem Ita"
    ],
    "wof:name":"Ikot Edem Ita",
    "wof:placetype":"locality"
},
  "geometry": {"coordinates":[8.5076,4.91139],"type":"Point"}
}