{
  "type": "Feature",
  "properties": {
    "gn:admin1_code":"26.0",
    "gn:admin2_code":"7010.0",
    "gn:asciiname":"Tse-Hemba Gbantule",
    "gn:country_code":"NG",
    "gn:dem":106,
    "gn:feature_class":"P",
    "gn:feature_code":"PPL",
    "gn:name":"Tse-Hemba Gbantule",
    "gn:population":0,
    "gn:timezone":"Africa/Lagos",
    "iso:country":"NG",
    "wof:name":"Tse-Hemba Gbantule",
    "wof:placetype":"locality"
},
  "geometry": {"coordinates":[8.54569,7.08142],"type":"Point"}
}