{
  "type": "Feature",
  "properties": {
    "gn:admin1_code":"39.0",
    "gn:admin2_code":"18010.0",
    "gn:admin3_code":"JI1704",
    "gn:asciiname":"Yaya",
    "gn:country_code":"NG",
    "gn:dem":411,
    "gn:feature_class":"P",
    "gn:feature_code":"PPL",
    "gn:name":"Yaya",
    "gn:population":0,
    "gn:timezone":"Africa/Lagos",
    "iso:country":"NG",
    "name:aze_x_preferred":[
        "Yaya"
    ],
    "name:ceb_x_preferred":[
        "Yaya"
    ],
    "name:ces_x_preferred":[
        "Jaja"
    ],
    "name:deu_x_preferred":[
        "Yaya"
    ],
    "name:por_x_preferred":[
        "Yaya"
    ],
    "name:que_x_preferred":[
        "Yaya suti"
    ],
    "name:spa_x_preferred":[
        "Yaya"
    ],
    "name:swe_x_preferred":[
        "Yaya"
    ],
    "wof:name":"Yaya",
    "wof:placetype":"locality"
},
  "geometry": {"coordinates":[8.62628,12.63802],"type":"Point"}
}