{
  "type": "Feature",
  "properties": {
    "gn:admin1_code":"23.0",
    "gn:admin2_code":"19020.0",
    "gn:admin3_code":"KD2002",
    "gn:asciiname":"Tukura",
    "gn:country_code":"NG",
    "gn:dem":502,
    "gn:feature_class":"P",
    "gn:feature_code":"PPL",
    "gn:name":"Tukura",
    "gn:population":0,
    "gn:timezone":"Africa/Lagos",
    "iso:country":"NG",
    "wof:name":"Tukura",
    "wof:placetype":"locality"
},
  "geometry": {"coordinates":[8.34056,9.23133],"type":"Point"}
}