{
  "type": "Feature",
  "properties": {
    "gn:admin1_code":"49.0",
    "gn:asciiname":"Tof",
    "gn:country_code":"NG",
    "gn:dem":1050,
    "gn:feature_class":"P",
    "gn:feature_code":"PPL",
    "gn:name":"Tof",
    "gn:population":0,
    "gn:timezone":"Africa/Lagos",
    "iso:country":"NG",
    "wof:name":"Tof",
    "wof:placetype":"locality"
},
  "geometry": {"coordinates":[8.78515,9.08753],"type":"Point"}
}