{
  "type": "Feature",
  "properties": {
    "gn:admin1_code":"26.0",
    "gn:admin2_code":"7021",
    "gn:asciiname":"Mngukposu",
    "gn:country_code":"NG",
    "gn:dem":159,
    "gn:feature_class":"P",
    "gn:feature_code":"PPL",
    "gn:name":"Mngukposu",
    "gn:population":0,
    "gn:timezone":"Africa/Lagos",
    "iso:country":"NG",
    "wof:name":"Mngukposu",
    "wof:placetype":"locality"
},
  "geometry": {"coordinates":[9.70384,7.67434],"type":"Point"}
}