{
  "type": "Feature",
  "properties": {
    "gn:admin1_code":"31.0",
    "gn:admin2_code":"27022.0",
    "gn:asciiname":"Gidan Sarikin Doma",
    "gn:country_code":"NG",
    "gn:dem":341,
    "gn:feature_class":"P",
    "gn:feature_code":"PPL",
    "gn:name":"Gidan Sarikin Doma",
    "gn:population":0,
    "gn:timezone":"Africa/Lagos",
    "iso:country":"NG",
    "wof:name":"Gidan Sarikin Doma",
    "wof:placetype":"locality"
},
  "geometry": {"coordinates":[6.43103,10.17646],"type":"Point"}
}