{
  "type": "Feature",
  "properties": {
    "gn:admin1_code":"16.0",
    "gn:admin2_code":"28016.0",
    "gn:asciiname":"Itoko",
    "gn:cc2":"NG",
    "gn:country_code":"NG",
    "gn:dem":176,
    "gn:feature_class":"P",
    "gn:feature_code":"PPL",
    "gn:name":"Itoko",
    "gn:population":0,
    "gn:timezone":"Africa/Lagos",
    "iso:country":"NG",
    "name:und_x_variant":[
        "Itawkaw",
        "Itoko"
    ],
    "wof:name":"Itoko",
    "wof:placetype":"locality"
},
  "geometry": {"coordinates":[3.68333,7.31667],"type":"Point"}
}