{
  "type": "Feature",
  "properties": {
    "gn:admin1_code":"36.0",
    "gn:admin2_code":"10004.0",
    "gn:asciiname":"Tubegbe",
    "gn:country_code":"NG",
    "gn:dem":7,
    "gn:feature_class":"P",
    "gn:feature_code":"PPL",
    "gn:name":"Tubegbe",
    "gn:population":0,
    "gn:timezone":"Africa/Lagos",
    "iso:country":"NG",
    "name:und_x_variant":[
        "Tebegbe",
        "Tubegbe"
    ],
    "wof:name":"Tubegbe",
    "wof:placetype":"locality"
},
  "geometry": {"coordinates":[5.86848,5.11817],"type":"Point"}
}