{
  "type": "Feature",
  "properties": {
    "gn:admin1_code":"53.0",
    "gn:admin2_code":"11012.0",
    "gn:asciiname":"Umuezekaoha",
    "gn:country_code":"NG",
    "gn:dem":135,
    "gn:feature_class":"P",
    "gn:feature_code":"PPL",
    "gn:name":"Umuezekaoha",
    "gn:population":0,
    "gn:timezone":"Africa/Lagos",
    "iso:country":"NG",
    "wof:name":"Umuezekaoha",
    "wof:placetype":"locality"
},
  "geometry": {"coordinates":[8.00325,6.65323],"type":"Point"}
}