{
  "type": "Feature",
  "properties": {
    "gn:admin1_code":"16.0",
    "gn:admin2_code":"28016.0",
    "gn:asciiname":"Majape",
    "gn:cc2":"NG",
    "gn:country_code":"NG",
    "gn:dem":66,
    "gn:feature_class":"P",
    "gn:feature_code":"PPL",
    "gn:name":"Majape",
    "gn:population":0,
    "gn:timezone":"Africa/Lagos",
    "iso:country":"NG",
    "name:und_x_variant":[
        "Majepe",
        "Majape"
    ],
    "wof:name":"Majape",
    "wof:placetype":"locality"
},
  "geometry": {"coordinates":[3.31667,7.28333],"type":"Point"}
}