{
  "type": "Feature",
  "properties": {
    "gn:admin1_code":"40.0",
    "gn:admin2_code":"502.0",
    "gn:admin3_code":"50201",
    "gn:asciiname":"Illela-Kakore",
    "gn:country_code":"NG",
    "gn:dem":221,
    "gn:feature_class":"P",
    "gn:feature_code":"PPL",
    "gn:name":"Illela-Kakore",
    "gn:population":0,
    "gn:timezone":"Africa/Lagos",
    "iso:country":"NG",
    "wof:name":"Illela-Kakore",
    "wof:placetype":"locality"
},
  "geometry": {"coordinates":[4.3244,13.14092],"type":"Point"}
}