{
  "type": "Feature",
  "properties": {
    "gn:admin1_code":"27.0",
    "gn:admin2_code":"112.0",
    "gn:admin3_code":"11202",
    "gn:asciiname":"Vio",
    "gn:country_code":"NG",
    "gn:dem":664,
    "gn:feature_class":"P",
    "gn:feature_code":"PPL",
    "gn:name":"Vio",
    "gn:population":0,
    "gn:timezone":"Africa/Lagos",
    "iso:country":"NG",
    "wof:name":"Vio",
    "wof:placetype":"locality"
},
  "geometry": {"coordinates":[12.08502,10.58302],"type":"Point"}
}