{
  "type": "Feature",
  "properties": {
    "gn:admin1_code":"45.0",
    "gn:asciiname":"Abanwan",
    "gn:country_code":"NG",
    "gn:dem":16,
    "gn:feature_class":"P",
    "gn:feature_code":"PPL",
    "gn:name":"Abanwan",
    "gn:population":0,
    "gn:timezone":"Africa/Lagos",
    "iso:country":"NG",
    "name:und_x_variant":[
        "Agbanwan",
        "Abanwan"
    ],
    "wof:name":"Abanwan",
    "wof:placetype":"locality"
},
  "geometry": {"coordinates":[7.97464,5.69637],"type":"Point"}
}