{
  "type": "Feature",
  "properties": {
    "gn:admin1_code":"32.0",
    "gn:admin2_code":"31019.0",
    "gn:asciiname":"Sanija",
    "gn:country_code":"NG",
    "gn:dem":199,
    "gn:feature_class":"P",
    "gn:feature_code":"PPL",
    "gn:name":"Sanija",
    "gn:population":0,
    "gn:timezone":"Africa/Lagos",
    "iso:country":"NG",
    "wof:name":"Sanija",
    "wof:placetype":"locality"
},
  "geometry": {"coordinates":[3.35,7.86667],"type":"Point"}
}