{
  "type": "Feature",
  "properties": {
    "gn:admin1_code":"31.0",
    "gn:admin2_code":"27025",
    "gn:asciiname":"Gbasakun",
    "gn:country_code":"NG",
    "gn:dem":122,
    "gn:feature_class":"P",
    "gn:feature_code":"PPL",
    "gn:name":"Gbasakun",
    "gn:population":0,
    "gn:timezone":"Africa/Lagos",
    "iso:country":"NG",
    "wof:name":"Gbasakun",
    "wof:placetype":"locality"
},
  "geometry": {"coordinates":[5.87086,9.49545],"type":"Point"}
}