{
  "type": "Feature",
  "properties": {
    "gn:admin1_code":"23.0",
    "gn:admin2_code":"19007",
    "gn:admin3_code":"KD0706",
    "gn:asciiname":"Ninte",
    "gn:country_code":"NG",
    "gn:dem":514,
    "gn:feature_class":"P",
    "gn:feature_code":"PPL",
    "gn:name":"Ninte",
    "gn:population":0,
    "gn:timezone":"Africa/Lagos",
    "iso:country":"NG",
    "wof:name":"Ninte",
    "wof:placetype":"locality"
},
  "geometry": {"coordinates":[8.2807,9.37425],"type":"Point"}
}