{
  "type": "Feature",
  "properties": {
    "gn:admin1_code":"46.0",
    "gn:admin2_code":"5008.0",
    "gn:admin3_code":"BA0807",
    "gn:asciiname":"Dela",
    "gn:country_code":"NG",
    "gn:dem":516,
    "gn:feature_class":"P",
    "gn:feature_code":"PPL",
    "gn:name":"Dela",
    "gn:population":0,
    "gn:timezone":"Africa/Lagos",
    "iso:country":"NG",
    "name:eng_x_preferred":[
        "Dela"
    ],
    "wof:name":"Dela",
    "wof:placetype":"locality"
},
  "geometry": {"coordinates":[9.99759,10.92628],"type":"Point"}
}