{
  "type": "Feature",
  "properties": {
    "gn:admin1_code":"31.0",
    "gn:admin2_code":"27018.0",
    "gn:asciiname":"Gidan-Maiganga",
    "gn:country_code":"NG",
    "gn:dem":446,
    "gn:feature_class":"P",
    "gn:feature_code":"PPL",
    "gn:name":"Gidan-Maiganga",
    "gn:population":0,
    "gn:timezone":"Africa/Lagos",
    "iso:country":"NG",
    "wof:name":"Gidan-Maiganga",
    "wof:placetype":"locality"
},
  "geometry": {"coordinates":[7.19526,9.77187],"type":"Point"}
}