{
  "type": "Feature",
  "properties": {
    "gn:admin1_code":"29.0",
    "gn:admin2_code":"20036.0",
    "gn:admin3_code":"KN2808",
    "gn:asciiname":"Gazana",
    "gn:country_code":"NG",
    "gn:dem":449,
    "gn:feature_class":"P",
    "gn:feature_code":"PPL",
    "gn:name":"Gazana",
    "gn:population":0,
    "gn:timezone":"Africa/Lagos",
    "iso:country":"NG",
    "wof:name":"Gazana",
    "wof:placetype":"locality"
},
  "geometry": {"coordinates":[8.39666,11.79628],"type":"Point"}
}