{
  "type": "Feature",
  "properties": {
    "gn:admin1_code":"26.0",
    "gn:admin2_code":"7001.0",
    "gn:asciiname":"Utonkon",
    "gn:country_code":"NG",
    "gn:dem":106,
    "gn:feature_class":"P",
    "gn:feature_code":"PPL",
    "gn:name":"Utonkon",
    "gn:population":0,
    "gn:timezone":"Africa/Lagos",
    "iso:country":"NG",
    "name:und_x_variant":[
        "Utunkon"
    ],
    "wof:name":"Utonkon",
    "wof:placetype":"locality"
},
  "geometry": {"coordinates":[8.03486,6.94761],"type":"Point"}
}