{
  "type": "Feature",
  "properties": {
    "gn:admin1_code":"35.0",
    "gn:admin2_code":"2002.0",
    "gn:asciiname":"Hammajoda",
    "gn:country_code":"NG",
    "gn:dem":391,
    "gn:feature_class":"P",
    "gn:feature_code":"PPL",
    "gn:name":"Hammajoda",
    "gn:population":0,
    "gn:timezone":"Africa/Lagos",
    "iso:country":"NG",
    "wof:name":"Hammajoda",
    "wof:placetype":"locality"
},
  "geometry": {"coordinates":[12.38383,8.93645],"type":"Point"}
}