{
  "type": "Feature",
  "properties": {
    "gn:admin1_code":"49.0",
    "gn:admin2_code":"32010",
    "gn:asciiname":"Nagani",
    "gn:country_code":"NG",
    "gn:dem":189,
    "gn:feature_class":"P",
    "gn:feature_code":"PPL",
    "gn:name":"Nagani",
    "gn:population":0,
    "gn:timezone":"Africa/Lagos",
    "iso:country":"NG",
    "wof:name":"Nagani",
    "wof:placetype":"locality"
},
  "geometry": {"coordinates":[9.83958,8.75225],"type":"Point"}
}