{
  "type": "Feature",
  "properties": {
    "gn:admin1_code":"32.0",
    "gn:admin2_code":"31024.0",
    "gn:asciiname":"Karamo",
    "gn:country_code":"NG",
    "gn:dem":410,
    "gn:feature_class":"P",
    "gn:feature_code":"PPL",
    "gn:name":"Karamo",
    "gn:population":0,
    "gn:timezone":"Africa/Lagos",
    "iso:country":"NG",
    "wof:name":"Karamo",
    "wof:placetype":"locality"
},
  "geometry": {"coordinates":[4.01667,8.65],"type":"Point"}
}