{
  "type": "Feature",
  "properties": {
    "gn:admin1_code":"28.0",
    "gn:admin2_code":"17011.0",
    "gn:asciiname":"Awo",
    "gn:country_code":"NG",
    "gn:dem":137,
    "gn:feature_class":"P",
    "gn:feature_code":"PPL",
    "gn:name":"Awo",
    "gn:population":0,
    "gn:timezone":"Africa/Lagos",
    "iso:country":"NG",
    "wof:name":"Awo",
    "wof:placetype":"locality"
},
  "geometry": {"coordinates":[7.03454,5.58273],"type":"Point"}
}