{
  "type": "Feature",
  "properties": {
    "gn:admin1_code":"27.0",
    "gn:admin2_code":"111.0",
    "gn:admin3_code":"11102",
    "gn:asciiname":"Dure Karguma",
    "gn:country_code":"NG",
    "gn:dem":354,
    "gn:feature_class":"P",
    "gn:feature_code":"PPL",
    "gn:name":"Dure Karguma",
    "gn:population":0,
    "gn:timezone":"Africa/Lagos",
    "iso:country":"NG",
    "name:und_x_variant":[
        "Dure Kargumua",
        "Dure Kargum",
        "Dure Karguma"
    ],
    "wof:name":"Dure Karguma",
    "wof:placetype":"locality"
},
  "geometry": {"coordinates":[13.56422,11.28988],"type":"Point"}
}