{
  "type": "Feature",
  "properties": {
    "gn:admin1_code":"30.0",
    "gn:admin2_code":"24003.0",
    "gn:asciiname":"Kokouna",
    "gn:cc2":"NG",
    "gn:country_code":"NG",
    "gn:dem":165,
    "gn:feature_class":"P",
    "gn:feature_code":"PPL",
    "gn:name":"Kokouna",
    "gn:population":0,
    "gn:timezone":"Africa/Lagos",
    "iso:country":"NG",
    "name:azb_x_preferred":[
        "\u06a9\u0648\u06a9\u0648\u0646\u0627"
    ],
    "name:fas_x_preferred":[
        "\u06a9\u0648\u06a9\u0648\u0646\u0627"
    ],
    "name:fra_x_preferred":[
        "Kokouna"
    ],
    "name:und_x_variant":[
        "Kokona",
        "Kokouna"
    ],
    "wof:name":"Kokouna",
    "wof:placetype":"locality"
},
  "geometry": {"coordinates":[5.08333,8.85],"type":"Point"}
}