{
  "type": "Feature",
  "properties": {
    "gn:admin1_code":"31.0",
    "gn:admin2_code":"27022.0",
    "gn:asciiname":"Burisidna",
    "gn:cc2":"NG",
    "gn:country_code":"NG",
    "gn:dem":430,
    "gn:feature_class":"P",
    "gn:feature_code":"PPL",
    "gn:name":"Burisidna",
    "gn:population":0,
    "gn:timezone":"Africa/Lagos",
    "iso:country":"NG",
    "name:und_x_variant":[
        "Buresidna",
        "Burisidna"
    ],
    "wof:name":"Burisidna",
    "wof:placetype":"locality"
},
  "geometry": {"coordinates":[6.91667,10.33333],"type":"Point"}
}