{
  "type": "Feature",
  "properties": {
    "gn:admin1_code":"51.0",
    "gn:admin2_code":"613.0",
    "gn:admin3_code":"61310",
    "gn:asciiname":"Zango Bogaje",
    "gn:country_code":"NG",
    "gn:dem":306,
    "gn:feature_class":"P",
    "gn:feature_code":"PPL",
    "gn:name":"Zango Bogaje",
    "gn:population":0,
    "gn:timezone":"Africa/Lagos",
    "iso:country":"NG",
    "wof:name":"Zango Bogaje",
    "wof:placetype":"locality"
},
  "geometry": {"coordinates":[5.95784,13.51637],"type":"Point"}
}