{
  "type": "Feature",
  "properties": {
    "gn:admin1_code":"26.0",
    "gn:admin2_code":"7007.0",
    "gn:asciiname":"Iyorjan",
    "gn:country_code":"NG",
    "gn:dem":203,
    "gn:feature_class":"P",
    "gn:feature_code":"PPL",
    "gn:name":"Iyorjan",
    "gn:population":0,
    "gn:timezone":"Africa/Lagos",
    "iso:country":"NG",
    "wof:name":"Iyorjan",
    "wof:placetype":"locality"
},
  "geometry": {"coordinates":[8.56991,7.39828],"type":"Point"}
}