{
  "type": "Feature",
  "properties": {
    "gn:admin1_code":"44.0",
    "gn:admin2_code":"711.0",
    "gn:admin3_code":"71111",
    "gn:asciiname":"Gogi",
    "gn:country_code":"NG",
    "gn:dem":353,
    "gn:feature_class":"P",
    "gn:feature_code":"PPL",
    "gn:name":"Gogi",
    "gn:population":0,
    "gn:timezone":"Africa/Lagos",
    "iso:country":"NG",
    "name:vie_x_preferred":[
        "Gogi"
    ],
    "wof:name":"Gogi",
    "wof:placetype":"locality"
},
  "geometry": {"coordinates":[10.12013,13.14319],"type":"Point"}
}