{
  "type": "Feature",
  "properties": {
    "gn:admin1_code":"24.0",
    "gn:admin2_code":"413.0",
    "gn:admin3_code":"41306",
    "gn:asciiname":"Liman",
    "gn:country_code":"NG",
    "gn:dem":628,
    "gn:feature_class":"P",
    "gn:feature_code":"PPL",
    "gn:name":"Liman",
    "gn:population":0,
    "gn:timezone":"Africa/Lagos",
    "iso:country":"NG",
    "name:aze_x_preferred":[
        "Liman"
    ],
    "name:bel_x_preferred":[
        "\u041b\u0456\u043c\u0430\u043d"
    ],
    "name:bul_x_preferred":[
        "\u041b\u0438\u043c\u0430\u043d"
    ],
    "name:ceb_x_preferred":[
        "Liman"
    ],
    "name:deu_x_preferred":[
        "Liman"
    ],
    "name:heb_x_preferred":[
        "\u05dc\u05d9\u05de\u05df"
    ],
    "name:hrv_x_preferred":[
        "Liman"
    ],
    "name:hye_x_preferred":[
        "\u053c\u056b\u0574\u0561\u0576"
    ],
    "name:ita_x_preferred":[
        "Liman"
    ],
    "name:pol_x_preferred":[
        "Liman"
    ],
    "name:rus_x_preferred":[
        "\u041b\u0438\u043c\u0430\u043d"
    ],
    "name:slk_x_preferred":[
        "Liman"
    ],
    "name:srp_x_preferred":[
        "\u041b\u0438\u043c\u0430\u043d"
    ],
    "name:swe_x_preferred":[
        "Liman"
    ],
    "name:ukr_x_preferred":[
        "\u041b\u0438\u043c\u0430\u043d"
    ],
    "wof:name":"Liman",
    "wof:placetype":"locality"
},
  "geometry": {"coordinates":[7.01574,11.6604],"type":"Point"}
}