{
  "type": "Feature",
  "properties": {
    "gn:admin1_code":"26.0",
    "gn:admin2_code":"7005",
    "gn:asciiname":"Iyar",
    "gn:country_code":"NG",
    "gn:dem":111,
    "gn:feature_class":"P",
    "gn:feature_code":"PPL",
    "gn:name":"Iyar",
    "gn:population":0,
    "gn:timezone":"Africa/Lagos",
    "iso:country":"NG",
    "name:ara_x_preferred":[
        "\u0623\u064a\u0627\u0631"
    ],
    "name:bel_x_preferred":[
        "\u0406\u044f\u0440"
    ],
    "name:cat_x_preferred":[
        "Iar"
    ],
    "name:ceb_x_preferred":[
        "Iyyar"
    ],
    "name:ces_x_preferred":[
        "Ijar"
    ],
    "name:deu_x_preferred":[
        "Ijjar"
    ],
    "name:epo_x_preferred":[
        "Ijaro"
    ],
    "name:est_x_preferred":[
        "Ijar"
    ],
    "name:eus_x_preferred":[
        "Iyar"
    ],
    "name:fas_x_preferred":[
        "\u0627\u06cc\u0627\u0631"
    ],
    "name:fra_x_preferred":[
        "Iyar"
    ],
    "name:heb_x_preferred":[
        "\u05d0\u05d9\u05d9\u05e8"
    ],
    "name:hun_x_preferred":[
        "Ijj\u00e1r"
    ],
    "name:ind_x_preferred":[
        "Iyar"
    ],
    "name:ita_x_preferred":[
        "Iyar"
    ],
    "name:mkd_x_preferred":[
        "\u0418\u0458\u0430\u0440"
    ],
    "name:msa_x_preferred":[
        "Iyar"
    ],
    "name:nld_x_preferred":[
        "Iar"
    ],
    "name:nno_x_preferred":[
        "Ijj\u00e1r"
    ],
    "name:nor_x_preferred":[
        "Ij\u00e1r"
    ],
    "name:pol_x_preferred":[
        "Ijar"
    ],
    "name:por_x_preferred":[
        "Iyar"
    ],
    "name:ron_x_preferred":[
        "Iyar"
    ],
    "name:rus_x_preferred":[
        "\u0418\u044f\u0440"
    ],
    "name:slk_x_preferred":[
        "Ijar"
    ],
    "name:slv_x_preferred":[
        "Iyar"
    ],
    "name:spa_x_preferred":[
        "Iyar"
    ],
    "name:swe_x_preferred":[
        "Ijar"
    ],
    "name:tgl_x_preferred":[
        "Iyyar"
    ],
    "name:tur_x_preferred":[
        "\u0130yar"
    ],
    "name:ukr_x_preferred":[
        "\u0406\u044f\u0440"
    ],
    "name:yid_x_preferred":[
        "\u05d0\u05d9\u05d9\u05e8"
    ],
    "name:zho_x_preferred":[
        "\u4ee5\u73e5\u6708"
    ],
    "wof:name":"Iyar",
    "wof:placetype":"locality"
},
  "geometry": {"coordinates":[8.75728,7.45631],"type":"Point"}
}