{
  "type": "Feature",
  "properties": {
    "gn:admin1_code":"27.0",
    "gn:admin2_code":"121.0",
    "gn:admin3_code":"12102",
    "gn:asciiname":"Kulli",
    "gn:country_code":"NG",
    "gn:dem":295,
    "gn:feature_class":"P",
    "gn:feature_code":"PPL",
    "gn:name":"Kulli",
    "gn:population":0,
    "gn:timezone":"Africa/Lagos",
    "iso:country":"NG",
    "name:ceb_x_preferred":[
        "Kulli"
    ],
    "name:ces_x_preferred":[
        "Kulli"
    ],
    "name:est_x_preferred":[
        "Kulli"
    ],
    "name:fin_x_preferred":[
        "Kulli"
    ],
    "name:nld_x_preferred":[
        "Kulli"
    ],
    "name:pol_x_preferred":[
        "Kulli"
    ],
    "name:spa_x_preferred":[
        "Kulli"
    ],
    "name:ukr_x_preferred":[
        "\u041a\u0443\u043b\u043b\u0456"
    ],
    "name:vol_x_preferred":[
        "Kulli"
    ],
    "wof:name":"Kulli",
    "wof:placetype":"locality"
},
  "geometry": {"coordinates":[13.70422,12.27076],"type":"Point"}
}