{
  "type": "Feature",
  "properties": {
    "gn:admin1_code":"35.0",
    "gn:admin2_code":"2001.0",
    "gn:asciiname":"Njendure",
    "gn:country_code":"NG",
    "gn:dem":176,
    "gn:feature_class":"P",
    "gn:feature_code":"PPL",
    "gn:name":"Njendure",
    "gn:population":0,
    "gn:timezone":"Africa/Lagos",
    "iso:country":"NG",
    "name:eng_x_preferred":[
        "Njendure"
    ],
    "name:eng_x_variant":[
        "Bakin Diwe"
    ],
    "wof:name":"Njendure",
    "wof:placetype":"locality"
},
  "geometry": {"coordinates":[11.88079,9.40196],"type":"Point"}
}