{
  "type": "Feature",
  "properties": {
    "gn:admin1_code":"29.0",
    "gn:admin2_code":"20023.0",
    "gn:admin3_code":"KN0805",
    "gn:asciiname":"Balarabe",
    "gn:country_code":"NG",
    "gn:dem":405,
    "gn:feature_class":"P",
    "gn:feature_code":"PPL",
    "gn:name":"Balarabe",
    "gn:population":0,
    "gn:timezone":"Africa/Lagos",
    "iso:country":"NG",
    "wof:name":"Balarabe",
    "wof:placetype":"locality"
},
  "geometry": {"coordinates":[8.70733,12.50961],"type":"Point"}
}