{
  "type": "Feature",
  "properties": {
    "iso:country":"NG",
    "name:bul_x_preferred":[
        "\u0413\u0431\u043e\u043d\u0433\u0430\u043d"
    ],
    "name:ceb_x_preferred":[
        "Gbongan"
    ],
    "name:eng_x_preferred":[
        "Gbongan"
    ],
    "name:nld_x_preferred":[
        "Gbongan"
    ],
    "name:yor_x_preferred":[
        "Gb\u1ecd\u0300ng\u00e1n"
    ],
    "qs:gn_country":"NG",
    "qs:gn_fcode":"PPL",
    "qs:gn_pop":139485,
    "qs:name":"Gbongan",
    "qs:name_adm0":"Nigeria",
    "qs:name_adm1":"Osun",
    "qs:photos":0,
    "qs:photos_1k":0,
    "qs:photos_9k":1,
    "qs:photos_9r":1,
    "qs:photos_all":1,
    "qs:photos_sr":0,
    "qs:placetype":"Town",
    "qs:pop_sr":"9",
    "qs:woe_adm0":23424908,
    "wd:wordcount":985,
    "wof:name":"Gbongan",
    "wof:placetype":"locality",
    "wof:population":139485
},
  "geometry": {"coordinates":[4.35,7.46667],"type":"Point"}
}