{
  "type": "Feature",
  "properties": {
    "gn:admin1_code":"31.0",
    "gn:admin2_code":"27019",
    "gn:asciiname":"Lambata",
    "gn:country_code":"NG",
    "gn:dem":254,
    "gn:feature_class":"P",
    "gn:feature_code":"PPL",
    "gn:name":"Lambata",
    "gn:population":0,
    "gn:timezone":"Africa/Lagos",
    "iso:country":"NG",
    "wof:name":"Lambata",
    "wof:placetype":"locality"
},
  "geometry": {"coordinates":[6.59877,9.51159],"type":"Point"}
}