{
  "type": "Feature",
  "properties": {
    "gn:admin1_code":"27.0",
    "gn:admin2_code":"112.0",
    "gn:admin3_code":"11210",
    "gn:asciiname":"Garu",
    "gn:country_code":"NG",
    "gn:dem":348,
    "gn:feature_class":"P",
    "gn:feature_code":"PPL",
    "gn:name":"Garu",
    "gn:population":0,
    "gn:timezone":"Africa/Lagos",
    "iso:country":"NG",
    "name:ceb_x_preferred":[
        "Garu"
    ],
    "name:spa_x_preferred":[
        "Garu"
    ],
    "name:swe_x_preferred":[
        "Garu"
    ],
    "wof:name":"Garu",
    "wof:placetype":"locality"
},
  "geometry": {"coordinates":[12.53442,10.39491],"type":"Point"}
}