{
  "type": "Feature",
  "properties": {
    "gn:admin1_code":"55.0",
    "gn:asciiname":"Gila",
    "gn:country_code":"NG",
    "gn:dem":300,
    "gn:feature_class":"P",
    "gn:feature_code":"PPL",
    "gn:name":"Gila",
    "gn:population":0,
    "gn:timezone":"Africa/Lagos",
    "iso:country":"NG",
    "name:eng_x_preferred":[
        "Gila"
    ],
    "name:eng_x_variant":[
        "Gilo"
    ],
    "wof:name":"Gila",
    "wof:placetype":"locality"
},
  "geometry": {"coordinates":[10.97282,9.71939],"type":"Point"}
}