{
  "type": "Feature",
  "properties": {
    "gn:admin1_code":"55.0",
    "gn:asciiname":"Gila",
    "gn:country_code":"NG",
    "gn:dem":300,
    "gn:feature_class":"P",
    "gn:feature_code":"PPL",
    "gn:name":"Gila",
    "gn:population":0,
    "gn:timezone":"Africa/Lagos",
    "iso:country":"NG",
    "name:ara_x_preferred":[
        "\u062c\u064a\u0644\u0627"
    ],
    "name:ben_x_preferred":[
        "\u099c\u09bf\u09b2\u09be"
    ],
    "name:cat_x_preferred":[
        "Gila"
    ],
    "name:ceb_x_preferred":[
        "Gila"
    ],
    "name:deu_x_preferred":[
        "Gila"
    ],
    "name:ell_x_preferred":[
        "\u0393\u03ba\u03af\u03bb\u03b1"
    ],
    "name:eng_x_preferred":[
        "Gila"
    ],
    "name:eng_x_variant":[
        "Gilo"
    ],
    "name:fin_x_preferred":[
        "Gila"
    ],
    "name:fra_x_preferred":[
        "Gila"
    ],
    "name:heb_x_preferred":[
        "\u05d2\u05d9\u05dc\u05d4"
    ],
    "name:hin_x_preferred":[
        "\u0917\u093f\u0932\u093e"
    ],
    "name:hun_x_preferred":[
        "Gila"
    ],
    "name:ita_x_preferred":[
        "Gila"
    ],
    "name:kor_x_preferred":[
        "\uae38\ub77c"
    ],
    "name:nld_x_preferred":[
        "Gila"
    ],
    "name:pol_x_preferred":[
        "Gila"
    ],
    "name:por_x_preferred":[
        "Gila"
    ],
    "name:ron_x_preferred":[
        "Gila"
    ],
    "name:rus_x_preferred":[
        "Gila"
    ],
    "name:spa_x_preferred":[
        "Gila"
    ],
    "name:srp_x_preferred":[
        "\u0425\u0438\u043b\u0430"
    ],
    "name:swe_x_preferred":[
        "Gila"
    ],
    "name:tur_x_preferred":[
        "Gila"
    ],
    "wof:name":"Gila",
    "wof:placetype":"locality"
},
  "geometry": {"coordinates":[10.97282,9.71939],"type":"Point"}
}