{
  "type": "Feature",
  "properties": {
    "gn:admin1_code":"45.0",
    "gn:asciiname":"Ogo Ubi",
    "gn:country_code":"NG",
    "gn:dem":30,
    "gn:feature_class":"P",
    "gn:feature_code":"PPL",
    "gn:name":"Ogo Ubi",
    "gn:population":0,
    "gn:timezone":"Africa/Lagos",
    "iso:country":"NG",
    "wof:name":"Ogo Ubi",
    "wof:placetype":"locality"
},
  "geometry": {"coordinates":[7.74824,5.5101],"type":"Point"}
}