{
  "type": "Feature",
  "properties": {
    "gn:admin1_code":"40.0",
    "gn:admin2_code":"507.0",
    "gn:admin3_code":"50703",
    "gn:asciiname":"Abarsh",
    "gn:country_code":"NG",
    "gn:dem":240,
    "gn:feature_class":"P",
    "gn:feature_code":"PPL",
    "gn:name":"Abarsh",
    "gn:population":0,
    "gn:timezone":"Africa/Lagos",
    "iso:country":"NG",
    "wof:name":"Abarsh",
    "wof:placetype":"locality"
},
  "geometry": {"coordinates":[3.85639,12.12299],"type":"Point"}
}