{
  "type": "Feature",
  "properties": {
    "gn:admin1_code":"43.0",
    "gn:admin2_code":"35001",
    "gn:asciiname":"Mazhinti",
    "gn:country_code":"NG",
    "gn:dem":225,
    "gn:feature_class":"P",
    "gn:feature_code":"PPL",
    "gn:name":"Mazhinti",
    "gn:population":0,
    "gn:timezone":"Africa/Lagos",
    "iso:country":"NG",
    "wof:name":"Mazhinti",
    "wof:placetype":"locality"
},
  "geometry": {"coordinates":[11.37579,8.73501],"type":"Point"}
}