{
  "type": "Feature",
  "properties": {
    "gn:admin1_code":"52.0",
    "gn:admin2_code":"6003.0",
    "gn:asciiname":"Sampor",
    "gn:country_code":"NG",
    "gn:dem":21,
    "gn:feature_class":"P",
    "gn:feature_code":"PPL",
    "gn:name":"Sampor",
    "gn:population":0,
    "gn:timezone":"Africa/Lagos",
    "iso:country":"NG",
    "wof:name":"Sampor",
    "wof:placetype":"locality"
},
  "geometry": {"coordinates":[6.35568,5.14581],"type":"Point"}
}