{
  "type": "Feature",
  "properties": {
    "gn:admin1_code":"41.0",
    "gn:admin2_code":"23004.0",
    "gn:asciiname":"Oguma",
    "gn:country_code":"NG",
    "gn:dem":52,
    "gn:feature_class":"P",
    "gn:feature_code":"PPLA2",
    "gn:name":"Oguma",
    "gn:population":0,
    "gn:timezone":"Africa/Lagos",
    "iso:country":"NG",
    "name:und_x_variant":[
        "Ogum",
        "Oguma"
    ],
    "wof:name":"Oguma",
    "wof:placetype":"locality"
},
  "geometry": {"coordinates":[7.06229,7.89635],"type":"Point"}
}